Protoss_Gateway 2 10811
Protoss_Zealot 3 7041
Protoss_Assimilator 1 5532
Protoss_Cybernetics_Core 1 7185
Protoss_Dragoon 5 12241
Protoss_Robotics_Facility 1 12145
Singularity_Charge 1 11173
12241
