Protoss_Nexus 1 7076
Protoss_Gateway 3 11215
Protoss_Assimilator 1 6611
Protoss_Cybernetics_Core 1 8069
Protoss_Dragoon 4 12224
Protoss_Robotics_Facility 1 12392
Protoss_Zealot 1 12248
12392
