Protoss_Gateway 2 9409
Protoss_Zealot 4 8086
Protoss_Assimilator 1 5442
Protoss_Cybernetics_Core 1 8130
Protoss_Citadel_of_Adun 1 9611
Protoss_Dragoon 1 9563
Protoss_Templar_Archives 1 11054
Protoss_Forge 1 11667
Protoss_Dark_Templar 2 12268
12268
