Protoss_Gateway 2 7761
Protoss_Assimilator 1 4666
Protoss_Zealot 1 5271
Protoss_Cybernetics_Core 1 6826
Protoss_Dragoon 5 11619
Protoss_Robotics_Facility 1 10661
Protoss_Robotics_Support_Bay 1 11505
Protoss_Shuttle 1 12479
Singularity_Charge 1 11321
12479
