Protoss_Nexus 1 7882
Protoss_Gateway 4 12449
Protoss_Assimilator 1 7217
Protoss_Zealot 1 7875
Protoss_Cybernetics_Core 1 8496
Protoss_Dragoon 2 11122
Protoss_Robotics_Facility 1 11100
Protoss_Observatory 1 11991
12449
