Protoss_Gateway 2 6415
Protoss_Zealot 6 8756
Protoss_Assimilator 1 8050
Protoss_Shield_Battery 1 9026
Protoss_Cybernetics_Core 2 10549
Protoss_Nexus 1 12982
Protoss_Dragoon 2 12115
12982
