Protoss_Gateway 2 5186
Protoss_Zealot 5 8080
Protoss_Assimilator 1 7433
Protoss_Cybernetics_Core 1 8882
Protoss_Robotics_Facility 1 10961
Protoss_Dragoon 1 10749
Protoss_Shuttle 1 12377
Protoss_Robotics_Support_Bay 1 11709
12377
