Protoss_Nexus 1 7099
Protoss_Gateway 3 9241
Protoss_Assimilator 1 6874
Protoss_Cybernetics_Core 1 7796
Protoss_Dragoon 4 10778
Protoss_Zealot 1 11171
Protoss_Robotics_Facility 1 12907
12907
