Protoss_Gateway 1 4199
Protoss_Assimilator 1 4337
Protoss_Cybernetics_Core 1 5853
Protoss_Dragoon 5 12168
Protoss_Citadel_of_Adun 1 10548
Protoss_Nexus 1 12388
Singularity_Charge 1 10384
Protoss_Templar_Archives 1 12043
12388
