Protoss_Gateway 4 12059
Protoss_Assimilator 1 4666
Protoss_Cybernetics_Core 1 5948
Protoss_Dragoon 6 12436
Protoss_Robotics_Facility 1 9475
Protoss_Observatory 1 10172
Protoss_Observer 1 11190
12436
