Protoss_Assimilator 1 3434
Protoss_Gateway 2 9513
Protoss_Cybernetics_Core 1 6329
Protoss_Robotics_Facility 1 8268
Protoss_Dragoon 6 12183
Protoss_Observatory 1 9001
Protoss_Observer 2 10900
Protoss_Shuttle 1 12345
Singularity_Charge 1 11343
12345
