Protoss_Gateway 1 4287
Protoss_Zealot 3 7553
Protoss_Assimilator 1 6012
Protoss_Cybernetics_Core 1 7351
Protoss_Dragoon 4 12585
Protoss_Robotics_Facility 1 10470
Protoss_Shuttle 1 11989
Protoss_Observatory 1 11445
12585
