Protoss_Gateway 2 9939
Protoss_Assimilator 1 4701
Protoss_Cybernetics_Core 1 5947
Protoss_Zealot 1 6570
Protoss_Dragoon 6 11559
Singularity_Charge 1 10160
Protoss_Robotics_Facility 1 12693
12693
