Protoss_Gateway 1 4432
Protoss_Assimilator 1 4659
Protoss_Cybernetics_Core 1 6176
Protoss_Dragoon 3 10012
Protoss_Robotics_Facility 1 9317
Protoss_Observatory 1 10311
Protoss_Nexus 1 12857
Protoss_Observer 1 11483
12857
