Protoss_Gateway 2 9946
Protoss_Assimilator 1 4258
Protoss_Cybernetics_Core 1 6642
Protoss_Zealot 1 6792
Protoss_Dragoon 5 11214
Singularity_Charge 1 10494
Protoss_Robotics_Facility 1 12807
12807
