Protoss_Gateway 1 4243
Protoss_Zealot 4 9986
Protoss_Assimilator 1 5434
Protoss_Cybernetics_Core 1 7151
Protoss_Robotics_Facility 1 9294
Protoss_Dragoon 2 11311
Protoss_Shuttle 1 10849
Protoss_Robotics_Support_Bay 1 10588
Protoss_Reaver 1 12676
Protoss_Observatory 1 11903
12676
