Protoss_Assimilator 1 3532
Protoss_Gateway 1 4812
Protoss_Cybernetics_Core 1 6270
Protoss_Robotics_Facility 1 8202
Protoss_Dragoon 2 9834
Protoss_Shuttle 1 9611
Protoss_Robotics_Support_Bay 1 8991
Protoss_Observatory 1 9219
Protoss_Observer 1 10454
Protoss_Reaver 1 12050
12050
