Protoss_Gateway 3 12579
Protoss_Assimilator 1 4578
Protoss_Zealot 1 5197
Protoss_Cybernetics_Core 1 7021
Protoss_Dragoon 5 12519
Protoss_Nexus 1 11842
Protoss_Robotics_Facility 1 12165
Singularity_Charge 1 10840
12579
