Protoss_Gateway 2 5080
Protoss_Zealot 5 9377
Protoss_Nexus 1 8978
Protoss_Assimilator 2 10608
Protoss_Cybernetics_Core 1 10283
Protoss_Dragoon 2 11673
Protoss_Citadel_of_Adun 1 12476
12476
