Protoss_Assimilator 1 3378
Protoss_Gateway 1 4723
Protoss_Cybernetics_Core 1 6301
Protoss_Stargate 1 8020
Protoss_Robotics_Facility 1 8916
Protoss_Corsair 3 10728
Protoss_Shuttle 1 10350
Protoss_Forge 1 11104
Protoss_Dragoon 1 11590
Protoss_Photon_Cannon 1 12477
12477
