Protoss_Gateway 2 6438
Protoss_Assimilator 1 4373
Protoss_Cybernetics_Core 1 5606
Protoss_Dragoon 6 11883
Protoss_Nexus 1 12630
Singularity_Charge 1 9858
Protoss_Robotics_Facility 1 13238
13238
