Protoss_Gateway 2 6672
Protoss_Assimilator 1 4359
Protoss_Cybernetics_Core 1 5958
Protoss_Dragoon 5 10639
Protoss_Robotics_Facility 1 10653
Singularity_Charge 1 10040
Protoss_Nexus 1 13574
Protoss_Observatory 1 11631
13574
