Protoss_Gateway 2 5320
Protoss_Zealot 8 10729
Protoss_Nexus 1 11206
Protoss_Assimilator 1 9879
Protoss_Forge 1 10472
Protoss_Cybernetics_Core 1 11948
Protoss_Photon_Cannon 2 12360
12360
