Protoss_Gateway 2 5440
Protoss_Zealot 5 11276
Protoss_Nexus 1 9871
Protoss_Assimilator 2 11039
Protoss_Cybernetics_Core 1 9864
Protoss_Citadel_of_Adun 1 11475
Protoss_Dragoon 1 11384
11475
