Protoss_Gateway 2 5133
Protoss_Zealot 9 12002
Protoss_Nexus 1 8914
Protoss_Assimilator 2 11540
Protoss_Cybernetics_Core 1 9858
Protoss_Dragoon 2 11088
Protoss_Citadel_of_Adun 1 11898
12002
