Protoss_Gateway 2 6866
Protoss_Assimilator 1 4433
Protoss_Cybernetics_Core 1 5629
Protoss_Zealot 4 8888
Protoss_Dragoon 3 10886
Protoss_Citadel_of_Adun 1 10340
Protoss_Templar_Archives 1 11844
Protoss_Forge 1 11873
11873
