Protoss_Gateway 2 9811
Protoss_Zealot 3 6930
Protoss_Assimilator 1 7347
Protoss_Nexus 1 9406
Protoss_Cybernetics_Core 1 8887
Protoss_Forge 1 8862
Protoss_Dragoon 1 10116
Protoss_Photon_Cannon 1 11871
11871
