Protoss_Assimilator 1 3727
Protoss_Gateway 1 4748
Protoss_Cybernetics_Core 1 6494
Protoss_Robotics_Facility 1 8422
Protoss_Dragoon 2 11671
Protoss_Robotics_Support_Bay 1 9148
Protoss_Shuttle 2 11396
Protoss_Reaver 1 11722
11722
