Protoss_Gateway 2 5218
Protoss_Zealot 5 10044
Protoss_Nexus 1 9984
Protoss_Assimilator 2 10706
Protoss_Cybernetics_Core 1 9523
Protoss_Dragoon 2 11562
Protoss_Citadel_of_Adun 1 12412
12412
