Protoss_Gateway 2 7987
Protoss_Assimilator 1 4609
Protoss_Zealot 2 6741
Protoss_Cybernetics_Core 1 7012
Protoss_Dragoon 3 9519
Protoss_Citadel_of_Adun 1 8626
Protoss_Templar_Archives 1 10192
Protoss_Dark_Templar 3 12515
Protoss_Forge 1 11756
12515
