Protoss_Gateway 2 4887
Protoss_Zealot 5 10024
Protoss_Nexus 1 9876
Protoss_Assimilator 2 12283
Protoss_Cybernetics_Core 1 9914
Protoss_Dragoon 4 12557
Protoss_Forge 1 11809
12557
