Protoss_Gateway 2 11349
Protoss_Zealot 3 7890
Protoss_Assimilator 1 5373
Protoss_Cybernetics_Core 1 7334
Protoss_Dragoon 3 11521
Protoss_Citadel_of_Adun 1 11156
Protoss_Robotics_Facility 1 12745
12745
