Protoss_Gateway 2 11790
Protoss_Zealot 2 6260
Protoss_Assimilator 1 5304
Protoss_Cybernetics_Core 1 6896
Protoss_Dragoon 4 11512
Protoss_Nexus 1 11897
Protoss_Robotics_Facility 1 12727
12727
