Protoss_Gateway 2 5840
Protoss_Zealot 6 10229
Protoss_Nexus 1 9789
Protoss_Assimilator 2 11749
Protoss_Cybernetics_Core 1 10287
Protoss_Dragoon 2 11671
Protoss_Citadel_of_Adun 1 12489
12489
