Protoss_Gateway 2 11600
Protoss_Assimilator 1 4261
Protoss_Zealot 3 6933
Protoss_Cybernetics_Core 1 6912
Protoss_Dragoon 5 12118
Protoss_Robotics_Facility 1 11865
Singularity_Charge 1 11126
12118
