Protoss_Gateway 1 4141
Protoss_Assimilator 1 4401
Protoss_Cybernetics_Core 1 5745
Protoss_Zealot 1 5554
Protoss_Dragoon 5 11840
Protoss_Robotics_Facility 1 9490
Protoss_Robotics_Support_Bay 1 10283
Protoss_Observatory 1 10308
Protoss_Reaver 1 12018
12018
