Protoss_Gateway 2 4944
Protoss_Zealot 5 12125
Protoss_Nexus 1 8876
Protoss_Forge 1 8080
Protoss_Assimilator 2 10422
Protoss_Cybernetics_Core 1 9754
Protoss_Photon_Cannon 1 10081
Protoss_Dragoon 1 10956
Protoss_Robotics_Facility 1 12826
12826
