Protoss_Gateway 2 11660
Protoss_Assimilator 1 4472
Protoss_Cybernetics_Core 1 5756
Protoss_Zealot 1 5651
Protoss_Dragoon 4 10687
Protoss_Citadel_of_Adun 1 9528
Protoss_Templar_Archives 1 11297
Singularity_Charge 1 10011
Protoss_Dark_Templar 1 12502
12502
