Protoss_Gateway 2 10748
Protoss_Assimilator 1 4139
Protoss_Cybernetics_Core 1 5509
Protoss_Zealot 1 5472
Protoss_Dragoon 6 11954
Protoss_Nexus 1 11112
Singularity_Charge 1 9783
Protoss_Robotics_Facility 1 13192
13192
