Protoss_Gateway 2 11923
Protoss_Zealot 2 6634
Protoss_Assimilator 1 5391
Protoss_Cybernetics_Core 1 6634
Protoss_Dragoon 4 11630
Protoss_Robotics_Facility 1 10895
Singularity_Charge 1 10842
Protoss_Shuttle 1 12289
Protoss_Robotics_Support_Bay 1 11700
12289
