Protoss_Gateway 1 4246
Protoss_Assimilator 1 4539
Protoss_Cybernetics_Core 1 5879
Protoss_Dragoon 4 11635
Protoss_Zealot 1 9052
Protoss_Nexus 1 11607
Protoss_Robotics_Facility 1 11002
Protoss_Observatory 1 11849
Protoss_Robotics_Support_Bay 1 11918
11918
