Protoss_Gateway 2 9948
Protoss_Assimilator 1 4188
Protoss_Cybernetics_Core 1 5685
Protoss_Zealot 1 5566
Protoss_Dragoon 2 8091
Protoss_Citadel_of_Adun 1 8620
Protoss_Robotics_Facility 1 9304
Protoss_Templar_Archives 1 10208
Protoss_Shuttle 1 10852
Protoss_Dark_Templar 2 11439
11439
