Protoss_Gateway 2 6434
Protoss_Zealot 7 11004
Protoss_Nexus 1 9979
Protoss_Assimilator 1 9043
Protoss_Cybernetics_Core 1 10561
Protoss_Citadel_of_Adun 1 12067
Protoss_Dragoon 2 12513
12513
