Protoss_Gateway 2 4992
Protoss_Zealot 7 10425
Protoss_Nexus 1 9938
Protoss_Assimilator 1 9002
Protoss_Cybernetics_Core 1 10531
Protoss_Citadel_of_Adun 1 12162
Protoss_Dragoon 2 12221
12221
