Protoss_Gateway 2 10546
Protoss_Assimilator 1 4496
Protoss_Zealot 2 6880
Protoss_Cybernetics_Core 1 6901
Protoss_Dragoon 5 12332
Protoss_Robotics_Facility 1 10608
Protoss_Robotics_Support_Bay 1 11316
Protoss_Observatory 1 11615
Singularity_Charge 1 11243
12332
