Protoss_Gateway 2 9110
Protoss_Assimilator 1 4605
Protoss_Zealot 1 5183
Protoss_Cybernetics_Core 1 6067
Protoss_Dragoon 6 11471
Singularity_Charge 1 9727
Protoss_Nexus 1 14059
14059
