Protoss_Gateway 1 4179
Protoss_Zealot 3 7343
Protoss_Assimilator 1 5490
Protoss_Cybernetics_Core 1 6661
Protoss_Dragoon 4 11764
Protoss_Nexus 1 13017
Protoss_Robotics_Facility 1 12598
13017
