Protoss_Gateway 2 10366
Protoss_Zealot 3 7047
Protoss_Assimilator 1 5869
Protoss_Cybernetics_Core 1 7027
Protoss_Dragoon 5 11834
Protoss_Robotics_Facility 1 12131
Singularity_Charge 1 11261
Protoss_Forge 1 12232
12232
