Protoss_Gateway 1 4218
Protoss_Zealot 3 7922
Protoss_Assimilator 1 5252
Protoss_Cybernetics_Core 1 6648
Protoss_Citadel_of_Adun 1 8187
Protoss_Dragoon 1 9042
Protoss_Templar_Archives 1 9656
Protoss_Forge 1 9416
Protoss_Dark_Templar 2 12341
Protoss_Nexus 1 12906
Protoss_Photon_Cannon 2 11928
12906
