Protoss_Gateway 2 6588
Protoss_Assimilator 1 4234
Protoss_Cybernetics_Core 1 5689
Protoss_Dragoon 9 12089
Protoss_Robotics_Facility 1 10614
Singularity_Charge 1 9686
Protoss_Observatory 1 11393
12089
