Protoss_Gateway 2 5149
Protoss_Zealot 5 10615
Protoss_Assimilator 2 10811
Protoss_Cybernetics_Core 1 9564
Protoss_Nexus 1 11428
Protoss_Citadel_of_Adun 1 11524
Protoss_Dragoon 2 11934
11934
