Protoss_Gateway 2 5259
Protoss_Assimilator 1 5234
Protoss_Cybernetics_Core 1 6873
Protoss_Zealot 2 7199
Protoss_Dragoon 6 12382
Protoss_Robotics_Facility 1 11294
Protoss_Observatory 1 12077
12382
