Protoss_Gateway 3 12646
Protoss_Assimilator 1 4343
Protoss_Cybernetics_Core 1 5622
Protoss_Dragoon 8 11796
Protoss_Robotics_Facility 1 10930
Singularity_Charge 1 9806
Protoss_Observatory 1 11701
12646
