Protoss_Gateway 2 7249
Protoss_Assimilator 1 5060
Protoss_Zealot 3 7173
Protoss_Cybernetics_Core 1 6626
Protoss_Dragoon 6 11071
Singularity_Charge 1 10886
Protoss_Nexus 1 14115
14115
