Protoss_Gateway 1 4245
Protoss_Assimilator 1 4337
Protoss_Cybernetics_Core 1 5730
Protoss_Zealot 1 5724
Protoss_Dragoon 6 12590
Singularity_Charge 1 9906
Protoss_Nexus 1 13470
13470
