Protoss_Gateway 2 11909
Protoss_Assimilator 1 4147
Protoss_Cybernetics_Core 1 5723
Protoss_Zealot 1 5636
Protoss_Dragoon 5 12089
Protoss_Nexus 1 12179
Protoss_Robotics_Facility 1 12033
Singularity_Charge 1 10155
12179
