Protoss_Gateway 1 4051
Protoss_Assimilator 1 4512
Protoss_Zealot 1 5013
Protoss_Cybernetics_Core 1 5926
Protoss_Dragoon 2 9335
Protoss_Citadel_of_Adun 1 8139
Protoss_Templar_Archives 1 9722
Protoss_Dark_Templar 2 12048
Protoss_Nexus 1 13418
13418
