Protoss_Gateway 2 5033
Protoss_Zealot 7 12321
Protoss_Assimilator 2 10300
Protoss_Nexus 1 10129
Protoss_Cybernetics_Core 1 9552
Protoss_Citadel_of_Adun 1 11130
Protoss_Dragoon 2 11135
Protoss_Templar_Archives 1 12649
12649
