Protoss_Gateway 2 10400
Protoss_Assimilator 1 4158
Protoss_Cybernetics_Core 1 5566
Protoss_Zealot 2 11104
Protoss_Dragoon 4 10242
Protoss_Citadel_of_Adun 1 9413
Protoss_Templar_Archives 1 11001
Singularity_Charge 1 10664
Protoss_Dark_Templar 2 12224
12224
