Protoss_Gateway 1 4259
Protoss_Assimilator 1 5159
Protoss_Zealot 2 6687
Protoss_Cybernetics_Core 1 6725
Protoss_Dragoon 5 12458
Protoss_Nexus 1 11200
Protoss_Robotics_Facility 1 11746
12458
