Protoss_Gateway 1 4224
Protoss_Assimilator 1 4423
Protoss_Zealot 3 7147
Protoss_Cybernetics_Core 1 7085
Protoss_Dragoon 4 12077
Protoss_Nexus 1 12464
Protoss_Robotics_Facility 1 12352
12464
