Protoss_Gateway 2 7529
Protoss_Zealot 1 5098
Protoss_Assimilator 1 5317
Protoss_Cybernetics_Core 1 6649
Protoss_Dragoon 7 12268
Protoss_Robotics_Facility 1 12266
Singularity_Charge 1 10860
12268
