Protoss_Gateway 3 12652
Protoss_Assimilator 1 4442
Protoss_Cybernetics_Core 1 5759
Protoss_Dragoon 3 9478
Protoss_Nexus 1 10866
Protoss_Robotics_Facility 1 10974
Protoss_Observatory 1 11690
12652
