Protoss_Gateway 1 4220
Protoss_Assimilator 1 4444
Protoss_Zealot 2 6708
Protoss_Cybernetics_Core 1 6795
Protoss_Dragoon 3 10345
Protoss_Citadel_of_Adun 1 8888
Protoss_Templar_Archives 1 10381
Protoss_Nexus 1 13082
Protoss_Dark_Templar 1 11805
13082
