Protoss_Gateway 2 5133
Protoss_Zealot 7 11856
Protoss_Nexus 1 9944
Protoss_Assimilator 1 8672
Protoss_Forge 1 9529
Protoss_Photon_Cannon 2 11211
Protoss_Cybernetics_Core 1 11970
11970
