Protoss_Gateway 1 4085
Protoss_Assimilator 1 4193
Protoss_Cybernetics_Core 1 5696
Protoss_Dragoon 4 10488
Protoss_Robotics_Facility 1 9913
Protoss_Shuttle 1 11309
Protoss_Robotics_Support_Bay 1 10760
Protoss_Reaver 1 12919
12919
