Protoss_Gateway 2 12080
Protoss_Assimilator 1 4719
Protoss_Cybernetics_Core 1 6409
Protoss_Dragoon 5 12431
Protoss_Robotics_Facility 1 10128
Protoss_Forge 1 10704
Protoss_Observatory 1 11065
Singularity_Charge 1 10706
Protoss_Observer 1 12097
12431
