Protoss_Gateway 1 4369
Protoss_Assimilator 1 4412
Protoss_Cybernetics_Core 1 5876
Protoss_Robotics_Facility 1 8389
Protoss_Dragoon 4 11761
Protoss_Shuttle 1 9874
Protoss_Observatory 1 9268
Protoss_Observer 2 11598
Protoss_Nexus 1 14185
14185
