Protoss_Gateway 2 10524
Protoss_Zealot 2 6017
Protoss_Assimilator 1 5374
Protoss_Cybernetics_Core 1 7246
Protoss_Citadel_of_Adun 1 8729
Protoss_Dragoon 2 9613
Protoss_Templar_Archives 1 10198
Protoss_Forge 1 10678
Protoss_Dark_Templar 3 12522
12522
