Protoss_Gateway 1 4199
Protoss_Assimilator 1 4275
Protoss_Cybernetics_Core 1 5756
Protoss_Robotics_Facility 1 7786
Protoss_Zealot 2 8083
Protoss_Shuttle 1 9184
Protoss_Dragoon 3 12045
Protoss_Robotics_Support_Bay 1 9293
Protoss_Reaver 1 11052
12045
