Protoss_Gateway 2 8172
Protoss_Assimilator 2 4899
Protoss_Cybernetics_Core 1 6321
Protoss_Zealot 1 6160
Protoss_Dragoon 7 12604
Protoss_Citadel_of_Adun 1 12263
Singularity_Charge 1 10872
12604
