Protoss_Gateway 1 4167
Protoss_Zealot 2 6699
Protoss_Assimilator 1 5770
Protoss_Cybernetics_Core 1 6710
Protoss_Dragoon 5 12347
Protoss_Robotics_Facility 1 10336
Protoss_Shuttle 1 11733
Protoss_Observatory 1 11912
12347
