Protoss_Gateway 1 4445
Protoss_Assimilator 1 4564
Protoss_Cybernetics_Core 1 5993
Protoss_Zealot 2 10034
Protoss_Dragoon 2 9168
Protoss_Robotics_Facility 1 10538
Protoss_Citadel_of_Adun 1 11235
Protoss_Observatory 1 11297
Protoss_Forge 1 11572
Protoss_Templar_Archives 1 12696
12696
