Protoss_Gateway 2 8919
Protoss_Assimilator 1 4698
Protoss_Zealot 2 6778
Protoss_Cybernetics_Core 1 6880
Protoss_Dragoon 5 12437
Protoss_Nexus 1 13562
Protoss_Robotics_Facility 1 12985
Singularity_Charge 1 11337
13562
