Protoss_Gateway 2 12509
Protoss_Assimilator 1 4428
Protoss_Zealot 2 6915
Protoss_Cybernetics_Core 1 6927
Protoss_Dragoon 4 12490
Protoss_Nexus 1 12202
Protoss_Robotics_Facility 1 12592
Singularity_Charge 1 11071
12592
