Protoss_Gateway 1 4504
Protoss_Assimilator 1 5398
Protoss_Zealot 2 6924
Protoss_Cybernetics_Core 1 6942
Protoss_Dragoon 4 11583
Protoss_Robotics_Facility 1 10870
Protoss_Nexus 1 13786
Singularity_Charge 1 11094
Protoss_Observatory 1 11849
13786
