Protoss_Gateway 2 7518
Protoss_Assimilator 1 4352
Protoss_Zealot 1 5200
Protoss_Cybernetics_Core 1 6912
Protoss_Dragoon 6 11299
Protoss_Citadel_of_Adun 1 9993
Protoss_Templar_Archives 1 11475
Protoss_Forge 1 11661
Singularity_Charge 1 11118
11661
