Protoss_Gateway 2 12593
Protoss_Zealot 3 7050
Protoss_Assimilator 1 5253
Protoss_Cybernetics_Core 1 7035
Protoss_Dragoon 4 11976
Protoss_Nexus 1 11910
Protoss_Robotics_Facility 1 11685
Singularity_Charge 1 11120
12593
