Protoss_Gateway 2 9860
Protoss_Zealot 1 5592
Protoss_Assimilator 1 5852
Protoss_Cybernetics_Core 1 7272
Protoss_Dragoon 6 12391
Protoss_Robotics_Facility 1 12295
Singularity_Charge 1 10955
12391
