Protoss_Gateway 2 11527
Protoss_Zealot 3 6994
Protoss_Assimilator 1 5581
Protoss_Cybernetics_Core 1 7019
Protoss_Dragoon 4 11849
Protoss_Nexus 1 12428
Protoss_Robotics_Facility 1 12800
Singularity_Charge 1 11071
12800
