Protoss_Gateway 2 4968
Protoss_Zealot 6 11929
Protoss_Nexus 1 9878
Protoss_Assimilator 2 11423
Protoss_Cybernetics_Core 1 10602
Protoss_Dragoon 1 11829
Protoss_Citadel_of_Adun 1 12200
12200
