Protoss_Gateway 1 4123
Protoss_Assimilator 1 4410
Protoss_Cybernetics_Core 1 5727
Protoss_Zealot 1 5692
Protoss_Dragoon 5 12212
Singularity_Charge 1 10128
Protoss_Nexus 1 13184
Protoss_Robotics_Facility 1 13040
13184
