Protoss_Gateway 2 11111
Protoss_Assimilator 1 4552
Protoss_Zealot 1 5341
Protoss_Cybernetics_Core 1 6064
Protoss_Dragoon 5 12449
Protoss_Nexus 1 11765
Singularity_Charge 1 10000
Protoss_Robotics_Facility 1 12622
12622
