Protoss_Gateway 1 4149
Protoss_Assimilator 1 4470
Protoss_Zealot 2 6795
Protoss_Cybernetics_Core 1 6867
Protoss_Dragoon 4 12124
Protoss_Nexus 1 12429
Protoss_Robotics_Facility 1 12841
Singularity_Charge 1 11153
12841
