Protoss_Gateway 2 6864
Protoss_Assimilator 1 4392
Protoss_Cybernetics_Core 1 5641
Protoss_Dragoon 8 12282
Singularity_Charge 1 9830
Protoss_Citadel_of_Adun 1 12102
Protoss_Zealot 1 12187
12282
