Protoss_Gateway 2 10081
Protoss_Zealot 4 9989
Protoss_Assimilator 1 7252
Protoss_Cybernetics_Core 1 9266
Protoss_Robotics_Facility 1 11246
Protoss_Dragoon 2 11445
Protoss_Shuttle 1 12655
Protoss_Robotics_Support_Bay 1 12022
12655
