Protoss_Gateway 2 7943
Protoss_Assimilator 1 4515
Protoss_Cybernetics_Core 1 5686
Protoss_Zealot 1 5490
Protoss_Dragoon 8 12291
Protoss_Robotics_Facility 1 11048
Protoss_Observatory 1 11789
12291
