Protoss_Gateway 1 4272
Protoss_Assimilator 1 4501
Protoss_Zealot 3 7123
Protoss_Cybernetics_Core 1 7031
Protoss_Dragoon 4 11710
Protoss_Robotics_Facility 1 10700
Protoss_Shuttle 1 12181
Protoss_Observatory 1 11615
Singularity_Charge 1 11240
12181
