Protoss_Gateway 2 4963
Protoss_Zealot 9 11180
Protoss_Nexus 1 9772
Protoss_Assimilator 2 11710
Protoss_Cybernetics_Core 1 10269
Protoss_Citadel_of_Adun 1 11835
Protoss_Dragoon 1 12478
12478
