Protoss_Gateway 2 9236
Protoss_Assimilator 1 4309
Protoss_Cybernetics_Core 1 5856
Protoss_Zealot 1 5941
Protoss_Dragoon 5 12326
Protoss_Nexus 1 12997
Singularity_Charge 1 10304
Protoss_Robotics_Facility 1 12687
12997
