Protoss_Gateway 2 11082
Protoss_Assimilator 1 5287
Protoss_Zealot 2 6672
Protoss_Cybernetics_Core 1 6798
Protoss_Dragoon 6 12569
Protoss_Robotics_Facility 1 10602
Protoss_Shuttle 1 12113
Protoss_Observatory 1 11485
Singularity_Charge 1 10971
12569
