Protoss_Gateway 2 11114
Protoss_Assimilator 1 4385
Protoss_Zealot 2 6591
Protoss_Cybernetics_Core 1 6617
Protoss_Dragoon 5 12320
Protoss_Robotics_Facility 1 10418
Protoss_Shuttle 1 11821
Singularity_Charge 1 11062
Protoss_Observatory 1 11832
12320
