Protoss_Gateway 2 11993
Protoss_Zealot 2 6670
Protoss_Assimilator 1 5317
Protoss_Cybernetics_Core 1 6664
Protoss_Dragoon 4 11902
Protoss_Nexus 1 12388
Protoss_Robotics_Facility 1 11981
Singularity_Charge 1 10717
12388
