Protoss_Gateway 1 4155
Protoss_Assimilator 1 4499
Protoss_Zealot 5 11522
Protoss_Cybernetics_Core 1 6984
Protoss_Dragoon 1 8243
Protoss_Citadel_of_Adun 1 9792
Protoss_Robotics_Facility 1 10333
Protoss_Templar_Archives 1 11235
Protoss_Shuttle 1 11733
Singularity_Charge 1 10804
Protoss_Dark_Templar 1 12434
12434
