Protoss_Gateway 2 9646
Protoss_Assimilator 1 4517
Protoss_Zealot 4 12049
Protoss_Cybernetics_Core 1 6825
Protoss_Dragoon 3 10728
Protoss_Nexus 1 13506
Singularity_Charge 1 11159
Protoss_Robotics_Facility 1 13252
13506
