Protoss_Gateway 2 8086
Protoss_Assimilator 1 4188
Protoss_Cybernetics_Core 1 5952
Protoss_Zealot 1 6298
Protoss_Dragoon 6 11182
Protoss_Robotics_Facility 1 10238
Protoss_Shuttle 1 11701
Protoss_Robotics_Support_Bay 1 11889
11889
