Protoss_Gateway 2 12732
Protoss_Assimilator 1 4412
Protoss_Zealot 2 6643
Protoss_Cybernetics_Core 1 6608
Protoss_Dragoon 4 11270
Protoss_Robotics_Facility 1 10541
Protoss_Observatory 1 11234
Protoss_Nexus 1 13707
Singularity_Charge 1 10857
13707
