Protoss_Gateway 2 12634
Protoss_Assimilator 1 4394
Protoss_Zealot 1 5107
Protoss_Cybernetics_Core 1 6918
Protoss_Dragoon 4 11464
Protoss_Nexus 1 11752
Protoss_Robotics_Facility 1 12297
Singularity_Charge 1 10702
12634
