Protoss_Gateway 2 4998
Protoss_Zealot 10 11022
Protoss_Nexus 1 8777
Protoss_Assimilator 1 8598
Protoss_Cybernetics_Core 1 10960
Protoss_Citadel_of_Adun 1 12419
Protoss_Dragoon 2 12411
12419
