Protoss_Gateway 2 9514
Protoss_Assimilator 1 4188
Protoss_Cybernetics_Core 1 5894
Protoss_Dragoon 2 11949
Protoss_Citadel_of_Adun 1 7657
Protoss_Templar_Archives 1 9116
Protoss_Zealot 1 9160
Protoss_Dark_Templar 3 11536
11949
