Protoss_Gateway 1 4085
Protoss_Assimilator 1 4387
Protoss_Cybernetics_Core 1 5671
Protoss_Zealot 1 6403
Protoss_Dragoon 5 12528
Protoss_Robotics_Facility 1 10669
Singularity_Charge 1 9742
Protoss_Observatory 1 11376
Protoss_Nexus 1 14087
14087
