Protoss_Gateway 2 11335
Protoss_Zealot 3 7015
Protoss_Assimilator 1 5276
Protoss_Cybernetics_Core 1 7125
Protoss_Dragoon 3 10561
Protoss_Citadel_of_Adun 1 8917
Protoss_Templar_Archives 1 10416
Protoss_Dark_Templar 1 11662
11662
