Protoss_Gateway 1 4087
Protoss_Assimilator 1 4391
Protoss_Cybernetics_Core 1 5718
Protoss_Zealot 1 5528
Protoss_Dragoon 5 11706
Protoss_Robotics_Facility 1 10295
Singularity_Charge 1 9821
Protoss_Robotics_Support_Bay 1 11076
Protoss_Observatory 1 11179
Protoss_Reaver 1 12893
12893
