Protoss_Gateway 2 8755
Protoss_Assimilator 1 4530
Protoss_Cybernetics_Core 1 5809
Protoss_Zealot 1 5944
Protoss_Dragoon 7 11890
Protoss_Citadel_of_Adun 1 9874
Protoss_Templar_Archives 1 11323
Singularity_Charge 1 10061
11890
