Protoss_Gateway 2 9607
Protoss_Assimilator 1 4275
Protoss_Zealot 2 6131
Protoss_Cybernetics_Core 1 6239
Protoss_Dragoon 7 12071
Protoss_Robotics_Facility 1 12307
Singularity_Charge 1 10482
12307
