Protoss_Gateway 2 9927
Protoss_Assimilator 1 4412
Protoss_Cybernetics_Core 1 5933
Protoss_Dragoon 5 11196
Protoss_Citadel_of_Adun 1 9705
Protoss_Templar_Archives 1 11189
Singularity_Charge 1 9830
Protoss_Forge 1 11871
Protoss_Dark_Templar 2 12402
12402
