Protoss_Gateway 2 8955
Protoss_Assimilator 1 4422
Protoss_Zealot 3 10281
Protoss_Cybernetics_Core 1 6705
Protoss_Dragoon 5 11911
Protoss_Robotics_Facility 1 10909
Singularity_Charge 1 10860
Protoss_Shuttle 1 12312
Protoss_Observatory 1 12110
12312
