Protoss_Gateway 2 8688
Protoss_Assimilator 1 4725
Protoss_Zealot 3 7341
Protoss_Cybernetics_Core 1 7271
Protoss_Dragoon 2 11085
Protoss_Citadel_of_Adun 1 9652
Protoss_Templar_Archives 1 11184
Protoss_Dark_Templar 2 12410
12410
