Protoss_Gateway 2 11551
Protoss_Assimilator 1 4352
Protoss_Cybernetics_Core 1 5587
Protoss_Zealot 1 5917
Protoss_Dragoon 5 11659
Protoss_Nexus 1 11981
Singularity_Charge 1 9824
Protoss_Robotics_Facility 1 13179
13179
