Protoss_Gateway 2 5458
Protoss_Zealot 2 7985
Protoss_Assimilator 1 6056
Protoss_Cybernetics_Core 1 7736
Protoss_Citadel_of_Adun 1 9204
Protoss_Dragoon 2 10507
Protoss_Templar_Archives 1 10660
Protoss_Dark_Templar 2 11875
11875
