Protoss_Gateway 2 11895
Protoss_Assimilator 1 4332
Protoss_Zealot 2 6775
Protoss_Cybernetics_Core 1 6819
Protoss_Dragoon 5 12449
Protoss_Robotics_Facility 1 11117
Singularity_Charge 1 10813
Protoss_Observatory 1 11858
12449
