Protoss_Gateway 2 11272
Protoss_Assimilator 1 4366
Protoss_Zealot 2 6708
Protoss_Cybernetics_Core 1 6746
Protoss_Dragoon 4 11302
Protoss_Robotics_Facility 1 10484
Protoss_Shuttle 1 11961
Protoss_Observatory 1 11496
Singularity_Charge 1 10834
11961
