Protoss_Gateway 2 11229
Protoss_Assimilator 1 4432
Protoss_Zealot 2 6713
Protoss_Cybernetics_Core 1 6740
Protoss_Dragoon 4 11486
Protoss_Robotics_Facility 1 10450
Protoss_Shuttle 1 11996
Protoss_Observatory 1 11479
Singularity_Charge 1 10787
11996
