Protoss_Gateway 1 4145
Protoss_Assimilator 1 4397
Protoss_Cybernetics_Core 1 5647
Protoss_Zealot 1 6008
Protoss_Dragoon 5 11571
Protoss_Robotics_Facility 1 10554
Protoss_Nexus 1 13105
Singularity_Charge 1 10398
Protoss_Shuttle 1 12494
13105
