Protoss_Gateway 2 12538
Protoss_Assimilator 1 4472
Protoss_Cybernetics_Core 1 6312
Protoss_Zealot 1 6362
Protoss_Dragoon 5 12265
Protoss_Nexus 1 12157
Singularity_Charge 1 10848
Protoss_Robotics_Facility 1 12834
12834
