Protoss_Gateway 2 11396
Protoss_Assimilator 1 4368
Protoss_Zealot 2 6646
Protoss_Cybernetics_Core 1 6532
Protoss_Dragoon 5 12010
Protoss_Robotics_Facility 1 10574
Protoss_Shuttle 1 11999
Singularity_Charge 1 10872
Protoss_Observatory 1 11685
12010
