Protoss_Gateway 2 11041
Protoss_Assimilator 1 4308
Protoss_Zealot 2 6711
Protoss_Cybernetics_Core 1 6732
Protoss_Dragoon 4 11372
Protoss_Robotics_Facility 1 10571
Protoss_Shuttle 1 11967
Protoss_Observatory 1 11412
Singularity_Charge 1 10790
11967
