Protoss_Gateway 1 4185
Protoss_Assimilator 1 4308
Protoss_Zealot 2 6620
Protoss_Cybernetics_Core 1 6800
Protoss_Dragoon 5 12560
Protoss_Nexus 1 12602
Singularity_Charge 1 10919
Protoss_Robotics_Facility 1 13036
13036
