Protoss_Gateway 2 12023
Protoss_Assimilator 1 4580
Protoss_Zealot 2 7205
Protoss_Cybernetics_Core 1 7144
Protoss_Dragoon 4 12115
Protoss_Robotics_Facility 1 11228
Protoss_Observatory 1 11954
12115
