Protoss_Gateway 2 11767
Protoss_Assimilator 1 4463
Protoss_Cybernetics_Core 1 5860
Protoss_Zealot 1 5821
Protoss_Dragoon 4 12241
Protoss_Nexus 1 10284
Protoss_Robotics_Facility 1 10750
Protoss_Observatory 1 11537
12241
