Protoss_Gateway 2 11510
Protoss_Assimilator 1 4385
Protoss_Cybernetics_Core 1 5748
Protoss_Zealot 1 5575
Protoss_Dragoon 4 12590
Protoss_Nexus 1 11083
Protoss_Robotics_Facility 1 11489
12590
