Protoss_Gateway 2 10548
Protoss_Assimilator 1 4286
Protoss_Zealot 2 6550
Protoss_Cybernetics_Core 1 6599
Protoss_Dragoon 6 12197
Protoss_Robotics_Facility 1 10058
Protoss_Observatory 1 10772
Singularity_Charge 1 10676
Protoss_Robotics_Support_Bay 1 11577
Protoss_Observer 1 12058
12197
