Protoss_Gateway 2 11604
Protoss_Assimilator 1 4581
Protoss_Zealot 2 6945
Protoss_Cybernetics_Core 1 6986
Protoss_Dragoon 4 11621
Protoss_Robotics_Facility 1 11474
Singularity_Charge 1 11334
11621
