Protoss_Gateway 2 8797
Protoss_Assimilator 1 4460
Protoss_Zealot 2 7366
Protoss_Cybernetics_Core 1 6694
Protoss_Dragoon 8 12364
Protoss_Robotics_Facility 1 11287
Singularity_Charge 1 10450
Protoss_Shuttle 1 12757
12757
