Protoss_Gateway 2 10346
Protoss_Assimilator 1 4278
Protoss_Cybernetics_Core 1 5872
Protoss_Zealot 1 5753
Protoss_Dragoon 6 12376
Protoss_Robotics_Facility 1 9913
Protoss_Observatory 1 10719
Singularity_Charge 1 10187
Protoss_Observer 1 12178
Protoss_Shuttle 1 12822
12822
