Protoss_Gateway 2 11379
Protoss_Assimilator 1 4615
Protoss_Zealot 2 7343
Protoss_Cybernetics_Core 1 7211
Protoss_Dragoon 5 12572
Protoss_Robotics_Facility 1 10838
Protoss_Observatory 1 11590
Protoss_Shuttle 1 12321
Singularity_Charge 1 11393
12572
