Protoss_Gateway 1 4224
Protoss_Assimilator 1 4438
Protoss_Zealot 3 7012
Protoss_Cybernetics_Core 1 8080
Protoss_Dragoon 3 11589
Protoss_Nexus 1 11812
Protoss_Robotics_Facility 1 13078
13078
