Protoss_Gateway 2 8288
Protoss_Assimilator 1 4264
Protoss_Cybernetics_Core 1 5642
Protoss_Dragoon 8 12377
Protoss_Robotics_Facility 1 10946
Singularity_Charge 1 9440
Protoss_Observatory 1 11744
12377
