Protoss_Gateway 2 5007
Protoss_Assimilator 1 4987
Protoss_Cybernetics_Core 1 6830
Protoss_Zealot 2 7243
Protoss_Dragoon 7 11650
Protoss_Robotics_Facility 1 13072
Singularity_Charge 1 11331
13072
