Protoss_Gateway 2 12653
Protoss_Assimilator 1 4451
Protoss_Zealot 1 5312
Protoss_Cybernetics_Core 1 7154
Protoss_Dragoon 4 11703
Protoss_Nexus 1 12072
Protoss_Robotics_Facility 1 11875
Singularity_Charge 1 10834
12653
