Protoss_Gateway 2 7433
Protoss_Assimilator 1 4905
Protoss_Zealot 1 5338
Protoss_Cybernetics_Core 1 6664
Protoss_Dragoon 3 9581
Protoss_Nexus 1 12375
Protoss_Robotics_Facility 1 11998
Singularity_Charge 1 10980
Protoss_Forge 1 11941
12375
