Protoss_Gateway 2 8092
Protoss_Assimilator 1 4371
Protoss_Zealot 2 6728
Protoss_Cybernetics_Core 1 6743
Protoss_Dragoon 7 11875
Protoss_Shield_Battery 1 8060
Protoss_Robotics_Facility 1 13034
13034
