Protoss_Gateway 2 6710
Protoss_Assimilator 1 4210
Protoss_Zealot 5 8347
Protoss_Cybernetics_Core 1 8701
Protoss_Dragoon 2 9955
Protoss_Robotics_Facility 1 11375
Protoss_Nexus 1 13394
Protoss_Observatory 1 12074
13394
