Protoss_Gateway 2 11434
Protoss_Assimilator 1 4710
Protoss_Zealot 2 6807
Protoss_Cybernetics_Core 1 6847
Protoss_Dragoon 4 11381
Protoss_Robotics_Facility 1 11202
Singularity_Charge 1 10942
Protoss_Observatory 1 12001
12001
