Protoss_Gateway 2 9184
Protoss_Assimilator 1 4407
Protoss_Cybernetics_Core 1 5614
Protoss_Zealot 1 5950
Protoss_Dragoon 7 12464
Singularity_Charge 1 9464
Protoss_Robotics_Facility 1 11905
12464
