Protoss_Gateway 1 4211
Protoss_Assimilator 1 4510
Protoss_Cybernetics_Core 1 5919
Protoss_Zealot 2 7975
Protoss_Dragoon 3 11627
Protoss_Robotics_Facility 1 8444
Protoss_Observatory 1 9645
Protoss_Shuttle 1 10659
Protoss_Robotics_Support_Bay 1 10932
Protoss_Observer 1 11502
11627
