Protoss_Gateway 2 8259
Protoss_Assimilator 1 4436
Protoss_Zealot 2 7697
Protoss_Cybernetics_Core 1 6980
Protoss_Dragoon 7 12016
Protoss_Robotics_Facility 1 11978
Singularity_Charge 1 11006
12016
