Protoss_Gateway 2 8692
Protoss_Assimilator 1 4382
Protoss_Zealot 2 6658
Protoss_Cybernetics_Core 1 6629
Protoss_Dragoon 6 11931
Protoss_Robotics_Facility 1 11884
Singularity_Charge 1 11112
11931
