Protoss_Gateway 1 4540
Protoss_Assimilator 1 4581
Protoss_Cybernetics_Core 1 6034
Protoss_Robotics_Facility 1 8072
Protoss_Dragoon 2 11369
Protoss_Shuttle 1 9468
Protoss_Robotics_Support_Bay 1 9170
Protoss_Reaver 2 12565
12565
