Protoss_Gateway 1 4066
Protoss_Assimilator 1 4542
Protoss_Cybernetics_Core 1 5742
Protoss_Zealot 1 5490
Protoss_Dragoon 5 11995
Protoss_Nexus 1 10986
Protoss_Forge 1 10261
Protoss_Photon_Cannon 2 11628
11995
