Protoss_Gateway 3 11783
Protoss_Assimilator 1 4571
Protoss_Zealot 2 6986
Protoss_Cybernetics_Core 1 7063
Protoss_Dragoon 4 11908
Protoss_Robotics_Facility 1 10573
Protoss_Observatory 1 11311
Singularity_Charge 1 11126
Protoss_Observer 1 12345
12345
