Protoss_Gateway 2 10123
Protoss_Assimilator 1 4419
Protoss_Zealot 2 6646
Protoss_Cybernetics_Core 1 6713
Protoss_Dragoon 5 11676
Protoss_Robotics_Facility 1 9844
Protoss_Shuttle 1 11376
Protoss_Robotics_Support_Bay 1 11577
Singularity_Charge 1 11120
11676
