Protoss_Gateway 2 10302
Protoss_Assimilator 1 4423
Protoss_Cybernetics_Core 1 5718
Protoss_Zealot 1 5552
Protoss_Dragoon 2 8038
Protoss_Citadel_of_Adun 1 9039
Protoss_Templar_Archives 1 10776
Protoss_Dark_Templar 2 11990
11990
