Protoss_Gateway 1 4253
Protoss_Assimilator 1 4331
Protoss_Cybernetics_Core 1 5729
Protoss_Robotics_Facility 1 7921
Protoss_Dragoon 5 12563
Protoss_Observatory 1 9067
Protoss_Observer 2 11032
Protoss_Shuttle 1 12390
12563
