Protoss_Gateway 2 8961
Protoss_Assimilator 1 4429
Protoss_Cybernetics_Core 1 6219
Protoss_Zealot 1 5759
Protoss_Dragoon 7 12148
Protoss_Robotics_Facility 1 10263
Singularity_Charge 1 10052
Protoss_Observatory 1 11129
Protoss_Observer 1 12233
12233
