Protoss_Gateway 4 11829
Protoss_Assimilator 1 4412
Protoss_Cybernetics_Core 1 5625
Protoss_Zealot 1 5540
Protoss_Dragoon 5 12074
Protoss_Nexus 1 11730
Singularity_Charge 1 9991
12074
