Protoss_Gateway 2 4943
Protoss_Zealot 5 9567
Protoss_Nexus 1 10113
Protoss_Assimilator 2 11054
Protoss_Cybernetics_Core 1 9713
Protoss_Dragoon 4 12168
Protoss_Citadel_of_Adun 1 11824
12168
