Protoss_Gateway 1 4116
Protoss_Assimilator 1 4201
Protoss_Cybernetics_Core 1 5657
Protoss_Dragoon 4 10064
Protoss_Robotics_Facility 1 7965
Protoss_Shuttle 1 9485
Protoss_Observatory 1 9486
Protoss_Observer 1 11072
Protoss_Nexus 1 13454
13454
