Protoss_Gateway 3 12213
Protoss_Assimilator 1 4512
Protoss_Zealot 2 6842
Protoss_Cybernetics_Core 1 6896
Protoss_Dragoon 3 11012
Protoss_Nexus 1 12596
Singularity_Charge 1 11156
12596
