Protoss_Gateway 1 4138
Protoss_Assimilator 1 4442
Protoss_Cybernetics_Core 1 5791
Protoss_Zealot 1 5712
Protoss_Dragoon 5 11638
Protoss_Robotics_Facility 1 9806
Protoss_Shuttle 1 11256
Protoss_Robotics_Support_Bay 1 10648
Singularity_Charge 1 10052
Protoss_Reaver 1 12814
Protoss_Observatory 1 12032
12814
