Protoss_Gateway 3 9945
Protoss_Assimilator 1 4185
Protoss_Cybernetics_Core 1 5743
Protoss_Dragoon 5 12153
Protoss_Robotics_Facility 1 10977
Protoss_Citadel_of_Adun 1 10594
Singularity_Charge 1 9642
Protoss_Forge 1 11238
Protoss_Templar_Archives 1 12203
12203
