Protoss_Gateway 2 10116
Protoss_Assimilator 1 4346
Protoss_Zealot 3 6702
Protoss_Cybernetics_Core 1 6855
Protoss_Dragoon 7 12464
Protoss_Robotics_Facility 1 12434
Singularity_Charge 1 10813
12464
