Protoss_Gateway 3 12339
Protoss_Assimilator 1 4308
Protoss_Zealot 2 11973
Protoss_Cybernetics_Core 1 7028
Protoss_Citadel_of_Adun 1 8958
Protoss_Dragoon 5 12519
Protoss_Templar_Archives 1 12239
12519
