Protoss_Gateway 2 10729
Protoss_Assimilator 1 4438
Protoss_Zealot 2 6725
Protoss_Cybernetics_Core 1 6798
Protoss_Dragoon 5 12089
Protoss_Robotics_Facility 1 10204
Protoss_Shuttle 1 11677
Protoss_Observatory 1 11384
Singularity_Charge 1 11088
12089
