Protoss_Gateway 3 12743
Protoss_Assimilator 1 4240
Protoss_Zealot 2 6596
Protoss_Cybernetics_Core 1 6636
Protoss_Dragoon 4 11425
Protoss_Nexus 1 12265
Protoss_Robotics_Facility 1 11868
Singularity_Charge 1 10807
12743
