Protoss_Gateway 1 4792
Protoss_Assimilator 1 4652
Protoss_Zealot 3 7692
Protoss_Cybernetics_Core 1 7880
Protoss_Dragoon 1 9439
Protoss_Robotics_Facility 2 11350
Protoss_Observatory 1 11586
Protoss_Shuttle 1 12318
Protoss_Robotics_Support_Bay 1 12104
12318
