Protoss_Gateway 1 4397
Protoss_Assimilator 1 4514
Protoss_Zealot 1 5388
Protoss_Cybernetics_Core 1 7097
Protoss_Dragoon 4 11751
Protoss_Robotics_Facility 1 10005
Protoss_Robotics_Support_Bay 1 10785
Singularity_Charge 1 10787
11751
