Protoss_Gateway 1 4230
Protoss_Assimilator 1 4117
Protoss_Cybernetics_Core 1 5726
Protoss_Zealot 1 5455
Protoss_Dragoon 5 12307
Protoss_Robotics_Facility 1 9614
Protoss_Nexus 1 12365
Protoss_Observatory 1 10491
Singularity_Charge 1 9862
Protoss_Observer 1 11844
12365
