Protoss_Nexus 1 7360
Protoss_Gateway 2 7281
Protoss_Forge 1 7865
Protoss_Zealot 9 12283
Protoss_Photon_Cannon 3 11312
Protoss_Assimilator 1 9999
Protoss_Cybernetics_Core 1 12841
12841
