Protoss_Gateway 1 4265
Protoss_Assimilator 1 4129
Protoss_Zealot 1 5278
Protoss_Cybernetics_Core 1 7294
Protoss_Dragoon 2 10456
Protoss_Robotics_Facility 1 9434
Protoss_Shuttle 1 10848
Protoss_Robotics_Support_Bay 1 10677
Protoss_Reaver 1 12790
12790
