Protoss_Gateway 2 11628
Protoss_Assimilator 1 4657
Protoss_Zealot 2 6874
Protoss_Cybernetics_Core 1 6931
Protoss_Dragoon 4 12256
Protoss_Robotics_Facility 1 11296
Protoss_Observatory 1 12083
12256
