Protoss_Gateway 2 11019
Protoss_Assimilator 1 4504
Protoss_Zealot 3 12055
Protoss_Cybernetics_Core 1 7255
Protoss_Dragoon 4 11764
Protoss_Citadel_of_Adun 1 10368
Protoss_Templar_Archives 1 11843
Singularity_Charge 1 11255
12055
