Protoss_Gateway 3 12617
Protoss_Assimilator 1 4414
Protoss_Zealot 2 6810
Protoss_Cybernetics_Core 1 6866
Protoss_Dragoon 4 11597
Protoss_Nexus 1 11885
Protoss_Robotics_Facility 1 12114
Singularity_Charge 1 10872
12617
