Protoss_Gateway 2 7785
Protoss_Assimilator 1 4452
Protoss_Zealot 1 5112
Protoss_Cybernetics_Core 1 7268
Protoss_Dragoon 6 11507
Protoss_Robotics_Facility 1 11656
Singularity_Charge 1 11182
11656
