Protoss_Gateway 2 9160
Protoss_Assimilator 1 5263
Protoss_Cybernetics_Core 1 6304
Protoss_Zealot 3 12105
Protoss_Dragoon 6 12165
Protoss_Robotics_Facility 1 10119
Protoss_Observatory 1 11161
Protoss_Observer 1 12272
12272
