Protoss_Gateway 2 11938
Protoss_Assimilator 1 4436
Protoss_Cybernetics_Core 1 5648
Protoss_Zealot 1 5537
Protoss_Dragoon 4 10924
Protoss_Nexus 1 12338
Singularity_Charge 1 9871
Protoss_Robotics_Facility 1 12920
12920
