Protoss_Gateway 2 11759
Protoss_Assimilator 1 4874
Protoss_Zealot 2 5209
Protoss_Cybernetics_Core 1 6945
Protoss_Dragoon 4 11682
Protoss_Nexus 1 12401
Protoss_Robotics_Facility 1 11950
Singularity_Charge 1 10743
12401
