Protoss_Gateway 2 10009
Protoss_Assimilator 1 4366
Protoss_Zealot 2 6769
Protoss_Cybernetics_Core 1 6772
Protoss_Dragoon 5 11539
Protoss_Robotics_Facility 1 10059
Protoss_Observatory 1 11196
Singularity_Charge 1 10760
Protoss_Nexus 1 13983
Protoss_Observer 1 12298
13983
