Protoss_Gateway 2 11058
Protoss_Assimilator 1 4325
Protoss_Zealot 2 6617
Protoss_Cybernetics_Core 1 6627
Protoss_Dragoon 4 11188
Protoss_Robotics_Facility 1 10140
Protoss_Shuttle 1 11709
Protoss_Observatory 1 11047
Singularity_Charge 1 10752
11709
