Protoss_Gateway 1 4190
Protoss_Assimilator 1 4504
Protoss_Zealot 2 7164
Protoss_Cybernetics_Core 1 7284
Protoss_Dragoon 4 12133
Protoss_Nexus 1 12798
Protoss_Citadel_of_Adun 1 11841
12798
