Protoss_Gateway 1 4188
Protoss_Assimilator 1 4217
Protoss_Zealot 2 7208
Protoss_Cybernetics_Core 1 6833
Protoss_Citadel_of_Adun 1 8355
Protoss_Dragoon 2 9920
Protoss_Templar_Archives 1 9804
Protoss_Forge 1 10176
Protoss_Dark_Templar 1 11021
Protoss_Photon_Cannon 1 11466
Protoss_High_Templar 1 12121
12121
