Protoss_Gateway 2 12614
Protoss_Assimilator 1 5212
Protoss_Zealot 2 6828
Protoss_Cybernetics_Core 1 6874
Protoss_Dragoon 4 11811
Protoss_Nexus 1 12451
Protoss_Robotics_Facility 1 12063
Singularity_Charge 1 10898
12614
