Protoss_Gateway 2 10349
Protoss_Assimilator 1 4410
Protoss_Zealot 2 6406
Protoss_Cybernetics_Core 1 6721
Protoss_Dragoon 5 12262
Protoss_Robotics_Facility 1 9682
Protoss_Shuttle 1 11080
Protoss_Observatory 1 10654
Singularity_Charge 1 10810
Protoss_Observer 1 11923
Protoss_Robotics_Support_Bay 1 11966
12262
