Protoss_Gateway 2 10949
Protoss_Zealot 2 6687
Protoss_Assimilator 1 5714
Protoss_Cybernetics_Core 1 6804
Protoss_Dragoon 4 11773
Protoss_Robotics_Facility 1 11089
Singularity_Charge 1 11080
Protoss_Observatory 1 11865
11865
