Protoss_Gateway 2 10928
Protoss_Assimilator 1 4161
Protoss_Zealot 2 6605
Protoss_Cybernetics_Core 1 6782
Protoss_Dragoon 6 12499
Protoss_Robotics_Facility 1 10598
Protoss_Observatory 1 11333
Singularity_Charge 1 10720
Protoss_Observer 1 12359
12499
