Protoss_Gateway 2 9187
Protoss_Assimilator 1 4338
Protoss_Cybernetics_Core 1 5819
Protoss_Zealot 1 5554
Protoss_Dragoon 6 11767
Protoss_Robotics_Facility 1 10444
Singularity_Charge 1 9754
Protoss_Shuttle 1 11847
Protoss_Observatory 1 11659
11847
