Protoss_Gateway 2 10943
Protoss_Assimilator 1 4363
Protoss_Zealot 2 6845
Protoss_Cybernetics_Core 1 7212
Protoss_Dragoon 5 12344
Protoss_Robotics_Facility 1 10432
Protoss_Shuttle 1 11827
Singularity_Charge 1 11065
Protoss_Observatory 1 11975
12344
