Protoss_Gateway 1 4073
Protoss_Assimilator 1 4420
Protoss_Cybernetics_Core 1 5815
Protoss_Zealot 1 5660
Protoss_Dragoon 5 11758
Protoss_Robotics_Facility 1 10066
Singularity_Charge 1 10026
Protoss_Shuttle 1 11689
Protoss_Observatory 1 11157
Protoss_Robotics_Support_Bay 1 12010
12010
