Protoss_Gateway 2 10975
Protoss_Assimilator 1 4227
Protoss_Zealot 2 6564
Protoss_Cybernetics_Core 1 6624
Protoss_Dragoon 4 11188
Protoss_Robotics_Facility 1 10530
Protoss_Observatory 1 11319
Singularity_Charge 1 10854
Protoss_Nexus 1 14008
Protoss_Observer 1 12345
14008
