Protoss_Gateway 1 4089
Protoss_Assimilator 1 4422
Protoss_Zealot 2 6670
Protoss_Cybernetics_Core 1 6650
Protoss_Dragoon 5 12303
Protoss_Robotics_Facility 1 10027
Protoss_Robotics_Support_Bay 1 10737
Singularity_Charge 1 10790
Protoss_Shuttle 1 12289
12303
