Protoss_Gateway 2 11162
Protoss_Assimilator 1 4565
Protoss_Cybernetics_Core 1 5941
Protoss_Zealot 1 5762
Protoss_Dragoon 5 12092
Protoss_Robotics_Facility 1 10631
Singularity_Charge 1 10283
Protoss_Shuttle 1 12049
12092
