Protoss_Gateway 3 12318
Protoss_Assimilator 1 4414
Protoss_Zealot 2 6872
Protoss_Cybernetics_Core 1 6898
Protoss_Dragoon 5 12502
Protoss_Nexus 1 12722
Singularity_Charge 1 11033
12722
