Protoss_Gateway 2 11718
Protoss_Zealot 2 6895
Protoss_Assimilator 1 5309
Protoss_Cybernetics_Core 1 7135
Protoss_Dragoon 4 11846
Protoss_Nexus 1 11957
Singularity_Charge 1 10921
11957
