Protoss_Gateway 2 10299
Protoss_Assimilator 1 4483
Protoss_Zealot 2 6863
Protoss_Cybernetics_Core 1 6866
Protoss_Dragoon 5 11750
Protoss_Robotics_Facility 1 10182
Protoss_Observatory 1 10994
Singularity_Charge 1 11039
Protoss_Observer 1 12289
12289
