Protoss_Gateway 2 10349
Protoss_Assimilator 1 4567
Protoss_Zealot 2 7000
Protoss_Cybernetics_Core 1 6971
Protoss_Dragoon 5 11729
Protoss_Robotics_Facility 1 10353
Protoss_Shuttle 1 11847
Singularity_Charge 1 11088
Protoss_Robotics_Support_Bay 1 12066
12066
