Protoss_Gateway 2 10224
Protoss_Assimilator 1 4495
Protoss_Zealot 2 6898
Protoss_Cybernetics_Core 1 6942
Protoss_Dragoon 5 11706
Protoss_Robotics_Facility 1 10321
Protoss_Shuttle 1 11756
Protoss_Robotics_Support_Bay 1 11638
Singularity_Charge 1 11238
11756
