Protoss_Gateway 1 4152
Protoss_Assimilator 1 4447
Protoss_Zealot 2 6933
Protoss_Cybernetics_Core 1 6983
Protoss_Dragoon 4 11802
Protoss_Citadel_of_Adun 1 10410
Protoss_Templar_Archives 1 11947
Protoss_Nexus 1 14171
Singularity_Charge 1 11399
14171
