Protoss_Gateway 1 4218
Protoss_Assimilator 1 4495
Protoss_Zealot 2 6907
Protoss_Cybernetics_Core 1 6912
Protoss_Dragoon 4 12042
Protoss_Citadel_of_Adun 1 10637
Protoss_Nexus 1 13320
Protoss_Templar_Archives 1 12084
Singularity_Charge 1 11211
13320
