Protoss_Gateway 1 4199
Protoss_Assimilator 1 4445
Protoss_Zealot 2 7041
Protoss_Cybernetics_Core 1 6892
Protoss_Dragoon 4 11632
Protoss_Citadel_of_Adun 1 9406
Protoss_Templar_Archives 1 11221
Protoss_Nexus 1 13604
Singularity_Charge 1 11123
13604
