Protoss_Gateway 2 11171
Protoss_Assimilator 1 4452
Protoss_Zealot 2 6459
Protoss_Cybernetics_Core 1 6671
Protoss_Dragoon 5 12505
Protoss_Robotics_Facility 1 10476
Protoss_Shuttle 1 11996
Singularity_Charge 1 10684
Protoss_Robotics_Support_Bay 1 11833
12505
