Protoss_Gateway 2 11363
Protoss_Assimilator 1 4186
Protoss_Zealot 2 6869
Protoss_Cybernetics_Core 1 6869
Protoss_Dragoon 4 11791
Protoss_Robotics_Facility 1 10937
Singularity_Charge 1 10702
Protoss_Shuttle 1 12368
12368
