Protoss_Gateway 2 10812
Protoss_Assimilator 1 4436
Protoss_Zealot 2 6298
Protoss_Cybernetics_Core 1 7691
Protoss_Dragoon 4 12060
Protoss_Robotics_Facility 1 10861
Protoss_Observatory 1 11656
12060
