Protoss_Gateway 2 10706
Protoss_Assimilator 1 4567
Protoss_Zealot 2 7319
Protoss_Cybernetics_Core 1 7340
Protoss_Dragoon 5 11957
Protoss_Robotics_Facility 1 10791
Protoss_Shuttle 1 12514
Singularity_Charge 1 11366
12514
