Protoss_Gateway 2 10580
Protoss_Assimilator 1 4413
Protoss_Cybernetics_Core 1 5639
Protoss_Zealot 1 5774
Protoss_Dragoon 6 12057
Protoss_Robotics_Facility 1 9660
Singularity_Charge 1 9306
Protoss_Observatory 1 10469
Protoss_Observer 1 11487
12057
