Protoss_Gateway 2 10457
Protoss_Assimilator 1 4543
Protoss_Zealot 2 7059
Protoss_Cybernetics_Core 1 7018
Protoss_Dragoon 5 11671
Protoss_Robotics_Facility 1 10645
Protoss_Shuttle 1 12154
Singularity_Charge 1 11273
Protoss_Robotics_Support_Bay 1 12080
12154
