Protoss_Gateway 2 10858
Protoss_Assimilator 1 4227
Protoss_Zealot 2 6664
Protoss_Cybernetics_Core 1 6747
Protoss_Dragoon 5 12086
Protoss_Robotics_Facility 1 10459
Protoss_Observatory 1 11179
Singularity_Charge 1 11041
Protoss_Observer 1 12307
12307
