Protoss_Gateway 1 4195
Protoss_Assimilator 1 4514
Protoss_Zealot 2 6860
Protoss_Cybernetics_Core 1 6940
Protoss_Dragoon 4 11436
Protoss_Citadel_of_Adun 1 10013
Protoss_Templar_Archives 1 11469
Protoss_Nexus 1 13571
Singularity_Charge 1 11071
Protoss_Forge 1 12026
13571
