Protoss_Gateway 1 4198
Protoss_Assimilator 1 4508
Protoss_Zealot 2 6819
Protoss_Cybernetics_Core 1 6869
Protoss_Dragoon 4 11390
Protoss_Citadel_of_Adun 1 9804
Protoss_Templar_Archives 1 11253
Protoss_Nexus 1 13495
Singularity_Charge 1 10957
Protoss_Forge 1 12096
Protoss_Dark_Templar 1 12578
13495
