Protoss_Gateway 2 11455
Protoss_Assimilator 1 4180
Protoss_Cybernetics_Core 1 5588
Protoss_Zealot 1 5344
Protoss_Citadel_of_Adun 1 7038
Protoss_Dragoon 3 11524
Protoss_Templar_Archives 1 8529
Protoss_Dark_Templar 1 9865
Protoss_Nexus 1 12157
12157
