Protoss_Gateway 2 9892
Protoss_Zealot 2 6672
Protoss_Assimilator 1 5667
Protoss_Cybernetics_Core 1 6923
Protoss_Dragoon 5 11600
Protoss_Robotics_Facility 1 11725
Singularity_Charge 1 11211
11725
