Protoss_Gateway 2 7287
Protoss_Assimilator 1 4299
Protoss_Zealot 1 5265
Protoss_Cybernetics_Core 1 6380
Protoss_Dragoon 7 11435
Protoss_Robotics_Facility 1 11665
Singularity_Charge 1 10076
11665
