Protoss_Gateway 1 4344
Protoss_Assimilator 1 4552
Protoss_Zealot 2 6514
Protoss_Cybernetics_Core 1 6538
Protoss_Dragoon 4 12101
Protoss_Robotics_Facility 1 10315
Protoss_Observatory 1 11024
Protoss_Robotics_Support_Bay 1 11065
Singularity_Charge 1 10781
Protoss_Reaver 1 13077
13077
