Protoss_Gateway 2 7931
Protoss_Assimilator 1 4562
Protoss_Zealot 3 7712
Protoss_Cybernetics_Core 1 6801
Protoss_Dragoon 5 12230
Protoss_Robotics_Facility 1 11401
Singularity_Charge 1 11317
12230
