Protoss_Gateway 2 5270
Protoss_Assimilator 2 5944
Protoss_Zealot 7 11350
Protoss_Cybernetics_Core 1 8385
Protoss_Dragoon 3 12587
Protoss_Citadel_of_Adun 1 11313
Protoss_Forge 1 12118
12587
