Protoss_Gateway 2 5036
Protoss_Assimilator 1 5091
Protoss_Cybernetics_Core 1 6852
Protoss_Zealot 2 7431
Protoss_Dragoon 5 11524
Protoss_Robotics_Facility 1 10014
Protoss_Observatory 1 11239
Singularity_Charge 1 11077
Protoss_Observer 1 12257
12257
