Protoss_Gateway 2 4902
Protoss_Assimilator 1 5459
Protoss_Cybernetics_Core 1 6873
Protoss_Zealot 2 7627
Protoss_Citadel_of_Adun 1 8947
Protoss_Forge 1 9356
Protoss_Templar_Archives 1 10823
Protoss_High_Templar 2 12370
12370
