Protoss_Gateway 2 5004
Protoss_Zealot 5 7656
Protoss_Nexus 1 10768
Protoss_Forge 2 10003
Protoss_Assimilator 1 10151
Protoss_Photon_Cannon 3 12493
Protoss_Cybernetics_Core 1 12312
12493
