Protoss_Gateway 2 11390
Protoss_Assimilator 1 4360
Protoss_Cybernetics_Core 1 6245
Protoss_Zealot 1 6353
Protoss_Dragoon 4 11542
Protoss_Nexus 1 11681
Singularity_Charge 1 11006
11681
