Protoss_Gateway 2 7448
Protoss_Assimilator 1 4574
Protoss_Zealot 1 5124
Protoss_Cybernetics_Core 1 6789
Protoss_Dragoon 7 11928
Protoss_Robotics_Facility 1 10731
Singularity_Charge 1 10717
Protoss_Shuttle 1 12181
Protoss_Robotics_Support_Bay 1 11577
12181
