Protoss_Gateway 1 4041
Protoss_Assimilator 1 4252
Protoss_Cybernetics_Core 1 5666
Protoss_Zealot 1 5449
Protoss_Dragoon 5 12063
Protoss_Robotics_Facility 1 10789
Protoss_Nexus 1 13332
Protoss_Observatory 1 12001
Singularity_Charge 1 11372
13332
