Protoss_Gateway 2 11256
Protoss_Assimilator 1 4325
Protoss_Zealot 2 6716
Protoss_Cybernetics_Core 1 6661
Protoss_Dragoon 4 11419
Protoss_Robotics_Facility 1 10479
Protoss_Shuttle 1 11999
Protoss_Observatory 1 11713
Singularity_Charge 1 11153
11999
