Protoss_Gateway 2 7433
Protoss_Assimilator 1 4376
Protoss_Zealot 2 6447
Protoss_Cybernetics_Core 1 6391
Protoss_Dragoon 9 12431
Protoss_Robotics_Facility 1 11465
Singularity_Charge 1 10330
12431
