Protoss_Gateway 2 10508
Protoss_Assimilator 1 4287
Protoss_Cybernetics_Core 1 6768
Protoss_Zealot 1 6593
Protoss_Dragoon 5 11837
Protoss_Robotics_Facility 1 10377
Protoss_Observatory 1 11147
Singularity_Charge 1 10594
11837
