Protoss_Gateway 3 11709
Protoss_Assimilator 1 4442
Protoss_Zealot 2 6699
Protoss_Cybernetics_Core 1 6773
Protoss_Dragoon 3 11843
Protoss_Nexus 1 11715
Protoss_Robotics_Facility 1 11490
Singularity_Charge 1 10816
11843
