Protoss_Gateway 2 7477
Protoss_Assimilator 1 4335
Protoss_Zealot 2 6397
Protoss_Cybernetics_Core 1 6462
Protoss_Dragoon 8 12508
Protoss_Robotics_Facility 1 10422
Singularity_Charge 1 10766
Protoss_Observatory 1 11782
12508
