Protoss_Gateway 1 4085
Protoss_Assimilator 1 4116
Protoss_Zealot 2 6392
Protoss_Cybernetics_Core 1 6451
Protoss_Dragoon 5 12165
Protoss_Robotics_Facility 1 9226
Protoss_Robotics_Support_Bay 1 9920
Protoss_Reaver 1 11877
Protoss_Observatory 1 11381
12165
