Protoss_Gateway 2 10758
Protoss_Assimilator 1 4420
Protoss_Zealot 2 6570
Protoss_Cybernetics_Core 1 6823
Protoss_Dragoon 5 11975
Protoss_Robotics_Facility 1 10557
Protoss_Observatory 1 11508
Singularity_Charge 1 11226
11975
