Protoss_Gateway 2 9962
Protoss_Assimilator 1 4445
Protoss_Zealot 2 6362
Protoss_Cybernetics_Core 1 6637
Protoss_Dragoon 5 11609
Protoss_Robotics_Facility 1 10181
Protoss_Observatory 1 11034
Singularity_Charge 1 10679
Protoss_Observer 1 12333
12333
