Protoss_Gateway 1 4135
Protoss_Assimilator 1 4136
Protoss_Zealot 3 10354
Protoss_Cybernetics_Core 1 6999
Protoss_Dragoon 3 12191
Protoss_Nexus 1 12447
Protoss_Robotics_Facility 1 13129
Singularity_Charge 1 11396
13129
