Protoss_Gateway 3 12438
Protoss_Assimilator 1 4700
Protoss_Zealot 2 6708
Protoss_Cybernetics_Core 1 6454
Protoss_Dragoon 5 12554
Protoss_Nexus 1 12726
Singularity_Charge 1 10954
12726
