Protoss_Gateway 3 11411
Protoss_Assimilator 1 4488
Protoss_Cybernetics_Core 1 5818
Protoss_Dragoon 7 12010
Protoss_Robotics_Facility 1 10776
Singularity_Charge 1 10000
Protoss_Observatory 1 12010
12010
