Protoss_Gateway 3 12690
Protoss_Assimilator 1 4555
Protoss_Zealot 2 6465
Protoss_Cybernetics_Core 1 6807
Protoss_Dragoon 6 12408
Protoss_Robotics_Facility 1 11363
Singularity_Charge 1 10693
12690
