Protoss_Gateway 2 11677
Protoss_Assimilator 1 4410
Protoss_Zealot 3 7117
Protoss_Cybernetics_Core 1 7097
Protoss_Dragoon 4 12320
Protoss_Robotics_Facility 1 10769
Protoss_Shuttle 1 12257
Protoss_Observatory 1 11988
12320
