Protoss_Gateway 1 4079
Protoss_Assimilator 1 4376
Protoss_Zealot 2 7144
Protoss_Cybernetics_Core 1 6744
Protoss_Dragoon 5 12546
Protoss_Robotics_Facility 1 9314
Protoss_Shuttle 1 10720
Protoss_Robotics_Support_Bay 1 10310
Protoss_Reaver 1 12278
12546
