Protoss_Gateway 2 12220
Protoss_Assimilator 1 4373
Protoss_Zealot 2 6670
Protoss_Cybernetics_Core 1 6681
Protoss_Dragoon 4 11845
Protoss_Robotics_Facility 1 9894
Protoss_Shuttle 1 11294
Protoss_Observatory 1 10948
Singularity_Charge 1 11012
Protoss_Observer 1 12153
Protoss_Robotics_Support_Bay 1 11949
12220
