Protoss_Gateway 2 10126
Protoss_Assimilator 1 4474
Protoss_Zealot 2 6845
Protoss_Cybernetics_Core 1 6778
Protoss_Dragoon 6 12590
Protoss_Robotics_Facility 1 10173
Protoss_Shuttle 1 12192
Singularity_Charge 1 10813
Protoss_Observatory 1 11896
12590
