Protoss_Gateway 2 10231
Protoss_Assimilator 1 4252
Protoss_Zealot 2 6915
Protoss_Cybernetics_Core 1 6965
Protoss_Dragoon 5 11764
Protoss_Robotics_Facility 1 10277
Protoss_Observatory 1 11368
Singularity_Charge 1 10927
11764
