Protoss_Gateway 2 10092
Protoss_Assimilator 1 4172
Protoss_Zealot 2 6629
Protoss_Cybernetics_Core 1 6912
Protoss_Dragoon 5 11492
Protoss_Robotics_Facility 1 12405
Singularity_Charge 1 10930
12405
