Protoss_Gateway 3 9927
Protoss_Assimilator 1 4572
Protoss_Zealot 2 6620
Protoss_Cybernetics_Core 1 6743
Protoss_Dragoon 7 11931
Protoss_Robotics_Facility 1 11673
Singularity_Charge 1 11132
11931
