Protoss_Gateway 2 8764
Protoss_Assimilator 1 4515
Protoss_Zealot 1 5256
Protoss_Cybernetics_Core 1 6175
Protoss_Dragoon 7 12440
Protoss_Robotics_Facility 1 11667
Singularity_Charge 1 10231
12440
