Protoss_Gateway 2 11234
Protoss_Assimilator 1 4220
Protoss_Zealot 2 7641
Protoss_Cybernetics_Core 1 7719
Protoss_Dragoon 3 11808
Protoss_Robotics_Facility 1 11021
Protoss_Observatory 1 11712
Protoss_Robotics_Support_Bay 1 11946
11946
