Protoss_Gateway 3 12428
Protoss_Zealot 2 7129
Protoss_Nexus 1 8665
Protoss_Assimilator 1 7378
Protoss_Forge 1 8260
Protoss_Cybernetics_Core 1 9213
Protoss_Photon_Cannon 3 10391
Protoss_Dragoon 2 11767
12428
