Protoss_Gateway 2 9981
Protoss_Assimilator 1 4318
Protoss_Zealot 2 6541
Protoss_Cybernetics_Core 1 6529
Protoss_Citadel_of_Adun 1 8589
Protoss_Dragoon 1 8796
Protoss_Templar_Archives 1 10097
Protoss_Dark_Templar 2 11548
Protoss_Forge 1 11215
11548
