Protoss_Gateway 2 6803
Protoss_Assimilator 1 4363
Protoss_Zealot 1 5072
Protoss_Cybernetics_Core 1 6197
Protoss_Dragoon 7 11559
Protoss_Nexus 1 12251
Singularity_Charge 1 10160
Protoss_Citadel_of_Adun 1 12573
12573
