Protoss_Gateway 2 10663
Protoss_Assimilator 1 4388
Protoss_Zealot 2 6711
Protoss_Cybernetics_Core 1 6860
Protoss_Dragoon 4 11896
Protoss_Robotics_Facility 1 10582
Protoss_Shuttle 1 12090
Singularity_Charge 1 11074
12090
