Protoss_Gateway 2 10349
Protoss_Assimilator 1 4527
Protoss_Zealot 2 6953
Protoss_Cybernetics_Core 1 7053
Protoss_Dragoon 5 11785
Protoss_Citadel_of_Adun 1 9855
Protoss_Templar_Archives 1 11344
Singularity_Charge 1 11138
11785
