Protoss_Gateway 2 9400
Protoss_Assimilator 1 4777
Protoss_Zealot 1 4943
Protoss_Cybernetics_Core 1 7040
Protoss_Dragoon 3 11998
Protoss_Citadel_of_Adun 1 8382
Protoss_Templar_Archives 1 9727
Protoss_Forge 1 9700
Protoss_Dark_Templar 2 10854
Protoss_Photon_Cannon 2 11656
11998
