Protoss_Gateway 1 4255
Protoss_Assimilator 1 4428
Protoss_Cybernetics_Core 1 5977
Protoss_Robotics_Facility 1 8136
Protoss_Dragoon 3 11692
Protoss_Shuttle 1 9545
Protoss_Robotics_Support_Bay 1 8987
Protoss_Reaver 2 12643
12643
