Protoss_Gateway 2 11241
Protoss_Assimilator 1 4472
Protoss_Zealot 2 6807
Protoss_Cybernetics_Core 1 6912
Protoss_Dragoon 6 12540
Protoss_Robotics_Facility 1 10522
Protoss_Observatory 1 11314
Singularity_Charge 1 10933
12540
