Protoss_Gateway 2 10483
Protoss_Assimilator 1 4439
Protoss_Zealot 2 6880
Protoss_Cybernetics_Core 1 7111
Protoss_Dragoon 5 12001
Protoss_Robotics_Facility 1 10107
Protoss_Shuttle 1 11549
Protoss_Observatory 1 11659
Singularity_Charge 1 11340
12001
