Protoss_Gateway 1 4514
Protoss_Assimilator 1 4821
Protoss_Cybernetics_Core 1 6269
Protoss_Robotics_Facility 1 8356
Protoss_Dragoon 4 12197
Protoss_Shuttle 1 9757
Protoss_Observatory 1 9345
Protoss_Observer 1 11256
Protoss_Robotics_Support_Bay 1 11205
12197
