Protoss_Gateway 2 9217
Protoss_Zealot 2 6790
Protoss_Assimilator 1 5073
Protoss_Cybernetics_Core 1 7274
Protoss_Dragoon 6 11565
Protoss_Robotics_Facility 1 11512
Singularity_Charge 1 10851
11565
