Protoss_Gateway 2 10946
Protoss_Assimilator 1 4489
Protoss_Zealot 2 6848
Protoss_Cybernetics_Core 1 6961
Protoss_Dragoon 5 12358
Protoss_Robotics_Facility 1 10166
Protoss_Shuttle 1 11789
Protoss_Observatory 1 11297
12358
