Protoss_Gateway 2 9514
Protoss_Assimilator 1 4259
Protoss_Zealot 2 6924
Protoss_Cybernetics_Core 1 6971
Protoss_Dragoon 6 12551
Protoss_Shield_Battery 1 9950
Singularity_Charge 1 11410
12551
