Protoss_Nexus 1 6969
Protoss_Gateway 3 8933
Protoss_Assimilator 2 11976
Protoss_Zealot 8 11032
Protoss_Cybernetics_Core 1 9877
Protoss_Citadel_of_Adun 1 11831
Protoss_Dragoon 1 12152
Protoss_Forge 1 12093
12152
