Protoss_Gateway 2 10572
Protoss_Assimilator 1 4761
Protoss_Zealot 3 9595
Protoss_Cybernetics_Core 1 7905
Protoss_Nexus 1 11234
Protoss_Dragoon 3 12490
Protoss_Shield_Battery 1 11201
12490
