Protoss_Gateway 3 12405
Protoss_Assimilator 1 4682
Protoss_Cybernetics_Core 1 6084
Protoss_Dragoon 6 12461
Protoss_Robotics_Facility 1 8663
Protoss_Observatory 1 9462
Protoss_Observer 1 10510
12461
