Protoss_Gateway 1 4294
Protoss_Assimilator 1 4565
Protoss_Cybernetics_Core 1 6029
Protoss_Zealot 1 5856
Protoss_Dragoon 2 9148
Protoss_Robotics_Facility 1 8736
Protoss_Shuttle 1 10170
Protoss_Observatory 1 9562
Protoss_Robotics_Support_Bay 1 10039
Protoss_Observer 1 11013
Protoss_Reaver 1 12609
12609
