Protoss_Gateway 2 10529
Protoss_Assimilator 1 5180
Protoss_Zealot 2 6310
Protoss_Cybernetics_Core 1 7126
Protoss_Dragoon 5 11766
Protoss_Robotics_Facility 1 13039
Singularity_Charge 1 11343
13039
