Protoss_Gateway 2 10981
Protoss_Assimilator 1 4644
Protoss_Zealot 2 6822
Protoss_Cybernetics_Core 1 6940
Protoss_Dragoon 3 10917
Protoss_Robotics_Facility 1 9815
Protoss_Shuttle 1 11374
Protoss_Robotics_Support_Bay 1 11021
Protoss_Reaver 1 12973
Protoss_Observatory 1 12111
12973
