Protoss_Gateway 2 5238
Protoss_Zealot 7 9873
Protoss_Assimilator 1 6804
Protoss_Cybernetics_Core 1 9327
Protoss_Citadel_of_Adun 1 11111
Protoss_Dragoon 1 11085
Protoss_Robotics_Facility 1 12392
Protoss_Templar_Archives 1 12746
12746
