Protoss_Gateway 1 4138
Protoss_Assimilator 1 4390
Protoss_Zealot 2 6775
Protoss_Cybernetics_Core 1 6637
Protoss_Robotics_Facility 1 8556
Protoss_Dragoon 4 11597
Protoss_Shuttle 1 9956
Protoss_Observatory 1 9607
Protoss_Robotics_Support_Bay 1 10346
Protoss_Observer 1 10799
Protoss_Reaver 1 12591
12591
