Protoss_Gateway 3 12198
Protoss_Assimilator 1 4902
Protoss_Zealot 1 5320
Protoss_Cybernetics_Core 1 6731
Protoss_Robotics_Facility 1 8681
Protoss_Dragoon 4 11758
Protoss_Observatory 1 9947
Protoss_Observer 2 12023
12198
