Protoss_Gateway 1 4520
Protoss_Assimilator 1 4644
Protoss_Cybernetics_Core 1 6132
Protoss_Dragoon 4 12051
Protoss_Robotics_Facility 1 11420
Protoss_Nexus 1 13225
Singularity_Charge 1 10487
13225
