Protoss_Gateway 2 9863
Protoss_Zealot 3 6763
Protoss_Assimilator 1 5178
Protoss_Cybernetics_Core 1 6961
Protoss_Dragoon 4 11597
Protoss_Robotics_Facility 1 9446
Protoss_Shuttle 1 11074
Protoss_Observatory 1 10670
Protoss_Observer 1 11917
11917
