Protoss_Gateway 2 9261
Protoss_Assimilator 2 6656
Protoss_Zealot 4 9156
Protoss_Cybernetics_Core 1 8730
Protoss_Citadel_of_Adun 1 10426
Protoss_Templar_Archives 1 11882
Protoss_Robotics_Facility 1 13217
13217
