Protoss_Gateway 2 10629
Protoss_Zealot 4 9061
Protoss_Nexus 1 10780
Protoss_Assimilator 1 9358
Protoss_Cybernetics_Core 1 10250
Protoss_Forge 1 11003
Protoss_Dragoon 2 12102
12102
