Protoss_Gateway 2 5856
Protoss_Zealot 6 10094
Protoss_Assimilator 1 7246
Protoss_Cybernetics_Core 1 9353
Protoss_Robotics_Facility 1 11479
Protoss_Shield_Battery 1 10632
Protoss_Dragoon 1 11518
11518
