Protoss_Gateway 2 11253
Protoss_Assimilator 1 4293
Protoss_Zealot 2 6675
Protoss_Cybernetics_Core 1 6681
Protoss_Dragoon 6 12490
Protoss_Robotics_Facility 1 9660
Protoss_Observatory 1 10725
Protoss_Observer 1 11746
12490
