Protoss_Gateway 2 9090
Protoss_Assimilator 1 4242
Protoss_Zealot 2 6741
Protoss_Cybernetics_Core 1 6768
Protoss_Citadel_of_Adun 1 8289
Protoss_Dragoon 2 9592
Protoss_Templar_Archives 1 9792
Protoss_Forge 1 10028
Protoss_Dark_Templar 1 11275
Protoss_Nexus 1 13420
13420
