Protoss_Gateway 2 9033
Protoss_Assimilator 1 4564
Protoss_Zealot 3 7224
Protoss_Cybernetics_Core 1 8275
Protoss_Robotics_Facility 1 10207
Protoss_Dragoon 5 12281
Protoss_Observatory 1 10946
Protoss_Observer 1 11973
12281
