Protoss_Gateway 2 12333
Protoss_Assimilator 1 4924
Protoss_Zealot 2 7122
Protoss_Cybernetics_Core 1 6964
Protoss_Dragoon 2 11817
Protoss_Robotics_Facility 1 9920
Protoss_Forge 1 9542
Protoss_Observatory 1 10643
Protoss_Observer 1 11673
12333
