Protoss_Gateway 2 10670
Protoss_Assimilator 1 4482
Protoss_Zealot 2 6503
Protoss_Cybernetics_Core 1 7286
Protoss_Dragoon 5 12380
Protoss_Robotics_Facility 1 9731
Protoss_Observatory 1 10472
Protoss_Observer 1 11497
12380
