Protoss_Gateway 1 4217
Protoss_Assimilator 1 4264
Protoss_Cybernetics_Core 1 5686
Protoss_Dragoon 3 12549
Protoss_Robotics_Facility 1 8351
Protoss_Shuttle 1 9757
Protoss_Robotics_Support_Bay 1 9228
Protoss_Citadel_of_Adun 1 10589
Protoss_Reaver 1 11315
Protoss_Stargate 1 12448
12549
