Protoss_Gateway 3 11711
Protoss_Zealot 7 9690
Protoss_Nexus 1 10746
Protoss_Assimilator 1 9206
Protoss_Cybernetics_Core 1 10875
Protoss_Forge 1 11578
Protoss_Dragoon 2 12323
12323
