Protoss_Gateway 2 10373
Protoss_Assimilator 1 5089
Protoss_Zealot 2 6257
Protoss_Cybernetics_Core 1 7065
Protoss_Dragoon 3 10465
Protoss_Citadel_of_Adun 1 9409
Protoss_Templar_Archives 1 10997
Protoss_Forge 1 11830
Protoss_Dark_Templar 2 12370
12370
