Protoss_Gateway 1 4012
Protoss_Zealot 3 6994
Protoss_Assimilator 1 5493
Protoss_Cybernetics_Core 1 7053
Protoss_Dragoon 4 11820
Protoss_Robotics_Facility 1 9952
Protoss_Shuttle 1 11420
Protoss_Robotics_Support_Bay 1 11114
Protoss_Reaver 1 12992
12992
