Protoss_Gateway 2 7369
Protoss_Assimilator 1 4987
Protoss_Zealot 1 5247
Protoss_Cybernetics_Core 1 6734
Protoss_Dragoon 7 12355
Protoss_Citadel_of_Adun 1 11402
Singularity_Charge 1 10643
12355
