Protoss_Gateway 2 12153
Protoss_Assimilator 1 4498
Protoss_Cybernetics_Core 1 5967
Protoss_Dragoon 5 12124
Protoss_Robotics_Facility 1 11237
Singularity_Charge 1 10120
Protoss_Observatory 1 11997
12153
