Protoss_Gateway 2 10363
Protoss_Assimilator 1 4527
Protoss_Zealot 1 5221
Protoss_Cybernetics_Core 1 7059
Protoss_Dragoon 5 11706
Singularity_Charge 1 10948
Protoss_Nexus 1 14256
14256
