Protoss_Gateway 2 6959
Protoss_Assimilator 1 4234
Protoss_Cybernetics_Core 1 5619
Protoss_Dragoon 6 11451
Protoss_Robotics_Facility 1 9812
Protoss_Observatory 1 10599
Protoss_Robotics_Support_Bay 1 10680
Protoss_Reaver 1 12542
12542
