Protoss_Gateway 2 4891
Protoss_Zealot 9 9500
Protoss_Forge 1 7641
Protoss_Photon_Cannon 3 11344
Protoss_Nexus 1 12227
Protoss_Assimilator 1 10849
Protoss_Cybernetics_Core 1 12140
12227
