Protoss_Gateway 1 3989
Protoss_Zealot 3 7106
Protoss_Assimilator 1 5552
Protoss_Cybernetics_Core 1 7293
Protoss_Robotics_Facility 1 9559
Protoss_Dragoon 3 11199
Protoss_Shuttle 1 11080
Protoss_Robotics_Support_Bay 1 11100
Protoss_Reaver 1 12828
12828
