Protoss_Gateway 3 10091
Protoss_Assimilator 1 4284
Protoss_Zealot 3 8452
Protoss_Nexus 1 9652
Protoss_Cybernetics_Core 1 8581
Protoss_Dragoon 4 12265
Protoss_Robotics_Facility 1 12203
12265
