Protoss_Gateway 2 5273
Protoss_Zealot 3 7414
Protoss_Assimilator 1 6072
Protoss_Cybernetics_Core 1 7272
Protoss_Dragoon 3 10814
Protoss_Citadel_of_Adun 1 10054
Protoss_Templar_Archives 1 11546
11546
