Protoss_Gateway 3 11486
Protoss_Assimilator 1 4504
Protoss_Zealot 4 12034
Protoss_Cybernetics_Core 1 6765
Protoss_Dragoon 2 9982
Protoss_Nexus 1 11298
Protoss_Citadel_of_Adun 1 11835
12034
