Protoss_Gateway 2 9661
Protoss_Assimilator 1 4432
Protoss_Zealot 2 7334
Protoss_Cybernetics_Core 1 7193
Protoss_Dragoon 2 9841
Protoss_Citadel_of_Adun 1 10618
Protoss_Nexus 1 13645
Protoss_Templar_Archives 1 12410
Singularity_Charge 1 11233
13645
