Protoss_Gateway 2 11143
Protoss_Assimilator 1 4183
Protoss_Zealot 2 7385
Protoss_Cybernetics_Core 1 7063
Protoss_Dragoon 3 11495
Protoss_Robotics_Facility 1 10236
Protoss_Shuttle 1 12084
Singularity_Charge 1 10780
Protoss_Robotics_Support_Bay 1 11744
12084
