Protoss_Gateway 1 4299
Protoss_Assimilator 1 4657
Protoss_Zealot 1 5426
Protoss_Cybernetics_Core 1 6909
Protoss_Dragoon 4 12206
Protoss_Robotics_Facility 1 10971
Protoss_Nexus 1 13762
Protoss_Observatory 1 11878
13762
