Protoss_Gateway 3 12438
Protoss_Assimilator 1 4220
Protoss_Cybernetics_Core 1 5592
Protoss_Dragoon 7 12376
Protoss_Robotics_Facility 1 10465
Singularity_Charge 1 9666
Protoss_Observatory 1 11567
12438
