Protoss_Gateway 2 7401
Protoss_Zealot 2 11446
Protoss_Assimilator 1 5440
Protoss_Cybernetics_Core 1 6929
Protoss_Dragoon 6 11126
Protoss_Robotics_Facility 1 12177
Singularity_Charge 1 10907
12177
