Protoss_Gateway 2 10940
Protoss_Assimilator 1 4464
Protoss_Zealot 1 5092
Protoss_Cybernetics_Core 1 6886
Protoss_Dragoon 6 12546
Singularity_Charge 1 10676
Protoss_Nexus 1 13761
13761
