Protoss_Gateway 2 8385
Protoss_Assimilator 1 4505
Protoss_Cybernetics_Core 1 5941
Protoss_Dragoon 8 12127
Protoss_Robotics_Facility 1 10848
Singularity_Charge 1 9982
Protoss_Observatory 1 11612
12127
