Protoss_Gateway 3 12751
Protoss_Assimilator 1 4615
Protoss_Cybernetics_Core 1 6197
Protoss_Dragoon 8 12083
Protoss_Robotics_Facility 1 11316
Singularity_Charge 1 10640
Protoss_Observatory 1 12074
12751
