Protoss_Nexus 1 6637
Protoss_Gateway 2 6276
Protoss_Zealot 5 10738
Protoss_Assimilator 1 7665
Protoss_Forge 1 9112
Protoss_Cybernetics_Core 1 9971
Protoss_Photon_Cannon 7 12513
Protoss_Citadel_of_Adun 1 11692
12513
