Protoss_Gateway 2 10248
Protoss_Assimilator 1 4236
Protoss_Zealot 2 6122
Protoss_Cybernetics_Core 1 7050
Protoss_Dragoon 5 12066
Protoss_Robotics_Facility 1 9396
Protoss_Shuttle 1 11054
Protoss_Observatory 1 10526
Protoss_Observer 1 11897
Protoss_Robotics_Support_Bay 1 11893
12066
