Protoss_Gateway 2 9883
Protoss_Assimilator 1 4485
Protoss_Zealot 3 10872
Protoss_Cybernetics_Core 1 7469
Protoss_Citadel_of_Adun 1 8944
Protoss_Dragoon 1 9124
Protoss_Templar_Archives 1 10398
Protoss_Dark_Templar 1 11591
Protoss_High_Templar 1 12036
12036
