Protoss_Gateway 2 11988
Protoss_Assimilator 1 4504
Protoss_Cybernetics_Core 1 5787
Protoss_Zealot 1 5774
Protoss_Dragoon 5 12309
Protoss_Shield_Battery 1 6950
Protoss_Nexus 1 12660
Singularity_Charge 1 10313
12660
