Protoss_Gateway 2 11249
Protoss_Assimilator 1 5314
Protoss_Zealot 2 6725
Protoss_Cybernetics_Core 1 7111
Protoss_Dragoon 5 12587
Protoss_Robotics_Facility 1 10573
Protoss_Shuttle 1 12040
Protoss_Observatory 1 11346
Singularity_Charge 1 10951
12587
