Protoss_Gateway 2 7432
Protoss_Assimilator 1 4176
Protoss_Zealot 1 5192
Protoss_Cybernetics_Core 1 6858
Protoss_Dragoon 6 11559
Protoss_Robotics_Facility 1 10620
Protoss_Observatory 1 11501
Protoss_Robotics_Support_Bay 1 11551
Singularity_Charge 1 10960
11559
