Protoss_Gateway 2 8739
Protoss_Assimilator 1 4397
Protoss_Zealot 2 6345
Protoss_Cybernetics_Core 1 7843
Protoss_Dragoon 5 11949
Protoss_Robotics_Facility 1 10681
Protoss_Observatory 1 11372
11949
