Protoss_Gateway 1 4147
Protoss_Assimilator 1 4485
Protoss_Zealot 1 5121
Protoss_Cybernetics_Core 1 7069
Protoss_Dragoon 4 11597
Protoss_Robotics_Facility 1 9311
Protoss_Shuttle 1 10711
Protoss_Robotics_Support_Bay 1 10752
Protoss_Reaver 1 12477
12477
