Protoss_Gateway 2 10697
Protoss_Assimilator 1 4334
Protoss_Zealot 2 6678
Protoss_Cybernetics_Core 1 6725
Protoss_Dragoon 6 12437
Protoss_Robotics_Facility 1 10093
Protoss_Shuttle 1 11528
Protoss_Observatory 1 11356
Singularity_Charge 1 10816
12437
