Protoss_Gateway 2 10410
Protoss_Assimilator 1 4133
Protoss_Cybernetics_Core 1 5525
Protoss_Zealot 1 5458
Protoss_Dragoon 3 9484
Protoss_Citadel_of_Adun 1 9462
Protoss_Robotics_Facility 1 9971
Protoss_Templar_Archives 1 10916
Protoss_Shuttle 1 11434
Protoss_Dark_Templar 2 12121
12121
