Protoss_Gateway 1 4116
Protoss_Assimilator 1 4409
Protoss_Zealot 2 6880
Protoss_Cybernetics_Core 1 6760
Protoss_Dragoon 4 11308
Protoss_Robotics_Facility 1 10280
Protoss_Robotics_Support_Bay 1 11000
Singularity_Charge 1 10778
Protoss_Nexus 1 14004
14004
