Protoss_Gateway 2 10185
Protoss_Assimilator 1 4477
Protoss_Zealot 2 7671
Protoss_Cybernetics_Core 1 7013
Protoss_Citadel_of_Adun 1 8458
Protoss_Dragoon 3 12478
Protoss_Templar_Archives 1 9902
Protoss_Dark_Templar 3 12434
12478
