Protoss_Gateway 1 4316
Protoss_Assimilator 1 4555
Protoss_Zealot 2 6716
Protoss_Cybernetics_Core 1 6776
Protoss_Dragoon 3 10310
Protoss_Citadel_of_Adun 1 10059
Protoss_Nexus 1 12868
Protoss_Templar_Archives 1 11708
Protoss_Forge 1 11588
12868
