Protoss_Gateway 2 5036
Protoss_Zealot 3 8432
Protoss_Nexus 1 8837
Protoss_Assimilator 1 7303
Protoss_Cybernetics_Core 1 8323
Protoss_Dragoon 4 11384
Protoss_Forge 1 10956
Protoss_Citadel_of_Adun 1 12520
Protoss_Photon_Cannon 1 12467
12520
