Protoss_Gateway 2 11156
Protoss_Assimilator 1 4539
Protoss_Cybernetics_Core 1 6039
Protoss_Dragoon 5 12464
Protoss_Robotics_Facility 1 10557
Protoss_Observatory 1 11463
Singularity_Charge 1 10769
Protoss_Shuttle 1 12418
12464
