Protoss_Gateway 2 10741
Protoss_Assimilator 1 4469
Protoss_Zealot 2 6813
Protoss_Cybernetics_Core 1 6929
Protoss_Dragoon 6 12537
Protoss_Robotics_Facility 1 10347
Protoss_Shuttle 1 11777
Singularity_Charge 1 10857
Protoss_Robotics_Support_Bay 1 11736
12537
