Protoss_Gateway 3 12166
Protoss_Assimilator 1 4379
Protoss_Zealot 3 7676
Protoss_Cybernetics_Core 1 7445
Protoss_Dragoon 5 12279
Protoss_Robotics_Facility 1 11313
Singularity_Charge 1 11138
Protoss_Observatory 1 12074
12279
