Protoss_Gateway 2 10548
Protoss_Assimilator 1 4233
Protoss_Zealot 3 7252
Protoss_Cybernetics_Core 1 7261
Protoss_Dragoon 3 10810
Protoss_Citadel_of_Adun 1 9623
Protoss_Templar_Archives 1 11304
Protoss_Forge 1 12078
Protoss_Dark_Templar 2 12551
12551
