Protoss_Gateway 2 9530
Protoss_Assimilator 1 4264
Protoss_Zealot 2 6833
Protoss_Cybernetics_Core 1 6971
Protoss_Dragoon 5 12221
Protoss_Robotics_Facility 1 10564
Protoss_Observatory 1 11308
Singularity_Charge 1 10898
Protoss_Observer 1 12324
12324
