Protoss_Gateway 2 5052
Protoss_Zealot 7 11221
Protoss_Nexus 1 9745
Protoss_Assimilator 1 8418
Protoss_Cybernetics_Core 1 10117
Protoss_Dragoon 1 11354
Protoss_Citadel_of_Adun 1 11963
11963
