Protoss_Gateway 1 4280
Protoss_Assimilator 2 5159
Protoss_Zealot 3 10486
Protoss_Cybernetics_Core 1 7038
Protoss_Citadel_of_Adun 1 8494
Protoss_Dragoon 2 9625
Protoss_Templar_Archives 1 10009
Protoss_Dark_Templar 2 12325
Protoss_Nexus 1 13127
Protoss_Forge 1 12188
13127
