Protoss_Gateway 2 7691
Protoss_Zealot 10 11958
Protoss_Assimilator 1 7571
Protoss_Cybernetics_Core 1 8787
Protoss_Citadel_of_Adun 1 10438
Protoss_Robotics_Facility 1 11846
Protoss_Forge 1 11297
Protoss_Photon_Cannon 1 12576
12576
