Protoss_Gateway 2 5096
Protoss_Zealot 7 10738
Protoss_Nexus 1 10328
Protoss_Assimilator 2 11489
Protoss_Cybernetics_Core 1 10795
Protoss_Dragoon 2 12159
Protoss_Citadel_of_Adun 1 12549
12549
