Protoss_Gateway 2 5006
Protoss_Zealot 5 9389
Protoss_Nexus 1 9119
Protoss_Assimilator 2 11083
Protoss_Cybernetics_Core 1 9536
Protoss_Dragoon 4 12502
Protoss_Robotics_Facility 1 12692
12692
