Protoss_Gateway 2 5003
Protoss_Zealot 7 10679
Protoss_Nexus 1 10538
Protoss_Assimilator 2 11453
Protoss_Cybernetics_Core 1 10757
Protoss_Citadel_of_Adun 1 12434
Protoss_Dragoon 2 12560
12560
