Protoss_Gateway 1 4392
Protoss_Assimilator 1 4215
Protoss_Cybernetics_Core 1 5909
Protoss_Zealot 2 7217
Protoss_Robotics_Facility 1 7844
Protoss_Shuttle 1 9260
Protoss_Robotics_Support_Bay 1 8911
Protoss_Dragoon 1 9592
Protoss_Reaver 1 12322
12322
