Protoss_Gateway 2 12211
Protoss_Assimilator 1 4271
Protoss_Cybernetics_Core 1 5699
Protoss_Robotics_Facility 1 7807
Protoss_Dragoon 4 12329
Protoss_Shuttle 1 9223
Protoss_Observatory 1 8742
Protoss_Observer 3 11828
Protoss_Nexus 1 12792
12792
