Protoss_Assimilator 1 3951
Protoss_Gateway 1 5117
Protoss_Cybernetics_Core 1 6750
Protoss_Robotics_Facility 2 9745
Protoss_Shuttle 1 10123
Protoss_Observatory 1 9499
Protoss_Robotics_Support_Bay 1 10169
Protoss_Observer 1 10966
Protoss_Reaver 2 12562
Protoss_Dragoon 1 12549
12562
