Protoss_Gateway 2 12277
Protoss_Assimilator 1 4441
Protoss_Cybernetics_Core 1 5750
Protoss_Zealot 1 5549
Protoss_Dragoon 5 11530
Singularity_Charge 1 9967
Protoss_Robotics_Facility 1 12999
12999
