Protoss_Gateway 4 12712
Protoss_Assimilator 1 4571
Protoss_Cybernetics_Core 1 5990
Protoss_Robotics_Facility 1 8285
Protoss_Dragoon 3 11959
Protoss_Citadel_of_Adun 1 9387
Protoss_Shuttle 1 9699
Protoss_Observatory 1 9240
Protoss_Observer 1 11373
12712
