Protoss_Gateway 2 11963
Protoss_Zealot 2 6140
Protoss_Assimilator 1 5325
Protoss_Cybernetics_Core 1 6867
Protoss_Dragoon 5 12551
Protoss_Nexus 1 11390
Protoss_Robotics_Facility 1 11629
12551
