Protoss_Gateway 2 11019
Protoss_Assimilator 1 5145
Protoss_Cybernetics_Core 1 6071
Protoss_Zealot 1 6397
Protoss_Dragoon 5 12350
Protoss_Nexus 1 11114
Protoss_Robotics_Facility 1 11825
12350
