Protoss_Assimilator 1 3716
Protoss_Gateway 2 9929
Protoss_Cybernetics_Core 1 6331
Protoss_Robotics_Facility 1 8307
Protoss_Dragoon 5 12175
Protoss_Observatory 1 9017
Protoss_Observer 1 10056
Protoss_Shuttle 1 11652
Singularity_Charge 1 10743
12175
