Protoss_Gateway 2 10343
Protoss_Assimilator 1 4892
Protoss_Zealot 4 11505
Protoss_Cybernetics_Core 1 7681
Protoss_Dragoon 3 11782
Protoss_Robotics_Facility 1 11392
Protoss_Shuttle 1 12789
12789
