Protoss_Gateway 1 4214
Protoss_Assimilator 1 4242
Protoss_Cybernetics_Core 1 5876
Protoss_Stargate 1 7595
Protoss_Robotics_Facility 1 8353
Protoss_Dragoon 5 12601
Protoss_Observatory 1 9178
Protoss_Observer 2 11427
Protoss_Shuttle 1 12785
12785
