Protoss_Gateway 2 9686
Protoss_Assimilator 1 4201
Protoss_Zealot 3 6994
Protoss_Cybernetics_Core 1 7161
Protoss_Dragoon 6 12578
Protoss_Robotics_Facility 1 12226
Singularity_Charge 1 10842
Protoss_Nexus 1 13999
13999
