Protoss_Gateway 1 4141
Protoss_Assimilator 1 4229
Protoss_Zealot 2 6845
Protoss_Cybernetics_Core 1 6962
Protoss_Dragoon 4 12262
Protoss_Nexus 1 13552
Singularity_Charge 1 11141
13552
