Protoss_Gateway 2 7445
Protoss_Assimilator 1 4975
Protoss_Zealot 1 5151
Protoss_Cybernetics_Core 1 6700
Protoss_Dragoon 7 12423
Protoss_Robotics_Facility 1 10399
Protoss_Nexus 1 13161
Protoss_Observatory 1 11185
Protoss_Observer 1 12207
13161
