Protoss_Gateway 1 4104
Protoss_Assimilator 1 4404
Protoss_Cybernetics_Core 1 5607
Protoss_Zealot 1 5610
Protoss_Dragoon 5 11539
Protoss_Nexus 1 12798
Protoss_Robotics_Facility 1 12709
Singularity_Charge 1 11205
12798
