Protoss_Gateway 2 10908
Protoss_Assimilator 1 4179
Protoss_Zealot 2 7132
Protoss_Cybernetics_Core 1 6965
Protoss_Dragoon 5 12396
Protoss_Robotics_Facility 1 10643
Protoss_Shuttle 1 12312
Singularity_Charge 1 10957
12396
