Protoss_Gateway 2 6749
Protoss_Assimilator 1 4865
Protoss_Zealot 9 10152
Protoss_Shield_Battery 1 7298
Protoss_Cybernetics_Core 1 9400
Protoss_Dragoon 4 12373
Protoss_Citadel_of_Adun 1 12369
12373
