Protoss_Gateway 2 10848
Protoss_Assimilator 1 4281
Protoss_Zealot 2 6661
Protoss_Cybernetics_Core 1 6817
Protoss_Dragoon 3 10216
Protoss_Citadel_of_Adun 1 9563
Protoss_Templar_Archives 1 11200
Protoss_Forge 1 11194
Singularity_Charge 1 10875
Protoss_Dark_Templar 2 12499
12499
