Protoss_Gateway 2 10035
Protoss_Assimilator 1 4379
Protoss_Zealot 2 6532
Protoss_Cybernetics_Core 1 6522
Protoss_Dragoon 5 11319
Protoss_Robotics_Facility 1 10151
Protoss_Observatory 1 11024
Singularity_Charge 1 10840
Protoss_Observer 1 12043
Protoss_Robotics_Support_Bay 1 11963
12043
