Protoss_Gateway 2 11029
Protoss_Assimilator 1 4337
Protoss_Zealot 3 6994
Protoss_Cybernetics_Core 1 6929
Protoss_Dragoon 5 12429
Protoss_Robotics_Facility 1 9390
Protoss_Shuttle 1 10934
Protoss_Observatory 2 11540
12429
