Protoss_Gateway 2 11158
Protoss_Assimilator 1 4188
Protoss_Zealot 2 6760
Protoss_Cybernetics_Core 1 6814
Protoss_Dragoon 4 12352
Protoss_Robotics_Facility 1 10438
Protoss_Shuttle 1 12008
Protoss_Observatory 1 11510
Singularity_Charge 1 11264
12352
