Protoss_Gateway 2 12329
Protoss_Assimilator 1 4527
Protoss_Zealot 2 6626
Protoss_Cybernetics_Core 1 6504
Protoss_Dragoon 4 11097
Protoss_Citadel_of_Adun 1 9576
Protoss_Templar_Archives 1 11098
Protoss_Forge 1 11281
Singularity_Charge 1 10755
Protoss_Dark_Templar 1 12291
12329
