Protoss_Gateway 2 12570
Protoss_Assimilator 1 4564
Protoss_Zealot 2 6989
Protoss_Cybernetics_Core 1 7002
Protoss_Citadel_of_Adun 1 8554
Protoss_Dragoon 2 9642
Protoss_Templar_Archives 1 10038
Protoss_Nexus 1 12403
Protoss_Dark_Templar 1 11258
Protoss_Forge 1 11595
Protoss_High_Templar 1 12587
12587
