Protoss_Gateway 2 9523
Protoss_Assimilator 1 4378
Protoss_Zealot 2 6517
Protoss_Cybernetics_Core 1 6675
Protoss_Dragoon 7 12347
Protoss_Robotics_Facility 1 11391
Singularity_Charge 1 10772
12347
