Protoss_Gateway 2 11130
Protoss_Assimilator 1 4433
Protoss_Zealot 2 6807
Protoss_Cybernetics_Core 1 6825
Protoss_Dragoon 5 12513
Protoss_Robotics_Facility 1 10036
Protoss_Shuttle 1 11522
Protoss_Observatory 1 11425
Singularity_Charge 1 10983
12513
