Protoss_Gateway 2 12710
Protoss_Assimilator 1 4401
Protoss_Zealot 2 6769
Protoss_Cybernetics_Core 1 6864
Protoss_Dragoon 4 11498
Protoss_Nexus 1 12559
Protoss_Robotics_Facility 1 12379
Singularity_Charge 1 10977
12710
