Protoss_Gateway 2 5129
Protoss_Zealot 3 9813
Protoss_Assimilator 3 10455
Protoss_Nexus 1 9810
Protoss_Cybernetics_Core 1 9089
Protoss_Dragoon 3 11957
Protoss_Robotics_Facility 1 13069
13069
