Protoss_Gateway 1 4149
Protoss_Assimilator 1 4259
Protoss_Zealot 2 7182
Protoss_Cybernetics_Core 1 7107
Protoss_Dragoon 4 11899
Protoss_Citadel_of_Adun 1 10076
Protoss_Templar_Archives 1 11563
Protoss_Forge 1 11115
Singularity_Charge 1 10872
11899
