Protoss_Gateway 1 4169
Protoss_Assimilator 1 4451
Protoss_Zealot 2 6699
Protoss_Cybernetics_Core 1 6746
Protoss_Dragoon 4 11363
Protoss_Nexus 1 12388
Protoss_Citadel_of_Adun 1 11695
Singularity_Charge 1 10804
Protoss_Forge 1 11964
12388
