Protoss_Gateway 2 5232
Protoss_Zealot 8 12339
Protoss_Nexus 1 9783
Protoss_Assimilator 2 11755
Protoss_Cybernetics_Core 1 9675
Protoss_Dragoon 2 11477
Protoss_Citadel_of_Adun 1 11497
12339
