Protoss_Gateway 2 9225
Protoss_Assimilator 1 4174
Protoss_Zealot 2 6532
Protoss_Cybernetics_Core 1 6618
Protoss_Dragoon 1 7810
Protoss_Citadel_of_Adun 1 8707
Protoss_Templar_Archives 1 10152
Protoss_Dark_Templar 2 11404
Protoss_Nexus 1 13439
Protoss_Forge 1 11685
13439
