Protoss_Gateway 1 4419
Protoss_Assimilator 1 4483
Protoss_Cybernetics_Core 1 5999
Protoss_Dragoon 4 11188
Protoss_Robotics_Facility 1 8461
Protoss_Robotics_Support_Bay 1 9193
Protoss_Shield_Battery 1 9497
Protoss_Reaver 1 11078
Protoss_Observatory 1 11641
11641
