Protoss_Gateway 1 4332
Protoss_Assimilator 1 4925
Protoss_Zealot 3 7883
Protoss_Shield_Battery 1 6587
Protoss_Cybernetics_Core 1 7902
Protoss_Dragoon 1 9256
Protoss_Robotics_Facility 2 11044
Protoss_Observatory 1 11395
Protoss_Shuttle 1 12121
Protoss_Robotics_Support_Bay 1 11811
12121
