Protoss_Gateway 2 4946
Protoss_Zealot 6 9266
Protoss_Assimilator 1 7647
Protoss_Cybernetics_Core 1 8749
Protoss_Forge 1 9825
Protoss_Shield_Battery 1 9960
Protoss_Dragoon 2 10566
Protoss_Photon_Cannon 1 11081
11081
