Protoss_Gateway 3 7910
Protoss_Zealot 9 11033
Protoss_Forge 2 8600
Protoss_Photon_Cannon 2 9849
Protoss_Assimilator 1 10012
Protoss_Cybernetics_Core 1 11061
Protoss_Dragoon 1 12534
12534
