Protoss_Gateway 2 5385
Protoss_Zealot 9 10050
Protoss_Assimilator 1 8139
Protoss_Cybernetics_Core 1 10051
Protoss_Robotics_Facility 1 12323
Protoss_Shield_Battery 1 11925
Protoss_Dragoon 2 12496
12496
