Protoss_Gateway 2 5181
Protoss_Zealot 7 10937
Protoss_Nexus 1 9982
Protoss_Shield_Battery 1 8526
Protoss_Assimilator 1 8850
Protoss_Forge 1 11382
Protoss_Cybernetics_Core 1 12102
12102
