Protoss_Gateway 2 11085
Protoss_Assimilator 1 4561
Protoss_Cybernetics_Core 1 6484
Protoss_Dragoon 1 7697
Protoss_Citadel_of_Adun 1 8175
Protoss_Templar_Archives 1 10214
Protoss_Zealot 1 10832
Protoss_Dark_Templar 1 11473
Protoss_High_Templar 2 12573
12573
