Protoss_Gateway 2 9847
Protoss_Zealot 4 9288
Protoss_Assimilator 1 6308
Protoss_Cybernetics_Core 1 8275
Protoss_Robotics_Facility 1 11360
Protoss_Dragoon 2 11129
Protoss_Robotics_Support_Bay 1 12082
12082
