Protoss_Nexus 1 7464
Protoss_Gateway 2 9293
Protoss_Assimilator 2 8470
Protoss_Cybernetics_Core 1 8319
Protoss_Robotics_Facility 1 10851
Protoss_Dragoon 4 11883
Protoss_Observatory 1 11577
11883
