Protoss_Nexus 1 6988
Protoss_Assimilator 2 9023
Protoss_Gateway 1 6653
Protoss_Cybernetics_Core 1 8209
Protoss_Stargate 1 10020
Protoss_Citadel_of_Adun 1 9984
Protoss_Forge 1 9920
Protoss_Photon_Cannon 3 12127
Protoss_Corsair 2 12134
Protoss_Templar_Archives 1 12007
12134
