Protoss_Gateway 1 4229
Protoss_Assimilator 1 4498
Protoss_Zealot 2 6427
Protoss_Cybernetics_Core 1 7419
Protoss_Dragoon 3 12014
Protoss_Robotics_Facility 1 10261
Protoss_Shuttle 1 11682
Protoss_Robotics_Support_Bay 1 10999
12014
