Protoss_Assimilator 1 3580
Protoss_Gateway 2 11769
Protoss_Cybernetics_Core 1 6389
Protoss_Robotics_Facility 1 8404
Protoss_Dragoon 4 11679
Protoss_Shuttle 1 9867
Protoss_Observatory 1 9407
Protoss_Observer 1 10710
Singularity_Charge 1 11262
11769
