Protoss_Gateway 3 12072
Protoss_Assimilator 1 4331
Protoss_Zealot 2 6829
Protoss_Cybernetics_Core 1 6886
Protoss_Dragoon 4 12102
Protoss_Robotics_Facility 1 10091
Protoss_Observatory 1 10858
Protoss_Observer 1 11922
12102
