Protoss_Gateway 2 8246
Protoss_Assimilator 1 4555
Protoss_Zealot 3 6961
Protoss_Cybernetics_Core 1 7125
Protoss_Dragoon 7 12430
Protoss_Robotics_Facility 1 12424
Singularity_Charge 1 11343
12430
