Protoss_Gateway 2 9176
Protoss_Zealot 3 7063
Protoss_Assimilator 1 5657
Protoss_Cybernetics_Core 1 7024
Protoss_Dragoon 2 9746
Protoss_Citadel_of_Adun 1 9402
Protoss_Templar_Archives 1 10850
Protoss_Forge 1 10928
Protoss_Dark_Templar 2 12073
Protoss_Photon_Cannon 1 12297
12297
