Protoss_Gateway 1 4332
Protoss_Assimilator 1 4880
Protoss_Zealot 2 7122
Protoss_Cybernetics_Core 1 6991
Protoss_Dragoon 4 11720
Protoss_Robotics_Facility 1 9985
Protoss_Shuttle 1 11396
Protoss_Robotics_Support_Bay 1 10845
Singularity_Charge 1 10831
Protoss_Reaver 1 13010
13010
