Protoss_Gateway 2 8127
Protoss_Assimilator 1 4395
Protoss_Zealot 2 6712
Protoss_Cybernetics_Core 1 6845
Protoss_Dragoon 5 10917
Protoss_Robotics_Facility 1 12273
Singularity_Charge 1 11343
12273
