Protoss_Assimilator 1 3601
Protoss_Gateway 1 4646
Protoss_Cybernetics_Core 1 6169
Protoss_Robotics_Facility 1 8100
Protoss_Zealot 2 8120
Protoss_Shuttle 1 9509
Protoss_Dragoon 3 12446
Protoss_Robotics_Support_Bay 1 9374
Protoss_Reaver 2 12932
12932
