Protoss_Gateway 1 4126
Protoss_Assimilator 1 4234
Protoss_Cybernetics_Core 1 5838
Protoss_Robotics_Facility 1 7917
Protoss_Dragoon 4 11188
Protoss_Shuttle 1 9413
Protoss_Robotics_Support_Bay 1 9126
Protoss_Observatory 1 9811
Protoss_Reaver 1 10990
Protoss_Observer 1 11815
11815
