Protoss_Gateway 2 8254
Protoss_Assimilator 1 4381
Protoss_Cybernetics_Core 1 5835
Protoss_Dragoon 7 11975
Protoss_Robotics_Facility 1 11269
Protoss_Zealot 1 10697
Singularity_Charge 1 9891
11975
