Protoss_Gateway 1 4341
Protoss_Zealot 6 12315
Protoss_Nexus 1 9558
Protoss_Assimilator 2 12014
Protoss_Cybernetics_Core 1 10133
Protoss_Dragoon 1 11454
Protoss_Citadel_of_Adun 1 11911
12315
