Protoss_Gateway 2 9286
Protoss_Zealot 2 7954
Protoss_Nexus 1 7989
Protoss_Assimilator 1 6523
Protoss_Cybernetics_Core 1 8007
Protoss_Dragoon 5 12051
Protoss_Shield_Battery 1 11584
12051
