Protoss_Gateway 2 10035
Protoss_Assimilator 1 4461
Protoss_Cybernetics_Core 1 5715
Protoss_Dragoon 4 10406
Protoss_Citadel_of_Adun 1 9245
Protoss_Templar_Archives 1 11063
Singularity_Charge 1 10020
Protoss_Forge 1 11434
Protoss_Dark_Templar 1 12455
12455
