Protoss_Nexus 1 6846
Protoss_Gateway 4 13046
Protoss_Assimilator 2 12125
Protoss_Cybernetics_Core 1 7442
Protoss_Dragoon 7 15751
Protoss_Robotics_Facility 1 12418
Singularity_Charge 1 11428
Protoss_Shuttle 1 14496
Protoss_Observatory 1 13955
Protoss_Zealot 4 15108
Protoss_Observer 1 15507
15751
