Protoss_Gateway 3 13331
Protoss_Assimilator 1 5408
Protoss_Zealot 2 7214
Protoss_Cybernetics_Core 1 7167
Protoss_Dragoon 8 14706
Protoss_Nexus 1 12619
Protoss_Robotics_Facility 1 12951
Singularity_Charge 1 11527
Protoss_Observatory 1 13730
Protoss_Observer 1 14797
14797
