Protoss_Gateway 4 14701
Protoss_Assimilator 2 13407
Protoss_Cybernetics_Core 1 5941
Protoss_Dragoon 6 13473
Protoss_Citadel_of_Adun 1 9324
Protoss_Templar_Archives 1 10785
Singularity_Charge 1 10017
Protoss_Nexus 1 13827
Protoss_Robotics_Facility 1 13595
Protoss_Observatory 1 14372
Protoss_Observer 1 15389
15389
