Protoss_Gateway 2 15712
Protoss_Assimilator 1 4624
Protoss_Cybernetics_Core 1 6116
Protoss_Dragoon 8 15654
Protoss_Robotics_Facility 1 10055
Protoss_Shuttle 1 11452
Singularity_Charge 1 10128
Protoss_Robotics_Support_Bay 1 11328
Protoss_Reaver 1 13063
Protoss_Nexus 1 16189
Protoss_Observatory 1 14264
Protoss_Observer 1 15274
16189
