Protoss_Gateway 3 10382
Protoss_Assimilator 2 15566
Protoss_Cybernetics_Core 1 5595
Protoss_Dragoon 12 15511
Protoss_Nexus 1 11033
Singularity_Charge 1 9455
Protoss_Robotics_Facility 1 11858
Protoss_Zealot 1 12283
Protoss_Observatory 1 12781
Protoss_Shuttle 1 13934
Protoss_Observer 1 14777
15566
