Protoss_Gateway 4 15530
Protoss_Assimilator 1 4201
Protoss_Cybernetics_Core 1 5973
Protoss_Dragoon 7 13617
Singularity_Charge 1 9836
Protoss_Nexus 2 15008
Protoss_Robotics_Facility 1 15001
15530
