Protoss_Gateway 2 9069
Protoss_Assimilator 1 5098
Protoss_Cybernetics_Core 1 6962
Protoss_Dragoon 8 14199
Protoss_Nexus 1 13631
Singularity_Charge 1 10790
Protoss_Robotics_Facility 1 13785
Protoss_Shuttle 1 15213
Protoss_Robotics_Support_Bay 1 15225
15225
