Protoss_Gateway 3 15936
Protoss_Assimilator 1 4293
Protoss_Cybernetics_Core 1 5686
Protoss_Dragoon 7 15000
Protoss_Robotics_Facility 1 9636
Singularity_Charge 1 9704
Protoss_Observatory 1 10454
Protoss_Observer 2 14483
Protoss_Nexus 1 14122
Protoss_Shuttle 1 13050
15936
