Protoss_Gateway 2 10670
Protoss_Assimilator 1 4504
Protoss_Cybernetics_Core 1 5875
Protoss_Dragoon 10 15727
Protoss_Nexus 2 14708
Singularity_Charge 1 9938
Protoss_Robotics_Facility 1 14760
Protoss_Zealot 1 14607
15727
