Protoss_Gateway 3 15876
Protoss_Assimilator 1 4499
Protoss_Zealot 2 6632
Protoss_Cybernetics_Core 1 6782
Protoss_Citadel_of_Adun 1 8297
Protoss_Dragoon 5 15508
Protoss_Templar_Archives 1 10375
Protoss_Nexus 2 16266
Protoss_Dark_Templar 2 11632
Protoss_Stargate 1 15985
16266
