Protoss_Gateway 5 15416
Protoss_Assimilator 1 4261
Protoss_Zealot 1 5190
Protoss_Cybernetics_Core 1 6888
Protoss_Dragoon 11 15768
Protoss_Nexus 1 12792
Singularity_Charge 1 10984
Protoss_Robotics_Facility 1 14048
Protoss_Observatory 1 14805
15768
