Protoss_Gateway 2 8047
Protoss_Assimilator 1 4154
Protoss_Cybernetics_Core 1 5573
Protoss_Dragoon 10 15629
Singularity_Charge 1 9675
Protoss_Nexus 2 15147
Protoss_Robotics_Facility 1 12800
Protoss_Observatory 1 13523
Protoss_Observer 2 15554
15629
