Protoss_Gateway 2 14484
Protoss_Assimilator 2 4792
Protoss_Cybernetics_Core 1 6630
Protoss_Forge 1 7630
Protoss_Robotics_Facility 1 9690
Protoss_Photon_Cannon 2 10305
Protoss_Robotics_Support_Bay 1 10510
Protoss_Shuttle 1 11916
Protoss_Reaver 1 13474
Protoss_Citadel_of_Adun 1 14344
14484
