Protoss_Gateway 2 8112
Protoss_Assimilator 2 14061
Protoss_Cybernetics_Core 1 5772
Protoss_Dragoon 7 14934
Protoss_Robotics_Facility 1 10827
Protoss_Zealot 3 14439
Singularity_Charge 1 9872
Protoss_Shuttle 1 12589
Protoss_Observatory 1 12257
Protoss_Nexus 1 14920
Protoss_Citadel_of_Adun 1 14036
Protoss_Observer 2 14442
Protoss_Templar_Archives 1 15961
15961
