Protoss_Gateway 2 13694
Protoss_Assimilator 1 4240
Protoss_Cybernetics_Core 1 5819
Protoss_Robotics_Facility 1 8155
Protoss_Dragoon 3 13653
Protoss_Shuttle 1 9567
Protoss_Robotics_Support_Bay 1 9265
Protoss_Observatory 1 9894
Protoss_Zealot 2 11249
Protoss_Reaver 2 16281
Protoss_Observer 2 13597
Protoss_Nexus 1 14591
16281
