Protoss_Gateway 2 8114
Protoss_Assimilator 1 4265
Protoss_Cybernetics_Core 1 5658
Protoss_Dragoon 10 13538
Protoss_Zealot 3 15119
Singularity_Charge 1 9713
Protoss_Robotics_Facility 1 12385
Protoss_Shuttle 1 13793
Protoss_Robotics_Support_Bay 1 13582
Protoss_Reaver 1 15653
15653
