Protoss_Gateway 3 10884
Protoss_Zealot 7 14906
Protoss_Assimilator 1 6072
Protoss_Cybernetics_Core 1 7322
Protoss_Dragoon 8 13623
Protoss_Robotics_Facility 1 12857
Protoss_Shuttle 1 14253
Protoss_Robotics_Support_Bay 1 14232
Protoss_Reaver 1 15960
15960
