Protoss_Assimilator 1 3573
Protoss_Gateway 4 15920
Protoss_Cybernetics_Core 1 6425
Protoss_Zealot 3 14910
Protoss_Robotics_Facility 1 8524
Protoss_Dragoon 7 14049
Protoss_Observatory 1 9433
Protoss_Observer 3 12558
Singularity_Charge 1 11160
Protoss_Citadel_of_Adun 1 13883
15920
