Protoss_Gateway 2 9497
Protoss_Zealot 4 12403
Protoss_Assimilator 1 5467
Protoss_Cybernetics_Core 1 7063
Protoss_Dragoon 7 14340
Protoss_Robotics_Facility 1 10980
Protoss_Nexus 1 13793
Singularity_Charge 1 11021
Protoss_Observatory 1 11846
Protoss_Observer 1 12869
Protoss_Shuttle 1 14240
Protoss_Robotics_Support_Bay 1 14368
Protoss_Reaver 1 16098
16098
