Protoss_Gateway 2 10650
Protoss_Assimilator 1 4470
Protoss_Zealot 2 6146
Protoss_Cybernetics_Core 1 6008
Protoss_Dragoon 4 10839
Protoss_Citadel_of_Adun 1 8407
Protoss_Templar_Archives 1 10392
Singularity_Charge 1 9672
Protoss_Dark_Templar 6 14527
Protoss_Nexus 1 15160
15160
