Protoss_Gateway 3 13397
Protoss_Assimilator 1 4265
Protoss_Cybernetics_Core 1 5635
Protoss_Dragoon 11 15130
Protoss_Nexus 1 12467
Singularity_Charge 1 9719
Protoss_Robotics_Facility 1 12449
Protoss_Observatory 1 13209
Protoss_Observer 2 15144
15144
