Protoss_Gateway 3 11582
Protoss_Assimilator 1 4176
Protoss_Cybernetics_Core 1 5655
Protoss_Dragoon 9 15434
Protoss_Nexus 1 11690
Singularity_Charge 1 9667
Protoss_Robotics_Facility 1 13369
Protoss_Zealot 3 12953
Protoss_Observatory 1 14072
15434
