Protoss_Gateway 2 7223
Protoss_Assimilator 1 4995
Protoss_Zealot 6 14552
Protoss_Cybernetics_Core 1 6582
Protoss_Dragoon 11 15715
Singularity_Charge 1 10371
Protoss_Robotics_Facility 1 12402
Protoss_Shuttle 1 13960
Protoss_Robotics_Support_Bay 1 13841
Protoss_Reaver 1 15899
15899
