Protoss_Gateway 3 13865
Protoss_Assimilator 2 14996
Protoss_Cybernetics_Core 1 5730
Protoss_Dragoon 10 15197
Protoss_Nexus 1 11673
Singularity_Charge 1 9689
Protoss_Robotics_Facility 1 12256
Protoss_Observatory 1 13343
Protoss_Robotics_Support_Bay 1 14251
Protoss_Observer 1 14556
15197
