Protoss_Gateway 2 8575
Protoss_Assimilator 1 4303
Protoss_Cybernetics_Core 1 5616
Protoss_Dragoon 10 15607
Protoss_Zealot 5 14249
Singularity_Charge 1 9528
Protoss_Robotics_Facility 1 14171
Protoss_Nexus 1 16676
16676
