Protoss_Gateway 4 15497
Protoss_Assimilator 1 4499
Protoss_Cybernetics_Core 1 5750
Protoss_Dragoon 11 15783
Singularity_Charge 1 9587
Protoss_Robotics_Facility 1 11862
Protoss_Nexus 1 13967
Protoss_Zealot 1 12529
Protoss_Observatory 1 12645
Protoss_Observer 2 14771
15783
