Protoss_Nexus 2 15517
Protoss_Gateway 3 10877
Protoss_Assimilator 2 14325
Protoss_Cybernetics_Core 1 7397
Protoss_Dragoon 10 14319
Singularity_Charge 1 11321
Protoss_Robotics_Facility 1 13485
Protoss_Citadel_of_Adun 1 14232
Protoss_Observatory 1 14226
Protoss_Shuttle 1 15150
Protoss_Zealot 1 15375
15517
