Protoss_Gateway 4 15093
Protoss_Assimilator 1 4267
Protoss_Cybernetics_Core 1 5853
Protoss_Zealot 1 6544
Protoss_Dragoon 8 15247
Protoss_Nexus 1 11897
Singularity_Charge 1 9566
Protoss_Robotics_Facility 1 11553
Protoss_Shuttle 1 13068
Protoss_Robotics_Support_Bay 1 12691
Protoss_Reaver 1 14626
Protoss_Observatory 1 13853
Protoss_Observer 1 15450
15450
