Protoss_Gateway 3 15469
Protoss_Assimilator 1 4652
Protoss_Cybernetics_Core 1 6168
Protoss_Dragoon 11 15350
Protoss_Robotics_Facility 1 10390
Singularity_Charge 1 10062
Protoss_Observatory 1 11157
Protoss_Observer 2 14907
Protoss_Nexus 1 16113
16113
