Protoss_Nexus 1 6902
Protoss_Gateway 4 14578
Protoss_Assimilator 1 5933
Protoss_Cybernetics_Core 1 7441
Protoss_Zealot 4 15522
Protoss_Dragoon 7 15797
Protoss_Robotics_Facility 1 10825
Protoss_Shuttle 1 12304
Protoss_Robotics_Support_Bay 1 11908
Protoss_Observatory 1 12045
Protoss_Observer 1 14388
Singularity_Charge 1 13794
15797
