Protoss_Gateway 2 11111
Protoss_Assimilator 1 4464
Protoss_Cybernetics_Core 1 5780
Protoss_Dragoon 7 14839
Protoss_Citadel_of_Adun 1 9807
Protoss_Templar_Archives 1 11275
Singularity_Charge 1 9894
Protoss_Dark_Templar 3 13627
Protoss_Nexus 1 16418
Protoss_Robotics_Facility 1 16324
16418
