Protoss_Gateway 4 13972
Protoss_Assimilator 1 4229
Protoss_Cybernetics_Core 1 5723
Protoss_Dragoon 6 11226
Singularity_Charge 1 9663
Protoss_Citadel_of_Adun 2 13256
Protoss_Nexus 1 14295
Protoss_Robotics_Facility 1 13640
Protoss_Templar_Archives 1 14733
Protoss_Shuttle 1 15072
Protoss_Observatory 1 14562
15072
