Protoss_Gateway 2 6456
Protoss_Assimilator 1 4275
Protoss_Cybernetics_Core 1 5683
Protoss_Dragoon 14 15768
Singularity_Charge 1 9344
Protoss_Nexus 1 14468
Protoss_Robotics_Facility 1 15633
15768
