Protoss_Nexus 1 7069
Protoss_Gateway 2 8860
Protoss_Assimilator 2 14903
Protoss_Cybernetics_Core 1 7777
Protoss_Zealot 3 14966
Protoss_Dragoon 8 13618
Protoss_Forge 1 11449
Protoss_Photon_Cannon 2 14559
Singularity_Charge 1 12543
Protoss_Robotics_Facility 1 16287
16287
