Protoss_Gateway 1 4322
Protoss_Assimilator 1 4315
Protoss_Cybernetics_Core 1 5961
Protoss_Zealot 4 9100
Protoss_Robotics_Facility 1 8057
Protoss_Shuttle 1 9465
Protoss_Robotics_Support_Bay 1 9492
Protoss_Reaver 2 14667
Protoss_Dragoon 3 15490
Protoss_Observatory 1 11375
Protoss_Observer 1 13071
Protoss_Shield_Battery 1 14248
15490
