Protoss_Gateway 3 13567
Protoss_Nexus 1 7563
Protoss_Assimilator 2 14669
Protoss_Cybernetics_Core 1 7185
Protoss_Dragoon 12 15232
Protoss_Robotics_Facility 1 12386
Singularity_Charge 1 11688
Protoss_Observatory 1 13295
Protoss_Observer 1 14841
15232
