Protoss_Gateway 3 15778
Protoss_Assimilator 1 4297
Protoss_Cybernetics_Core 1 5727
Protoss_Dragoon 6 15431
Protoss_Robotics_Facility 1 8310
Protoss_Shuttle 1 9926
Protoss_Zealot 2 11013
Protoss_Observatory 2 12727
Protoss_Robotics_Support_Bay 1 10646
Protoss_Reaver 1 12395
Singularity_Charge 1 11592
Protoss_Nexus 1 15835
15835
