Protoss_Gateway 2 8042
Protoss_Assimilator 2 14641
Protoss_Cybernetics_Core 1 6091
Protoss_Dragoon 14 15824
Singularity_Charge 1 9771
Protoss_Nexus 3 17239
Protoss_Robotics_Facility 1 14278
Protoss_Observatory 1 14987
17239
