Protoss_Gateway 2 9770
Protoss_Assimilator 1 4334
Protoss_Cybernetics_Core 1 5709
Protoss_Dragoon 10 14732
Protoss_Robotics_Facility 1 9822
Singularity_Charge 1 9742
Protoss_Observatory 1 10531
Protoss_Observer 2 13117
Protoss_Nexus 1 14705
Protoss_Shuttle 1 15564
15564
