Protoss_Gateway 3 9782
Protoss_Assimilator 1 4281
Protoss_Cybernetics_Core 1 5990
Protoss_Dragoon 11 14837
Protoss_Zealot 2 12902
Singularity_Charge 1 10032
Protoss_Nexus 1 15693
Protoss_Citadel_of_Adun 1 15251
Protoss_Robotics_Facility 1 16151
16151
