Protoss_Gateway 2 13972
Protoss_Assimilator 1 4656
Protoss_Cybernetics_Core 1 5671
Protoss_Dragoon 6 13617
Protoss_Robotics_Facility 1 10160
Singularity_Charge 1 9880
Protoss_Shuttle 1 11619
Protoss_Robotics_Support_Bay 1 11123
Protoss_Nexus 2 16392
Protoss_Reaver 1 13355
Protoss_Observatory 1 13087
Protoss_Observer 2 15576
16392
