Protoss_Gateway 2 10577
Protoss_Assimilator 1 4226
Protoss_Zealot 6 13679
Protoss_Cybernetics_Core 1 6959
Protoss_Dragoon 6 14902
Protoss_Robotics_Facility 1 10261
Protoss_Observatory 1 10962
Protoss_Shuttle 1 11914
Protoss_Robotics_Support_Bay 1 11991
Singularity_Charge 1 11744
Protoss_Observer 2 15178
Protoss_Reaver 1 14353
Protoss_Nexus 1 16312
16312
