Protoss_Gateway 2 9939
Protoss_Assimilator 1 4400
Protoss_Cybernetics_Core 1 5854
Protoss_Dragoon 11 14969
Protoss_Robotics_Facility 1 10267
Singularity_Charge 1 9739
Protoss_Observatory 1 11053
Protoss_Observer 2 13038
Protoss_Nexus 1 15650
Protoss_Shuttle 1 14636
15650
