Protoss_Gateway 2 12087
Protoss_Assimilator 1 4293
Protoss_Cybernetics_Core 1 5802
Protoss_Dragoon 5 13390
Protoss_Robotics_Facility 1 8581
Protoss_Shuttle 1 10057
Protoss_Robotics_Support_Bay 1 9682
Protoss_Citadel_of_Adun 1 10799
Protoss_Reaver 2 14510
Protoss_Templar_Archives 1 12614
Protoss_Dark_Templar 3 15329
15329
