Protoss_Nexus 1 6717
Protoss_Gateway 4 13938
Protoss_Assimilator 2 10646
Protoss_Cybernetics_Core 1 7619
Protoss_Zealot 3 14546
Protoss_Dragoon 14 15799
Protoss_Robotics_Facility 1 11451
Protoss_Shield_Battery 1 11006
Singularity_Charge 1 11709
Protoss_Observatory 1 13822
Protoss_Observer 1 14885
Protoss_Citadel_of_Adun 1 15514
15799
