Protoss_Gateway 2 9860
Protoss_Assimilator 1 4283
Protoss_Cybernetics_Core 1 5862
Protoss_Dragoon 9 14284
Singularity_Charge 1 10055
Protoss_Nexus 1 12956
Protoss_Robotics_Facility 1 13784
Protoss_Zealot 2 15582
Protoss_Shuttle 1 15333
15582
