Protoss_Gateway 2 9623
Protoss_Zealot 6 14369
Protoss_Assimilator 1 6289
Protoss_Cybernetics_Core 1 8655
Protoss_Dragoon 8 15489
Protoss_Nexus 1 15278
Singularity_Charge 1 12565
15489
