Protoss_Gateway 2 6741
Protoss_Assimilator 2 12353
Protoss_Cybernetics_Core 1 5800
Protoss_Dragoon 6 15639
Protoss_Nexus 1 12075
Singularity_Charge 1 9663
Protoss_Citadel_of_Adun 1 11723
Protoss_Robotics_Facility 1 12885
Protoss_Templar_Archives 1 13171
Protoss_Shuttle 1 14341
Protoss_Dark_Templar 3 15511
Protoss_Stargate 1 15663
15663
