Protoss_Gateway 1 4287
Protoss_Assimilator 1 4608
Protoss_Cybernetics_Core 1 5868
Protoss_Dragoon 7 15366
Protoss_Robotics_Facility 1 10489
Singularity_Charge 1 10253
Protoss_Shuttle 1 11894
Protoss_Robotics_Support_Bay 1 11369
Protoss_Reaver 1 13507
Protoss_Observatory 1 12628
Protoss_Observer 2 15213
Protoss_Zealot 1 15071
15366
