Protoss_Gateway 4 14990
Protoss_Assimilator 1 4553
Protoss_Cybernetics_Core 1 6239
Protoss_Dragoon 6 15505
Protoss_Robotics_Facility 1 10124
Protoss_Nexus 1 12627
Singularity_Charge 1 10266
Protoss_Citadel_of_Adun 1 11897
Protoss_Shuttle 1 12626
Protoss_Observatory 1 12503
Protoss_Observer 1 14645
15505
