Protoss_Gateway 2 10409
Protoss_Assimilator 1 4659
Protoss_Cybernetics_Core 1 6020
Protoss_Dragoon 11 15497
Protoss_Robotics_Facility 1 8862
Protoss_Observatory 1 10517
Protoss_Observer 3 14724
Singularity_Charge 1 12045
Protoss_Nexus 1 16347
16347
