Protoss_Gateway 4 15541
Protoss_Assimilator 1 4331
Protoss_Cybernetics_Core 1 5860
Protoss_Dragoon 9 14458
Protoss_Nexus 2 15527
Singularity_Charge 1 9799
Protoss_Robotics_Facility 1 12892
Protoss_Observatory 1 13610
Protoss_Observer 2 15532
15541
