Protoss_Gateway 2 11819
Protoss_Assimilator 1 4644
Protoss_Cybernetics_Core 1 5914
Protoss_Robotics_Facility 1 8209
Protoss_Dragoon 9 15437
Protoss_Observatory 1 9069
Protoss_Observer 3 14437
Singularity_Charge 1 13406
Protoss_Nexus 1 16931
16931
