Protoss_Gateway 3 15972
Protoss_Assimilator 1 4330
Protoss_Cybernetics_Core 1 6024
Protoss_Dragoon 9 14568
Protoss_Nexus 1 13000
Singularity_Charge 1 10158
Protoss_Robotics_Facility 1 14070
Protoss_Zealot 2 13868
Protoss_Observatory 1 14855
15972
