Protoss_Gateway 2 8698
Protoss_Assimilator 2 4935
Protoss_Cybernetics_Core 1 6500
Protoss_Dragoon 8 14969
Protoss_Zealot 3 13524
Protoss_Robotics_Facility 1 12440
Singularity_Charge 1 12113
Protoss_Shuttle 1 13887
Protoss_Robotics_Support_Bay 1 13646
Protoss_Observatory 1 14897
Protoss_Reaver 1 16153
16153
