Protoss_Gateway 3 12149
Protoss_Assimilator 1 4272
Protoss_Cybernetics_Core 1 5796
Protoss_Dragoon 8 15748
Singularity_Charge 1 9710
Protoss_Citadel_of_Adun 1 11320
Protoss_Zealot 10 14121
Protoss_Robotics_Facility 1 15696
Protoss_Templar_Archives 1 15416
Leg_Enhancements 1 14355
15748
