Protoss_Gateway 2 11821
Protoss_Assimilator 2 7397
Protoss_Zealot 5 8917
Protoss_Cybernetics_Core 1 9211
Protoss_Dragoon 5 15197
Protoss_Citadel_of_Adun 1 11010
Protoss_Templar_Archives 1 12567
Protoss_Dark_Templar 2 14808
15197
