Protoss_Gateway 4 14452
Protoss_Assimilator 1 4390
Protoss_Cybernetics_Core 1 5740
Protoss_Dragoon 9 14954
Protoss_Robotics_Facility 1 9882
Protoss_Observatory 1 10725
Singularity_Charge 1 10017
Protoss_Nexus 2 15489
Protoss_Observer 3 14502
15489
