Protoss_Gateway 3 10480
Protoss_Forge 1 5266
Protoss_Zealot 7 13151
Protoss_Photon_Cannon 4 11505
Protoss_Assimilator 1 11492
Protoss_Cybernetics_Core 1 12798
Protoss_Nexus 1 16067
Protoss_Dragoon 2 14634
Protoss_Citadel_of_Adun 1 15750
16067
