Protoss_Gateway 2 10543
Protoss_Assimilator 1 4467
Protoss_Cybernetics_Core 1 5849
Protoss_Dragoon 8 14510
Protoss_Robotics_Facility 1 9812
Singularity_Charge 1 9525
Protoss_Observatory 1 10924
Protoss_Observer 1 12102
Protoss_Nexus 1 14311
Protoss_Shuttle 1 13656
Protoss_Robotics_Support_Bay 1 13405
Protoss_Reaver 1 15325
Protoss_Zealot 2 15371
15371
