Protoss_Gateway 2 9832
Protoss_Assimilator 1 4221
Protoss_Cybernetics_Core 1 5598
Protoss_Dragoon 8 15443
Protoss_Robotics_Facility 1 9923
Singularity_Charge 1 9622
Protoss_Shuttle 1 11379
Protoss_Robotics_Support_Bay 1 10763
Protoss_Zealot 2 11636
Protoss_Reaver 1 12937
Protoss_Observatory 1 12436
Protoss_Nexus 1 15156
Protoss_Observer 1 13826
15443
