Protoss_Nexus 1 7288
Protoss_Gateway 4 14427
Protoss_Assimilator 1 6861
Protoss_Cybernetics_Core 1 8509
Protoss_Dragoon 9 15036
Protoss_Robotics_Facility 1 12483
Protoss_Zealot 3 15456
Protoss_Shuttle 1 13957
Singularity_Charge 1 12594
Protoss_Observatory 1 13858
Protoss_Observer 1 15046
Protoss_Citadel_of_Adun 1 15943
15943
