Protoss_Gateway 1 4436
Protoss_Assimilator 1 4954
Protoss_Cybernetics_Core 1 6274
Protoss_Dragoon 8 15657
Protoss_Robotics_Facility 1 11384
Singularity_Charge 1 10465
Protoss_Shuttle 1 13123
Protoss_Robotics_Support_Bay 1 12478
Protoss_Reaver 1 14681
Protoss_Observatory 1 14331
Protoss_Nexus 1 16989
16989
