Protoss_Gateway 2 11762
Protoss_Assimilator 2 15159
Protoss_Cybernetics_Core 1 5669
Protoss_Dragoon 7 13918
Protoss_Nexus 1 11753
Protoss_Robotics_Facility 1 11768
Singularity_Charge 1 9868
Protoss_Shuttle 1 13226
Protoss_Robotics_Support_Bay 1 13112
Protoss_Stargate 1 14740
Protoss_Reaver 1 14930
Protoss_Zealot 2 14780
15159
