Protoss_Gateway 2 11494
Protoss_Zealot 3 6888
Protoss_Assimilator 1 5366
Protoss_Cybernetics_Core 1 7053
Protoss_Dragoon 7 14351
Protoss_Robotics_Facility 1 10546
Protoss_Shuttle 1 11967
Protoss_Robotics_Support_Bay 1 11482
Singularity_Charge 1 10860
Protoss_Reaver 2 15183
15183
