Protoss_Gateway 2 10068
Protoss_Assimilator 2 6213
Protoss_Zealot 4 11118
Protoss_Cybernetics_Core 1 7774
Protoss_Dragoon 4 11474
Protoss_Shield_Battery 1 10236
Singularity_Charge 1 11647
11647
