Protoss_Gateway 3 15756
Protoss_Assimilator 1 4536
Protoss_Cybernetics_Core 1 6045
Protoss_Robotics_Facility 1 8315
Protoss_Dragoon 4 14846
Protoss_Zealot 2 9839
Protoss_Shuttle 1 9721
Protoss_Robotics_Support_Bay 1 9382
Protoss_Reaver 2 13134
Protoss_Observatory 1 12108
Protoss_Observer 2 15295
Protoss_Nexus 1 16691
16691
