Protoss_Gateway 5 15804
Protoss_Nexus 2 12745
Protoss_Assimilator 2 14331
Protoss_Zealot 2 6888
Protoss_Cybernetics_Core 1 7104
Protoss_Dragoon 9 14663
Protoss_Robotics_Facility 1 13523
Protoss_Observatory 1 14681
Singularity_Charge 1 14116
15804
