Protoss_Gateway 3 15987
Protoss_Assimilator 1 4637
Protoss_Cybernetics_Core 1 6511
Protoss_Robotics_Facility 1 8798
Protoss_Dragoon 5 15336
Protoss_Robotics_Support_Bay 1 9521
Protoss_Shuttle 2 15855
Protoss_Zealot 3 11549
Protoss_Reaver 2 14554
Gravitic_Drive 1 13523
Protoss_Observatory 1 15171
15987
