Protoss_Gateway 3 13649
Protoss_Assimilator 1 4407
Protoss_Cybernetics_Core 1 5812
Protoss_Dragoon 9 15156
Protoss_Robotics_Facility 1 9695
Protoss_Observatory 1 10447
Singularity_Charge 1 9789
Protoss_Nexus 2 16568
Protoss_Observer 3 13609
Protoss_Shuttle 1 16009
16568
