Protoss_Gateway 2 9345
Protoss_Assimilator 1 4529
Protoss_Cybernetics_Core 1 5868
Protoss_Dragoon 5 15487
Protoss_Citadel_of_Adun 1 9620
Protoss_Robotics_Facility 1 10576
Protoss_Templar_Archives 1 11099
Protoss_Shuttle 1 11985
Protoss_Dark_Templar 4 13801
Protoss_Nexus 1 15305
15487
