Protoss_Gateway 2 10057
Protoss_Assimilator 1 4403
Protoss_Cybernetics_Core 1 5746
Protoss_Dragoon 12 14849
Protoss_Robotics_Facility 1 10337
Singularity_Charge 1 9755
Protoss_Observatory 1 11103
Protoss_Observer 2 13008
Protoss_Nexus 1 14957
Protoss_Robotics_Support_Bay 1 14826
Protoss_Shuttle 1 15779
15779
