Protoss_Nexus 2 16716
Protoss_Gateway 3 13691
Protoss_Assimilator 2 9152
Protoss_Cybernetics_Core 1 7488
Protoss_Zealot 3 13978
Protoss_Dragoon 10 15508
Protoss_Robotics_Facility 1 11799
Protoss_Shuttle 1 13234
Protoss_Robotics_Support_Bay 1 12587
Protoss_Observatory 1 12628
Protoss_Reaver 1 14792
Singularity_Charge 1 14346
Protoss_Citadel_of_Adun 1 16043
16716
