Protoss_Gateway 3 15775
Protoss_Assimilator 1 4548
Protoss_Cybernetics_Core 1 5794
Protoss_Dragoon 12 14793
Singularity_Charge 1 9477
Protoss_Robotics_Facility 1 11875
Protoss_Observatory 1 12601
Protoss_Nexus 1 15696
Protoss_Observer 1 14292
15775
