Protoss_Gateway 2 9263
Protoss_Assimilator 2 15147
Protoss_Cybernetics_Core 1 5651
Protoss_Dragoon 9 14870
Protoss_Nexus 2 15151
Singularity_Charge 1 9730
Protoss_Robotics_Facility 1 12601
Protoss_Observatory 1 13421
Protoss_Observer 2 15351
Protoss_Citadel_of_Adun 1 15068
15351
