Protoss_Gateway 1 4395
Protoss_Assimilator 1 5142
Protoss_Cybernetics_Core 1 6219
Protoss_Zealot 2 13378
Protoss_Dragoon 3 11188
Protoss_Robotics_Facility 1 10364
Protoss_Robotics_Support_Bay 1 11289
Protoss_Shuttle 1 12033
Protoss_Reaver 2 15130
15130
