Protoss_Gateway 3 13982
Protoss_Assimilator 1 4615
Protoss_Cybernetics_Core 1 6195
Protoss_Dragoon 9 14139
Protoss_Robotics_Facility 1 8744
Protoss_Observatory 1 9606
Protoss_Observer 2 12829
Protoss_Shuttle 2 15428
Singularity_Charge 1 11870
Protoss_Zealot 3 15001
15428
