Protoss_Gateway 2 12623
Protoss_Assimilator 2 14822
Protoss_Cybernetics_Core 1 5796
Protoss_Dragoon 8 14685
Protoss_Robotics_Facility 1 9806
Singularity_Charge 1 9760
Protoss_Observatory 1 10670
Protoss_Nexus 1 12981
Protoss_Observer 2 13000
Protoss_Robotics_Support_Bay 1 12336
Protoss_Shuttle 1 14440
Protoss_Reaver 1 16057
16057
