Protoss_Gateway 5 15269
Protoss_Assimilator 1 4245
Protoss_Cybernetics_Core 1 5928
Protoss_Dragoon 11 15756
Protoss_Nexus 1 11577
Singularity_Charge 1 9850
Protoss_Robotics_Facility 1 11997
Protoss_Observatory 1 12802
Protoss_Observer 2 14698
Protoss_Citadel_of_Adun 1 14835
15756
