Protoss_Gateway 2 10968
Protoss_Zealot 3 7144
Protoss_Assimilator 1 5417
Protoss_Cybernetics_Core 1 7185
Protoss_Dragoon 7 14480
Protoss_Robotics_Facility 1 11861
Singularity_Charge 1 11314
Protoss_Nexus 1 14883
Protoss_Shuttle 1 13848
Protoss_Robotics_Support_Bay 1 13677
Protoss_Reaver 1 15432
15432
