Protoss_Gateway 2 10918
Protoss_Assimilator 1 4586
Protoss_Cybernetics_Core 1 5963
Protoss_Zealot 5 15469
Protoss_Dragoon 8 13503
Protoss_Robotics_Facility 1 10628
Singularity_Charge 1 9975
Protoss_Shuttle 1 12194
Protoss_Observatory 1 11583
Protoss_Observer 3 15053
15469
