Protoss_Gateway 3 11071
Protoss_Assimilator 1 4303
Protoss_Zealot 5 13363
Protoss_Cybernetics_Core 1 6110
Protoss_Dragoon 7 15771
Protoss_Citadel_of_Adun 1 8789
Protoss_Templar_Archives 1 10498
Protoss_Dark_Templar 3 12391
Leg_Enhancements 1 12964
15771
