Protoss_Gateway 3 15914
Protoss_Assimilator 1 4195
Protoss_Cybernetics_Core 1 5623
Protoss_Dragoon 10 14925
Protoss_Robotics_Facility 1 9980
Singularity_Charge 1 9473
Protoss_Observatory 1 10980
Protoss_Nexus 1 13372
Protoss_Observer 3 15280
15914
