Protoss_Gateway 2 5301
Protoss_Zealot 5 7867
Protoss_Assimilator 1 6608
Protoss_Cybernetics_Core 1 9176
Protoss_Forge 1 9592
Protoss_Dragoon 1 10593
Protoss_Photon_Cannon 2 11649
11649
