Protoss_Gateway 3 14469
Protoss_Zealot 5 15441
Protoss_Assimilator 1 7043
Protoss_Cybernetics_Core 1 8260
Protoss_Dragoon 7 15398
Protoss_Nexus 1 14241
Protoss_Robotics_Facility 1 14031
Singularity_Charge 1 12748
15441
