Protoss_Gateway 3 10785
Protoss_Assimilator 1 4436
Protoss_Cybernetics_Core 1 5816
Protoss_Dragoon 11 15124
Protoss_Nexus 1 10339
Singularity_Charge 1 11928
Protoss_Robotics_Facility 1 14283
Protoss_Citadel_of_Adun 1 15046
Protoss_Observatory 1 15224
15224
