Protoss_Gateway 3 10709
Protoss_Assimilator 1 4119
Protoss_Cybernetics_Core 1 5578
Protoss_Dragoon 11 15060
Protoss_Nexus 1 11036
Singularity_Charge 1 9376
Protoss_Robotics_Facility 1 11959
Protoss_Zealot 3 13773
Protoss_Observatory 1 12648
Protoss_Observer 2 14771
15060
