Protoss_Gateway 2 6468
Protoss_Assimilator 1 4315
Protoss_Cybernetics_Core 1 5909
Protoss_Dragoon 13 15724
Singularity_Charge 1 9594
Protoss_Nexus 1 15404
Protoss_Robotics_Facility 1 15102
15724
