Protoss_Gateway 3 13240
Protoss_Assimilator 1 4659
Protoss_Cybernetics_Core 1 5948
Protoss_Dragoon 6 14561
Protoss_Citadel_of_Adun 1 8996
Protoss_Zealot 1 9118
Protoss_Templar_Archives 1 11268
Singularity_Charge 1 10289
Protoss_Dark_Templar 3 15249
Protoss_Nexus 1 15166
15249
