Protoss_Gateway 2 6623
Protoss_Assimilator 1 4770
Protoss_Cybernetics_Core 1 6018
Protoss_Dragoon 7 14839
Protoss_Citadel_of_Adun 1 9375
Protoss_Zealot 2 10169
Protoss_Templar_Archives 1 11048
Singularity_Charge 1 9989
Protoss_Dark_Templar 1 12322
Protoss_Nexus 2 16196
Protoss_Robotics_Facility 1 14410
16196
