Protoss_Gateway 2 10106
Protoss_Assimilator 1 4472
Protoss_Cybernetics_Core 1 5844
Protoss_Dragoon 8 13798
Protoss_Robotics_Facility 1 9787
Singularity_Charge 1 9862
Protoss_Observatory 1 10634
Protoss_Shuttle 1 11862
Protoss_Robotics_Support_Bay 1 12053
Protoss_Zealot 3 14926
Protoss_Observer 1 12705
Protoss_Reaver 2 16291
16291
