Protoss_Gateway 2 8537
Protoss_Assimilator 1 4508
Protoss_Zealot 3 7425
Protoss_Cybernetics_Core 1 6845
Protoss_Dragoon 5 11744
Protoss_Citadel_of_Adun 1 9645
Protoss_Templar_Archives 1 11344
Protoss_Dark_Templar 2 12935
Protoss_Nexus 1 16673
16673
