Protoss_Gateway 3 14228
Protoss_Assimilator 1 4283
Protoss_Cybernetics_Core 1 6144
Protoss_Dragoon 7 15458
Protoss_Robotics_Facility 1 9174
Protoss_Nexus 1 11643
Protoss_Observatory 1 9934
Protoss_Observer 2 12195
Singularity_Charge 1 13193
15458
