Protoss_Gateway 2 11101
Protoss_Assimilator 1 4359
Protoss_Cybernetics_Core 1 5658
Protoss_Zealot 1 5680
Protoss_Dragoon 9 15768
Protoss_Robotics_Facility 1 10639
Singularity_Charge 1 9858
Protoss_Shuttle 1 12062
Protoss_Robotics_Support_Bay 1 11691
Protoss_Reaver 1 13990
Protoss_Nexus 1 15952
Protoss_Observatory 1 14735
15952
