Protoss_Gateway 3 12077
Protoss_Zealot 3 9339
Protoss_Nexus 2 10860
Protoss_Assimilator 2 15512
Protoss_Cybernetics_Core 1 10713
Protoss_Dragoon 7 15219
Protoss_Robotics_Facility 1 16244
16244
