Protoss_Gateway 1 4353
Protoss_Forge 1 4656
Protoss_Zealot 6 15273
Protoss_Photon_Cannon 10 13942
Protoss_Assimilator 1 11209
Protoss_Nexus 1 13440
Protoss_Cybernetics_Core 1 13347
15273
