Protoss_Gateway 2 8686
Protoss_Assimilator 1 4578
Protoss_Cybernetics_Core 1 6131
Protoss_Dragoon 8 13015
Protoss_Robotics_Facility 1 11135
Singularity_Charge 1 10340
Protoss_Observatory 1 12828
Protoss_Nexus 1 15491
Protoss_Zealot 4 15222
Protoss_Observer 1 13875
Protoss_Shuttle 1 15326
15491
