Protoss_Gateway 2 8134
Protoss_Assimilator 1 4344
Protoss_Cybernetics_Core 1 5729
Protoss_Dragoon 6 12285
Singularity_Charge 1 9800
Protoss_Nexus 1 12775
Protoss_Robotics_Facility 1 12346
Protoss_Shuttle 1 13761
Protoss_Robotics_Support_Bay 1 13826
Protoss_Zealot 2 14669
Protoss_Observatory 1 14697
Protoss_Reaver 1 15711
15711
