Protoss_Nexus 2 15615
Protoss_Gateway 3 14120
Protoss_Assimilator 2 12348
Protoss_Cybernetics_Core 1 7733
Protoss_Zealot 1 7795
Protoss_Dragoon 3 10822
Protoss_Citadel_of_Adun 1 11341
Protoss_Robotics_Facility 1 12610
Protoss_Templar_Archives 1 13331
Singularity_Charge 1 12477
Protoss_Shuttle 1 14404
Protoss_Dark_Templar 3 15336
Protoss_Forge 1 14581
Protoss_Observatory 1 14837
15615
