Protoss_Gateway 1 4248
Protoss_Assimilator 1 4192
Protoss_Cybernetics_Core 1 5805
Protoss_Dragoon 8 15060
Protoss_Robotics_Facility 1 9459
Protoss_Shuttle 1 10852
Singularity_Charge 1 9467
Protoss_Robotics_Support_Bay 1 10958
Protoss_Zealot 1 11680
Protoss_Reaver 2 14227
Protoss_Observatory 1 12964
Protoss_Observer 1 15052
Protoss_Nexus 1 17427
17427
