Protoss_Gateway 3 14158
Protoss_Zealot 1 5200
Protoss_Nexus 1 8387
Protoss_Assimilator 2 13182
Protoss_Cybernetics_Core 1 8076
Protoss_Dragoon 11 15074
Singularity_Charge 1 12198
Protoss_Robotics_Facility 1 14227
Protoss_Shuttle 1 15795
Protoss_Observatory 1 15247
15795
