Protoss_Gateway 3 12909
Protoss_Assimilator 1 4230
Protoss_Cybernetics_Core 1 5730
Protoss_Dragoon 9 14428
Protoss_Nexus 1 11731
Singularity_Charge 1 9830
Protoss_Robotics_Facility 1 12033
Protoss_Observatory 1 13197
Protoss_Observer 1 14572
Protoss_Robotics_Support_Bay 1 14959
Protoss_Shuttle 1 15930
15930
