Protoss_Gateway 2 13040
Protoss_Assimilator 1 4337
Protoss_Cybernetics_Core 1 5755
Protoss_Zealot 1 5592
Protoss_Dragoon 8 14327
Singularity_Charge 1 9726
Protoss_Nexus 1 12878
Protoss_Robotics_Facility 1 14158
Protoss_Shuttle 1 15684
15684
