Protoss_Gateway 2 6523
Protoss_Assimilator 1 4183
Protoss_Cybernetics_Core 1 5677
Protoss_Dragoon 8 13711
Protoss_Nexus 1 12779
Protoss_Robotics_Facility 1 12284
Singularity_Charge 1 10544
Protoss_Shuttle 1 13711
Protoss_Robotics_Support_Bay 1 13781
Protoss_Reaver 1 15518
Protoss_Observatory 1 14750
15518
