Protoss_Gateway 2 9381
Protoss_Zealot 3 8513
Protoss_Nexus 1 8980
Protoss_Assimilator 2 11553
Protoss_Cybernetics_Core 1 8783
Protoss_Dragoon 9 15262
Protoss_Robotics_Facility 1 13865
Singularity_Charge 1 13000
Protoss_Shuttle 1 15350
Protoss_Robotics_Support_Bay 1 14679
15350
