Protoss_Gateway 2 13900
Protoss_Assimilator 2 13325
Protoss_Cybernetics_Core 1 5669
Protoss_Dragoon 4 10529
Protoss_Citadel_of_Adun 1 8969
Protoss_Templar_Archives 1 10504
Singularity_Charge 1 9710
Protoss_Nexus 1 13266
Protoss_Dark_Templar 4 15156
Protoss_Stargate 1 13726
Protoss_Arbiter_Tribunal 1 16059
16059
