Protoss_Gateway 2 4867
Protoss_Zealot 6 8066
Protoss_Assimilator 2 15264
Protoss_Cybernetics_Core 1 8868
Protoss_Dragoon 8 15522
Protoss_Nexus 1 13765
Protoss_Robotics_Facility 1 14357
Protoss_Forge 1 14415
Singularity_Charge 1 13488
15522
