Protoss_Gateway 4 15601
Protoss_Assimilator 1 4504
Protoss_Cybernetics_Core 1 5727
Protoss_Citadel_of_Adun 1 7239
Protoss_Dragoon 9 14644
Protoss_Nexus 1 12317
Protoss_Zealot 4 14411
Singularity_Charge 1 10000
Protoss_Robotics_Facility 1 12496
Protoss_Shuttle 1 13992
Protoss_Observatory 1 14565
15601
