Protoss_Gateway 2 8641
Protoss_Zealot 1 5718
Protoss_Nexus 1 8301
Protoss_Assimilator 2 9918
Protoss_Cybernetics_Core 1 8367
Protoss_Dragoon 7 15613
Protoss_Citadel_of_Adun 1 11149
Protoss_Forge 1 11584
Protoss_Templar_Archives 1 12662
Protoss_Robotics_Facility 1 13377
Protoss_Photon_Cannon 2 13463
Protoss_Dark_Templar 2 14214
Protoss_Stargate 1 14934
Protoss_Shuttle 1 14882
Protoss_Observatory 1 14315
15613
