Protoss_Gateway 3 14222
Protoss_Assimilator 1 4340
Protoss_Zealot 2 6719
Protoss_Cybernetics_Core 1 6893
Protoss_Dragoon 11 15683
Singularity_Charge 1 10781
Protoss_Nexus 1 13841
Protoss_Robotics_Facility 1 13681
Protoss_Shuttle 1 15087
Protoss_Observatory 1 14546
15683
