Protoss_Gateway 3 9312
Protoss_Assimilator 1 4504
Protoss_Cybernetics_Core 1 5916
Protoss_Dragoon 9 15775
Singularity_Charge 1 9909
Protoss_Nexus 2 15818
Protoss_Robotics_Facility 1 14259
Protoss_Observatory 2 15096
15818
