Protoss_Gateway 3 13135
Protoss_Assimilator 1 4347
Protoss_Cybernetics_Core 1 5809
Protoss_Robotics_Facility 1 8005
Protoss_Dragoon 11 15600
Protoss_Observatory 1 8804
Protoss_Observer 2 11944
Protoss_Nexus 1 13691
Singularity_Charge 1 12184
15600
