Protoss_Gateway 1 4147
Protoss_Assimilator 1 4373
Protoss_Cybernetics_Core 1 5718
Protoss_Dragoon 6 15156
Protoss_Robotics_Facility 1 8343
Protoss_Shuttle 1 9743
Protoss_Robotics_Support_Bay 1 9287
Protoss_Zealot 2 11247
Protoss_Reaver 1 11722
Protoss_Observatory 1 11180
Protoss_Nexus 1 14269
Protoss_Observer 2 13518
15156
