Protoss_Gateway 2 10082
Protoss_Assimilator 1 4192
Protoss_Cybernetics_Core 1 5619
Protoss_Dragoon 5 15238
Protoss_Citadel_of_Adun 1 8450
Protoss_Templar_Archives 1 9898
Protoss_Robotics_Facility 1 11463
Protoss_Dark_Templar 5 13544
Protoss_Shuttle 1 12936
Protoss_Nexus 1 15874
15874
