Protoss_Gateway 2 6639
Protoss_Assimilator 1 4564
Protoss_Cybernetics_Core 1 6037
Protoss_Dragoon 11 14476
Singularity_Charge 1 10414
Protoss_Nexus 1 14503
Protoss_Citadel_of_Adun 1 13177
Protoss_Zealot 2 14314
Protoss_Templar_Archives 1 14854
14854
