Protoss_Gateway 3 16024
Protoss_Assimilator 1 4426
Protoss_Cybernetics_Core 1 5829
Protoss_Dragoon 9 15534
Protoss_Nexus 2 16591
Protoss_Robotics_Facility 1 10883
Singularity_Charge 1 9938
Protoss_Observatory 1 13034
Protoss_Observer 2 15087
16591
