Protoss_Gateway 2 13053
Protoss_Assimilator 2 13735
Protoss_Cybernetics_Core 1 5853
Protoss_Dragoon 7 15756
Protoss_Nexus 1 11736
Singularity_Charge 1 9713
Protoss_Citadel_of_Adun 1 11373
Protoss_Robotics_Facility 1 12642
Protoss_Templar_Archives 1 13237
Protoss_Shuttle 1 14349
Protoss_Dark_Templar 3 15584
Protoss_Observatory 1 14422
Protoss_Observer 1 15529
15756
