Protoss_Gateway 2 8673
Protoss_Assimilator 1 4491
Protoss_Cybernetics_Core 1 5911
Protoss_Zealot 3 15386
Protoss_Dragoon 8 14132
Singularity_Charge 1 9642
Protoss_Nexus 1 12611
Protoss_Robotics_Facility 1 12281
Protoss_Shuttle 1 13720
Protoss_Robotics_Support_Bay 1 13160
Protoss_Reaver 1 15436
15436
