Protoss_Gateway 4 15504
Protoss_Assimilator 1 4176
Protoss_Cybernetics_Core 1 5655
Protoss_Dragoon 12 15739
Protoss_Nexus 1 12571
Singularity_Charge 1 9960
Protoss_Robotics_Facility 1 13361
Protoss_Observatory 1 14562
15739
