Protoss_Gateway 4 15917
Protoss_Assimilator 2 12888
Protoss_Cybernetics_Core 1 5642
Protoss_Dragoon 9 13871
Protoss_Nexus 2 16977
Singularity_Charge 1 9587
Protoss_Citadel_of_Adun 1 11529
Protoss_Robotics_Facility 1 12452
Protoss_Observatory 1 13241
Protoss_Observer 2 15175
16977
