Protoss_Gateway 2 8186
Protoss_Assimilator 1 4553
Protoss_Cybernetics_Core 1 5841
Protoss_Dragoon 7 12633
Protoss_Nexus 2 17474
Singularity_Charge 1 9540
Protoss_Robotics_Facility 1 12834
Protoss_Shuttle 1 14303
Protoss_Zealot 2 14033
Protoss_Observatory 1 13901
Protoss_Robotics_Support_Bay 1 14545
Protoss_Observer 1 15146
17474
