Protoss_Gateway 3 14756
Protoss_Assimilator 1 4246
Protoss_Cybernetics_Core 1 5832
Protoss_Dragoon 10 14773
Protoss_Robotics_Facility 1 9936
Singularity_Charge 1 9960
Protoss_Observatory 1 10757
Protoss_Observer 3 13966
Protoss_Nexus 1 14983
14983
