Protoss_Gateway 4 15342
Protoss_Assimilator 1 4360
Protoss_Cybernetics_Core 1 5910
Protoss_Dragoon 13 15745
Protoss_Nexus 1 12006
Singularity_Charge 1 9915
Protoss_Zealot 1 11677
Protoss_Robotics_Facility 1 14606
15745
