Protoss_Gateway 4 14986
Protoss_Assimilator 1 4234
Protoss_Cybernetics_Core 1 5630
Protoss_Dragoon 12 15616
Protoss_Robotics_Facility 1 9592
Protoss_Observatory 1 10354
Singularity_Charge 1 9654
Protoss_Observer 1 11783
Protoss_Nexus 1 14147
Protoss_Citadel_of_Adun 1 15623
15623
