Protoss_Gateway 3 12188
Protoss_Assimilator 1 4419
Protoss_Cybernetics_Core 1 5838
Protoss_Dragoon 10 15045
Protoss_Zealot 1 9109
Protoss_Nexus 1 11507
Protoss_Robotics_Facility 1 11044
Singularity_Charge 1 9812
Protoss_Observatory 1 11769
Protoss_Observer 2 13729
Protoss_Shuttle 1 15792
15792
