Protoss_Gateway 2 8127
Protoss_Assimilator 1 4166
Protoss_Cybernetics_Core 1 5595
Protoss_Zealot 1 5511
Protoss_Dragoon 10 15095
Singularity_Charge 1 9754
Protoss_Nexus 1 12640
Protoss_Robotics_Facility 1 12869
Protoss_Shuttle 1 14268
Protoss_Observatory 1 13930
Protoss_Robotics_Support_Bay 1 14826
Protoss_Observer 1 15111
15111
