Protoss_Gateway 2 12710
Protoss_Assimilator 1 4330
Protoss_Cybernetics_Core 1 5786
Protoss_Dragoon 8 14769
Protoss_Nexus 1 11408
Protoss_Robotics_Facility 1 11504
Singularity_Charge 1 9900
Protoss_Observatory 1 12417
Protoss_Shuttle 1 13346
Protoss_Robotics_Support_Bay 1 13377
Protoss_Observer 1 14189
Protoss_Reaver 1 15785
Protoss_Zealot 1 15389
15785
