Protoss_Assimilator 2 6596
Protoss_Nexus 1 7536
Protoss_Gateway 3 11929
Protoss_Cybernetics_Core 2 11396
Protoss_Zealot 3 9784
Protoss_Dragoon 5 14840
Protoss_Robotics_Facility 1 15687
15687
