Protoss_Gateway 3 15232
Protoss_Assimilator 1 4173
Protoss_Cybernetics_Core 1 5636
Protoss_Dragoon 10 15648
Protoss_Zealot 1 9124
Singularity_Charge 1 9300
Protoss_Nexus 2 15274
Protoss_Robotics_Facility 1 14866
15648
