Protoss_Gateway 2 4906
Protoss_Zealot 13 15061
Protoss_Forge 1 6990
Protoss_Photon_Cannon 4 10825
Protoss_Assimilator 1 10900
Protoss_Cybernetics_Core 1 12598
Protoss_Citadel_of_Adun 1 14556
Protoss_Dragoon 2 15431
Protoss_Templar_Archives 1 16000
16000
