Protoss_Gateway 2 6738
Protoss_Assimilator 1 4464
Protoss_Cybernetics_Core 1 5756
Protoss_Dragoon 7 11736
Protoss_Robotics_Facility 1 11231
Singularity_Charge 1 9989
Protoss_Observatory 1 12079
Protoss_Nexus 1 14926
Protoss_Observer 1 13158
Protoss_Robotics_Support_Bay 1 13416
Protoss_Shuttle 1 14689
Protoss_Reaver 1 16247
16247
