Protoss_Assimilator 3 14174
Protoss_Gateway 4 16063
Protoss_Zealot 11 15392
Protoss_Nexus 1 9848
Protoss_Cybernetics_Core 1 9997
Protoss_Forge 1 10188
Protoss_Photon_Cannon 2 12559
Protoss_Citadel_of_Adun 1 13319
Protoss_Templar_Archives 1 15706
16063
