Protoss_Gateway 2 7467
Protoss_Assimilator 1 4428
Protoss_Zealot 1 5139
Protoss_Cybernetics_Core 1 6731
Protoss_Dragoon 10 14202
Protoss_Nexus 1 13003
Singularity_Charge 1 10494
Protoss_Robotics_Facility 1 14107
Protoss_Observatory 1 15045
15045
