Protoss_Gateway 2 10289
Protoss_Assimilator 1 4429
Protoss_Cybernetics_Core 1 5793
Protoss_Dragoon 9 15673
Protoss_Robotics_Facility 1 10246
Singularity_Charge 1 9872
Protoss_Shuttle 1 11667
Protoss_Zealot 4 12718
Protoss_Observatory 1 11615
Protoss_Observer 2 13520
15673
