Protoss_Gateway 3 15792
Protoss_Assimilator 1 4597
Protoss_Cybernetics_Core 1 5963
Protoss_Dragoon 8 15294
Protoss_Nexus 1 12227
Singularity_Charge 1 10008
Protoss_Robotics_Facility 1 12212
Protoss_Observatory 1 13485
Protoss_Observer 1 14865
15792
