Protoss_Gateway 1 4271
Protoss_Assimilator 1 4346
Protoss_Cybernetics_Core 1 5796
Protoss_Dragoon 3 9636
Protoss_Robotics_Facility 1 9885
Protoss_Citadel_of_Adun 1 10529
Protoss_Shuttle 1 11316
Singularity_Charge 1 10048
Protoss_Robotics_Support_Bay 1 11062
Protoss_Zealot 2 13334
Protoss_Reaver 2 15922
Protoss_Templar_Archives 1 13280
Protoss_Nexus 1 16339
Protoss_Dark_Templar 1 14861
16339
