Protoss_Gateway 3 13738
Protoss_Assimilator 1 5123
Protoss_Zealot 4 14732
Protoss_Cybernetics_Core 1 7299
Protoss_Dragoon 10 15336
Protoss_Nexus 1 12693
Singularity_Charge 1 11043
Protoss_Robotics_Facility 1 13137
Protoss_Observatory 1 13933
Protoss_Observer 1 14958
15336
