Protoss_Gateway 2 10044
Protoss_Assimilator 1 4155
Protoss_Cybernetics_Core 1 5745
Protoss_Dragoon 9 14834
Protoss_Robotics_Facility 1 9636
Singularity_Charge 1 9663
Protoss_Observatory 1 10452
Protoss_Observer 2 12506
Protoss_Nexus 1 14133
Protoss_Shuttle 1 13864
Protoss_Robotics_Support_Bay 1 13681
Protoss_Reaver 1 15714
15714
