Protoss_Gateway 4 15950
Protoss_Assimilator 1 4248
Protoss_Cybernetics_Core 1 5803
Protoss_Dragoon 13 15332
Singularity_Charge 1 9601
Protoss_Nexus 1 12801
Protoss_Robotics_Facility 1 12990
Protoss_Observatory 1 14053
Protoss_Observer 1 15078
15950
