Protoss_Gateway 2 8677
Protoss_Zealot 2 5947
Protoss_Assimilator 1 5429
Protoss_Cybernetics_Core 1 7218
Protoss_Dragoon 10 14890
Protoss_Robotics_Facility 1 11545
Singularity_Charge 1 11870
Protoss_Robotics_Support_Bay 1 13061
Protoss_Shuttle 1 13994
Protoss_Observatory 1 13528
Protoss_Observer 1 14988
14988
