Protoss_Nexus 1 6748
Protoss_Gateway 3 11544
Protoss_Assimilator 1 6109
Protoss_Cybernetics_Core 1 7842
Protoss_Zealot 4 13539
Protoss_Dragoon 8 15759
Protoss_Robotics_Facility 1 11744
Singularity_Charge 1 11914
Protoss_Observatory 1 12710
Protoss_Observer 1 13802
Protoss_Shuttle 1 15160
Protoss_Robotics_Support_Bay 1 14590
15759
