Protoss_Gateway 5 12724
Protoss_Zealot 4 15166
Protoss_Assimilator 1 6371
Protoss_Cybernetics_Core 1 9410
Protoss_Dragoon 4 15809
Protoss_Robotics_Facility 1 11624
Protoss_Robotics_Support_Bay 1 12429
Protoss_Shuttle 1 13188
Protoss_Reaver 1 14746
Singularity_Charge 1 13960
Protoss_Nexus 1 16846
Protoss_Observatory 1 15190
16846
