Protoss_Gateway 2 8424
Protoss_Assimilator 1 4491
Protoss_Cybernetics_Core 1 5935
Protoss_Dragoon 3 9619
Protoss_Citadel_of_Adun 1 10103
Protoss_Zealot 3 11736
Protoss_Robotics_Facility 1 11679
Singularity_Charge 1 9885
Protoss_Templar_Archives 1 11917
Protoss_Shuttle 1 13073
Protoss_Dark_Templar 5 15449
Protoss_Nexus 1 17191
17191
