Protoss_Gateway 2 12852
Protoss_Assimilator 1 4368
Protoss_Cybernetics_Core 1 5813
Protoss_Dragoon 5 11668
Protoss_Nexus 1 11683
Singularity_Charge 1 9850
Protoss_Robotics_Facility 2 12920
Protoss_Shuttle 1 13419
Protoss_Robotics_Support_Bay 1 13068
Protoss_Zealot 4 15017
Protoss_Reaver 2 15091
15091
