Protoss_Gateway 1 4293
Protoss_Assimilator 2 15329
Protoss_Cybernetics_Core 1 6178
Protoss_Dragoon 6 14483
Protoss_Robotics_Facility 1 10148
Protoss_Shuttle 1 11557
Singularity_Charge 1 10201
Protoss_Robotics_Support_Bay 1 10937
Protoss_Reaver 2 15106
Protoss_Observatory 1 14799
Protoss_Nexus 1 17111
17111
