Protoss_Gateway 4 16047
Protoss_Assimilator 1 4256
Protoss_Cybernetics_Core 1 5929
Protoss_Dragoon 9 14872
Protoss_Robotics_Facility 1 11258
Singularity_Charge 1 9865
Protoss_Observatory 1 11982
Protoss_Nexus 2 15971
Protoss_Observer 2 15207
16047
