Protoss_Gateway 4 13177
Protoss_Zealot 6 10097
Protoss_Assimilator 1 9293
Protoss_Cybernetics_Core 1 10569
Protoss_Dragoon 4 15083
Protoss_Nexus 1 16312
Singularity_Charge 1 14311
16312
