Protoss_Gateway 2 11424
Protoss_Assimilator 1 4198
Protoss_Cybernetics_Core 1 5660
Protoss_Dragoon 11 15493
Protoss_Nexus 2 16319
Protoss_Robotics_Facility 1 10690
Singularity_Charge 1 9882
Protoss_Shuttle 1 13240
Protoss_Robotics_Support_Bay 1 13934
Protoss_Reaver 1 15673
Protoss_Observatory 1 15294
16319
