Protoss_Gateway 3 15484
Protoss_Assimilator 1 4524
Protoss_Cybernetics_Core 1 5831
Protoss_Dragoon 6 15262
Protoss_Citadel_of_Adun 1 8611
Protoss_Robotics_Facility 1 9592
Protoss_Zealot 1 9500
Protoss_Templar_Archives 1 10448
Protoss_Shuttle 1 11309
Protoss_Dark_Templar 2 11685
Protoss_Nexus 1 15314
Protoss_Observatory 1 14877
15484
