Protoss_Gateway 2 12569
Protoss_Zealot 2 6492
Protoss_Assimilator 1 5765
Protoss_Cybernetics_Core 1 7572
Protoss_Dragoon 6 13902
Protoss_Nexus 1 11774
Singularity_Charge 1 11453
Protoss_Citadel_of_Adun 1 13221
Protoss_Robotics_Facility 1 14502
Protoss_Templar_Archives 1 14769
Protoss_Shuttle 1 15911
15911
