Protoss_Gateway 2 14284
Protoss_Assimilator 1 4160
Protoss_Cybernetics_Core 1 5606
Protoss_Dragoon 7 15490
Protoss_Robotics_Facility 1 9625
Singularity_Charge 1 9531
Protoss_Shuttle 1 11016
Protoss_Robotics_Support_Bay 1 10548
Protoss_Reaver 1 12688
Protoss_Zealot 2 12904
Protoss_Observatory 1 12253
Protoss_Nexus 1 14601
Protoss_Observer 2 14429
15490
