Protoss_Gateway 2 11158
Protoss_Assimilator 1 4578
Protoss_Cybernetics_Core 1 5974
Protoss_Dragoon 7 14371
Protoss_Robotics_Facility 1 10741
Singularity_Charge 1 10275
Protoss_Observatory 1 11679
Protoss_Shuttle 1 12589
Protoss_Zealot 2 12993
Protoss_Observer 1 13594
14371
