Protoss_Assimilator 1 3715
Protoss_Gateway 2 15105
Protoss_Cybernetics_Core 1 6380
Protoss_Dragoon 6 14754
Protoss_Robotics_Facility 1 8700
Protoss_Shuttle 2 15955
Protoss_Observatory 1 11109
Singularity_Charge 1 11358
Protoss_Nexus 1 14373
Protoss_Observer 2 13512
Protoss_Forge 1 12858
Protoss_Photon_Cannon 1 14716
15955
