Protoss_Gateway 2 10689
Protoss_Assimilator 1 4186
Protoss_Cybernetics_Core 1 5759
Protoss_Dragoon 7 14302
Protoss_Robotics_Facility 1 9886
Singularity_Charge 1 9877
Protoss_Observatory 1 10670
Protoss_Nexus 1 14386
Protoss_Observer 1 12517
Protoss_Robotics_Support_Bay 1 12576
Protoss_Shuttle 1 13875
Protoss_Reaver 1 15433
15433
