Protoss_Gateway 6 15184
Protoss_Assimilator 1 4189
Protoss_Cybernetics_Core 1 5729
Protoss_Dragoon 8 15540
Protoss_Nexus 2 15337
Singularity_Charge 1 9803
Protoss_Robotics_Facility 1 12213
Protoss_Observatory 1 13043
Protoss_Observer 2 15125
15540
