Protoss_Gateway 2 12924
Protoss_Assimilator 1 4826
Protoss_Cybernetics_Core 1 5952
Protoss_Dragoon 8 14141
Protoss_Nexus 2 16963
Singularity_Charge 1 10096
Protoss_Robotics_Facility 1 13102
Protoss_Shuttle 1 14528
Protoss_Robotics_Support_Bay 1 14050
Protoss_Reaver 1 16231
16963
