Protoss_Gateway 1 4114
Protoss_Assimilator 1 4395
Protoss_Cybernetics_Core 1 5664
Protoss_Dragoon 5 15071
Protoss_Robotics_Facility 1 8319
Protoss_Shuttle 1 9728
Protoss_Robotics_Support_Bay 1 9998
Protoss_Nexus 2 16272
Protoss_Zealot 2 12444
Protoss_Reaver 1 12580
Protoss_Observatory 1 12165
Protoss_Observer 2 14408
16272
