Protoss_Gateway 2 7700
Protoss_Assimilator 2 4894
Protoss_Zealot 1 5256
Protoss_Cybernetics_Core 1 6939
Protoss_Dragoon 12 15314
Singularity_Charge 1 10831
Protoss_Nexus 2 16462
16462
