Protoss_Gateway 3 15330
Protoss_Assimilator 1 5014
Protoss_Zealot 4 13729
Protoss_Cybernetics_Core 1 6419
Protoss_Dragoon 7 15253
Protoss_Nexus 1 12060
Protoss_Robotics_Facility 1 11400
Singularity_Charge 1 10632
Protoss_Shuttle 1 12795
Protoss_Robotics_Support_Bay 1 12578
Protoss_Observatory 1 12991
Protoss_Reaver 1 14567
Protoss_Observer 1 15392
15392
