Protoss_Assimilator 2 4934
Protoss_Gateway 6 15857
Protoss_Cybernetics_Core 1 6424
Protoss_Dragoon 5 13450
Protoss_Nexus 2 13271
Singularity_Charge 1 10254
Protoss_Robotics_Facility 1 13429
Protoss_Shuttle 1 14926
Protoss_Robotics_Support_Bay 1 14852
15857
