Protoss_Gateway 4 15389
Protoss_Assimilator 1 4208
Protoss_Cybernetics_Core 1 5547
Protoss_Dragoon 8 15759
Protoss_Nexus 2 14630
Singularity_Charge 1 9730
Protoss_Zealot 2 15348
15759
