Protoss_Gateway 2 10580
Protoss_Assimilator 1 4675
Protoss_Cybernetics_Core 1 5879
Protoss_Dragoon 4 13456
Protoss_Citadel_of_Adun 1 9178
Protoss_Robotics_Facility 1 10696
Protoss_Templar_Archives 1 10829
Protoss_Dark_Templar 4 14861
Protoss_Shuttle 1 12427
Protoss_Zealot 1 13199
Protoss_Nexus 1 17427
17427
