Protoss_Gateway 4 14535
Protoss_Assimilator 1 4126
Protoss_Cybernetics_Core 1 5712
Protoss_Zealot 5 15503
Protoss_Dragoon 10 14024
Protoss_Robotics_Facility 1 10169
Singularity_Charge 1 9666
Protoss_Observatory 1 10880
Protoss_Observer 3 14739
Protoss_Shuttle 1 15716
15716
