Protoss_Gateway 2 9255
Protoss_Assimilator 2 5569
Protoss_Zealot 2 6992
Protoss_Cybernetics_Core 1 7148
Protoss_Dragoon 6 12868
Protoss_Robotics_Facility 1 12244
Singularity_Charge 1 11633
Protoss_Robotics_Support_Bay 1 13213
Protoss_Shuttle 1 13934
Protoss_Nexus 1 16531
Protoss_Reaver 1 15779
16531
