Protoss_Gateway 2 9974
Protoss_Assimilator 1 4303
Protoss_Zealot 2 6769
Protoss_Cybernetics_Core 1 6848
Protoss_Dragoon 9 15083
Protoss_Nexus 2 16205
Singularity_Charge 1 11630
16205
