Protoss_Gateway 3 15236
Protoss_Assimilator 1 4293
Protoss_Cybernetics_Core 1 5630
Protoss_Dragoon 5 12191
Protoss_Robotics_Facility 1 9812
Singularity_Charge 1 9692
Protoss_Observatory 1 10573
Protoss_Nexus 1 13025
Protoss_Shuttle 1 11964
Protoss_Robotics_Support_Bay 1 12376
Protoss_Observer 2 15307
Protoss_Zealot 2 14355
Protoss_Reaver 1 14482
15307
