Protoss_Gateway 2 12226
Protoss_Assimilator 2 13688
Protoss_Cybernetics_Core 1 5882
Protoss_Dragoon 10 15121
Protoss_Nexus 1 11779
Protoss_Robotics_Facility 1 12130
Singularity_Charge 1 10248
Protoss_Observatory 1 12890
Protoss_Observer 1 14127
Protoss_Shuttle 1 15833
Protoss_Robotics_Support_Bay 1 15222
15833
