Protoss_Gateway 2 14829
Protoss_Assimilator 2 5821
Protoss_Zealot 3 7518
Protoss_Cybernetics_Core 1 7605
Protoss_Citadel_of_Adun 1 9282
Protoss_Dragoon 5 15818
Protoss_Templar_Archives 1 10780
Protoss_Nexus 1 13307
Protoss_Dark_Templar 2 13087
Protoss_Forge 1 12302
Protoss_Photon_Cannon 1 13639
Protoss_Robotics_Facility 1 15709
15818
