Protoss_Gateway 5 15800
Protoss_Assimilator 1 4343
Protoss_Cybernetics_Core 1 6065
Protoss_Dragoon 9 14969
Protoss_Nexus 2 16186
Protoss_Robotics_Facility 1 11992
Singularity_Charge 1 10143
Protoss_Observatory 1 12869
Protoss_Observer 1 15023
16186
