Protoss_Gateway 2 10073
Protoss_Zealot 2 6052
Protoss_Assimilator 1 5569
Protoss_Cybernetics_Core 1 7189
Protoss_Dragoon 9 14489
Protoss_Robotics_Facility 1 10857
Protoss_Shuttle 1 12251
Singularity_Charge 1 10980
Protoss_Robotics_Support_Bay 1 12860
Protoss_Reaver 1 14810
Protoss_Observatory 1 14466
14810
