Protoss_Gateway 4 15784
Protoss_Assimilator 1 4580
Protoss_Cybernetics_Core 1 6334
Protoss_Dragoon 7 13652
Protoss_Nexus 1 11897
Singularity_Charge 1 10254
Protoss_Robotics_Facility 1 12538
Protoss_Observatory 1 13409
Protoss_Observer 2 15435
Protoss_Zealot 2 14639
Protoss_Shuttle 1 16059
16059
