Protoss_Gateway 3 12908
Protoss_Assimilator 1 4564
Protoss_Cybernetics_Core 1 5910
Protoss_Dragoon 7 13172
Protoss_Robotics_Facility 1 10097
Singularity_Charge 1 10136
Protoss_Observatory 1 10861
Protoss_Observer 2 12773
Protoss_Zealot 3 15032
Protoss_Citadel_of_Adun 1 14361
Protoss_Shuttle 1 14469
15032
