Protoss_Gateway 4 14853
Protoss_Assimilator 1 4232
Protoss_Cybernetics_Core 1 5674
Protoss_Dragoon 10 14717
Singularity_Charge 1 9476
Protoss_Nexus 1 12365
Protoss_Robotics_Facility 1 13156
Protoss_Observatory 1 13872
Protoss_Observer 1 15380
15380
