Protoss_Gateway 2 5524
Protoss_Assimilator 2 7717
Protoss_Zealot 4 7460
Protoss_Cybernetics_Core 1 9289
Protoss_Dragoon 8 14937
Protoss_Nexus 1 13601
Singularity_Charge 1 13266
14937
