Protoss_Gateway 2 8462
Protoss_Zealot 4 13100
Protoss_Nexus 2 15763
Protoss_Assimilator 1 7075
Protoss_Cybernetics_Core 1 8303
Protoss_Dragoon 8 14445
Protoss_Robotics_Facility 1 13965
Singularity_Charge 1 12932
15763
