Protoss_Gateway 2 13542
Protoss_Assimilator 1 4423
Protoss_Cybernetics_Core 1 6017
Protoss_Dragoon 8 15756
Protoss_Robotics_Facility 1 9949
Protoss_Observatory 1 10643
Singularity_Charge 1 10207
Protoss_Nexus 1 13222
Protoss_Observer 2 14496
Protoss_Shuttle 1 13079
Protoss_Robotics_Support_Bay 2 13539
Protoss_Reaver 1 16092
16092
