Protoss_Gateway 2 10422
Protoss_Assimilator 3 14830
Protoss_Zealot 3 9222
Protoss_Nexus 2 14378
Protoss_Cybernetics_Core 1 9309
Protoss_Dragoon 5 14738
Protoss_Robotics_Facility 1 12083
Protoss_Shuttle 1 13793
Protoss_Robotics_Support_Bay 1 13690
Protoss_Reaver 1 15571
15571
