Protoss_Gateway 3 15646
Protoss_Assimilator 1 4609
Protoss_Cybernetics_Core 1 6122
Protoss_Dragoon 7 14208
Protoss_Nexus 2 16680
Protoss_Zealot 3 15213
Protoss_Robotics_Facility 1 12649
Singularity_Charge 1 12107
Protoss_Observatory 1 14097
Protoss_Observer 1 15187
16680
