Protoss_Gateway 2 10310
Protoss_Assimilator 1 4352
Protoss_Cybernetics_Core 1 6030
Protoss_Dragoon 7 14436
Protoss_Robotics_Facility 1 10384
Singularity_Charge 1 9740
Protoss_Shuttle 1 12245
Protoss_Observatory 1 11707
Protoss_Zealot 2 13233
Protoss_Nexus 2 17431
Protoss_Observer 1 13619
17431
