Protoss_Gateway 2 10182
Protoss_Assimilator 1 4268
Protoss_Cybernetics_Core 1 5663
Protoss_Dragoon 8 14855
Protoss_Robotics_Facility 2 10172
Singularity_Charge 1 9736
Protoss_Observatory 1 10920
Protoss_Nexus 1 13418
Protoss_Observer 1 11938
Protoss_Shuttle 1 13709
Protoss_Robotics_Support_Bay 1 13463
Protoss_Reaver 1 15267
15267
