Protoss_Gateway 3 14516
Protoss_Assimilator 1 4398
Protoss_Cybernetics_Core 1 5657
Protoss_Dragoon 8 15115
Protoss_Citadel_of_Adun 1 10234
Singularity_Charge 1 9751
Protoss_Templar_Archives 1 11928
Protoss_Nexus 1 14566
Protoss_Dark_Templar 2 13494
Protoss_Robotics_Facility 1 15379
15379
