Protoss_Nexus 2 16058
Protoss_Gateway 3 15762
Protoss_Assimilator 1 5939
Protoss_Cybernetics_Core 1 7509
Protoss_Zealot 1 7700
Protoss_Dragoon 8 14940
Protoss_Robotics_Facility 1 15573
16058
