Protoss_Gateway 4 14690
Protoss_Assimilator 1 4498
Protoss_Cybernetics_Core 1 5780
Protoss_Dragoon 6 15294
Protoss_Citadel_of_Adun 1 9715
Protoss_Templar_Archives 1 11159
Singularity_Charge 1 9856
Protoss_Zealot 1 11194
Protoss_Dark_Templar 4 13927
Protoss_Nexus 1 14557
15294
