Protoss_Gateway 2 8317
Protoss_Assimilator 1 4249
Protoss_Cybernetics_Core 1 5831
Protoss_Dragoon 9 15625
Protoss_Citadel_of_Adun 1 9883
Protoss_Templar_Archives 1 11345
Singularity_Charge 1 9959
Protoss_Zealot 1 11209
Protoss_Dark_Templar 2 13248
Protoss_Nexus 1 15014
Protoss_Robotics_Facility 1 14913
15625
