Protoss_Gateway 3 15257
Protoss_Assimilator 2 4736
Protoss_Cybernetics_Core 1 5813
Protoss_Dragoon 6 15402
Protoss_Robotics_Facility 1 10175
Singularity_Charge 1 9935
Protoss_Observatory 1 11186
Protoss_Nexus 1 13331
Protoss_Observer 2 15266
Protoss_Shuttle 1 12816
Protoss_Robotics_Support_Bay 1 12691
Protoss_Zealot 2 14077
Protoss_Reaver 1 14441
15402
