Protoss_Gateway 2 11352
Protoss_Assimilator 1 4306
Protoss_Cybernetics_Core 1 5739
Protoss_Dragoon 4 15165
Protoss_Citadel_of_Adun 1 7651
Protoss_Templar_Archives 1 9415
Protoss_Nexus 1 12259
Protoss_Dark_Templar 4 13353
Protoss_Zealot 1 11484
Protoss_Robotics_Facility 1 14899
15165
