Protoss_Gateway 2 14481
Protoss_Assimilator 1 4425
Protoss_Cybernetics_Core 1 5769
Protoss_Dragoon 7 14697
Protoss_Robotics_Facility 1 9824
Protoss_Shuttle 1 11379
Singularity_Charge 1 10014
Protoss_Robotics_Support_Bay 1 10787
Protoss_Reaver 1 12937
Protoss_Nexus 1 14946
Protoss_Observatory 1 13409
Protoss_Observer 1 14528
Protoss_Citadel_of_Adun 1 15833
15833
