Protoss_Gateway 2 8891
Protoss_Assimilator 1 4492
Protoss_Zealot 2 6046
Protoss_Cybernetics_Core 1 6023
Protoss_Dragoon 9 14896
Protoss_Citadel_of_Adun 1 8434
Protoss_Templar_Archives 1 9901
Protoss_Dark_Templar 2 11138
Protoss_Nexus 1 16863
Singularity_Charge 1 14138
16863
