Protoss_Gateway 4 14316
Protoss_Assimilator 1 4403
Protoss_Cybernetics_Core 1 5841
Protoss_Dragoon 7 14834
Protoss_Zealot 4 12649
Singularity_Charge 1 9719
Protoss_Nexus 1 14124
Protoss_Robotics_Facility 1 14100
Protoss_Shuttle 1 15939
Protoss_Robotics_Support_Bay 1 15344
15939
