Protoss_Gateway 1 4350
Protoss_Assimilator 1 4401
Protoss_Zealot 2 6203
Protoss_Cybernetics_Core 1 6248
Protoss_Dragoon 8 15762
Protoss_Robotics_Facility 1 10380
Protoss_Robotics_Support_Bay 1 11144
Protoss_Shuttle 1 12326
Protoss_Reaver 1 14005
Singularity_Charge 1 12565
Protoss_Nexus 1 16767
16767
