Protoss_Gateway 2 14023
Protoss_Assimilator 2 15276
Protoss_Cybernetics_Core 1 6125
Protoss_Dragoon 9 15704
Protoss_Nexus 2 13711
Singularity_Charge 1 9915
Protoss_Robotics_Facility 1 13438
Protoss_Citadel_of_Adun 1 14221
Protoss_Observatory 1 14911
Protoss_Templar_Archives 1 15760
15760
