Protoss_Nexus 2 15761
Protoss_Gateway 3 15986
Protoss_Assimilator 2 11794
Protoss_Cybernetics_Core 1 7638
Protoss_Zealot 1 7413
Protoss_Dragoon 10 15664
Protoss_Robotics_Facility 1 12603
Singularity_Charge 1 12364
Protoss_Observatory 1 13817
Protoss_Observer 1 14862
Protoss_Citadel_of_Adun 1 15760
15986
