Protoss_Gateway 2 6724
Protoss_Assimilator 2 15544
Protoss_Cybernetics_Core 1 5841
Protoss_Dragoon 9 15107
Protoss_Nexus 1 12322
Singularity_Charge 1 10137
Protoss_Robotics_Facility 1 13431
Protoss_Shuttle 1 14888
Protoss_Robotics_Support_Bay 1 14821
15544
