Protoss_Gateway 3 13078
Protoss_Assimilator 1 4246
Protoss_Cybernetics_Core 1 5651
Protoss_Dragoon 8 14949
Protoss_Robotics_Facility 1 9717
Singularity_Charge 1 9640
Protoss_Observatory 1 10437
Protoss_Nexus 1 13421
Protoss_Observer 2 12497
Protoss_Shuttle 1 13855
Protoss_Robotics_Support_Bay 1 13747
Protoss_Reaver 1 15685
15685
