Protoss_Gateway 2 12506
Protoss_Assimilator 1 4491
Protoss_Cybernetics_Core 1 5907
Protoss_Dragoon 8 14035
Protoss_Nexus 1 11861
Singularity_Charge 1 9839
Protoss_Robotics_Facility 1 12566
Protoss_Shuttle 1 14045
Protoss_Robotics_Support_Bay 1 13857
Protoss_Zealot 2 14897
Protoss_Reaver 1 15676
15676
