Protoss_Gateway 3 9308
Protoss_Zealot 5 13878
Protoss_Nexus 1 8686
Protoss_Assimilator 1 7057
Protoss_Cybernetics_Core 1 8467
Protoss_Dragoon 8 13017
Singularity_Charge 1 12323
Protoss_Robotics_Facility 1 15428
15428
