Protoss_Gateway 4 15991
Protoss_Zealot 1 5227
Protoss_Assimilator 1 5873
Protoss_Cybernetics_Core 1 6864
Protoss_Nexus 2 16101
Protoss_Dragoon 9 15127
Protoss_Robotics_Facility 1 11101
Protoss_Observatory 1 11997
Singularity_Charge 1 11598
Protoss_Observer 2 13896
16101
