Protoss_Gateway 2 14303
Protoss_Zealot 5 9383
Protoss_Forge 1 5730
Protoss_Photon_Cannon 2 8015
Protoss_Assimilator 1 8565
Protoss_Cybernetics_Core 1 9668
Protoss_Nexus 1 12387
Protoss_Robotics_Facility 1 12178
Protoss_Dragoon 5 15613
Protoss_Robotics_Support_Bay 1 13460
Protoss_Reaver 1 15363
15613
