Protoss_Gateway 1 4283
Protoss_Assimilator 2 13944
Protoss_Cybernetics_Core 1 5827
Protoss_Dragoon 5 15153
Protoss_Robotics_Facility 1 10285
Singularity_Charge 1 9900
Protoss_Shuttle 1 11709
Protoss_Robotics_Support_Bay 1 11060
Protoss_Zealot 2 12599
Protoss_Reaver 1 13267
Protoss_Nexus 2 17247
Protoss_Observatory 1 14246
Protoss_Observer 1 15476
17247
