Protoss_Nexus 2 15482
Protoss_Gateway 4 16013
Protoss_Assimilator 1 5952
Protoss_Cybernetics_Core 1 7442
Protoss_Zealot 1 7671
Protoss_Dragoon 12 15633
Protoss_Robotics_Facility 1 12812
Singularity_Charge 1 11855
Protoss_Observatory 1 14125
16013
