Protoss_Nexus 2 14130
Protoss_Gateway 4 15548
Protoss_Assimilator 1 5881
Protoss_Zealot 3 12359
Protoss_Cybernetics_Core 1 7580
Protoss_Dragoon 12 15818
Singularity_Charge 1 12347
Protoss_Robotics_Facility 1 14278
15818
