Protoss_Gateway 2 8632
Protoss_Assimilator 2 13603
Protoss_Cybernetics_Core 1 5639
Protoss_Dragoon 9 14791
Protoss_Nexus 1 11302
Protoss_Robotics_Facility 1 10999
Singularity_Charge 1 9900
Protoss_Observatory 1 11944
Protoss_Stargate 2 16222
Protoss_Observer 1 12959
Protoss_Fleet_Beacon 1 15055
16222
