Protoss_Gateway 4 14543
Protoss_Assimilator 1 4315
Protoss_Cybernetics_Core 1 5731
Protoss_Dragoon 7 14956
Protoss_Nexus 1 11620
Protoss_Robotics_Facility 1 11957
Singularity_Charge 1 10062
Protoss_Observatory 1 12682
Protoss_Zealot 2 14710
Protoss_Observer 2 14812
14956
