Protoss_Gateway 2 14948
Protoss_Assimilator 1 4205
Protoss_Cybernetics_Core 1 5739
Protoss_Zealot 3 12570
Protoss_Dragoon 6 14791
Protoss_Robotics_Facility 1 9895
Singularity_Charge 1 9408
Protoss_Shuttle 1 11361
Protoss_Robotics_Support_Bay 1 10794
Protoss_Reaver 1 13025
Protoss_Observatory 1 12424
Protoss_Observer 2 14730
14948
