Protoss_Gateway 2 13976
Protoss_Assimilator 1 4466
Protoss_Cybernetics_Core 1 5756
Protoss_Dragoon 7 15244
Protoss_Nexus 2 17472
Singularity_Charge 1 9812
Protoss_Robotics_Facility 1 12042
Protoss_Shuttle 1 13445
Protoss_Robotics_Support_Bay 1 12941
Protoss_Zealot 2 14879
Protoss_Reaver 1 15003
17472
