Protoss_Gateway 2 15059
Protoss_Assimilator 2 15424
Protoss_Cybernetics_Core 1 5977
Protoss_Dragoon 7 15658
Protoss_Nexus 2 15205
Singularity_Charge 1 10055
Protoss_Robotics_Facility 1 12651
Protoss_Observatory 1 13804
Protoss_Citadel_of_Adun 1 15226
Protoss_Observer 1 14922
15658
