Protoss_Nexus 1 7234
Protoss_Gateway 4 15643
Protoss_Assimilator 2 14108
Protoss_Cybernetics_Core 1 8069
Protoss_Zealot 6 14727
Protoss_Dragoon 8 15032
Protoss_Robotics_Facility 1 13997
Singularity_Charge 1 12097
Protoss_Observatory 1 15104
Protoss_Shuttle 1 15933
15933
