Protoss_Gateway 4 13632
Protoss_Assimilator 2 15353
Protoss_Cybernetics_Core 1 5865
Protoss_Nexus 1 8961
Protoss_Dragoon 8 12903
Protoss_Zealot 7 14806
Protoss_Citadel_of_Adun 1 12236
Singularity_Charge 1 11454
Protoss_Robotics_Facility 1 16059
16059
