Protoss_Gateway 3 13594
Protoss_Assimilator 1 4346
Protoss_Cybernetics_Core 1 5651
Protoss_Zealot 1 5654
Protoss_Dragoon 11 15288
Protoss_Robotics_Facility 1 10125
Singularity_Charge 1 10087
Protoss_Observatory 1 10819
Protoss_Observer 2 13592
Protoss_Nexus 1 14121
15288
