Protoss_Gateway 4 15292
Protoss_Assimilator 2 13403
Protoss_Cybernetics_Core 1 5727
Protoss_Dragoon 5 11477
Protoss_Robotics_Facility 1 10115
Singularity_Charge 1 9967
Protoss_Observatory 1 10968
Protoss_Nexus 2 16170
Protoss_Observer 2 13949
Protoss_Zealot 1 12526
Protoss_Citadel_of_Adun 1 13808
Protoss_Templar_Archives 1 15806
16170
