Protoss_Gateway 4 15163
Protoss_Assimilator 2 12693
Protoss_Cybernetics_Core 1 5623
Protoss_Dragoon 5 14351
Protoss_Citadel_of_Adun 1 9134
Protoss_Templar_Archives 1 10581
Singularity_Charge 1 9765
Protoss_Nexus 1 13373
Protoss_Dark_Templar 1 11791
Protoss_Stargate 1 12681
Protoss_Arbiter_Tribunal 1 14247
Protoss_Arbiter 1 18065
18065
