Protoss_Gateway 2 6570
Protoss_Assimilator 1 4653
Protoss_Cybernetics_Core 1 5881
Protoss_Dragoon 8 15511
Protoss_Citadel_of_Adun 1 10164
Singularity_Charge 1 9970
Protoss_Templar_Archives 1 11607
Protoss_Zealot 2 11841
Protoss_Dark_Templar 4 14217
Protoss_Nexus 1 15273
15511
