Protoss_Gateway 2 8364
Protoss_Assimilator 2 14635
Protoss_Cybernetics_Core 1 5870
Protoss_Dragoon 6 13286
Singularity_Charge 1 9906
Protoss_Nexus 2 14474
Protoss_Citadel_of_Adun 1 12110
Protoss_Templar_Archives 1 13653
Protoss_Dark_Templar 2 14872
Protoss_Stargate 1 16213
16213
