Protoss_Gateway 2 15356
Protoss_Assimilator 2 4949
Protoss_Zealot 2 5958
Protoss_Cybernetics_Core 1 5944
Protoss_Dragoon 7 15045
Protoss_Robotics_Facility 1 8887
Protoss_Shuttle 1 10346
Protoss_Robotics_Support_Bay 1 10449
Protoss_Reaver 1 12211
Protoss_Observatory 1 11978
Singularity_Charge 1 12075
Protoss_Observer 3 15318
Protoss_Nexus 1 16459
16459
