Protoss_Gateway 2 6741
Protoss_Assimilator 1 4211
Protoss_Cybernetics_Core 1 5771
Protoss_Dragoon 12 15224
Singularity_Charge 1 9891
Protoss_Nexus 1 14791
Protoss_Robotics_Facility 1 14796
15224
