Protoss_Gateway 2 12683
Protoss_Assimilator 1 4368
Protoss_Cybernetics_Core 1 5666
Protoss_Dragoon 10 15028
Protoss_Robotics_Facility 1 9733
Singularity_Charge 1 9698
Protoss_Nexus 2 16120
Protoss_Observatory 1 11391
Protoss_Observer 3 14575
16120
