Protoss_Gateway 2 8765
Protoss_Zealot 4 14177
Protoss_Nexus 1 8986
Protoss_Assimilator 2 12301
Protoss_Cybernetics_Core 1 8297
Protoss_Dragoon 6 15470
Protoss_Robotics_Facility 1 12595
Protoss_Shuttle 1 14007
Protoss_Robotics_Support_Bay 1 13321
Protoss_Stargate 1 14832
Protoss_Reaver 1 15565
Protoss_Observatory 1 14830
15565
