Protoss_Gateway 4 15585
Protoss_Assimilator 4 12539
Protoss_Zealot 3 7030
Protoss_Nexus 1 10135
Protoss_Cybernetics_Core 1 9980
Protoss_Dragoon 7 14791
Protoss_Robotics_Facility 1 15308
Singularity_Charge 1 14302
15585
