Protoss_Gateway 2 5174
Protoss_Zealot 8 9351
Protoss_Assimilator 1 7692
Protoss_Cybernetics_Core 1 9621
Protoss_Dragoon 7 14603
Protoss_Nexus 2 17469
Protoss_Robotics_Facility 1 15001
Singularity_Charge 1 13796
17469
