Protoss_Assimilator 1 3450
Protoss_Gateway 3 14028
Protoss_Cybernetics_Core 1 6084
Protoss_Dragoon 6 15812
Protoss_Citadel_of_Adun 1 9506
Protoss_Robotics_Facility 1 11003
Protoss_Templar_Archives 1 10949
Singularity_Charge 1 9751
Protoss_Dark_Templar 4 15563
Protoss_Shuttle 1 12497
Protoss_Observatory 1 12069
Protoss_Observer 1 14092
Protoss_Zealot 2 15248
15812
