Protoss_Gateway 4 15871
Protoss_Forge 1 5587
Protoss_Zealot 3 12743
Protoss_Photon_Cannon 2 8510
Protoss_Assimilator 1 8085
Protoss_Cybernetics_Core 1 9168
Protoss_Dragoon 8 15215
Protoss_Nexus 1 15693
Singularity_Charge 1 14009
15871
