Protoss_Gateway 1 4179
Protoss_Assimilator 1 4413
Protoss_Zealot 9 13158
Protoss_Forge 1 6833
Protoss_Photon_Cannon 2 8720
Protoss_Cybernetics_Core 1 11189
Protoss_Nexus 2 15655
Protoss_Robotics_Facility 1 13418
Protoss_Shuttle 1 14993
Protoss_Robotics_Support_Bay 1 14834
15655
