Protoss_Gateway 3 12216
Protoss_Assimilator 1 4495
Protoss_Cybernetics_Core 1 5885
Protoss_Dragoon 10 15502
Protoss_Robotics_Facility 1 8398
Protoss_Shuttle 1 9833
Protoss_Zealot 2 11086
Protoss_Robotics_Support_Bay 1 9809
Protoss_Reaver 1 11544
Protoss_Observatory 1 11314
Protoss_Observer 1 12435
Singularity_Charge 1 11797
15502
