Protoss_Gateway 4 15852
Protoss_Assimilator 1 4158
Protoss_Cybernetics_Core 1 5588
Protoss_Dragoon 11 15721
Protoss_Nexus 2 16432
Singularity_Charge 1 9496
Protoss_Robotics_Facility 1 11452
Protoss_Observatory 1 12341
Protoss_Observer 3 15488
16432
