Protoss_Gateway 2 8232
Protoss_Assimilator 1 4199
Protoss_Cybernetics_Core 1 5702
Protoss_Dragoon 8 15341
Protoss_Citadel_of_Adun 1 10079
Singularity_Charge 1 9634
Protoss_Zealot 2 10905
Protoss_Templar_Archives 1 11519
Protoss_Dark_Templar 2 12970
Protoss_Nexus 1 15066
15341
