Protoss_Gateway 2 13913
Protoss_Assimilator 1 4347
Protoss_Cybernetics_Core 1 5727
Protoss_Dragoon 7 15121
Protoss_Nexus 1 11589
Singularity_Charge 1 9660
Protoss_Robotics_Facility 1 12175
Protoss_Shuttle 1 13580
Protoss_Robotics_Support_Bay 1 12948
Protoss_Zealot 2 14633
Protoss_Observatory 1 14177
Protoss_Reaver 1 15138
15138
