Protoss_Gateway 1 4217
Protoss_Zealot 3 6951
Protoss_Assimilator 1 5486
Protoss_Cybernetics_Core 1 7262
Protoss_Robotics_Facility 1 9266
Protoss_Dragoon 6 14969
Protoss_Shuttle 1 10714
Protoss_Robotics_Support_Bay 1 10333
Protoss_Reaver 1 12272
Protoss_Observatory 1 12092
Protoss_Observer 1 13571
Singularity_Charge 1 12637
Protoss_Nexus 1 17203
17203
