Protoss_Gateway 4 12333
Protoss_Zealot 8 13378
Protoss_Assimilator 4 13971
Protoss_Forge 1 7654
Protoss_Photon_Cannon 2 12420
Protoss_Nexus 1 12300
Protoss_Cybernetics_Core 1 13167
Protoss_Dragoon 2 14536
14536
