Protoss_Gateway 7 14947
Protoss_Assimilator 2 6992
Protoss_Zealot 6 15514
Protoss_Cybernetics_Core 1 9867
Protoss_Dragoon 2 11147
Protoss_Citadel_of_Adun 1 11461
Protoss_Templar_Archives 1 12917
Protoss_Nexus 1 14692
Protoss_Dark_Templar 2 14117
15514
