Protoss_Gateway 2 15011
Protoss_Assimilator 1 4268
Protoss_Cybernetics_Core 1 5622
Protoss_Dragoon 6 14984
Protoss_Robotics_Facility 1 9551
Protoss_Shuttle 1 10957
Singularity_Charge 1 9572
Protoss_Robotics_Support_Bay 1 10362
Protoss_Zealot 2 12061
Protoss_Observatory 1 11526
Protoss_Reaver 1 12539
Protoss_Nexus 1 14976
Protoss_Observer 2 14672
15011
