Protoss_Nexus 3 15028
Protoss_Gateway 4 15977
Protoss_Assimilator 2 13716
Protoss_Zealot 1 6886
Protoss_Cybernetics_Core 1 7777
Protoss_Citadel_of_Adun 1 9279
Protoss_Dragoon 3 14817
Protoss_Forge 1 9812
Protoss_Templar_Archives 1 10846
Protoss_Photon_Cannon 1 11902
Protoss_Dark_Templar 1 12101
Protoss_Robotics_Facility 1 14764
15977
