Protoss_Gateway 3 15813
Protoss_Assimilator 1 4501
Protoss_Cybernetics_Core 1 5906
Protoss_Dragoon 11 15417
Protoss_Robotics_Facility 1 10807
Singularity_Charge 1 9975
Protoss_Observatory 1 11678
Protoss_Nexus 1 14453
Protoss_Observer 2 13656
15813
