Protoss_Gateway 1 4147
Protoss_Assimilator 1 4243
Protoss_Cybernetics_Core 1 5636
Protoss_Dragoon 7 15783
Protoss_Nexus 2 15807
Protoss_Robotics_Facility 1 10991
Singularity_Charge 1 9294
Protoss_Shuttle 1 12394
Protoss_Robotics_Support_Bay 1 11755
Protoss_Reaver 2 15749
Protoss_Observatory 1 13955
15807
