Protoss_Gateway 3 15266
Protoss_Zealot 4 8326
Protoss_Forge 1 5809
Protoss_Photon_Cannon 3 10683
Protoss_Assimilator 1 8610
Protoss_Cybernetics_Core 1 9871
Protoss_Dragoon 8 15745
Protoss_Citadel_of_Adun 1 15683
Singularity_Charge 1 14355
15745
