Protoss_Gateway 3 15847
Protoss_Zealot 2 6787
Protoss_Assimilator 1 5755
Protoss_Cybernetics_Core 1 6908
Protoss_Dragoon 5 12654
Protoss_Nexus 2 15959
Singularity_Charge 1 11387
Protoss_Robotics_Facility 1 13564
Protoss_Observatory 1 14482
15959
