Protoss_Gateway 2 4752
Protoss_Zealot 6 7735
Protoss_Forge 1 7395
Protoss_Photon_Cannon 3 11840
Protoss_Assimilator 2 15131
Protoss_Cybernetics_Core 1 10370
Protoss_Citadel_of_Adun 1 12409
Protoss_Nexus 1 15139
Protoss_Templar_Archives 1 14133
Protoss_Robotics_Facility 1 15888
Protoss_Dark_Templar 1 15493
15888
