Protoss_Gateway 1 4217
Protoss_Assimilator 1 4441
Protoss_Cybernetics_Core 1 5794
Protoss_Robotics_Facility 1 8035
Protoss_Dragoon 6 15276
Protoss_Shuttle 1 9429
Protoss_Robotics_Support_Bay 1 9809
Protoss_Zealot 2 12933
Protoss_Reaver 2 15943
Protoss_Observatory 1 11884
Protoss_Nexus 2 17212
Singularity_Charge 1 14120
17212
