Protoss_Gateway 3 15089
Protoss_Assimilator 1 4542
Protoss_Cybernetics_Core 1 6009
Protoss_Dragoon 8 15472
Protoss_Robotics_Facility 1 10637
Protoss_Nexus 2 13847
Singularity_Charge 1 9909
Protoss_Observatory 1 11375
Protoss_Observer 2 13990
15472
