Protoss_Gateway 3 15544
Protoss_Assimilator 1 4372
Protoss_Cybernetics_Core 1 5846
Protoss_Dragoon 8 15762
Protoss_Nexus 1 11460
Singularity_Charge 1 9771
Protoss_Robotics_Facility 1 11978
Protoss_Shuttle 1 13589
Protoss_Robotics_Support_Bay 1 13138
Protoss_Observatory 1 13654
Protoss_Reaver 1 15147
Protoss_Zealot 2 14642
15762
