Protoss_Gateway 2 13896
Protoss_Assimilator 1 4363
Protoss_Cybernetics_Core 1 6036
Protoss_Dragoon 8 15666
Protoss_Robotics_Facility 1 9774
Singularity_Charge 1 9809
Protoss_Shuttle 1 11268
Protoss_Robotics_Support_Bay 1 10752
Protoss_Reaver 2 15395
Protoss_Nexus 1 14560
Protoss_Observatory 1 13351
15666
