Protoss_Gateway 1 4164
Protoss_Assimilator 1 4363
Protoss_Cybernetics_Core 1 5790
Protoss_Robotics_Facility 1 8067
Protoss_Dragoon 3 14591
Protoss_Shuttle 2 15778
Protoss_Robotics_Support_Bay 1 9113
Protoss_Zealot 2 10703
Protoss_Reaver 2 14476
Protoss_Nexus 2 16474
Protoss_Observatory 1 12127
16474
