Protoss_Gateway 2 4937
Protoss_Zealot 8 12239
Protoss_Assimilator 1 7169
Protoss_Cybernetics_Core 1 9131
Protoss_Dragoon 6 14542
Protoss_Robotics_Facility 1 12946
Protoss_Observatory 1 13637
Singularity_Charge 1 13310
Protoss_Observer 1 15184
15184
