Protoss_Gateway 3 14674
Protoss_Assimilator 1 4252
Protoss_Cybernetics_Core 1 5746
Protoss_Dragoon 9 15370
Protoss_Nexus 2 17001
Protoss_Robotics_Facility 1 10705
Singularity_Charge 1 10040
Protoss_Observatory 1 11485
Protoss_Observer 2 15102
Protoss_Shuttle 1 13981
17001
