Protoss_Gateway 2 7411
Protoss_Zealot 3 15134
Protoss_Assimilator 2 14009
Protoss_Cybernetics_Core 1 6500
Protoss_Dragoon 7 12393
Protoss_Nexus 1 11817
Singularity_Charge 1 10433
Protoss_Robotics_Facility 1 12591
Protoss_Shuttle 1 14174
Protoss_Robotics_Support_Bay 1 13519
Protoss_Stargate 1 15079
Protoss_Observatory 1 14286
Protoss_Reaver 1 15732
15732
