Protoss_Gateway 2 15582
Protoss_Assimilator 1 4461
Protoss_Cybernetics_Core 1 5777
Protoss_Dragoon 7 14697
Protoss_Robotics_Facility 1 9816
Singularity_Charge 1 9777
Protoss_Observatory 1 10662
Protoss_Nexus 1 12918
Protoss_Observer 1 11701
Protoss_Shuttle 1 13059
Protoss_Robotics_Support_Bay 1 12559
Protoss_Reaver 1 14819
15582
