Protoss_Gateway 3 15585
Protoss_Assimilator 1 4256
Protoss_Cybernetics_Core 1 5996
Protoss_Dragoon 14 15680
Singularity_Charge 1 9721
Protoss_Nexus 1 14349
Protoss_Robotics_Facility 1 14482
15680
