Protoss_Gateway 4 15312
Protoss_Nexus 1 7732
Protoss_Zealot 2 8080
Protoss_Assimilator 1 6829
Protoss_Cybernetics_Core 1 8080
Protoss_Dragoon 8 14791
Protoss_Robotics_Facility 1 16147
16147
