Protoss_Gateway 2 12015
Protoss_Assimilator 1 4237
Protoss_Cybernetics_Core 1 5654
Protoss_Dragoon 10 15156
Protoss_Nexus 1 11974
Protoss_Robotics_Facility 1 11705
Singularity_Charge 1 9818
Protoss_Shuttle 1 13264
Protoss_Observatory 1 12730
Protoss_Observer 1 14107
Protoss_Robotics_Support_Bay 1 14180
15156
