Protoss_Gateway 2 11560
Protoss_Zealot 3 7477
Protoss_Assimilator 2 11802
Protoss_Cybernetics_Core 1 7722
Protoss_Nexus 1 10937
Protoss_Dragoon 8 15174
Protoss_Robotics_Facility 1 13475
Singularity_Charge 1 12745
Protoss_Robotics_Support_Bay 1 14284
Protoss_Observatory 1 14554
15174
