Protoss_Gateway 2 12105
Protoss_Assimilator 1 4589
Protoss_Zealot 2 6646
Protoss_Cybernetics_Core 1 6889
Protoss_Dragoon 4 14729
Protoss_Nexus 2 17406
Protoss_Citadel_of_Adun 1 10833
Protoss_Robotics_Facility 1 11976
Protoss_Templar_Archives 1 12421
Protoss_Shuttle 1 13404
Protoss_Dark_Templar 3 14723
Protoss_Observatory 1 13762
Protoss_Observer 1 14797
17406
