Protoss_Gateway 3 14857
Protoss_Assimilator 1 4524
Protoss_Cybernetics_Core 1 5949
Protoss_Zealot 3 14209
Protoss_Dragoon 8 15610
Protoss_Robotics_Facility 1 10009
Protoss_Nexus 1 12513
Singularity_Charge 1 9748
Protoss_Shuttle 1 11549
Protoss_Observatory 1 11054
Protoss_Robotics_Support_Bay 1 12288
Protoss_Observer 2 15052
Protoss_Reaver 1 14227
15610
