Protoss_Gateway 3 12031
Protoss_Zealot 6 9536
Protoss_Shield_Battery 1 6199
Protoss_Assimilator 1 8088
Protoss_Cybernetics_Core 1 9892
Protoss_Dragoon 9 14751
Singularity_Charge 1 13794
Protoss_Robotics_Facility 1 16121
16121
