Protoss_Gateway 3 15538
Protoss_Assimilator 1 4458
Protoss_Cybernetics_Core 1 5623
Protoss_Dragoon 8 14997
Protoss_Robotics_Facility 1 9781
Singularity_Charge 1 9702
Protoss_Observatory 1 10516
Protoss_Nexus 2 15554
Protoss_Observer 3 14224
15554
