Protoss_Gateway 4 14840
Protoss_Assimilator 2 5165
Protoss_Cybernetics_Core 1 6501
Protoss_Dragoon 4 15355
Protoss_Citadel_of_Adun 1 9106
Protoss_Templar_Archives 1 10884
Protoss_Zealot 1 10422
Singularity_Charge 1 10544
Protoss_Dark_Templar 4 13526
Protoss_Nexus 1 14728
Protoss_Robotics_Facility 1 15850
15850
