Protoss_Gateway 3 14307
Protoss_Assimilator 2 4981
Protoss_Cybernetics_Core 1 6204
Protoss_Dragoon 10 15762
Protoss_Nexus 2 14178
Singularity_Charge 1 10199
Protoss_Robotics_Facility 1 16252
16252
