Protoss_Gateway 4 15049
Protoss_Assimilator 1 4400
Protoss_Cybernetics_Core 1 5714
Protoss_Dragoon 9 15431
Protoss_Nexus 2 15950
Singularity_Charge 1 9967
Protoss_Robotics_Facility 1 11998
Protoss_Observatory 1 12726
Protoss_Observer 2 14707
15950
