Protoss_Gateway 2 12734
Protoss_Assimilator 1 4431
Protoss_Zealot 2 6181
Protoss_Cybernetics_Core 1 7439
Protoss_Dragoon 8 15083
Protoss_Nexus 1 12268
Protoss_Robotics_Facility 1 12311
Singularity_Charge 1 11662
Protoss_Observatory 1 13174
Protoss_Observer 2 15175
15175
