Protoss_Gateway 4 14884
Protoss_Zealot 4 8051
Protoss_Assimilator 1 5247
Protoss_Cybernetics_Core 1 7275
Protoss_Dragoon 7 15496
Protoss_Robotics_Facility 1 11719
Singularity_Charge 1 11249
Protoss_Nexus 1 14241
Protoss_Observatory 1 13124
Protoss_Observer 2 15222
15496
