Protoss_Gateway 2 11458
Protoss_Assimilator 1 4542
Protoss_Cybernetics_Core 1 5875
Protoss_Dragoon 9 15475
Protoss_Robotics_Facility 1 10381
Singularity_Charge 1 10509
Protoss_Observatory 1 11256
Protoss_Nexus 1 14539
Protoss_Observer 3 15361
15475
