Protoss_Gateway 2 13912
Protoss_Assimilator 1 5268
Protoss_Cybernetics_Core 1 5837
Protoss_Dragoon 6 15405
Protoss_Nexus 2 16764
Protoss_Robotics_Facility 1 10661
Protoss_Shuttle 1 12064
Protoss_Robotics_Support_Bay 1 11717
Protoss_Zealot 2 13053
Protoss_Reaver 1 13733
Protoss_Observatory 1 13356
Protoss_Observer 2 15438
16764
