Protoss_Gateway 5 15336
Protoss_Assimilator 1 4193
Protoss_Cybernetics_Core 1 5708
Protoss_Zealot 1 5841
Protoss_Dragoon 7 15452
Protoss_Nexus 2 14787
Singularity_Charge 1 9780
Protoss_Robotics_Facility 1 11770
Protoss_Observatory 1 12756
Protoss_Observer 2 14762
Protoss_Citadel_of_Adun 1 15560
15560
