Protoss_Gateway 2 8489
Protoss_Assimilator 3 7185
Protoss_Cybernetics_Core 1 6349
Protoss_Dragoon 7 11893
Protoss_Robotics_Facility 1 12003
Singularity_Charge 1 10128
Protoss_Shuttle 1 13448
Protoss_Robotics_Support_Bay 1 13472
Protoss_Zealot 2 14121
Protoss_Reaver 1 15211
Protoss_Observatory 1 14886
Protoss_Nexus 1 17264
17264
