Protoss_Gateway 2 14026
Protoss_Assimilator 1 4242
Protoss_Cybernetics_Core 1 5645
Protoss_Robotics_Facility 1 7767
Protoss_Dragoon 8 15458
Protoss_Observatory 1 8690
Protoss_Observer 1 10056
Protoss_Nexus 1 13363
Singularity_Charge 1 11908
Protoss_Shuttle 1 13647
Protoss_Robotics_Support_Bay 1 13253
Protoss_Zealot 2 15152
Protoss_Reaver 1 15205
15458
