Protoss_Gateway 2 4799
Protoss_Zealot 8 10597
Protoss_Forge 1 6896
Protoss_Photon_Cannon 3 12626
Protoss_Assimilator 1 9759
Protoss_Cybernetics_Core 1 11729
Protoss_Dragoon 1 13097
13097
