Protoss_Gateway 1 4126
Protoss_Assimilator 2 12769
Protoss_Cybernetics_Core 1 5803
Protoss_Dragoon 8 14886
Protoss_Nexus 1 11875
Singularity_Charge 1 9877
Protoss_Robotics_Facility 1 12136
Protoss_Shuttle 1 13530
Protoss_Robotics_Support_Bay 1 13435
Protoss_Reaver 1 15161
Protoss_Stargate 2 16096
Protoss_Observatory 2 15332
16096
