Protoss_Gateway 2 8401
Protoss_Assimilator 1 4543
Protoss_Cybernetics_Core 1 6014
Protoss_Dragoon 10 14826
Singularity_Charge 1 9792
Protoss_Nexus 1 13597
Protoss_Citadel_of_Adun 1 12595
Protoss_Templar_Archives 1 15187
Protoss_Robotics_Facility 1 15758
15758
