Protoss_Gateway 2 8029
Protoss_Assimilator 1 4271
Protoss_Cybernetics_Core 1 5988
Protoss_Dragoon 10 14776
Protoss_Nexus 1 11238
Singularity_Charge 1 9701
Protoss_Zealot 2 10995
Protoss_Robotics_Facility 1 14117
Protoss_Shuttle 1 15681
Protoss_Robotics_Support_Bay 1 15108
15681
