Protoss_Gateway 2 10059
Protoss_Zealot 2 8537
Protoss_Nexus 1 8817
Protoss_Assimilator 2 11347
Protoss_Cybernetics_Core 1 8497
Protoss_Dragoon 6 14770
Protoss_Robotics_Facility 1 11416
Protoss_Shuttle 1 12833
Protoss_Robotics_Support_Bay 1 12334
Protoss_Reaver 1 14994
Singularity_Charge 1 14240
14994
