Protoss_Nexus 1 6892
Protoss_Gateway 2 7589
Protoss_Assimilator 2 11550
Protoss_Cybernetics_Core 1 7305
Protoss_Zealot 1 7776
Protoss_Dragoon 10 14536
Protoss_Robotics_Facility 1 12468
Singularity_Charge 1 10968
Protoss_Observatory 1 13172
Protoss_Citadel_of_Adun 1 13899
Protoss_Observer 2 15105
Protoss_Templar_Archives 1 15342
15342
