Protoss_Assimilator 3 12274
Protoss_Gateway 2 11309
Protoss_Zealot 3 7726
Protoss_Nexus 2 17177
Protoss_Forge 1 8423
Protoss_Photon_Cannon 1 9671
Protoss_Cybernetics_Core 1 10373
Protoss_Dragoon 5 14600
Protoss_Robotics_Facility 1 12862
Protoss_Shuttle 1 14273
Protoss_Robotics_Support_Bay 1 13734
Protoss_Reaver 1 15987
17177
