Protoss_Gateway 2 10237
Protoss_Assimilator 1 4400
Protoss_Cybernetics_Core 1 5783
Protoss_Dragoon 9 15663
Protoss_Robotics_Facility 1 9783
Singularity_Charge 1 9783
Protoss_Observatory 1 10516
Protoss_Observer 1 11552
Protoss_Shuttle 1 12909
Protoss_Zealot 4 13416
Protoss_Nexus 1 16544
Protoss_Citadel_of_Adun 1 15747
16544
