Protoss_Nexus 1 6772
Protoss_Gateway 3 14200
Protoss_Assimilator 1 5768
Protoss_Cybernetics_Core 1 7290
Protoss_Zealot 2 15190
Protoss_Dragoon 10 15803
Singularity_Charge 1 12051
Protoss_Robotics_Facility 1 14009
Protoss_Shuttle 1 15418
Protoss_Observatory 1 14818
15803
