Protoss_Gateway 2 4723
Protoss_Zealot 6 7647
Protoss_Assimilator 1 6370
Protoss_Cybernetics_Core 1 7471
Protoss_Dragoon 8 15010
Protoss_Citadel_of_Adun 1 12987
Protoss_Templar_Archives 1 14739
Singularity_Charge 1 14188
15010
