Protoss_Gateway 3 13332
Protoss_Assimilator 1 4512
Protoss_Cybernetics_Core 1 6083
Protoss_Dragoon 10 14978
Singularity_Charge 1 10029
Protoss_Nexus 1 13537
Protoss_Robotics_Facility 1 13964
Protoss_Zealot 1 14762
Protoss_Observatory 1 14927
14978
