Protoss_Gateway 2 12077
Protoss_Zealot 2 6962
Protoss_Assimilator 1 5575
Protoss_Cybernetics_Core 1 6778
Protoss_Dragoon 9 14998
Protoss_Robotics_Facility 1 11385
Singularity_Charge 1 11112
Protoss_Observatory 1 12171
Protoss_Observer 2 14066
Protoss_Nexus 1 17004
Protoss_Shuttle 1 16021
17004
