Protoss_Gateway 2 12188
Protoss_Assimilator 1 4373
Protoss_Cybernetics_Core 1 5812
Protoss_Dragoon 9 14480
Protoss_Nexus 1 11618
Protoss_Robotics_Facility 1 11506
Singularity_Charge 1 9897
Protoss_Robotics_Support_Bay 1 12373
Protoss_Shuttle 1 13281
Protoss_Reaver 1 15536
15536
