Protoss_Nexus 2 15210
Protoss_Gateway 3 12067
Protoss_Assimilator 1 5922
Protoss_Cybernetics_Core 1 7678
Protoss_Zealot 1 7899
Protoss_Dragoon 10 15578
Protoss_Robotics_Facility 1 11556
Singularity_Charge 1 11454
Protoss_Observatory 1 12442
Protoss_Observer 2 15055
15578
