Protoss_Gateway 1 4208
Protoss_Assimilator 2 14647
Protoss_Cybernetics_Core 1 5920
Protoss_Zealot 1 5721
Protoss_Dragoon 6 15177
Protoss_Nexus 1 12040
Singularity_Charge 1 9970
Protoss_Robotics_Facility 1 12185
Protoss_Shuttle 1 13586
Protoss_Robotics_Support_Bay 1 13185
Protoss_Reaver 1 15144
Protoss_Stargate 1 15265
Protoss_Observatory 1 14870
15265
