Protoss_Gateway 2 6308
Protoss_Zealot 2 7322
Protoss_Assimilator 1 5904
Protoss_Cybernetics_Core 1 7747
Protoss_Dragoon 6 14887
Protoss_Nexus 2 16015
Singularity_Charge 1 11849
Protoss_Robotics_Facility 1 13908
Protoss_Shuttle 1 15605
Protoss_Observatory 1 15114
16015
