Protoss_Gateway 3 15087
Protoss_Assimilator 2 13515
Protoss_Cybernetics_Core 1 5688
Protoss_Zealot 1 5666
Protoss_Dragoon 4 10705
Protoss_Nexus 2 13890
Singularity_Charge 1 9944
Protoss_Citadel_of_Adun 1 11528
Protoss_Templar_Archives 1 12971
Protoss_Dark_Templar 2 14840
15087
