Protoss_Gateway 3 15405
Protoss_Assimilator 1 4514
Protoss_Cybernetics_Core 1 5796
Protoss_Dragoon 2 9455
Protoss_Citadel_of_Adun 1 7679
Protoss_Templar_Archives 1 9200
Protoss_Dark_Templar 4 11726
Protoss_Nexus 1 13843
Protoss_Robotics_Facility 1 13972
Protoss_Zealot 2 13843
Protoss_Shuttle 1 15383
Protoss_Observatory 1 14832
15405
