Protoss_Gateway 4 15465
Protoss_Assimilator 1 4334
Protoss_Zealot 2 6670
Protoss_Cybernetics_Core 1 6699
Protoss_Dragoon 8 13435
Protoss_Citadel_of_Adun 1 11775
Singularity_Charge 1 11808
Protoss_Templar_Archives 1 13397
Protoss_Nexus 1 15653
Protoss_Dark_Templar 4 15800
15800
