Protoss_Gateway 1 4286
Protoss_Assimilator 1 4517
Protoss_Cybernetics_Core 1 5942
Protoss_Zealot 1 5733
Protoss_Dragoon 6 13514
Protoss_Robotics_Facility 1 10040
Protoss_Observatory 1 10733
Singularity_Charge 1 10190
Protoss_Nexus 1 13489
Protoss_Observer 2 12752
Protoss_Shuttle 1 14109
Protoss_Robotics_Support_Bay 1 14150
Protoss_Reaver 1 15896
15896
