Protoss_Gateway 2 11052
Protoss_Assimilator 1 4366
Protoss_Cybernetics_Core 1 5856
Protoss_Dragoon 9 15177
Protoss_Robotics_Facility 1 11367
Singularity_Charge 1 9730
Protoss_Observatory 1 12274
Protoss_Nexus 1 14643
Protoss_Observer 2 15111
Protoss_Zealot 2 13603
15177
