Protoss_Gateway 2 9424
Protoss_Assimilator 1 4350
Protoss_Zealot 2 6775
Protoss_Cybernetics_Core 1 6795
Protoss_Dragoon 8 14925
Protoss_Nexus 2 17171
Singularity_Charge 1 11056
Protoss_Robotics_Facility 1 13671
Protoss_Shuttle 1 15225
Protoss_Observatory 1 14818
17171
