Protoss_Gateway 4 15809
Protoss_Assimilator 1 4306
Protoss_Cybernetics_Core 1 5657
Protoss_Dragoon 10 15092
Singularity_Charge 1 9809
Protoss_Nexus 1 12816
Protoss_Robotics_Facility 1 13001
Protoss_Observatory 1 13709
Protoss_Observer 1 14721
15809
