Protoss_Gateway 1 4141
Protoss_Assimilator 1 4180
Protoss_Cybernetics_Core 1 5589
Protoss_Zealot 1 5590
Protoss_Dragoon 8 15271
Protoss_Robotics_Facility 1 9818
Singularity_Charge 1 9818
Protoss_Shuttle 1 11265
Protoss_Robotics_Support_Bay 1 10983
Protoss_Reaver 2 15653
Protoss_Nexus 1 16977
16977
