Protoss_Gateway 2 9348
Protoss_Assimilator 1 4395
Protoss_Cybernetics_Core 1 5748
Protoss_Dragoon 9 12961
Protoss_Robotics_Facility 1 10448
Singularity_Charge 1 9839
Protoss_Shuttle 1 12131
Protoss_Robotics_Support_Bay 1 11501
Protoss_Reaver 1 13932
Protoss_Nexus 1 16386
Protoss_Zealot 2 14724
Protoss_Observatory 1 14905
16386
