Protoss_Gateway 2 15151
Protoss_Assimilator 1 4177
Protoss_Cybernetics_Core 1 5796
Protoss_Dragoon 7 15742
Protoss_Robotics_Facility 1 8348
Protoss_Observatory 1 9074
Protoss_Observer 2 10992
Protoss_Nexus 1 13781
Singularity_Charge 1 11504
Protoss_Shuttle 1 12997
Protoss_Robotics_Support_Bay 1 12761
Protoss_Reaver 1 14620
15742
