Protoss_Gateway 3 14769
Protoss_Assimilator 2 4949
Protoss_Cybernetics_Core 1 6405
Protoss_Zealot 1 6763
Protoss_Dragoon 5 15423
Protoss_Shield_Battery 1 9205
Protoss_Citadel_of_Adun 1 11088
Singularity_Charge 1 10117
Protoss_Nexus 1 13638
Protoss_Templar_Archives 1 12737
Protoss_Dark_Templar 2 13980
15423
