Protoss_Gateway 2 5039
Protoss_Zealot 7 13937
Protoss_Assimilator 1 7455
Protoss_Cybernetics_Core 1 8868
Protoss_Dragoon 8 15531
Protoss_Citadel_of_Adun 1 13714
Protoss_Forge 1 14613
Singularity_Charge 1 13725
Protoss_Templar_Archives 1 15577
15577
