Protoss_Gateway 3 13578
Protoss_Assimilator 3 11581
Protoss_Zealot 7 12263
Protoss_Nexus 1 10677
Protoss_Cybernetics_Core 1 9961
Protoss_Citadel_of_Adun 1 12189
Protoss_Dragoon 4 14252
Protoss_Templar_Archives 1 13925
Protoss_Dark_Templar 3 15352
15352
