Protoss_Nexus 1 7247
Protoss_Gateway 2 7970
Protoss_Assimilator 1 6181
Protoss_Cybernetics_Core 1 7749
Protoss_Zealot 2 15315
Protoss_Dragoon 9 15625
Protoss_Robotics_Facility 1 15174
15625
