Protoss_Nexus 2 16617
Protoss_Gateway 2 7735
Protoss_Assimilator 2 13208
Protoss_Cybernetics_Core 1 7236
Protoss_Zealot 1 7934
Protoss_Dragoon 10 15077
Protoss_Robotics_Facility 1 11725
Protoss_Observatory 1 12865
Protoss_Shuttle 1 13802
Protoss_Robotics_Support_Bay 1 13639
Protoss_Observer 1 14753
Singularity_Charge 1 14279
16617
