Protoss_Gateway 4 15510
Protoss_Assimilator 1 4179
Protoss_Cybernetics_Core 1 5644
Protoss_Zealot 1 6105
Protoss_Dragoon 4 10541
Protoss_Citadel_of_Adun 1 9254
Protoss_Templar_Archives 1 10723
Singularity_Charge 1 9926
Protoss_Dark_Templar 4 14761
Protoss_Nexus 1 13705
15510
