Protoss_Gateway 3 15907
Protoss_Assimilator 1 4372
Protoss_Cybernetics_Core 1 5777
Protoss_Dragoon 10 15669
Protoss_Robotics_Facility 1 9841
Singularity_Charge 1 9783
Protoss_Observatory 1 10946
Protoss_Observer 2 12842
Protoss_Nexus 2 16263
16263
