Protoss_Gateway 2 15018
Protoss_Assimilator 1 4420
Protoss_Cybernetics_Core 1 5840
Protoss_Dragoon 7 15339
Protoss_Robotics_Facility 1 8436
Protoss_Shuttle 1 9896
Protoss_Robotics_Support_Bay 1 9396
Protoss_Reaver 2 13284
Protoss_Observatory 1 12549
Singularity_Charge 1 12989
Protoss_Observer 1 14108
15339
