Protoss_Gateway 2 10529
Protoss_Assimilator 1 4530
Protoss_Zealot 3 13752
Protoss_Cybernetics_Core 1 6904
Protoss_Dragoon 9 14872
Protoss_Robotics_Facility 1 10511
Protoss_Observatory 1 11268
Singularity_Charge 1 10626
Protoss_Observer 1 12342
Protoss_Shuttle 1 14165
Protoss_Nexus 1 17279
17279
