Protoss_Gateway 1 4337
Protoss_Assimilator 2 13117
Protoss_Cybernetics_Core 1 5786
Protoss_Dragoon 8 15753
Protoss_Nexus 1 12581
Singularity_Charge 1 9961
Protoss_Stargate 2 14927
Protoss_Fleet_Beacon 1 13149
Protoss_Carrier 1 16532
16532
