Protoss_Gateway 2 5575
Protoss_Assimilator 3 13224
Protoss_Zealot 12 14862
Protoss_Nexus 1 10692
Protoss_Forge 1 9187
Protoss_Photon_Cannon 2 10675
Protoss_Cybernetics_Core 1 12298
Protoss_Citadel_of_Adun 1 13782
Protoss_Robotics_Facility 1 15095
Protoss_Templar_Archives 1 15675
15675
