Protoss_Gateway 2 11958
Protoss_Assimilator 2 12699
Protoss_Cybernetics_Core 1 6162
Protoss_Dragoon 7 15045
Protoss_Nexus 1 11493
Protoss_Citadel_of_Adun 1 10865
Singularity_Charge 1 10076
Protoss_Templar_Archives 1 12482
Protoss_Dark_Templar 4 15288
Protoss_Robotics_Facility 1 15137
15288
