Protoss_Gateway 3 13183
Protoss_Assimilator 1 4542
Protoss_Cybernetics_Core 1 5813
Protoss_Dragoon 11 15768
Protoss_Robotics_Facility 1 9832
Protoss_Nexus 1 12483
Singularity_Charge 1 9830
Protoss_Observatory 1 10610
Protoss_Observer 3 13556
15768
