Protoss_Nexus 2 16695
Protoss_Gateway 3 12049
Protoss_Assimilator 1 5771
Protoss_Cybernetics_Core 1 7372
Protoss_Zealot 6 15476
Protoss_Dragoon 11 15701
Protoss_Robotics_Facility 1 11398
Singularity_Charge 1 11419
Protoss_Observatory 1 12196
Protoss_Shuttle 1 13293
Protoss_Robotics_Support_Bay 1 13040
Protoss_Observer 1 14610
16695
