Protoss_Gateway 2 10202
Protoss_Zealot 4 15023
Protoss_Assimilator 1 5619
Protoss_Cybernetics_Core 1 6801
Protoss_Dragoon 5 12824
Protoss_Nexus 1 13489
Singularity_Charge 1 11159
Protoss_Robotics_Facility 1 13115
Protoss_Shuttle 1 14543
Protoss_Robotics_Support_Bay 1 14466
Protoss_Observatory 1 14650
Protoss_Reaver 1 16250
16250
