Protoss_Gateway 3 15898
Protoss_Assimilator 1 4395
Protoss_Cybernetics_Core 1 5753
Protoss_Dragoon 11 14919
Protoss_Nexus 2 16181
Singularity_Charge 1 10023
Protoss_Robotics_Facility 1 14660
16181
