Protoss_Gateway 4 15734
Protoss_Assimilator 1 4135
Protoss_Cybernetics_Core 1 5649
Protoss_Dragoon 9 14738
Singularity_Charge 1 9417
Protoss_Nexus 2 14484
Protoss_Robotics_Facility 1 12671
Protoss_Observatory 1 13421
Protoss_Observer 1 14472
15734
