Protoss_Assimilator 2 4940
Protoss_Gateway 4 15362
Protoss_Cybernetics_Core 1 6391
Protoss_Zealot 1 6462
Protoss_Dragoon 6 14270
Protoss_Nexus 2 14171
Singularity_Charge 1 10254
Protoss_Citadel_of_Adun 1 13654
Protoss_Templar_Archives 1 15135
15362
