Protoss_Nexus 1 6807
Protoss_Gateway 4 14146
Protoss_Assimilator 2 11680
Protoss_Cybernetics_Core 1 7444
Protoss_Zealot 1 7949
Protoss_Dragoon 10 14711
Protoss_Robotics_Facility 1 12976
Singularity_Charge 1 12268
Protoss_Shuttle 1 14367
Protoss_Robotics_Support_Bay 1 13891
Protoss_Reaver 1 16130
16130
