Protoss_Assimilator 2 5016
Protoss_Gateway 4 15260
Protoss_Cybernetics_Core 1 6511
Protoss_Dragoon 9 15739
Protoss_Nexus 2 14005
Singularity_Charge 1 10427
Protoss_Robotics_Facility 1 14050
Protoss_Observatory 1 15004
15739
