Protoss_Gateway 2 9226
Protoss_Assimilator 1 4293
Protoss_Cybernetics_Core 1 5729
Protoss_Dragoon 6 12415
Protoss_Robotics_Facility 1 10786
Singularity_Charge 1 10033
Protoss_Zealot 4 15097
Protoss_Shuttle 1 13357
Protoss_Robotics_Support_Bay 1 13084
Protoss_Observatory 1 13179
Protoss_Citadel_of_Adun 1 14313
Protoss_Reaver 1 14915
15097
