Protoss_Gateway 3 13135
Protoss_Assimilator 2 14650
Protoss_Cybernetics_Core 1 5622
Protoss_Dragoon 7 14483
Protoss_Citadel_of_Adun 1 8794
Protoss_Templar_Archives 1 10394
Protoss_Nexus 2 17238
Singularity_Charge 1 9953
Protoss_Dark_Templar 1 11673
Protoss_Robotics_Facility 1 13064
Protoss_Observatory 1 13899
Protoss_Observer 1 14944
17238
