Protoss_Gateway 2 9476
Protoss_Assimilator 1 4469
Protoss_Zealot 3 7311
Protoss_Cybernetics_Core 1 7128
Protoss_Dragoon 8 15320
Protoss_Nexus 2 16470
Singularity_Charge 1 11053
Protoss_Robotics_Facility 1 13107
Protoss_Observatory 1 13801
Protoss_Observer 1 14812
16470
