Protoss_Gateway 3 15776
Protoss_Assimilator 1 4647
Protoss_Cybernetics_Core 1 5933
Protoss_Dragoon 9 15263
Protoss_Robotics_Facility 1 8802
Protoss_Observatory 1 10127
Protoss_Observer 2 12251
Singularity_Charge 1 11870
Protoss_Nexus 1 15991
15991
