Protoss_Gateway 2 10308
Protoss_Assimilator 1 4564
Protoss_Cybernetics_Core 1 6402
Protoss_Dragoon 8 14180
Protoss_Robotics_Facility 1 10226
Singularity_Charge 1 10077
Protoss_Observatory 1 11496
Protoss_Observer 2 13395
Protoss_Shuttle 1 14753
Protoss_Zealot 2 15053
15053
