Protoss_Gateway 3 13163
Protoss_Assimilator 1 4431
Protoss_Cybernetics_Core 1 5844
Protoss_Dragoon 8 13324
Protoss_Robotics_Facility 1 9756
Singularity_Charge 1 9979
Protoss_Observatory 1 10819
Protoss_Observer 1 12111
Protoss_Citadel_of_Adun 1 12901
Protoss_Zealot 4 14496
Protoss_Shuttle 1 15634
15634
