Protoss_Gateway 2 13425
Protoss_Assimilator 1 4496
Protoss_Cybernetics_Core 1 5985
Protoss_Zealot 1 5809
Protoss_Dragoon 9 15736
Protoss_Robotics_Facility 1 11040
Singularity_Charge 1 10117
Protoss_Observatory 1 12118
Protoss_Nexus 1 14384
Protoss_Observer 2 14048
15736
