Protoss_Gateway 2 10776
Protoss_Assimilator 1 4455
Protoss_Cybernetics_Core 1 6096
Protoss_Zealot 1 6122
Protoss_Dragoon 6 12010
Protoss_Citadel_of_Adun 1 9948
Protoss_Templar_Archives 1 11537
Singularity_Charge 1 10140
Protoss_Dark_Templar 4 15443
Protoss_Nexus 1 15987
Protoss_Robotics_Facility 1 15461
15987
