Protoss_Gateway 4 15406
Protoss_Assimilator 1 4306
Protoss_Cybernetics_Core 1 5960
Protoss_Dragoon 11 15658
Protoss_Robotics_Facility 1 9338
Protoss_Observatory 1 10269
Singularity_Charge 1 10048
Protoss_Observer 3 13354
Protoss_Nexus 1 15571
15658
