Protoss_Gateway 2 11051
Protoss_Assimilator 2 13622
Protoss_Cybernetics_Core 1 6851
Protoss_Dragoon 3 11068
Protoss_Citadel_of_Adun 1 9456
Protoss_Templar_Archives 1 10905
Protoss_Dark_Templar 4 15379
Protoss_Nexus 1 14702
Protoss_Stargate 1 15533
15533
