Protoss_Gateway 2 9283
Protoss_Assimilator 1 4444
Protoss_Cybernetics_Core 1 5669
Protoss_Dragoon 9 13626
Protoss_Nexus 2 17465
Singularity_Charge 1 9713
Protoss_Robotics_Facility 1 12319
Protoss_Shuttle 1 13776
Protoss_Robotics_Support_Bay 1 13776
Protoss_Reaver 1 15550
Protoss_Observatory 1 14829
17465
