Protoss_Gateway 3 16006
Protoss_Assimilator 1 4552
Protoss_Zealot 2 6084
Protoss_Cybernetics_Core 1 6192
Protoss_Dragoon 8 15610
Protoss_Nexus 1 12742
Singularity_Charge 1 11094
Protoss_Citadel_of_Adun 1 15059
16006
