Protoss_Gateway 2 8591
Protoss_Assimilator 1 4600
Protoss_Cybernetics_Core 1 5993
Protoss_Robotics_Facility 1 8190
Protoss_Shuttle 1 9765
Protoss_Dragoon 6 13005
Protoss_Observatory 1 10146
Protoss_Observer 2 12375
Protoss_Forge 1 11544
Singularity_Charge 1 11380
Protoss_Photon_Cannon 1 13254
Protoss_Nexus 1 16923
16923
