Protoss_Gateway 2 12552
Protoss_Assimilator 1 4360
Protoss_Cybernetics_Core 1 5745
Protoss_Dragoon 9 15335
Protoss_Nexus 2 13430
Singularity_Charge 1 9634
Protoss_Robotics_Facility 1 14338
Protoss_Shuttle 1 15757
Protoss_Robotics_Support_Bay 1 15057
15757
