Protoss_Gateway 2 14876
Protoss_Zealot 3 7240
Protoss_Assimilator 1 6084
Protoss_Cybernetics_Core 1 7543
Protoss_Dragoon 6 15376
Protoss_Nexus 1 12031
Protoss_Robotics_Facility 1 12019
Singularity_Charge 1 11653
Protoss_Shuttle 1 13460
Protoss_Robotics_Support_Bay 1 13380
Protoss_Reaver 1 15147
15376
