Protoss_Gateway 2 10128
Protoss_Assimilator 1 4414
Protoss_Cybernetics_Core 1 5810
Protoss_Dragoon 11 15156
Protoss_Robotics_Facility 1 10181
Singularity_Charge 1 9841
Protoss_Observatory 1 10939
Protoss_Observer 2 13208
Protoss_Nexus 1 14752
Protoss_Shuttle 1 14566
Protoss_Robotics_Support_Bay 1 14922
Protoss_Zealot 1 15400
15400
