Protoss_Gateway 2 14557
Protoss_Assimilator 1 4483
Protoss_Cybernetics_Core 1 5944
Protoss_Dragoon 4 15332
Protoss_Robotics_Facility 1 8808
Protoss_Shuttle 1 10202
Protoss_Robotics_Support_Bay 1 9598
Protoss_Zealot 2 11224
Protoss_Reaver 1 11760
Protoss_Observatory 1 11318
Protoss_Observer 2 13466
Protoss_Nexus 1 15173
15332
