Protoss_Gateway 2 12724
Protoss_Assimilator 1 4549
Protoss_Cybernetics_Core 1 6017
Protoss_Zealot 1 5923
Protoss_Robotics_Facility 1 8366
Protoss_Dragoon 9 15748
Protoss_Nexus 1 12758
Protoss_Observatory 1 10924
Protoss_Observer 2 12816
Protoss_Shuttle 1 14174
Protoss_Robotics_Support_Bay 1 13460
Singularity_Charge 1 13971
15748
