Protoss_Gateway 3 11850
Protoss_Assimilator 1 4191
Protoss_Cybernetics_Core 1 5768
Protoss_Dragoon 9 14773
Protoss_Citadel_of_Adun 1 9801
Protoss_Robotics_Facility 1 10734
Singularity_Charge 1 10172
Protoss_Observatory 1 11448
Protoss_Observer 3 14385
Protoss_Nexus 1 16822
16822
