Protoss_Gateway 2 13536
Protoss_Assimilator 1 4299
Protoss_Cybernetics_Core 1 5840
Protoss_Dragoon 8 14943
Protoss_Robotics_Facility 1 9847
Protoss_Nexus 2 15218
Protoss_Observatory 1 10655
Singularity_Charge 1 9961
Protoss_Observer 2 12573
Protoss_Shuttle 1 14288
Protoss_Robotics_Support_Bay 1 14112
Protoss_Reaver 1 15864
Protoss_Zealot 1 15351
15864
