Protoss_Gateway 1 4107
Protoss_Assimilator 1 4337
Protoss_Cybernetics_Core 1 5569
Protoss_Dragoon 4 13447
Protoss_Robotics_Facility 2 13069
Protoss_Shuttle 2 13489
Protoss_Robotics_Support_Bay 1 9789
Protoss_Zealot 2 12160
Protoss_Reaver 3 15694
Gravitic_Drive 1 13523
15694
