Protoss_Gateway 2 10365
Protoss_Assimilator 1 4650
Protoss_Cybernetics_Core 1 5955
Protoss_Dragoon 9 15680
Protoss_Citadel_of_Adun 1 8933
Protoss_Templar_Archives 1 10580
Protoss_Zealot 1 10875
Singularity_Charge 1 10011
Protoss_Dark_Templar 2 11995
Protoss_Nexus 1 15469
Protoss_Robotics_Facility 1 15731
15731
