Protoss_Gateway 4 16003
Protoss_Assimilator 1 4381
Protoss_Cybernetics_Core 1 5753
Protoss_Dragoon 8 15007
Protoss_Robotics_Facility 1 9646
Protoss_Observatory 1 10446
Singularity_Charge 1 9771
Protoss_Observer 2 12444
Protoss_Nexus 1 14253
Protoss_Shuttle 1 13442
Protoss_Robotics_Support_Bay 1 13251
Protoss_Reaver 1 15000
Protoss_Zealot 2 15418
16003
