Protoss_Gateway 3 15588
Protoss_Assimilator 1 4618
Protoss_Cybernetics_Core 1 5774
Protoss_Dragoon 6 15209
Protoss_Citadel_of_Adun 1 9017
Protoss_Templar_Archives 1 10509
Singularity_Charge 1 9856
Protoss_Nexus 2 15276
Protoss_Dark_Templar 3 14477
15588
