Protoss_Gateway 4 14977
Protoss_Assimilator 1 4593
Protoss_Cybernetics_Core 1 5721
Protoss_Dragoon 11 15571
Protoss_Zealot 2 10180
Singularity_Charge 1 9923
Protoss_Nexus 1 12900
Protoss_Robotics_Facility 1 13053
Protoss_Observatory 1 14144
15571
