Protoss_Gateway 2 12069
Protoss_Assimilator 2 14518
Protoss_Cybernetics_Core 1 5938
Protoss_Dragoon 9 15493
Protoss_Nexus 2 16231
Protoss_Robotics_Facility 1 11331
Singularity_Charge 1 9765
Protoss_Observatory 1 12294
Protoss_Shuttle 1 13629
Protoss_Observer 3 15125
16231
