Protoss_Gateway 2 11067
Protoss_Assimilator 2 14455
Protoss_Zealot 2 10969
Protoss_Cybernetics_Core 1 6075
Protoss_Citadel_of_Adun 2 9317
Protoss_Dragoon 4 14319
Protoss_Robotics_Facility 1 9032
Protoss_Templar_Archives 1 10779
Protoss_Nexus 1 13503
Protoss_Shuttle 1 12482
Protoss_Dark_Templar 2 12791
Protoss_Observatory 1 12492
Protoss_Observer 1 14821
14821
