Protoss_Gateway 2 11947
Protoss_Assimilator 2 14477
Protoss_Cybernetics_Core 1 5802
Protoss_Dragoon 11 15452
Protoss_Nexus 1 11854
Singularity_Charge 1 10043
Protoss_Robotics_Facility 1 12001
Protoss_Observatory 1 12724
Protoss_Observer 3 15506
15506
