Protoss_Gateway 4 15255
Protoss_Assimilator 1 4414
Protoss_Cybernetics_Core 1 5888
Protoss_Dragoon 10 15613
Protoss_Nexus 1 10531
Protoss_Robotics_Facility 1 11688
Singularity_Charge 1 9918
Protoss_Observatory 1 13454
Protoss_Observer 1 14721
15613
