Protoss_Gateway 3 12888
Protoss_Assimilator 2 14736
Protoss_Cybernetics_Core 1 5711
Protoss_Dragoon 7 13017
Singularity_Charge 1 9920
Protoss_Nexus 1 12795
Protoss_Robotics_Facility 1 12690
Protoss_Shuttle 1 14221
Protoss_Robotics_Support_Bay 1 14180
Protoss_Observatory 1 14224
Protoss_Observer 1 15356
15356
