Protoss_Gateway 3 12424
Protoss_Assimilator 2 13106
Protoss_Cybernetics_Core 1 5753
Protoss_Dragoon 6 13974
Protoss_Robotics_Facility 1 8365
Protoss_Observatory 3 10152
Protoss_Nexus 1 12694
Protoss_Observer 3 14458
Singularity_Charge 1 11480
Protoss_Citadel_of_Adun 1 13788
Protoss_Zealot 2 14118
Protoss_Templar_Archives 1 15507
15507
