Protoss_Gateway 4 13594
Protoss_Assimilator 1 4340
Protoss_Cybernetics_Core 1 5669
Protoss_Dragoon 11 14697
Protoss_Nexus 2 17232
Singularity_Charge 1 10172
Protoss_Robotics_Facility 1 12652
Protoss_Zealot 1 13349
Protoss_Observatory 1 13422
Protoss_Observer 2 15485
17232
