Protoss_Gateway 3 15902
Protoss_Assimilator 1 4253
Protoss_Cybernetics_Core 1 5711
Protoss_Dragoon 11 14826
Singularity_Charge 1 9885
Protoss_Nexus 2 15210
Protoss_Robotics_Facility 1 14817
15902
