Protoss_Gateway 5 15506
Protoss_Assimilator 3 13410
Protoss_Zealot 7 10676
Protoss_Nexus 1 10562
Protoss_Cybernetics_Core 1 10612
Protoss_Forge 1 11314
Protoss_Photon_Cannon 2 12952
Protoss_Citadel_of_Adun 1 13059
Protoss_Templar_Archives 1 14534
Protoss_Dark_Templar 1 15821
15821
