Protoss_Gateway 3 15304
Protoss_Assimilator 1 4457
Protoss_Cybernetics_Core 1 5708
Protoss_Dragoon 8 15061
Protoss_Nexus 2 13793
Singularity_Charge 1 9865
Protoss_Robotics_Facility 1 14078
Protoss_Shuttle 1 15611
15611
