Protoss_Gateway 2 10874
Protoss_Assimilator 2 15094
Protoss_Cybernetics_Core 1 5844
Protoss_Dragoon 6 15133
Protoss_Robotics_Facility 1 11025
Singularity_Charge 1 9587
Protoss_Nexus 2 14961
Protoss_Observatory 1 12099
Protoss_Observer 3 15093
Protoss_Citadel_of_Adun 1 14309
Protoss_Templar_Archives 1 16027
16027
