Protoss_Gateway 2 5101
Protoss_Zealot 5 7553
Protoss_Assimilator 1 6554
Protoss_Cybernetics_Core 1 7565
Protoss_Dragoon 12 15739
Protoss_Nexus 1 15805
Singularity_Charge 1 13084
Protoss_Robotics_Facility 1 16084
16084
