Protoss_Gateway 3 12842
Protoss_Assimilator 1 4232
Protoss_Cybernetics_Core 1 5750
Protoss_Dragoon 11 15797
Protoss_Nexus 2 16758
Singularity_Charge 1 9909
Protoss_Robotics_Facility 1 11902
Protoss_Observatory 1 12964
Protoss_Observer 2 14938
16758
