Protoss_Assimilator 3 15348
Protoss_Gateway 2 15056
Protoss_Cybernetics_Core 1 6437
Protoss_Dragoon 6 14480
Protoss_Nexus 1 11968
Protoss_Robotics_Facility 1 11858
Singularity_Charge 1 10386
Protoss_Shuttle 1 13495
Protoss_Robotics_Support_Bay 1 13831
Protoss_Reaver 1 15717
Protoss_Zealot 1 15342
15717
