Protoss_Gateway 2 15298
Protoss_Assimilator 2 4902
Protoss_Cybernetics_Core 1 6213
Protoss_Dragoon 7 14916
Protoss_Robotics_Facility 1 9848
Protoss_Shuttle 1 11341
Protoss_Robotics_Support_Bay 1 11052
Protoss_Reaver 1 12899
Protoss_Observatory 1 13236
Protoss_Nexus 1 16076
Singularity_Charge 1 14249
16076
