Protoss_Gateway 5 15658
Protoss_Assimilator 1 4233
Protoss_Cybernetics_Core 1 5680
Protoss_Dragoon 6 15692
Protoss_Nexus 2 13824
Protoss_Robotics_Facility 1 11348
Singularity_Charge 1 9777
Protoss_Shuttle 1 13155
Protoss_Zealot 1 13261
Protoss_Robotics_Support_Bay 1 13242
Protoss_Reaver 1 15132
Protoss_Observatory 1 15151
15692
