Protoss_Gateway 2 10152
Protoss_Assimilator 2 13673
Protoss_Cybernetics_Core 1 6072
Protoss_Dragoon 9 15607
Protoss_Robotics_Facility 1 9663
Protoss_Nexus 2 14858
Protoss_Observatory 1 10482
Singularity_Charge 1 9836
Protoss_Observer 5 15488
Protoss_Citadel_of_Adun 1 14930
15607
