Protoss_Gateway 2 9289
Protoss_Assimilator 1 4451
Protoss_Cybernetics_Core 1 5835
Protoss_Zealot 3 12926
Protoss_Dragoon 9 15499
Protoss_Robotics_Facility 1 11925
Singularity_Charge 1 10058
Protoss_Observatory 1 12721
Protoss_Shuttle 1 13752
Protoss_Nexus 1 16553
Protoss_Observer 1 14695
16553
