Protoss_Gateway 1 4038
Protoss_Assimilator 1 4097
Protoss_Cybernetics_Core 1 5528
Protoss_Zealot 1 5499
Protoss_Dragoon 7 14551
Singularity_Charge 1 9669
Protoss_Nexus 2 14548
Protoss_Robotics_Facility 1 12054
Protoss_Shuttle 1 13668
Protoss_Robotics_Support_Bay 1 13523
Protoss_Reaver 1 15404
Protoss_Observatory 1 14668
15404
