Protoss_Gateway 2 11591
Protoss_Assimilator 3 11262
Protoss_Zealot 4 9418
Protoss_Nexus 2 16259
Protoss_Forge 1 8105
Protoss_Photon_Cannon 1 9496
Protoss_Cybernetics_Core 1 10913
Protoss_Dragoon 5 15004
Protoss_Robotics_Facility 1 14350
Protoss_Observatory 1 15253
16259
