Protoss_Gateway 3 14146
Protoss_Forge 1 4709
Protoss_Assimilator 1 4975
Protoss_Cybernetics_Core 1 6050
Protoss_Dragoon 13 15746
Protoss_Zealot 1 8410
Singularity_Charge 1 10019
Protoss_Robotics_Facility 1 12300
Protoss_Observatory 1 13267
Protoss_Observer 1 14490
Protoss_Nexus 1 16667
16667
