Protoss_Gateway 3 15672
Protoss_Assimilator 2 14648
Protoss_Cybernetics_Core 1 5663
Protoss_Dragoon 7 13351
Protoss_Nexus 2 16366
Singularity_Charge 1 9672
Protoss_Robotics_Facility 1 11915
Protoss_Observatory 1 13532
Protoss_Observer 1 14768
16366
