Protoss_Gateway 3 12599
Protoss_Assimilator 2 15555
Protoss_Cybernetics_Core 1 5979
Protoss_Dragoon 10 15268
Protoss_Nexus 1 11302
Protoss_Robotics_Facility 1 11662
Singularity_Charge 1 10032
Protoss_Observatory 1 12749
Protoss_Observer 3 15532
15555
