Protoss_Nexus 2 13746
Protoss_Gateway 4 15386
Protoss_Assimilator 1 5789
Protoss_Cybernetics_Core 1 7331
Protoss_Dragoon 13 15739
Singularity_Charge 1 11422
Protoss_Robotics_Facility 1 13956
Protoss_Observatory 1 14783
15739
