Protoss_Gateway 2 12169
Protoss_Assimilator 2 13922
Protoss_Cybernetics_Core 1 5919
Protoss_Dragoon 6 15191
Protoss_Citadel_of_Adun 1 9238
Protoss_Nexus 1 12151
Protoss_Templar_Archives 1 11036
Singularity_Charge 1 9821
Protoss_Dark_Templar 2 13517
Protoss_Robotics_Facility 1 13911
15191
