Protoss_Gateway 2 15308
Protoss_Assimilator 1 4644
Protoss_Cybernetics_Core 1 6023
Protoss_Dragoon 6 15592
Protoss_Robotics_Facility 1 8698
Protoss_Shuttle 1 10226
Protoss_Observatory 1 10299
Protoss_Robotics_Support_Bay 1 10677
Protoss_Observer 2 14395
Protoss_Reaver 1 12995
Protoss_Nexus 1 15191
Singularity_Charge 1 14358
15592
