Protoss_Gateway 2 10313
Protoss_Assimilator 1 4707
Protoss_Cybernetics_Core 1 5982
Protoss_Dragoon 10 15350
Protoss_Robotics_Facility 1 10323
Singularity_Charge 1 10163
Protoss_Observatory 1 11097
Protoss_Nexus 1 13989
Protoss_Observer 1 12236
Protoss_Shuttle 1 14202
Protoss_Robotics_Support_Bay 1 14706
15350
