Protoss_Gateway 3 15702
Protoss_Assimilator 1 3997
Protoss_Cybernetics_Core 1 5847
Protoss_Dragoon 9 13096
Protoss_Robotics_Facility 1 8321
Protoss_Observatory 1 9036
Protoss_Observer 2 11235
Singularity_Charge 1 10594
Protoss_Shuttle 1 13987
Protoss_Nexus 1 16243
Protoss_Zealot 3 15415
16243
