Protoss_Gateway 2 15920
Protoss_Assimilator 1 4337
Protoss_Cybernetics_Core 1 5771
Protoss_Dragoon 5 15648
Protoss_Robotics_Facility 1 9427
Protoss_Nexus 2 15696
Protoss_Shuttle 1 10908
Protoss_Robotics_Support_Bay 1 10749
Protoss_Zealot 2 12067
Protoss_Reaver 1 12474
Protoss_Stargate 1 15489
Protoss_Observatory 1 15240
15920
