Protoss_Gateway 3 15921
Protoss_Assimilator 1 4297
Protoss_Cybernetics_Core 2 5667
Protoss_Dragoon 7 15282
Protoss_Robotics_Facility 1 10078
Singularity_Charge 1 9704
Protoss_Shuttle 1 11484
Protoss_Robotics_Support_Bay 1 11518
Protoss_Zealot 2 13062
Protoss_Reaver 1 13270
Protoss_Observatory 1 12808
Protoss_Observer 2 14976
Protoss_Nexus 1 16293
16293
