Protoss_Gateway 3 12232
Protoss_Assimilator 2 14051
Protoss_Cybernetics_Core 1 5535
Protoss_Dragoon 9 13798
Protoss_Nexus 1 11071
Singularity_Charge 1 9443
Protoss_Robotics_Facility 1 11439
Protoss_Observatory 1 12363
Protoss_Observer 1 14320
14320
