Protoss_Gateway 2 10350
Protoss_Assimilator 1 4501
Protoss_Cybernetics_Core 1 5898
Protoss_Dragoon 7 13058
Protoss_Robotics_Facility 1 10024
Singularity_Charge 1 9894
Protoss_Observatory 1 10822
Protoss_Observer 3 14502
Protoss_Nexus 2 16212
Protoss_Citadel_of_Adun 1 15589
16212
