Protoss_Gateway 3 15895
Protoss_Assimilator 1 4392
Protoss_Cybernetics_Core 1 5636
Protoss_Dragoon 8 14337
Protoss_Nexus 2 15540
Singularity_Charge 1 9610
Protoss_Robotics_Facility 1 11565
Protoss_Observatory 1 12331
Protoss_Observer 3 15119
15895
