Protoss_Gateway 4 15986
Protoss_Assimilator 3 13827
Protoss_Zealot 1 5455
Protoss_Cybernetics_Core 1 6249
Protoss_Dragoon 9 15335
Protoss_Nexus 1 12327
Singularity_Charge 1 10465
Protoss_Robotics_Facility 1 13429
Protoss_Observatory 1 14220
15986
