Protoss_Gateway 2 10085
Protoss_Assimilator 1 4148
Protoss_Cybernetics_Core 1 5543
Protoss_Dragoon 10 13629
Protoss_Robotics_Facility 1 10020
Singularity_Charge 1 9473
Protoss_Observatory 1 10803
Protoss_Observer 2 14944
Protoss_Nexus 2 17080
17080
