Protoss_Gateway 3 15315
Protoss_Assimilator 2 13097
Protoss_Cybernetics_Core 1 5947
Protoss_Dragoon 7 14047
Protoss_Nexus 1 11153
Protoss_Robotics_Facility 1 11208
Singularity_Charge 1 9920
Protoss_Shuttle 1 13091
Protoss_Observatory 1 12446
Protoss_Observer 1 13934
Protoss_Robotics_Support_Bay 1 13769
Protoss_Citadel_of_Adun 1 15176
Protoss_Reaver 1 15785
15785
