Protoss_Gateway 3 15569
Protoss_Assimilator 1 4382
Protoss_Cybernetics_Core 1 5711
Protoss_Dragoon 10 15663
Singularity_Charge 1 9786
Protoss_Nexus 2 15526
Protoss_Zealot 1 11265
Protoss_Robotics_Facility 1 14290
Protoss_Observatory 1 14998
15663
