Protoss_Gateway 1 4151
Protoss_Assimilator 1 4632
Protoss_Zealot 5 14259
Protoss_Cybernetics_Core 1 7003
Protoss_Dragoon 5 15379
Protoss_Robotics_Facility 1 9821
Protoss_Shuttle 1 11695
Protoss_Observatory 1 11783
Protoss_Observer 1 12854
Protoss_Robotics_Support_Bay 1 12919
Singularity_Charge 1 12312
Protoss_Reaver 1 14669
Protoss_Nexus 1 16173
16173
