Protoss_Gateway 3 14295
Protoss_Assimilator 1 4590
Protoss_Cybernetics_Core 1 5800
Protoss_Dragoon 8 15704
Protoss_Nexus 1 11157
Protoss_Robotics_Facility 1 11073
Singularity_Charge 1 10117
Protoss_Shuttle 1 12532
Protoss_Robotics_Support_Bay 1 12253
Protoss_Zealot 2 13006
Protoss_Reaver 1 14090
Protoss_Observatory 1 13358
15704
