Protoss_Gateway 2 9589
Protoss_Zealot 5 14821
Protoss_Assimilator 1 6576
Protoss_Cybernetics_Core 1 7435
Protoss_Dragoon 10 15309
Singularity_Charge 1 11873
Protoss_Nexus 1 16495
16495
