Protoss_Nexus 2 15818
Protoss_Gateway 3 12687
Protoss_Assimilator 2 12621
Protoss_Cybernetics_Core 1 7574
Protoss_Zealot 2 13053
Protoss_Dragoon 11 15405
Protoss_Robotics_Facility 1 11375
Singularity_Charge 1 11419
Protoss_Observatory 1 12148
Protoss_Observer 3 15263
Protoss_Citadel_of_Adun 1 15888
15888
