Protoss_Gateway 3 10597
Protoss_Zealot 4 14639
Protoss_Nexus 1 9403
Protoss_Assimilator 1 7823
Protoss_Cybernetics_Core 1 8835
Protoss_Dragoon 7 14726
Protoss_Robotics_Facility 1 14547
Singularity_Charge 1 13178
Protoss_Observatory 1 15295
15295
