Protoss_Gateway 6 15991
Protoss_Assimilator 1 4230
Protoss_Cybernetics_Core 1 5601
Protoss_Dragoon 5 13137
Protoss_Robotics_Facility 1 9665
Singularity_Charge 1 9666
Protoss_Shuttle 1 11107
Protoss_Nexus 2 15851
Protoss_Robotics_Support_Bay 1 11357
Protoss_Reaver 1 13136
Protoss_Observatory 1 12645
Protoss_Observer 2 14841
15991
