Protoss_Gateway 2 9475
Protoss_Assimilator 1 4644
Protoss_Cybernetics_Core 1 5923
Protoss_Dragoon 10 15297
Protoss_Robotics_Facility 1 11230
Singularity_Charge 1 10134
Protoss_Zealot 2 11891
Protoss_Observatory 1 12016
Protoss_Observer 2 14827
Protoss_Nexus 1 17266
17266
