Protoss_Nexus 2 16888
Protoss_Gateway 2 7015
Protoss_Assimilator 2 13673
Protoss_Cybernetics_Core 1 7710
Protoss_Dragoon 7 15569
Protoss_Robotics_Facility 1 14442
Singularity_Charge 1 13178
Protoss_Observatory 1 15278
16888
