Protoss_Gateway 4 15599
Protoss_Assimilator 1 4293
Protoss_Cybernetics_Core 1 5727
Protoss_Dragoon 10 15671
Protoss_Nexus 2 14807
Singularity_Charge 1 9686
Protoss_Robotics_Facility 1 14785
15671
