Protoss_Gateway 2 11048
Protoss_Assimilator 2 5194
Protoss_Zealot 2 6968
Protoss_Cybernetics_Core 1 7176
Protoss_Dragoon 5 15203
Protoss_Citadel_of_Adun 1 10758
Protoss_Robotics_Facility 1 12177
Protoss_Templar_Archives 1 12312
Singularity_Charge 1 11147
Protoss_Nexus 1 14583
Protoss_Shuttle 1 13574
Protoss_Dark_Templar 2 13760
Protoss_Observatory 1 13980
Protoss_Observer 1 15392
15392
