Protoss_Gateway 4 15604
Protoss_Zealot 1 4861
Protoss_Assimilator 1 5187
Protoss_Cybernetics_Core 1 6485
Protoss_Dragoon 5 10359
Protoss_Nexus 2 14624
Singularity_Charge 1 11685
Protoss_Robotics_Facility 1 14407
Protoss_Observatory 1 15140
Protoss_Shuttle 1 15965
15965
