Protoss_Gateway 2 6324
Protoss_Assimilator 1 4281
Protoss_Cybernetics_Core 1 5569
Protoss_Dragoon 6 15669
Protoss_Nexus 2 17235
Singularity_Charge 1 9657
Protoss_Robotics_Facility 1 12124
Protoss_Shuttle 1 13545
Protoss_Robotics_Support_Bay 1 13026
Protoss_Observatory 1 14081
Protoss_Reaver 1 15103
Protoss_Zealot 2 14513
17235
