Protoss_Gateway 2 11051
Protoss_Assimilator 2 13414
Protoss_Zealot 1 5063
Protoss_Cybernetics_Core 1 6787
Protoss_Dragoon 8 13737
Protoss_Nexus 1 11548
Protoss_Citadel_of_Adun 1 11493
Singularity_Charge 1 10456
Protoss_Templar_Archives 1 13029
Protoss_Dark_Templar 2 14837
Protoss_Robotics_Facility 1 15818
15818
