Protoss_Gateway 2 10589
Protoss_Assimilator 1 4452
Protoss_Cybernetics_Core 1 5748
Protoss_Zealot 2 13436
Protoss_Dragoon 8 14922
Protoss_Robotics_Facility 1 10119
Singularity_Charge 1 10149
Protoss_Shuttle 1 11622
Protoss_Observatory 1 11485
Protoss_Robotics_Support_Bay 1 12265
Protoss_Reaver 1 14002
Protoss_Nexus 1 15947
Protoss_Observer 1 15011
15947
