Protoss_Gateway 4 15652
Protoss_Assimilator 2 14759
Protoss_Cybernetics_Core 1 5759
Protoss_Dragoon 5 15789
Protoss_Citadel_of_Adun 1 7580
Protoss_Templar_Archives 1 9175
Protoss_Nexus 2 14037
Protoss_Dark_Templar 3 12701
Protoss_Robotics_Facility 1 14894
15789
