Protoss_Gateway 2 10202
Protoss_Assimilator 1 4580
Protoss_Cybernetics_Core 1 5919
Protoss_Dragoon 11 15205
Singularity_Charge 1 10480
Protoss_Nexus 1 13757
Protoss_Robotics_Facility 1 15483
15483
