Protoss_Gateway 2 15656
Protoss_Assimilator 1 4521
Protoss_Cybernetics_Core 1 5891
Protoss_Dragoon 8 15607
Protoss_Robotics_Facility 1 10045
Protoss_Shuttle 1 11449
Singularity_Charge 1 10155
Protoss_Robotics_Support_Bay 1 11494
Protoss_Reaver 1 13224
Protoss_Observatory 1 12830
Protoss_Nexus 1 15849
Protoss_Observer 1 14912
15849
