Protoss_Gateway 3 13141
Protoss_Assimilator 1 4985
Protoss_Cybernetics_Core 1 6383
Protoss_Dragoon 13 15790
Protoss_Robotics_Facility 1 10023
Protoss_Observatory 1 10860
Protoss_Observer 2 15149
Singularity_Charge 1 12675
15790
