Protoss_Gateway 2 8421
Protoss_Assimilator 2 5110
Protoss_Cybernetics_Core 1 6541
Protoss_Dragoon 11 15309
Protoss_Nexus 1 13158
Singularity_Charge 1 10436
Protoss_Robotics_Facility 1 12841
Protoss_Shuttle 1 14294
Protoss_Robotics_Support_Bay 1 14760
15309
