Protoss_Gateway 2 16005
Protoss_Assimilator 1 4464
Protoss_Cybernetics_Core 1 5949
Protoss_Dragoon 5 15219
Protoss_Robotics_Facility 1 8547
Protoss_Shuttle 1 10053
Protoss_Robotics_Support_Bay 1 9888
Protoss_Zealot 2 11443
Protoss_Reaver 2 15094
Protoss_Observatory 1 11878
Protoss_Observer 1 12989
Singularity_Charge 1 14595
16005
