Protoss_Gateway 1 4347
Protoss_Assimilator 1 4572
Protoss_Cybernetics_Core 1 6216
Protoss_Zealot 1 5783
Protoss_Dragoon 7 15230
Protoss_Robotics_Facility 1 10532
Singularity_Charge 1 10160
Protoss_Shuttle 1 12315
Protoss_Robotics_Support_Bay 1 11646
Protoss_Reaver 1 14099
Protoss_Nexus 1 16143
Protoss_Observatory 1 14308
Protoss_Observer 1 15356
16143
