Protoss_Gateway 4 14123
Protoss_Assimilator 2 4774
Protoss_Cybernetics_Core 1 6178
Protoss_Dragoon 9 15347
Singularity_Charge 1 10260
Protoss_Nexus 1 13442
Protoss_Robotics_Facility 1 13017
Protoss_Observatory 1 13879
Protoss_Observer 1 14923
15347
