Protoss_Nexus 1 6777
Protoss_Gateway 2 10267
Protoss_Assimilator 1 5718
Protoss_Cybernetics_Core 1 7463
Protoss_Zealot 1 7469
Protoss_Dragoon 10 15115
Protoss_Forge 1 11121
Singularity_Charge 1 11334
Protoss_Photon_Cannon 2 12726
Protoss_Robotics_Facility 1 14100
Protoss_Observatory 1 14909
Protoss_Shuttle 1 15813
15813
