Protoss_Gateway 2 9517
Protoss_Assimilator 1 4188
Protoss_Zealot 1 5194
Protoss_Cybernetics_Core 1 6189
Protoss_Dragoon 8 14448
Singularity_Charge 1 10368
Protoss_Robotics_Facility 1 12418
Protoss_Observatory 1 13351
Protoss_Nexus 1 15669
Protoss_Observer 2 15330
Protoss_Robotics_Support_Bay 1 14565
Protoss_Shuttle 1 15991
15991
