Protoss_Gateway 3 15077
Protoss_Assimilator 2 12670
Protoss_Cybernetics_Core 1 5717
Protoss_Dragoon 9 15244
Protoss_Nexus 1 11961
Singularity_Charge 1 9736
Protoss_Robotics_Facility 1 12016
Protoss_Citadel_of_Adun 1 13060
Protoss_Observatory 1 12989
Protoss_Observer 1 14019
Protoss_Templar_Archives 1 14838
Protoss_Shuttle 1 15825
15825
