Protoss_Gateway 2 12140
Protoss_Assimilator 1 4913
Protoss_Zealot 1 5613
Protoss_Cybernetics_Core 1 6927
Protoss_Dragoon 8 15300
Protoss_Nexus 2 14981
Singularity_Charge 1 11129
Protoss_Robotics_Facility 1 15469
15469
