Protoss_Gateway 2 11108
Protoss_Assimilator 1 4251
Protoss_Cybernetics_Core 1 5765
Protoss_Dragoon 11 14735
Protoss_Robotics_Facility 1 9985
Singularity_Charge 1 9666
Protoss_Observatory 1 10787
Protoss_Observer 2 15356
Protoss_Nexus 2 17163
Protoss_Citadel_of_Adun 1 15852
17163
