Protoss_Gateway 2 10117
Protoss_Assimilator 1 4423
Protoss_Cybernetics_Core 1 5739
Protoss_Dragoon 10 14196
Protoss_Robotics_Facility 1 9932
Singularity_Charge 1 9704
Protoss_Observatory 1 10997
Protoss_Observer 2 13627
Protoss_Nexus 2 16571
16571
