Protoss_Gateway 2 13122
Protoss_Assimilator 1 4450
Protoss_Cybernetics_Core 1 5819
Protoss_Zealot 1 5821
Protoss_Dragoon 9 15417
Protoss_Robotics_Facility 1 10751
Singularity_Charge 1 10199
Protoss_Shuttle 1 12154
Protoss_Robotics_Support_Bay 1 11640
Protoss_Reaver 1 13712
Protoss_Observatory 1 13131
Protoss_Observer 2 15479
15479
