Protoss_Gateway 2 10951
Protoss_Assimilator 1 4461
Protoss_Cybernetics_Core 1 5780
Protoss_Dragoon 7 15183
Protoss_Robotics_Facility 1 10009
Singularity_Charge 1 9909
Protoss_Observatory 1 10779
Protoss_Observer 1 11914
Protoss_Nexus 1 14248
Protoss_Shuttle 1 14272
Protoss_Zealot 2 14000
15183
