Protoss_Assimilator 3 5985
Protoss_Gateway 2 15473
Protoss_Zealot 2 7085
Protoss_Cybernetics_Core 1 8158
Protoss_Dragoon 6 14954
Protoss_Robotics_Facility 1 10658
Protoss_Shuttle 1 12069
Protoss_Robotics_Support_Bay 1 11813
Protoss_Reaver 1 13648
Protoss_Nexus 1 15117
15473
