Protoss_Gateway 2 10902
Protoss_Assimilator 1 5099
Protoss_Zealot 2 6427
Protoss_Cybernetics_Core 1 6599
Protoss_Dragoon 7 14495
Singularity_Charge 1 10728
Protoss_Nexus 1 15754
Protoss_Robotics_Facility 1 15989
15989
