Protoss_Gateway 3 13346
Protoss_Assimilator 1 4842
Protoss_Cybernetics_Core 1 6160
Protoss_Dragoon 8 13642
Protoss_Robotics_Facility 1 10225
Protoss_Observatory 1 10993
Protoss_Observer 2 13337
Singularity_Charge 1 12258
Protoss_Shuttle 1 14462
Protoss_Robotics_Support_Bay 1 13970
Protoss_Reaver 1 16020
16020
