Protoss_Gateway 3 12149
Protoss_Zealot 4 8028
Protoss_Forge 1 5112
Protoss_Assimilator 1 6236
Protoss_Cybernetics_Core 1 7448
Protoss_Dragoon 9 15121
Protoss_Robotics_Facility 1 13072
Singularity_Charge 1 11703
Protoss_Observatory 1 14275
Protoss_Observer 1 15359
15359
