Protoss_Gateway 2 6330
Protoss_Assimilator 1 4373
Protoss_Cybernetics_Core 1 5635
Protoss_Dragoon 10 13403
Protoss_Zealot 5 15099
Singularity_Charge 1 9692
Protoss_Robotics_Facility 2 15218
15218
