Protoss_Gateway 2 8543
Protoss_Assimilator 1 4612
Protoss_Cybernetics_Core 1 6064
Protoss_Dragoon 11 14559
Protoss_Robotics_Facility 1 10980
Singularity_Charge 1 10269
Protoss_Shuttle 1 12538
Protoss_Observatory 1 12554
Protoss_Observer 1 13603
Protoss_Robotics_Support_Bay 1 13620
Protoss_Reaver 1 15486
15486
