Protoss_Gateway 2 14933
Protoss_Assimilator 1 4425
Protoss_Zealot 1 5151
Protoss_Cybernetics_Core 1 6766
Protoss_Dragoon 6 14594
Protoss_Robotics_Facility 2 10865
Protoss_Robotics_Support_Bay 1 10390
Protoss_Shuttle 1 11622
Protoss_Reaver 2 13548
14933
