Protoss_Gateway 2 10369
Protoss_Assimilator 1 4419
Protoss_Cybernetics_Core 1 5974
Protoss_Dragoon 11 15669
Protoss_Robotics_Facility 1 9867
Singularity_Charge 1 9874
Protoss_Observatory 1 10599
Protoss_Observer 2 12798
Protoss_Nexus 1 15543
Protoss_Zealot 1 15561
15669
