Protoss_Gateway 3 14758
Protoss_Assimilator 1 4395
Protoss_Cybernetics_Core 1 5796
Protoss_Dragoon 4 15219
Protoss_Robotics_Facility 1 9826
Protoss_Zealot 3 13180
Singularity_Charge 1 9989
Protoss_Robotics_Support_Bay 1 11128
Protoss_Shuttle 1 11901
Protoss_Observatory 1 11419
Protoss_Reaver 1 13459
Protoss_Nexus 1 15293
Protoss_Observer 1 14284
15293
