Protoss_Gateway 2 10193
Protoss_Assimilator 1 4612
Protoss_Cybernetics_Core 1 5939
Protoss_Zealot 1 6517
Protoss_Dragoon 11 14717
Singularity_Charge 1 10462
Protoss_Robotics_Facility 1 13699
Protoss_Observatory 1 14479
Protoss_Observer 1 15520
15520
