Protoss_Gateway 2 12314
Protoss_Assimilator 1 4812
Protoss_Cybernetics_Core 1 6375
Protoss_Dragoon 8 15739
Protoss_Robotics_Facility 1 8660
Protoss_Observatory 1 9432
Protoss_Observer 3 15295
Protoss_Shuttle 1 13357
Singularity_Charge 1 12792
Protoss_Zealot 2 14402
15739
