Protoss_Gateway 2 14184
Protoss_Assimilator 2 13741
Protoss_Cybernetics_Core 1 5745
Protoss_Zealot 1 5540
Protoss_Dragoon 7 15235
Protoss_Robotics_Facility 1 8485
Protoss_Observatory 1 9576
Protoss_Observer 3 14783
Protoss_Nexus 1 13667
Singularity_Charge 1 11539
Protoss_Citadel_of_Adun 1 13147
Protoss_Templar_Archives 1 14832
15235
