Protoss_Gateway 2 8177
Protoss_Assimilator 1 4406
Protoss_Cybernetics_Core 1 5791
Protoss_Dragoon 8 15373
Singularity_Charge 1 9739
Protoss_Nexus 3 14856
Protoss_Robotics_Facility 1 15711
15711
