Protoss_Nexus 2 16139
Protoss_Gateway 3 15965
Protoss_Assimilator 2 10695
Protoss_Cybernetics_Core 1 7250
Protoss_Zealot 1 7533
Protoss_Dragoon 12 15358
Protoss_Robotics_Facility 1 12745
Singularity_Charge 1 11726
Protoss_Observatory 1 13444
Protoss_Observer 2 15374
Protoss_Citadel_of_Adun 1 15888
16139
