Protoss_Gateway 3 15629
Protoss_Assimilator 1 4630
Protoss_Cybernetics_Core 1 6214
Protoss_Dragoon 10 15230
Protoss_Robotics_Facility 1 10122
Singularity_Charge 1 10108
Protoss_Observatory 1 10842
Protoss_Observer 2 12866
Protoss_Nexus 1 14740
Protoss_Shuttle 1 14838
Protoss_Zealot 1 15072
15629
