Protoss_Gateway 2 8335
Protoss_Assimilator 1 4842
Protoss_Cybernetics_Core 1 6422
Protoss_Dragoon 11 15307
Protoss_Nexus 1 12842
Protoss_Robotics_Facility 1 13112
Protoss_Observatory 1 14065
Protoss_Observer 1 15434
15434
