Protoss_Gateway 2 9498
Protoss_Assimilator 1 4366
Protoss_Cybernetics_Core 1 5636
Protoss_Dragoon 4 15071
Protoss_Citadel_of_Adun 1 7884
Protoss_Templar_Archives 1 9327
Protoss_Dark_Templar 5 13488
Protoss_Nexus 1 14238
Singularity_Charge 1 13784
Protoss_Robotics_Facility 1 16529
16529
