Protoss_Gateway 2 9530
Protoss_Assimilator 1 4290
Protoss_Cybernetics_Core 1 5835
Protoss_Dragoon 5 14191
Protoss_Citadel_of_Adun 1 9083
Protoss_Templar_Archives 1 10624
Protoss_Nexus 1 12608
Protoss_Dark_Templar 4 12944
14191
