Protoss_Gateway 2 12384
Protoss_Assimilator 2 14345
Protoss_Cybernetics_Core 1 5895
Protoss_Zealot 1 5868
Protoss_Dragoon 7 14135
Protoss_Robotics_Facility 1 10163
Protoss_Nexus 1 13069
Singularity_Charge 1 10383
Protoss_Observatory 1 11147
Protoss_Observer 2 13152
Protoss_Citadel_of_Adun 1 13758
Protoss_Templar_Archives 1 15387
Protoss_Stargate 1 16221
16221
