Protoss_Gateway 3 13751
Protoss_Assimilator 2 12763
Protoss_Cybernetics_Core 1 5528
Protoss_Dragoon 10 15806
Protoss_Nexus 1 11542
Singularity_Charge 1 9827
Protoss_Stargate 1 13131
Protoss_Fleet_Beacon 1 14790
Protoss_Zealot 1 15585
15806
