Protoss_Gateway 2 9365
Protoss_Assimilator 2 5480
Protoss_Zealot 4 8540
Protoss_Cybernetics_Core 1 7631
Protoss_Dragoon 9 15446
Protoss_Citadel_of_Adun 1 12482
Singularity_Charge 1 12601
Protoss_Templar_Archives 1 15321
15446
