Protoss_Gateway 2 9823
Protoss_Assimilator 2 15152
Protoss_Cybernetics_Core 1 5958
Protoss_Dragoon 4 14480
Protoss_Citadel_of_Adun 1 9381
Protoss_Templar_Archives 1 10902
Protoss_Robotics_Facility 1 12591
Protoss_Dark_Templar 2 12124
Protoss_Nexus 1 14876
Protoss_Observatory 1 13452
Protoss_Stargate 1 14967
Protoss_Observer 1 14490
15152
