Protoss_Gateway 2 10629
Protoss_Assimilator 1 4423
Protoss_Cybernetics_Core 1 5645
Protoss_Dragoon 10 15306
Protoss_Nexus 1 11757
Singularity_Charge 1 9704
Protoss_Robotics_Facility 1 12320
Protoss_Shuttle 1 13896
Protoss_Robotics_Support_Bay 1 13936
Protoss_Reaver 1 15776
15776
