Protoss_Gateway 2 10943
Protoss_Assimilator 1 4313
Protoss_Cybernetics_Core 1 5892
Protoss_Dragoon 10 14881
Protoss_Nexus 1 11639
Singularity_Charge 1 10052
Protoss_Robotics_Facility 1 14755
14881
