Protoss_Gateway 2 11825
Protoss_Assimilator 2 14148
Protoss_Cybernetics_Core 1 5695
Protoss_Zealot 1 5575
Protoss_Dragoon 3 13552
Protoss_Citadel_of_Adun 1 7660
Protoss_Templar_Archives 1 9220
Protoss_Dark_Templar 2 11635
Protoss_Nexus 2 17453
Protoss_Stargate 1 11710
Protoss_Arbiter_Tribunal 1 13704
Protoss_Arbiter 1 18250
18250
