Protoss_Gateway 2 7919
Protoss_Assimilator 1 4436
Protoss_Cybernetics_Core 1 5841
Protoss_Dragoon 12 14972
Singularity_Charge 1 9730
Protoss_Nexus 1 12619
Protoss_Robotics_Facility 1 13447
Protoss_Observatory 1 14387
Protoss_Observer 1 15576
15576
