Protoss_Gateway 2 7050
Protoss_Assimilator 1 4608
Protoss_Cybernetics_Core 1 6034
Protoss_Dragoon 10 15519
Singularity_Charge 1 10026
Protoss_Nexus 2 16856
Protoss_Robotics_Facility 1 13207
Protoss_Observatory 1 14129
Protoss_Observer 1 15192
16856
