Protoss_Gateway 1 4111
Protoss_Assimilator 2 15266
Protoss_Cybernetics_Core 1 5572
Protoss_Robotics_Facility 2 15235
Protoss_Dragoon 3 15557
Protoss_Shuttle 2 14030
Protoss_Robotics_Support_Bay 1 8634
Protoss_Reaver 3 16183
Protoss_Nexus 1 14291
Gravitic_Drive 1 12862
Protoss_Observatory 1 14706
16183
