Protoss_Gateway 2 12817
Protoss_Assimilator 1 4356
Protoss_Cybernetics_Core 1 5635
Protoss_Dragoon 9 15121
Protoss_Robotics_Facility 1 8325
Protoss_Shuttle 1 9731
Protoss_Robotics_Support_Bay 1 9660
Protoss_Reaver 1 11672
Protoss_Observatory 1 12259
Protoss_Zealot 1 12693
Protoss_Observer 1 13726
Singularity_Charge 1 14331
15121
