Protoss_Gateway 3 13543
Protoss_Assimilator 1 4754
Protoss_Cybernetics_Core 1 6029
Protoss_Dragoon 11 15178
Singularity_Charge 1 10319
Protoss_Nexus 1 14635
Protoss_Robotics_Facility 1 15490
Protoss_Zealot 1 15419
15490
