Protoss_Gateway 2 14414
Protoss_Zealot 3 7767
Protoss_Assimilator 1 6817
Protoss_Cybernetics_Core 1 8133
Protoss_Dragoon 7 15727
Protoss_Nexus 1 14260
Protoss_Robotics_Facility 1 14010
Singularity_Charge 1 12215
Protoss_Shuttle 1 15640
Protoss_Robotics_Support_Bay 1 15085
15727
