Protoss_Gateway 3 15460
Protoss_Assimilator 1 4258
Protoss_Cybernetics_Core 1 5671
Protoss_Dragoon 9 14840
Protoss_Robotics_Facility 1 10264
Singularity_Charge 1 9762
Protoss_Observatory 1 11068
Protoss_Nexus 1 13732
Protoss_Observer 3 13919
15460
