Protoss_Gateway 2 9418
Protoss_Assimilator 1 4321
Protoss_Cybernetics_Core 1 5797
Protoss_Dragoon 10 15519
Protoss_Robotics_Facility 1 11539
Singularity_Charge 1 9918
Protoss_Observatory 1 12417
Protoss_Observer 3 15242
Protoss_Nexus 2 16740
16740
