Protoss_Gateway 2 12470
Protoss_Assimilator 2 12915
Protoss_Cybernetics_Core 1 5762
Protoss_Dragoon 9 14984
Protoss_Robotics_Facility 1 10169
Singularity_Charge 1 9771
Protoss_Nexus 1 13020
Protoss_Observatory 1 11114
Protoss_Observer 3 14423
Protoss_Citadel_of_Adun 1 13185
Protoss_Stargate 1 15650
Protoss_Templar_Archives 1 16029
16029
