Protoss_Gateway 2 15792
Protoss_Assimilator 2 13804
Protoss_Cybernetics_Core 1 5762
Protoss_Dragoon 6 13222
Protoss_Nexus 1 11668
Singularity_Charge 1 9786
Protoss_Robotics_Facility 2 12437
Protoss_Observatory 1 12720
Protoss_Robotics_Support_Bay 1 13193
Protoss_Observer 1 13793
Protoss_Shuttle 1 14452
Protoss_Reaver 2 16285
16285
