Protoss_Gateway 2 9462
Protoss_Assimilator 1 4498
Protoss_Cybernetics_Core 1 6040
Protoss_Dragoon 9 15388
Protoss_Citadel_of_Adun 1 10293
Protoss_Forge 1 10322
Singularity_Charge 1 10180
Protoss_Templar_Archives 1 11882
Protoss_Photon_Cannon 1 13153
Protoss_Dark_Templar 2 13171
Protoss_Nexus 1 16413
16413
