Protoss_Gateway 3 14165
Protoss_Assimilator 1 4379
Protoss_Cybernetics_Core 1 5701
Protoss_Dragoon 10 15396
Protoss_Robotics_Facility 1 9727
Singularity_Charge 1 9511
Protoss_Observatory 1 10441
Protoss_Observer 2 13179
Protoss_Nexus 1 14147
Protoss_Shuttle 1 14537
Protoss_Zealot 3 15339
15396
