Protoss_Gateway 1 4262
Protoss_Assimilator 1 4473
Protoss_Cybernetics_Core 1 5865
Protoss_Dragoon 8 15156
Protoss_Robotics_Facility 1 9841
Singularity_Charge 1 9827
Protoss_Observatory 1 10574
Protoss_Nexus 1 13227
Protoss_Observer 1 12154
Protoss_Shuttle 1 13512
Protoss_Robotics_Support_Bay 1 13254
Protoss_Reaver 1 15070
Protoss_Citadel_of_Adun 1 15353
15353
