Protoss_Assimilator 1 3956
Protoss_Gateway 4 14152
Protoss_Cybernetics_Core 1 6475
Protoss_Dragoon 9 14530
Protoss_Robotics_Facility 1 11171
Singularity_Charge 1 10149
Protoss_Nexus 1 13417
Protoss_Observatory 1 12603
Protoss_Observer 2 14516
Protoss_Shuttle 1 15874
15874
