Protoss_Gateway 4 15437
Protoss_Assimilator 1 4457
Protoss_Cybernetics_Core 1 5925
Protoss_Dragoon 5 15710
Protoss_Citadel_of_Adun 1 7839
Protoss_Templar_Archives 1 9457
Protoss_Dark_Templar 5 13751
Protoss_Nexus 1 13811
Singularity_Charge 1 13515
Protoss_Robotics_Facility 1 16004
16004
