Protoss_Gateway 2 8074
Protoss_Assimilator 2 14790
Protoss_Cybernetics_Core 1 5752
Protoss_Dragoon 8 14650
Singularity_Charge 1 9663
Protoss_Nexus 2 14402
Protoss_Citadel_of_Adun 1 12137
Protoss_Templar_Archives 1 14256
Protoss_Dark_Templar 1 15742
15742
