Protoss_Gateway 4 14993
Protoss_Assimilator 1 4268
Protoss_Cybernetics_Core 1 5636
Protoss_Dragoon 10 15361
Protoss_Robotics_Facility 1 9709
Singularity_Charge 1 9733
Protoss_Observatory 1 10731
Protoss_Robotics_Support_Bay 1 10795
Protoss_Observer 3 15561
Protoss_Nexus 2 15851
15851
