Protoss_Gateway 2 8701
Protoss_Assimilator 1 4287
Protoss_Cybernetics_Core 1 5632
Protoss_Dragoon 9 15376
Protoss_Robotics_Facility 1 10011
Singularity_Charge 1 9534
Protoss_Shuttle 1 11701
Protoss_Robotics_Support_Bay 1 11189
Protoss_Zealot 2 12137
Protoss_Reaver 2 15369
Protoss_Nexus 1 15415
15415
