Protoss_Gateway 1 4188
Protoss_Assimilator 1 4354
Protoss_Cybernetics_Core 1 5633
Protoss_Zealot 2 8660
Protoss_Dragoon 4 14363
Protoss_Robotics_Facility 1 8269
Protoss_Shuttle 2 14742
Protoss_Robotics_Support_Bay 1 9701
Protoss_Reaver 3 16300
Protoss_Observatory 1 12609
Protoss_Nexus 1 15341
16300
