Protoss_Gateway 2 12049
Protoss_Assimilator 1 4275
Protoss_Cybernetics_Core 1 5870
Protoss_Dragoon 10 15590
Protoss_Robotics_Facility 1 8569
Protoss_Shuttle 1 9962
Protoss_Robotics_Support_Bay 1 9835
Protoss_Reaver 1 11567
Protoss_Observatory 1 11782
Protoss_Observer 1 12795
Singularity_Charge 1 12060
15590
