Protoss_Gateway 4 15697
Protoss_Assimilator 4 7095
Protoss_Cybernetics_Core 1 6064
Protoss_Zealot 1 6441
Protoss_Dragoon 8 15215
Singularity_Charge 1 11094
Protoss_Nexus 1 14989
Protoss_Robotics_Facility 1 15226
15697
