Protoss_Gateway 3 15217
Protoss_Assimilator 1 4155
Protoss_Cybernetics_Core 1 5575
Protoss_Dragoon 4 9189
Protoss_Citadel_of_Adun 1 9162
Protoss_Zealot 1 10076
Singularity_Charge 1 9236
Protoss_Templar_Archives 1 10729
Protoss_Dark_Templar 5 15161
Protoss_Nexus 1 14658
Protoss_Robotics_Facility 1 16359
16359
