Protoss_Gateway 2 13846
Protoss_Assimilator 1 4208
Protoss_Cybernetics_Core 1 5865
Protoss_Zealot 2 11847
Protoss_Robotics_Facility 1 8070
Protoss_Dragoon 4 15063
Protoss_Shuttle 1 9655
Protoss_Robotics_Support_Bay 1 9000
Protoss_Reaver 1 11283
Protoss_Observatory 1 11243
Protoss_Observer 1 13191
Gravitic_Drive 1 12847
Protoss_Nexus 1 17282
17282
