Protoss_Assimilator 3 13305
Protoss_Gateway 2 9895
Protoss_Cybernetics_Core 1 6367
Protoss_Dragoon 7 15420
Protoss_Robotics_Facility 1 9273
Protoss_Zealot 2 10972
Protoss_Shuttle 1 10703
Protoss_Robotics_Support_Bay 1 10125
Protoss_Reaver 1 12261
Protoss_Nexus 1 14333
Protoss_Observatory 1 13260
Protoss_Citadel_of_Adun 1 14026
15420
