Protoss_Gateway 2 10878
Protoss_Assimilator 1 4229
Protoss_Cybernetics_Core 1 5660
Protoss_Dragoon 9 15001
Protoss_Robotics_Facility 1 9557
Protoss_Observatory 1 10298
Singularity_Charge 1 9757
Protoss_Observer 1 11581
Protoss_Shuttle 1 12980
Protoss_Nexus 1 15371
Protoss_Robotics_Support_Bay 1 13857
Protoss_Reaver 1 15905
15905
