Protoss_Gateway 4 14979
Protoss_Zealot 1 5107
Protoss_Nexus 1 8504
Protoss_Assimilator 2 10924
Protoss_Cybernetics_Core 1 8164
Protoss_Dragoon 9 14466
Protoss_Robotics_Facility 1 13172
Singularity_Charge 1 12294
Protoss_Observatory 1 13933
Protoss_Observer 1 14944
Protoss_Citadel_of_Adun 1 15904
15904
