Protoss_Gateway 3 13700
Protoss_Assimilator 1 4193
Protoss_Cybernetics_Core 1 5658
Protoss_Dragoon 10 15639
Protoss_Robotics_Facility 1 10416
Singularity_Charge 1 9941
Protoss_Nexus 1 13117
Protoss_Observatory 1 11205
Protoss_Observer 4 14856
15639
