Protoss_Gateway 3 10843
Protoss_Assimilator 2 5674
Protoss_Zealot 5 15097
Protoss_Cybernetics_Core 1 8568
Protoss_Dragoon 6 13298
Protoss_Citadel_of_Adun 1 12036
Protoss_Robotics_Facility 1 14890
Singularity_Charge 1 13033
Protoss_Templar_Archives 1 15724
15724
