Protoss_Gateway 4 12137
Protoss_Assimilator 3 7551
Protoss_Zealot 6 9699
Protoss_Cybernetics_Core 1 8843
Protoss_Dragoon 10 15712
Protoss_Robotics_Facility 1 14227
Singularity_Charge 1 12953
Protoss_Shuttle 1 15631
15712
