Protoss_Nexus 1 6893
Protoss_Gateway 4 13682
Protoss_Assimilator 2 12396
Protoss_Cybernetics_Core 1 7641
Protoss_Zealot 5 14657
Protoss_Dragoon 9 15753
Protoss_Robotics_Facility 1 12288
Protoss_Observatory 1 13163
Protoss_Shuttle 1 14115
Singularity_Charge 1 13512
Protoss_Observer 1 14958
15753
