Protoss_Gateway 3 14496
Protoss_Assimilator 1 4532
Protoss_Zealot 1 5219
Protoss_Cybernetics_Core 1 5875
Protoss_Dragoon 11 15731
Protoss_Robotics_Facility 1 10179
Singularity_Charge 1 9836
Protoss_Observatory 1 10889
Protoss_Observer 4 14557
Protoss_Nexus 1 14598
Protoss_Shuttle 1 15633
15731
