Protoss_Gateway 3 15017
Protoss_Assimilator 1 4210
Protoss_Cybernetics_Core 1 5737
Protoss_Dragoon 10 14676
Singularity_Charge 1 9435
Protoss_Nexus 1 13755
Protoss_Robotics_Facility 1 14180
Protoss_Observatory 1 14925
15017
