Protoss_Gateway 3 15677
Protoss_Zealot 4 11715
Protoss_Assimilator 1 5522
Protoss_Cybernetics_Core 1 7458
Protoss_Dragoon 10 14987
Protoss_Nexus 1 14686
Singularity_Charge 1 12139
Protoss_Robotics_Facility 1 14722
15677
