Protoss_Nexus 1 6909
Protoss_Gateway 3 13223
Protoss_Assimilator 2 9700
Protoss_Cybernetics_Core 1 7577
Protoss_Zealot 1 7744
Protoss_Dragoon 14 15733
Protoss_Robotics_Facility 1 12567
Protoss_Observatory 1 13282
Singularity_Charge 1 12900
Protoss_Observer 2 15351
15733
