Protoss_Nexus 2 15453
Protoss_Gateway 2 7647
Protoss_Assimilator 1 5727
Protoss_Cybernetics_Core 1 7296
Protoss_Zealot 3 15213
Protoss_Dragoon 6 12165
Protoss_Robotics_Facility 1 11695
Singularity_Charge 1 11480
Protoss_Shuttle 1 13229
Protoss_Robotics_Support_Bay 1 13617
Protoss_Reaver 1 15343
15453
