Protoss_Gateway 2 8988
Protoss_Assimilator 1 4517
Protoss_Cybernetics_Core 1 5897
Protoss_Dragoon 12 15358
Singularity_Charge 1 9850
Protoss_Nexus 2 15375
Protoss_Robotics_Facility 1 15477
15477
