Protoss_Gateway 2 10694
Protoss_Assimilator 1 4135
Protoss_Cybernetics_Core 1 5549
Protoss_Dragoon 5 14632
Protoss_Citadel_of_Adun 2 8887
Protoss_Robotics_Facility 1 10690
Protoss_Templar_Archives 1 10583
Protoss_Zealot 1 10477
Protoss_Dark_Templar 3 13207
Protoss_Shuttle 1 12312
Protoss_Observatory 1 12091
Protoss_Nexus 1 15473
15473
