Protoss_Gateway 2 7916
Protoss_Assimilator 1 4362
Protoss_Cybernetics_Core 1 5689
Protoss_Dragoon 12 15818
Protoss_Robotics_Facility 1 9737
Singularity_Charge 1 9367
Protoss_Observatory 1 10750
Protoss_Nexus 1 13290
Protoss_Observer 2 12766
15818
