Protoss_Gateway 3 15053
Protoss_Assimilator 1 4372
Protoss_Cybernetics_Core 1 5761
Protoss_Dragoon 6 14387
Protoss_Robotics_Facility 1 8237
Protoss_Shuttle 1 10027
Protoss_Zealot 2 12067
Protoss_Observatory 1 10474
Protoss_Observer 2 14809
Protoss_Robotics_Support_Bay 1 11429
Singularity_Charge 1 11606
Protoss_Reaver 1 13364
Protoss_Nexus 1 15426
15426
