Protoss_Gateway 3 15583
Protoss_Assimilator 2 15138
Protoss_Cybernetics_Core 1 5973
Protoss_Dragoon 11 15753
Protoss_Nexus 2 16247
Protoss_Robotics_Facility 1 11100
Singularity_Charge 1 9827
Protoss_Observatory 1 12124
Protoss_Observer 3 15252
16247
