Protoss_Gateway 4 15416
Protoss_Assimilator 1 4403
Protoss_Cybernetics_Core 1 5635
Protoss_Dragoon 6 13427
Singularity_Charge 1 9663
Protoss_Nexus 2 14665
Protoss_Robotics_Facility 1 12604
Protoss_Observatory 1 13564
Protoss_Observer 1 14619
15416
