Protoss_Gateway 3 12643
Protoss_Assimilator 1 5009
Protoss_Cybernetics_Core 1 6444
Protoss_Dragoon 8 14334
Protoss_Nexus 2 17177
Singularity_Charge 1 10523
Protoss_Robotics_Facility 1 14045
17177
