Protoss_Gateway 1 4189
Protoss_Assimilator 1 4376
Protoss_Cybernetics_Core 1 5787
Protoss_Robotics_Facility 2 15961
Protoss_Dragoon 3 15159
Protoss_Shuttle 1 9456
Protoss_Robotics_Support_Bay 1 9420
Protoss_Zealot 2 10937
Protoss_Reaver 3 15108
Protoss_Nexus 1 14332
Protoss_Observatory 1 12786
15961
