Protoss_Gateway 2 9813
Protoss_Assimilator 1 4359
Protoss_Cybernetics_Core 1 5714
Protoss_Dragoon 10 15543
Protoss_Robotics_Facility 1 9935
Singularity_Charge 1 9578
Protoss_Observatory 1 10901
Protoss_Nexus 1 13202
Protoss_Observer 2 13112
Protoss_Robotics_Support_Bay 1 13446
Protoss_Shuttle 1 14654
15543
