Protoss_Gateway 2 8348
Protoss_Assimilator 1 4732
Protoss_Zealot 1 5592
Protoss_Cybernetics_Core 1 6548
Protoss_Dragoon 9 15644
Singularity_Charge 1 10399
Protoss_Nexus 1 16108
Protoss_Stargate 1 15430
Protoss_Robotics_Facility 1 16135
16135
