Protoss_Gateway 2 7668
Protoss_Zealot 2 5882
Protoss_Assimilator 2 13410
Protoss_Cybernetics_Core 1 7035
Protoss_Dragoon 5 10813
Protoss_Nexus 1 13550
Protoss_Citadel_of_Adun 1 12585
Singularity_Charge 1 11217
Protoss_Robotics_Facility 1 13652
Protoss_Templar_Archives 1 14139
Protoss_Shuttle 1 15383
Protoss_Dark_Templar 2 15388
Protoss_Observatory 1 15200
15388
