Protoss_Gateway 2 9617
Protoss_Assimilator 1 4532
Protoss_Cybernetics_Core 1 5952
Protoss_Dragoon 7 15724
Protoss_Citadel_of_Adun 1 9331
Protoss_Templar_Archives 1 10770
Protoss_Zealot 2 10673
Singularity_Charge 1 9956
Protoss_Dark_Templar 4 13172
Protoss_Nexus 1 15409
15724
