Protoss_Gateway 3 12533
Protoss_Assimilator 1 4474
Protoss_Cybernetics_Core 1 5739
Protoss_Dragoon 11 14354
Protoss_Robotics_Facility 1 9818
Singularity_Charge 1 9882
Protoss_Observatory 1 10643
Protoss_Observer 1 11914
Protoss_Robotics_Support_Bay 1 14467
Protoss_Zealot 1 15014
Protoss_Shuttle 1 15520
15520
