Protoss_Gateway 3 13012
Protoss_Assimilator 2 8672
Protoss_Zealot 4 9860
Protoss_Nexus 1 9082
Protoss_Cybernetics_Core 1 9958
Protoss_Shield_Battery 1 10706
Protoss_Dragoon 6 15543
Protoss_Robotics_Facility 1 14875
Singularity_Charge 1 13962
15543
