Protoss_Gateway 2 9029
Protoss_Zealot 1 5098
Protoss_Nexus 1 8465
Protoss_Assimilator 2 9670
Protoss_Cybernetics_Core 1 8674
Protoss_Dragoon 6 15584
Protoss_Citadel_of_Adun 1 11262
Protoss_Robotics_Facility 1 13166
Protoss_Templar_Archives 1 12839
Protoss_Dark_Templar 2 14038
Protoss_Stargate 1 14605
Protoss_Shuttle 1 14560
Protoss_Observatory 1 15069
15584
