Protoss_Gateway 2 9832
Protoss_Assimilator 2 15427
Protoss_Cybernetics_Core 1 5806
Protoss_Dragoon 8 12999
Protoss_Robotics_Facility 1 9929
Singularity_Charge 1 9707
Protoss_Observatory 1 10851
Protoss_Observer 2 12831
Protoss_Nexus 2 16617
Protoss_Citadel_of_Adun 1 14197
Protoss_Templar_Archives 1 15721
16617
