Protoss_Gateway 2 12681
Protoss_Assimilator 1 4982
Protoss_Cybernetics_Core 1 6768
Protoss_Zealot 1 6658
Protoss_Dragoon 9 15481
Protoss_Nexus 2 17428
Protoss_Robotics_Facility 1 12449
Singularity_Charge 1 10840
Protoss_Observatory 1 13134
Protoss_Observer 2 15380
17428
