Protoss_Gateway 1 4182
Protoss_Assimilator 1 4322
Protoss_Cybernetics_Core 1 5759
Protoss_Dragoon 7 14776
Protoss_Robotics_Facility 1 10731
Singularity_Charge 1 9970
Protoss_Shuttle 1 12230
Protoss_Robotics_Support_Bay 1 11536
Protoss_Reaver 2 15328
Protoss_Nexus 2 17481
17481
