Protoss_Gateway 2 8256
Protoss_Zealot 5 13618
Protoss_Assimilator 1 5623
Protoss_Cybernetics_Core 1 7141
Protoss_Dragoon 8 14981
Protoss_Robotics_Facility 1 12187
Singularity_Charge 1 11709
Protoss_Shuttle 1 13940
Protoss_Robotics_Support_Bay 1 13772
14981
