Protoss_Gateway 4 15781
Protoss_Assimilator 1 4188
Protoss_Cybernetics_Core 1 5671
Protoss_Dragoon 11 14518
Singularity_Charge 1 9841
Protoss_Nexus 1 13111
Protoss_Robotics_Facility 1 13825
Protoss_Observatory 1 14583
15781
