Protoss_Gateway 2 8885
Protoss_Assimilator 1 4395
Protoss_Cybernetics_Core 1 5885
Protoss_Dragoon 5 13634
Protoss_Citadel_of_Adun 1 9252
Protoss_Templar_Archives 1 10883
Singularity_Charge 1 9935
Protoss_Dark_Templar 4 15326
Protoss_Nexus 1 14782
15326
