Protoss_Gateway 1 4381
Protoss_Assimilator 1 4779
Protoss_Zealot 3 7325
Protoss_Cybernetics_Core 1 6576
Protoss_Dragoon 6 15522
Protoss_Robotics_Facility 1 10372
Protoss_Robotics_Support_Bay 1 11107
Singularity_Charge 1 10866
Protoss_Reaver 2 14801
15522
