Protoss_Gateway 2 14231
Protoss_Assimilator 1 4158
Protoss_Cybernetics_Core 1 5551
Protoss_Robotics_Facility 1 7868
Protoss_Dragoon 8 15508
Protoss_Shuttle 1 9271
Protoss_Robotics_Support_Bay 1 9114
Protoss_Reaver 2 14652
Protoss_Observatory 1 13703
Singularity_Charge 1 14126
Protoss_Observer 1 15476
15508
