Protoss_Nexus 1 7015
Protoss_Gateway 3 10786
Protoss_Assimilator 2 13931
Protoss_Cybernetics_Core 1 7381
Protoss_Zealot 2 14803
Protoss_Dragoon 12 15508
Singularity_Charge 1 11384
Protoss_Robotics_Facility 1 14584
Protoss_Observatory 1 15341
15508
