Protoss_Assimilator 3 7309
Protoss_Gateway 4 14232
Protoss_Cybernetics_Core 1 6716
Protoss_Dragoon 9 15534
Protoss_Nexus 2 13720
Singularity_Charge 1 10550
Protoss_Robotics_Facility 1 15329
15534
