Protoss_Gateway 2 14388
Protoss_Assimilator 1 4337
Protoss_Zealot 2 11224
Protoss_Cybernetics_Core 1 6680
Protoss_Dragoon 7 15707
Protoss_Robotics_Facility 1 10185
Protoss_Shuttle 1 11607
Protoss_Robotics_Support_Bay 1 11120
Singularity_Charge 1 10995
Protoss_Reaver 1 13165
Protoss_Nexus 1 15101
Protoss_Observatory 1 13523
Protoss_Observer 1 15029
15707
