Protoss_Gateway 3 14723
Protoss_Assimilator 1 4397
Protoss_Cybernetics_Core 1 5794
Protoss_Dragoon 11 15358
Protoss_Robotics_Facility 1 8245
Protoss_Observatory 1 9077
Protoss_Observer 4 15304
Protoss_Nexus 1 13015
Singularity_Charge 1 11041
Protoss_Citadel_of_Adun 1 15242
15358
