Protoss_Gateway 2 7662
Protoss_Assimilator 2 12633
Protoss_Zealot 13 15105
Protoss_Forge 1 11143
Protoss_Nexus 1 13836
Protoss_Photon_Cannon 2 15657
Protoss_Cybernetics_Core 1 13893
Protoss_Robotics_Facility 1 16195
16195
