Protoss_Assimilator 5 6798
Protoss_Gateway 2 9151
Protoss_Cybernetics_Core 1 6652
Protoss_Robotics_Facility 1 8802
Protoss_Dragoon 6 14811
Protoss_Zealot 2 11408
Protoss_Shuttle 1 10249
Protoss_Robotics_Support_Bay 1 10245
Protoss_Reaver 1 12024
Protoss_Citadel_of_Adun 1 12784
Protoss_Templar_Archives 1 14753
14811
