Protoss_Gateway 3 16044
Protoss_Assimilator 2 6623
Protoss_Zealot 2 7205
Protoss_Cybernetics_Core 1 8417
Protoss_Dragoon 7 14682
Protoss_Nexus 1 14080
Singularity_Charge 1 12274
Protoss_Robotics_Facility 1 14337
Protoss_Observatory 1 15064
16044
