Protoss_Gateway 2 11481
Protoss_Assimilator 3 14862
Protoss_Cybernetics_Core 1 6454
Protoss_Dragoon 10 15607
Protoss_Nexus 2 17033
Protoss_Robotics_Facility 1 11568
Singularity_Charge 1 10245
Protoss_Observatory 1 12528
Protoss_Observer 3 15517
17033
