Protoss_Gateway 2 12833
Protoss_Forge 1 4859
Protoss_Zealot 3 8503
Protoss_Assimilator 1 8326
Protoss_Photon_Cannon 3 15427
Protoss_Cybernetics_Core 1 9589
Protoss_Dragoon 2 14956
Protoss_Citadel_of_Adun 1 12029
Protoss_Robotics_Facility 1 13039
Protoss_Templar_Archives 1 14003
Protoss_Shuttle 1 14469
15427
