Protoss_Gateway 4 15880
Protoss_Assimilator 1 4217
Protoss_Cybernetics_Core 1 5639
Protoss_Zealot 2 11991
Protoss_Dragoon 3 13337
Protoss_Robotics_Facility 1 9712
Protoss_Nexus 2 16339
Singularity_Charge 1 9648
Protoss_Shuttle 1 11320
Protoss_Robotics_Support_Bay 1 11290
Protoss_Reaver 1 13063
Protoss_Observatory 1 12503
Protoss_Observer 2 15367
16339
