Protoss_Gateway 3 15778
Protoss_Assimilator 1 4612
Protoss_Cybernetics_Core 1 6110
Protoss_Dragoon 8 15175
Protoss_Nexus 2 13862
Singularity_Charge 1 10326
Protoss_Robotics_Facility 1 15004
15778
