Protoss_Gateway 3 14107
Protoss_Assimilator 1 4524
Protoss_Cybernetics_Core 1 6029
Protoss_Dragoon 12 15136
Protoss_Nexus 1 11995
Singularity_Charge 1 9900
Protoss_Robotics_Facility 1 13396
Protoss_Shuttle 1 15324
Protoss_Observatory 1 14927
Protoss_Robotics_Support_Bay 1 15335
15335
