Protoss_Gateway 2 8789
Protoss_Assimilator 1 4229
Protoss_Cybernetics_Core 1 5828
Protoss_Dragoon 9 14433
Protoss_Robotics_Facility 1 9982
Singularity_Charge 1 9704
Protoss_Shuttle 1 11379
Protoss_Robotics_Support_Bay 1 10975
Protoss_Reaver 1 12937
Protoss_Observatory 1 12590
14433
