Protoss_Gateway 3 15340
Protoss_Assimilator 1 4242
Protoss_Cybernetics_Core 1 5850
Protoss_Dragoon 8 14840
Protoss_Robotics_Facility 1 10994
Singularity_Charge 1 9906
Protoss_Shuttle 1 12485
Protoss_Robotics_Support_Bay 1 12533
Protoss_Nexus 1 14847
Protoss_Reaver 2 16188
16188
