Protoss_Gateway 2 9549
Protoss_Assimilator 1 4164
Protoss_Cybernetics_Core 1 5768
Protoss_Dragoon 11 15704
Protoss_Robotics_Facility 1 11575
Singularity_Charge 1 9768
Protoss_Nexus 1 13743
Protoss_Observatory 1 12936
Protoss_Observer 1 13972
Protoss_Shuttle 1 15330
15704
