Protoss_Gateway 2 9763
Protoss_Zealot 3 7117
Protoss_Assimilator 1 5402
Protoss_Cybernetics_Core 1 7224
Protoss_Dragoon 10 15411
Protoss_Robotics_Facility 1 12442
Singularity_Charge 1 11018
Protoss_Observatory 1 13307
Protoss_Nexus 1 16268
Protoss_Observer 2 15512
16268
