Protoss_Gateway 2 13277
Protoss_Assimilator 2 12209
Protoss_Cybernetics_Core 1 5774
Protoss_Dragoon 9 15180
Protoss_Robotics_Facility 1 10336
Singularity_Charge 1 9719
Protoss_Nexus 1 12862
Protoss_Observatory 1 11210
Protoss_Citadel_of_Adun 1 13385
Protoss_Observer 3 15517
Protoss_Stargate 1 15108
Protoss_Templar_Archives 1 15125
15517
