Protoss_Gateway 2 8933
Protoss_Assimilator 2 15450
Protoss_Cybernetics_Core 1 5654
Protoss_Dragoon 8 14723
Singularity_Charge 1 9815
Protoss_Nexus 2 16792
Protoss_Robotics_Facility 1 12903
Protoss_Citadel_of_Adun 1 13343
Protoss_Templar_Archives 1 14878
16792
