Protoss_Gateway 3 13788
Protoss_Assimilator 1 4422
Protoss_Cybernetics_Core 1 5721
Protoss_Zealot 3 10676
Protoss_Robotics_Facility 1 7945
Protoss_Dragoon 4 14630
Protoss_Shuttle 1 9339
Protoss_Robotics_Support_Bay 1 8877
Protoss_Reaver 2 15059
Protoss_Observatory 1 11237
Protoss_Nexus 1 14007
Protoss_Observer 2 13463
15059
