Protoss_Nexus 2 11528
Protoss_Gateway 5 15658
Protoss_Assimilator 2 10950
Protoss_Cybernetics_Core 1 7628
Protoss_Dragoon 7 14954
Protoss_Citadel_of_Adun 1 11177
Protoss_Templar_Archives 1 12629
Singularity_Charge 1 11618
Protoss_Stargate 1 14080
Protoss_Dark_Templar 2 13839
Protoss_Forge 1 14636
15658
