Protoss_Assimilator 2 5026
Protoss_Gateway 2 6912
Protoss_Zealot 2 7284
Protoss_Cybernetics_Core 1 7578
Protoss_Dragoon 7 12317
Protoss_Citadel_of_Adun 1 12169
Singularity_Charge 1 11489
Protoss_Templar_Archives 1 13691
Protoss_Nexus 1 15611
Protoss_Dark_Templar 2 14949
Protoss_Robotics_Facility 1 16394
16394
