Protoss_Gateway 4 14058
Protoss_Assimilator 1 4232
Protoss_Cybernetics_Core 1 5721
Protoss_Dragoon 12 15756
Protoss_Nexus 2 13202
Singularity_Charge 1 9420
Protoss_Robotics_Facility 1 13475
Protoss_Observatory 1 14763
15756
