Protoss_Gateway 2 12225
Protoss_Assimilator 2 15371
Protoss_Cybernetics_Core 1 6023
Protoss_Zealot 1 5838
Protoss_Dragoon 8 15180
Protoss_Nexus 1 12106
Protoss_Robotics_Facility 1 11877
Singularity_Charge 1 10207
Protoss_Shuttle 1 13975
Protoss_Observatory 1 13474
Protoss_Robotics_Support_Bay 1 14261
Protoss_Observer 1 14818
15371
