Protoss_Gateway 2 14009
Protoss_Assimilator 1 4135
Protoss_Zealot 1 5101
Protoss_Cybernetics_Core 1 5990
Protoss_Dragoon 9 15244
Protoss_Nexus 2 14517
Singularity_Charge 1 9666
Protoss_Robotics_Facility 1 13734
Protoss_Shuttle 1 15154
Protoss_Robotics_Support_Bay 1 14539
15244
