Protoss_Gateway 3 12403
Protoss_Assimilator 2 14695
Protoss_Cybernetics_Core 1 5680
Protoss_Dragoon 9 14044
Protoss_Nexus 1 12217
Singularity_Charge 1 9584
Protoss_Robotics_Facility 1 11726
Protoss_Citadel_of_Adun 1 12817
Protoss_Observatory 1 12790
Protoss_Observer 1 13905
Protoss_Templar_Archives 1 15034
15034
