Protoss_Gateway 2 10337
Protoss_Assimilator 2 14952
Protoss_Cybernetics_Core 1 5761
Protoss_Dragoon 10 15484
Protoss_Robotics_Facility 1 10438
Singularity_Charge 1 9856
Protoss_Observatory 1 11194
Protoss_Nexus 2 15423
Protoss_Observer 2 15143
15484
