Protoss_Gateway 2 15350
Protoss_Assimilator 2 5910
Protoss_Zealot 1 5288
Protoss_Cybernetics_Core 1 7435
Protoss_Dragoon 6 14682
Protoss_Robotics_Facility 1 11565
Singularity_Charge 1 11249
Protoss_Shuttle 1 13015
Protoss_Robotics_Support_Bay 1 12335
Protoss_Reaver 2 16270
16270
