Protoss_Gateway 2 9138
Protoss_Assimilator 1 4404
Protoss_Cybernetics_Core 1 5794
Protoss_Dragoon 9 14155
Protoss_Nexus 2 13635
Singularity_Charge 1 9815
Protoss_Robotics_Facility 1 13750
Protoss_Shuttle 1 15178
Protoss_Zealot 2 15055
Protoss_Observatory 1 14854
15178
