Protoss_Gateway 3 15675
Protoss_Assimilator 2 4843
Protoss_Zealot 2 12321
Protoss_Cybernetics_Core 1 6662
Protoss_Dragoon 5 15124
Protoss_Robotics_Facility 1 10811
Singularity_Charge 1 10430
Protoss_Shuttle 1 12254
Protoss_Robotics_Support_Bay 1 12007
Protoss_Reaver 1 13827
Protoss_Nexus 1 16085
Protoss_Observatory 1 14393
Protoss_Observer 1 15447
16085
