Protoss_Gateway 3 13460
Protoss_Assimilator 1 4289
Protoss_Cybernetics_Core 1 5690
Protoss_Dragoon 9 15145
Protoss_Robotics_Facility 1 9630
Singularity_Charge 1 9528
Protoss_Observatory 1 10380
Protoss_Nexus 1 13099
Protoss_Observer 2 12286
Protoss_Shuttle 1 13969
Protoss_Robotics_Support_Bay 1 14309
Protoss_Reaver 1 16297
16297
