Protoss_Gateway 2 9909
Protoss_Assimilator 1 4207
Protoss_Cybernetics_Core 1 5582
Protoss_Dragoon 6 11975
Protoss_Robotics_Facility 1 10141
Singularity_Charge 1 9458
Protoss_Observatory 1 11088
Protoss_Nexus 2 15540
Protoss_Observer 1 12116
Protoss_Shuttle 1 13603
Protoss_Robotics_Support_Bay 1 13737
Protoss_Reaver 1 15474
Protoss_Zealot 2 15090
15540
