Protoss_Gateway 2 8049
Protoss_Assimilator 1 4365
Protoss_Cybernetics_Core 1 5686
Protoss_Dragoon 11 14766
Singularity_Charge 1 9560
Protoss_Nexus 1 15472
Protoss_Robotics_Facility 1 14559
15472
