Protoss_Gateway 2 13448
Protoss_Assimilator 1 4496
Protoss_Cybernetics_Core 1 5746
Protoss_Dragoon 7 15818
Protoss_Robotics_Facility 1 9680
Protoss_Shuttle 1 11197
Singularity_Charge 1 9803
Protoss_Observatory 1 10753
Protoss_Robotics_Support_Bay 1 10898
Protoss_Zealot 2 12301
Protoss_Reaver 1 13003
Protoss_Observer 1 14035
Protoss_Nexus 1 16866
16866
