Protoss_Nexus 1 6687
Protoss_Gateway 2 7597
Protoss_Assimilator 2 10152
Protoss_Cybernetics_Core 1 7332
Protoss_Dragoon 10 13816
Protoss_Citadel_of_Adun 1 11430
Singularity_Charge 1 11457
Protoss_Templar_Archives 1 13771
Protoss_Stargate 1 14940
14940
