Protoss_Gateway 2 7855
Protoss_Assimilator 1 4356
Protoss_Cybernetics_Core 1 5601
Protoss_Dragoon 12 15519
Singularity_Charge 1 9642
Protoss_Nexus 1 12698
Protoss_Robotics_Facility 1 12986
Protoss_Observatory 1 13765
Protoss_Observer 1 14777
15519
