Protoss_Gateway 3 15798
Protoss_Assimilator 1 4568
Protoss_Cybernetics_Core 1 5781
Protoss_Dragoon 8 15818
Protoss_Robotics_Facility 1 8552
Protoss_Zealot 1 9116
Protoss_Shuttle 1 10035
Protoss_Observatory 1 10681
Protoss_Robotics_Support_Bay 1 11302
Protoss_Observer 2 15242
Singularity_Charge 1 11606
Protoss_Reaver 1 13604
Protoss_Nexus 1 16170
16170
