Protoss_Gateway 3 13230
Protoss_Assimilator 1 4164
Protoss_Cybernetics_Core 1 5786
Protoss_Dragoon 10 15531
Protoss_Nexus 1 12245
Singularity_Charge 1 9862
Protoss_Robotics_Facility 1 13526
Protoss_Zealot 2 14183
Protoss_Observatory 1 15057
15531
