Protoss_Gateway 3 14398
Protoss_Assimilator 1 4387
Protoss_Cybernetics_Core 1 5592
Protoss_Dragoon 10 14963
Protoss_Robotics_Facility 1 9551
Protoss_Observatory 1 10310
Singularity_Charge 1 9604
Protoss_Observer 3 13697
Protoss_Nexus 1 13369
14963
