Protoss_Gateway 3 14512
Protoss_Zealot 1 5110
Protoss_Nexus 1 7634
Protoss_Assimilator 2 9181
Protoss_Cybernetics_Core 1 7738
Protoss_Dragoon 12 15712
Protoss_Robotics_Facility 1 11752
Protoss_Observatory 1 12636
Protoss_Observer 2 14531
Singularity_Charge 1 12976
15712
