Protoss_Gateway 4 14831
Protoss_Assimilator 1 4406
Protoss_Cybernetics_Core 1 5806
Protoss_Dragoon 8 15642
Protoss_Nexus 2 14542
Singularity_Charge 1 9707
Protoss_Robotics_Facility 1 11746
Protoss_Observatory 1 12511
Protoss_Observer 3 15427
Protoss_Shuttle 1 16015
16015
