Protoss_Gateway 2 15659
Protoss_Assimilator 1 4590
Protoss_Cybernetics_Core 1 6099
Protoss_Dragoon 7 14861
Protoss_Robotics_Facility 1 10191
Protoss_Shuttle 1 11813
Protoss_Robotics_Support_Bay 1 11198
Singularity_Charge 1 11504
Protoss_Observatory 2 12734
Protoss_Reaver 1 13398
Protoss_Nexus 1 16420
Protoss_Observer 2 15576
16420
