Protoss_Gateway 4 15798
Protoss_Assimilator 1 4416
Protoss_Cybernetics_Core 1 5828
Protoss_Dragoon 8 14840
Protoss_Robotics_Facility 1 9674
Singularity_Charge 1 9736
Protoss_Observatory 1 10752
Protoss_Observer 1 11821
Protoss_Zealot 4 13302
Protoss_Shuttle 1 13208
Protoss_Nexus 1 15371
Protoss_Robotics_Support_Bay 1 14597
15798
