Protoss_Gateway 2 10937
Protoss_Assimilator 2 15068
Protoss_Cybernetics_Core 1 5610
Protoss_Dragoon 8 14817
Protoss_Citadel_of_Adun 1 9383
Protoss_Templar_Archives 1 10852
Singularity_Charge 1 9821
Protoss_Dark_Templar 2 12148
Protoss_Nexus 2 17411
Protoss_Stargate 1 14870
17411
