Protoss_Nexus 1 6842
Protoss_Gateway 4 15889
Protoss_Assimilator 2 12959
Protoss_Cybernetics_Core 1 7404
Protoss_Zealot 1 7823
Protoss_Dragoon 12 15499
Protoss_Robotics_Facility 1 12560
Singularity_Charge 1 11756
Protoss_Observatory 1 13301
Protoss_Observer 1 14317
15889
