Protoss_Nexus 1 7012
Protoss_Gateway 3 13327
Protoss_Assimilator 2 12517
Protoss_Cybernetics_Core 1 7884
Protoss_Zealot 2 14288
Protoss_Dragoon 9 13889
Protoss_Robotics_Facility 1 12665
Singularity_Charge 1 12124
Protoss_Shuttle 1 14317
Protoss_Robotics_Support_Bay 1 14079
14317
