Protoss_Gateway 3 13160
Protoss_Assimilator 1 4196
Protoss_Cybernetics_Core 1 5649
Protoss_Dragoon 10 15080
Protoss_Nexus 1 11807
Singularity_Charge 1 9572
Protoss_Robotics_Facility 1 11943
Protoss_Observatory 1 12792
Protoss_Observer 1 13981
Protoss_Zealot 2 15254
15254
