Protoss_Gateway 2 10625
Protoss_Assimilator 1 4744
Protoss_Cybernetics_Core 1 5938
Protoss_Zealot 5 13978
Protoss_Dragoon 6 12227
Protoss_Robotics_Facility 1 10330
Singularity_Charge 1 10131
Protoss_Robotics_Support_Bay 1 11892
Protoss_Shuttle 1 13275
Protoss_Reaver 1 15454
Protoss_Nexus 1 17030
17030
