Protoss_Gateway 2 9757
Protoss_Zealot 4 7867
Protoss_Assimilator 1 5309
Protoss_Cybernetics_Core 1 7246
Protoss_Dragoon 11 15791
Singularity_Charge 1 11261
Protoss_Nexus 1 16893
16893
