Protoss_Gateway 3 15826
Protoss_Assimilator 1 4253
Protoss_Cybernetics_Core 1 5709
Protoss_Dragoon 11 14995
Protoss_Robotics_Facility 1 11094
Singularity_Charge 1 9762
Protoss_Observatory 1 11852
Protoss_Observer 3 15201
Protoss_Nexus 1 15498
15826
