Protoss_Gateway 2 12626
Protoss_Assimilator 2 13709
Protoss_Cybernetics_Core 1 5695
Protoss_Zealot 1 5663
Protoss_Dragoon 8 14319
Protoss_Nexus 1 12432
Singularity_Charge 1 9941
Protoss_Citadel_of_Adun 1 12005
Protoss_Templar_Archives 1 13609
Protoss_Robotics_Facility 1 14230
Protoss_Dark_Templar 2 15443
Protoss_Shuttle 1 15634
Protoss_Observatory 1 15278
15634
