Protoss_Gateway 2 11493
Protoss_Assimilator 2 13722
Protoss_Cybernetics_Core 1 5865
Protoss_Zealot 3 14938
Protoss_Dragoon 6 12751
Protoss_Nexus 1 12119
Singularity_Charge 1 10029
Protoss_Robotics_Facility 1 12385
Protoss_Citadel_of_Adun 1 12917
Protoss_Observatory 1 13198
Protoss_Templar_Archives 1 14398
Protoss_Observer 1 14235
Protoss_Stargate 1 15937
Protoss_Shuttle 1 15816
Protoss_Dark_Templar 2 15669
15937
