Protoss_Gateway 2 10401
Protoss_Assimilator 1 4504
Protoss_Cybernetics_Core 1 5676
Protoss_Dragoon 8 15294
Protoss_Robotics_Facility 1 10198
Singularity_Charge 1 9880
Protoss_Observatory 1 10901
Protoss_Observer 2 14303
Protoss_Nexus 1 14118
Protoss_Shuttle 1 13460
Protoss_Robotics_Support_Bay 1 13484
Protoss_Reaver 1 15369
15369
