Protoss_Gateway 3 13089
Protoss_Assimilator 1 4622
Protoss_Cybernetics_Core 1 5941
Protoss_Dragoon 9 15710
Protoss_Robotics_Facility 1 8720
Protoss_Observatory 1 9486
Protoss_Observer 2 11483
Singularity_Charge 1 11936
Protoss_Nexus 1 16303
16303
