Protoss_Gateway 3 15386
Protoss_Assimilator 1 4589
Protoss_Cybernetics_Core 1 6026
Protoss_Dragoon 8 14217
Protoss_Robotics_Facility 1 8648
Protoss_Observatory 1 9516
Protoss_Observer 1 10575
Protoss_Nexus 1 13819
Protoss_Shuttle 1 13387
Singularity_Charge 1 12243
Protoss_Citadel_of_Adun 1 14595
Protoss_Zealot 2 15078
15386
