Protoss_Nexus 1 6868
Protoss_Gateway 3 13965
Protoss_Assimilator 2 11462
Protoss_Cybernetics_Core 1 7603
Protoss_Zealot 1 7489
Protoss_Dragoon 7 13825
Protoss_Citadel_of_Adun 1 11370
Protoss_Templar_Archives 1 12816
Singularity_Charge 1 12177
Protoss_Robotics_Facility 1 14228
Protoss_Dark_Templar 4 15124
Protoss_Forge 1 14787
Protoss_Observatory 1 15189
15189
