Protoss_Gateway 2 8156
Protoss_Assimilator 1 4476
Protoss_Cybernetics_Core 1 5769
Protoss_Dragoon 11 14984
Protoss_Robotics_Facility 1 11100
Singularity_Charge 1 9713
Protoss_Nexus 2 16389
Protoss_Observatory 1 11836
Protoss_Observer 2 13744
16389
