Protoss_Gateway 4 15506
Protoss_Assimilator 1 4537
Protoss_Cybernetics_Core 1 6012
Protoss_Dragoon 8 14313
Protoss_Robotics_Facility 1 9935
Singularity_Charge 1 9944
Protoss_Observatory 1 10678
Protoss_Observer 4 14458
Protoss_Nexus 2 15292
15506
