Protoss_Assimilator 2 5042
Protoss_Gateway 3 10799
Protoss_Zealot 2 12983
Protoss_Cybernetics_Core 1 7388
Protoss_Dragoon 6 15174
Protoss_Robotics_Facility 1 10286
Protoss_Shuttle 1 11683
Protoss_Robotics_Support_Bay 1 11717
Singularity_Charge 1 11240
Protoss_Reaver 1 13534
Protoss_Nexus 1 15827
Protoss_Observatory 1 14056
Protoss_Observer 1 15113
15827
