Protoss_Gateway 3 14948
Protoss_Assimilator 1 4205
Protoss_Cybernetics_Core 1 5569
Protoss_Dragoon 6 15033
Protoss_Robotics_Facility 1 9604
Singularity_Charge 1 9239
Protoss_Shuttle 1 11016
Protoss_Robotics_Support_Bay 1 11034
Protoss_Reaver 1 13130
Protoss_Zealot 2 14733
Protoss_Nexus 1 14791
Protoss_Observatory 1 13204
Protoss_Observer 2 15131
15131
