Protoss_Gateway 4 15656
Protoss_Assimilator 1 4445
Protoss_Cybernetics_Core 1 5806
Protoss_Dragoon 8 15674
Protoss_Robotics_Facility 1 9892
Singularity_Charge 1 9900
Protoss_Observatory 1 10658
Protoss_Nexus 2 15385
Protoss_Observer 3 14765
15674
