Protoss_Gateway 2 10407
Protoss_Assimilator 1 4369
Protoss_Cybernetics_Core 1 6096
Protoss_Dragoon 11 15133
Protoss_Robotics_Facility 1 10544
Singularity_Charge 1 9768
Protoss_Observatory 1 11335
Protoss_Observer 1 12345
Protoss_Citadel_of_Adun 1 14840
15133
