Protoss_Gateway 4 15390
Protoss_Assimilator 1 4290
Protoss_Cybernetics_Core 1 5671
Protoss_Zealot 1 5718
Protoss_Dragoon 7 14770
Protoss_Citadel_of_Adun 1 8484
Protoss_Templar_Archives 1 9959
Singularity_Charge 1 10005
Protoss_Dark_Templar 2 11469
Protoss_Nexus 1 14608
Protoss_Robotics_Facility 1 15162
15390
