Protoss_Gateway 2 6817
Protoss_Assimilator 2 4599
Protoss_Cybernetics_Core 1 6112
Protoss_Dragoon 5 10251
Protoss_Citadel_of_Adun 1 10199
Singularity_Charge 1 9877
Protoss_Templar_Archives 1 11985
Protoss_Robotics_Facility 1 13110
Protoss_Dark_Templar 4 15151
Protoss_Shuttle 1 14560
Protoss_Nexus 1 16954
16954
