Protoss_Gateway 3 11688
Protoss_Zealot 1 5112
Protoss_Nexus 1 8364
Protoss_Assimilator 2 9539
Protoss_Cybernetics_Core 1 8042
Protoss_Dragoon 9 15013
Protoss_Robotics_Facility 1 12398
Protoss_Observatory 1 13193
Protoss_Shuttle 1 14057
Singularity_Charge 1 12757
Protoss_Observer 1 14900
15013
