Protoss_Gateway 2 9391
Protoss_Zealot 2 6102
Protoss_Nexus 2 16969
Protoss_Assimilator 2 9418
Protoss_Cybernetics_Core 1 8572
Protoss_Dragoon 7 14334
Protoss_Robotics_Facility 1 11509
Protoss_Observatory 1 12259
Protoss_Shuttle 1 13738
Protoss_Observer 2 14183
Protoss_Robotics_Support_Bay 1 13291
Protoss_Reaver 1 16025
Singularity_Charge 1 14480
16969
