Protoss_Gateway 2 8153
Protoss_Assimilator 1 4214
Protoss_Cybernetics_Core 1 5689
Protoss_Dragoon 13 15683
Singularity_Charge 1 9675
Protoss_Nexus 1 14141
Protoss_Robotics_Facility 1 14302
15683
