Protoss_Gateway 3 14569
Protoss_Assimilator 2 12708
Protoss_Cybernetics_Core 1 5809
Protoss_Nexus 1 8940
Protoss_Dragoon 10 13807
Singularity_Charge 1 10600
Protoss_Robotics_Facility 1 12545
Protoss_Observatory 1 13263
Protoss_Shuttle 1 14332
Protoss_Zealot 2 14669
Protoss_Observer 1 15175
15175
