Protoss_Assimilator 3 10870
Protoss_Gateway 2 10694
Protoss_Zealot 4 9377
Protoss_Nexus 2 16799
Protoss_Cybernetics_Core 1 9526
Protoss_Dragoon 7 14733
Protoss_Robotics_Facility 1 13633
Protoss_Observatory 1 14356
Protoss_Observer 1 15380
Singularity_Charge 1 14478
Protoss_Robotics_Support_Bay 1 15347
16799
