Protoss_Nexus 1 6846
Protoss_Gateway 2 7941
Protoss_Assimilator 2 12646
Protoss_Zealot 3 13343
Protoss_Cybernetics_Core 1 7466
Protoss_Dragoon 7 13599
Protoss_Citadel_of_Adun 1 11168
Protoss_Templar_Archives 1 13057
Protoss_Forge 1 13480
Protoss_Dark_Templar 2 14703
Protoss_Photon_Cannon 1 14915
Protoss_Stargate 1 15612
15612
