Protoss_Gateway 4 15015
Protoss_Assimilator 2 4908
Protoss_Cybernetics_Core 1 6348
Protoss_Dragoon 9 15633
Singularity_Charge 1 10181
Protoss_Nexus 1 13743
Protoss_Robotics_Facility 1 13405
Protoss_Shuttle 1 14832
Protoss_Observatory 1 14786
15633
