Protoss_Gateway 2 8060
Protoss_Assimilator 1 4249
Protoss_Cybernetics_Core 1 5797
Protoss_Zealot 1 5628
Protoss_Citadel_of_Adun 1 7629
Protoss_Templar_Archives 1 9078
Protoss_Dark_Templar 4 11448
Protoss_Nexus 2 14607
Protoss_Stargate 1 14268
14607
