Protoss_Nexus 1 6704
Protoss_Gateway 5 15337
Protoss_Assimilator 2 11474
Protoss_Cybernetics_Core 1 7209
Protoss_Zealot 3 15476
Protoss_Dragoon 12 14867
Singularity_Charge 1 11039
Protoss_Robotics_Facility 1 13282
Protoss_Citadel_of_Adun 1 14870
Protoss_Observatory 1 14299
Protoss_Observer 1 15415
15476
