Protoss_Gateway 4 15582
Protoss_Assimilator 1 4586
Protoss_Cybernetics_Core 1 5882
Protoss_Dragoon 9 15546
Protoss_Robotics_Facility 1 9970
Singularity_Charge 1 9707
Protoss_Nexus 2 15401
Protoss_Observatory 1 11192
Protoss_Observer 4 15506
15582
