Protoss_Assimilator 2 5036
Protoss_Gateway 2 8894
Protoss_Cybernetics_Core 1 6276
Protoss_Zealot 1 6269
Protoss_Dragoon 8 13684
Protoss_Nexus 1 13129
Singularity_Charge 1 10684
Protoss_Citadel_of_Adun 1 13044
Protoss_Templar_Archives 1 14592
Protoss_Stargate 1 15152
Protoss_Dark_Templar 2 15797
15797
