Protoss_Gateway 4 15948
Protoss_Assimilator 1 4158
Protoss_Cybernetics_Core 1 5585
Protoss_Dragoon 8 14954
Protoss_Robotics_Facility 1 10109
Singularity_Charge 1 9590
Protoss_Observatory 1 10810
Protoss_Nexus 2 14952
Protoss_Observer 4 14701
15948
