Protoss_Nexus 1 6769
Protoss_Gateway 5 13141
Protoss_Assimilator 2 10984
Protoss_Cybernetics_Core 1 7534
Protoss_Dragoon 10 14480
Protoss_Robotics_Facility 1 12469
Singularity_Charge 1 11917
Protoss_Shuttle 1 14142
Protoss_Observatory 1 13497
Protoss_Observer 1 14985
Protoss_Zealot 4 15342
15342
