Protoss_Nexus 3 16787
Protoss_Gateway 2 7095
Protoss_Assimilator 2 9132
Protoss_Cybernetics_Core 1 7577
Protoss_Dragoon 6 11062
Protoss_Citadel_of_Adun 1 11595
Singularity_Charge 1 11621
Protoss_Templar_Archives 1 13414
Protoss_Stargate 2 16291
Protoss_Dark_Templar 2 14829
Protoss_Arbiter_Tribunal 1 15940
16787
