Protoss_Nexus 1 6959
Protoss_Gateway 5 15648
Protoss_Assimilator 2 9443
Protoss_Zealot 1 7384
Protoss_Cybernetics_Core 1 7951
Protoss_Dragoon 13 15751
Protoss_Robotics_Facility 1 12389
Singularity_Charge 1 11694
Protoss_Observatory 1 13225
Protoss_Citadel_of_Adun 1 14499
Protoss_Observer 2 15315
15751
