Protoss_Gateway 4 14289
Protoss_Assimilator 1 4615
Protoss_Cybernetics_Core 1 5961
Protoss_Dragoon 11 15578
Protoss_Robotics_Facility 1 10090
Protoss_Observatory 1 10847
Singularity_Charge 1 10187
Protoss_Observer 2 12968
Protoss_Nexus 1 14415
15578
