Protoss_Gateway 2 15121
Protoss_Assimilator 2 4786
Protoss_Cybernetics_Core 1 5911
Protoss_Zealot 3 12757
Protoss_Dragoon 6 14413
Protoss_Robotics_Facility 1 10766
Singularity_Charge 1 10163
Protoss_Shuttle 1 12623
Protoss_Robotics_Support_Bay 1 11971
Protoss_Reaver 1 14181
Protoss_Observatory 1 15272
15272
