Protoss_Gateway 2 12149
Protoss_Assimilator 2 13824
Protoss_Cybernetics_Core 1 6149
Protoss_Zealot 1 6336
Protoss_Dragoon 6 13520
Protoss_Nexus 1 12280
Protoss_Robotics_Facility 1 11906
Protoss_Citadel_of_Adun 1 11695
Singularity_Charge 1 10494
Protoss_Templar_Archives 1 13173
Protoss_Observatory 1 12666
Protoss_Shuttle 1 14162
Protoss_Dark_Templar 2 14433
Protoss_Observer 1 15067
Protoss_Stargate 1 16152
16152
