Protoss_Gateway 2 15609
Protoss_Assimilator 1 4290
Protoss_Cybernetics_Core 1 5718
Protoss_Dragoon 7 14849
Protoss_Robotics_Facility 1 8392
Protoss_Shuttle 1 10275
Protoss_Zealot 1 10413
Protoss_Observatory 1 10210
Protoss_Observer 2 14513
Protoss_Robotics_Support_Bay 1 11218
Protoss_Reaver 1 13033
Singularity_Charge 1 11416
Protoss_Nexus 1 15985
15985
