Protoss_Gateway 2 10910
Protoss_Assimilator 2 13774
Protoss_Cybernetics_Core 1 5993
Protoss_Dragoon 5 12203
Protoss_Nexus 1 11582
Singularity_Charge 1 10002
Protoss_Robotics_Facility 1 11934
Protoss_Shuttle 1 13334
Protoss_Robotics_Support_Bay 1 12737
Protoss_Observatory 1 13283
Protoss_Reaver 1 14892
Protoss_Zealot 4 15538
15538
