Protoss_Gateway 4 13526
Protoss_Assimilator 1 4155
Protoss_Cybernetics_Core 1 5777
Protoss_Robotics_Facility 1 7726
Protoss_Dragoon 13 15592
Protoss_Observatory 1 8682
Protoss_Observer 4 15064
Protoss_Nexus 1 13290
Singularity_Charge 1 12713
15592
