Protoss_Gateway 2 11856
Protoss_Assimilator 1 4799
Protoss_Cybernetics_Core 1 6153
Protoss_Zealot 2 12983
Protoss_Dragoon 4 12007
Protoss_Robotics_Facility 1 10707
Singularity_Charge 1 10253
Protoss_Citadel_of_Adun 1 11951
Protoss_Observatory 1 11416
Protoss_Observer 1 12441
Protoss_Templar_Archives 1 13770
Protoss_Shuttle 1 14784
Protoss_Nexus 1 16617
Protoss_Dark_Templar 2 15249
16617
