Protoss_Gateway 3 13242
Protoss_Assimilator 1 4122
Protoss_Cybernetics_Core 1 5714
Protoss_Zealot 1 5584
Protoss_Dragoon 11 15540
Protoss_Nexus 1 11750
Singularity_Charge 1 9631
Protoss_Robotics_Facility 1 12025
Protoss_Observatory 1 12958
Protoss_Observer 2 14952
15540
