Protoss_Nexus 1 6839
Protoss_Gateway 3 14660
Protoss_Assimilator 2 10037
Protoss_Cybernetics_Core 1 7463
Protoss_Zealot 1 7706
Protoss_Dragoon 10 15265
Protoss_Robotics_Facility 1 12771
Singularity_Charge 1 11595
Protoss_Citadel_of_Adun 1 14124
Protoss_Observatory 1 13633
Protoss_Observer 1 14666
Protoss_Templar_Archives 1 15993
15993
