Protoss_Gateway 3 13242
Protoss_Assimilator 2 15071
Protoss_Cybernetics_Core 1 5654
Protoss_Dragoon 10 14653
Protoss_Robotics_Facility 1 10213
Singularity_Charge 1 9657
Protoss_Nexus 1 12965
Protoss_Observatory 1 11053
Protoss_Observer 3 15321
Protoss_Citadel_of_Adun 1 15346
15346
