Protoss_Gateway 4 15765
Protoss_Assimilator 1 4472
Protoss_Cybernetics_Core 1 5692
Protoss_Dragoon 11 15824
Protoss_Nexus 1 11749
Singularity_Charge 1 9757
Protoss_Robotics_Facility 1 12352
Protoss_Observatory 1 13722
Protoss_Observer 1 15272
15824
