Protoss_Gateway 3 14851
Protoss_Nexus 1 7983
Protoss_Zealot 2 7723
Protoss_Assimilator 2 10774
Protoss_Cybernetics_Core 1 7833
Protoss_Dragoon 8 14650
Protoss_Stargate 2 15546
Protoss_Robotics_Facility 1 13375
Protoss_Citadel_of_Adun 1 13119
Singularity_Charge 1 12452
Protoss_Fleet_Beacon 1 14364
Protoss_Carrier 1 17743
17743
