Protoss_Gateway 6 15307
Protoss_Assimilator 1 4578
Protoss_Cybernetics_Core 1 6058
Protoss_Dragoon 8 13719
Protoss_Robotics_Facility 1 8613
Protoss_Observatory 1 9557
Protoss_Observer 4 14710
Protoss_Nexus 1 15074
Singularity_Charge 1 12726
15307
