Protoss_Gateway 3 10126
Protoss_Assimilator 1 4635
Protoss_Cybernetics_Core 1 6497
Protoss_Dragoon 4 15790
Protoss_Citadel_of_Adun 1 8392
Protoss_Templar_Archives 1 10426
Protoss_Dark_Templar 6 14905
Protoss_Nexus 1 16317
16317
