Protoss_Gateway 2 10766
Protoss_Assimilator 1 4422
Protoss_Cybernetics_Core 1 5914
Protoss_Zealot 1 5824
Protoss_Dragoon 8 15496
Protoss_Citadel_of_Adun 1 10255
Singularity_Charge 1 9877
Protoss_Templar_Archives 1 12046
Protoss_Dark_Templar 4 14908
Protoss_Nexus 1 16825
Protoss_Robotics_Facility 1 16523
16825
