Protoss_Gateway 2 14247
Protoss_Assimilator 1 4236
Protoss_Cybernetics_Core 1 5860
Protoss_Zealot 2 13322
Protoss_Dragoon 8 15559
Protoss_Robotics_Facility 1 9818
Protoss_Shuttle 1 11227
Singularity_Charge 1 9853
Protoss_Robotics_Support_Bay 1 11441
Protoss_Reaver 1 13168
Protoss_Nexus 1 15008
Protoss_Observatory 1 13658
Protoss_Observer 1 14786
15559
