Protoss_Gateway 5 7897
Protoss_Assimilator 1 7779
Protoss_Cybernetics_Core 1 9349
Protoss_Zealot 2 9719
Protoss_Dragoon 8 14884
Protoss_Robotics_Facility 1 14482
Singularity_Charge 1 13014
Protoss_Shuttle 1 16018
16018
