Protoss_Gateway 2 10461
Protoss_Assimilator 1 4249
Protoss_Cybernetics_Core 1 5764
Protoss_Dragoon 9 15496
Protoss_Robotics_Facility 1 10107
Singularity_Charge 1 9429
Protoss_Observatory 1 11056
Protoss_Observer 2 13123
Protoss_Robotics_Support_Bay 1 13017
Protoss_Nexus 1 15698
Protoss_Zealot 2 14145
Protoss_Shuttle 1 15646
15698
