Protoss_Nexus 2 14651
Protoss_Gateway 2 10252
Protoss_Assimilator 1 6026
Protoss_Cybernetics_Core 1 7594
Protoss_Dragoon 9 15145
Protoss_Robotics_Facility 1 10043
Protoss_Observatory 1 10801
Protoss_Observer 1 12213
Protoss_Shuttle 1 13015
Singularity_Charge 1 12786
15145
