Protoss_Gateway 2 12162
Protoss_Assimilator 2 13877
Protoss_Cybernetics_Core 1 6083
Protoss_Dragoon 9 14574
Protoss_Robotics_Facility 1 10438
Singularity_Charge 1 10067
Protoss_Nexus 1 13102
Protoss_Observatory 1 11297
Protoss_Observer 2 15064
Protoss_Citadel_of_Adun 1 15071
15071
