Protoss_Gateway 2 9576
Protoss_Assimilator 1 4548
Protoss_Cybernetics_Core 1 5979
Protoss_Dragoon 8 15774
Protoss_Citadel_of_Adun 1 8894
Protoss_Templar_Archives 1 10349
Protoss_Nexus 1 13010
Protoss_Dark_Templar 3 12751
15774
