Protoss_Gateway 2 11914
Protoss_Assimilator 2 13773
Protoss_Cybernetics_Core 1 5695
Protoss_Zealot 1 5440
Protoss_Dragoon 7 13781
Protoss_Robotics_Facility 1 9704
Protoss_Observatory 1 10394
Protoss_Nexus 2 17387
Singularity_Charge 1 9701
Protoss_Observer 2 12523
Protoss_Citadel_of_Adun 1 13910
Protoss_Templar_Archives 1 15367
17387
