Protoss_Gateway 4 15648
Protoss_Assimilator 1 4414
Protoss_Cybernetics_Core 1 5769
Protoss_Dragoon 10 14802
Singularity_Charge 1 10029
Protoss_Nexus 2 15377
Protoss_Robotics_Facility 1 15554
15648
