Protoss_Gateway 2 10679
Protoss_Assimilator 1 4624
Protoss_Cybernetics_Core 1 5879
Protoss_Dragoon 8 15508
Protoss_Citadel_of_Adun 2 9937
Protoss_Nexus 1 12491
Protoss_Templar_Archives 1 11494
Protoss_Dark_Templar 2 12936
Protoss_Robotics_Facility 1 14141
15508
