Protoss_Nexus 1 6921
Protoss_Gateway 4 15664
Protoss_Assimilator 2 10464
Protoss_Cybernetics_Core 1 7419
Protoss_Zealot 1 7767
Protoss_Dragoon 10 14390
Protoss_Robotics_Facility 1 11989
Singularity_Charge 1 11636
Protoss_Shuttle 1 13665
Protoss_Robotics_Support_Bay 1 13244
Protoss_Reaver 1 15223
Protoss_Observatory 1 14987
15664
