Protoss_Gateway 2 14270
Protoss_Assimilator 1 4436
Protoss_Cybernetics_Core 1 5660
Protoss_Dragoon 8 15724
Protoss_Robotics_Facility 1 9660
Singularity_Charge 1 9716
Protoss_Shuttle 2 15977
Protoss_Robotics_Support_Bay 1 10817
Protoss_Zealot 2 12190
Protoss_Reaver 1 13014
Protoss_Nexus 1 14785
Protoss_Observatory 1 13077
Protoss_Observer 1 14554
15977
