Protoss_Gateway 2 10013
Protoss_Assimilator 1 4615
Protoss_Cybernetics_Core 1 6043
Protoss_Dragoon 9 14510
Protoss_Robotics_Facility 1 10725
Singularity_Charge 1 10092
Protoss_Observatory 1 11423
Protoss_Observer 3 14490
Protoss_Nexus 1 14883
14883
