Protoss_Gateway 2 11121
Protoss_Assimilator 1 4542
Protoss_Zealot 6 13214
Protoss_Cybernetics_Core 1 6907
Protoss_Dragoon 7 15669
Protoss_Robotics_Facility 1 10842
Protoss_Observatory 1 11565
Protoss_Shuttle 1 12339
Singularity_Charge 1 11223
Protoss_Observer 2 14063
Protoss_Nexus 1 16878
16878
