Protoss_Nexus 2 15628
Protoss_Gateway 2 7524
Protoss_Assimilator 2 10447
Protoss_Cybernetics_Core 1 7799
Protoss_Zealot 1 7937
Protoss_Dragoon 8 14644
Protoss_Robotics_Facility 1 12131
Singularity_Charge 1 11879
Protoss_Shuttle 1 13688
Protoss_Robotics_Support_Bay 1 13845
Protoss_Reaver 1 15659
15659
