Protoss_Gateway 2 6463
Protoss_Assimilator 1 4169
Protoss_Cybernetics_Core 1 5557
Protoss_Dragoon 9 15388
Protoss_Citadel_of_Adun 1 10180
Singularity_Charge 1 9452
Protoss_Templar_Archives 1 12188
Protoss_Nexus 2 16335
Protoss_Dark_Templar 2 13532
16335
