Protoss_Gateway 3 13906
Protoss_Assimilator 1 4747
Protoss_Cybernetics_Core 1 6036
Protoss_Dragoon 9 15424
Protoss_Zealot 5 15072
Protoss_Robotics_Facility 1 11078
Singularity_Charge 1 10172
Protoss_Observatory 1 11862
Protoss_Observer 1 13356
Protoss_Shuttle 1 14909
15424
