Protoss_Gateway 2 10733
Protoss_Assimilator 1 4382
Protoss_Cybernetics_Core 1 5800
Protoss_Dragoon 7 13178
Protoss_Robotics_Facility 1 9914
Singularity_Charge 1 9745
Protoss_Observatory 1 10784
Protoss_Observer 2 12728
Protoss_Nexus 1 14232
Protoss_Shuttle 1 14086
Protoss_Robotics_Support_Bay 1 13658
Protoss_Zealot 2 14835
Protoss_Reaver 1 15780
15780
