Protoss_Gateway 4 15485
Protoss_Assimilator 1 4571
Protoss_Cybernetics_Core 1 5979
Protoss_Dragoon 7 14600
Protoss_Nexus 1 11728
Singularity_Charge 1 10096
Protoss_Robotics_Facility 1 12048
Protoss_Shuttle 1 13530
Protoss_Robotics_Support_Bay 1 12917
Protoss_Reaver 1 15227
15485
