Protoss_Gateway 3 14603
Protoss_Assimilator 2 14718
Protoss_Cybernetics_Core 1 6517
Protoss_Dragoon 10 15519
Protoss_Robotics_Facility 1 10308
Singularity_Charge 1 10275
Protoss_Observatory 1 11006
Protoss_Nexus 1 13326
Protoss_Observer 3 15304
15519
