Protoss_Gateway 2 8145
Protoss_Assimilator 1 4343
Protoss_Cybernetics_Core 1 5592
Protoss_Zealot 1 5619
Protoss_Dragoon 10 14963
Singularity_Charge 1 9742
Protoss_Nexus 1 13527
Protoss_Robotics_Facility 1 13374
Protoss_Shuttle 1 14768
Protoss_Observatory 1 14158
Protoss_Robotics_Support_Bay 1 15083
15083
