Protoss_Gateway 3 14525
Protoss_Assimilator 1 4552
Protoss_Cybernetics_Core 1 5701
Protoss_Dragoon 9 14992
Protoss_Nexus 1 12137
Singularity_Charge 1 9929
Protoss_Robotics_Facility 1 13179
Protoss_Observatory 1 14226
Protoss_Observer 1 15315
15315
