Protoss_Gateway 3 13612
Protoss_Assimilator 1 4313
Protoss_Cybernetics_Core 1 5666
Protoss_Dragoon 7 12853
Singularity_Charge 1 9335
Protoss_Nexus 1 13067
Protoss_Robotics_Facility 1 12955
Protoss_Shuttle 1 14402
Protoss_Robotics_Support_Bay 1 14169
Protoss_Reaver 1 15963
15963
