Protoss_Gateway 3 15750
Protoss_Assimilator 1 4150
Protoss_Cybernetics_Core 1 5712
Protoss_Zealot 3 13357
Protoss_Dragoon 7 14747
Protoss_Nexus 1 11071
Protoss_Robotics_Facility 1 11283
Singularity_Charge 1 9721
Protoss_Shuttle 1 12746
Protoss_Robotics_Support_Bay 1 12876
Protoss_Reaver 1 14628
Protoss_Observatory 1 14660
15750
