Protoss_Gateway 2 10590
Protoss_Assimilator 3 15471
Protoss_Cybernetics_Core 1 6125
Protoss_Zealot 1 6312
Protoss_Dragoon 6 13140
Protoss_Robotics_Facility 1 10378
Singularity_Charge 1 9847
Protoss_Observatory 1 11240
Protoss_Nexus 1 14048
Protoss_Observer 1 12541
Protoss_Shuttle 1 13995
Protoss_Robotics_Support_Bay 1 13532
Protoss_Reaver 1 15553
15553
