Protoss_Gateway 3 14095
Protoss_Assimilator 2 15008
Protoss_Cybernetics_Core 1 5698
Protoss_Dragoon 8 15598
Protoss_Robotics_Facility 1 9774
Singularity_Charge 1 9739
Protoss_Shuttle 1 11229
Protoss_Nexus 1 13418
Protoss_Robotics_Support_Bay 1 11587
Protoss_Reaver 1 13329
Protoss_Observatory 1 12928
Protoss_Observer 2 15093
15598
