Protoss_Gateway 2 13684
Protoss_Assimilator 1 4473
Protoss_Cybernetics_Core 1 5755
Protoss_Zealot 2 13673
Protoss_Dragoon 6 15183
Protoss_Robotics_Facility 1 10172
Singularity_Charge 1 10061
Protoss_Shuttle 1 11578
Protoss_Nexus 1 13641
Protoss_Robotics_Support_Bay 1 11773
Protoss_Reaver 1 13689
Protoss_Observatory 1 13759
Protoss_Observer 1 14827
15183
