Protoss_Nexus 2 14276
Protoss_Gateway 8 15866
Protoss_Assimilator 2 14096
Protoss_Cybernetics_Core 1 7442
Protoss_Dragoon 10 14357
Protoss_Robotics_Facility 1 12651
Singularity_Charge 1 11881
Protoss_Observatory 1 13490
Protoss_Observer 1 14587
15866
