Protoss_Gateway 3 15873
Protoss_Assimilator 1 4785
Protoss_Cybernetics_Core 1 6233
Protoss_Dragoon 7 14378
Protoss_Citadel_of_Adun 1 8606
Protoss_Templar_Archives 1 10147
Singularity_Charge 1 10055
Protoss_Dark_Templar 2 11422
Protoss_Nexus 1 14957
Protoss_Robotics_Facility 1 14902
15873
