Protoss_Gateway 3 14377
Protoss_Assimilator 1 4592
Protoss_Cybernetics_Core 1 5917
Protoss_Dragoon 10 14751
Protoss_Robotics_Facility 1 9949
Protoss_Observatory 1 10692
Singularity_Charge 1 10092
Protoss_Observer 2 12836
Protoss_Nexus 1 15249
15249
