Protoss_Gateway 5 16021
Protoss_Zealot 2 8051
Protoss_Nexus 1 8308
Protoss_Assimilator 2 8873
Protoss_Cybernetics_Core 1 8209
Protoss_Dragoon 7 15244
Protoss_Robotics_Facility 1 10895
Protoss_Shuttle 1 12301
Protoss_Robotics_Support_Bay 1 12275
Protoss_Reaver 1 14002
Protoss_Observatory 1 13548
Singularity_Charge 1 13477
Protoss_Observer 1 14827
16021
