Protoss_Gateway 3 14251
Protoss_Assimilator 1 4352
Protoss_Cybernetics_Core 1 5720
Protoss_Dragoon 10 15578
Protoss_Robotics_Facility 1 8913
Protoss_Observatory 1 9617
Protoss_Observer 3 12561
Protoss_Nexus 1 13448
Singularity_Charge 1 12271
Protoss_Shuttle 1 14952
15578
