Protoss_Gateway 3 14887
Protoss_Zealot 13 13878
Protoss_Forge 1 7144
Protoss_Photon_Cannon 3 10800
Protoss_Assimilator 1 12610
Protoss_Cybernetics_Core 1 13691
Protoss_Dragoon 2 14998
14998
