Protoss_Nexus 2 14210
Protoss_Gateway 2 7747
Protoss_Assimilator 1 6023
Protoss_Cybernetics_Core 1 7524
Protoss_Zealot 3 14786
Protoss_Dragoon 6 13529
Protoss_Robotics_Facility 1 11120
Protoss_Robotics_Support_Bay 1 11854
Protoss_Shuttle 1 13015
Protoss_Observatory 1 13193
Protoss_Reaver 1 14573
Protoss_Air_Weapons_1 1 14378
Protoss_Observer 1 15397
15397
