Protoss_Gateway 3 15888
Protoss_Assimilator 2 13050
Protoss_Cybernetics_Core 1 5717
Protoss_Zealot 1 5569
Protoss_Dragoon 7 15376
Protoss_Citadel_of_Adun 1 8999
Protoss_Templar_Archives 1 10461
Singularity_Charge 1 9704
Protoss_Nexus 1 13196
Protoss_Dark_Templar 1 11855
Protoss_Robotics_Facility 1 13274
Protoss_Observatory 1 14561
Protoss_Stargate 1 16213
Protoss_Observer 1 15582
16213
