Protoss_Gateway 4 14698
Protoss_Assimilator 1 4498
Protoss_Cybernetics_Core 1 5868
Protoss_Dragoon 12 14524
Singularity_Charge 1 10248
Protoss_Nexus 1 15243
Protoss_Zealot 3 15538
15538
