Protoss_Gateway 5 15918
Protoss_Assimilator 2 4818
Protoss_Cybernetics_Core 1 6172
Protoss_Dragoon 7 14931
Protoss_Nexus 2 14207
Singularity_Charge 1 10131
Protoss_Robotics_Facility 1 14097
Protoss_Observatory 1 14826
15918
