Protoss_Gateway 2 13504
Protoss_Assimilator 1 4464
Protoss_Cybernetics_Core 1 5626
Protoss_Zealot 2 13469
Protoss_Dragoon 8 15806
Protoss_Nexus 2 17147
Protoss_Robotics_Facility 1 10491
Protoss_Shuttle 1 11967
Protoss_Robotics_Support_Bay 1 11914
Protoss_Reaver 1 13639
Protoss_Observatory 1 13314
Singularity_Charge 1 12689
Protoss_Observer 2 15432
17147
