Protoss_Nexus 2 16029
Protoss_Gateway 3 15967
Protoss_Assimilator 1 6020
Protoss_Cybernetics_Core 1 7937
Protoss_Zealot 1 8022
Protoss_Dragoon 10 14817
Protoss_Robotics_Facility 1 12405
Singularity_Charge 1 12221
Protoss_Observatory 1 14466
Protoss_Observer 1 15488
16029
