Protoss_Gateway 2 13883
Protoss_Assimilator 1 4126
Protoss_Cybernetics_Core 1 5712
Protoss_Dragoon 8 15388
Protoss_Robotics_Facility 1 9379
Protoss_Shuttle 1 10776
Protoss_Robotics_Support_Bay 1 10190
Protoss_Zealot 1 10439
Singularity_Charge 1 9839
Protoss_Reaver 2 13894
Protoss_Observatory 1 11972
Protoss_Observer 1 14718
15388
