Protoss_Nexus 2 14585
Protoss_Gateway 2 8098
Protoss_Assimilator 2 13832
Protoss_Cybernetics_Core 1 7820
Protoss_Zealot 1 7375
Protoss_Dragoon 8 14706
Protoss_Citadel_of_Adun 1 13670
Singularity_Charge 1 12247
Protoss_Robotics_Facility 1 14648
Protoss_Templar_Archives 1 15476
15476
