Protoss_Nexus 1 6886
Protoss_Gateway 2 7896
Protoss_Assimilator 2 10283
Protoss_Cybernetics_Core 1 7533
Protoss_Dragoon 6 13131
Protoss_Citadel_of_Adun 1 11184
Protoss_Robotics_Facility 1 12589
Protoss_Templar_Archives 1 12852
Singularity_Charge 1 12192
Protoss_Shuttle 1 14077
Protoss_Dark_Templar 2 14231
Protoss_Stargate 1 15147
Protoss_Observatory 1 14290
Protoss_Observer 1 15315
15315
