Protoss_Gateway 4 15113
Protoss_Assimilator 1 4242
Protoss_Cybernetics_Core 1 5730
Protoss_Dragoon 9 15730
Protoss_Citadel_of_Adun 1 9861
Singularity_Charge 1 9426
Protoss_Nexus 1 13792
Protoss_Templar_Archives 1 12510
Protoss_Dark_Templar 2 13956
Protoss_Robotics_Facility 1 15395
15730
