Protoss_Gateway 2 5341
Protoss_Zealot 11 14205
Protoss_Assimilator 1 6779
Protoss_Forge 1 7496
Protoss_Photon_Cannon 2 9006
Protoss_Cybernetics_Core 1 10697
Protoss_Citadel_of_Adun 1 12525
Protoss_Dragoon 2 12731
Protoss_Templar_Archives 1 14126
Protoss_High_Templar 1 15366
15366
