Protoss_Gateway 2 5194
Protoss_Zealot 10 10861
Protoss_Forge 1 6539
Protoss_Photon_Cannon 3 14890
Protoss_Assimilator 1 8380
Protoss_Cybernetics_Core 1 12280
Protoss_Robotics_Facility 1 14209
Protoss_Shuttle 1 15618
Protoss_Robotics_Support_Bay 1 15067
15618
