Protoss_Gateway 1 4220
Protoss_Assimilator 1 4275
Protoss_Cybernetics_Core 1 5727
Protoss_Zealot 2 10963
Protoss_Robotics_Facility 1 8010
Protoss_Dragoon 2 15388
Protoss_Shuttle 1 9456
Protoss_Robotics_Support_Bay 1 9133
Protoss_Reaver 1 11110
Protoss_Observatory 1 10422
Protoss_Observer 3 13792
Protoss_Nexus 1 14273
15388
