Protoss_Gateway 1 4309
Protoss_Assimilator 1 4556
Protoss_Cybernetics_Core 1 5851
Protoss_Stargate 1 7562
Protoss_Dragoon 6 15347
Protoss_Scout 1 9611
Protoss_Robotics_Facility 1 12285
Protoss_Observatory 1 13242
Protoss_Nexus 1 15697
Protoss_Observer 2 15386
Singularity_Charge 1 13904
15697
