Protoss_Gateway 2 6491
Protoss_Assimilator 2 13927
Protoss_Cybernetics_Core 1 5679
Protoss_Dragoon 9 15033
Protoss_Nexus 1 11987
Singularity_Charge 1 9809
Protoss_Robotics_Facility 1 11928
Protoss_Observatory 1 13070
Protoss_Citadel_of_Adun 1 14253
Protoss_Observer 1 14710
Protoss_Templar_Archives 1 15974
Protoss_Stargate 1 16294
16294
