Protoss_Gateway 3 12708
Protoss_Assimilator 2 13526
Protoss_Cybernetics_Core 1 5816
Protoss_Dragoon 4 12499
Protoss_Robotics_Facility 1 9625
Protoss_Nexus 2 16278
Protoss_Observatory 1 10313
Singularity_Charge 1 10017
Protoss_Observer 3 13483
Protoss_Citadel_of_Adun 1 13423
Protoss_Stargate 1 15748
Protoss_Templar_Archives 1 15545
16278
