Protoss_Gateway 2 8153
Protoss_Assimilator 1 4703
Protoss_Cybernetics_Core 1 6185
Protoss_Dragoon 9 14978
Protoss_Robotics_Facility 1 12106
Singularity_Charge 1 10736
Protoss_Observatory 1 12872
Protoss_Observer 1 14000
Protoss_Citadel_of_Adun 1 15453
Protoss_Shuttle 1 15677
Protoss_Zealot 2 15280
15677
