Protoss_Nexus 2 16656
Protoss_Gateway 3 12487
Protoss_Assimilator 2 11118
Protoss_Zealot 1 6822
Protoss_Cybernetics_Core 1 7521
Protoss_Dragoon 13 15268
Singularity_Charge 1 11639
Protoss_Robotics_Facility 1 14328
16656
