Protoss_Gateway 1 4120
Protoss_Assimilator 1 4201
Protoss_Cybernetics_Core 1 5582
Protoss_Dragoon 5 14890
Protoss_Robotics_Facility 1 9623
Singularity_Charge 1 9584
Protoss_Shuttle 1 11028
Protoss_Observatory 1 10418
Protoss_Nexus 2 16910
Protoss_Robotics_Support_Bay 1 11551
Protoss_Observer 3 15312
Protoss_Zealot 2 13422
Protoss_Reaver 1 13607
16910
