Protoss_Nexus 1 6956
Protoss_Gateway 2 7830
Protoss_Assimilator 1 6127
Protoss_Cybernetics_Core 1 7659
Protoss_Zealot 2 13884
Protoss_Dragoon 8 15092
Protoss_Robotics_Facility 1 11545
Protoss_Observatory 1 12569
Protoss_Observer 2 14824
Singularity_Charge 1 13462
15092
