Protoss_Gateway 2 10826
Protoss_Assimilator 2 14797
Protoss_Cybernetics_Core 1 5607
Protoss_Dragoon 9 13681
Protoss_Nexus 2 11589
Singularity_Charge 1 9479
Protoss_Robotics_Facility 1 12086
Protoss_Observatory 1 13220
Protoss_Shuttle 1 14107
Protoss_Observer 1 14950
Protoss_Robotics_Support_Bay 1 14799
Protoss_Zealot 2 15333
Protoss_Citadel_of_Adun 1 16016
16016
