Protoss_Nexus 3 15224
Protoss_Gateway 2 7736
Protoss_Assimilator 1 5727
Protoss_Cybernetics_Core 1 7389
Protoss_Zealot 1 7515
Protoss_Dragoon 6 14264
Protoss_Robotics_Facility 1 13257
Singularity_Charge 1 11375
Protoss_Observatory 1 14214
Protoss_Citadel_of_Adun 1 15418
Protoss_Observer 1 15248
15418
