Protoss_Gateway 2 13117
Protoss_Zealot 6 10493
Protoss_Nexus 2 17226
Protoss_Assimilator 2 12829
Protoss_Cybernetics_Core 1 10012
Protoss_Forge 1 10479
Protoss_Citadel_of_Adun 1 11667
Protoss_Dragoon 2 13353
Protoss_Templar_Archives 1 13269
Protoss_Photon_Cannon 1 14012
Protoss_Dark_Templar 3 15800
Protoss_Stargate 1 15350
17226
