Protoss_Gateway 2 11957
Protoss_Assimilator 1 4401
Protoss_Cybernetics_Core 1 5775
Protoss_Dragoon 6 15294
Protoss_Robotics_Facility 1 10640
Singularity_Charge 1 9877
Protoss_Nexus 2 17215
Protoss_Shuttle 1 12936
Protoss_Observatory 1 12325
Protoss_Zealot 3 13987
Protoss_Observer 1 13779
17215
