Protoss_Gateway 2 10858
Protoss_Assimilator 1 4195
Protoss_Cybernetics_Core 1 5610
Protoss_Dragoon 10 14990
Protoss_Nexus 1 11746
Singularity_Charge 1 9865
Protoss_Robotics_Facility 1 12755
Protoss_Zealot 1 12513
Protoss_Shuttle 1 14827
Protoss_Robotics_Support_Bay 1 14303
14990
