Protoss_Nexus 1 6735
Protoss_Gateway 2 7653
Protoss_Assimilator 1 5873
Protoss_Cybernetics_Core 1 7583
Protoss_Zealot 1 7773
Protoss_Dragoon 8 14700
Protoss_Robotics_Facility 1 12721
Singularity_Charge 1 12215
Protoss_Shuttle 1 14162
Protoss_Robotics_Support_Bay 1 13535
Protoss_Reaver 1 15720
15720
