Protoss_Gateway 2 12602
Protoss_Assimilator 2 13581
Protoss_Cybernetics_Core 1 5712
Protoss_Zealot 1 5493
Protoss_Dragoon 10 15771
Protoss_Robotics_Facility 1 9895
Singularity_Charge 1 9786
Protoss_Observatory 1 10719
Protoss_Nexus 1 13170
Protoss_Observer 4 15473
Protoss_Citadel_of_Adun 1 13925
Protoss_Stargate 1 15814
15814
