Protoss_Nexus 1 6938
Protoss_Gateway 2 7823
Protoss_Assimilator 2 9632
Protoss_Cybernetics_Core 1 7461
Protoss_Zealot 1 7799
Protoss_Dragoon 6 15575
Protoss_Citadel_of_Adun 1 10799
Protoss_Robotics_Facility 1 12521
Protoss_Templar_Archives 1 12346
Singularity_Charge 1 11887
Protoss_Shuttle 1 14001
Protoss_Dark_Templar 2 13828
Protoss_Forge 1 13755
Protoss_Observatory 1 14177
Protoss_Stargate 1 15466
Protoss_Photon_Cannon 1 15351
Protoss_Observer 1 15201
15575
