Protoss_Gateway 4 15450
Protoss_Assimilator 1 4435
Protoss_Cybernetics_Core 1 5676
Protoss_Dragoon 9 15329
Protoss_Robotics_Facility 1 9689
Singularity_Charge 1 9672
Protoss_Observatory 1 10405
Protoss_Observer 3 15131
Protoss_Nexus 2 14976
15450
