Protoss_Assimilator 1 3424
Protoss_Gateway 3 15655
Protoss_Cybernetics_Core 1 5999
Protoss_Dragoon 6 15745
Protoss_Citadel_of_Adun 1 8625
Protoss_Robotics_Facility 1 10105
Protoss_Templar_Archives 1 10612
Singularity_Charge 1 9692
Protoss_Shuttle 1 11759
Protoss_Dark_Templar 4 13544
Protoss_Nexus 1 14757
15745
