Protoss_Gateway 3 12377
Protoss_Assimilator 2 15415
Protoss_Cybernetics_Core 1 5832
Protoss_Dragoon 10 15440
Protoss_Nexus 2 15892
Singularity_Charge 1 9847
Protoss_Robotics_Facility 1 11992
Protoss_Observatory 1 12835
Protoss_Observer 2 15056
Protoss_Citadel_of_Adun 1 15305
15892
