Protoss_Nexus 2 16032
Protoss_Gateway 4 15329
Protoss_Assimilator 1 5749
Protoss_Cybernetics_Core 1 7269
Protoss_Zealot 3 14452
Protoss_Dragoon 12 15765
Protoss_Robotics_Facility 1 12557
Singularity_Charge 1 10933
Protoss_Observatory 1 13374
Protoss_Observer 2 15541
16032
