Protoss_Gateway 3 13581
Protoss_Assimilator 1 4716
Protoss_Cybernetics_Core 1 6261
Protoss_Robotics_Facility 1 8258
Protoss_Dragoon 9 15191
Protoss_Shuttle 2 11332
Protoss_Nexus 1 13559
Protoss_Observatory 1 12212
Singularity_Charge 1 11665
Protoss_Observer 1 15014
15191
