Protoss_Gateway 2 6484
Protoss_Assimilator 2 15293
Protoss_Cybernetics_Core 1 5669
Protoss_Dragoon 10 14188
Singularity_Charge 1 9812
Protoss_Nexus 1 13088
Protoss_Robotics_Facility 1 13462
Protoss_Observatory 1 14211
Protoss_Shuttle 1 14990
Protoss_Robotics_Support_Bay 1 15326
15326
