Protoss_Gateway 2 12974
Protoss_Assimilator 1 4466
Protoss_Zealot 3 7104
Protoss_Cybernetics_Core 1 7068
Protoss_Dragoon 7 14703
Protoss_Nexus 1 12678
Protoss_Robotics_Facility 1 12461
Singularity_Charge 1 10962
Protoss_Shuttle 1 13875
Protoss_Robotics_Support_Bay 1 13940
Protoss_Reaver 1 15711
Protoss_Observatory 1 14779
15711
