Protoss_Gateway 2 13638
Protoss_Assimilator 1 4400
Protoss_Zealot 2 6131
Protoss_Cybernetics_Core 1 6983
Protoss_Dragoon 8 15382
Protoss_Robotics_Facility 1 9244
Protoss_Observatory 1 9960
Protoss_Observer 2 11856
Protoss_Nexus 2 16369
Singularity_Charge 1 12256
16369
