Protoss_Gateway 2 13271
Protoss_Assimilator 1 4476
Protoss_Cybernetics_Core 1 5736
Protoss_Dragoon 9 15136
Protoss_Robotics_Facility 1 10598
Singularity_Charge 1 10165
Protoss_Observatory 1 11520
Protoss_Observer 4 15494
Protoss_Nexus 1 17403
17403
