Protoss_Gateway 2 8960
Protoss_Assimilator 1 4350
Protoss_Cybernetics_Core 1 5920
Protoss_Dragoon 10 15376
Protoss_Nexus 1 11532
Singularity_Charge 1 9581
Protoss_Robotics_Facility 1 11830
Protoss_Shuttle 1 13246
Protoss_Robotics_Support_Bay 1 13160
Protoss_Reaver 1 15003
Protoss_Observatory 1 14144
15376
