Protoss_Gateway 1 4097
Protoss_Assimilator 1 4369
Protoss_Cybernetics_Core 1 5585
Protoss_Dragoon 9 15733
Protoss_Robotics_Facility 1 10125
Singularity_Charge 1 9642
Protoss_Shuttle 1 11610
Protoss_Robotics_Support_Bay 1 10974
Protoss_Reaver 1 13203
Protoss_Observatory 1 13114
Protoss_Nexus 2 17340
Protoss_Observer 2 15564
17340
