Protoss_Nexus 1 6717
Protoss_Gateway 2 7785
Protoss_Assimilator 1 5844
Protoss_Cybernetics_Core 1 7363
Protoss_Zealot 2 14549
Protoss_Dragoon 10 14796
Protoss_Robotics_Facility 1 11881
Singularity_Charge 1 11943
Protoss_Shuttle 1 13387
Protoss_Robotics_Support_Bay 1 12876
Protoss_Reaver 1 14945
Protoss_Observatory 1 14479
14945
