Protoss_Gateway 3 16063
Protoss_Assimilator 1 4791
Protoss_Cybernetics_Core 1 5919
Protoss_Dragoon 3 9827
Protoss_Citadel_of_Adun 2 9563
Protoss_Templar_Archives 1 11126
Singularity_Charge 1 10150
Protoss_Dark_Templar 6 15080
Protoss_Nexus 1 16142
16142
