Protoss_Nexus 1 6826
Protoss_Gateway 2 13212
Protoss_Assimilator 2 12986
Protoss_Cybernetics_Core 1 7608
Protoss_Zealot 1 7255
Protoss_Dragoon 8 15797
Protoss_Robotics_Facility 1 14243
Protoss_Observatory 1 14946
15797
