Protoss_Nexus 1 6836
Protoss_Gateway 3 13076
Protoss_Assimilator 2 10090
Protoss_Cybernetics_Core 1 7550
Protoss_Dragoon 5 15710
Protoss_Citadel_of_Adun 1 10700
Protoss_Forge 1 10997
Protoss_Templar_Archives 1 12264
Protoss_Robotics_Facility 1 12891
Protoss_Photon_Cannon 2 12942
Protoss_Shuttle 1 14297
Protoss_Stargate 1 14618
Protoss_Dark_Templar 3 14369
Protoss_Observatory 1 14662
15710
