Protoss_Gateway 5 15345
Protoss_Assimilator 1 4126
Protoss_Cybernetics_Core 1 5546
Protoss_Zealot 1 5288
Protoss_Dragoon 10 15818
Protoss_Nexus 2 14198
Singularity_Charge 1 11281
Protoss_Robotics_Facility 1 14899
15818
