Protoss_Gateway 3 12298
Protoss_Zealot 4 8246
Protoss_Assimilator 1 6307
Protoss_Cybernetics_Core 1 8317
Protoss_Dragoon 10 15669
Protoss_Robotics_Facility 1 13516
Singularity_Charge 1 12429
Protoss_Observatory 1 14208
Protoss_Observer 1 15222
15669
