Protoss_Gateway 4 15147
Protoss_Assimilator 1 4354
Protoss_Cybernetics_Core 1 5726
Protoss_Dragoon 6 15033
Protoss_Citadel_of_Adun 1 8822
Protoss_Templar_Archives 1 10328
Singularity_Charge 1 9629
Protoss_Nexus 1 12558
Protoss_Dark_Templar 1 11548
Protoss_Robotics_Facility 1 12477
Protoss_Observatory 1 13870
Protoss_Observer 1 15179
15179
