Protoss_Gateway 2 13533
Protoss_Assimilator 2 13409
Protoss_Cybernetics_Core 1 5616
Protoss_Dragoon 9 14969
Protoss_Robotics_Facility 1 9933
Singularity_Charge 1 9736
Protoss_Observatory 1 10683
Protoss_Nexus 1 13685
Protoss_Observer 2 13097
Protoss_Citadel_of_Adun 1 13122
14969
