Protoss_Gateway 2 12298
Protoss_Assimilator 2 12930
Protoss_Cybernetics_Core 1 6617
Protoss_Zealot 1 6283
Protoss_Dragoon 9 15025
Protoss_Nexus 1 11829
Protoss_Robotics_Facility 1 12443
Singularity_Charge 1 10714
Protoss_Observatory 1 13438
Protoss_Shuttle 1 14587
Protoss_Robotics_Support_Bay 1 14065
Protoss_Citadel_of_Adun 1 15623
Protoss_Observer 1 15430
15623
