Protoss_Nexus 2 12959
Protoss_Gateway 3 15814
Protoss_Assimilator 2 12839
Protoss_Cybernetics_Core 1 7466
Protoss_Dragoon 10 14685
Protoss_Robotics_Facility 1 13031
Protoss_Citadel_of_Adun 1 13084
Singularity_Charge 1 11899
Protoss_Shuttle 1 14756
Protoss_Observatory 1 14949
15814
