Protoss_Assimilator 2 4764
Protoss_Gateway 1 4668
Protoss_Cybernetics_Core 1 6232
Protoss_Zealot 3 15447
Protoss_Dragoon 5 12721
Protoss_Robotics_Facility 1 10265
Protoss_Observatory 1 10956
Protoss_Observer 1 12002
Protoss_Nexus 1 14136
Protoss_Shuttle 1 13515
Protoss_Robotics_Support_Bay 1 13255
Singularity_Charge 1 13058
Protoss_Reaver 1 15120
15447
