Protoss_Gateway 2 6394
Protoss_Assimilator 1 4233
Protoss_Cybernetics_Core 1 5628
Protoss_Dragoon 6 10948
Protoss_Citadel_of_Adun 1 8840
Protoss_Zealot 1 8917
Protoss_Templar_Archives 1 10546
Singularity_Charge 1 9716
Protoss_Dark_Templar 2 12180
Protoss_Nexus 2 16717
Protoss_Robotics_Facility 1 16279
16717
