Protoss_Nexus 2 13424
Protoss_Gateway 4 13823
Protoss_Assimilator 1 5945
Protoss_Cybernetics_Core 1 7502
Protoss_Zealot 1 7741
Protoss_Dragoon 10 15373
Protoss_Robotics_Facility 1 12932
Protoss_Observatory 1 13684
Protoss_Observer 1 14920
15373
