Protoss_Gateway 2 10003
Protoss_Assimilator 1 4253
Protoss_Cybernetics_Core 1 5690
Protoss_Zealot 1 5569
Protoss_Dragoon 4 14720
Protoss_Citadel_of_Adun 1 8894
Protoss_Robotics_Facility 1 10214
Protoss_Templar_Archives 1 10334
Protoss_Shuttle 2 15915
Protoss_Dark_Templar 2 11714
Protoss_Observatory 1 12293
Protoss_Nexus 1 15022
Protoss_Observer 2 14212
Protoss_Robotics_Support_Bay 1 15262
15915
