Protoss_Gateway 4 15699
Protoss_Assimilator 1 4417
Protoss_Cybernetics_Core 1 5769
Protoss_Zealot 1 5531
Protoss_Dragoon 5 11597
Protoss_Nexus 2 15549
Singularity_Charge 1 9926
Protoss_Citadel_of_Adun 1 12198
Protoss_Templar_Archives 1 13638
Protoss_Dark_Templar 2 14846
Protoss_Robotics_Facility 1 15683
15699
