Protoss_Gateway 2 6984
Protoss_Assimilator 1 4551
Protoss_Cybernetics_Core 1 5938
Protoss_Dragoon 10 13634
Protoss_Robotics_Facility 1 11139
Singularity_Charge 1 9599
Protoss_Shuttle 1 12866
Protoss_Robotics_Support_Bay 1 12537
Protoss_Reaver 1 14438
Protoss_Zealot 2 14496
14496
