Protoss_Gateway 1 4572
Protoss_Assimilator 1 4805
Protoss_Cybernetics_Core 1 6405
Protoss_Dragoon 5 13631
Protoss_Robotics_Facility 1 10726
Singularity_Charge 1 10414
Protoss_Shuttle 1 12143
Protoss_Robotics_Support_Bay 1 11467
Protoss_Zealot 2 14493
Protoss_Reaver 1 13701
Protoss_Observatory 1 14186
14493
