Protoss_Gateway 6 15179
Protoss_Assimilator 1 4826
Protoss_Cybernetics_Core 1 5786
Protoss_Dragoon 8 15783
Protoss_Nexus 2 12312
Singularity_Charge 1 10155
Protoss_Robotics_Facility 1 12882
Protoss_Observatory 1 14021
Protoss_Observer 1 15037
15783
