Protoss_Gateway 2 9893
Protoss_Assimilator 2 14345
Protoss_Cybernetics_Core 1 5753
Protoss_Dragoon 12 15045
Singularity_Charge 1 9634
Protoss_Nexus 1 12602
Protoss_Robotics_Facility 1 12974
Protoss_Observatory 1 13737
Protoss_Observer 1 14759
Protoss_Citadel_of_Adun 1 15965
15965
