Protoss_Gateway 2 14316
Protoss_Assimilator 1 4413
Protoss_Cybernetics_Core 1 5717
Protoss_Dragoon 8 15616
Protoss_Nexus 2 17179
Singularity_Charge 1 9771
Protoss_Robotics_Facility 1 11943
Protoss_Shuttle 1 13439
Protoss_Robotics_Support_Bay 1 13431
Protoss_Reaver 1 15182
17179
