Protoss_Gateway 3 13392
Protoss_Assimilator 2 13713
Protoss_Cybernetics_Core 1 5516
Protoss_Dragoon 10 14831
Protoss_Nexus 1 11197
Protoss_Robotics_Facility 1 10748
Singularity_Charge 1 9520
Protoss_Observatory 1 11482
Protoss_Observer 2 13381
Protoss_Citadel_of_Adun 1 15523
15523
