Protoss_Gateway 2 12889
Protoss_Assimilator 1 4226
Protoss_Cybernetics_Core 1 5733
Protoss_Dragoon 8 15388
Protoss_Robotics_Facility 1 9709
Protoss_Shuttle 1 11150
Singularity_Charge 1 9897
Protoss_Robotics_Support_Bay 1 10623
Protoss_Observatory 1 10910
Protoss_Reaver 2 15275
Protoss_Nexus 1 15280
Protoss_Observer 1 13548
15388
