Protoss_Gateway 1 4767
Protoss_Assimilator 1 4793
Protoss_Cybernetics_Core 1 6402
Protoss_Dragoon 5 12130
Protoss_Robotics_Facility 1 11202
Singularity_Charge 1 10494
Protoss_Shuttle 1 12867
Protoss_Robotics_Support_Bay 1 12499
Protoss_Zealot 2 14834
Protoss_Reaver 2 15969
15969
