Protoss_Gateway 2 12727
Protoss_Assimilator 2 13429
Protoss_Cybernetics_Core 1 5692
Protoss_Zealot 1 5712
Protoss_Dragoon 10 15493
Protoss_Nexus 1 12024
Singularity_Charge 1 9885
Protoss_Robotics_Facility 1 12800
Protoss_Citadel_of_Adun 1 13094
Protoss_Observatory 1 13520
Protoss_Observer 1 14563
Protoss_Templar_Archives 1 15225
15493
