Protoss_Gateway 3 15040
Protoss_Assimilator 1 4652
Protoss_Zealot 2 6248
Protoss_Cybernetics_Core 1 7319
Protoss_Dragoon 5 13936
Protoss_Robotics_Facility 1 10716
Protoss_Nexus 1 12400
Protoss_Shuttle 1 12122
Protoss_Robotics_Support_Bay 1 11592
Protoss_Reaver 1 13709
Protoss_Observatory 1 14594
15040
