Protoss_Gateway 2 6425
Protoss_Assimilator 1 4420
Protoss_Cybernetics_Core 1 5806
Protoss_Dragoon 6 12253
Protoss_Nexus 2 17455
Singularity_Charge 1 9467
Protoss_Robotics_Facility 1 11404
Protoss_Shuttle 1 12810
Protoss_Robotics_Support_Bay 1 12768
Protoss_Reaver 1 14631
Protoss_Observatory 1 14246
Protoss_Zealot 2 14727
Protoss_Observer 1 15456
17455
