Protoss_Gateway 3 14898
Protoss_Assimilator 1 4205
Protoss_Cybernetics_Core 1 5657
Protoss_Dragoon 10 15806
Protoss_Nexus 1 12696
Singularity_Charge 1 9959
Protoss_Robotics_Facility 1 13614
Protoss_Shuttle 1 15178
Protoss_Robotics_Support_Bay 1 15170
15806
