Protoss_Nexus 1 6681
Protoss_Gateway 2 7668
Protoss_Assimilator 2 11151
Protoss_Cybernetics_Core 1 7381
Protoss_Zealot 2 15424
Protoss_Dragoon 11 15680
Protoss_Stargate 2 14148
Singularity_Charge 1 11671
Protoss_Fleet_Beacon 1 13589
Protoss_Carrier 1 17260
17260
