Protoss_Gateway 2 9826
Protoss_Assimilator 1 4116
Protoss_Cybernetics_Core 1 5543
Protoss_Dragoon 7 15689
Protoss_Citadel_of_Adun 1 8724
Protoss_Robotics_Facility 1 9573
Protoss_Templar_Archives 1 10267
Protoss_Shuttle 1 11124
Protoss_Dark_Templar 3 12566
Protoss_Nexus 1 14873
Protoss_Observatory 1 14390
15689
