Protoss_Gateway 4 15664
Protoss_Assimilator 1 4384
Protoss_Cybernetics_Core 1 5753
Protoss_Dragoon 6 14785
Protoss_Robotics_Facility 1 8280
Protoss_Shuttle 1 10056
Protoss_Zealot 2 11115
Protoss_Observatory 1 10032
Protoss_Robotics_Support_Bay 1 10702
Protoss_Observer 1 11127
Singularity_Charge 1 11399
Protoss_Nexus 1 14589
Protoss_Reaver 1 13733
15664
