Protoss_Assimilator 2 4872
Protoss_Gateway 2 15011
Protoss_Cybernetics_Core 1 6664
Protoss_Zealot 1 6658
Protoss_Dragoon 4 14150
Protoss_Robotics_Facility 1 9358
Protoss_Shuttle 1 10779
Protoss_Robotics_Support_Bay 1 10965
Protoss_Reaver 1 12697
Protoss_Observatory 1 12332
Singularity_Charge 1 12001
Protoss_Observer 1 13521
Protoss_Nexus 1 15461
15461
