Protoss_Gateway 3 12596
Protoss_Assimilator 2 13027
Protoss_Cybernetics_Core 1 5740
Protoss_Zealot 1 5560
Protoss_Dragoon 8 14343
Protoss_Nexus 1 11550
Singularity_Charge 1 9686
Protoss_Robotics_Facility 1 11825
Protoss_Observatory 1 12628
Protoss_Citadel_of_Adun 1 14071
Protoss_Observer 2 14525
Protoss_Templar_Archives 1 15678
Protoss_Stargate 1 15965
15965
