Protoss_Gateway 2 15078
Protoss_Assimilator 2 14047
Protoss_Cybernetics_Core 1 5783
Protoss_Dragoon 7 14226
Protoss_Robotics_Facility 1 9747
Singularity_Charge 1 9856
Protoss_Observatory 1 10576
Protoss_Nexus 1 13152
Protoss_Observer 3 14095
Protoss_Citadel_of_Adun 1 13334
Protoss_Templar_Archives 1 15674
15674
