Protoss_Gateway 2 8297
Protoss_Assimilator 1 4385
Protoss_Cybernetics_Core 1 5578
Protoss_Zealot 2 14531
Protoss_Citadel_of_Adun 1 7208
Protoss_Dragoon 8 14600
Protoss_Templar_Archives 1 8775
Protoss_Dark_Templar 2 9979
Protoss_Nexus 1 15851
Singularity_Charge 1 13067
Protoss_Robotics_Facility 1 15455
15851
