Protoss_Gateway 3 12579
Protoss_Assimilator 1 4376
Protoss_Cybernetics_Core 1 5616
Protoss_Zealot 1 5581
Protoss_Dragoon 9 13924
Protoss_Nexus 1 11630
Singularity_Charge 1 9800
Protoss_Robotics_Facility 1 11922
Protoss_Observatory 1 12686
Protoss_Observer 2 14592
Protoss_Shuttle 1 15950
Protoss_Robotics_Support_Bay 1 15322
15950
