Protoss_Gateway 2 10929
Protoss_Assimilator 2 14639
Protoss_Cybernetics_Core 1 5929
Protoss_Dragoon 11 15751
Protoss_Nexus 1 11747
Singularity_Charge 1 9733
Protoss_Robotics_Facility 1 12477
Protoss_Observatory 1 13294
Protoss_Observer 2 15351
Protoss_Citadel_of_Adun 1 14914
15751
