Protoss_Gateway 2 13546
Protoss_Assimilator 1 4251
Protoss_Cybernetics_Core 1 5648
Protoss_Zealot 1 5648
Protoss_Dragoon 9 15686
Protoss_Robotics_Facility 2 15676
Protoss_Robotics_Support_Bay 1 10140
Protoss_Shuttle 1 11159
Protoss_Reaver 1 13244
Singularity_Charge 1 11612
Protoss_Nexus 1 15912
15912
