Protoss_Assimilator 3 5711
Protoss_Gateway 4 14560
Protoss_Cybernetics_Core 1 6734
Protoss_Dragoon 10 15701
Singularity_Charge 1 10769
Protoss_Nexus 1 14185
Protoss_Robotics_Facility 1 13662
Protoss_Observatory 1 15151
15701
