Protoss_Gateway 4 14210
Protoss_Assimilator 1 4193
Protoss_Cybernetics_Core 1 5704
Protoss_Dragoon 8 15531
Protoss_Robotics_Facility 1 10443
Singularity_Charge 1 10043
Protoss_Observatory 1 11174
Protoss_Nexus 1 13879
Protoss_Observer 2 13972
15531
