Protoss_Gateway 2 12039
Protoss_Assimilator 2 15116
Protoss_Cybernetics_Core 1 6043
Protoss_Dragoon 6 14981
Protoss_Nexus 1 11229
Protoss_Citadel_of_Adun 1 10865
Singularity_Charge 1 9915
Protoss_Robotics_Facility 1 11910
Protoss_Templar_Archives 1 12374
Protoss_Shuttle 1 13316
Protoss_Dark_Templar 2 13620
Protoss_Observatory 1 13532
Protoss_Observer 1 14783
15116
