Protoss_Gateway 1 4155
Protoss_Assimilator 1 4510
Protoss_Cybernetics_Core 1 5724
Protoss_Zealot 2 10952
Protoss_Dragoon 6 15124
Protoss_Robotics_Facility 1 8357
Protoss_Shuttle 2 15151
Protoss_Robotics_Support_Bay 1 9616
Protoss_Reaver 1 11605
Protoss_Observatory 1 11448
Protoss_Observer 2 13401
Protoss_Nexus 1 15119
15151
