Protoss_Gateway 2 8209
Protoss_Assimilator 1 4352
Protoss_Cybernetics_Core 1 5860
Protoss_Dragoon 11 15200
Singularity_Charge 1 9724
Protoss_Robotics_Facility 1 11638
Protoss_Zealot 2 12468
Protoss_Shuttle 1 13056
Protoss_Robotics_Support_Bay 1 12568
Protoss_Reaver 1 14675
Protoss_Observatory 1 14480
15200
