Protoss_Gateway 2 10829
Protoss_Assimilator 2 14563
Protoss_Cybernetics_Core 1 5897
Protoss_Dragoon 10 15619
Protoss_Nexus 1 11548
Singularity_Charge 1 9841
Protoss_Robotics_Facility 1 12510
Protoss_Shuttle 1 13916
Protoss_Observatory 1 13632
Protoss_Zealot 2 15216
Protoss_Robotics_Support_Bay 1 14300
Protoss_Observer 1 14952
15619
