Protoss_Gateway 2 10591
Protoss_Assimilator 2 14866
Protoss_Cybernetics_Core 1 6005
Protoss_Dragoon 9 15373
Protoss_Nexus 1 11215
Protoss_Robotics_Facility 1 11638
Singularity_Charge 1 9885
Protoss_Shuttle 1 13056
Protoss_Robotics_Support_Bay 1 13364
Protoss_Zealot 2 14127
Protoss_Reaver 1 15228
Protoss_Observatory 1 15092
15373
