Protoss_Gateway 3 10334
Protoss_Assimilator 1 4218
Protoss_Cybernetics_Core 1 5739
Protoss_Dragoon 11 15159
Protoss_Robotics_Facility 1 9663
Protoss_Observatory 1 10390
Singularity_Charge 1 9792
Protoss_Observer 1 11399
Protoss_Shuttle 1 13035
Protoss_Robotics_Support_Bay 1 12730
Protoss_Zealot 3 14039
Protoss_Reaver 1 14628
15159
