Protoss_Gateway 2 10529
Protoss_Assimilator 1 4542
Protoss_Cybernetics_Core 1 6176
Protoss_Dragoon 7 12644
Protoss_Robotics_Facility 1 9964
Singularity_Charge 1 10128
Protoss_Observatory 2 13078
Protoss_Robotics_Support_Bay 1 11101
Protoss_Reaver 1 13010
Protoss_Shuttle 1 14587
Protoss_Nexus 1 16954
Protoss_Observer 1 15430
16954
