Protoss_Gateway 2 11982
Protoss_Assimilator 1 4395
Protoss_Cybernetics_Core 1 5702
Protoss_Dragoon 11 15475
Protoss_Nexus 1 12334
Singularity_Charge 1 9912
Protoss_Robotics_Facility 1 12058
Protoss_Observatory 1 12869
Protoss_Observer 2 14777
15475
