Protoss_Gateway 2 13502
Protoss_Assimilator 2 13313
Protoss_Cybernetics_Core 1 5639
Protoss_Zealot 1 5487
Protoss_Dragoon 7 15294
Protoss_Citadel_of_Adun 1 8824
Protoss_Templar_Archives 1 10419
Singularity_Charge 1 9584
Protoss_Nexus 1 13382
Protoss_Dark_Templar 2 12844
Protoss_Stargate 1 13232
Protoss_Arbiter_Tribunal 1 14857
15294
