Protoss_Assimilator 1 3629
Protoss_Gateway 4 15598
Protoss_Cybernetics_Core 1 6210
Protoss_Dragoon 7 13708
Protoss_Robotics_Facility 1 10551
Protoss_Zealot 1 9936
Singularity_Charge 1 9953
Protoss_Nexus 2 16367
Protoss_Observatory 1 11750
Protoss_Observer 3 14996
16367
