Protoss_Gateway 2 14494
Protoss_Assimilator 2 14323
Protoss_Cybernetics_Core 1 5625
Protoss_Zealot 1 5569
Protoss_Dragoon 6 15045
Protoss_Citadel_of_Adun 1 9252
Protoss_Templar_Archives 1 10840
Singularity_Charge 1 10005
Protoss_Nexus 1 13735
Protoss_Dark_Templar 1 12110
Protoss_Robotics_Facility 1 14293
Protoss_Shuttle 1 16062
16062
