Protoss_Gateway 2 11928
Protoss_Assimilator 2 13196
Protoss_Cybernetics_Core 1 5742
Protoss_Zealot 1 6269
Protoss_Nexus 1 9788
Protoss_Dragoon 7 15285
Protoss_Citadel_of_Adun 1 11601
Protoss_Templar_Archives 1 13283
Protoss_Stargate 1 13815
Singularity_Charge 1 12350
Protoss_Arbiter_Tribunal 1 15242
Protoss_Dark_Templar 1 15271
15285
