Protoss_Gateway 2 9598
Protoss_Assimilator 2 14376
Protoss_Cybernetics_Core 1 5870
Protoss_Dragoon 7 15297
Protoss_Robotics_Facility 1 9922
Protoss_Nexus 2 15093
Singularity_Charge 1 9792
Protoss_Observatory 1 10983
Protoss_Observer 2 12880
Protoss_Citadel_of_Adun 1 14704
15297
