Protoss_Nexus 1 7137
Protoss_Gateway 2 8279
Protoss_Assimilator 1 6333
Protoss_Cybernetics_Core 1 7830
Protoss_Zealot 1 8010
Protoss_Dragoon 12 15683
Singularity_Charge 1 12230
Protoss_Robotics_Facility 1 15800
15800
