Protoss_Assimilator 3 11780
Protoss_Gateway 3 14825
Protoss_Nexus 1 8463
Protoss_Zealot 7 12658
Protoss_Cybernetics_Core 1 8878
Protoss_Dragoon 3 15505
Protoss_Robotics_Facility 2 14231
Protoss_Shuttle 1 14914
Protoss_Robotics_Support_Bay 1 14353
Protoss_Reaver 1 16224
16224
