Protoss_Gateway 2 14701
Protoss_Assimilator 1 4278
Protoss_Cybernetics_Core 1 5775
Protoss_Zealot 2 13697
Protoss_Dragoon 7 14817
Protoss_Robotics_Facility 1 9285
Protoss_Robotics_Support_Bay 1 10005
Protoss_Shuttle 1 11215
Protoss_Reaver 2 14396
14817
