Protoss_Gateway 4 14540
Protoss_Assimilator 1 4332
Protoss_Cybernetics_Core 1 5565
Protoss_Dragoon 7 12320
Singularity_Charge 1 9253
Protoss_Nexus 1 12725
Protoss_Citadel_of_Adun 1 13229
Protoss_Robotics_Facility 1 14505
Protoss_Templar_Archives 1 15125
Protoss_Shuttle 1 15907
15907
