Protoss_Gateway 3 13040
Protoss_Assimilator 1 4738
Protoss_Cybernetics_Core 1 5947
Protoss_Dragoon 13 15688
Protoss_Robotics_Facility 1 8679
Protoss_Observatory 1 9470
Protoss_Observer 2 11427
Singularity_Charge 1 12133
15688
