Protoss_Gateway 3 15680
Protoss_Assimilator 1 4180
Protoss_Cybernetics_Core 1 5677
Protoss_Dragoon 5 11694
Protoss_Robotics_Facility 1 9787
Singularity_Charge 1 9806
Protoss_Shuttle 1 11721
Protoss_Observatory 1 11489
Protoss_Robotics_Support_Bay 1 11704
Protoss_Observer 1 12719
Protoss_Nexus 1 15072
Protoss_Zealot 1 13410
Protoss_Reaver 1 14538
15680
