Protoss_Gateway 2 8089
Protoss_Assimilator 1 4580
Protoss_Cybernetics_Core 1 5851
Protoss_Dragoon 10 15449
Singularity_Charge 1 9546
Protoss_Nexus 2 15025
Protoss_Robotics_Facility 1 14812
15449
