Protoss_Nexus 2 14007
Protoss_Gateway 6 15277
Protoss_Assimilator 2 14360
Protoss_Cybernetics_Core 1 7665
Protoss_Dragoon 6 14369
Protoss_Citadel_of_Adun 1 10027
Protoss_Templar_Archives 1 12056
Singularity_Charge 1 11337
Protoss_Dark_Templar 2 13269
15277
