Protoss_Nexus 1 6511
Protoss_Gateway 2 6798
Protoss_Assimilator 2 11502
Protoss_Zealot 3 7975
Protoss_Cybernetics_Core 1 7597
Protoss_Dragoon 10 15592
Protoss_Citadel_of_Adun 1 12001
Protoss_Templar_Archives 1 13466
Protoss_Stargate 1 13829
Singularity_Charge 1 12218
Protoss_Robotics_Facility 1 15449
Protoss_Arbiter_Tribunal 1 15307
15592
