Protoss_Gateway 2 10524
Protoss_Assimilator 1 4398
Protoss_Cybernetics_Core 1 5901
Protoss_Dragoon 7 15112
Protoss_Robotics_Facility 1 9572
Protoss_Citadel_of_Adun 1 9312
Protoss_Templar_Archives 1 10859
Protoss_Shuttle 1 11057
Protoss_Dark_Templar 2 12074
Protoss_Observatory 1 13409
Protoss_Nexus 1 16111
16111
