Protoss_Gateway 2 11970
Protoss_Assimilator 1 4395
Protoss_Cybernetics_Core 1 6100
Protoss_Dragoon 8 15720
Protoss_Robotics_Facility 1 10220
Protoss_Robotics_Support_Bay 1 10964
Singularity_Charge 1 10823
Protoss_Shuttle 1 12348
Protoss_Observatory 1 12639
Protoss_Reaver 1 14012
Protoss_Observer 1 14837
15720
