Protoss_Gateway 4 15899
Protoss_Assimilator 1 4088
Protoss_Cybernetics_Core 1 5543
Protoss_Dragoon 10 14676
Protoss_Robotics_Facility 1 9317
Protoss_Observatory 1 10043
Singularity_Charge 1 9461
Protoss_Nexus 2 15413
Protoss_Observer 3 14651
15899
