Protoss_Gateway 2 14619
Protoss_Assimilator 1 4403
Protoss_Cybernetics_Core 1 5794
Protoss_Zealot 1 5631
Protoss_Dragoon 7 15165
Protoss_Robotics_Facility 1 10045
Protoss_Shuttle 1 11469
Singularity_Charge 1 10064
Protoss_Robotics_Support_Bay 1 11044
Protoss_Reaver 1 13027
Protoss_Nexus 1 14756
Protoss_Observatory 1 12797
Protoss_Observer 2 14733
15165
