Protoss_Gateway 2 14376
Protoss_Assimilator 2 14582
Protoss_Cybernetics_Core 1 5780
Protoss_Dragoon 9 15598
Protoss_Robotics_Facility 1 9727
Singularity_Charge 1 9642
Protoss_Nexus 1 12570
Protoss_Shuttle 1 11935
Protoss_Robotics_Support_Bay 1 11916
Protoss_Reaver 1 13809
Protoss_Observatory 1 14234
Protoss_Observer 1 15242
15598
