Protoss_Gateway 4 15636
Protoss_Assimilator 1 4564
Protoss_Cybernetics_Core 1 6254
Protoss_Dragoon 4 13207
Protoss_Robotics_Facility 1 9487
Protoss_Robotics_Support_Bay 1 10210
Protoss_Shuttle 1 10935
Protoss_Zealot 2 11537
Protoss_Reaver 1 12493
Protoss_Observatory 1 11925
Protoss_Observer 2 14322
Protoss_Nexus 1 15953
Singularity_Charge 1 14584
15953
