Protoss_Nexus 2 16590
Protoss_Gateway 4 15576
Protoss_Assimilator 2 10407
Protoss_Cybernetics_Core 1 7515
Protoss_Dragoon 7 15402
Protoss_Robotics_Facility 1 10377
Protoss_Zealot 2 11429
Protoss_Observatory 1 11289
Protoss_Observer 3 14941
Singularity_Charge 1 13480
16590
