Protoss_Gateway 2 9110
Protoss_Assimilator 1 4564
Protoss_Cybernetics_Core 1 5783
Protoss_Dragoon 12 15273
Singularity_Charge 1 10052
Protoss_Nexus 1 14018
Protoss_Robotics_Facility 1 14588
15273
