Protoss_Nexus 1 6763
Protoss_Gateway 3 11418
Protoss_Assimilator 2 12709
Protoss_Cybernetics_Core 1 7360
Protoss_Zealot 3 14069
Protoss_Dragoon 12 15189
Protoss_Robotics_Facility 1 11790
Singularity_Charge 1 11630
Protoss_Shuttle 1 13808
Protoss_Robotics_Support_Bay 1 14205
Protoss_Reaver 1 15966
15966
