Protoss_Gateway 3 12968
Protoss_Assimilator 2 13921
Protoss_Cybernetics_Core 1 5692
Protoss_Zealot 3 15517
Protoss_Dragoon 7 15344
Protoss_Nexus 1 11674
Singularity_Charge 1 9888
Protoss_Robotics_Facility 1 11994
Protoss_Observatory 1 12756
Protoss_Citadel_of_Adun 1 13823
Protoss_Observer 2 14689
Protoss_Templar_Archives 1 15277
Protoss_Stargate 1 15635
15635
