Protoss_Gateway 3 15795
Protoss_Assimilator 2 15528
Protoss_Cybernetics_Core 1 5670
Protoss_Zealot 1 5502
Protoss_Dragoon 7 14583
Protoss_Nexus 2 15722
Singularity_Charge 1 9836
Protoss_Robotics_Facility 1 12244
Protoss_Observatory 1 12942
Protoss_Observer 2 14935
15795
