Protoss_Gateway 2 11963
Protoss_Assimilator 2 13915
Protoss_Cybernetics_Core 1 5808
Protoss_Dragoon 11 15546
Protoss_Robotics_Facility 1 9927
Singularity_Charge 1 9780
Protoss_Observatory 1 10627
Protoss_Nexus 1 12902
Protoss_Observer 2 12535
Protoss_Citadel_of_Adun 1 14257
15546
