Protoss_Gateway 2 6374
Protoss_Assimilator 2 7107
Protoss_Zealot 8 9766
Protoss_Cybernetics_Core 1 9504
Protoss_Dragoon 9 15411
Singularity_Charge 1 13980
Protoss_Nexus 1 17289
17289
