Protoss_Gateway 4 14330
Protoss_Assimilator 2 4750
Protoss_Cybernetics_Core 1 6509
Protoss_Nexus 1 9988
Protoss_Dragoon 11 15794
Protoss_Robotics_Facility 1 13039
Singularity_Charge 1 11644
Protoss_Observatory 1 13737
Protoss_Observer 1 14753
15794
