Protoss_Gateway 3 13214
Protoss_Assimilator 1 4717
Protoss_Cybernetics_Core 1 6487
Protoss_Dragoon 12 14849
Singularity_Charge 1 10149
Protoss_Nexus 1 13439
Protoss_Shield_Battery 1 13321
Protoss_Robotics_Facility 1 16020
Protoss_Zealot 1 15327
16020
