Protoss_Gateway 4 15721
Protoss_Assimilator 1 4372
Protoss_Cybernetics_Core 1 5592
Protoss_Dragoon 9 14913
Protoss_Nexus 2 16072
Protoss_Robotics_Facility 1 11474
Singularity_Charge 1 9771
Protoss_Observatory 1 12336
Protoss_Observer 3 15131
16072
