Protoss_Gateway 3 16056
Protoss_Zealot 2 6111
Protoss_Assimilator 2 14590
Protoss_Cybernetics_Core 1 7287
Protoss_Dragoon 8 15478
Protoss_Nexus 2 16184
Protoss_Robotics_Facility 1 12371
Singularity_Charge 1 11311
Protoss_Observatory 1 13241
Protoss_Observer 2 15517
Protoss_Citadel_of_Adun 1 15269
16184
