Protoss_Gateway 2 12146
Protoss_Assimilator 2 14685
Protoss_Cybernetics_Core 1 5696
Protoss_Zealot 1 5753
Protoss_Dragoon 8 15585
Protoss_Nexus 2 15996
Singularity_Charge 1 9938
Protoss_Robotics_Facility 1 12158
Protoss_Observatory 1 13184
Protoss_Observer 2 15393
15996
