Protoss_Gateway 4 14771
Protoss_Assimilator 2 13508
Protoss_Cybernetics_Core 1 6178
Protoss_Nexus 2 15172
Protoss_Dragoon 9 15127
Protoss_Robotics_Facility 1 12717
Singularity_Charge 1 11065
Protoss_Observatory 1 13494
Protoss_Observer 1 14631
15172
