Protoss_Gateway 2 12375
Protoss_Assimilator 1 4211
Protoss_Cybernetics_Core 1 5613
Protoss_Dragoon 8 15048
Protoss_Robotics_Facility 1 10096
Singularity_Charge 1 9792
Protoss_Nexus 1 12921
Protoss_Observatory 1 11069
Protoss_Observer 1 12684
Protoss_Robotics_Support_Bay 1 12958
Protoss_Shuttle 1 14231
Protoss_Zealot 2 13811
Protoss_Reaver 1 15811
15811
