Protoss_Gateway 2 10580
Protoss_Assimilator 1 4564
Protoss_Cybernetics_Core 1 5879
Protoss_Dragoon 12 15437
Protoss_Robotics_Facility 1 10402
Singularity_Charge 1 9985
Protoss_Observatory 1 11410
Protoss_Observer 1 12471
Protoss_Shuttle 1 14209
Protoss_Robotics_Support_Bay 1 13617
Protoss_Nexus 1 17280
17280
