Protoss_Gateway 2 14249
Protoss_Assimilator 1 4293
Protoss_Cybernetics_Core 1 5809
Protoss_Dragoon 8 14782
Protoss_Robotics_Facility 1 10106
Singularity_Charge 1 9695
Protoss_Observatory 1 10823
Protoss_Observer 3 15134
Protoss_Nexus 1 14269
15134
