Protoss_Nexus 1 6637
Protoss_Gateway 3 15969
Protoss_Assimilator 1 5935
Protoss_Cybernetics_Core 1 7261
Protoss_Zealot 3 14118
Protoss_Dragoon 8 13257
Protoss_Robotics_Facility 1 14806
Singularity_Charge 1 13450
15969
