Protoss_Nexus 2 14981
Protoss_Gateway 4 15500
Protoss_Assimilator 2 12043
Protoss_Cybernetics_Core 1 7504
Protoss_Zealot 1 7741
Protoss_Dragoon 8 14357
Protoss_Robotics_Facility 1 12567
Singularity_Charge 1 11694
Protoss_Observatory 1 13577
Protoss_Observer 2 15473
15500
