Protoss_Gateway 2 10805
Protoss_Assimilator 1 4416
Protoss_Cybernetics_Core 1 5847
Protoss_Dragoon 10 15268
Protoss_Robotics_Facility 1 10072
Singularity_Charge 1 9754
Protoss_Observatory 1 10812
Protoss_Nexus 2 15325
Protoss_Observer 3 14259
15325
