Protoss_Nexus 1 6640
Protoss_Gateway 2 7397
Protoss_Assimilator 1 5969
Protoss_Cybernetics_Core 1 7293
Protoss_Zealot 1 7270
Protoss_Dragoon 8 14047
Protoss_Robotics_Facility 1 14136
Singularity_Charge 1 13108
Protoss_Shuttle 1 15532
15532
