Protoss_Gateway 2 13640
Protoss_Assimilator 2 13027
Protoss_Zealot 1 5519
Protoss_Cybernetics_Core 1 7003
Protoss_Dragoon 6 14937
Protoss_Robotics_Facility 1 10403
Protoss_Nexus 1 12732
Singularity_Charge 1 10699
Protoss_Observatory 1 11520
Protoss_Observer 3 15447
Protoss_Citadel_of_Adun 1 13359
Protoss_Templar_Archives 1 15308
15447
