Protoss_Gateway 2 10189
Protoss_Assimilator 1 4217
Protoss_Cybernetics_Core 1 5837
Protoss_Dragoon 10 14987
Protoss_Robotics_Facility 1 9604
Singularity_Charge 1 9581
Protoss_Observatory 1 10513
Protoss_Nexus 2 15751
Protoss_Observer 3 13407
15751
