Protoss_Gateway 2 6424
Protoss_Assimilator 1 4376
Protoss_Cybernetics_Core 1 5604
Protoss_Dragoon 10 15771
Singularity_Charge 1 9830
Protoss_Nexus 2 14879
Protoss_Robotics_Facility 1 14938
15771
