Protoss_Gateway 7 15766
Protoss_Zealot 4 12593
Protoss_Nexus 2 15101
Protoss_Assimilator 2 11230
Protoss_Cybernetics_Core 1 8455
Protoss_Dragoon 6 15294
Protoss_Robotics_Facility 1 12992
Protoss_Observatory 2 13752
Singularity_Charge 1 13120
Protoss_Observer 1 14780
15766
