Protoss_Gateway 4 15083
Protoss_Assimilator 2 11992
Protoss_Nexus 1 8364
Protoss_Cybernetics_Core 1 7565
Protoss_Zealot 1 7512
Protoss_Dragoon 10 15168
Protoss_Robotics_Facility 1 11676
Singularity_Charge 1 11808
Protoss_Observatory 1 12613
Protoss_Observer 3 15459
15459
