Protoss_Gateway 2 9359
Protoss_Assimilator 3 7047
Protoss_Zealot 5 13103
Protoss_Cybernetics_Core 1 8251
Protoss_Dragoon 5 12282
Protoss_Citadel_of_Adun 1 10798
Protoss_Templar_Archives 1 13237
Protoss_Dark_Templar 4 15777
Singularity_Charge 1 13921
15777
