Protoss_Gateway 2 6361
Protoss_Assimilator 1 4170
Protoss_Cybernetics_Core 1 5622
Protoss_Dragoon 7 15071
Singularity_Charge 1 9458
Protoss_Nexus 2 14812
Protoss_Robotics_Facility 1 12826
Protoss_Shuttle 1 14229
Protoss_Robotics_Support_Bay 1 13924
Protoss_Reaver 1 15846
15846
