Protoss_Gateway 3 12402
Protoss_Assimilator 1 4397
Protoss_Cybernetics_Core 1 5783
Protoss_Dragoon 13 15721
Protoss_Nexus 1 11095
Protoss_Robotics_Facility 1 11527
Singularity_Charge 1 9903
Protoss_Observatory 1 12353
Protoss_Observer 1 13381
15721
