Protoss_Nexus 2 17215
Protoss_Gateway 2 8066
Protoss_Assimilator 2 12045
Protoss_Cybernetics_Core 1 7649
Protoss_Dragoon 10 14899
Protoss_Robotics_Facility 1 13283
Protoss_Zealot 2 12547
Singularity_Charge 1 12057
Protoss_Citadel_of_Adun 1 14364
Protoss_Observatory 1 14239
17215
