Protoss_Gateway 2 12361
Protoss_Assimilator 1 4191
Protoss_Cybernetics_Core 1 5683
Protoss_Zealot 1 5587
Protoss_Dragoon 10 15089
Protoss_Nexus 2 17070
Singularity_Charge 1 9727
Protoss_Robotics_Facility 1 12177
Protoss_Observatory 1 14501
Protoss_Observer 1 15514
17070
