Protoss_Gateway 3 15359
Protoss_Assimilator 1 4337
Protoss_Cybernetics_Core 1 5658
Protoss_Dragoon 9 15578
Protoss_Robotics_Facility 1 10691
Singularity_Charge 1 9619
Protoss_Nexus 2 15038
Protoss_Observatory 1 11627
Protoss_Observer 3 14543
Protoss_Shuttle 1 15901
15901
