Protoss_Gateway 2 12058
Protoss_Assimilator 2 13094
Protoss_Cybernetics_Core 1 5715
Protoss_Dragoon 11 15704
Protoss_Robotics_Facility 1 8164
Protoss_Zealot 1 8891
Protoss_Observatory 1 9048
Protoss_Observer 3 13302
Protoss_Nexus 1 12969
Singularity_Charge 1 11255
Protoss_Citadel_of_Adun 1 13000
Protoss_Templar_Archives 1 15329
15704
