Protoss_Gateway 1 4354
Protoss_Assimilator 1 4571
Protoss_Cybernetics_Core 1 6040
Protoss_Dragoon 4 14985
Protoss_Robotics_Facility 1 8653
Protoss_Zealot 2 9814
Protoss_Shuttle 1 10087
Protoss_Robotics_Support_Bay 1 9458
Protoss_Reaver 3 15944
Protoss_Shield_Battery 1 13033
Gravitic_Drive 1 13809
15944
