Protoss_Gateway 3 10451
Protoss_Zealot 4 7647
Protoss_Assimilator 1 6090
Protoss_Cybernetics_Core 1 8114
Protoss_Dragoon 9 15071
Protoss_Robotics_Facility 1 12856
Singularity_Charge 1 11896
Protoss_Observatory 1 13547
Protoss_Observer 2 15456
15456
