Protoss_Gateway 3 14088
Protoss_Assimilator 1 4403
Protoss_Cybernetics_Core 1 5750
Protoss_Dragoon 8 15405
Protoss_Robotics_Facility 1 8615
Protoss_Observatory 1 9530
Protoss_Observer 1 11039
Protoss_Nexus 1 13335
Singularity_Charge 1 11785
Protoss_Shuttle 1 15468
Protoss_Citadel_of_Adun 1 15510
15510
