Protoss_Gateway 4 16005
Protoss_Assimilator 1 4327
Protoss_Cybernetics_Core 1 5742
Protoss_Dragoon 6 15297
Protoss_Robotics_Facility 1 8262
Protoss_Zealot 4 13789
Protoss_Shuttle 1 9678
Protoss_Robotics_Support_Bay 1 9537
Protoss_Reaver 1 11526
Singularity_Charge 1 11343
Protoss_Nexus 1 15034
16005
