Protoss_Nexus 2 14040
Protoss_Gateway 4 14683
Protoss_Assimilator 2 13330
Protoss_Cybernetics_Core 1 7542
Protoss_Zealot 1 7714
Protoss_Dragoon 10 15800
Singularity_Charge 1 11589
Protoss_Citadel_of_Adun 1 13638
Protoss_Templar_Archives 1 15225
Protoss_Stargate 1 15534
15800
