Protoss_Nexus 2 15845
Protoss_Gateway 4 14929
Protoss_Assimilator 2 13125
Protoss_Cybernetics_Core 1 7379
Protoss_Zealot 3 14060
Protoss_Dragoon 10 15546
Protoss_Robotics_Facility 1 11840
Singularity_Charge 1 11279
Protoss_Observatory 1 12771
Protoss_Observer 2 14663
15845
