Protoss_Gateway 4 15210
Protoss_Assimilator 1 4164
Protoss_Cybernetics_Core 1 5589
Protoss_Dragoon 10 15566
Protoss_Nexus 2 14577
Singularity_Charge 1 9458
Protoss_Zealot 1 15037
15566
