Protoss_Gateway 2 7429
Protoss_Assimilator 1 4387
Protoss_Zealot 1 5066
Protoss_Cybernetics_Core 1 6722
Protoss_Dragoon 10 14144
Protoss_Nexus 1 11848
Protoss_Robotics_Facility 1 12025
Singularity_Charge 1 10500
Protoss_Observatory 1 12809
Protoss_Observer 1 13925
Protoss_Robotics_Support_Bay 1 14548
Protoss_Shuttle 1 15283
15283
