Protoss_Gateway 3 15621
Protoss_Assimilator 1 4343
Protoss_Cybernetics_Core 1 5847
Protoss_Dragoon 7 15660
Protoss_Robotics_Facility 1 8489
Protoss_Zealot 2 9962
Protoss_Shuttle 1 9945
Protoss_Observatory 1 9872
Protoss_Observer 2 14587
Protoss_Robotics_Support_Bay 1 11144
Protoss_Reaver 1 12905
Singularity_Charge 1 11507
Protoss_Nexus 1 15836
15836
