Protoss_Gateway 3 13707
Protoss_Assimilator 2 15032
Protoss_Cybernetics_Core 1 5800
Protoss_Dragoon 12 15642
Protoss_Nexus 1 12236
Singularity_Charge 1 9742
Protoss_Robotics_Facility 1 11950
Protoss_Observatory 1 12774
Protoss_Observer 2 14736
Protoss_Zealot 1 14771
Protoss_Citadel_of_Adun 1 15637
15642
