Protoss_Nexus 2 13641
Protoss_Gateway 3 15722
Protoss_Assimilator 2 13747
Protoss_Cybernetics_Core 1 7117
Protoss_Zealot 1 6801
Protoss_Dragoon 12 15506
Singularity_Charge 1 11674
Protoss_Robotics_Facility 1 13658
Protoss_Citadel_of_Adun 1 14120
Protoss_Observatory 1 14928
Protoss_Forge 1 15512
15722
