Protoss_Gateway 4 15626
Protoss_Assimilator 2 13982
Protoss_Cybernetics_Core 1 5636
Protoss_Zealot 1 5434
Protoss_Citadel_of_Adun 1 7132
Protoss_Dragoon 7 15268
Protoss_Templar_Archives 1 8572
Protoss_Dark_Templar 7 12950
Protoss_Nexus 1 11813
Protoss_Robotics_Facility 1 15032
15626
