Protoss_Nexus 1 6725
Protoss_Gateway 3 14205
Protoss_Assimilator 2 13079
Protoss_Cybernetics_Core 1 7357
Protoss_Zealot 1 7155
Protoss_Dragoon 13 15508
Protoss_Robotics_Facility 1 12985
Singularity_Charge 1 12956
Protoss_Observatory 1 14154
Protoss_Observer 1 15286
Protoss_Citadel_of_Adun 1 15886
15886
