Protoss_Gateway 4 12898
Protoss_Zealot 4 15023
Protoss_Nexus 2 9379
Protoss_Assimilator 2 12964
Protoss_Cybernetics_Core 1 8846
Protoss_Dragoon 8 15253
Protoss_Robotics_Facility 1 13109
Singularity_Charge 1 13160
Protoss_Observatory 1 14954
15253
