Protoss_Gateway 4 15994
Protoss_Assimilator 1 4255
Protoss_Cybernetics_Core 1 5594
Protoss_Dragoon 9 15420
Protoss_Nexus 2 16139
Protoss_Robotics_Facility 1 11107
Singularity_Charge 1 9540
Protoss_Observatory 1 11905
Protoss_Observer 3 14742
16139
