Protoss_Nexus 1 6704
Protoss_Gateway 4 14004
Protoss_Assimilator 2 14339
Protoss_Zealot 3 14645
Protoss_Cybernetics_Core 1 7935
Protoss_Dragoon 12 15812
Protoss_Robotics_Facility 1 13265
Protoss_Observatory 1 14278
Singularity_Charge 1 13600
15812
