Protoss_Gateway 2 10483
Protoss_Assimilator 1 4275
Protoss_Cybernetics_Core 1 5939
Protoss_Dragoon 8 14673
Protoss_Citadel_of_Adun 1 8837
Protoss_Templar_Archives 1 10296
Singularity_Charge 1 9640
Protoss_Zealot 1 10682
Protoss_Dark_Templar 2 12089
Protoss_Nexus 1 14522
Protoss_Robotics_Facility 1 13669
Protoss_Shuttle 1 15102
Protoss_Robotics_Support_Bay 1 14586
Protoss_Observatory 1 15114
15114
