Protoss_Gateway 2 6590
Protoss_Assimilator 2 13736
Protoss_Cybernetics_Core 1 5929
Protoss_Dragoon 10 14770
Singularity_Charge 1 9628
Protoss_Nexus 1 13377
Protoss_Robotics_Facility 1 14322
Protoss_Observatory 1 15113
15113
