Protoss_Gateway 1 4239
Protoss_Assimilator 1 4211
Protoss_Cybernetics_Core 1 5717
Protoss_Dragoon 7 14843
Protoss_Robotics_Facility 1 8287
Protoss_Shuttle 1 9684
Protoss_Robotics_Support_Bay 1 9895
Protoss_Reaver 1 11713
Protoss_Observatory 1 12508
Protoss_Nexus 1 16257
Protoss_Observer 1 14511
Singularity_Charge 1 14560
16257
