Protoss_Gateway 2 12334
Protoss_Assimilator 1 4261
Protoss_Cybernetics_Core 1 5614
Protoss_Zealot 3 14645
Protoss_Dragoon 9 15797
Protoss_Nexus 1 11784
Singularity_Charge 1 9941
Protoss_Robotics_Facility 1 12089
Protoss_Shuttle 1 13486
Protoss_Robotics_Support_Bay 1 12932
Protoss_Reaver 1 15044
Protoss_Observatory 1 14356
15797
