Protoss_Gateway 5 14433
Protoss_Assimilator 1 4378
Protoss_Cybernetics_Core 1 5707
Protoss_Dragoon 10 15595
Protoss_Nexus 1 11065
Protoss_Robotics_Facility 1 10835
Singularity_Charge 1 9601
Protoss_Shuttle 1 12456
Protoss_Observatory 1 12274
Protoss_Observer 1 13682
Protoss_Robotics_Support_Bay 1 14074
Protoss_Zealot 3 14932
15595
