Protoss_Gateway 1 4152
Protoss_Assimilator 2 11999
Protoss_Cybernetics_Core 1 5742
Protoss_Zealot 1 5721
Protoss_Dragoon 4 14234
Protoss_Citadel_of_Adun 1 7618
Protoss_Templar_Archives 1 9067
Protoss_Dark_Templar 3 15607
Protoss_Nexus 1 12615
Protoss_Stargate 1 12477
Protoss_Arbiter_Tribunal 1 14493
15607
