Protoss_Gateway 5 16019
Protoss_Assimilator 1 4388
Protoss_Cybernetics_Core 1 5601
Protoss_Dragoon 9 15505
Protoss_Robotics_Facility 1 8223
Protoss_Zealot 1 8805
Protoss_Nexus 2 15643
Protoss_Observatory 1 10514
Protoss_Observer 4 14203
Singularity_Charge 1 11331
Protoss_Citadel_of_Adun 1 14948
16019
