Protoss_Gateway 2 15213
Protoss_Assimilator 1 4332
Protoss_Cybernetics_Core 1 5715
Protoss_Dragoon 6 14791
Protoss_Robotics_Facility 1 8170
Protoss_Zealot 2 9927
Protoss_Shuttle 1 9576
Protoss_Robotics_Support_Bay 1 9434
Protoss_Reaver 1 11409
Protoss_Nexus 1 14725
Singularity_Charge 1 12897
15213
