Protoss_Gateway 3 13678
Protoss_Assimilator 1 4151
Protoss_Cybernetics_Core 1 5546
Protoss_Dragoon 11 15531
Protoss_Robotics_Facility 1 9490
Singularity_Charge 1 9590
Protoss_Observatory 1 10567
Protoss_Nexus 1 13603
Protoss_Observer 3 13477
Protoss_Citadel_of_Adun 1 13872
15531
