Protoss_Gateway 2 12191
Protoss_Assimilator 1 4283
Protoss_Cybernetics_Core 1 5827
Protoss_Zealot 1 6049
Protoss_Dragoon 9 15642
Protoss_Nexus 1 11943
Singularity_Charge 1 9897
Protoss_Robotics_Facility 1 12036
Protoss_Observatory 1 12872
Protoss_Shuttle 1 14095
Protoss_Robotics_Support_Bay 1 14666
Protoss_Observer 1 14938
15642
