Protoss_Gateway 4 15260
Protoss_Assimilator 1 4065
Protoss_Zealot 2 6582
Protoss_Cybernetics_Core 1 6751
Protoss_Dragoon 10 14703
Protoss_Nexus 2 16872
Protoss_Robotics_Facility 1 11185
Singularity_Charge 1 10626
Protoss_Observatory 1 12230
Protoss_Observer 3 15371
Protoss_Citadel_of_Adun 1 15078
16872
