Protoss_Gateway 2 10338
Protoss_Assimilator 1 4448
Protoss_Cybernetics_Core 1 5873
Protoss_Dragoon 9 15203
Protoss_Robotics_Facility 1 8482
Protoss_Zealot 1 9245
Protoss_Observatory 1 9282
Protoss_Observer 3 14654
Singularity_Charge 1 11492
Protoss_Nexus 1 15524
Protoss_Citadel_of_Adun 1 14988
15524
