Protoss_Gateway 4 14737
Protoss_Assimilator 1 4306
Protoss_Cybernetics_Core 1 5998
Protoss_Dragoon 7 15513
Protoss_Nexus 2 12971
Protoss_Robotics_Facility 1 13576
Singularity_Charge 1 12086
Protoss_Observatory 1 14275
15513
