Protoss_Gateway 3 14607
Protoss_Assimilator 2 14544
Protoss_Cybernetics_Core 1 5655
Protoss_Dragoon 11 14799
Protoss_Robotics_Facility 1 10011
Singularity_Charge 1 9522
Protoss_Observatory 1 10804
Protoss_Observer 2 15005
Protoss_Nexus 1 14279
Protoss_Citadel_of_Adun 1 15163
15163
