Protoss_Gateway 2 13293
Protoss_Assimilator 2 13752
Protoss_Cybernetics_Core 1 5563
Protoss_Zealot 1 5481
Protoss_Dragoon 9 15715
Protoss_Citadel_of_Adun 1 9116
Protoss_Templar_Archives 1 10605
Singularity_Charge 1 9827
Protoss_Dark_Templar 1 11864
Protoss_Nexus 1 14460
Protoss_Robotics_Facility 1 13522
Protoss_Observatory 1 14426
Protoss_Observer 1 15485
15715
