Protoss_Gateway 2 12618
Protoss_Assimilator 1 4726
Protoss_Zealot 1 5338
Protoss_Cybernetics_Core 1 6681
Protoss_Dragoon 7 14272
Protoss_Nexus 1 11706
Singularity_Charge 1 10389
Protoss_Robotics_Facility 1 12398
Protoss_Forge 1 13173
Protoss_Observatory 1 13643
Protoss_Citadel_of_Adun 1 15892
15892
