Protoss_Gateway 2 6841
Protoss_Assimilator 2 14180
Protoss_Cybernetics_Core 1 6067
Protoss_Dragoon 8 14931
Singularity_Charge 1 9730
Protoss_Nexus 1 13588
Protoss_Robotics_Facility 1 13306
Protoss_Observatory 1 14390
Protoss_Citadel_of_Adun 1 15602
Protoss_Observer 1 15459
15602
