Protoss_Gateway 2 10190
Protoss_Assimilator 1 4431
Protoss_Cybernetics_Core 1 5721
Protoss_Dragoon 12 15417
Protoss_Robotics_Facility 1 10075
Singularity_Charge 1 9642
Protoss_Observatory 1 10932
Protoss_Nexus 1 14245
Protoss_Observer 3 14888
15417
