Protoss_Gateway 3 15855
Protoss_Zealot 1 5063
Protoss_Assimilator 1 5537
Protoss_Cybernetics_Core 1 7269
Protoss_Dragoon 7 14700
Protoss_Nexus 2 15274
Singularity_Charge 1 10977
Protoss_Robotics_Facility 1 13564
Protoss_Observatory 1 14584
15855
