Protoss_Gateway 4 14862
Protoss_Assimilator 1 4346
Protoss_Cybernetics_Core 1 5661
Protoss_Dragoon 8 15224
Protoss_Nexus 2 13266
Singularity_Charge 1 9543
Protoss_Robotics_Facility 1 12745
Protoss_Citadel_of_Adun 1 13709
Protoss_Observatory 1 13727
Protoss_Observer 1 15037
Protoss_Templar_Archives 1 15560
Protoss_Stargate 1 16193
16193
