Protoss_Gateway 1 4130
Protoss_Assimilator 1 4239
Protoss_Cybernetics_Core 1 5689
Protoss_Zealot 1 5631
Protoss_Dragoon 8 15487
Protoss_Robotics_Facility 1 10276
Singularity_Charge 1 9400
Protoss_Shuttle 1 12110
Protoss_Robotics_Support_Bay 1 12298
Protoss_Nexus 1 15311
Protoss_Reaver 1 14157
Protoss_Observatory 1 13371
Protoss_Observer 1 14982
15487
