Protoss_Gateway 3 15350
Protoss_Assimilator 1 4681
Protoss_Cybernetics_Core 1 6226
Protoss_Dragoon 8 14188
Singularity_Charge 1 10384
Protoss_Nexus 1 14459
Protoss_Robotics_Facility 1 14536
Protoss_Zealot 2 15185
15350
