Protoss_Gateway 3 12563
Protoss_Assimilator 2 14720
Protoss_Cybernetics_Core 1 5585
Protoss_Zealot 1 5481
Protoss_Dragoon 10 15707
Protoss_Robotics_Facility 1 9758
Protoss_Observatory 1 10469
Protoss_Nexus 1 12633
Singularity_Charge 1 9882
Protoss_Observer 4 14910
Protoss_Citadel_of_Adun 1 15065
15707
