Protoss_Nexus 1 6780
Protoss_Gateway 2 7373
Protoss_Assimilator 2 15447
Protoss_Cybernetics_Core 1 7486
Protoss_Zealot 4 12269
Protoss_Dragoon 9 15745
Protoss_Robotics_Facility 1 15771
Singularity_Charge 1 14337
15771
