Protoss_Nexus 1 6638
Protoss_Gateway 2 7490
Protoss_Assimilator 2 13726
Protoss_Cybernetics_Core 1 7117
Protoss_Zealot 1 7492
Protoss_Dragoon 12 15171
Protoss_Robotics_Facility 1 12038
Protoss_Observatory 1 12901
Singularity_Charge 1 12244
Protoss_Observer 2 15125
15171
