Protoss_Gateway 4 13757
Protoss_Assimilator 1 4308
Protoss_Cybernetics_Core 1 5769
Protoss_Dragoon 10 14899
Protoss_Robotics_Facility 1 8359
Protoss_Zealot 1 8932
Protoss_Observatory 1 9237
Protoss_Observer 2 11153
Protoss_Nexus 1 13217
Singularity_Charge 1 11308
Protoss_Shuttle 1 15839
15839
