Protoss_Gateway 4 14892
Protoss_Assimilator 2 15021
Protoss_Cybernetics_Core 1 6213
Protoss_Zealot 1 6251
Protoss_Dragoon 7 15607
Protoss_Citadel_of_Adun 1 8841
Protoss_Templar_Archives 1 10322
Protoss_Nexus 2 12892
Singularity_Charge 1 9970
Protoss_Dark_Templar 2 12838
Protoss_Robotics_Facility 1 13385
Protoss_Observatory 1 14436
Protoss_Observer 1 15453
15607
