Protoss_Gateway 2 12789
Protoss_Assimilator 2 15361
Protoss_Cybernetics_Core 1 5753
Protoss_Dragoon 9 15745
Protoss_Robotics_Facility 1 8367
Protoss_Zealot 1 8958
Protoss_Observatory 1 9291
Protoss_Observer 3 13472
Protoss_Nexus 2 15615
Singularity_Charge 1 11533
Protoss_Citadel_of_Adun 1 15204
15745
