Protoss_Nexus 1 6868
Protoss_Gateway 3 15451
Protoss_Assimilator 1 6160
Protoss_Cybernetics_Core 1 7565
Protoss_Zealot 1 7387
Protoss_Dragoon 7 13956
Protoss_Robotics_Facility 1 12910
Singularity_Charge 1 12865
Protoss_Shuttle 1 14361
Protoss_Robotics_Support_Bay 1 14242
Protoss_Reaver 1 16112
16112
