Protoss_Gateway 3 11158
Protoss_Assimilator 1 4144
Protoss_Cybernetics_Core 1 5592
Protoss_Dragoon 13 15326
Protoss_Robotics_Facility 1 10268
Singularity_Charge 1 9610
Protoss_Zealot 3 14189
Protoss_Observatory 1 11094
Protoss_Shuttle 1 12441
Protoss_Observer 1 13284
15326
