Protoss_Gateway 3 12814
Protoss_Assimilator 2 14246
Protoss_Cybernetics_Core 1 5847
Protoss_Dragoon 11 15710
Protoss_Nexus 1 11510
Singularity_Charge 1 9683
Protoss_Robotics_Facility 1 12434
Protoss_Observatory 1 13178
Protoss_Citadel_of_Adun 1 14320
Protoss_Observer 1 15034
Protoss_Templar_Archives 1 15833
15833
