Protoss_Gateway 2 10035
Protoss_Assimilator 3 15526
Protoss_Zealot 2 9754
Protoss_Nexus 1 10102
Protoss_Cybernetics_Core 1 9219
Protoss_Dragoon 9 15429
Singularity_Charge 1 13491
Protoss_Robotics_Facility 1 16050
16050
