Protoss_Gateway 3 13338
Protoss_Assimilator 1 4552
Protoss_Cybernetics_Core 1 5727
Protoss_Zealot 1 5914
Protoss_Dragoon 11 15794
Protoss_Robotics_Facility 1 8765
Protoss_Observatory 1 9780
Protoss_Observer 1 10899
Protoss_Nexus 2 15526
Singularity_Charge 1 12063
15794
