Protoss_Gateway 2 9078
Protoss_Assimilator 1 4580
Protoss_Cybernetics_Core 1 5914
Protoss_Dragoon 13 15025
Singularity_Charge 1 9859
Protoss_Robotics_Facility 1 11896
Protoss_Shuttle 1 13293
Protoss_Robotics_Support_Bay 1 13509
15025
