Protoss_Gateway 3 15590
Protoss_Assimilator 1 4412
Protoss_Cybernetics_Core 1 5797
Protoss_Dragoon 7 15727
Protoss_Robotics_Facility 1 8237
Protoss_Shuttle 1 9886
Protoss_Zealot 2 10981
Protoss_Robotics_Support_Bay 1 10195
Protoss_Reaver 1 12041
Singularity_Charge 1 11340
Protoss_Nexus 1 14579
Protoss_Observatory 1 13326
Protoss_Observer 1 14382
Protoss_Citadel_of_Adun 1 16040
16040
