Protoss_Gateway 3 13302
Protoss_Assimilator 2 14227
Protoss_Cybernetics_Core 1 5690
Protoss_Dragoon 10 15309
Protoss_Nexus 1 11343
Singularity_Charge 1 9698
Protoss_Robotics_Facility 1 12327
Protoss_Zealot 1 13220
Protoss_Citadel_of_Adun 1 14304
Protoss_Observatory 1 13670
Protoss_Observer 1 14686
Protoss_Templar_Archives 1 16021
16021
