Protoss_Nexus 2 12360
Protoss_Gateway 2 12734
Protoss_Assimilator 2 13864
Protoss_Zealot 2 8153
Protoss_Cybernetics_Core 1 7646
Protoss_Dragoon 7 15446
Protoss_Robotics_Facility 1 13529
Singularity_Charge 1 11691
Protoss_Citadel_of_Adun 1 13726
Protoss_Observatory 1 14337
Protoss_Templar_Archives 1 15247
Protoss_Shuttle 1 15397
15446
