Protoss_Gateway 2 10597
Protoss_Assimilator 2 14105
Protoss_Cybernetics_Core 1 5750
Protoss_Dragoon 7 15519
Protoss_Robotics_Facility 1 8223
Protoss_Zealot 2 15345
Protoss_Observatory 1 9086
Protoss_Observer 2 11072
Protoss_Nexus 1 13833
Singularity_Charge 1 11320
Protoss_Citadel_of_Adun 1 13021
Protoss_Templar_Archives 1 14613
Protoss_Shuttle 1 15362
Protoss_Stargate 1 15615
15615
