Protoss_Gateway 2 9697
Protoss_Assimilator 1 4638
Protoss_Cybernetics_Core 1 6187
Protoss_Zealot 1 5929
Protoss_Dragoon 12 15499
Protoss_Robotics_Facility 1 11991
Singularity_Charge 1 10137
Protoss_Shuttle 1 13401
Protoss_Robotics_Support_Bay 1 12994
Protoss_Reaver 1 15108
15499
