Protoss_Gateway 2 11070
Protoss_Assimilator 2 14912
Protoss_Cybernetics_Core 1 5786
Protoss_Dragoon 9 15546
Protoss_Robotics_Facility 1 8369
Protoss_Observatory 1 9449
Protoss_Zealot 1 10161
Protoss_Observer 2 11347
Protoss_Nexus 2 16080
Singularity_Charge 1 11369
Protoss_Citadel_of_Adun 1 13104
Protoss_Templar_Archives 1 14941
16080
