Protoss_Gateway 5 15746
Protoss_Assimilator 1 4340
Protoss_Cybernetics_Core 1 5837
Protoss_Dragoon 7 15686
Protoss_Robotics_Facility 1 8452
Protoss_Zealot 4 14039
Protoss_Observatory 1 9326
Protoss_Observer 2 11241
Protoss_Nexus 1 13639
Singularity_Charge 1 11442
Protoss_Shuttle 1 14414
Protoss_Citadel_of_Adun 1 14837
15746
