Protoss_Gateway 2 15067
Protoss_Assimilator 1 4309
Protoss_Cybernetics_Core 1 5685
Protoss_Dragoon 6 14720
Protoss_Robotics_Facility 1 8234
Protoss_Zealot 1 8909
Protoss_Shuttle 1 9813
Protoss_Robotics_Support_Bay 1 10067
Protoss_Reaver 1 11795
Protoss_Observatory 1 11672
Singularity_Charge 1 11276
Protoss_Observer 2 14680
Protoss_Nexus 1 15299
Protoss_Citadel_of_Adun 1 15611
15611
