Protoss_Nexus 1 6701
Protoss_Gateway 2 7512
Protoss_Assimilator 2 13688
Protoss_Cybernetics_Core 1 7237
Protoss_Zealot 2 9785
Protoss_Dragoon 10 15168
Protoss_Robotics_Facility 1 13612
Protoss_Observatory 1 14420
Protoss_Citadel_of_Adun 1 15216
Protoss_Observer 1 15512
15512
