Protoss_Gateway 2 11846
Protoss_Assimilator 1 4384
Protoss_Cybernetics_Core 1 5802
Protoss_Zealot 1 5549
Protoss_Dragoon 10 15273
Protoss_Nexus 1 12406
Singularity_Charge 1 9721
Protoss_Robotics_Facility 1 12916
Protoss_Observatory 1 14676
15273
