Protoss_Gateway 4 14022
Protoss_Assimilator 1 4448
Protoss_Cybernetics_Core 1 5663
Protoss_Zealot 1 5467
Protoss_Dragoon 11 15391
Protoss_Nexus 1 11714
Singularity_Charge 1 9903
Protoss_Robotics_Facility 1 12080
Protoss_Observatory 1 12999
Protoss_Observer 2 15520
Protoss_Citadel_of_Adun 1 15999
15999
