Protoss_Gateway 3 12555
Protoss_Assimilator 2 13252
Protoss_Cybernetics_Core 1 5724
Protoss_Dragoon 10 15291
Protoss_Nexus 1 11383
Singularity_Charge 1 9525
Protoss_Robotics_Facility 1 12286
Protoss_Observatory 1 13116
Protoss_Citadel_of_Adun 1 13868
Protoss_Observer 1 14268
Protoss_Templar_Archives 1 15652
Protoss_Zealot 1 15272
15652
