Protoss_Assimilator 2 12845
Protoss_Gateway 2 11616
Protoss_Cybernetics_Core 1 6219
Protoss_Zealot 1 6163
Protoss_Dragoon 6 15616
Protoss_Nexus 1 11690
Protoss_Citadel_of_Adun 1 10890
Singularity_Charge 1 10360
Protoss_Robotics_Facility 1 12704
Protoss_Templar_Archives 1 12532
Protoss_Shuttle 1 14109
Protoss_Dark_Templar 2 14138
Protoss_Observatory 2 14562
Protoss_Stargate 1 15449
Protoss_Observer 1 14952
15616
