Protoss_Gateway 4 14241
Protoss_Assimilator 2 14535
Protoss_Cybernetics_Core 1 5613
Protoss_Zealot 1 5408
Protoss_Dragoon 11 15762
Protoss_Nexus 1 11594
Singularity_Charge 1 9815
Protoss_Robotics_Facility 1 11945
Protoss_Observatory 1 12830
Protoss_Observer 2 15295
15762
