Protoss_Gateway 2 9002
Protoss_Assimilator 1 4656
Protoss_Zealot 2 6359
Protoss_Cybernetics_Core 1 6588
Protoss_Dragoon 10 14638
Singularity_Charge 1 10725
Protoss_Nexus 2 17131
Protoss_Robotics_Facility 1 14530
17131
