Protoss_Gateway 4 15511
Protoss_Assimilator 1 4207
Protoss_Zealot 1 5139
Protoss_Cybernetics_Core 1 6769
Protoss_Dragoon 9 15610
Protoss_Nexus 2 13855
Singularity_Charge 1 11030
Protoss_Robotics_Facility 1 13368
Protoss_Observatory 1 14217
Protoss_Observer 1 15473
15610
