Protoss_Nexus 1 6622
Protoss_Gateway 4 15825
Protoss_Assimilator 2 10239
Protoss_Cybernetics_Core 1 7496
Protoss_Zealot 1 7553
Protoss_Dragoon 7 15786
Protoss_Citadel_of_Adun 1 11404
Protoss_Robotics_Facility 1 12462
Protoss_Templar_Archives 1 12845
Singularity_Charge 1 11732
Protoss_Shuttle 2 14285
Protoss_Observatory 1 13501
Protoss_Dark_Templar 2 14179
Protoss_Forge 1 14983
Protoss_Observer 1 15128
15825
