Protoss_Assimilator 2 15312
Protoss_Gateway 4 15217
Protoss_Cybernetics_Core 1 6204
Protoss_Zealot 1 6152
Protoss_Dragoon 6 15326
Protoss_Citadel_of_Adun 1 8683
Protoss_Robotics_Facility 1 9898
Protoss_Templar_Archives 1 10135
Protoss_Shuttle 1 11306
Protoss_Dark_Templar 4 12484
Protoss_Nexus 1 14548
Protoss_Observatory 1 12824
Protoss_Observer 1 14115
15326
