Protoss_Gateway 4 14436
Protoss_Assimilator 1 4205
Protoss_Cybernetics_Core 1 5588
Protoss_Robotics_Facility 1 7785
Protoss_Dragoon 8 15800
Protoss_Observatory 1 8599
Protoss_Observer 4 15032
Protoss_Nexus 2 15160
Singularity_Charge 1 11832
15800
