Protoss_Gateway 4 15298
Protoss_Assimilator 2 12835
Protoss_Cybernetics_Core 1 5745
Protoss_Dragoon 8 15253
Protoss_Nexus 1 11775
Protoss_Robotics_Facility 1 11098
Singularity_Charge 1 9584
Protoss_Observatory 1 11796
Protoss_Citadel_of_Adun 1 13056
Protoss_Observer 2 14844
Protoss_Stargate 1 14754
Protoss_Templar_Archives 1 14832
15298
