Protoss_Gateway 3 12353
Protoss_Assimilator 2 14550
Protoss_Cybernetics_Core 1 5592
Protoss_Dragoon 11 14793
Protoss_Nexus 2 17226
Singularity_Charge 1 9695
Protoss_Robotics_Facility 1 12004
Protoss_Observatory 1 12909
Protoss_Observer 2 14812
17226
