Protoss_Gateway 2 7449
Protoss_Assimilator 1 4426
Protoss_Zealot 4 13709
Protoss_Cybernetics_Core 1 6800
Protoss_Dragoon 8 14829
Protoss_Nexus 1 13041
Singularity_Charge 1 10497
Protoss_Robotics_Facility 1 12791
Protoss_Shuttle 1 14431
Protoss_Robotics_Support_Bay 1 14085
Protoss_Reaver 1 15989
15989
