Protoss_Gateway 2 13366
Protoss_Assimilator 1 4495
Protoss_Cybernetics_Core 1 5789
Protoss_Zealot 2 13515
Protoss_Dragoon 6 14709
Protoss_Nexus 1 10834
Protoss_Robotics_Facility 1 10507
Protoss_Shuttle 1 12151
Protoss_Robotics_Support_Bay 1 12098
Protoss_Reaver 1 13824
Protoss_Observatory 1 13468
Singularity_Charge 1 12795
Protoss_Observer 1 14648
14709
