Protoss_Gateway 2 8429
Protoss_Assimilator 2 14540
Protoss_Cybernetics_Core 1 6078
Protoss_Nexus 1 8873
Protoss_Dragoon 13 15151
Singularity_Charge 1 10845
Protoss_Robotics_Facility 1 12987
Protoss_Observatory 1 14223
Protoss_Shuttle 1 15046
15151
