Protoss_Gateway 4 14622
Protoss_Assimilator 2 13463
Protoss_Cybernetics_Core 1 5566
Protoss_Zealot 1 5458
Protoss_Citadel_of_Adun 1 7029
Protoss_Dragoon 7 15121
Protoss_Templar_Archives 1 8518
Protoss_Dark_Templar 1 9718
Protoss_Nexus 1 11841
Protoss_Robotics_Facility 1 11738
Protoss_Observatory 1 12544
Protoss_Observer 2 14762
15121
