Protoss_Gateway 4 13529
Protoss_Assimilator 1 4120
Protoss_Cybernetics_Core 1 5525
Protoss_Dragoon 10 15461
Protoss_Robotics_Facility 1 10056
Singularity_Charge 1 9470
Protoss_Nexus 1 12896
Protoss_Observatory 1 10816
Protoss_Observer 1 11947
Protoss_Shuttle 1 14642
15461
