Protoss_Gateway 2 15936
Protoss_Assimilator 1 4590
Protoss_Cybernetics_Core 1 5844
Protoss_Zealot 1 5780
Protoss_Robotics_Facility 1 8309
Protoss_Dragoon 6 15671
Protoss_Shuttle 1 9722
Protoss_Robotics_Support_Bay 1 9527
Protoss_Reaver 1 11722
Protoss_Observatory 1 11798
Protoss_Observer 2 14414
Protoss_Nexus 1 16569
Singularity_Charge 1 13919
16569
