Protoss_Gateway 5 15264
Protoss_Assimilator 2 13021
Protoss_Cybernetics_Core 1 5727
Protoss_Dragoon 7 13787
Protoss_Nexus 1 11273
Protoss_Robotics_Facility 1 10757
Singularity_Charge 1 9622
Protoss_Observatory 1 11665
Protoss_Citadel_of_Adun 1 12883
Protoss_Observer 1 12886
Protoss_Templar_Archives 1 14964
Protoss_Zealot 3 15547
15547
