Protoss_Gateway 2 8475
Protoss_Nexus 2 13584
Protoss_Zealot 1 5528
Protoss_Assimilator 2 11269
Protoss_Cybernetics_Core 1 7485
Protoss_Dragoon 7 14063
Protoss_Robotics_Facility 1 11893
Singularity_Charge 1 11785
Protoss_Observatory 1 12824
Protoss_Observer 2 14753
Protoss_Citadel_of_Adun 1 14642
Protoss_Forge 1 14263
Protoss_Stargate 1 15874
Protoss_Photon_Cannon 1 15819
15874
