Protoss_Nexus 1 6690
Protoss_Gateway 2 7673
Protoss_Assimilator 2 11964
Protoss_Cybernetics_Core 1 7419
Protoss_Zealot 1 7571
Protoss_Dragoon 11 14723
Protoss_Robotics_Facility 1 12226
Singularity_Charge 1 11999
Protoss_Citadel_of_Adun 1 13659
Protoss_Shuttle 1 13735
Protoss_Robotics_Support_Bay 1 14050
Protoss_Templar_Archives 1 15178
Protoss_Stargate 1 15612
Protoss_Reaver 1 15787
15787
