Protoss_Gateway 3 11393
Protoss_Assimilator 1 4240
Protoss_Cybernetics_Core 1 5775
Protoss_Zealot 1 5616
Protoss_Dragoon 13 15303
Protoss_Robotics_Facility 1 10864
Singularity_Charge 1 9757
Protoss_Observatory 1 11960
Protoss_Observer 2 14039
15303
