Protoss_Gateway 2 11388
Protoss_Assimilator 1 4409
Protoss_Cybernetics_Core 1 5942
Protoss_Dragoon 10 15644
Protoss_Robotics_Facility 1 9658
Protoss_Observatory 1 10403
Protoss_Observer 3 14998
Singularity_Charge 1 12675
Protoss_Shuttle 1 14155
Protoss_Nexus 1 16676
16676
