Protoss_Gateway 2 13949
Protoss_Assimilator 1 4635
Protoss_Cybernetics_Core 1 6159
Protoss_Dragoon 7 15600
Protoss_Robotics_Facility 1 9017
Protoss_Shuttle 2 16050
Protoss_Robotics_Support_Bay 1 10055
Protoss_Reaver 1 11988
Protoss_Observatory 1 11215
Protoss_Observer 1 13210
16050
