Protoss_Nexus 1 6827
Protoss_Gateway 4 15475
Protoss_Assimilator 2 10829
Protoss_Cybernetics_Core 1 7387
Protoss_Zealot 1 7916
Protoss_Dragoon 12 15484
Protoss_Robotics_Facility 1 12914
Singularity_Charge 1 11838
Protoss_Observatory 1 13942
Protoss_Citadel_of_Adun 1 14803
Protoss_Observer 1 15181
15484
