Protoss_Assimilator 3 12607
Protoss_Gateway 2 9643
Protoss_Zealot 3 8142
Protoss_Nexus 1 9886
Protoss_Cybernetics_Core 1 9189
Protoss_Dragoon 8 14152
Protoss_Stargate 2 16168
Singularity_Charge 1 12964
Protoss_Fleet_Beacon 1 15459
16168
