Protoss_Gateway 3 15885
Protoss_Assimilator 1 4391
Protoss_Cybernetics_Core 1 6195
Protoss_Zealot 2 12090
Protoss_Dragoon 7 15702
Protoss_Robotics_Facility 1 10200
Protoss_Shuttle 1 11645
Protoss_Robotics_Support_Bay 1 11518
Protoss_Reaver 1 13325
Singularity_Charge 1 12506
Protoss_Observatory 1 13411
Protoss_Observer 1 14439
15885
