Protoss_Gateway 2 12314
Protoss_Assimilator 1 4512
Protoss_Cybernetics_Core 1 5671
Protoss_Zealot 2 14830
Protoss_Dragoon 9 15721
Protoss_Nexus 1 11999
Singularity_Charge 1 9812
Protoss_Robotics_Facility 1 12294
Protoss_Shuttle 1 13726
Protoss_Robotics_Support_Bay 1 13560
Protoss_Reaver 1 15489
Protoss_Observatory 1 15104
15721
