Protoss_Gateway 1 4287
Protoss_Assimilator 1 4654
Protoss_Cybernetics_Core 1 5951
Protoss_Robotics_Facility 1 8122
Protoss_Dragoon 4 15551
Protoss_Shuttle 1 9640
Protoss_Robotics_Support_Bay 1 9828
Protoss_Reaver 2 14312
Protoss_Zealot 3 14432
Protoss_Nexus 1 17329
Protoss_Observatory 1 15189
17329
