Protoss_Nexus 2 15745
Protoss_Gateway 2 7486
Protoss_Assimilator 1 5876
Protoss_Cybernetics_Core 1 7356
Protoss_Zealot 2 13403
Protoss_Dragoon 10 14925
Singularity_Charge 1 11656
Protoss_Robotics_Facility 1 14066
Protoss_Shuttle 1 15500
15745
