Protoss_Gateway 3 14251
Protoss_Assimilator 2 14578
Protoss_Cybernetics_Core 1 5799
Protoss_Dragoon 9 14199
Singularity_Charge 1 9461
Protoss_Nexus 1 13650
Protoss_Robotics_Facility 1 13573
Protoss_Citadel_of_Adun 1 14930
Protoss_Observatory 1 14477
14930
