Protoss_Gateway 3 11090
Protoss_Assimilator 1 4575
Protoss_Cybernetics_Core 1 5932
Protoss_Nexus 1 9536
Protoss_Dragoon 9 13965
Protoss_Zealot 4 14827
Singularity_Charge 1 10960
Protoss_Robotics_Facility 1 15342
15342
