Protoss_Gateway 4 14835
Protoss_Assimilator 2 13065
Protoss_Cybernetics_Core 1 5952
Protoss_Dragoon 5 14802
Protoss_Nexus 1 11617
Protoss_Citadel_of_Adun 1 10482
Singularity_Charge 1 9909
Protoss_Templar_Archives 1 12027
Protoss_Stargate 1 12648
Protoss_Dark_Templar 1 13430
Protoss_Arbiter_Tribunal 1 14149
14835
