Protoss_Nexus 1 6731
Protoss_Gateway 5 14862
Protoss_Assimilator 2 7884
Protoss_Cybernetics_Core 1 7591
Protoss_Dragoon 8 15083
Protoss_Robotics_Facility 1 11009
Protoss_Citadel_of_Adun 1 11423
Protoss_Observatory 1 11755
Singularity_Charge 1 11498
Protoss_Templar_Archives 1 12974
Protoss_Observer 4 15444
Protoss_Stargate 1 13524
Protoss_Dark_Templar 2 14723
15444
