Protoss_Nexus 1 6599
Protoss_Gateway 2 12008
Protoss_Assimilator 2 9156
Protoss_Cybernetics_Core 1 7264
Protoss_Zealot 2 8420
Protoss_Dragoon 10 15733
Protoss_Citadel_of_Adun 1 11565
Singularity_Charge 1 11191
Protoss_Robotics_Facility 1 13137
Protoss_Templar_Archives 1 13275
Protoss_Stargate 1 13635
Protoss_Observatory 1 13968
Protoss_Dark_Templar 1 14632
Protoss_Arbiter_Tribunal 1 15122
Protoss_Observer 1 15067
15733
