Protoss_Gateway 3 15541
Protoss_Assimilator 1 4267
Protoss_Cybernetics_Core 1 6143
Protoss_Dragoon 9 14322
Singularity_Charge 1 9812
Protoss_Nexus 1 13120
Protoss_Robotics_Facility 1 13762
Protoss_Observatory 1 14549
Protoss_Citadel_of_Adun 1 15956
15956
