Protoss_Nexus 2 14422
Protoss_Gateway 3 13502
Protoss_Assimilator 3 9659
Protoss_Cybernetics_Core 1 7463
Protoss_Dragoon 7 15642
Protoss_Citadel_of_Adun 1 9368
Singularity_Charge 1 12944
Protoss_Robotics_Facility 1 15446
Protoss_Templar_Archives 1 15228
Protoss_Stargate 1 15610
15642
