Protoss_Gateway 2 6674
Protoss_Assimilator 1 4272
Protoss_Cybernetics_Core 1 5730
Protoss_Dragoon 10 14486
Singularity_Charge 1 9566
Protoss_Robotics_Facility 1 11785
Protoss_Observatory 1 12673
Protoss_Zealot 2 13366
Protoss_Observer 1 14086
Protoss_Nexus 1 16920
Protoss_Robotics_Support_Bay 1 15159
16920
