Protoss_Gateway 2 8540
Protoss_Assimilator 1 4428
Protoss_Cybernetics_Core 1 5841
Protoss_Dragoon 6 11375
Protoss_Citadel_of_Adun 1 9504
Protoss_Templar_Archives 1 11311
Singularity_Charge 1 9915
Protoss_Dark_Templar 3 13620
Protoss_Nexus 1 15157
Protoss_Robotics_Facility 1 15812
15812
