Protoss_Gateway 3 9391
Protoss_Assimilator 2 6732
Protoss_Cybernetics_Core 1 5649
Protoss_Dragoon 5 10631
Singularity_Charge 1 10073
Protoss_Nexus 2 16146
Protoss_Robotics_Facility 1 13371
Protoss_Citadel_of_Adun 1 13883
Protoss_Shuttle 1 14771
Protoss_Robotics_Support_Bay 1 14593
Protoss_Templar_Archives 1 15680
16146
