Protoss_Gateway 2 11294
Protoss_Assimilator 1 4571
Protoss_Cybernetics_Core 1 5853
Protoss_Dragoon 10 15431
Protoss_Nexus 2 16135
Protoss_Robotics_Facility 1 11536
Singularity_Charge 1 9985
Protoss_Observatory 1 12525
Protoss_Observer 2 15509
Protoss_Citadel_of_Adun 1 15931
16135
