Protoss_Gateway 4 16056
Protoss_Assimilator 2 14964
Protoss_Cybernetics_Core 1 5888
Protoss_Dragoon 8 13266
Protoss_Nexus 1 11703
Singularity_Charge 1 10111
Protoss_Citadel_of_Adun 1 12892
Protoss_Templar_Archives 1 14818
16056
