Protoss_Gateway 1 4401
Protoss_Assimilator 1 4758
Protoss_Cybernetics_Core 1 6109
Protoss_Dragoon 4 15424
Protoss_Robotics_Facility 1 8846
Protoss_Shuttle 1 11272
Protoss_Robotics_Support_Bay 1 10662
Protoss_Nexus 1 13281
Protoss_Reaver 3 15913
15913
