Protoss_Gateway 2 9421
Protoss_Assimilator 3 15550
Protoss_Cybernetics_Core 1 6239
Protoss_Dragoon 8 14843
Protoss_Nexus 2 15725
Singularity_Charge 1 10286
Protoss_Robotics_Facility 1 13071
Protoss_Observatory 1 13895
Protoss_Observer 1 15014
Protoss_Citadel_of_Adun 1 15782
15782
