Protoss_Gateway 2 8748
Protoss_Assimilator 1 4594
Protoss_Cybernetics_Core 1 5789
Protoss_Dragoon 5 12265
Protoss_Nexus 1 12103
Protoss_Zealot 2 10621
Singularity_Charge 1 9859
Protoss_Robotics_Facility 1 12267
Protoss_Robotics_Support_Bay 1 13001
Protoss_Shuttle 1 14112
Protoss_Observatory 1 13785
Protoss_Reaver 1 15670
15670
