Protoss_Gateway 3 15826
Protoss_Assimilator 2 11966
Protoss_Cybernetics_Core 1 5829
Protoss_Dragoon 9 15095
Protoss_Nexus 1 12306
Singularity_Charge 1 9888
Protoss_Citadel_of_Adun 1 12560
Protoss_Robotics_Facility 1 14144
Protoss_Templar_Archives 1 14860
Protoss_Stargate 1 15785
Protoss_Observatory 1 15012
15826
