Protoss_Gateway 3 12321
Protoss_Assimilator 1 4605
Protoss_Cybernetics_Core 1 6371
Protoss_Dragoon 10 15022
Protoss_Robotics_Facility 1 10966
Singularity_Charge 1 10070
Protoss_Nexus 1 13366
Protoss_Observatory 1 11758
Protoss_Observer 2 13732
Protoss_Robotics_Support_Bay 1 13667
Protoss_Zealot 2 15140
Protoss_Reaver 1 15606
15606
