Protoss_Gateway 2 5033
Protoss_Zealot 8 9017
Protoss_Forge 1 7095
Protoss_Photon_Cannon 4 13036
Protoss_Nexus 1 13184
Protoss_Assimilator 1 11739
Protoss_Cybernetics_Core 1 13913
Protoss_Citadel_of_Adun 1 15800
15800
