Protoss_Gateway 3 15681
Protoss_Assimilator 1 4142
Protoss_Cybernetics_Core 1 5576
Protoss_Dragoon 11 15791
Singularity_Charge 1 9382
Protoss_Nexus 2 14387
Protoss_Robotics_Facility 1 12601
Protoss_Observatory 1 13512
Protoss_Observer 2 15450
15791
