Protoss_Gateway 2 9378
Protoss_Assimilator 1 4992
Protoss_Zealot 3 7340
Protoss_Cybernetics_Core 1 6822
Protoss_Dragoon 10 15373
Protoss_Robotics_Facility 2 12952
Protoss_Nexus 1 13395
Protoss_Observatory 1 13778
Singularity_Charge 1 13444
Protoss_Observer 1 14862
15373
