Protoss_Gateway 2 12948
Protoss_Assimilator 2 13922
Protoss_Cybernetics_Core 1 5777
Protoss_Zealot 1 5531
Protoss_Dragoon 7 15244
Protoss_Citadel_of_Adun 1 9248
Protoss_Templar_Archives 1 10792
Singularity_Charge 1 9912
Protoss_Dark_Templar 1 12060
Protoss_Nexus 1 13966
Protoss_Stargate 1 14547
15244
