Protoss_Gateway 2 11749
Protoss_Assimilator 1 4681
Protoss_Zealot 1 5417
Protoss_Cybernetics_Core 1 6235
Protoss_Dragoon 6 15592
Protoss_Robotics_Facility 1 8839
Protoss_Shuttle 1 10284
Protoss_Robotics_Support_Bay 1 9660
Protoss_Reaver 2 14276
Protoss_Observatory 1 11738
Protoss_Observer 1 15302
15592
