Protoss_Gateway 1 4091
Protoss_Assimilator 1 4167
Protoss_Cybernetics_Core 1 5592
Protoss_Dragoon 6 14981
Protoss_Robotics_Facility 1 9671
Singularity_Charge 1 9599
Protoss_Observatory 1 10434
Protoss_Nexus 1 13189
Protoss_Observer 2 12333
Protoss_Robotics_Support_Bay 1 12124
Protoss_Zealot 2 13507
Protoss_Shuttle 1 13711
Protoss_Reaver 1 15269
15269
