Protoss_Gateway 2 14528
Protoss_Assimilator 1 4318
Protoss_Cybernetics_Core 1 5604
Protoss_Dragoon 8 15733
Protoss_Robotics_Facility 1 9033
Protoss_Shuttle 1 10474
Protoss_Robotics_Support_Bay 1 9919
Protoss_Reaver 2 15369
Singularity_Charge 1 11302
Protoss_Observatory 1 14578
15733
