Protoss_Gateway 2 9251
Protoss_Assimilator 2 14347
Protoss_Zealot 1 5240
Protoss_Cybernetics_Core 1 7016
Protoss_Dragoon 9 15088
Protoss_Nexus 1 13550
Singularity_Charge 1 10788
Protoss_Robotics_Facility 1 12818
Protoss_Stargate 1 14517
Protoss_Observatory 1 13624
Protoss_Observer 2 15535
15535
