Protoss_Gateway 2 9260
Protoss_Assimilator 1 4281
Protoss_Cybernetics_Core 1 5827
Protoss_Zealot 1 6242
Protoss_Dragoon 10 14261
Singularity_Charge 1 10122
Protoss_Nexus 2 16594
16594
