Protoss_Nexus 2 15278
Protoss_Gateway 4 14900
Protoss_Assimilator 1 5777
Protoss_Cybernetics_Core 1 7359
Protoss_Zealot 1 7308
Protoss_Dragoon 9 15259
Protoss_Robotics_Facility 1 11274
Singularity_Charge 1 11264
Protoss_Observatory 1 12092
Protoss_Observer 3 15125
15278
