Protoss_Gateway 4 15049
Protoss_Assimilator 2 13805
Protoss_Zealot 2 6052
Protoss_Cybernetics_Core 1 6782
Protoss_Dragoon 7 15671
Protoss_Nexus 1 11976
Protoss_Robotics_Facility 1 11556
Singularity_Charge 1 10638
Protoss_Citadel_of_Adun 1 12271
Protoss_Observatory 1 12298
Protoss_Observer 2 14961
Protoss_Templar_Archives 1 14642
15671
