Protoss_Gateway 6 15895
Protoss_Assimilator 1 4249
Protoss_Cybernetics_Core 1 5870
Protoss_Dragoon 9 15721
Protoss_Nexus 2 12532
Singularity_Charge 1 9751
Protoss_Robotics_Facility 1 12670
Protoss_Observatory 1 13572
Protoss_Observer 1 14642
Protoss_Citadel_of_Adun 1 15636
15895
