Protoss_Gateway 2 10293
Protoss_Assimilator 1 4510
Protoss_Cybernetics_Core 1 5914
Protoss_Dragoon 12 15183
Protoss_Robotics_Facility 1 9774
Singularity_Charge 1 9833
Protoss_Observatory 1 10614
Protoss_Observer 1 11800
Protoss_Nexus 1 16162
16162
