Protoss_Gateway 4 15160
Protoss_Assimilator 1 4281
Protoss_Cybernetics_Core 1 5544
Protoss_Nexus 2 15210
Protoss_Dragoon 8 12724
Singularity_Charge 1 9206
Protoss_Robotics_Facility 1 11809
Protoss_Observatory 1 12805
Protoss_Observer 2 14730
Protoss_Citadel_of_Adun 1 15975
15975
