Protoss_Gateway 2 15330
Protoss_Assimilator 1 4572
Protoss_Cybernetics_Core 1 6009
Protoss_Dragoon 2 14831
Protoss_Robotics_Facility 1 8539
Protoss_Shuttle 1 10335
Protoss_Robotics_Support_Bay 1 9727
Protoss_Zealot 2 11834
Protoss_Reaver 2 14064
Protoss_Observatory 1 11894
Protoss_Nexus 1 14898
Gravitic_Drive 1 13977
15330
