Protoss_Gateway 3 14120
Protoss_Assimilator 1 4508
Protoss_Cybernetics_Core 1 5813
Protoss_Dragoon 8 14736
Protoss_Robotics_Facility 1 11107
Protoss_Zealot 4 13526
Protoss_Shuttle 1 12648
Singularity_Charge 1 11240
Protoss_Observatory 1 12401
Protoss_Observer 3 15252
15252
