Protoss_Gateway 3 14791
Protoss_Assimilator 1 4117
Protoss_Zealot 2 6484
Protoss_Cybernetics_Core 1 6994
Protoss_Dragoon 9 13728
Protoss_Robotics_Facility 1 11662
Singularity_Charge 1 10866
Protoss_Observatory 1 12374
Protoss_Observer 2 14613
Protoss_Nexus 1 15777
15777
