Protoss_Gateway 4 15579
Protoss_Assimilator 1 4236
Protoss_Cybernetics_Core 1 5636
Protoss_Dragoon 12 14258
Singularity_Charge 1 9768
Protoss_Nexus 1 13808
Protoss_Robotics_Facility 1 13145
Protoss_Observatory 1 13924
Protoss_Observer 1 14941
15579
