Protoss_Gateway 3 11004
Protoss_Assimilator 2 12955
Protoss_Cybernetics_Core 1 5765
Protoss_Dragoon 9 15004
Protoss_Nexus 1 11190
Protoss_Robotics_Facility 1 10672
Singularity_Charge 1 9692
Protoss_Observatory 1 11722
Protoss_Observer 3 15386
Protoss_Citadel_of_Adun 1 13751
Protoss_Templar_Archives 1 15340
Protoss_Stargate 1 15761
15761
