Protoss_Gateway 4 15617
Protoss_Assimilator 1 4309
Protoss_Cybernetics_Core 1 5689
Protoss_Dragoon 9 13298
Protoss_Nexus 1 11897
Singularity_Charge 1 9653
Protoss_Robotics_Facility 1 12368
Protoss_Shuttle 1 13796
Protoss_Zealot 2 14650
Protoss_Observatory 1 14267
Protoss_Citadel_of_Adun 1 15899
15899
