Protoss_Gateway 2 6506
Protoss_Assimilator 2 5351
Protoss_Zealot 10 11146
Protoss_Cybernetics_Core 1 11992
Protoss_Robotics_Facility 1 14113
Protoss_Dragoon 4 14956
Protoss_Shuttle 1 15538
15538
