Protoss_Assimilator 3 6020
Protoss_Gateway 2 9987
Protoss_Zealot 1 6068
Protoss_Cybernetics_Core 1 7839
Protoss_Dragoon 10 15527
Protoss_Robotics_Facility 1 12563
Singularity_Charge 1 11570
Protoss_Shuttle 1 14184
Protoss_Robotics_Support_Bay 1 13874
Protoss_Reaver 1 15742
15742
