Protoss_Gateway 3 10287
Protoss_Assimilator 1 4611
Protoss_Cybernetics_Core 1 5947
Protoss_Dragoon 6 14925
Protoss_Citadel_of_Adun 1 9189
Protoss_Templar_Archives 1 10632
Singularity_Charge 1 9607
Protoss_Dark_Templar 5 13649
Protoss_Nexus 1 14738
14925
