Protoss_Gateway 3 12983
Protoss_Assimilator 1 4286
Protoss_Cybernetics_Core 1 6042
Protoss_Robotics_Facility 1 7975
Protoss_Dragoon 8 14252
Protoss_Shuttle 1 9413
Protoss_Observatory 1 9181
Protoss_Observer 4 13104
Singularity_Charge 1 10816
Protoss_Zealot 3 15113
15113
