Protoss_Gateway 2 9702
Protoss_Assimilator 2 14748
Protoss_Cybernetics_Core 1 5868
Protoss_Dragoon 10 15104
Protoss_Nexus 1 12502
Singularity_Charge 1 9856
Protoss_Robotics_Facility 1 13134
Protoss_Zealot 2 13843
Protoss_Observatory 1 13889
Protoss_Shuttle 1 14868
Protoss_Observer 1 15034
15104
