Protoss_Gateway 2 12454
Protoss_Assimilator 1 4332
Protoss_Cybernetics_Core 1 5780
Protoss_Dragoon 6 15351
Protoss_Robotics_Facility 1 8568
Protoss_Shuttle 1 9977
Protoss_Observatory 1 9415
Protoss_Robotics_Support_Bay 1 9773
Protoss_Observer 1 10820
Protoss_Reaver 2 14195
Singularity_Charge 1 13970
15351
