Protoss_Gateway 2 9993
Protoss_Assimilator 1 4467
Protoss_Cybernetics_Core 1 6058
Protoss_Robotics_Facility 1 8053
Protoss_Zealot 3 13700
Protoss_Observatory 1 8760
Protoss_Dragoon 8 15300
Protoss_Observer 4 12895
Singularity_Charge 1 11226
Protoss_Shuttle 1 14253
Protoss_Nexus 1 16787
16787
