Protoss_Gateway 3 13072
Protoss_Assimilator 1 4739
Protoss_Cybernetics_Core 1 6213
Protoss_Dragoon 11 15556
Protoss_Nexus 1 12359
Singularity_Charge 1 10333
Protoss_Robotics_Facility 1 15434
15556
