Protoss_Gateway 2 9290
Protoss_Assimilator 1 4429
Protoss_Cybernetics_Core 1 5815
Protoss_Dragoon 11 15411
Protoss_Nexus 1 10334
Singularity_Charge 1 9806
Protoss_Robotics_Facility 1 11814
Protoss_Observatory 1 12534
Protoss_Observer 1 13545
15411
