Protoss_Gateway 3 14772
Protoss_Assimilator 1 4461
Protoss_Cybernetics_Core 1 5765
Protoss_Dragoon 10 13927
Singularity_Charge 1 9887
Protoss_Nexus 1 14086
Protoss_Robotics_Facility 1 14566
Protoss_Zealot 4 15130
Protoss_Observatory 1 15285
15285
