Protoss_Gateway 3 11961
Protoss_Assimilator 1 4710
Protoss_Cybernetics_Core 1 6023
Protoss_Dragoon 11 15380
Protoss_Robotics_Facility 1 10245
Singularity_Charge 1 10465
Protoss_Observatory 1 11719
Protoss_Observer 2 13959
Protoss_Nexus 1 16524
16524
