Protoss_Gateway 3 15854
Protoss_Assimilator 2 4791
Protoss_Cybernetics_Core 1 6318
Protoss_Dragoon 9 15110
Protoss_Robotics_Facility 1 10858
Singularity_Charge 1 10370
Protoss_Observatory 1 11990
Protoss_Observer 3 15544
Protoss_Nexus 1 15593
15854
