Protoss_Gateway 1 4733
Protoss_Assimilator 1 4662
Protoss_Cybernetics_Core 1 6324
Protoss_Dragoon 5 15753
Protoss_Robotics_Facility 1 10456
Singularity_Charge 1 10128
Protoss_Shuttle 1 11967
Protoss_Zealot 1 11774
Protoss_Robotics_Support_Bay 1 11555
Protoss_Reaver 1 13525
Protoss_Nexus 2 16863
Protoss_Observatory 1 15010
16863
