Protoss_Gateway 3 10946
Protoss_Assimilator 1 4785
Protoss_Cybernetics_Core 1 6652
Protoss_Dragoon 10 13997
Singularity_Charge 1 11116
Protoss_Citadel_of_Adun 1 13040
Protoss_Templar_Archives 1 14531
Protoss_Zealot 3 15036
15036
