Protoss_Gateway 2 6507
Protoss_Assimilator 2 15434
Protoss_Cybernetics_Core 1 5857
Protoss_Dragoon 12 15095
Protoss_Nexus 1 12878
Protoss_Robotics_Facility 1 12617
Singularity_Charge 1 11892
Protoss_Observatory 1 13339
Protoss_Observer 2 15422
15434
