Protoss_Gateway 3 15683
Protoss_Assimilator 1 4226
Protoss_Cybernetics_Core 1 5941
Protoss_Dragoon 10 15768
Protoss_Robotics_Facility 1 11395
Singularity_Charge 1 10099
Protoss_Nexus 2 16695
Protoss_Observatory 1 12102
Protoss_Observer 2 14519
16695
