Protoss_Gateway 3 16002
Protoss_Assimilator 1 4504
Protoss_Zealot 2 13027
Protoss_Cybernetics_Core 1 7583
Protoss_Dragoon 4 12104
Protoss_Stargate 1 10521
Protoss_Citadel_of_Adun 1 11314
Protoss_Scout 1 12436
Protoss_Templar_Archives 1 13037
Protoss_Dark_Templar 3 15395
Protoss_Nexus 1 16844
16844
