Protoss_Gateway 2 10104
Protoss_Assimilator 2 5063
Protoss_Cybernetics_Core 1 6352
Protoss_Citadel_of_Adun 1 7946
Protoss_Dragoon 2 15666
Protoss_Templar_Archives 1 9538
Protoss_Dark_Templar 5 15080
Protoss_Robotics_Facility 1 12036
Protoss_Zealot 1 11168
Protoss_Nexus 1 16193
Protoss_Shuttle 1 15011
16193
