Protoss_Gateway 2 9605
Protoss_Assimilator 1 4663
Protoss_Cybernetics_Core 1 6169
Protoss_Dragoon 10 15710
Protoss_Citadel_of_Adun 1 8649
Protoss_Nexus 1 12615
Singularity_Charge 1 12170
Protoss_Robotics_Facility 1 15946
15946
