Protoss_Gateway 3 14260
Protoss_Assimilator 1 4454
Protoss_Cybernetics_Core 1 6031
Protoss_Dragoon 11 14956
Singularity_Charge 1 9923
Protoss_Nexus 1 14049
Protoss_Robotics_Facility 1 13463
Protoss_Observatory 1 14614
14956
