Protoss_Gateway 2 8472
Protoss_Assimilator 3 6825
Protoss_Cybernetics_Core 1 6163
Protoss_Dragoon 8 12543
Protoss_Citadel_of_Adun 1 11727
Singularity_Charge 1 10339
Protoss_Templar_Archives 1 13223
Protoss_Dark_Templar 2 14659
Protoss_Nexus 1 16186
Protoss_Robotics_Facility 1 16102
16186
