Protoss_Gateway 5 16031
Protoss_Assimilator 1 4482
Protoss_Cybernetics_Core 1 5919
Protoss_Dragoon 8 15183
Protoss_Nexus 1 13574
Protoss_Robotics_Facility 1 13371
Singularity_Charge 1 11687
Protoss_Observatory 1 14237
Protoss_Observer 1 15288
16031
