Protoss_Gateway 3 13684
Protoss_Assimilator 2 14666
Protoss_Cybernetics_Core 1 6375
Protoss_Dragoon 8 15647
Protoss_Citadel_of_Adun 1 10580
Singularity_Charge 1 10245
Protoss_Templar_Archives 1 12036
Protoss_Nexus 1 14005
Protoss_Dark_Templar 2 13266
Protoss_Stargate 1 15574
Protoss_Zealot 1 15393
15647
