Protoss_Gateway 2 10477
Protoss_Assimilator 1 4665
Protoss_Cybernetics_Core 1 5958
Protoss_Dragoon 7 15292
Protoss_Robotics_Facility 1 10040
Protoss_Shuttle 1 11455
Singularity_Charge 1 10275
Protoss_Robotics_Support_Bay 1 11679
Protoss_Reaver 1 13420
Protoss_Zealot 2 13671
Protoss_Observatory 1 13374
Protoss_Observer 1 14453
15292
