Protoss_Gateway 2 10141
Protoss_Assimilator 1 4344
Protoss_Cybernetics_Core 1 6065
Protoss_Dragoon 7 13880
Protoss_Robotics_Facility 1 8861
Protoss_Observatory 1 10099
Protoss_Observer 2 15383
Singularity_Charge 1 11701
Protoss_Nexus 1 14869
15383
