Protoss_Gateway 3 12255
Protoss_Assimilator 1 4300
Protoss_Cybernetics_Core 1 5955
Protoss_Dragoon 12 15515
Protoss_Nexus 2 17036
Singularity_Charge 1 10077
Protoss_Robotics_Facility 1 16453
17036
