Protoss_Gateway 2 15943
Protoss_Assimilator 2 15007
Protoss_Cybernetics_Core 1 5568
Protoss_Dragoon 5 11419
Protoss_Nexus 1 11899
Singularity_Charge 1 9236
Protoss_Stargate 2 13159
Protoss_Zealot 2 13278
Protoss_Fleet_Beacon 1 14263
Protoss_Carrier 2 17771
17771
