Protoss_Gateway 2 6702
Protoss_Assimilator 1 4608
Protoss_Cybernetics_Core 1 6144
Protoss_Dragoon 10 13034
Protoss_Robotics_Facility 1 11817
Singularity_Charge 1 10070
Protoss_Observatory 1 12718
Protoss_Shuttle 1 13848
Protoss_Zealot 4 15459
Protoss_Robotics_Support_Bay 1 14278
Protoss_Observer 1 14691
15459
