Protoss_Gateway 3 12375
Protoss_Assimilator 1 4346
Protoss_Cybernetics_Core 1 5831
Protoss_Dragoon 11 14044
Protoss_Robotics_Facility 1 9998
Protoss_Observatory 1 10779
Singularity_Charge 1 10092
Protoss_Observer 1 11885
Protoss_Shuttle 1 15209
Protoss_Zealot 3 15039
15209
