Protoss_Gateway 2 11019
Protoss_Assimilator 1 4549
Protoss_Cybernetics_Core 1 5941
Protoss_Dragoon 10 15146
Protoss_Robotics_Facility 1 10568
Protoss_Observatory 1 11391
Singularity_Charge 1 11775
Protoss_Nexus 1 14861
Protoss_Observer 2 15283
15283
