Protoss_Gateway 3 12798
Protoss_Assimilator 1 4878
Protoss_Cybernetics_Core 1 6257
Protoss_Dragoon 9 15292
Protoss_Nexus 1 12139
Singularity_Charge 1 10633
Protoss_Robotics_Facility 1 14420
Protoss_Observatory 1 15260
15292
