Protoss_Gateway 2 10060
Protoss_Assimilator 1 4325
Protoss_Cybernetics_Core 1 5951
Protoss_Dragoon 9 13781
Protoss_Robotics_Facility 1 8501
Protoss_Observatory 1 9890
Protoss_Observer 1 10919
Singularity_Charge 1 11658
Protoss_Nexus 1 16320
Protoss_Stargate 2 15457
16320
