Protoss_Gateway 4 15833
Protoss_Assimilator 1 4559
Protoss_Cybernetics_Core 1 5827
Protoss_Dragoon 9 13712
Singularity_Charge 1 9660
Protoss_Nexus 2 16285
Protoss_Robotics_Facility 1 13498
Protoss_Observatory 1 14308
Protoss_Observer 1 15551
16285
