Protoss_Gateway 2 10264
Protoss_Assimilator 1 4829
Protoss_Cybernetics_Core 1 6192
Protoss_Robotics_Facility 1 8277
Protoss_Dragoon 6 14653
Protoss_Observatory 1 8975
Protoss_Observer 1 10205
Protoss_Shuttle 2 13190
Singularity_Charge 1 12429
Protoss_Nexus 1 17108
17108
