Protoss_Gateway 2 10028
Protoss_Assimilator 1 4278
Protoss_Cybernetics_Core 1 5786
Protoss_Dragoon 7 13353
Protoss_Robotics_Facility 1 9339
Protoss_Observatory 1 10045
Singularity_Charge 1 9997
Protoss_Observer 2 13173
Protoss_Nexus 1 14253
Protoss_Zealot 4 15096
Protoss_Shuttle 1 15026
15096
