Protoss_Gateway 4 15915
Protoss_Assimilator 1 4330
Protoss_Cybernetics_Core 1 5742
Protoss_Dragoon 12 15515
Protoss_Nexus 1 11943
Singularity_Charge 1 9792
Protoss_Zealot 1 11563
Protoss_Robotics_Facility 1 14632
15915
