Protoss_Gateway 1 4325
Protoss_Assimilator 1 4627
Protoss_Cybernetics_Core 1 6175
Protoss_Robotics_Facility 1 8344
Protoss_Zealot 1 7575
Protoss_Dragoon 6 15818
Protoss_Robotics_Support_Bay 1 9067
Protoss_Reaver 1 10983
Protoss_Shuttle 2 16043
Protoss_Observatory 1 12663
Protoss_Nexus 1 17005
17005
