Protoss_Gateway 2 9141
Protoss_Assimilator 1 4548
Protoss_Cybernetics_Core 1 5699
Protoss_Dragoon 8 14180
Protoss_Nexus 1 11937
Protoss_Zealot 5 15042
Singularity_Charge 1 9894
Protoss_Robotics_Facility 1 12212
Protoss_Observatory 1 13254
15042
