Protoss_Nexus 1 7361
Protoss_Gateway 3 10748
Protoss_Assimilator 1 6937
Protoss_Cybernetics_Core 1 8275
Protoss_Zealot 6 14607
Protoss_Dragoon 7 14868
Singularity_Charge 1 12119
Protoss_Robotics_Facility 1 14085
Protoss_Observatory 1 15192
15192
