Protoss_Gateway 3 13770
Protoss_Assimilator 1 4653
Protoss_Cybernetics_Core 1 6160
Protoss_Dragoon 9 15587
Protoss_Robotics_Facility 1 8890
Protoss_Observatory 1 9677
Protoss_Observer 2 11692
Singularity_Charge 1 11876
Protoss_Shuttle 1 14753
15587
