Protoss_Nexus 1 7054
Protoss_Gateway 4 15526
Protoss_Assimilator 2 12510
Protoss_Cybernetics_Core 1 7682
Protoss_Dragoon 14 15797
Singularity_Charge 1 11782
Protoss_Robotics_Facility 1 15743
15797
