Protoss_Gateway 4 15807
Protoss_Assimilator 1 4719
Protoss_Cybernetics_Core 1 6350
Protoss_Dragoon 8 14173
Protoss_Zealot 2 10985
Singularity_Charge 1 10216
Protoss_Nexus 1 14935
Protoss_Citadel_of_Adun 1 13915
Protoss_Robotics_Facility 1 15461
15807
