Protoss_Gateway 3 13991
Protoss_Assimilator 1 4363
Protoss_Cybernetics_Core 1 6039
Protoss_Robotics_Facility 1 8062
Protoss_Dragoon 9 15569
Protoss_Observatory 1 8782
Protoss_Observer 3 14089
Protoss_Shuttle 1 11232
Singularity_Charge 1 11039
Protoss_Nexus 1 14496
Protoss_Robotics_Support_Bay 1 14757
15569
