Protoss_Gateway 2 7957
Protoss_Assimilator 1 4549
Protoss_Zealot 2 6851
Protoss_Cybernetics_Core 1 7031
Protoss_Dragoon 11 14618
Protoss_Robotics_Facility 1 12134
Singularity_Charge 1 11884
Protoss_Observatory 1 13124
Protoss_Observer 2 15093
Protoss_Nexus 1 17291
17291
