Protoss_Gateway 2 8326
Protoss_Assimilator 1 4294
Protoss_Cybernetics_Core 1 5736
Protoss_Dragoon 12 15101
Singularity_Charge 1 9477
Protoss_Nexus 1 14013
Protoss_Robotics_Facility 1 15259
15259
