Protoss_Gateway 3 15364
Protoss_Assimilator 1 4578
Protoss_Cybernetics_Core 1 5996
Protoss_Dragoon 10 15256
Singularity_Charge 1 10136
Protoss_Robotics_Facility 1 12184
Protoss_Observatory 1 13175
Protoss_Nexus 1 15491
Protoss_Observer 2 15171
15491
