Protoss_Gateway 3 15892
Protoss_Assimilator 1 4536
Protoss_Cybernetics_Core 1 5829
Protoss_Dragoon 13 14431
Singularity_Charge 1 10033
Protoss_Citadel_of_Adun 1 14901
Protoss_Nexus 1 16574
16574
