Protoss_Gateway 2 9609
Protoss_Assimilator 1 4717
Protoss_Cybernetics_Core 1 6055
Protoss_Dragoon 7 15366
Singularity_Charge 1 10297
Protoss_Citadel_of_Adun 1 11828
Protoss_Templar_Archives 1 13441
Protoss_Stargate 1 13825
Protoss_Nexus 1 15516
Protoss_Arbiter_Tribunal 1 15485
15516
