Protoss_Gateway 4 15819
Protoss_Assimilator 1 4757
Protoss_Cybernetics_Core 1 5791
Protoss_Dragoon 11 14611
Protoss_Nexus 1 10142
Protoss_Robotics_Facility 1 14446
Singularity_Charge 1 12784
Protoss_Observatory 1 15271
Protoss_Zealot 1 15580
15819
