Protoss_Gateway 4 15350
Protoss_Assimilator 2 14584
Protoss_Cybernetics_Core 1 5794
Protoss_Dragoon 5 15478
Protoss_Zealot 1 7856
Protoss_Citadel_of_Adun 1 8622
Protoss_Templar_Archives 1 10455
Protoss_Dark_Templar 5 14378
Protoss_Nexus 1 13720
15478
