Protoss_Gateway 2 12201
Protoss_Assimilator 1 4218
Protoss_Cybernetics_Core 1 5655
Protoss_Dragoon 7 15249
Protoss_Robotics_Facility 1 8606
Protoss_Zealot 2 10283
Protoss_Shuttle 1 10189
Protoss_Robotics_Support_Bay 1 9655
Protoss_Reaver 2 14393
Protoss_Observatory 1 12309
Protoss_Observer 2 14980
Singularity_Charge 1 13180
15249
