Protoss_Gateway 2 8011
Protoss_Assimilator 1 4644
Protoss_Cybernetics_Core 1 5945
Protoss_Dragoon 8 12768
Protoss_Citadel_of_Adun 2 11594
Singularity_Charge 1 10575
Protoss_Templar_Archives 1 13104
Protoss_Nexus 1 15546
Protoss_Dark_Templar 2 14429
Protoss_Zealot 2 15434
15546
