Protoss_Gateway 3 15389
Protoss_Assimilator 1 4666
Protoss_Zealot 1 5878
Protoss_Cybernetics_Core 1 6475
Protoss_Dragoon 6 14883
Protoss_Robotics_Facility 1 10568
Singularity_Charge 1 10458
Protoss_Shuttle 1 12143
Protoss_Robotics_Support_Bay 1 12467
Protoss_Nexus 1 16178
Protoss_Reaver 1 15344
Protoss_Observatory 1 14886
16178
