Protoss_Gateway 2 10144
Protoss_Assimilator 1 4469
Protoss_Zealot 2 6042
Protoss_Cybernetics_Core 1 6080
Protoss_Dragoon 11 14963
Singularity_Charge 1 10640
Protoss_Robotics_Facility 1 14790
14963
