Protoss_Gateway 2 13561
Protoss_Assimilator 1 4574
Protoss_Cybernetics_Core 1 5919
Protoss_Dragoon 4 13024
Protoss_Robotics_Facility 1 8422
Protoss_Zealot 2 11900
Protoss_Shuttle 1 9940
Protoss_Observatory 1 9399
Protoss_Robotics_Support_Bay 1 10201
Protoss_Observer 2 13205
Protoss_Reaver 1 12381
Protoss_Nexus 1 16500
16500
