Protoss_Gateway 3 12974
Protoss_Assimilator 1 4807
Protoss_Cybernetics_Core 1 6488
Protoss_Dragoon 10 15205
Protoss_Nexus 1 11917
Protoss_Robotics_Facility 1 11575
Singularity_Charge 1 10187
Protoss_Observatory 1 12456
Protoss_Observer 2 14505
Protoss_Citadel_of_Adun 1 14816
15205
