Protoss_Gateway 2 9845
Protoss_Assimilator 1 4729
Protoss_Cybernetics_Core 1 5982
Protoss_Zealot 1 5995
Protoss_Dragoon 11 14692
Singularity_Charge 1 10736
Protoss_Robotics_Facility 1 13456
Protoss_Observatory 1 14167
Protoss_Observer 1 15192
15192
