Protoss_Gateway 3 13258
Protoss_Assimilator 1 4352
Protoss_Cybernetics_Core 1 5809
Protoss_Dragoon 7 15183
Protoss_Citadel_of_Adun 1 9409
Protoss_Templar_Archives 1 10969
Protoss_Zealot 1 10773
Singularity_Charge 1 10172
Protoss_Dark_Templar 3 13595
Protoss_Robotics_Facility 1 13536
Protoss_Shuttle 1 15589
15589
