Protoss_Gateway 2 7179
Protoss_Assimilator 1 4237
Protoss_Cybernetics_Core 1 5784
Protoss_Dragoon 7 11707
Protoss_Citadel_of_Adun 1 9573
Protoss_Templar_Archives 1 11333
Singularity_Charge 1 10531
Protoss_Dark_Templar 4 14903
Protoss_Zealot 1 13783
Protoss_Nexus 1 16815
Protoss_Robotics_Facility 1 16419
16815
