Protoss_Gateway 5 15307
Protoss_Assimilator 1 4638
Protoss_Cybernetics_Core 1 5913
Protoss_Dragoon 9 15512
Protoss_Nexus 1 12158
Protoss_Zealot 2 15361
Protoss_Robotics_Facility 1 12900
Singularity_Charge 1 11094
Protoss_Observatory 1 13648
Protoss_Citadel_of_Adun 1 15093
Protoss_Observer 1 15207
15512
