Protoss_Gateway 2 11752
Protoss_Assimilator 1 4653
Protoss_Cybernetics_Core 1 6181
Protoss_Robotics_Facility 1 8287
Protoss_Dragoon 7 14150
Protoss_Shuttle 1 9690
Protoss_Observatory 1 9272
Protoss_Observer 3 13103
Singularity_Charge 1 12446
14150
