Protoss_Gateway 2 8033
Protoss_Assimilator 1 4249
Protoss_Cybernetics_Core 1 5714
Protoss_Dragoon 11 15759
Protoss_Robotics_Facility 1 11400
Singularity_Charge 1 9689
Protoss_Shuttle 1 13079
Protoss_Nexus 1 14902
Protoss_Robotics_Support_Bay 1 12947
Protoss_Reaver 1 14686
Protoss_Observatory 1 14618
15759
