Protoss_Gateway 2 6520
Protoss_Assimilator 1 4533
Protoss_Cybernetics_Core 1 5743
Protoss_Dragoon 7 11239
Protoss_Zealot 3 12229
Protoss_Citadel_of_Adun 1 10580
Protoss_Templar_Archives 1 12146
Singularity_Charge 1 10787
Protoss_Dark_Templar 2 13485
Protoss_Nexus 1 16171
16171
