Protoss_Gateway 3 14339
Protoss_Assimilator 1 4688
Protoss_Cybernetics_Core 1 5970
Protoss_Dragoon 10 15749
Protoss_Nexus 1 12505
Singularity_Charge 1 10253
Protoss_Shield_Battery 1 11625
Protoss_Robotics_Facility 1 13624
Protoss_Observatory 1 14480
Protoss_Observer 1 15551
15749
