Protoss_Gateway 3 14797
Protoss_Assimilator 1 4728
Protoss_Cybernetics_Core 1 6230
Protoss_Dragoon 11 15790
Protoss_Robotics_Facility 1 9052
Protoss_Observatory 1 10150
Protoss_Observer 2 13063
Protoss_Nexus 1 14796
Singularity_Charge 1 12089
15790
