Protoss_Gateway 2 10499
Protoss_Assimilator 1 4447
Protoss_Zealot 2 6064
Protoss_Cybernetics_Core 1 6004
Protoss_Dragoon 9 15497
Protoss_Citadel_of_Adun 2 10915
Singularity_Charge 1 10143
Protoss_Templar_Archives 1 12424
Protoss_Dark_Templar 2 13661
Protoss_Nexus 1 16197
16197
