Protoss_Gateway 4 15131
Protoss_Assimilator 1 4186
Protoss_Shield_Battery 1 4992
Protoss_Cybernetics_Core 1 5831
Protoss_Dragoon 10 14480
Protoss_Robotics_Facility 1 9652
Singularity_Charge 1 9616
Protoss_Observatory 1 10514
Protoss_Observer 2 12503
Protoss_Nexus 1 14291
Protoss_Zealot 2 15566
15566
