Protoss_Gateway 4 15888
Protoss_Assimilator 1 4347
Protoss_Cybernetics_Core 1 6194
Protoss_Dragoon 10 15148
Singularity_Charge 1 9877
Protoss_Nexus 1 13161
Protoss_Robotics_Facility 1 13362
Protoss_Observatory 1 14261
Protoss_Observer 1 15392
15888
