Protoss_Gateway 2 12732
Protoss_Assimilator 2 4868
Protoss_Cybernetics_Core 1 6241
Protoss_Dragoon 5 15446
Protoss_Robotics_Facility 1 8861
Protoss_Shuttle 1 10350
Protoss_Robotics_Support_Bay 1 9972
Protoss_Reaver 1 11908
Protoss_Observatory 1 11940
Singularity_Charge 1 11665
Protoss_Nexus 1 15864
Protoss_Observer 1 14190
Protoss_Forge 1 14528
15864
