Protoss_Gateway 2 9570
Protoss_Assimilator 1 4501
Protoss_Cybernetics_Core 1 5942
Protoss_Dragoon 8 15102
Protoss_Citadel_of_Adun 1 9121
Protoss_Templar_Archives 1 10726
Protoss_Zealot 1 10788
Singularity_Charge 1 9953
Protoss_Dark_Templar 2 12036
Protoss_Nexus 1 14700
Protoss_Robotics_Facility 1 15320
15320
