Protoss_Assimilator 1 3977
Protoss_Gateway 2 10278
Protoss_Cybernetics_Core 1 6762
Protoss_Dragoon 4 11354
Protoss_Robotics_Facility 1 9496
Protoss_Observatory 1 10394
Protoss_Zealot 1 11455
Protoss_Observer 3 15488
Protoss_Citadel_of_Adun 1 12093
Protoss_Shuttle 1 12950
Protoss_Templar_Archives 1 13602
Protoss_Forge 1 13416
Singularity_Charge 1 12950
Protoss_Dark_Templar 2 14864
Protoss_Nexus 1 17174
17174
