Protoss_Gateway 4 14860
Protoss_Assimilator 1 4483
Protoss_Cybernetics_Core 1 5875
Protoss_Dragoon 10 14079
Singularity_Charge 1 10023
Protoss_Nexus 1 13540
Protoss_Robotics_Facility 1 13731
Protoss_Observatory 1 14611
14860
