Protoss_Gateway 2 9677
Protoss_Assimilator 1 4631
Protoss_Cybernetics_Core 1 6151
Protoss_Dragoon 8 15402
Protoss_Robotics_Facility 1 9205
Protoss_Observatory 1 9929
Protoss_Observer 2 11837
Singularity_Charge 1 12353
Protoss_Nexus 1 15672
Protoss_Citadel_of_Adun 1 15823
15823
