Protoss_Gateway 2 15484
Protoss_Assimilator 1 4542
Protoss_Cybernetics_Core 1 6034
Protoss_Zealot 2 10744
Protoss_Dragoon 6 14959
Protoss_Robotics_Facility 1 8723
Protoss_Shuttle 1 10321
Protoss_Robotics_Support_Bay 1 9901
Protoss_Reaver 1 11879
Protoss_Observatory 1 11564
Protoss_Observer 2 15112
Protoss_Nexus 1 15988
Singularity_Charge 1 14182
15988
