Protoss_Gateway 4 15778
Protoss_Assimilator 1 4574
Protoss_Cybernetics_Core 1 6245
Protoss_Dragoon 8 15104
Protoss_Robotics_Facility 1 8665
Protoss_Observatory 1 10248
Protoss_Nexus 2 15473
Protoss_Observer 2 12371
Singularity_Charge 1 11817
15778
