Protoss_Gateway 2 9958
Protoss_Assimilator 1 4463
Protoss_Zealot 1 5190
Protoss_Cybernetics_Core 1 6907
Protoss_Citadel_of_Adun 1 8431
Protoss_Dragoon 6 14736
Protoss_Templar_Archives 1 9899
Protoss_Dark_Templar 2 11166
Protoss_Nexus 1 14324
Protoss_Robotics_Facility 1 13608
Protoss_Shuttle 1 15128
Protoss_Robotics_Support_Bay 1 15294
15294
