Protoss_Gateway 2 5238
Protoss_Zealot 6 12090
Protoss_Assimilator 1 6351
Protoss_Cybernetics_Core 1 7597
Protoss_Dragoon 5 12336
Protoss_Citadel_of_Adun 1 11336
Protoss_Templar_Archives 1 13101
Protoss_Dark_Templar 2 14319
Protoss_Robotics_Facility 1 16210
16210
