Protoss_Gateway 2 6409
Protoss_Assimilator 1 4412
Protoss_Cybernetics_Core 1 5707
Protoss_Dragoon 8 14897
Protoss_Zealot 2 14424
Protoss_Robotics_Facility 1 11048
Singularity_Charge 1 9587
Protoss_Shuttle 1 12472
Protoss_Nexus 1 14810
Protoss_Robotics_Support_Bay 1 12986
Protoss_Reaver 1 14825
Protoss_Observatory 1 14314
14897
