Protoss_Gateway 3 15570
Protoss_Assimilator 1 4940
Protoss_Cybernetics_Core 1 6188
Protoss_Dragoon 7 13034
Protoss_Robotics_Facility 1 9161
Protoss_Observatory 1 10453
Protoss_Observer 2 13897
Protoss_Nexus 1 15390
Singularity_Charge 1 12645
Protoss_Citadel_of_Adun 1 14796
15570
