Protoss_Gateway 2 15457
Protoss_Assimilator 1 4703
Protoss_Cybernetics_Core 1 6115
Protoss_Dragoon 5 14934
Protoss_Robotics_Facility 1 10668
Singularity_Charge 1 10326
Protoss_Robotics_Support_Bay 1 11387
Protoss_Shuttle 1 12113
Protoss_Zealot 2 13078
Protoss_Reaver 1 13671
Protoss_Nexus 1 15820
Protoss_Observatory 1 14043
Protoss_Observer 1 15083
15820
