Protoss_Gateway 1 4477
Protoss_Assimilator 1 4783
Protoss_Cybernetics_Core 1 6931
Protoss_Zealot 1 7371
Protoss_Robotics_Facility 1 9224
Protoss_Dragoon 7 15284
Protoss_Shuttle 1 10665
Protoss_Robotics_Support_Bay 1 11087
Protoss_Reaver 2 16229
Protoss_Observatory 1 12812
Protoss_Observer 1 14066
Singularity_Charge 1 13516
16229
