Protoss_Gateway 2 6921
Protoss_Assimilator 1 4480
Protoss_Cybernetics_Core 1 6014
Protoss_Dragoon 13 15775
Protoss_Zealot 2 9536
Singularity_Charge 1 9997
Protoss_Nexus 1 15798
15798
