Protoss_Gateway 2 7229
Protoss_Assimilator 2 14581
Protoss_Cybernetics_Core 1 5768
Protoss_Dragoon 13 15278
Protoss_Nexus 1 12748
Singularity_Charge 1 11197
Protoss_Robotics_Facility 1 15487
15487
