Protoss_Gateway 1 4287
Protoss_Assimilator 1 4564
Protoss_Cybernetics_Core 1 5906
Protoss_Zealot 1 5724
Protoss_Dragoon 6 13324
Protoss_Robotics_Facility 1 10902
Singularity_Charge 1 10267
Protoss_Shuttle 1 12699
Protoss_Robotics_Support_Bay 1 11988
Protoss_Reaver 2 15796
15796
