Protoss_Gateway 3 14194
Protoss_Assimilator 1 4676
Protoss_Cybernetics_Core 1 5988
Protoss_Dragoon 12 15483
Protoss_Nexus 1 13392
Protoss_Robotics_Facility 1 12845
Singularity_Charge 1 12572
Protoss_Observatory 1 13570
Protoss_Observer 1 14878
15483
