Protoss_Gateway 4 15052
Protoss_Assimilator 1 4722
Protoss_Cybernetics_Core 1 6236
Protoss_Dragoon 10 15314
Protoss_Robotics_Facility 1 10533
Singularity_Charge 1 9967
Protoss_Shuttle 1 11945
Protoss_Robotics_Support_Bay 1 11275
Protoss_Observatory 1 11365
Protoss_Reaver 1 13654
Protoss_Observer 2 15522
15522
