Protoss_Nexus 2 16394
Protoss_Gateway 3 14740
Protoss_Assimilator 1 6368
Protoss_Cybernetics_Core 1 7916
Protoss_Zealot 3 14607
Protoss_Dragoon 5 12307
Protoss_Forge 1 10432
Protoss_Photon_Cannon 3 15813
Singularity_Charge 1 11731
Protoss_Robotics_Facility 1 14745
16394
