Protoss_Gateway 4 14832
Protoss_Assimilator 1 4589
Protoss_Cybernetics_Core 1 5906
Protoss_Dragoon 8 13933
Protoss_Robotics_Facility 1 10198
Singularity_Charge 1 10079
Protoss_Observatory 1 11015
Protoss_Observer 3 13890
Protoss_Nexus 1 14519
Protoss_Shuttle 1 15248
15248
