Protoss_Gateway 4 15004
Protoss_Assimilator 1 4545
Protoss_Cybernetics_Core 1 6077
Protoss_Dragoon 13 15395
Protoss_Nexus 1 12125
Singularity_Charge 1 10158
Protoss_Robotics_Facility 1 12297
Protoss_Observatory 1 13150
Protoss_Observer 2 15288
15395
