Protoss_Gateway 2 9163
Protoss_Assimilator 1 4741
Protoss_Zealot 6 14837
Protoss_Cybernetics_Core 1 7912
Protoss_Dragoon 5 13975
Protoss_Robotics_Facility 1 11897
Protoss_Shuttle 1 13599
Singularity_Charge 1 12499
Protoss_Robotics_Support_Bay 1 13257
Protoss_Reaver 1 15534
15534
