Protoss_Gateway 5 14471
Protoss_Assimilator 1 4483
Protoss_Cybernetics_Core 1 5758
Protoss_Dragoon 12 15461
Singularity_Charge 1 9960
Protoss_Nexus 1 13099
Protoss_Robotics_Facility 1 13885
15461
