Protoss_Gateway 2 8777
Protoss_Assimilator 3 6428
Protoss_Zealot 2 7855
Protoss_Cybernetics_Core 1 7577
Protoss_Dragoon 11 15414
Singularity_Charge 1 11337
Protoss_Nexus 1 16241
16241
