Protoss_Gateway 2 8421
Protoss_Assimilator 1 4578
Protoss_Cybernetics_Core 1 5955
Protoss_Dragoon 7 15797
Protoss_Citadel_of_Adun 1 10521
Protoss_Robotics_Facility 1 11670
Singularity_Charge 1 10040
Protoss_Zealot 1 12068
Protoss_Templar_Archives 1 13113
Protoss_Shuttle 1 13987
Protoss_Observatory 1 13491
Protoss_Dark_Templar 2 14480
Protoss_Nexus 1 17007
Protoss_Observer 1 15266
17007
