Protoss_Gateway 1 4207
Protoss_Assimilator 1 4504
Protoss_Cybernetics_Core 1 5875
Protoss_Dragoon 6 14992
Protoss_Robotics_Facility 1 8202
Protoss_Shuttle 1 9626
Protoss_Robotics_Support_Bay 1 9282
Protoss_Reaver 2 13269
Protoss_Zealot 2 13268
Protoss_Observatory 1 12623
Protoss_Nexus 1 15922
Protoss_Observer 2 15178
Gravitic_Drive 1 14358
15922
