Protoss_Gateway 2 5218
Protoss_Zealot 6 13517
Protoss_Assimilator 1 7719
Protoss_Cybernetics_Core 1 8494
Protoss_Dragoon 8 15737
Protoss_Nexus 1 13531
Protoss_Robotics_Facility 1 14152
Protoss_Observatory 1 15159
15737
