Protoss_Gateway 5 13704
Protoss_Assimilator 1 4593
Protoss_Cybernetics_Core 1 5856
Protoss_Dragoon 10 15329
Singularity_Charge 1 10260
Protoss_Nexus 1 13544
Protoss_Robotics_Facility 1 13018
Protoss_Observatory 1 13754
Protoss_Observer 1 14914
Protoss_Citadel_of_Adun 1 15899
15899
