Protoss_Gateway 3 14275
Protoss_Assimilator 1 4488
Protoss_Cybernetics_Core 1 5945
Protoss_Dragoon 13 15534
Singularity_Charge 1 9887
Protoss_Nexus 1 14422
Protoss_Robotics_Facility 1 13882
Protoss_Observatory 1 14764
15534
