Protoss_Nexus 2 14093
Protoss_Gateway 3 14926
Protoss_Assimilator 1 5852
Protoss_Cybernetics_Core 1 7359
Protoss_Zealot 1 7810
Protoss_Dragoon 7 15095
Singularity_Charge 1 11109
Protoss_Robotics_Facility 1 14392
Protoss_Observatory 1 15140
15140
