Protoss_Gateway 2 9937
Protoss_Assimilator 1 4659
Protoss_Cybernetics_Core 1 6182
Protoss_Dragoon 7 15069
Protoss_Robotics_Facility 1 10241
Protoss_Shuttle 1 11865
Protoss_Robotics_Support_Bay 1 11903
Protoss_Zealot 2 12244
Protoss_Reaver 1 13895
Protoss_Observatory 1 14040
Singularity_Charge 1 14043
15069
