Protoss_Gateway 2 9674
Protoss_Assimilator 2 4659
Protoss_Cybernetics_Core 1 6102
Protoss_Zealot 1 6075
Protoss_Dragoon 6 12227
Protoss_Citadel_of_Adun 1 10529
Singularity_Charge 1 10238
Protoss_Templar_Archives 1 12001
Protoss_Dark_Templar 4 14788
Protoss_Nexus 1 16625
16625
