Protoss_Gateway 4 15740
Protoss_Assimilator 2 4906
Protoss_Zealot 2 7092
Protoss_Cybernetics_Core 1 7060
Protoss_Dragoon 9 15797
Singularity_Charge 1 11014
Protoss_Nexus 1 14447
Protoss_Robotics_Facility 1 15207
15797
