Protoss_Gateway 2 10047
Protoss_Zealot 3 8660
Protoss_Assimilator 1 7044
Protoss_Cybernetics_Core 1 8721
Protoss_Dragoon 7 15455
Protoss_Robotics_Facility 1 13952
Singularity_Charge 1 12944
Protoss_Nexus 1 16161
Protoss_Observatory 1 14690
16161
