Protoss_Gateway 3 13176
Protoss_Assimilator 1 4776
Protoss_Cybernetics_Core 1 6274
Protoss_Dragoon 9 14706
Protoss_Citadel_of_Adun 1 9492
Protoss_Nexus 2 17175
Protoss_Robotics_Facility 1 11941
Protoss_Observatory 1 12977
Singularity_Charge 1 12638
Protoss_Observer 1 14058
17175
