Protoss_Gateway 4 15071
Protoss_Assimilator 1 4679
Protoss_Cybernetics_Core 1 5963
Protoss_Dragoon 10 15219
Singularity_Charge 1 10026
Protoss_Nexus 1 14430
Protoss_Zealot 1 13180
Protoss_Robotics_Facility 1 14875
15219
