Protoss_Gateway 2 9729
Protoss_Assimilator 1 4373
Protoss_Cybernetics_Core 1 6188
Protoss_Dragoon 11 14779
Protoss_Citadel_of_Adun 1 8619
Protoss_Nexus 2 17373
Singularity_Charge 1 11709
17373
