Protoss_Gateway 3 14079
Protoss_Assimilator 2 14786
Protoss_Cybernetics_Core 1 5875
Protoss_Dragoon 11 14553
Protoss_Nexus 1 11386
Singularity_Charge 1 9938
Protoss_Robotics_Facility 1 12260
Protoss_Observatory 1 13166
Protoss_Observer 2 15078
15078
