Protoss_Assimilator 1 3588
Protoss_Gateway 1 4668
Protoss_Cybernetics_Core 1 6113
Protoss_Robotics_Facility 1 8133
Protoss_Dragoon 3 14436
Protoss_Shuttle 1 9529
Protoss_Robotics_Support_Bay 1 9019
Protoss_Observatory 1 9196
Protoss_Observer 3 14164
Protoss_Nexus 1 12881
Protoss_Reaver 1 13339
Gravitic_Drive 1 13983
14436
