Protoss_Gateway 3 15683
Protoss_Assimilator 1 4337
Protoss_Cybernetics_Core 1 5803
Protoss_Dragoon 4 15325
Protoss_Citadel_of_Adun 1 8399
Protoss_Templar_Archives 1 10010
Protoss_Dark_Templar 5 14207
Protoss_Nexus 1 13713
Singularity_Charge 1 10860
Protoss_Robotics_Facility 1 16071
16071
