Protoss_Gateway 3 15844
Protoss_Assimilator 1 4422
Protoss_Cybernetics_Core 1 5777
Protoss_Dragoon 8 14837
Protoss_Robotics_Facility 1 8357
Protoss_Observatory 1 9199
Protoss_Observer 3 13138
Protoss_Nexus 1 12694
Singularity_Charge 1 11422
15844
