Protoss_Gateway 3 13325
Protoss_Assimilator 1 4542
Protoss_Cybernetics_Core 1 5882
Protoss_Dragoon 13 15805
Singularity_Charge 1 9901
Protoss_Nexus 1 13233
Protoss_Robotics_Facility 1 13222
Protoss_Observatory 1 14845
15805
