Protoss_Gateway 2 9930
Protoss_Assimilator 1 4606
Protoss_Cybernetics_Core 1 5838
Protoss_Dragoon 10 15215
Protoss_Nexus 1 12700
Singularity_Charge 1 10067
Protoss_Zealot 1 11326
Protoss_Robotics_Facility 1 14187
15215
