Protoss_Gateway 2 9513
Protoss_Assimilator 1 4234
Protoss_Cybernetics_Core 1 5777
Protoss_Dragoon 8 13471
Protoss_Nexus 1 12078
Protoss_Zealot 3 14929
Singularity_Charge 1 9830
Protoss_Robotics_Facility 1 12582
Protoss_Shuttle 1 14030
Protoss_Observatory 1 13444
Protoss_Robotics_Support_Bay 1 13860
Protoss_Reaver 1 15591
15591
