Protoss_Gateway 3 15738
Protoss_Assimilator 1 4548
Protoss_Cybernetics_Core 1 5929
Protoss_Dragoon 9 14817
Singularity_Charge 1 10002
Protoss_Nexus 1 13571
Protoss_Zealot 3 15251
Protoss_Robotics_Facility 1 13904
Protoss_Observatory 1 14662
15738
