Protoss_Gateway 4 16003
Protoss_Assimilator 1 4505
Protoss_Cybernetics_Core 1 5739
Protoss_Dragoon 8 15481
Protoss_Nexus 1 12312
Singularity_Charge 1 9847
Protoss_Zealot 1 11288
Protoss_Robotics_Facility 1 12466
Protoss_Shuttle 1 13902
Protoss_Robotics_Support_Bay 1 13705
Protoss_Observatory 1 14090
Protoss_Observer 1 15125
16003
