Protoss_Gateway 3 12336
Protoss_Assimilator 1 4403
Protoss_Cybernetics_Core 1 5923
Protoss_Zealot 2 11263
Protoss_Dragoon 9 15263
Protoss_Robotics_Facility 1 9395
Protoss_Observatory 1 10149
Protoss_Observer 2 12547
Singularity_Charge 1 11658
Protoss_Nexus 1 16200
16200
