Protoss_Gateway 3 11856
Protoss_Assimilator 1 4356
Protoss_Cybernetics_Core 1 5689
Protoss_Citadel_of_Adun 1 7271
Protoss_Dragoon 1 7131
Protoss_Templar_Archives 1 8714
Protoss_Dark_Templar 11 15704
Protoss_Nexus 1 15941
Protoss_Forge 1 14644
15941
