Protoss_Gateway 3 13867
Protoss_Assimilator 1 4375
Protoss_Cybernetics_Core 1 5824
Protoss_Dragoon 12 15793
Protoss_Robotics_Facility 1 9926
Protoss_Observatory 1 10634
Singularity_Charge 1 10128
Protoss_Observer 2 12547
Protoss_Nexus 1 15578
Protoss_Zealot 1 15561
15793
