Protoss_Gateway 3 15792
Protoss_Assimilator 1 4161
Protoss_Cybernetics_Core 1 5655
Protoss_Dragoon 8 15168
Protoss_Robotics_Facility 1 10002
Singularity_Charge 1 9638
Protoss_Observatory 1 10699
Protoss_Observer 2 15141
Protoss_Nexus 1 14026
Protoss_Zealot 4 13583
Protoss_Shuttle 1 13569
15792
