Protoss_Gateway 2 13969
Protoss_Assimilator 1 4736
Protoss_Cybernetics_Core 1 6039
Protoss_Dragoon 6 15396
Protoss_Robotics_Facility 1 8988
Protoss_Zealot 2 9608
Protoss_Shuttle 2 13542
Protoss_Robotics_Support_Bay 1 10512
Protoss_Reaver 1 12240
Protoss_Observatory 1 13737
Protoss_Observer 1 14832
15396
