Protoss_Gateway 2 8041
Protoss_Assimilator 1 4695
Protoss_Cybernetics_Core 1 6036
Protoss_Zealot 3 13832
Protoss_Dragoon 6 11883
Singularity_Charge 1 9740
Protoss_Robotics_Facility 1 11733
Protoss_Robotics_Support_Bay 1 12565
Protoss_Shuttle 1 13357
Protoss_Reaver 1 14915
Protoss_Nexus 1 17055
17055
