Protoss_Gateway 4 15030
Protoss_Assimilator 1 4616
Protoss_Cybernetics_Core 1 5853
Protoss_Dragoon 11 15497
Protoss_Nexus 1 11880
Singularity_Charge 1 9931
Protoss_Robotics_Facility 1 12790
Protoss_Observatory 1 13655
Protoss_Observer 1 14783
Protoss_Citadel_of_Adun 1 15391
15497
