Protoss_Gateway 2 9554
Protoss_Assimilator 1 4572
Protoss_Zealot 1 5256
Protoss_Cybernetics_Core 1 6166
Protoss_Dragoon 11 15180
Singularity_Charge 1 10207
Protoss_Robotics_Facility 1 12389
Protoss_Observatory 1 13324
Protoss_Nexus 1 16022
Protoss_Observer 2 15254
16022
