Protoss_Gateway 4 16040
Protoss_Assimilator 1 4229
Protoss_Cybernetics_Core 1 5838
Protoss_Dragoon 10 14685
Protoss_Nexus 1 11918
Singularity_Charge 1 10019
Protoss_Robotics_Facility 1 14473
Protoss_Observatory 1 15170
16040
