Protoss_Assimilator 1 3569
Protoss_Gateway 1 4524
Protoss_Cybernetics_Core 1 5985
Protoss_Dragoon 8 15797
Protoss_Robotics_Facility 1 8624
Protoss_Shuttle 1 10116
Protoss_Robotics_Support_Bay 1 9894
Protoss_Reaver 2 13269
Singularity_Charge 1 11621
Protoss_Nexus 1 15769
Protoss_Observatory 1 15162
15797
