Protoss_Gateway 2 10471
Protoss_Assimilator 1 4650
Protoss_Cybernetics_Core 1 6331
Protoss_Dragoon 8 14331
Protoss_Citadel_of_Adun 2 14322
Protoss_Robotics_Facility 1 11868
Protoss_Observatory 1 12771
Protoss_Shuttle 1 13518
Singularity_Charge 1 12364
14331
