Protoss_Gateway 4 14771
Protoss_Assimilator 1 4631
Protoss_Cybernetics_Core 1 6040
Protoss_Dragoon 10 13847
Singularity_Charge 1 10099
Protoss_Nexus 1 14125
Protoss_Zealot 2 14708
Protoss_Robotics_Facility 1 15973
15973
