Protoss_Gateway 2 9980
Protoss_Assimilator 1 4253
Protoss_Cybernetics_Core 1 5686
Protoss_Dragoon 9 15440
Protoss_Nexus 1 10568
Protoss_Forge 1 9769
Protoss_Photon_Cannon 2 13203
Protoss_Zealot 2 15190
Singularity_Charge 1 11445
Protoss_Robotics_Facility 1 15510
15510
