Protoss_Gateway 2 6476
Protoss_Assimilator 2 14873
Protoss_Cybernetics_Core 1 5730
Protoss_Dragoon 7 14433
Protoss_Citadel_of_Adun 1 9416
Singularity_Charge 1 9391
Protoss_Templar_Archives 1 11023
Protoss_Nexus 1 14774
Protoss_Dark_Templar 1 13333
14873
