Protoss_Gateway 2 9380
Protoss_Assimilator 1 4469
Protoss_Cybernetics_Core 1 5911
Protoss_Dragoon 11 15712
Singularity_Charge 1 10194
Protoss_Nexus 2 14774
Protoss_Robotics_Facility 1 15007
15712
