Protoss_Gateway 2 13763
Protoss_Assimilator 1 4812
Protoss_Zealot 1 5505
Protoss_Cybernetics_Core 1 6536
Protoss_Dragoon 7 15189
Protoss_Robotics_Facility 1 9614
Protoss_Shuttle 1 11806
Protoss_Robotics_Support_Bay 1 11233
Protoss_Reaver 1 13364
Protoss_Observatory 1 14271
15189
