Protoss_Gateway 3 15588
Protoss_Assimilator 1 4555
Protoss_Zealot 1 5215
Protoss_Cybernetics_Core 1 7079
Protoss_Dragoon 11 15648
Protoss_Nexus 1 13799
Singularity_Charge 1 11153
Protoss_Robotics_Facility 2 14621
Protoss_Observatory 1 14650
15648
