Protoss_Gateway 3 15667
Protoss_Assimilator 1 4452
Protoss_Cybernetics_Core 1 5913
Protoss_Dragoon 7 15519
Protoss_Robotics_Facility 1 9783
Protoss_Shuttle 1 11199
Singularity_Charge 1 9777
Protoss_Robotics_Support_Bay 1 10794
Protoss_Zealot 2 12529
Protoss_Reaver 1 12836
Protoss_Observatory 1 12891
Protoss_Observer 1 14461
15667
