Protoss_Gateway 4 16013
Protoss_Assimilator 1 4331
Protoss_Cybernetics_Core 1 5963
Protoss_Dragoon 10 14659
Protoss_Nexus 1 12640
Singularity_Charge 1 10140
Protoss_Robotics_Facility 1 14751
16013
