Protoss_Gateway 1 4410
Protoss_Assimilator 1 4534
Protoss_Cybernetics_Core 1 5942
Protoss_Zealot 2 11329
Protoss_Robotics_Facility 1 8561
Protoss_Dragoon 4 13946
Protoss_Robotics_Support_Bay 1 9265
Protoss_Shield_Battery 1 9500
Protoss_Shuttle 2 13422
Protoss_Reaver 2 15915
Gravitic_Drive 1 13253
Protoss_Nexus 1 16822
16822
