Protoss_Gateway 3 13293
Protoss_Assimilator 1 4150
Protoss_Cybernetics_Core 1 5551
Protoss_Dragoon 9 13192
Singularity_Charge 1 9525
Protoss_Nexus 1 13458
Protoss_Zealot 5 14522
Protoss_Citadel_of_Adun 1 15473
15473
