Protoss_Gateway 3 12848
Protoss_Assimilator 1 4593
Protoss_Cybernetics_Core 1 6184
Protoss_Dragoon 9 14371
Protoss_Robotics_Facility 1 12352
Singularity_Charge 1 10487
Protoss_Zealot 2 13180
Protoss_Observatory 1 13075
Protoss_Observer 1 14673
Protoss_Nexus 1 17159
17159
