Protoss_Gateway 2 9789
Protoss_Assimilator 1 4198
Protoss_Cybernetics_Core 1 5645
Protoss_Dragoon 12 15724
Protoss_Robotics_Facility 1 9139
Protoss_Observatory 1 9947
Singularity_Charge 1 9894
Protoss_Observer 4 14739
Protoss_Nexus 1 15154
15724
