Protoss_Gateway 3 12516
Protoss_Assimilator 2 13846
Protoss_Cybernetics_Core 1 5941
Protoss_Dragoon 11 15671
Protoss_Nexus 1 11850
Singularity_Charge 1 9953
Protoss_Robotics_Facility 1 13415
Protoss_Zealot 1 12599
Protoss_Stargate 1 15602
Protoss_Observatory 1 14893
15671
