Protoss_Gateway 2 6443
Protoss_Assimilator 1 4210
Protoss_Cybernetics_Core 1 5762
Protoss_Dragoon 9 13956
Protoss_Robotics_Facility 1 10819
Singularity_Charge 1 9426
Protoss_Zealot 2 11107
Protoss_Robotics_Support_Bay 1 12844
Protoss_Shuttle 1 13773
Protoss_Reaver 1 15331
Protoss_Observatory 1 14780
15331
