Protoss_Gateway 3 10185
Protoss_Assimilator 1 4592
Protoss_Cybernetics_Core 1 5932
Protoss_Dragoon 8 13541
Singularity_Charge 1 10122
Protoss_Zealot 4 13109
Protoss_Citadel_of_Adun 1 13120
Protoss_Templar_Archives 1 14588
Protoss_Nexus 1 16565
Protoss_Dark_Templar 2 15791
16565
