Protoss_Gateway 2 8256
Protoss_Assimilator 1 4622
Protoss_Cybernetics_Core 1 5954
Protoss_Dragoon 10 14729
Protoss_Citadel_of_Adun 1 10291
Singularity_Charge 1 9976
Protoss_Nexus 2 17054
Protoss_Robotics_Facility 1 14081
Protoss_Observatory 1 14997
17054
