Protoss_Gateway 2 12708
Protoss_Assimilator 1 4441
Protoss_Cybernetics_Core 1 5733
Protoss_Dragoon 8 15797
Protoss_Robotics_Facility 1 8305
Protoss_Shuttle 1 9710
Protoss_Robotics_Support_Bay 1 9133
Protoss_Reaver 1 11321
Protoss_Observatory 1 11662
Protoss_Observer 1 12784
Protoss_Nexus 1 16675
16675
