Protoss_Gateway 2 12175
Protoss_Assimilator 1 4515
Protoss_Cybernetics_Core 1 5996
Protoss_Dragoon 10 15001
Protoss_Robotics_Facility 1 10598
Singularity_Charge 1 10158
Protoss_Observatory 1 11363
Protoss_Observer 3 15052
Protoss_Nexus 1 16237
16237
