Protoss_Gateway 2 12168
Protoss_Assimilator 1 4684
Protoss_Cybernetics_Core 1 5941
Protoss_Dragoon 6 15629
Protoss_Robotics_Facility 1 8707
Protoss_Shuttle 1 10116
Protoss_Robotics_Support_Bay 1 9974
Protoss_Reaver 2 13559
Protoss_Nexus 1 17043
Singularity_Charge 1 14336
17043
