Protoss_Gateway 2 10205
Protoss_Assimilator 1 4512
Protoss_Cybernetics_Core 1 5889
Protoss_Dragoon 9 14160
Protoss_Robotics_Facility 1 10273
Singularity_Charge 1 9836
Protoss_Zealot 3 15141
Protoss_Observatory 1 11577
Protoss_Observer 1 12829
Protoss_Citadel_of_Adun 1 13318
Protoss_Shuttle 1 14806
Protoss_Templar_Archives 2 15248
15248
