Protoss_Gateway 2 8216
Protoss_Assimilator 1 4496
Protoss_Cybernetics_Core 1 6154
Protoss_Dragoon 11 15420
Singularity_Charge 1 10026
Protoss_Nexus 2 14949
Protoss_Robotics_Facility 1 15404
15420
