Protoss_Gateway 3 14930
Protoss_Assimilator 1 4349
Protoss_Cybernetics_Core 1 5739
Protoss_Dragoon 8 13520
Protoss_Robotics_Facility 1 11189
Protoss_Observatory 1 11949
Singularity_Charge 1 11448
Protoss_Observer 2 15327
Protoss_Nexus 1 15501
Protoss_Citadel_of_Adun 1 14904
15501
