Protoss_Gateway 2 6649
Protoss_Assimilator 1 4428
Protoss_Cybernetics_Core 1 5692
Protoss_Dragoon 8 15702
Singularity_Charge 1 9375
Protoss_Nexus 2 15813
Protoss_Robotics_Facility 1 13685
Protoss_Shuttle 1 15648
Protoss_Robotics_Support_Bay 1 15003
15813
