Protoss_Gateway 2 10046
Protoss_Assimilator 1 4258
Protoss_Cybernetics_Core 1 5745
Protoss_Dragoon 9 14824
Protoss_Robotics_Facility 1 9930
Singularity_Charge 1 9770
Protoss_Observatory 1 10714
Protoss_Observer 3 14856
Protoss_Nexus 2 14065
14856
