Protoss_Gateway 1 4170
Protoss_Assimilator 1 4234
Protoss_Cybernetics_Core 1 5707
Protoss_Zealot 2 8885
Protoss_Robotics_Facility 1 7835
Protoss_Dragoon 5 14981
Protoss_Shuttle 3 16035
Protoss_Robotics_Support_Bay 1 9038
Protoss_Reaver 2 12493
Protoss_Observatory 1 13560
Gravitic_Drive 1 13436
Protoss_Observer 1 14651
16035
