Protoss_Gateway 3 14685
Protoss_Assimilator 1 4426
Protoss_Cybernetics_Core 1 5935
Protoss_Dragoon 9 14694
Protoss_Robotics_Facility 1 11593
Singularity_Charge 1 10172
Protoss_Nexus 2 17147
Protoss_Observatory 1 12282
Protoss_Observer 2 14306
17147
