Protoss_Gateway 4 15987
Protoss_Assimilator 1 4681
Protoss_Cybernetics_Core 1 5837
Protoss_Dragoon 9 15025
Protoss_Nexus 1 12422
Singularity_Charge 1 9594
Protoss_Robotics_Facility 1 12731
Protoss_Observatory 1 13655
Protoss_Observer 1 14966
15987
