Protoss_Nexus 1 6769
Protoss_Gateway 3 15219
Protoss_Assimilator 2 12632
Protoss_Cybernetics_Core 1 7539
Protoss_Zealot 4 14578
Protoss_Dragoon 10 15761
Protoss_Stargate 2 15331
Singularity_Charge 1 12177
Protoss_Fleet_Beacon 1 14846
15761
