Protoss_Gateway 2 8411
Protoss_Assimilator 1 4499
Protoss_Cybernetics_Core 1 5797
Protoss_Dragoon 12 15092
Singularity_Charge 1 9757
Protoss_Nexus 2 15998
Protoss_Robotics_Facility 1 13482
Protoss_Observatory 1 14453
Protoss_Observer 1 15476
15998
