Protoss_Gateway 2 11332
Protoss_Assimilator 2 5159
Protoss_Zealot 5 13371
Protoss_Cybernetics_Core 1 6811
Protoss_Dragoon 2 9127
Protoss_Robotics_Facility 1 10587
Protoss_Shuttle 1 12004
Protoss_Observatory 1 11536
Protoss_Robotics_Support_Bay 1 12651
Singularity_Charge 1 12755
Protoss_Reaver 2 16020
16020
