Protoss_Gateway 1 4170
Protoss_Assimilator 2 13726
Protoss_Cybernetics_Core 1 5866
Protoss_Dragoon 3 9587
Protoss_Stargate 2 13932
Protoss_Scout 2 12938
Protoss_Nexus 1 13600
Protoss_Air_Weapons_1 1 12133
Protoss_Fleet_Beacon 1 13951
Protoss_Carrier 2 17869
17869
