Protoss_Gateway 2 6400
Protoss_Assimilator 1 4703
Protoss_Cybernetics_Core 1 5793
Protoss_Dragoon 12 14823
Singularity_Charge 1 10450
Protoss_Nexus 1 13869
Protoss_Robotics_Facility 1 14120
Protoss_Observatory 1 15328
15328
