Protoss_Gateway 3 12977
Protoss_Assimilator 1 5096
Protoss_Zealot 7 15222
Protoss_Cybernetics_Core 1 7811
Protoss_Dragoon 7 13532
Protoss_Citadel_of_Adun 1 12691
Singularity_Charge 1 12168
15222
