Protoss_Gateway 3 11765
Protoss_Assimilator 1 4229
Protoss_Cybernetics_Core 1 5917
Protoss_Dragoon 11 14354
Singularity_Charge 1 9730
Protoss_Nexus 2 17162
Protoss_Robotics_Facility 1 16328
17162
