Protoss_Gateway 2 9877
Protoss_Assimilator 1 4985
Protoss_Cybernetics_Core 1 6270
Protoss_Dragoon 2 8714
Protoss_Citadel_of_Adun 1 8370
Protoss_Templar_Archives 1 10375
Protoss_Dark_Templar 4 12705
Protoss_Nexus 1 15495
Protoss_Robotics_Facility 1 15611
15611
