Protoss_Gateway 2 10613
Protoss_Assimilator 1 4663
Protoss_Cybernetics_Core 1 6153
Protoss_Dragoon 6 15718
Protoss_Citadel_of_Adun 1 9668
Protoss_Templar_Archives 1 11129
Singularity_Charge 1 10201
Protoss_Dark_Templar 4 13675
Protoss_Nexus 1 14547
15718
