Protoss_Gateway 1 4372
Protoss_Assimilator 1 4470
Protoss_Cybernetics_Core 1 5824
Protoss_Zealot 4 13726
Protoss_Robotics_Facility 1 8389
Protoss_Dragoon 3 10933
Protoss_Shuttle 1 10164
Protoss_Robotics_Support_Bay 1 10114
Protoss_Reaver 3 15340
15340
