Protoss_Gateway 2 10428
Protoss_Assimilator 1 4495
Protoss_Cybernetics_Core 1 6023
Protoss_Dragoon 8 13555
Protoss_Robotics_Facility 1 10292
Singularity_Charge 1 9704
Protoss_Observatory 1 10989
Protoss_Observer 2 13068
Protoss_Nexus 2 16404
Protoss_Zealot 2 14944
Protoss_Shuttle 1 15989
16404
