Protoss_Gateway 2 10215
Protoss_Assimilator 1 4390
Protoss_Cybernetics_Core 1 5702
Protoss_Dragoon 10 14750
Protoss_Robotics_Facility 1 10230
Singularity_Charge 1 9689
Protoss_Observatory 1 11053
Protoss_Observer 4 15503
Protoss_Nexus 2 15655
15655
