Protoss_Gateway 2 6874
Protoss_Assimilator 1 4562
Protoss_Cybernetics_Core 1 5963
Protoss_Dragoon 11 15502
Protoss_Citadel_of_Adun 1 10501
Singularity_Charge 1 9622
Protoss_Zealot 1 11156
Protoss_Templar_Archives 1 11944
Protoss_Dark_Templar 2 13828
15502
