Protoss_Gateway 3 15577
Protoss_Assimilator 1 5158
Protoss_Cybernetics_Core 1 6329
Protoss_Dragoon 9 15273
Protoss_Robotics_Facility 1 10252
Protoss_Observatory 1 11306
Protoss_Observer 4 15165
Protoss_Nexus 1 15030
Singularity_Charge 1 12265
15577
