Protoss_Gateway 2 9473
Protoss_Assimilator 1 4792
Protoss_Zealot 1 5329
Protoss_Cybernetics_Core 1 7250
Protoss_Dragoon 8 14195
Singularity_Charge 1 10992
Protoss_Nexus 1 14652
Protoss_Robotics_Facility 1 14480
Protoss_Shuttle 1 16021
16021
