Protoss_Gateway 2 9497
Protoss_Assimilator 2 5244
Protoss_Zealot 2 7202
Protoss_Cybernetics_Core 1 7123
Protoss_Dragoon 10 15475
Singularity_Charge 1 11109
Protoss_Nexus 1 14920
Protoss_Robotics_Facility 1 14787
15475
