Protoss_Gateway 4 14780
Protoss_Assimilator 1 4264
Protoss_Cybernetics_Core 1 5952
Protoss_Dragoon 9 15373
Protoss_Nexus 2 14724
Singularity_Charge 1 9818
Protoss_Robotics_Facility 1 15537
15537
