Protoss_Gateway 3 14240
Protoss_Assimilator 1 4368
Protoss_Cybernetics_Core 1 5834
Protoss_Dragoon 9 14094
Singularity_Charge 1 10181
Protoss_Nexus 1 13647
Protoss_Robotics_Facility 1 13901
Protoss_Shuttle 1 15675
Protoss_Robotics_Support_Bay 1 15215
15675
