Protoss_Gateway 2 5235
Protoss_Zealot 3 6324
Protoss_Assimilator 1 6547
Protoss_Cybernetics_Core 1 7880
Protoss_Dragoon 7 15819
Protoss_Nexus 1 13894
Singularity_Charge 1 11665
Protoss_Robotics_Facility 1 13573
Protoss_Shuttle 1 15004
Protoss_Robotics_Support_Bay 1 14321
15819
