Protoss_Gateway 3 14581
Protoss_Assimilator 2 14418
Protoss_Cybernetics_Core 1 5831
Protoss_Dragoon 7 13822
Protoss_Robotics_Facility 1 11543
Protoss_Zealot 2 11066
Singularity_Charge 1 9997
Protoss_Nexus 1 14254
Protoss_Observatory 1 12334
Protoss_Observer 2 14358
14581
