Protoss_Gateway 2 7602
Protoss_Assimilator 1 4603
Protoss_Zealot 2 6580
Protoss_Cybernetics_Core 1 6731
Protoss_Dragoon 11 14531
Singularity_Charge 1 10750
Protoss_Nexus 1 14317
Protoss_Robotics_Facility 1 14348
Protoss_Observatory 1 15307
15307
