Protoss_Gateway 2 8253
Protoss_Assimilator 2 14986
Protoss_Cybernetics_Core 1 5815
Protoss_Dragoon 5 11092
Protoss_Citadel_of_Adun 1 10726
Protoss_Zealot 1 10583
Singularity_Charge 1 9865
Protoss_Robotics_Facility 2 16494
Protoss_Templar_Archives 1 12233
Protoss_Nexus 1 14438
Protoss_Dark_Templar 1 13624
Protoss_Stargate 1 14849
16494
