Protoss_Gateway 3 14783
Protoss_Assimilator 1 4517
Protoss_Cybernetics_Core 1 5761
Protoss_Dragoon 10 15508
Singularity_Charge 1 9657
Protoss_Nexus 2 14724
Protoss_Robotics_Facility 1 15701
15701
