Protoss_Gateway 3 12828
Protoss_Assimilator 1 4199
Protoss_Cybernetics_Core 1 5876
Protoss_Dragoon 8 13608
Singularity_Charge 1 9762
Protoss_Nexus 2 16997
Protoss_Robotics_Facility 1 16320
16997
