Protoss_Gateway 2 8348
Protoss_Assimilator 1 4493
Protoss_Cybernetics_Core 1 5841
Protoss_Dragoon 7 14495
Protoss_Robotics_Facility 1 11457
Protoss_Zealot 4 12741
Singularity_Charge 1 10099
Protoss_Shuttle 1 13057
Protoss_Observatory 1 12723
Protoss_Observer 1 13900
Protoss_Nexus 1 16654
16654
