Protoss_Gateway 2 12091
Protoss_Assimilator 1 4232
Protoss_Cybernetics_Core 1 6007
Protoss_Robotics_Facility 1 7987
Protoss_Dragoon 2 8637
Protoss_Shuttle 1 9399
Protoss_Robotics_Support_Bay 1 9126
Protoss_Zealot 2 10919
Protoss_Reaver 2 12564
Protoss_Citadel_of_Adun 1 11228
Protoss_Templar_Archives 1 13309
Protoss_Dark_Templar 1 15088
15088
