Protoss_Gateway 4 15529
Protoss_Assimilator 1 4600
Protoss_Cybernetics_Core 1 6036
Protoss_Dragoon 8 15534
Protoss_Robotics_Facility 1 8700
Protoss_Observatory 1 9667
Protoss_Observer 5 15071
Singularity_Charge 1 11892
Protoss_Nexus 1 15878
15878
