Protoss_Nexus 1 7508
Protoss_Gateway 3 12446
Protoss_Assimilator 2 12333
Protoss_Zealot 9 15283
Protoss_Cybernetics_Core 1 8436
Protoss_Dragoon 4 12563
Protoss_Citadel_of_Adun 1 11729
Protoss_Templar_Archives 1 13250
Singularity_Charge 1 13472
Protoss_Dark_Templar 2 15759
15759
