Protoss_Gateway 2 10717
Protoss_Assimilator 1 4545
Protoss_Cybernetics_Core 1 6106
Protoss_Dragoon 8 13397
Protoss_Robotics_Facility 1 10410
Singularity_Charge 1 9771
Protoss_Observatory 1 11409
Protoss_Observer 3 14607
Protoss_Nexus 2 17286
17286
