Protoss_Gateway 2 13492
Protoss_Assimilator 1 4583
Protoss_Cybernetics_Core 1 5926
Protoss_Dragoon 4 15541
Protoss_Robotics_Facility 1 8681
Protoss_Shuttle 1 10109
Protoss_Observatory 1 9595
Protoss_Robotics_Support_Bay 1 9696
Protoss_Observer 2 15081
Protoss_Reaver 2 14257
Gravitic_Drive 1 14021
15541
