Protoss_Gateway 4 14584
Protoss_Assimilator 1 4410
Protoss_Cybernetics_Core 1 5802
Protoss_Dragoon 11 14109
Singularity_Charge 1 9894
Protoss_Robotics_Facility 1 11871
Protoss_Nexus 1 14488
Protoss_Observatory 1 12634
Protoss_Observer 1 13663
Protoss_Shuttle 1 15230
Protoss_Zealot 2 15214
15230
