Protoss_Gateway 3 15312
Protoss_Assimilator 1 4473
Protoss_Cybernetics_Core 1 5696
Protoss_Dragoon 9 14577
Protoss_Robotics_Facility 1 8448
Protoss_Observatory 1 9209
Protoss_Observer 2 14481
Protoss_Nexus 2 15884
Singularity_Charge 1 12048
Protoss_Shuttle 1 15977
15977
