Protoss_Gateway 2 6826
Protoss_Assimilator 1 4593
Protoss_Cybernetics_Core 1 6065
Protoss_Dragoon 8 15278
Protoss_Zealot 1 10056
Singularity_Charge 1 9755
Protoss_Nexus 2 15674
Protoss_Robotics_Facility 1 15285
15674
