Protoss_Gateway 3 14429
Protoss_Assimilator 1 4690
Protoss_Cybernetics_Core 1 6182
Protoss_Dragoon 11 15717
Protoss_Robotics_Facility 1 10299
Protoss_Observatory 1 11035
Singularity_Charge 1 10326
Protoss_Observer 4 15430
Protoss_Nexus 1 15021
15717
