Protoss_Gateway 2 9504
Protoss_Assimilator 1 4688
Protoss_Cybernetics_Core 1 6358
Protoss_Dragoon 8 13061
Protoss_Robotics_Facility 1 10797
Singularity_Charge 1 10245
Protoss_Observatory 1 11791
Protoss_Observer 3 14951
Protoss_Nexus 1 15330
15330
