Protoss_Gateway 2 15149
Protoss_Assimilator 1 4534
Protoss_Cybernetics_Core 1 5875
Protoss_Dragoon 8 15383
Protoss_Robotics_Facility 1 10368
Singularity_Charge 1 9989
Protoss_Observatory 1 11134
Protoss_Nexus 1 13560
Protoss_Observer 1 12412
Protoss_Robotics_Support_Bay 1 12704
Protoss_Shuttle 1 13770
Protoss_Reaver 1 15328
15383
