Protoss_Gateway 2 10470
Protoss_Assimilator 1 4431
Protoss_Cybernetics_Core 1 5628
Protoss_Dragoon 9 15572
Protoss_Robotics_Facility 1 9885
Singularity_Charge 1 9344
Protoss_Observatory 1 10689
Protoss_Nexus 3 17387
Protoss_Observer 1 12163
Protoss_Shuttle 1 14724
Protoss_Robotics_Support_Bay 1 14293
17387
