Protoss_Nexus 2 15357
Protoss_Gateway 5 15614
Protoss_Zealot 8 10893
Protoss_Assimilator 1 8107
Protoss_Cybernetics_Core 1 9737
Protoss_Dragoon 6 14432
Protoss_Robotics_Facility 1 15307
Protoss_Citadel_of_Adun 1 15131
Singularity_Charge 1 13772
15614
