Protoss_Gateway 3 14429
Protoss_Assimilator 1 4673
Protoss_Cybernetics_Core 1 6160
Protoss_Dragoon 9 15753
Protoss_Robotics_Facility 1 10740
Singularity_Charge 1 10480
Protoss_Observatory 1 11602
Protoss_Nexus 1 14753
Protoss_Observer 3 14980
15753
