Protoss_Gateway 3 12958
Protoss_Assimilator 1 4798
Protoss_Zealot 2 7290
Protoss_Cybernetics_Core 1 7104
Protoss_Dragoon 10 15434
Protoss_Robotics_Facility 1 10024
Protoss_Observatory 1 10794
Protoss_Observer 2 12942
Singularity_Charge 1 12506
15434
