Protoss_Gateway 3 15788
Protoss_Assimilator 1 4164
Protoss_Cybernetics_Core 1 5575
Protoss_Dragoon 10 15001
Protoss_Nexus 2 15400
Singularity_Charge 1 9452
Protoss_Robotics_Facility 1 12995
Protoss_Observatory 1 13730
Protoss_Shuttle 1 14724
15788
