Protoss_Gateway 3 11395
Protoss_Assimilator 1 4147
Protoss_Cybernetics_Core 1 5832
Protoss_Dragoon 12 15614
Protoss_Nexus 2 17152
Singularity_Charge 1 9872
Protoss_Robotics_Facility 1 12891
Protoss_Observatory 1 13596
Protoss_Observer 2 15495
17152
