Protoss_Nexus 2 16290
Protoss_Gateway 3 15677
Protoss_Assimilator 2 8969
Protoss_Cybernetics_Core 1 7422
Protoss_Zealot 3 13776
Protoss_Citadel_of_Adun 1 8923
Protoss_Dragoon 5 15145
Protoss_Robotics_Facility 1 10276
Protoss_Shuttle 1 11870
Protoss_Robotics_Support_Bay 1 11726
Protoss_Reaver 1 13701
Protoss_Observatory 1 12838
16290
