Protoss_Gateway 6 15672
Protoss_Assimilator 1 4529
Protoss_Cybernetics_Core 1 5799
Protoss_Dragoon 9 13829
Protoss_Nexus 1 12221
Singularity_Charge 1 9850
Protoss_Robotics_Facility 1 12480
Protoss_Observatory 1 13332
Protoss_Observer 2 15269
15672
