Protoss_Gateway 3 11282
Protoss_Assimilator 1 4410
Protoss_Cybernetics_Core 1 5831
Protoss_Dragoon 11 14634
Protoss_Nexus 2 17346
Singularity_Charge 1 9792
Protoss_Robotics_Facility 1 13694
Protoss_Observatory 1 14693
17346
