Protoss_Gateway 2 10518
Protoss_Assimilator 1 4296
Protoss_Cybernetics_Core 1 5729
Protoss_Dragoon 12 15578
Protoss_Robotics_Facility 1 9622
Protoss_Observatory 1 10435
Singularity_Charge 1 9748
Protoss_Observer 2 13422
Protoss_Nexus 1 17076
17076
