Protoss_Gateway 2 6447
Protoss_Assimilator 1 4265
Protoss_Cybernetics_Core 1 5607
Protoss_Dragoon 9 15411
Protoss_Citadel_of_Adun 1 9968
Singularity_Charge 1 9780
Protoss_Templar_Archives 1 11475
Protoss_Zealot 2 11607
Protoss_Dark_Templar 2 12727
Protoss_Nexus 1 15191
15411
