Protoss_Gateway 3 14093
Protoss_Assimilator 1 4676
Protoss_Cybernetics_Core 1 6087
Protoss_Dragoon 11 15549
Protoss_Robotics_Facility 1 10533
Protoss_Nexus 1 13666
Singularity_Charge 1 11043
Protoss_Observatory 1 11791
Protoss_Observer 3 14759
15549
