Protoss_Gateway 3 11707
Protoss_Assimilator 1 4578
Protoss_Zealot 3 12800
Protoss_Cybernetics_Core 1 7173
Protoss_Dragoon 10 15661
Protoss_Nexus 1 11817
Singularity_Charge 1 10919
Protoss_Robotics_Facility 1 13126
Protoss_Observatory 1 13873
Protoss_Observer 1 15310
15661
