Protoss_Gateway 2 6418
Protoss_Assimilator 1 4289
Protoss_Cybernetics_Core 1 5729
Protoss_Dragoon 9 15373
Protoss_Robotics_Facility 1 10674
Singularity_Charge 1 9762
Protoss_Shuttle 2 13482
Protoss_Robotics_Support_Bay 1 11868
Protoss_Reaver 1 13771
Protoss_Observatory 1 13172
Protoss_Nexus 1 16237
Protoss_Observer 1 14595
16237
