Protoss_Assimilator 2 10594
Protoss_Gateway 2 13561
Protoss_Zealot 7 13545
Protoss_Nexus 1 11604
Protoss_Forge 1 10488
Protoss_Photon_Cannon 5 14798
Protoss_Cybernetics_Core 1 12497
Protoss_Dragoon 3 15130
15130
