Protoss_Gateway 2 9621
Protoss_Assimilator 1 4350
Protoss_Cybernetics_Core 1 5692
Protoss_Dragoon 12 15383
Protoss_Robotics_Facility 1 8350
Protoss_Observatory 1 9129
Protoss_Shuttle 1 10489
Singularity_Charge 1 11321
Protoss_Nexus 1 14225
Protoss_Robotics_Support_Bay 1 13400
Protoss_Reaver 1 16171
16171
