Protoss_Gateway 1 4309
Protoss_Assimilator 1 4659
Protoss_Cybernetics_Core 1 6204
Protoss_Robotics_Facility 1 8442
Protoss_Dragoon 2 15790
Protoss_Zealot 3 13239
Protoss_Shuttle 1 10189
Protoss_Robotics_Support_Bay 1 9683
Protoss_Reaver 3 16295
Protoss_Nexus 1 16739
Gravitic_Drive 1 14277
16739
