Protoss_Gateway 3 14115
Protoss_Assimilator 1 4461
Protoss_Cybernetics_Core 1 5917
Protoss_Dragoon 8 13441
Protoss_Robotics_Facility 1 9840
Protoss_Observatory 1 10598
Singularity_Charge 1 9956
Protoss_Observer 2 12872
Protoss_Nexus 1 14359
Protoss_Zealot 5 15184
15184
