Protoss_Gateway 2 9036
Protoss_Assimilator 1 4245
Protoss_Cybernetics_Core 1 5903
Protoss_Dragoon 9 14129
Singularity_Charge 1 9745
Protoss_Nexus 2 16840
Protoss_Robotics_Facility 1 13732
Protoss_Shuttle 1 15356
Protoss_Robotics_Support_Bay 1 15205
16840
