Protoss_Gateway 4 13997
Protoss_Assimilator 1 4451
Protoss_Cybernetics_Core 1 5822
Protoss_Dragoon 9 15710
Singularity_Charge 1 9814
Protoss_Nexus 2 14463
Protoss_Citadel_of_Adun 1 15245
15710
