Protoss_Nexus 1 6868
Protoss_Gateway 4 14313
Protoss_Assimilator 1 5954
Protoss_Cybernetics_Core 1 7618
Protoss_Zealot 1 7954
Protoss_Dragoon 11 15508
Protoss_Robotics_Facility 1 12548
Singularity_Charge 1 11764
Protoss_Shuttle 1 14054
15508
