Protoss_Gateway 3 12929
Protoss_Assimilator 2 15359
Protoss_Cybernetics_Core 1 5926
Protoss_Dragoon 8 14751
Protoss_Nexus 1 11190
Protoss_Robotics_Facility 1 11444
Singularity_Charge 1 12550
Protoss_Observatory 1 14814
15359
