Protoss_Gateway 4 14282
Protoss_Assimilator 1 4191
Protoss_Cybernetics_Core 1 5648
Protoss_Dragoon 8 15724
Protoss_Nexus 2 14294
Protoss_Robotics_Facility 1 11277
Singularity_Charge 1 9514
Protoss_Observatory 1 11979
Protoss_Observer 3 15514
Protoss_Citadel_of_Adun 1 13653
Protoss_Zealot 1 14271
15724
