Protoss_Gateway 4 10798
Protoss_Assimilator 1 4472
Protoss_Zealot 14 15532
Protoss_Cybernetics_Core 1 7245
Protoss_Dragoon 4 12089
Protoss_Citadel_of_Adun 1 11004
Singularity_Charge 1 13883
Leg_Enhancements 1 14068
15532
