Protoss_Gateway 4 15002
Protoss_Assimilator 1 4425
Protoss_Cybernetics_Core 1 5853
Protoss_Dragoon 8 13873
Protoss_Robotics_Facility 1 9834
Protoss_Observatory 1 10531
Singularity_Charge 1 9960
Protoss_Observer 2 13663
Protoss_Nexus 1 14393
Protoss_Shuttle 1 15362
Protoss_Zealot 2 15119
15362
