Protoss_Nexus 2 16897
Protoss_Gateway 4 12460
Protoss_Assimilator 2 13981
Protoss_Cybernetics_Core 1 7638
Protoss_Dragoon 12 15695
Protoss_Zealot 1 9795
Protoss_Robotics_Facility 1 12423
Singularity_Charge 1 11665
Protoss_Observatory 1 13257
Protoss_Observer 1 15171
16897
