Protoss_Gateway 2 8610
Protoss_Assimilator 1 4777
Protoss_Cybernetics_Core 1 6391
Protoss_Dragoon 8 15364
Singularity_Charge 1 10392
Protoss_Nexus 2 15160
Protoss_Zealot 1 13984
Protoss_Robotics_Facility 1 15566
15566
