Protoss_Gateway 2 7032
Protoss_Assimilator 1 4581
Protoss_Cybernetics_Core 1 5837
Protoss_Dragoon 7 12805
Protoss_Zealot 4 13795
Singularity_Charge 1 10092
Protoss_Nexus 1 13723
Protoss_Citadel_of_Adun 1 14019
Protoss_Robotics_Facility 1 15510
Protoss_Templar_Archives 1 15785
15785
