Protoss_Gateway 4 15933
Protoss_Assimilator 1 4439
Protoss_Cybernetics_Core 1 5799
Protoss_Dragoon 8 15613
Protoss_Zealot 2 8057
Protoss_Nexus 2 14784
Singularity_Charge 1 10166
Protoss_Robotics_Facility 1 15101
15933
