Protoss_Gateway 4 15671
Protoss_Assimilator 1 4256
Protoss_Cybernetics_Core 1 5897
Protoss_Dragoon 14 15680
Singularity_Charge 1 9887
Protoss_Nexus 1 14415
Protoss_Robotics_Facility 1 14678
15680
