Protoss_Gateway 3 15964
Protoss_Assimilator 1 4542
Protoss_Cybernetics_Core 1 5730
Protoss_Zealot 1 5516
Protoss_Dragoon 10 15464
Singularity_Charge 1 10128
Protoss_Nexus 1 13366
Protoss_Robotics_Facility 1 13902
Protoss_Observatory 1 14921
15964
