Protoss_Gateway 2 5377
Protoss_Zealot 4 10769
Protoss_Assimilator 1 6898
Protoss_Cybernetics_Core 1 8611
Protoss_Dragoon 10 15522
Protoss_Nexus 1 13844
Protoss_Robotics_Facility 1 14583
Singularity_Charge 1 12960
15522
