Protoss_Gateway 4 14344
Protoss_Assimilator 1 4564
Protoss_Cybernetics_Core 1 5857
Protoss_Dragoon 7 13822
Protoss_Nexus 1 11496
Protoss_Zealot 7 14988
Singularity_Charge 1 9967
Protoss_Citadel_of_Adun 1 13483
14988
