Protoss_Gateway 3 13679
Protoss_Assimilator 1 4193
Protoss_Cybernetics_Core 1 5799
Protoss_Dragoon 11 14237
Protoss_Nexus 1 11657
Singularity_Charge 1 10019
Protoss_Robotics_Facility 1 12007
Protoss_Observatory 1 14366
14366
