Protoss_Gateway 4 14524
Protoss_Assimilator 2 13092
Protoss_Cybernetics_Core 1 5794
Protoss_Dragoon 8 13858
Protoss_Citadel_of_Adun 1 9535
Protoss_Stargate 1 10818
Singularity_Charge 1 9682
Protoss_Templar_Archives 1 11229
Protoss_Nexus 1 13083
Protoss_Arbiter_Tribunal 1 12936
Protoss_Arbiter 1 17275
Protoss_Zealot 3 15192
17275
