Protoss_Gateway 4 15090
Protoss_Assimilator 1 4564
Protoss_Cybernetics_Core 1 6007
Protoss_Dragoon 10 15527
Protoss_Nexus 1 12077
Protoss_Robotics_Facility 1 11905
Singularity_Charge 1 10004
Protoss_Observatory 1 13026
Protoss_Zealot 1 13495
Protoss_Observer 2 15046
15527
