Protoss_Assimilator 1 3620
Protoss_Gateway 5 15811
Protoss_Cybernetics_Core 1 6248
Protoss_Robotics_Facility 1 8180
Protoss_Dragoon 7 14827
Protoss_Shuttle 1 9823
Protoss_Observatory 1 9219
Protoss_Observer 3 12428
Singularity_Charge 1 11709
Protoss_Nexus 1 15208
Protoss_Citadel_of_Adun 1 14452
15811
