Protoss_Gateway 3 15318
Protoss_Assimilator 1 4594
Protoss_Cybernetics_Core 1 5993
Protoss_Dragoon 6 12892
Protoss_Nexus 1 11715
Singularity_Charge 1 10019
Protoss_Robotics_Facility 1 12581
Protoss_Shuttle 1 14228
Protoss_Robotics_Support_Bay 1 13791
Protoss_Reaver 1 15786
15786
