Protoss_Gateway 2 8756
Protoss_Assimilator 1 4488
Protoss_Cybernetics_Core 1 5765
Protoss_Dragoon 14 15465
Singularity_Charge 1 9777
Protoss_Robotics_Facility 1 13166
Protoss_Observatory 1 13854
Protoss_Observer 1 14885
15465
