Protoss_Gateway 2 9655
Protoss_Assimilator 1 4529
Protoss_Cybernetics_Core 1 5926
Protoss_Dragoon 11 15388
Singularity_Charge 1 10048
Protoss_Nexus 1 15900
Protoss_Robotics_Facility 1 15540
15900
