Protoss_Gateway 4 13550
Protoss_Assimilator 2 14948
Protoss_Cybernetics_Core 1 5755
Protoss_Dragoon 9 15748
Protoss_Robotics_Facility 1 9866
Protoss_Nexus 2 17128
Singularity_Charge 1 9604
Protoss_Observatory 1 10866
Protoss_Observer 3 13694
Protoss_Zealot 1 15368
17128
