Protoss_Gateway 3 13476
Protoss_Assimilator 1 4704
Protoss_Cybernetics_Core 1 5996
Protoss_Zealot 1 5973
Protoss_Dragoon 10 15571
Singularity_Charge 1 10245
Protoss_Nexus 2 16001
16001
