Protoss_Gateway 2 8282
Protoss_Assimilator 1 4432
Protoss_Cybernetics_Core 1 5759
Protoss_Dragoon 4 9761
Protoss_Citadel_of_Adun 1 9378
Protoss_Templar_Archives 1 10899
Protoss_Zealot 3 13030
Singularity_Charge 1 9755
Protoss_Dark_Templar 5 14575
Protoss_Nexus 1 16389
Protoss_Robotics_Facility 1 16426
16426
