Protoss_Gateway 3 13104
Protoss_Assimilator 2 13889
Protoss_Cybernetics_Core 1 5601
Protoss_Dragoon 5 9411
Singularity_Charge 1 9262
Protoss_Nexus 1 13000
Protoss_Citadel_of_Adun 1 12023
Protoss_Robotics_Facility 1 13510
Protoss_Templar_Archives 1 13474
Protoss_Shuttle 1 14911
Protoss_Dark_Templar 3 14758
Protoss_Observatory 1 14773
14911
