Protoss_Gateway 4 14448
Protoss_Assimilator 2 11856
Protoss_Cybernetics_Core 1 5644
Protoss_Dragoon 7 12680
Protoss_Nexus 1 11670
Protoss_Robotics_Facility 1 11847
Singularity_Charge 1 10070
Protoss_Citadel_of_Adun 1 11933
Protoss_Templar_Archives 1 13785
Protoss_Shuttle 1 14777
Protoss_Dark_Templar 3 15417
Protoss_Stargate 1 15695
15695
