Protoss_Gateway 2 6980
Protoss_Assimilator 1 4444
Protoss_Cybernetics_Core 1 6160
Protoss_Dragoon 5 10020
Singularity_Charge 1 9839
Protoss_Robotics_Facility 1 12109
Protoss_Zealot 4 12614
Protoss_Shuttle 1 13512
Protoss_Robotics_Support_Bay 1 13007
Protoss_Reaver 1 15070
15070
