Protoss_Gateway 2 12751
Protoss_Assimilator 1 4681
Protoss_Cybernetics_Core 1 6336
Protoss_Dragoon 7 14122
Protoss_Robotics_Facility 1 10135
Protoss_Shuttle 1 11623
Protoss_Observatory 1 11072
Protoss_Observer 2 13590
Protoss_Robotics_Support_Bay 1 12696
Singularity_Charge 1 12638
Protoss_Reaver 1 15490
15490
