Protoss_Gateway 3 13284
Protoss_Assimilator 1 4463
Protoss_Cybernetics_Core 1 5923
Protoss_Zealot 5 13539
Protoss_Dragoon 7 14893
Protoss_Robotics_Facility 1 10726
Singularity_Charge 1 10169
Protoss_Observatory 1 11474
Protoss_Shuttle 1 12491
Protoss_Observer 2 15119
15119
