Protoss_Gateway 3 15740
Protoss_Assimilator 1 4401
Protoss_Cybernetics_Core 1 5749
Protoss_Dragoon 6 14826
Protoss_Robotics_Facility 1 10024
Protoss_Zealot 2 13706
Singularity_Charge 1 9932
Protoss_Shuttle 1 11721
Protoss_Robotics_Support_Bay 1 11069
Protoss_Reaver 1 13279
Protoss_Observatory 1 13010
Protoss_Observer 2 15494
Protoss_Nexus 1 16901
16901
