Protoss_Gateway 1 4180
Protoss_Assimilator 1 4379
Protoss_Cybernetics_Core 1 5767
Protoss_Robotics_Facility 1 7887
Protoss_Zealot 1 7176
Protoss_Dragoon 5 15537
Protoss_Shuttle 1 9283
Protoss_Robotics_Support_Bay 1 8776
Protoss_Reaver 2 12381
Protoss_Observatory 1 12272
Protoss_Observer 1 13908
Gravitic_Drive 1 13371
15537
