Protoss_Gateway 3 15327
Protoss_Assimilator 1 4369
Protoss_Cybernetics_Core 1 5769
Protoss_Zealot 3 11484
Protoss_Dragoon 5 14583
Protoss_Citadel_of_Adun 2 9810
Protoss_Templar_Archives 1 11306
Singularity_Charge 1 10406
Protoss_Dark_Templar 2 12712
Protoss_Robotics_Facility 1 14044
Protoss_Nexus 1 15906
Protoss_Observatory 1 15072
15906
