Protoss_Gateway 5 15738
Protoss_Assimilator 1 4294
Protoss_Cybernetics_Core 1 5635
Protoss_Dragoon 11 14941
Protoss_Nexus 2 16190
Singularity_Charge 1 9375
Protoss_Robotics_Facility 1 13229
Protoss_Observatory 1 13934
Protoss_Observer 1 15002
16190
