Protoss_Gateway 2 9828
Protoss_Assimilator 1 4512
Protoss_Cybernetics_Core 1 5933
Protoss_Dragoon 9 15803
Protoss_Citadel_of_Adun 1 8042
Protoss_Templar_Archives 1 9485
Protoss_Zealot 2 13328
Protoss_Dark_Templar 2 11062
15803
