Protoss_Gateway 2 10315
Protoss_Assimilator 1 4199
Protoss_Cybernetics_Core 1 5633
Protoss_Dragoon 6 15622
Protoss_Citadel_of_Adun 1 9065
Protoss_Templar_Archives 1 10529
Singularity_Charge 1 9821
Protoss_Dark_Templar 6 14546
Protoss_Nexus 2 16742
16742
