Protoss_Gateway 3 14648
Protoss_Assimilator 1 4211
Protoss_Cybernetics_Core 1 5796
Protoss_Dragoon 8 13901
Protoss_Robotics_Facility 1 10652
Singularity_Charge 1 9481
Protoss_Shuttle 1 12403
Protoss_Robotics_Support_Bay 1 11723
Protoss_Zealot 4 15438
Protoss_Reaver 2 15527
15527
