Protoss_Gateway 2 13934
Protoss_Assimilator 1 4526
Protoss_Cybernetics_Core 1 5914
Protoss_Zealot 2 11844
Protoss_Dragoon 6 15329
Protoss_Robotics_Facility 1 8682
Protoss_Observatory 1 9437
Protoss_Shuttle 1 10594
Protoss_Robotics_Support_Bay 1 10740
Protoss_Observer 2 14748
Protoss_Reaver 1 13707
Protoss_Nexus 1 16565
Singularity_Charge 1 13813
16565
