Protoss_Gateway 2 11873
Protoss_Assimilator 1 4763
Protoss_Cybernetics_Core 1 6342
Protoss_Dragoon 7 15350
Protoss_Robotics_Facility 1 8742
Protoss_Zealot 2 9301
Protoss_Shuttle 1 10152
Protoss_Robotics_Support_Bay 1 9616
Protoss_Reaver 1 11710
Protoss_Observatory 1 11445
Protoss_Observer 1 12712
15350
