Protoss_Gateway 2 6569
Protoss_Assimilator 1 4515
Protoss_Cybernetics_Core 1 5765
Protoss_Dragoon 8 15131
Protoss_Robotics_Facility 1 10465
Singularity_Charge 1 9733
Protoss_Zealot 6 14012
Protoss_Shuttle 1 12048
Protoss_Nexus 1 17386
17386
