Protoss_Gateway 3 15037
Protoss_Assimilator 1 4164
Protoss_Cybernetics_Core 1 5657
Protoss_Dragoon 10 15189
Protoss_Robotics_Facility 1 9955
Singularity_Charge 1 9391
Protoss_Observatory 1 10768
Protoss_Observer 4 15190
Protoss_Nexus 1 15277
15277
