Protoss_Nexus 2 16076
Protoss_Gateway 3 10703
Protoss_Assimilator 1 5815
Protoss_Cybernetics_Core 1 7455
Protoss_Dragoon 8 15044
Protoss_Robotics_Facility 1 12046
Protoss_Zealot 2 11439
Singularity_Charge 1 11131
Protoss_Shuttle 1 13526
Protoss_Robotics_Support_Bay 1 13263
Protoss_Reaver 1 15161
Protoss_Observatory 1 14966
16076
