Protoss_Gateway 3 13223
Protoss_Assimilator 1 4511
Protoss_Cybernetics_Core 1 5729
Protoss_Dragoon 13 15761
Protoss_Nexus 1 12962
Singularity_Charge 1 10480
Protoss_Robotics_Facility 1 12970
Protoss_Observatory 1 13943
Protoss_Observer 1 14973
15761
