Protoss_Gateway 3 15945
Protoss_Assimilator 1 4675
Protoss_Zealot 1 5417
Protoss_Cybernetics_Core 1 6892
Protoss_Dragoon 8 14422
Protoss_Nexus 2 16841
Singularity_Charge 1 10816
16841
