Protoss_Gateway 2 6942
Protoss_Assimilator 1 4293
Protoss_Cybernetics_Core 1 5695
Protoss_Dragoon 10 14905
Protoss_Zealot 3 11614
Singularity_Charge 1 9521
Protoss_Nexus 2 15703
Protoss_Robotics_Facility 1 15322
15703
