Protoss_Gateway 2 9249
Protoss_Assimilator 2 5158
Protoss_Cybernetics_Core 1 6813
Protoss_Dragoon 6 12227
Protoss_Citadel_of_Adun 1 11232
Singularity_Charge 1 10487
Protoss_Templar_Archives 1 12819
Protoss_Dark_Templar 4 15161
15161
