Protoss_Gateway 2 7858
Protoss_Assimilator 1 4826
Protoss_Zealot 2 6836
Protoss_Cybernetics_Core 1 6870
Protoss_Dragoon 11 15673
Singularity_Charge 1 10640
Protoss_Nexus 2 15025
Protoss_Robotics_Facility 1 15854
15854
