Protoss_Gateway 3 15675
Protoss_Assimilator 1 4195
Protoss_Cybernetics_Core 1 5750
Protoss_Dragoon 10 14890
Protoss_Robotics_Facility 1 10006
Singularity_Charge 1 9774
Protoss_Observatory 1 10699
Protoss_Observer 3 13630
Protoss_Nexus 2 16345
16345
