Protoss_Gateway 4 15151
Protoss_Assimilator 1 4428
Protoss_Cybernetics_Core 1 5750
Protoss_Dragoon 10 14612
Protoss_Nexus 1 12221
Singularity_Charge 1 9850
Protoss_Robotics_Facility 1 12371
Protoss_Observatory 1 13321
Protoss_Observer 1 14882
Protoss_Citadel_of_Adun 1 15500
15500
