Protoss_Gateway 3 13922
Protoss_Assimilator 1 4435
Protoss_Cybernetics_Core 1 6017
Protoss_Dragoon 11 15294
Protoss_Robotics_Facility 1 10324
Singularity_Charge 1 9877
Protoss_Observatory 1 11043
Protoss_Nexus 1 13783
Protoss_Observer 2 13255
Protoss_Shuttle 1 15134
Protoss_Robotics_Support_Bay 1 14529
15294
