Protoss_Gateway 2 9623
Protoss_Nexus 1 7954
Protoss_Assimilator 1 6260
Protoss_Cybernetics_Core 1 7976
Protoss_Zealot 9 15178
Protoss_Dragoon 7 15797
Protoss_Shield_Battery 1 10011
Singularity_Charge 1 14270
15797
