Protoss_Gateway 1 4190
Protoss_Assimilator 1 4275
Protoss_Cybernetics_Core 1 5829
Protoss_Dragoon 6 15320
Protoss_Robotics_Facility 1 8670
Protoss_Shuttle 1 10155
Protoss_Robotics_Support_Bay 1 9762
Protoss_Zealot 2 11581
Protoss_Reaver 2 13374
Gravitic_Drive 1 14068
15320
