Protoss_Gateway 2 6453
Protoss_Assimilator 1 4230
Protoss_Cybernetics_Core 1 5626
Protoss_Dragoon 7 13936
Protoss_Citadel_of_Adun 1 8920
Protoss_Zealot 1 9152
Protoss_Templar_Archives 1 10486
Singularity_Charge 1 9291
Protoss_Dark_Templar 5 15323
15323
