Protoss_Nexus 1 6903
Protoss_Gateway 2 8363
Protoss_Assimilator 2 12893
Protoss_Cybernetics_Core 1 7369
Protoss_Dragoon 8 13090
Protoss_Robotics_Facility 1 13113
Singularity_Charge 1 11966
Protoss_Stargate 1 14091
Protoss_Observatory 1 13908
Protoss_Fleet_Beacon 1 15554
15554
