Protoss_Gateway 4 16047
Protoss_Assimilator 1 4212
Protoss_Cybernetics_Core 1 5797
Protoss_Zealot 1 5497
Protoss_Dragoon 11 15698
Protoss_Robotics_Facility 1 10829
Singularity_Charge 1 9572
Protoss_Observatory 1 11562
Protoss_Nexus 2 15908
Protoss_Observer 2 13469
16047
