Protoss_Gateway 2 7788
Protoss_Assimilator 1 4401
Protoss_Cybernetics_Core 1 5724
Protoss_Dragoon 4 14032
Protoss_Citadel_of_Adun 1 9892
Protoss_Robotics_Facility 1 10915
Protoss_Templar_Archives 1 11461
Protoss_Shuttle 1 12485
Protoss_Dark_Templar 3 13766
Protoss_Nexus 1 15160
15160
