Protoss_Nexus 2 15871
Protoss_Gateway 3 10518
Protoss_Assimilator 2 14227
Protoss_Cybernetics_Core 1 7580
Protoss_Zealot 5 12908
Protoss_Dragoon 6 12047
Protoss_Robotics_Facility 1 12393
Singularity_Charge 1 11343
Protoss_Shuttle 1 14265
Protoss_Robotics_Support_Bay 1 13586
Protoss_Citadel_of_Adun 1 15437
Protoss_Reaver 1 16222
16222
