Protoss_Gateway 3 13728
Protoss_Assimilator 1 4234
Protoss_Cybernetics_Core 1 5692
Protoss_Zealot 1 5512
Protoss_Dragoon 8 15168
Singularity_Charge 1 9704
Protoss_Nexus 2 15944
Protoss_Robotics_Facility 1 12285
Protoss_Observatory 1 13096
Protoss_Observer 1 14358
15944
