Protoss_Gateway 3 14925
Protoss_Assimilator 1 4401
Protoss_Cybernetics_Core 1 5604
Protoss_Dragoon 9 14995
Protoss_Nexus 2 15059
Singularity_Charge 1 9350
Protoss_Robotics_Facility 1 14703
Protoss_Citadel_of_Adun 1 14859
15059
