Protoss_Gateway 3 11829
Protoss_Assimilator 1 4586
Protoss_Cybernetics_Core 1 6162
Protoss_Robotics_Facility 1 8239
Protoss_Dragoon 8 14992
Protoss_Observatory 1 9164
Protoss_Observer 3 12280
Singularity_Charge 1 11387
Protoss_Citadel_of_Adun 1 13912
Protoss_Templar_Archives 1 15716
Protoss_Shuttle 1 16028
16028
