Protoss_Nexus 2 15416
Protoss_Gateway 4 16024
Protoss_Assimilator 2 14322
Protoss_Zealot 2 8095
Protoss_Cybernetics_Core 1 8316
Protoss_Dragoon 13 15380
Singularity_Charge 1 12162
Protoss_Citadel_of_Adun 1 14493
16024
