Protoss_Gateway 2 6839
Protoss_Assimilator 1 4539
Protoss_Cybernetics_Core 1 5961
Protoss_Dragoon 10 15537
Singularity_Charge 1 9719
Protoss_Nexus 2 15017
Protoss_Robotics_Facility 1 14392
Protoss_Shuttle 1 15866
Protoss_Robotics_Support_Bay 1 15303
15866
