Protoss_Gateway 2 13325
Protoss_Assimilator 1 4372
Protoss_Cybernetics_Core 1 5759
Protoss_Zealot 4 14341
Protoss_Dragoon 7 15461
Protoss_Nexus 1 12227
Protoss_Robotics_Facility 1 11785
Singularity_Charge 1 10079
Protoss_Observatory 1 12554
Protoss_Observer 2 14449
15461
