Protoss_Nexus 1 7083
Protoss_Gateway 3 10946
Protoss_Assimilator 2 14538
Protoss_Cybernetics_Core 1 7843
Protoss_Zealot 5 14732
Protoss_Dragoon 8 14656
Protoss_Robotics_Facility 1 10726
Protoss_Shield_Battery 1 11379
Protoss_Shuttle 1 14440
Protoss_Robotics_Support_Bay 1 13918
Protoss_Reaver 1 15998
15998
