Protoss_Gateway 2 6387
Protoss_Assimilator 2 15042
Protoss_Cybernetics_Core 1 5628
Protoss_Dragoon 11 12998
Singularity_Charge 1 9755
Protoss_Citadel_of_Adun 2 14985
Protoss_Nexus 1 15325
15325
