Protoss_Gateway 3 16024
Protoss_Assimilator 1 4491
Protoss_Cybernetics_Core 1 5973
Protoss_Dragoon 8 15022
Singularity_Charge 1 10106
Protoss_Robotics_Facility 1 12329
Protoss_Nexus 1 14774
Protoss_Shuttle 1 13965
Protoss_Robotics_Support_Bay 1 13728
Protoss_Observatory 1 13794
Protoss_Zealot 2 14966
Protoss_Reaver 1 15834
16024
