Protoss_Gateway 4 15794
Protoss_Assimilator 1 4514
Protoss_Cybernetics_Core 1 5926
Protoss_Dragoon 10 14722
Protoss_Nexus 1 11989
Singularity_Charge 1 10033
Protoss_Robotics_Facility 1 12987
Protoss_Observatory 1 13952
Protoss_Observer 1 15090
15794
