Protoss_Assimilator 3 6500
Protoss_Gateway 2 9273
Protoss_Cybernetics_Core 1 6629
Protoss_Dragoon 10 15569
Singularity_Charge 1 10418
Protoss_Nexus 1 13495
Protoss_Robotics_Facility 1 13659
Protoss_Observatory 1 14387
15569
