Protoss_Gateway 5 15450
Protoss_Assimilator 1 4375
Protoss_Cybernetics_Core 1 5765
Protoss_Dragoon 10 13945
Protoss_Robotics_Facility 1 10178
Singularity_Charge 1 9770
Protoss_Observatory 1 10984
Protoss_Observer 2 12891
Protoss_Citadel_of_Adun 1 15204
Protoss_Zealot 2 14885
15450
