Protoss_Gateway 4 16040
Protoss_Assimilator 2 14610
Protoss_Cybernetics_Core 1 5802
Protoss_Dragoon 9 15190
Protoss_Nexus 2 15502
Singularity_Charge 1 9740
Protoss_Robotics_Facility 1 12241
Protoss_Observatory 1 13093
Protoss_Observer 2 15100
16040
