Protoss_Gateway 3 13992
Protoss_Assimilator 1 4176
Protoss_Cybernetics_Core 1 5568
Protoss_Dragoon 9 15253
Protoss_Zealot 2 10518
Protoss_Citadel_of_Adun 1 9857
Singularity_Charge 1 9408
Protoss_Templar_Archives 1 11326
Protoss_Dark_Templar 2 12789
Protoss_Nexus 1 14835
15253
