Protoss_Gateway 3 14256
Protoss_Assimilator 1 4337
Protoss_Cybernetics_Core 1 5734
Protoss_Dragoon 13 15461
Singularity_Charge 1 9521
Protoss_Robotics_Facility 1 12516
Protoss_Nexus 1 13888
Protoss_Observatory 1 13288
Protoss_Observer 2 15217
15461
