Protoss_Gateway 2 4918
Protoss_Zealot 14 12507
Protoss_Forge 1 6463
Protoss_Photon_Cannon 4 9010
Protoss_Assimilator 1 10975
Protoss_Cybernetics_Core 1 12585
Protoss_Dragoon 4 15402
15402
