Protoss_Gateway 1 4186
Protoss_Assimilator 1 4220
Protoss_Cybernetics_Core 1 5704
Protoss_Dragoon 7 15303
Protoss_Robotics_Facility 1 9892
Singularity_Charge 1 9419
Protoss_Shuttle 1 11309
Protoss_Observatory 1 10699
Protoss_Observer 2 13032
Protoss_Nexus 1 14854
15303
