Protoss_Gateway 2 9394
Protoss_Zealot 7 14865
Protoss_Assimilator 2 14933
Protoss_Cybernetics_Core 1 8013
Protoss_Dragoon 5 15095
Protoss_Nexus 1 15156
Singularity_Charge 1 13175
15156
