Protoss_Gateway 3 14370
Protoss_Assimilator 1 4316
Protoss_Cybernetics_Core 1 5721
Protoss_Dragoon 11 15607
Protoss_Nexus 2 16720
Singularity_Charge 1 9645
Protoss_Robotics_Facility 1 13908
Protoss_Observatory 1 14690
16720
