Protoss_Gateway 4 15472
Protoss_Assimilator 1 4527
Protoss_Cybernetics_Core 1 6009
Protoss_Dragoon 7 14413
Protoss_Nexus 1 11774
Singularity_Charge 1 9814
Protoss_Robotics_Facility 1 12314
Protoss_Zealot 5 15558
Protoss_Observatory 1 13264
Protoss_Citadel_of_Adun 1 14205
Protoss_Observer 2 15188
Protoss_Templar_Archives 1 15921
15921
