Protoss_Gateway 3 15876
Protoss_Assimilator 1 4461
Protoss_Cybernetics_Core 1 5947
Protoss_Dragoon 7 15014
Protoss_Robotics_Facility 1 11114
Singularity_Charge 1 9967
Protoss_Nexus 3 14971
Protoss_Observatory 1 12967
Protoss_Observer 2 15430
15876
