Protoss_Gateway 2 8058
Protoss_Assimilator 1 4212
Protoss_Cybernetics_Core 1 5648
Protoss_Dragoon 12 14505
Singularity_Charge 1 9353
Protoss_Robotics_Facility 1 13083
Protoss_Shuttle 1 15333
15333
