Protoss_Gateway 3 14879
Protoss_Assimilator 1 4485
Protoss_Cybernetics_Core 1 5705
Protoss_Dragoon 9 15496
Protoss_Nexus 2 15589
Protoss_Robotics_Facility 1 11202
Singularity_Charge 1 9865
Protoss_Observatory 1 12884
Protoss_Observer 2 14780
Protoss_Citadel_of_Adun 1 15908
15908
