Protoss_Gateway 3 11964
Protoss_Assimilator 1 4527
Protoss_Zealot 7 15580
Protoss_Cybernetics_Core 1 7250
Protoss_Dragoon 11 14688
Protoss_Robotics_Facility 1 11005
Singularity_Charge 1 10926
Protoss_Observatory 1 11729
Protoss_Observer 2 13853
Protoss_Shuttle 1 15479
15580
