Protoss_Gateway 4 14933
Protoss_Assimilator 1 4432
Protoss_Cybernetics_Core 1 5768
Protoss_Dragoon 11 15475
Singularity_Charge 1 9865
Protoss_Nexus 2 15592
Protoss_Robotics_Facility 1 14675
15592
