Protoss_Gateway 4 11055
Protoss_Assimilator 1 4619
Protoss_Cybernetics_Core 1 6067
Protoss_Dragoon 3 12263
Protoss_Citadel_of_Adun 1 7788
Protoss_Templar_Archives 1 9264
Protoss_Dark_Templar 4 13814
Protoss_Robotics_Facility 1 12139
Protoss_Shuttle 1 13884
13884
