Protoss_Gateway 4 14339
Protoss_Zealot 2 7346
Protoss_Nexus 2 14036
Protoss_Assimilator 2 12936
Protoss_Forge 1 8291
Protoss_Cybernetics_Core 1 9743
Protoss_Photon_Cannon 1 10008
Protoss_Dragoon 4 15563
Protoss_Citadel_of_Adun 1 11502
Protoss_Templar_Archives 1 13229
Protoss_Dark_Templar 2 14875
15563
