Protoss_Assimilator 1 3652
Protoss_Gateway 4 15449
Protoss_Cybernetics_Core 1 6270
Protoss_Dragoon 11 15768
Protoss_Robotics_Facility 1 8489
Protoss_Observatory 1 9664
Protoss_Observer 3 15061
Singularity_Charge 1 10780
Protoss_Nexus 1 15581
15768
