Protoss_Gateway 4 15450
Protoss_Assimilator 1 4268
Protoss_Cybernetics_Core 1 5693
Protoss_Dragoon 8 14107
Protoss_Nexus 2 14838
Singularity_Charge 1 9923
Protoss_Robotics_Facility 1 12614
Protoss_Observatory 1 13340
Protoss_Observer 1 15244
15450
