Protoss_Gateway 3 14613
Protoss_Assimilator 1 4234
Protoss_Cybernetics_Core 1 5707
Protoss_Dragoon 8 15314
Protoss_Nexus 2 14605
Singularity_Charge 1 9375
Protoss_Robotics_Facility 1 14934
15314
