Protoss_Gateway 3 13610
Protoss_Assimilator 1 4744
Protoss_Cybernetics_Core 1 6247
Protoss_Zealot 1 7091
Protoss_Dragoon 9 14998
Protoss_Robotics_Facility 1 10748
Singularity_Charge 1 10222
Protoss_Nexus 2 17156
Protoss_Observatory 1 11571
Protoss_Observer 1 12617
17156
