Protoss_Gateway 3 12124
Protoss_Assimilator 1 4469
Protoss_Cybernetics_Core 1 6233
Protoss_Dragoon 11 14669
Protoss_Nexus 1 11899
Protoss_Robotics_Facility 1 11287
Singularity_Charge 1 10040
Protoss_Observatory 1 13087
Protoss_Observer 2 14991
14991
