Protoss_Gateway 3 15615
Protoss_Assimilator 1 4234
Protoss_Cybernetics_Core 1 6080
Protoss_Dragoon 12 15645
Protoss_Robotics_Facility 1 9739
Protoss_Observatory 1 10485
Singularity_Charge 1 9903
Protoss_Observer 2 12412
Protoss_Nexus 1 14908
Protoss_Shuttle 1 15494
15645
