Protoss_Gateway 2 8458
Protoss_Zealot 3 13234
Protoss_Nexus 1 8057
Protoss_Cybernetics_Core 1 7451
Protoss_Assimilator 2 10930
Protoss_Dragoon 8 15039
Protoss_Robotics_Facility 1 13974
15039
