Protoss_Gateway 1 4103
Protoss_Assimilator 3 12034
Protoss_Zealot 6 10012
Protoss_Nexus 1 10423
Protoss_Forge 1 9248
Protoss_Photon_Cannon 1 10762
Protoss_Cybernetics_Core 1 12849
Protoss_Robotics_Facility 1 15008
Protoss_Dragoon 2 15674
15674
