Protoss_Gateway 3 15106
Protoss_Assimilator 1 4688
Protoss_Cybernetics_Core 1 5986
Protoss_Dragoon 10 15124
Protoss_Robotics_Facility 1 9000
Protoss_Observatory 1 9704
Protoss_Observer 2 11685
Protoss_Shuttle 1 15011
Protoss_Zealot 1 14871
15124
