Protoss_Gateway 3 6570
Protoss_Assimilator 1 4461
Protoss_Cybernetics_Core 1 5802
Protoss_Dragoon 8 15032
Protoss_Nexus 1 11759
Singularity_Charge 1 9477
Protoss_Robotics_Facility 1 12914
Protoss_Zealot 3 15495
Protoss_Observatory 1 13891
Protoss_Observer 1 15112
15495
