Protoss_Nexus 1 6949
Protoss_Gateway 3 11253
Protoss_Assimilator 1 5939
Protoss_Zealot 1 7129
Protoss_Cybernetics_Core 1 7709
Protoss_Dragoon 13 15739
Protoss_Robotics_Facility 1 13153
Protoss_Citadel_of_Adun 1 13144
Singularity_Charge 1 12323
15739
