Protoss_Gateway 4 13956
Protoss_Nexus 1 7626
Protoss_Assimilator 2 15289
Protoss_Cybernetics_Core 1 7234
Protoss_Zealot 1 7328
Protoss_Dragoon 9 15429
Protoss_Robotics_Facility 1 12565
Protoss_Observatory 1 13434
Protoss_Shuttle 1 14156
Singularity_Charge 1 12935
Protoss_Robotics_Support_Bay 1 14573
Protoss_Observer 1 14999
15429
