Protoss_Gateway 3 14619
Protoss_Assimilator 1 4452
Protoss_Cybernetics_Core 1 5786
Protoss_Dragoon 11 14831
Protoss_Citadel_of_Adun 1 9182
Protoss_Robotics_Facility 1 10192
Singularity_Charge 1 9821
Protoss_Observatory 1 11419
Protoss_Observer 3 14295
Protoss_Nexus 2 16133
16133
