Protoss_Gateway 2 14102
Protoss_Zealot 6 9092
Protoss_Assimilator 1 6541
Protoss_Cybernetics_Core 1 8655
Protoss_Citadel_of_Adun 1 10362
Protoss_Dragoon 3 12285
Protoss_Templar_Archives 1 12053
Protoss_Nexus 1 14851
Protoss_Dark_Templar 2 14486
Protoss_Stargate 1 15280
15280
