Protoss_Nexus 2 15101
Protoss_Gateway 5 15466
Protoss_Assimilator 1 6285
Protoss_Cybernetics_Core 1 8222
Protoss_Dragoon 7 13866
Protoss_Robotics_Facility 1 12109
Singularity_Charge 1 12309
Protoss_Observatory 1 13152
Protoss_Shuttle 1 14667
Protoss_Forge 1 15115
Protoss_Citadel_of_Adun 1 15760
15760
