Protoss_Gateway 2 10580
Protoss_Assimilator 1 4448
Protoss_Cybernetics_Core 1 5853
Protoss_Dragoon 4 15789
Protoss_Robotics_Facility 1 9982
Singularity_Charge 1 9973
Protoss_Nexus 2 17197
Protoss_Observatory 1 10857
Protoss_Shuttle 1 12541
Protoss_Robotics_Support_Bay 1 12427
Protoss_Reaver 1 14233
Protoss_Zealot 2 14224
Protoss_Observer 1 15058
17197
