Protoss_Gateway 3 10463
Protoss_Assimilator 1 4511
Protoss_Cybernetics_Core 1 5938
Protoss_Dragoon 13 15358
Protoss_Robotics_Facility 1 10011
Singularity_Charge 1 10005
Protoss_Observatory 1 10814
Protoss_Observer 1 12810
Protoss_Nexus 1 16386
16386
