Protoss_Gateway 3 12746
Protoss_Zealot 1 5253
Protoss_Assimilator 2 14285
Protoss_Cybernetics_Core 1 6778
Protoss_Dragoon 9 15218
Protoss_Nexus 1 12827
Singularity_Charge 1 11598
Protoss_Robotics_Facility 1 14025
15218
