Protoss_Gateway 4 14679
Protoss_Assimilator 1 4615
Protoss_Cybernetics_Core 1 6110
Protoss_Dragoon 4 13010
Protoss_Robotics_Facility 1 9014
Protoss_Observatory 1 9931
Protoss_Observer 3 13810
Protoss_Nexus 1 13303
Singularity_Charge 1 12419
Protoss_Zealot 3 14827
Protoss_Shuttle 1 15168
15168
