Protoss_Gateway 3 13507
Protoss_Assimilator 2 14440
Protoss_Cybernetics_Core 1 5606
Protoss_Dragoon 8 15607
Protoss_Robotics_Facility 1 9721
Protoss_Shuttle 1 11235
Singularity_Charge 1 9888
Protoss_Robotics_Support_Bay 1 10715
Protoss_Nexus 1 13448
Protoss_Reaver 1 12793
Protoss_Observatory 1 13084
Protoss_Observer 1 14186
15607
