Protoss_Gateway 2 10483
Protoss_Assimilator 2 12130
Protoss_Cybernetics_Core 1 5628
Protoss_Dragoon 6 15619
Protoss_Nexus 1 11124
Protoss_Robotics_Facility 1 11498
Singularity_Charge 1 9745
Protoss_Shuttle 1 12956
Protoss_Robotics_Support_Bay 1 12688
Protoss_Zealot 3 14587
Protoss_Reaver 1 14748
Protoss_Observatory 1 14810
15619
