Protoss_Gateway 2 6728
Protoss_Assimilator 1 4574
Protoss_Cybernetics_Core 1 5932
Protoss_Dragoon 9 13866
Protoss_Zealot 2 10510
Singularity_Charge 1 10172
Protoss_Robotics_Facility 1 13222
Protoss_Shuttle 1 14721
Protoss_Robotics_Support_Bay 1 14167
14721
