Protoss_Gateway 4 15921
Protoss_Assimilator 1 4489
Protoss_Cybernetics_Core 1 5824
Protoss_Dragoon 7 13526
Protoss_Robotics_Facility 1 10498
Singularity_Charge 1 9540
Protoss_Observatory 1 11191
Protoss_Nexus 2 16623
Protoss_Observer 2 13170
16623
