Protoss_Gateway 2 6885
Protoss_Assimilator 1 4208
Protoss_Cybernetics_Core 1 5566
Protoss_Dragoon 11 13983
Protoss_Zealot 2 10071
Singularity_Charge 1 9806
Protoss_Robotics_Facility 1 13145
Protoss_Shuttle 1 14601
Protoss_Robotics_Support_Bay 1 14417
Protoss_Observatory 1 14883
Protoss_Reaver 1 16159
16159
