Protoss_Gateway 3 11537
Protoss_Assimilator 1 4242
Protoss_Cybernetics_Core 1 5690
Protoss_Dragoon 11 15001
Protoss_Nexus 1 11528
Singularity_Charge 1 9783
Protoss_Robotics_Facility 1 13309
Protoss_Zealot 1 14783
Protoss_Shuttle 1 15301
Protoss_Observatory 1 14615
15301
