Protoss_Gateway 2 10277
Protoss_Assimilator 1 4479
Protoss_Cybernetics_Core 1 5882
Protoss_Dragoon 10 15019
Protoss_Robotics_Facility 1 9914
Singularity_Charge 1 9844
Protoss_Observatory 1 10696
Protoss_Observer 2 14622
Protoss_Nexus 1 14636
15019
