Protoss_Gateway 3 11171
Protoss_Assimilator 1 4511
Protoss_Cybernetics_Core 1 5888
Protoss_Dragoon 10 15698
Protoss_Nexus 1 11791
Singularity_Charge 1 10079
Protoss_Zealot 3 14121
Protoss_Robotics_Facility 1 13980
Protoss_Observatory 1 14764
15698
