Protoss_Gateway 4 15883
Protoss_Assimilator 1 4491
Protoss_Cybernetics_Core 1 6004
Protoss_Dragoon 8 13813
Protoss_Robotics_Facility 1 9755
Protoss_Observatory 1 10494
Singularity_Charge 1 9818
Protoss_Observer 5 15225
Protoss_Nexus 2 16260
Protoss_Citadel_of_Adun 1 16000
16260
