Protoss_Gateway 2 6470
Protoss_Assimilator 1 4245
Protoss_Cybernetics_Core 1 5742
Protoss_Dragoon 10 14814
Singularity_Charge 1 9616
Protoss_Zealot 2 12023
Protoss_Nexus 1 13694
Protoss_Robotics_Facility 1 13535
Protoss_Shuttle 1 15271
Protoss_Robotics_Support_Bay 1 14883
15271
