Protoss_Gateway 5 15652
Protoss_Assimilator 1 4546
Protoss_Cybernetics_Core 1 5862
Protoss_Dragoon 8 15680
Protoss_Robotics_Facility 1 10217
Singularity_Charge 1 10026
Protoss_Observatory 1 10948
Protoss_Observer 3 13758
Protoss_Nexus 2 15982
15982
