Protoss_Gateway 2 6324
Protoss_Assimilator 1 4420
Protoss_Cybernetics_Core 1 5628
Protoss_Dragoon 5 13746
Protoss_Robotics_Facility 1 10456
Protoss_Zealot 5 11938
Singularity_Charge 1 9438
Protoss_Shuttle 1 11856
Protoss_Robotics_Support_Bay 1 11558
Protoss_Reaver 1 13519
Protoss_Nexus 1 16525
16525
