Protoss_Nexus 1 6737
Protoss_Gateway 4 15185
Protoss_Assimilator 2 12917
Protoss_Cybernetics_Core 1 7430
Protoss_Zealot 5 14572
Protoss_Dragoon 10 13667
Protoss_Robotics_Facility 1 12339
Singularity_Charge 1 11454
Protoss_Observatory 1 13703
15185
