Protoss_Gateway 2 7887
Protoss_Assimilator 1 4234
Protoss_Cybernetics_Core 1 5780
Protoss_Dragoon 8 13595
Protoss_Robotics_Facility 1 10895
Singularity_Charge 1 9660
Protoss_Shuttle 1 12304
Protoss_Robotics_Support_Bay 1 11884
Protoss_Reaver 2 16112
Protoss_Zealot 2 14922
16112
