Protoss_Gateway 4 14666
Protoss_Assimilator 1 4561
Protoss_Cybernetics_Core 1 5971
Protoss_Dragoon 8 13310
Protoss_Nexus 1 11510
Singularity_Charge 1 9882
Protoss_Robotics_Facility 1 12780
Protoss_Shuttle 1 14247
Protoss_Robotics_Support_Bay 1 14006
Protoss_Reaver 1 15805
15805
