Protoss_Assimilator 2 15453
Protoss_Gateway 2 10236
Protoss_Cybernetics_Core 1 6289
Protoss_Dragoon 5 14981
Protoss_Robotics_Facility 1 9809
Protoss_Citadel_of_Adun 1 9549
Protoss_Templar_Archives 1 10995
Protoss_Shuttle 1 11490
Protoss_Dark_Templar 3 13315
Protoss_Observatory 1 12616
Protoss_Nexus 1 15587
Protoss_Observer 1 13791
15587
