Protoss_Gateway 2 11793
Protoss_Assimilator 1 4220
Protoss_Cybernetics_Core 1 5777
Protoss_Dragoon 6 13725
Protoss_Nexus 2 16934
Protoss_Robotics_Facility 1 11509
Singularity_Charge 1 9874
Protoss_Shuttle 1 12904
Protoss_Observatory 1 12237
Protoss_Robotics_Support_Bay 1 12448
Protoss_Observer 1 13747
Protoss_Reaver 1 15411
Protoss_Zealot 2 15345
16934
