Protoss_Gateway 2 13511
Protoss_Assimilator 1 4379
Protoss_Cybernetics_Core 1 6002
Protoss_Dragoon 7 15190
Protoss_Robotics_Facility 1 8730
Protoss_Shuttle 1 10152
Protoss_Observatory 1 10179
Protoss_Robotics_Support_Bay 1 10858
Protoss_Observer 2 15318
Protoss_Reaver 2 14494
Singularity_Charge 1 14482
15318
