Protoss_Gateway 5 15997
Protoss_Assimilator 2 13985
Protoss_Cybernetics_Core 1 5610
Protoss_Dragoon 4 10113
Protoss_Citadel_of_Adun 1 9050
Protoss_Templar_Archives 1 10542
Singularity_Charge 1 9408
Protoss_Nexus 2 15239
Protoss_Dark_Templar 2 12914
Protoss_Robotics_Facility 1 13017
Protoss_Observatory 1 14318
15997
