Protoss_Gateway 5 15387
Protoss_Assimilator 1 4337
Protoss_Cybernetics_Core 1 5919
Protoss_Dragoon 7 15644
Protoss_Zealot 1 10849
Singularity_Charge 1 9916
Protoss_Nexus 2 15063
Protoss_Robotics_Facility 1 14539
15644
