Protoss_Gateway 2 6403
Protoss_Assimilator 1 4365
Protoss_Cybernetics_Core 1 5551
Protoss_Dragoon 8 15388
Protoss_Nexus 1 12005
Singularity_Charge 1 9458
Protoss_Robotics_Facility 1 11755
Protoss_Shuttle 1 13293
Protoss_Robotics_Support_Bay 1 12698
Protoss_Reaver 1 15012
Protoss_Observatory 1 15298
15388
