Protoss_Gateway 2 10085
Protoss_Assimilator 1 4232
Protoss_Cybernetics_Core 1 5870
Protoss_Dragoon 8 12566
Protoss_Robotics_Facility 1 9600
Protoss_Observatory 1 10342
Singularity_Charge 1 9789
Protoss_Observer 1 11376
Protoss_Nexus 1 14662
Protoss_Shuttle 1 13618
Protoss_Robotics_Support_Bay 1 13506
Protoss_Reaver 1 15401
Protoss_Zealot 2 15078
15401
