Protoss_Gateway 4 15391
Protoss_Assimilator 1 4173
Protoss_Cybernetics_Core 1 5639
Protoss_Dragoon 11 15598
Singularity_Charge 1 9900
Protoss_Nexus 1 13268
Protoss_Robotics_Facility 1 13018
Protoss_Observatory 1 13719
Protoss_Observer 1 14736
15598
