Protoss_Gateway 4 15387
Protoss_Assimilator 1 4182
Protoss_Cybernetics_Core 1 5701
Protoss_Zealot 1 5595
Protoss_Dragoon 9 15610
Protoss_Robotics_Facility 1 10342
Singularity_Charge 1 10087
Protoss_Observatory 1 11110
Protoss_Nexus 2 17412
Protoss_Observer 2 13507
17412
