Protoss_Gateway 3 12029
Protoss_Zealot 3 6312
Protoss_Assimilator 1 6703
Protoss_Nexus 2 16414
Protoss_Cybernetics_Core 1 9532
Protoss_Dragoon 10 15168
Singularity_Charge 1 13345
16414
