Protoss_Gateway 2 8124
Protoss_Zealot 3 7185
Protoss_Assimilator 1 6166
Protoss_Cybernetics_Core 1 7237
Protoss_Dragoon 12 15595
Singularity_Charge 1 12209
Protoss_Nexus 1 16863
16863
