Protoss_Assimilator 2 9877
Protoss_Gateway 4 15475
Protoss_Zealot 3 12216
Protoss_Forge 1 6992
Protoss_Photon_Cannon 5 15789
Protoss_Nexus 2 12877
Protoss_Cybernetics_Core 1 12069
Protoss_Citadel_of_Adun 1 13684
Protoss_Dragoon 1 13506
Protoss_Templar_Archives 1 15636
15789
