Protoss_Gateway 2 9557
Protoss_Assimilator 2 14654
Protoss_Cybernetics_Core 1 5676
Protoss_Dragoon 9 15592
Protoss_Citadel_of_Adun 1 8724
Protoss_Templar_Archives 1 10201
Singularity_Charge 1 9628
Protoss_Dark_Templar 2 11422
Protoss_Nexus 1 13557
Protoss_Robotics_Facility 1 15365
15592
