Protoss_Gateway 4 15690
Protoss_Assimilator 2 14819
Protoss_Cybernetics_Core 1 5682
Protoss_Dragoon 10 14191
Protoss_Nexus 1 11457
Singularity_Charge 1 9347
Protoss_Robotics_Facility 1 11540
Protoss_Observatory 1 12253
Protoss_Observer 1 13267
15690
