Protoss_Gateway 2 15083
Protoss_Assimilator 2 13316
Protoss_Cybernetics_Core 1 5724
Protoss_Dragoon 5 12707
Protoss_Nexus 2 17427
Protoss_Robotics_Facility 1 10857
Singularity_Charge 1 9938
Protoss_Shuttle 1 12541
Protoss_Robotics_Support_Bay 1 11887
Protoss_Reaver 1 14447
Protoss_Observatory 1 13869
Protoss_Zealot 1 14672
Protoss_Observer 1 15272
17427
