Protoss_Gateway 2 8443
Protoss_Assimilator 1 4195
Protoss_Cybernetics_Core 1 5705
Protoss_Dragoon 9 13951
Protoss_Robotics_Facility 1 10340
Singularity_Charge 1 9391
Protoss_Shuttle 1 11794
Protoss_Robotics_Support_Bay 1 11153
Protoss_Observatory 1 12415
Protoss_Reaver 1 13625
Protoss_Nexus 1 16338
Protoss_Observer 1 14827
16338
