Protoss_Gateway 2 7454
Protoss_Assimilator 1 5069
Protoss_Zealot 5 14882
Protoss_Cybernetics_Core 1 6949
Protoss_Dragoon 10 13670
Singularity_Charge 1 10948
Protoss_Nexus 1 15892
Protoss_Citadel_of_Adun 1 15261
15892
