Protoss_Nexus 2 16363
Protoss_Gateway 2 8499
Protoss_Assimilator 1 6097
Protoss_Cybernetics_Core 1 7612
Protoss_Zealot 5 14557
Protoss_Dragoon 8 15759
Protoss_Robotics_Facility 1 13920
Singularity_Charge 1 13134
Protoss_Observatory 1 14909
16363
