Protoss_Nexus 1 6725
Protoss_Gateway 5 13821
Protoss_Assimilator 1 5996
Protoss_Cybernetics_Core 1 7419
Protoss_Dragoon 16 15809
Protoss_Robotics_Facility 1 12338
Protoss_Zealot 2 14279
Singularity_Charge 1 11879
15809
