Protoss_Assimilator 5 12593
Protoss_Gateway 3 15860
Protoss_Cybernetics_Core 1 6596
Protoss_Dragoon 9 15016
Protoss_Nexus 1 12251
Singularity_Charge 1 10720
Protoss_Robotics_Facility 1 13068
Protoss_Observatory 1 13872
Protoss_Citadel_of_Adun 1 14674
Protoss_Observer 1 14935
15860
