Protoss_Gateway 3 12359
Protoss_Assimilator 2 14591
Protoss_Cybernetics_Core 1 5607
Protoss_Dragoon 12 15391
Protoss_Nexus 1 11273
Singularity_Charge 1 9508
Protoss_Robotics_Facility 1 12036
Protoss_Observatory 1 12812
Protoss_Observer 2 14710
Protoss_Citadel_of_Adun 1 14970
15391
