Protoss_Gateway 2 7325
Protoss_Assimilator 1 4564
Protoss_Cybernetics_Core 1 5889
Protoss_Dragoon 7 15408
Protoss_Robotics_Facility 1 10855
Singularity_Charge 1 9795
Protoss_Nexus 1 12977
Protoss_Shuttle 1 12251
Protoss_Robotics_Support_Bay 1 11785
Protoss_Reaver 1 14535
Protoss_Zealot 2 14010
Protoss_Observatory 1 13891
Protoss_Observer 1 15359
15408
