Protoss_Nexus 2 14450
Protoss_Gateway 2 8443
Protoss_Assimilator 2 14038
Protoss_Cybernetics_Core 1 7621
Protoss_Dragoon 9 14770
Protoss_Robotics_Facility 1 12737
Singularity_Charge 1 11478
Protoss_Citadel_of_Adun 1 14383
Protoss_Observatory 1 13684
14770
