Protoss_Gateway 2 10106
Protoss_Assimilator 2 14076
Protoss_Cybernetics_Core 1 5742
Protoss_Zealot 3 13551
Protoss_Citadel_of_Adun 2 8753
Protoss_Dragoon 4 14791
Protoss_Templar_Archives 1 10379
Singularity_Charge 1 9836
Protoss_Dark_Templar 2 11829
Protoss_Nexus 1 14217
Protoss_Stargate 1 13750
Protoss_Arbiter_Tribunal 1 15482
15482
