Protoss_Nexus 2 16679
Protoss_Gateway 2 8566
Protoss_Assimilator 1 5828
Protoss_Cybernetics_Core 1 7401
Protoss_Zealot 2 8347
Protoss_Dragoon 9 15475
Singularity_Charge 1 12165
Protoss_Robotics_Facility 1 14307
Protoss_Observatory 1 15162
16679
