Protoss_Gateway 2 9882
Protoss_Assimilator 1 4144
Protoss_Cybernetics_Core 1 5557
Protoss_Dragoon 10 15294
Protoss_Robotics_Facility 1 9547
Singularity_Charge 1 9525
Protoss_Observatory 1 10288
Protoss_Nexus 2 15458
Protoss_Observer 3 15137
15458
