Protoss_Gateway 4 14799
Protoss_Assimilator 1 4220
Protoss_Cybernetics_Core 1 5607
Protoss_Zealot 2 9593
Protoss_Dragoon 6 15142
Protoss_Robotics_Facility 1 7750
Protoss_Shuttle 1 9213
Protoss_Robotics_Support_Bay 1 8845
Protoss_Reaver 1 10829
Protoss_Nexus 1 14073
Protoss_Observatory 1 12124
Protoss_Observer 1 14525
15142
