Protoss_Gateway 2 11149
Protoss_Assimilator 1 4227
Protoss_Cybernetics_Core 1 5895
Protoss_Zealot 1 5680
Protoss_Dragoon 9 14972
Protoss_Nexus 1 12368
Singularity_Charge 1 9771
Protoss_Robotics_Facility 1 13241
Protoss_Observatory 1 14232
Protoss_Shuttle 1 15362
Protoss_Robotics_Support_Bay 1 15189
15362
