Protoss_Nexus 1 6716
Protoss_Gateway 4 14505
Protoss_Assimilator 2 12112
Protoss_Cybernetics_Core 1 7351
Protoss_Zealot 1 7562
Protoss_Dragoon 12 14820
Protoss_Robotics_Facility 1 13804
Singularity_Charge 1 11981
Protoss_Observatory 1 14599
14820
