Protoss_Gateway 4 15735
Protoss_Assimilator 1 4420
Protoss_Cybernetics_Core 1 5838
Protoss_Dragoon 9 14735
Singularity_Charge 1 9841
Protoss_Nexus 1 12900
Protoss_Robotics_Facility 1 12764
Protoss_Observatory 1 13544
Protoss_Observer 2 15453
15735
