Protoss_Gateway 3 10755
Protoss_Assimilator 1 4331
Protoss_Cybernetics_Core 1 5727
Protoss_Dragoon 9 13681
Protoss_Nexus 1 11121
Protoss_Robotics_Facility 1 10504
Singularity_Charge 1 9739
Protoss_Observatory 1 11466
Protoss_Observer 2 13747
Protoss_Zealot 3 14543
Protoss_Shuttle 1 15263
15263
