Protoss_Gateway 4 15437
Protoss_Assimilator 1 4404
Protoss_Zealot 2 6444
Protoss_Cybernetics_Core 1 6661
Protoss_Dragoon 11 15513
Protoss_Nexus 1 12495
Protoss_Robotics_Facility 1 12010
Singularity_Charge 1 10763
Protoss_Observatory 1 12742
Protoss_Observer 2 15491
15513
