Protoss_Gateway 2 12829
Protoss_Assimilator 1 4592
Protoss_Cybernetics_Core 1 5930
Protoss_Zealot 1 5715
Protoss_Dragoon 9 15505
Protoss_Robotics_Facility 1 9976
Protoss_Observatory 1 10667
Singularity_Charge 1 10052
Protoss_Nexus 1 13451
Protoss_Observer 2 12965
Protoss_Robotics_Support_Bay 1 12925
Protoss_Shuttle 1 14630
15505
