Protoss_Gateway 2 12740
Protoss_Assimilator 1 4173
Protoss_Cybernetics_Core 1 5626
Protoss_Zealot 1 6198
Protoss_Robotics_Facility 1 8146
Protoss_Dragoon 6 15821
Protoss_Shuttle 2 15389
Protoss_Robotics_Support_Bay 1 8912
Protoss_Reaver 1 11254
Protoss_Observatory 1 12777
Protoss_Nexus 1 15463
Gravitic_Drive 1 12757
Protoss_Observer 1 13799
Singularity_Charge 1 13746
15821
