Protoss_Gateway 3 9620
Protoss_Assimilator 1 4458
Protoss_Cybernetics_Core 1 6077
Protoss_Dragoon 13 14752
Singularity_Charge 1 9991
Protoss_Zealot 3 15169
Protoss_Citadel_of_Adun 1 14645
15169
