Protoss_Gateway 3 15605
Protoss_Assimilator 1 4277
Protoss_Zealot 2 6374
Protoss_Cybernetics_Core 1 6503
Protoss_Dragoon 8 15619
Protoss_Robotics_Facility 1 10946
Singularity_Charge 1 10635
Protoss_Nexus 1 13514
Protoss_Observatory 1 11638
Protoss_Observer 2 14107
Protoss_Citadel_of_Adun 1 13234
Protoss_Templar_Archives 1 15526
15619
