Protoss_Gateway 4 14974
Protoss_Assimilator 2 12702
Protoss_Cybernetics_Core 1 5557
Protoss_Dragoon 8 14044
Protoss_Nexus 2 14551
Singularity_Charge 1 9514
Protoss_Robotics_Facility 1 13857
Protoss_Citadel_of_Adun 1 14030
Protoss_Observatory 1 14571
Protoss_Observer 1 15582
15582
