Protoss_Gateway 1 4180
Protoss_Assimilator 1 4395
Protoss_Cybernetics_Core 1 5793
Protoss_Dragoon 6 14135
Protoss_Nexus 2 14190
Singularity_Charge 1 9666
Protoss_Robotics_Facility 1 11855
Protoss_Shuttle 1 13755
Protoss_Robotics_Support_Bay 1 13990
Protoss_Zealot 1 14996
Protoss_Reaver 1 15752
Protoss_Observatory 1 15199
15752
