Protoss_Gateway 4 14910
Protoss_Assimilator 1 4296
Protoss_Zealot 1 5241
Protoss_Nexus 2 14462
Protoss_Cybernetics_Core 1 7644
Protoss_Dragoon 11 15824
Singularity_Charge 1 11311
Protoss_Robotics_Facility 1 14165
Protoss_Forge 1 15547
15824
