Protoss_Gateway 4 14297
Protoss_Assimilator 2 14967
Protoss_Zealot 2 6488
Protoss_Cybernetics_Core 1 6520
Protoss_Dragoon 8 14662
Protoss_Robotics_Facility 1 10260
Protoss_Observatory 1 10997
Singularity_Charge 1 10760
Protoss_Observer 3 15371
Protoss_Nexus 1 14010
15371
