Protoss_Gateway 2 5371
Protoss_Zealot 11 13381
Protoss_Forge 1 8042
Protoss_Assimilator 1 9964
Protoss_Photon_Cannon 4 13696
Protoss_Cybernetics_Core 1 13540
Protoss_Dragoon 2 14829
14829
