Protoss_Gateway 2 13234
Protoss_Zealot 5 12488
Protoss_Assimilator 1 5257
Protoss_Cybernetics_Core 1 6876
Protoss_Dragoon 6 15458
Protoss_Robotics_Facility 1 9723
Protoss_Shuttle 1 11168
Protoss_Robotics_Support_Bay 1 10913
Protoss_Reaver 1 12779
Protoss_Observatory 1 12620
Singularity_Charge 1 12440
Protoss_Observer 1 13638
Protoss_Nexus 1 16591
16591
