Protoss_Nexus 1 6775
Protoss_Gateway 4 13356
Protoss_Assimilator 2 10293
Protoss_Cybernetics_Core 1 7425
Protoss_Dragoon 12 14752
Protoss_Robotics_Facility 1 12633
Singularity_Charge 1 11363
Protoss_Observatory 1 13476
Protoss_Observer 2 15509
15509
