Protoss_Nexus 2 17283
Protoss_Gateway 5 14357
Protoss_Assimilator 2 10403
Protoss_Cybernetics_Core 1 7476
Protoss_Zealot 4 14232
Protoss_Dragoon 5 12225
Protoss_Robotics_Facility 1 11009
Protoss_Shuttle 1 12672
Singularity_Charge 1 11521
Protoss_Observatory 2 14537
Protoss_Observer 1 15570
17283
