Protoss_Gateway 2 12728
Protoss_Assimilator 2 14881
Protoss_Cybernetics_Core 1 5606
Protoss_Dragoon 4 12194
Protoss_Nexus 2 16017
Protoss_Robotics_Facility 1 11010
Singularity_Charge 1 9505
Protoss_Citadel_of_Adun 1 11373
Protoss_Observatory 1 11836
Protoss_Templar_Archives 1 13375
Protoss_Observer 1 13290
Protoss_Shuttle 1 14045
Protoss_Dark_Templar 2 14653
16017
