Protoss_Gateway 2 10012
Protoss_Zealot 7 10978
Protoss_Forge 1 5824
Protoss_Photon_Cannon 3 8627
Protoss_Assimilator 1 8566
Protoss_Cybernetics_Core 1 10972
Protoss_Dragoon 4 14202
Protoss_Citadel_of_Adun 1 14525
14525
