Protoss_Gateway 2 13084
Protoss_Assimilator 2 13447
Protoss_Cybernetics_Core 1 5805
Protoss_Dragoon 10 15824
Protoss_Robotics_Facility 1 9873
Singularity_Charge 1 9894
Protoss_Nexus 1 13178
Protoss_Observatory 1 11158
Protoss_Observer 3 14373
Protoss_Citadel_of_Adun 1 13687
15824
