Protoss_Gateway 2 11682
Protoss_Assimilator 2 14737
Protoss_Cybernetics_Core 1 5554
Protoss_Zealot 2 13012
Protoss_Dragoon 8 15745
Protoss_Nexus 1 11569
Protoss_Robotics_Facility 1 11612
Singularity_Charge 1 9830
Protoss_Shuttle 1 13012
Protoss_Robotics_Support_Bay 1 13073
Protoss_Observatory 1 13772
Protoss_Reaver 1 14813
Protoss_Citadel_of_Adun 1 15343
15745
