Protoss_Gateway 1 4103
Protoss_Assimilator 1 4311
Protoss_Cybernetics_Core 1 5611
Protoss_Zealot 4 14566
Protoss_Dragoon 6 12824
Protoss_Robotics_Facility 1 10037
Singularity_Charge 1 9935
Protoss_Shuttle 1 11443
Protoss_Robotics_Support_Bay 1 10790
Protoss_Reaver 2 14541
Protoss_Observatory 1 14085
Protoss_Nexus 1 16950
Protoss_Observer 1 15365
16950
