Protoss_Nexus 2 16536
Protoss_Gateway 2 7747
Protoss_Assimilator 1 5862
Protoss_Cybernetics_Core 1 7521
Protoss_Zealot 1 7755
Protoss_Dragoon 8 13819
Protoss_Robotics_Facility 1 13658
Singularity_Charge 1 12596
Protoss_Shuttle 1 15672
16536
