Protoss_Gateway 4 15994
Protoss_Assimilator 2 13641
Protoss_Cybernetics_Core 1 5709
Protoss_Dragoon 9 15364
Protoss_Robotics_Facility 1 10233
Protoss_Nexus 1 12456
Singularity_Charge 1 9701
Protoss_Observatory 1 11110
Protoss_Observer 3 13916
Protoss_Citadel_of_Adun 1 12814
Protoss_Templar_Archives 1 15134
15994
