Protoss_Gateway 3 14285
Protoss_Assimilator 1 4470
Protoss_Cybernetics_Core 1 5854
Protoss_Nexus 1 10617
Protoss_Dragoon 8 13801
Singularity_Charge 1 9546
Protoss_Robotics_Facility 1 13399
Protoss_Zealot 2 14982
Protoss_Shuttle 1 15476
Protoss_Observatory 1 14878
15476
