Protoss_Gateway 2 12497
Protoss_Assimilator 1 4132
Protoss_Zealot 3 6801
Protoss_Cybernetics_Core 1 7043
Protoss_Dragoon 9 15300
Protoss_Nexus 1 11847
Protoss_Robotics_Facility 1 11948
Singularity_Charge 1 10731
Protoss_Shuttle 1 14575
Protoss_Robotics_Support_Bay 1 14315
Protoss_Reaver 1 16133
Protoss_Observatory 1 15338
16133
