Protoss_Gateway 2 14625
Protoss_Assimilator 1 4425
Protoss_Cybernetics_Core 1 5736
Protoss_Dragoon 6 15282
Protoss_Robotics_Facility 1 9835
Protoss_Shuttle 1 11285
Singularity_Charge 1 9868
Protoss_Robotics_Support_Bay 1 11122
Protoss_Nexus 1 13811
Protoss_Reaver 1 13016
Protoss_Observatory 1 12695
Protoss_Observer 2 15146
15282
