Protoss_Gateway 2 12598
Protoss_Assimilator 2 12252
Protoss_Cybernetics_Core 1 5575
Protoss_Dragoon 5 14577
Protoss_Citadel_of_Adun 1 8809
Protoss_Templar_Archives 1 10327
Protoss_Nexus 1 12467
Protoss_Dark_Templar 1 11527
Protoss_Stargate 2 14994
Singularity_Charge 1 11249
Protoss_Fleet_Beacon 1 13951
Protoss_Carrier 1 17653
17653
