Protoss_Gateway 3 12523
Protoss_Assimilator 1 4182
Protoss_Cybernetics_Core 1 5630
Protoss_Zealot 1 5557
Protoss_Dragoon 8 13731
Protoss_Nexus 2 16515
Singularity_Charge 1 9581
Protoss_Robotics_Facility 1 12152
Protoss_Observatory 1 13342
Protoss_Observer 2 15272
16515
