Protoss_Gateway 3 15880
Protoss_Assimilator 1 4141
Protoss_Cybernetics_Core 1 5683
Protoss_Zealot 1 5464
Protoss_Dragoon 10 15794
Protoss_Robotics_Facility 1 9496
Protoss_Observatory 1 10185
Singularity_Charge 1 9839
Protoss_Nexus 1 13009
Protoss_Observer 2 12166
Protoss_Shuttle 1 13524
Protoss_Robotics_Support_Bay 1 13539
Protoss_Reaver 1 15460
15880
