Protoss_Gateway 3 13530
Protoss_Assimilator 2 12566
Protoss_Cybernetics_Core 1 5688
Protoss_Nexus 1 10265
Protoss_Dragoon 9 15048
Protoss_Robotics_Facility 1 10342
Singularity_Charge 1 9420
Protoss_Observatory 1 11409
Protoss_Observer 3 15438
Protoss_Citadel_of_Adun 1 14430
Protoss_Zealot 1 15412
15438
