Protoss_Gateway 2 13010
Protoss_Assimilator 1 4318
Protoss_Cybernetics_Core 1 5584
Protoss_Zealot 1 5537
Protoss_Dragoon 8 14351
Protoss_Robotics_Facility 1 9797
Singularity_Charge 1 9730
Protoss_Observatory 1 10554
Protoss_Nexus 2 17095
Protoss_Observer 5 15307
17095
