Protoss_Gateway 2 14279
Protoss_Assimilator 2 15162
Protoss_Cybernetics_Core 1 5553
Protoss_Zealot 1 5587
Protoss_Dragoon 7 14521
Protoss_Robotics_Facility 1 10659
Singularity_Charge 1 9604
Protoss_Observatory 1 11802
Protoss_Nexus 1 14002
Protoss_Observer 2 13697
Protoss_Citadel_of_Adun 1 13632
Protoss_Templar_Archives 1 15081
Protoss_Shuttle 1 15189
15189
