Protoss_Gateway 2 11420
Protoss_Assimilator 2 15131
Protoss_Cybernetics_Core 1 5613
Protoss_Dragoon 10 15639
Protoss_Robotics_Facility 1 9581
Protoss_Nexus 2 15614
Singularity_Charge 1 9678
Protoss_Observatory 1 10583
Protoss_Observer 4 14859
15639
