Protoss_Gateway 2 11153
Protoss_Assimilator 1 4229
Protoss_Cybernetics_Core 1 5585
Protoss_Zealot 2 12517
Protoss_Dragoon 8 15271
Protoss_Nexus 1 10524
Protoss_Robotics_Facility 1 10265
Protoss_Shuttle 1 11841
Protoss_Robotics_Support_Bay 1 11985
Protoss_Reaver 1 13715
Singularity_Charge 1 12493
Protoss_Observatory 1 13449
Protoss_Observer 1 14666
15271
