Protoss_Gateway 2 9680
Protoss_Assimilator 1 4477
Protoss_Cybernetics_Core 1 5794
Protoss_Dragoon 7 14635
Protoss_Robotics_Facility 1 9766
Protoss_Shuttle 1 11191
Singularity_Charge 1 9800
Protoss_Robotics_Support_Bay 1 10519
Protoss_Zealot 1 10776
Protoss_Reaver 1 12749
Protoss_Nexus 1 15002
Protoss_Observatory 1 13247
Protoss_Observer 1 14268
15002
