Protoss_Gateway 2 13520
Protoss_Assimilator 1 4325
Protoss_Cybernetics_Core 1 5727
Protoss_Zealot 1 5625
Protoss_Dragoon 9 15235
Protoss_Nexus 1 11785
Singularity_Charge 1 10067
Protoss_Robotics_Facility 1 12235
Protoss_Shuttle 1 14221
Protoss_Robotics_Support_Bay 1 14678
15235
