Protoss_Gateway 3 15785
Protoss_Assimilator 1 4234
Protoss_Cybernetics_Core 1 5677
Protoss_Dragoon 9 15478
Protoss_Nexus 2 15716
Singularity_Charge 1 9765
Protoss_Robotics_Facility 1 12071
Protoss_Observatory 1 13232
Protoss_Observer 2 15362
15785
