Protoss_Gateway 3 15539
Protoss_Assimilator 1 4495
Protoss_Cybernetics_Core 1 5764
Protoss_Nexus 2 11497
Protoss_Dragoon 9 14738
Singularity_Charge 1 9522
Protoss_Robotics_Facility 1 13833
Protoss_Observatory 1 14691
15539
