Protoss_Gateway 2 10779
Protoss_Assimilator 2 12904
Protoss_Cybernetics_Core 1 5575
Protoss_Dragoon 7 14969
Protoss_Nexus 1 11112
Protoss_Robotics_Facility 1 10643
Singularity_Charge 1 9502
Protoss_Shuttle 1 12280
Protoss_Robotics_Support_Bay 1 12247
Protoss_Reaver 1 14011
Protoss_Zealot 2 13483
Protoss_Observatory 1 13415
Protoss_Citadel_of_Adun 1 14780
Protoss_Observer 1 14835
Protoss_Stargate 1 16153
16153
