Protoss_Gateway 2 9137
Protoss_Assimilator 1 4479
Protoss_Cybernetics_Core 1 5859
Protoss_Dragoon 11 15107
Singularity_Charge 1 9897
Protoss_Nexus 1 13263
Protoss_Robotics_Facility 1 13958
Protoss_Citadel_of_Adun 1 13646
15107
