Protoss_Gateway 2 10530
Protoss_Assimilator 1 4575
Protoss_Cybernetics_Core 1 5938
Protoss_Zealot 1 5707
Protoss_Dragoon 10 15115
Protoss_Robotics_Facility 1 10804
Singularity_Charge 1 9950
Protoss_Shuttle 1 12339
Protoss_Robotics_Support_Bay 1 12938
Protoss_Observatory 1 13403
Protoss_Reaver 1 14713
Protoss_Observer 1 15538
15538
