Protoss_Gateway 2 11316
Protoss_Assimilator 1 4473
Protoss_Zealot 1 5326
Protoss_Cybernetics_Core 1 6405
Protoss_Dragoon 6 14817
Protoss_Citadel_of_Adun 1 9631
Protoss_Robotics_Facility 1 11403
Protoss_Templar_Archives 1 11145
Protoss_Dark_Templar 3 13716
Protoss_Shuttle 1 13111
Protoss_Observatory 1 12626
Protoss_Observer 2 15178
15178
