Protoss_Gateway 2 6453
Protoss_Assimilator 1 4202
Protoss_Cybernetics_Core 1 5610
Protoss_Dragoon 9 13462
Singularity_Charge 1 9868
Protoss_Robotics_Facility 1 11890
Protoss_Shuttle 1 13290
Protoss_Robotics_Support_Bay 1 12607
Protoss_Zealot 3 14344
Protoss_Reaver 1 14851
Protoss_Observatory 1 14688
Protoss_Nexus 1 17490
17490
