Protoss_Gateway 3 13675
Protoss_Assimilator 1 4413
Protoss_Cybernetics_Core 1 5850
Protoss_Dragoon 11 15616
Protoss_Zealot 2 9658
Protoss_Nexus 1 12570
Singularity_Charge 1 9730
Protoss_Robotics_Facility 1 13151
Protoss_Observatory 1 14592
15616
