Protoss_Gateway 2 11865
Protoss_Assimilator 1 4174
Protoss_Cybernetics_Core 1 5458
Protoss_Dragoon 7 13149
Protoss_Robotics_Facility 1 9484
Protoss_Observatory 1 10310
Singularity_Charge 1 9640
Protoss_Nexus 1 12959
Protoss_Observer 2 12762
Protoss_Shuttle 1 14269
Protoss_Robotics_Support_Bay 1 13737
Protoss_Reaver 1 15888
Protoss_Zealot 2 15222
15888
