Protoss_Gateway 4 15052
Protoss_Assimilator 1 4204
Protoss_Cybernetics_Core 1 5616
Protoss_Dragoon 12 15054
Protoss_Nexus 1 9434
Singularity_Charge 1 11027
Protoss_Zealot 1 12023
Protoss_Robotics_Facility 1 13687
Protoss_Shuttle 1 15652
15652
