Protoss_Gateway 2 11914
Protoss_Assimilator 2 13472
Protoss_Cybernetics_Core 1 6090
Protoss_Dragoon 10 15692
Protoss_Nexus 1 12043
Singularity_Charge 1 10052
Protoss_Robotics_Facility 1 13301
Protoss_Stargate 1 14800
Protoss_Observatory 1 14237
Protoss_Observer 1 15280
15692
