Protoss_Gateway 2 14382
Protoss_Assimilator 1 4340
Protoss_Cybernetics_Core 1 5777
Protoss_Zealot 1 5701
Protoss_Robotics_Facility 1 7972
Protoss_Dragoon 4 15411
Protoss_Robotics_Support_Bay 1 8697
Protoss_Shuttle 1 10062
Protoss_Reaver 1 11620
Protoss_Observatory 1 11960
Protoss_Observer 1 13243
Protoss_Nexus 1 17266
17266
