Protoss_Nexus 2 15065
Protoss_Gateway 5 16021
Protoss_Assimilator 2 9557
Protoss_Cybernetics_Core 1 7615
Protoss_Zealot 2 14686
Protoss_Dragoon 8 15753
Protoss_Robotics_Facility 1 11685
Singularity_Charge 1 11551
Protoss_Observatory 1 12434
Protoss_Observer 1 14265
Protoss_Citadel_of_Adun 1 14840
Protoss_Forge 1 14468
Protoss_Shuttle 1 15623
16021
