Protoss_Gateway 4 15863
Protoss_Assimilator 2 14313
Protoss_Cybernetics_Core 1 5639
Protoss_Dragoon 11 15171
Protoss_Nexus 1 12897
Singularity_Charge 1 10152
Protoss_Robotics_Facility 1 12967
Protoss_Observatory 1 13857
Protoss_Citadel_of_Adun 1 14696
Protoss_Observer 1 14873
15863
