Protoss_Gateway 3 14426
Protoss_Assimilator 1 4512
Protoss_Cybernetics_Core 1 5783
Protoss_Dragoon 5 15715
Protoss_Robotics_Facility 1 8422
Protoss_Shuttle 1 9845
Protoss_Robotics_Support_Bay 1 9326
Protoss_Zealot 2 11341
Protoss_Reaver 2 13168
Protoss_Observatory 1 14224
Gravitic_Drive 1 13942
Protoss_Nexus 1 17057
Protoss_Observer 1 15380
17057
