Protoss_Gateway 2 8134
Protoss_Assimilator 1 4147
Protoss_Cybernetics_Core 1 5534
Protoss_Zealot 3 15453
Protoss_Dragoon 10 14577
Singularity_Charge 1 9701
Protoss_Nexus 1 13524
Protoss_Robotics_Facility 1 13558
Protoss_Shuttle 1 15096
Protoss_Robotics_Support_Bay 1 14574
15453
