Protoss_Gateway 3 15942
Protoss_Assimilator 1 4120
Protoss_Cybernetics_Core 1 5598
Protoss_Dragoon 10 15271
Protoss_Robotics_Facility 1 9440
Protoss_Observatory 1 10152
Singularity_Charge 1 9464
Protoss_Nexus 1 12701
Protoss_Observer 2 12072
Protoss_Shuttle 1 13504
Protoss_Robotics_Support_Bay 1 12941
Protoss_Reaver 1 15135
15942
