Protoss_Assimilator 3 12112
Protoss_Gateway 4 14971
Protoss_Zealot 3 9195
Protoss_Nexus 1 9523
Protoss_Cybernetics_Core 1 9368
Protoss_Dragoon 9 15405
Protoss_Robotics_Facility 1 15130
Singularity_Charge 1 13430
Protoss_Citadel_of_Adun 1 15590
15590
