Protoss_Gateway 3 15096
Protoss_Assimilator 2 12948
Protoss_Cybernetics_Core 1 5648
Protoss_Dragoon 11 15199
Protoss_Robotics_Facility 1 9655
Protoss_Nexus 1 11926
Singularity_Charge 1 9672
Protoss_Observatory 1 10488
Protoss_Observer 2 12459
15199
