Protoss_Gateway 2 9015
Protoss_Assimilator 2 6415
Protoss_Cybernetics_Core 1 5793
Protoss_Dragoon 11 14760
Singularity_Charge 1 9918
Protoss_Nexus 2 16980
Protoss_Robotics_Facility 1 13473
Protoss_Observatory 1 14308
Protoss_Observer 1 15529
16980
