Protoss_Gateway 6 15230
Protoss_Assimilator 1 4252
Protoss_Cybernetics_Core 1 5756
Protoss_Dragoon 6 15174
Protoss_Nexus 2 14995
Protoss_Robotics_Facility 1 11448
Singularity_Charge 1 9882
Protoss_Shuttle 1 12869
Protoss_Robotics_Support_Bay 1 12514
Protoss_Reaver 1 14427
Protoss_Observatory 1 14714
15230
