Protoss_Assimilator 3 12156
Protoss_Gateway 4 14966
Protoss_Nexus 1 8291
Protoss_Cybernetics_Core 1 8149
Protoss_Zealot 2 11683
Protoss_Dragoon 11 15698
Protoss_Citadel_of_Adun 1 11189
Singularity_Charge 1 13720
Protoss_Robotics_Facility 1 15785
Leg_Enhancements 1 14516
15785
