Protoss_Gateway 2 9611
Protoss_Zealot 3 7094
Protoss_Assimilator 1 5288
Protoss_Cybernetics_Core 1 6889
Protoss_Dragoon 11 15666
Singularity_Charge 1 10720
Protoss_Nexus 1 13667
Protoss_Robotics_Facility 1 13523
Protoss_Shuttle 1 14970
Protoss_Robotics_Support_Bay 1 14653
15666
