Protoss_Gateway 3 15912
Protoss_Assimilator 2 14326
Protoss_Cybernetics_Core 1 5743
Protoss_Zealot 3 15105
Protoss_Dragoon 6 13822
Protoss_Nexus 1 12052
Protoss_Robotics_Facility 1 11934
Singularity_Charge 1 10131
Protoss_Citadel_of_Adun 1 13103
Protoss_Observatory 1 12710
Protoss_Observer 2 14674
Protoss_Templar_Archives 1 14601
Protoss_Stargate 1 15527
15912
