Protoss_Gateway 2 15087
Protoss_Assimilator 1 4612
Protoss_Cybernetics_Core 1 6058
Protoss_Dragoon 4 14480
Protoss_Robotics_Facility 1 9259
Protoss_Shuttle 1 10758
Protoss_Robotics_Support_Bay 1 10075
Protoss_Reaver 2 13856
Protoss_Zealot 1 11991
Protoss_Observatory 1 12811
Protoss_Nexus 1 15783
Protoss_Observer 1 14680
Gravitic_Drive 1 13878
15783
