Protoss_Nexus 2 14885
Protoss_Gateway 2 7807
Protoss_Assimilator 1 5619
Protoss_Cybernetics_Core 1 7327
Protoss_Zealot 1 8080
Protoss_Dragoon 10 15534
Singularity_Charge 1 11887
15534
