Protoss_Nexus 1 6696
Protoss_Gateway 4 12956
Protoss_Assimilator 2 9861
Protoss_Cybernetics_Core 1 7644
Protoss_Zealot 3 14803
Protoss_Dragoon 10 14824
Protoss_Robotics_Facility 1 11951
Singularity_Charge 1 11902
Protoss_Observatory 1 12711
Protoss_Shuttle 1 14048
Protoss_Observer 1 14891
14891
