Protoss_Gateway 2 9232
Protoss_Assimilator 1 4517
Protoss_Cybernetics_Core 1 5731
Protoss_Dragoon 10 14202
Protoss_Robotics_Facility 1 10582
Singularity_Charge 1 9973
Protoss_Observatory 1 11981
Protoss_Zealot 1 12658
Protoss_Observer 2 14405
Protoss_Nexus 1 16047
16047
