Protoss_Gateway 2 12728
Protoss_Assimilator 1 4167
Protoss_Zealot 1 5130
Protoss_Cybernetics_Core 1 5942
Protoss_Dragoon 7 15294
Protoss_Citadel_of_Adun 1 7732
Protoss_Templar_Archives 1 9238
Protoss_Dark_Templar 2 11685
Protoss_Nexus 1 12897
Protoss_Robotics_Facility 1 15067
Singularity_Charge 1 14252
15294
