Protoss_Gateway 2 11077
Protoss_Assimilator 3 5534
Protoss_Zealot 2 6898
Protoss_Cybernetics_Core 1 6892
Protoss_Nexus 1 10105
Protoss_Dragoon 10 15657
Protoss_Robotics_Facility 1 13690
Singularity_Charge 1 12651
Protoss_Forge 1 13900
15657
