Protoss_Gateway 4 13916
Protoss_Assimilator 2 14516
Protoss_Cybernetics_Core 1 5557
Protoss_Zealot 1 5522
Protoss_Dragoon 9 14442
Protoss_Nexus 1 11564
Singularity_Charge 1 9678
Protoss_Robotics_Facility 1 11629
Protoss_Observatory 1 12366
Protoss_Observer 2 14329
Protoss_Citadel_of_Adun 1 15175
Protoss_Shuttle 1 15819
15819
