Protoss_Gateway 2 8560
Protoss_Zealot 2 7302
Protoss_Nexus 2 16414
Protoss_Assimilator 2 10660
Protoss_Cybernetics_Core 1 7512
Protoss_Dragoon 9 15232
Protoss_Robotics_Facility 1 12203
Singularity_Charge 1 11808
Protoss_Observatory 1 13081
Protoss_Observer 2 15353
Protoss_Citadel_of_Adun 1 15160
16414
