Protoss_Gateway 3 11979
Protoss_Assimilator 1 4369
Protoss_Cybernetics_Core 1 5582
Protoss_Dragoon 12 14943
Protoss_Nexus 1 10735
Protoss_Robotics_Facility 1 11243
Singularity_Charge 1 9666
Protoss_Observatory 1 12013
Protoss_Observer 2 15134
15134
