Protoss_Gateway 2 8304
Protoss_Zealot 2 5885
Protoss_Assimilator 1 5516
Protoss_Cybernetics_Core 1 7536
Protoss_Dragoon 6 14429
Protoss_Nexus 1 14649
Singularity_Charge 1 11862
Protoss_Citadel_of_Adun 1 13550
Protoss_Templar_Archives 1 15039
Protoss_Robotics_Facility 1 16440
16440
