Protoss_Nexus 2 16544
Protoss_Gateway 2 7940
Protoss_Assimilator 1 5748
Protoss_Cybernetics_Core 1 7571
Protoss_Zealot 1 7855
Protoss_Dragoon 10 15396
Singularity_Charge 1 12083
Protoss_Robotics_Facility 1 16280
16544
