Protoss_Gateway 1 4082
Protoss_Assimilator 1 4384
Protoss_Cybernetics_Core 1 5638
Protoss_Zealot 1 5598
Protoss_Dragoon 6 15083
Protoss_Robotics_Facility 1 9809
Singularity_Charge 1 9768
Protoss_Shuttle 1 11200
Protoss_Robotics_Support_Bay 1 11182
Protoss_Reaver 1 12910
Protoss_Nexus 1 14829
Protoss_Observatory 1 12800
Protoss_Observer 2 14768
15083
