Protoss_Gateway 2 9710
Protoss_Assimilator 1 4214
Protoss_Cybernetics_Core 1 5598
Protoss_Zealot 1 5598
Protoss_Dragoon 13 15756
Protoss_Robotics_Facility 1 9919
Protoss_Observatory 1 10687
Singularity_Charge 1 9973
Protoss_Observer 2 15412
Protoss_Nexus 1 16243
16243
