Protoss_Nexus 2 15220
Protoss_Gateway 4 15964
Protoss_Assimilator 2 12746
Protoss_Cybernetics_Core 1 7387
Protoss_Zealot 1 7123
Protoss_Dragoon 10 14987
Protoss_Citadel_of_Adun 1 12444
Singularity_Charge 1 12016
Protoss_Robotics_Facility 1 14621
Protoss_Templar_Archives 1 14655
15964
