Protoss_Gateway 1 4167
Protoss_Assimilator 1 4236
Protoss_Zealot 2 6128
Protoss_Cybernetics_Core 1 6015
Protoss_Dragoon 8 15647
Protoss_Nexus 1 12366
Singularity_Charge 1 9777
Protoss_Robotics_Facility 1 13756
Protoss_Shuttle 1 15405
15647
