Protoss_Gateway 2 15751
Protoss_Assimilator 1 4679
Protoss_Cybernetics_Core 1 6204
Protoss_Dragoon 6 15472
Protoss_Robotics_Facility 1 10175
Protoss_Nexus 1 12559
Singularity_Charge 1 9891
Protoss_Shuttle 1 11595
Protoss_Robotics_Support_Bay 1 11404
Protoss_Zealot 2 13829
Protoss_Reaver 2 15167
15751
