Protoss_Gateway 4 14309
Protoss_Assimilator 1 4172
Protoss_Cybernetics_Core 1 5598
Protoss_Zealot 1 5440
Protoss_Dragoon 12 15759
Protoss_Nexus 1 12461
Singularity_Charge 1 9724
Protoss_Robotics_Facility 1 12554
Protoss_Observatory 1 13454
Protoss_Observer 2 15362
15759
