Protoss_Gateway 4 13997
Protoss_Assimilator 2 13767
Protoss_Cybernetics_Core 1 5800
Protoss_Dragoon 6 14586
Protoss_Citadel_of_Adun 1 8928
Protoss_Templar_Archives 1 10559
Protoss_Nexus 1 12336
Singularity_Charge 1 9982
Protoss_Dark_Templar 2 14395
Protoss_Robotics_Facility 1 13661
Protoss_Observatory 1 15209
15209
