Protoss_Gateway 1 4205
Protoss_Assimilator 1 4382
Protoss_Cybernetics_Core 1 5670
Protoss_Zealot 2 12702
Protoss_Dragoon 6 15633
Protoss_Robotics_Facility 1 10160
Protoss_Shuttle 1 11557
Protoss_Robotics_Support_Bay 1 11322
Protoss_Reaver 1 13279
Protoss_Observatory 2 13910
Singularity_Charge 1 13374
Protoss_Observer 2 15359
15633
