Protoss_Gateway 2 15009
Protoss_Assimilator 1 4360
Protoss_Cybernetics_Core 1 5636
Protoss_Dragoon 6 15227
Protoss_Robotics_Facility 1 9721
Singularity_Charge 1 9704
Protoss_Nexus 1 12830
Protoss_Shuttle 1 12014
Protoss_Robotics_Support_Bay 1 12014
Protoss_Zealot 2 13767
Protoss_Reaver 1 13970
Protoss_Observatory 1 14621
15227
