Protoss_Gateway 2 8938
Protoss_Assimilator 1 4501
Protoss_Cybernetics_Core 1 5778
Protoss_Dragoon 11 15063
Protoss_Robotics_Facility 1 11386
Singularity_Charge 1 9970
Protoss_Robotics_Support_Bay 1 12514
Protoss_Zealot 2 12842
Protoss_Shuttle 1 13905
Protoss_Reaver 1 15463
15463
