Protoss_Gateway 2 6617
Protoss_Assimilator 1 4267
Protoss_Cybernetics_Core 1 5853
Protoss_Dragoon 7 11691
Protoss_Citadel_of_Adun 1 10925
Singularity_Charge 1 9517
Protoss_Robotics_Facility 1 13450
Protoss_Templar_Archives 1 13113
Protoss_Dark_Templar 3 15812
Protoss_Nexus 1 16639
Protoss_Shuttle 1 15588
16639
