Protoss_Nexus 1 6656
Protoss_Gateway 2 7711
Protoss_Assimilator 2 14297
Protoss_Cybernetics_Core 1 7483
Protoss_Zealot 3 15228
Protoss_Dragoon 7 14366
Protoss_Robotics_Facility 1 12257
Protoss_Shuttle 1 13764
Protoss_Observatory 1 13310
Protoss_Robotics_Support_Bay 1 13394
Protoss_Observer 1 14803
Singularity_Charge 1 14434
15228
