Protoss_Nexus 1 6527
Protoss_Gateway 2 15879
Protoss_Assimilator 1 5657
Protoss_Cybernetics_Core 1 7084
Protoss_Zealot 1 6769
Protoss_Dragoon 6 14786
Singularity_Charge 1 11279
Protoss_Robotics_Facility 1 15165
15879
