Protoss_Gateway 2 11064
Protoss_Assimilator 2 14650
Protoss_Cybernetics_Core 1 5909
Protoss_Dragoon 8 14632
Protoss_Nexus 1 11942
Singularity_Charge 1 10049
Protoss_Citadel_of_Adun 1 11793
Protoss_Robotics_Facility 1 13201
Protoss_Templar_Archives 1 13843
Protoss_Observatory 1 14100
Protoss_Dark_Templar 1 15086
Protoss_Observer 1 15134
15134
