Protoss_Gateway 4 15115
Protoss_Assimilator 1 4451
Protoss_Cybernetics_Core 1 5911
Protoss_Dragoon 9 15326
Protoss_Citadel_of_Adun 1 9810
Protoss_Templar_Archives 1 11254
Singularity_Charge 1 9941
Protoss_Nexus 1 13730
Protoss_Dark_Templar 2 12478
Protoss_Stargate 1 16147
16147
