Protoss_Gateway 2 6274
Protoss_Assimilator 1 4234
Protoss_Cybernetics_Core 1 5692
Protoss_Dragoon 11 15604
Protoss_Nexus 1 11826
Singularity_Charge 1 9587
Protoss_Robotics_Facility 1 14506
Protoss_Observatory 1 15249
15604
