Protoss_Gateway 2 13972
Protoss_Assimilator 1 4818
Protoss_Zealot 4 12845
Protoss_Cybernetics_Core 1 6794
Protoss_Dragoon 7 15625
Protoss_Robotics_Facility 1 9925
Protoss_Shuttle 1 11326
Protoss_Robotics_Support_Bay 1 11296
Singularity_Charge 1 10939
Protoss_Reaver 1 13036
Protoss_Nexus 1 14607
Protoss_Observatory 1 14625
15625
