Protoss_Gateway 2 14348
Protoss_Assimilator 2 13346
Protoss_Cybernetics_Core 1 6026
Protoss_Dragoon 4 11641
Protoss_Nexus 1 11997
Protoss_Citadel_of_Adun 1 11348
Singularity_Charge 1 10136
Protoss_Robotics_Facility 1 12250
Protoss_Templar_Archives 1 13089
Protoss_Observatory 1 13027
Protoss_Shuttle 1 14111
Protoss_Dark_Templar 3 15571
Protoss_Observer 1 14954
15571
