Protoss_Gateway 3 13303
Protoss_Assimilator 1 4232
Protoss_Cybernetics_Core 1 5607
Protoss_Dragoon 6 15127
Protoss_Citadel_of_Adun 1 8436
Protoss_Robotics_Facility 1 9663
Protoss_Templar_Archives 1 10354
Protoss_Zealot 1 10264
Protoss_Shuttle 1 11212
Protoss_Dark_Templar 3 12701
Protoss_Nexus 1 16105
Protoss_Observatory 1 14935
16105
