Protoss_Gateway 2 14212
Protoss_Assimilator 2 13507
Protoss_Cybernetics_Core 1 5859
Protoss_Zealot 1 5944
Protoss_Dragoon 5 13008
Protoss_Nexus 2 17234
Protoss_Robotics_Facility 1 11362
Singularity_Charge 1 10040
Protoss_Citadel_of_Adun 1 11954
Protoss_Shuttle 1 13003
Protoss_Templar_Archives 1 13760
Protoss_Dark_Templar 1 14984
17234
