Protoss_Nexus 1 6780
Protoss_Gateway 3 14446
Protoss_Assimilator 2 12368
Protoss_Cybernetics_Core 1 7479
Protoss_Zealot 1 7398
Protoss_Dragoon 10 14533
Protoss_Robotics_Facility 1 12401
Singularity_Charge 1 11814
Protoss_Observatory 1 13553
Protoss_Observer 2 15509
Protoss_Citadel_of_Adun 1 15525
15525
