Protoss_Gateway 2 9969
Protoss_Assimilator 1 4164
Protoss_Cybernetics_Core 1 5613
Protoss_Zealot 1 5396
Protoss_Dragoon 6 15771
Protoss_Citadel_of_Adun 1 8140
Protoss_Robotics_Facility 1 9936
Protoss_Templar_Archives 1 10325
Protoss_Shuttle 2 15348
Protoss_Dark_Templar 3 14671
Protoss_Observatory 1 11767
Protoss_Observer 1 12822
Protoss_Nexus 1 15457
15771
