Protoss_Gateway 2 12279
Protoss_Assimilator 2 11929
Protoss_Cybernetics_Core 1 5566
Protoss_Zealot 1 5446
Protoss_Dragoon 9 15326
Protoss_Nexus 1 10536
Protoss_Robotics_Facility 1 11436
Singularity_Charge 1 11718
Protoss_Observatory 1 12487
Protoss_Observer 2 14470
Protoss_Citadel_of_Adun 1 14329
Protoss_Stargate 1 15546
Protoss_Templar_Archives 1 15809
15809
