Protoss_Gateway 3 14604
Protoss_Assimilator 2 5187
Protoss_Zealot 2 7005
Protoss_Cybernetics_Core 1 7038
Protoss_Dragoon 6 15073
Protoss_Robotics_Facility 1 11385
Singularity_Charge 1 10853
Protoss_Nexus 1 13919
Protoss_Observatory 1 12091
Protoss_Observer 2 14317
15073
