Protoss_Gateway 9 10308
Protoss_Assimilator 1 7477
Protoss_Cybernetics_Core 1 9245
Protoss_Dragoon 2 11562
Protoss_Zealot 2 12836
Protoss_Citadel_of_Adun 1 12563
Protoss_Robotics_Facility 1 13507
Protoss_Nexus 1 15617
Protoss_Templar_Archives 1 14370
Singularity_Charge 1 12991
Protoss_Shuttle 1 15052
Protoss_Dark_Templar 2 15590
15617
