Protoss_Gateway 2 8859
Protoss_Assimilator 2 14606
Protoss_Cybernetics_Core 1 5783
Protoss_Citadel_of_Adun 1 7378
Protoss_Dragoon 8 15736
Protoss_Templar_Archives 1 9406
Protoss_Dark_Templar 3 14454
Protoss_Nexus 1 15971
Protoss_Stargate 1 15651
Singularity_Charge 1 14115
15971
