Protoss_Gateway 2 10565
Protoss_Assimilator 2 12872
Protoss_Cybernetics_Core 1 5844
Protoss_Dragoon 8 15016
Protoss_Nexus 1 11134
Protoss_Robotics_Facility 1 11518
Singularity_Charge 1 9771
Protoss_Citadel_of_Adun 1 12962
Protoss_Observatory 1 12341
Protoss_Observer 2 14238
Protoss_Templar_Archives 1 16037
16037
