Protoss_Assimilator 1 3658
Protoss_Gateway 3 13309
Protoss_Cybernetics_Core 1 6036
Protoss_Robotics_Facility 1 8685
Protoss_Dragoon 10 15822
Protoss_Shuttle 2 15282
Singularity_Charge 1 9711
Protoss_Observatory 1 10737
Protoss_Observer 3 13706
Protoss_Robotics_Support_Bay 1 11982
15822
