Protoss_Nexus 1 6840
Protoss_Gateway 2 14560
Protoss_Assimilator 2 9402
Protoss_Cybernetics_Core 1 7543
Protoss_Stargate 2 9881
Protoss_Forge 1 9870
Protoss_Corsair 4 12119
Protoss_Photon_Cannon 3 12693
Protoss_Dragoon 2 14502
Protoss_Robotics_Facility 1 14312
Protoss_Robotics_Support_Bay 1 15076
Protoss_Shuttle 1 15904
15904
