Protoss_Nexus 1 6775
Protoss_Gateway 4 12558
Protoss_Assimilator 2 11085
Protoss_Cybernetics_Core 1 7398
Protoss_Dragoon 11 14308
Protoss_Robotics_Facility 1 11847
Protoss_Zealot 1 11522
Singularity_Charge 1 11785
Protoss_Observatory 1 12616
Protoss_Observer 2 14549
Protoss_Robotics_Support_Bay 1 14401
14549
