Protoss_Gateway 3 14133
Protoss_Assimilator 2 12800
Protoss_Cybernetics_Core 1 5998
Protoss_Dragoon 6 15622
Protoss_Citadel_of_Adun 1 9569
Protoss_Nexus 1 12558
Singularity_Charge 1 10029
Protoss_Templar_Archives 1 11496
Protoss_Robotics_Facility 1 13229
Protoss_Dark_Templar 3 15288
Protoss_Observatory 1 14123
Protoss_Stargate 1 15411
Protoss_Observer 1 15327
15622
