Protoss_Gateway 3 13406
Protoss_Assimilator 1 4255
Protoss_Cybernetics_Core 1 5674
Protoss_Dragoon 10 15756
Protoss_Robotics_Facility 1 8370
Protoss_Observatory 1 9354
Protoss_Observer 4 14446
Protoss_Nexus 2 16026
Singularity_Charge 1 11270
16026
