Protoss_Nexus 2 15660
Protoss_Gateway 4 15492
Protoss_Assimilator 1 5794
Protoss_Cybernetics_Core 1 7231
Protoss_Zealot 1 7536
Protoss_Dragoon 3 10298
Protoss_Citadel_of_Adun 1 10987
Protoss_Robotics_Facility 1 12904
Protoss_Templar_Archives 1 12451
Protoss_Dark_Templar 2 13851
Protoss_Shuttle 1 14320
Protoss_Observatory 1 14072
Protoss_Observer 1 15163
15660
