Protoss_Gateway 2 9857
Protoss_Assimilator 2 14004
Protoss_Cybernetics_Core 1 5623
Protoss_Robotics_Facility 1 7965
Protoss_Dragoon 8 15358
Protoss_Observatory 1 8878
Protoss_Zealot 1 9588
Protoss_Observer 2 11622
Protoss_Nexus 1 14039
Protoss_Citadel_of_Adun 1 13195
Singularity_Charge 1 12912
Protoss_Templar_Archives 1 14670
15358
