Protoss_Gateway 2 9684
Protoss_Assimilator 3 10337
Protoss_Zealot 3 8794
Protoss_Nexus 2 16317
Protoss_Cybernetics_Core 1 8966
Protoss_Dragoon 5 13020
Protoss_Robotics_Facility 1 12098
Protoss_Shuttle 1 13542
Protoss_Observatory 1 13020
Protoss_Robotics_Support_Bay 1 13494
Protoss_Observer 1 14385
Protoss_Reaver 1 16066
16317
