Protoss_Gateway 2 10207
Protoss_Assimilator 2 14396
Protoss_Cybernetics_Core 1 5707
Protoss_Dragoon 7 15581
Protoss_Robotics_Facility 1 8913
Protoss_Citadel_of_Adun 1 9213
Protoss_Templar_Archives 1 10662
Protoss_Shuttle 1 11133
Protoss_Dark_Templar 4 13289
Protoss_Nexus 1 14493
Protoss_Stargate 1 14285
15581
