Protoss_Gateway 2 9959
Protoss_Assimilator 2 14424
Protoss_Cybernetics_Core 1 5613
Protoss_Zealot 1 5516
Protoss_Dragoon 8 15153
Protoss_Citadel_of_Adun 1 8769
Protoss_Robotics_Facility 1 10223
Protoss_Templar_Archives 1 10234
Protoss_Shuttle 1 11628
Protoss_Dark_Templar 3 13787
Protoss_Nexus 1 14899
Protoss_Observatory 1 13412
Protoss_Observer 1 15096
15153
