Protoss_Gateway 2 10068
Protoss_Assimilator 1 4425
Protoss_Cybernetics_Core 1 5800
Protoss_Dragoon 8 13374
Protoss_Robotics_Facility 1 9946
Singularity_Charge 1 9827
Protoss_Observatory 1 11309
Protoss_Observer 1 13003
Protoss_Nexus 2 16465
Protoss_Shuttle 1 14361
Protoss_Robotics_Support_Bay 1 14849
Protoss_Zealot 2 15430
16465
