Protoss_Gateway 3 12820
Protoss_Assimilator 1 4501
Protoss_Cybernetics_Core 1 5774
Protoss_Zealot 1 5625
Protoss_Dragoon 10 14311
Protoss_Nexus 1 12043
Singularity_Charge 1 9932
Protoss_Robotics_Facility 1 15629
15629
