Protoss_Gateway 4 15331
Protoss_Assimilator 1 4167
Protoss_Cybernetics_Core 1 5565
Protoss_Dragoon 7 15200
Protoss_Nexus 2 14954
Singularity_Charge 1 9508
Protoss_Robotics_Facility 1 11998
Protoss_Observatory 1 12751
Protoss_Observer 2 14645
15331
