Protoss_Gateway 3 15776
Protoss_Assimilator 1 4499
Protoss_Cybernetics_Core 1 5816
Protoss_Dragoon 6 15791
Protoss_Robotics_Facility 1 8343
Protoss_Zealot 2 10109
Protoss_Shuttle 1 9746
Protoss_Robotics_Support_Bay 1 9256
Protoss_Reaver 1 11839
Protoss_Observatory 1 12388
Scarab_Damage 1 13213
Protoss_Observer 2 15210
Protoss_Nexus 1 16761
16761
