Protoss_Gateway 2 8484
Protoss_Assimilator 1 4489
Protoss_Zealot 3 7870
Protoss_Cybernetics_Core 1 7050
Protoss_Dragoon 10 15721
Protoss_Robotics_Facility 1 12412
Singularity_Charge 1 11270
Protoss_Observatory 1 13285
Protoss_Nexus 2 17092
Protoss_Observer 2 15558
17092
