Protoss_Gateway 4 15807
Protoss_Assimilator 1 4261
Protoss_Cybernetics_Core 1 5862
Protoss_Dragoon 8 14308
Singularity_Charge 1 9964
Protoss_Nexus 2 15081
Protoss_Robotics_Facility 1 14536
15807
