Protoss_Gateway 2 8632
Protoss_Assimilator 1 4407
Protoss_Cybernetics_Core 1 5821
Protoss_Dragoon 4 14943
Protoss_Citadel_of_Adun 1 7698
Protoss_Templar_Archives 1 9149
Protoss_Zealot 1 9149
Protoss_Dark_Templar 5 12800
Protoss_Nexus 1 15470
Protoss_Robotics_Facility 1 15421
15470
