Protoss_Gateway 4 13730
Protoss_Assimilator 2 14284
Protoss_Cybernetics_Core 1 5633
Protoss_Dragoon 12 14956
Protoss_Nexus 1 12271
Singularity_Charge 1 9499
Protoss_Robotics_Facility 1 12870
Protoss_Observatory 1 13855
Protoss_Citadel_of_Adun 1 14914
Protoss_Observer 1 15200
15200
