Protoss_Zealot 23 15427
Protoss_Gateway 2 12482
Protoss_Assimilator 1 4564
Protoss_Cybernetics_Core 1 5999
Protoss_Dragoon 6 13756
Protoss_Robotics_Facility 1 10690
Singularity_Charge 1 10106
Protoss_Observatory 1 12307
Protoss_Observer 1 13575
15427
