Protoss_Gateway 3 15450
Protoss_Assimilator 2 4932
Protoss_Cybernetics_Core 1 6225
Protoss_Zealot 1 7079
Protoss_Dragoon 7 13980
Singularity_Charge 1 10600
Protoss_Nexus 1 13852
Protoss_Robotics_Facility 1 13924
Protoss_Shuttle 1 15640
Protoss_Robotics_Support_Bay 1 15206
15640
