Protoss_Gateway 2 5805
Protoss_Zealot 11 15293
Protoss_Assimilator 1 7565
Protoss_Cybernetics_Core 1 10189
Protoss_Dragoon 6 14542
Protoss_Robotics_Facility 1 13308
Protoss_Shuttle 1 14996
15293
