Protoss_Gateway 3 14234
Protoss_Zealot 15 12630
Protoss_Forge 1 8202
Protoss_Photon_Cannon 2 14821
Protoss_Assimilator 1 12627
Protoss_Cybernetics_Core 1 13442
Protoss_Citadel_of_Adun 1 14926
Protoss_Dragoon 1 15291
15291
