Protoss_Gateway 3 16005
Protoss_Assimilator 1 4328
Protoss_Cybernetics_Core 1 6015
Protoss_Dragoon 6 12499
Protoss_Nexus 2 16181
Protoss_Robotics_Facility 1 12468
Protoss_Shuttle 1 13902
Protoss_Observatory 1 13257
Protoss_Robotics_Support_Bay 1 13580
Protoss_Reaver 1 15460
Protoss_Zealot 2 15225
16181
