Protoss_Gateway 2 12248
Protoss_Assimilator 1 4482
Protoss_Cybernetics_Core 1 5742
Protoss_Dragoon 8 13980
Protoss_Nexus 1 11741
Singularity_Charge 1 9982
Protoss_Robotics_Facility 1 11934
Protoss_Shuttle 1 13635
Protoss_Robotics_Support_Bay 1 13801
Protoss_Observatory 1 14546
Protoss_Zealot 2 15292
Protoss_Reaver 1 16019
16019
