Protoss_Gateway 3 15915
Protoss_Assimilator 1 4287
Protoss_Cybernetics_Core 1 5837
Protoss_Dragoon 9 15010
Protoss_Robotics_Facility 1 10080
Singularity_Charge 1 9622
Protoss_Observatory 1 10861
Protoss_Observer 3 14669
Protoss_Nexus 2 16151
16151
