Protoss_Gateway 3 15768
Protoss_Assimilator 1 4407
Protoss_Cybernetics_Core 1 5832
Protoss_Dragoon 10 15543
Protoss_Nexus 2 15589
Singularity_Charge 1 9821
Protoss_Robotics_Facility 1 13552
Protoss_Observatory 1 14761
Protoss_Citadel_of_Adun 1 15497
15768
