Protoss_Gateway 2 6434
Protoss_Assimilator 1 4381
Protoss_Cybernetics_Core 1 5721
Protoss_Dragoon 15 15794
Singularity_Charge 1 9739
Protoss_Robotics_Facility 1 13868
Protoss_Nexus 1 15940
Protoss_Observatory 1 14674
15940
