Protoss_Gateway 2 10631
Protoss_Assimilator 1 4649
Protoss_Cybernetics_Core 1 5853
Protoss_Zealot 1 5800
Protoss_Dragoon 10 15408
Protoss_Robotics_Facility 1 10094
Singularity_Charge 1 9991
Protoss_Observatory 1 11237
Protoss_Observer 2 13132
Protoss_Robotics_Support_Bay 1 13397
Protoss_Shuttle 1 14490
Protoss_Reaver 1 16048
16048
