Protoss_Gateway 2 9762
Protoss_Assimilator 1 4783
Protoss_Cybernetics_Core 1 6242
Protoss_Dragoon 9 14173
Protoss_Robotics_Facility 1 11165
Singularity_Charge 1 10509
Protoss_Observatory 1 12000
Protoss_Observer 2 13966
Protoss_Shuttle 1 15324
15324
