Protoss_Gateway 2 13624
Protoss_Assimilator 1 4350
Protoss_Cybernetics_Core 1 5949
Protoss_Dragoon 9 15546
Protoss_Nexus 1 12331
Singularity_Charge 1 10383
Protoss_Robotics_Facility 1 13848
Protoss_Observatory 1 14590
15546
