Protoss_Gateway 2 15997
Protoss_Assimilator 1 4416
Protoss_Cybernetics_Core 1 5841
Protoss_Dragoon 6 15551
Protoss_Robotics_Facility 1 8768
Protoss_Shuttle 1 10176
Protoss_Robotics_Support_Bay 1 9660
Protoss_Nexus 1 12859
Protoss_Reaver 2 14681
Protoss_Observatory 1 11458
Protoss_Observer 2 15506
15997
