Protoss_Gateway 4 15672
Protoss_Assimilator 1 4552
Protoss_Cybernetics_Core 1 5903
Protoss_Dragoon 5 14769
Protoss_Citadel_of_Adun 2 8904
Protoss_Zealot 1 9492
Protoss_Templar_Archives 1 10353
Protoss_Dark_Templar 3 14776
Protoss_Nexus 1 13691
Protoss_Robotics_Facility 1 15063
15672
