Protoss_Gateway 2 12784
Protoss_Assimilator 3 13514
Protoss_Cybernetics_Core 1 6116
Protoss_Dragoon 5 12777
Protoss_Nexus 1 13056
Singularity_Charge 1 10544
Protoss_Robotics_Facility 1 12873
Protoss_Citadel_of_Adun 1 13976
Protoss_Stargate 1 15117
Protoss_Observatory 1 14513
Protoss_Observer 1 15529
15529
