Protoss_Gateway 2 10452
Protoss_Assimilator 1 4515
Protoss_Cybernetics_Core 1 5996
Protoss_Dragoon 7 13684
Protoss_Robotics_Facility 1 10009
Singularity_Charge 1 10231
Protoss_Observatory 1 11082
Protoss_Observer 1 12169
Protoss_Nexus 1 15286
Protoss_Shuttle 1 14194
Protoss_Robotics_Support_Bay 1 14277
Protoss_Reaver 1 16013
Protoss_Zealot 1 15424
16013
