Protoss_Gateway 4 14215
Protoss_Assimilator 1 4412
Protoss_Cybernetics_Core 1 5677
Protoss_Dragoon 12 15563
Protoss_Nexus 1 11987
Singularity_Charge 1 9745
Protoss_Robotics_Facility 1 12922
Protoss_Observatory 1 13750
Protoss_Observer 1 15093
15563
