Protoss_Gateway 3 14449
Protoss_Assimilator 2 14301
Protoss_Cybernetics_Core 1 5822
Protoss_Dragoon 7 15666
Protoss_Citadel_of_Adun 1 7689
Protoss_Templar_Archives 1 9189
Protoss_Dark_Templar 4 11871
Protoss_Nexus 1 13957
15666
