Protoss_Gateway 3 13274
Protoss_Nexus 1 7859
Protoss_Assimilator 2 10845
Protoss_Cybernetics_Core 1 7650
Protoss_Forge 1 8055
Protoss_Dragoon 4 15673
Protoss_Photon_Cannon 1 9661
Protoss_Citadel_of_Adun 1 10811
Protoss_Templar_Archives 1 12311
Protoss_Dark_Templar 3 15095
Protoss_Robotics_Facility 1 14801
Protoss_Stargate 1 15028
15673
