Protoss_Gateway 3 15121
Protoss_Assimilator 1 4496
Protoss_Cybernetics_Core 1 6135
Protoss_Dragoon 10 15225
Protoss_Citadel_of_Adun 1 9908
Protoss_Templar_Archives 1 11433
Singularity_Charge 1 10099
Protoss_Dark_Templar 2 13024
Protoss_Nexus 1 16310
16310
