Protoss_Gateway 4 14695
Protoss_Assimilator 1 4337
Protoss_Cybernetics_Core 1 5588
Protoss_Dragoon 10 14928
Protoss_Nexus 2 17468
Singularity_Charge 1 9531
Protoss_Robotics_Facility 1 12005
Protoss_Observatory 1 12695
Protoss_Observer 2 14595
17468
