Protoss_Gateway 4 13949
Protoss_Assimilator 2 15389
Protoss_Cybernetics_Core 1 6106
Protoss_Dragoon 8 14795
Protoss_Nexus 1 12281
Singularity_Charge 1 9814
Protoss_Robotics_Facility 1 12630
Protoss_Observatory 1 13542
Protoss_Shuttle 1 14484
Protoss_Robotics_Support_Bay 1 14900
Protoss_Zealot 1 15251
Protoss_Observer 1 15327
15389
