Protoss_Gateway 2 12053
Protoss_Assimilator 1 4240
Protoss_Cybernetics_Core 1 5731
Protoss_Robotics_Facility 1 8010
Protoss_Dragoon 8 14913
Protoss_Observatory 1 9091
Protoss_Observer 2 11118
Protoss_Nexus 1 12573
Protoss_Shuttle 1 12705
Singularity_Charge 1 11504
Protoss_Robotics_Support_Bay 1 12672
Protoss_Reaver 1 14640
14913
