Protoss_Gateway 2 9007
Protoss_Zealot 4 8344
Protoss_Assimilator 1 5875
Protoss_Cybernetics_Core 1 7975
Protoss_Dragoon 9 14922
Protoss_Nexus 1 15091
Singularity_Charge 1 12536
Protoss_Robotics_Facility 1 15907
15907
