Protoss_Gateway 2 10126
Protoss_Assimilator 1 4419
Protoss_Zealot 3 7141
Protoss_Cybernetics_Core 1 7170
Protoss_Dragoon 9 14597
Singularity_Charge 1 11431
Protoss_Nexus 2 17245
Protoss_Robotics_Facility 1 14583
17245
