Protoss_Gateway 2 12309
Protoss_Assimilator 1 4363
Protoss_Zealot 3 7069
Protoss_Cybernetics_Core 1 8253
Protoss_Dragoon 4 15388
Protoss_Robotics_Facility 1 10725
Protoss_Citadel_of_Adun 1 10689
Protoss_Templar_Archives 1 12168
Protoss_Shuttle 1 12326
Protoss_Observatory 1 12803
Protoss_Dark_Templar 3 14666
Protoss_Observer 1 14029
Protoss_Forge 1 15032
15388
