Protoss_Gateway 3 14777
Protoss_Assimilator 1 4305
Protoss_Cybernetics_Core 1 5762
Protoss_Dragoon 10 15415
Protoss_Robotics_Facility 1 8912
Protoss_Robotics_Support_Bay 1 9521
Protoss_Shuttle 1 10262
Protoss_Reaver 1 11781
Singularity_Charge 1 12009
Protoss_Observatory 1 13885
Protoss_Nexus 2 16939
Protoss_Observer 1 15346
16939
