Protoss_Gateway 2 9525
Protoss_Assimilator 1 4328
Protoss_Zealot 2 6874
Protoss_Cybernetics_Core 1 7120
Protoss_Dragoon 12 15721
Singularity_Charge 1 11115
Protoss_Robotics_Facility 1 14057
Protoss_Nexus 1 15514
Protoss_Observatory 1 15268
15721
