Protoss_Gateway 3 12178
Protoss_Assimilator 2 13738
Protoss_Cybernetics_Core 1 5622
Protoss_Dragoon 13 15563
Protoss_Nexus 1 11018
Protoss_Robotics_Facility 1 11021
Singularity_Charge 1 9599
Protoss_Observatory 1 12017
Protoss_Observer 2 14162
15563
