Protoss_Gateway 3 16032
Protoss_Assimilator 1 4185
Protoss_Cybernetics_Core 1 5689
Protoss_Dragoon 7 15739
Protoss_Nexus 2 15930
Protoss_Robotics_Facility 1 11136
Singularity_Charge 1 9496
Protoss_Robotics_Support_Bay 1 11902
Protoss_Shuttle 1 13290
Protoss_Zealot 2 13208
Protoss_Reaver 1 15006
Protoss_Observatory 1 15055
16032
