Protoss_Gateway 2 14797
Protoss_Assimilator 1 4559
Protoss_Cybernetics_Core 1 6857
Protoss_Zealot 2 13392
Protoss_Dragoon 4 15622
Protoss_Robotics_Facility 1 10251
Protoss_Shuttle 1 11663
Singularity_Charge 1 10523
Protoss_Robotics_Support_Bay 1 11466
Protoss_Reaver 1 13221
Protoss_Nexus 2 17367
Protoss_Observatory 1 13604
Protoss_Observer 2 15497
17367
