Protoss_Gateway 4 15501
Protoss_Assimilator 1 4240
Protoss_Cybernetics_Core 1 5610
Protoss_Dragoon 10 15528
Protoss_Nexus 2 14032
Singularity_Charge 1 9277
Protoss_Robotics_Facility 1 15826
15826
