Protoss_Gateway 1 4188
Protoss_Assimilator 1 4416
Protoss_Cybernetics_Core 1 5657
Protoss_Zealot 3 13594
Protoss_Dragoon 4 10405
Protoss_Robotics_Facility 1 10497
Singularity_Charge 1 10084
Protoss_Nexus 2 17207
Protoss_Shuttle 1 12494
Protoss_Robotics_Support_Bay 1 12042
Protoss_Reaver 1 14287
Protoss_Observatory 1 13933
Protoss_Observer 1 15112
17207
