Protoss_Gateway 3 12639
Protoss_Assimilator 2 14287
Protoss_Cybernetics_Core 1 5920
Protoss_Dragoon 11 15493
Protoss_Nexus 1 11771
Singularity_Charge 1 9953
Protoss_Robotics_Facility 1 12159
Protoss_Observatory 1 13026
Protoss_Observer 2 15178
Protoss_Citadel_of_Adun 1 14721
15493
