Protoss_Gateway 1 4351
Protoss_Assimilator 1 4337
Protoss_Cybernetics_Core 1 5838
Protoss_Robotics_Facility 1 8029
Protoss_Dragoon 4 14766
Protoss_Shuttle 1 9450
Protoss_Robotics_Support_Bay 1 9079
Protoss_Reaver 2 12547
Protoss_Observatory 1 12717
Protoss_Observer 1 13810
Gravitic_Drive 1 13143
Protoss_Nexus 1 16076
16076
