Protoss_Gateway 1 4258
Protoss_Zealot 3 7027
Protoss_Assimilator 1 5456
Protoss_Cybernetics_Core 1 6980
Protoss_Dragoon 6 15717
Protoss_Robotics_Facility 1 9446
Protoss_Shuttle 1 10965
Protoss_Robotics_Support_Bay 1 10545
Protoss_Reaver 3 15679
Protoss_Nexus 1 16459
Protoss_Observatory 1 14644
16459
