Protoss_Gateway 3 15959
Protoss_Assimilator 1 4328
Protoss_Cybernetics_Core 1 5753
Protoss_Dragoon 6 15189
Protoss_Robotics_Facility 1 8284
Protoss_Shuttle 2 15860
Protoss_Zealot 2 11036
Protoss_Observatory 1 9825
Protoss_Observer 1 10846
Protoss_Robotics_Support_Bay 1 10754
Protoss_Reaver 1 12632
Singularity_Charge 1 11311
Protoss_Nexus 1 15308
15959
