Protoss_Nexus 2 16872
Protoss_Gateway 4 12248
Protoss_Assimilator 2 10830
Protoss_Zealot 2 8366
Protoss_Cybernetics_Core 1 8408
Protoss_Dragoon 9 15819
Protoss_Robotics_Facility 1 13529
Singularity_Charge 1 12440
Protoss_Observatory 1 14976
16872
