Protoss_Gateway 2 9817
Protoss_Assimilator 4 15396
Protoss_Cybernetics_Core 1 6289
Protoss_Dragoon 8 15481
Singularity_Charge 1 10547
Protoss_Nexus 1 14478
Protoss_Stargate 1 15334
15481
