Protoss_Gateway 4 15169
Protoss_Assimilator 1 4445
Protoss_Cybernetics_Core 1 5856
Protoss_Dragoon 6 15698
Protoss_Robotics_Facility 1 10024
Singularity_Charge 1 9979
Protoss_Shuttle 1 11554
Protoss_Robotics_Support_Bay 1 11062
Protoss_Zealot 1 11680
Protoss_Reaver 1 13112
Protoss_Nexus 1 14861
Protoss_Observatory 1 12976
Protoss_Observer 2 14912
15698
