Protoss_Gateway 2 10524
Protoss_Assimilator 2 6030
Protoss_Zealot 2 6231
Protoss_Cybernetics_Core 1 7619
Protoss_Dragoon 7 15581
Protoss_Nexus 2 16770
Protoss_Citadel_of_Adun 1 11745
Protoss_Templar_Archives 1 13205
Protoss_Robotics_Facility 1 14741
Protoss_Dark_Templar 2 14416
16770
