Protoss_Nexus 1 6899
Protoss_Gateway 4 15140
Protoss_Assimilator 2 10359
Protoss_Cybernetics_Core 1 7328
Protoss_Zealot 1 7744
Protoss_Dragoon 4 10778
Protoss_Citadel_of_Adun 1 10085
Protoss_Templar_Archives 1 11563
Protoss_Stargate 1 13102
Protoss_Dark_Templar 4 14208
Protoss_Arbiter_Tribunal 1 14701
15140
