Protoss_Gateway 3 15093
Protoss_Assimilator 1 4488
Protoss_Zealot 3 7138
Protoss_Cybernetics_Core 1 7056
Protoss_Dragoon 9 15095
Protoss_Nexus 2 14074
Singularity_Charge 1 11000
Protoss_Robotics_Facility 1 14135
Protoss_Observatory 1 15218
15218
