Protoss_Nexus 1 7774
Protoss_Assimilator 1 6314
Protoss_Gateway 6 15507
Protoss_Cybernetics_Core 2 14806
Protoss_Zealot 3 11710
Protoss_Dragoon 4 12830
Protoss_Citadel_of_Adun 1 10968
Protoss_Templar_Archives 1 12710
Protoss_Shield_Battery 1 12489
Protoss_Dark_Templar 4 15369
15507
