Protoss_Gateway 3 13670
Protoss_Assimilator 1 4486
Protoss_Cybernetics_Core 1 5999
Protoss_Dragoon 7 13997
Protoss_Nexus 2 16414
Protoss_Robotics_Facility 1 11107
Singularity_Charge 1 9880
Protoss_Observatory 1 11994
Protoss_Observer 2 14762
Protoss_Zealot 2 14988
16414
