Protoss_Gateway 2 6643
Protoss_Assimilator 1 4378
Protoss_Cybernetics_Core 1 5800
Protoss_Dragoon 8 13626
Singularity_Charge 1 10049
Protoss_Nexus 1 13869
Protoss_Citadel_of_Adun 1 12863
Protoss_Robotics_Facility 1 13908
Protoss_Templar_Archives 1 14415
Protoss_Shuttle 1 15482
Protoss_Dark_Templar 1 15660
15660
