Protoss_Gateway 3 12633
Protoss_Assimilator 1 4303
Protoss_Cybernetics_Core 1 5761
Protoss_Dragoon 13 15824
Protoss_Nexus 1 12324
Singularity_Charge 1 9757
Protoss_Shield_Battery 1 14019
Protoss_Robotics_Facility 1 15785
15824
