Protoss_Gateway 4 16035
Protoss_Assimilator 1 4673
Protoss_Zealot 1 5288
Protoss_Cybernetics_Core 1 6866
Protoss_Dragoon 9 15657
Protoss_Nexus 2 16313
Protoss_Robotics_Facility 1 12071
Singularity_Charge 1 11071
Protoss_Observatory 1 13037
Protoss_Observer 2 15318
16313
