Protoss_Gateway 2 9624
Protoss_Assimilator 1 4316
Protoss_Cybernetics_Core 1 5829
Protoss_Dragoon 11 15022
Singularity_Charge 1 9836
Protoss_Robotics_Facility 1 12294
Protoss_Robotics_Support_Bay 1 13223
Protoss_Reaver 1 15242
15242
