Protoss_Gateway 2 4726
Protoss_Zealot 11 12585
Protoss_Assimilator 1 7877
Protoss_Forge 1 7947
Protoss_Cybernetics_Core 1 10022
Protoss_Photon_Cannon 4 12194
Protoss_Dragoon 4 15221
Protoss_Robotics_Facility 1 15127
Protoss_Nexus 1 16508
16508
