Protoss_Nexus 1 6739
Protoss_Gateway 4 13196
Protoss_Assimilator 2 11468
Protoss_Cybernetics_Core 1 7414
Protoss_Zealot 2 13085
Protoss_Dragoon 9 15042
Protoss_Robotics_Facility 1 12014
Singularity_Charge 1 11914
Protoss_Observatory 1 12723
Protoss_Shuttle 1 13460
Protoss_Robotics_Support_Bay 1 14005
Protoss_Observer 1 14303
Protoss_Stargate 1 15502
Protoss_Reaver 1 15899
15899
