Protoss_Gateway 3 9214
Protoss_Zealot 2 7510
Protoss_Assimilator 1 6779
Protoss_Cybernetics_Core 1 8038
Protoss_Dragoon 9 15756
Singularity_Charge 1 12683
Protoss_Nexus 1 16157
16157
