Protoss_Gateway 3 16044
Protoss_Assimilator 1 4196
Protoss_Cybernetics_Core 1 5572
Protoss_Dragoon 6 13192
Protoss_Nexus 1 12567
Singularity_Charge 1 9841
Protoss_Robotics_Facility 1 12165
Protoss_Shuttle 1 14030
Protoss_Robotics_Support_Bay 1 13920
Protoss_Zealot 2 14888
Protoss_Reaver 1 15691
16044
