Protoss_Nexus 2 15552
Protoss_Gateway 2 8412
Protoss_Assimilator 2 11522
Protoss_Cybernetics_Core 1 7401
Protoss_Dragoon 3 10400
Protoss_Citadel_of_Adun 2 10136
Protoss_Zealot 2 11262
Protoss_Templar_Archives 1 11838
Singularity_Charge 1 11805
Protoss_Dark_Templar 5 15256
Protoss_Robotics_Facility 1 15243
15552
