Protoss_Gateway 5 15820
Protoss_Assimilator 2 13309
Protoss_Cybernetics_Core 1 5913
Protoss_Dragoon 9 14283
Singularity_Charge 1 10136
Protoss_Nexus 1 14005
Protoss_Robotics_Facility 1 13788
Protoss_Observatory 1 14545
Protoss_Citadel_of_Adun 1 15595
Protoss_Observer 1 15573
15820
