Protoss_Gateway 3 14342
Protoss_Assimilator 1 4381
Protoss_Cybernetics_Core 1 5822
Protoss_Dragoon 8 13751
Protoss_Robotics_Facility 1 9923
Singularity_Charge 1 9780
Protoss_Observatory 1 10626
Protoss_Nexus 1 13423
Protoss_Observer 2 12605
Protoss_Citadel_of_Adun 1 13321
Protoss_Zealot 3 15576
15576
