Protoss_Gateway 3 11897
Protoss_Assimilator 1 4594
Protoss_Cybernetics_Core 1 5840
Protoss_Dragoon 14 15547
Protoss_Robotics_Facility 1 10002
Singularity_Charge 1 9931
Protoss_Observatory 1 10728
Protoss_Observer 3 13744
15547
