Protoss_Gateway 4 15763
Protoss_Assimilator 1 4179
Protoss_Cybernetics_Core 1 5575
Protoss_Dragoon 7 12010
Singularity_Charge 1 9619
Protoss_Nexus 1 12608
Protoss_Robotics_Facility 1 12499
Protoss_Citadel_of_Adun 1 13062
Protoss_Zealot 4 14490
Protoss_Shuttle 1 14326
Protoss_Templar_Archives 2 14850
Protoss_Observatory 1 14451
Protoss_Observer 1 15479
15763
