Protoss_Gateway 3 15473
Protoss_Assimilator 2 14118
Protoss_Cybernetics_Core 1 6026
Protoss_Dragoon 6 15557
Protoss_Citadel_of_Adun 1 9336
Protoss_Robotics_Facility 1 10825
Protoss_Templar_Archives 1 10799
Protoss_Nexus 1 13032
Protoss_Dark_Templar 2 12007
Protoss_Shuttle 1 12444
Protoss_Observatory 1 12525
Protoss_Observer 1 14950
15557
