Protoss_Gateway 4 16029
Protoss_Assimilator 1 4199
Protoss_Cybernetics_Core 1 5721
Protoss_Dragoon 5 15724
Protoss_Robotics_Facility 1 9613
Singularity_Charge 1 9575
Protoss_Shuttle 1 11396
Protoss_Robotics_Support_Bay 1 10797
Protoss_Zealot 2 12239
Protoss_Reaver 1 13174
Protoss_Nexus 1 15631
Protoss_Observatory 1 13795
Protoss_Observer 1 15550
16029
