Protoss_Gateway 2 6456
Protoss_Assimilator 2 14995
Protoss_Cybernetics_Core 1 7354
Protoss_Zealot 1 7085
Protoss_Dragoon 6 13178
Protoss_Nexus 1 13901
Protoss_Citadel_of_Adun 1 13028
Singularity_Charge 1 12028
Protoss_Templar_Archives 1 14613
Protoss_Dark_Templar 2 15821
15821
