Protoss_Gateway 3 15836
Protoss_Assimilator 1 4204
Protoss_Cybernetics_Core 1 5610
Protoss_Dragoon 9 14673
Singularity_Charge 1 9280
Protoss_Nexus 2 14065
Protoss_Robotics_Facility 1 13719
Protoss_Observatory 1 14593
15836
