Protoss_Gateway 2 4817
Protoss_Zealot 2 5888
Protoss_Assimilator 1 6372
Protoss_Cybernetics_Core 1 7548
Protoss_Dragoon 10 15253
Protoss_Nexus 1 13236
Protoss_Robotics_Facility 1 15058
Singularity_Charge 1 14460
15253
