Protoss_Gateway 3 15555
Protoss_Assimilator 1 4357
Protoss_Cybernetics_Core 1 5629
Protoss_Dragoon 12 14846
Singularity_Charge 1 9417
Protoss_Nexus 1 15189
Protoss_Citadel_of_Adun 1 14834
Protoss_Robotics_Facility 1 15756
15756
