Protoss_Gateway 2 9703
Protoss_Assimilator 1 4232
Protoss_Cybernetics_Core 1 5626
Protoss_Zealot 1 5610
Protoss_Dragoon 4 15396
Protoss_Citadel_of_Adun 1 7908
Protoss_Robotics_Facility 1 9308
Protoss_Templar_Archives 1 10242
Protoss_Shuttle 1 11253
Protoss_Dark_Templar 3 12613
Protoss_Observatory 1 11694
Protoss_Nexus 2 16594
Protoss_Observer 2 15523
16594
