Protoss_Gateway 2 13155
Protoss_Assimilator 2 13470
Protoss_Cybernetics_Core 1 6263
Protoss_Dragoon 7 15455
Protoss_Nexus 2 17051
Protoss_Citadel_of_Adun 1 10723
Singularity_Charge 1 10269
Protoss_Templar_Archives 1 12242
Protoss_Stargate 1 13889
Protoss_Dark_Templar 1 13447
17051
