Protoss_Gateway 4 14948
Protoss_Assimilator 1 4220
Protoss_Cybernetics_Core 1 5604
Protoss_Dragoon 8 12745
Protoss_Robotics_Facility 1 9749
Singularity_Charge 1 9724
Protoss_Observatory 1 10550
Protoss_Observer 1 11712
Protoss_Citadel_of_Adun 1 13356
Protoss_Nexus 1 15406
Protoss_Templar_Archives 1 14851
Protoss_Shuttle 1 15312
15406
