Protoss_Gateway 2 10413
Protoss_Assimilator 1 4413
Protoss_Zealot 4 15248
Protoss_Cybernetics_Core 1 7092
Protoss_Dragoon 6 14024
Protoss_Robotics_Facility 1 9238
Protoss_Observatory 1 10027
Protoss_Observer 3 12828
Protoss_Nexus 1 14406
Singularity_Charge 1 12142
Protoss_Shuttle 1 14800
Protoss_Robotics_Support_Bay 1 14243
15248
