Protoss_Gateway 2 6251
Protoss_Assimilator 3 12349
Protoss_Zealot 7 10679
Protoss_Nexus 1 10536
Protoss_Cybernetics_Core 1 10556
Protoss_Dragoon 6 14908
Protoss_Robotics_Facility 1 15060
15060
