Protoss_Assimilator 3 9915
Protoss_Gateway 4 14033
Protoss_Zealot 6 14721
Protoss_Nexus 2 16989
Protoss_Cybernetics_Core 1 9623
Protoss_Dragoon 4 15048
Protoss_Citadel_of_Adun 1 12229
Protoss_Templar_Archives 1 14714
16989
