Protoss_Assimilator 2 12962
Protoss_Gateway 2 12087
Protoss_Cybernetics_Core 1 6245
Protoss_Dragoon 5 12563
Protoss_Nexus 2 17305
Protoss_Citadel_of_Adun 1 10678
Singularity_Charge 1 9944
Protoss_Robotics_Facility 1 12207
Protoss_Templar_Archives 1 12432
Protoss_Shuttle 1 13779
Protoss_High_Templar 4 15791
17305
