Protoss_Gateway 3 15475
Protoss_Nexus 1 8692
Protoss_Zealot 2 7709
Protoss_Assimilator 2 9914
Protoss_Cybernetics_Core 1 9141
Protoss_Dragoon 9 14899
Protoss_Robotics_Facility 1 13424
Protoss_Observatory 1 14208
Singularity_Charge 1 13515
15475
