Protoss_Nexus 1 6965
Protoss_Gateway 2 7066
Protoss_Assimilator 2 12656
Protoss_Cybernetics_Core 1 7852
Protoss_Zealot 1 7858
Protoss_Dragoon 10 14861
Protoss_Robotics_Facility 1 12627
Singularity_Charge 1 12353
Protoss_Observatory 1 13538
Protoss_Observer 1 14639
Protoss_Stargate 1 15828
15828
