Protoss_Gateway 5 14935
Protoss_Assimilator 1 4347
Protoss_Cybernetics_Core 1 5592
Protoss_Dragoon 8 15148
Protoss_Nexus 2 15394
Singularity_Charge 1 9745
Protoss_Robotics_Facility 1 12368
Protoss_Observatory 1 13109
Protoss_Zealot 3 14926
Protoss_Observer 2 15008
Protoss_Citadel_of_Adun 1 15743
15743
