Protoss_Gateway 2 9298
Protoss_Assimilator 1 4271
Protoss_Cybernetics_Core 1 5717
Protoss_Dragoon 8 14984
Protoss_Robotics_Facility 1 9089
Protoss_Observatory 1 9814
Singularity_Charge 1 9868
Protoss_Observer 2 12122
Protoss_Nexus 2 17400
Protoss_Shuttle 1 14010
Protoss_Robotics_Support_Bay 1 14131
17400
