Protoss_Forge 1 4426
Protoss_Photon_Cannon 6 12910
Protoss_Gateway 2 15112
Protoss_Assimilator 2 14459
Protoss_Cybernetics_Core 1 10084
Protoss_Nexus 1 12450
Protoss_Zealot 1 10671
Protoss_Citadel_of_Adun 1 12168
Protoss_Dragoon 2 13127
Protoss_Templar_Archives 1 14063
15112
