Protoss_Nexus 2 14346
Protoss_Gateway 2 7805
Protoss_Assimilator 2 14594
Protoss_Cybernetics_Core 1 7495
Protoss_Zealot 1 7735
Protoss_Dragoon 10 14486
Protoss_Robotics_Facility 1 13602
Singularity_Charge 1 13011
Protoss_Shuttle 1 15014
Protoss_Robotics_Support_Bay 1 14627
Protoss_Observatory 1 15297
15297
