Protoss_Gateway 2 6389
Protoss_Assimilator 2 14218
Protoss_Cybernetics_Core 1 5685
Protoss_Dragoon 6 12098
Protoss_Nexus 1 12000
Singularity_Charge 1 9350
Protoss_Citadel_of_Adun 1 10984
Protoss_Robotics_Facility 1 12177
Protoss_Templar_Archives 1 12737
Protoss_Shuttle 1 13785
Protoss_Dark_Templar 4 15148
Protoss_Observatory 1 15193
15193
