Protoss_Gateway 3 15355
Protoss_Assimilator 1 4110
Protoss_Cybernetics_Core 1 5547
Protoss_Dragoon 9 15704
Protoss_Nexus 1 12419
Singularity_Charge 1 9701
Protoss_Robotics_Facility 1 12026
Protoss_Shuttle 1 13436
Protoss_Robotics_Support_Bay 1 13280
Protoss_Reaver 1 15193
Protoss_Observatory 1 14934
15704
