Protoss_Gateway 2 8420
Protoss_Nexus 2 15813
Protoss_Assimilator 2 10956
Protoss_Cybernetics_Core 1 7632
Protoss_Zealot 1 8367
Protoss_Dragoon 9 14785
Protoss_Robotics_Facility 1 12150
Protoss_Observatory 1 12885
Singularity_Charge 1 12748
Protoss_Observer 2 14929
15813
