Protoss_Gateway 3 14165
Protoss_Assimilator 1 4394
Protoss_Zealot 1 5069
Protoss_Cybernetics_Core 1 6213
Protoss_Dragoon 8 15429
Protoss_Robotics_Facility 1 10052
Singularity_Charge 1 9935
Protoss_Nexus 1 12830
Protoss_Shuttle 1 12213
Protoss_Robotics_Support_Bay 1 11975
Protoss_Reaver 1 13771
Protoss_Observatory 1 13539
Protoss_Observer 1 14897
15429
