Protoss_Gateway 2 10445
Protoss_Assimilator 1 4154
Protoss_Cybernetics_Core 1 5813
Protoss_Dragoon 8 14981
Protoss_Robotics_Facility 1 9087
Protoss_Shuttle 1 10820
Singularity_Charge 1 9587
Protoss_Observatory 1 10462
Protoss_Robotics_Support_Bay 1 11278
Protoss_Observer 1 11663
Protoss_Reaver 1 13259
Protoss_Nexus 1 15555
15555
