Protoss_Nexus 2 15055
Protoss_Gateway 2 8275
Protoss_Assimilator 1 6209
Protoss_Cybernetics_Core 1 7586
Protoss_Dragoon 9 14992
Protoss_Zealot 2 13474
Protoss_Robotics_Facility 1 14963
Singularity_Charge 1 13076
15055
