Protoss_Gateway 2 14790
Protoss_Assimilator 1 4473
Protoss_Cybernetics_Core 1 5904
Protoss_Dragoon 7 15437
Protoss_Robotics_Facility 1 9783
Protoss_Zealot 2 10916
Protoss_Shuttle 1 11183
Protoss_Robotics_Support_Bay 1 10520
Singularity_Charge 1 9844
Protoss_Reaver 1 12741
Protoss_Nexus 1 14674
Protoss_Observatory 1 13015
Protoss_Observer 1 15108
15437
