Protoss_Nexus 2 14396
Protoss_Gateway 4 14557
Protoss_Assimilator 1 5742
Protoss_Cybernetics_Core 1 7419
Protoss_Zealot 1 7592
Protoss_Dragoon 11 15774
Singularity_Charge 1 11873
Protoss_Robotics_Facility 1 14019
Protoss_Observatory 1 14767
15774
