Protoss_Assimilator 2 7297
Protoss_Gateway 2 10130
Protoss_Zealot 2 7755
Protoss_Nexus 1 8951
Protoss_Cybernetics_Core 1 8939
Protoss_Dragoon 6 13866
Protoss_Shield_Battery 1 11041
Protoss_Robotics_Facility 1 13384
Protoss_Shuttle 1 14827
Singularity_Charge 1 13447
Protoss_Robotics_Support_Bay 1 14570
14827
