Protoss_Gateway 3 10609
Protoss_Zealot 4 6771
Protoss_Assimilator 2 13592
Protoss_Cybernetics_Core 1 8528
Protoss_Nexus 1 10669
Protoss_Dragoon 12 15244
Protoss_Shield_Battery 1 13097
Singularity_Charge 1 12880
15244
