Protoss_Gateway 3 11174
Protoss_Assimilator 1 4407
Protoss_Cybernetics_Core 1 5966
Protoss_Dragoon 13 14820
Protoss_Nexus 1 11861
Singularity_Charge 1 10055
Protoss_Robotics_Facility 1 14984
14984
