Protoss_Gateway 1 4350
Protoss_Assimilator 1 4551
Protoss_Zealot 2 11496
Protoss_Cybernetics_Core 1 7212
Protoss_Dragoon 5 15156
Protoss_Robotics_Facility 1 10450
Protoss_Robotics_Support_Bay 1 11147
Protoss_Shuttle 1 12228
Protoss_Reaver 2 15325
15325
