Protoss_Gateway 1 4152
Protoss_Assimilator 1 4251
Protoss_Cybernetics_Core 1 5808
Protoss_Dragoon 6 13552
Protoss_Robotics_Facility 1 10017
Protoss_Observatory 1 10750
Singularity_Charge 1 10081
Protoss_Nexus 2 16521
Protoss_Observer 3 13691
Protoss_Forge 2 14796
Protoss_Citadel_of_Adun 1 15820
16521
