Protoss_Gateway 4 14755
Protoss_Assimilator 1 4217
Protoss_Cybernetics_Core 1 5666
Protoss_Dragoon 8 15431
Protoss_Nexus 2 12472
Singularity_Charge 1 9748
Protoss_Robotics_Facility 1 12042
Protoss_Observatory 1 12768
Protoss_Observer 1 14247
15431
