Protoss_Assimilator 3 14177
Protoss_Gateway 2 9091
Protoss_Zealot 2 7041
Protoss_Cybernetics_Core 1 8114
Protoss_Nexus 2 15289
Protoss_Dragoon 7 14182
Singularity_Charge 1 12139
Protoss_Robotics_Facility 1 15030
15289
