Protoss_Gateway 2 10928
Protoss_Assimilator 1 4447
Protoss_Cybernetics_Core 1 5841
Protoss_Dragoon 9 14272
Protoss_Robotics_Facility 1 10314
Singularity_Charge 1 9880
Protoss_Shuttle 1 11809
Protoss_Observatory 1 11621
Protoss_Observer 2 15318
Protoss_Robotics_Support_Bay 1 12566
Protoss_Reaver 1 14494
Protoss_Nexus 1 17033
17033
