Protoss_Gateway 4 15880
Protoss_Assimilator 2 13836
Protoss_Cybernetics_Core 1 5903
Protoss_Dragoon 6 15393
Protoss_Nexus 2 16224
Protoss_Citadel_of_Adun 1 10729
Singularity_Charge 1 10190
Protoss_Zealot 2 11894
Protoss_Templar_Archives 1 12552
Protoss_Dark_Templar 2 14293
16224
