Protoss_Gateway 2 12254
Protoss_Assimilator 1 4246
Protoss_Cybernetics_Core 1 5753
Protoss_Dragoon 5 11398
Protoss_Nexus 1 11569
Protoss_Citadel_of_Adun 1 11001
Singularity_Charge 1 9771
Protoss_Robotics_Facility 1 12907
Protoss_Templar_Archives 1 12526
Protoss_Zealot 1 12632
Protoss_Dark_Templar 4 14984
Protoss_Shuttle 1 14338
Protoss_High_Templar 2 15174
Protoss_Forge 1 15119
15174
