Protoss_Gateway 2 10208
Protoss_Assimilator 1 4492
Protoss_Cybernetics_Core 1 5772
Protoss_Zealot 1 5639
Protoss_Dragoon 10 15426
Protoss_Robotics_Facility 1 9973
Protoss_Observatory 1 10766
Singularity_Charge 1 10093
Protoss_Observer 2 13027
Protoss_Nexus 1 16202
Protoss_Shuttle 1 14996
Protoss_Robotics_Support_Bay 1 15314
16202
