Protoss_Gateway 2 16059
Protoss_Assimilator 1 4409
Protoss_Zealot 3 12119
Protoss_Cybernetics_Core 1 6848
Protoss_Dragoon 6 15797
Protoss_Robotics_Facility 1 9695
Protoss_Shuttle 2 15989
Protoss_Robotics_Support_Bay 1 10664
Singularity_Charge 1 10594
Protoss_Reaver 1 12670
Protoss_Observatory 1 12658
Protoss_Nexus 1 15379
Protoss_Observer 1 14028
16059
