Protoss_Gateway 2 11527
Protoss_Assimilator 1 4368
Protoss_Zealot 2 6836
Protoss_Cybernetics_Core 1 7068
Protoss_Dragoon 5 13087
Protoss_Nexus 2 17362
Protoss_Citadel_of_Adun 1 10545
Protoss_Robotics_Facility 1 12594
Protoss_Templar_Archives 1 12659
Protoss_Dark_Templar 2 14188
Protoss_Shuttle 1 14578
Protoss_Observatory 1 13961
Protoss_Observer 1 15421
17362
