Protoss_Gateway 2 11076
Protoss_Assimilator 1 4403
Protoss_Cybernetics_Core 1 5846
Protoss_Dragoon 9 13945
Protoss_Robotics_Facility 1 10415
Singularity_Charge 1 9900
Protoss_Shuttle 1 11818
Protoss_Observatory 1 11714
Protoss_Observer 1 12737
Protoss_Robotics_Support_Bay 1 13172
Protoss_Reaver 1 14904
Protoss_Zealot 1 14882
Protoss_Nexus 1 17456
17456
