Protoss_Gateway 2 13600
Protoss_Assimilator 1 4416
Protoss_Cybernetics_Core 1 5831
Protoss_Dragoon 8 15063
Protoss_Robotics_Facility 1 9813
Protoss_Observatory 1 10526
Singularity_Charge 1 9967
Protoss_Nexus 1 13306
Protoss_Observer 1 11560
Protoss_Robotics_Support_Bay 1 11701
Protoss_Shuttle 1 14584
Protoss_Reaver 1 16153
16153
