Protoss_Gateway 2 6487
Protoss_Assimilator 1 4527
Protoss_Cybernetics_Core 1 5860
Protoss_Dragoon 12 15774
Singularity_Charge 1 9836
Protoss_Nexus 2 15880
Protoss_Robotics_Facility 1 15654
15880
