Protoss_Gateway 3 13253
Protoss_Assimilator 1 4469
Protoss_Cybernetics_Core 1 5907
Protoss_Dragoon 12 15636
Protoss_Nexus 1 11657
Singularity_Charge 1 9868
Protoss_Robotics_Facility 1 12089
Protoss_Observatory 1 13696
Protoss_Observer 1 14715
15636
