Protoss_Nexus 2 16702
Protoss_Gateway 3 14354
Protoss_Assimilator 1 5748
Protoss_Cybernetics_Core 1 7392
Protoss_Zealot 1 7498
Protoss_Dragoon 6 12224
Protoss_Citadel_of_Adun 1 11686
Singularity_Charge 1 11653
Protoss_Templar_Archives 1 13135
Protoss_Dark_Templar 1 15578
16702
