Protoss_Gateway 3 13520
Protoss_Assimilator 1 4215
Protoss_Cybernetics_Core 1 5786
Protoss_Dragoon 8 14957
Protoss_Robotics_Facility 1 9620
Protoss_Observatory 1 10393
Singularity_Charge 1 9856
Protoss_Nexus 1 14048
Protoss_Observer 3 14355
Protoss_Shuttle 1 14028
14957
