Protoss_Gateway 2 15658
Protoss_Assimilator 1 4359
Protoss_Cybernetics_Core 1 5952
Protoss_Dragoon 8 15563
Protoss_Robotics_Facility 1 8511
Protoss_Shuttle 1 9921
Protoss_Robotics_Support_Bay 1 9411
Protoss_Reaver 1 11716
Protoss_Observatory 1 11436
Protoss_Observer 2 13422
Protoss_Nexus 1 16348
Singularity_Charge 1 14273
16348
