Protoss_Gateway 3 14863
Protoss_Assimilator 1 4722
Protoss_Cybernetics_Core 1 6470
Protoss_Dragoon 9 15278
Protoss_Robotics_Facility 1 11624
Singularity_Charge 1 10670
Protoss_Observatory 1 12559
Protoss_Nexus 1 15346
Protoss_Observer 2 15239
Protoss_Forge 1 15295
15346
