Protoss_Gateway 4 14783
Protoss_Assimilator 2 14686
Protoss_Cybernetics_Core 1 5907
Protoss_Zealot 1 6172
Protoss_Dragoon 6 15429
Protoss_Citadel_of_Adun 2 14985
Protoss_Nexus 2 15444
Protoss_Robotics_Facility 1 12004
Singularity_Charge 1 11659
Protoss_Observatory 1 12733
Protoss_Observer 2 14710
15444
