Protoss_Gateway 2 15529
Protoss_Assimilator 1 4773
Protoss_Zealot 2 11683
Protoss_Cybernetics_Core 1 7319
Protoss_Dragoon 6 15411
Protoss_Robotics_Facility 1 9945
Protoss_Shuttle 1 11388
Protoss_Robotics_Support_Bay 1 10822
Singularity_Charge 1 10992
Protoss_Reaver 2 16063
Protoss_Observatory 1 13346
Protoss_Nexus 1 16205
Protoss_Observer 1 14367
16205
