Protoss_Gateway 2 10233
Protoss_Assimilator 1 4452
Protoss_Cybernetics_Core 1 5835
Protoss_Dragoon 11 15581
Protoss_Robotics_Facility 1 10276
Singularity_Charge 1 9994
Protoss_Shuttle 1 11674
Protoss_Robotics_Support_Bay 1 11826
Protoss_Reaver 2 15454
15581
