Protoss_Gateway 2 5227
Protoss_Zealot 5 7246
Protoss_Assimilator 2 15507
Protoss_Cybernetics_Core 1 8241
Protoss_Dragoon 8 15467
Protoss_Robotics_Facility 1 11828
Protoss_Nexus 1 13977
Protoss_Observatory 1 12574
Protoss_Observer 2 14563
15507
