Protoss_Gateway 2 8554
Protoss_Assimilator 1 4208
Protoss_Cybernetics_Core 1 5688
Protoss_Dragoon 8 15115
Protoss_Robotics_Facility 1 8268
Protoss_Observatory 1 9881
Protoss_Observer 2 15359
Protoss_Shuttle 1 12307
Singularity_Charge 1 11091
Protoss_Robotics_Support_Bay 1 12566
Protoss_Zealot 2 13346
Protoss_Reaver 1 14535
Protoss_Nexus 1 16205
Protoss_Citadel_of_Adun 1 15691
16205
