Protoss_Gateway 2 4960
Protoss_Zealot 14 14077
Protoss_Forge 1 6075
Protoss_Photon_Cannon 4 12262
Protoss_Assimilator 1 12599
Protoss_Cybernetics_Core 1 13918
Protoss_Dragoon 2 15358
15358
