Protoss_Gateway 2 6465
Protoss_Assimilator 2 15171
Protoss_Cybernetics_Core 1 5654
Protoss_Zealot 1 6251
Protoss_Dragoon 8 15710
Protoss_Nexus 2 14545
Protoss_Robotics_Facility 1 11814
Protoss_Observatory 1 12748
Protoss_Observer 2 14639
Singularity_Charge 1 13910
Protoss_Robotics_Support_Bay 1 14720
15710
