Protoss_Gateway 3 14392
Protoss_Assimilator 2 14696
Protoss_Zealot 1 5221
Protoss_Cybernetics_Core 1 6899
Protoss_Dragoon 9 15824
Protoss_Citadel_of_Adun 1 8458
Protoss_Templar_Archives 1 9908
Protoss_Nexus 1 12069
Protoss_Dark_Templar 1 11103
Protoss_Robotics_Facility 1 12699
Protoss_Observatory 1 13450
Protoss_Observer 1 14467
Singularity_Charge 1 13957
15824
