Protoss_Gateway 4 15198
Protoss_Assimilator 1 4496
Protoss_Cybernetics_Core 1 5829
Protoss_Dragoon 9 14217
Protoss_Robotics_Facility 1 10118
Singularity_Charge 1 10038
Protoss_Observatory 1 10908
Protoss_Nexus 1 13353
Protoss_Observer 3 15061
Protoss_Shuttle 1 15784
15784
