Protoss_Gateway 2 8429
Protoss_Assimilator 2 14988
Protoss_Cybernetics_Core 1 5843
Protoss_Citadel_of_Adun 1 7334
Protoss_Dragoon 6 15490
Protoss_Templar_Archives 1 8951
Protoss_Dark_Templar 4 11653
Protoss_Nexus 1 13913
Protoss_Stargate 1 13947
15490
