Protoss_Gateway 1 4103
Protoss_Assimilator 1 4378
Protoss_Cybernetics_Core 1 5791
Protoss_Dragoon 5 15385
Protoss_Robotics_Facility 1 8651
Protoss_Zealot 2 10791
Protoss_Shuttle 1 10053
Protoss_Robotics_Support_Bay 1 9672
Protoss_Reaver 1 11611
Protoss_Nexus 1 14030
Protoss_Observatory 1 12575
Protoss_Observer 1 13594
15385
