Protoss_Gateway 3 15021
Protoss_Assimilator 2 12907
Protoss_Cybernetics_Core 1 6162
Protoss_Dragoon 6 15323
Protoss_Nexus 1 11182
Protoss_Robotics_Facility 1 11249
Singularity_Charge 1 9850
Protoss_Shuttle 1 12769
Protoss_Observatory 1 12373
Protoss_Robotics_Support_Bay 1 12493
Protoss_Zealot 2 14136
Protoss_Reaver 1 14836
15323
