Protoss_Gateway 2 12592
Protoss_Assimilator 1 4161
Protoss_Cybernetics_Core 1 5849
Protoss_Dragoon 8 15060
Protoss_Robotics_Facility 1 9649
Singularity_Charge 1 9669
Protoss_Observatory 1 10392
Protoss_Observer 1 11443
Protoss_Nexus 1 13647
Protoss_Shuttle 1 13056
Protoss_Robotics_Support_Bay 1 12991
Protoss_Zealot 1 13697
Protoss_Reaver 1 14974
15060
