Protoss_Gateway 3 14592
Protoss_Assimilator 1 4245
Protoss_Cybernetics_Core 1 5742
Protoss_Dragoon 11 15253
Protoss_Robotics_Facility 1 9663
Singularity_Charge 1 9707
Protoss_Observatory 1 10573
Protoss_Observer 1 12280
Protoss_Nexus 1 14583
15253
