Protoss_Gateway 4 15989
Protoss_Assimilator 1 4035
Protoss_Cybernetics_Core 1 5625
Protoss_Dragoon 10 15420
Protoss_Nexus 2 15242
Protoss_Robotics_Facility 1 10745
Singularity_Charge 1 9575
Protoss_Observatory 1 11685
Protoss_Observer 3 14873
15989
