Protoss_Gateway 2 10793
Protoss_Assimilator 1 4251
Protoss_Cybernetics_Core 1 5818
Protoss_Dragoon 6 14641
Protoss_Citadel_of_Adun 1 9716
Protoss_Robotics_Facility 1 10797
Singularity_Charge 1 9490
Protoss_Templar_Archives 1 12116
Protoss_Shuttle 1 12953
Protoss_Dark_Templar 2 13526
Protoss_Observatory 1 13785
Protoss_Zealot 1 14294
Protoss_Observer 1 14873
Protoss_Nexus 1 17346
17346
