Protoss_Gateway 2 13049
Protoss_Assimilator 1 4246
Protoss_Cybernetics_Core 1 5553
Protoss_Dragoon 10 15379
Protoss_Robotics_Facility 1 9800
Singularity_Charge 1 9490
Protoss_Nexus 1 12716
Protoss_Observatory 1 10645
Protoss_Observer 2 12538
Protoss_Shuttle 1 13896
Protoss_Robotics_Support_Bay 1 13825
Protoss_Reaver 1 15588
15588
