Protoss_Gateway 3 15871
Protoss_Assimilator 2 15274
Protoss_Cybernetics_Core 1 5868
Protoss_Dragoon 9 15013
Protoss_Nexus 1 12041
Singularity_Charge 1 9742
Protoss_Robotics_Facility 1 12447
Protoss_Observatory 1 13509
Protoss_Shuttle 1 14592
Protoss_Observer 2 15444
15871
