Protoss_Nexus 2 13732
Protoss_Gateway 6 15248
Protoss_Assimilator 1 5849
Protoss_Cybernetics_Core 1 7319
Protoss_Zealot 1 7489
Protoss_Dragoon 10 14758
Singularity_Charge 1 11630
Protoss_Robotics_Facility 1 13991
Protoss_Observatory 1 15007
15248
