Protoss_Gateway 2 13233
Protoss_Assimilator 1 4376
Protoss_Cybernetics_Core 1 5809
Protoss_Dragoon 7 15268
Protoss_Robotics_Facility 1 9949
Singularity_Charge 1 9607
Protoss_Nexus 1 12821
Protoss_Observatory 1 10999
Protoss_Observer 1 12043
Protoss_Robotics_Support_Bay 1 12710
Protoss_Shuttle 1 14086
Protoss_Reaver 1 15644
15644
