Protoss_Gateway 3 12785
Protoss_Assimilator 1 4622
Protoss_Cybernetics_Core 1 6094
Protoss_Dragoon 5 12489
Protoss_Robotics_Facility 2 11523
Protoss_Observatory 1 12249
Protoss_Observer 1 13575
Protoss_Zealot 3 14475
Singularity_Charge 1 13187
Protoss_Shuttle 1 14974
14974
