Protoss_Gateway 2 8095
Protoss_Assimilator 2 14973
Protoss_Cybernetics_Core 1 5607
Protoss_Dragoon 10 15025
Singularity_Charge 1 9560
Protoss_Nexus 1 12555
Protoss_Robotics_Facility 1 13383
Protoss_Citadel_of_Adun 1 13761
Protoss_Shuttle 1 14891
Protoss_Robotics_Support_Bay 1 14952
Protoss_Templar_Archives 1 15914
15914
