Protoss_Gateway 6 15956
Protoss_Assimilator 1 4433
Protoss_Cybernetics_Core 1 5686
Protoss_Dragoon 6 14419
Protoss_Robotics_Facility 1 9885
Singularity_Charge 1 9862
Protoss_Observatory 1 10614
Protoss_Nexus 2 14961
Protoss_Observer 3 13454
15956
