Protoss_Gateway 2 10224
Protoss_Assimilator 1 4559
Protoss_Cybernetics_Core 1 6026
Protoss_Dragoon 10 15256
Protoss_Robotics_Facility 1 10216
Singularity_Charge 1 10000
Protoss_Observatory 1 10973
Protoss_Observer 2 13071
Protoss_Nexus 1 14411
Protoss_Shuttle 1 14610
Protoss_Robotics_Support_Bay 1 14024
Protoss_Reaver 1 16174
16174
