Protoss_Gateway 2 16062
Protoss_Assimilator 1 4469
Protoss_Cybernetics_Core 1 6046
Protoss_Dragoon 6 14872
Protoss_Robotics_Facility 1 10039
Singularity_Charge 1 9856
Protoss_Shuttle 1 11452
Protoss_Robotics_Support_Bay 1 11136
Protoss_Zealot 2 12722
Protoss_Reaver 2 14801
Protoss_Observatory 1 12515
Protoss_Nexus 1 15593
16062
