Protoss_Gateway 3 7546
Protoss_Assimilator 1 6529
Protoss_Cybernetics_Core 1 8873
Protoss_Zealot 2 8528
Protoss_Dragoon 8 15271
Protoss_Nexus 1 14809
Singularity_Charge 1 13017
Protoss_Robotics_Facility 1 15518
Protoss_Stargate 1 16265
16265
