Protoss_Nexus 2 16802
Protoss_Gateway 3 13477
Protoss_Assimilator 2 11698
Protoss_Cybernetics_Core 1 7177
Protoss_Zealot 3 13073
Protoss_Dragoon 8 14193
Protoss_Robotics_Facility 2 12963
Singularity_Charge 1 11820
Protoss_Shuttle 1 14575
Protoss_Robotics_Support_Bay 1 13981
Protoss_Reaver 1 16133
16802
