Protoss_Gateway 2 11167
Protoss_Assimilator 1 4211
Protoss_Zealot 2 6798
Protoss_Cybernetics_Core 1 6819
Protoss_Dragoon 6 13760
Protoss_Robotics_Facility 1 10494
Protoss_Observatory 1 11223
Protoss_Observer 2 13117
Singularity_Charge 1 11396
Protoss_Nexus 1 14734
Protoss_Shuttle 1 14475
Protoss_Robotics_Support_Bay 1 14234
Protoss_Reaver 1 16033
16033
