Protoss_Gateway 2 12959
Protoss_Assimilator 2 4728
Protoss_Cybernetics_Core 1 6307
Protoss_Dragoon 9 15388
Protoss_Nexus 1 12093
Singularity_Charge 1 10245
Protoss_Robotics_Facility 1 12430
Protoss_Observatory 1 13924
Protoss_Observer 1 14947
15388
