Protoss_Gateway 3 12410
Protoss_Assimilator 1 4394
Protoss_Cybernetics_Core 1 5911
Protoss_Dragoon 6 14283
Protoss_Robotics_Facility 1 10066
Singularity_Charge 1 9711
Protoss_Observatory 1 11033
Protoss_Observer 1 12053
Protoss_Zealot 4 13773
Protoss_Shuttle 1 13411
14283
