Protoss_Gateway 3 10697
Protoss_Assimilator 1 4712
Protoss_Zealot 10 13577
Protoss_Cybernetics_Core 1 7310
Protoss_Dragoon 2 14021
Protoss_Citadel_of_Adun 1 9150
Protoss_Templar_Archives 1 13666
Leg_Enhancements 1 12361
Protoss_Dark_Templar 3 15121
15121
