Protoss_Gateway 4 15684
Protoss_Assimilator 1 4311
Protoss_Cybernetics_Core 1 5699
Protoss_Dragoon 9 15631
Protoss_Nexus 2 16574
Protoss_Citadel_of_Adun 1 10275
Singularity_Charge 1 9707
Protoss_Robotics_Facility 1 11934
Protoss_Templar_Archives 1 12039
Protoss_Shuttle 1 13395
Protoss_Dark_Templar 2 13547
Protoss_Observatory 1 13296
Protoss_Observer 1 14762
16574
