Protoss_Gateway 4 15806
Protoss_Assimilator 1 4619
Protoss_Cybernetics_Core 1 5976
Protoss_Dragoon 8 13093
Protoss_Robotics_Facility 1 10186
Singularity_Charge 1 9961
Protoss_Observatory 1 11198
Protoss_Observer 1 12280
Protoss_Shuttle 1 13960
Protoss_Nexus 1 15789
Protoss_Robotics_Support_Bay 1 13939
Protoss_Zealot 2 14496
Protoss_Reaver 1 16247
16247
