Protoss_Gateway 3 11973
Protoss_Zealot 2 7679
Protoss_Assimilator 1 6201
Protoss_Cybernetics_Core 1 8082
Protoss_Dragoon 7 14594
Protoss_Robotics_Facility 1 12001
Singularity_Charge 1 11770
Protoss_Observatory 1 12695
Protoss_Nexus 1 15669
Protoss_Observer 2 14663
Protoss_Shuttle 1 15391
Protoss_Robotics_Support_Bay 1 15004
15669
