Protoss_Gateway 4 14806
Protoss_Assimilator 1 4590
Protoss_Cybernetics_Core 1 5948
Protoss_Nexus 2 14299
Protoss_Dragoon 10 14966
Singularity_Charge 1 10848
Protoss_Robotics_Facility 1 13908
Protoss_Observatory 1 14795
14966
