Protoss_Nexus 1 6957
Protoss_Gateway 2 7689
Protoss_Assimilator 1 5824
Protoss_Cybernetics_Core 1 7479
Protoss_Zealot 4 15356
Protoss_Dragoon 9 15314
Protoss_Robotics_Facility 1 11501
Protoss_Shuttle 1 12901
Protoss_Robotics_Support_Bay 1 12560
Protoss_Reaver 1 14532
Protoss_Observatory 1 14072
Singularity_Charge 1 13702
15356
