Protoss_Gateway 4 15311
Protoss_Assimilator 1 4205
Protoss_Cybernetics_Core 1 5831
Protoss_Dragoon 10 15704
Protoss_Nexus 2 16050
Singularity_Charge 1 9499
Protoss_Citadel_of_Adun 1 14892
16050
