Protoss_Gateway 4 14528
Protoss_Zealot 1 4940
Protoss_Assimilator 1 6375
Protoss_Cybernetics_Core 1 8241
Protoss_Dragoon 10 15115
Protoss_Nexus 1 13688
Singularity_Charge 1 11990
Protoss_Robotics_Facility 1 14645
15115
