Protoss_Gateway 3 15626
Protoss_Assimilator 2 13855
Protoss_Cybernetics_Core 1 5911
Protoss_Dragoon 10 15452
Protoss_Nexus 1 9779
Protoss_Robotics_Facility 1 11310
Protoss_Observatory 1 12007
Singularity_Charge 1 11322
Protoss_Observer 2 14162
Protoss_Shuttle 1 15561
Protoss_Robotics_Support_Bay 1 14919
Protoss_Zealot 2 15421
15626
