Protoss_Gateway 4 15166
Protoss_Assimilator 1 4255
Protoss_Cybernetics_Core 1 5685
Protoss_Dragoon 7 14302
Protoss_Robotics_Facility 1 8138
Protoss_Observatory 1 9035
Protoss_Nexus 2 15494
Protoss_Observer 3 12023
Singularity_Charge 1 13038
15494
