Protoss_Assimilator 2 5093
Protoss_Gateway 3 14377
Protoss_Cybernetics_Core 1 6468
Protoss_Dragoon 13 15824
Singularity_Charge 1 10573
Protoss_Nexus 1 13615
Protoss_Citadel_of_Adun 1 15504
15824
