Protoss_Gateway 2 8311
Protoss_Assimilator 1 4498
Protoss_Cybernetics_Core 1 5808
Protoss_Dragoon 12 15393
Singularity_Charge 1 9476
Protoss_Nexus 1 12842
Protoss_Robotics_Facility 1 12196
Protoss_Shuttle 1 13788
Protoss_Robotics_Support_Bay 1 13329
Protoss_Reaver 1 15346
15393
