Protoss_Gateway 2 6830
Protoss_Assimilator 1 4553
Protoss_Cybernetics_Core 1 5878
Protoss_Dragoon 7 14515
Protoss_Nexus 2 13786
Singularity_Charge 1 10014
Protoss_Citadel_of_Adun 1 13003
Protoss_Templar_Archives 1 14808
Protoss_Stargate 1 15391
15391
