Protoss_Nexus 1 6906
Protoss_Gateway 3 15020
Protoss_Assimilator 2 11967
Protoss_Cybernetics_Core 1 7378
Protoss_Zealot 1 7911
Protoss_Dragoon 12 15101
Protoss_Robotics_Facility 1 11976
Singularity_Charge 1 11167
Protoss_Shuttle 1 13407
Protoss_Robotics_Support_Bay 1 13655
Protoss_Reaver 1 15706
Protoss_Stargate 1 16199
16199
