Protoss_Nexus 1 6660
Protoss_Gateway 2 7492
Protoss_Assimilator 2 12512
Protoss_Cybernetics_Core 1 7316
Protoss_Zealot 2 13381
Protoss_Dragoon 9 14911
Protoss_Robotics_Facility 1 11635
Protoss_Shuttle 1 13056
Singularity_Charge 1 11911
Protoss_Robotics_Support_Bay 1 12670
Protoss_Reaver 1 14801
14911
