Protoss_Gateway 2 15585
Protoss_Assimilator 1 4420
Protoss_Cybernetics_Core 1 5831
Protoss_Dragoon 7 15569
Protoss_Robotics_Facility 1 8278
Protoss_Shuttle 2 15160
Protoss_Robotics_Support_Bay 1 9534
Protoss_Zealot 2 10729
Protoss_Reaver 1 11339
Protoss_Observatory 1 11843
Protoss_Nexus 1 14733
Protoss_Observer 1 12992
15585
