Protoss_Gateway 3 15254
Protoss_Assimilator 1 4258
Protoss_Cybernetics_Core 1 5686
Protoss_Dragoon 9 15780
Protoss_Nexus 3 15461
Singularity_Charge 1 9710
Protoss_Robotics_Facility 1 14799
15780
