Protoss_Gateway 2 6383
Protoss_Assimilator 1 4312
Protoss_Cybernetics_Core 1 5570
Protoss_Dragoon 11 14351
Singularity_Charge 1 9563
Protoss_Robotics_Facility 1 12559
Protoss_Nexus 2 17232
Protoss_Observatory 1 13289
Protoss_Observer 1 15175
17232
