Protoss_Nexus 1 6775
Protoss_Gateway 2 7818
Protoss_Assimilator 2 10938
Protoss_Cybernetics_Core 1 7428
Protoss_Dragoon 11 14817
Protoss_Robotics_Facility 1 11931
Singularity_Charge 1 11852
Protoss_Shuttle 1 13387
Protoss_Observatory 2 14567
Protoss_Robotics_Support_Bay 1 12903
Protoss_Reaver 1 14945
14945
