Protoss_Nexus 1 6915
Protoss_Gateway 4 15141
Protoss_Assimilator 2 10622
Protoss_Zealot 2 8420
Protoss_Cybernetics_Core 1 8409
Protoss_Dragoon 9 15443
Protoss_Forge 1 11832
Protoss_Robotics_Facility 1 13137
Protoss_Photon_Cannon 1 13403
Singularity_Charge 1 12461
Protoss_Citadel_of_Adun 1 14348
Protoss_Observatory 1 13876
Protoss_Observer 1 14926
Protoss_Templar_Archives 1 15898
15898
