Protoss_Gateway 2 13109
Protoss_Assimilator 1 4354
Protoss_Cybernetics_Core 1 5683
Protoss_Dragoon 8 15391
Protoss_Robotics_Facility 1 9761
Protoss_Observatory 1 10459
Singularity_Charge 1 9824
Protoss_Observer 3 13357
Protoss_Nexus 1 13732
Protoss_Shuttle 1 13864
Protoss_Robotics_Support_Bay 1 13212
Protoss_Reaver 1 15422
15422
