Protoss_Gateway 5 15529
Protoss_Assimilator 1 4341
Protoss_Cybernetics_Core 1 5529
Protoss_Dragoon 6 9797
Protoss_Nexus 2 13740
Singularity_Charge 1 9221
Protoss_Citadel_of_Adun 1 12991
Protoss_Templar_Archives 1 14559
15529
