Protoss_Gateway 2 15528
Protoss_Zealot 5 12684
Protoss_Assimilator 2 14550
Protoss_Nexus 1 12709
Protoss_Forge 1 10877
Protoss_Cybernetics_Core 1 12230
Protoss_Photon_Cannon 2 13296
Protoss_Citadel_of_Adun 1 14079
Protoss_Robotics_Facility 1 15364
Protoss_Templar_Archives 1 15737
15737
