Protoss_Gateway 2 9981
Protoss_Assimilator 1 4267
Protoss_Cybernetics_Core 1 5749
Protoss_Dragoon 8 15089
Protoss_Robotics_Facility 1 9686
Singularity_Charge 1 9642
Protoss_Observatory 1 10532
Protoss_Nexus 2 15770
Protoss_Observer 2 12825
Protoss_Shuttle 1 14183
Protoss_Robotics_Support_Bay 1 13945
Protoss_Reaver 1 15741
Protoss_Zealot 2 15400
15770
