Protoss_Gateway 2 10283
Protoss_Assimilator 1 4390
Protoss_Cybernetics_Core 1 5565
Protoss_Dragoon 3 9499
Protoss_Robotics_Facility 1 9873
Protoss_Citadel_of_Adun 1 9566
Protoss_Templar_Archives 1 11045
Protoss_Shuttle 1 11309
Protoss_Robotics_Support_Bay 1 10724
Protoss_Dark_Templar 4 14387
Protoss_Reaver 2 14947
Protoss_Nexus 1 15880
15880
