Protoss_Gateway 3 13711
Protoss_Assimilator 2 14136
Protoss_Cybernetics_Core 1 5655
Protoss_Dragoon 9 15411
Protoss_Nexus 1 10490
Protoss_Robotics_Facility 1 10759
Protoss_Observatory 1 11764
Protoss_Shuttle 1 12851
Singularity_Charge 1 11876
Protoss_Observer 1 13694
Protoss_Robotics_Support_Bay 1 13689
Protoss_Reaver 1 15413
Protoss_Zealot 2 15538
15538
