Protoss_Assimilator 1 3522
Protoss_Gateway 3 15570
Protoss_Cybernetics_Core 1 6207
Protoss_Robotics_Facility 1 8177
Protoss_Dragoon 6 14524
Protoss_Shuttle 1 9582
Protoss_Robotics_Support_Bay 1 10894
Protoss_Forge 1 11279
Protoss_Photon_Cannon 1 12573
Protoss_Reaver 1 13786
Protoss_Nexus 1 16269
16269
