Protoss_Gateway 2 12191
Protoss_Assimilator 1 4150
Protoss_Cybernetics_Core 1 5623
Protoss_Dragoon 10 14877
Protoss_Nexus 1 11592
Singularity_Charge 1 9593
Protoss_Robotics_Facility 1 11597
Protoss_Observatory 1 12554
Protoss_Observer 3 15519
15519
