Protoss_Gateway 2 7466
Protoss_Assimilator 1 5019
Protoss_Cybernetics_Core 1 6242
Protoss_Dragoon 7 14132
Protoss_Nexus 2 14143
Singularity_Charge 1 10398
Protoss_Forge 2 13046
Protoss_Robotics_Facility 1 16002
16002
