Protoss_Gateway 3 12146
Protoss_Assimilator 1 4315
Protoss_Cybernetics_Core 1 5892
Protoss_Dragoon 10 14457
Protoss_Nexus 1 11342
Protoss_Robotics_Facility 1 11149
Singularity_Charge 1 9827
Protoss_Observatory 1 11887
Protoss_Observer 2 13785
14457
