Protoss_Gateway 4 14922
Protoss_Nexus 1 7594
Protoss_Assimilator 2 10463
Protoss_Cybernetics_Core 1 7796
Protoss_Zealot 3 14698
Protoss_Dragoon 8 13833
Protoss_Robotics_Facility 1 12730
Singularity_Charge 1 12361
Protoss_Observatory 1 13509
Protoss_Stargate 2 15763
Protoss_Observer 1 14534
Protoss_Fleet_Beacon 1 16009
Protoss_Shuttle 1 16041
16041
