Protoss_Gateway 2 8259
Protoss_Assimilator 2 12367
Protoss_Cybernetics_Core 1 6225
Protoss_Dragoon 5 14375
Protoss_Nexus 1 11059
Protoss_Robotics_Facility 1 10858
Singularity_Charge 1 9903
Protoss_Stargate 2 16178
Protoss_Observatory 1 11886
Protoss_Fleet_Beacon 1 13214
Protoss_Zealot 4 15514
Protoss_Observer 1 14153
Protoss_Carrier 1 17111
17111
