Protoss_Assimilator 3 6972
Protoss_Gateway 2 12943
Protoss_Cybernetics_Core 1 6356
Protoss_Dragoon 10 15712
Protoss_Nexus 2 16606
Singularity_Charge 1 10365
Protoss_Robotics_Facility 1 12387
Protoss_Observatory 1 13127
Protoss_Observer 2 15105
16606
