Protoss_Gateway 1 4111
Protoss_Assimilator 1 4214
Protoss_Cybernetics_Core 1 5680
Protoss_Zealot 1 5575
Protoss_Dragoon 8 15007
Protoss_Robotics_Facility 1 11239
Singularity_Charge 1 9941
Protoss_Shuttle 1 12705
Protoss_Robotics_Support_Bay 1 12276
Protoss_Observatory 1 12686
Protoss_Reaver 1 14263
Protoss_Observer 1 15122
15122
