Protoss_Nexus 1 7026
Protoss_Gateway 5 15551
Protoss_Assimilator 1 6115
Protoss_Cybernetics_Core 1 8086
Protoss_Zealot 4 15362
Protoss_Dragoon 13 15388
Protoss_Robotics_Facility 1 12987
Singularity_Charge 1 12116
Protoss_Shuttle 1 14689
Protoss_Observatory 1 15096
15551
