Protoss_Gateway 3 12043
Protoss_Assimilator 1 4132
Protoss_Cybernetics_Core 1 5666
Protoss_Robotics_Facility 1 7705
Protoss_Shuttle 1 9113
Protoss_Dragoon 10 15746
Singularity_Charge 1 10458
Protoss_Observatory 1 11712
Protoss_Observer 2 13622
Protoss_Nexus 1 16237
16237
