Protoss_Nexus 1 7503
Protoss_Gateway 4 15785
Protoss_Assimilator 2 12495
Protoss_Cybernetics_Core 1 7842
Protoss_Zealot 1 7466
Protoss_Dragoon 8 14695
Protoss_Robotics_Facility 1 10690
Protoss_Observatory 1 11514
Protoss_Observer 1 12749
Singularity_Charge 1 13999
Protoss_Robotics_Support_Bay 1 15159
15785
