Protoss_Gateway 2 15769
Protoss_Assimilator 1 4152
Protoss_Cybernetics_Core 1 5607
Protoss_Dragoon 6 14697
Protoss_Robotics_Facility 1 8069
Protoss_Shuttle 1 9497
Protoss_Robotics_Support_Bay 1 9503
Protoss_Reaver 4 15893
Protoss_Nexus 1 15087
15893
