Protoss_Gateway 3 12955
Protoss_Assimilator 1 4331
Protoss_Cybernetics_Core 1 5617
Protoss_Dragoon 11 15660
Protoss_Zealot 1 7676
Protoss_Robotics_Facility 1 9398
Protoss_Observatory 1 10236
Singularity_Charge 1 9584
Protoss_Nexus 2 16989
Protoss_Observer 5 15383
16989
