Protoss_Gateway 2 9538
Protoss_Assimilator 1 4409
Protoss_Cybernetics_Core 1 5869
Protoss_Dragoon 7 12591
Protoss_Robotics_Facility 1 9862
Singularity_Charge 1 9859
Protoss_Observatory 1 10831
Protoss_Observer 2 12746
Protoss_Nexus 2 15488
Protoss_Shuttle 1 14490
Protoss_Robotics_Support_Bay 1 14056
Protoss_Reaver 1 16048
16048
