Protoss_Nexus 2 16620
Protoss_Gateway 2 8625
Protoss_Assimilator 2 12910
Protoss_Cybernetics_Core 1 7416
Protoss_Zealot 2 10954
Protoss_Dragoon 8 13532
Protoss_Robotics_Facility 1 11384
Protoss_Observatory 1 12134
Singularity_Charge 1 11469
Protoss_Observer 2 14186
16620
