Protoss_Gateway 2 10335
Protoss_Assimilator 1 4431
Protoss_Cybernetics_Core 1 5829
Protoss_Zealot 3 15242
Protoss_Dragoon 8 13784
Protoss_Robotics_Facility 1 9844
Protoss_Observatory 1 10608
Singularity_Charge 1 9947
Protoss_Observer 2 13237
Protoss_Nexus 1 15030
Protoss_Shuttle 1 14824
Protoss_Robotics_Support_Bay 1 14826
15242
