Protoss_Assimilator 2 6908
Protoss_Gateway 2 9728
Protoss_Zealot 3 8449
Protoss_Cybernetics_Core 1 7706
Protoss_Nexus 1 10129
Protoss_Dragoon 9 14878
Protoss_Robotics_Facility 1 14849
Singularity_Charge 1 13128
14878
