Protoss_Forge 1 4088
Protoss_Photon_Cannon 4 8606
Protoss_Gateway 2 11205
Protoss_Assimilator 2 15573
Protoss_Cybernetics_Core 1 9504
Protoss_Zealot 3 15544
Protoss_Dragoon 6 14682
Protoss_Nexus 1 14504
15573
