Protoss_Gateway 2 8136
Protoss_Zealot 2 5803
Protoss_Assimilator 1 6416
Protoss_Cybernetics_Core 1 7766
Protoss_Dragoon 7 14913
Protoss_Robotics_Facility 1 12316
Singularity_Charge 1 11791
Protoss_Nexus 1 14861
Protoss_Observatory 1 13654
Protoss_Observer 1 14850
Protoss_Robotics_Support_Bay 1 14988
14988
