Protoss_Gateway 3 13492
Protoss_Assimilator 1 4299
Protoss_Zealot 2 13512
Protoss_Cybernetics_Core 1 6017
Protoss_Robotics_Facility 1 8026
Protoss_Dragoon 9 15733
Protoss_Observatory 1 9010
Protoss_Observer 2 11590
Protoss_Nexus 1 12936
Singularity_Charge 1 11185
15733
