Protoss_Gateway 2 11911
Protoss_Assimilator 2 13875
Protoss_Zealot 2 6368
Protoss_Cybernetics_Core 1 6747
Protoss_Dragoon 8 14630
Protoss_Nexus 1 12254
Protoss_Robotics_Facility 1 11837
Singularity_Charge 1 10875
Protoss_Shuttle 1 13278
Protoss_Observatory 1 12636
Protoss_Robotics_Support_Bay 1 13428
Protoss_Observer 1 14121
Protoss_Reaver 1 16253
16253
