Protoss_Gateway 3 15251
Protoss_Assimilator 2 15169
Protoss_Cybernetics_Core 1 5894
Protoss_Dragoon 7 14419
Protoss_Robotics_Facility 1 10289
Protoss_Nexus 1 12947
Singularity_Charge 1 10117
Protoss_Shuttle 1 12020
Protoss_Robotics_Support_Bay 1 11994
Protoss_Reaver 1 13938
Protoss_Observatory 1 13443
Protoss_Observer 1 14762
15251
