Protoss_Gateway 2 10618
Protoss_Assimilator 1 4104
Protoss_Cybernetics_Core 1 5467
Protoss_Dragoon 7 15791
Protoss_Robotics_Facility 1 9974
Singularity_Charge 1 9695
Protoss_Shuttle 1 11414
Protoss_Nexus 2 17220
Protoss_Robotics_Support_Bay 1 11423
Protoss_Reaver 1 13253
Protoss_Observatory 1 12694
Protoss_Zealot 2 13021
Protoss_Observer 2 14958
17220
