Protoss_Gateway 4 14587
Protoss_Assimilator 1 4676
Protoss_Cybernetics_Core 1 6590
Protoss_Dragoon 8 15350
Protoss_Nexus 2 14528
Singularity_Charge 1 10371
Protoss_Robotics_Facility 1 16094
16094
