Protoss_Gateway 2 11645
Protoss_Assimilator 1 4270
Protoss_Cybernetics_Core 1 5838
Protoss_Dragoon 8 15516
Protoss_Robotics_Facility 1 9557
Protoss_Nexus 2 15684
Singularity_Charge 1 9660
Protoss_Observatory 1 10441
Protoss_Observer 3 13571
15684
