Protoss_Gateway 3 12860
Protoss_Zealot 4 7913
Protoss_Assimilator 1 6307
Protoss_Cybernetics_Core 1 8001
Protoss_Dragoon 9 15458
Protoss_Nexus 1 15066
Singularity_Charge 1 12347
Protoss_Robotics_Facility 1 14624
Protoss_Observatory 1 15317
15458
