Protoss_Gateway 4 15593
Protoss_Assimilator 2 14764
Protoss_Cybernetics_Core 1 5796
Protoss_Dragoon 3 9224
Protoss_Citadel_of_Adun 1 9245
Protoss_Robotics_Facility 1 9818
Protoss_Templar_Archives 1 10786
Protoss_Shuttle 1 11241
Protoss_Dark_Templar 6 14808
Protoss_Nexus 1 14728
15593
