Protoss_Gateway 1 4264
Protoss_Assimilator 1 4400
Protoss_Cybernetics_Core 1 5784
Protoss_Zealot 3 12512
Protoss_Dragoon 6 14732
Protoss_Robotics_Facility 1 10107
Singularity_Charge 1 9704
Protoss_Shuttle 1 11502
Protoss_Robotics_Support_Bay 1 11183
Protoss_Reaver 1 13060
Protoss_Observatory 1 12252
Protoss_Observer 2 14869
Protoss_Nexus 1 16461
16461
