Protoss_Gateway 2 13328
Protoss_Assimilator 1 4542
Protoss_Zealot 2 6137
Protoss_Cybernetics_Core 1 6254
Protoss_Dragoon 6 14729
Protoss_Robotics_Facility 1 10333
Singularity_Charge 1 10166
Protoss_Observatory 1 11030
Protoss_Nexus 1 13697
Protoss_Observer 2 13170
Protoss_Citadel_of_Adun 1 12918
Protoss_Shuttle 1 14276
Protoss_Templar_Archives 1 14434
Protoss_Dark_Templar 1 15712
15712
