Protoss_Gateway 2 7545
Protoss_Assimilator 2 13707
Protoss_Cybernetics_Core 1 5570
Protoss_Dragoon 12 14319
Protoss_Nexus 1 13279
Protoss_Citadel_of_Adun 1 13490
Protoss_Templar_Archives 1 15608
Protoss_Robotics_Facility 1 16226
16226
