Protoss_Gateway 2 8139
Protoss_Assimilator 1 4409
Protoss_Cybernetics_Core 1 5803
Protoss_Dragoon 10 14896
Singularity_Charge 1 9716
Protoss_Nexus 2 14181
Protoss_Robotics_Facility 1 13778
Protoss_Shuttle 1 15304
Protoss_Robotics_Support_Bay 1 14818
Protoss_Observatory 1 14883
15304
