Protoss_Nexus 1 6628
Protoss_Gateway 4 14724
Protoss_Assimilator 2 10359
Protoss_Cybernetics_Core 1 7439
Protoss_Dragoon 13 15186
Protoss_Robotics_Facility 1 12276
Singularity_Charge 1 11653
Protoss_Observatory 1 13296
Protoss_Observer 2 15307
Protoss_Citadel_of_Adun 1 16049
16049
