Protoss_Gateway 2 14288
Protoss_Assimilator 2 14250
Protoss_Cybernetics_Core 1 6061
Protoss_Dragoon 8 14998
Protoss_Nexus 1 11642
Singularity_Charge 1 9768
Protoss_Robotics_Facility 1 12399
Protoss_Observatory 1 13111
Protoss_Robotics_Support_Bay 1 13687
Protoss_Citadel_of_Adun 1 14493
Protoss_Observer 1 14127
Protoss_Shuttle 1 15526
15526
