Protoss_Gateway 2 12487
Protoss_Assimilator 1 4164
Protoss_Cybernetics_Core 1 5607
Protoss_Zealot 1 5511
Protoss_Dragoon 8 13766
Protoss_Robotics_Facility 1 10529
Singularity_Charge 1 9853
Protoss_Nexus 2 17013
Protoss_Observatory 1 11409
Protoss_Observer 4 15273
17013
