Protoss_Gateway 2 10035
Protoss_Assimilator 1 4413
Protoss_Cybernetics_Core 1 6131
Protoss_Dragoon 12 15265
Singularity_Charge 1 10213
Protoss_Forge 1 11753
Protoss_Nexus 1 14829
Protoss_Photon_Cannon 2 15102
15265
