Protoss_Gateway 2 12058
Protoss_Assimilator 2 14622
Protoss_Cybernetics_Core 1 6192
Protoss_Zealot 2 14771
Protoss_Dragoon 7 14990
Protoss_Nexus 1 11738
Protoss_Robotics_Facility 1 11831
Singularity_Charge 1 10155
Protoss_Shuttle 1 13296
Protoss_Observatory 1 12699
Protoss_Robotics_Support_Bay 1 13795
Protoss_Observer 1 14139
Protoss_Reaver 1 15890
15890
