Protoss_Gateway 2 12535
Protoss_Assimilator 1 4442
Protoss_Cybernetics_Core 1 5870
Protoss_Dragoon 8 14732
Protoss_Robotics_Facility 1 8417
Protoss_Observatory 1 9478
Protoss_Shuttle 1 10632
Protoss_Observer 3 13237
Singularity_Charge 1 11653
Protoss_Robotics_Support_Bay 1 13310
Protoss_Nexus 1 15997
15997
