Protoss_Assimilator 3 14657
Protoss_Gateway 3 16034
Protoss_Cybernetics_Core 1 6876
Protoss_Dragoon 6 13087
Protoss_Nexus 1 13031
Singularity_Charge 1 10661
Protoss_Robotics_Facility 1 12979
Protoss_Citadel_of_Adun 1 14218
Protoss_Observatory 1 14047
Protoss_Stargate 1 15106
Protoss_Observer 1 15081
Protoss_Templar_Archives 1 15860
16034
