Protoss_Assimilator 2 5159
Protoss_Gateway 2 8664
Protoss_Cybernetics_Core 1 6703
Protoss_Dragoon 10 15115
Singularity_Charge 1 10444
Protoss_Nexus 2 17081
Protoss_Robotics_Facility 1 16246
Protoss_Citadel_of_Adun 1 16043
17081
