Protoss_Gateway 4 13521
Protoss_Assimilator 3 5199
Protoss_Zealot 1 5519
Protoss_Cybernetics_Core 1 6962
Protoss_Nexus 2 11179
Protoss_Dragoon 12 15739
Singularity_Charge 1 12502
Protoss_Robotics_Facility 1 15193
15739
