Protoss_Gateway 2 9286
Protoss_Assimilator 1 4422
Protoss_Cybernetics_Core 1 5856
Protoss_Zealot 4 14923
Protoss_Dragoon 8 14492
Protoss_Robotics_Facility 1 11015
Singularity_Charge 1 10286
Protoss_Observatory 1 11991
Protoss_Observer 1 13252
Protoss_Nexus 1 15912
Protoss_Shuttle 1 15456
15912
