Protoss_Gateway 3 15669
Protoss_Zealot 4 13416
Protoss_Assimilator 1 5521
Protoss_Cybernetics_Core 1 6664
Protoss_Dragoon 6 14896
Protoss_Nexus 1 10872
Protoss_Robotics_Facility 1 10945
Protoss_Shuttle 1 12394
Protoss_Robotics_Support_Bay 1 12092
Protoss_Reaver 1 13952
Protoss_Observatory 1 13528
Protoss_Observer 1 14777
15669
