Protoss_Gateway 5 15406
Protoss_Assimilator 1 4243
Protoss_Cybernetics_Core 1 5730
Protoss_Robotics_Facility 1 7833
Protoss_Dragoon 8 15142
Protoss_Observatory 1 9145
Protoss_Observer 4 13346
Protoss_Nexus 2 13934
Singularity_Charge 1 10878
15406
