Protoss_Gateway 2 8569
Protoss_Assimilator 1 4466
Protoss_Zealot 3 7185
Protoss_Cybernetics_Core 1 7319
Protoss_Dragoon 3 10511
Protoss_Robotics_Facility 1 10555
Protoss_Citadel_of_Adun 1 11174
Protoss_Templar_Archives 1 12652
Protoss_Shuttle 1 12681
Singularity_Charge 1 11475
Protoss_Dark_Templar 4 14963
Protoss_Nexus 1 16913
16913
