Protoss_Gateway 2 9506
Protoss_Assimilator 2 13665
Protoss_Forge 1 7201
Protoss_Cybernetics_Core 1 7960
Protoss_Dragoon 6 14357
Protoss_Nexus 1 11700
Protoss_Citadel_of_Adun 1 11955
Protoss_Robotics_Facility 1 13005
Singularity_Charge 1 11633
Protoss_Templar_Archives 1 13998
Protoss_Robotics_Support_Bay 1 14782
Protoss_Shield_Battery 1 14829
Protoss_Dark_Templar 2 15537
15537
