Protoss_Gateway 3 16051
Protoss_Assimilator 1 4583
Protoss_Cybernetics_Core 1 6204
Protoss_Zealot 1 6201
Protoss_Dragoon 9 14861
Singularity_Charge 1 10523
Protoss_Nexus 1 15125
Protoss_Robotics_Facility 1 14316
Protoss_Citadel_of_Adun 1 14222
Protoss_Templar_Archives 1 15708
Protoss_Observatory 1 15083
16051
