Protoss_Gateway 1 4161
Protoss_Assimilator 1 4398
Protoss_Zealot 1 5165
Protoss_Cybernetics_Core 1 6172
Protoss_Robotics_Facility 1 8179
Protoss_Dragoon 6 14714
Protoss_Shuttle 1 9582
Protoss_Robotics_Support_Bay 1 9549
Protoss_Reaver 2 15269
Protoss_Observatory 1 11315
Protoss_Observer 2 13618
Protoss_Nexus 1 17138
17138
