Protoss_Gateway 2 13060
Protoss_Assimilator 1 4495
Protoss_Cybernetics_Core 1 5865
Protoss_Zealot 3 14238
Protoss_Dragoon 8 15739
Protoss_Nexus 1 11918
Protoss_Robotics_Facility 1 12152
Singularity_Charge 1 10380
Protoss_Shuttle 1 13714
Protoss_Robotics_Support_Bay 1 13551
Protoss_Reaver 1 15454
15739
