Protoss_Gateway 2 11133
Protoss_Assimilator 1 4568
Protoss_Cybernetics_Core 1 5856
Protoss_Dragoon 10 15115
Protoss_Robotics_Facility 1 10743
Singularity_Charge 1 10032
Protoss_Observatory 1 11558
Protoss_Observer 2 15011
Protoss_Nexus 1 14801
15115
