Protoss_Nexus 1 7356
Protoss_Gateway 4 13141
Protoss_Assimilator 2 10770
Protoss_Cybernetics_Core 1 8146
Protoss_Dragoon 12 14802
Protoss_Citadel_of_Adun 1 11745
Singularity_Charge 1 12089
14802
