Protoss_Gateway 4 14829
Protoss_Assimilator 1 4256
Protoss_Cybernetics_Core 1 5718
Protoss_Dragoon 12 14868
Singularity_Charge 1 9748
Protoss_Nexus 1 13852
Protoss_Robotics_Facility 1 14129
Protoss_Observatory 1 14886
Protoss_Citadel_of_Adun 1 16028
16028
