Protoss_Gateway 2 5162
Protoss_Zealot 2 6245
Protoss_Assimilator 1 6504
Protoss_Cybernetics_Core 1 8108
Protoss_Dragoon 8 14779
Protoss_Robotics_Facility 1 13927
Protoss_Nexus 1 15060
Singularity_Charge 1 12593
Protoss_Robotics_Support_Bay 1 14786
Protoss_Shuttle 1 15874
15874
