Protoss_Gateway 2 13370
Protoss_Assimilator 1 4577
Protoss_Cybernetics_Core 1 6015
Protoss_Dragoon 6 15311
Protoss_Stargate 1 9714
Protoss_Fleet_Beacon 1 11373
Singularity_Charge 1 10067
Protoss_Carrier 1 14931
Protoss_Robotics_Facility 1 14559
Protoss_Nexus 1 17355
17355
