Protoss_Gateway 5 15997
Protoss_Assimilator 1 4319
Protoss_Cybernetics_Core 1 5876
Protoss_Dragoon 8 14934
Protoss_Robotics_Facility 1 8363
Protoss_Observatory 1 9146
Protoss_Nexus 2 16020
Protoss_Observer 2 11212
Singularity_Charge 1 12657
16020
