Protoss_Gateway 5 13853
Protoss_Assimilator 2 14373
Protoss_Cybernetics_Core 1 5999
Protoss_Dragoon 8 15350
Protoss_Robotics_Facility 1 10097
Singularity_Charge 1 9944
Protoss_Observatory 1 10860
Protoss_Nexus 1 13348
Protoss_Observer 5 15585
15585
