Protoss_Gateway 2 9513
Protoss_Assimilator 2 6684
Protoss_Zealot 4 9181
Protoss_Cybernetics_Core 1 8434
Protoss_Dragoon 10 15587
Singularity_Charge 1 12836
Protoss_Nexus 1 16262
16262
