Protoss_Gateway 2 8996
Protoss_Assimilator 1 4697
Protoss_Cybernetics_Core 1 6210
Protoss_Zealot 1 6040
Protoss_Dragoon 11 15742
Protoss_Nexus 1 12245
Singularity_Charge 1 10456
Protoss_Robotics_Facility 1 13119
Protoss_Shuttle 1 15667
Protoss_Robotics_Support_Bay 1 15101
15742
