Protoss_Gateway 4 15684
Protoss_Assimilator 2 13511
Protoss_Cybernetics_Core 1 5784
Protoss_Dragoon 9 14542
Protoss_Robotics_Facility 1 10047
Singularity_Charge 1 9862
Protoss_Nexus 1 12946
Protoss_Observatory 1 10899
Protoss_Observer 3 13987
Protoss_Citadel_of_Adun 1 13365
Protoss_Templar_Archives 1 15289
Protoss_Stargate 1 15681
15684
