Protoss_Gateway 2 10916
Protoss_Assimilator 2 15131
Protoss_Cybernetics_Core 1 5578
Protoss_Dragoon 9 15657
Protoss_Nexus 1 11138
Protoss_Robotics_Facility 1 10816
Singularity_Charge 1 9736
Protoss_Shuttle 1 12473
Protoss_Robotics_Support_Bay 1 12165
Protoss_Observatory 1 13563
Protoss_Reaver 1 15173
15657
