Protoss_Nexus 1 6587
Protoss_Gateway 2 7504
Protoss_Assimilator 1 5721
Protoss_Cybernetics_Core 1 7155
Protoss_Zealot 1 7524
Protoss_Dragoon 10 15022
Singularity_Charge 1 11527
Protoss_Robotics_Facility 1 13505
Protoss_Observatory 1 15221
15221
