Protoss_Gateway 2 12131
Protoss_Assimilator 1 4311
Protoss_Cybernetics_Core 1 5669
Protoss_Zealot 3 14616
Protoss_Dragoon 10 15809
Protoss_Nexus 1 11894
Singularity_Charge 1 9724
Protoss_Robotics_Facility 1 11910
Protoss_Shuttle 1 13389
Protoss_Robotics_Support_Bay 1 13351
Protoss_Reaver 1 15407
Protoss_Observatory 1 14590
15809
