Protoss_Nexus 1 7243
Protoss_Gateway 3 13758
Protoss_Assimilator 1 6555
Protoss_Cybernetics_Core 1 7807
Protoss_Zealot 4 14955
Protoss_Dragoon 7 13798
Protoss_Robotics_Facility 1 12639
Protoss_Robotics_Support_Bay 1 13693
Singularity_Charge 1 13307
Protoss_Shuttle 1 14903
14955
