Protoss_Gateway 4 15757
Protoss_Assimilator 1 4381
Protoss_Zealot 5 14783
Protoss_Cybernetics_Core 1 5933
Protoss_Citadel_of_Adun 1 7384
Protoss_Dragoon 1 7298
Protoss_Templar_Archives 1 9001
Protoss_Dark_Templar 7 13617
Protoss_Nexus 1 13960
15757
