Protoss_Gateway 4 14448
Protoss_Assimilator 1 4202
Protoss_Cybernetics_Core 1 5661
Protoss_Dragoon 8 15648
Protoss_Nexus 2 14557
Singularity_Charge 1 9689
Protoss_Robotics_Facility 1 11900
Protoss_Observatory 1 12816
Protoss_Observer 2 15336
15648
