Protoss_Gateway 2 15406
Protoss_Assimilator 1 4448
Protoss_Cybernetics_Core 1 5859
Protoss_Dragoon 5 15759
Protoss_Robotics_Facility 1 9496
Protoss_Shuttle 1 11229
Protoss_Robotics_Support_Bay 1 10724
Singularity_Charge 1 10711
Protoss_Reaver 1 12787
Protoss_Zealot 1 13073
Protoss_Nexus 1 15453
15759
