Protoss_Assimilator 3 12634
Protoss_Gateway 3 15977
Protoss_Zealot 3 9140
Protoss_Nexus 1 9122
Protoss_Cybernetics_Core 1 9269
Protoss_Dragoon 9 15221
Protoss_Robotics_Facility 1 13990
Singularity_Charge 1 13474
Protoss_Shuttle 1 15427
Protoss_Robotics_Support_Bay 1 15025
15977
