Protoss_Nexus 2 14515
Protoss_Gateway 4 14090
Protoss_Assimilator 2 13662
Protoss_Cybernetics_Core 1 7539
Protoss_Zealot 1 7744
Protoss_Dragoon 8 14199
Protoss_Robotics_Facility 1 12262
Protoss_Observatory 1 13241
Singularity_Charge 1 12549
Protoss_Observer 2 15310
15310
