Protoss_Gateway 3 13758
Protoss_Assimilator 2 13536
Protoss_Cybernetics_Core 1 5825
Protoss_Dragoon 7 15203
Protoss_Nexus 1 11607
Singularity_Charge 1 9821
Protoss_Robotics_Facility 1 12093
Protoss_Citadel_of_Adun 1 13220
Protoss_Observatory 1 12806
Protoss_Observer 1 14025
Protoss_Templar_Archives 1 14677
Protoss_Stargate 1 15217
Protoss_Zealot 2 14944
15217
