Protoss_Gateway 3 15402
Protoss_Nexus 1 7833
Protoss_Assimilator 1 6119
Protoss_Cybernetics_Core 1 7177
Protoss_Zealot 1 7458
Protoss_Dragoon 10 14985
Protoss_Robotics_Facility 1 12683
Protoss_Robotics_Support_Bay 1 13538
Protoss_Shuttle 1 14638
Protoss_Reaver 1 16200
16200
