Protoss_Gateway 2 9153
Protoss_Assimilator 1 4597
Protoss_Cybernetics_Core 1 6007
Protoss_Dragoon 7 15756
Protoss_Robotics_Facility 1 10630
Singularity_Charge 1 9935
Protoss_Zealot 4 12866
Protoss_Shuttle 1 12228
Protoss_Observatory 1 11987
Protoss_Observer 2 14338
Protoss_Nexus 2 16682
16682
