Protoss_Gateway 3 15607
Protoss_Assimilator 1 4357
Protoss_Cybernetics_Core 1 5800
Protoss_Zealot 3 14642
Protoss_Dragoon 8 15762
Protoss_Nexus 1 11981
Protoss_Robotics_Facility 1 11435
Singularity_Charge 1 9730
Protoss_Shuttle 1 12851
Protoss_Robotics_Support_Bay 1 12893
Protoss_Reaver 1 14722
Protoss_Observatory 1 14612
15762
