Protoss_Gateway 3 13464
Protoss_Assimilator 1 4517
Protoss_Cybernetics_Core 1 6314
Protoss_Dragoon 9 15221
Protoss_Robotics_Facility 1 8392
Protoss_Shuttle 1 9984
Protoss_Observatory 1 9451
Protoss_Observer 4 15459
Singularity_Charge 1 11840
15459
