Protoss_Gateway 3 15977
Protoss_Assimilator 2 14957
Protoss_Cybernetics_Core 1 5630
Protoss_Dragoon 7 14975
Protoss_Citadel_of_Adun 1 8625
Protoss_Templar_Archives 1 10126
Singularity_Charge 1 9830
Protoss_Dark_Templar 4 12669
Protoss_Nexus 1 13855
15977
