Protoss_Assimilator 1 4433
Protoss_Gateway 2 14882
Protoss_Cybernetics_Core 1 6365
Protoss_Zealot 1 6078
Protoss_Dragoon 6 15692
Protoss_Nexus 2 13310
Singularity_Charge 1 10216
Protoss_Robotics_Facility 1 13309
Protoss_Observatory 1 14874
15692
