Protoss_Nexus 1 6701
Protoss_Gateway 4 14273
Protoss_Assimilator 2 12015
Protoss_Zealot 5 14607
Protoss_Cybernetics_Core 1 7732
Protoss_Dragoon 7 13746
Protoss_Robotics_Facility 1 11651
Protoss_Observatory 1 12607
Singularity_Charge 1 12151
Protoss_Observer 3 15380
15380
