Protoss_Gateway 4 14948
Protoss_Assimilator 1 4523
Protoss_Cybernetics_Core 1 6096
Protoss_Dragoon 12 15825
Protoss_Robotics_Facility 1 9955
Protoss_Observatory 1 10692
Singularity_Charge 1 10033
Protoss_Observer 2 15478
Protoss_Citadel_of_Adun 1 14999
15825
