Protoss_Nexus 2 17133
Protoss_Gateway 4 13744
Protoss_Assimilator 2 10278
Protoss_Cybernetics_Core 1 7521
Protoss_Zealot 2 7676
Protoss_Dragoon 8 13918
Protoss_Robotics_Facility 2 14141
Protoss_Citadel_of_Adun 1 13227
Singularity_Charge 1 12154
Protoss_Observatory 1 14877
17133
