Protoss_Nexus 1 7377
Protoss_Forge 1 5976
Protoss_Photon_Cannon 7 14580
Protoss_Gateway 3 14311
Protoss_Assimilator 2 11227
Protoss_Cybernetics_Core 1 10492
Protoss_Citadel_of_Adun 1 12267
Protoss_Templar_Archives 1 13714
Protoss_Dark_Templar 3 15511
15511
