Protoss_Gateway 3 12128
Protoss_Assimilator 1 4234
Protoss_Cybernetics_Core 1 5846
Protoss_Robotics_Facility 1 7798
Protoss_Dragoon 9 14597
Protoss_Observatory 1 8952
Protoss_Observer 3 13030
Protoss_Nexus 1 12120
Singularity_Charge 1 10898
14597
