Protoss_Gateway 2 15915
Protoss_Assimilator 1 4264
Protoss_Cybernetics_Core 1 5791
Protoss_Zealot 3 14470
Protoss_Dragoon 6 13254
Protoss_Robotics_Facility 1 9829
Singularity_Charge 1 10011
Protoss_Observatory 1 10733
Protoss_Nexus 1 13298
Protoss_Observer 1 11914
Protoss_Shuttle 1 13272
Protoss_Robotics_Support_Bay 1 13195
Protoss_Reaver 1 14997
15915
