Protoss_Nexus 1 6546
Protoss_Gateway 4 15806
Protoss_Assimilator 2 10520
Protoss_Cybernetics_Core 1 7347
Protoss_Zealot 4 14528
Protoss_Dragoon 8 13620
Protoss_Robotics_Facility 1 11761
Singularity_Charge 1 11363
Protoss_Shuttle 1 13202
Protoss_Robotics_Support_Bay 1 13013
Protoss_Reaver 1 14854
Protoss_Observatory 1 14777
Protoss_Citadel_of_Adun 1 15931
15931
