Protoss_Gateway 3 12443
Protoss_Assimilator 1 4233
Protoss_Cybernetics_Core 1 5714
Protoss_Zealot 1 5446
Protoss_Dragoon 11 15355
Protoss_Nexus 1 11557
Singularity_Charge 1 9704
Protoss_Robotics_Facility 1 11676
Protoss_Observatory 1 12849
Protoss_Observer 2 15052
15355
