Protoss_Gateway 3 12626
Protoss_Assimilator 1 4234
Protoss_Cybernetics_Core 1 5794
Protoss_Dragoon 6 12069
Protoss_Robotics_Facility 1 9625
Singularity_Charge 1 9716
Protoss_Observatory 1 10443
Protoss_Citadel_of_Adun 1 11370
Protoss_Observer 3 14903
Protoss_Zealot 8 15427
15427
