Protoss_Gateway 4 14513
Protoss_Assimilator 1 4398
Protoss_Cybernetics_Core 1 5765
Protoss_Dragoon 10 14767
Protoss_Robotics_Facility 1 9728
Protoss_Observatory 1 10418
Singularity_Charge 1 9865
Protoss_Observer 2 12315
Protoss_Nexus 1 14662
Protoss_Citadel_of_Adun 1 14420
Protoss_Shuttle 1 15514
15514
