Protoss_Gateway 6 15488
Protoss_Assimilator 1 4126
Protoss_Cybernetics_Core 1 5758
Protoss_Zealot 1 5528
Protoss_Dragoon 9 15736
Singularity_Charge 1 9449
Protoss_Nexus 1 12975
Protoss_Robotics_Facility 1 12884
Protoss_Observatory 1 13803
Protoss_Observer 1 15014
15736
