Protoss_Gateway 2 6981
Protoss_Assimilator 2 14830
Protoss_Cybernetics_Core 1 5686
Protoss_Dragoon 6 14975
Protoss_Citadel_of_Adun 1 8497
Protoss_Zealot 1 8367
Protoss_Robotics_Facility 1 10422
Protoss_Templar_Archives 1 10193
Protoss_Dark_Templar 3 15405
Protoss_Shuttle 1 11838
Protoss_Nexus 1 13708
Protoss_Stargate 1 13281
Protoss_Arbiter_Tribunal 1 15580
15580
