Protoss_Gateway 4 14882
Protoss_Assimilator 1 4220
Protoss_Cybernetics_Core 1 5619
Protoss_Dragoon 11 14849
Protoss_Nexus 1 11654
Singularity_Charge 1 9578
Protoss_Zealot 1 11543
Protoss_Robotics_Facility 1 14593
14882
