Protoss_Gateway 2 11970
Protoss_Assimilator 1 4556
Protoss_Cybernetics_Core 1 5907
Protoss_Zealot 1 5692
Protoss_Dragoon 6 13298
Protoss_Nexus 1 11446
Singularity_Charge 1 10032
Protoss_Citadel_of_Adun 1 11472
Protoss_Robotics_Facility 1 13125
Protoss_Templar_Archives 1 13088
Protoss_Shuttle 1 14519
Protoss_Dark_Templar 2 14501
14519
