Protoss_Gateway 4 13208
Protoss_Nexus 1 7484
Protoss_Zealot 4 15389
Protoss_Assimilator 1 6128
Protoss_Cybernetics_Core 1 7717
Protoss_Dragoon 11 15139
Protoss_Robotics_Facility 1 12155
Singularity_Charge 1 11934
Protoss_Observatory 1 12925
Protoss_Observer 1 13992
15389
