Protoss_Nexus 1 6565
Protoss_Gateway 4 13019
Protoss_Assimilator 2 10501
Protoss_Cybernetics_Core 1 7220
Protoss_Zealot 3 14484
Protoss_Dragoon 14 15692
Protoss_Robotics_Facility 1 12424
Protoss_Citadel_of_Adun 1 13233
Singularity_Charge 1 12320
Protoss_Observatory 1 13157
Protoss_Observer 2 15242
Protoss_Stargate 1 15075
Protoss_Templar_Archives 1 14985
15692
