Protoss_Gateway 3 12696
Protoss_Assimilator 1 4106
Protoss_Cybernetics_Core 1 5661
Protoss_Dragoon 8 14152
Protoss_Robotics_Facility 1 10094
Singularity_Charge 1 9710
Protoss_Nexus 2 16939
Protoss_Observatory 1 10885
Protoss_Observer 4 14903
16939
