Protoss_Gateway 2 15826
Protoss_Assimilator 2 15375
Protoss_Cybernetics_Core 1 5610
Protoss_Dragoon 7 15508
Protoss_Robotics_Facility 1 9540
Protoss_Observatory 1 10234
Singularity_Charge 1 9745
Protoss_Nexus 1 12930
Protoss_Observer 2 15362
Protoss_Zealot 1 11379
Protoss_Shuttle 1 12646
Protoss_Robotics_Support_Bay 1 12781
Protoss_Reaver 1 14538
15826
