Protoss_Gateway 2 15419
Protoss_Assimilator 1 4673
Protoss_Cybernetics_Core 1 6050
Protoss_Dragoon 5 14846
Protoss_Stargate 1 10544
Protoss_Scout 1 12458
Singularity_Charge 1 10816
Protoss_Fleet_Beacon 1 12760
Protoss_Carrier 1 16381
Protoss_Shield_Battery 1 15187
16381
