Protoss_Gateway 2 9804
Protoss_Assimilator 1 4164
Protoss_Cybernetics_Core 1 5481
Protoss_Dragoon 8 14978
Protoss_Robotics_Facility 1 9376
Singularity_Charge 1 9414
Protoss_Observatory 1 10238
Protoss_Observer 2 15403
Protoss_Nexus 2 17490
Protoss_Zealot 4 13618
Protoss_Shuttle 1 13755
17490
