Protoss_Gateway 2 12509
Protoss_Assimilator 2 14142
Protoss_Cybernetics_Core 1 5663
Protoss_Zealot 2 14171
Protoss_Dragoon 6 12964
Protoss_Nexus 1 11913
Singularity_Charge 1 9733
Protoss_Robotics_Facility 1 12118
Protoss_Shuttle 1 13697
Protoss_Robotics_Support_Bay 1 13397
Protoss_Reaver 1 15255
Protoss_Observatory 1 15067
15255
