Protoss_Gateway 3 13231
Protoss_Assimilator 1 4385
Protoss_Cybernetics_Core 1 5623
Protoss_Dragoon 10 15505
Protoss_Nexus 1 11115
Protoss_Robotics_Facility 1 11067
Singularity_Charge 1 9762
Protoss_Observatory 1 12165
Protoss_Observer 2 14063
Protoss_Citadel_of_Adun 1 14818
15505
