Protoss_Gateway 3 13616
Protoss_Assimilator 1 4433
Protoss_Cybernetics_Core 1 5724
Protoss_Dragoon 10 15440
Protoss_Robotics_Facility 1 9802
Singularity_Charge 1 9780
Protoss_Observatory 1 10534
Protoss_Nexus 1 13224
Protoss_Observer 3 13343
15440
