Protoss_Nexus 2 16743
Protoss_Gateway 2 7644
Protoss_Assimilator 2 11314
Protoss_Cybernetics_Core 1 7409
Protoss_Zealot 3 15345
Protoss_Dragoon 8 13585
Protoss_Robotics_Facility 1 11703
Singularity_Charge 1 11320
Protoss_Shuttle 1 13103
Protoss_Robotics_Support_Bay 2 12973
Protoss_Reaver 1 14716
Protoss_Observatory 1 13882
Protoss_Observer 1 15541
16743
