Protoss_Nexus 1 6652
Protoss_Gateway 4 11838
Protoss_Assimilator 1 5759
Protoss_Cybernetics_Core 1 7310
Protoss_Zealot 1 7793
Protoss_Dragoon 16 15288
Singularity_Charge 1 11047
Protoss_Robotics_Facility 1 14907
15288
