Protoss_Assimilator 1 3504
Protoss_Gateway 2 11553
Protoss_Cybernetics_Core 1 6090
Protoss_Dragoon 7 15569
Protoss_Citadel_of_Adun 1 8938
Protoss_Robotics_Facility 1 10473
Protoss_Templar_Archives 1 10916
Singularity_Charge 1 9768
Protoss_Shuttle 1 11900
Protoss_Dark_Templar 4 15724
Protoss_Nexus 1 15461
Protoss_Observatory 1 13611
Protoss_Observer 1 15547
15724
