Protoss_Gateway 3 8500
Protoss_Assimilator 2 6329
Protoss_Zealot 2 8118
Protoss_Cybernetics_Core 1 8235
Protoss_Dragoon 6 12856
Protoss_Nexus 2 16802
Protoss_Robotics_Facility 1 12964
Singularity_Charge 1 12239
Protoss_Shuttle 1 14490
Protoss_Robotics_Support_Bay 1 14406
Protoss_Observatory 1 15089
Protoss_Reaver 1 16145
16802
