Protoss_Nexus 2 17051
Protoss_Gateway 2 9551
Protoss_Assimilator 2 10334
Protoss_Cybernetics_Core 1 6931
Protoss_Zealot 1 6617
Protoss_Dragoon 10 14682
Protoss_Robotics_Facility 1 12060
Singularity_Charge 1 11179
Protoss_Citadel_of_Adun 1 12882
Protoss_Observatory 1 12876
Protoss_Observer 2 14789
Protoss_Stargate 1 14822
Protoss_Templar_Archives 1 14674
17051
