Protoss_Gateway 2 14493
Protoss_Assimilator 1 4287
Protoss_Cybernetics_Core 1 5575
Protoss_Zealot 1 5440
Protoss_Dragoon 8 15686
Protoss_Robotics_Facility 1 9914
Singularity_Charge 1 9645
Protoss_Shuttle 1 11314
Protoss_Robotics_Support_Bay 1 10674
Protoss_Reaver 2 15749
Protoss_Nexus 1 14835
Protoss_Observatory 1 12745
Protoss_Observer 2 14891
15749
