Protoss_Gateway 4 15118
Protoss_Assimilator 1 4128
Protoss_Cybernetics_Core 1 5682
Protoss_Dragoon 4 11442
Protoss_Nexus 1 11100
Protoss_Robotics_Facility 1 10839
Singularity_Charge 1 9768
Protoss_Shuttle 1 12462
Protoss_Robotics_Support_Bay 1 12165
Protoss_Zealot 2 12915
Protoss_Reaver 1 14020
Protoss_Observatory 1 13605
Protoss_Citadel_of_Adun 1 14607
Protoss_Observer 1 14844
Protoss_Templar_Archives 1 16047
16047
