Protoss_Gateway 2 10878
Protoss_Assimilator 1 4660
Protoss_Cybernetics_Core 1 6203
Protoss_Dragoon 8 14956
Protoss_Robotics_Facility 2 16074
Protoss_Citadel_of_Adun 1 10704
Singularity_Charge 1 10560
Protoss_Templar_Archives 1 12209
Protoss_Dark_Templar 2 13500
16074
