Protoss_Gateway 2 8104
Protoss_Assimilator 1 4359
Protoss_Cybernetics_Core 1 5644
Protoss_Zealot 3 14209
Protoss_Dragoon 8 15768
Protoss_Nexus 1 11681
Protoss_Robotics_Facility 1 11354
Singularity_Charge 1 9736
Protoss_Shuttle 1 13021
Protoss_Robotics_Support_Bay 1 13150
Protoss_Reaver 1 14877
Protoss_Observatory 1 14213
15768
