Protoss_Gateway 2 8609
Protoss_Assimilator 2 14162
Protoss_Cybernetics_Core 1 6002
Protoss_Zealot 1 5985
Protoss_Dragoon 10 15159
Singularity_Charge 1 9695
Protoss_Nexus 1 13537
Protoss_Citadel_of_Adun 1 13552
Protoss_Templar_Archives 1 15667
Protoss_Robotics_Facility 1 16465
16465
