Protoss_Gateway 2 14401
Protoss_Assimilator 1 4429
Protoss_Zealot 3 7214
Protoss_Cybernetics_Core 1 7009
Protoss_Dragoon 7 15789
Protoss_Robotics_Facility 1 11774
Protoss_Nexus 1 13737
Singularity_Charge 1 10901
Protoss_Observatory 1 12593
Protoss_Observer 1 13641
15789
