Protoss_Nexus 2 17103
Protoss_Gateway 2 8153
Protoss_Assimilator 2 11192
Protoss_Cybernetics_Core 1 7619
Protoss_Dragoon 11 14990
Protoss_Robotics_Facility 1 11884
Singularity_Charge 1 11677
Protoss_Shuttle 1 13296
Protoss_Observatory 1 12765
Protoss_Robotics_Support_Bay 1 13854
Protoss_Observer 2 15430
Protoss_Reaver 1 16191
17103
