Protoss_Nexus 2 16341
Protoss_Gateway 2 7615
Protoss_Assimilator 1 5748
Protoss_Cybernetics_Core 1 7226
Protoss_Zealot 2 7644
Protoss_Dragoon 7 13927
Protoss_Robotics_Facility 1 13961
Singularity_Charge 1 12912
Protoss_Observatory 1 14773
16341
