Protoss_Gateway 2 11361
Protoss_Assimilator 1 4510
Protoss_Cybernetics_Core 1 5851
Protoss_Dragoon 9 15227
Protoss_Robotics_Facility 1 10829
Singularity_Charge 1 10062
Protoss_Observatory 1 11548
Protoss_Observer 2 14332
Protoss_Shuttle 1 13943
Protoss_Zealot 2 13884
Protoss_Nexus 1 17137
17137
