Protoss_Gateway 2 8244
Protoss_Assimilator 1 4376
Protoss_Cybernetics_Core 1 5707
Protoss_Zealot 1 5552
Protoss_Dragoon 10 14802
Singularity_Charge 1 9373
Protoss_Nexus 1 13471
Protoss_Robotics_Facility 1 13283
Protoss_Observatory 1 14075
Protoss_Observer 1 15321
15321
