Protoss_Gateway 2 12431
Protoss_Assimilator 1 4527
Protoss_Cybernetics_Core 2 14720
Protoss_Zealot 3 14721
Protoss_Robotics_Facility 1 8246
Protoss_Dragoon 2 9595
Protoss_Shuttle 1 9649
Protoss_Robotics_Support_Bay 1 9452
Protoss_Reaver 2 13130
14721
