Protoss_Nexus 1 6587
Protoss_Gateway 2 7609
Protoss_Assimilator 2 12967
Protoss_Cybernetics_Core 1 7398
Protoss_Zealot 1 7466
Protoss_Dragoon 12 15499
Protoss_Robotics_Facility 1 13353
Singularity_Charge 1 11606
Protoss_Shuttle 1 14838
Protoss_Robotics_Support_Bay 1 14343
15499
