Protoss_Gateway 4 15895
Protoss_Assimilator 1 4114
Protoss_Cybernetics_Core 1 5493
Protoss_Dragoon 12 14934
Protoss_Nexus 2 16227
Singularity_Charge 1 9379
Protoss_Robotics_Facility 1 11814
Protoss_Observatory 1 12695
Protoss_Observer 3 15468
16227
