Protoss_Gateway 3 13635
Protoss_Zealot 2 7281
Protoss_Nexus 1 8124
Protoss_Assimilator 2 11253
Protoss_Cybernetics_Core 1 7474
Protoss_Dragoon 11 15396
Protoss_Robotics_Facility 1 11468
Protoss_Observatory 1 12200
Protoss_Observer 3 15017
Protoss_Citadel_of_Adun 1 14909
Singularity_Charge 1 14281
15396
