Protoss_Gateway 3 12807
Protoss_Assimilator 2 15570
Protoss_Zealot 1 5042
Protoss_Cybernetics_Core 1 5900
Protoss_Dragoon 12 15642
Protoss_Nexus 1 12488
Singularity_Charge 1 9929
Protoss_Robotics_Facility 1 12104
Protoss_Observatory 1 13071
Protoss_Observer 2 14976
15642
