Protoss_Nexus 1 6587
Protoss_Gateway 4 14759
Protoss_Assimilator 2 11323
Protoss_Cybernetics_Core 1 7308
Protoss_Zealot 1 7428
Protoss_Dragoon 6 11583
Protoss_Citadel_of_Adun 1 11071
Singularity_Charge 1 10980
Protoss_Robotics_Facility 1 13204
Protoss_Templar_Archives 1 13577
Protoss_Shuttle 1 14715
Protoss_Dark_Templar 2 14791
Protoss_Stargate 1 15328
Protoss_Observatory 1 14457
15328
