Protoss_Gateway 2 11645
Protoss_Assimilator 1 4594
Protoss_Cybernetics_Core 1 6124
Protoss_Dragoon 7 13024
Protoss_Robotics_Facility 1 10696
Singularity_Charge 1 10340
Protoss_Observatory 1 11432
Protoss_Observer 1 12529
Protoss_Citadel_of_Adun 1 13182
Protoss_Shuttle 1 14030
Protoss_Zealot 4 14808
14808
