Protoss_Gateway 4 13938
Protoss_Assimilator 1 4286
Protoss_Cybernetics_Core 1 6058
Protoss_Dragoon 13 15651
Protoss_Citadel_of_Adun 1 10777
Singularity_Charge 1 9945
Protoss_Zealot 2 14518
15651
