Protoss_Gateway 4 16012
Protoss_Assimilator 1 4169
Protoss_Cybernetics_Core 1 5613
Protoss_Robotics_Facility 1 7748
Protoss_Dragoon 9 13686
Protoss_Shuttle 1 9230
Protoss_Observatory 1 8990
Protoss_Observer 3 14314
Singularity_Charge 1 10589
Protoss_Nexus 1 16010
16012
