Protoss_Gateway 3 14455
Protoss_Assimilator 1 4571
Protoss_Cybernetics_Core 1 5897
Protoss_Dragoon 12 15118
Protoss_Robotics_Facility 1 11590
Singularity_Charge 1 11497
Protoss_Observatory 1 12404
Protoss_Observer 1 13502
15118
