Protoss_Gateway 3 14275
Protoss_Assimilator 1 4511
Protoss_Cybernetics_Core 1 5699
Protoss_Zealot 1 5739
Protoss_Dragoon 9 15790
Protoss_Robotics_Facility 1 11565
Singularity_Charge 1 10106
Protoss_Nexus 1 14283
Protoss_Observatory 1 12426
Protoss_Observer 3 15323
15790
