Protoss_Gateway 2 10234
Protoss_Assimilator 1 4578
Protoss_Cybernetics_Core 1 6124
Protoss_Robotics_Facility 1 8395
Protoss_Dragoon 9 14861
Protoss_Observatory 1 9216
Protoss_Observer 5 15449
Singularity_Charge 1 11423
Protoss_Shuttle 1 13553
15449
