Protoss_Gateway 3 14721
Protoss_Assimilator 1 4578
Protoss_Cybernetics_Core 1 5860
Protoss_Dragoon 7 15061
Protoss_Robotics_Facility 1 10762
Singularity_Charge 1 10282
Protoss_Shuttle 1 12626
Protoss_Nexus 1 14545
Protoss_Observatory 1 12852
Protoss_Observer 1 14271
15061
