Protoss_Gateway 2 13366
Protoss_Assimilator 1 4469
Protoss_Cybernetics_Core 1 5758
Protoss_Dragoon 5 14780
Protoss_Robotics_Facility 1 8552
Protoss_Shuttle 1 9962
Protoss_Robotics_Support_Bay 1 9581
Protoss_Zealot 2 11190
Protoss_Reaver 1 11558
Protoss_Observatory 1 11144
Protoss_Observer 1 12519
Protoss_Nexus 1 17171
17171
