Protoss_Gateway 2 10158
Protoss_Assimilator 1 4552
Protoss_Cybernetics_Core 1 6050
Protoss_Dragoon 8 12783
Singularity_Charge 1 10406
Protoss_Robotics_Facility 1 13514
Protoss_Nexus 1 15498
Protoss_Shuttle 1 15033
15498
