Protoss_Gateway 3 14294
Protoss_Assimilator 1 4653
Protoss_Cybernetics_Core 1 5992
Protoss_Dragoon 7 13612
Protoss_Robotics_Facility 1 8809
Protoss_Observatory 1 9514
Protoss_Observer 2 13392
Protoss_Shuttle 1 12706
Protoss_Citadel_of_Adun 1 14347
Singularity_Charge 1 13048
Protoss_Zealot 2 14474
Protoss_Templar_Archives 1 15885
15885
