Protoss_Gateway 2 14509
Protoss_Assimilator 2 5307
Protoss_Cybernetics_Core 1 6555
Protoss_Dragoon 2 8878
Protoss_Robotics_Facility 1 10309
Protoss_Forge 1 9817
Protoss_Photon_Cannon 1 11245
Protoss_Shuttle 1 11726
Protoss_Zealot 2 12727
Protoss_Robotics_Support_Bay 1 11668
Protoss_Reaver 1 13412
Protoss_Citadel_of_Adun 1 13913
14509
