Protoss_Gateway 3 12734
Protoss_Assimilator 1 4286
Protoss_Cybernetics_Core 1 5988
Protoss_Dragoon 12 15711
Protoss_Robotics_Facility 1 9117
Protoss_Shuttle 1 10526
Protoss_Observatory 1 9894
Protoss_Observer 1 11369
Singularity_Charge 1 12140
Protoss_Shield_Battery 1 13408
Protoss_Citadel_of_Adun 1 15081
15711
