Protoss_Gateway 2 6570
Protoss_Assimilator 1 4205
Protoss_Cybernetics_Core 1 5825
Protoss_Dragoon 7 13810
Protoss_Robotics_Facility 1 11129
Singularity_Charge 1 9945
Protoss_Zealot 4 12690
Protoss_Observatory 1 11855
Protoss_Shuttle 1 12589
Protoss_Observer 1 13432
13810
