Protoss_Gateway 3 15172
Protoss_Assimilator 1 4412
Protoss_Cybernetics_Core 1 5721
Protoss_Dragoon 9 12617
Protoss_Citadel_of_Adun 1 11446
Singularity_Charge 1 10845
Protoss_Templar_Archives 1 12921
Protoss_Dark_Templar 2 14144
Protoss_Nexus 1 15997
Protoss_Zealot 2 15310
15997
