Protoss_Gateway 4 15428
Protoss_Assimilator 1 4192
Protoss_Cybernetics_Core 1 5604
Protoss_Dragoon 6 14890
Protoss_Robotics_Facility 1 10390
Singularity_Charge 1 9609
Protoss_Observatory 1 11479
Protoss_Nexus 2 14715
Protoss_Citadel_of_Adun 1 12782
Protoss_Observer 2 14680
Protoss_Templar_Archives 1 14544
15428
