Protoss_Gateway 3 12905
Protoss_Assimilator 1 4344
Protoss_Cybernetics_Core 1 5928
Protoss_Dragoon 13 15544
Protoss_Robotics_Facility 1 9614
Protoss_Shuttle 1 11023
Protoss_Observatory 1 10409
Protoss_Observer 2 14871
Protoss_Shield_Battery 1 12682
Singularity_Charge 1 12097
15544
