Protoss_Gateway 3 13192
Protoss_Assimilator 1 4299
Protoss_Cybernetics_Core 1 5729
Protoss_Robotics_Facility 1 7909
Protoss_Dragoon 9 15395
Protoss_Observatory 1 8635
Protoss_Shuttle 1 9596
Protoss_Observer 3 13056
Singularity_Charge 1 14094
15395
