Protoss_Gateway 2 9219
Protoss_Assimilator 1 4461
Protoss_Cybernetics_Core 1 6182
Protoss_Dragoon 9 13472
Singularity_Charge 1 10414
Protoss_Robotics_Facility 1 14125
Protoss_Nexus 1 15917
Protoss_Zealot 2 14549
Protoss_Observatory 1 14840
Protoss_Shuttle 1 15765
15917
