Protoss_Gateway 2 9138
Protoss_Assimilator 2 5120
Protoss_Cybernetics_Core 1 6482
Protoss_Zealot 2 14914
Protoss_Dragoon 5 15110
Protoss_Nexus 1 14364
Protoss_Robotics_Facility 1 15512
15512
