Protoss_Gateway 2 10207
Protoss_Assimilator 1 4384
Protoss_Cybernetics_Core 1 5831
Protoss_Dragoon 7 12748
Protoss_Robotics_Facility 1 8899
Protoss_Observatory 1 9613
Protoss_Observer 2 11549
Singularity_Charge 1 11540
Protoss_Nexus 2 16568
Protoss_Citadel_of_Adun 1 15643
16568
