Protoss_Gateway 3 15697
Protoss_Assimilator 1 4720
Protoss_Cybernetics_Core 1 6270
Protoss_Dragoon 9 14988
Protoss_Robotics_Facility 1 9987
Protoss_Observatory 1 10765
Protoss_Observer 2 12836
Protoss_Nexus 1 15015
Singularity_Charge 1 13684
15697
