Protoss_Gateway 3 15219
Protoss_Assimilator 1 4717
Protoss_Cybernetics_Core 1 6260
Protoss_Dragoon 10 15218
Protoss_Robotics_Facility 1 9797
Protoss_Observatory 1 10516
Protoss_Observer 2 13517
Singularity_Charge 1 13831
Protoss_Shuttle 1 15435
15435
