Protoss_Gateway 2 13711
Protoss_Assimilator 1 4643
Protoss_Cybernetics_Core 1 5897
Protoss_Dragoon 8 15585
Protoss_Robotics_Facility 1 8158
Protoss_Zealot 2 9667
Protoss_Shuttle 1 9655
Protoss_Nexus 1 14103
Protoss_Observatory 1 12079
Protoss_Citadel_of_Adun 1 13552
Protoss_Observer 1 13312
Singularity_Charge 1 13560
Protoss_Templar_Archives 1 15470
15585
