Protoss_Gateway 3 10572
Protoss_Assimilator 1 4635
Protoss_Cybernetics_Core 1 5980
Protoss_Dragoon 8 13637
Protoss_Robotics_Facility 1 8703
Protoss_Observatory 1 9616
Protoss_Observer 2 12579
Singularity_Charge 1 12637
Protoss_Nexus 2 16887
16887
