Protoss_Gateway 2 11265
Protoss_Assimilator 1 4578
Protoss_Cybernetics_Core 1 5889
Protoss_Dragoon 6 14831
Protoss_Stargate 1 10383
Singularity_Charge 1 10450
Protoss_Fleet_Beacon 1 12007
Protoss_Carrier 1 15539
Protoss_Robotics_Facility 1 15030
15539
