Protoss_Gateway 2 10748
Protoss_Assimilator 1 4300
Protoss_Cybernetics_Core 1 5869
Protoss_Dragoon 10 15066
Protoss_Robotics_Facility 1 9974
Protoss_Observatory 1 10807
Protoss_Observer 2 12722
Singularity_Charge 1 11819
15066
