Protoss_Gateway 2 10050
Protoss_Assimilator 1 4687
Protoss_Cybernetics_Core 1 6214
Protoss_Dragoon 9 14019
Protoss_Robotics_Facility 1 10017
Protoss_Observatory 1 10892
Singularity_Charge 1 10209
Protoss_Observer 2 13296
Protoss_Shuttle 1 14311
Protoss_Nexus 1 16500
16500
