Protoss_Gateway 3 16032
Protoss_Assimilator 1 4578
Protoss_Cybernetics_Core 1 5876
Protoss_Zealot 3 14929
Protoss_Dragoon 6 12292
Protoss_Robotics_Facility 1 10355
Singularity_Charge 1 10194
Protoss_Observatory 1 11167
Protoss_Observer 2 13088
Protoss_Nexus 1 15934
Protoss_Shuttle 1 15091
16032
