Protoss_Gateway 2 10231
Protoss_Assimilator 1 4586
Protoss_Cybernetics_Core 1 6206
Protoss_Dragoon 11 15812
Protoss_Robotics_Facility 1 11048
Singularity_Charge 1 10172
Protoss_Observatory 1 12140
Protoss_Observer 2 14208
Protoss_Nexus 1 15529
15812
