Protoss_Gateway 2 16024
Protoss_Assimilator 1 4757
Protoss_Cybernetics_Core 1 6124
Protoss_Dragoon 4 15358
Protoss_Robotics_Facility 1 8845
Protoss_Shuttle 1 10262
Protoss_Robotics_Support_Bay 1 9872
Protoss_Reaver 2 13456
Protoss_Observatory 1 13011
Protoss_Nexus 1 15944
Protoss_Observer 1 14281
16024
