Protoss_Gateway 1 4569
Protoss_Assimilator 1 4618
Protoss_Cybernetics_Core 1 6036
Protoss_Dragoon 2 11259
Protoss_Robotics_Facility 1 8825
Protoss_Zealot 2 10139
Protoss_Robotics_Support_Bay 1 9647
Protoss_Shuttle 1 10372
Protoss_Reaver 1 12037
12037
