Protoss_Gateway 3 12626
Protoss_Assimilator 1 4491
Protoss_Cybernetics_Core 1 5881
Protoss_Dragoon 9 14678
Protoss_Nexus 2 15810
Singularity_Charge 1 10062
Protoss_Robotics_Facility 1 15797
Protoss_Citadel_of_Adun 1 15658
15810
