Protoss_Gateway 2 10891
Protoss_Assimilator 1 4398
Protoss_Cybernetics_Core 1 5955
Protoss_Dragoon 7 13323
Protoss_Robotics_Facility 1 9093
Protoss_Observatory 1 9960
Protoss_Observer 2 12222
Singularity_Charge 1 11226
Protoss_Nexus 1 15622
Protoss_Citadel_of_Adun 1 14762
Protoss_Zealot 2 14673
15622
