Protoss_Gateway 2 14737
Protoss_Assimilator 1 4556
Protoss_Cybernetics_Core 1 5932
Protoss_Robotics_Facility 1 8151
Protoss_Dragoon 5 14387
Protoss_Shuttle 1 9567
Protoss_Robotics_Support_Bay 1 9279
Protoss_Reaver 2 15842
Protoss_Zealot 1 10780
Protoss_Observatory 1 12038
Protoss_Observer 1 14073
Singularity_Charge 1 14080
15842
