Protoss_Gateway 1 4236
Protoss_Assimilator 1 4330
Protoss_Cybernetics_Core 1 5720
Protoss_Zealot 1 6112
Protoss_Dragoon 6 12936
Singularity_Charge 1 9514
Protoss_Robotics_Facility 1 11553
Protoss_Citadel_of_Adun 1 11806
Protoss_Shuttle 1 13116
Protoss_Templar_Archives 1 13526
Protoss_Dark_Templar 1 14736
Protoss_Robotics_Support_Bay 1 15154
15154
