Protoss_Gateway 2 10072
Protoss_Assimilator 1 4514
Protoss_Cybernetics_Core 1 5772
Protoss_Robotics_Facility 1 8078
Protoss_Dragoon 10 15680
Protoss_Observatory 1 9060
Protoss_Observer 4 14812
Protoss_Nexus 2 16590
Singularity_Charge 1 12521
16590
