Protoss_Gateway 2 9961
Protoss_Assimilator 1 4480
Protoss_Cybernetics_Core 1 5771
Protoss_Robotics_Facility 1 7931
Protoss_Dragoon 11 15050
Protoss_Observatory 1 8709
Protoss_Observer 3 14556
Singularity_Charge 1 12214
Protoss_Nexus 1 16012
16012
