Protoss_Gateway 3 12276
Protoss_Assimilator 1 4504
Protoss_Cybernetics_Core 1 5750
Protoss_Robotics_Facility 1 8013
Protoss_Dragoon 8 15461
Protoss_Shuttle 1 9421
Protoss_Observatory 1 8892
Protoss_Observer 6 15582
Singularity_Charge 1 11072
Protoss_Nexus 1 16909
16909
