Protoss_Gateway 2 12443
Protoss_Assimilator 1 4363
Protoss_Cybernetics_Core 1 5767
Protoss_Dragoon 7 13675
Protoss_Robotics_Facility 1 9348
Protoss_Observatory 1 10055
Protoss_Observer 3 14819
Singularity_Charge 1 11482
Protoss_Nexus 2 16716
Protoss_Citadel_of_Adun 1 14543
Protoss_Zealot 2 15346
16716
