Protoss_Gateway 4 15860
Protoss_Assimilator 1 4710
Protoss_Cybernetics_Core 1 6087
Protoss_Dragoon 6 13975
Protoss_Robotics_Facility 1 10456
Singularity_Charge 1 10209
Protoss_Citadel_of_Adun 1 12002
Protoss_Observatory 1 11321
Protoss_Observer 1 12434
Protoss_Nexus 1 15243
Protoss_Templar_Archives 1 14167
Protoss_Shuttle 1 15413
15860
