Protoss_Gateway 2 10529
Protoss_Assimilator 1 4379
Protoss_Cybernetics_Core 1 6065
Protoss_Dragoon 6 14736
Protoss_Robotics_Facility 1 8634
Protoss_Robotics_Support_Bay 1 9477
Protoss_Shuttle 1 11133
Protoss_Reaver 1 12691
Protoss_Nexus 1 15344
Protoss_Observatory 1 14218
15344
