Protoss_Gateway 2 9892
Protoss_Assimilator 1 4286
Protoss_Cybernetics_Core 1 5916
Protoss_Dragoon 10 15592
Protoss_Robotics_Facility 1 8883
Protoss_Observatory 1 9972
Protoss_Observer 4 14849
Singularity_Charge 1 11592
Protoss_Nexus 2 16629
16629
