Protoss_Gateway 2 13792
Protoss_Assimilator 1 4429
Protoss_Cybernetics_Core 1 6021
Protoss_Zealot 3 15251
Protoss_Dragoon 7 14318
Protoss_Robotics_Facility 1 10675
Singularity_Charge 1 10480
Protoss_Shuttle 2 15500
Protoss_Robotics_Support_Bay 1 11990
Protoss_Reaver 1 14198
Protoss_Citadel_of_Adun 1 14794
15500
