Protoss_Gateway 3 12823
Protoss_Assimilator 1 4632
Protoss_Cybernetics_Core 1 6223
Protoss_Zealot 4 15471
Protoss_Dragoon 8 14290
Protoss_Nexus 1 12659
Singularity_Charge 1 10838
Protoss_Robotics_Facility 1 13362
Protoss_Observatory 1 14628
Protoss_Shuttle 1 15399
15471
