Protoss_Gateway 2 9929
Protoss_Assimilator 1 4223
Protoss_Cybernetics_Core 1 5824
Protoss_Dragoon 7 15206
Protoss_Robotics_Facility 1 8672
Protoss_Observatory 1 9382
Protoss_Observer 3 14505
Protoss_Nexus 1 14736
Singularity_Charge 1 12558
Protoss_Shuttle 1 15863
15863
