Protoss_Gateway 3 15307
Protoss_Assimilator 1 4527
Protoss_Cybernetics_Core 1 6192
Protoss_Dragoon 8 14707
Protoss_Robotics_Facility 1 10707
Singularity_Charge 1 10487
Protoss_Observatory 1 12490
Protoss_Nexus 1 15485
Protoss_Observer 1 13700
Protoss_Shuttle 1 15058
15485
