Protoss_Gateway 1 4230
Protoss_Assimilator 1 4325
Protoss_Cybernetics_Core 1 5746
Protoss_Robotics_Facility 1 7860
Protoss_Dragoon 4 14463
Protoss_Zealot 2 9450
Protoss_Shuttle 1 9462
Protoss_Robotics_Support_Bay 1 9437
Protoss_Reaver 3 14260
14463
