Protoss_Gateway 3 9892
Protoss_Assimilator 1 4662
Protoss_Zealot 7 15441
Protoss_Cybernetics_Core 1 7114
Protoss_Dragoon 7 12565
Protoss_Citadel_of_Adun 1 13107
Singularity_Charge 1 12250
Protoss_Templar_Archives 1 14793
Protoss_Robotics_Facility 1 15900
15900
