Protoss_Gateway 3 14750
Protoss_Nexus 1 8073
Protoss_Zealot 2 7788
Protoss_Assimilator 1 7212
Protoss_Cybernetics_Core 1 9046
Protoss_Dragoon 8 14827
Protoss_Shield_Battery 1 11117
Singularity_Charge 1 12909
14827
