Protoss_Gateway 3 13111
Protoss_Assimilator 1 4791
Protoss_Cybernetics_Core 1 5955
Protoss_Dragoon 8 15355
Protoss_Robotics_Facility 1 10800
Singularity_Charge 1 10219
Protoss_Zealot 4 13817
Protoss_Shuttle 1 12652
Protoss_Observatory 1 12016
Protoss_Observer 1 13602
Protoss_Citadel_of_Adun 1 14461
15355
