Protoss_Gateway 2 8755
Protoss_Assimilator 1 4824
Protoss_Cybernetics_Core 1 6276
Protoss_Zealot 3 12697
Protoss_Dragoon 12 15695
Singularity_Charge 1 10282
Protoss_Nexus 1 15483
Protoss_Robotics_Facility 1 15886
15886
