Protoss_Gateway 2 9045
Protoss_Assimilator 1 4366
Protoss_Cybernetics_Core 1 5582
Protoss_Zealot 3 14995
Protoss_Dragoon 7 11802
Singularity_Charge 1 9419
Protoss_Citadel_of_Adun 1 11279
Protoss_Templar_Archives 1 12775
Protoss_Robotics_Facility 1 13441
Protoss_Dark_Templar 2 14041
Protoss_Shuttle 1 15077
15077
