Protoss_Gateway 2 10122
Protoss_Assimilator 1 4590
Protoss_Cybernetics_Core 1 6296
Protoss_Dragoon 7 13310
Protoss_Robotics_Facility 1 8912
Protoss_Observatory 1 10109
Protoss_Observer 2 13707
Protoss_Zealot 1 11380
Protoss_Shuttle 1 12636
Protoss_Robotics_Support_Bay 1 12568
Singularity_Charge 1 11884
Protoss_Reaver 1 15303
Protoss_Nexus 1 16635
16635
