Protoss_Gateway 2 14253
Protoss_Assimilator 1 4615
Protoss_Cybernetics_Core 1 6043
Protoss_Dragoon 5 15710
Protoss_Robotics_Facility 1 8678
Protoss_Shuttle 1 10087
Protoss_Robotics_Support_Bay 1 9799
Protoss_Reaver 1 11661
Protoss_Zealot 1 11197
Protoss_Observatory 1 11196
Protoss_Nexus 1 14664
Protoss_Observer 3 15141
15710
