Protoss_Gateway 2 8014
Protoss_Assimilator 1 4457
Protoss_Cybernetics_Core 1 5970
Protoss_Dragoon 12 15556
Protoss_Robotics_Facility 1 12958
Singularity_Charge 1 11138
Protoss_Observatory 1 13722
Protoss_Nexus 1 16222
16222
