Protoss_Gateway 3 15460
Protoss_Assimilator 1 4586
Protoss_Cybernetics_Core 1 6014
Protoss_Dragoon 12 15262
Protoss_Nexus 1 12322
Protoss_Robotics_Facility 1 11833
Singularity_Charge 1 11116
Protoss_Observatory 1 12767
Protoss_Observer 1 14380
15460
