Protoss_Gateway 1 4309
Protoss_Assimilator 1 4624
Protoss_Cybernetics_Core 1 6094
Protoss_Dragoon 4 14867
Protoss_Robotics_Facility 1 8722
Protoss_Zealot 2 9832
Protoss_Shuttle 2 15823
Protoss_Robotics_Support_Bay 1 10070
Protoss_Reaver 2 13796
Protoss_Nexus 1 15745
15823
