Protoss_Nexus 1 7056
Protoss_Gateway 3 12127
Protoss_Assimilator 1 6708
Protoss_Zealot 8 15544
Protoss_Cybernetics_Core 1 9468
Protoss_Dragoon 2 13083
Protoss_Citadel_of_Adun 1 12220
Protoss_Forge 2 12075
Protoss_Photon_Cannon 3 14864
Protoss_Templar_Archives 1 14070
Protoss_Dark_Templar 1 15322
15544
