Protoss_Gateway 5 15879
Protoss_Assimilator 1 4652
Protoss_Cybernetics_Core 1 6119
Protoss_Dragoon 9 15800
Protoss_Robotics_Facility 1 8877
Protoss_Observatory 1 9755
Protoss_Observer 2 11824
Protoss_Nexus 1 14339
Singularity_Charge 1 11955
Protoss_Shuttle 1 13495
15879
