Protoss_Gateway 2 7400
Protoss_Assimilator 1 4198
Protoss_Cybernetics_Core 1 5626
Protoss_Dragoon 14 15734
Singularity_Charge 1 9967
Protoss_Nexus 1 14408
Protoss_Robotics_Facility 1 14924
15734
