Protoss_Gateway 2 10704
Protoss_Assimilator 1 4776
Protoss_Cybernetics_Core 1 6184
Protoss_Dragoon 8 15336
Protoss_Robotics_Facility 1 10135
Protoss_Observatory 1 10978
Singularity_Charge 1 10501
Protoss_Nexus 1 13917
Protoss_Observer 2 12942
Protoss_Shuttle 1 14440
Protoss_Robotics_Support_Bay 1 14057
Protoss_Reaver 1 15998
15998
