Protoss_Gateway 4 15971
Protoss_Assimilator 1 4412
Protoss_Zealot 1 5393
Protoss_Cybernetics_Core 1 6383
Protoss_Dragoon 8 14431
Protoss_Robotics_Facility 1 11943
Singularity_Charge 1 10327
Protoss_Observatory 1 12765
Protoss_Nexus 1 15210
Protoss_Observer 2 14669
15971
