Protoss_Gateway 4 15611
Protoss_Assimilator 1 4833
Protoss_Zealot 4 14938
Protoss_Cybernetics_Core 1 7008
Protoss_Dragoon 9 15095
Protoss_Robotics_Facility 1 10801
Protoss_Observatory 1 11521
Singularity_Charge 1 11358
Protoss_Observer 2 13486
Protoss_Nexus 1 15041
15611
