Protoss_Gateway 3 9511
Protoss_Assimilator 1 4637
Protoss_Cybernetics_Core 1 6251
Protoss_Dragoon 6 11517
Protoss_Zealot 4 12858
Singularity_Charge 1 10267
Protoss_Nexus 1 16225
16225
