Protoss_Gateway 2 10704
Protoss_Assimilator 1 4467
Protoss_Cybernetics_Core 1 5875
Protoss_Dragoon 9 14685
Protoss_Citadel_of_Adun 2 15667
Protoss_Robotics_Facility 1 9455
Protoss_Observatory 1 10165
Protoss_Observer 2 13192
Singularity_Charge 1 11870
Protoss_Nexus 1 15173
15667
