Protoss_Gateway 3 12789
Protoss_Assimilator 1 4666
Protoss_Zealot 8 14866
Protoss_Cybernetics_Core 1 6650
Protoss_Dragoon 8 15761
Protoss_Citadel_of_Adun 1 11009
Singularity_Charge 1 12009
15761
