Protoss_Gateway 3 10723
Protoss_Assimilator 1 4586
Protoss_Cybernetics_Core 1 5933
Protoss_Dragoon 9 14199
Protoss_Nexus 1 11602
Singularity_Charge 1 10029
Protoss_Zealot 1 11499
Protoss_Robotics_Facility 1 15355
Protoss_Citadel_of_Adun 1 15722
15722
