Protoss_Gateway 3 11726
Protoss_Assimilator 1 4824
Protoss_Zealot 2 6024
Protoss_Cybernetics_Core 1 6200
Protoss_Dragoon 12 15105
Singularity_Charge 1 11526
Protoss_Citadel_of_Adun 1 14016
Protoss_Templar_Archives 1 15511
15511
