Protoss_Gateway 1 4517
Protoss_Assimilator 1 4694
Protoss_Cybernetics_Core 1 6277
Protoss_Dragoon 6 14810
Protoss_Robotics_Facility 1 10738
Singularity_Charge 1 10655
Protoss_Shuttle 1 12209
Protoss_Zealot 1 12032
Protoss_Robotics_Support_Bay 1 12170
Protoss_Reaver 1 14005
Protoss_Observatory 1 13456
Protoss_Observer 1 15432
15432
