Protoss_Gateway 1 4092
Protoss_Zealot 3 7217
Protoss_Assimilator 1 5412
Protoss_Cybernetics_Core 1 7046
Protoss_Robotics_Facility 1 9300
Protoss_Dragoon 6 15500
Protoss_Robotics_Support_Bay 1 10118
Protoss_Reaver 3 15859
Protoss_Observatory 1 11218
Protoss_Nexus 1 13537
Protoss_Observer 1 12700
15859
