Protoss_Gateway 3 8970
Protoss_Assimilator 1 4682
Protoss_Cybernetics_Core 1 5967
Protoss_Dragoon 12 14864
Protoss_Robotics_Facility 1 11088
Singularity_Charge 1 9798
Protoss_Observatory 1 11873
Protoss_Nexus 1 14261
Protoss_Observer 2 14835
14864
