Protoss_Gateway 2 11347
Protoss_Assimilator 1 4341
Protoss_Cybernetics_Core 1 5961
Protoss_Robotics_Facility 1 8091
Protoss_Dragoon 9 14779
Protoss_Observatory 1 8952
Protoss_Observer 2 13978
Singularity_Charge 1 10740
14779
