Protoss_Gateway 3 15842
Protoss_Assimilator 1 4520
Protoss_Cybernetics_Core 1 5810
Protoss_Dragoon 5 15702
Protoss_Citadel_of_Adun 1 7697
Protoss_Templar_Archives 1 9304
Protoss_Dark_Templar 6 12863
Protoss_Nexus 1 15117
Protoss_Forge 1 13649
15842
