Protoss_Gateway 3 15263
Protoss_Assimilator 1 4444
Protoss_Cybernetics_Core 1 5928
Protoss_Dragoon 8 14773
Protoss_Zealot 2 9975
Singularity_Charge 1 9923
Protoss_Nexus 1 13054
Protoss_Robotics_Facility 1 12989
Protoss_Observatory 1 13855
Protoss_Observer 1 14900
15263
