Protoss_Gateway 2 8112
Protoss_Assimilator 1 4283
Protoss_Cybernetics_Core 1 5633
Protoss_Dragoon 11 15268
Singularity_Charge 1 9739
Protoss_Nexus 1 13136
Protoss_Robotics_Facility 1 13696
Protoss_Observatory 1 14532
15268
