Protoss_Gateway 2 7024
Protoss_Assimilator 1 4461
Protoss_Cybernetics_Core 1 5919
Protoss_Dragoon 10 13507
Singularity_Charge 1 10143
Protoss_Nexus 1 13819
Protoss_Citadel_of_Adun 1 13681
Protoss_Templar_Archives 1 15895
15895
