Protoss_Gateway 2 13850
Protoss_Assimilator 1 4527
Protoss_Zealot 1 5446
Protoss_Cybernetics_Core 1 6863
Protoss_Dragoon 7 15344
Protoss_Robotics_Facility 1 9165
Protoss_Shuttle 1 10577
Protoss_Robotics_Support_Bay 1 10443
Protoss_Reaver 2 13723
Singularity_Charge 1 12155
Protoss_Observatory 1 13392
Protoss_Nexus 1 16426
Protoss_Observer 1 15536
16426
