Protoss_Gateway 2 8291
Protoss_Assimilator 2 14363
Protoss_Cybernetics_Core 1 5784
Protoss_Dragoon 10 15251
Protoss_Robotics_Facility 1 11470
Protoss_Zealot 1 10934
Singularity_Charge 1 9989
Protoss_Observatory 1 12336
Protoss_Nexus 1 15074
Protoss_Observer 2 14710
Protoss_Stargate 1 15392
15392
