Protoss_Gateway 2 9503
Protoss_Assimilator 1 4293
Protoss_Cybernetics_Core 1 6127
Protoss_Dragoon 9 14981
Protoss_Robotics_Facility 1 8523
Protoss_Observatory 1 9493
Protoss_Observer 3 15269
Protoss_Nexus 2 17005
Singularity_Charge 1 11504
17005
