Protoss_Gateway 1 4338
Protoss_Assimilator 1 4659
Protoss_Cybernetics_Core 1 6100
Protoss_Dragoon 7 14170
Protoss_Robotics_Facility 1 10163
Singularity_Charge 1 10092
Protoss_Shuttle 1 11579
Protoss_Observatory 1 11046
Protoss_Robotics_Support_Bay 1 12053
Protoss_Observer 1 12422
Protoss_Reaver 2 15676
15676
