Protoss_Gateway 2 5165
Protoss_Zealot 7 8958
Protoss_Assimilator 1 6757
Protoss_Cybernetics_Core 1 8825
Protoss_Dragoon 6 12991
Protoss_Citadel_of_Adun 1 11418
Protoss_Templar_Archives 1 13411
Protoss_Dark_Templar 2 14744
Protoss_Nexus 1 16847
16847
