Protoss_Gateway 4 13754
Protoss_Assimilator 1 4359
Protoss_Cybernetics_Core 1 5765
Protoss_Dragoon 10 14717
Singularity_Charge 1 10487
Protoss_Nexus 1 13566
Protoss_Zealot 5 15579
15579
