Protoss_Gateway 2 6514
Protoss_Assimilator 1 4404
Protoss_Cybernetics_Core 1 5796
Protoss_Dragoon 11 14738
Protoss_Nexus 1 12246
Singularity_Charge 1 9841
Protoss_Robotics_Facility 1 12469
Protoss_Observatory 1 13223
Protoss_Observer 2 15277
15277
