Protoss_Gateway 2 8686
Protoss_Assimilator 1 4622
Protoss_Zealot 2 14519
Protoss_Cybernetics_Core 1 7215
Protoss_Dragoon 8 15344
Protoss_Robotics_Facility 1 10662
Protoss_Observatory 1 11372
Singularity_Charge 1 11292
Protoss_Observer 3 15353
Protoss_Nexus 1 15614
15614
