Protoss_Gateway 3 13589
Protoss_Assimilator 1 4520
Protoss_Cybernetics_Core 1 6255
Protoss_Robotics_Facility 1 8297
Protoss_Dragoon 7 14802
Protoss_Observatory 1 9013
Protoss_Observer 2 12242
Protoss_Shuttle 2 15150
Singularity_Charge 1 11431
Protoss_Nexus 1 17399
17399
