Protoss_Gateway 4 15067
Protoss_Assimilator 1 4390
Protoss_Cybernetics_Core 1 5670
Protoss_Dragoon 11 15358
Protoss_Robotics_Facility 1 9863
Protoss_Observatory 1 10567
Singularity_Charge 1 9872
Protoss_Observer 2 14073
Protoss_Nexus 1 15148
15358
