Protoss_Gateway 4 15277
Protoss_Assimilator 1 4125
Protoss_Cybernetics_Core 1 5723
Protoss_Dragoon 3 8210
Protoss_Robotics_Facility 1 10229
Protoss_Zealot 3 14895
Protoss_Citadel_of_Adun 1 10858
Singularity_Charge 1 9440
Protoss_Observatory 1 11204
Protoss_Templar_Archives 1 12794
Protoss_Shuttle 1 13035
Protoss_Nexus 1 14983
Protoss_Dark_Templar 3 15120
15277
