Protoss_Gateway 3 10861
Protoss_Assimilator 2 13997
Protoss_Cybernetics_Core 1 5622
Protoss_Dragoon 8 15688
Protoss_Robotics_Facility 1 9979
Protoss_Observatory 1 10895
Singularity_Charge 1 10706
Protoss_Observer 2 12810
Protoss_Nexus 1 13866
Protoss_Zealot 3 13414
Protoss_Shuttle 1 14891
15688
