Protoss_Gateway 2 8560
Protoss_Assimilator 1 4640
Protoss_Cybernetics_Core 1 6223
Protoss_Dragoon 11 15587
Protoss_Robotics_Facility 1 10424
Singularity_Charge 1 10377
Protoss_Observatory 1 11384
Protoss_Observer 2 13720
Protoss_Nexus 1 14823
15587
