Protoss_Gateway 2 8544
Protoss_Forge 1 5354
Protoss_Zealot 2 6266
Protoss_Assimilator 1 6310
Protoss_Photon_Cannon 1 6712
Protoss_Cybernetics_Core 1 7858
Protoss_Dragoon 11 15364
Singularity_Charge 1 11747
Protoss_Robotics_Facility 1 13728
Protoss_Shuttle 1 15667
15667
