Protoss_Gateway 4 14701
Protoss_Assimilator 1 4444
Protoss_Cybernetics_Core 1 6020
Protoss_Dragoon 11 15136
Protoss_Nexus 1 11861
Singularity_Charge 1 10163
Protoss_Robotics_Facility 1 12809
Protoss_Observatory 1 13645
15136
