Protoss_Gateway 2 7887
Protoss_Assimilator 2 15305
Protoss_Cybernetics_Core 1 5759
Protoss_Dragoon 10 14305
Singularity_Charge 1 9689
Protoss_Zealot 1 11496
Protoss_Nexus 1 14002
Protoss_Robotics_Facility 1 14117
Protoss_Shuttle 1 15999
15999
