Protoss_Gateway 4 14616
Protoss_Assimilator 2 14714
Protoss_Cybernetics_Core 1 6002
Protoss_Dragoon 11 15511
Protoss_Nexus 1 12194
Protoss_Robotics_Facility 1 12330
Singularity_Charge 1 10468
Protoss_Observatory 1 13195
Protoss_Observer 1 14528
15511
