Protoss_Gateway 2 10044
Protoss_Assimilator 1 4501
Protoss_Cybernetics_Core 1 5888
Protoss_Dragoon 11 15660
Protoss_Robotics_Facility 1 8498
Protoss_Observatory 1 9339
Protoss_Observer 3 14838
Singularity_Charge 1 11489
Protoss_Nexus 2 17067
17067
