Protoss_Gateway 2 5251
Protoss_Zealot 9 15509
Protoss_Assimilator 1 6048
Protoss_Cybernetics_Core 1 7711
Protoss_Dragoon 4 10462
Protoss_Citadel_of_Adun 1 11414
Protoss_Templar_Archives 1 12933
Singularity_Charge 1 12037
Protoss_High_Templar 2 15549
Protoss_Forge 1 14355
15549
