Protoss_Gateway 4 16009
Protoss_Zealot 3 10649
Protoss_Assimilator 1 5617
Protoss_Cybernetics_Core 1 7375
Protoss_Dragoon 3 10822
Protoss_Citadel_of_Adun 1 9080
Protoss_Templar_Archives 1 10536
Protoss_Dark_Templar 6 15522
Protoss_Robotics_Facility 1 13526
Protoss_Shuttle 1 15530
16009
