Protoss_Gateway 2 8231
Protoss_Assimilator 1 4463
Protoss_Cybernetics_Core 1 5903
Protoss_Dragoon 4 9844
Protoss_Citadel_of_Adun 1 10627
Protoss_Zealot 2 10706
Singularity_Charge 1 9850
Protoss_Templar_Archives 1 12141
Protoss_Robotics_Facility 1 12916
Protoss_Dark_Templar 3 14855
Protoss_Nexus 1 15757
Protoss_Shuttle 1 14490
Protoss_Observatory 1 14750
15757
