Protoss_Gateway 1 4272
Protoss_Assimilator 1 4842
Protoss_Zealot 3 8380
Protoss_Cybernetics_Core 1 8171
Protoss_Robotics_Facility 1 10150
Protoss_Dragoon 2 10759
Protoss_Citadel_of_Adun 1 10660
Protoss_Robotics_Support_Bay 1 11101
Protoss_Shuttle 1 11821
Protoss_Templar_Archives 1 12409
Protoss_Reaver 2 14918
Protoss_Dark_Templar 2 15112
15112
