Protoss_Gateway 2 9329
Protoss_Assimilator 1 4425
Protoss_Zealot 3 11844
Protoss_Cybernetics_Core 1 6314
Protoss_Dragoon 8 15344
Singularity_Charge 1 10362
Protoss_Nexus 1 14861
Protoss_Robotics_Facility 1 14951
15344
