Protoss_Gateway 3 12213
Protoss_Assimilator 1 4278
Protoss_Cybernetics_Core 1 5717
Protoss_Dragoon 11 13649
Protoss_Robotics_Facility 1 11732
Singularity_Charge 1 9935
Protoss_Zealot 5 15512
Protoss_Observatory 1 12512
Protoss_Observer 1 13542
Protoss_Shuttle 1 15140
Protoss_Nexus 1 17036
17036
