Protoss_Gateway 2 6307
Protoss_Assimilator 1 4379
Protoss_Cybernetics_Core 1 5707
Protoss_Dragoon 13 14902
Protoss_Zealot 2 9810
Singularity_Charge 1 9367
Protoss_Nexus 1 14894
Protoss_Robotics_Facility 1 15692
15692
