Protoss_Gateway 4 15050
Protoss_Assimilator 1 4498
Protoss_Cybernetics_Core 1 5727
Protoss_Dragoon 12 15712
Singularity_Charge 1 9680
Protoss_Nexus 1 12871
Protoss_Robotics_Facility 1 12370
Protoss_Observatory 1 13143
Protoss_Observer 2 15064
15712
