Protoss_Gateway 2 9929
Protoss_Assimilator 1 4581
Protoss_Cybernetics_Core 1 5948
Protoss_Dragoon 8 13912
Protoss_Robotics_Facility 1 9892
Protoss_Observatory 1 10598
Singularity_Charge 1 10070
Protoss_Observer 2 12554
Protoss_Nexus 1 13903
Protoss_Shuttle 1 13255
Protoss_Robotics_Support_Bay 1 12897
Protoss_Reaver 1 15044
Protoss_Zealot 2 14774
15044
