Protoss_Gateway 2 8870
Protoss_Zealot 5 14710
Protoss_Assimilator 1 6497
Protoss_Cybernetics_Core 1 7694
Protoss_Dragoon 9 13848
Protoss_Robotics_Facility 1 13734
Singularity_Charge 1 12206
Protoss_Shuttle 1 15179
Protoss_Robotics_Support_Bay 1 14507
15179
