Protoss_Gateway 2 13171
Protoss_Assimilator 1 4334
Protoss_Cybernetics_Core 1 6121
Protoss_Dragoon 5 15273
Protoss_Robotics_Facility 1 8773
Protoss_Shuttle 1 10176
Protoss_Robotics_Support_Bay 1 9557
Protoss_Zealot 2 11367
Protoss_Reaver 2 13797
Gravitic_Drive 1 13280
Protoss_Nexus 1 16401
Protoss_Observatory 1 14621
16401
