Protoss_Nexus 2 15618
Protoss_Gateway 3 11600
Protoss_Assimilator 2 15555
Protoss_Cybernetics_Core 1 7442
Protoss_Zealot 1 8132
Protoss_Dragoon 8 13258
Protoss_Robotics_Facility 1 12578
Singularity_Charge 1 12353
Protoss_Shuttle 1 14045
Protoss_Robotics_Support_Bay 1 13618
Protoss_Observatory 1 14113
Protoss_Reaver 1 15603
15618
