Protoss_Gateway 3 15324
Protoss_Assimilator 1 4472
Protoss_Cybernetics_Core 1 5781
Protoss_Dragoon 7 15069
Protoss_Nexus 2 16148
Singularity_Charge 1 9575
Protoss_Robotics_Facility 1 13340
Protoss_Observatory 1 14350
16148
