Protoss_Gateway 2 6516
Protoss_Assimilator 1 4422
Protoss_Cybernetics_Core 1 5689
Protoss_Dragoon 9 12531
Protoss_Robotics_Facility 1 11524
Singularity_Charge 1 9686
Protoss_Shuttle 1 13173
Protoss_Robotics_Support_Bay 1 12724
Protoss_Reaver 1 14731
Protoss_Zealot 2 14546
14731
