Protoss_Nexus 1 6739
Protoss_Gateway 2 9045
Protoss_Assimilator 1 5635
Protoss_Cybernetics_Core 1 7208
Protoss_Zealot 1 7308
Protoss_Dragoon 10 14618
Protoss_Robotics_Facility 1 12399
Protoss_Observatory 1 13412
Singularity_Charge 1 12809
Protoss_Observer 1 14537
14618
