Protoss_Gateway 3 16051
Protoss_Assimilator 1 4791
Protoss_Cybernetics_Core 1 6285
Protoss_Dragoon 11 15051
Singularity_Charge 1 9982
Protoss_Robotics_Facility 1 11956
Protoss_Nexus 1 14664
Protoss_Observatory 1 12784
Protoss_Observer 2 14749
16051
