Protoss_Gateway 2 9468
Protoss_Assimilator 2 14698
Protoss_Cybernetics_Core 1 5677
Protoss_Dragoon 7 14630
Protoss_Citadel_of_Adun 1 8818
Protoss_Robotics_Facility 1 9630
Protoss_Templar_Archives 1 10324
Protoss_Zealot 3 14827
Protoss_Shuttle 2 15084
Protoss_Dark_Templar 2 11744
Protoss_Nexus 1 14861
Protoss_Observatory 1 13434
Protoss_Robotics_Support_Bay 1 14650
Protoss_Forge 1 15482
15482
