Protoss_Gateway 5 13531
Protoss_Assimilator 2 14370
Protoss_Cybernetics_Core 1 5969
Protoss_Dragoon 8 13825
Singularity_Charge 1 10160
Protoss_Nexus 1 13218
Protoss_Robotics_Facility 1 13362
Protoss_Observatory 1 14366
Protoss_Zealot 3 15005
Protoss_Shuttle 1 15915
15915
