Protoss_Gateway 3 13224
Protoss_Zealot 4 14192
Protoss_Nexus 1 8677
Protoss_Assimilator 2 12166
Protoss_Cybernetics_Core 1 8837
Protoss_Dragoon 9 15311
Singularity_Charge 1 13518
15311
