Protoss_Gateway 3 13694
Protoss_Assimilator 2 14835
Protoss_Cybernetics_Core 1 5663
Protoss_Dragoon 11 15628
Protoss_Robotics_Facility 1 9671
Singularity_Charge 1 9666
Protoss_Observatory 1 10437
Protoss_Observer 4 15149
Protoss_Nexus 1 13465
Protoss_Citadel_of_Adun 1 13545
Protoss_Templar_Archives 1 15352
15628
