Protoss_Gateway 2 14061
Protoss_Assimilator 1 4574
Protoss_Zealot 3 15386
Protoss_Cybernetics_Core 1 6789
Protoss_Dragoon 6 14565
Protoss_Robotics_Facility 1 10151
Protoss_Observatory 1 10880
Protoss_Nexus 1 13530
Protoss_Observer 2 12790
Singularity_Charge 1 11281
Protoss_Shuttle 1 14148
Protoss_Robotics_Support_Bay 1 13520
Protoss_Reaver 1 15793
15793
