Protoss_Forge 1 5031
Protoss_Photon_Cannon 6 14214
Protoss_Nexus 2 17115
Protoss_Assimilator 1 9419
Protoss_Gateway 1 10312
Protoss_Cybernetics_Core 1 11876
Protoss_Stargate 2 13689
Protoss_Scout 2 15597
17115
