Protoss_Gateway 2 8133
Protoss_Assimilator 1 4360
Protoss_Cybernetics_Core 1 5707
Protoss_Dragoon 9 15060
Singularity_Charge 1 9719
Protoss_Robotics_Facility 1 11714
Protoss_Zealot 2 11628
Protoss_Shuttle 1 13185
Protoss_Robotics_Support_Bay 1 12742
Protoss_Reaver 1 15108
15108
