Protoss_Gateway 2 11465
Protoss_Assimilator 1 4761
Protoss_Cybernetics_Core 1 6219
Protoss_Dragoon 9 15712
Protoss_Robotics_Facility 1 10924
Singularity_Charge 1 10311
Protoss_Shuttle 1 12435
Protoss_Zealot 4 13315
Protoss_Observatory 1 12874
Protoss_Observer 1 14292
Protoss_Nexus 1 16896
16896
