Protoss_Nexus 1 6817
Protoss_Gateway 6 15585
Protoss_Assimilator 2 13371
Protoss_Cybernetics_Core 1 7624
Protoss_Zealot 5 14512
Protoss_Dragoon 7 13393
Protoss_Robotics_Facility 1 12234
Singularity_Charge 1 11489
Protoss_Observatory 1 12938
Protoss_Observer 2 14844
Protoss_Citadel_of_Adun 1 15495
15585
