Protoss_Gateway 3 15179
Protoss_Assimilator 1 4572
Protoss_Cybernetics_Core 1 5951
Protoss_Dragoon 1 7163
Protoss_Robotics_Facility 1 8940
Protoss_Nexus 1 11503
Protoss_Observatory 1 9676
Protoss_Observer 1 10751
Protoss_Forge 1 10766
Protoss_Zealot 3 14058
Protoss_Shuttle 1 12147
Protoss_Photon_Cannon 4 14643
15179
