Protoss_Gateway 2 6511
Protoss_Assimilator 1 4476
Protoss_Cybernetics_Core 1 5888
Protoss_Dragoon 12 14751
Singularity_Charge 1 9997
Protoss_Nexus 1 14337
Protoss_Zealot 2 13041
Protoss_Robotics_Facility 1 14847
14847
