Protoss_Gateway 2 9021
Protoss_Assimilator 1 4372
Protoss_Cybernetics_Core 1 5933
Protoss_Zealot 1 6807
Protoss_Citadel_of_Adun 1 7951
Protoss_Robotics_Facility 1 9172
Protoss_Templar_Archives 1 9672
Protoss_Shuttle 1 10606
Protoss_Dark_Templar 4 12980
Protoss_Forge 1 11108
Protoss_Photon_Cannon 2 14444
Protoss_Dragoon 4 15512
Protoss_Observatory 1 14549
15512
