Protoss_Gateway 4 13638
Protoss_Assimilator 1 4113
Protoss_Cybernetics_Core 1 5598
Protoss_Dragoon 13 15557
Singularity_Charge 1 9704
Protoss_Nexus 1 12663
Protoss_Robotics_Facility 1 14770
15557
