Protoss_Gateway 3 15961
Protoss_Assimilator 1 4466
Protoss_Cybernetics_Core 1 5736
Protoss_Dragoon 8 15821
Protoss_Robotics_Facility 1 9926
Singularity_Charge 1 9698
Protoss_Observatory 1 10651
Protoss_Observer 2 12693
Protoss_Nexus 1 14062
Protoss_Zealot 4 13492
Protoss_Shuttle 1 14297
15961
