Protoss_Gateway 2 7871
Protoss_Assimilator 1 4349
Protoss_Zealot 3 6892
Protoss_Cybernetics_Core 1 7340
Protoss_Dragoon 10 14966
Protoss_Nexus 1 14500
Singularity_Charge 1 11662
Protoss_Robotics_Facility 1 15010
15010
