Protoss_Gateway 3 15779
Protoss_Assimilator 1 4432
Protoss_Cybernetics_Core 1 5850
Protoss_Dragoon 11 15351
Protoss_Robotics_Facility 1 9926
Singularity_Charge 1 9843
Protoss_Observatory 1 10648
Protoss_Observer 3 15561
Protoss_Nexus 1 14832
Protoss_Shuttle 1 14718
15779
