Protoss_Forge 1 4872
Protoss_Photon_Cannon 3 13847
Protoss_Nexus 2 11393
Protoss_Gateway 1 9094
Protoss_Assimilator 2 11363
Protoss_Cybernetics_Core 1 11417
Protoss_Zealot 4 15024
Protoss_Stargate 1 13434
Protoss_Robotics_Facility 1 14404
Protoss_Corsair 2 15441
Protoss_Robotics_Support_Bay 1 15155
15441
