Protoss_Forge 1 4735
Protoss_Photon_Cannon 7 15300
Protoss_Nexus 2 15731
Protoss_Gateway 2 12672
Protoss_Zealot 3 11250
Protoss_Assimilator 2 12693
Protoss_Cybernetics_Core 1 11393
Protoss_Dragoon 1 12636
Protoss_Stargate 1 13698
Protoss_Corsair 1 14727
Protoss_Citadel_of_Adun 1 15945
15945
