Protoss_Gateway 2 5294
Protoss_Zealot 9 9463
Protoss_Forge 1 9885
Protoss_Photon_Cannon 6 15347
Protoss_Nexus 1 13454
Protoss_Assimilator 2 14799
Protoss_Cybernetics_Core 1 12690
Protoss_Stargate 1 14763
15347
