Protoss_Nexus 1 7432
Protoss_Forge 1 5929
Protoss_Gateway 4 12067
Protoss_Assimilator 2 14658
Protoss_Photon_Cannon 2 15518
Protoss_Cybernetics_Core 1 9056
Protoss_Zealot 14 15140
Protoss_Citadel_of_Adun 1 10843
Protoss_Templar_Archives 1 14955
Leg_Enhancements 1 13775
15518
