Protoss_Gateway 2 5518
Protoss_Zealot 14 14432
Protoss_Assimilator 1 9216
Protoss_Cybernetics_Core 1 11007
Protoss_Dragoon 2 15212
Protoss_Robotics_Facility 1 14324
Protoss_Shuttle 1 15839
15839
