Protoss_Forge 1 3975
Protoss_Photon_Cannon 6 14959
Protoss_Nexus 1 8730
Protoss_Gateway 1 7982
Protoss_Assimilator 2 10884
Protoss_Cybernetics_Core 1 10142
Protoss_Zealot 2 11534
Protoss_Robotics_Facility 1 12260
Protoss_Stargate 1 12867
Protoss_Robotics_Support_Bay 1 12996
Protoss_Corsair 2 15017
Protoss_Reaver 2 16276
16276
