Protoss_Nexus 1 6804
Protoss_Forge 1 6481
Protoss_Gateway 4 15741
Protoss_Assimilator 2 10780
Protoss_Photon_Cannon 5 14129
Protoss_Cybernetics_Core 1 9766
Protoss_Zealot 3 13837
Protoss_Dragoon 2 12080
Protoss_Stargate 1 11804
Protoss_Citadel_of_Adun 1 12968
Protoss_Corsair 2 13621
Protoss_Templar_Archives 1 15257
15741
