Protoss_Forge 1 4148
Protoss_Nexus 1 7874
Protoss_Gateway 5 14474
Protoss_Photon_Cannon 2 8864
Protoss_Assimilator 2 12449
Protoss_Zealot 11 15554
Protoss_Cybernetics_Core 1 10679
Protoss_Citadel_of_Adun 1 12292
Protoss_Stargate 1 13030
Protoss_Corsair 1 13985
Protoss_Templar_Archives 1 14990
15554
