Protoss_Forge 1 4015
Protoss_Nexus 1 7805
Protoss_Gateway 5 15526
Protoss_Photon_Cannon 2 8909
Protoss_Assimilator 2 15339
Protoss_Zealot 10 15185
Protoss_Cybernetics_Core 1 10021
Protoss_Citadel_of_Adun 1 11724
Protoss_Templar_Archives 1 14645
15526
