Protoss_Gateway 3 10656
Protoss_Assimilator 1 4498
Protoss_Zealot 11 14314
Protoss_Cybernetics_Core 1 6950
Protoss_Dragoon 1 8510
Protoss_Citadel_of_Adun 1 9772
Protoss_Templar_Archives 1 11676
Protoss_Forge 1 13123
Protoss_High_Templar 4 14694
Leg_Enhancements 1 12733
Protoss_Archon 1 14097
Protoss_Photon_Cannon 1 14878
Protoss_Nexus 1 17157
17157
