Protoss_Gateway 1 4221
Protoss_Assimilator 1 4220
Protoss_Cybernetics_Core 1 5794
Protoss_Stargate 1 7559
Protoss_Dragoon 1 7544
Protoss_Corsair 4 12858
Protoss_Robotics_Facility 1 10112
Protoss_Forge 1 10196
Protoss_Shuttle 1 11543
Protoss_Photon_Cannon 3 14403
Protoss_Robotics_Support_Bay 1 11978
Protoss_Zealot 1 13992
Protoss_Reaver 1 14737
14737
