Protoss_Gateway 3 11067
Protoss_Zealot 11 15437
Protoss_Assimilator 1 6759
Protoss_Cybernetics_Core 1 8560
Protoss_Citadel_of_Adun 1 10101
Protoss_Dragoon 1 9944
Protoss_Templar_Archives 1 12157
Protoss_Dark_Templar 2 14575
Protoss_High_Templar 2 15292
Leg_Enhancements 1 13816
15437
