Protoss_Forge 1 4110
Protoss_Photon_Cannon 2 6859
Protoss_Nexus 1 8064
Protoss_Gateway 5 15288
Protoss_Assimilator 1 8657
Protoss_Zealot 10 15251
Protoss_Cybernetics_Core 1 10155
Protoss_Citadel_of_Adun 1 12211
15288
