Protoss_Forge 1 3844
Protoss_Photon_Cannon 4 14959
Protoss_Nexus 1 9417
Protoss_Gateway 5 16019
Protoss_Assimilator 2 12810
Protoss_Cybernetics_Core 1 10182
Protoss_Zealot 8 15244
Protoss_Citadel_of_Adun 1 12009
Protoss_Dragoon 1 11988
Protoss_Templar_Archives 1 14506
Protoss_High_Templar 2 15724
16019
