Protoss_Forge 1 4472
Protoss_Nexus 1 7654
Protoss_Photon_Cannon 4 15354
Protoss_Gateway 3 13430
Protoss_Assimilator 2 9968
Protoss_Cybernetics_Core 1 10038
Protoss_Zealot 3 12702
Protoss_Stargate 1 11798
Protoss_Citadel_of_Adun 1 12146
Protoss_Corsair 3 14982
Protoss_Templar_Archives 1 13714
Protoss_Dark_Templar 2 15388
15388
