Protoss_Forge 1 3923
Protoss_Nexus 1 8078
Protoss_Photon_Cannon 6 14681
Protoss_Gateway 3 15533
Protoss_Assimilator 2 12197
Protoss_Zealot 4 13063
Protoss_Cybernetics_Core 1 11736
Protoss_Stargate 1 13551
Protoss_Citadel_of_Adun 1 14224
Protoss_Corsair 2 15378
Protoss_Templar_Archives 1 15936
15936
