Protoss_Nexus 1 6900
Protoss_Gateway 4 12801
Protoss_Forge 1 6550
Protoss_Photon_Cannon 2 7889
Protoss_Zealot 14 15579
Protoss_Assimilator 2 9405
Protoss_Cybernetics_Core 1 10640
Protoss_Citadel_of_Adun 1 12424
Protoss_Templar_Archives 1 15154
15579
