Protoss_Gateway 2 4975
Protoss_Zealot 14 14285
Protoss_Assimilator 1 8484
Protoss_Cybernetics_Core 1 9646
Protoss_Citadel_of_Adun 1 11107
Protoss_Dragoon 1 11092
Protoss_Nexus 1 15132
Protoss_Templar_Archives 1 14004
Protoss_Forge 1 14749
Protoss_High_Templar 2 15475
15475
