Protoss_Forge 1 4630
Protoss_Nexus 1 7398
Protoss_Photon_Cannon 3 8255
Protoss_Gateway 3 15662
Protoss_Assimilator 3 13918
Protoss_Zealot 5 14598
Protoss_Cybernetics_Core 1 13455
Protoss_Citadel_of_Adun 1 14986
15662
