Protoss_Gateway 2 4758
Protoss_Zealot 13 10975
Protoss_Nexus 1 13881
Protoss_Assimilator 1 12662
Protoss_Forge 1 13065
Protoss_Cybernetics_Core 1 14229
Protoss_Photon_Cannon 2 15184
Protoss_Stargate 1 16045
16045
