Protoss_Forge 1 4343
Protoss_Photon_Cannon 6 10460
Protoss_Nexus 1 9835
Protoss_Gateway 2 14992
Protoss_Assimilator 2 12551
Protoss_Zealot 2 13767
Protoss_Cybernetics_Core 1 11268
Protoss_Stargate 1 12976
Protoss_Citadel_of_Adun 1 13410
Protoss_Corsair 2 14794
Protoss_Templar_Archives 1 14928
14992
