Protoss_Forge 1 4094
Protoss_Photon_Cannon 3 15704
Protoss_Nexus 1 8121
Protoss_Gateway 3 14622
Protoss_Assimilator 2 9634
Protoss_Zealot 5 14932
Protoss_Cybernetics_Core 1 11390
Protoss_Citadel_of_Adun 1 12867
Protoss_Templar_Archives 1 15588
15704
