Protoss_Nexus 1 7010
Protoss_Gateway 4 15001
Protoss_Forge 1 6510
Protoss_Assimilator 2 9558
Protoss_Photon_Cannon 3 15222
Protoss_Zealot 8 15342
Protoss_Cybernetics_Core 1 9877
Protoss_Stargate 1 11582
Protoss_Citadel_of_Adun 1 11464
Protoss_Templar_Archives 1 12933
Protoss_Corsair 1 12637
Protoss_Robotics_Facility 1 14852
Protoss_Dark_Templar 2 14387
15342
