Protoss_Nexus 1 7124
Protoss_Gateway 1 6230
Protoss_Forge 1 6769
Protoss_Zealot 3 12462
Protoss_Photon_Cannon 6 15083
Protoss_Assimilator 2 10947
Protoss_Cybernetics_Core 1 10349
Protoss_Stargate 1 12076
Protoss_Citadel_of_Adun 1 12604
Protoss_Corsair 3 15040
Protoss_Templar_Archives 1 14165
Protoss_Dark_Templar 1 15464
15464
