Protoss_Forge 1 4144
Protoss_Gateway 2 15895
Protoss_Photon_Cannon 2 15269
Protoss_Zealot 6 14373
Protoss_Nexus 1 9688
Protoss_Assimilator 2 9535
Protoss_Cybernetics_Core 1 9415
Protoss_Stargate 1 11567
Protoss_Citadel_of_Adun 1 11689
Protoss_Corsair 4 15286
Protoss_Templar_Archives 1 14467
Protoss_Dark_Templar 1 15692
15895
