Protoss_Forge 1 3904
Protoss_Photon_Cannon 3 8891
Protoss_Nexus 1 9573
Protoss_Gateway 3 13253
Protoss_Zealot 11 15552
Protoss_Cybernetics_Core 1 10062
Protoss_Assimilator 2 12953
Protoss_Citadel_of_Adun 1 12118
Protoss_Templar_Archives 1 15716
15716
