Protoss_Forge 1 3867
Protoss_Photon_Cannon 3 15639
Protoss_Nexus 1 8997
Protoss_Gateway 3 13979
Protoss_Assimilator 2 10774
Protoss_Cybernetics_Core 1 9544
Protoss_Zealot 8 15008
Protoss_Stargate 1 11860
Protoss_Citadel_of_Adun 1 12847
Protoss_Corsair 1 13035
Protoss_Templar_Archives 1 15192
15639
