Protoss_Forge 1 3889
Protoss_Photon_Cannon 4 15660
Protoss_Nexus 1 8788
Protoss_Gateway 2 14808
Protoss_Assimilator 2 11818
Protoss_Zealot 3 11472
Protoss_Cybernetics_Core 1 11469
Protoss_Dragoon 1 12906
Protoss_Stargate 1 13488
Protoss_Citadel_of_Adun 1 13717
Protoss_Corsair 2 15312
Protoss_Templar_Archives 1 15348
15660
