Protoss_Gateway 4 11020
Protoss_Assimilator 1 4668
Protoss_Zealot 3 7575
Protoss_Cybernetics_Core 1 7625
Protoss_Dragoon 9 14700
Protoss_Robotics_Facility 1 14610
Singularity_Charge 1 14065
Protoss_Forge 1 15023
15023
