Protoss_Forge 1 4956
Protoss_Photon_Cannon 4 13762
Protoss_Nexus 1 8762
Protoss_Gateway 1 7747
Protoss_Assimilator 2 11790
Protoss_Cybernetics_Core 1 9497
Protoss_Zealot 3 12441
Protoss_Stargate 1 11229
Protoss_Robotics_Facility 1 12888
Protoss_Corsair 3 14775
Protoss_Robotics_Support_Bay 1 14236
Protoss_Reaver 1 15987
15987
