Protoss_Gateway 2 15520
Protoss_Zealot 12 15432
Protoss_Forge 1 5739
Protoss_Nexus 1 10427
Protoss_Photon_Cannon 2 14855
Protoss_Assimilator 2 11708
Protoss_Cybernetics_Core 1 10842
Protoss_Stargate 1 13162
Protoss_Citadel_of_Adun 1 13593
Protoss_Corsair 1 14148
15520
