Protoss_Forge 1 4741
Protoss_Nexus 1 7473
Protoss_Photon_Cannon 6 15227
Protoss_Gateway 5 14568
Protoss_Assimilator 2 11770
Protoss_Cybernetics_Core 1 9258
Protoss_Zealot 5 14408
Protoss_Stargate 1 10955
Protoss_Corsair 1 11903
Protoss_Robotics_Facility 1 13295
Protoss_Robotics_Support_Bay 1 14091
Protoss_Reaver 1 15899
Protoss_Dragoon 1 15671
15899
