Protoss_Forge 1 3781
Protoss_Photon_Cannon 2 6000
Protoss_Nexus 1 9052
Protoss_Gateway 3 14487
Protoss_Assimilator 2 10688
Protoss_Cybernetics_Core 1 10098
Protoss_Zealot 4 14439
Protoss_Stargate 1 12670
Protoss_Citadel_of_Adun 1 13574
Protoss_Corsair 2 15419
Protoss_Templar_Archives 1 15131
15419
