Protoss_Forge 1 3951
Protoss_Nexus 1 7840
Protoss_Gateway 4 15532
Protoss_Photon_Cannon 4 14908
Protoss_Assimilator 2 10861
Protoss_Cybernetics_Core 1 9156
Protoss_Zealot 2 11522
Protoss_Stargate 1 10917
Protoss_Citadel_of_Adun 1 11702
Protoss_Corsair 4 15535
Protoss_Templar_Archives 1 13334
Protoss_High_Templar 1 14735
15535
