Protoss_Forge 1 4229
Protoss_Nexus 1 7591
Protoss_Photon_Cannon 6 15525
Protoss_Gateway 6 15049
Protoss_Zealot 4 12819
Protoss_Assimilator 2 10883
Protoss_Cybernetics_Core 1 11070
Protoss_Citadel_of_Adun 1 12738
Protoss_Templar_Archives 1 14187
Protoss_High_Templar 4 15633
15633
