Protoss_Forge 1 5174
Protoss_Photon_Cannon 3 9393
Protoss_Nexus 1 9769
Protoss_Gateway 4 14955
Protoss_Assimilator 2 15514
Protoss_Cybernetics_Core 1 10325
Protoss_Zealot 7 14967
Protoss_Stargate 1 12176
Protoss_Citadel_of_Adun 1 12422
Protoss_Corsair 1 13112
Protoss_Templar_Archives 1 15864
15864
