Protoss_Forge 1 4621
Protoss_Photon_Cannon 4 13067
Protoss_Nexus 1 8648
Protoss_Gateway 3 15350
Protoss_Assimilator 2 10139
Protoss_Cybernetics_Core 1 9687
Protoss_Zealot 6 15128
Protoss_Citadel_of_Adun 1 12175
Protoss_Templar_Archives 1 13827
15350
