Protoss_Forge 1 4965
Protoss_Nexus 1 7527
Protoss_Photon_Cannon 2 7753
Protoss_Gateway 4 14799
Protoss_Assimilator 2 10429
Protoss_Cybernetics_Core 1 10167
Protoss_Zealot 4 15585
Protoss_Stargate 1 11902
Protoss_Citadel_of_Adun 1 11903
Protoss_Dragoon 1 12815
Protoss_Corsair 2 14721
Protoss_Templar_Archives 1 13704
Protoss_High_Templar 2 15818
15818
