Protoss_Forge 1 4590
Protoss_Photon_Cannon 4 15134
Protoss_Nexus 1 8226
Protoss_Gateway 4 15996
Protoss_Assimilator 2 11691
Protoss_Zealot 6 13829
Protoss_Cybernetics_Core 1 11319
Protoss_Stargate 1 13187
Protoss_Citadel_of_Adun 1 13287
Protoss_Corsair 2 15555
Protoss_Templar_Archives 1 15178
15996
