Protoss_Nexus 1 7047
Protoss_Gateway 1 6866
Protoss_Assimilator 1 7344
Protoss_Forge 1 7848
Protoss_Zealot 3 11149
Protoss_Photon_Cannon 4 10722
Protoss_Cybernetics_Core 1 11838
11838
