Protoss_Forge 1 4129
Protoss_Nexus 1 7483
Protoss_Photon_Cannon 2 6765
Protoss_Gateway 6 16059
Protoss_Assimilator 2 10297
Protoss_Cybernetics_Core 1 9462
Protoss_Zealot 3 14452
Protoss_Stargate 1 11318
Protoss_Citadel_of_Adun 1 11601
Protoss_Dragoon 1 11761
Protoss_Corsair 2 13284
Protoss_Templar_Archives 1 13457
Protoss_High_Templar 2 14788
16059
