Protoss_Forge 1 4313
Protoss_Photon_Cannon 6 11711
Protoss_Nexus 1 8513
Protoss_Gateway 2 12904
Protoss_Assimilator 2 13152
Protoss_Zealot 7 15517
Protoss_Cybernetics_Core 1 12794
Protoss_Stargate 1 14693
Protoss_Citadel_of_Adun 1 15807
15807
