Protoss_Gateway 1 4198
Protoss_Zealot 7 14540
Protoss_Nexus 1 8917
Protoss_Assimilator 1 7681
Protoss_Cybernetics_Core 1 9075
Protoss_Forge 1 8914
Protoss_Stargate 1 10765
Protoss_Dragoon 1 10652
Protoss_Photon_Cannon 2 14714
Protoss_Corsair 2 14914
14914
