Protoss_Forge 1 4242
Protoss_Photon_Cannon 5 15082
Protoss_Nexus 1 8654
Protoss_Gateway 3 14939
Protoss_Assimilator 2 12749
Protoss_Cybernetics_Core 1 9153
Protoss_Zealot 4 13916
Protoss_Stargate 1 11242
Protoss_Citadel_of_Adun 1 12040
Protoss_Corsair 3 14686
Protoss_Templar_Archives 1 13688
Protoss_High_Templar 2 15546
15546
