Protoss_Gateway 3 14152
Protoss_Zealot 9 13913
Protoss_Assimilator 2 7009
Protoss_Cybernetics_Core 1 8671
Protoss_Stargate 1 10601
Protoss_Citadel_of_Adun 1 11193
Protoss_Corsair 1 12315
Protoss_Templar_Archives 1 13312
Protoss_Forge 1 13275
Protoss_Dark_Templar 2 15472
15472
