Protoss_Forge 1 3930
Protoss_Photon_Cannon 3 13269
Protoss_Nexus 1 8964
Protoss_Gateway 4 14162
Protoss_Assimilator 2 9822
Protoss_Cybernetics_Core 1 9629
Protoss_Zealot 3 12699
Protoss_Dragoon 2 15645
Protoss_Citadel_of_Adun 1 11549
Protoss_Templar_Archives 1 12994
Protoss_Dark_Templar 2 15607
Protoss_High_Templar 2 15730
15730
