Protoss_Gateway 2 9535
Protoss_Assimilator 1 4615
Protoss_Zealot 10 14818
Protoss_Cybernetics_Core 1 6447
Protoss_Dragoon 1 7740
Protoss_Citadel_of_Adun 1 8499
Protoss_Templar_Archives 1 11153
Protoss_High_Templar 4 13956
Leg_Enhancements 1 11703
Protoss_Nexus 1 15318
Protoss_Forge 1 13615
Protoss_Archon 2 14428
Protoss_Photon_Cannon 2 15600
15600
