Protoss_Forge 1 4068
Protoss_Photon_Cannon 4 15751
Protoss_Nexus 1 8569
Protoss_Gateway 4 13488
Protoss_Assimilator 2 11650
Protoss_Zealot 7 14136
Protoss_Cybernetics_Core 1 9668
Protoss_Dragoon 1 11135
Protoss_Citadel_of_Adun 1 11828
Protoss_Templar_Archives 1 14011
Protoss_High_Templar 1 15206
15751
