Protoss_Forge 1 4356
Protoss_Photon_Cannon 4 13555
Protoss_Nexus 1 8908
Protoss_Gateway 3 16054
Protoss_Assimilator 2 10628
Protoss_Zealot 5 14786
Protoss_Cybernetics_Core 1 10299
Protoss_Stargate 1 12019
Protoss_Dragoon 1 11867
Protoss_Corsair 2 14189
Protoss_Citadel_of_Adun 1 13947
Protoss_Templar_Archives 1 15525
16054
