Protoss_Gateway 2 13414
Protoss_Zealot 12 15492
Protoss_Forge 1 5183
Protoss_Photon_Cannon 3 7201
Protoss_Assimilator 1 7328
Protoss_Cybernetics_Core 1 11249
Protoss_Dragoon 1 12461
Protoss_Citadel_of_Adun 1 12826
Protoss_Ground_Weapons_1 1 14482
15492
