Protoss_Forge 1 3734
Protoss_Photon_Cannon 4 15470
Protoss_Nexus 1 9175
Protoss_Gateway 2 13830
Protoss_Assimilator 2 11291
Protoss_Cybernetics_Core 1 9788
Protoss_Zealot 4 13714
Protoss_Dragoon 1 11091
Protoss_Stargate 1 11718
Protoss_Citadel_of_Adun 1 12560
Protoss_Corsair 2 15251
Protoss_Templar_Archives 1 14537
15470
