Protoss_Forge 1 4559
Protoss_Photon_Cannon 4 14864
Protoss_Nexus 1 8782
Protoss_Gateway 3 13687
Protoss_Assimilator 2 11691
Protoss_Cybernetics_Core 1 9233
Protoss_Zealot 7 15520
Protoss_Citadel_of_Adun 1 10782
Protoss_Dragoon 1 11062
Protoss_Templar_Archives 1 13170
Protoss_High_Templar 2 14433
Protoss_Dark_Templar 1 14908
Leg_Enhancements 1 13717
Protoss_Robotics_Facility 1 16134
16134
