Protoss_Forge 1 4204
Protoss_Photon_Cannon 4 15513
Protoss_Nexus 1 8721
Protoss_Gateway 2 14270
Protoss_Assimilator 2 11543
Protoss_Zealot 6 15529
Protoss_Cybernetics_Core 1 9639
Protoss_Stargate 1 11762
Protoss_Citadel_of_Adun 1 11815
Protoss_Corsair 2 14145
Protoss_Templar_Archives 1 15444
15529
