Protoss_Nexus 1 6991
Protoss_Forge 1 5707
Protoss_Gateway 2 15188
Protoss_Photon_Cannon 7 14673
Protoss_Assimilator 2 10592
Protoss_Zealot 4 12977
Protoss_Cybernetics_Core 1 9342
Protoss_Stargate 1 11282
Protoss_Citadel_of_Adun 1 11897
Protoss_Dragoon 1 12115
Protoss_Corsair 4 15087
Protoss_Templar_Archives 1 13975
Protoss_High_Templar 1 15569
Protoss_Dark_Templar 1 15756
15756
