Protoss_Forge 1 4450
Protoss_Nexus 1 7650
Protoss_Photon_Cannon 4 15434
Protoss_Gateway 3 14870
Protoss_Assimilator 2 12525
Protoss_Zealot 4 14628
Protoss_Cybernetics_Core 1 10742
Protoss_Stargate 1 12505
Protoss_Dragoon 1 12291
Protoss_Citadel_of_Adun 1 12914
Protoss_Corsair 1 13442
Protoss_Templar_Archives 1 14529
Protoss_Dark_Templar 1 15748
Protoss_High_Templar 1 15748
15748
