Protoss_Forge 1 4132
Protoss_Photon_Cannon 4 15427
Protoss_Nexus 1 8902
Protoss_Gateway 3 16054
Protoss_Assimilator 2 11680
Protoss_Zealot 7 15102
Protoss_Cybernetics_Core 1 11003
Protoss_Stargate 1 13071
Protoss_Citadel_of_Adun 1 13589
Protoss_Corsair 2 15315
16054
