Protoss_Forge 1 4609
Protoss_Photon_Cannon 6 15745
Protoss_Nexus 1 9172
Protoss_Gateway 4 14967
Protoss_Assimilator 2 11054
Protoss_Zealot 5 15072
Protoss_Cybernetics_Core 1 11080
Protoss_Citadel_of_Adun 1 12614
Protoss_Dragoon 1 12715
Protoss_Templar_Archives 1 14232
15745
