Protoss_Forge 1 4634
Protoss_Nexus 1 7585
Protoss_Photon_Cannon 5 15671
Protoss_Gateway 3 11916
Protoss_Assimilator 2 10296
Protoss_Zealot 11 14891
Protoss_Cybernetics_Core 1 9535
Protoss_Dragoon 2 13137
Protoss_Citadel_of_Adun 1 11285
Protoss_Templar_Archives 1 14319
Leg_Enhancements 1 14246
15671
