Protoss_Gateway 2 5249
Protoss_Zealot 10 12272
Protoss_Assimilator 1 7770
Protoss_Cybernetics_Core 1 9593
Protoss_Citadel_of_Adun 1 11480
Protoss_Stargate 1 12271
Protoss_Dragoon 1 11908
Protoss_Templar_Archives 1 13313
Protoss_Corsair 1 13223
Protoss_Forge 1 13599
Protoss_Nexus 1 16533
Protoss_Dark_Templar 2 15625
16533
