Protoss_Forge 1 4839
Protoss_Nexus 1 7808
Protoss_Photon_Cannon 6 15661
Protoss_Gateway 1 7662
Protoss_Zealot 4 13006
Protoss_Assimilator 2 14724
Protoss_Cybernetics_Core 1 11205
Protoss_Stargate 1 13022
Protoss_Dragoon 1 14126
Protoss_Corsair 2 15029
Protoss_Robotics_Facility 1 15623
15661
