Protoss_Forge 1 3728
Protoss_Photon_Cannon 6 13697
Protoss_Nexus 1 9325
Protoss_Gateway 1 8232
Protoss_Assimilator 2 11500
Protoss_Cybernetics_Core 1 9734
Protoss_Zealot 3 12389
Protoss_Stargate 1 11620
Protoss_Robotics_Facility 1 13219
Protoss_Corsair 3 14683
Protoss_Shuttle 1 14724
Protoss_Robotics_Support_Bay 1 14252
14724
