Protoss_Forge 1 4264
Protoss_Photon_Cannon 2 8603
Protoss_Nexus 1 8920
Protoss_Gateway 4 12090
Protoss_Assimilator 1 8234
Protoss_Zealot 13 15140
Protoss_Cybernetics_Core 1 10878
Protoss_Citadel_of_Adun 1 13950
15140
