Protoss_Forge 1 3869
Protoss_Nexus 1 8016
Protoss_Gateway 5 14424
Protoss_Photon_Cannon 2 7643
Protoss_Assimilator 2 11172
Protoss_Cybernetics_Core 1 9348
Protoss_Zealot 9 15318
Protoss_Citadel_of_Adun 1 12194
Protoss_Stargate 1 12504
Protoss_Corsair 2 15368
Protoss_Templar_Archives 1 14809
15368
