Protoss_Forge 1 4571
Protoss_Photon_Cannon 4 15505
Protoss_Nexus 1 9116
Protoss_Gateway 3 15283
Protoss_Assimilator 2 12081
Protoss_Zealot 1 10653
Protoss_Cybernetics_Core 1 11680
Protoss_Stargate 1 13364
Protoss_Citadel_of_Adun 1 13868
Protoss_Corsair 2 15371
Protoss_Templar_Archives 1 15579
15579
