Protoss_Forge 1 5187
Protoss_Nexus 1 8005
Protoss_Photon_Cannon 8 15674
Protoss_Gateway 3 15204
Protoss_Assimilator 2 11200
Protoss_Cybernetics_Core 1 10430
Protoss_Zealot 5 14405
Protoss_Stargate 1 12205
Protoss_Citadel_of_Adun 1 13324
Protoss_Corsair 3 15128
Protoss_Templar_Archives 1 14784
15674
