Protoss_Forge 1 4120
Protoss_Photon_Cannon 6 15181
Protoss_Nexus 1 8370
Protoss_Gateway 4 15931
Protoss_Assimilator 2 11642
Protoss_Cybernetics_Core 1 9943
Protoss_Zealot 4 14563
Protoss_Stargate 1 11637
Protoss_Citadel_of_Adun 1 11868
Protoss_Corsair 1 12608
Protoss_Templar_Archives 1 15059
15931
