Protoss_Forge 1 4707
Protoss_Nexus 1 7637
Protoss_Photon_Cannon 3 13912
Protoss_Gateway 4 15021
Protoss_Assimilator 2 10155
Protoss_Cybernetics_Core 1 9058
Protoss_Zealot 7 14218
Protoss_Stargate 1 11110
Protoss_Citadel_of_Adun 1 11966
Protoss_Corsair 2 13890
Protoss_Templar_Archives 1 13600
15021
