Protoss_Forge 2 5655
Protoss_Nexus 1 7174
Protoss_Photon_Cannon 7 14553
Protoss_Gateway 2 14513
Protoss_Assimilator 2 11032
Protoss_Zealot 5 14666
Protoss_Cybernetics_Core 1 10275
Protoss_Stargate 1 12230
Protoss_Citadel_of_Adun 1 13413
Protoss_Corsair 1 13188
Protoss_Templar_Archives 1 15429
15429
