Protoss_Gateway 2 9355
Protoss_Zealot 5 11010
Protoss_Assimilator 1 5452
Protoss_Cybernetics_Core 1 7018
Protoss_Dragoon 1 8231
Protoss_Citadel_of_Adun 1 8876
Protoss_Templar_Archives 1 10612
Protoss_Nexus 1 13357
Protoss_High_Templar 4 14474
Protoss_Forge 1 12274
Protoss_Archon 1 12589
Protoss_Photon_Cannon 6 15707
15707
