Protoss_Forge 1 3972
Protoss_Nexus 1 7512
Protoss_Photon_Cannon 4 14049
Protoss_Gateway 2 14936
Protoss_Assimilator 2 13571
Protoss_Zealot 5 15392
Protoss_Cybernetics_Core 1 10634
Protoss_Stargate 1 12325
Protoss_Citadel_of_Adun 1 12380
Protoss_Dragoon 1 12800
Protoss_Corsair 1 13501
Protoss_Templar_Archives 1 14693
15392
