Protoss_Forge 1 4000
Protoss_Photon_Cannon 6 15775
Protoss_Nexus 1 9549
Protoss_Gateway 3 13880
Protoss_Assimilator 2 10606
Protoss_Cybernetics_Core 1 11260
Protoss_Zealot 3 13975
Protoss_Citadel_of_Adun 1 12809
Protoss_Dragoon 1 13029
Protoss_Templar_Archives 1 14332
Protoss_High_Templar 2 15639
Protoss_Dark_Templar 1 15654
15775
