Protoss_Gateway 2 13865
Protoss_Assimilator 1 4391
Protoss_Zealot 7 14885
Protoss_Cybernetics_Core 1 6869
Protoss_Stargate 1 8602
Protoss_Dragoon 1 8474
Protoss_Citadel_of_Adun 1 9242
Protoss_Corsair 1 9579
Protoss_Templar_Archives 1 10922
Protoss_Forge 1 11388
Protoss_Dark_Templar 2 13248
Protoss_Photon_Cannon 3 15670
Protoss_Nexus 1 17225
17225
