Protoss_Forge 1 5407
Protoss_Nexus 1 8150
Protoss_Photon_Cannon 6 12519
Protoss_Gateway 4 14846
Protoss_Assimilator 2 10512
Protoss_Cybernetics_Core 1 10695
Protoss_Stargate 1 13232
Protoss_Corsair 2 15192
Protoss_Citadel_of_Adun 1 14793
Protoss_Dragoon 2 15139
15192
