Protoss_Forge 1 4567
Protoss_Nexus 1 7607
Protoss_Photon_Cannon 4 15505
Protoss_Gateway 4 15261
Protoss_Assimilator 2 10856
Protoss_Cybernetics_Core 1 9655
Protoss_Zealot 3 13009
Protoss_Dragoon 1 10880
Protoss_Stargate 1 11387
Protoss_Citadel_of_Adun 1 11648
Protoss_Corsair 2 13433
Protoss_Templar_Archives 1 13157
Protoss_Dark_Templar 2 14837
15505
