Protoss_Gateway 2 5039
Protoss_Zealot 12 12274
Protoss_Nexus 1 13108
Protoss_Assimilator 1 11998
Protoss_Cybernetics_Core 1 13624
Protoss_Stargate 1 15347
Protoss_Forge 1 14919
15347
