Protoss_Forge 2 6096
Protoss_Nexus 1 7559
Protoss_Gateway 2 15629
Protoss_Photon_Cannon 2 7822
Protoss_Zealot 5 14897
Protoss_Assimilator 2 12787
Protoss_Cybernetics_Core 1 11742
Protoss_Stargate 1 13794
Protoss_Citadel_of_Adun 1 14607
Protoss_Corsair 1 14745
15629
