Protoss_Forge 1 4353
Protoss_Photon_Cannon 4 14583
Protoss_Nexus 1 8358
Protoss_Gateway 1 7265
Protoss_Assimilator 2 11376
Protoss_Zealot 4 12058
Protoss_Cybernetics_Core 1 9541
Protoss_Stargate 1 11702
Protoss_Corsair 3 15032
Protoss_Robotics_Facility 1 14305
Protoss_Observatory 1 15042
Protoss_Robotics_Support_Bay 1 15275
15275
