Protoss_Gateway 2 14827
Protoss_Assimilator 1 4545
Protoss_Zealot 5 14821
Protoss_Cybernetics_Core 1 7328
Protoss_Dragoon 1 8542
Protoss_Robotics_Facility 1 9651
Protoss_Forge 1 10548
Protoss_Shuttle 1 11077
Protoss_Robotics_Support_Bay 1 10997
Protoss_Citadel_of_Adun 1 11853
Protoss_Reaver 1 12729
Protoss_Templar_Archives 1 13489
Protoss_Photon_Cannon 2 15259
Protoss_High_Templar 1 15115
15259
