Protoss_Forge 1 3740
Protoss_Photon_Cannon 6 14571
Protoss_Nexus 1 8390
Protoss_Gateway 2 15971
Protoss_Zealot 4 11083
Protoss_Assimilator 2 11601
Protoss_Cybernetics_Core 1 11190
Protoss_Stargate 1 12960
Protoss_Citadel_of_Adun 1 13564
Protoss_Corsair 1 13960
Protoss_Templar_Archives 1 15075
15971
