Protoss_Gateway 3 14153
Protoss_Zealot 11 14057
Protoss_Assimilator 1 9024
Protoss_Forge 1 10293
Protoss_Cybernetics_Core 1 12001
Protoss_Photon_Cannon 1 12563
Protoss_Citadel_of_Adun 1 13773
14153
