Protoss_Forge 1 4053
Protoss_Photon_Cannon 2 7173
Protoss_Nexus 1 8351
Protoss_Gateway 2 12737
Protoss_Assimilator 2 11047
Protoss_Cybernetics_Core 1 9661
Protoss_Zealot 9 15093
Protoss_Stargate 1 11380
Protoss_Citadel_of_Adun 1 11957
Protoss_Corsair 3 15339
Protoss_Templar_Archives 1 14568
15339
