Protoss_Forge 1 3910
Protoss_Photon_Cannon 6 15417
Protoss_Nexus 1 9306
Protoss_Gateway 4 14806
Protoss_Assimilator 2 11029
Protoss_Zealot 3 13559
Protoss_Cybernetics_Core 1 10325
Protoss_Citadel_of_Adun 1 12037
Protoss_Dragoon 1 12648
Protoss_Templar_Archives 1 13837
Protoss_High_Templar 2 15554
15554
