Protoss_Forge 1 4177
Protoss_Photon_Cannon 2 5834
Protoss_Nexus 1 8916
Protoss_Gateway 1 8256
Protoss_Assimilator 2 11835
Protoss_Zealot 6 15231
Protoss_Cybernetics_Core 1 9956
Protoss_Stargate 1 11769
Protoss_Dragoon 1 11387
Protoss_Citadel_of_Adun 1 12031
Protoss_Corsair 1 13088
Protoss_Templar_Archives 1 14843
15231
