Protoss_Forge 3 7261
Protoss_Nexus 1 7347
Protoss_Gateway 3 14401
Protoss_Assimilator 1 8165
Protoss_Zealot 12 15254
Protoss_Photon_Cannon 2 14551
Protoss_Cybernetics_Core 1 11657
Protoss_Stargate 1 13863
Protoss_Citadel_of_Adun 1 13805
Protoss_Corsair 1 15330
15330
