Protoss_Forge 2 15317
Protoss_Photon_Cannon 5 15388
Protoss_Nexus 1 8718
Protoss_Gateway 2 12631
Protoss_Assimilator 2 10612
Protoss_Cybernetics_Core 1 9163
Protoss_Zealot 5 13729
Protoss_Stargate 1 10862
Protoss_Citadel_of_Adun 1 11914
Protoss_Corsair 3 14991
Protoss_Templar_Archives 1 14707
15388
