Protoss_Forge 1 4229
Protoss_Photon_Cannon 3 15609
Protoss_Nexus 1 8671
Protoss_Gateway 1 8095
Protoss_Assimilator 2 9926
Protoss_Cybernetics_Core 1 9544
Protoss_Zealot 6 15046
Protoss_Dragoon 1 10775
Protoss_Stargate 1 11498
Protoss_Robotics_Facility 1 12509
Protoss_Corsair 3 14203
Protoss_Robotics_Support_Bay 1 13274
Protoss_Reaver 1 15287
15609
