Protoss_Nexus 1 7410
Protoss_Forge 1 6115
Protoss_Gateway 3 15634
Protoss_Photon_Cannon 4 14489
Protoss_Assimilator 2 9719
Protoss_Cybernetics_Core 1 9680
Protoss_Zealot 5 13755
Protoss_Stargate 1 11454
Protoss_Citadel_of_Adun 1 11730
Protoss_Templar_Archives 1 13410
Protoss_Corsair 2 13954
15634
