Protoss_Nexus 1 7072
Protoss_Gateway 3 12244
Protoss_Forge 1 6272
Protoss_Assimilator 2 13545
Protoss_Photon_Cannon 3 13939
Protoss_Cybernetics_Core 1 8156
Protoss_Zealot 10 14999
Protoss_Dragoon 1 9777
Protoss_Stargate 1 10308
Protoss_Citadel_of_Adun 1 11638
Protoss_Corsair 4 15111
Protoss_Templar_Archives 1 15314
15314
