Protoss_Forge 1 4128
Protoss_Photon_Cannon 4 15793
Protoss_Nexus 1 8844
Protoss_Gateway 3 15617
Protoss_Assimilator 2 11175
Protoss_Zealot 3 14669
Protoss_Cybernetics_Core 1 9500
Protoss_Stargate 1 11349
Protoss_Citadel_of_Adun 1 12213
Protoss_Dragoon 1 12402
Protoss_Corsair 3 14472
Protoss_Templar_Archives 1 14800
15793
