Protoss_Forge 1 4428
Protoss_Photon_Cannon 6 14725
Protoss_Nexus 1 8999
Protoss_Gateway 3 15631
Protoss_Assimilator 2 11554
Protoss_Cybernetics_Core 1 9400
Protoss_Zealot 4 14707
Protoss_Stargate 1 11503
Protoss_Citadel_of_Adun 1 12555
Protoss_Corsair 3 15397
Protoss_Templar_Archives 1 14604
15631
