Protoss_Forge 2 6140
Protoss_Nexus 1 7278
Protoss_Gateway 5 16057
Protoss_Photon_Cannon 6 15598
Protoss_Assimilator 2 9816
Protoss_Zealot 8 15538
Protoss_Cybernetics_Core 1 9037
Protoss_Stargate 1 10822
Protoss_Citadel_of_Adun 1 11083
Protoss_Templar_Archives 1 12624
Protoss_Corsair 1 12216
Protoss_High_Templar 4 15692
16057
