Protoss_Forge 1 4125
Protoss_Nexus 1 7664
Protoss_Gateway 3 13767
Protoss_Photon_Cannon 1 7561
Protoss_Assimilator 2 9905
Protoss_Zealot 5 15333
Protoss_Cybernetics_Core 1 9023
Protoss_Stargate 1 11008
Protoss_Dragoon 1 10822
Protoss_Citadel_of_Adun 1 11717
Protoss_Corsair 2 13401
Protoss_Templar_Archives 1 13220
Protoss_High_Templar 2 14507
15333
