Protoss_Gateway 1 3877
Protoss_Zealot 10 14723
Protoss_Assimilator 1 6084
Protoss_Forge 1 8120
Protoss_Cybernetics_Core 1 10550
Protoss_Citadel_of_Adun 1 12029
Protoss_Dragoon 1 13861
Protoss_Photon_Cannon 2 15003
Protoss_Templar_Archives 1 15541
Protoss_Ground_Weapons_1 1 14138
15541
