Protoss_Gateway 1 3716
Protoss_Zealot 4 14827
Protoss_Assimilator 1 6548
Protoss_Forge 1 7792
Protoss_Photon_Cannon 3 14214
Protoss_Cybernetics_Core 1 9609
Protoss_Dragoon 2 15190
Protoss_Stargate 1 11664
Protoss_Robotics_Facility 1 13094
Protoss_Corsair 1 12683
Protoss_Shuttle 1 14594
Protoss_Robotics_Support_Bay 1 14372
Protoss_Ground_Weapons_1 1 14453
Protoss_Reaver 1 16152
16152
