Protoss_Forge 1 4272
Protoss_Nexus 1 7597
Protoss_Photon_Cannon 6 14997
Protoss_Gateway 4 15904
Protoss_Assimilator 2 10340
Protoss_Cybernetics_Core 1 8919
Protoss_Zealot 4 14203
Protoss_Stargate 1 10759
Protoss_Dragoon 1 10418
Protoss_Citadel_of_Adun 1 11309
Protoss_Corsair 1 12307
Protoss_Templar_Archives 1 13515
Protoss_Dark_Templar 2 14899
15904
