Protoss_Forge 1 3813
Protoss_Nexus 1 7705
Protoss_Gateway 3 13817
Protoss_Photon_Cannon 2 8594
Protoss_Assimilator 2 10431
Protoss_Cybernetics_Core 1 8519
Protoss_Zealot 2 13076
Protoss_Stargate 1 10753
Protoss_Citadel_of_Adun 1 11229
Protoss_Dragoon 1 11425
Protoss_Corsair 2 13492
Protoss_Templar_Archives 1 12987
Protoss_Dark_Templar 1 14196
Protoss_High_Templar 1 15025
15025
