Protoss_Forge 1 4173
Protoss_Nexus 1 7686
Protoss_Gateway 4 13246
Protoss_Photon_Cannon 2 8012
Protoss_Assimilator 2 10609
Protoss_Zealot 13 15506
Protoss_Cybernetics_Core 1 10032
Protoss_Stargate 1 11871
Protoss_Dragoon 1 11606
Protoss_Citadel_of_Adun 1 12075
Protoss_Templar_Archives 1 13992
15506
