Protoss_Forge 1 4141
Protoss_Nexus 2 17367
Protoss_Photon_Cannon 3 15110
Protoss_Gateway 3 12576
Protoss_Assimilator 2 10474
Protoss_Cybernetics_Core 1 9002
Protoss_Zealot 3 14651
Protoss_Stargate 1 10704
Protoss_Citadel_of_Adun 1 10701
Protoss_Corsair 2 12816
Protoss_Templar_Archives 1 12460
Protoss_Dark_Templar 2 13933
17367
