Protoss_Forge 1 4460
Protoss_Photon_Cannon 4 9066
Protoss_Nexus 1 8882
Protoss_Gateway 2 14035
Protoss_Assimilator 2 11054
Protoss_Zealot 6 14999
Protoss_Cybernetics_Core 1 10688
Protoss_Stargate 1 12401
Protoss_Dragoon 1 12244
Protoss_Citadel_of_Adun 1 13037
Protoss_Corsair 3 15526
15526
