Protoss_Nexus 1 7808
Protoss_Forge 1 6372
Protoss_Gateway 3 13770
Protoss_Photon_Cannon 6 14489
Protoss_Assimilator 2 11925
Protoss_Cybernetics_Core 1 9946
Protoss_Zealot 6 15002
Protoss_Stargate 1 12087
Protoss_Citadel_of_Adun 1 12232
Protoss_Corsair 2 14631
Protoss_Templar_Archives 1 14974
15002
