Protoss_Forge 1 4735
Protoss_Nexus 1 7809
Protoss_Photon_Cannon 5 14302
Protoss_Gateway 1 7811
Protoss_Assimilator 3 13559
Protoss_Zealot 3 13354
Protoss_Cybernetics_Core 1 10018
Protoss_Stargate 1 11962
Protoss_Dragoon 1 12063
Protoss_Corsair 3 14762
Protoss_Citadel_of_Adun 1 13574
14762
