Protoss_Forge 1 4681
Protoss_Nexus 1 7511
Protoss_Photon_Cannon 6 15066
Protoss_Gateway 1 7975
Protoss_Assimilator 2 10902
Protoss_Cybernetics_Core 1 10622
Protoss_Zealot 2 13050
Protoss_Stargate 1 12331
Protoss_Dragoon 1 12022
Protoss_Robotics_Facility 1 13839
Protoss_Corsair 2 14230
Protoss_Robotics_Support_Bay 1 15139
15139
