Protoss_Forge 1 3719
Protoss_Nexus 1 7454
Protoss_Gateway 4 13381
Protoss_Assimilator 2 9201
Protoss_Photon_Cannon 5 15708
Protoss_Cybernetics_Core 1 8784
Protoss_Citadel_of_Adun 1 10398
Protoss_Dragoon 1 10588
Protoss_Templar_Archives 1 11849
Protoss_Zealot 3 15547
Protoss_Dark_Templar 2 13052
Protoss_High_Templar 6 15271
Protoss_Archon 1 14727
15708
