Protoss_Gateway 1 4286
Protoss_Zealot 8 14970
Protoss_Nexus 1 8796
Protoss_Assimilator 2 14571
Protoss_Cybernetics_Core 1 8592
Protoss_Forge 1 8695
Protoss_Photon_Cannon 2 11649
Protoss_Stargate 1 10788
Protoss_Corsair 2 13126
Protoss_Citadel_of_Adun 1 15665
15665
