Protoss_Gateway 2 4918
Protoss_Zealot 11 13744
Protoss_Assimilator 1 7703
Protoss_Cybernetics_Core 1 9428
Protoss_Stargate 1 11176
Protoss_Citadel_of_Adun 1 11628
Protoss_Forge 1 11720
Protoss_Corsair 1 12134
Protoss_Templar_Archives 1 15523
Protoss_Nexus 1 17065
17065
