Protoss_Forge 2 6857
Protoss_Nexus 1 7304
Protoss_Gateway 3 14592
Protoss_Assimilator 2 10830
Protoss_Photon_Cannon 3 14725
Protoss_Zealot 5 14051
Protoss_Cybernetics_Core 1 9626
Protoss_Stargate 1 11601
Protoss_Citadel_of_Adun 1 12841
Protoss_Corsair 3 15500
Protoss_Templar_Archives 1 14306
Protoss_High_Templar 1 15701
15701
