Protoss_Forge 1 4155
Protoss_Nexus 1 8017
Protoss_Photon_Cannon 4 15663
Protoss_Gateway 2 13681
Protoss_Assimilator 2 10641
Protoss_Zealot 6 13401
Protoss_Cybernetics_Core 1 9295
Protoss_Stargate 1 11188
Protoss_Citadel_of_Adun 1 11793
Protoss_Corsair 1 12512
Protoss_Templar_Archives 1 13493
Protoss_Dark_Templar 2 14905
15663
