Protoss_Forge 1 4997
Protoss_Nexus 1 7369
Protoss_Photon_Cannon 3 14306
Protoss_Gateway 3 12438
Protoss_Assimilator 2 9844
Protoss_Zealot 7 14347
Protoss_Cybernetics_Core 1 9378
Protoss_Stargate 1 11356
Protoss_Citadel_of_Adun 1 12602
Protoss_Corsair 3 14824
Protoss_Templar_Archives 1 15061
15061
