Protoss_Forge 1 4416
Protoss_Photon_Cannon 3 15550
Protoss_Nexus 1 8680
Protoss_Gateway 1 7675
Protoss_Assimilator 2 11153
Protoss_Cybernetics_Core 1 9192
Protoss_Zealot 4 13995
Protoss_Stargate 1 10882
Protoss_Citadel_of_Adun 1 11396
Protoss_Corsair 3 14405
Protoss_Templar_Archives 1 13575
15550
