Protoss_Forge 1 4761
Protoss_Photon_Cannon 6 13773
Protoss_Nexus 1 10711
Protoss_Gateway 2 15664
Protoss_Assimilator 2 11954
Protoss_Cybernetics_Core 1 11010
Protoss_Zealot 3 13404
Protoss_Stargate 1 12966
Protoss_Robotics_Facility 1 14138
Protoss_Corsair 2 14882
Protoss_Robotics_Support_Bay 1 15089
15664
