Protoss_Forge 1 4905
Protoss_Nexus 1 7661
Protoss_Photon_Cannon 2 9528
Protoss_Gateway 2 14235
Protoss_Assimilator 2 10082
Protoss_Cybernetics_Core 1 9375
Protoss_Stargate 1 11232
Protoss_Zealot 2 14379
Protoss_Citadel_of_Adun 1 12582
Protoss_Corsair 3 14271
Protoss_Templar_Archives 1 14121
Protoss_Dark_Templar 1 15449
Protoss_High_Templar 1 15499
15499
