Protoss_Nexus 1 7104
Protoss_Gateway 6 15918
Protoss_Forge 1 6386
Protoss_Assimilator 2 10733
Protoss_Photon_Cannon 2 11700
Protoss_Cybernetics_Core 1 8344
Protoss_Zealot 5 14651
Protoss_Stargate 1 10788
Protoss_Citadel_of_Adun 1 12100
Protoss_Corsair 2 12872
Protoss_Templar_Archives 1 13688
Protoss_Dark_Templar 1 15783
15918
