Protoss_Forge 1 3753
Protoss_Nexus 1 7339
Protoss_Photon_Cannon 4 15332
Protoss_Gateway 4 14049
Protoss_Assimilator 2 11212
Protoss_Zealot 5 14051
Protoss_Cybernetics_Core 1 9216
Protoss_Stargate 1 10993
Protoss_Citadel_of_Adun 1 10932
Protoss_Corsair 1 11929
Protoss_Templar_Archives 1 13668
Protoss_High_Templar 2 15033
Leg_Enhancements 1 13921
Protoss_Dark_Templar 1 15171
15332
