Protoss_Forge 1 4668
Protoss_Nexus 1 7759
Protoss_Photon_Cannon 4 14935
Protoss_Gateway 3 15406
Protoss_Assimilator 2 11282
Protoss_Zealot 3 12500
Protoss_Cybernetics_Core 1 9429
Protoss_Dragoon 1 11638
Protoss_Citadel_of_Adun 1 12576
Protoss_Templar_Archives 1 14409
Protoss_Dark_Templar 1 15789
Protoss_High_Templar 1 15803
15803
