Protoss_Gateway 3 12377
Protoss_Zealot 8 10395
Protoss_Assimilator 1 6636
Protoss_Cybernetics_Core 1 8044
Protoss_Dragoon 10 14957
Protoss_Stargate 1 10247
Singularity_Charge 1 13825
14957
