Protoss_Forge 1 4594
Protoss_Photon_Cannon 6 14338
Protoss_Nexus 1 9141
Protoss_Gateway 3 15544
Protoss_Assimilator 2 11578
Protoss_Cybernetics_Core 1 10334
Protoss_Zealot 1 10448
Protoss_Stargate 1 12054
Protoss_Citadel_of_Adun 1 13177
Protoss_Corsair 3 15081
Protoss_Templar_Archives 1 14892
15544
