Protoss_Forge 1 5036
Protoss_Nexus 1 7366
Protoss_Photon_Cannon 5 14328
Protoss_Gateway 1 7665
Protoss_Assimilator 3 12178
Protoss_Cybernetics_Core 1 9179
Protoss_Zealot 5 14891
Protoss_Stargate 1 10979
Protoss_Corsair 4 14710
Protoss_Robotics_Facility 1 13371
Protoss_Robotics_Support_Bay 1 14311
Protoss_Reaver 1 16159
16159
