Protoss_Gateway 2 5250
Protoss_Zealot 13 14751
Protoss_Forge 1 8576
Protoss_Photon_Cannon 3 15554
Protoss_Nexus 1 12947
Protoss_Assimilator 1 11841
Protoss_Cybernetics_Core 1 12754
Protoss_Citadel_of_Adun 1 14361
Protoss_Templar_Archives 1 16040
16040
