Protoss_Forge 1 3959
Protoss_Photon_Cannon 7 15189
Protoss_Nexus 1 8484
Protoss_Gateway 1 7745
Protoss_Assimilator 2 11219
Protoss_Cybernetics_Core 1 11632
Protoss_Zealot 4 14985
Protoss_Stargate 2 14558
Protoss_Citadel_of_Adun 2 14581
Protoss_Corsair 1 15509
Protoss_Templar_Archives 1 16035
16035
