Protoss_Nexus 1 7108
Protoss_Forge 1 6324
Protoss_Gateway 3 15375
Protoss_Photon_Cannon 3 9685
Protoss_Assimilator 2 10940
Protoss_Zealot 3 13255
Protoss_Cybernetics_Core 1 10594
Protoss_Stargate 1 12287
Protoss_Dragoon 1 12098
Protoss_Citadel_of_Adun 1 13000
Protoss_Corsair 3 15257
Protoss_Templar_Archives 1 14474
Protoss_Dark_Templar 1 15736
15736
