Protoss_Gateway 2 14549
Protoss_Zealot 8 14584
Protoss_Nexus 1 8759
Protoss_Forge 1 7615
Protoss_Cybernetics_Core 1 9286
Protoss_Assimilator 2 10627
Protoss_Photon_Cannon 2 12052
Protoss_Dragoon 1 10705
Protoss_Stargate 1 12154
Protoss_Citadel_of_Adun 1 13376
Protoss_Corsair 3 15497
Protoss_Templar_Archives 1 15162
15497
