Protoss_Forge 1 4783
Protoss_Photon_Cannon 5 10475
Protoss_Nexus 1 10888
Protoss_Gateway 4 14947
Protoss_Assimilator 2 12308
Protoss_Cybernetics_Core 1 11306
Protoss_Zealot 4 15137
Protoss_Citadel_of_Adun 1 13013
Protoss_Templar_Archives 1 14462
Protoss_Dark_Templar 2 15695
15695
