Protoss_Nexus 1 6977
Protoss_Gateway 6 15915
Protoss_Forge 1 6583
Protoss_Photon_Cannon 4 13910
Protoss_Assimilator 2 10078
Protoss_Zealot 5 13592
Protoss_Cybernetics_Core 1 8808
Protoss_Stargate 1 10903
Protoss_Dragoon 1 10836
Protoss_Citadel_of_Adun 1 11660
Protoss_Corsair 1 11868
Protoss_Templar_Archives 1 13250
Protoss_Dark_Templar 1 14711
Protoss_High_Templar 2 14773
15915
