Protoss_Forge 1 4230
Protoss_Photon_Cannon 6 15572
Protoss_Nexus 1 7828
Protoss_Gateway 3 14873
Protoss_Assimilator 2 9891
Protoss_Cybernetics_Core 1 9308
Protoss_Zealot 4 13785
Protoss_Stargate 1 11375
Protoss_Citadel_of_Adun 1 11831
Protoss_Corsair 1 12312
Protoss_Templar_Archives 1 13448
Protoss_High_Templar 1 14905
15572
