Protoss_Gateway 2 4685
Protoss_Zealot 14 12160
Protoss_Assimilator 1 8355
Protoss_Cybernetics_Core 1 10486
Protoss_Dragoon 2 12522
Protoss_Stargate 1 13190
Protoss_Citadel_of_Adun 1 13253
Protoss_Forge 1 13691
Protoss_Corsair 2 15157
Protoss_Templar_Archives 1 14774
Protoss_Photon_Cannon 1 15294
15294
