Protoss_Forge 1 4429
Protoss_Photon_Cannon 2 6102
Protoss_Nexus 1 8958
Protoss_Gateway 4 13931
Protoss_Assimilator 2 9876
Protoss_Cybernetics_Core 1 9403
Protoss_Stargate 1 11129
Protoss_Citadel_of_Adun 1 11565
Protoss_Corsair 1 12090
Protoss_Templar_Archives 1 13057
Protoss_Dark_Templar 2 14489
Protoss_High_Templar 4 15631
Protoss_Zealot 1 15567
15631
