Protoss_Forge 1 4562
Protoss_Nexus 1 7448
Protoss_Photon_Cannon 2 11545
Protoss_Gateway 3 13185
Protoss_Assimilator 2 12146
Protoss_Cybernetics_Core 1 9305
Protoss_Zealot 8 14748
Protoss_Dragoon 1 10693
Protoss_Stargate 1 11208
Protoss_Citadel_of_Adun 1 12381
Protoss_Corsair 1 12672
14748
