Protoss_Forge 1 4747
Protoss_Nexus 1 7637
Protoss_Photon_Cannon 3 14243
Protoss_Gateway 4 15968
Protoss_Assimilator 2 9709
Protoss_Cybernetics_Core 1 8897
Protoss_Zealot 7 15087
Protoss_Stargate 1 10791
Protoss_Citadel_of_Adun 1 11364
Protoss_Corsair 4 14663
Protoss_Templar_Archives 1 14897
Leg_Enhancements 1 14399
15968
