Protoss_Forge 1 3804
Protoss_Photon_Cannon 4 12872
Protoss_Nexus 1 9780
Protoss_Gateway 4 15896
Protoss_Assimilator 2 10624
Protoss_Zealot 2 10808
Protoss_Cybernetics_Core 1 10332
Protoss_Stargate 1 12070
Protoss_Citadel_of_Adun 1 12245
Protoss_Dragoon 1 12203
Protoss_Corsair 2 14875
Protoss_Templar_Archives 1 13767
Protoss_Dark_Templar 2 15151
15896
