Protoss_Forge 1 4325
Protoss_Photon_Cannon 2 5884
Protoss_Nexus 1 8823
Protoss_Gateway 3 14443
Protoss_Assimilator 2 12007
Protoss_Cybernetics_Core 1 9273
Protoss_Zealot 9 15541
Protoss_Stargate 1 11146
Protoss_Corsair 3 13957
Protoss_Citadel_of_Adun 1 12770
Protoss_Templar_Archives 1 14774
Protoss_Ground_Weapons_1 1 14299
15541
