Protoss_Gateway 2 5325
Protoss_Zealot 9 12390
Protoss_Assimilator 1 8177
Protoss_Cybernetics_Core 1 9127
Protoss_Dragoon 5 14773
Protoss_Robotics_Facility 1 12608
Protoss_Shuttle 1 14023
Protoss_Robotics_Support_Bay 1 13809
Protoss_Reaver 1 15937
15937
