Protoss_Nexus 1 7057
Protoss_Gateway 3 12450
Protoss_Forge 1 6662
Protoss_Photon_Cannon 7 15151
Protoss_Zealot 6 14303
Protoss_Assimilator 3 12709
Protoss_Cybernetics_Core 1 9602
Protoss_Stargate 1 11901
Protoss_Citadel_of_Adun 1 12826
Protoss_Corsair 3 15037
15151
