Protoss_Forge 1 4347
Protoss_Nexus 1 7661
Protoss_Photon_Cannon 3 14479
Protoss_Gateway 4 15978
Protoss_Assimilator 2 9838
Protoss_Cybernetics_Core 1 9646
Protoss_Zealot 4 14054
Protoss_Dragoon 1 11050
Protoss_Stargate 1 11612
Protoss_Citadel_of_Adun 1 12684
Protoss_Corsair 1 12591
Protoss_Templar_Archives 1 14251
Protoss_Dark_Templar 2 15554
15978
