Protoss_Forge 1 4832
Protoss_Nexus 1 7445
Protoss_Photon_Cannon 2 6645
Protoss_Gateway 3 14629
Protoss_Assimilator 2 10870
Protoss_Cybernetics_Core 1 9280
Protoss_Zealot 8 15207
Protoss_Stargate 1 10970
Protoss_Citadel_of_Adun 1 12062
Protoss_Corsair 2 12792
Protoss_Robotics_Facility 1 14774
Protoss_Templar_Archives 1 15804
15804
