Protoss_Gateway 3 15312
Protoss_Zealot 12 15336
Protoss_Assimilator 1 10799
Protoss_Cybernetics_Core 1 11671
Protoss_Nexus 1 14624
Protoss_Citadel_of_Adun 1 13360
Protoss_Dragoon 2 14196
Protoss_Forge 1 14306
15336
