Protoss_Gateway 3 15173
Protoss_Zealot 10 13065
Protoss_Assimilator 1 6848
Protoss_Cybernetics_Core 1 8380
Protoss_Stargate 1 10188
Protoss_Dragoon 1 10149
Protoss_Citadel_of_Adun 1 11186
Protoss_Corsair 1 11215
Protoss_Templar_Archives 1 13300
Protoss_High_Templar 2 14635
Protoss_Nexus 1 17425
17425
