Protoss_Forge 1 5238
Protoss_Nexus 1 7522
Protoss_Gateway 3 13654
Protoss_Photon_Cannon 2 14081
Protoss_Assimilator 2 10489
Protoss_Cybernetics_Core 1 8780
Protoss_Zealot 3 10785
Protoss_Stargate 1 10698
Protoss_Citadel_of_Adun 1 11505
Protoss_Corsair 3 14370
Protoss_Templar_Archives 1 13275
Protoss_Dark_Templar 3 15780
Protoss_High_Templar 1 15253
15780
