Protoss_Forge 1 4335
Protoss_Nexus 1 7740
Protoss_Gateway 4 14104
Protoss_Photon_Cannon 1 7782
Protoss_Assimilator 2 9775
Protoss_Cybernetics_Core 1 9311
Protoss_Zealot 1 9181
Protoss_Stargate 1 11045
Protoss_Dragoon 8 15663
Protoss_Robotics_Facility 1 12560
Protoss_Corsair 1 12017
Protoss_Shuttle 1 13966
Protoss_Robotics_Support_Bay 1 13775
Protoss_Reaver 1 15550
15663
