Protoss_Forge 2 12029
Protoss_Photon_Cannon 3 8293
Protoss_Gateway 4 15339
Protoss_Zealot 8 15438
Protoss_Assimilator 1 8592
Protoss_Cybernetics_Core 1 10204
Protoss_Stargate 1 12057
Protoss_Dragoon 1 11867
Protoss_Citadel_of_Adun 1 12945
Protoss_Corsair 1 13237
15438
