Protoss_Gateway 5 14369
Protoss_Zealot 6 13062
Protoss_Nexus 1 8952
Protoss_Assimilator 1 7852
Protoss_Cybernetics_Core 1 10836
Protoss_Dragoon 3 15145
Protoss_Forge 1 12746
Protoss_Photon_Cannon 4 15762
15762
