Protoss_Nexus 1 7184
Protoss_Forge 1 6152
Protoss_Gateway 2 12735
Protoss_Photon_Cannon 7 14905
Protoss_Assimilator 2 9438
Protoss_Zealot 2 10012
Protoss_Cybernetics_Core 1 10252
Protoss_Stargate 1 12025
Protoss_Citadel_of_Adun 1 11887
Protoss_Corsair 3 15210
Protoss_Templar_Archives 1 13790
Protoss_Dark_Templar 2 15054
Protoss_High_Templar 1 15104
15210
