Protoss_Forge 1 4227
Protoss_Photon_Cannon 4 14625
Protoss_Nexus 1 9622
Protoss_Gateway 1 8651
Protoss_Assimilator 2 10793
Protoss_Cybernetics_Core 1 10518
Protoss_Zealot 1 10112
Protoss_Stargate 1 12201
Protoss_Dragoon 1 11937
Protoss_Corsair 3 14991
Protoss_Robotics_Facility 1 14708
14991
