Protoss_Forge 1 4760
Protoss_Nexus 1 7606
Protoss_Photon_Cannon 3 12151
Protoss_Gateway 3 15369
Protoss_Assimilator 2 12918
Protoss_Zealot 4 15567
Protoss_Cybernetics_Core 1 9045
Protoss_Stargate 1 11251
Protoss_Dragoon 1 11615
Protoss_Citadel_of_Adun 1 12216
Protoss_Corsair 4 15400
Protoss_Templar_Archives 1 15488
15567
