Protoss_Nexus 1 6936
Protoss_Forge 1 5276
Protoss_Photon_Cannon 3 12373
Protoss_Gateway 1 7609
Protoss_Zealot 5 15544
Protoss_Cybernetics_Core 1 9763
Protoss_Assimilator 2 13476
Protoss_Stargate 1 15420
Protoss_Citadel_of_Adun 1 15744
15744
