Protoss_Forge 1 3953
Protoss_Photon_Cannon 3 8469
Protoss_Gateway 2 13006
Protoss_Zealot 7 15424
Protoss_Nexus 1 12368
Protoss_Assimilator 2 14102
Protoss_Cybernetics_Core 1 12428
Protoss_Stargate 1 14435
Protoss_Dragoon 2 14562
Protoss_Citadel_of_Adun 1 15585
15585
