Protoss_Forge 1 5050
Protoss_Nexus 1 7658
Protoss_Photon_Cannon 2 6830
Protoss_Gateway 3 13583
Protoss_Assimilator 2 9946
Protoss_Cybernetics_Core 1 9192
Protoss_Zealot 10 15579
Protoss_Dragoon 1 10602
Protoss_Stargate 1 11271
Protoss_Citadel_of_Adun 1 11812
Protoss_Corsair 3 13975
Protoss_Templar_Archives 1 14800
15579
