Protoss_Forge 1 4498
Protoss_Nexus 1 7656
Protoss_Photon_Cannon 4 13336
Protoss_Gateway 4 16021
Protoss_Assimilator 2 10381
Protoss_Cybernetics_Core 1 9969
Protoss_Zealot 1 10003
Protoss_Citadel_of_Adun 1 11856
Protoss_Stargate 1 12303
Protoss_Corsair 3 15014
Protoss_Templar_Archives 1 14126
Protoss_Dark_Templar 2 15396
16021
