Protoss_Forge 1 4112
Protoss_Photon_Cannon 2 5884
Protoss_Nexus 1 8793
Protoss_Gateway 2 15090
Protoss_Assimilator 2 10290
Protoss_Zealot 2 10510
Protoss_Cybernetics_Core 1 9999
Protoss_Stargate 1 12312
Protoss_Dragoon 1 12279
Protoss_Citadel_of_Adun 1 12785
Protoss_Corsair 2 15032
Protoss_Robotics_Facility 1 14546
Protoss_Templar_Archives 1 14985
15090
