Protoss_Forge 1 4647
Protoss_Photon_Cannon 7 15818
Protoss_Nexus 1 8686
Protoss_Gateway 3 12715
Protoss_Assimilator 2 12661
Protoss_Cybernetics_Core 1 9179
Protoss_Zealot 5 14177
Protoss_Citadel_of_Adun 1 11082
Protoss_Dragoon 1 10948
Protoss_Templar_Archives 1 14153
Leg_Enhancements 1 14188
Protoss_Dark_Templar 1 15648
Protoss_High_Templar 2 15671
15818
