Protoss_Forge 1 4311
Protoss_Photon_Cannon 2 5925
Protoss_Nexus 1 8914
Protoss_Gateway 3 12318
Protoss_Assimilator 2 12639
Protoss_Cybernetics_Core 1 9522
Protoss_Zealot 11 15348
Protoss_Citadel_of_Adun 1 11629
Protoss_Templar_Archives 1 14289
15348
