Protoss_Forge 1 4268
Protoss_Photon_Cannon 5 15386
Protoss_Nexus 1 8964
Protoss_Gateway 4 14980
Protoss_Assimilator 2 11317
Protoss_Cybernetics_Core 1 9466
Protoss_Zealot 3 15307
Protoss_Dragoon 1 10895
Protoss_Citadel_of_Adun 1 11546
Protoss_Templar_Archives 1 13220
Protoss_High_Templar 3 15519
15519
