Protoss_Forge 1 4710
Protoss_Nexus 1 7661
Protoss_Photon_Cannon 3 14289
Protoss_Gateway 4 15734
Protoss_Assimilator 2 9239
Protoss_Cybernetics_Core 1 9175
Protoss_Zealot 7 13834
Protoss_Stargate 1 10859
Protoss_Citadel_of_Adun 1 11509
Protoss_Corsair 1 11797
Protoss_Templar_Archives 1 13155
Protoss_Dark_Templar 2 14954
Leg_Enhancements 1 14440
15734
