Protoss_Forge 1 4248
Protoss_Photon_Cannon 4 10394
Protoss_Nexus 1 9257
Protoss_Gateway 4 15283
Protoss_Assimilator 2 11897
Protoss_Zealot 3 12418
Protoss_Cybernetics_Core 1 11469
Protoss_Stargate 1 13944
Protoss_Citadel_of_Adun 1 14383
Protoss_Corsair 1 14991
15283
