Protoss_Forge 1 3857
Protoss_Photon_Cannon 5 13806
Protoss_Nexus 1 10023
Protoss_Gateway 1 8985
Protoss_Assimilator 3 11960
Protoss_Zealot 4 13492
Protoss_Cybernetics_Core 1 11175
Protoss_Stargate 1 13711
Protoss_Citadel_of_Adun 1 14254
14254
