Protoss_Gateway 2 4779
Protoss_Zealot 17 15397
Protoss_Nexus 1 12915
Protoss_Assimilator 2 14752
Protoss_Forge 1 12949
Protoss_Cybernetics_Core 1 14180
Protoss_Photon_Cannon 1 14205
Protoss_Stargate 1 15940
15940
