Protoss_Nexus 1 6912
Protoss_Forge 1 5789
Protoss_Gateway 3 14806
Protoss_Photon_Cannon 4 14817
Protoss_Assimilator 2 9924
Protoss_Zealot 8 15585
Protoss_Cybernetics_Core 1 9697
Protoss_Stargate 1 11620
Protoss_Citadel_of_Adun 1 12664
Protoss_Corsair 3 14619
Protoss_Templar_Archives 1 14285
15585
