Protoss_Forge 1 4169
Protoss_Nexus 1 7661
Protoss_Photon_Cannon 5 14815
Protoss_Gateway 1 7233
Protoss_Assimilator 2 11083
Protoss_Cybernetics_Core 1 9001
Protoss_Zealot 6 14616
Protoss_Stargate 1 11181
Protoss_Citadel_of_Adun 1 12324
Protoss_Corsair 1 13085
14815
