Protoss_Forge 1 4867
Protoss_Nexus 1 7866
Protoss_Photon_Cannon 2 7866
Protoss_Gateway 6 15658
Protoss_Assimilator 2 10031
Protoss_Cybernetics_Core 1 9716
Protoss_Stargate 1 11437
Protoss_Citadel_of_Adun 1 11683
Protoss_Corsair 2 13270
Protoss_Templar_Archives 1 13305
Protoss_High_Templar 3 15642
Protoss_Dark_Templar 1 15648
15658
