Protoss_Forge 1 3992
Protoss_Nexus 1 7767
Protoss_Gateway 4 14344
Protoss_Photon_Cannon 3 15186
Protoss_Assimilator 2 10100
Protoss_Cybernetics_Core 1 8753
Protoss_Zealot 4 12886
Protoss_Stargate 1 10642
Protoss_Citadel_of_Adun 1 11522
Protoss_Corsair 2 13899
Protoss_Templar_Archives 1 13185
Protoss_Dark_Templar 1 14501
Protoss_High_Templar 1 14937
15186
