Protoss_Gateway 2 12305
Protoss_Assimilator 1 4363
Protoss_Cybernetics_Core 1 5663
Protoss_Zealot 3 8832
Protoss_Stargate 1 7367
Protoss_Citadel_of_Adun 1 8385
Protoss_Corsair 2 10436
Protoss_Templar_Archives 1 10193
Protoss_Forge 1 11146
Protoss_Dark_Templar 1 11510
Protoss_Photon_Cannon 2 15664
Protoss_High_Templar 3 15478
15664
