Protoss_Gateway 2 14393
Protoss_Zealot 6 11230
Protoss_Assimilator 2 14693
Protoss_Cybernetics_Core 1 6814
Protoss_Stargate 1 8514
Protoss_Dragoon 1 8272
Protoss_Corsair 3 11844
Protoss_Citadel_of_Adun 1 10550
Protoss_Templar_Archives 1 12090
Protoss_Dark_Templar 2 14618
Protoss_Nexus 1 15341
Protoss_High_Templar 1 15718
15718
