Protoss_Nexus 1 7290
Protoss_Gateway 4 10730
Protoss_Forge 1 6740
Protoss_Photon_Cannon 2 8299
Protoss_Zealot 15 14373
Protoss_Assimilator 2 14532
Protoss_Cybernetics_Core 1 13407
Protoss_Stargate 1 15305
15305
