Protoss_Forge 1 4845
Protoss_Nexus 1 7509
Protoss_Photon_Cannon 4 14480
Protoss_Gateway 3 14469
Protoss_Assimilator 2 11338
Protoss_Cybernetics_Core 1 9535
Protoss_Zealot 4 15482
Protoss_Stargate 1 11216
Protoss_Dragoon 1 11202
Protoss_Citadel_of_Adun 1 12437
Protoss_Corsair 3 14712
Protoss_Templar_Archives 1 14069
Protoss_Dark_Templar 1 15303
15482
