Protoss_Forge 1 4214
Protoss_Nexus 1 8017
Protoss_Photon_Cannon 4 15650
Protoss_Gateway 3 14840
Protoss_Assimilator 2 10281
Protoss_Cybernetics_Core 1 9277
Protoss_Zealot 5 15116
Protoss_Stargate 1 11134
Protoss_Citadel_of_Adun 1 12309
Protoss_Dragoon 1 12329
Protoss_Corsair 1 12912
Protoss_Templar_Archives 1 15403
15650
