Protoss_Forge 1 4167
Protoss_Nexus 1 7615
Protoss_Gateway 3 14133
Protoss_Photon_Cannon 6 15622
Protoss_Assimilator 2 9081
Protoss_Cybernetics_Core 1 8887
Protoss_Zealot 3 13354
Protoss_Stargate 1 10786
Protoss_Dragoon 1 10348
Protoss_Citadel_of_Adun 1 10916
Protoss_Corsair 2 12605
Protoss_Templar_Archives 1 13404
Protoss_Dark_Templar 1 14998
Protoss_High_Templar 2 15674
15674
