Protoss_Gateway 2 5184
Protoss_Zealot 12 14232
Protoss_Assimilator 1 7943
Protoss_Cybernetics_Core 1 10111
Protoss_Stargate 1 12199
Protoss_Forge 1 12387
Protoss_Corsair 1 13211
Protoss_Photon_Cannon 3 15284
Protoss_Citadel_of_Adun 2 16054
Protoss_Dragoon 2 15461
16054
