Protoss_Forge 1 3959
Protoss_Photon_Cannon 4 8264
Protoss_Nexus 1 9580
Protoss_Gateway 3 14546
Protoss_Assimilator 2 11926
Protoss_Cybernetics_Core 1 10812
Protoss_Zealot 5 14595
Protoss_Stargate 1 13193
Protoss_Citadel_of_Adun 1 13662
Protoss_Corsair 2 15137
Protoss_Templar_Archives 1 15233
15233
