Protoss_Forge 1 4897
Protoss_Photon_Cannon 5 14755
Protoss_Nexus 1 8961
Protoss_Gateway 1 7903
Protoss_Assimilator 2 11481
Protoss_Cybernetics_Core 1 9403
Protoss_Zealot 3 13887
Protoss_Stargate 2 13477
Protoss_Dragoon 1 11015
Protoss_Citadel_of_Adun 1 12623
Protoss_Corsair 4 15403
Protoss_Robotics_Facility 1 16110
16110
