Protoss_Gateway 1 4106
Protoss_Assimilator 1 4215
Protoss_Zealot 3 7589
Protoss_Cybernetics_Core 1 7126
Protoss_Stargate 1 8847
Protoss_Dragoon 2 10552
Protoss_Citadel_of_Adun 1 9558
Protoss_Corsair 3 12020
Protoss_Templar_Archives 1 11118
Protoss_Forge 1 11622
Protoss_Dark_Templar 1 12660
Protoss_Nexus 1 15292
Protoss_High_Templar 1 14009
Protoss_Photon_Cannon 1 15780
15780
