Protoss_Forge 1 4429
Protoss_Photon_Cannon 4 14687
Protoss_Nexus 1 8861
Protoss_Gateway 2 12324
Protoss_Assimilator 2 12479
Protoss_Cybernetics_Core 1 9266
Protoss_Zealot 6 14794
Protoss_Stargate 1 11222
Protoss_Dragoon 1 11111
Protoss_Corsair 3 14715
Protoss_Citadel_of_Adun 1 13524
Protoss_Templar_Archives 1 15547
15547
