Protoss_Forge 1 4239
Protoss_Nexus 1 7692
Protoss_Gateway 5 14367
Protoss_Assimilator 2 12506
Protoss_Photon_Cannon 3 11632
Protoss_Cybernetics_Core 1 8446
Protoss_Stargate 1 10212
Protoss_Zealot 6 15432
Protoss_Corsair 2 12790
Protoss_Citadel_of_Adun 1 12219
15432
