Protoss_Forge 1 3929
Protoss_Nexus 1 7521
Protoss_Gateway 3 13242
Protoss_Assimilator 2 10416
Protoss_Photon_Cannon 8 15519
Protoss_Zealot 2 8900
Protoss_Cybernetics_Core 1 8850
Protoss_Dragoon 1 10055
Protoss_Stargate 1 10686
Protoss_Citadel_of_Adun 1 11320
Protoss_Corsair 2 13050
Protoss_Templar_Archives 1 12855
Protoss_Dark_Templar 1 14073
Protoss_High_Templar 2 15139
15519
