Protoss_Forge 1 4091
Protoss_Nexus 1 7800
Protoss_Photon_Cannon 2 6952
Protoss_Gateway 4 14244
Protoss_Assimilator 2 10824
Protoss_Cybernetics_Core 1 10100
Protoss_Zealot 6 15242
Protoss_Stargate 1 12103
Protoss_Dragoon 1 11843
Protoss_Citadel_of_Adun 1 13158
Protoss_Corsair 2 14297
15242
