Protoss_Gateway 2 14628
Protoss_Assimilator 1 4548
Protoss_Zealot 3 7191
Protoss_Cybernetics_Core 1 7196
Protoss_Dragoon 5 15200
Protoss_Robotics_Facility 1 9702
Protoss_Robotics_Support_Bay 1 10541
Protoss_Reaver 2 15351
Protoss_Nexus 1 13661
Protoss_Shuttle 1 13609
15351
