Protoss_Forge 1 4272
Protoss_Nexus 1 7802
Protoss_Photon_Cannon 4 14793
Protoss_Gateway 4 14232
Protoss_Assimilator 1 7703
Protoss_Cybernetics_Core 1 9214
Protoss_Zealot 11 15582
Protoss_Stargate 1 11014
Protoss_Citadel_of_Adun 1 11730
Protoss_Corsair 2 13147
15582
