Protoss_Forge 1 4517
Protoss_Photon_Cannon 6 11681
Protoss_Nexus 1 9265
Protoss_Gateway 3 15422
Protoss_Assimilator 2 13714
Protoss_Cybernetics_Core 1 10046
Protoss_Zealot 3 11680
Protoss_Stargate 1 13254
Protoss_Citadel_of_Adun 1 13729
Protoss_Corsair 1 14279
Protoss_Templar_Archives 1 15631
15631
