Protoss_Forge 1 4479
Protoss_Photon_Cannon 6 14771
Protoss_Nexus 1 9281
Protoss_Gateway 2 12915
Protoss_Assimilator 2 15558
Protoss_Zealot 9 15389
Protoss_Cybernetics_Core 1 10594
Protoss_Stargate 1 12429
Protoss_Citadel_of_Adun 1 12349
Protoss_Corsair 1 13512
15558
