Protoss_Forge 1 4242
Protoss_Photon_Cannon 4 15493
Protoss_Nexus 1 8741
Protoss_Gateway 3 15579
Protoss_Assimilator 2 13037
Protoss_Cybernetics_Core 1 9292
Protoss_Zealot 8 14487
Protoss_Stargate 1 11018
Protoss_Citadel_of_Adun 1 11461
Protoss_Corsair 5 14999
Protoss_Templar_Archives 1 15934
Leg_Enhancements 1 14603
15934
