Protoss_Gateway 1 4351
Protoss_Zealot 8 14335
Protoss_Nexus 1 8873
Protoss_Forge 1 7467
Protoss_Photon_Cannon 3 11032
Protoss_Assimilator 2 13716
Protoss_Cybernetics_Core 1 13621
Protoss_Stargate 1 15695
Protoss_Robotics_Facility 1 16397
16397
