Protoss_Forge 1 4590
Protoss_Photon_Cannon 5 13061
Protoss_Nexus 1 8993
Protoss_Gateway 4 15029
Protoss_Assimilator 2 10214
Protoss_Zealot 5 13638
Protoss_Cybernetics_Core 1 9880
Protoss_Stargate 1 11561
Protoss_Citadel_of_Adun 1 12097
Protoss_Corsair 2 13477
Protoss_Templar_Archives 1 13881
Protoss_Dark_Templar 2 15159
15159
