Protoss_Forge 1 3763
Protoss_Photon_Cannon 12 15686
Protoss_Nexus 1 9271
Protoss_Gateway 1 8742
Protoss_Assimilator 1 8802
Protoss_Cybernetics_Core 1 12801
Protoss_Zealot 1 13322
Protoss_Stargate 1 14681
15686
