Protoss_Forge 1 4665
Protoss_Photon_Cannon 1 5937
Protoss_Nexus 1 8144
Protoss_Gateway 2 14484
Protoss_Assimilator 2 9749
Protoss_Zealot 4 12450
Protoss_Cybernetics_Core 1 9778
Protoss_Stargate 1 11907
Protoss_Citadel_of_Adun 1 12099
Protoss_Corsair 2 14391
Protoss_Templar_Archives 1 13714
Protoss_Robotics_Facility 1 14700
Protoss_Dark_Templar 2 15791
15791
