Protoss_Forge 1 4747
Protoss_Nexus 1 7755
Protoss_Gateway 5 14929
Protoss_Assimilator 2 11462
Protoss_Photon_Cannon 2 14981
Protoss_Cybernetics_Core 1 8622
Protoss_Zealot 3 13902
Protoss_Dragoon 1 9920
Protoss_Stargate 1 10800
Protoss_Citadel_of_Adun 1 10975
Protoss_Corsair 2 12915
Protoss_Templar_Archives 1 12749
Protoss_High_Templar 1 14975
Protoss_Dark_Templar 1 15022
15022
