Protoss_Forge 1 4733
Protoss_Photon_Cannon 5 14572
Protoss_Nexus 1 8396
Protoss_Gateway 3 15768
Protoss_Assimilator 2 11025
Protoss_Cybernetics_Core 1 9633
Protoss_Zealot 3 11859
Protoss_Stargate 1 11517
Protoss_Citadel_of_Adun 1 12055
Protoss_Corsair 1 12479
Protoss_Templar_Archives 1 13629
Protoss_High_Templar 2 14922
15768
