Protoss_Forge 1 4722
Protoss_Nexus 1 7846
Protoss_Photon_Cannon 4 15142
Protoss_Assimilator 3 11511
Protoss_Gateway 3 14380
Protoss_Cybernetics_Core 1 9503
Protoss_Zealot 6 13992
Protoss_Stargate 1 11220
Protoss_Citadel_of_Adun 1 11827
Protoss_Corsair 3 15504
15504
