Protoss_Forge 1 4868
Protoss_Nexus 1 7781
Protoss_Photon_Cannon 4 13055
Protoss_Gateway 4 15857
Protoss_Assimilator 1 7163
Protoss_Zealot 4 14636
Protoss_Cybernetics_Core 1 11519
Protoss_Stargate 1 13935
Protoss_Dragoon 1 13675
Protoss_Citadel_of_Adun 1 14591
Protoss_Corsair 1 15143
15857
