Protoss_Forge 1 4413
Protoss_Photon_Cannon 3 8059
Protoss_Nexus 1 9400
Protoss_Gateway 1 8780
Protoss_Zealot 2 11332
Protoss_Assimilator 2 15425
Protoss_Cybernetics_Core 1 15708
15708
