Protoss_Nexus 1 7275
Protoss_Forge 1 6315
Protoss_Gateway 4 13893
Protoss_Photon_Cannon 2 15167
Protoss_Assimilator 2 10632
Protoss_Cybernetics_Core 1 9501
Protoss_Zealot 2 10106
Protoss_Dragoon 8 15730
Protoss_Stargate 1 12530
Protoss_Corsair 2 14792
15730
