Protoss_Forge 1 4144
Protoss_Nexus 1 7597
Protoss_Photon_Cannon 3 11264
Protoss_Gateway 1 8440
Protoss_Assimilator 2 10100
Protoss_Cybernetics_Core 1 10111
Protoss_Zealot 2 12424
Protoss_Stargate 2 12861
Protoss_Corsair 5 15064
Protoss_Citadel_of_Adun 1 15093
15093
