Protoss_Forge 1 4091
Protoss_Photon_Cannon 2 8493
Protoss_Nexus 1 8759
Protoss_Gateway 1 8256
Protoss_Assimilator 2 10372
Protoss_Cybernetics_Core 1 9876
Protoss_Zealot 2 12233
Protoss_Stargate 1 11647
Protoss_Robotics_Facility 1 13058
Protoss_Corsair 4 15473
Protoss_Dragoon 1 13573
Protoss_Shuttle 1 14695
Protoss_Robotics_Support_Bay 1 14211
15473
