Protoss_Nexus 1 7410
Protoss_Forge 1 6362
Protoss_Gateway 3 12391
Protoss_Photon_Cannon 6 15631
Protoss_Assimilator 2 9618
Protoss_Cybernetics_Core 1 9509
Protoss_Citadel_of_Adun 1 11006
Protoss_Templar_Archives 1 12574
Protoss_Zealot 3 15561
Protoss_High_Templar 4 15309
Protoss_Dark_Templar 1 14574
Protoss_Archon 1 14676
15631
