Protoss_Forge 1 4829
Protoss_Photon_Cannon 2 6448
Protoss_Nexus 1 8602
Protoss_Gateway 3 15315
Protoss_Assimilator 2 11730
Protoss_Cybernetics_Core 1 9197
Protoss_Zealot 6 14777
Protoss_Stargate 1 11056
Protoss_Citadel_of_Adun 1 11990
Protoss_Corsair 4 14912
Protoss_Templar_Archives 1 14152
Protoss_Dark_Templar 2 15592
15592
