Protoss_Nexus 1 7085
Protoss_Forge 1 5906
Protoss_Gateway 5 15703
Protoss_Photon_Cannon 4 15140
Protoss_Assimilator 2 9585
Protoss_Cybernetics_Core 1 9232
Protoss_Zealot 3 14124
Protoss_Dragoon 1 10471
Protoss_Stargate 1 11151
Protoss_Citadel_of_Adun 1 12053
Protoss_Corsair 1 12149
Protoss_Templar_Archives 1 13564
Protoss_High_Templar 2 14799
Protoss_Dark_Templar 1 14875
15703
