Protoss_Forge 1 3844
Protoss_Photon_Cannon 3 7072
Protoss_Nexus 1 9971
Protoss_Gateway 1 9233
Protoss_Zealot 3 15072
Protoss_Assimilator 2 14388
Protoss_Cybernetics_Core 1 14259
Protoss_Stargate 1 15978
15978
