Protoss_Nexus 1 7137
Protoss_Gateway 4 13703
Protoss_Forge 1 6680
Protoss_Assimilator 2 15484
Protoss_Zealot 10 14496
Protoss_Photon_Cannon 5 15361
Protoss_Cybernetics_Core 1 9421
Protoss_Citadel_of_Adun 1 11328
Protoss_Dragoon 1 11548
Protoss_Templar_Archives 1 14209
Leg_Enhancements 1 14589
15484
