Protoss_Forge 1 4297
Protoss_Photon_Cannon 2 5752
Protoss_Nexus 1 8651
Protoss_Gateway 3 13640
Protoss_Assimilator 2 12122
Protoss_Zealot 10 15523
Protoss_Cybernetics_Core 1 9968
Protoss_Citadel_of_Adun 1 11774
Protoss_Dragoon 1 11744
Protoss_Stargate 2 15640
15640
