Protoss_Forge 1 3888
Protoss_Photon_Cannon 4 14722
Protoss_Nexus 2 14463
Protoss_Gateway 1 8553
Protoss_Assimilator 2 11478
Protoss_Cybernetics_Core 1 10075
Protoss_Zealot 5 14592
Protoss_Stargate 2 13740
Protoss_Corsair 4 15061
15061
