Protoss_Gateway 1 4079
Protoss_Zealot 5 12646
Protoss_Assimilator 1 5358
Protoss_Cybernetics_Core 1 7125
Protoss_Robotics_Facility 1 9153
Protoss_Dragoon 1 8881
Protoss_Stargate 1 10374
Protoss_Shuttle 1 10600
Protoss_Robotics_Support_Bay 1 10409
Protoss_Corsair 4 15321
Protoss_Reaver 1 12296
Protoss_Forge 1 12175
Protoss_Photon_Cannon 3 15276
15321
