Protoss_Gateway 2 15447
Protoss_Assimilator 1 4653
Protoss_Zealot 6 13071
Protoss_Forge 1 10788
Protoss_Photon_Cannon 1 12069
Protoss_Cybernetics_Core 1 13141
Protoss_Citadel_of_Adun 1 14860
Protoss_Dragoon 1 14634
15447
