Protoss_Gateway 5 15892
Protoss_Zealot 10 13960
Protoss_Nexus 1 9798
Protoss_Assimilator 2 13259
Protoss_Cybernetics_Core 1 9838
Protoss_Forge 1 10069
Protoss_Stargate 1 11561
Protoss_Photon_Cannon 3 14375
Protoss_Citadel_of_Adun 1 12460
Protoss_Corsair 1 12851
Protoss_Templar_Archives 1 14118
15892
