Protoss_Forge 1 4565
Protoss_Photon_Cannon 3 15380
Protoss_Nexus 1 8872
Protoss_Gateway 4 14461
Protoss_Assimilator 2 10770
Protoss_Zealot 3 12599
Protoss_Cybernetics_Core 1 9980
Protoss_Stargate 1 11807
Protoss_Dragoon 1 11524
Protoss_Citadel_of_Adun 1 12321
Protoss_Corsair 2 14888
Protoss_Templar_Archives 1 13811
Protoss_High_Templar 4 15660
15660
