Protoss_Forge 1 4347
Protoss_Nexus 1 7629
Protoss_Photon_Cannon 3 13869
Protoss_Gateway 2 11547
Protoss_Assimilator 2 14344
Protoss_Cybernetics_Core 1 9601
Protoss_Zealot 9 15315
Protoss_Stargate 1 11388
Protoss_Citadel_of_Adun 1 11812
Protoss_Corsair 2 14642
15315
