Protoss_Forge 1 4889
Protoss_Nexus 1 7843
Protoss_Gateway 2 11944
Protoss_Photon_Cannon 2 15813
Protoss_Assimilator 2 11734
Protoss_Zealot 7 14590
Protoss_Cybernetics_Core 1 8945
Protoss_Stargate 1 10898
Protoss_Citadel_of_Adun 1 11452
Protoss_Corsair 1 11906
Protoss_Templar_Archives 1 14191
Protoss_Dark_Templar 2 15710
Leg_Enhancements 1 14510
15813
