Protoss_Gateway 6 15838
Protoss_Zealot 5 15277
Protoss_Nexus 1 8762
Protoss_Assimilator 2 9270
Protoss_Cybernetics_Core 1 8364
Protoss_Stargate 1 10127
Protoss_Citadel_of_Adun 1 10720
Protoss_Forge 1 10928
Protoss_Corsair 1 11086
Protoss_Templar_Archives 1 12198
Protoss_Photon_Cannon 1 12645
Protoss_Dark_Templar 2 13734
Protoss_High_Templar 2 14878
15838
