Protoss_Forge 1 4808
Protoss_Nexus 1 7679
Protoss_Photon_Cannon 2 13004
Protoss_Gateway 2 12532
Protoss_Assimilator 2 10369
Protoss_Cybernetics_Core 1 8755
Protoss_Zealot 4 12918
Protoss_Stargate 1 10437
Protoss_Dragoon 1 10055
Protoss_Citadel_of_Adun 1 10981
Protoss_Corsair 1 11712
Protoss_Templar_Archives 1 15220
15220
