Protoss_Forge 1 4732
Protoss_Photon_Cannon 3 14272
Protoss_Nexus 1 8724
Protoss_Gateway 2 13236
Protoss_Assimilator 2 12752
Protoss_Cybernetics_Core 1 9311
Protoss_Zealot 6 15046
Protoss_Dragoon 1 10716
Protoss_Stargate 1 11667
Protoss_Citadel_of_Adun 1 12503
Protoss_Corsair 4 15544
Protoss_Templar_Archives 1 14841
15544
