Protoss_Forge 1 4325
Protoss_Photon_Cannon 5 15582
Protoss_Nexus 1 9156
Protoss_Gateway 2 12708
Protoss_Assimilator 2 12952
Protoss_Cybernetics_Core 1 9715
Protoss_Zealot 9 14912
Protoss_Stargate 1 11443
Protoss_Citadel_of_Adun 1 12166
Protoss_Corsair 4 15500
Protoss_Templar_Archives 1 14614
Protoss_Dragoon 2 15563
15582
