Protoss_Forge 1 4578
Protoss_Nexus 1 7887
Protoss_Gateway 4 15099
Protoss_Photon_Cannon 5 15487
Protoss_Assimilator 2 9869
Protoss_Cybernetics_Core 1 9263
Protoss_Zealot 2 13112
Protoss_Stargate 1 11488
Protoss_Citadel_of_Adun 1 11865
Protoss_Corsair 1 12465
Protoss_Templar_Archives 1 13758
15487
