Protoss_Forge 1 4116
Protoss_Photon_Cannon 3 15399
Protoss_Nexus 1 8910
Protoss_Gateway 2 13754
Protoss_Assimilator 2 10864
Protoss_Cybernetics_Core 1 9694
Protoss_Zealot 7 14912
Protoss_Stargate 1 11680
Protoss_Corsair 3 15157
Protoss_Citadel_of_Adun 1 13252
15399
