Protoss_Gateway 2 15839
Protoss_Assimilator 1 4230
Protoss_Zealot 9 14912
Protoss_Cybernetics_Core 1 6519
Protoss_Dragoon 1 7754
Protoss_Stargate 1 8719
Protoss_Corsair 5 15140
Protoss_Nexus 1 12685
Protoss_Forge 1 12219
Protoss_Citadel_of_Adun 1 14489
15839
