Protoss_Forge 1 4311
Protoss_Photon_Cannon 4 15376
Protoss_Nexus 1 8239
Protoss_Gateway 1 7324
Protoss_Assimilator 2 9349
Protoss_Zealot 5 14344
Protoss_Cybernetics_Core 1 9109
Protoss_Stargate 2 12893
Protoss_Robotics_Facility 1 12292
Protoss_Corsair 4 14167
Protoss_Robotics_Support_Bay 1 13340
Protoss_Reaver 1 15256
15376
