Protoss_Forge 1 4354
Protoss_Photon_Cannon 3 15393
Protoss_Nexus 1 9245
Protoss_Gateway 3 12544
Protoss_Assimilator 2 13735
Protoss_Zealot 9 15514
Protoss_Cybernetics_Core 1 10201
Protoss_Dragoon 1 11398
Protoss_Citadel_of_Adun 1 11909
Protoss_Stargate 2 15545
15545
