Protoss_Forge 1 4112
Protoss_Photon_Cannon 4 15494
Protoss_Nexus 1 8665
Protoss_Gateway 2 15971
Protoss_Assimilator 2 11133
Protoss_Zealot 4 14054
Protoss_Cybernetics_Core 1 10556
Protoss_Stargate 1 12553
Protoss_Citadel_of_Adun 1 12775
Protoss_Corsair 2 15342
Protoss_Templar_Archives 1 15135
15971
