Protoss_Forge 2 15558
Protoss_Nexus 1 7577
Protoss_Photon_Cannon 6 14092
Protoss_Gateway 2 12238
Protoss_Assimilator 2 10467
Protoss_Cybernetics_Core 1 9627
Protoss_Zealot 5 14496
Protoss_Stargate 1 11514
Protoss_Citadel_of_Adun 1 11818
Protoss_Corsair 2 14107
Protoss_Templar_Archives 1 13957
Protoss_Dark_Templar 2 15191
15558
