Protoss_Forge 1 4129
Protoss_Photon_Cannon 2 7031
Protoss_Nexus 1 8223
Protoss_Gateway 4 14000
Protoss_Assimilator 2 10226
Protoss_Cybernetics_Core 1 9235
Protoss_Zealot 5 15055
Protoss_Stargate 1 11157
Protoss_Citadel_of_Adun 1 11683
Protoss_Corsair 2 12977
Protoss_Templar_Archives 1 14966
15055
