Protoss_Gateway 2 15620
Protoss_Assimilator 1 4514
Protoss_Zealot 4 11607
Protoss_Cybernetics_Core 1 7022
Protoss_Dragoon 1 8341
Protoss_Robotics_Facility 1 10069
Protoss_Shuttle 1 11513
Protoss_Robotics_Support_Bay 1 10952
Protoss_Reaver 2 14611
Protoss_Citadel_of_Adun 1 13741
Protoss_Forge 1 14575
Protoss_Templar_Archives 1 15655
15655
