Protoss_Forge 1 4652
Protoss_Nexus 1 7878
Protoss_Photon_Cannon 4 15016
Protoss_Gateway 3 13568
Protoss_Assimilator 2 10186
Protoss_Zealot 3 15512
Protoss_Cybernetics_Core 1 10467
Protoss_Stargate 2 13243
Protoss_Citadel_of_Adun 1 12595
Protoss_Corsair 4 15473
Protoss_Templar_Archives 1 15438
15512
