Protoss_Forge 1 4071
Protoss_Photon_Cannon 5 14840
Protoss_Nexus 1 8441
Protoss_Gateway 3 15194
Protoss_Assimilator 2 10919
Protoss_Cybernetics_Core 1 10466
Protoss_Zealot 3 14373
Protoss_Stargate 1 12300
Protoss_Dragoon 1 11934
Protoss_Citadel_of_Adun 1 13185
Protoss_Corsair 1 13237
Protoss_Templar_Archives 1 15680
15680
