Protoss_Gateway 2 4656
Protoss_Zealot 9 14028
Protoss_Assimilator 1 6952
Protoss_Cybernetics_Core 1 9005
Protoss_Stargate 1 11365
Protoss_Dragoon 1 11451
Protoss_Citadel_of_Adun 1 12149
Protoss_Corsair 1 12918
Protoss_Forge 1 14367
14367
