Protoss_Forge 1 4501
Protoss_Photon_Cannon 5 14586
Protoss_Nexus 1 9213
Protoss_Gateway 1 8294
Protoss_Assimilator 2 9497
Protoss_Cybernetics_Core 1 9787
Protoss_Zealot 4 14215
Protoss_Stargate 2 12998
Protoss_Dragoon 1 11021
Protoss_Robotics_Facility 1 12469
Protoss_Corsair 4 15081
Protoss_Robotics_Support_Bay 1 13920
Protoss_Reaver 1 15644
15644
