Protoss_Nexus 1 7023
Protoss_Gateway 4 15547
Protoss_Forge 1 6039
Protoss_Photon_Cannon 1 7291
Protoss_Assimilator 2 10138
Protoss_Cybernetics_Core 1 8484
Protoss_Zealot 9 14751
Protoss_Dragoon 1 9718
Protoss_Stargate 1 10458
Protoss_Citadel_of_Adun 1 11642
Protoss_Corsair 2 12611
Protoss_Templar_Archives 1 14426
15547
