Protoss_Gateway 1 4082
Protoss_Zealot 8 14036
Protoss_Assimilator 1 5273
Protoss_Cybernetics_Core 1 6497
Protoss_Stargate 1 8494
Protoss_Robotics_Facility 1 9929
Protoss_Corsair 1 9690
Protoss_Forge 1 10505
Protoss_Robotics_Support_Bay 1 10787
Protoss_Photon_Cannon 2 13188
Protoss_Reaver 1 12556
Protoss_Shield_Battery 1 14256
Protoss_Shuttle 1 15867
15867
