Protoss_Forge 1 4227
Protoss_Nexus 1 8061
Protoss_Gateway 1 7264
Protoss_Assimilator 2 9784
Protoss_Photon_Cannon 3 14230
Protoss_Cybernetics_Core 1 9011
Protoss_Zealot 5 14677
Protoss_Stargate 1 10846
Protoss_Dragoon 1 10810
Protoss_Robotics_Facility 1 12262
Protoss_Corsair 4 14683
Protoss_Robotics_Support_Bay 1 13064
Protoss_Reaver 1 15070
15070
