Protoss_Forge 1 4766
Protoss_Nexus 1 7625
Protoss_Photon_Cannon 3 15683
Protoss_Gateway 3 13430
Protoss_Assimilator 2 11013
Protoss_Cybernetics_Core 1 9201
Protoss_Zealot 7 14733
Protoss_Stargate 1 10882
Protoss_Corsair 4 14470
Protoss_Citadel_of_Adun 1 12601
Protoss_Templar_Archives 1 15470
15683
