Protoss_Forge 1 4792
Protoss_Nexus 1 7395
Protoss_Photon_Cannon 4 15809
Protoss_Gateway 4 14702
Protoss_Assimilator 2 9252
Protoss_Cybernetics_Core 1 9122
Protoss_Zealot 1 9541
Protoss_Stargate 1 10919
Protoss_Citadel_of_Adun 1 11949
Protoss_Corsair 3 13627
Protoss_Templar_Archives 1 13504
Protoss_Dark_Templar 2 14823
15809
