Protoss_Forge 1 4804
Protoss_Nexus 1 7663
Protoss_Photon_Cannon 4 15556
Protoss_Gateway 4 15308
Protoss_Assimilator 2 9882
Protoss_Cybernetics_Core 1 9365
Protoss_Stargate 1 11096
Protoss_Citadel_of_Adun 1 11288
Protoss_Dragoon 1 11630
Protoss_Corsair 2 13755
Protoss_Templar_Archives 1 13290
Protoss_Zealot 2 15067
Protoss_High_Templar 2 15206
15556
