Protoss_Forge 1 4293
Protoss_Photon_Cannon 2 6238
Protoss_Nexus 1 10029
Protoss_Gateway 3 10457
Protoss_Zealot 15 15034
Protoss_Assimilator 1 12948
Protoss_Cybernetics_Core 1 14009
15034
