Protoss_Gateway 2 9984
Protoss_Assimilator 1 4155
Protoss_Zealot 4 14736
Protoss_Cybernetics_Core 1 6087
Protoss_Stargate 1 7895
Protoss_Dragoon 7 13544
Protoss_Corsair 5 14841
Singularity_Charge 1 12116
Protoss_Citadel_of_Adun 1 14616
14841
