Protoss_Nexus 1 6988
Protoss_Gateway 2 11816
Protoss_Assimilator 2 9122
Protoss_Zealot 10 13946
Protoss_Cybernetics_Core 1 8714
Protoss_Stargate 1 10402
Protoss_Citadel_of_Adun 1 10698
Protoss_Corsair 1 11432
Protoss_Templar_Archives 1 12952
Protoss_Forge 1 13340
Leg_Enhancements 1 13643
Protoss_High_Templar 2 15066
Protoss_Photon_Cannon 3 15752
15752
