Protoss_Forge 1 4796
Protoss_Gateway 1 6264
Protoss_Photon_Cannon 2 6499
Protoss_Assimilator 2 13647
Protoss_Cybernetics_Core 1 8251
Protoss_Stargate 1 10001
Protoss_Dragoon 1 9818
Protoss_Nexus 1 12464
Protoss_Corsair 5 15143
Protoss_Citadel_of_Adun 1 12118
Protoss_Zealot 2 14777
Protoss_Templar_Archives 1 13745
Protoss_Dark_Templar 1 15142
15143
