Protoss_Gateway 2 15487
Protoss_Zealot 10 14546
Protoss_Forge 1 7394
Protoss_Nexus 1 10354
Protoss_Assimilator 2 11499
Protoss_Photon_Cannon 3 14915
Protoss_Cybernetics_Core 1 10384
Protoss_Stargate 1 12872
Protoss_Robotics_Facility 1 14218
Protoss_Corsair 2 14885
Protoss_Robotics_Support_Bay 1 15132
Protoss_Shuttle 1 15904
15904
