Protoss_Gateway 2 12908
Protoss_Assimilator 2 13568
Protoss_Cybernetics_Core 1 5944
Protoss_Zealot 2 7082
Protoss_Stargate 1 7723
Protoss_Citadel_of_Adun 1 8339
Protoss_Dragoon 2 9376
Protoss_Corsair 1 8871
Protoss_Templar_Archives 1 10313
Protoss_Nexus 1 13035
Protoss_Dark_Templar 2 12768
Protoss_Forge 1 13000
Protoss_High_Templar 2 14240
Protoss_Photon_Cannon 2 15085
Protoss_Archon 1 14851
15085
