Protoss_Forge 1 4166
Protoss_Photon_Cannon 4 15194
Protoss_Nexus 1 8216
Protoss_Gateway 2 13908
Protoss_Assimilator 2 11892
Protoss_Cybernetics_Core 1 9974
Protoss_Zealot 4 14689
Protoss_Stargate 1 11791
Protoss_Dragoon 1 11957
Protoss_Citadel_of_Adun 1 12766
Protoss_Corsair 3 14739
Protoss_Templar_Archives 1 15511
15511
