Protoss_Gateway 1 4255
Protoss_Assimilator 1 4479
Protoss_Zealot 3 7113
Protoss_Cybernetics_Core 1 7085
Protoss_Dragoon 6 15768
Protoss_Robotics_Facility 1 10050
Protoss_Shuttle 1 11455
Protoss_Robotics_Support_Bay 1 11393
Protoss_Reaver 2 15000
Protoss_Forge 1 12623
Singularity_Charge 1 12748
15768
