Protoss_Forge 1 4021
Protoss_Photon_Cannon 2 15200
Protoss_Nexus 1 8381
Protoss_Gateway 4 14764
Protoss_Assimilator 2 11158
Protoss_Cybernetics_Core 1 9068
Protoss_Zealot 8 15579
Protoss_Stargate 1 10786
Protoss_Citadel_of_Adun 1 11379
Protoss_Corsair 4 14999
15579
