Protoss_Forge 1 4425
Protoss_Photon_Cannon 6 14919
Protoss_Nexus 1 9131
Protoss_Gateway 3 14976
Protoss_Assimilator 2 11519
Protoss_Cybernetics_Core 1 10070
Protoss_Zealot 4 13656
Protoss_Stargate 1 12041
Protoss_Citadel_of_Adun 1 12876
Protoss_Corsair 3 15058
15058
