Protoss_Forge 1 4612
Protoss_Nexus 1 7632
Protoss_Photon_Cannon 5 15142
Protoss_Gateway 1 7015
Protoss_Assimilator 2 13182
Protoss_Cybernetics_Core 1 8455
Protoss_Zealot 5 13934
Protoss_Stargate 1 10139
Protoss_Dragoon 1 10956
Protoss_Corsair 3 15573
Protoss_Robotics_Facility 1 14840
15573
