Protoss_Forge 1 4833
Protoss_Nexus 1 7868
Protoss_Gateway 4 14335
Protoss_Assimilator 2 11894
Protoss_Photon_Cannon 5 15772
Protoss_Cybernetics_Core 1 9121
Protoss_Zealot 9 14203
Protoss_Dragoon 1 10327
Protoss_Citadel_of_Adun 1 10830
Protoss_Templar_Archives 1 13698
Leg_Enhancements 1 13769
Protoss_Ground_Weapons_1 1 13986
Protoss_Dark_Templar 2 15323
Protoss_High_Templar 2 15739
15772
