Protoss_Forge 2 4761
Protoss_Photon_Cannon 3 8278
Protoss_Gateway 2 13903
Protoss_Zealot 2 12430
Protoss_Nexus 1 12188
Protoss_Assimilator 2 12222
Protoss_Cybernetics_Core 1 11566
Protoss_Stargate 1 13812
Protoss_Citadel_of_Adun 1 14319
Protoss_Corsair 1 14756
Protoss_Templar_Archives 1 15939
15939
