Protoss_Forge 1 4429
Protoss_Photon_Cannon 2 5896
Protoss_Nexus 1 8554
Protoss_Gateway 2 14778
Protoss_Assimilator 2 10480
Protoss_Cybernetics_Core 1 9102
Protoss_Zealot 5 14045
Protoss_Stargate 1 10926
Protoss_Corsair 4 14827
Protoss_Citadel_of_Adun 1 12639
Protoss_Templar_Archives 2 14455
14827
