Protoss_Gateway 1 4149
Protoss_Zealot 5 11162
Protoss_Assimilator 1 5468
Protoss_Cybernetics_Core 1 6570
Protoss_Stargate 1 8448
Protoss_Dragoon 1 8272
Protoss_Forge 1 8793
Protoss_Corsair 3 14879
Protoss_Photon_Cannon 5 15566
Protoss_Nexus 1 14097
Protoss_Robotics_Facility 1 14067
15566
