Protoss_Assimilator 1 3772
Protoss_Gateway 1 4821
Protoss_Cybernetics_Core 1 6285
Protoss_Robotics_Facility 1 8231
Protoss_Dragoon 1 7551
Protoss_Zealot 2 9397
Protoss_Shuttle 1 9633
Protoss_Robotics_Support_Bay 1 9433
Protoss_Citadel_of_Adun 1 11126
Protoss_Reaver 2 15081
Protoss_Forge 1 11369
Protoss_Photon_Cannon 3 15718
Protoss_Templar_Archives 1 13356
Protoss_High_Templar 1 14561
15718
