Protoss_Forge 1 4883
Protoss_Nexus 1 7562
Protoss_Gateway 4 15542
Protoss_Photon_Cannon 2 13105
Protoss_Assimilator 2 12481
Protoss_Cybernetics_Core 1 8370
Protoss_Zealot 7 13226
Protoss_Stargate 1 10071
Protoss_Citadel_of_Adun 1 10975
Protoss_Corsair 3 12731
Protoss_Templar_Archives 1 14282
Leg_Enhancements 1 13954
15542
