Protoss_Forge 2 15093
Protoss_Photon_Cannon 7 15044
Protoss_Nexus 1 8054
Protoss_Gateway 2 13259
Protoss_Assimilator 2 9456
Protoss_Cybernetics_Core 1 8516
Protoss_Zealot 10 15228
Protoss_Stargate 1 10467
Protoss_Corsair 2 12427
Protoss_Citadel_of_Adun 1 12119
15228
