Protoss_Gateway 1 4394
Protoss_Zealot 10 15251
Protoss_Forge 1 7407
Protoss_Photon_Cannon 4 14154
Protoss_Nexus 1 12952
Protoss_Assimilator 1 13451
Protoss_Cybernetics_Core 1 15523
15523
