Protoss_Forge 1 4407
Protoss_Nexus 1 7527
Protoss_Photon_Cannon 2 13509
Protoss_Gateway 5 15149
Protoss_Assimilator 2 9389
Protoss_Cybernetics_Core 1 8812
Protoss_Zealot 3 12833
Protoss_Stargate 1 10601
Protoss_Dragoon 1 10476
Protoss_Citadel_of_Adun 1 11532
Protoss_Corsair 2 12567
Protoss_Templar_Archives 1 13018
Protoss_Dark_Templar 1 14258
15149
