Protoss_Forge 1 4832
Protoss_Nexus 1 7716
Protoss_Photon_Cannon 3 15095
Protoss_Gateway 2 12980
Protoss_Assimilator 2 9219
Protoss_Cybernetics_Core 1 8718
Protoss_Zealot 6 14238
Protoss_Stargate 1 10587
Protoss_Citadel_of_Adun 1 11424
Protoss_Corsair 2 12658
Protoss_Templar_Archives 1 14177
Protoss_Dark_Templar 2 15549
15549
