Protoss_Nexus 1 7102
Protoss_Gateway 4 14010
Protoss_Forge 1 6315
Protoss_Assimilator 2 9623
Protoss_Photon_Cannon 2 11445
Protoss_Cybernetics_Core 1 8794
Protoss_Zealot 6 15131
Protoss_Dragoon 1 10034
Protoss_Stargate 1 10765
Protoss_Citadel_of_Adun 1 11469
Protoss_Corsair 1 11888
Protoss_Templar_Archives 1 13065
Protoss_High_Templar 2 14270
Protoss_Archon 1 14984
15131
