Protoss_Forge 1 4158
Protoss_Photon_Cannon 3 14353
Protoss_Nexus 1 8241
Protoss_Gateway 3 14124
Protoss_Assimilator 2 10684
Protoss_Cybernetics_Core 1 9406
Protoss_Zealot 7 14958
Protoss_Stargate 1 11132
Protoss_Citadel_of_Adun 1 11704
Protoss_Corsair 1 12081
Protoss_Templar_Archives 1 13404
Protoss_High_Templar 2 15391
15391
