Protoss_Forge 1 4725
Protoss_Photon_Cannon 3 14668
Protoss_Nexus 1 8937
Protoss_Gateway 3 13586
Protoss_Assimilator 2 11407
Protoss_Cybernetics_Core 1 9809
Protoss_Zealot 8 15175
Protoss_Stargate 1 11895
Protoss_Citadel_of_Adun 1 12274
Protoss_Corsair 2 13992
15175
