Protoss_Forge 1 4412
Protoss_Photon_Cannon 4 13222
Protoss_Nexus 1 8455
Protoss_Gateway 1 8461
Protoss_Assimilator 2 9617
Protoss_Cybernetics_Core 1 9904
Protoss_Stargate 1 11709
Protoss_Zealot 3 13700
Protoss_Robotics_Facility 1 12440
Protoss_Corsair 3 15055
Protoss_Robotics_Support_Bay 1 13174
Protoss_Reaver 1 15047
15055
