Protoss_Gateway 2 4624
Protoss_Zealot 11 14496
Protoss_Nexus 2 14099
Protoss_Assimilator 2 14617
Protoss_Forge 1 11265
Protoss_Photon_Cannon 2 15347
Protoss_Cybernetics_Core 1 13084
Protoss_Stargate 1 14887
Protoss_Robotics_Facility 1 16216
16216
