Protoss_Gateway 2 13060
Protoss_Assimilator 1 4193
Protoss_Cybernetics_Core 1 5780
Protoss_Zealot 11 14335
Protoss_Stargate 1 8087
Protoss_Corsair 3 10978
Protoss_Citadel_of_Adun 1 12529
Protoss_Robotics_Facility 1 14329
Protoss_Shuttle 1 15769
Protoss_Robotics_Support_Bay 1 15312
15769
