Protoss_Gateway 4 15309
Protoss_Zealot 9 15239
Protoss_Assimilator 1 6996
Protoss_Cybernetics_Core 1 8335
Protoss_Stargate 1 10066
Protoss_Forge 1 9951
Protoss_Citadel_of_Adun 1 10937
Protoss_Photon_Cannon 4 13387
Protoss_Corsair 2 12198
Protoss_Templar_Archives 1 13245
15309
