Protoss_Gateway 2 13603
Protoss_Zealot 11 14742
Protoss_Nexus 1 8554
Protoss_Assimilator 2 11417
Protoss_Cybernetics_Core 1 9307
Protoss_Forge 1 9975
Protoss_Stargate 1 11169
Protoss_Citadel_of_Adun 1 12307
Protoss_Corsair 2 13357
Protoss_Photon_Cannon 2 15573
Protoss_Templar_Archives 1 15457
15573
