Protoss_Forge 1 4432
Protoss_Photon_Cannon 4 15348
Protoss_Nexus 1 8535
Protoss_Gateway 1 8086
Protoss_Assimilator 2 11083
Protoss_Zealot 3 12819
Protoss_Cybernetics_Core 1 10698
Protoss_Dragoon 1 11957
Protoss_Stargate 2 14492
Protoss_Corsair 3 15468
Protoss_Robotics_Facility 1 15358
15468
