Protoss_Gateway 4 13501
Protoss_Assimilator 1 4512
Protoss_Zealot 5 9491
Protoss_Cybernetics_Core 1 6488
Protoss_Stargate 1 8172
Protoss_Dragoon 11 15549
Protoss_Scout 1 10066
Protoss_Nexus 1 12514
15549
