Protoss_Gateway 2 9030
Protoss_Assimilator 1 4071
Protoss_Zealot 7 13568
Protoss_Cybernetics_Core 1 6952
Protoss_Dragoon 1 8199
Protoss_Citadel_of_Adun 1 8628
Protoss_Templar_Archives 1 10085
Protoss_High_Templar 2 11293
Protoss_Forge 1 11531
Protoss_Dark_Templar 2 12399
Protoss_Archon 1 11755
Protoss_Photon_Cannon 2 13181
Leg_Enhancements 1 12320
Protoss_Nexus 1 17159
17159
