Protoss_Gateway 1 4169
Protoss_Zealot 4 9430
Protoss_Assimilator 1 5339
Protoss_Cybernetics_Core 1 6946
Protoss_Robotics_Facility 1 8950
Protoss_Dragoon 1 8568
Protoss_Stargate 1 10000
Protoss_Shuttle 1 10583
Protoss_Robotics_Support_Bay 1 10482
Protoss_Corsair 5 15585
Protoss_Reaver 1 12457
Protoss_Forge 1 12421
Protoss_Photon_Cannon 3 15448
15585
