Protoss_Forge 1 4205
Protoss_Photon_Cannon 4 13561
Protoss_Nexus 1 8873
Protoss_Gateway 3 15967
Protoss_Assimilator 2 12143
Protoss_Cybernetics_Core 1 9576
Protoss_Zealot 4 14127
Protoss_Stargate 1 11473
Protoss_Citadel_of_Adun 1 11420
Protoss_Corsair 3 15512
Protoss_Templar_Archives 1 13972
Protoss_Dark_Templar 1 15692
15967
