Protoss_Gateway 2 5080
Protoss_Zealot 15 13872
Protoss_Forge 1 8909
Protoss_Nexus 1 12697
Protoss_Photon_Cannon 1 11518
Protoss_Assimilator 2 15229
Protoss_Cybernetics_Core 1 13211
Protoss_Stargate 1 15353
15353
