Protoss_Forge 1 3792
Protoss_Photon_Cannon 4 14354
Protoss_Nexus 1 8815
Protoss_Gateway 3 15588
Protoss_Assimilator 2 10776
Protoss_Cybernetics_Core 1 9789
Protoss_Zealot 4 14952
Protoss_Stargate 1 11810
Protoss_Dragoon 1 11641
Protoss_Citadel_of_Adun 1 12522
Protoss_Corsair 2 13875
Protoss_Templar_Archives 1 14082
Protoss_Dark_Templar 1 15528
15588
