Protoss_Forge 1 4302
Protoss_Photon_Cannon 5 14951
Protoss_Nexus 1 8721
Protoss_Gateway 3 12244
Protoss_Assimilator 2 9920
Protoss_Zealot 7 15064
Protoss_Cybernetics_Core 1 9314
Protoss_Citadel_of_Adun 1 10925
Protoss_Dragoon 1 10813
Protoss_Templar_Archives 1 12895
Protoss_High_Templar 4 15633
Protoss_Dark_Templar 1 15341
Protoss_Archon 1 14908
15633
