Protoss_Nexus 1 7369
Protoss_Forge 1 6122
Protoss_Gateway 4 12478
Protoss_Photon_Cannon 7 15162
Protoss_Zealot 10 14721
Protoss_Cybernetics_Core 1 10161
Protoss_Assimilator 2 10220
Protoss_Citadel_of_Adun 1 12068
Protoss_Templar_Archives 1 13697
Protoss_High_Templar 3 15824
15824
