Protoss_Forge 1 4488
Protoss_Photon_Cannon 3 15506
Protoss_Nexus 1 9207
Protoss_Gateway 2 13526
Protoss_Assimilator 2 10567
Protoss_Cybernetics_Core 1 9756
Protoss_Zealot 2 11575
Protoss_Stargate 1 11470
Protoss_Citadel_of_Adun 1 11717
Protoss_Corsair 2 13650
Protoss_Robotics_Facility 1 13731
Protoss_Templar_Archives 1 13747
Protoss_Shuttle 1 15175
Protoss_Dark_Templar 2 15183
15506
