Protoss_Forge 1 3835
Protoss_Photon_Cannon 3 11126
Protoss_Nexus 1 9169
Protoss_Gateway 3 14142
Protoss_Assimilator 2 12190
Protoss_Zealot 7 15245
Protoss_Cybernetics_Core 1 10139
Protoss_Stargate 1 12067
Protoss_Dragoon 1 11902
Protoss_Corsair 2 14092
Protoss_Citadel_of_Adun 1 14935
15245
