Protoss_Forge 1 4081
Protoss_Nexus 1 7882
Protoss_Photon_Cannon 2 15000
Protoss_Gateway 4 12754
Protoss_Assimilator 2 13507
Protoss_Cybernetics_Core 1 9652
Protoss_Zealot 12 15075
Protoss_Citadel_of_Adun 1 11352
Protoss_Stargate 1 13867
Protoss_Templar_Archives 1 15014
Protoss_Corsair 1 15266
Leg_Enhancements 1 14466
15266
