Protoss_Gateway 2 4985
Protoss_Zealot 12 15078
Protoss_Nexus 2 16556
Protoss_Assimilator 1 9061
Protoss_Cybernetics_Core 1 10193
Protoss_Stargate 1 12051
Protoss_Dragoon 1 11808
Protoss_Forge 1 12412
Protoss_Corsair 2 13919
Protoss_Photon_Cannon 3 15718
16556
