Protoss_Gateway 2 9671
Protoss_Assimilator 1 4464
Protoss_Zealot 7 12986
Protoss_Cybernetics_Core 1 7398
Protoss_Dragoon 1 8741
Protoss_Citadel_of_Adun 1 9293
Protoss_Templar_Archives 1 10747
Protoss_High_Templar 4 14395
Protoss_Archon 1 12709
Protoss_Forge 1 13605
Protoss_Nexus 1 15593
Leg_Enhancements 1 12947
Protoss_Photon_Cannon 3 15787
15787
