Protoss_Forge 1 4293
Protoss_Photon_Cannon 4 14221
Protoss_Nexus 1 8111
Protoss_Gateway 2 13502
Protoss_Assimilator 2 10814
Protoss_Zealot 9 15579
Protoss_Cybernetics_Core 1 9454
Protoss_Stargate 1 11188
Protoss_Citadel_of_Adun 1 11979
Protoss_Corsair 3 14721
15579
