Protoss_Forge 1 5110
Protoss_Photon_Cannon 4 15007
Protoss_Nexus 1 8864
Protoss_Gateway 2 12453
Protoss_Assimilator 2 10672
Protoss_Cybernetics_Core 1 9781
Protoss_Zealot 8 15547
Protoss_Stargate 1 11671
Protoss_Citadel_of_Adun 1 11790
Protoss_Corsair 3 15476
Protoss_Templar_Archives 1 15446
15547
