Protoss_Forge 1 4243
Protoss_Nexus 2 14940
Protoss_Photon_Cannon 3 15439
Protoss_Gateway 1 7253
Protoss_Assimilator 2 10760
Protoss_Zealot 2 11288
Protoss_Cybernetics_Core 1 10420
Protoss_Robotics_Facility 1 12452
Protoss_Stargate 1 12370
Protoss_Corsair 2 14554
Protoss_Robotics_Support_Bay 1 13416
Protoss_Reaver 1 15346
15439
