Protoss_Forge 1 3907
Protoss_Nexus 1 7900
Protoss_Gateway 3 14409
Protoss_Assimilator 2 11452
Protoss_Photon_Cannon 1 7798
Protoss_Cybernetics_Core 1 9108
Protoss_Zealot 6 14648
Protoss_Stargate 1 10806
Protoss_Corsair 4 14464
Protoss_Citadel_of_Adun 1 12476
Protoss_Templar_Archives 1 14029
14648
