Protoss_Gateway 2 13583
Protoss_Assimilator 2 13767
Protoss_Zealot 4 9636
Protoss_Cybernetics_Core 1 6345
Protoss_Stargate 1 8107
Protoss_Dragoon 1 7772
Protoss_Citadel_of_Adun 1 9252
Protoss_Corsair 3 15392
Protoss_Templar_Archives 1 11066
Protoss_Forge 1 10796
Protoss_Nexus 1 13939
Protoss_Dark_Templar 1 12493
Protoss_Photon_Cannon 2 13614
Protoss_High_Templar 3 15300
15392
