Protoss_Forge 2 12532
Protoss_Nexus 1 7694
Protoss_Photon_Cannon 4 15471
Protoss_Gateway 3 16005
Protoss_Assimilator 2 13425
Protoss_Zealot 4 12541
Protoss_Cybernetics_Core 1 9602
Protoss_Stargate 1 11703
Protoss_Corsair 3 15043
Protoss_Citadel_of_Adun 1 13697
Protoss_Templar_Archives 1 15427
16005
