Protoss_Forge 1 4262
Protoss_Nexus 1 7773
Protoss_Photon_Cannon 3 15271
Protoss_Gateway 3 12541
Protoss_Assimilator 2 10878
Protoss_Cybernetics_Core 1 8879
Protoss_Stargate 1 10619
Protoss_Zealot 4 13492
Protoss_Citadel_of_Adun 1 10987
Protoss_Corsair 2 13375
Protoss_Templar_Archives 1 13406
Protoss_High_Templar 2 14767
Protoss_Dark_Templar 1 15607
15607
