Protoss_Forge 1 4584
Protoss_Photon_Cannon 3 15655
Protoss_Nexus 1 8171
Protoss_Gateway 2 15157
Protoss_Assimilator 2 12965
Protoss_Cybernetics_Core 1 10306
Protoss_Zealot 2 12857
Protoss_Stargate 1 12054
Protoss_Dragoon 1 11659
Protoss_Corsair 1 13009
Protoss_Citadel_of_Adun 1 13700
Protoss_Templar_Archives 1 15285
15655
