Protoss_Forge 1 3892
Protoss_Nexus 1 7790
Protoss_Photon_Cannon 3 14931
Protoss_Gateway 2 11469
Protoss_Assimilator 2 11636
Protoss_Zealot 11 15310
Protoss_Cybernetics_Core 1 9690
Protoss_Citadel_of_Adun 1 11136
Protoss_Stargate 2 14053
Protoss_Templar_Archives 1 14554
Leg_Enhancements 1 14097
15310
