Protoss_Forge 1 4308
Protoss_Photon_Cannon 3 15216
Protoss_Nexus 1 8908
Protoss_Gateway 1 7856
Protoss_Assimilator 2 9608
Protoss_Cybernetics_Core 1 9380
Protoss_Zealot 4 13673
Protoss_Stargate 2 12559
Protoss_Citadel_of_Adun 1 11632
Protoss_Corsair 7 15520
Protoss_Templar_Archives 1 14639
15520
