Protoss_Gateway 2 15214
Protoss_Zealot 9 13972
Protoss_Nexus 1 8902
Protoss_Forge 1 7668
Protoss_Assimilator 2 13267
Protoss_Photon_Cannon 4 15417
Protoss_Cybernetics_Core 1 12450
Protoss_Stargate 1 14131
Protoss_Citadel_of_Adun 1 14341
Protoss_Corsair 1 15078
Protoss_Templar_Archives 1 15860
15860
