Protoss_Forge 1 4261
Protoss_Photon_Cannon 5 15436
Protoss_Nexus 1 8721
Protoss_Gateway 3 14292
Protoss_Assimilator 2 11377
Protoss_Cybernetics_Core 1 9974
Protoss_Zealot 7 15298
Protoss_Stargate 1 11886
Protoss_Citadel_of_Adun 1 12298
Protoss_Corsair 2 13875
Protoss_Templar_Archives 1 15015
15436
