Protoss_Forge 1 5095
Protoss_Photon_Cannon 3 14802
Protoss_Nexus 1 8987
Protoss_Gateway 2 14139
Protoss_Assimilator 2 10160
Protoss_Cybernetics_Core 1 9642
Protoss_Zealot 7 15099
Protoss_Stargate 1 11435
Protoss_Citadel_of_Adun 1 12116
Protoss_Corsair 2 14259
Protoss_Templar_Archives 1 15983
15983
