Protoss_Forge 1 4539
Protoss_Photon_Cannon 3 15437
Protoss_Nexus 1 8496
Protoss_Gateway 4 15226
Protoss_Assimilator 2 15321
Protoss_Cybernetics_Core 1 9365
Protoss_Zealot 9 15163
Protoss_Stargate 1 11194
Protoss_Citadel_of_Adun 1 12263
Protoss_Corsair 1 12254
Protoss_Templar_Archives 1 15157
15437
