Protoss_Nexus 1 7301
Protoss_Forge 1 5727
Protoss_Photon_Cannon 2 7127
Protoss_Gateway 4 14347
Protoss_Assimilator 2 10602
Protoss_Cybernetics_Core 1 10085
Protoss_Stargate 1 11769
Protoss_Zealot 10 15550
Protoss_Citadel_of_Adun 1 12383
Protoss_Corsair 1 12790
Protoss_Templar_Archives 1 15345
15550
