Protoss_Gateway 2 4474
Protoss_Zealot 14 15324
Protoss_Assimilator 1 6386
Protoss_Cybernetics_Core 1 9624
Protoss_Stargate 1 11384
Protoss_Citadel_of_Adun 1 12459
Protoss_Corsair 2 13232
Protoss_Forge 1 12934
Protoss_Templar_Archives 1 14060
Protoss_Dark_Templar 1 15335
15335
