Protoss_Forge 1 3713
Protoss_Nexus 1 7465
Protoss_Photon_Cannon 3 15070
Protoss_Gateway 2 12826
Protoss_Assimilator 2 9920
Protoss_Zealot 2 10779
Protoss_Cybernetics_Core 1 9289
Protoss_Stargate 1 11138
Protoss_Citadel_of_Adun 1 11712
Protoss_Corsair 3 14063
Protoss_Templar_Archives 1 13302
Protoss_Dark_Templar 2 14510
Protoss_High_Templar 2 15721
15721
