Protoss_Gateway 3 15447
Protoss_Zealot 8 13420
Protoss_Forge 2 11985
Protoss_Photon_Cannon 4 13315
Protoss_Assimilator 1 11382
Protoss_Cybernetics_Core 1 14589
Protoss_Dragoon 1 15794
15794
