Protoss_Forge 1 4593
Protoss_Nexus 1 7421
Protoss_Photon_Cannon 4 15604
Protoss_Gateway 2 14944
Protoss_Assimilator 3 11133
Protoss_Cybernetics_Core 1 9296
Protoss_Stargate 1 10996
Protoss_Zealot 5 15239
Protoss_Corsair 5 15570
Protoss_Citadel_of_Adun 1 13056
15604
