Protoss_Gateway 2 5048
Protoss_Zealot 9 9624
Protoss_Nexus 1 12849
Protoss_Assimilator 1 11505
Protoss_Forge 1 11976
Protoss_Cybernetics_Core 1 13834
Protoss_Photon_Cannon 1 13649
13834
