Protoss_Forge 1 3760
Protoss_Nexus 1 7904
Protoss_Photon_Cannon 3 14290
Protoss_Gateway 2 13555
Protoss_Assimilator 3 12371
Protoss_Cybernetics_Core 1 9075
Protoss_Zealot 6 14876
Protoss_Dragoon 1 10365
Protoss_Stargate 1 10853
Protoss_Citadel_of_Adun 1 11098
Protoss_Corsair 4 14554
Protoss_Templar_Archives 1 13391
Protoss_Dark_Templar 1 15001
15001
