Protoss_Forge 1 4826
Protoss_Photon_Cannon 4 15797
Protoss_Nexus 1 8819
Protoss_Gateway 2 13346
Protoss_Assimilator 2 11127
Protoss_Cybernetics_Core 1 9387
Protoss_Zealot 6 14891
Protoss_Stargate 1 11539
Protoss_Citadel_of_Adun 1 12367
Protoss_Corsair 1 12503
Protoss_Templar_Archives 1 14769
15797
