Protoss_Forge 1 4031
Protoss_Nexus 1 7515
Protoss_Photon_Cannon 1 6300
Protoss_Gateway 4 14840
Protoss_Assimilator 2 10712
Protoss_Zealot 11 15560
Protoss_Cybernetics_Core 1 9931
Protoss_Stargate 1 11669
Protoss_Citadel_of_Adun 1 12049
Protoss_Corsair 1 12608
15560
