Protoss_Forge 1 4748
Protoss_Nexus 1 7661
Protoss_Photon_Cannon 3 15613
Protoss_Gateway 1 7796
Protoss_Assimilator 2 10428
Protoss_Cybernetics_Core 1 9345
Protoss_Zealot 6 14331
Protoss_Stargate 1 11094
Protoss_Robotics_Facility 1 12920
Protoss_Corsair 4 15127
Protoss_Robotics_Support_Bay 1 13620
Protoss_Shuttle 1 14619
15613
