Protoss_Gateway 1 4135
Protoss_Zealot 4 10248
Protoss_Assimilator 2 14770
Protoss_Cybernetics_Core 1 6662
Protoss_Stargate 1 8380
Protoss_Dragoon 1 8147
Protoss_Forge 1 8800
Protoss_Corsair 4 15380
Protoss_Photon_Cannon 5 15743
Protoss_Nexus 1 14089
Protoss_Robotics_Facility 1 13874
Protoss_Robotics_Support_Bay 1 14748
15743
