Protoss_Forge 1 4739
Protoss_Nexus 1 7593
Protoss_Photon_Cannon 6 15789
Protoss_Gateway 2 14080
Protoss_Assimilator 2 11082
Protoss_Zealot 4 14256
Protoss_Cybernetics_Core 1 10171
Protoss_Stargate 1 11904
Protoss_Citadel_of_Adun 1 12593
Protoss_Corsair 3 15064
Protoss_Dragoon 2 15496
15789
