Protoss_Forge 1 4306
Protoss_Photon_Cannon 3 14227
Protoss_Nexus 1 9005
Protoss_Gateway 3 13978
Protoss_Assimilator 2 10119
Protoss_Cybernetics_Core 1 9608
Protoss_Zealot 4 14235
Protoss_Stargate 1 11342
Protoss_Citadel_of_Adun 1 11949
Protoss_Corsair 2 13814
Protoss_Templar_Archives 1 13404
Protoss_Dark_Templar 1 14659
14659
