Protoss_Forge 1 4792
Protoss_Photon_Cannon 3 15557
Protoss_Nexus 1 8826
Protoss_Gateway 3 13934
Protoss_Assimilator 2 13748
Protoss_Cybernetics_Core 1 9509
Protoss_Zealot 8 15371
Protoss_Stargate 1 11274
Protoss_Dragoon 1 11375
Protoss_Citadel_of_Adun 1 12296
Protoss_Corsair 2 14332
15557
