Protoss_Forge 1 4375
Protoss_Nexus 1 7480
Protoss_Photon_Cannon 5 11076
Protoss_Gateway 1 8408
Protoss_Zealot 5 14919
Protoss_Cybernetics_Core 1 12691
Protoss_Assimilator 2 12611
Protoss_Stargate 2 15586
15586
