Protoss_Forge 1 4644
Protoss_Photon_Cannon 3 14384
Protoss_Nexus 1 9052
Protoss_Gateway 3 12637
Protoss_Assimilator 2 10875
Protoss_Zealot 5 12992
Protoss_Cybernetics_Core 1 9754
Protoss_Citadel_of_Adun 1 11238
Protoss_Stargate 3 15644
Protoss_Dragoon 1 14188
Protoss_Corsair 2 15310
Leg_Enhancements 1 14448
15644
