Protoss_Nexus 1 7217
Protoss_Forge 1 5753
Protoss_Gateway 4 16043
Protoss_Photon_Cannon 3 14776
Protoss_Assimilator 2 10208
Protoss_Zealot 10 14862
Protoss_Cybernetics_Core 1 9652
Protoss_Stargate 1 11443
Protoss_Citadel_of_Adun 1 11750
Protoss_Corsair 1 12558
Protoss_Templar_Archives 1 14379
Protoss_High_Templar 2 15794
16043
