Protoss_Gateway 2 4725
Protoss_Zealot 9 10685
Protoss_Nexus 2 16399
Protoss_Assimilator 1 8973
Protoss_Cybernetics_Core 1 10428
Protoss_Stargate 1 12741
Protoss_Citadel_of_Adun 1 12680
Protoss_Forge 1 12915
Protoss_Corsair 2 15187
Protoss_Templar_Archives 1 14477
Protoss_Photon_Cannon 2 15130
Protoss_Dark_Templar 1 15815
16399
