Protoss_Forge 1 4062
Protoss_Nexus 1 7720
Protoss_Photon_Cannon 2 13091
Protoss_Gateway 2 13979
Protoss_Assimilator 2 12386
Protoss_Zealot 4 15286
Protoss_Cybernetics_Core 1 10032
Protoss_Stargate 1 11867
Protoss_Dragoon 2 14334
Protoss_Citadel_of_Adun 1 12273
Protoss_Corsair 3 15220
Protoss_Templar_Archives 1 14554
15286
