Protoss_Forge 1 4934
Protoss_Nexus 1 7612
Protoss_Photon_Cannon 2 15636
Protoss_Gateway 4 13171
Protoss_Zealot 5 14827
Protoss_Assimilator 2 10931
Protoss_Cybernetics_Core 2 10717
Protoss_Stargate 1 11889
Protoss_Citadel_of_Adun 1 12762
Protoss_Corsair 2 13975
Protoss_Templar_Archives 1 14639
15636
