Protoss_Forge 1 4075
Protoss_Photon_Cannon 4 15433
Protoss_Nexus 1 8838
Protoss_Gateway 2 12855
Protoss_Assimilator 2 10486
Protoss_Cybernetics_Core 1 9308
Protoss_Zealot 4 13311
Protoss_Stargate 1 11065
Protoss_Citadel_of_Adun 1 11809
Protoss_Corsair 2 13893
Protoss_Templar_Archives 1 13469
Protoss_High_Templar 2 15227
15433
