Protoss_Gateway 2 5019
Protoss_Zealot 12 11230
Protoss_Assimilator 1 7510
Protoss_Cybernetics_Core 1 10549
Protoss_Stargate 2 13048
Protoss_Dragoon 2 12350
Protoss_Forge 1 12601
Protoss_Corsair 4 15353
Protoss_Photon_Cannon 2 15311
15353
