Protoss_Forge 1 4529
Protoss_Photon_Cannon 5 14770
Protoss_Nexus 1 9953
Protoss_Gateway 2 13464
Protoss_Assimilator 2 11906
Protoss_Cybernetics_Core 1 10511
Protoss_Zealot 7 15465
Protoss_Stargate 1 12237
Protoss_Citadel_of_Adun 1 12715
Protoss_Corsair 2 15216
Protoss_Templar_Archives 1 15457
15465
