Protoss_Forge 2 13472
Protoss_Nexus 1 7448
Protoss_Photon_Cannon 2 11230
Protoss_Gateway 2 14379
Protoss_Assimilator 2 9790
Protoss_Cybernetics_Core 1 8496
Protoss_Zealot 4 15005
Protoss_Stargate 1 10188
Protoss_Corsair 5 15061
Protoss_Citadel_of_Adun 1 12896
Protoss_Templar_Archives 1 14639
Protoss_Robotics_Facility 1 16428
16428
