Protoss_Forge 1 4224
Protoss_Nexus 1 7811
Protoss_Photon_Cannon 1 6268
Protoss_Gateway 6 15548
Protoss_Assimilator 2 9400
Protoss_Cybernetics_Core 1 8901
Protoss_Zealot 4 12233
Protoss_Citadel_of_Adun 1 10536
Protoss_Templar_Archives 1 12497
Protoss_Dark_Templar 4 14963
Protoss_High_Templar 1 15572
15572
