Protoss_Forge 1 4562
Protoss_Photon_Cannon 2 15373
Protoss_Nexus 1 8443
Protoss_Gateway 4 15440
Protoss_Assimilator 2 10613
Protoss_Zealot 4 12851
Protoss_Cybernetics_Core 1 10226
Protoss_Citadel_of_Adun 1 11969
Protoss_Templar_Archives 1 13498
Protoss_Dark_Templar 4 15809
15809
