Protoss_Forge 1 4044
Protoss_Nexus 1 7468
Protoss_Photon_Cannon 2 13478
Protoss_Gateway 5 15598
Protoss_Assimilator 2 12273
Protoss_Zealot 6 15415
Protoss_Cybernetics_Core 1 9511
Protoss_Stargate 1 11287
Protoss_Citadel_of_Adun 1 11973
Protoss_Corsair 1 12280
Protoss_Templar_Archives 1 13809
Protoss_Dark_Templar 1 15414
15598
