Protoss_Forge 2 14609
Protoss_Nexus 1 7691
Protoss_Photon_Cannon 2 6952
Protoss_Gateway 3 13226
Protoss_Assimilator 2 10609
Protoss_Cybernetics_Core 1 9331
Protoss_Zealot 10 15409
Protoss_Stargate 1 11078
Protoss_Citadel_of_Adun 1 12175
Protoss_Corsair 2 13647
Protoss_Templar_Archives 1 15191
15409
