Protoss_Forge 1 4922
Protoss_Nexus 1 7550
Protoss_Photon_Cannon 3 12496
Protoss_Gateway 6 15885
Protoss_Assimilator 2 9773
Protoss_Cybernetics_Core 1 9266
Protoss_Zealot 8 15547
Protoss_Stargate 1 10979
Protoss_Citadel_of_Adun 1 11945
Protoss_Corsair 2 13788
15885
