Protoss_Forge 1 4956
Protoss_Nexus 1 7433
Protoss_Gateway 4 11898
Protoss_Assimilator 2 11631
Protoss_Photon_Cannon 4 15610
Protoss_Cybernetics_Core 1 8297
Protoss_Zealot 11 15244
Protoss_Citadel_of_Adun 1 11071
Protoss_Dragoon 1 13725
Protoss_Templar_Archives 1 14333
Protoss_Ground_Weapons_1 1 13799
15610
