Protoss_Gateway 2 5129
Protoss_Zealot 15 15447
Protoss_Assimilator 1 10422
Protoss_Nexus 1 12590
Protoss_Forge 1 11354
Protoss_Cybernetics_Core 1 12295
Protoss_Photon_Cannon 4 14657
Protoss_Stargate 1 15332
15447
