Protoss_Nexus 1 7284
Protoss_Forge 1 5835
Protoss_Photon_Cannon 4 15041
Protoss_Gateway 2 13846
Protoss_Assimilator 2 11904
Protoss_Cybernetics_Core 1 9838
Protoss_Zealot 6 14847
Protoss_Stargate 1 11936
Protoss_Citadel_of_Adun 1 12235
Protoss_Corsair 1 12898
Protoss_Templar_Archives 1 15851
15851
