Protoss_Forge 1 4650
Protoss_Nexus 1 7483
Protoss_Photon_Cannon 2 14722
Protoss_Gateway 2 13059
Protoss_Assimilator 2 9809
Protoss_Cybernetics_Core 1 8519
Protoss_Zealot 4 11868
Protoss_Stargate 1 10227
Protoss_Citadel_of_Adun 1 10861
Protoss_Corsair 4 15427
Protoss_Templar_Archives 1 12446
Protoss_Dark_Templar 2 14504
Protoss_High_Templar 1 15604
15604
