Protoss_Forge 1 4899
Protoss_Nexus 1 7638
Protoss_Photon_Cannon 2 6873
Protoss_Gateway 4 12974
Protoss_Assimilator 2 14524
Protoss_Cybernetics_Core 1 9640
Protoss_Zealot 15 15424
Protoss_Stargate 1 11349
Protoss_Citadel_of_Adun 1 11756
Protoss_Corsair 1 12298
Protoss_Templar_Archives 1 15391
15424
