Protoss_Forge 1 3986
Protoss_Photon_Cannon 6 15812
Protoss_Nexus 1 9098
Protoss_Gateway 1 8139
Protoss_Assimilator 2 11459
Protoss_Zealot 3 14876
Protoss_Cybernetics_Core 1 9983
Protoss_Stargate 1 11776
Protoss_Corsair 2 14528
Protoss_Robotics_Facility 1 14429
Protoss_Robotics_Support_Bay 1 15142
15812
