Protoss_Forge 1 5013
Protoss_Nexus 1 8100
Protoss_Photon_Cannon 3 15468
Protoss_Gateway 2 12450
Protoss_Assimilator 2 10272
Protoss_Cybernetics_Core 1 9533
Protoss_Zealot 5 14107
Protoss_Stargate 1 11330
Protoss_Citadel_of_Adun 1 12018
Protoss_Corsair 1 12353
Protoss_Templar_Archives 1 13492
Protoss_High_Templar 2 15227
15468
