Protoss_Forge 1 4750
Protoss_Nexus 1 7661
Protoss_Photon_Cannon 5 15710
Protoss_Gateway 4 14241
Protoss_Assimilator 2 11595
Protoss_Zealot 6 14964
Protoss_Cybernetics_Core 1 10183
Protoss_Stargate 1 11876
Protoss_Citadel_of_Adun 1 12832
Protoss_Corsair 1 12825
15710
