Protoss_Forge 1 4316
Protoss_Photon_Cannon 3 14186
Protoss_Nexus 1 8531
Protoss_Gateway 2 13227
Protoss_Assimilator 2 10239
Protoss_Cybernetics_Core 1 9353
Protoss_Zealot 3 13217
Protoss_Stargate 1 11157
Protoss_Citadel_of_Adun 1 11907
Protoss_Dragoon 1 12069
Protoss_Corsair 4 15260
Protoss_Templar_Archives 1 13457
Protoss_Dark_Templar 2 14867
15260
