Protoss_Forge 1 4524
Protoss_Nexus 1 7773
Protoss_Photon_Cannon 2 15294
Protoss_Gateway 3 13132
Protoss_Assimilator 2 11480
Protoss_Cybernetics_Core 1 8774
Protoss_Zealot 11 15421
Protoss_Stargate 1 10569
Protoss_Dragoon 1 10523
Protoss_Citadel_of_Adun 1 11174
Protoss_Corsair 2 12872
Leg_Enhancements 1 14109
15421
