Protoss_Forge 1 4060
Protoss_Photon_Cannon 5 15636
Protoss_Nexus 1 8436
Protoss_Gateway 4 16060
Protoss_Assimilator 2 10820
Protoss_Cybernetics_Core 1 8851
Protoss_Zealot 8 15342
Protoss_Stargate 1 10718
Protoss_Citadel_of_Adun 1 11746
Protoss_Corsair 2 12807
Protoss_Templar_Archives 1 14339
16060
