Protoss_Forge 1 4343
Protoss_Nexus 1 7664
Protoss_Photon_Cannon 3 13257
Protoss_Assimilator 2 11232
Protoss_Gateway 3 15102
Protoss_Cybernetics_Core 1 10073
Protoss_Zealot 7 15362
Protoss_Stargate 1 11826
Protoss_Citadel_of_Adun 1 12677
Protoss_Corsair 3 15093
Protoss_Templar_Archives 1 15409
15409
