Protoss_Gateway 2 4960
Protoss_Zealot 7 12754
Protoss_Nexus 2 17007
Protoss_Assimilator 1 7668
Protoss_Cybernetics_Core 1 9055
Protoss_Stargate 1 11040
Protoss_Dragoon 1 10910
Protoss_Corsair 2 12956
Protoss_Forge 1 13220
Protoss_Photon_Cannon 2 14632
Protoss_Citadel_of_Adun 1 14808
17007
