Protoss_Forge 1 4082
Protoss_Photon_Cannon 5 15102
Protoss_Nexus 1 8604
Protoss_Gateway 1 7685
Protoss_Assimilator 2 11437
Protoss_Zealot 6 15172
Protoss_Cybernetics_Core 2 11153
Protoss_Dragoon 1 12431
Protoss_Stargate 1 13306
Protoss_Citadel_of_Adun 1 14329
Protoss_Corsair 2 15172
15172
