Protoss_Gateway 3 14708
Protoss_Assimilator 1 4315
Protoss_Zealot 6 12430
Protoss_Cybernetics_Core 1 6634
Protoss_Stargate 1 8396
Protoss_Citadel_of_Adun 1 9131
Protoss_Corsair 1 9825
Protoss_Dragoon 1 10157
Protoss_Templar_Archives 1 12209
Protoss_Dark_Templar 2 13766
Protoss_Forge 1 14350
Protoss_High_Templar 1 15402
Leg_Enhancements 1 14337
15402
