Protoss_Nexus 1 6991
Protoss_Forge 1 5957
Protoss_Gateway 1 7706
Protoss_Photon_Cannon 3 14909
Protoss_Assimilator 2 9209
Protoss_Zealot 5 15029
Protoss_Cybernetics_Core 1 9624
Protoss_Stargate 2 12903
Protoss_Robotics_Facility 1 12456
Protoss_Corsair 5 15512
Protoss_Citadel_of_Adun 1 13546
Protoss_Shuttle 1 13893
Protoss_Robotics_Support_Bay 1 13387
Protoss_Reaver 1 15632
15632
