Protoss_Gateway 1 4223
Protoss_Assimilator 1 4230
Protoss_Cybernetics_Core 1 5868
Protoss_Zealot 4 10144
Protoss_Dragoon 1 7067
Protoss_Stargate 1 7733
Protoss_Corsair 4 15017
Protoss_Robotics_Facility 1 11445
Protoss_Forge 2 12747
Protoss_Shuttle 1 12848
Protoss_Photon_Cannon 2 14439
Protoss_Robotics_Support_Bay 1 13491
Protoss_Reaver 1 15346
15346
