Protoss_Forge 1 4836
Protoss_Photon_Cannon 4 13869
Protoss_Nexus 1 9161
Protoss_Gateway 2 14998
Protoss_Assimilator 2 10306
Protoss_Zealot 2 13311
Protoss_Cybernetics_Core 1 10331
Protoss_Stargate 2 12880
Protoss_Citadel_of_Adun 1 12956
Protoss_Corsair 5 15547
Protoss_Templar_Archives 1 15241
15547
