Protoss_Forge 1 4524
Protoss_Nexus 2 13626
Protoss_Photon_Cannon 2 6818
Protoss_Gateway 1 7673
Protoss_Assimilator 2 12345
Protoss_Cybernetics_Core 1 9331
Protoss_Zealot 6 15541
Protoss_Stargate 1 11030
Protoss_Corsair 4 15479
Protoss_Robotics_Facility 1 14269
Protoss_Shuttle 1 15716
Protoss_Robotics_Support_Bay 1 15219
15716
