Protoss_Gateway 2 5074
Protoss_Zealot 15 13056
Protoss_Assimilator 1 8344
Protoss_Cybernetics_Core 1 10122
Protoss_Stargate 1 12233
Protoss_Forge 1 12481
Protoss_Corsair 2 14508
Protoss_Photon_Cannon 1 13904
Protoss_Robotics_Facility 1 15076
Protoss_Citadel_of_Adun 1 15880
15880
