Protoss_Forge 1 4536
Protoss_Nexus 1 7740
Protoss_Photon_Cannon 2 15134
Protoss_Gateway 3 16025
Protoss_Assimilator 2 13237
Protoss_Cybernetics_Core 1 9327
Protoss_Zealot 10 14704
Protoss_Stargate 1 11219
Protoss_Citadel_of_Adun 1 12156
Protoss_Corsair 1 12351
Protoss_Templar_Archives 1 14919
16025
