Protoss_Forge 1 4602
Protoss_Photon_Cannon 3 12364
Protoss_Nexus 1 8752
Protoss_Gateway 3 14862
Protoss_Assimilator 2 13849
Protoss_Cybernetics_Core 1 9588
Protoss_Zealot 7 15099
Protoss_Stargate 1 11456
Protoss_Corsair 1 12535
Protoss_Citadel_of_Adun 1 13536
15099
