Protoss_Forge 1 5402
Protoss_Photon_Cannon 5 15516
Protoss_Nexus 1 8727
Protoss_Gateway 2 10328
Protoss_Assimilator 2 13229
Protoss_Cybernetics_Core 1 9845
Protoss_Zealot 11 15263
Protoss_Citadel_of_Adun 1 11423
Protoss_Stargate 2 14724
15516
