Protoss_Forge 1 5105
Protoss_Nexus 1 7664
Protoss_Photon_Cannon 2 7450
Protoss_Gateway 3 12778
Protoss_Assimilator 2 8898
Protoss_Zealot 10 14868
Protoss_Cybernetics_Core 1 10261
Protoss_Citadel_of_Adun 1 11712
Protoss_Templar_Archives 1 14134
Protoss_High_Templar 2 15373
15373
