Protoss_Forge 1 4255
Protoss_Photon_Cannon 2 6314
Protoss_Nexus 2 17250
Protoss_Gateway 3 15308
Protoss_Assimilator 2 9905
Protoss_Cybernetics_Core 1 9523
Protoss_Zealot 3 13685
Protoss_Stargate 1 11380
Protoss_Dragoon 1 11027
Protoss_Citadel_of_Adun 1 12160
Protoss_Corsair 3 14944
Protoss_Templar_Archives 1 13748
Protoss_Dark_Templar 2 15745
17250
