Protoss_Forge 1 4447
Protoss_Photon_Cannon 3 15511
Protoss_Nexus 1 8402
Protoss_Gateway 1 7400
Protoss_Assimilator 2 13474
Protoss_Zealot 4 14923
Protoss_Cybernetics_Core 1 11604
Protoss_Dragoon 1 13078
Protoss_Stargate 1 13601
Protoss_Citadel_of_Adun 1 14922
Protoss_Corsair 2 15509
15511
