Protoss_Forge 1 4973
Protoss_Nexus 1 7846
Protoss_Photon_Cannon 7 12569
Protoss_Gateway 4 14985
Protoss_Assimilator 2 13338
Protoss_Cybernetics_Core 1 12008
Protoss_Zealot 3 14756
Protoss_Stargate 1 13734
Protoss_Citadel_of_Adun 1 14127
Protoss_Corsair 1 14871
14985
