Protoss_Forge 1 4384
Protoss_Photon_Cannon 4 15159
Protoss_Nexus 1 8630
Protoss_Gateway 2 12974
Protoss_Assimilator 2 10536
Protoss_Cybernetics_Core 1 9245
Protoss_Zealot 3 10984
Protoss_Stargate 1 10966
Protoss_Citadel_of_Adun 1 11903
Protoss_Corsair 3 15514
Protoss_Templar_Archives 1 13763
Protoss_Dragoon 2 14788
Protoss_High_Templar 1 15572
15572
