Protoss_Forge 1 4875
Protoss_Photon_Cannon 3 15221
Protoss_Nexus 1 8762
Protoss_Gateway 3 13597
Protoss_Assimilator 2 10071
Protoss_Cybernetics_Core 1 10098
Protoss_Zealot 10 15526
Protoss_Stargate 1 11952
Protoss_Citadel_of_Adun 1 12286
Protoss_Corsair 2 13799
15526
