Protoss_Gateway 2 4764
Protoss_Zealot 7 7911
Protoss_Nexus 1 11376
Protoss_Assimilator 1 9940
Protoss_Forge 1 10441
Protoss_Cybernetics_Core 1 11963
Protoss_Photon_Cannon 3 14561
Protoss_Dragoon 4 14305
Protoss_Stargate 1 13775
Protoss_Corsair 1 14721
14721
