Protoss_Forge 1 4252
Protoss_Photon_Cannon 2 12868
Protoss_Nexus 1 8092
Protoss_Gateway 3 15936
Protoss_Assimilator 2 10144
Protoss_Zealot 11 15547
Protoss_Cybernetics_Core 1 9424
Protoss_Citadel_of_Adun 1 11139
Protoss_Stargate 1 14602
Protoss_Templar_Archives 1 14493
Leg_Enhancements 1 14071
Protoss_Ground_Weapons_1 1 14595
15936
