Protoss_Forge 1 4774
Protoss_Nexus 1 7761
Protoss_Photon_Cannon 3 15287
Protoss_Gateway 3 15898
Protoss_Assimilator 2 11314
Protoss_Zealot 5 15026
Protoss_Cybernetics_Core 1 9708
Protoss_Stargate 1 12372
Protoss_Citadel_of_Adun 1 13272
Protoss_Dragoon 1 13283
Protoss_Corsair 3 15535
15898
