Protoss_Forge 1 4679
Protoss_Photon_Cannon 4 14921
Protoss_Nexus 1 8750
Protoss_Gateway 2 12708
Protoss_Assimilator 2 10030
Protoss_Zealot 6 14189
Protoss_Cybernetics_Core 1 9371
Protoss_Stargate 1 11315
Protoss_Dragoon 1 11193
Protoss_Corsair 3 15017
Protoss_Citadel_of_Adun 1 12817
Protoss_Templar_Archives 1 15710
15710
