Protoss_Forge 2 15569
Protoss_Photon_Cannon 2 6172
Protoss_Nexus 1 8964
Protoss_Gateway 3 13855
Protoss_Assimilator 2 10949
Protoss_Cybernetics_Core 1 9447
Protoss_Zealot 8 15043
Protoss_Stargate 1 11201
Protoss_Corsair 2 14440
Protoss_Citadel_of_Adun 1 13088
15569
