Protoss_Forge 1 4237
Protoss_Photon_Cannon 3 14458
Protoss_Nexus 1 8798
Protoss_Gateway 3 15064
Protoss_Assimilator 2 11970
Protoss_Cybernetics_Core 1 9468
Protoss_Zealot 5 14988
Protoss_Stargate 1 11386
Protoss_Citadel_of_Adun 1 12233
Protoss_Dragoon 1 12508
Protoss_Corsair 3 14792
Protoss_Templar_Archives 1 14584
15064
