Protoss_Forge 1 4277
Protoss_Photon_Cannon 3 14750
Protoss_Nexus 1 8838
Protoss_Gateway 3 14171
Protoss_Assimilator 2 10502
Protoss_Cybernetics_Core 1 9274
Protoss_Zealot 8 15178
Protoss_Stargate 1 11315
Protoss_Dragoon 1 11267
Protoss_Citadel_of_Adun 1 12557
Protoss_Corsair 4 15488
Protoss_Templar_Archives 1 14455
15488
