Protoss_Gateway 2 4905
Protoss_Zealot 9 13785
Protoss_Forge 1 7120
Protoss_Photon_Cannon 6 14966
Protoss_Nexus 1 11738
Protoss_Assimilator 2 15447
Protoss_Cybernetics_Core 1 13379
Protoss_Stargate 1 15606
Protoss_Citadel_of_Adun 1 15732
15732
