Protoss_Forge 1 4752
Protoss_Nexus 1 7574
Protoss_Photon_Cannon 3 14625
Protoss_Gateway 2 15614
Protoss_Assimilator 2 10688
Protoss_Cybernetics_Core 1 9282
Protoss_Zealot 7 15298
Protoss_Stargate 1 11137
Protoss_Corsair 4 14909
Protoss_Citadel_of_Adun 1 13738
15614
