Protoss_Forge 1 3794
Protoss_Photon_Cannon 5 15317
Protoss_Nexus 1 9120
Protoss_Gateway 2 15926
Protoss_Assimilator 1 8377
Protoss_Zealot 3 13035
Protoss_Cybernetics_Core 1 12308
Protoss_Stargate 1 14225
Protoss_Citadel_of_Adun 2 15214
15926
