Protoss_Forge 1 4416
Protoss_Nexus 1 7603
Protoss_Photon_Cannon 2 6789
Protoss_Gateway 3 14745
Protoss_Assimilator 2 10791
Protoss_Cybernetics_Core 1 9877
Protoss_Zealot 5 14830
Protoss_Dragoon 1 11322
Protoss_Stargate 1 11800
Protoss_Citadel_of_Adun 1 12421
Protoss_Corsair 3 15321
Protoss_Templar_Archives 1 14882
15321
