Protoss_Gateway 2 4739
Protoss_Zealot 9 14247
Protoss_Forge 1 8117
Protoss_Nexus 1 10942
Protoss_Assimilator 2 12819
Protoss_Photon_Cannon 2 11122
Protoss_Cybernetics_Core 1 11881
Protoss_Stargate 1 13695
Protoss_Citadel_of_Adun 1 14544
Protoss_Corsair 1 14736
14736
