Protoss_Forge 1 4289
Protoss_Photon_Cannon 2 6191
Protoss_Nexus 1 9142
Protoss_Gateway 3 15201
Protoss_Assimilator 2 10267
Protoss_Cybernetics_Core 1 9561
Protoss_Zealot 6 15573
Protoss_Stargate 1 11245
Protoss_Corsair 4 14929
Protoss_Citadel_of_Adun 1 12851
Protoss_Templar_Archives 1 14990
15573
