Protoss_Forge 1 4297
Protoss_Nexus 1 7714
Protoss_Gateway 4 14307
Protoss_Photon_Cannon 2 14981
Protoss_Assimilator 2 8884
Protoss_Cybernetics_Core 1 8952
Protoss_Zealot 2 11658
Protoss_Stargate 1 10677
Protoss_Citadel_of_Adun 1 10896
Protoss_Dragoon 1 10766
Protoss_Corsair 4 14727
Protoss_Templar_Archives 1 12473
Protoss_Dark_Templar 2 14313
Protoss_High_Templar 2 15818
15818
