Protoss_Forge 1 4103
Protoss_Photon_Cannon 4 13437
Protoss_Nexus 1 9562
Protoss_Gateway 1 8677
Protoss_Assimilator 2 11568
Protoss_Cybernetics_Core 1 10458
Protoss_Zealot 3 12866
Protoss_Stargate 2 13658
Protoss_Dragoon 1 12004
Protoss_Corsair 4 15166
Protoss_Citadel_of_Adun 1 14342
15166
