Protoss_Gateway 2 12271
Protoss_Assimilator 1 4477
Protoss_Zealot 13 15067
Protoss_Cybernetics_Core 1 7003
Protoss_Dragoon 1 8237
Protoss_Stargate 1 9119
Protoss_Citadel_of_Adun 1 9994
Protoss_Corsair 1 10135
Protoss_Forge 1 11442
Protoss_Templar_Archives 1 13065
Leg_Enhancements 1 12932
Protoss_Photon_Cannon 1 14884
Protoss_Nexus 1 16948
Protoss_Dark_Templar 2 15710
16948
