Protoss_Forge 1 4267
Protoss_Nexus 1 7565
Protoss_Photon_Cannon 3 15363
Protoss_Gateway 2 14827
Protoss_Assimilator 2 12075
Protoss_Zealot 4 14092
Protoss_Cybernetics_Core 1 9204
Protoss_Dragoon 1 10523
Protoss_Stargate 1 11936
Protoss_Citadel_of_Adun 1 12795
Protoss_Corsair 3 14792
15363
