Protoss_Forge 1 4946
Protoss_Nexus 1 7702
Protoss_Photon_Cannon 4 15511
Protoss_Gateway 3 13448
Protoss_Assimilator 1 9023
Protoss_Cybernetics_Core 1 10287
Protoss_Zealot 9 15509
Protoss_Citadel_of_Adun 1 12326
15511
