Protoss_Forge 1 4631
Protoss_Photon_Cannon 1 5884
Protoss_Nexus 1 8329
Protoss_Gateway 2 13025
Protoss_Assimilator 2 10593
Protoss_Cybernetics_Core 1 8920
Protoss_Zealot 4 14824
Protoss_Stargate 1 10853
Protoss_Citadel_of_Adun 1 11660
Protoss_Dragoon 1 12200
Protoss_Corsair 3 14985
Protoss_Templar_Archives 1 13908
14985
