Protoss_Forge 1 4328
Protoss_Photon_Cannon 2 6159
Protoss_Nexus 1 8894
Protoss_Gateway 3 13433
Protoss_Assimilator 2 10659
Protoss_Cybernetics_Core 1 9421
Protoss_Zealot 6 14572
Protoss_Stargate 1 11274
Protoss_Citadel_of_Adun 1 11802
Protoss_Dragoon 1 12712
Protoss_Corsair 3 14906
Protoss_Templar_Archives 1 13757
Protoss_Dark_Templar 2 15692
15692
