Protoss_Nexus 1 7042
Protoss_Gateway 6 15709
Protoss_Forge 1 6424
Protoss_Assimilator 2 10376
Protoss_Photon_Cannon 1 7775
Protoss_Cybernetics_Core 1 8654
Protoss_Zealot 4 15201
Protoss_Stargate 1 10686
Protoss_Dragoon 1 10233
Protoss_Citadel_of_Adun 1 11379
Protoss_Corsair 1 11628
Protoss_Templar_Archives 1 13157
Protoss_Dark_Templar 1 14366
Protoss_High_Templar 2 14966
15709
