Protoss_Forge 1 4308
Protoss_Photon_Cannon 6 15467
Protoss_Nexus 1 8693
Protoss_Gateway 3 13337
Protoss_Assimilator 2 11925
Protoss_Cybernetics_Core 1 9201
Protoss_Zealot 6 14332
Protoss_Stargate 1 10993
Protoss_Dragoon 1 10895
Protoss_Citadel_of_Adun 1 11821
Protoss_Corsair 1 12131
Protoss_Templar_Archives 1 14105
Protoss_Dark_Templar 1 15789
Protoss_High_Templar 1 15809
15809
