Protoss_Forge 1 4179
Protoss_Nexus 1 7944
Protoss_Photon_Cannon 3 14496
Protoss_Gateway 2 13442
Protoss_Assimilator 2 10319
Protoss_Cybernetics_Core 1 9585
Protoss_Zealot 3 13978
Protoss_Stargate 1 11444
Protoss_Dragoon 1 11296
Protoss_Citadel_of_Adun 1 12324
Protoss_Corsair 3 14373
Protoss_Templar_Archives 1 13767
Protoss_Dark_Templar 2 15177
15177
