Protoss_Forge 1 4521
Protoss_Nexus 1 8089
Protoss_Photon_Cannon 4 15001
Protoss_Gateway 4 14474
Protoss_Assimilator 2 11802
Protoss_Cybernetics_Core 1 10008
Protoss_Zealot 4 15551
Protoss_Citadel_of_Adun 1 11781
Protoss_Dragoon 2 13877
Protoss_Templar_Archives 1 13495
Protoss_Dark_Templar 1 14978
Protoss_High_Templar 2 15531
15551
