Protoss_Gateway 2 12049
Protoss_Forge 1 4874
Protoss_Zealot 13 15075
Protoss_Photon_Cannon 2 14846
Protoss_Nexus 1 9457
Protoss_Assimilator 2 13770
Protoss_Cybernetics_Core 1 9721
Protoss_Citadel_of_Adun 1 12558
Protoss_Templar_Archives 1 14112
15075
