Protoss_Forge 1 3975
Protoss_Nexus 1 7585
Protoss_Gateway 3 15187
Protoss_Photon_Cannon 4 13520
Protoss_Assimilator 2 11347
Protoss_Zealot 3 13518
Protoss_Cybernetics_Core 1 9049
Protoss_Stargate 1 10910
Protoss_Dragoon 1 11226
Protoss_Corsair 4 15389
Protoss_Robotics_Facility 1 13868
Protoss_Robotics_Support_Bay 1 14791
Protoss_Observatory 1 14982
15389
