Protoss_Nexus 1 7070
Protoss_Forge 1 5666
Protoss_Gateway 1 6588
Protoss_Photon_Cannon 4 14501
Protoss_Assimilator 1 7496
Protoss_Cybernetics_Core 1 8546
Protoss_Zealot 3 13706
Protoss_Stargate 1 11339
Protoss_Dragoon 1 12771
Protoss_Corsair 3 14748
Protoss_Citadel_of_Adun 1 15880
15880
