Protoss_Gateway 1 4101
Protoss_Assimilator 1 4128
Protoss_Cybernetics_Core 1 5543
Protoss_Zealot 6 14882
Protoss_Dragoon 2 7921
Protoss_Stargate 1 7505
Protoss_Corsair 4 13764
Protoss_Forge 1 10022
Protoss_Nexus 1 14184
Protoss_Photon_Cannon 4 15663
Protoss_Citadel_of_Adun 1 13896
15663
