Protoss_Forge 1 4354
Protoss_Nexus 1 7637
Protoss_Photon_Cannon 3 15458
Protoss_Gateway 3 13264
Protoss_Assimilator 2 10098
Protoss_Cybernetics_Core 1 9339
Protoss_Zealot 4 13930
Protoss_Stargate 1 11087
Protoss_Citadel_of_Adun 1 11461
Protoss_Corsair 3 14891
Protoss_Dragoon 1 13068
Protoss_Templar_Archives 1 13583
Protoss_Dark_Templar 3 15050
15458
