Protoss_Gateway 2 4867
Protoss_Zealot 11 10270
Protoss_Nexus 1 11187
Protoss_Assimilator 2 13057
Protoss_Forge 1 10789
Protoss_Cybernetics_Core 1 12476
Protoss_Photon_Cannon 3 15707
Protoss_Dragoon 1 13722
Protoss_Stargate 1 14789
Protoss_Citadel_of_Adun 1 15059
15707
