Protoss_Gateway 2 5016
Protoss_Zealot 18 15137
Protoss_Nexus 1 12344
Protoss_Assimilator 1 11652
Protoss_Forge 1 12776
Protoss_Photon_Cannon 2 15721
Protoss_Cybernetics_Core 1 14996
15721
