Protoss_Forge 1 4376
Protoss_Photon_Cannon 2 15370
Protoss_Nexus 1 8490
Protoss_Gateway 2 14246
Protoss_Assimilator 2 10000
Protoss_Cybernetics_Core 1 9020
Protoss_Zealot 2 11212
Protoss_Stargate 1 11113
Protoss_Citadel_of_Adun 1 11755
Protoss_Corsair 2 13668
Protoss_Templar_Archives 1 13567
Protoss_Robotics_Facility 1 14266
Protoss_Dark_Templar 2 15578
Protoss_Shuttle 1 15784
15784
