Protoss_Gateway 2 10309
Protoss_Assimilator 1 4660
Protoss_Zealot 12 14244
Protoss_Cybernetics_Core 1 6974
Protoss_Stargate 1 9018
Protoss_Corsair 1 9965
Protoss_Citadel_of_Adun 1 11102
Protoss_Forge 1 12011
Protoss_Templar_Archives 1 13793
Protoss_Photon_Cannon 2 15543
Protoss_Dark_Templar 1 15338
Leg_Enhancements 1 14185
15543
