Protoss_Forge 1 4044
Protoss_Photon_Cannon 2 7930
Protoss_Nexus 1 8021
Protoss_Gateway 4 15535
Protoss_Assimilator 2 10894
Protoss_Zealot 8 14847
Protoss_Cybernetics_Core 1 10337
Protoss_Stargate 1 12081
Protoss_Citadel_of_Adun 1 12204
Protoss_Corsair 2 13981
Protoss_Templar_Archives 1 14753
15535
