Protoss_Forge 1 4748
Protoss_Photon_Cannon 5 14189
Protoss_Nexus 1 8469
Protoss_Gateway 2 15994
Protoss_Assimilator 2 10650
Protoss_Zealot 9 15125
Protoss_Cybernetics_Core 1 8800
Protoss_Stargate 1 10651
Protoss_Citadel_of_Adun 1 11768
Protoss_Corsair 4 14955
Protoss_Templar_Archives 1 15864
15994
