Protoss_Forge 2 12769
Protoss_Nexus 1 7366
Protoss_Photon_Cannon 6 14139
Protoss_Gateway 4 15210
Protoss_Assimilator 2 9427
Protoss_Cybernetics_Core 1 9027
Protoss_Dragoon 1 10418
Protoss_Citadel_of_Adun 1 11404
Protoss_Zealot 5 14446
Protoss_Templar_Archives 1 13935
Protoss_High_Templar 2 15651
Protoss_Dark_Templar 1 15496
15651
