Protoss_Forge 1 4631
Protoss_Photon_Cannon 4 15474
Protoss_Nexus 1 8422
Protoss_Gateway 3 15266
Protoss_Assimilator 2 12312
Protoss_Cybernetics_Core 1 9489
Protoss_Dragoon 1 10681
Protoss_Stargate 1 11467
Protoss_Citadel_of_Adun 1 11677
Protoss_Zealot 2 12564
Protoss_Corsair 3 15075
Protoss_Templar_Archives 1 13375
Protoss_Dark_Templar 1 14969
15474
