Protoss_Forge 1 4322
Protoss_Nexus 1 7413
Protoss_Gateway 3 14095
Protoss_Photon_Cannon 4 15825
Protoss_Assimilator 2 10229
Protoss_Cybernetics_Core 1 8589
Protoss_Zealot 4 15163
Protoss_Stargate 1 10288
Protoss_Citadel_of_Adun 1 11212
Protoss_Corsair 4 15140
Protoss_Templar_Archives 1 12797
Protoss_Dark_Templar 1 14030
Protoss_High_Templar 1 14050
15825
