Protoss_Forge 1 4271
Protoss_Nexus 1 7389
Protoss_Photon_Cannon 3 13472
Protoss_Gateway 4 15367
Protoss_Assimilator 2 10113
Protoss_Cybernetics_Core 1 9917
Protoss_Zealot 7 15304
Protoss_Stargate 1 11664
Protoss_Citadel_of_Adun 1 11832
Protoss_Corsair 2 13747
15367
