Protoss_Gateway 4 14459
Protoss_Zealot 10 14841
Protoss_Forge 1 5470
Protoss_Nexus 1 9270
Protoss_Photon_Cannon 4 15729
Protoss_Assimilator 2 11092
Protoss_Cybernetics_Core 1 9823
Protoss_Stargate 1 11645
Protoss_Citadel_of_Adun 1 12693
Protoss_Corsair 1 12588
Protoss_Templar_Archives 1 14958
15729
