Protoss_Forge 1 4435
Protoss_Nexus 1 7784
Protoss_Gateway 4 12757
Protoss_Photon_Cannon 1 7293
Protoss_Assimilator 2 9608
Protoss_Zealot 4 11314
Protoss_Cybernetics_Core 1 9181
Protoss_Stargate 1 11409
Protoss_Corsair 2 15228
Protoss_Dragoon 8 15285
Singularity_Charge 1 14337
15285
