Protoss_Forge 1 4414
Protoss_Photon_Cannon 3 15676
Protoss_Nexus 1 8591
Protoss_Gateway 5 14941
Protoss_Assimilator 1 7887
Protoss_Cybernetics_Core 1 9078
Protoss_Zealot 11 15143
Protoss_Citadel_of_Adun 1 10934
Protoss_Templar_Archives 1 13956
Leg_Enhancements 1 14080
15676
