Protoss_Forge 1 4224
Protoss_Nexus 1 7653
Protoss_Photon_Cannon 2 6841
Protoss_Gateway 3 15235
Protoss_Assimilator 2 11124
Protoss_Zealot 6 15134
Protoss_Cybernetics_Core 1 10764
Protoss_Stargate 1 12463
Protoss_Citadel_of_Adun 1 13035
Protoss_Corsair 1 13477
Protoss_Templar_Archives 1 14870
15235
