Protoss_Nexus 1 7339
Protoss_Forge 1 5853
Protoss_Gateway 5 15532
Protoss_Photon_Cannon 5 15707
Protoss_Assimilator 2 11849
Protoss_Zealot 10 15324
Protoss_Cybernetics_Core 1 10034
Protoss_Citadel_of_Adun 1 11648
Protoss_Stargate 1 12022
Protoss_Corsair 1 13211
Leg_Enhancements 1 14606
15707
