Protoss_Forge 1 4243
Protoss_Photon_Cannon 6 15503
Protoss_Nexus 1 8630
Protoss_Gateway 4 15251
Protoss_Assimilator 2 11252
Protoss_Cybernetics_Core 1 9462
Protoss_Zealot 3 13533
Protoss_Stargate 1 11296
Protoss_Corsair 1 12286
Protoss_Citadel_of_Adun 1 13024
Protoss_Templar_Archives 1 14484
Protoss_High_Templar 2 15710
15710
