Protoss_Forge 1 4327
Protoss_Nexus 1 7852
Protoss_Photon_Cannon 5 15273
Protoss_Gateway 4 13729
Protoss_Assimilator 2 11866
Protoss_Cybernetics_Core 1 9779
Protoss_Zealot 7 15394
Protoss_Citadel_of_Adun 1 11449
Protoss_Dragoon 1 12358
Protoss_Templar_Archives 1 13141
Protoss_High_Templar 2 14837
Protoss_Dark_Templar 2 15601
15601
