Protoss_Gateway 2 9539
Protoss_Assimilator 1 4409
Protoss_Zealot 7 14107
Protoss_Cybernetics_Core 1 6724
Protoss_Dragoon 6 15279
Protoss_Robotics_Facility 1 8981
Protoss_Shuttle 1 10375
Protoss_Robotics_Support_Bay 1 10067
Protoss_Reaver 2 14298
15279
