Protoss_Forge 1 4287
Protoss_Nexus 1 7597
Protoss_Gateway 4 16021
Protoss_Photon_Cannon 8 15611
Protoss_Assimilator 2 14616
Protoss_Cybernetics_Core 1 8512
Protoss_Zealot 12 14929
Protoss_Citadel_of_Adun 1 11243
Protoss_Templar_Archives 1 13278
Protoss_Ground_Weapons_1 1 14451
Leg_Enhancements 1 14454
16021
