Protoss_Forge 1 4688
Protoss_Photon_Cannon 8 15686
Protoss_Nexus 1 8917
Protoss_Gateway 1 7691
Protoss_Assimilator 2 13387
Protoss_Zealot 3 12956
Protoss_Cybernetics_Core 1 11622
Protoss_Stargate 1 13399
Protoss_Corsair 1 14426
Protoss_Citadel_of_Adun 1 15689
15689
