Protoss_Forge 1 4211
Protoss_Nexus 1 7660
Protoss_Photon_Cannon 2 6952
Protoss_Gateway 2 11415
Protoss_Assimilator 2 10681
Protoss_Zealot 11 15380
Protoss_Cybernetics_Core 1 9769
Protoss_Stargate 1 12183
Protoss_Citadel_of_Adun 1 12399
Protoss_Corsair 1 13188
15380
