Protoss_Forge 1 4378
Protoss_Photon_Cannon 2 6604
Protoss_Nexus 1 8731
Protoss_Gateway 4 15333
Protoss_Assimilator 2 9683
Protoss_Cybernetics_Core 1 9301
Protoss_Zealot 8 15067
Protoss_Stargate 1 11151
Protoss_Citadel_of_Adun 1 11961
Protoss_Corsair 2 13117
Protoss_Templar_Archives 1 14910
15333
