Protoss_Forge 1 4378
Protoss_Photon_Cannon 3 14935
Protoss_Nexus 1 8740
Protoss_Gateway 4 15807
Protoss_Assimilator 2 9816
Protoss_Cybernetics_Core 1 9479
Protoss_Zealot 7 14809
Protoss_Stargate 1 11252
Protoss_Citadel_of_Adun 1 12112
Protoss_Corsair 1 12233
Protoss_Templar_Archives 1 14515
15807
