Protoss_Forge 1 4302
Protoss_Photon_Cannon 1 5556
Protoss_Nexus 1 8450
Protoss_Gateway 4 14038
Protoss_Assimilator 2 8541
Protoss_Zealot 2 9994
Protoss_Cybernetics_Core 1 9424
Protoss_Dragoon 11 15736
Singularity_Charge 1 13081
Protoss_Stargate 1 15012
15736
