Protoss_Forge 1 4723
Protoss_Photon_Cannon 3 15218
Protoss_Nexus 1 8844
Protoss_Gateway 2 15614
Protoss_Assimilator 2 10862
Protoss_Cybernetics_Core 1 9667
Protoss_Zealot 7 15570
Protoss_Stargate 1 11371
Protoss_Citadel_of_Adun 1 12936
Protoss_Corsair 4 15430
Protoss_Templar_Archives 1 14657
15614
