Protoss_Forge 1 4669
Protoss_Nexus 1 7503
Protoss_Photon_Cannon 4 15350
Protoss_Gateway 1 7641
Protoss_Assimilator 2 11430
Protoss_Cybernetics_Core 1 9949
Protoss_Stargate 1 11690
Protoss_Zealot 3 15272
Protoss_Citadel_of_Adun 1 13068
Protoss_Corsair 4 15544
15544
