Protoss_Gateway 2 15140
Protoss_Assimilator 1 4546
Protoss_Zealot 3 10009
Protoss_Cybernetics_Core 1 6879
Protoss_Stargate 1 8870
Protoss_Citadel_of_Adun 1 8832
Protoss_Dragoon 1 8928
Protoss_Corsair 1 9810
Protoss_Templar_Archives 1 10455
Protoss_Forge 1 10492
Protoss_Dark_Templar 1 12174
Protoss_Photon_Cannon 4 15468
Protoss_High_Templar 2 14785
Protoss_Nexus 1 15985
Psionic_Storm 1 14533
15985
