Protoss_Forge 1 4126
Protoss_Photon_Cannon 3 15247
Protoss_Nexus 1 8548
Protoss_Gateway 4 13647
Protoss_Assimilator 2 10638
Protoss_Zealot 10 15324
Protoss_Cybernetics_Core 1 9304
Protoss_Stargate 1 11107
Protoss_Citadel_of_Adun 1 11461
Protoss_Templar_Archives 1 14714
15324
