Protoss_Forge 1 4030
Protoss_Nexus 1 8191
Protoss_Gateway 2 14949
Protoss_Photon_Cannon 8 15797
Protoss_Assimilator 2 11309
Protoss_Cybernetics_Core 1 9271
Protoss_Zealot 3 11525
Protoss_Stargate 1 11046
Protoss_Citadel_of_Adun 1 11594
Protoss_Corsair 3 14537
Protoss_Templar_Archives 1 13387
Protoss_Dark_Templar 1 14653
15797
