Protoss_Forge 1 4097
Protoss_Photon_Cannon 2 13760
Protoss_Nexus 1 8396
Protoss_Gateway 4 15523
Protoss_Assimilator 2 10021
Protoss_Cybernetics_Core 1 8838
Protoss_Zealot 7 14584
Protoss_Stargate 1 10522
Protoss_Dragoon 1 10476
Protoss_Citadel_of_Adun 1 11769
Protoss_Corsair 2 12697
Protoss_Templar_Archives 1 14450
15523
