Protoss_Forge 1 3672
Protoss_Photon_Cannon 2 7828
Protoss_Nexus 1 9237
Protoss_Gateway 2 14333
Protoss_Assimilator 2 12415
Protoss_Cybernetics_Core 1 10135
Protoss_Zealot 4 13521
Protoss_Stargate 1 11851
Protoss_Citadel_of_Adun 1 11831
Protoss_Corsair 1 13082
Protoss_Templar_Archives 1 13946
Protoss_Robotics_Facility 1 15395
Protoss_Dark_Templar 2 15616
15616
