Protoss_Forge 1 4927
Protoss_Photon_Cannon 3 15511
Protoss_Nexus 1 8197
Protoss_Assimilator 2 11879
Protoss_Gateway 3 14802
Protoss_Zealot 12 15283
Protoss_Cybernetics_Core 1 9681
Protoss_Stargate 1 11448
Protoss_Citadel_of_Adun 1 12239
Protoss_Corsair 3 14704
15511
