Protoss_Forge 1 4239
Protoss_Photon_Cannon 2 15620
Protoss_Nexus 1 8907
Protoss_Gateway 3 14306
Protoss_Assimilator 2 11309
Protoss_Cybernetics_Core 1 9277
Protoss_Zealot 8 15550
Protoss_Stargate 1 11090
Protoss_Citadel_of_Adun 1 11985
Protoss_Corsair 2 13071
Protoss_Templar_Archives 1 13761
Protoss_Dark_Templar 2 15771
15771
