Protoss_Forge 2 6312
Protoss_Nexus 1 7569
Protoss_Gateway 3 13716
Protoss_Photon_Cannon 2 11700
Protoss_Assimilator 2 10344
Protoss_Zealot 9 15427
Protoss_Cybernetics_Core 1 9686
Protoss_Stargate 1 11418
Protoss_Corsair 2 14057
Protoss_Dragoon 1 12800
Protoss_Citadel_of_Adun 1 13088
Protoss_Templar_Archives 1 15225
15427
