Protoss_Forge 1 4375
Protoss_Photon_Cannon 3 15227
Protoss_Nexus 1 9049
Protoss_Gateway 2 9456
Protoss_Assimilator 2 12473
Protoss_Zealot 9 13899
Protoss_Cybernetics_Core 1 11468
Protoss_Stargate 1 13345
Protoss_Citadel_of_Adun 1 13539
Protoss_Corsair 1 14578
Protoss_Templar_Archives 1 15179
Protoss_Dragoon 2 15045
15227
