Protoss_Forge 1 4433
Protoss_Photon_Cannon 5 9985
Protoss_Nexus 1 10906
Protoss_Gateway 3 15794
Protoss_Assimilator 2 12494
Protoss_Zealot 4 15093
Protoss_Cybernetics_Core 1 11783
Protoss_Dragoon 1 13330
Protoss_Robotics_Facility 1 14283
Protoss_Citadel_of_Adun 1 15008
Protoss_Shuttle 1 15693
Protoss_Robotics_Support_Bay 1 15194
15794
