Protoss_Forge 1 3794
Protoss_Photon_Cannon 3 6036
Protoss_Nexus 1 9666
Protoss_Gateway 2 15921
Protoss_Assimilator 1 10343
Protoss_Zealot 2 13884
Protoss_Cybernetics_Core 1 12836
Protoss_Stargate 1 14523
Protoss_Citadel_of_Adun 1 15317
Protoss_Dragoon 1 15159
Protoss_Corsair 1 15523
15921
