Protoss_Gateway 2 5109
Protoss_Zealot 12 14683
Protoss_Nexus 2 12917
Protoss_Assimilator 1 10709
Protoss_Forge 1 11306
Protoss_Photon_Cannon 5 15458
Protoss_Cybernetics_Core 1 14107
15458
