Protoss_Forge 1 4019
Protoss_Photon_Cannon 5 12619
Protoss_Nexus 1 8305
Protoss_Gateway 5 15523
Protoss_Assimilator 2 14314
Protoss_Zealot 8 15471
Protoss_Cybernetics_Core 1 11186
Protoss_Dragoon 1 12382
Protoss_Citadel_of_Adun 1 13196
15523
