Protoss_Forge 2 5721
Protoss_Nexus 1 7202
Protoss_Gateway 2 12541
Protoss_Photon_Cannon 5 15133
Protoss_Assimilator 2 10056
Protoss_Cybernetics_Core 1 9421
Protoss_Zealot 3 13559
Protoss_Stargate 1 11406
Protoss_Citadel_of_Adun 1 11695
Protoss_Corsair 3 14455
Protoss_Templar_Archives 1 13439
Protoss_High_Templar 1 14723
Protoss_Dark_Templar 1 15314
15314
