Protoss_Forge 1 4344
Protoss_Photon_Cannon 4 15541
Protoss_Nexus 1 8466
Protoss_Gateway 1 7628
Protoss_Assimilator 2 13417
Protoss_Cybernetics_Core 1 9280
Protoss_Zealot 2 12949
Protoss_Stargate 2 13269
Protoss_Scout 3 15487
15541
