Protoss_Gateway 1 4098
Protoss_Forge 1 4455
Protoss_Zealot 5 15236
Protoss_Photon_Cannon 8 15723
Protoss_Nexus 1 9385
Protoss_Assimilator 2 11824
Protoss_Cybernetics_Core 1 10021
Protoss_Stargate 1 11849
Protoss_Corsair 3 14906
Protoss_Citadel_of_Adun 1 14311
Protoss_Shield_Battery 1 14674
15723
