Protoss_Gateway 5 15747
Protoss_Forge 1 4493
Protoss_Zealot 4 12131
Protoss_Photon_Cannon 4 15385
Protoss_Nexus 1 9311
Protoss_Assimilator 2 9964
Protoss_Cybernetics_Core 1 9503
Protoss_Citadel_of_Adun 1 11174
Protoss_Templar_Archives 1 13076
Protoss_High_Templar 4 15683
Protoss_Dark_Templar 1 14925
Leg_Enhancements 1 14153
15747
