Protoss_Gateway 2 12424
Protoss_Forge 1 4425
Protoss_Zealot 5 14139
Protoss_Photon_Cannon 3 13166
Protoss_Nexus 1 9698
Protoss_Assimilator 2 11238
Protoss_Cybernetics_Core 1 10498
Protoss_Stargate 1 12183
Protoss_Citadel_of_Adun 1 12614
Protoss_Corsair 1 13630
14139
