Protoss_Gateway 3 12968
Protoss_Forge 1 4454
Protoss_Zealot 6 14253
Protoss_Photon_Cannon 7 14905
Protoss_Nexus 1 9464
Protoss_Assimilator 2 10032
Protoss_Cybernetics_Core 1 10089
Protoss_Citadel_of_Adun 1 11919
Protoss_Templar_Archives 1 15822
15822
