Protoss_Forge 1 4599
Protoss_Photon_Cannon 3 15092
Protoss_Nexus 1 7822
Protoss_Gateway 3 15983
Protoss_Assimilator 2 11938
Protoss_Zealot 6 14906
Protoss_Cybernetics_Core 1 9623
Protoss_Stargate 1 11631
Protoss_Dragoon 1 11682
Protoss_Citadel_of_Adun 1 12460
Protoss_Corsair 1 13474
Protoss_Templar_Archives 1 14420
15983
