Protoss_Forge 1 4289
Protoss_Nexus 1 7574
Protoss_Photon_Cannon 2 9585
Protoss_Gateway 3 14351
Protoss_Assimilator 1 7085
Protoss_Zealot 8 15520
Protoss_Cybernetics_Core 1 11651
Protoss_Stargate 1 13386
Protoss_Citadel_of_Adun 1 13407
Protoss_Corsair 1 14414
15520
