Protoss_Forge 1 5077
Protoss_Nexus 1 7923
Protoss_Photon_Cannon 6 15385
Protoss_Gateway 2 14007
Protoss_Assimilator 2 11098
Protoss_Zealot 7 14859
Protoss_Cybernetics_Core 1 10054
Protoss_Stargate 1 11886
Protoss_Citadel_of_Adun 1 11973
Protoss_Corsair 2 14025
Protoss_Templar_Archives 1 13947
Protoss_Dark_Templar 2 15671
15671
