Protoss_Forge 1 3757
Protoss_Photon_Cannon 5 13465
Protoss_Nexus 1 8539
Protoss_Gateway 3 15694
Protoss_Assimilator 2 10289
Protoss_Zealot 3 13296
Protoss_Cybernetics_Core 1 9978
Protoss_Dragoon 2 15551
Protoss_Stargate 1 11857
Protoss_Citadel_of_Adun 1 13117
Protoss_Corsair 4 15520
Protoss_Templar_Archives 1 14718
15694
