Protoss_Gateway 2 10171
Protoss_Assimilator 1 4666
Protoss_Zealot 8 14010
Protoss_Cybernetics_Core 1 7176
Protoss_Dragoon 1 8510
Protoss_Citadel_of_Adun 1 11010
Protoss_Nexus 1 14206
Protoss_Templar_Archives 1 13220
Protoss_High_Templar 2 15253
Leg_Enhancements 1 14322
15253
