Protoss_Gateway 2 5256
Protoss_Zealot 11 13234
Protoss_Forge 1 7916
Protoss_Assimilator 1 9002
Protoss_Photon_Cannon 1 10652
Protoss_Cybernetics_Core 1 12403
Protoss_Dragoon 1 13614
Protoss_Citadel_of_Adun 1 14619
14619
