Protoss_Gateway 2 11857
Protoss_Forge 1 5016
Protoss_Zealot 7 14774
Protoss_Photon_Cannon 2 10339
Protoss_Nexus 1 11434
Protoss_Assimilator 2 14194
Protoss_Cybernetics_Core 1 12255
Protoss_Dragoon 1 13503
Protoss_Stargate 1 14110
Protoss_Citadel_of_Adun 1 14537
Protoss_Corsair 1 15207
15207
