Protoss_Forge 1 4185
Protoss_Nexus 1 7669
Protoss_Gateway 3 12449
Protoss_Assimilator 2 14680
Protoss_Photon_Cannon 2 14747
Protoss_Zealot 14 15289
Protoss_Cybernetics_Core 1 9052
Protoss_Stargate 1 11229
Protoss_Citadel_of_Adun 1 11629
Protoss_Corsair 1 12195
Protoss_Ground_Weapons_1 1 14360
Protoss_Templar_Archives 1 15807
Leg_Enhancements 1 14557
15807
