Protoss_Forge 1 3910
Protoss_Photon_Cannon 7 15389
Protoss_Nexus 1 8419
Protoss_Gateway 1 7545
Protoss_Assimilator 1 7514
Protoss_Zealot 5 13553
Protoss_Cybernetics_Core 1 9172
Protoss_Stargate 1 11178
Protoss_Corsair 3 14879
Protoss_Citadel_of_Adun 1 12952
15389
