Protoss_Nexus 1 7117
Protoss_Forge 1 5701
Protoss_Photon_Cannon 3 15244
Protoss_Gateway 2 13403
Protoss_Assimilator 2 9763
Protoss_Cybernetics_Core 1 9459
Protoss_Zealot 4 13305
Protoss_Stargate 1 11247
Protoss_Dragoon 1 11161
Protoss_Citadel_of_Adun 1 12078
Protoss_Corsair 4 15245
Protoss_Templar_Archives 1 13552
Protoss_Dark_Templar 2 14799
15245
