Protoss_Gateway 2 4899
Protoss_Zealot 13 12649
Protoss_Forge 1 9469
Protoss_Assimilator 1 11064
Protoss_Photon_Cannon 3 14493
Protoss_Cybernetics_Core 1 12519
Protoss_Stargate 1 14580
Protoss_Citadel_of_Adun 1 15440
Protoss_Corsair 1 15561
15561
