Protoss_Gateway 2 11074
Protoss_Assimilator 1 4536
Protoss_Zealot 7 14183
Protoss_Cybernetics_Core 1 6987
Protoss_Dragoon 1 8788
Protoss_Stargate 1 9588
Protoss_Corsair 1 11373
Protoss_Shield_Battery 1 12256
Protoss_Forge 1 14496
14496
