Protoss_Forge 1 3784
Protoss_Photon_Cannon 4 15452
Protoss_Nexus 1 9334
Protoss_Gateway 1 8355
Protoss_Assimilator 2 10719
Protoss_Zealot 2 10261
Protoss_Cybernetics_Core 1 10063
Protoss_Stargate 2 14725
Protoss_Robotics_Facility 1 13522
Protoss_Corsair 3 15492
Protoss_Robotics_Support_Bay 1 14321
Protoss_Shuttle 1 15157
15492
