Protoss_Forge 1 4176
Protoss_Photon_Cannon 4 13492
Protoss_Nexus 1 9447
Protoss_Gateway 5 16038
Protoss_Assimilator 2 12113
Protoss_Zealot 7 14827
Protoss_Cybernetics_Core 1 10850
Protoss_Citadel_of_Adun 1 12438
Protoss_Templar_Archives 1 14888
16038
