Protoss_Forge 2 14003
Protoss_Photon_Cannon 5 15550
Protoss_Assimilator 2 11654
Protoss_Gateway 1 9782
Protoss_Zealot 1 10766
Protoss_Cybernetics_Core 1 11889
Protoss_Dragoon 1 13156
Protoss_Stargate 1 13664
Protoss_Citadel_of_Adun 1 13924
Protoss_Corsair 1 14658
Protoss_Templar_Archives 1 15870
15870
