Protoss_Forge 1 5140
Protoss_Nexus 1 7751
Protoss_Photon_Cannon 6 15661
Protoss_Gateway 1 8077
Protoss_Assimilator 1 8720
Protoss_Zealot 5 14058
Protoss_Cybernetics_Core 1 13122
Protoss_Robotics_Facility 1 15980
15980
