Protoss_Forge 1 4084
Protoss_Photon_Cannon 5 15594
Protoss_Gateway 1 6267
Protoss_Nexus 1 9318
Protoss_Assimilator 2 9623
Protoss_Cybernetics_Core 1 9089
Protoss_Stargate 2 15135
Protoss_Corsair 4 14794
Protoss_Robotics_Facility 1 14277
Protoss_Shuttle 1 15828
15828
