Protoss_Gateway 3 12261
Protoss_Assimilator 1 4479
Protoss_Zealot 9 13659
Protoss_Cybernetics_Core 1 7212
Protoss_Citadel_of_Adun 1 8809
Protoss_Dragoon 2 15619
Leg_Enhancements 1 11829
Protoss_Templar_Archives 1 13597
Protoss_Forge 1 14199
Protoss_High_Templar 2 14864
Protoss_Photon_Cannon 2 15639
15639
