Protoss_Nexus 1 7020
Protoss_Gateway 4 12173
Protoss_Assimilator 1 6099
Protoss_Forge 1 6554
Protoss_Cybernetics_Core 1 7924
Protoss_Photon_Cannon 1 8006
Protoss_Zealot 15 15374
Protoss_Citadel_of_Adun 1 9671
Protoss_Templar_Archives 1 13918
Leg_Enhancements 1 12645
Protoss_Ground_Weapons_1 1 13043
Protoss_Robotics_Facility 1 15780
Protoss_High_Templar 2 15651
15780
