Protoss_Forge 1 4780
Protoss_Nexus 1 7635
Protoss_Photon_Cannon 3 14303
Protoss_Gateway 3 12618
Protoss_Assimilator 2 10286
Protoss_Cybernetics_Core 1 8894
Protoss_Zealot 5 14712
Protoss_Citadel_of_Adun 1 10454
Protoss_Dragoon 1 10737
Protoss_Templar_Archives 1 12315
Protoss_Dark_Templar 1 13754
Protoss_High_Templar 2 13851
Protoss_Archon 1 14449
Protoss_Robotics_Facility 1 15985
15985
