Protoss_Forge 2 5800
Protoss_Nexus 1 7464
Protoss_Photon_Cannon 3 8915
Protoss_Gateway 4 15547
Protoss_Assimilator 1 10530
Protoss_Zealot 8 14983
Protoss_Cybernetics_Core 1 12185
Protoss_Citadel_of_Adun 1 13937
15547
