Protoss_Gateway 2 4550
Protoss_Zealot 11 10191
Protoss_Nexus 1 13012
Protoss_Assimilator 2 13862
Protoss_Cybernetics_Core 1 12655
Protoss_Forge 1 13106
Protoss_Stargate 1 14476
Protoss_Dragoon 1 14357
Protoss_Photon_Cannon 2 15092
Protoss_Corsair 1 15438
15438
