Protoss_Nexus 2 16392
Protoss_Gateway 3 7106
Protoss_Zealot 9 13147
Protoss_Assimilator 2 11718
Protoss_Forge 1 9598
Protoss_Cybernetics_Core 1 11178
Protoss_Photon_Cannon 4 15573
Protoss_Citadel_of_Adun 1 14491
16392
