Protoss_Forge 1 4141
Protoss_Nexus 1 8010
Protoss_Gateway 2 14338
Protoss_Assimilator 2 10098
Protoss_Photon_Cannon 3 14675
Protoss_Cybernetics_Core 1 9389
Protoss_Zealot 2 15219
Protoss_Stargate 1 11317
Protoss_Robotics_Facility 1 13156
Protoss_Corsair 2 13313
Protoss_Dragoon 1 13631
Protoss_Robotics_Support_Bay 1 13942
Protoss_Reaver 1 15764
15764
