Protoss_Forge 1 4041
Protoss_Photon_Cannon 2 15032
Protoss_Nexus 1 8305
Protoss_Gateway 5 15845
Protoss_Assimilator 2 9665
Protoss_Cybernetics_Core 1 9075
Protoss_Zealot 11 15263
Protoss_Stargate 1 11050
Protoss_Corsair 2 12951
Protoss_Citadel_of_Adun 1 12866
Protoss_Shield_Battery 1 14909
15845
