Protoss_Forge 2 6232
Protoss_Nexus 1 7449
Protoss_Gateway 2 15405
Protoss_Photon_Cannon 6 15025
Protoss_Assimilator 2 9386
Protoss_Cybernetics_Core 1 9036
Protoss_Zealot 3 12817
Protoss_Stargate 1 10884
Protoss_Dragoon 1 10719
Protoss_Robotics_Facility 1 12300
Protoss_Corsair 2 15317
15405
