Protoss_Forge 1 4884
Protoss_Nexus 1 7705
Protoss_Photon_Cannon 1 6569
Protoss_Gateway 4 13013
Protoss_Assimilator 2 15406
Protoss_Zealot 14 15447
Protoss_Cybernetics_Core 1 9475
Protoss_Citadel_of_Adun 1 11039
Protoss_Dragoon 1 13251
Protoss_Templar_Archives 1 15383
Leg_Enhancements 1 14006
15447
