Protoss_Forge 1 3980
Protoss_Nexus 2 15309
Protoss_Assimilator 2 9127
Protoss_Gateway 1 7913
Protoss_Photon_Cannon 7 15620
Protoss_Zealot 1 9143
Protoss_Cybernetics_Core 1 9813
Protoss_Stargate 1 11789
Protoss_Robotics_Facility 1 12728
Protoss_Corsair 1 12798
Protoss_Robotics_Support_Bay 1 13542
Protoss_Reaver 1 15782
15782
