Protoss_Gateway 2 5278
Protoss_Zealot 15 15567
Protoss_Assimilator 1 6005
Protoss_Cybernetics_Core 1 7485
Protoss_Dragoon 1 8780
Protoss_Citadel_of_Adun 1 9225
Protoss_Forge 1 11478
Leg_Enhancements 1 12521
Protoss_Templar_Archives 1 14588
15567
