Protoss_Forge 1 4234
Protoss_Nexus 1 7683
Protoss_Photon_Cannon 8 15712
Protoss_Gateway 4 14970
Protoss_Assimilator 2 9214
Protoss_Cybernetics_Core 1 9112
Protoss_Zealot 5 13341
Protoss_Citadel_of_Adun 1 10744
Protoss_Templar_Archives 1 12760
Protoss_High_Templar 2 14239
Protoss_Archon 1 14923
Protoss_Ground_Weapons_1 1 14533
Leg_Enhancements 1 14614
15712
