Protoss_Gateway 2 4738
Protoss_Zealot 10 9492
Protoss_Nexus 1 12103
Protoss_Assimilator 2 14115
Protoss_Cybernetics_Core 1 11509
Protoss_Forge 1 11543
Protoss_Stargate 1 13371
Protoss_Photon_Cannon 3 15691
Protoss_Citadel_of_Adun 1 14508
Protoss_Corsair 1 14578
15691
