Protoss_Forge 1 4047
Protoss_Photon_Cannon 6 15803
Protoss_Gateway 4 15561
Protoss_Nexus 1 10625
Protoss_Zealot 3 10830
Protoss_Assimilator 2 13297
Protoss_Cybernetics_Core 1 11971
Protoss_Citadel_of_Adun 1 13426
Protoss_Templar_Archives 1 14910
15803
