Protoss_Gateway 2 5010
Protoss_Zealot 9 15289
Protoss_Assimilator 2 15517
Protoss_Nexus 1 12295
Protoss_Forge 2 11331
Protoss_Cybernetics_Core 1 12230
Protoss_Photon_Cannon 2 14518
Protoss_Citadel_of_Adun 1 13771
15517
