Protoss_Forge 1 4192
Protoss_Photon_Cannon 5 14654
Protoss_Nexus 1 9769
Protoss_Gateway 2 14341
Protoss_Assimilator 2 12579
Protoss_Cybernetics_Core 1 10698
Protoss_Zealot 2 11329
Protoss_Stargate 1 12464
Protoss_Citadel_of_Adun 1 12702
Protoss_Corsair 3 15488
Protoss_Templar_Archives 1 14585
15488
