Protoss_Forge 1 3845
Protoss_Nexus 1 7682
Protoss_Photon_Cannon 5 15120
Protoss_Assimilator 2 12986
Protoss_Gateway 4 15570
Protoss_Cybernetics_Core 1 10294
Protoss_Zealot 9 14432
Protoss_Citadel_of_Adun 1 11873
Protoss_Templar_Archives 1 14455
Protoss_High_Templar 1 15724
15724
