Protoss_Gateway 2 4653
Protoss_Zealot 9 9671
Protoss_Forge 1 7271
Protoss_Photon_Cannon 3 15193
Protoss_Nexus 2 14510
Protoss_Assimilator 2 14780
Protoss_Cybernetics_Core 1 14281
15193
