Protoss_Gateway 4 15792
Protoss_Zealot 14 15046
Protoss_Nexus 1 10755
Protoss_Forge 1 9409
Protoss_Assimilator 1 9876
Protoss_Photon_Cannon 1 10664
Protoss_Cybernetics_Core 1 11546
Protoss_Citadel_of_Adun 1 13299
15792
