Protoss_Forge 1 4305
Protoss_Nexus 1 7961
Protoss_Gateway 5 14480
Protoss_Photon_Cannon 3 15787
Protoss_Assimilator 2 10767
Protoss_Zealot 12 15267
Protoss_Cybernetics_Core 1 10161
Protoss_Citadel_of_Adun 1 11922
Protoss_Templar_Archives 1 15525
15787
