Protoss_Forge 1 4135
Protoss_Photon_Cannon 3 15013
Protoss_Nexus 1 8875
Protoss_Gateway 4 13668
Protoss_Assimilator 1 7969
Protoss_Zealot 11 14850
Protoss_Cybernetics_Core 1 9547
Protoss_Citadel_of_Adun 1 11238
Leg_Enhancements 1 14202
15013
