Protoss_Forge 2 12653
Protoss_Photon_Cannon 3 14062
Protoss_Gateway 2 15432
Protoss_Assimilator 1 9185
Protoss_Zealot 3 15456
Protoss_Cybernetics_Core 1 10469
Protoss_Stargate 1 12341
Protoss_Citadel_of_Adun 1 12829
Protoss_Corsair 2 14212
Protoss_Templar_Archives 1 15542
15542
