Protoss_Forge 1 4407
Protoss_Nexus 1 7904
Protoss_Photon_Cannon 7 15721
Protoss_Gateway 4 15435
Protoss_Assimilator 2 10747
Protoss_Cybernetics_Core 1 10305
Protoss_Zealot 7 14446
Protoss_Citadel_of_Adun 1 12105
Protoss_Templar_Archives 1 14417
15721
