Protoss_Nexus 1 7111
Protoss_Forge 1 6061
Protoss_Gateway 4 15724
Protoss_Assimilator 2 9036
Protoss_Photon_Cannon 5 15303
Protoss_Cybernetics_Core 1 9324
Protoss_Zealot 3 13264
Protoss_Stargate 1 11520
Protoss_Citadel_of_Adun 1 11325
Protoss_Dragoon 1 11486
Protoss_Corsair 3 15075
Protoss_Templar_Archives 1 13353
Protoss_Dark_Templar 2 14603
Protoss_High_Templar 2 15704
15724
