Protoss_Forge 1 4179
Protoss_Nexus 1 7401
Protoss_Photon_Cannon 3 15664
Protoss_Gateway 3 13392
Protoss_Assimilator 1 7789
Protoss_Cybernetics_Core 1 9248
Protoss_Zealot 8 14815
Protoss_Dragoon 1 11196
Protoss_Citadel_of_Adun 1 12863
Protoss_Templar_Archives 1 15369
15664
