Protoss_Forge 1 4899
Protoss_Nexus 1 8027
Protoss_Photon_Cannon 2 7178
Protoss_Gateway 2 14061
Protoss_Assimilator 2 12210
Protoss_Zealot 5 15447
Protoss_Cybernetics_Core 1 10638
Protoss_Dragoon 1 12698
Protoss_Citadel_of_Adun 1 13346
Protoss_Stargate 2 14912
15447
