Protoss_Forge 1 4311
Protoss_Photon_Cannon 4 12983
Protoss_Nexus 1 8487
Protoss_Gateway 2 15434
Protoss_Assimilator 2 10287
Protoss_Cybernetics_Core 1 8891
Protoss_Zealot 2 11028
Protoss_Stargate 1 10610
Protoss_Corsair 4 15017
Protoss_Citadel_of_Adun 1 12362
Protoss_Templar_Archives 1 13877
Protoss_Dark_Templar 1 15648
15648
