Protoss_Forge 2 13088
Protoss_Nexus 1 7639
Protoss_Photon_Cannon 3 15055
Protoss_Gateway 4 14727
Protoss_Assimilator 2 10334
Protoss_Cybernetics_Core 1 9997
Protoss_Zealot 5 14326
Protoss_Stargate 1 11778
Protoss_Citadel_of_Adun 1 11993
Protoss_Dragoon 1 12294
Protoss_Corsair 1 12725
Protoss_Templar_Archives 1 13697
15055
