Protoss_Forge 1 4611
Protoss_Photon_Cannon 3 7089
Protoss_Nexus 1 9461
Protoss_Gateway 3 13647
Protoss_Assimilator 3 15017
Protoss_Zealot 6 14838
Protoss_Cybernetics_Core 1 10092
Protoss_Stargate 1 11830
Protoss_Citadel_of_Adun 1 12311
Protoss_Dragoon 1 12446
Protoss_Corsair 2 13688
15017
