Protoss_Forge 2 13605
Protoss_Nexus 1 7508
Protoss_Photon_Cannon 4 13400
Protoss_Gateway 4 16003
Protoss_Assimilator 2 10189
Protoss_Cybernetics_Core 1 9405
Protoss_Zealot 5 13170
Protoss_Stargate 1 11204
Protoss_Citadel_of_Adun 1 11935
Protoss_Corsair 1 12283
Protoss_Templar_Archives 1 13469
Protoss_Dark_Templar 1 14685
Protoss_High_Templar 1 15824
16003
