Protoss_Forge 2 14568
Protoss_Photon_Cannon 2 15591
Protoss_Nexus 1 8387
Protoss_Gateway 4 14208
Protoss_Assimilator 2 10856
Protoss_Cybernetics_Core 1 9043
Protoss_Zealot 3 12869
Protoss_Stargate 1 10964
Protoss_Citadel_of_Adun 1 11772
Protoss_Dragoon 1 12007
Protoss_Corsair 1 11999
Protoss_Templar_Archives 1 13249
Protoss_Dark_Templar 3 15642
Protoss_High_Templar 2 15557
15642
