Protoss_Forge 1 4908
Protoss_Nexus 1 7951
Protoss_Photon_Cannon 2 7031
Protoss_Gateway 4 13897
Protoss_Assimilator 2 10827
Protoss_Cybernetics_Core 1 9579
Protoss_Zealot 4 12863
Protoss_Stargate 1 11545
Protoss_Dragoon 8 15437
Protoss_Corsair 4 15491
Singularity_Charge 1 14551
15491
