Protoss_Forge 1 4015
Protoss_Photon_Cannon 3 15699
Protoss_Nexus 1 8905
Protoss_Gateway 3 13685
Protoss_Assimilator 2 15037
Protoss_Zealot 10 14912
Protoss_Cybernetics_Core 1 9492
Protoss_Stargate 1 11655
Protoss_Citadel_of_Adun 1 12377
Protoss_Corsair 1 13141
15699
