Protoss_Nexus 2 15268
Protoss_Forge 1 6435
Protoss_Photon_Cannon 5 15664
Protoss_Gateway 3 12255
Protoss_Assimilator 2 15051
Protoss_Cybernetics_Core 1 9623
Protoss_Zealot 12 15558
Protoss_Citadel_of_Adun 1 11270
Leg_Enhancements 1 14229
Protoss_Templar_Archives 1 15659
15664
