Protoss_Forge 1 5355
Protoss_Photon_Cannon 5 14774
Protoss_Nexus 1 10240
Protoss_Gateway 1 8990
Protoss_Assimilator 2 13480
Protoss_Zealot 5 14396
Protoss_Cybernetics_Core 1 11579
Protoss_Stargate 1 13289
Protoss_Corsair 2 15359
Protoss_Robotics_Facility 1 15701
15701
