Protoss_Gateway 2 4572
Protoss_Zealot 15 12901
Protoss_Assimilator 1 9231
Protoss_Cybernetics_Core 1 11019
Protoss_Forge 1 12116
Protoss_Stargate 1 13472
Protoss_Photon_Cannon 1 13716
Protoss_Corsair 1 14426
Protoss_Nexus 1 17430
17430
