Protoss_Forge 1 4078
Protoss_Photon_Cannon 9 15641
Protoss_Nexus 1 8886
Protoss_Gateway 4 15592
Protoss_Assimilator 1 8863
Protoss_Zealot 4 14036
Protoss_Cybernetics_Core 1 10966
Protoss_Stargate 1 13781
Protoss_Citadel_of_Adun 1 14443
Protoss_Corsair 1 14900
15641
