Protoss_Forge 1 3971
Protoss_Photon_Cannon 3 15148
Protoss_Nexus 1 8712
Protoss_Gateway 2 13176
Protoss_Assimilator 2 11692
Protoss_Zealot 7 15471
Protoss_Cybernetics_Core 1 9602
Protoss_Dragoon 1 10930
Protoss_Stargate 1 11983
Protoss_Citadel_of_Adun 1 12412
Protoss_Corsair 3 15166
Protoss_Templar_Archives 1 14897
15471
