Protoss_Forge 1 3908
Protoss_Nexus 1 7594
Protoss_Photon_Cannon 1 6964
Protoss_Gateway 4 14013
Protoss_Assimilator 2 10423
Protoss_Zealot 4 13211
Protoss_Cybernetics_Core 1 9650
Protoss_Stargate 1 11968
Protoss_Citadel_of_Adun 1 11888
Protoss_Corsair 2 13834
Protoss_Templar_Archives 1 14115
Protoss_Dragoon 3 15639
Protoss_Ground_Weapons_1 1 14516
15639
