Protoss_Nexus 1 6497
Protoss_Forge 1 5069
Protoss_Gateway 4 15819
Protoss_Photon_Cannon 3 14606
Protoss_Assimilator 2 10780
Protoss_Zealot 9 14493
Protoss_Cybernetics_Core 1 8938
Protoss_Stargate 1 10884
Protoss_Corsair 3 14660
Protoss_Citadel_of_Adun 1 12697
Protoss_Templar_Archives 1 15459
15819
