Protoss_Forge 1 4230
Protoss_Photon_Cannon 3 13324
Protoss_Nexus 1 8629
Protoss_Gateway 4 14606
Protoss_Assimilator 2 11096
Protoss_Cybernetics_Core 1 9766
Protoss_Zealot 5 14923
Protoss_Stargate 1 11447
Protoss_Dragoon 1 12060
Protoss_Citadel_of_Adun 1 12869
Protoss_Corsair 2 15125
15125
