Protoss_Forge 1 4663
Protoss_Nexus 1 7544
Protoss_Photon_Cannon 2 15715
Protoss_Gateway 4 15125
Protoss_Assimilator 2 9955
Protoss_Cybernetics_Core 1 8800
Protoss_Zealot 3 12983
Protoss_Stargate 1 10497
Protoss_Dragoon 1 10529
Protoss_Citadel_of_Adun 1 11379
Protoss_Corsair 3 13521
Protoss_Templar_Archives 1 13088
Protoss_Dark_Templar 2 14360
Protoss_High_Templar 2 15461
15715
