Protoss_Forge 2 15450
Protoss_Photon_Cannon 5 15512
Protoss_Nexus 1 8206
Protoss_Gateway 3 14546
Protoss_Assimilator 2 9820
Protoss_Cybernetics_Core 1 9394
Protoss_Zealot 5 14552
Protoss_Stargate 1 11669
Protoss_Citadel_of_Adun 1 12337
Protoss_Corsair 2 13673
Protoss_Templar_Archives 1 13796
Protoss_Dark_Templar 1 15276
15512
