Protoss_Forge 1 4357
Protoss_Photon_Cannon 4 13036
Protoss_Nexus 1 8150
Protoss_Gateway 2 14827
Protoss_Assimilator 2 9498
Protoss_Cybernetics_Core 1 9418
Protoss_Zealot 5 14069
Protoss_Stargate 1 11204
Protoss_Corsair 3 15219
Protoss_Citadel_of_Adun 1 13512
Protoss_Templar_Archives 1 15210
15219
