Protoss_Nexus 1 6614
Protoss_Forge 1 5036
Protoss_Photon_Cannon 1 6301
Protoss_Gateway 4 15690
Protoss_Assimilator 2 8923
Protoss_Cybernetics_Core 1 8683
Protoss_Zealot 3 10255
Protoss_Stargate 2 10923
Protoss_Citadel_of_Adun 1 11371
Protoss_Corsair 7 14230
Protoss_Templar_Archives 1 13106
Protoss_Dark_Templar 1 15025
15690
