Protoss_Gateway 1 4087
Protoss_Forge 1 4812
Protoss_Zealot 12 15037
Protoss_Photon_Cannon 9 14056
Protoss_Nexus 1 12801
Protoss_Assimilator 1 11124
Protoss_Cybernetics_Core 1 13249
Protoss_Citadel_of_Adun 1 15756
15756
