Protoss_Forge 1 4460
Protoss_Photon_Cannon 7 15509
Protoss_Nexus 1 10421
Protoss_Gateway 2 13779
Protoss_Assimilator 2 12883
Protoss_Cybernetics_Core 1 11270
Protoss_Zealot 6 15544
Protoss_Stargate 1 12951
Protoss_Citadel_of_Adun 1 14273
Protoss_Corsair 1 13922
15544
