Protoss_Forge 1 4505
Protoss_Photon_Cannon 1 5810
Protoss_Nexus 1 7998
Protoss_Gateway 4 12648
Protoss_Assimilator 2 12817
Protoss_Cybernetics_Core 1 9043
Protoss_Zealot 13 14481
Protoss_Citadel_of_Adun 1 10755
Protoss_Stargate 2 15720
15720
