Protoss_Forge 1 4283
Protoss_Nexus 1 7689
Protoss_Gateway 2 12642
Protoss_Photon_Cannon 3 14870
Protoss_Assimilator 2 11082
Protoss_Zealot 9 15538
Protoss_Cybernetics_Core 1 8929
Protoss_Stargate 1 11368
Protoss_Citadel_of_Adun 1 11821
Protoss_Corsair 4 15321
Protoss_Templar_Archives 1 15311
15538
