Protoss_Forge 1 4309
Protoss_Nexus 1 7777
Protoss_Photon_Cannon 3 14663
Protoss_Gateway 2 12794
Protoss_Assimilator 2 10234
Protoss_Cybernetics_Core 1 9511
Protoss_Zealot 7 14970
Protoss_Stargate 1 11244
Protoss_Citadel_of_Adun 1 11911
Protoss_Corsair 4 15248
Protoss_Templar_Archives 1 15345
15345
