Protoss_Forge 1 4625
Protoss_Photon_Cannon 1 5962
Protoss_Nexus 1 8288
Protoss_Gateway 2 7653
Protoss_Assimilator 2 14944
Protoss_Zealot 15 15435
Protoss_Cybernetics_Core 1 10325
Protoss_Stargate 1 12082
Protoss_Corsair 3 15157
Protoss_Citadel_of_Adun 1 14450
15435
