Protoss_Forge 1 4341
Protoss_Photon_Cannon 3 15259
Protoss_Nexus 1 8876
Protoss_Gateway 4 14178
Protoss_Assimilator 2 13972
Protoss_Cybernetics_Core 1 9427
Protoss_Zealot 9 14317
Protoss_Citadel_of_Adun 1 10965
Leg_Enhancements 1 13989
Protoss_Dragoon 3 15733
15733
