Protoss_Nexus 1 6602
Protoss_Forge 1 5060
Protoss_Photon_Cannon 4 14548
Protoss_Gateway 1 7126
Protoss_Assimilator 2 9277
Protoss_Cybernetics_Core 1 8614
Protoss_Zealot 3 10527
Protoss_Stargate 1 10327
Protoss_Robotics_Facility 1 11960
Protoss_Corsair 5 15102
Protoss_Robotics_Support_Bay 1 12732
Protoss_Citadel_of_Adun 1 13859
Protoss_Shuttle 1 14335
Protoss_Templar_Archives 1 15339
Protoss_Reaver 1 16118
16118
