Protoss_Nexus 1 6611
Protoss_Forge 1 5177
Protoss_Photon_Cannon 2 14027
Protoss_Gateway 3 15927
Protoss_Assimilator 2 14685
Protoss_Cybernetics_Core 1 8789
Protoss_Zealot 8 15394
Protoss_Stargate 1 11065
Protoss_Corsair 4 15046
Protoss_Citadel_of_Adun 1 12901
15927
