Protoss_Nexus 1 7035
Protoss_Gateway 4 13246
Protoss_Assimilator 1 6147
Protoss_Forge 1 6978
Protoss_Zealot 14 14958
Protoss_Photon_Cannon 3 15562
Protoss_Cybernetics_Core 1 8856
Protoss_Stargate 1 10554
Protoss_Corsair 2 14932
Protoss_Citadel_of_Adun 1 12252
15562
