Protoss_Forge 2 6466
Protoss_Nexus 1 7148
Protoss_Gateway 4 12621
Protoss_Assimilator 2 12874
Protoss_Cybernetics_Core 1 8090
Protoss_Photon_Cannon 2 14237
Protoss_Zealot 15 15513
Protoss_Stargate 1 10177
Protoss_Corsair 2 14979
Protoss_Citadel_of_Adun 1 12080
15513
