Protoss_Nexus 1 7073
Protoss_Forge 1 5552
Protoss_Assimilator 1 6367
Protoss_Gateway 4 11376
Protoss_Photon_Cannon 1 7951
Protoss_Cybernetics_Core 1 8587
Protoss_Zealot 17 15090
Protoss_Citadel_of_Adun 1 10391
Protoss_Stargate 2 14574
Leg_Enhancements 1 13324
Protoss_Ground_Weapons_1 1 13617
Protoss_Corsair 2 15512
15512
