Protoss_Forge 1 4764
Protoss_Nexus 1 7424
Protoss_Photon_Cannon 1 6186
Protoss_Gateway 2 14846
Protoss_Assimilator 2 9349
Protoss_Cybernetics_Core 1 8598
Protoss_Zealot 4 11815
Protoss_Stargate 2 12842
Protoss_Citadel_of_Adun 1 11074
Protoss_Corsair 7 15453
Protoss_Templar_Archives 1 12640
Protoss_Dark_Templar 2 15039
15453
