Protoss_Forge 1 4106
Protoss_Nexus 1 7637
Protoss_Gateway 4 13848
Protoss_Assimilator 1 7038
Protoss_Photon_Cannon 5 14202
Protoss_Cybernetics_Core 1 8764
Protoss_Zealot 14 15412
Protoss_Citadel_of_Adun 1 10248
Leg_Enhancements 1 13278
15412
