Protoss_Nexus 1 6532
Protoss_Forge 1 5025
Protoss_Photon_Cannon 3 9727
Protoss_Gateway 2 14712
Protoss_Assimilator 2 10106
Protoss_Cybernetics_Core 1 8537
Protoss_Zealot 4 15111
Protoss_Stargate 2 11482
Protoss_Corsair 8 15333
Protoss_Citadel_of_Adun 1 14191
15333
