Protoss_Forge 1 4032
Protoss_Photon_Cannon 2 13708
Protoss_Nexus 1 7942
Protoss_Gateway 2 15956
Protoss_Assimilator 2 10609
Protoss_Cybernetics_Core 1 8724
Protoss_Zealot 4 13167
Protoss_Stargate 1 10587
Protoss_Citadel_of_Adun 1 11543
Protoss_Corsair 4 14669
Protoss_Templar_Archives 1 13141
Protoss_Dark_Templar 1 14489
Protoss_Arbiter_Tribunal 1 14941
15956
