Protoss_Forge 1 4504
Protoss_Photon_Cannon 4 13959
Protoss_Nexus 1 8949
Protoss_Gateway 1 8105
Protoss_Assimilator 2 9835
Protoss_Zealot 3 12904
Protoss_Cybernetics_Core 1 9618
Protoss_Stargate 1 11444
Protoss_Dragoon 1 11366
Protoss_Robotics_Facility 1 13207
Protoss_Corsair 4 15535
Protoss_Robotics_Support_Bay 1 14012
15535
