Protoss_Forge 1 4312
Protoss_Photon_Cannon 3 15265
Protoss_Nexus 1 12297
Protoss_Gateway 1 11546
Protoss_Assimilator 1 11670
Protoss_Zealot 2 14689
Protoss_Cybernetics_Core 1 13840
15265
