Protoss_Forge 1 4000
Protoss_Photon_Cannon 9 14872
Protoss_Nexus 1 8498
Protoss_Gateway 3 12334
Protoss_Assimilator 2 12298
Protoss_Zealot 5 11707
Protoss_Cybernetics_Core 1 9348
Protoss_Citadel_of_Adun 1 10981
Protoss_Templar_Archives 1 12986
Protoss_High_Templar 3 15449
Protoss_Dark_Templar 1 14231
Protoss_Archon 1 14962
15449
