Protoss_Forge 1 4312
Protoss_Photon_Cannon 3 14287
Protoss_Nexus 1 8952
Protoss_Gateway 4 15956
Protoss_Assimilator 2 10354
Protoss_Cybernetics_Core 1 9468
Protoss_Zealot 3 12096
Protoss_Stargate 1 11308
Protoss_Dragoon 1 11234
Protoss_Citadel_of_Adun 1 12153
Protoss_Corsair 3 14393
Protoss_Templar_Archives 1 13748
Protoss_Dark_Templar 2 14966
15956
