Protoss_Forge 2 6415
Protoss_Nexus 1 7282
Protoss_Gateway 2 11118
Protoss_Assimilator 2 10949
Protoss_Photon_Cannon 2 14150
Protoss_Cybernetics_Core 1 8469
Protoss_Zealot 8 14809
Protoss_Stargate 1 10481
Protoss_Corsair 3 15163
Protoss_Citadel_of_Adun 1 12064
15163
