Protoss_Gateway 2 5227
Protoss_Zealot 10 11414
Protoss_Assimilator 1 7483
Protoss_Cybernetics_Core 1 9468
Protoss_Stargate 1 11172
Protoss_Citadel_of_Adun 1 11235
Protoss_Corsair 1 12113
Protoss_Templar_Archives 1 13073
Protoss_Nexus 1 15385
Protoss_Forge 1 13747
Protoss_Dark_Templar 1 14612
Protoss_Photon_Cannon 2 15382
Protoss_High_Templar 1 15683
15683
