Protoss_Forge 1 4663
Protoss_Photon_Cannon 4 15439
Protoss_Nexus 1 8876
Protoss_Gateway 1 8227
Protoss_Assimilator 2 10112
Protoss_Zealot 6 13892
Protoss_Cybernetics_Core 1 9684
Protoss_Stargate 2 12783
Protoss_Corsair 6 15430
Protoss_Citadel_of_Adun 1 15333
15439
