Protoss_Forge 1 4303
Protoss_Photon_Cannon 9 10595
Protoss_Nexus 1 12608
Protoss_Gateway 1 11865
Protoss_Assimilator 2 15080
Protoss_Cybernetics_Core 1 13849
Protoss_Dragoon 1 15051
Protoss_Stargate 1 15547
15547
