Protoss_Forge 1 4713
Protoss_Photon_Cannon 2 6547
Protoss_Nexus 1 8850
Protoss_Gateway 4 15298
Protoss_Assimilator 2 11414
Protoss_Zealot 10 15544
Protoss_Cybernetics_Core 1 9690
Protoss_Stargate 1 11371
Protoss_Citadel_of_Adun 1 12245
Protoss_Corsair 2 13504
15544
