Protoss_Forge 1 3852
Protoss_Photon_Cannon 3 13734
Protoss_Nexus 1 7910
Protoss_Gateway 4 15248
Protoss_Assimilator 2 10139
Protoss_Zealot 4 11391
Protoss_Cybernetics_Core 1 9511
Protoss_Stargate 1 11427
Protoss_Citadel_of_Adun 1 11689
Protoss_Corsair 1 12781
Protoss_Templar_Archives 1 13392
Protoss_Dark_Templar 1 14615
Protoss_High_Templar 1 15715
15715
