Protoss_Forge 1 4793
Protoss_Nexus 1 7653
Protoss_Photon_Cannon 3 15146
Protoss_Gateway 4 15829
Protoss_Assimilator 2 12172
Protoss_Zealot 8 14786
Protoss_Cybernetics_Core 1 9198
Protoss_Stargate 1 11211
Protoss_Citadel_of_Adun 1 12084
Protoss_Corsair 2 13594
Protoss_Templar_Archives 1 15934
15934
