Protoss_Gateway 2 5109
Protoss_Zealot 10 15582
Protoss_Forge 1 7875
Protoss_Nexus 1 11715
Protoss_Photon_Cannon 2 12878
Protoss_Assimilator 2 11516
Protoss_Cybernetics_Core 1 11695
Protoss_Stargate 1 13557
Protoss_Citadel_of_Adun 1 14095
Protoss_Corsair 1 14519
Protoss_Templar_Archives 1 15549
15582
