Protoss_Gateway 2 5039
Protoss_Zealot 12 14499
Protoss_Assimilator 1 7805
Protoss_Cybernetics_Core 1 9639
Protoss_Forge 1 10498
Protoss_Stargate 1 11947
Protoss_Photon_Cannon 3 15445
Protoss_Citadel_of_Adun 1 12844
Protoss_Corsair 2 13811
15445
