Protoss_Nexus 1 6792
Protoss_Forge 1 5338
Protoss_Photon_Cannon 2 13813
Protoss_Gateway 3 11831
Protoss_Assimilator 3 13369
Protoss_Cybernetics_Core 1 8739
Protoss_Zealot 12 14993
Protoss_Stargate 1 10835
Protoss_Citadel_of_Adun 1 11333
Protoss_Corsair 4 15184
Protoss_Ground_Weapons_1 1 14167
Leg_Enhancements 1 14416
15184
