Protoss_Forge 1 4050
Protoss_Photon_Cannon 5 12058
Protoss_Nexus 1 8459
Protoss_Gateway 6 15921
Protoss_Assimilator 2 10755
Protoss_Cybernetics_Core 1 9307
Protoss_Zealot 4 14835
Protoss_Stargate 1 11227
Protoss_Citadel_of_Adun 1 11809
Protoss_Corsair 1 12254
Protoss_Templar_Archives 1 13670
Protoss_Robotics_Facility 1 15446
Protoss_High_Templar 2 14875
Protoss_Dark_Templar 1 14990
15921
