Protoss_Gateway 3 15192
Protoss_Zealot 9 15576
Protoss_Nexus 1 8493
Protoss_Forge 1 7132
Protoss_Photon_Cannon 2 10649
Protoss_Assimilator 2 11414
Protoss_Cybernetics_Core 1 12615
Protoss_Citadel_of_Adun 1 14105
Protoss_Templar_Archives 1 15661
15661
