Protoss_Forge 1 4196
Protoss_Nexus 1 7937
Protoss_Gateway 4 12848
Protoss_Assimilator 2 12680
Protoss_Zealot 10 15149
Protoss_Photon_Cannon 4 15022
Protoss_Cybernetics_Core 1 9232
Protoss_Dragoon 1 10602
Protoss_Citadel_of_Adun 1 10992
Protoss_Templar_Archives 1 13855
Leg_Enhancements 1 14030
Protoss_High_Templar 2 15341
Protoss_Dark_Templar 1 15355
Protoss_Ground_Weapons_1 1 14317
15355
