Protoss_Forge 2 14184
Protoss_Photon_Cannon 4 13506
Protoss_Nexus 1 9261
Protoss_Gateway 2 15059
Protoss_Assimilator 2 10810
Protoss_Zealot 4 13858
Protoss_Cybernetics_Core 1 10290
Protoss_Stargate 1 12073
Protoss_Citadel_of_Adun 1 13275
15059
