Protoss_Forge 1 4540
Protoss_Photon_Cannon 3 14123
Protoss_Nexus 1 7925
Protoss_Gateway 4 15304
Protoss_Assimilator 2 11727
Protoss_Cybernetics_Core 1 8630
Protoss_Zealot 4 12400
Protoss_Stargate 1 10320
Protoss_Citadel_of_Adun 1 11066
Protoss_Corsair 3 14434
Protoss_Templar_Archives 1 12962
Protoss_High_Templar 2 15604
15604
