Protoss_Forge 1 4152
Protoss_Nexus 1 7477
Protoss_Photon_Cannon 3 15467
Protoss_Gateway 1 7452
Protoss_Assimilator 2 12961
Protoss_Zealot 4 14358
Protoss_Cybernetics_Core 1 9684
Protoss_Stargate 1 12245
Protoss_Corsair 2 14455
15467
