Protoss_Forge 1 4881
Protoss_Photon_Cannon 4 14212
Protoss_Nexus 1 8853
Protoss_Gateway 3 15762
Protoss_Assimilator 2 10894
Protoss_Zealot 3 14964
Protoss_Cybernetics_Core 1 9718
Protoss_Stargate 1 11792
Protoss_Dragoon 2 12733
Protoss_Citadel_of_Adun 1 12710
Protoss_Corsair 3 15134
Protoss_Templar_Archives 1 14339
Protoss_Dark_Templar 1 15546
15762
