Protoss_Forge 1 4750
Protoss_Nexus 1 7635
Protoss_Photon_Cannon 3 14710
Protoss_Gateway 2 11793
Protoss_Assimilator 2 13744
Protoss_Cybernetics_Core 1 10029
Protoss_Zealot 9 15257
Protoss_Stargate 1 11766
Protoss_Citadel_of_Adun 1 12563
Protoss_Corsair 2 14033
Protoss_Templar_Archives 1 15842
15842
