Protoss_Forge 1 4654
Protoss_Nexus 1 7518
Protoss_Photon_Cannon 4 13078
Protoss_Gateway 4 15526
Protoss_Assimilator 2 11967
Protoss_Cybernetics_Core 1 9271
Protoss_Zealot 6 14651
Protoss_Stargate 1 11318
Protoss_Dragoon 1 11586
Protoss_Citadel_of_Adun 1 12352
Protoss_Corsair 1 12368
Protoss_Templar_Archives 1 14724
15526
