Protoss_Forge 1 4275
Protoss_Nexus 1 7705
Protoss_Gateway 5 14314
Protoss_Assimilator 2 15214
Protoss_Photon_Cannon 3 12446
Protoss_Zealot 4 15441
Protoss_Cybernetics_Core 1 9389
Protoss_Dragoon 10 15751
Protoss_Robotics_Facility 1 15881
15881
