Protoss_Nexus 1 7038
Protoss_Forge 1 5585
Protoss_Photon_Cannon 5 14913
Protoss_Gateway 3 14317
Protoss_Assimilator 2 10883
Protoss_Cybernetics_Core 1 10839
Protoss_Zealot 4 14950
Protoss_Stargate 1 13063
Protoss_Citadel_of_Adun 1 13883
Protoss_Corsair 2 15345
Protoss_Templar_Archives 1 15342
15345
