Protoss_Forge 1 3835
Protoss_Photon_Cannon 3 6718
Protoss_Nexus 1 9134
Protoss_Gateway 3 13728
Protoss_Assimilator 2 10057
Protoss_Cybernetics_Core 1 9520
Protoss_Zealot 6 13937
Protoss_Citadel_of_Adun 1 11099
Protoss_Stargate 1 11962
Protoss_Corsair 3 15503
Protoss_Templar_Archives 1 15046
Leg_Enhancements 1 14041
15503
