Protoss_Forge 1 4420
Protoss_Nexus 1 7874
Protoss_Gateway 4 14206
Protoss_Assimilator 2 9394
Protoss_Photon_Cannon 3 15408
Protoss_Cybernetics_Core 1 8601
Protoss_Zealot 4 12948
Protoss_Stargate 1 10440
Protoss_Citadel_of_Adun 1 11131
Protoss_Dragoon 1 10989
Protoss_Corsair 4 15219
Protoss_Templar_Archives 1 12729
Protoss_Dark_Templar 1 14088
15408
