Protoss_Forge 1 4344
Protoss_Nexus 1 7596
Protoss_Photon_Cannon 2 14992
Protoss_Gateway 3 13675
Protoss_Assimilator 2 10963
Protoss_Zealot 8 15248
Protoss_Cybernetics_Core 1 9555
Protoss_Stargate 1 11396
Protoss_Citadel_of_Adun 1 12239
Protoss_Corsair 2 14153
Protoss_Templar_Archives 1 14750
15248
