Protoss_Forge 1 4133
Protoss_Nexus 1 7541
Protoss_Photon_Cannon 1 6408
Protoss_Gateway 5 15312
Protoss_Assimilator 2 8313
Protoss_Cybernetics_Core 1 8560
Protoss_Zealot 1 8958
Protoss_Stargate 1 10458
Protoss_Citadel_of_Adun 1 11076
Protoss_Corsair 2 12400
Protoss_Templar_Archives 1 12541
Protoss_Dark_Templar 2 15031
Protoss_High_Templar 2 14960
15312
