Protoss_Forge 1 4278
Protoss_Photon_Cannon 7 15693
Protoss_Nexus 1 8940
Protoss_Gateway 1 7987
Protoss_Assimilator 2 10644
Protoss_Cybernetics_Core 1 9501
Protoss_Zealot 4 13188
Protoss_Stargate 1 11220
Protoss_Citadel_of_Adun 1 11888
Protoss_Dragoon 1 12317
Protoss_Corsair 2 14156
Protoss_Templar_Archives 1 13477
Protoss_High_Templar 1 14928
15693
