Protoss_Forge 1 4558
Protoss_Photon_Cannon 5 15676
Protoss_Nexus 1 9643
Protoss_Gateway 2 15170
Protoss_Assimilator 2 10872
Protoss_Zealot 4 15146
Protoss_Cybernetics_Core 1 12074
Protoss_Dragoon 1 13403
Protoss_Citadel_of_Adun 1 13845
Protoss_Templar_Archives 1 15561
15676
