Protoss_Forge 2 6321
Protoss_Nexus 1 7102
Protoss_Gateway 3 15620
Protoss_Assimilator 2 10182
Protoss_Photon_Cannon 3 14963
Protoss_Cybernetics_Core 1 8784
Protoss_Zealot 8 15517
Protoss_Stargate 1 10607
Protoss_Dragoon 1 10655
Protoss_Citadel_of_Adun 1 11979
Protoss_Corsair 2 13270
Protoss_Templar_Archives 1 14335
15620
