Protoss_Gateway 3 16022
Protoss_Zealot 11 15190
Protoss_Nexus 1 9077
Protoss_Forge 1 7795
Protoss_Photon_Cannon 5 13049
Protoss_Assimilator 2 14781
Protoss_Cybernetics_Core 1 11124
Protoss_Dragoon 2 15224
Protoss_Robotics_Facility 1 14138
Protoss_Shield_Battery 1 13185
Protoss_Citadel_of_Adun 1 15004
Protoss_Stargate 1 15391
16022
