Protoss_Forge 1 3822
Protoss_Photon_Cannon 3 14192
Protoss_Nexus 1 9024
Protoss_Gateway 5 13954
Protoss_Assimilator 3 15583
Protoss_Zealot 11 15336
Protoss_Cybernetics_Core 1 9965
Protoss_Stargate 1 12056
Protoss_Dragoon 1 11814
Protoss_Citadel_of_Adun 1 12794
15583
