Protoss_Forge 1 4777
Protoss_Photon_Cannon 3 15439
Protoss_Nexus 1 8769
Protoss_Gateway 4 14674
Protoss_Assimilator 2 9466
Protoss_Cybernetics_Core 1 9154
Protoss_Zealot 4 13644
Protoss_Stargate 1 10901
Protoss_Dragoon 1 11460
Protoss_Corsair 2 12832
Protoss_Citadel_of_Adun 1 12368
Protoss_Templar_Archives 1 13811
Protoss_High_Templar 2 15159
15439
