Protoss_Forge 1 3869
Protoss_Nexus 1 7574
Protoss_Photon_Cannon 4 14935
Protoss_Gateway 3 14104
Protoss_Assimilator 2 10262
Protoss_Zealot 8 15125
Protoss_Cybernetics_Core 1 9750
Protoss_Stargate 1 11659
Protoss_Citadel_of_Adun 1 12687
Protoss_Corsair 3 14873
15125
