Protoss_Gateway 1 4130
Protoss_Assimilator 1 4344
Protoss_Zealot 4 10088
Protoss_Cybernetics_Core 1 6511
Protoss_Stargate 1 8318
Protoss_Dragoon 1 8319
Protoss_Corsair 1 9459
Protoss_Citadel_of_Adun 1 10199
Protoss_Forge 1 10840
Protoss_Templar_Archives 1 11720
Protoss_Photon_Cannon 3 14239
Protoss_Dark_Templar 2 14114
Protoss_Nexus 1 16743
Protoss_High_Templar 1 15338
16743
