Protoss_Gateway 3 14418
Protoss_Zealot 11 15380
Protoss_Nexus 1 8965
Protoss_Forge 1 7631
Protoss_Photon_Cannon 2 10754
Protoss_Assimilator 2 11386
Protoss_Cybernetics_Core 1 11755
Protoss_Stargate 1 13509
Protoss_Citadel_of_Adun 1 13536
Protoss_Dragoon 1 13318
Protoss_Corsair 1 14470
Protoss_Templar_Archives 1 15090
15380
