Protoss_Forge 1 4221
Protoss_Photon_Cannon 5 14657
Protoss_Nexus 1 7992
Protoss_Gateway 1 7741
Protoss_Assimilator 2 11092
Protoss_Zealot 4 14531
Protoss_Cybernetics_Core 1 9315
Protoss_Dragoon 1 10725
Protoss_Stargate 1 11292
Protoss_Corsair 4 14999
Protoss_Citadel_of_Adun 1 13021
Protoss_Templar_Archives 1 15116
15116
