Protoss_Forge 2 8954
Protoss_Photon_Cannon 5 10402
Protoss_Gateway 2 11860
Protoss_Assimilator 1 8617
Protoss_Zealot 2 13106
Protoss_Cybernetics_Core 1 13403
Protoss_Robotics_Facility 1 15411
Protoss_Dragoon 1 14861
15411
