Protoss_Forge 1 4101
Protoss_Nexus 1 7840
Protoss_Gateway 4 15184
Protoss_Assimilator 2 10249
Protoss_Photon_Cannon 3 14097
Protoss_Cybernetics_Core 1 8736
Protoss_Zealot 5 15152
Protoss_Stargate 1 10648
Protoss_Citadel_of_Adun 1 11573
Protoss_Corsair 2 13003
Protoss_Templar_Archives 1 13065
Protoss_High_Templar 2 15446
15446
