Protoss_Forge 1 3708
Protoss_Photon_Cannon 3 15230
Protoss_Nexus 1 8981
Protoss_Gateway 2 14527
Protoss_Assimilator 2 14231
Protoss_Cybernetics_Core 1 9432
Protoss_Zealot 5 13243
Protoss_Stargate 1 11590
Protoss_Citadel_of_Adun 1 11660
Protoss_Corsair 1 12632
Protoss_Templar_Archives 1 13878
Protoss_Robotics_Facility 1 15390
Protoss_Dark_Templar 1 15303
15390
