Protoss_Forge 1 4966
Protoss_Nexus 1 7638
Protoss_Photon_Cannon 2 15636
Protoss_Gateway 2 11996
Protoss_Assimilator 2 9476
Protoss_Cybernetics_Core 1 8768
Protoss_Zealot 10 15204
Protoss_Stargate 1 10613
Protoss_Citadel_of_Adun 1 11420
Protoss_Corsair 1 11862
Protoss_Templar_Archives 1 14229
Leg_Enhancements 1 14399
15636
