Protoss_Forge 1 4220
Protoss_Photon_Cannon 4 13178
Protoss_Nexus 1 8736
Protoss_Gateway 2 15046
Protoss_Assimilator 2 10966
Protoss_Cybernetics_Core 1 9189
Protoss_Zealot 3 13978
Protoss_Stargate 1 11090
Protoss_Corsair 3 14148
Protoss_Citadel_of_Adun 1 14104
Protoss_Templar_Archives 1 15705
15705
