Protoss_Forge 1 3895
Protoss_Photon_Cannon 5 15808
Protoss_Nexus 1 9104
Protoss_Gateway 3 12646
Protoss_Assimilator 2 11830
Protoss_Cybernetics_Core 1 9713
Protoss_Zealot 6 14127
Protoss_Citadel_of_Adun 1 11342
Protoss_Dragoon 1 11384
Protoss_Templar_Archives 1 13581
Protoss_High_Templar 2 14902
Protoss_Dark_Templar 1 15247
Leg_Enhancements 1 14381
15808
