Protoss_Forge 1 4486
Protoss_Photon_Cannon 2 11788
Protoss_Nexus 1 8048
Protoss_Gateway 2 11074
Protoss_Assimilator 2 11074
Protoss_Cybernetics_Core 1 8882
Protoss_Zealot 10 15394
Protoss_Stargate 1 10705
Protoss_Citadel_of_Adun 1 10811
Protoss_Corsair 3 14885
Leg_Enhancements 1 13995
15394
