Protoss_Forge 1 4044
Protoss_Nexus 1 7471
Protoss_Photon_Cannon 2 6805
Protoss_Gateway 2 13947
Protoss_Assimilator 2 10371
Protoss_Cybernetics_Core 1 9248
Protoss_Zealot 7 15152
Protoss_Stargate 1 10958
Protoss_Dragoon 1 10956
Protoss_Corsair 4 14639
Protoss_Citadel_of_Adun 1 12911
Protoss_Templar_Archives 1 14821
15152
