Protoss_Forge 1 4271
Protoss_Nexus 1 7623
Protoss_Photon_Cannon 1 6389
Protoss_Gateway 2 14205
Protoss_Assimilator 2 10957
Protoss_Cybernetics_Core 1 8885
Protoss_Zealot 8 15579
Protoss_Stargate 1 11071
Protoss_Corsair 3 14748
Protoss_Citadel_of_Adun 1 13267
Protoss_Templar_Archives 1 14982
15579
