Protoss_Forge 1 4982
Protoss_Nexus 1 7679
Protoss_Photon_Cannon 3 15234
Protoss_Gateway 4 15847
Protoss_Assimilator 2 11559
Protoss_Cybernetics_Core 1 9532
Protoss_Zealot 3 13155
Protoss_Stargate 1 11330
Protoss_Corsair 2 13685
Protoss_Citadel_of_Adun 1 13293
Protoss_Templar_Archives 1 14806
15847
