Protoss_Forge 1 4005
Protoss_Nexus 1 7565
Protoss_Photon_Cannon 3 14479
Protoss_Gateway 2 13670
Protoss_Assimilator 2 11718
Protoss_Cybernetics_Core 1 9374
Protoss_Zealot 9 15544
Protoss_Stargate 1 11210
Protoss_Citadel_of_Adun 1 11429
Protoss_Corsair 3 15049
Leg_Enhancements 1 14548
15544
