Protoss_Forge 1 4305
Protoss_Photon_Cannon 2 6107
Protoss_Nexus 1 9100
Protoss_Gateway 1 8270
Protoss_Assimilator 2 10735
Protoss_Cybernetics_Core 1 9804
Protoss_Zealot 7 15342
Protoss_Stargate 1 11511
Protoss_Robotics_Facility 1 13364
Protoss_Corsair 3 14508
Protoss_Robotics_Support_Bay 1 14324
15342
