Protoss_Forge 2 12719
Protoss_Photon_Cannon 3 13997
Protoss_Gateway 3 13600
Protoss_Assimilator 1 7428
Protoss_Cybernetics_Core 1 9207
Protoss_Zealot 7 15406
Protoss_Dragoon 1 10412
Protoss_Stargate 1 11034
Protoss_Citadel_of_Adun 1 11314
Protoss_Corsair 1 11979
Protoss_Templar_Archives 1 14528
Leg_Enhancements 1 14460
15406
