Protoss_Forge 1 4204
Protoss_Nexus 1 7509
Protoss_Gateway 2 11616
Protoss_Photon_Cannon 2 15415
Protoss_Assimilator 2 10223
Protoss_Cybernetics_Core 1 8212
Protoss_Stargate 1 10060
Protoss_Zealot 9 14715
Protoss_Citadel_of_Adun 2 12046
Protoss_Corsair 3 15064
Protoss_Templar_Archives 1 13486
Protoss_High_Templar 1 15774
15774
