Protoss_Forge 1 4493
Protoss_Photon_Cannon 3 8858
Protoss_Nexus 1 9096
Protoss_Gateway 4 15389
Protoss_Assimilator 1 8022
Protoss_Cybernetics_Core 1 10946
Protoss_Citadel_of_Adun 1 12626
Protoss_Zealot 5 15406
Protoss_Dragoon 1 13541
15406
