Protoss_Nexus 1 6921
Protoss_Forge 1 5440
Protoss_Gateway 1 7073
Protoss_Photon_Cannon 3 14561
Protoss_Assimilator 2 9972
Protoss_Zealot 7 15362
Protoss_Cybernetics_Core 1 9266
Protoss_Stargate 2 11912
Protoss_Corsair 7 15116
Protoss_Citadel_of_Adun 1 12684
Protoss_Templar_Archives 1 15912
15912
