Protoss_Forge 1 4804
Protoss_Nexus 1 7680
Protoss_Photon_Cannon 3 15124
Protoss_Gateway 2 13602
Protoss_Assimilator 2 10395
Protoss_Cybernetics_Core 1 10065
Protoss_Zealot 6 15339
Protoss_Stargate 1 11754
Protoss_Citadel_of_Adun 1 12166
Protoss_Corsair 2 13723
Protoss_Templar_Archives 1 14573
15339
