Protoss_Forge 1 3965
Protoss_Photon_Cannon 2 8432
Protoss_Nexus 1 12050
Protoss_Gateway 3 15506
Protoss_Assimilator 2 12632
Protoss_Zealot 3 15219
Protoss_Cybernetics_Core 1 12617
Protoss_Stargate 1 14405
Protoss_Citadel_of_Adun 1 14420
Protoss_Corsair 1 15435
15506
