Protoss_Forge 1 4764
Protoss_Nexus 1 7799
Protoss_Photon_Cannon 5 15597
Protoss_Gateway 3 14001
Protoss_Assimilator 2 9762
Protoss_Cybernetics_Core 1 9396
Protoss_Stargate 1 11097
Protoss_Zealot 4 13120
Protoss_Citadel_of_Adun 1 11667
Protoss_Corsair 4 14914
Protoss_Templar_Archives 1 13144
Protoss_Dark_Templar 1 14369
Protoss_High_Templar 2 15300
15597
