Protoss_Forge 1 4808
Protoss_Nexus 1 7657
Protoss_Photon_Cannon 2 15616
Protoss_Gateway 2 13474
Protoss_Assimilator 2 10232
Protoss_Cybernetics_Core 1 8967
Protoss_Zealot 10 15356
Protoss_Stargate 1 10879
Protoss_Citadel_of_Adun 1 11742
Protoss_Corsair 1 11818
Protoss_Templar_Archives 1 14039
Protoss_Robotics_Facility 1 14888
15616
