Protoss_Gateway 3 11578
Protoss_Assimilator 1 4271
Protoss_Zealot 11 14604
Protoss_Cybernetics_Core 1 8578
Protoss_Dragoon 2 14811
Protoss_Stargate 1 10405
Protoss_Corsair 3 13691
Protoss_Citadel_of_Adun 1 14270
14811
