Protoss_Forge 2 12687
Protoss_Photon_Cannon 6 15746
Protoss_Nexus 1 8870
Protoss_Gateway 2 13005
Protoss_Assimilator 2 11048
Protoss_Cybernetics_Core 1 9263
Protoss_Zealot 4 13603
Protoss_Stargate 1 11039
Protoss_Citadel_of_Adun 1 11901
Protoss_Corsair 2 12896
Protoss_Templar_Archives 1 13548
Protoss_Dark_Templar 2 14793
15746
