Protoss_Gateway 2 11566
Protoss_Assimilator 1 4827
Protoss_Zealot 5 12419
Protoss_Cybernetics_Core 1 7218
Protoss_Stargate 1 8956
Protoss_Dragoon 1 9851
Protoss_Corsair 2 11636
Protoss_Citadel_of_Adun 1 11203
Protoss_Templar_Archives 1 12952
Protoss_Forge 1 12891
Protoss_Dark_Templar 2 14224
Protoss_Photon_Cannon 2 15669
Protoss_Nexus 1 16869
Protoss_High_Templar 2 15373
16869
