Protoss_Forge 1 4068
Protoss_Photon_Cannon 5 14719
Protoss_Nexus 1 8736
Protoss_Gateway 3 14145
Protoss_Assimilator 2 10669
Protoss_Cybernetics_Core 1 9228
Protoss_Zealot 9 15160
Protoss_Stargate 1 10933
Protoss_Corsair 1 11873
Protoss_Citadel_of_Adun 1 12573
Protoss_Templar_Archives 1 14702
15160
