Protoss_Forge 1 5271
Protoss_Nexus 1 7754
Protoss_Photon_Cannon 4 13541
Protoss_Gateway 3 14711
Protoss_Assimilator 3 15014
Protoss_Cybernetics_Core 1 9539
Protoss_Zealot 3 13097
Protoss_Stargate 1 11374
Protoss_Citadel_of_Adun 1 11743
Protoss_Corsair 4 15286
Protoss_Templar_Archives 1 13261
Protoss_Dark_Templar 1 14694
15286
