Protoss_Forge 1 4404
Protoss_Nexus 1 7645
Protoss_Gateway 4 13407
Protoss_Assimilator 2 10574
Protoss_Photon_Cannon 2 14501
Protoss_Cybernetics_Core 1 8699
Protoss_Zealot 10 15412
Protoss_Dragoon 1 10070
Protoss_Citadel_of_Adun 1 10445
Protoss_Templar_Archives 1 13949
Leg_Enhancements 1 13500
Protoss_Dark_Templar 2 15707
15707
