Protoss_Forge 1 4214
Protoss_Photon_Cannon 3 14852
Protoss_Nexus 1 8829
Protoss_Gateway 3 14765
Protoss_Assimilator 2 10258
Protoss_Cybernetics_Core 1 9506
Protoss_Zealot 5 13987
Protoss_Dragoon 1 10722
Protoss_Stargate 1 11503
Protoss_Citadel_of_Adun 1 12795
Protoss_Corsair 2 13381
Protoss_Templar_Archives 1 14329
14852
