Protoss_Forge 1 4934
Protoss_Photon_Cannon 6 14160
Protoss_Nexus 1 8901
Protoss_Gateway 4 14967
Protoss_Assimilator 2 10182
Protoss_Cybernetics_Core 1 9653
Protoss_Zealot 2 11882
Protoss_Dragoon 1 10860
Protoss_Stargate 1 11832
Protoss_Citadel_of_Adun 1 12280
Protoss_Corsair 2 13662
Protoss_Templar_Archives 1 13833
Protoss_High_Templar 2 15054
15054
