Protoss_Forge 1 4659
Protoss_Nexus 1 7626
Protoss_Photon_Cannon 4 14419
Protoss_Gateway 2 12986
Protoss_Assimilator 2 11393
Protoss_Cybernetics_Core 1 9230
Protoss_Zealot 6 14862
Protoss_Stargate 1 11210
Protoss_Dragoon 1 11079
Protoss_Citadel_of_Adun 1 12118
Protoss_Corsair 2 13656
Protoss_Templar_Archives 1 15232
15232
