Protoss_Forge 1 4346
Protoss_Photon_Cannon 4 14831
Protoss_Nexus 1 8493
Protoss_Gateway 2 15889
Protoss_Assimilator 2 10512
Protoss_Cybernetics_Core 1 9681
Protoss_Stargate 2 13366
Protoss_Corsair 5 15014
Protoss_Citadel_of_Adun 1 14042
Protoss_Templar_Archives 1 15602
15889
