Protoss_Forge 1 3910
Protoss_Photon_Cannon 2 13260
Protoss_Nexus 1 7944
Protoss_Gateway 3 15163
Protoss_Assimilator 2 10881
Protoss_Cybernetics_Core 1 8563
Protoss_Zealot 4 13937
Protoss_Dragoon 1 10078
Protoss_Stargate 2 14943
Protoss_Corsair 3 15137
Protoss_Robotics_Facility 1 13693
Protoss_Robotics_Support_Bay 1 14395
Protoss_Reaver 1 16215
16215
