Protoss_Gateway 2 15410
Protoss_Assimilator 1 4817
Protoss_Zealot 6 14124
Protoss_Cybernetics_Core 1 6457
Protoss_Dragoon 1 7822
Protoss_Robotics_Facility 1 9184
Protoss_Forge 1 9864
Protoss_Shuttle 1 10615
Protoss_Robotics_Support_Bay 1 10781
Protoss_Reaver 2 14075
Protoss_Photon_Cannon 3 14981
Protoss_Citadel_of_Adun 1 15517
15517
