Protoss_Forge 1 4404
Protoss_Nexus 1 7547
Protoss_Photon_Cannon 3 15762
Protoss_Gateway 4 15762
Protoss_Assimilator 2 10133
Protoss_Cybernetics_Core 1 9444
Protoss_Stargate 1 11263
Protoss_Citadel_of_Adun 1 11765
Protoss_Corsair 3 13994
Protoss_Zealot 1 12617
Protoss_Templar_Archives 1 13258
Protoss_Dark_Templar 2 14928
15762
