Protoss_Forge 1 4079
Protoss_Photon_Cannon 3 15680
Protoss_Nexus 1 9254
Protoss_Gateway 4 12950
Protoss_Assimilator 2 13120
Protoss_Zealot 11 14824
Protoss_Cybernetics_Core 1 9953
Protoss_Citadel_of_Adun 1 11417
Protoss_Dragoon 1 11448
Protoss_Templar_Archives 1 14783
15680
