Protoss_Forge 1 4987
Protoss_Nexus 1 7541
Protoss_Photon_Cannon 2 6704
Protoss_Gateway 4 14778
Protoss_Zealot 5 14879
Protoss_Assimilator 2 12024
Protoss_Cybernetics_Core 1 11427
Protoss_Stargate 1 13130
Protoss_Dragoon 1 12680
Protoss_Citadel_of_Adun 1 13659
Protoss_Corsair 2 14985
Protoss_Templar_Archives 1 15140
15140
