Protoss_Forge 1 4407
Protoss_Nexus 1 8037
Protoss_Gateway 3 14067
Protoss_Photon_Cannon 2 8073
Protoss_Assimilator 2 9863
Protoss_Cybernetics_Core 1 9631
Protoss_Zealot 3 13981
Protoss_Stargate 1 11429
Protoss_Citadel_of_Adun 1 12421
Protoss_Corsair 3 14639
Protoss_Dragoon 1 12871
Protoss_Templar_Archives 1 13887
Protoss_Dark_Templar 1 15200
Protoss_High_Templar 2 15355
15355
