Protoss_Forge 1 4223
Protoss_Nexus 1 7609
Protoss_Photon_Cannon 1 6358
Protoss_Gateway 4 12997
Protoss_Assimilator 2 11496
Protoss_Zealot 14 15582
Protoss_Cybernetics_Core 1 9582
Protoss_Citadel_of_Adun 1 11888
Protoss_Templar_Archives 1 15801
15801
