Protoss_Forge 1 4457
Protoss_Nexus 1 7565
Protoss_Photon_Cannon 5 14551
Protoss_Gateway 2 16059
Protoss_Zealot 3 12734
Protoss_Assimilator 2 12526
Protoss_Cybernetics_Core 1 11876
Protoss_Stargate 1 13595
Protoss_Citadel_of_Adun 1 13969
Protoss_Corsair 1 14537
Protoss_Templar_Archives 1 15479
16059
