Protoss_Forge 1 4403
Protoss_Nexus 1 7588
Protoss_Photon_Cannon 4 13661
Protoss_Gateway 4 15845
Protoss_Assimilator 2 10788
Protoss_Cybernetics_Core 1 9511
Protoss_Zealot 3 11194
Protoss_Stargate 1 11309
Protoss_Citadel_of_Adun 1 11914
Protoss_Corsair 3 14616
Protoss_Templar_Archives 1 13381
Protoss_Dark_Templar 2 14761
15845
