Protoss_Forge 1 3911
Protoss_Photon_Cannon 2 14204
Protoss_Nexus 1 8291
Protoss_Gateway 4 13606
Protoss_Assimilator 2 13300
Protoss_Zealot 12 15479
Protoss_Cybernetics_Core 1 9528
Protoss_Citadel_of_Adun 1 11876
Protoss_Dragoon 1 13072
Protoss_Templar_Archives 1 15331
15479
