Protoss_Forge 1 4429
Protoss_Photon_Cannon 7 14630
Protoss_Nexus 1 8832
Protoss_Gateway 2 13909
Protoss_Assimilator 2 11297
Protoss_Zealot 2 10114
Protoss_Cybernetics_Core 1 9519
Protoss_Stargate 1 11345
Protoss_Citadel_of_Adun 1 12078
Protoss_Corsair 2 13571
Protoss_Templar_Archives 1 13553
Protoss_Dark_Templar 1 14969
14969
