Protoss_Forge 1 4915
Protoss_Photon_Cannon 4 14859
Protoss_Nexus 1 8736
Protoss_Gateway 1 7837
Protoss_Assimilator 2 11272
Protoss_Zealot 3 13012
Protoss_Cybernetics_Core 1 10010
Protoss_Stargate 1 11855
Protoss_Dragoon 1 12057
Protoss_Corsair 3 14906
Protoss_Robotics_Facility 1 14199
14906
