Protoss_Forge 1 3892
Protoss_Photon_Cannon 2 5870
Protoss_Nexus 1 8879
Protoss_Gateway 3 14330
Protoss_Assimilator 2 11101
Protoss_Zealot 5 15119
Protoss_Cybernetics_Core 1 10242
Protoss_Stargate 1 11942
Protoss_Citadel_of_Adun 1 12972
Protoss_Corsair 1 12962
Protoss_Templar_Archives 1 14487
Protoss_Robotics_Facility 1 15926
Protoss_Dark_Templar 1 15680
15926
