Protoss_Nexus 1 6997
Protoss_Forge 1 5945
Protoss_Gateway 4 14445
Protoss_Photon_Cannon 2 9791
Protoss_Assimilator 2 10246
Protoss_Cybernetics_Core 1 9269
Protoss_Stargate 1 11210
Protoss_Robotics_Facility 1 12502
Protoss_Zealot 1 12023
Protoss_Dragoon 6 15812
Protoss_Corsair 1 12163
Protoss_Shuttle 1 13954
Protoss_Robotics_Support_Bay 1 13867
Protoss_Reaver 1 16145
16145
