Protoss_Gateway 2 12684
Protoss_Zealot 4 13152
Protoss_Assimilator 1 5474
Protoss_Cybernetics_Core 1 7256
Protoss_Stargate 1 9335
Protoss_Nexus 1 11386
Protoss_Citadel_of_Adun 1 10350
Protoss_Corsair 1 10311
Protoss_Forge 1 11004
Protoss_Templar_Archives 1 12080
Protoss_Photon_Cannon 3 15505
Protoss_Dark_Templar 2 14103
Protoss_High_Templar 2 15271
15505
