Protoss_Gateway 3 13552
Protoss_Forge 1 4300
Protoss_Photon_Cannon 6 14870
Protoss_Nexus 1 9777
Protoss_Assimilator 2 10957
Protoss_Cybernetics_Core 1 10425
Protoss_Zealot 3 14914
Protoss_Stargate 1 12182
Protoss_Citadel_of_Adun 1 12719
Protoss_Dragoon 1 12958
Protoss_Corsair 3 15096
Protoss_Templar_Archives 1 14181
Protoss_Dark_Templar 1 15396
15396
