Protoss_Nexus 1 7127
Protoss_Forge 1 6115
Protoss_Gateway 6 15899
Protoss_Assimilator 2 9260
Protoss_Photon_Cannon 2 15729
Protoss_Cybernetics_Core 1 8493
Protoss_Zealot 3 11976
Protoss_Stargate 1 10371
Protoss_Dragoon 1 10116
Protoss_Citadel_of_Adun 1 11395
Protoss_Corsair 3 13700
Protoss_Templar_Archives 1 13056
Protoss_High_Templar 3 15376
15899
