Protoss_Nexus 1 7069
Protoss_Gateway 4 14846
Protoss_Forge 1 6504
Protoss_Assimilator 2 11203
Protoss_Photon_Cannon 1 7822
Protoss_Zealot 9 15441
Protoss_Cybernetics_Core 1 9074
Protoss_Stargate 1 10906
Protoss_Citadel_of_Adun 1 11148
Protoss_Corsair 2 13281
Protoss_Templar_Archives 1 13012
Protoss_Dark_Templar 2 14220
Protoss_High_Templar 2 14553
15441
