Protoss_Forge 1 4066
Protoss_Photon_Cannon 4 15791
Protoss_Nexus 1 8572
Protoss_Gateway 3 12691
Protoss_Assimilator 3 13252
Protoss_Cybernetics_Core 1 9093
Protoss_Zealot 8 14821
Protoss_Stargate 1 10898
Protoss_Citadel_of_Adun 1 11629
Protoss_Corsair 1 12017
Protoss_Templar_Archives 1 13448
Protoss_High_Templar 1 15341
15791
