Protoss_Nexus 1 6960
Protoss_Gateway 4 14809
Protoss_Forge 1 6207
Protoss_Assimilator 2 10915
Protoss_Photon_Cannon 4 13064
Protoss_Zealot 4 13665
Protoss_Cybernetics_Core 1 8835
Protoss_Stargate 1 10998
Protoss_Corsair 1 11955
Protoss_Citadel_of_Adun 1 12927
Protoss_Templar_Archives 1 14443
14809
