Protoss_Forge 1 4499
Protoss_Photon_Cannon 2 5856
Protoss_Nexus 1 9034
Protoss_Gateway 5 15380
Protoss_Assimilator 2 13053
Protoss_Zealot 11 14689
Protoss_Cybernetics_Core 1 9905
Protoss_Citadel_of_Adun 1 11411
Protoss_Templar_Archives 1 14358
Protoss_High_Templar 2 15598
Protoss_Dark_Templar 1 15809
15809
