Protoss_Forge 1 4985
Protoss_Nexus 1 7986
Protoss_Gateway 1 7590
Protoss_Photon_Cannon 3 14246
Protoss_Assimilator 2 9738
Protoss_Cybernetics_Core 1 9371
Protoss_Zealot 4 13609
Protoss_Stargate 2 13927
Protoss_Corsair 5 15219
Protoss_Citadel_of_Adun 1 15170
15219
