Protoss_Forge 1 4015
Protoss_Photon_Cannon 2 5931
Protoss_Nexus 1 8733
Protoss_Gateway 5 15763
Protoss_Assimilator 2 10909
Protoss_Zealot 7 15512
Protoss_Cybernetics_Core 1 9870
Protoss_Stargate 1 11789
Protoss_Citadel_of_Adun 1 12509
Protoss_Corsair 2 13732
15763
