Protoss_Gateway 1 3718
Protoss_Zealot 9 13826
Protoss_Forge 1 6279
Protoss_Photon_Cannon 3 15727
Protoss_Nexus 1 11528
Protoss_Assimilator 1 9753
Protoss_Cybernetics_Core 1 11508
Protoss_Stargate 1 13503
Protoss_Citadel_of_Adun 1 14862
Protoss_Corsair 2 15394
15727
