Protoss_Forge 1 4000
Protoss_Photon_Cannon 7 15405
Protoss_Nexus 1 8583
Protoss_Assimilator 2 13098
Protoss_Gateway 3 12833
Protoss_Cybernetics_Core 1 9924
Protoss_Zealot 10 15418
Protoss_Dragoon 1 11138
Protoss_Citadel_of_Adun 1 11900
Protoss_Templar_Archives 1 14474
Protoss_High_Templar 1 15721
15721
