Protoss_Forge 1 4008
Protoss_Photon_Cannon 7 14788
Protoss_Nexus 1 11258
Protoss_Gateway 1 10682
Protoss_Assimilator 2 13192
Protoss_Cybernetics_Core 1 12263
Protoss_Stargate 1 13987
Protoss_Citadel_of_Adun 1 13855
Protoss_Corsair 1 14941
Protoss_Templar_Archives 1 15766
15766
