Protoss_Forge 1 4126
Protoss_Photon_Cannon 3 15148
Protoss_Nexus 1 8709
Protoss_Gateway 4 13002
Protoss_Assimilator 2 14467
Protoss_Cybernetics_Core 1 9263
Protoss_Zealot 9 14753
Protoss_Citadel_of_Adun 1 10924
Protoss_Dragoon 1 10971
Protoss_Templar_Archives 1 14371
Leg_Enhancements 1 14077
15148
