Protoss_Forge 1 4065
Protoss_Photon_Cannon 5 15288
Protoss_Nexus 1 8668
Protoss_Gateway 1 7659
Protoss_Assimilator 2 13548
Protoss_Zealot 6 14961
Protoss_Cybernetics_Core 1 9731
Protoss_Dragoon 1 11223
Protoss_Stargate 1 11830
Protoss_Citadel_of_Adun 1 13070
Protoss_Corsair 3 15479
15479
