Protoss_Forge 2 13641
Protoss_Nexus 1 7581
Protoss_Photon_Cannon 5 15765
Protoss_Gateway 2 13025
Protoss_Assimilator 2 10313
Protoss_Cybernetics_Core 1 9506
Protoss_Zealot 3 13281
Protoss_Stargate 1 11236
Protoss_Citadel_of_Adun 1 11651
Protoss_Corsair 3 14022
Protoss_Templar_Archives 1 13176
Protoss_Dark_Templar 2 14518
15765
