Protoss_Forge 1 4308
Protoss_Photon_Cannon 3 11164
Protoss_Nexus 1 8074
Protoss_Gateway 5 15836
Protoss_Assimilator 2 13141
Protoss_Cybernetics_Core 1 9154
Protoss_Zealot 4 13334
Protoss_Stargate 1 10976
Protoss_Corsair 3 15494
Protoss_Dragoon 1 12508
Protoss_Citadel_of_Adun 1 13069
Protoss_Templar_Archives 1 14679
15836
