Protoss_Forge 1 4057
Protoss_Nexus 1 8010
Protoss_Gateway 4 13523
Protoss_Photon_Cannon 2 8073
Protoss_Assimilator 2 15280
Protoss_Zealot 12 15280
Protoss_Cybernetics_Core 1 10694
Protoss_Citadel_of_Adun 1 12207
Protoss_Templar_Archives 1 15765
15765
