Protoss_Forge 1 3727
Protoss_Photon_Cannon 6 15455
Protoss_Nexus 1 8333
Protoss_Gateway 1 7694
Protoss_Assimilator 2 10483
Protoss_Cybernetics_Core 1 9623
Protoss_Zealot 3 12192
Protoss_Stargate 1 11579
Protoss_Robotics_Facility 1 13091
Protoss_Dragoon 1 12592
Protoss_Corsair 3 14939
Protoss_Shuttle 1 14976
15455
