Protoss_Gateway 3 13480
Protoss_Assimilator 1 4654
Protoss_Zealot 12 14914
Protoss_Cybernetics_Core 1 7144
Protoss_Stargate 1 8854
Protoss_Forge 1 8818
Protoss_Citadel_of_Adun 1 10119
Protoss_Corsair 2 10931
Leg_Enhancements 1 13784
Protoss_Templar_Archives 1 15492
15492
