Protoss_Forge 1 4652
Protoss_Nexus 1 7694
Protoss_Photon_Cannon 4 15436
Protoss_Gateway 2 15784
Protoss_Assimilator 2 11628
Protoss_Cybernetics_Core 1 10113
Protoss_Zealot 5 14868
Protoss_Stargate 1 12196
Protoss_Dragoon 1 12871
Protoss_Corsair 3 15157
Protoss_Citadel_of_Adun 1 14480
Protoss_Templar_Archives 1 15924
15924
