Protoss_Forge 2 12961
Protoss_Photon_Cannon 3 9960
Protoss_Nexus 1 8935
Protoss_Gateway 5 16054
Protoss_Assimilator 2 12694
Protoss_Zealot 5 14944
Protoss_Cybernetics_Core 1 11464
Protoss_Stargate 1 13210
Protoss_Citadel_of_Adun 1 13075
Protoss_Corsair 1 14148
16054
