Protoss_Forge 1 4331
Protoss_Nexus 1 7550
Protoss_Photon_Cannon 4 13633
Protoss_Gateway 4 15649
Protoss_Assimilator 2 10201
Protoss_Zealot 8 15005
Protoss_Cybernetics_Core 1 9585
Protoss_Stargate 1 11457
Protoss_Citadel_of_Adun 1 12342
Protoss_Corsair 4 15473
15649
