Protoss_Nexus 1 6950
Protoss_Gateway 3 12892
Protoss_Forge 2 15339
Protoss_Assimilator 2 10037
Protoss_Photon_Cannon 4 14084
Protoss_Zealot 4 13641
Protoss_Cybernetics_Core 1 9719
Protoss_Dragoon 1 10936
Protoss_Stargate 1 11555
Protoss_Citadel_of_Adun 1 11784
Protoss_Corsair 1 12760
Protoss_Templar_Archives 1 13474
Protoss_Dark_Templar 1 14829
Protoss_High_Templar 2 14896
15339
