Protoss_Gateway 2 14661
Protoss_Assimilator 1 4420
Protoss_Zealot 7 15567
Protoss_Cybernetics_Core 1 6541
Protoss_Stargate 1 8222
Protoss_Dragoon 1 7816
Protoss_Citadel_of_Adun 1 8929
Protoss_Corsair 1 9228
Protoss_Templar_Archives 1 10624
Protoss_Forge 1 10911
Protoss_Dark_Templar 2 13485
Protoss_Photon_Cannon 2 15145
Protoss_Nexus 1 14891
Protoss_High_Templar 1 14618
15567
