Protoss_Forge 1 4349
Protoss_Photon_Cannon 4 15516
Protoss_Nexus 1 8592
Protoss_Gateway 2 13416
Protoss_Assimilator 2 11679
Protoss_Zealot 6 14631
Protoss_Cybernetics_Core 1 10346
Protoss_Dragoon 1 11647
Protoss_Citadel_of_Adun 1 12501
Protoss_Stargate 1 13377
Protoss_Templar_Archives 1 13946
Protoss_Corsair 1 14434
Protoss_Dark_Templar 2 15751
15751
