Protoss_Gateway 2 5088
Protoss_Zealot 15 14999
Protoss_Assimilator 1 9632
Protoss_Cybernetics_Core 1 11177
Protoss_Forge 1 11620
Protoss_Citadel_of_Adun 1 13053
Protoss_Photon_Cannon 2 14214
Protoss_Templar_Archives 1 15435
15435
