Protoss_Forge 1 4104
Protoss_Nexus 1 7615
Protoss_Gateway 4 15072
Protoss_Assimilator 2 13491
Protoss_Photon_Cannon 1 7879
Protoss_Zealot 14 15269
Protoss_Cybernetics_Core 1 11494
Protoss_Citadel_of_Adun 1 13116
Protoss_Ground_Weapons_1 1 13901
Protoss_Templar_Archives 1 15375
15375
