Protoss_Forge 2 12686
Protoss_Photon_Cannon 4 14959
Protoss_Nexus 1 9106
Protoss_Gateway 1 8148
Protoss_Assimilator 2 11029
Protoss_Zealot 4 14273
Protoss_Cybernetics_Core 1 10464
Protoss_Stargate 1 12607
Protoss_Citadel_of_Adun 1 12765
Protoss_Corsair 1 13559
Protoss_Templar_Archives 1 14508
Protoss_Dark_Templar 1 15739
15739
