Protoss_Forge 1 4268
Protoss_Nexus 2 15717
Protoss_Photon_Cannon 3 8438
Protoss_Gateway 2 15228
Protoss_Assimilator 2 11206
Protoss_Zealot 2 10474
Protoss_Cybernetics_Core 1 10527
Protoss_Stargate 1 12373
Protoss_Citadel_of_Adun 1 12665
Protoss_Dragoon 1 12534
Protoss_Corsair 2 15029
Protoss_Templar_Archives 1 15009
15717
