Protoss_Nexus 1 7050
Protoss_Forge 1 5503
Protoss_Photon_Cannon 3 14973
Protoss_Gateway 3 12137
Protoss_Assimilator 2 10944
Protoss_Cybernetics_Core 1 9494
Protoss_Zealot 11 14382
Protoss_Citadel_of_Adun 1 10940
Protoss_Templar_Archives 1 14098
Protoss_Robotics_Facility 1 15586
Leg_Enhancements 1 13895
Protoss_High_Templar 2 15358
Protoss_Dark_Templar 1 15502
Protoss_Ground_Weapons_1 1 14442
15586
