Protoss_Forge 1 4641
Protoss_Photon_Cannon 4 13623
Protoss_Nexus 1 8276
Protoss_Gateway 2 13375
Protoss_Assimilator 3 12010
Protoss_Cybernetics_Core 1 9372
Protoss_Zealot 7 15547
Protoss_Stargate 1 11187
Protoss_Citadel_of_Adun 1 11702
Protoss_Corsair 2 14259
Protoss_Templar_Archives 1 13395
15547
