Protoss_Forge 2 5916
Protoss_Nexus 1 7247
Protoss_Gateway 3 15456
Protoss_Photon_Cannon 3 14570
Protoss_Zealot 10 15327
Protoss_Assimilator 3 14680
Protoss_Cybernetics_Core 1 10066
Protoss_Stargate 1 11890
Protoss_Citadel_of_Adun 1 12488
Protoss_Dragoon 1 12487
Protoss_Corsair 3 15239
15456
