Protoss_Gateway 2 5118
Protoss_Zealot 13 14660
Protoss_Assimilator 1 8560
Protoss_Cybernetics_Core 1 11150
Protoss_Citadel_of_Adun 1 12775
Protoss_Dragoon 1 12923
Protoss_Stargate 1 13518
Protoss_Corsair 1 14516
Protoss_Templar_Archives 1 15321
Protoss_Forge 1 15255
15321
