Protoss_Gateway 2 5086
Protoss_Zealot 19 15430
Protoss_Nexus 1 12198
Protoss_Forge 1 10673
Protoss_Assimilator 2 15254
Protoss_Photon_Cannon 1 13419
Protoss_Cybernetics_Core 1 13760
Protoss_Stargate 1 15547
Protoss_Citadel_of_Adun 1 15593
15593
