Protoss_Forge 1 4609
Protoss_Nexus 1 7773
Protoss_Photon_Cannon 1 6557
Protoss_Gateway 2 13277
Protoss_Assimilator 3 14152
Protoss_Cybernetics_Core 1 9409
Protoss_Stargate 1 11137
Protoss_Citadel_of_Adun 1 10984
Protoss_Dragoon 1 11477
Protoss_Corsair 4 15014
Protoss_Zealot 4 14312
Protoss_Templar_Archives 1 14145
Leg_Enhancements 1 14214
Protoss_Dark_Templar 2 15677
15677
