Protoss_Forge 1 3936
Protoss_Nexus 1 7855
Protoss_Photon_Cannon 6 15347
Protoss_Gateway 1 7707
Protoss_Zealot 6 15529
Protoss_Assimilator 2 14453
Protoss_Cybernetics_Core 1 14705
15529
