Protoss_Forge 1 4707
Protoss_Photon_Cannon 3 15689
Protoss_Nexus 1 9479
Protoss_Gateway 2 15014
Protoss_Assimilator 2 12823
Protoss_Zealot 4 14115
Protoss_Cybernetics_Core 1 10695
Protoss_Stargate 1 12403
Protoss_Citadel_of_Adun 1 12429
Protoss_Corsair 2 15137
Protoss_Templar_Archives 1 14401
15689
