Protoss_Forge 1 4858
Protoss_Photon_Cannon 6 14908
Protoss_Nexus 1 9748
Protoss_Gateway 1 8865
Protoss_Assimilator 2 9305
Protoss_Zealot 3 12434
Protoss_Cybernetics_Core 1 10807
Protoss_Stargate 1 12927
Protoss_Citadel_of_Adun 1 12816
Protoss_Corsair 2 14783
Protoss_Templar_Archives 1 14815
14908
