Protoss_Forge 1 4714
Protoss_Photon_Cannon 6 15129
Protoss_Gateway 3 16032
Protoss_Nexus 1 9584
Protoss_Assimilator 2 11379
Protoss_Zealot 3 13507
Protoss_Cybernetics_Core 1 9918
Protoss_Stargate 1 11719
Protoss_Citadel_of_Adun 1 12529
Protoss_Corsair 2 13630
Protoss_Dragoon 1 13784
Protoss_Templar_Archives 1 14626
16032
