Protoss_Forge 1 3948
Protoss_Nexus 1 7915
Protoss_Gateway 2 15166
Protoss_Assimilator 2 10366
Protoss_Photon_Cannon 4 14542
Protoss_Cybernetics_Core 1 8762
Protoss_Zealot 3 13583
Protoss_Dragoon 1 10254
Protoss_Stargate 1 10762
Protoss_Citadel_of_Adun 1 11524
Protoss_Corsair 2 13606
Protoss_Robotics_Facility 1 13505
Protoss_Templar_Archives 1 13375
Protoss_Shuttle 1 15503
Protoss_Robotics_Support_Bay 1 14914
15503
