Protoss_Forge 1 4744
Protoss_Nexus 1 7685
Protoss_Gateway 4 15953
Protoss_Photon_Cannon 2 14745
Protoss_Assimilator 2 14606
Protoss_Zealot 4 13574
Protoss_Cybernetics_Core 1 8677
Protoss_Dragoon 1 10231
Protoss_Stargate 1 11421
Protoss_Corsair 1 12409
Protoss_Citadel_of_Adun 1 13056
Protoss_Templar_Archives 1 15213
Protoss_Robotics_Facility 1 16173
16173
