Protoss_Forge 1 4125
Protoss_Photon_Cannon 6 15253
Protoss_Nexus 1 8935
Protoss_Gateway 3 12915
Protoss_Assimilator 2 10473
Protoss_Cybernetics_Core 1 9718
Protoss_Zealot 1 9394
Protoss_Dragoon 1 10924
Protoss_Stargate 1 12243
Protoss_Citadel_of_Adun 1 12599
Protoss_Corsair 2 14124
Protoss_Templar_Archives 1 14194
Protoss_High_Templar 2 15519
Protoss_Dark_Templar 1 15727
15727
