Protoss_Gateway 2 4805
Protoss_Zealot 15 15585
Protoss_Assimilator 1 8232
Protoss_Cybernetics_Core 1 9969
Protoss_Citadel_of_Adun 1 11484
Protoss_Templar_Archives 1 13316
Protoss_Forge 1 14549
Leg_Enhancements 1 14504
15585
