Protoss_Forge 1 4739
Protoss_Photon_Cannon 2 6303
Protoss_Nexus 1 8961
Protoss_Gateway 4 15823
Protoss_Assimilator 2 10608
Protoss_Cybernetics_Core 1 9986
Protoss_Zealot 2 12143
Protoss_Dragoon 1 11281
Protoss_Stargate 1 11967
Protoss_Citadel_of_Adun 1 12002
Protoss_Corsair 3 15327
Protoss_Templar_Archives 1 14733
15823
