Protoss_Gateway 3 14695
Protoss_Zealot 4 9430
Protoss_Nexus 1 8785
Protoss_Assimilator 2 10068
Protoss_Cybernetics_Core 1 8680
Protoss_Stargate 1 10430
Protoss_Citadel_of_Adun 1 10979
Protoss_Corsair 3 13237
Protoss_Forge 1 11715
Protoss_Templar_Archives 1 12697
Protoss_Photon_Cannon 4 15347
Protoss_Dark_Templar 1 15145
Protoss_High_Templar 1 15572
15572
