Protoss_Forge 1 4296
Protoss_Photon_Cannon 2 5899
Protoss_Nexus 1 8861
Protoss_Gateway 2 13823
Protoss_Assimilator 2 10267
Protoss_Cybernetics_Core 1 9778
Protoss_Zealot 3 11710
Protoss_Stargate 1 11520
Protoss_Citadel_of_Adun 1 11585
Protoss_Corsair 3 14432
Protoss_Templar_Archives 1 13272
Protoss_Dark_Templar 2 15238
15238
