Protoss_Nexus 1 7127
Protoss_Gateway 3 14910
Protoss_Forge 1 6703
Protoss_Assimilator 2 10060
Protoss_Photon_Cannon 2 12853
Protoss_Cybernetics_Core 1 9293
Protoss_Zealot 3 14525
Protoss_Stargate 1 11046
Protoss_Dragoon 1 10810
Protoss_Citadel_of_Adun 1 11865
Protoss_Corsair 4 14941
Protoss_Templar_Archives 1 13697
Protoss_Dark_Templar 1 15124
15124
