Protoss_Forge 1 4090
Protoss_Photon_Cannon 3 9513
Protoss_Gateway 2 13293
Protoss_Nexus 2 13834
Protoss_Assimilator 2 15225
Protoss_Cybernetics_Core 1 9087
Protoss_Zealot 5 14710
Protoss_Stargate 1 11485
Protoss_Citadel_of_Adun 1 11865
Protoss_Corsair 1 12509
15225
