Protoss_Forge 1 4294
Protoss_Nexus 1 7653
Protoss_Photon_Cannon 4 13554
Protoss_Gateway 3 14077
Protoss_Assimilator 3 14455
Protoss_Cybernetics_Core 1 10224
Protoss_Zealot 6 15245
Protoss_Stargate 1 12126
Protoss_Dragoon 1 11770
Protoss_Citadel_of_Adun 1 13192
Protoss_Corsair 2 15040
Protoss_Templar_Archives 1 14824
15245
