Protoss_Forge 1 4391
Protoss_Photon_Cannon 4 14387
Protoss_Nexus 1 8897
Protoss_Gateway 4 16027
Protoss_Assimilator 2 12713
Protoss_Zealot 3 11780
Protoss_Cybernetics_Core 1 10230
Protoss_Stargate 1 12125
Protoss_Citadel_of_Adun 1 12444
Protoss_Corsair 1 13126
Protoss_Templar_Archives 1 13966
Protoss_Dark_Templar 1 15194
16027
