Protoss_Gateway 2 9551
Protoss_Assimilator 1 4334
Protoss_Zealot 8 14203
Protoss_Cybernetics_Core 1 7202
Protoss_Citadel_of_Adun 1 8840
Protoss_Dragoon 1 8744
Protoss_Templar_Archives 1 10536
Protoss_High_Templar 4 15436
Protoss_Forge 1 12416
Protoss_Dark_Templar 2 13108
Protoss_Archon 1 12514
Protoss_Photon_Cannon 2 14063
Leg_Enhancements 1 13117
15436
