Protoss_Forge 1 4344
Protoss_Photon_Cannon 4 14425
Protoss_Nexus 1 8409
Protoss_Gateway 3 13527
Protoss_Assimilator 2 10378
Protoss_Cybernetics_Core 1 9276
Protoss_Zealot 3 11019
Protoss_Stargate 1 11100
Protoss_Citadel_of_Adun 1 11256
Protoss_Corsair 1 12213
Protoss_Templar_Archives 1 12940
Protoss_Robotics_Facility 1 14511
Protoss_High_Templar 2 14788
Protoss_Dark_Templar 1 15136
15136
