Protoss_Gateway 2 11547
Protoss_Assimilator 1 4366
Protoss_Zealot 6 14001
Protoss_Cybernetics_Core 1 7028
Protoss_Dragoon 3 11586
Protoss_Stargate 1 9347
Protoss_Corsair 3 13545
Protoss_Citadel_of_Adun 1 12449
Protoss_Templar_Archives 1 13927
Protoss_Forge 1 13473
Protoss_Photon_Cannon 1 14944
Protoss_Dark_Templar 2 15487
15487
