Protoss_Forge 1 4281
Protoss_Photon_Cannon 4 15639
Protoss_Nexus 1 8159
Protoss_Gateway 4 15078
Protoss_Assimilator 2 11192
Protoss_Cybernetics_Core 1 9327
Protoss_Zealot 7 14458
Protoss_Stargate 1 11077
Protoss_Citadel_of_Adun 1 11497
Protoss_Corsair 1 12049
Protoss_Templar_Archives 1 14859
Leg_Enhancements 1 14530
15639
