Protoss_Nexus 1 7176
Protoss_Gateway 4 14475
Protoss_Forge 1 6443
Protoss_Assimilator 3 13308
Protoss_Photon_Cannon 1 7734
Protoss_Cybernetics_Core 1 8367
Protoss_Zealot 5 15116
Protoss_Dragoon 1 9674
Protoss_Stargate 1 10235
Protoss_Citadel_of_Adun 1 11549
Protoss_Corsair 2 12190
Protoss_Templar_Archives 1 13209
Protoss_Dark_Templar 1 14460
15116
