Protoss_Nexus 1 7193
Protoss_Gateway 1 6204
Protoss_Forge 1 6731
Protoss_Assimilator 2 9375
Protoss_Photon_Cannon 2 15156
Protoss_Cybernetics_Core 1 8496
Protoss_Zealot 2 10834
Protoss_Dragoon 1 9704
Protoss_Stargate 1 10753
Protoss_Robotics_Facility 1 12222
Protoss_Corsair 5 15263
Protoss_Shuttle 1 13779
Protoss_Robotics_Support_Bay 1 13693
Protoss_Reaver 1 15436
15436
