Protoss_Forge 1 5004
Protoss_Nexus 1 7641
Protoss_Photon_Cannon 2 6909
Protoss_Gateway 2 12075
Protoss_Assimilator 2 10597
Protoss_Cybernetics_Core 1 9298
Protoss_Zealot 9 15380
Protoss_Stargate 1 11031
Protoss_Dragoon 1 10989
Protoss_Citadel_of_Adun 1 11856
Protoss_Corsair 4 15008
Protoss_Templar_Archives 1 15648
15648
