Protoss_Forge 1 4435
Protoss_Photon_Cannon 2 6209
Protoss_Nexus 1 9426
Protoss_Gateway 4 14390
Protoss_Assimilator 2 10758
Protoss_Cybernetics_Core 1 9608
Protoss_Zealot 10 15509
Protoss_Stargate 1 11378
Protoss_Citadel_of_Adun 1 12031
Protoss_Corsair 1 12482
Protoss_Templar_Archives 1 14762
15509
