Protoss_Gateway 1 4196
Protoss_Assimilator 1 4416
Protoss_Zealot 6 10059
Protoss_Cybernetics_Core 1 6741
Protoss_Dragoon 1 7939
Protoss_Stargate 1 8813
Protoss_Citadel_of_Adun 1 9554
Protoss_Corsair 4 14648
Protoss_Templar_Archives 1 11455
Protoss_Forge 1 12434
Protoss_Dark_Templar 1 12967
Protoss_High_Templar 2 15262
Protoss_Photon_Cannon 1 15055
15262
