Protoss_Gateway 2 4975
Protoss_Zealot 10 14651
Protoss_Nexus 1 11405
Protoss_Assimilator 2 15277
Protoss_Cybernetics_Core 1 10805
Protoss_Stargate 1 12907
Protoss_Forge 1 12560
Protoss_Dragoon 2 15066
Protoss_Corsair 1 14177
Protoss_Photon_Cannon 2 15808
Protoss_Robotics_Facility 1 16350
16350
