Protoss_Forge 1 4811
Protoss_Nexus 1 7702
Protoss_Photon_Cannon 2 6873
Protoss_Gateway 4 15965
Protoss_Assimilator 2 11976
Protoss_Zealot 3 13934
Protoss_Cybernetics_Core 1 10082
Protoss_Stargate 1 11939
Protoss_Citadel_of_Adun 1 12119
Protoss_Corsair 2 14148
Protoss_Templar_Archives 1 13704
Protoss_High_Templar 2 15180
15965
