Protoss_Forge 2 6498
Protoss_Gateway 2 8509
Protoss_Photon_Cannon 7 15496
Protoss_Nexus 1 9608
Protoss_Assimilator 2 9986
Protoss_Cybernetics_Core 1 10003
Protoss_Zealot 4 12778
Protoss_Stargate 1 11825
Protoss_Dragoon 1 11653
Protoss_Corsair 3 15055
Protoss_Robotics_Facility 1 14837
15496
