Protoss_Forge 1 4170
Protoss_Nexus 1 7418
Protoss_Gateway 3 15691
Protoss_Assimilator 2 9405
Protoss_Photon_Cannon 3 15108
Protoss_Cybernetics_Core 1 8674
Protoss_Zealot 5 14007
Protoss_Stargate 1 10513
Protoss_Citadel_of_Adun 1 11221
Protoss_Corsair 5 15351
Protoss_Templar_Archives 1 13310
Protoss_Dark_Templar 1 15127
15691
