Protoss_Gateway 2 14762
Protoss_Zealot 10 15055
Protoss_Nexus 1 8512
Protoss_Assimilator 1 8739
Protoss_Cybernetics_Core 1 11761
Protoss_Stargate 1 13548
Protoss_Citadel_of_Adun 1 14452
Protoss_Corsair 1 14736
Protoss_Templar_Archives 1 15948
15948
