Protoss_Gateway 2 4700
Protoss_Zealot 12 15361
Protoss_Assimilator 1 6670
Protoss_Cybernetics_Core 1 8215
Protoss_Stargate 1 9944
Protoss_Corsair 2 11821
Protoss_Nexus 1 13212
Protoss_Dragoon 2 13618
Protoss_Forge 1 13725
Protoss_Photon_Cannon 1 15650
Protoss_Citadel_of_Adun 1 16024
16024
