Protoss_Forge 1 4262
Protoss_Nexus 1 7536
Protoss_Photon_Cannon 2 12636
Protoss_Gateway 4 14227
Protoss_Assimilator 2 10311
Protoss_Zealot 5 12869
Protoss_Cybernetics_Core 1 9470
Protoss_Stargate 1 11501
Protoss_Citadel_of_Adun 1 11774
Protoss_Corsair 1 12801
Protoss_Templar_Archives 1 13530
Protoss_High_Templar 4 15431
15431
