Protoss_Forge 1 4687
Protoss_Photon_Cannon 4 9487
Protoss_Nexus 1 9786
Protoss_Gateway 2 15339
Protoss_Assimilator 2 14938
Protoss_Cybernetics_Core 1 12406
Protoss_Zealot 4 15283
Protoss_Stargate 1 14169
Protoss_Citadel_of_Adun 1 14620
Protoss_Corsair 1 15122
15339
