Protoss_Forge 1 4821
Protoss_Photon_Cannon 2 6247
Protoss_Nexus 1 8876
Protoss_Gateway 2 13193
Protoss_Assimilator 2 9765
Protoss_Cybernetics_Core 1 9427
Protoss_Zealot 3 12836
Protoss_Stargate 1 11245
Protoss_Citadel_of_Adun 1 11382
Protoss_Corsair 2 13916
Protoss_Templar_Archives 1 12877
Protoss_Dark_Templar 2 14401
Protoss_High_Templar 2 15502
15502
