Protoss_Gateway 2 8175
Protoss_Assimilator 1 4400
Protoss_Zealot 13 13381
Protoss_Cybernetics_Core 1 5903
Protoss_Stargate 1 7660
Protoss_Dragoon 1 7471
Protoss_Corsair 1 8771
Protoss_Forge 1 12516
Protoss_Photon_Cannon 4 15753
Protoss_Nexus 1 16429
16429
