Protoss_Forge 1 4864
Protoss_Photon_Cannon 3 9088
Protoss_Nexus 1 8241
Protoss_Gateway 4 15380
Protoss_Zealot 6 15564
Protoss_Assimilator 2 11562
Protoss_Cybernetics_Core 1 11016
Protoss_Dragoon 1 12250
Protoss_Stargate 1 13250
Protoss_Citadel_of_Adun 1 14000
Protoss_Corsair 2 15242
15564
