Protoss_Forge 1 4542
Protoss_Photon_Cannon 3 14460
Protoss_Nexus 1 8875
Protoss_Gateway 4 15861
Protoss_Assimilator 2 11098
Protoss_Cybernetics_Core 1 9348
Protoss_Zealot 4 13583
Protoss_Stargate 1 11132
Protoss_Dragoon 1 11068
Protoss_Citadel_of_Adun 1 12116
Protoss_Corsair 1 12087
Protoss_Templar_Archives 1 13776
Protoss_Dark_Templar 2 15133
15861
