Protoss_Gateway 2 13599
Protoss_Assimilator 1 4391
Protoss_Zealot 6 13428
Protoss_Cybernetics_Core 1 7253
Protoss_Stargate 1 9378
Protoss_Dragoon 1 8905
Protoss_Citadel_of_Adun 1 9504
Protoss_Corsair 2 11200
Protoss_Templar_Archives 1 11527
Protoss_Forge 1 12191
Protoss_Dark_Templar 2 15607
Protoss_Photon_Cannon 1 14297
Protoss_High_Templar 1 15604
15607
