Protoss_Forge 1 4172
Protoss_Photon_Cannon 2 5577
Protoss_Nexus 1 8610
Protoss_Gateway 3 12924
Protoss_Assimilator 2 10928
Protoss_Cybernetics_Core 1 9548
Protoss_Zealot 10 15538
Protoss_Citadel_of_Adun 1 11052
Protoss_Stargate 2 15132
Leg_Enhancements 1 14141
15538
