Protoss_Gateway 2 4928
Protoss_Zealot 12 14768
Protoss_Nexus 1 9505
Protoss_Assimilator 1 8124
Protoss_Cybernetics_Core 1 9691
Protoss_Stargate 1 11470
Protoss_Dragoon 1 11392
Protoss_Forge 1 11809
Protoss_Corsair 3 14496
Protoss_Photon_Cannon 5 15440
15440
