Protoss_Gateway 2 4773
Protoss_Zealot 13 15314
Protoss_Assimilator 1 5737
Protoss_Cybernetics_Core 1 6880
Protoss_Stargate 1 8737
Protoss_Dragoon 1 8954
Protoss_Corsair 2 11437
Protoss_Nexus 1 14481
Protoss_Forge 1 13565
Protoss_Citadel_of_Adun 1 14810
Protoss_Photon_Cannon 1 15642
15642
