Protoss_Gateway 2 5033
Protoss_Zealot 9 15427
Protoss_Nexus 2 16114
Protoss_Assimilator 1 7568
Protoss_Cybernetics_Core 1 9315
Protoss_Stargate 1 11124
Protoss_Dragoon 2 11319
Protoss_Citadel_of_Adun 1 12326
Protoss_Corsair 2 13050
Protoss_Forge 1 12615
Protoss_Photon_Cannon 1 15212
16114
