Protoss_Forge 1 4905
Protoss_Nexus 1 7445
Protoss_Photon_Cannon 4 14919
Protoss_Gateway 4 15371
Protoss_Assimilator 2 9718
Protoss_Cybernetics_Core 1 9348
Protoss_Zealot 3 12411
Protoss_Stargate 1 11028
Protoss_Dragoon 1 10585
Protoss_Citadel_of_Adun 1 11584
Protoss_Corsair 3 13998
Protoss_Templar_Archives 1 13035
Protoss_Dark_Templar 2 14384
Protoss_High_Templar 2 15601
15601
