Protoss_Forge 1 4312
Protoss_Photon_Cannon 8 14969
Protoss_Nexus 1 8839
Protoss_Gateway 2 14213
Protoss_Assimilator 2 14197
Protoss_Zealot 6 15172
Protoss_Cybernetics_Core 1 11373
Protoss_Citadel_of_Adun 1 13081
Protoss_Templar_Archives 1 14894
15172
