Protoss_Forge 2 10594
Protoss_Photon_Cannon 4 12988
Protoss_Gateway 2 7512
Protoss_Zealot 4 14025
Protoss_Nexus 1 11961
Protoss_Assimilator 2 15147
Protoss_Cybernetics_Core 1 12438
Protoss_Stargate 2 15306
Protoss_Dragoon 1 13997
Protoss_Corsair 1 15052
15306
