Protoss_Forge 1 4511
Protoss_Photon_Cannon 2 6022
Protoss_Nexus 1 9139
Protoss_Gateway 4 15495
Protoss_Assimilator 2 11639
Protoss_Zealot 2 15403
Protoss_Cybernetics_Core 1 11336
Protoss_Stargate 1 13042
Protoss_Dragoon 1 12774
Protoss_Citadel_of_Adun 1 14389
Protoss_Corsair 1 14022
15495
