Protoss_Forge 1 4066
Protoss_Photon_Cannon 3 6058
Protoss_Gateway 2 8430
Protoss_Zealot 10 12927
Protoss_Nexus 1 15363
Protoss_Assimilator 2 14922
Protoss_Cybernetics_Core 1 15141
15363
