Protoss_Gateway 3 12794
Protoss_Zealot 13 14753
Protoss_Nexus 1 8417
Protoss_Assimilator 2 11260
Protoss_Forge 1 7962
Protoss_Cybernetics_Core 1 9011
Protoss_Photon_Cannon 3 15654
Protoss_Stargate 1 10850
Protoss_Citadel_of_Adun 1 11401
Protoss_Corsair 2 14309
Protoss_Templar_Archives 1 14086
Leg_Enhancements 1 14548
15654
