Protoss_Forge 1 3765
Protoss_Photon_Cannon 5 14931
Protoss_Nexus 1 8853
Protoss_Gateway 4 15813
Protoss_Assimilator 2 10397
Protoss_Zealot 4 11816
Protoss_Cybernetics_Core 1 9449
Protoss_Citadel_of_Adun 1 10968
Protoss_Templar_Archives 1 12465
Protoss_High_Templar 4 14829
Protoss_Dark_Templar 1 15189
Protoss_Archon 1 14479
15813
