Protoss_Forge 1 3828
Protoss_Nexus 1 7755
Protoss_Gateway 2 13284
Protoss_Assimilator 2 10088
Protoss_Photon_Cannon 2 13383
Protoss_Cybernetics_Core 1 8661
Protoss_Zealot 3 12877
Protoss_Stargate 1 10431
Protoss_Dragoon 1 10634
Protoss_Citadel_of_Adun 1 11028
Protoss_Corsair 4 14549
Protoss_Templar_Archives 1 12924
Protoss_Dark_Templar 2 14984
Protoss_Robotics_Facility 1 16265
16265
