Protoss_Forge 1 3876
Protoss_Nexus 1 7459
Protoss_Photon_Cannon 2 8346
Protoss_Gateway 4 15869
Protoss_Assimilator 2 14199
Protoss_Zealot 5 13469
Protoss_Cybernetics_Core 1 10457
Protoss_Stargate 1 12167
Protoss_Citadel_of_Adun 1 13313
Protoss_Corsair 1 13182
15869
