Protoss_Gateway 2 8954
Protoss_Assimilator 1 4207
Protoss_Cybernetics_Core 1 5648
Protoss_Zealot 11 13723
Protoss_Stargate 1 7338
Protoss_Dragoon 1 7930
Protoss_Corsair 1 8273
Protoss_Citadel_of_Adun 1 10739
Protoss_Templar_Archives 1 13331
Protoss_Dark_Templar 2 14913
Leg_Enhancements 1 14164
14913
