Protoss_Forge 1 4331
Protoss_Nexus 1 7833
Protoss_Photon_Cannon 1 6470
Protoss_Gateway 5 16024
Protoss_Assimilator 2 14405
Protoss_Zealot 8 14879
Protoss_Cybernetics_Core 1 9564
Protoss_Stargate 1 11394
Protoss_Citadel_of_Adun 1 12576
Protoss_Corsair 1 12722
16024
