Protoss_Forge 1 4812
Protoss_Nexus 1 7666
Protoss_Photon_Cannon 3 11477
Protoss_Gateway 6 15693
Protoss_Assimilator 2 11376
Protoss_Cybernetics_Core 1 9241
Protoss_Zealot 6 14607
Protoss_Stargate 1 10944
Protoss_Citadel_of_Adun 1 11287
Protoss_Corsair 2 15412
Protoss_Templar_Archives 1 14569
Leg_Enhancements 1 14580
15693
