Protoss_Forge 1 4870
Protoss_Nexus 1 7544
Protoss_Photon_Cannon 4 15108
Protoss_Gateway 3 15096
Protoss_Assimilator 2 10031
Protoss_Zealot 3 10773
Protoss_Cybernetics_Core 1 10395
Protoss_Stargate 1 12204
Protoss_Dragoon 5 15358
Protoss_Corsair 3 15348
15358
