Protoss_Forge 1 4736
Protoss_Nexus 1 7689
Protoss_Photon_Cannon 3 15273
Protoss_Gateway 4 15011
Protoss_Assimilator 2 10047
Protoss_Cybernetics_Core 1 9307
Protoss_Zealot 4 13220
Protoss_Stargate 1 11210
Protoss_Dragoon 1 10991
Protoss_Citadel_of_Adun 1 11941
Protoss_Corsair 2 14900
Protoss_Templar_Archives 1 13575
Protoss_Dark_Templar 2 14846
15273
