Protoss_Forge 1 3970
Protoss_Nexus 1 7623
Protoss_Gateway 2 15577
Protoss_Assimilator 3 10332
Protoss_Photon_Cannon 5 15402
Protoss_Zealot 6 13978
Protoss_Cybernetics_Core 1 9368
Protoss_Stargate 1 11251
Protoss_Dragoon 1 11132
Protoss_Citadel_of_Adun 1 12437
Protoss_Corsair 1 12620
Protoss_Templar_Archives 1 13982
Protoss_Dark_Templar 1 15224
15577
