Protoss_Forge 1 4283
Protoss_Photon_Cannon 5 15547
Protoss_Nexus 1 8051
Protoss_Gateway 2 13019
Protoss_Assimilator 2 12080
Protoss_Zealot 7 14759
Protoss_Cybernetics_Core 1 10114
Protoss_Stargate 1 12000
Protoss_Dragoon 1 11978
Protoss_Corsair 1 12948
Protoss_Citadel_of_Adun 1 14117
Protoss_Templar_Archives 1 15567
15567
