Protoss_Forge 1 4114
Protoss_Photon_Cannon 3 14240
Protoss_Nexus 1 8752
Protoss_Gateway 3 15795
Protoss_Assimilator 2 10485
Protoss_Cybernetics_Core 1 9239
Protoss_Zealot 7 14592
Protoss_Stargate 1 11023
Protoss_Citadel_of_Adun 1 11772
Protoss_Corsair 2 14993
Protoss_Templar_Archives 1 14663
15795
