Protoss_Forge 1 4788
Protoss_Nexus 1 7597
Protoss_Photon_Cannon 3 14414
Protoss_Gateway 3 15923
Protoss_Assimilator 2 10322
Protoss_Cybernetics_Core 1 9052
Protoss_Zealot 5 13861
Protoss_Stargate 1 10791
Protoss_Citadel_of_Adun 1 12182
Protoss_Corsair 5 15538
Protoss_Templar_Archives 1 13676
Protoss_Dark_Templar 2 15066
15923
