Protoss_Forge 1 4662
Protoss_Photon_Cannon 2 6028
Protoss_Nexus 1 9150
Protoss_Gateway 2 12917
Protoss_Assimilator 2 11297
Protoss_Cybernetics_Core 1 9569
Protoss_Zealot 8 15026
Protoss_Stargate 1 11481
Protoss_Citadel_of_Adun 1 12012
Protoss_Corsair 1 12462
Protoss_Templar_Archives 1 13811
Protoss_Robotics_Facility 1 15098
Protoss_Dark_Templar 1 15543
15543
