Protoss_Forge 1 4804
Protoss_Nexus 1 7677
Protoss_Photon_Cannon 2 14608
Protoss_Gateway 4 15649
Protoss_Assimilator 2 9648
Protoss_Cybernetics_Core 1 8894
Protoss_Zealot 8 15327
Protoss_Stargate 1 10800
Protoss_Citadel_of_Adun 1 11961
Protoss_Corsair 3 13656
Protoss_Templar_Archives 1 14609
15649
