Protoss_Forge 1 4619
Protoss_Nexus 1 7702
Protoss_Photon_Cannon 4 14744
Protoss_Gateway 3 16018
Protoss_Assimilator 3 14792
Protoss_Cybernetics_Core 1 9409
Protoss_Zealot 4 13729
Protoss_Stargate 1 11245
Protoss_Citadel_of_Adun 1 11938
Protoss_Corsair 2 13782
Protoss_Templar_Archives 1 13668
Protoss_High_Templar 2 15051
16018
