Protoss_Nexus 1 7143
Protoss_Gateway 4 14553
Protoss_Forge 1 6552
Protoss_Assimilator 2 13789
Protoss_Photon_Cannon 2 8622
Protoss_Zealot 9 14982
Protoss_Cybernetics_Core 1 10249
Protoss_Citadel_of_Adun 1 12045
Protoss_Dragoon 1 11840
Protoss_Templar_Archives 1 14105
14982
