Protoss_Forge 1 4343
Protoss_Photon_Cannon 2 6123
Protoss_Nexus 1 8626
Protoss_Gateway 4 15277
Protoss_Assimilator 2 11266
Protoss_Cybernetics_Core 1 9260
Protoss_Zealot 8 15058
Protoss_Stargate 1 11018
Protoss_Dragoon 1 11085
Protoss_Corsair 3 14376
Protoss_Citadel_of_Adun 1 12830
Protoss_Templar_Archives 1 15904
15904
