Protoss_Forge 1 4489
Protoss_Photon_Cannon 4 15338
Protoss_Nexus 1 8826
Protoss_Gateway 4 15778
Protoss_Assimilator 2 12706
Protoss_Cybernetics_Core 1 9463
Protoss_Zealot 10 15473
Protoss_Dragoon 1 10705
Protoss_Citadel_of_Adun 2 12119
Protoss_Templar_Archives 1 14844
Leg_Enhancements 1 14200
15778
