Protoss_Forge 1 4527
Protoss_Photon_Cannon 3 14287
Protoss_Nexus 1 8838
Protoss_Gateway 4 14133
Protoss_Assimilator 2 10034
Protoss_Cybernetics_Core 1 9160
Protoss_Zealot 3 12661
Protoss_Stargate 1 11192
Protoss_Citadel_of_Adun 1 11515
Protoss_Corsair 1 12222
Protoss_Templar_Archives 1 13027
Protoss_High_Templar 4 15347
15347
