Protoss_Forge 1 4755
Protoss_Nexus 1 7631
Protoss_Photon_Cannon 2 13424
Protoss_Gateway 2 14086
Protoss_Assimilator 2 9930
Protoss_Zealot 4 12064
Protoss_Cybernetics_Core 1 9520
Protoss_Stargate 1 11271
Protoss_Citadel_of_Adun 1 12162
Protoss_Dragoon 1 12420
Protoss_Corsair 4 15113
Protoss_Templar_Archives 1 14218
Protoss_Dark_Templar 2 15449
15449
