Protoss_Forge 1 4050
Protoss_Photon_Cannon 1 5524
Protoss_Nexus 1 8349
Protoss_Gateway 1 7378
Protoss_Assimilator 2 11762
Protoss_Zealot 6 15403
Protoss_Cybernetics_Core 1 9852
Protoss_Dragoon 1 11268
Protoss_Stargate 2 15141
Protoss_Robotics_Facility 1 13412
Protoss_Corsair 3 15067
Protoss_Shuttle 1 15105
Protoss_Robotics_Support_Bay 1 14697
15403
