Protoss_Forge 1 4027
Protoss_Nexus 1 7528
Protoss_Gateway 5 15159
Protoss_Photon_Cannon 3 13194
Protoss_Assimilator 2 10553
Protoss_Cybernetics_Core 1 9195
Protoss_Zealot 3 12696
Protoss_Citadel_of_Adun 1 10714
Protoss_Templar_Archives 1 12204
Protoss_High_Templar 2 14515
Protoss_Dark_Templar 1 14507
15159
