Protoss_Forge 1 4650
Protoss_Nexus 1 7465
Protoss_Photon_Cannon 3 13639
Protoss_Gateway 1 7501
Protoss_Assimilator 2 9951
Protoss_Zealot 6 15558
Protoss_Cybernetics_Core 1 9263
Protoss_Stargate 1 10982
Protoss_Robotics_Facility 1 12114
Protoss_Corsair 5 15526
Protoss_Shuttle 1 13805
Protoss_Robotics_Support_Bay 1 13754
Protoss_Reaver 1 15665
Protoss_Citadel_of_Adun 1 15890
15890
