Protoss_Forge 1 4350
Protoss_Nexus 1 7617
Protoss_Photon_Cannon 3 14545
Protoss_Gateway 2 12469
Protoss_Assimilator 2 9236
Protoss_Cybernetics_Core 1 9424
Protoss_Zealot 7 14993
Protoss_Stargate 1 11138
Protoss_Dragoon 1 10790
Protoss_Citadel_of_Adun 1 11717
Protoss_Corsair 3 14654
Protoss_Templar_Archives 1 15203
15203
