Protoss_Gateway 2 5063
Protoss_Zealot 14 13855
Protoss_Nexus 2 16433
Protoss_Assimilator 1 8019
Protoss_Cybernetics_Core 1 9684
Protoss_Stargate 1 11424
Protoss_Dragoon 1 11053
Protoss_Forge 1 11417
Protoss_Corsair 3 14636
Protoss_Photon_Cannon 6 15712
16433
