Protoss_Gateway 2 5007
Protoss_Zealot 10 11388
Protoss_Nexus 2 13031
Protoss_Assimilator 2 14060
Protoss_Cybernetics_Core 1 12093
Protoss_Forge 1 12478
Protoss_Stargate 1 13786
Protoss_Photon_Cannon 1 13775
Protoss_Robotics_Facility 1 15475
Protoss_Corsair 1 14724
15475
