Protoss_Forge 1 4281
Protoss_Nexus 1 7657
Protoss_Photon_Cannon 3 15544
Protoss_Gateway 3 14727
Protoss_Assimilator 2 10170
Protoss_Cybernetics_Core 1 9138
Protoss_Zealot 3 12699
Protoss_Stargate 1 10818
Protoss_Citadel_of_Adun 1 11009
Protoss_Corsair 5 15582
Protoss_Templar_Archives 1 12605
Protoss_Dark_Templar 2 15350
15582
