Protoss_Gateway 2 9263
Protoss_Assimilator 1 4394
Protoss_Cybernetics_Core 1 5633
Protoss_Zealot 15 15321
Protoss_Stargate 1 7475
Protoss_Dragoon 1 7315
Protoss_Corsair 1 8426
Protoss_Citadel_of_Adun 1 11491
Protoss_Forge 2 12851
Protoss_Templar_Archives 1 14437
Leg_Enhancements 1 14425
Protoss_Dark_Templar 1 15689
15689
