Protoss_Forge 1 4218
Protoss_Photon_Cannon 3 15487
Protoss_Nexus 1 8051
Protoss_Gateway 1 7401
Protoss_Assimilator 2 11688
Protoss_Cybernetics_Core 1 9207
Protoss_Zealot 6 15512
Protoss_Stargate 1 11059
Protoss_Citadel_of_Adun 1 12340
Protoss_Corsair 3 14350
Protoss_Templar_Archives 1 13790
Protoss_Robotics_Facility 1 16380
16380
