Protoss_Forge 1 4884
Protoss_Nexus 1 7553
Protoss_Photon_Cannon 3 14322
Protoss_Gateway 1 8149
Protoss_Assimilator 2 9693
Protoss_Cybernetics_Core 1 9590
Protoss_Zealot 3 12620
Protoss_Stargate 2 11889
Protoss_Corsair 7 15462
Protoss_Citadel_of_Adun 1 13878
Protoss_Templar_Archives 1 15432
15462
