Protoss_Forge 1 4255
Protoss_Nexus 1 7799
Protoss_Photon_Cannon 2 7026
Protoss_Gateway 4 14787
Protoss_Assimilator 2 11013
Protoss_Cybernetics_Core 1 9659
Protoss_Zealot 4 12482
Protoss_Stargate 1 11400
Protoss_Citadel_of_Adun 1 12181
Protoss_Corsair 2 13501
Protoss_Templar_Archives 1 13777
14787
