Protoss_Nexus 1 6933
Protoss_Forge 1 5977
Protoss_Gateway 2 14493
Protoss_Assimilator 2 10442
Protoss_Photon_Cannon 4 15559
Protoss_Cybernetics_Core 1 8581
Protoss_Zealot 7 14601
Protoss_Stargate 1 10279
Protoss_Citadel_of_Adun 1 11187
Protoss_Corsair 1 11320
Protoss_Templar_Archives 1 14273
Protoss_Dark_Templar 2 15789
15789
