Protoss_Forge 1 4242
Protoss_Photon_Cannon 2 14388
Protoss_Nexus 1 8301
Protoss_Gateway 2 13789
Protoss_Assimilator 2 9567
Protoss_Cybernetics_Core 1 8859
Protoss_Zealot 3 12629
Protoss_Stargate 1 10692
Protoss_Citadel_of_Adun 1 12059
Protoss_Corsair 4 14835
Protoss_Templar_Archives 1 13548
Protoss_Dark_Templar 2 15098
15098
