Protoss_Forge 1 4867
Protoss_Nexus 1 7817
Protoss_Photon_Cannon 2 15148
Protoss_Gateway 2 13312
Protoss_Assimilator 2 11651
Protoss_Cybernetics_Core 1 9394
Protoss_Zealot 8 15318
Protoss_Stargate 1 11217
Protoss_Citadel_of_Adun 1 11494
Protoss_Dragoon 1 11586
Protoss_Corsair 1 12588
15318
