Protoss_Forge 1 4249
Protoss_Nexus 1 7863
Protoss_Gateway 4 13492
Protoss_Assimilator 2 11127
Protoss_Cybernetics_Core 1 8509
Protoss_Photon_Cannon 4 15671
Protoss_Zealot 10 15055
Protoss_Stargate 1 10515
Protoss_Citadel_of_Adun 1 11475
Protoss_Corsair 2 15263
Leg_Enhancements 1 14422
15671
