Protoss_Forge 1 4521
Protoss_Photon_Cannon 4 10263
Protoss_Nexus 1 8692
Protoss_Gateway 1 7978
Protoss_Assimilator 2 14294
Protoss_Cybernetics_Core 1 12744
Protoss_Zealot 3 14704
Protoss_Stargate 1 14759
Protoss_Citadel_of_Adun 1 15235
15235
