Protoss_Forge 1 4741
Protoss_Nexus 1 7585
Protoss_Photon_Cannon 2 7154
Protoss_Gateway 2 14938
Protoss_Assimilator 2 9785
Protoss_Cybernetics_Core 1 9384
Protoss_Zealot 4 14707
Protoss_Stargate 1 11444
Protoss_Citadel_of_Adun 1 12078
Protoss_Corsair 3 14554
14938
