Protoss_Forge 1 3873
Protoss_Nexus 1 7629
Protoss_Gateway 4 12062
Protoss_Assimilator 2 14298
Protoss_Photon_Cannon 2 14249
Protoss_Cybernetics_Core 1 8648
Protoss_Zealot 11 14862
Protoss_Stargate 1 10550
Protoss_Corsair 2 12664
Protoss_Citadel_of_Adun 1 14247
14862
