Protoss_Forge 1 4862
Protoss_Nexus 1 7713
Protoss_Photon_Cannon 3 14744
Protoss_Gateway 4 16037
Protoss_Assimilator 2 10293
Protoss_Cybernetics_Core 1 9131
Protoss_Zealot 8 15462
Protoss_Stargate 1 10867
Protoss_Corsair 2 12706
Protoss_Citadel_of_Adun 1 13466
Protoss_Templar_Archives 1 15789
16037
