Protoss_Forge 1 4191
Protoss_Photon_Cannon 3 15292
Protoss_Nexus 1 8654
Protoss_Gateway 2 13751
Protoss_Assimilator 2 9656
Protoss_Cybernetics_Core 1 9100
Protoss_Zealot 8 14914
Protoss_Stargate 1 10847
Protoss_Citadel_of_Adun 1 12153
Protoss_Corsair 4 14762
Protoss_Templar_Archives 1 15749
15749
