Protoss_Nexus 1 7214
Protoss_Gateway 6 16032
Protoss_Forge 1 6245
Protoss_Assimilator 2 9810
Protoss_Photon_Cannon 3 15017
Protoss_Cybernetics_Core 1 8967
Protoss_Zealot 7 13960
Protoss_Stargate 1 10802
Protoss_Citadel_of_Adun 1 11303
Protoss_Corsair 1 11739
Protoss_Templar_Archives 1 12841
Protoss_High_Templar 4 15657
Protoss_Archon 1 15081
16032
