Protoss_Forge 1 4110
Protoss_Nexus 1 7691
Protoss_Gateway 3 14556
Protoss_Photon_Cannon 3 14287
Protoss_Assimilator 2 10733
Protoss_Cybernetics_Core 1 8844
Protoss_Zealot 7 15058
Protoss_Stargate 1 11090
Protoss_Citadel_of_Adun 1 11709
Protoss_Corsair 2 14560
Protoss_Templar_Archives 1 14799
15058
