Protoss_Forge 1 4410
Protoss_Photon_Cannon 2 14660
Protoss_Nexus 1 8097
Protoss_Gateway 4 14524
Protoss_Assimilator 2 9497
Protoss_Cybernetics_Core 1 8711
Protoss_Zealot 4 12699
Protoss_Stargate 1 10655
Protoss_Citadel_of_Adun 1 11227
Protoss_Corsair 3 13410
Protoss_Templar_Archives 1 12760
Protoss_Dark_Templar 2 13968
14660
