Protoss_Nexus 1 6862
Protoss_Gateway 1 6075
Protoss_Forge 1 6190
Protoss_Assimilator 2 10316
Protoss_Photon_Cannon 5 14325
Protoss_Cybernetics_Core 1 9020
Protoss_Zealot 3 13293
Protoss_Stargate 1 10718
Protoss_Corsair 5 15310
Protoss_Robotics_Facility 1 13513
Protoss_Shuttle 1 14929
Protoss_Robotics_Support_Bay 1 14489
15310
