Protoss_Forge 1 4599
Protoss_Nexus 1 7569
Protoss_Photon_Cannon 3 14233
Protoss_Gateway 4 15523
Protoss_Assimilator 2 11246
Protoss_Cybernetics_Core 1 9011
Protoss_Zealot 8 15447
Protoss_Stargate 1 10955
Protoss_Corsair 2 12842
Protoss_Citadel_of_Adun 1 12535
15523
