Protoss_Forge 1 4313
Protoss_Nexus 1 7896
Protoss_Gateway 2 13164
Protoss_Assimilator 2 10577
Protoss_Photon_Cannon 2 14539
Protoss_Cybernetics_Core 1 8925
Protoss_Zealot 4 12315
Protoss_Stargate 1 10664
Protoss_Citadel_of_Adun 1 11335
Protoss_Corsair 4 15216
Protoss_Templar_Archives 1 12987
Protoss_Robotics_Facility 1 14638
Protoss_Dark_Templar 2 14676
15216
