Protoss_Forge 1 4963
Protoss_Nexus 1 7641
Protoss_Photon_Cannon 2 14489
Protoss_Gateway 2 13670
Protoss_Assimilator 2 9987
Protoss_Cybernetics_Core 1 8988
Protoss_Zealot 3 12078
Protoss_Stargate 1 11031
Protoss_Citadel_of_Adun 1 12204
Protoss_Corsair 4 15096
Protoss_Templar_Archives 1 13714
Protoss_Dark_Templar 2 14951
15096
