Protoss_Forge 1 4371
Protoss_Nexus 1 7574
Protoss_Photon_Cannon 2 14381
Protoss_Gateway 4 16049
Protoss_Assimilator 2 10255
Protoss_Cybernetics_Core 1 8458
Protoss_Zealot 4 12020
Protoss_Stargate 1 10569
Protoss_Citadel_of_Adun 1 11172
Protoss_Corsair 5 15307
Protoss_Templar_Archives 1 12798
Protoss_Dark_Templar 2 14044
16049
