Protoss_Nexus 1 6600
Protoss_Forge 1 5175
Protoss_Photon_Cannon 3 15682
Protoss_Gateway 4 15286
Protoss_Assimilator 2 9238
Protoss_Cybernetics_Core 1 8594
Protoss_Zealot 9 15204
Protoss_Stargate 1 10387
Protoss_Citadel_of_Adun 1 11528
Protoss_Corsair 3 15266
Protoss_Templar_Archives 1 14982
Leg_Enhancements 1 14460
15682
