Protoss_Forge 1 4327
Protoss_Photon_Cannon 3 14040
Protoss_Nexus 1 9085
Protoss_Assimilator 2 10205
Protoss_Gateway 2 12901
Protoss_Zealot 8 15163
Protoss_Cybernetics_Core 1 10043
Protoss_Stargate 1 11807
Protoss_Citadel_of_Adun 1 11923
Protoss_Corsair 1 12743
Protoss_Templar_Archives 1 15290
Protoss_Ground_Weapons_1 1 14565
15290
