Protoss_Forge 1 4349
Protoss_Photon_Cannon 2 5829
Protoss_Nexus 1 8718
Protoss_Gateway 2 12994
Protoss_Assimilator 2 11227
Protoss_Cybernetics_Core 1 9143
Protoss_Zealot 9 15064
Protoss_Stargate 1 10876
Protoss_Corsair 2 12968
Protoss_Citadel_of_Adun 1 12716
Protoss_Templar_Archives 1 14827
15064
