Protoss_Nexus 1 7176
Protoss_Forge 1 6438
Protoss_Gateway 4 14923
Protoss_Photon_Cannon 3 15392
Protoss_Assimilator 2 9651
Protoss_Cybernetics_Core 1 9334
Protoss_Zealot 9 14958
Protoss_Stargate 1 11150
Protoss_Citadel_of_Adun 1 12024
Protoss_Corsair 2 12965
Protoss_Templar_Archives 1 14253
Protoss_Dark_Templar 2 15461
15461
