Protoss_Forge 1 4480
Protoss_Nexus 1 8165
Protoss_Gateway 1 7593
Protoss_Assimilator 2 9757
Protoss_Photon_Cannon 8 15294
Protoss_Cybernetics_Core 1 9182
Protoss_Zealot 4 14944
Protoss_Stargate 1 10961
Protoss_Citadel_of_Adun 1 11900
Protoss_Corsair 5 15558
Protoss_Robotics_Facility 1 15480
15558
