Protoss_Forge 1 4567
Protoss_Photon_Cannon 2 6294
Protoss_Nexus 1 8942
Protoss_Gateway 3 14578
Protoss_Assimilator 2 10672
Protoss_Zealot 5 14794
Protoss_Cybernetics_Core 1 9418
Protoss_Dragoon 1 10696
Protoss_Stargate 1 11435
Protoss_Citadel_of_Adun 1 12781
Protoss_Corsair 3 15301
15301
