Protoss_Forge 1 4851
Protoss_Photon_Cannon 3 15058
Protoss_Nexus 1 9075
Protoss_Gateway 3 15691
Protoss_Assimilator 2 11288
Protoss_Cybernetics_Core 1 9431
Protoss_Zealot 8 15427
Protoss_Dragoon 1 10631
Protoss_Stargate 1 11456
Protoss_Citadel_of_Adun 1 12614
Protoss_Corsair 2 13454
Protoss_Templar_Archives 1 15596
15691
