Protoss_Forge 1 4833
Protoss_Nexus 1 7852
Protoss_Photon_Cannon 3 14504
Protoss_Gateway 3 11979
Protoss_Assimilator 2 12744
Protoss_Cybernetics_Core 1 9184
Protoss_Zealot 12 15371
Protoss_Citadel_of_Adun 1 11101
Protoss_Stargate 2 13970
Protoss_Corsair 2 15394
Leg_Enhancements 1 14115
Protoss_Ground_Weapons_1 1 14519
15394
