Protoss_Gateway 2 4738
Protoss_Zealot 11 14712
Protoss_Shield_Battery 1 9276
Protoss_Forge 1 9621
Protoss_Photon_Cannon 4 13738
Protoss_Assimilator 1 12144
Protoss_Cybernetics_Core 1 13615
Protoss_Stargate 1 15666
15666
