Protoss_Nexus 1 7108
Protoss_Gateway 1 6532
Protoss_Forge 1 6637
Protoss_Assimilator 2 11167
Protoss_Photon_Cannon 4 12534
Protoss_Zealot 4 14136
Protoss_Cybernetics_Core 1 10041
Protoss_Stargate 1 11819
Protoss_Dragoon 1 11530
Protoss_Robotics_Facility 1 12843
Protoss_Corsair 4 15471
Protoss_Shuttle 1 14273
Protoss_Robotics_Support_Bay 1 15041
15471
