Protoss_Forge 1 4278
Protoss_Photon_Cannon 3 14681
Protoss_Nexus 1 8790
Protoss_Gateway 3 13344
Protoss_Assimilator 2 10403
Protoss_Zealot 7 14777
Protoss_Cybernetics_Core 1 9416
Protoss_Stargate 1 11206
Protoss_Citadel_of_Adun 1 11911
Protoss_Corsair 3 15011
Protoss_Templar_Archives 1 14259
15011
