Protoss_Forge 1 4489
Protoss_Photon_Cannon 3 7956
Protoss_Nexus 1 8738
Protoss_Gateway 4 15345
Protoss_Assimilator 2 10600
Protoss_Zealot 5 13337
Protoss_Cybernetics_Core 1 10198
Protoss_Stargate 1 11986
Protoss_Citadel_of_Adun 1 12864
Protoss_Corsair 1 12930
Protoss_Templar_Archives 1 14317
Protoss_High_Templar 2 15680
15680
