Protoss_Forge 1 4376
Protoss_Photon_Cannon 2 5653
Protoss_Nexus 1 9006
Protoss_Gateway 4 15816
Protoss_Assimilator 2 9934
Protoss_Cybernetics_Core 1 9187
Protoss_Zealot 8 15152
Protoss_Stargate 1 10961
Protoss_Citadel_of_Adun 1 11759
Protoss_Corsair 2 12848
Protoss_Templar_Archives 1 14519
15816
