Protoss_Nexus 1 7053
Protoss_Forge 1 5752
Protoss_Gateway 1 6984
Protoss_Photon_Cannon 3 14698
Protoss_Assimilator 2 9408
Protoss_Cybernetics_Core 1 8868
Protoss_Zealot 7 15195
Protoss_Stargate 1 10829
Protoss_Citadel_of_Adun 1 11797
Protoss_Corsair 4 14654
Protoss_Robotics_Facility 1 14135
Protoss_Robotics_Support_Bay 1 14837
15195
