Protoss_Gateway 4 15953
Protoss_Zealot 7 13196
Protoss_Nexus 1 9422
Protoss_Assimilator 2 11759
Protoss_Cybernetics_Core 1 10114
Protoss_Forge 1 10287
Protoss_Stargate 1 12334
Protoss_Photon_Cannon 3 15172
Protoss_Dragoon 1 12335
Protoss_Citadel_of_Adun 1 13499
Protoss_Corsair 1 13413
Protoss_Templar_Archives 1 14988
15953
