Protoss_Forge 1 4201
Protoss_Nexus 1 7670
Protoss_Gateway 2 12860
Protoss_Assimilator 2 9225
Protoss_Photon_Cannon 2 14195
Protoss_Zealot 10 15564
Protoss_Cybernetics_Core 1 9090
Protoss_Stargate 1 10824
Protoss_Citadel_of_Adun 1 11554
Protoss_Corsair 4 15304
Leg_Enhancements 1 14513
15564
