Protoss_Forge 1 4378
Protoss_Photon_Cannon 1 5692
Protoss_Nexus 1 8299
Protoss_Gateway 4 15731
Protoss_Assimilator 2 11863
Protoss_Zealot 8 14707
Protoss_Cybernetics_Core 1 9419
Protoss_Stargate 1 11214
Protoss_Citadel_of_Adun 1 11944
Protoss_Corsair 3 13700
Protoss_Ground_Weapons_1 1 14524
15731
