Protoss_Forge 1 4846
Protoss_Photon_Cannon 2 15477
Protoss_Nexus 1 8340
Protoss_Gateway 3 11982
Protoss_Assimilator 2 10062
Protoss_Cybernetics_Core 1 9222
Protoss_Zealot 12 15034
Protoss_Dragoon 1 10424
Protoss_Citadel_of_Adun 1 11219
Protoss_Stargate 2 15022
Leg_Enhancements 1 14156
Protoss_Ground_Weapons_1 1 14630
15477
