Protoss_Forge 1 4066
Protoss_Photon_Cannon 3 15101
Protoss_Nexus 1 8106
Protoss_Gateway 2 13861
Protoss_Assimilator 2 11168
Protoss_Zealot 5 13679
Protoss_Cybernetics_Core 1 10447
Protoss_Stargate 1 12155
Protoss_Citadel_of_Adun 1 12768
Protoss_Corsair 2 14903
Protoss_Templar_Archives 1 14478
15101
