Protoss_Forge 1 4290
Protoss_Photon_Cannon 3 14839
Protoss_Nexus 1 8393
Protoss_Gateway 1 7501
Protoss_Assimilator 2 10312
Protoss_Zealot 4 13583
Protoss_Cybernetics_Core 1 9636
Protoss_Stargate 1 11554
Protoss_Dragoon 1 11498
Protoss_Corsair 4 15435
Protoss_Robotics_Facility 1 14066
15435
