Protoss_Nexus 1 6884
Protoss_Forge 1 5443
Protoss_Photon_Cannon 4 15257
Protoss_Gateway 5 13913
Protoss_Assimilator 2 9825
Protoss_Cybernetics_Core 1 9349
Protoss_Zealot 3 11402
Protoss_Stargate 1 11090
Protoss_Citadel_of_Adun 1 11450
Protoss_Corsair 2 14967
Protoss_Templar_Archives 1 12965
Protoss_High_Templar 4 14714
Protoss_Archon 1 15057
15257
