Protoss_Forge 1 4316
Protoss_Nexus 1 7855
Protoss_Gateway 5 15440
Protoss_Assimilator 2 9449
Protoss_Photon_Cannon 2 12860
Protoss_Cybernetics_Core 1 8806
Protoss_Zealot 4 12134
Protoss_Stargate 1 10610
Protoss_Citadel_of_Adun 1 11080
Protoss_Corsair 1 11619
Protoss_Templar_Archives 1 13196
Protoss_High_Templar 4 15092
15440
