Protoss_Gateway 2 12563
Protoss_Assimilator 1 4467
Protoss_Cybernetics_Core 1 5813
Protoss_Robotics_Facility 1 7988
Protoss_Dragoon 3 11524
Protoss_Zealot 1 8603
Protoss_Shuttle 1 9406
Protoss_Observatory 1 9246
Protoss_Observer 2 11600
Protoss_Stargate 1 11421
Protoss_Corsair 4 15276
Protoss_Robotics_Support_Bay 1 12774
Protoss_Forge 1 13630
Protoss_Nexus 1 17074
Protoss_Reaver 1 16105
17074
