Protoss_Gateway 2 4998
Protoss_Zealot 17 14271
Protoss_Assimilator 1 9589
Protoss_Forge 1 11799
Protoss_Cybernetics_Core 1 14216
Protoss_Photon_Cannon 1 14951
Protoss_Citadel_of_Adun 1 15908
15908
