Protoss_Nexus 1 7222
Protoss_Forge 1 5676
Protoss_Photon_Cannon 11 15200
Protoss_Gateway 1 8585
Protoss_Assimilator 2 11202
Protoss_Zealot 1 9866
Protoss_Cybernetics_Core 1 10938
Protoss_Stargate 1 12684
Protoss_Robotics_Facility 1 13492
Protoss_Corsair 2 14680
Protoss_Robotics_Support_Bay 1 14270
Protoss_Reaver 1 16083
16083
