Protoss_Forge 1 4182
Protoss_Photon_Cannon 6 14890
Protoss_Nexus 1 11093
Protoss_Gateway 4 13695
Protoss_Zealot 8 15580
Protoss_Assimilator 1 12532
Protoss_Cybernetics_Core 1 15901
15901
