Protoss_Gateway 1 4389
Protoss_Assimilator 1 4783
Protoss_Cybernetics_Core 1 6125
Protoss_Zealot 2 7981
Protoss_Stargate 1 8077
Protoss_Citadel_of_Adun 1 9233
Protoss_Corsair 1 9353
Protoss_Dragoon 1 10200
Protoss_Templar_Archives 1 10969
Protoss_Dark_Templar 1 12271
Protoss_Forge 1 12172
Protoss_High_Templar 2 15044
Protoss_Photon_Cannon 2 15391
Protoss_Nexus 1 16215
16215
