Protoss_Forge 1 4848
Protoss_Photon_Cannon 4 14992
Protoss_Nexus 1 8342
Protoss_Gateway 2 15987
Protoss_Assimilator 2 11619
Protoss_Zealot 6 14559
Protoss_Cybernetics_Core 1 10144
Protoss_Dragoon 1 11349
Protoss_Stargate 1 12247
Protoss_Corsair 2 14805
Protoss_Citadel_of_Adun 1 14487
Protoss_Templar_Archives 1 15975
15987
