Protoss_Nexus 1 6760
Protoss_Forge 1 5926
Protoss_Photon_Cannon 4 14255
Protoss_Gateway 4 12219
Protoss_Assimilator 2 10458
Protoss_Cybernetics_Core 1 9528
Protoss_Zealot 10 15128
Protoss_Citadel_of_Adun 1 11247
Protoss_Dragoon 1 12189
Protoss_Templar_Archives 1 15026
Leg_Enhancements 1 14560
15128
