Protoss_Forge 1 4224
Protoss_Nexus 1 7795
Protoss_Photon_Cannon 2 7157
Protoss_Gateway 2 13751
Protoss_Assimilator 2 10714
Protoss_Cybernetics_Core 1 9563
Protoss_Zealot 3 12962
Protoss_Stargate 1 11576
Protoss_Citadel_of_Adun 1 12438
Protoss_Corsair 2 14291
Protoss_Templar_Archives 1 14036
14291
