Protoss_Gateway 2 5104
Protoss_Zealot 13 12026
Protoss_Assimilator 1 9348
Protoss_Cybernetics_Core 1 11686
Protoss_Stargate 1 13648
Protoss_Dragoon 1 13608
Protoss_Citadel_of_Adun 1 14332
Protoss_Forge 1 14320
Protoss_Corsair 1 14598
14598
