Protoss_Gateway 2 4716
Protoss_Zealot 12 14628
Protoss_Assimilator 2 13472
Protoss_Nexus 1 11794
Protoss_Forge 1 10220
Protoss_Cybernetics_Core 1 11705
Protoss_Photon_Cannon 2 15664
Protoss_Citadel_of_Adun 1 13275
Protoss_Stargate 1 13992
Protoss_Corsair 1 14991
15664
