Protoss_Gateway 3 15983
Protoss_Zealot 10 14914
Protoss_Forge 1 5923
Protoss_Nexus 1 10252
Protoss_Photon_Cannon 2 10093
Protoss_Assimilator 2 11743
Protoss_Cybernetics_Core 1 11775
Protoss_Stargate 1 13764
Protoss_Citadel_of_Adun 1 14401
Protoss_Corsair 1 14704
15983
