Protoss_Forge 1 4656
Protoss_Photon_Cannon 2 7201
Protoss_Nexus 1 8545
Protoss_Gateway 3 15500
Protoss_Assimilator 3 14417
Protoss_Zealot 7 15298
Protoss_Cybernetics_Core 1 12810
Protoss_Dragoon 1 14436
Protoss_Citadel_of_Adun 1 14789
15500
