Protoss_Forge 1 4466
Protoss_Photon_Cannon 8 14798
Protoss_Nexus 1 9000
Protoss_Gateway 3 15949
Protoss_Assimilator 2 14797
Protoss_Zealot 5 15200
Protoss_Cybernetics_Core 1 11049
Protoss_Citadel_of_Adun 1 12504
Protoss_Templar_Archives 1 13960
Protoss_Dark_Templar 1 15563
15949
