Protoss_Forge 1 3655
Protoss_Photon_Cannon 7 15622
Protoss_Nexus 2 15789
Protoss_Gateway 1 8550
Protoss_Assimilator 2 11484
Protoss_Cybernetics_Core 1 10022
Protoss_Dragoon 4 15145
Protoss_Stargate 1 11978
Protoss_Corsair 3 15172
15789
