Protoss_Gateway 1 4041
Protoss_Zealot 3 6792
Protoss_Assimilator 1 5652
Protoss_Cybernetics_Core 1 7812
Protoss_Stargate 1 9498
Protoss_Forge 1 8879
Protoss_Photon_Cannon 4 13931
Protoss_Corsair 3 13293
Protoss_Robotics_Facility 1 11710
Protoss_Citadel_of_Adun 1 13445
Protoss_Nexus 1 16585
Protoss_Robotics_Support_Bay 1 14794
16585
