Protoss_Gateway 3 15845
Protoss_Assimilator 1 4353
Protoss_Cybernetics_Core 1 5718
Protoss_Zealot 5 15061
Protoss_Stargate 1 7819
Protoss_Dragoon 1 7766
Protoss_Corsair 2 9942
Protoss_Citadel_of_Adun 1 9920
Protoss_Templar_Archives 1 11859
Protoss_Forge 1 12077
Protoss_Dark_Templar 1 13055
Protoss_Photon_Cannon 1 13734
Protoss_High_Templar 1 14199
15845
