Protoss_Forge 1 4003
Protoss_Photon_Cannon 3 13939
Protoss_Nexus 1 7954
Protoss_Gateway 2 13890
Protoss_Assimilator 2 10233
Protoss_Zealot 3 10761
Protoss_Cybernetics_Core 1 10179
Protoss_Stargate 1 12010
Protoss_Dragoon 2 13539
Protoss_Citadel_of_Adun 1 12276
Protoss_Templar_Archives 1 13785
Protoss_Corsair 2 14366
Protoss_High_Templar 2 15351
15351
