Protoss_Forge 1 4347
Protoss_Photon_Cannon 3 10435
Protoss_Nexus 1 9381
Protoss_Gateway 3 13618
Protoss_Assimilator 2 11003
Protoss_Cybernetics_Core 1 10089
Protoss_Zealot 1 9961
Protoss_Stargate 1 11882
Protoss_Dragoon 1 11495
Protoss_Citadel_of_Adun 1 12716
Protoss_Corsair 3 14849
Protoss_Templar_Archives 1 14206
Protoss_Dark_Templar 3 15497
15497
