Protoss_Gateway 3 15172
Protoss_Assimilator 1 4185
Protoss_Cybernetics_Core 1 5587
Protoss_Dragoon 7 15399
Protoss_Robotics_Facility 1 8165
Protoss_Shuttle 1 9576
Protoss_Robotics_Support_Bay 1 9073
Protoss_Reaver 2 12925
Gravitic_Drive 1 12956
15399
