Protoss_Gateway 2 12443
Protoss_Assimilator 2 15574
Protoss_Zealot 4 10978
Protoss_Cybernetics_Core 1 6759
Protoss_Stargate 1 8476
Protoss_Dragoon 1 8442
Protoss_Citadel_of_Adun 1 9279
Protoss_Corsair 1 9412
Protoss_Forge 1 9810
Protoss_Templar_Archives 1 10969
Protoss_Dark_Templar 1 12183
Protoss_Photon_Cannon 2 14261
Protoss_Nexus 1 15281
Protoss_High_Templar 2 14662
15574
