Protoss_Gateway 2 4714
Protoss_Zealot 17 13524
Protoss_Assimilator 1 8563
Protoss_Cybernetics_Core 1 12874
Protoss_Forge 1 13802
Protoss_Stargate 1 15148
Protoss_Photon_Cannon 1 15174
Protoss_Citadel_of_Adun 1 16059
16059
