Protoss_Gateway 2 5095
Protoss_Zealot 10 9816
Protoss_Assimilator 1 8408
Protoss_Cybernetics_Core 1 11153
Protoss_Dragoon 6 15689
Protoss_Robotics_Facility 1 13605
Protoss_Shuttle 1 15011
Protoss_Robotics_Support_Bay 1 14748
15689
