Protoss_Gateway 2 4905
Protoss_Zealot 19 15333
Protoss_Forge 1 10593
Protoss_Assimilator 1 10634
Protoss_Cybernetics_Core 1 12503
Protoss_Photon_Cannon 1 12331
Protoss_Citadel_of_Adun 1 14169
15333
