Protoss_Forge 1 4398
Protoss_Nexus 1 7945
Protoss_Photon_Cannon 1 6405
Protoss_Gateway 4 14066
Protoss_Assimilator 2 11134
Protoss_Cybernetics_Core 1 9437
Protoss_Zealot 12 15400
Protoss_Citadel_of_Adun 1 11257
Protoss_Dragoon 1 12000
Protoss_Robotics_Facility 1 14761
Protoss_Templar_Archives 1 14513
Leg_Enhancements 1 14431
Protoss_Ground_Weapons_1 1 14504
15400
