Protoss_Gateway 2 11750
Protoss_Assimilator 1 4811
Protoss_Cybernetics_Core 1 6119
Protoss_Stargate 1 7881
Protoss_Zealot 3 15421
Protoss_Scout 1 10005
Protoss_Citadel_of_Adun 1 11597
15421
