Protoss_Nexus 1 6919
Protoss_Forge 1 5499
Protoss_Gateway 1 7068
Protoss_Assimilator 2 10199
Protoss_Photon_Cannon 6 15699
Protoss_Cybernetics_Core 1 8837
Protoss_Zealot 2 9930
Protoss_Stargate 1 10537
Protoss_Robotics_Facility 1 12093
Protoss_Dragoon 1 12197
Protoss_Corsair 4 15084
Protoss_Shuttle 1 14107
Protoss_Robotics_Support_Bay 1 13624
15699
