Protoss_Forge 1 3993
Protoss_Photon_Cannon 8 15275
Protoss_Nexus 2 16032
Protoss_Assimilator 3 11486
Protoss_Gateway 1 9662
Protoss_Cybernetics_Core 1 11199
Protoss_Zealot 2 13476
Protoss_Citadel_of_Adun 1 14197
Protoss_Templar_Archives 1 15890
16032
