Protoss_Nexus 1 7164
Protoss_Gateway 1 6299
Protoss_Forge 1 6378
Protoss_Photon_Cannon 1 7634
Protoss_Zealot 4 15214
Protoss_Assimilator 1 8076
Protoss_Cybernetics_Core 1 10542
Protoss_Robotics_Facility 1 15712
15712
