Protoss_Forge 1 5045
Protoss_Nexus 1 7825
Protoss_Photon_Cannon 4 13756
Protoss_Gateway 3 15353
Protoss_Assimilator 2 11648
Protoss_Cybernetics_Core 1 10410
Protoss_Zealot 7 15456
Protoss_Stargate 1 12272
Protoss_Citadel_of_Adun 1 12667
Protoss_Corsair 2 14244
Protoss_Templar_Archives 1 14360
15456
