Protoss_Nexus 1 6868
Protoss_Forge 1 5464
Protoss_Photon_Cannon 2 14009
Protoss_Gateway 1 7668
Protoss_Assimilator 2 9617
Protoss_Zealot 4 12374
Protoss_Cybernetics_Core 1 9788
Protoss_Stargate 1 11494
Protoss_Dragoon 1 11512
Protoss_Robotics_Facility 1 12352
Protoss_Corsair 1 13015
Protoss_Shuttle 1 13814
Protoss_Robotics_Support_Bay 1 13389
14009
