Protoss_Forge 1 4533
Protoss_Photon_Cannon 2 14782
Protoss_Nexus 1 8763
Protoss_Gateway 2 16032
Protoss_Assimilator 2 8354
Protoss_Zealot 2 9880
Protoss_Cybernetics_Core 1 9749
Protoss_Stargate 1 11655
Protoss_Dragoon 2 13702
Protoss_Robotics_Facility 1 13047
Protoss_Corsair 4 15479
Protoss_Robotics_Support_Bay 1 13769
Protoss_Reaver 1 15591
16032
