Protoss_Forge 1 4327
Protoss_Nexus 1 7896
Protoss_Gateway 1 7419
Protoss_Photon_Cannon 3 13813
Protoss_Assimilator 2 9855
Protoss_Zealot 2 10136
Protoss_Cybernetics_Core 1 9943
Protoss_Dragoon 1 11729
Protoss_Stargate 2 12613
Protoss_Robotics_Facility 1 14182
Protoss_Corsair 4 14622
14622
