Protoss_Forge 1 3990
Protoss_Nexus 1 7879
Protoss_Gateway 4 14929
Protoss_Photon_Cannon 4 15752
Protoss_Assimilator 2 10634
Protoss_Zealot 3 11935
Protoss_Cybernetics_Core 1 9487
Protoss_Dragoon 1 10819
Protoss_Stargate 1 11402
Protoss_Citadel_of_Adun 1 11892
Protoss_Corsair 2 13638
Protoss_Templar_Archives 1 13624
Protoss_Robotics_Facility 1 16134
Protoss_Dark_Templar 1 15440
16134
