Protoss_Forge 1 3937
Protoss_Photon_Cannon 8 15606
Protoss_Nexus 1 9388
Protoss_Gateway 4 15658
Protoss_Assimilator 2 12851
Protoss_Zealot 4 14522
Protoss_Cybernetics_Core 1 11666
Protoss_Stargate 1 13357
Protoss_Citadel_of_Adun 1 13479
Protoss_Corsair 1 14307
Protoss_Templar_Archives 1 15027
15658
