Protoss_Gateway 4 14889
Protoss_Forge 1 4780
Protoss_Zealot 11 15302
Protoss_Photon_Cannon 3 11849
Protoss_Nexus 1 10297
Protoss_Assimilator 2 13887
Protoss_Cybernetics_Core 1 10779
Protoss_Dragoon 1 11995
Protoss_Citadel_of_Adun 1 13628
15302
