Protoss_Gateway 2 14282
Protoss_Assimilator 1 4512
Protoss_Zealot 2 6895
Protoss_Cybernetics_Core 1 7075
Protoss_Dragoon 5 14596
Protoss_Stargate 1 9722
Protoss_Corsair 1 10692
Protoss_Robotics_Facility 1 11926
Protoss_Shuttle 1 13335
Protoss_Observatory 1 12736
Protoss_Observer 1 14178
Singularity_Charge 1 14599
14599
