Protoss_Gateway 2 12191
Protoss_Assimilator 1 4556
Protoss_Zealot 3 12829
Protoss_Cybernetics_Core 1 7164
Protoss_Dragoon 1 8378
Protoss_Stargate 1 9313
Protoss_Citadel_of_Adun 1 10296
Protoss_Corsair 1 10261
Protoss_Templar_Archives 1 12052
Protoss_Nexus 1 15366
Protoss_Dark_Templar 1 14575
Leg_Enhancements 1 14087
15366
