Protoss_Nexus 1 6842
Protoss_Forge 1 5759
Protoss_Gateway 1 7419
Protoss_Assimilator 2 9715
Protoss_Photon_Cannon 2 8695
Protoss_Cybernetics_Core 1 9605
Protoss_Zealot 5 15397
Protoss_Stargate 1 11525
Protoss_Robotics_Facility 1 12865
Protoss_Dragoon 1 12742
Protoss_Corsair 3 14284
Protoss_Shuttle 1 14294
Protoss_Robotics_Support_Bay 1 14033
Protoss_Reaver 1 15852
Protoss_Citadel_of_Adun 1 15744
15852
