Protoss_Forge 2 15517
Protoss_Photon_Cannon 9 13629
Protoss_Nexus 1 8302
Protoss_Gateway 1 7843
Protoss_Assimilator 2 10274
Protoss_Zealot 2 10638
Protoss_Cybernetics_Core 1 10349
Protoss_Stargate 1 12164
Protoss_Robotics_Facility 1 13345
Protoss_Corsair 1 13814
Protoss_Robotics_Support_Bay 1 14112
Protoss_Reaver 1 15861
15861
