Protoss_Forge 1 4322
Protoss_Photon_Cannon 3 15288
Protoss_Nexus 1 8892
Protoss_Gateway 4 13284
Protoss_Assimilator 2 10258
Protoss_Zealot 2 10978
Protoss_Cybernetics_Core 1 10155
Protoss_Citadel_of_Adun 1 11674
Protoss_Dragoon 1 12131
Protoss_Templar_Archives 1 13448
Protoss_Dark_Templar 2 14729
Protoss_High_Templar 2 14714
Protoss_Robotics_Facility 1 16456
16456
