Protoss_Gateway 2 10859
Protoss_Assimilator 1 4643
Protoss_Cybernetics_Core 1 6094
Protoss_Zealot 10 13618
Protoss_Dragoon 1 8059
Protoss_Citadel_of_Adun 1 9637
Protoss_Templar_Archives 1 13075
Leg_Enhancements 1 12711
Protoss_Forge 1 13896
Protoss_High_Templar 2 14738
Protoss_Photon_Cannon 1 15723
15723
