Protoss_Gateway 3 15669
Protoss_Assimilator 1 4429
Protoss_Zealot 3 12112
Protoss_Cybernetics_Core 1 6386
Protoss_Stargate 1 8825
Protoss_Dragoon 2 12175
Protoss_Scout 1 11236
Protoss_Forge 1 10937
Protoss_Photon_Cannon 2 14624
Protoss_Nexus 1 16506
Protoss_Citadel_of_Adun 1 15599
16506
