Protoss_Forge 1 4593
Protoss_Nexus 1 7958
Protoss_Gateway 4 12517
Protoss_Assimilator 2 14837
Protoss_Photon_Cannon 1 7450
Protoss_Zealot 14 15456
Protoss_Cybernetics_Core 1 9716
Protoss_Citadel_of_Adun 1 11282
Protoss_Templar_Archives 1 14685
Leg_Enhancements 1 14334
15456
