Protoss_Gateway 2 14920
Protoss_Assimilator 1 4673
Protoss_Zealot 3 12617
Protoss_Cybernetics_Core 1 7170
Protoss_Robotics_Facility 1 9125
Protoss_Dragoon 4 14231
Protoss_Shuttle 1 10635
Protoss_Robotics_Support_Bay 1 10450
Protoss_Reaver 2 14020
Gravitic_Drive 1 14204
14920
