Protoss_Forge 1 5218
Protoss_Nexus 1 7812
Protoss_Photon_Cannon 6 15118
Protoss_Gateway 1 8370
Protoss_Assimilator 2 10349
Protoss_Cybernetics_Core 1 10041
Protoss_Zealot 2 10700
Protoss_Stargate 2 15372
Protoss_Robotics_Facility 1 12976
Protoss_Corsair 3 15392
Protoss_Robotics_Support_Bay 1 13670
Protoss_Reaver 1 15864
15864
