Protoss_Forge 1 3882
Protoss_Photon_Cannon 3 9047
Protoss_Nexus 1 9308
Protoss_Gateway 2 12680
Protoss_Assimilator 2 12595
Protoss_Cybernetics_Core 1 10044
Protoss_Zealot 5 15067
Protoss_Dragoon 1 11268
Protoss_Citadel_of_Adun 1 11920
Protoss_Templar_Archives 1 14436
15067
