Protoss_Forge 2 6064
Protoss_Nexus 1 7026
Protoss_Gateway 3 15484
Protoss_Photon_Cannon 3 15692
Protoss_Assimilator 2 11628
Protoss_Zealot 5 14190
Protoss_Cybernetics_Core 1 9459
Protoss_Stargate 1 11429
Protoss_Dragoon 1 11331
Protoss_Corsair 3 15053
Protoss_Citadel_of_Adun 1 13709
Protoss_Templar_Archives 1 15157
15692
