Protoss_Gateway 2 5297
Protoss_Zealot 8 14461
Protoss_Assimilator 1 7889
Protoss_Forge 1 9579
Protoss_Cybernetics_Core 1 11010
Protoss_Photon_Cannon 1 11491
Protoss_Dragoon 1 12271
Protoss_Citadel_of_Adun 1 12539
14461
