Protoss_Forge 2 6655
Protoss_Nexus 1 7249
Protoss_Gateway 3 13937
Protoss_Assimilator 2 11168
Protoss_Photon_Cannon 4 14461
Protoss_Zealot 4 13015
Protoss_Cybernetics_Core 1 9713
Protoss_Dragoon 1 10933
Protoss_Stargate 1 11517
Protoss_Citadel_of_Adun 1 11688
Protoss_Corsair 1 12593
Protoss_Templar_Archives 1 13397
Protoss_Dark_Templar 1 14703
Protoss_High_Templar 2 15335
15335
