Protoss_Forge 1 3864
Protoss_Nexus 1 8090
Protoss_Photon_Cannon 5 14804
Protoss_Gateway 3 13111
Protoss_Assimilator 2 9528
Protoss_Cybernetics_Core 1 10493
Protoss_Robotics_Facility 1 12465
Protoss_Stargate 1 12391
Protoss_Citadel_of_Adun 1 12892
Protoss_Robotics_Support_Bay 1 13416
Protoss_Corsair 2 14929
Protoss_Reaver 1 15315
Protoss_Templar_Archives 1 15640
15640
