Protoss_Assimilator 1 3428
Protoss_Forge 1 4095
Protoss_Gateway 2 7389
Protoss_Photon_Cannon 3 14111
Protoss_Zealot 15 14253
Protoss_Cybernetics_Core 1 9822
Protoss_Citadel_of_Adun 1 11276
Protoss_Ground_Weapons_1 1 10158
Protoss_Templar_Archives 1 15069
Leg_Enhancements 1 14390
15069
