Protoss_Forge 1 3933
Protoss_Photon_Cannon 8 15701
Protoss_Nexus 1 8317
Protoss_Gateway 2 12860
Protoss_Assimilator 2 10921
Protoss_Zealot 2 11935
Protoss_Cybernetics_Core 1 9731
Protoss_Stargate 1 11541
Protoss_Citadel_of_Adun 1 12121
Protoss_Corsair 3 15547
Protoss_Templar_Archives 1 13726
Protoss_High_Templar 2 15168
15701
