Protoss_Gateway 2 4668
Protoss_Zealot 11 13883
Protoss_Assimilator 1 7965
Protoss_Cybernetics_Core 1 10527
Protoss_Stargate 1 12365
Protoss_Dragoon 1 12373
Protoss_Citadel_of_Adun 1 13321
Protoss_Corsair 1 13319
13883
