Protoss_Forge 1 3929
Protoss_Photon_Cannon 3 8177
Protoss_Nexus 1 8825
Protoss_Gateway 3 15090
Protoss_Assimilator 2 11412
Protoss_Zealot 5 15317
Protoss_Cybernetics_Core 1 10722
Protoss_Stargate 1 12555
Protoss_Citadel_of_Adun 1 13651
Protoss_Corsair 2 15024
Protoss_Templar_Archives 1 15295
15317
