Protoss_Nexus 1 6783
Protoss_Forge 1 5554
Protoss_Gateway 5 11692
Protoss_Photon_Cannon 1 7378
Protoss_Assimilator 2 13224
Protoss_Zealot 14 14595
Protoss_Cybernetics_Core 1 9216
Protoss_Citadel_of_Adun 1 10659
Protoss_Templar_Archives 1 14960
Leg_Enhancements 1 13585
Protoss_Ground_Weapons_1 1 14191
14960
