Protoss_Gateway 4 14240
Protoss_Zealot 6 15127
Protoss_Assimilator 1 5705
Protoss_Cybernetics_Core 1 7353
Protoss_Stargate 1 9299
Protoss_Corsair 1 10363
Protoss_Dragoon 1 10712
Protoss_Robotics_Facility 1 11824
Protoss_Citadel_of_Adun 1 12506
Protoss_Observatory 1 12546
Protoss_Templar_Archives 1 14016
Protoss_Shuttle 1 15530
Protoss_Observer 1 15378
Protoss_Dark_Templar 1 15753
15753
