Protoss_Forge 1 4278
Protoss_Nexus 1 7796
Protoss_Photon_Cannon 2 7519
Protoss_Gateway 5 15361
Protoss_Assimilator 1 7928
Protoss_Cybernetics_Core 1 9874
Protoss_Zealot 12 15576
Protoss_Citadel_of_Adun 1 11680
Protoss_Dragoon 1 11512
Protoss_Templar_Archives 1 15825
Leg_Enhancements 1 14606
15825
