Protoss_Gateway 1 4029
Protoss_Zealot 5 11950
Protoss_Forge 1 5458
Protoss_Photon_Cannon 5 15802
Protoss_Nexus 1 10584
Protoss_Assimilator 2 11303
Protoss_Cybernetics_Core 1 10578
Protoss_Stargate 1 13042
Protoss_Robotics_Facility 1 14231
Protoss_Corsair 2 15213
Protoss_Dragoon 1 14340
Protoss_Robotics_Support_Bay 1 15136
15802
