Protoss_Forge 1 3867
Protoss_Nexus 1 7771
Protoss_Photon_Cannon 3 15522
Protoss_Gateway 4 13767
Protoss_Assimilator 2 12425
Protoss_Zealot 13 15113
Protoss_Cybernetics_Core 1 9984
Protoss_Citadel_of_Adun 1 11529
Protoss_Dragoon 1 11363
Protoss_Templar_Archives 1 14745
15522
