Protoss_Gateway 1 3787
Protoss_Zealot 11 13984
Protoss_Forge 1 6207
Protoss_Photon_Cannon 3 14448
Protoss_Nexus 1 12377
Protoss_Assimilator 2 13685
Protoss_Cybernetics_Core 1 13091
Protoss_Citadel_of_Adun 1 15538
Protoss_Dragoon 1 15379
15538
