Protoss_Forge 1 3719
Protoss_Photon_Cannon 6 14167
Protoss_Nexus 1 8971
Protoss_Gateway 4 13730
Protoss_Assimilator 1 8988
Protoss_Cybernetics_Core 1 10616
Protoss_Zealot 13 15582
Protoss_Citadel_of_Adun 1 12276
Protoss_Dragoon 1 12613
Protoss_Templar_Archives 1 15697
15697
