Protoss_Forge 1 4562
Protoss_Nexus 1 7872
Protoss_Photon_Cannon 3 13651
Protoss_Gateway 1 7249
Protoss_Zealot 5 14944
Protoss_Assimilator 1 8809
Protoss_Cybernetics_Core 1 10799
Protoss_Stargate 1 13455
Protoss_Corsair 1 14402
Protoss_Citadel_of_Adun 1 15409
15409
