Protoss_Gateway 4 13593
Protoss_Zealot 15 15558
Protoss_Forge 1 8260
Protoss_Photon_Cannon 1 10295
Protoss_Nexus 1 13237
Protoss_Assimilator 1 12086
Protoss_Cybernetics_Core 1 14129
Protoss_Citadel_of_Adun 1 15623
15623
