Protoss_Forge 1 4450
Protoss_Photon_Cannon 4 13611
Protoss_Nexus 1 8270
Protoss_Gateway 1 8227
Protoss_Assimilator 2 10292
Protoss_Cybernetics_Core 1 9803
Protoss_Zealot 4 14145
Protoss_Dragoon 1 10994
Protoss_Stargate 1 11794
Protoss_Robotics_Facility 1 12771
Protoss_Corsair 2 14531
Protoss_Citadel_of_Adun 1 14136
Protoss_Shuttle 1 14279
Protoss_Robotics_Support_Bay 1 13917
Protoss_Templar_Archives 1 15671
15671
