Protoss_Gateway 2 5035
Protoss_Zealot 13 15061
Protoss_Assimilator 1 9093
Protoss_Cybernetics_Core 1 10840
Protoss_Forge 1 11865
Protoss_Stargate 1 13017
Protoss_Citadel_of_Adun 1 13436
Protoss_Corsair 2 15434
15434
