Protoss_Gateway 2 5019
Protoss_Zealot 14 14453
Protoss_Assimilator 1 9504
Protoss_Forge 1 10406
Protoss_Photon_Cannon 1 13437
Protoss_Cybernetics_Core 1 14282
Protoss_Citadel_of_Adun 1 15852
15852
