Protoss_Forge 1 4654
Protoss_Nexus 1 7872
Protoss_Photon_Cannon 5 15767
Protoss_Gateway 1 7322
Protoss_Assimilator 2 9547
Protoss_Zealot 6 14818
Protoss_Cybernetics_Core 2 14426
Protoss_Stargate 1 11688
Protoss_Dragoon 1 11545
Protoss_Citadel_of_Adun 1 12317
15767
