Protoss_Assimilator 1 3485
Protoss_Forge 1 4211
Protoss_Photon_Cannon 3 13374
Protoss_Gateway 3 7947
Protoss_Zealot 13 13518
Protoss_Ground_Weapons_1 1 10275
Protoss_Nexus 2 14935
14935
