Protoss_Nexus 1 6878
Protoss_Forge 1 5446
Protoss_Photon_Cannon 8 15537
Protoss_Gateway 4 13034
Protoss_Assimilator 2 10556
Protoss_Cybernetics_Core 1 10698
Protoss_Citadel_of_Adun 1 12140
Protoss_Dragoon 1 11987
Protoss_Zealot 1 13006
Protoss_Templar_Archives 1 13754
Protoss_High_Templar 4 15028
15537
