Protoss_Forge 1 4150
Protoss_Nexus 1 7610
Protoss_Gateway 1 7594
Protoss_Photon_Cannon 2 8294
Protoss_Assimilator 1 8765
Protoss_Zealot 3 14505
Protoss_Cybernetics_Core 1 9882
14505
