Protoss_Forge 1 3895
Protoss_Photon_Cannon 4 15036
Protoss_Gateway 4 15948
Protoss_Nexus 1 9599
Protoss_Zealot 7 15283
Protoss_Assimilator 2 12247
Protoss_Cybernetics_Core 1 10006
Protoss_Citadel_of_Adun 1 11620
Protoss_Dragoon 1 12364
Protoss_Templar_Archives 1 14494
Leg_Enhancements 1 14551
15948
