Protoss_Forge 1 3760
Protoss_Photon_Cannon 4 15268
Protoss_Nexus 1 8829
Protoss_Gateway 1 7925
Protoss_Assimilator 2 10972
Protoss_Zealot 2 13691
Protoss_Cybernetics_Core 1 9781
Protoss_Stargate 1 11896
Protoss_Dragoon 1 12183
Protoss_Robotics_Facility 1 13688
Protoss_Corsair 1 12889
Protoss_Shuttle 1 15090
Protoss_Robotics_Support_Bay 1 14502
15268
