Protoss_Forge 1 4390
Protoss_Nexus 1 7474
Protoss_Photon_Cannon 6 15793
Protoss_Gateway 2 13369
Protoss_Assimilator 2 12624
Protoss_Cybernetics_Core 1 9179
Protoss_Zealot 3 13729
Protoss_Stargate 1 11097
Protoss_Citadel_of_Adun 1 11535
Protoss_Corsair 3 14455
Protoss_Templar_Archives 1 13226
Protoss_Dark_Templar 2 15104
15793
