Protoss_Forge 1 4881
Protoss_Nexus 1 7720
Protoss_Photon_Cannon 4 15749
Protoss_Gateway 3 14841
Protoss_Assimilator 2 11650
Protoss_Zealot 2 14777
Protoss_Cybernetics_Core 1 10738
Protoss_Dragoon 1 11981
Protoss_Stargate 1 12751
Protoss_Citadel_of_Adun 1 12917
Protoss_Corsair 1 13691
Protoss_Templar_Archives 1 14588
15749
