Protoss_Gateway 2 11750
Protoss_Assimilator 1 4622
Protoss_Zealot 8 15127
Protoss_Cybernetics_Core 1 7009
Protoss_Stargate 1 9142
Protoss_Dragoon 1 9263
Protoss_Citadel_of_Adun 1 10548
Protoss_Corsair 1 10100
Protoss_Templar_Archives 1 12813
Protoss_Nexus 1 15603
Protoss_Dark_Templar 1 14473
Protoss_Forge 1 15034
Leg_Enhancements 1 14167
15603
