Protoss_Forge 1 4166
Protoss_Photon_Cannon 12 14852
Protoss_Nexus 1 10679
Protoss_Gateway 1 9664
Protoss_Zealot 2 14107
Protoss_Assimilator 2 12896
Protoss_Cybernetics_Core 1 13638
Protoss_Stargate 1 16269
16269
