Protoss_Gateway 2 13722
Protoss_Zealot 8 14117
Protoss_Assimilator 1 8237
Protoss_Cybernetics_Core 1 9168
Protoss_Stargate 1 11367
Protoss_Citadel_of_Adun 1 12561
Protoss_Corsair 1 12317
Protoss_Forge 1 13567
Protoss_Templar_Archives 1 14300
Protoss_Photon_Cannon 1 15164
Protoss_Dark_Templar 2 15607
15607
