Protoss_Gateway 2 4846
Protoss_Zealot 10 14701
Protoss_Shield_Battery 1 7223
Protoss_Nexus 1 12312
Protoss_Forge 1 11121
Protoss_Assimilator 1 11572
Protoss_Photon_Cannon 2 13466
14701
