Protoss_Forge 1 4191
Protoss_Photon_Cannon 2 7937
Protoss_Nexus 2 17329
Protoss_Gateway 2 12255
Protoss_Assimilator 2 9860
Protoss_Zealot 2 10272
Protoss_Cybernetics_Core 1 9907
Protoss_Stargate 1 11605
Protoss_Citadel_of_Adun 1 11774
Protoss_Corsair 4 15343
Protoss_Templar_Archives 1 13231
Protoss_Dark_Templar 2 14723
17329
