Protoss_Gateway 5 14442
Protoss_Nexus 1 7249
Protoss_Forge 1 6020
Protoss_Photon_Cannon 2 14713
Protoss_Assimilator 1 8805
Protoss_Cybernetics_Core 1 9823
Protoss_Zealot 8 14344
Protoss_Stargate 1 11784
Protoss_Dragoon 1 12651
Protoss_Corsair 1 12917
Protoss_Citadel_of_Adun 1 13966
14713
