Protoss_Forge 1 3652
Protoss_Nexus 1 7699
Protoss_Gateway 3 14088
Protoss_Zealot 11 15172
Protoss_Photon_Cannon 4 11433
Protoss_Assimilator 2 13049
Protoss_Cybernetics_Core 1 11837
Protoss_Citadel_of_Adun 1 13581
Protoss_Templar_Archives 1 15712
15712
