Protoss_Forge 1 3839
Protoss_Nexus 1 7997
Protoss_Gateway 1 7034
Protoss_Photon_Cannon 8 13797
Protoss_Assimilator 2 10016
Protoss_Zealot 3 12473
Protoss_Cybernetics_Core 1 9541
Protoss_Stargate 1 11264
Protoss_Robotics_Facility 1 12663
Protoss_Corsair 2 15017
Protoss_Robotics_Support_Bay 1 13510
Protoss_Shuttle 1 14373
Protoss_Reaver 1 15931
Protoss_Citadel_of_Adun 1 15731
15931
