Protoss_Gateway 2 15558
Protoss_Zealot 9 14256
Protoss_Assimilator 1 5472
Protoss_Forge 1 7397
Protoss_Cybernetics_Core 1 10258
Protoss_Citadel_of_Adun 1 12103
Protoss_Photon_Cannon 5 14676
Protoss_Templar_Archives 1 13777
Protoss_Ground_Weapons_1 1 13292
Protoss_Robotics_Facility 1 16353
Protoss_Dark_Templar 1 15789
16353
