Protoss_Nexus 1 7477
Protoss_Forge 1 6589
Protoss_Photon_Cannon 8 15392
Protoss_Gateway 1 8797
Protoss_Assimilator 2 11797
Protoss_Cybernetics_Core 1 10575
Protoss_Zealot 2 13398
Protoss_Stargate 1 12692
Protoss_Dragoon 2 14032
Protoss_Citadel_of_Adun 1 13324
Protoss_Corsair 2 14748
Protoss_Templar_Archives 1 14954
15392
