Protoss_Forge 1 4609
Protoss_Nexus 1 8073
Protoss_Photon_Cannon 4 15351
Protoss_Gateway 3 14809
Protoss_Zealot 5 12997
Protoss_Assimilator 2 12610
Protoss_Cybernetics_Core 1 11206
Protoss_Citadel_of_Adun 1 12889
Protoss_Templar_Archives 1 14443
Protoss_Dark_Templar 1 15736
15736
