Protoss_Forge 3 6648
Protoss_Nexus 1 7451
Protoss_Gateway 3 14620
Protoss_Photon_Cannon 2 15821
Protoss_Assimilator 2 10965
Protoss_Zealot 6 14841
Protoss_Cybernetics_Core 1 10837
Protoss_Stargate 1 12586
Protoss_Dragoon 1 12253
Protoss_Citadel_of_Adun 1 12811
Protoss_Corsair 1 13521
Protoss_Templar_Archives 1 14809
15821
