Protoss_Forge 1 4208
Protoss_Photon_Cannon 3 14584
Protoss_Nexus 1 8349
Protoss_Gateway 5 15968
Protoss_Assimilator 2 9854
Protoss_Cybernetics_Core 1 9719
Protoss_Zealot 3 14707
Protoss_Stargate 1 11400
Protoss_Citadel_of_Adun 1 11411
Protoss_Dragoon 1 11451
Protoss_Corsair 1 12362
Protoss_Templar_Archives 1 13366
Protoss_Robotics_Facility 1 14733
Protoss_High_Templar 3 15806
15968
