Protoss_Gateway 3 15023
Protoss_Assimilator 1 4147
Protoss_Zealot 9 15087
Protoss_Cybernetics_Core 1 6418
Protoss_Stargate 1 8579
Protoss_Corsair 2 10425
Protoss_Citadel_of_Adun 1 11563
Protoss_Templar_Archives 1 13243
Protoss_Forge 1 13732
15087
