Protoss_Forge 1 4562
Protoss_Nexus 1 7967
Protoss_Gateway 2 14285
Protoss_Photon_Cannon 4 15408
Protoss_Assimilator 2 11991
Protoss_Zealot 3 12775
Protoss_Cybernetics_Core 1 10723
Protoss_Stargate 1 12460
Protoss_Citadel_of_Adun 1 12877
Protoss_Corsair 2 14590
Protoss_Templar_Archives 1 14364
Protoss_Dark_Templar 2 15663
15663
