Protoss_Nexus 1 7347
Protoss_Forge 1 6064
Protoss_Photon_Cannon 6 15600
Protoss_Gateway 1 8292
Protoss_Assimilator 2 10491
Protoss_Zealot 2 10154
Protoss_Cybernetics_Core 1 10126
Protoss_Stargate 1 11965
Protoss_Robotics_Facility 2 14714
Protoss_Corsair 1 13122
Protoss_Shuttle 1 15362
Protoss_Robotics_Support_Bay 1 14911
15600
