Protoss_Forge 1 3790
Protoss_Photon_Cannon 4 15695
Protoss_Nexus 1 8712
Protoss_Gateway 2 13629
Protoss_Assimilator 2 10455
Protoss_Zealot 5 13046
Protoss_Cybernetics_Core 1 9974
Protoss_Stargate 1 11753
Protoss_Citadel_of_Adun 1 12367
Protoss_Corsair 2 13662
Protoss_Templar_Archives 1 13903
Protoss_Robotics_Facility 1 15507
Protoss_Dark_Templar 2 15133
15695
