Protoss_Forge 1 4297
Protoss_Photon_Cannon 2 7020
Protoss_Nexus 1 8314
Protoss_Gateway 6 13397
Protoss_Assimilator 2 14682
Protoss_Cybernetics_Core 1 10050
Protoss_Zealot 14 15353
Protoss_Dragoon 1 11726
Protoss_Citadel_of_Adun 1 12012
15353
