Protoss_Forge 1 4313
Protoss_Photon_Cannon 5 15571
Protoss_Nexus 1 9415
Protoss_Gateway 4 15848
Protoss_Assimilator 2 10191
Protoss_Cybernetics_Core 1 10130
Protoss_Zealot 3 12927
Protoss_Stargate 1 11844
Protoss_Dragoon 1 11372
Protoss_Citadel_of_Adun 1 12138
Protoss_Corsair 1 12795
Protoss_Templar_Archives 1 13670
Protoss_Dark_Templar 1 14864
Protoss_High_Templar 1 15800
15848
