Protoss_Forge 1 4308
Protoss_Photon_Cannon 6 14801
Protoss_Nexus 1 8585
Protoss_Gateway 3 15863
Protoss_Assimilator 2 11041
Protoss_Cybernetics_Core 1 9845
Protoss_Zealot 6 15277
Protoss_Stargate 2 12468
Protoss_Citadel_of_Adun 1 12952
Protoss_Corsair 2 14821
Protoss_Templar_Archives 1 14544
15863
