Protoss_Forge 1 3997
Protoss_Photon_Cannon 6 15392
Protoss_Nexus 1 8858
Protoss_Gateway 3 14856
Protoss_Assimilator 2 11458
Protoss_Zealot 3 11253
Protoss_Cybernetics_Core 1 9830
Protoss_Stargate 1 11671
Protoss_Citadel_of_Adun 1 12089
Protoss_Corsair 2 14876
Protoss_Templar_Archives 1 14101
Protoss_High_Templar 1 15566
Protoss_Dark_Templar 1 15631
15631
