Protoss_Forge 1 4189
Protoss_Nexus 1 7577
Protoss_Photon_Cannon 6 15660
Protoss_Gateway 1 7953
Protoss_Zealot 2 13357
Protoss_Assimilator 2 12652
Protoss_Cybernetics_Core 1 12157
Protoss_Stargate 1 14001
Protoss_Robotics_Facility 1 15150
Protoss_Corsair 1 14961
15660
