Protoss_Forge 1 4947
Protoss_Nexus 1 7585
Protoss_Photon_Cannon 2 13359
Protoss_Gateway 4 14115
Protoss_Assimilator 2 14645
Protoss_Zealot 16 15383
Protoss_Cybernetics_Core 1 10940
Protoss_Dragoon 1 12569
Protoss_Citadel_of_Adun 1 12895
Protoss_Templar_Archives 1 14629
15383
