Protoss_Forge 1 4161
Protoss_Nexus 1 7888
Protoss_Gateway 3 14294
Protoss_Photon_Cannon 2 8030
Protoss_Zealot 9 15339
Protoss_Assimilator 2 11003
Protoss_Cybernetics_Core 1 11077
Protoss_Stargate 1 12921
Protoss_Citadel_of_Adun 1 12842
Protoss_Corsair 1 13957
Protoss_Templar_Archives 1 15669
15669
