Protoss_Gateway 2 4928
Protoss_Zealot 8 8563
Protoss_Assimilator 1 8022
Protoss_Cybernetics_Core 1 9649
Protoss_Stargate 1 11394
Protoss_Corsair 1 12333
Protoss_Nexus 1 14788
Protoss_Forge 1 13381
Protoss_Citadel_of_Adun 1 14887
Protoss_Photon_Cannon 1 15730
15730
