Protoss_Forge 1 4163
Protoss_Nexus 1 7574
Protoss_Photon_Cannon 6 14094
Protoss_Gateway 1 7861
Protoss_Assimilator 2 10193
Protoss_Cybernetics_Core 1 10002
Protoss_Zealot 4 13764
Protoss_Stargate 1 11927
Protoss_Robotics_Facility 1 12733
Protoss_Dragoon 1 12759
Protoss_Corsair 2 14180
Protoss_Shuttle 1 15321
Protoss_Robotics_Support_Bay 1 14700
15321
