Protoss_Gateway 3 15691
Protoss_Zealot 10 10179
Protoss_Nexus 1 12991
Protoss_Forge 1 11451
Protoss_Photon_Cannon 3 15361
Protoss_Cybernetics_Core 1 14475
Protoss_Assimilator 1 14168
15691
