Protoss_Gateway 3 15339
Protoss_Assimilator 1 4491
Protoss_Zealot 9 15339
Protoss_Cybernetics_Core 1 6899
Protoss_Stargate 1 9076
Protoss_Dragoon 1 9086
Protoss_Forge 1 9738
Protoss_Corsair 1 10495
Protoss_Photon_Cannon 2 14597
Protoss_Nexus 1 14507
Protoss_Citadel_of_Adun 1 13912
15339
