Protoss_Gateway 1 4366
Protoss_Zealot 11 15122
Protoss_Nexus 1 9788
Protoss_Assimilator 2 15491
Protoss_Forge 1 9588
Protoss_Cybernetics_Core 1 10716
Protoss_Photon_Cannon 3 13914
Protoss_Stargate 1 13086
Protoss_Citadel_of_Adun 1 14371
Protoss_Corsair 1 14054
15491
