Protoss_Forge 1 4019
Protoss_Nexus 1 7628
Protoss_Photon_Cannon 2 6869
Protoss_Gateway 1 7577
Protoss_Assimilator 2 12315
Protoss_Zealot 3 12959
Protoss_Cybernetics_Core 1 10078
Protoss_Stargate 1 11877
Protoss_Robotics_Facility 1 12742
Protoss_Corsair 1 12874
Protoss_Shuttle 1 14162
Protoss_Robotics_Support_Bay 1 13649
Protoss_Reaver 1 15741
Protoss_Citadel_of_Adun 1 16000
16000
