Protoss_Nexus 1 7038
Protoss_Gateway 5 16003
Protoss_Forge 1 6749
Protoss_Assimilator 2 10555
Protoss_Zealot 6 15213
Protoss_Photon_Cannon 1 8114
Protoss_Cybernetics_Core 1 9933
Protoss_Stargate 1 11658
Protoss_Citadel_of_Adun 1 11939
Protoss_Corsair 3 14964
Protoss_Templar_Archives 1 13474
Protoss_Dark_Templar 1 15417
16003
