Protoss_Forge 1 4079
Protoss_Nexus 1 7604
Protoss_Photon_Cannon 2 6892
Protoss_Gateway 3 13054
Protoss_Assimilator 2 10248
Protoss_Zealot 6 14013
Protoss_Cybernetics_Core 1 10024
Protoss_Dragoon 1 11308
Protoss_Citadel_of_Adun 1 11809
Protoss_Templar_Archives 1 14183
Protoss_Robotics_Facility 1 15565
Protoss_Dark_Templar 2 15391
Protoss_High_Templar 2 15487
15565
