Protoss_Forge 1 4401
Protoss_Nexus 1 7565
Protoss_Photon_Cannon 3 11470
Protoss_Gateway 3 15700
Protoss_Zealot 3 10551
Protoss_Assimilator 2 12449
Protoss_Cybernetics_Core 1 12103
Protoss_Citadel_of_Adun 1 14077
Protoss_Dragoon 2 15809
Protoss_Templar_Archives 1 15980
15980
