Protoss_Forge 1 3722
Protoss_Photon_Cannon 4 15300
Protoss_Nexus 1 8731
Protoss_Gateway 1 8073
Protoss_Assimilator 2 13148
Protoss_Zealot 4 13706
Protoss_Cybernetics_Core 1 12266
Protoss_Stargate 1 14210
Protoss_Citadel_of_Adun 1 14636
Protoss_Corsair 1 15216
15300
