Protoss_Forge 1 5028
Protoss_Nexus 1 7562
Protoss_Photon_Cannon 4 13816
Protoss_Gateway 5 15337
Protoss_Assimilator 2 10268
Protoss_Cybernetics_Core 1 9671
Protoss_Zealot 3 12406
Protoss_Stargate 1 11371
Protoss_Citadel_of_Adun 1 11850
Protoss_Corsair 1 12348
Protoss_Templar_Archives 1 13392
Protoss_High_Templar 1 14627
Protoss_Dark_Templar 2 14673
15337
