Protoss_Forge 1 5000
Protoss_Photon_Cannon 2 13345
Protoss_Nexus 1 8677
Protoss_Gateway 4 15484
Protoss_Assimilator 2 11963
Protoss_Zealot 6 15310
Protoss_Cybernetics_Core 1 10167
Protoss_Stargate 1 12327
15484
