Protoss_Forge 1 4548
Protoss_Photon_Cannon 2 6177
Protoss_Nexus 1 8703
Protoss_Gateway 6 13189
Protoss_Assimilator 2 10553
Protoss_Cybernetics_Core 1 9326
Protoss_Zealot 13 15447
Protoss_Dragoon 1 10602
Protoss_Citadel_of_Adun 1 11709
Protoss_Stargate 1 12678
Protoss_Templar_Archives 1 14977
15447
