Protoss_Forge 1 4192
Protoss_Nexus 1 7830
Protoss_Photon_Cannon 2 7046
Protoss_Gateway 3 10748
Protoss_Zealot 11 14366
Protoss_Assimilator 2 13647
Protoss_Cybernetics_Core 1 13149
Protoss_Citadel_of_Adun 1 14670
Protoss_Robotics_Facility 1 16049
16049
