Protoss_Forge 1 4736
Protoss_Photon_Cannon 3 15067
Protoss_Nexus 1 8153
Protoss_Gateway 1 7155
Protoss_Assimilator 2 9762
Protoss_Cybernetics_Core 1 9209
Protoss_Zealot 4 13694
Protoss_Stargate 1 11380
Protoss_Dragoon 1 11951
Protoss_Corsair 3 14546
Protoss_Robotics_Facility 1 14808
15067
