Protoss_Forge 1 4306
Protoss_Photon_Cannon 2 6434
Protoss_Nexus 1 9448
Protoss_Gateway 1 8232
Protoss_Assimilator 2 11273
Protoss_Cybernetics_Core 1 9942
Protoss_Zealot 3 12053
Protoss_Stargate 1 11710
Protoss_Robotics_Facility 1 13249
Protoss_Corsair 4 15462
Protoss_Robotics_Support_Bay 1 14098
Protoss_Shuttle 1 15084
Protoss_Citadel_of_Adun 1 15826
15826
