Protoss_Forge 1 4234
Protoss_Photon_Cannon 2 10179
Protoss_Nexus 1 8554
Protoss_Gateway 2 14033
Protoss_Assimilator 2 10337
Protoss_Zealot 4 13141
Protoss_Cybernetics_Core 1 9789
Protoss_Stargate 1 11715
Protoss_Dragoon 1 11278
Protoss_Citadel_of_Adun 1 12368
Protoss_Corsair 3 14540
Protoss_Templar_Archives 1 13811
Protoss_Dark_Templar 2 15358
Protoss_Robotics_Facility 1 15910
15910
