Protoss_Forge 1 4423
Protoss_Nexus 1 7650
Protoss_Photon_Cannon 2 6876
Protoss_Gateway 4 14853
Protoss_Assimilator 2 14532
Protoss_Zealot 9 15555
Protoss_Cybernetics_Core 1 11563
Protoss_Dragoon 1 12812
Protoss_Citadel_of_Adun 1 13198
Protoss_Templar_Archives 1 15365
15555
