Protoss_Nexus 1 7187
Protoss_Forge 1 5996
Protoss_Gateway 1 7896
Protoss_Photon_Cannon 2 14271
Protoss_Assimilator 2 9711
Protoss_Zealot 5 14789
Protoss_Cybernetics_Core 1 10553
Protoss_Stargate 1 12265
Protoss_Citadel_of_Adun 1 12697
Protoss_Dragoon 1 13391
Protoss_Corsair 1 13208
Protoss_Templar_Archives 1 14396
Protoss_Dark_Templar 1 15689
15689
