Protoss_Forge 1 4161
Protoss_Photon_Cannon 3 9006
Protoss_Gateway 2 9421
Protoss_Nexus 1 9672
Protoss_Assimilator 3 11164
Protoss_Cybernetics_Core 1 10943
Protoss_Zealot 2 13726
Protoss_Stargate 1 12676
Protoss_Dragoon 1 12402
Protoss_Robotics_Facility 1 14351
Protoss_Corsair 3 15532
Protoss_Shuttle 1 15775
15775
