Protoss_Nexus 1 7405
Protoss_Forge 1 6269
Protoss_Gateway 3 14193
Protoss_Photon_Cannon 3 12354
Protoss_Assimilator 2 9449
Protoss_Cybernetics_Core 1 10804
Protoss_Stargate 1 12534
Protoss_Citadel_of_Adun 1 12355
Protoss_Corsair 2 14355
Protoss_Templar_Archives 1 14069
Protoss_Dark_Templar 1 15478
Protoss_High_Templar 1 15505
Protoss_Dragoon 1 15525
15525
