Protoss_Nexus 2 17174
Protoss_Forge 1 5838
Protoss_Gateway 3 13722
Protoss_Assimilator 2 9564
Protoss_Photon_Cannon 2 12224
Protoss_Zealot 6 14218
Protoss_Cybernetics_Core 1 9336
Protoss_Stargate 1 11081
Protoss_Dragoon 1 10839
Protoss_Citadel_of_Adun 1 11949
Protoss_Corsair 1 12711
Protoss_Templar_Archives 1 13744
Protoss_Robotics_Facility 1 15592
Protoss_High_Templar 2 15183
Protoss_Dark_Templar 1 15338
17174
