Protoss_Gateway 3 9380
Protoss_Assimilator 1 4413
Protoss_Zealot 19 15579
Protoss_Cybernetics_Core 1 7161
Protoss_Dragoon 1 8709
Protoss_Citadel_of_Adun 1 9817
Leg_Enhancements 1 13152
Protoss_Templar_Archives 1 14587
Protoss_Forge 1 15260
15579
