Protoss_Forge 1 4407
Protoss_Photon_Cannon 2 6633
Protoss_Nexus 1 8762
Protoss_Gateway 1 7739
Protoss_Assimilator 2 9899
Protoss_Cybernetics_Core 1 9261
Protoss_Zealot 3 13957
Protoss_Stargate 1 11151
Protoss_Corsair 1 12096
Protoss_Citadel_of_Adun 1 12667
13957
