Protoss_Gateway 3 15590
Protoss_Assimilator 1 4735
Protoss_Cybernetics_Core 1 5753
Protoss_Zealot 5 13720
Protoss_Stargate 1 7711
Protoss_Dragoon 1 7696
Protoss_Corsair 2 11300
Protoss_Forge 1 9179
Protoss_Citadel_of_Adun 1 11528
Protoss_Robotics_Facility 1 14569
Leg_Enhancements 1 14501
15590
