Protoss_Forge 3 14933
Protoss_Photon_Cannon 4 9710
Protoss_Nexus 1 9317
Protoss_Gateway 1 8759
Protoss_Assimilator 2 11952
Protoss_Cybernetics_Core 1 11036
Protoss_Zealot 4 14815
Protoss_Stargate 1 13285
Protoss_Citadel_of_Adun 2 15545
Protoss_Dragoon 1 13918
Protoss_Corsair 1 14856
15545
