Protoss_Forge 1 4129
Protoss_Photon_Cannon 2 5548
Protoss_Nexus 1 9188
Protoss_Gateway 4 13375
Protoss_Assimilator 2 13802
Protoss_Cybernetics_Core 1 9775
Protoss_Zealot 10 14976
Protoss_Citadel_of_Adun 1 11475
Protoss_Templar_Archives 1 15914
15914
