Protoss_Forge 1 4003
Protoss_Photon_Cannon 3 12613
Protoss_Nexus 1 8288
Protoss_Gateway 3 14768
Protoss_Assimilator 2 10038
Protoss_Zealot 3 13612
Protoss_Cybernetics_Core 1 9968
Protoss_Stargate 1 11936
Protoss_Citadel_of_Adun 1 12365
Protoss_Corsair 1 13100
Protoss_Templar_Archives 1 13908
Protoss_Dark_Templar 1 15268
15268
