Protoss_Forge 1 4521
Protoss_Photon_Cannon 4 15405
Protoss_Nexus 2 16233
Protoss_Gateway 1 8834
Protoss_Assimilator 2 11423
Protoss_Zealot 3 13592
Protoss_Cybernetics_Core 1 10946
Protoss_Stargate 1 12676
Protoss_Robotics_Facility 1 14035
Protoss_Corsair 3 15570
Protoss_Robotics_Support_Bay 1 14878
16233
