Protoss_Gateway 2 10564
Protoss_Assimilator 1 4512
Protoss_Zealot 8 12482
Protoss_Cybernetics_Core 1 7243
Protoss_Dragoon 1 8700
Protoss_Citadel_of_Adun 1 9586
Protoss_Templar_Archives 1 11926
Protoss_Forge 1 13116
Protoss_High_Templar 3 14940
Leg_Enhancements 1 12666
Protoss_Photon_Cannon 1 14678
Protoss_Dark_Templar 1 14960
Protoss_Archon 1 14459
Protoss_Robotics_Facility 1 16330
16330
