Protoss_Forge 1 4255
Protoss_Photon_Cannon 2 7374
Protoss_Nexus 1 8455
Protoss_Gateway 1 8380
Protoss_Assimilator 2 9955
Protoss_Zealot 4 12696
Protoss_Cybernetics_Core 1 9959
Protoss_Stargate 1 11845
Protoss_Robotics_Facility 1 12572
Protoss_Corsair 3 15067
Protoss_Shuttle 1 14030
Protoss_Robotics_Support_Bay 1 13416
Protoss_Reaver 1 15588
15588
