Protoss_Forge 1 4442
Protoss_Nexus 1 7658
Protoss_Photon_Cannon 3 15663
Protoss_Gateway 5 15779
Protoss_Assimilator 2 12389
Protoss_Zealot 8 14045
Protoss_Cybernetics_Core 1 10635
Protoss_Citadel_of_Adun 1 12204
Protoss_Templar_Archives 1 15611
15779
