Protoss_Forge 1 4223
Protoss_Photon_Cannon 3 15401
Protoss_Nexus 1 8373
Protoss_Gateway 4 14475
Protoss_Assimilator 2 10552
Protoss_Cybernetics_Core 1 9782
Protoss_Zealot 2 11335
Protoss_Stargate 1 11614
Protoss_Citadel_of_Adun 1 12315
Protoss_Corsair 1 12567
Protoss_Templar_Archives 1 13793
Protoss_Dark_Templar 1 15019
Protoss_High_Templar 2 15259
15401
