Protoss_Forge 1 4151
Protoss_Photon_Cannon 3 14277
Protoss_Nexus 1 8753
Protoss_Gateway 4 15958
Protoss_Assimilator 2 9888
Protoss_Cybernetics_Core 1 9639
Protoss_Stargate 1 11541
Protoss_Zealot 2 12184
Protoss_Citadel_of_Adun 1 12068
Protoss_Corsair 3 14300
Protoss_Templar_Archives 1 13526
Protoss_Dark_Templar 2 14843
15958
