Protoss_Gateway 3 15437
Protoss_Zealot 9 12163
Protoss_Assimilator 1 6228
Protoss_Forge 1 6934
Protoss_Photon_Cannon 1 9137
Protoss_Cybernetics_Core 1 11407
Protoss_Dragoon 5 15658
Protoss_Citadel_of_Adun 1 14004
Protoss_Ground_Weapons_1 1 13370
15658
