Protoss_Nexus 1 7061
Protoss_Forge 1 5748
Protoss_Photon_Cannon 7 14921
Protoss_Gateway 1 9438
Protoss_Assimilator 2 15409
Protoss_Cybernetics_Core 1 11654
Protoss_Zealot 4 14042
Protoss_Stargate 2 13559
Protoss_Corsair 4 15485
15485
