Protoss_Forge 1 4062
Protoss_Photon_Cannon 6 15737
Protoss_Nexus 1 9549
Protoss_Gateway 1 8633
Protoss_Zealot 5 14540
Protoss_Assimilator 2 11505
Protoss_Cybernetics_Core 1 12450
Protoss_Stargate 1 14191
Protoss_Robotics_Facility 1 15305
Protoss_Corsair 1 15245
15737
