Protoss_Forge 1 4498
Protoss_Photon_Cannon 3 12932
Protoss_Nexus 1 8355
Protoss_Gateway 1 7807
Protoss_Assimilator 2 9560
Protoss_Cybernetics_Core 1 9333
Protoss_Zealot 1 9810
Protoss_Stargate 1 11045
Protoss_Robotics_Facility 1 12106
Protoss_Corsair 4 15438
Protoss_Shuttle 1 13641
Protoss_Robotics_Support_Bay 1 12991
Protoss_Reaver 1 15416
15438
