Protoss_Forge 1 4979
Protoss_Nexus 1 7544
Protoss_Photon_Cannon 2 6903
Protoss_Gateway 4 15858
Protoss_Assimilator 2 11720
Protoss_Zealot 4 15029
Protoss_Cybernetics_Core 1 10504
Protoss_Stargate 1 12294
Protoss_Dragoon 1 12540
Protoss_Citadel_of_Adun 1 13545
Protoss_Corsair 2 14115
Protoss_Templar_Archives 1 15122
15858
