Protoss_Forge 1 3763
Protoss_Photon_Cannon 1 6319
Protoss_Nexus 1 8275
Protoss_Gateway 3 14522
Protoss_Assimilator 2 10868
Protoss_Zealot 6 14746
Protoss_Cybernetics_Core 1 9182
Protoss_Stargate 1 10961
Protoss_Citadel_of_Adun 1 13208
Protoss_Dragoon 1 13885
Protoss_Templar_Archives 1 14724
14746
