Protoss_Forge 1 4476
Protoss_Nexus 1 7708
Protoss_Photon_Cannon 2 12553
Protoss_Gateway 4 15854
Protoss_Assimilator 2 13792
Protoss_Zealot 3 14554
Protoss_Cybernetics_Core 1 10840
Protoss_Citadel_of_Adun 1 13240
Protoss_Dragoon 1 13468
Protoss_Templar_Archives 1 14727
15854
