Protoss_Gateway 4 14862
Protoss_Zealot 8 15435
Protoss_Nexus 1 9394
Protoss_Assimilator 1 7934
Protoss_Cybernetics_Core 1 8882
Protoss_Stargate 1 10841
Protoss_Dragoon 1 11855
Protoss_Forge 1 11631
Protoss_Corsair 1 11815
Protoss_Citadel_of_Adun 1 14401
15435
