Protoss_Nexus 1 7007
Protoss_Gateway 4 14993
Protoss_Forge 1 6671
Protoss_Assimilator 2 8584
Protoss_Photon_Cannon 3 13084
Protoss_Cybernetics_Core 1 8385
Protoss_Stargate 1 10336
Protoss_Zealot 2 12596
Protoss_Citadel_of_Adun 1 10703
Protoss_Corsair 2 12438
Protoss_Templar_Archives 1 12579
Protoss_Dark_Templar 2 13927
Protoss_High_Templar 2 15028
15028
