Protoss_Forge 1 4166
Protoss_Photon_Cannon 7 14477
Protoss_Nexus 2 17381
Protoss_Gateway 1 8938
Protoss_Assimilator 2 15232
Protoss_Zealot 3 14914
Protoss_Cybernetics_Core 1 13164
Protoss_Stargate 1 15313
17381
