Protoss_Forge 1 4308
Protoss_Photon_Cannon 6 15587
Protoss_Nexus 1 8510
Protoss_Gateway 3 14712
Protoss_Assimilator 2 12078
Protoss_Zealot 3 10457
Protoss_Cybernetics_Core 1 9564
Protoss_Dragoon 2 11267
Protoss_Stargate 1 11375
Protoss_Citadel_of_Adun 1 12011
Protoss_Corsair 1 12599
Protoss_Templar_Archives 1 14168
Protoss_Dark_Templar 2 15434
15587
