Protoss_Forge 1 4128
Protoss_Photon_Cannon 2 14498
Protoss_Nexus 1 7957
Protoss_Gateway 2 13215
Protoss_Assimilator 2 9959
Protoss_Zealot 6 13158
Protoss_Cybernetics_Core 1 9620
Protoss_Stargate 1 11479
Protoss_Citadel_of_Adun 1 12280
Protoss_Corsair 3 14481
Protoss_Templar_Archives 1 14030
14498
