Protoss_Gateway 2 13461
Protoss_Zealot 6 13539
Protoss_Assimilator 1 5989
Protoss_Cybernetics_Core 1 7255
Protoss_Stargate 1 10393
Protoss_Dragoon 1 10225
Protoss_Citadel_of_Adun 1 11433
Protoss_Corsair 1 11440
Protoss_Forge 1 11938
Protoss_Templar_Archives 1 12999
Protoss_Dark_Templar 2 15247
15247
