Protoss_Forge 1 4520
Protoss_Photon_Cannon 3 14212
Protoss_Nexus 1 9218
Protoss_Gateway 4 14936
Protoss_Assimilator 2 11871
Protoss_Cybernetics_Core 1 9918
Protoss_Zealot 2 10562
Protoss_Stargate 1 11667
Protoss_Dragoon 3 15133
Protoss_Robotics_Facility 1 13309
Protoss_Corsair 2 14192
Protoss_Shuttle 1 15895
Protoss_Robotics_Support_Bay 1 15247
15895
