Protoss_Gateway 1 4223
Protoss_Assimilator 2 15572
Protoss_Zealot 2 6232
Protoss_Cybernetics_Core 1 7293
Protoss_Stargate 1 8980
Protoss_Dragoon 1 8644
Protoss_Citadel_of_Adun 1 9541
Protoss_Corsair 1 9977
Protoss_Templar_Archives 1 10987
Protoss_Forge 1 10925
Protoss_Dark_Templar 2 13289
Protoss_Photon_Cannon 3 15107
Protoss_Robotics_Facility 1 13459
Protoss_Nexus 1 15906
Protoss_High_Templar 1 14441
Protoss_Observatory 1 14169
Protoss_Observer 1 15254
15906
