Protoss_Forge 1 3994
Protoss_Photon_Cannon 2 12511
Protoss_Nexus 1 8206
Protoss_Gateway 3 15115
Protoss_Assimilator 2 9301
Protoss_Zealot 3 13943
Protoss_Cybernetics_Core 1 8904
Protoss_Stargate 1 10885
Protoss_Dragoon 1 11489
Protoss_Citadel_of_Adun 1 12331
Protoss_Corsair 3 14794
Protoss_Templar_Archives 1 14086
Protoss_Dark_Templar 1 15282
15282
