Protoss_Forge 1 4267
Protoss_Photon_Cannon 2 6227
Protoss_Nexus 1 9318
Protoss_Gateway 4 14080
Protoss_Zealot 15 15526
Protoss_Assimilator 2 13280
Protoss_Cybernetics_Core 1 10725
Protoss_Citadel_of_Adun 1 12307
Protoss_Templar_Archives 1 15427
15526
