Protoss_Forge 1 4150
Protoss_Nexus 1 7928
Protoss_Photon_Cannon 4 8495
Protoss_Gateway 3 14989
Protoss_Assimilator 2 10871
Protoss_Cybernetics_Core 1 11569
Protoss_Zealot 3 13984
Protoss_Stargate 1 13259
Protoss_Citadel_of_Adun 1 13057
Protoss_Dragoon 1 13122
Protoss_Templar_Archives 1 14635
Protoss_Corsair 2 15456
15456
