Protoss_Forge 1 4091
Protoss_Nexus 1 7345
Protoss_Photon_Cannon 4 13295
Protoss_Gateway 2 15819
Protoss_Assimilator 2 11036
Protoss_Cybernetics_Core 1 9863
Protoss_Zealot 3 15113
Protoss_Stargate 1 11614
Protoss_Robotics_Facility 1 12756
Protoss_Dragoon 2 13792
Protoss_Corsair 1 12602
Protoss_Citadel_of_Adun 1 13747
Protoss_Robotics_Support_Bay 1 13693
Protoss_Reaver 1 15439
Protoss_Templar_Archives 1 15405
15819
