Protoss_Forge 1 4300
Protoss_Nexus 1 7651
Protoss_Photon_Cannon 1 6347
Protoss_Gateway 4 14069
Protoss_Assimilator 2 9677
Protoss_Cybernetics_Core 1 8856
Protoss_Zealot 7 15011
Protoss_Stargate 1 10680
Protoss_Citadel_of_Adun 1 11537
Protoss_Corsair 1 11710
Protoss_Templar_Archives 1 13401
Protoss_Dark_Templar 1 15066
Protoss_High_Templar 1 15066
15066
