Protoss_Nexus 1 6974
Protoss_Gateway 1 5999
Protoss_Forge 1 6406
Protoss_Zealot 7 14853
Protoss_Assimilator 2 13805
Protoss_Photon_Cannon 2 9718
Protoss_Cybernetics_Core 1 10711
Protoss_Stargate 1 12550
Protoss_Citadel_of_Adun 1 13097
Protoss_Corsair 1 13521
Protoss_Templar_Archives 1 15757
15757
