Protoss_Forge 1 3921
Protoss_Nexus 1 7793
Protoss_Gateway 1 7000
Protoss_Photon_Cannon 5 15484
Protoss_Zealot 3 11677
Protoss_Assimilator 2 10571
Protoss_Cybernetics_Core 1 9649
Protoss_Stargate 2 13027
Protoss_Citadel_of_Adun 1 13176
Protoss_Corsair 5 15535
Protoss_Templar_Archives 1 15040
15535
