Protoss_Nexus 2 17057
Protoss_Gateway 2 11832
Protoss_Forge 1 6454
Protoss_Assimilator 2 9296
Protoss_Photon_Cannon 5 15590
Protoss_Cybernetics_Core 1 8294
Protoss_Zealot 1 8598
Protoss_Stargate 1 10393
Protoss_Dragoon 1 10181
Protoss_Citadel_of_Adun 1 11158
Protoss_Corsair 3 13536
Protoss_Templar_Archives 1 12787
Protoss_Dark_Templar 2 14032
Protoss_High_Templar 2 15133
17057
