Protoss_Forge 1 4669
Protoss_Photon_Cannon 2 6016
Protoss_Nexus 1 9475
Protoss_Gateway 3 15166
Protoss_Assimilator 2 11745
Protoss_Zealot 7 15380
Protoss_Cybernetics_Core 1 9956
Protoss_Stargate 1 11672
Protoss_Robotics_Facility 1 13020
Protoss_Corsair 2 15345
Protoss_Shuttle 1 14554
15380
