Protoss_Gateway 2 15481
Protoss_Zealot 10 15523
Protoss_Assimilator 1 5306
Protoss_Cybernetics_Core 1 7069
Protoss_Dragoon 1 8480
Protoss_Stargate 1 9249
Protoss_Forge 1 8841
Protoss_Citadel_of_Adun 1 10043
Protoss_Corsair 1 10188
Protoss_Photon_Cannon 1 11796
Protoss_Nexus 1 14897
Protoss_Robotics_Facility 1 14746
Leg_Enhancements 1 13079
Protoss_Templar_Archives 1 16021
16021
