Protoss_Gateway 5 14879
Protoss_Zealot 12 14979
Protoss_Forge 1 7041
Protoss_Photon_Cannon 3 13359
Protoss_Nexus 1 10556
Protoss_Assimilator 2 12203
Protoss_Cybernetics_Core 1 10457
Protoss_Citadel_of_Adun 1 12851
Protoss_Dragoon 1 13506
Protoss_Templar_Archives 1 15757
15757
