Protoss_Forge 1 4659
Protoss_Photon_Cannon 4 15671
Protoss_Nexus 1 7982
Protoss_Gateway 3 14718
Protoss_Assimilator 2 10763
Protoss_Zealot 5 15389
Protoss_Cybernetics_Core 1 10158
Protoss_Stargate 1 11983
Protoss_Citadel_of_Adun 1 13088
Protoss_Corsair 1 13024
Protoss_Templar_Archives 1 14607
15671
