Protoss_Nexus 1 7114
Protoss_Gateway 6 15574
Protoss_Forge 1 6465
Protoss_Assimilator 2 10059
Protoss_Photon_Cannon 2 11095
Protoss_Zealot 6 13012
Protoss_Cybernetics_Core 1 10344
Protoss_Stargate 1 12168
Protoss_Citadel_of_Adun 1 12195
Protoss_Templar_Archives 1 13641
Protoss_Corsair 1 13878
Protoss_Dark_Templar 2 14849
Protoss_High_Templar 1 15537
Protoss_Ground_Weapons_1 1 14358
15574
