Protoss_Forge 1 4191
Protoss_Nexus 1 7512
Protoss_Photon_Cannon 2 6875
Protoss_Gateway 5 15737
Protoss_Assimilator 2 14813
Protoss_Zealot 9 15468
Protoss_Cybernetics_Core 1 10050
Protoss_Stargate 1 11782
Protoss_Dragoon 1 12590
Protoss_Citadel_of_Adun 1 12833
Protoss_Corsair 3 14715
15737
