Protoss_Forge 2 6503
Protoss_Nexus 2 16377
Protoss_Gateway 4 15751
Protoss_Photon_Cannon 2 13918
Protoss_Assimilator 2 11227
Protoss_Zealot 3 12412
Protoss_Cybernetics_Core 1 9801
Protoss_Dragoon 1 11003
Protoss_Stargate 1 11776
Protoss_Citadel_of_Adun 1 11572
Protoss_Templar_Archives 1 13097
Protoss_Corsair 3 14914
Protoss_Dark_Templar 2 14820
16377
