Protoss_Forge 1 4188
Protoss_Photon_Cannon 4 15822
Protoss_Nexus 1 8459
Protoss_Gateway 3 15519
Protoss_Assimilator 2 11755
Protoss_Zealot 6 14674
Protoss_Cybernetics_Core 1 9791
Protoss_Stargate 1 11949
Protoss_Citadel_of_Adun 1 12902
Protoss_Dragoon 1 12932
Protoss_Corsair 1 12895
Protoss_Templar_Archives 1 14636
15822
