Protoss_Nexus 1 7038
Protoss_Gateway 3 15877
Protoss_Assimilator 2 11085
Protoss_Zealot 7 14759
Protoss_Forge 1 7685
Protoss_Cybernetics_Core 1 9321
Protoss_Photon_Cannon 1 10492
Protoss_Stargate 1 11456
Protoss_Robotics_Facility 1 11924
Protoss_Corsair 3 14230
Protoss_Dragoon 1 12715
Protoss_Shuttle 1 13752
Protoss_Citadel_of_Adun 1 13769
Protoss_Robotics_Support_Bay 1 13776
Protoss_Templar_Archives 1 15465
Protoss_Reaver 1 15820
15877
