Protoss_Gateway 3 9194
Protoss_Assimilator 2 11512
Protoss_Zealot 11 12292
Protoss_Forge 1 5821
Protoss_Photon_Cannon 2 15164
Protoss_Ground_Weapons_1 1 11731
Protoss_Nexus 1 15410
Protoss_Cybernetics_Core 1 14698
15410
