Protoss_Gateway 2 11171
Protoss_Assimilator 1 4953
Protoss_Zealot 9 14711
Protoss_Forge 1 6876
Protoss_Photon_Cannon 1 8659
Protoss_Cybernetics_Core 1 9724
Protoss_Citadel_of_Adun 1 11718
Protoss_Ground_Weapons_1 1 12989
Protoss_Templar_Archives 1 16024
16024
