Protoss_Forge 1 4120
Protoss_Photon_Cannon 5 14665
Protoss_Nexus 1 8311
Protoss_Gateway 3 15397
Protoss_Assimilator 2 11218
Protoss_Zealot 4 12781
Protoss_Cybernetics_Core 1 9732
Protoss_Stargate 1 11438
Protoss_Dragoon 1 11038
Protoss_Citadel_of_Adun 1 12668
Protoss_Corsair 3 14194
Protoss_Templar_Archives 1 14525
Protoss_Dark_Templar 2 15774
15774
