Protoss_Forge 1 3956
Protoss_Photon_Cannon 6 15718
Protoss_Nexus 1 8210
Protoss_Gateway 4 14540
Protoss_Assimilator 2 11955
Protoss_Zealot 8 14525
Protoss_Cybernetics_Core 1 10319
Protoss_Citadel_of_Adun 1 11860
Protoss_Templar_Archives 1 14164
Protoss_High_Templar 2 15613
Protoss_Dark_Templar 1 15645
15718
