Protoss_Nexus 1 6745
Protoss_Forge 1 5262
Protoss_Gateway 2 7572
Protoss_Assimilator 2 12023
Protoss_Zealot 11 14636
Protoss_Photon_Cannon 2 14136
Protoss_Cybernetics_Core 1 11216
Protoss_Stargate 2 13652
Protoss_Citadel_of_Adun 1 13432
Protoss_Corsair 2 15105
Protoss_Templar_Archives 1 15883
15883
