Protoss_Gateway 2 14420
Protoss_Assimilator 1 4366
Protoss_Zealot 6 13934
Protoss_Cybernetics_Core 1 7852
Protoss_Dragoon 1 9080
Protoss_Stargate 1 9802
Protoss_Citadel_of_Adun 1 11414
14420
