Protoss_Gateway 2 4924
Protoss_Zealot 13 15255
Protoss_Assimilator 1 8749
Protoss_Cybernetics_Core 1 10444
Protoss_Forge 1 11088
Protoss_Stargate 1 12149
Protoss_Dragoon 1 11817
Protoss_Photon_Cannon 2 13188
Protoss_Citadel_of_Adun 1 12909
15255
