Protoss_Forge 1 4169
Protoss_Photon_Cannon 6 15168
Protoss_Nexus 1 9988
Protoss_Gateway 3 14882
Protoss_Assimilator 2 11824
Protoss_Cybernetics_Core 1 10562
Protoss_Zealot 5 15055
Protoss_Stargate 1 12348
Protoss_Citadel_of_Adun 1 12949
Protoss_Corsair 2 14221
Protoss_Templar_Archives 1 14399
Protoss_Dark_Templar 1 15592
15592
