Protoss_Nexus 2 15217
Protoss_Gateway 4 14745
Protoss_Forge 2 15539
Protoss_Assimilator 2 12541
Protoss_Photon_Cannon 1 8303
Protoss_Cybernetics_Core 1 9358
Protoss_Zealot 10 14789
Protoss_Dragoon 1 10734
Protoss_Citadel_of_Adun 1 11250
Protoss_Templar_Archives 1 14127
Protoss_Ground_Weapons_1 1 14270
Leg_Enhancements 1 14314
15539
