Protoss_Nexus 1 7098
Protoss_Forge 1 5976
Protoss_Photon_Cannon 2 8937
Protoss_Gateway 3 9759
Protoss_Assimilator 2 13731
Protoss_Zealot 9 13114
Protoss_Cybernetics_Core 1 12921
Protoss_Citadel_of_Adun 1 14559
14559
