Protoss_Gateway 2 13867
Protoss_Zealot 3 6842
Protoss_Nexus 1 9675
Protoss_Forge 1 8841
Protoss_Assimilator 1 8957
Protoss_Cybernetics_Core 1 10353
Protoss_Photon_Cannon 7 14954
Protoss_Dragoon 4 15102
15102
