Protoss_Assimilator 1 3550
Protoss_Forge 1 4741
Protoss_Gateway 3 8458
Protoss_Photon_Cannon 2 13605
Protoss_Zealot 8 11461
Protoss_Cybernetics_Core 1 11515
Protoss_Ground_Weapons_1 1 10648
Protoss_Dragoon 6 15688
15688
