Protoss_Gateway 2 11234
Protoss_Zealot 10 14695
Protoss_Forge 1 7409
Protoss_Photon_Cannon 2 14009
Protoss_Nexus 1 11051
Protoss_Assimilator 1 9891
Protoss_Cybernetics_Core 1 12583
Protoss_Robotics_Facility 1 14954
Protoss_Citadel_of_Adun 1 14614
Protoss_Dragoon 1 15720
15720
