Protoss_Gateway 2 5082
Protoss_Zealot 11 13346
Protoss_Assimilator 1 7881
Protoss_Cybernetics_Core 1 9757
Protoss_Citadel_of_Adun 1 11540
Protoss_Dragoon 1 11460
Protoss_Templar_Archives 1 13366
Protoss_Forge 1 13772
Protoss_Dark_Templar 1 14635
Protoss_Photon_Cannon 1 15631
Leg_Enhancements 1 14472
15631
