Protoss_Gateway 2 12747
Protoss_Zealot 8 13722
Protoss_Assimilator 1 6182
Protoss_Forge 1 6968
Protoss_Photon_Cannon 2 15587
Protoss_Cybernetics_Core 1 10496
Protoss_Dragoon 1 11736
Protoss_Citadel_of_Adun 1 11998
Protoss_Templar_Archives 1 13685
Protoss_Ground_Weapons_1 1 13531
Protoss_High_Templar 2 14919
15587
