Protoss_Forge 1 4770
Protoss_Nexus 1 7575
Protoss_Photon_Cannon 4 15161
Protoss_Gateway 1 8107
Protoss_Assimilator 2 12200
Protoss_Zealot 3 13319
Protoss_Cybernetics_Core 1 10264
Protoss_Stargate 1 13424
Protoss_Citadel_of_Adun 1 13984
Protoss_Corsair 1 14396
Protoss_Templar_Archives 1 15789
15789
