Protoss_Gateway 3 15826
Protoss_Assimilator 1 4881
Protoss_Zealot 11 14929
Protoss_Cybernetics_Core 1 8983
Protoss_Citadel_of_Adun 1 10739
Protoss_Dragoon 1 10747
Protoss_Templar_Archives 1 14238
Leg_Enhancements 1 14058
Protoss_Forge 1 15529
15826
