Protoss_Forge 1 4049
Protoss_Photon_Cannon 3 15440
Protoss_Nexus 1 10407
Protoss_Gateway 2 9841
Protoss_Assimilator 1 9820
Protoss_Zealot 11 15112
Protoss_Cybernetics_Core 1 14568
Protoss_Citadel_of_Adun 1 16016
16016
