Protoss_Gateway 1 4521
Protoss_Assimilator 1 4688
Protoss_Zealot 8 14988
Protoss_Cybernetics_Core 1 6965
Protoss_Robotics_Facility 1 9503
Protoss_Dragoon 1 9058
Protoss_Shuttle 2 15889
Protoss_Robotics_Support_Bay 1 10624
Protoss_Shield_Battery 1 11328
Protoss_Reaver 2 14252
Protoss_Citadel_of_Adun 1 14222
15889
