Protoss_Assimilator 1 3598
Protoss_Gateway 1 4821
Protoss_Cybernetics_Core 1 6296
Protoss_Stargate 1 8023
Protoss_Robotics_Facility 1 9051
Protoss_Corsair 6 14818
Protoss_Shuttle 1 10869
Protoss_Forge 1 11158
Protoss_Photon_Cannon 2 15279
Protoss_Nexus 1 15843
Protoss_Air_Weapons_1 1 14167
15843
