Protoss_Gateway 2 12124
Protoss_Assimilator 1 4570
Protoss_Zealot 6 12214
Protoss_Cybernetics_Core 1 7755
Protoss_Dragoon 1 9058
Protoss_Citadel_of_Adun 1 9577
Protoss_Templar_Archives 1 11322
Protoss_Dark_Templar 1 12534
Protoss_Forge 1 12706
Leg_Enhancements 1 12521
Protoss_Robotics_Facility 1 14464
Protoss_Photon_Cannon 2 14651
Protoss_High_Templar 2 15161
15161
