Protoss_Gateway 2 5351
Protoss_Zealot 11 14329
Protoss_Assimilator 1 7281
Protoss_Forge 1 10155
Protoss_Cybernetics_Core 1 11086
Protoss_Citadel_of_Adun 1 12541
Protoss_Photon_Cannon 3 15793
Protoss_Templar_Archives 1 14076
Protoss_High_Templar 2 15449
15793
