Protoss_Gateway 2 4880
Protoss_Zealot 11 12634
Protoss_Assimilator 1 7444
Protoss_Forge 1 8127
Protoss_Photon_Cannon 2 14375
Protoss_Cybernetics_Core 1 11436
Protoss_Stargate 1 13788
Protoss_Dragoon 2 14744
Protoss_Corsair 1 14739
Protoss_Citadel_of_Adun 1 15629
Protoss_Ground_Weapons_1 1 14358
15629
