Protoss_Gateway 1 4180
Protoss_Assimilator 2 15440
Protoss_Zealot 3 9219
Protoss_Cybernetics_Core 1 7063
Protoss_Stargate 1 8759
Protoss_Dragoon 1 8357
Protoss_Citadel_of_Adun 1 9274
Protoss_Corsair 1 9898
Protoss_Templar_Archives 1 11114
Protoss_Forge 1 11499
Protoss_Dark_Templar 1 12610
Protoss_Nexus 1 14958
Protoss_High_Templar 2 15148
Protoss_Photon_Cannon 3 15402
15440
