Protoss_Gateway 2 10697
Protoss_Assimilator 1 4649
Protoss_Zealot 8 13327
Protoss_Cybernetics_Core 1 7221
Protoss_Dragoon 1 8444
Protoss_Citadel_of_Adun 1 9905
Protoss_Templar_Archives 1 12168
Protoss_Forge 1 13132
Protoss_Dark_Templar 1 14057
Leg_Enhancements 1 12938
Protoss_High_Templar 2 15423
Protoss_Photon_Cannon 1 14663
15423
