Protoss_Gateway 2 5036
Protoss_Zealot 15 14139
Protoss_Assimilator 1 9453
Protoss_Cybernetics_Core 1 12690
Protoss_Forge 1 12495
Protoss_Stargate 1 14451
Protoss_Dragoon 1 14205
Protoss_Citadel_of_Adun 1 15245
15245
