Protoss_Gateway 1 4492
Protoss_Assimilator 1 4783
Protoss_Cybernetics_Core 1 6282
Protoss_Zealot 3 8834
Protoss_Stargate 1 8138
Protoss_Corsair 1 9353
Protoss_Forge 1 10081
Protoss_Citadel_of_Adun 1 11717
Protoss_Photon_Cannon 4 14729
Protoss_Nexus 1 14602
Protoss_Robotics_Facility 1 16145
16145
