Protoss_Gateway 2 4975
Protoss_Zealot 15 13253
Protoss_Assimilator 1 9274
Protoss_Cybernetics_Core 1 12980
Protoss_Forge 1 13795
Protoss_Dragoon 2 14744
Protoss_Photon_Cannon 1 15323
15323
