Protoss_Gateway 2 10370
Protoss_Assimilator 1 4439
Protoss_Zealot 7 11549
Protoss_Cybernetics_Core 1 6958
Protoss_Citadel_of_Adun 1 9214
Protoss_Templar_Archives 1 11698
Protoss_Forge 1 12749
Protoss_High_Templar 4 15578
Leg_Enhancements 1 12155
Protoss_Archon 1 13806
Protoss_Nexus 1 16361
Protoss_Dark_Templar 1 14773
Protoss_Photon_Cannon 2 15361
16361
