Protoss_Gateway 3 14759
Protoss_Assimilator 1 4590
Protoss_Cybernetics_Core 1 6232
Protoss_Stargate 1 7966
Protoss_Forge 1 7556
Protoss_Photon_Cannon 1 8877
Protoss_Corsair 1 8914
Protoss_Zealot 7 15185
Protoss_Citadel_of_Adun 1 10957
Protoss_Templar_Archives 1 15140
Leg_Enhancements 1 13897
15185
