Protoss_Assimilator 1 3572
Protoss_Gateway 1 4621
Protoss_Cybernetics_Core 1 6184
Protoss_Dragoon 3 15531
Protoss_Stargate 1 8047
Protoss_Corsair 6 14824
Protoss_Robotics_Facility 1 10387
Protoss_Forge 1 10343
Protoss_Shuttle 1 12470
Protoss_Photon_Cannon 1 12777
Protoss_Air_Weapons_1 1 12733
Protoss_Nexus 1 16540
16540
