Protoss_Gateway 2 8633
Protoss_Assimilator 1 5196
Protoss_Forge 1 5437
Protoss_Photon_Cannon 3 15590
Protoss_Zealot 11 12851
Protoss_Cybernetics_Core 1 11070
Protoss_Citadel_of_Adun 1 12844
Protoss_Ground_Weapons_1 1 12199
Protoss_Templar_Archives 1 14983
15590
