Protoss_Gateway 4 15737
Protoss_Zealot 10 14756
Protoss_Nexus 1 9924
Protoss_Assimilator 1 9024
Protoss_Cybernetics_Core 1 10989
Protoss_Dragoon 2 12736
Protoss_Citadel_of_Adun 1 12789
Protoss_Templar_Archives 1 14767
Protoss_Forge 1 14895
15737
