Protoss_Gateway 2 5070
Protoss_Zealot 12 12361
Protoss_Forge 1 7230
Protoss_Photon_Cannon 3 14868
Protoss_Assimilator 1 10373
Protoss_Cybernetics_Core 1 11911
Protoss_Citadel_of_Adun 1 13843
Protoss_Dragoon 2 14173
Protoss_Templar_Archives 1 15972
15972
