Protoss_Forge 1 5186
Protoss_Nexus 1 7917
Protoss_Photon_Cannon 5 13304
Protoss_Gateway 2 14758
Protoss_Assimilator 2 10608
Protoss_Cybernetics_Core 1 10243
Protoss_Zealot 2 11490
Protoss_Stargate 1 12062
Protoss_Corsair 3 14983
Protoss_Dragoon 1 14436
Protoss_Robotics_Facility 1 15452
15452
