Protoss_Forge 1 4324
Protoss_Photon_Cannon 7 15114
Protoss_Nexus 1 9396
Protoss_Gateway 3 9614
Protoss_Zealot 14 15544
Protoss_Assimilator 2 14734
Protoss_Cybernetics_Core 1 15797
15797
