Protoss_Gateway 2 4845
Protoss_Zealot 8 11783
Protoss_Forge 1 8402
Protoss_Photon_Cannon 7 15717
Protoss_Nexus 1 11913
Protoss_Assimilator 2 15226
Protoss_Cybernetics_Core 1 13409
Protoss_Citadel_of_Adun 1 15930
Protoss_Dragoon 1 15805
15930
