Protoss_Gateway 2 10433
Protoss_Assimilator 1 4608
Protoss_Zealot 10 15346
Protoss_Forge 2 13877
Protoss_Cybernetics_Core 1 8642
Protoss_Citadel_of_Adun 1 10299
Protoss_Templar_Archives 1 13070
Protoss_Ground_Weapons_1 1 12426
Protoss_High_Templar 2 14319
Leg_Enhancements 1 13340
Protoss_Photon_Cannon 1 15371
Protoss_Archon 1 14825
15371
