Protoss_Gateway 2 13932
Protoss_Zealot 6 9891
Protoss_Forge 1 7300
Protoss_Photon_Cannon 4 10850
Protoss_Nexus 1 14481
Protoss_Assimilator 2 14515
Protoss_Cybernetics_Core 1 15778
15778
