Protoss_Nexus 1 7224
Protoss_Forge 1 6020
Protoss_Photon_Cannon 7 11988
Protoss_Assimilator 1 9797
Protoss_Gateway 4 15113
Protoss_Zealot 2 12134
Protoss_Cybernetics_Core 1 13411
Protoss_Dragoon 2 14641
15113
