Protoss_Gateway 2 14086
Protoss_Zealot 5 12566
Protoss_Nexus 1 9002
Protoss_Assimilator 1 8793
Protoss_Cybernetics_Core 1 9511
Protoss_Dragoon 2 13771
Protoss_Forge 1 10777
Protoss_Robotics_Facility 1 13163
Protoss_Photon_Cannon 2 14251
Protoss_Shuttle 1 14601
Protoss_Robotics_Support_Bay 1 14109
Protoss_Reaver 1 16159
16159
