Protoss_Forge 1 4832
Protoss_Photon_Cannon 5 15657
Protoss_Nexus 1 9341
Protoss_Gateway 2 12763
Protoss_Assimilator 2 10312
Protoss_Cybernetics_Core 1 9946
Protoss_Zealot 3 12081
Protoss_Dragoon 1 11147
Protoss_Stargate 1 11772
Protoss_Citadel_of_Adun 1 11958
Protoss_Corsair 3 15070
Protoss_Templar_Archives 1 13508
Protoss_Dark_Templar 2 14735
15657
