Protoss_Gateway 2 5083
Protoss_Zealot 9 15441
Protoss_Assimilator 1 6778
Protoss_Cybernetics_Core 1 8933
Protoss_Citadel_of_Adun 1 10449
Protoss_Dragoon 1 10390
Protoss_Templar_Archives 1 11998
Protoss_Forge 1 13243
Protoss_High_Templar 2 15556
Protoss_Photon_Cannon 1 14505
Leg_Enhancements 1 13640
15556
