Protoss_Forge 1 4050
Protoss_Nexus 1 7806
Protoss_Gateway 4 15168
Protoss_Photon_Cannon 3 14824
Protoss_Assimilator 2 11481
Protoss_Cybernetics_Core 1 9719
Protoss_Zealot 9 15166
Protoss_Stargate 1 11863
Protoss_Citadel_of_Adun 1 12345
Protoss_Corsair 1 12801
Protoss_Templar_Archives 1 15207
15207
