Protoss_Gateway 2 5254
Protoss_Zealot 13 14137
Protoss_Assimilator 1 7659
Protoss_Cybernetics_Core 1 8502
Protoss_Citadel_of_Adun 1 10321
Protoss_Dragoon 2 10749
Protoss_Forge 1 13710
Leg_Enhancements 1 13582
Protoss_Photon_Cannon 1 15091
Protoss_Templar_Archives 1 15528
15528
