Protoss_Forge 1 3810
Protoss_Photon_Cannon 3 12538
Protoss_Nexus 1 8943
Protoss_Gateway 3 15532
Protoss_Assimilator 2 11107
Protoss_Cybernetics_Core 1 9410
Protoss_Zealot 8 15368
Protoss_Stargate 1 11655
Protoss_Citadel_of_Adun 1 12075
Protoss_Corsair 1 12634
Protoss_Templar_Archives 1 14846
15532
