Protoss_Forge 1 3820
Protoss_Photon_Cannon 5 12332
Protoss_Nexus 1 9476
Protoss_Gateway 1 8745
Protoss_Assimilator 1 8657
Protoss_Cybernetics_Core 1 10395
Protoss_Zealot 1 10583
Protoss_Citadel_of_Adun 1 11967
Protoss_Dragoon 1 11834
12332
