Protoss_Gateway 4 13821
Protoss_Zealot 9 14358
Protoss_Assimilator 1 6204
Protoss_Cybernetics_Core 1 7869
Protoss_Forge 1 8184
Protoss_Stargate 1 9947
Protoss_Corsair 1 11132
Protoss_Photon_Cannon 3 14792
Protoss_Citadel_of_Adun 1 14101
Protoss_Ground_Weapons_1 1 14475
14792
