Protoss_Forge 1 4413
Protoss_Photon_Cannon 7 15374
Protoss_Nexus 1 9175
Protoss_Gateway 3 15425
Protoss_Assimilator 2 10536
Protoss_Zealot 3 11680
Protoss_Cybernetics_Core 1 9968
Protoss_Stargate 1 11836
Protoss_Citadel_of_Adun 1 11750
Protoss_Corsair 1 12787
Protoss_Templar_Archives 1 13492
Protoss_Dark_Templar 1 14805
15425
