Protoss_Gateway 2 5085
Protoss_Zealot 17 14925
Protoss_Assimilator 1 7245
Protoss_Cybernetics_Core 1 10687
Protoss_Stargate 1 12638
Protoss_Dragoon 1 12219
Protoss_Robotics_Facility 1 13721
Protoss_Corsair 1 13758
14925
