Protoss_Gateway 2 5379
Protoss_Zealot 8 13106
Protoss_Assimilator 1 6845
Protoss_Cybernetics_Core 1 8139
Protoss_Stargate 1 10064
Protoss_Citadel_of_Adun 1 10729
Protoss_Corsair 1 11004
Protoss_Forge 1 11423
Protoss_Photon_Cannon 2 13588
Protoss_Templar_Archives 1 13229
Protoss_Nexus 1 16467
16467
