Protoss_Gateway 2 5003
Protoss_Zealot 9 12039
Protoss_Assimilator 1 7532
Protoss_Cybernetics_Core 1 9569
Protoss_Dragoon 2 10792
Protoss_Citadel_of_Adun 1 11155
Protoss_Templar_Archives 1 13199
Protoss_High_Templar 2 14861
Leg_Enhancements 1 14131
14861
