Protoss_Forge 1 4580
Protoss_Nexus 1 8577
Protoss_Photon_Cannon 6 14524
Protoss_Gateway 4 15102
Protoss_Zealot 3 12456
Protoss_Assimilator 2 12872
Protoss_Cybernetics_Core 1 14010
Protoss_Dragoon 3 15344
15344
