Protoss_Gateway 1 4192
Protoss_Forge 1 4973
Protoss_Zealot 4 11527
Protoss_Photon_Cannon 4 15174
Protoss_Nexus 1 11826
Protoss_Assimilator 1 10100
Protoss_Cybernetics_Core 1 11597
Protoss_Dragoon 2 14378
Protoss_Stargate 1 14110
Protoss_Citadel_of_Adun 1 15276
Protoss_Corsair 1 15075
15276
