Protoss_Gateway 2 5260
Protoss_Zealot 11 14761
Protoss_Assimilator 1 8263
Protoss_Cybernetics_Core 1 9658
Protoss_Forge 1 10782
Protoss_Photon_Cannon 2 15670
Protoss_Dragoon 1 13471
15670
