Protoss_Gateway 2 5376
Protoss_Zealot 9 15017
Protoss_Assimilator 1 6276
Protoss_Cybernetics_Core 1 8421
Protoss_Stargate 1 10467
Protoss_Dragoon 1 10412
Protoss_Citadel_of_Adun 1 11436
Protoss_Corsair 1 11688
Protoss_Forge 1 12018
Protoss_Photon_Cannon 1 15281
15281
