Protoss_Forge 1 4037
Protoss_Nexus 1 8196
Protoss_Photon_Cannon 10 15044
Protoss_Gateway 3 13429
Protoss_Assimilator 2 10837
Protoss_Cybernetics_Core 1 10199
Protoss_Zealot 2 11205
Protoss_Citadel_of_Adun 1 12157
Protoss_Templar_Archives 1 13725
Protoss_High_Templar 2 14956
15044
