Protoss_Gateway 1 3950
Protoss_Zealot 9 12990
Protoss_Assimilator 1 6371
Protoss_Cybernetics_Core 1 8619
Protoss_Stargate 1 10649
Protoss_Citadel_of_Adun 1 11489
Protoss_Corsair 1 11600
Protoss_Templar_Archives 1 13170
Protoss_Dark_Templar 2 15493
Protoss_Nexus 1 16515
Protoss_Forge 1 15039
Leg_Enhancements 1 14438
16515
