Protoss_Gateway 2 12146
Protoss_Zealot 9 15084
Protoss_Assimilator 1 5961
Protoss_Cybernetics_Core 1 7224
Protoss_Dragoon 1 8454
Protoss_Stargate 1 9435
Protoss_Forge 1 9216
Protoss_Corsair 1 10384
Protoss_Citadel_of_Adun 1 11952
Protoss_Photon_Cannon 1 13904
15084
