Protoss_Forge 1 4024
Protoss_Nexus 1 8108
Protoss_Photon_Cannon 3 15818
Protoss_Gateway 3 12996
Protoss_Assimilator 2 13466
Protoss_Zealot 6 15573
Protoss_Cybernetics_Core 1 10897
Protoss_Stargate 1 13023
Protoss_Dragoon 1 12878
Protoss_Citadel_of_Adun 1 14748
15818
