Protoss_Gateway 2 4864
Protoss_Zealot 13 12214
Protoss_Assimilator 1 8563
Protoss_Cybernetics_Core 1 11430
Protoss_Citadel_of_Adun 1 12885
Protoss_Dragoon 1 12710
Protoss_Forge 1 13090
Protoss_Templar_Archives 1 14471
Protoss_Dark_Templar 1 15695
15695
