Protoss_Gateway 2 10221
Protoss_Forge 1 5470
Protoss_Zealot 11 15485
Protoss_Photon_Cannon 3 11249
Protoss_Nexus 1 10815
Protoss_Assimilator 2 15560
Protoss_Cybernetics_Core 1 13960
15560
