Protoss_Gateway 2 5325
Protoss_Zealot 9 13210
Protoss_Assimilator 1 6276
Protoss_Cybernetics_Core 1 8291
Protoss_Stargate 1 10248
Protoss_Citadel_of_Adun 1 11108
Protoss_Dragoon 1 11553
Protoss_Forge 1 13638
Protoss_Nexus 1 16361
16361
