Protoss_Gateway 2 5472
Protoss_Zealot 13 15274
Protoss_Assimilator 1 7387
Protoss_Cybernetics_Core 1 9637
Protoss_Citadel_of_Adun 1 11096
Protoss_Templar_Archives 1 13164
Protoss_High_Templar 2 14398
Protoss_Forge 1 14291
Protoss_Nexus 1 16843
Leg_Enhancements 1 14027
16843
