Protoss_Gateway 3 13177
Protoss_Forge 1 4878
Protoss_Zealot 9 15141
Protoss_Photon_Cannon 6 12069
Protoss_Nexus 1 11642
Protoss_Assimilator 1 12109
Protoss_Cybernetics_Core 1 15106
15141
