Protoss_Gateway 2 4989
Protoss_Zealot 11 11834
Protoss_Assimilator 1 8464
Protoss_Cybernetics_Core 1 9605
Protoss_Stargate 1 12076
Protoss_Dragoon 1 11875
Protoss_Robotics_Facility 1 13747
Protoss_Corsair 1 13290
Protoss_Forge 1 14146
Protoss_Robotics_Support_Bay 1 14495
Protoss_Shuttle 1 15216
Protoss_Photon_Cannon 1 15566
15566
