Protoss_Forge 1 4027
Protoss_Nexus 1 8095
Protoss_Gateway 4 12263
Protoss_Photon_Cannon 2 13803
Protoss_Assimilator 1 7769
Protoss_Zealot 5 14063
Protoss_Cybernetics_Core 1 9184
Protoss_Dragoon 8 15194
Singularity_Charge 1 13494
Protoss_Citadel_of_Adun 1 15011
Protoss_Ground_Weapons_1 1 14598
15194
