Protoss_Gateway 3 15245
Protoss_Assimilator 1 4890
Protoss_Zealot 6 14995
Protoss_Forge 1 6561
Protoss_Cybernetics_Core 1 8768
Protoss_Stargate 1 10585
Protoss_Citadel_of_Adun 1 10550
Protoss_Templar_Archives 1 12014
Protoss_Corsair 1 11585
Protoss_High_Templar 2 15434
Protoss_Dark_Templar 1 13368
Protoss_Ground_Weapons_1 1 12470
Protoss_Photon_Cannon 3 15712
15712
