Protoss_Gateway 2 14669
Protoss_Assimilator 1 4571
Protoss_Cybernetics_Core 1 6178
Protoss_Zealot 2 9573
Protoss_Stargate 1 8050
Protoss_Dragoon 3 12614
Protoss_Robotics_Facility 1 10412
Protoss_Corsair 1 10341
14669
