Protoss_Gateway 1 4256
Protoss_Assimilator 1 4527
Protoss_Zealot 5 14036
Protoss_Cybernetics_Core 1 8450
Protoss_Forge 1 9061
Protoss_Dragoon 1 9768
Protoss_Citadel_of_Adun 1 10324
Protoss_Photon_Cannon 2 13130
Protoss_Templar_Archives 1 12252
Protoss_Nexus 1 15066
Protoss_High_Templar 2 15756
15756
