Protoss_Gateway 1 4419
Protoss_Assimilator 1 4352
Protoss_Cybernetics_Core 1 6015
Protoss_Forge 1 6588
Protoss_Stargate 1 8330
Protoss_Photon_Cannon 3 11729
Protoss_Corsair 2 11292
Protoss_Zealot 3 14951
14951
