Protoss_Gateway 2 10632
Protoss_Assimilator 1 4572
Protoss_Zealot 5 10092
Protoss_Cybernetics_Core 1 7858
Protoss_Citadel_of_Adun 1 9517
Protoss_Forge 1 12232
Leg_Enhancements 1 13267
Protoss_Nexus 1 16493
16493
