Protoss_Forge 1 4141
Protoss_Photon_Cannon 4 15569
Protoss_Nexus 1 8860
Protoss_Gateway 3 15646
Protoss_Assimilator 2 11636
Protoss_Zealot 4 14587
Protoss_Cybernetics_Core 1 10788
Protoss_Stargate 1 13212
Protoss_Corsair 2 15424
Protoss_Citadel_of_Adun 1 15225
15646
