Protoss_Gateway 2 9314
Protoss_Assimilator 1 4851
Protoss_Zealot 5 15525
Protoss_Cybernetics_Core 1 7346
Protoss_Citadel_of_Adun 1 9219
Protoss_Templar_Archives 1 10689
Protoss_Forge 1 10652
Protoss_Dark_Templar 2 11941
Protoss_Nexus 1 15034
Protoss_High_Templar 2 13478
Protoss_Photon_Cannon 2 14435
Protoss_Archon 1 14002
15525
