Protoss_Gateway 2 4852
Protoss_Zealot 9 13400
Protoss_Assimilator 1 8051
Protoss_Cybernetics_Core 1 9053
Protoss_Citadel_of_Adun 1 10831
Protoss_Dragoon 1 10829
Protoss_Forge 1 11042
Protoss_Photon_Cannon 2 15054
Protoss_Templar_Archives 1 13489
Protoss_Dark_Templar 1 14949
Protoss_High_Templar 1 14956
Leg_Enhancements 1 13772
15054
