Protoss_Forge 1 4280
Protoss_Nexus 1 7852
Protoss_Photon_Cannon 10 15771
Protoss_Gateway 1 7969
Protoss_Assimilator 2 14434
Protoss_Zealot 4 12434
Protoss_Cybernetics_Core 1 10236
Protoss_Robotics_Facility 1 13107
Protoss_Citadel_of_Adun 1 13410
Protoss_Templar_Archives 1 15146
Protoss_Robotics_Support_Bay 1 14884
Protoss_Stargate 1 16109
16109
