Protoss_Gateway 2 5011
Protoss_Assimilator 1 5499
Protoss_Zealot 9 14512
Protoss_Cybernetics_Core 1 7171
Protoss_Stargate 1 9048
Protoss_Dragoon 1 9183
Protoss_Citadel_of_Adun 1 9760
Protoss_Corsair 1 10019
Leg_Enhancements 1 13699
14512
