Protoss_Gateway 2 15509
Protoss_Assimilator 1 4652
Protoss_Zealot 9 15188
Protoss_Cybernetics_Core 1 6870
Protoss_Dragoon 1 9051
Protoss_Robotics_Facility 1 10085
Protoss_Robotics_Support_Bay 1 10804
Protoss_Shuttle 1 11521
Protoss_Reaver 1 13142
Protoss_Forge 1 13483
Protoss_Citadel_of_Adun 1 15113
Protoss_Photon_Cannon 1 15761
Gravitic_Drive 1 14570
15761
