Protoss_Gateway 2 5085
Protoss_Zealot 12 13239
Protoss_Assimilator 1 9832
Protoss_Cybernetics_Core 1 11458
Protoss_Stargate 1 13253
Protoss_Dragoon 1 13119
Protoss_Citadel_of_Adun 1 14320
Protoss_Corsair 2 15086
Protoss_Forge 1 15374
15374
