Protoss_Gateway 4 12564
Protoss_Zealot 13 15412
Protoss_Forge 1 6583
Protoss_Photon_Cannon 3 15530
Protoss_Nexus 1 11594
Protoss_Assimilator 2 14906
Protoss_Cybernetics_Core 1 11256
Protoss_Citadel_of_Adun 1 12770
15530
