Protoss_Gateway 2 9181
Protoss_Assimilator 1 4783
Protoss_Cybernetics_Core 1 6153
Protoss_Zealot 11 13530
Protoss_Citadel_of_Adun 1 7858
Protoss_Templar_Archives 1 12634
Leg_Enhancements 1 11804
Protoss_Dark_Templar 2 14766
Protoss_Nexus 1 17465
17465
