Protoss_Gateway 3 11326
Protoss_Zealot 10 12668
Protoss_Assimilator 1 8552
Protoss_Cybernetics_Core 1 9577
Protoss_Nexus 1 11984
Protoss_Forge 1 12100
Protoss_Photon_Cannon 1 13421
Protoss_Citadel_of_Adun 1 14077
Protoss_Templar_Archives 1 15585
Protoss_Robotics_Facility 1 16339
16339
