Protoss_Gateway 2 11626
Protoss_Assimilator 1 4867
Protoss_Cybernetics_Core 1 6071
Protoss_Zealot 8 15375
Protoss_Stargate 1 8030
Protoss_Forge 1 7827
Protoss_Dragoon 1 8590
Protoss_Photon_Cannon 1 9134
Protoss_Corsair 1 9317
Protoss_Citadel_of_Adun 1 10889
Leg_Enhancements 1 14277
15375
