Protoss_Forge 1 4507
Protoss_Photon_Cannon 4 8807
Protoss_Nexus 1 10098
Protoss_Gateway 1 9513
Protoss_Assimilator 2 13183
Protoss_Zealot 5 14636
Protoss_Cybernetics_Core 1 11636
Protoss_Citadel_of_Adun 1 13294
Protoss_Robotics_Facility 1 14969
Protoss_Templar_Archives 1 15576
15576
