Protoss_Gateway 2 5150
Protoss_Zealot 10 15371
Protoss_Assimilator 1 6872
Protoss_Cybernetics_Core 1 9454
Protoss_Citadel_of_Adun 1 10987
Protoss_Dragoon 1 10822
Protoss_Templar_Archives 1 13163
Protoss_High_Templar 2 14510
Protoss_Forge 1 14424
Leg_Enhancements 1 13940
Protoss_Archon 1 14973
Protoss_Photon_Cannon 1 15734
15734
