Protoss_Gateway 2 9451
Protoss_Assimilator 1 4450
Protoss_Zealot 8 14439
Protoss_Cybernetics_Core 1 6958
Protoss_Dragoon 1 8166
Protoss_Citadel_of_Adun 1 9046
Protoss_Templar_Archives 1 10918
Protoss_High_Templar 4 13566
Protoss_Forge 1 12784
Protoss_Archon 2 13995
Leg_Enhancements 1 12931
Protoss_Photon_Cannon 1 14792
Protoss_Nexus 1 17357
17357
