Protoss_Gateway 2 10084
Protoss_Assimilator 1 4441
Protoss_Zealot 9 13609
Protoss_Cybernetics_Core 1 6967
Protoss_Dragoon 1 8312
Protoss_Citadel_of_Adun 1 9055
Protoss_Templar_Archives 1 11557
Protoss_High_Templar 3 14758
Protoss_Forge 1 14079
14758
