Protoss_Forge 1 4341
Protoss_Nexus 1 7878
Protoss_Gateway 3 12204
Protoss_Photon_Cannon 6 15549
Protoss_Assimilator 2 14221
Protoss_Zealot 10 14868
Protoss_Cybernetics_Core 1 10875
Protoss_Citadel_of_Adun 1 12532
Protoss_Robotics_Facility 1 15008
15549
