Protoss_Gateway 2 10924
Protoss_Assimilator 1 4732
Protoss_Zealot 6 11768
Protoss_Cybernetics_Core 1 7409
Protoss_Dragoon 1 9003
Protoss_Citadel_of_Adun 1 10300
Protoss_Templar_Archives 1 11853
Protoss_Forge 1 12459
Protoss_High_Templar 4 14839
Protoss_Nexus 1 15966
Protoss_Archon 1 13698
Protoss_Photon_Cannon 3 15601
Leg_Enhancements 1 14065
15966
