Protoss_Gateway 2 5099
Protoss_Zealot 14 14768
Protoss_Assimilator 1 9732
Protoss_Forge 1 10973
Protoss_Nexus 1 14847
Protoss_Cybernetics_Core 1 14216
Protoss_Photon_Cannon 1 14491
14847
