Protoss_Gateway 2 5496
Protoss_Zealot 8 9620
Protoss_Forge 1 6523
Protoss_Photon_Cannon 3 13093
Protoss_Assimilator 1 9010
Protoss_Cybernetics_Core 1 10747
Protoss_Stargate 2 13513
Protoss_Corsair 2 14967
14967
