Protoss_Forge 1 3936
Protoss_Nexus 1 7917
Protoss_Photon_Cannon 2 7927
Protoss_Gateway 5 13575
Protoss_Assimilator 2 14745
Protoss_Zealot 12 15580
Protoss_Cybernetics_Core 1 10529
Protoss_Dragoon 1 12088
Protoss_Citadel_of_Adun 1 12431
Protoss_Templar_Archives 1 15867
15867
