Protoss_Forge 1 4472
Protoss_Nexus 1 7925
Protoss_Photon_Cannon 7 13671
Protoss_Gateway 1 8004
Protoss_Assimilator 2 13709
Protoss_Cybernetics_Core 1 9552
Protoss_Zealot 4 15141
Protoss_Stargate 1 11340
Protoss_Corsair 3 14050
Protoss_Citadel_of_Adun 1 13558
Protoss_Templar_Archives 1 15592
15592
