Protoss_Gateway 3 12535
Protoss_Zealot 13 15067
Protoss_Assimilator 1 7815
Protoss_Cybernetics_Core 1 8957
Protoss_Nexus 1 12576
Protoss_Citadel_of_Adun 1 11872
Protoss_Forge 1 14900
15067
