Protoss_Forge 1 3912
Protoss_Nexus 1 8146
Protoss_Gateway 3 12694
Protoss_Photon_Cannon 2 15704
Protoss_Assimilator 2 12623
Protoss_Cybernetics_Core 1 9169
Protoss_Zealot 9 14748
Protoss_Citadel_of_Adun 1 11082
Protoss_Dragoon 1 11117
Protoss_Templar_Archives 1 14958
Protoss_Ground_Weapons_1 1 14627
15704
