Protoss_Forge 1 4072
Protoss_Photon_Cannon 5 14369
Protoss_Gateway 1 7177
Protoss_Nexus 1 10154
Protoss_Assimilator 2 15324
Protoss_Zealot 4 15434
Protoss_Cybernetics_Core 1 10676
Protoss_Stargate 1 12646
Protoss_Dragoon 1 13039
Protoss_Corsair 1 13605
Protoss_Citadel_of_Adun 1 15814
15814
