Protoss_Forge 1 4053
Protoss_Nexus 1 7698
Protoss_Gateway 5 13397
Protoss_Photon_Cannon 2 15215
Protoss_Assimilator 2 13739
Protoss_Zealot 13 14563
Protoss_Cybernetics_Core 1 9529
Protoss_Citadel_of_Adun 1 11014
Protoss_Dragoon 1 10961
Protoss_Templar_Archives 1 14306
Leg_Enhancements 1 13955
Protoss_Ground_Weapons_1 1 14365
Protoss_High_Templar 1 15819
15819
