Protoss_Gateway 1 4085
Protoss_Assimilator 1 4470
Protoss_Zealot 4 11834
Protoss_Cybernetics_Core 1 7037
Protoss_Dragoon 1 8253
Protoss_Stargate 1 9258
Protoss_Forge 1 9667
Protoss_Corsair 1 10290
Protoss_Photon_Cannon 3 15464
Protoss_Citadel_of_Adun 1 11611
Protoss_Robotics_Facility 1 13582
Protoss_Templar_Archives 1 13631
Protoss_Nexus 1 15542
Protoss_Robotics_Support_Bay 1 14419
Protoss_Dark_Templar 1 15088
15542
