Protoss_Gateway 3 15942
Protoss_Assimilator 1 4493
Protoss_Zealot 4 10864
Protoss_Cybernetics_Core 1 7047
Protoss_Stargate 1 8950
Protoss_Citadel_of_Adun 1 9514
Protoss_Dragoon 1 9511
Protoss_Corsair 1 9977
Protoss_Templar_Archives 1 11086
Protoss_Forge 1 11306
Protoss_Photon_Cannon 3 15636
Protoss_Dark_Templar 1 12920
Protoss_High_Templar 2 15194
15942
