Protoss_Gateway 1 4400
Protoss_Assimilator 1 4644
Protoss_Zealot 7 14680
Protoss_Cybernetics_Core 1 7250
Protoss_Stargate 1 9107
Protoss_Dragoon 1 9158
Protoss_Corsair 4 14285
Protoss_Nexus 1 14258
Protoss_Forge 2 13542
Protoss_Citadel_of_Adun 1 14282
Protoss_Templar_Archives 1 15914
15914
