Protoss_Gateway 2 4985
Protoss_Zealot 9 10510
Protoss_Shield_Battery 1 5382
Protoss_Assimilator 1 11459
Protoss_Forge 1 11932
Protoss_Cybernetics_Core 1 13638
Protoss_Photon_Cannon 2 15797
Protoss_Citadel_of_Adun 1 15175
15797
