Protoss_Gateway 3 15418
Protoss_Zealot 14 14871
Protoss_Assimilator 1 6646
Protoss_Cybernetics_Core 1 9263
Protoss_Citadel_of_Adun 1 10853
Leg_Enhancements 1 13816
Protoss_Templar_Archives 1 15983
15983
