Protoss_Gateway 2 4858
Protoss_Zealot 11 10722
Protoss_Forge 1 10037
Protoss_Photon_Cannon 3 12873
Protoss_Assimilator 1 12067
Protoss_Cybernetics_Core 1 13681
Protoss_Stargate 1 15463
15463
