Protoss_Gateway 2 13430
Protoss_Assimilator 1 4575
Protoss_Zealot 3 9383
Protoss_Cybernetics_Core 1 7068
Protoss_Dragoon 1 8268
Protoss_Robotics_Facility 1 10151
Protoss_Citadel_of_Adun 1 10783
Protoss_Shuttle 1 11565
Protoss_Robotics_Support_Bay 1 10933
Protoss_Reaver 2 14675
Protoss_Templar_Archives 1 13609
Protoss_Forge 1 14339
Protoss_High_Templar 1 14831
Protoss_Photon_Cannon 2 15625
15625
