Protoss_Gateway 3 9263
Protoss_Zealot 17 15390
Protoss_Nexus 1 8415
Protoss_Assimilator 1 10795
Protoss_Cybernetics_Core 1 12993
Protoss_Citadel_of_Adun 1 14775
Protoss_Forge 1 14412
Protoss_Photon_Cannon 1 15721
15721
