Protoss_Gateway 2 4975
Protoss_Zealot 12 13773
Protoss_Assimilator 1 9683
Protoss_Cybernetics_Core 1 10972
Protoss_Stargate 1 12729
Protoss_Dragoon 2 13961
Protoss_Corsair 1 13824
Protoss_Citadel_of_Adun 1 15061
Protoss_Forge 1 15096
15096
