Protoss_Gateway 2 5162
Protoss_Zealot 8 14101
Protoss_Assimilator 1 7157
Protoss_Cybernetics_Core 1 8604
Protoss_Stargate 1 10572
Protoss_Corsair 1 11522
Protoss_Nexus 1 17201
17201
