Protoss_Gateway 2 5390
Protoss_Zealot 9 13253
Protoss_Assimilator 1 7009
Protoss_Cybernetics_Core 1 8304
Protoss_Forge 1 8360
Protoss_Citadel_of_Adun 1 10763
Protoss_Templar_Archives 1 12870
Protoss_Photon_Cannon 2 14491
Protoss_High_Templar 2 14817
Leg_Enhancements 1 13743
Protoss_Ground_Weapons_1 1 14277
Protoss_Nexus 1 17466
17466
