Protoss_Nexus 1 6937
Protoss_Forge 1 5641
Protoss_Photon_Cannon 6 15822
Protoss_Gateway 2 9782
Protoss_Assimilator 2 10207
Protoss_Zealot 9 14973
Protoss_Cybernetics_Core 1 11354
Protoss_Stargate 1 13156
Protoss_Citadel_of_Adun 1 13164
Protoss_Corsair 1 14102
Protoss_Templar_Archives 1 14619
15822
