Protoss_Gateway 2 5515
Protoss_Zealot 10 12675
Protoss_Assimilator 1 6803
Protoss_Cybernetics_Core 1 8289
Protoss_Forge 1 8715
Protoss_Dragoon 1 9541
Protoss_Citadel_of_Adun 1 10627
Protoss_Templar_Archives 1 12362
Protoss_Photon_Cannon 2 14798
Protoss_Dark_Templar 1 14700
Protoss_Nexus 1 17039
Protoss_High_Templar 2 15800
17039
