Protoss_Gateway 2 11055
Protoss_Assimilator 1 4666
Protoss_Zealot 8 14161
Protoss_Cybernetics_Core 1 8361
Protoss_Stargate 1 10361
Protoss_Dragoon 1 10185
Protoss_Corsair 1 11307
Protoss_Citadel_of_Adun 1 12045
Protoss_Templar_Archives 1 13874
Protoss_Forge 1 13615
Protoss_Dark_Templar 2 15673
15673
