Protoss_Gateway 2 5175
Protoss_Zealot 13 14958
Protoss_Assimilator 1 6554
Protoss_Cybernetics_Core 1 9349
Protoss_Citadel_of_Adun 1 10912
Protoss_Dragoon 1 11802
Protoss_Templar_Archives 1 12438
Protoss_Forge 1 12258
Protoss_High_Templar 2 14059
Protoss_Photon_Cannon 1 15373
15373
