Protoss_Forge 1 4000
Protoss_Photon_Cannon 8 15784
Protoss_Nexus 1 10866
Protoss_Gateway 4 15482
Protoss_Assimilator 2 14366
Protoss_Zealot 5 15204
Protoss_Cybernetics_Core 1 13423
Protoss_Citadel_of_Adun 1 14882
15784
