Protoss_Forge 1 4741
Protoss_Photon_Cannon 10 14930
Protoss_Nexus 1 8856
Protoss_Gateway 3 13316
Protoss_Assimilator 2 11140
Protoss_Cybernetics_Core 1 9972
Protoss_Citadel_of_Adun 1 11436
Protoss_Dragoon 1 11685
Protoss_Templar_Archives 1 12914
Protoss_High_Templar 3 15775
Protoss_Dark_Templar 1 15197
15775
