Protoss_Gateway 2 9648
Protoss_Assimilator 1 4707
Protoss_Zealot 9 13744
Protoss_Cybernetics_Core 1 7328
Protoss_Dragoon 1 8539
Protoss_Forge 1 8628
Protoss_Citadel_of_Adun 1 10956
Protoss_Stargate 2 13935
Protoss_Photon_Cannon 1 14685
Protoss_Corsair 3 15573
Leg_Enhancements 1 13904
15573
