Protoss_Gateway 3 11238
Protoss_Assimilator 1 4496
Protoss_Zealot 11 14497
Protoss_Cybernetics_Core 1 7141
Protoss_Stargate 1 9706
Protoss_Citadel_of_Adun 1 10029
Protoss_Corsair 1 11658
Protoss_Nexus 1 15836
Leg_Enhancements 1 13048
Protoss_Templar_Archives 1 14655
15836
