Protoss_Gateway 2 10054
Protoss_Assimilator 1 4783
Protoss_Zealot 6 11446
Protoss_Cybernetics_Core 1 7060
Protoss_Dragoon 1 8444
Protoss_Citadel_of_Adun 1 9226
Protoss_Templar_Archives 1 12389
Protoss_Forge 1 12899
Leg_Enhancements 1 12184
Protoss_High_Templar 3 14868
Protoss_Nexus 1 15915
Protoss_Archon 1 14342
Protoss_Dark_Templar 1 15102
15915
