Protoss_Forge 1 5058
Protoss_Nexus 1 7841
Protoss_Photon_Cannon 7 15335
Protoss_Gateway 5 15980
Protoss_Assimilator 2 10682
Protoss_Zealot 2 9447
Protoss_Cybernetics_Core 1 9137
Protoss_Citadel_of_Adun 1 10840
Protoss_Templar_Archives 1 12422
Protoss_Dragoon 1 13099
Protoss_High_Templar 2 13643
Protoss_Dark_Templar 1 14199
Protoss_Robotics_Facility 1 15604
15980
