Protoss_Nexus 1 7398
Protoss_Forge 1 6728
Protoss_Photon_Cannon 8 14615
Protoss_Assimilator 2 11029
Protoss_Gateway 3 14209
Protoss_Cybernetics_Core 1 11448
Protoss_Stargate 2 13390
Protoss_Citadel_of_Adun 1 13398
Protoss_Corsair 3 15288
Protoss_Templar_Archives 1 15160
15288
