Protoss_Forge 1 5132
Protoss_Nexus 1 7947
Protoss_Photon_Cannon 3 14322
Protoss_Gateway 1 7668
Protoss_Assimilator 2 11472
Protoss_Cybernetics_Core 1 9595
Protoss_Zealot 2 11768
Protoss_Dragoon 1 10814
Protoss_Stargate 1 11535
Protoss_Corsair 4 15258
Protoss_Robotics_Facility 1 13694
Protoss_Robotics_Support_Bay 3 14681
Protoss_Shuttle 1 15421
15421
