Protoss_Nexus 1 7190
Protoss_Forge 1 5748
Protoss_Photon_Cannon 5 15238
Protoss_Gateway 3 11868
Protoss_Assimilator 1 7843
Protoss_Zealot 12 15052
Protoss_Cybernetics_Core 1 10568
Protoss_Citadel_of_Adun 1 12187
Protoss_Stargate 2 14762
Protoss_Corsair 1 15201
Protoss_Robotics_Facility 1 16454
16454
