Protoss_Forge 1 4150
Protoss_Nexus 1 7931
Protoss_Photon_Cannon 2 7323
Protoss_Gateway 5 14048
Protoss_Assimilator 2 14622
Protoss_Cybernetics_Core 1 10416
Protoss_Zealot 11 15485
Protoss_Citadel_of_Adun 1 12141
Protoss_Templar_Archives 1 15348
15485
