Protoss_Gateway 1 4455
Protoss_Assimilator 1 4359
Protoss_Zealot 6 12377
Protoss_Cybernetics_Core 1 8493
Protoss_Dragoon 1 9753
Protoss_Citadel_of_Adun 1 10340
Protoss_Forge 1 10779
Protoss_Templar_Archives 1 11909
Protoss_Dark_Templar 1 13497
Protoss_Photon_Cannon 1 14191
Leg_Enhancements 1 13275
Protoss_High_Templar 2 15698
Protoss_Nexus 1 16859
16859
