Protoss_Gateway 1 4185
Protoss_Assimilator 1 4455
Protoss_Zealot 3 9119
Protoss_Cybernetics_Core 1 6709
Protoss_Dragoon 1 7953
Protoss_Stargate 1 9190
Protoss_Citadel_of_Adun 1 9544
Protoss_Corsair 1 10173
Protoss_Templar_Archives 1 11247
Protoss_Forge 1 11017
Protoss_Photon_Cannon 3 14815
Protoss_Dark_Templar 1 12629
Protoss_Nexus 1 15498
Protoss_High_Templar 2 15249
Psionic_Storm 1 14226
15498
