Protoss_Nexus 1 7003
Protoss_Gateway 4 13302
Protoss_Assimilator 2 13716
Protoss_Forge 1 7066
Protoss_Photon_Cannon 1 8417
Protoss_Zealot 10 14271
Protoss_Cybernetics_Core 1 10372
Protoss_Citadel_of_Adun 1 11942
Protoss_Dragoon 1 11927
Protoss_Templar_Archives 1 14513
Protoss_Ground_Weapons_1 1 13992
Protoss_High_Templar 2 15753
15753
