Protoss_Nexus 1 7003
Protoss_Forge 1 5973
Protoss_Photon_Cannon 3 9247
Protoss_Gateway 5 14003
Protoss_Assimilator 2 11813
Protoss_Zealot 9 15187
Protoss_Cybernetics_Core 1 10455
Protoss_Citadel_of_Adun 1 12350
15187
