Protoss_Gateway 1 4312
Protoss_Assimilator 1 5127
Protoss_Zealot 2 9595
Protoss_Cybernetics_Core 1 6950
Protoss_Dragoon 1 8158
Protoss_Stargate 1 8974
Protoss_Robotics_Facility 1 10396
Protoss_Corsair 2 13597
Protoss_Forge 1 11184
Protoss_Shuttle 1 11909
Protoss_Shield_Battery 1 11372
Protoss_Robotics_Support_Bay 1 11461
Protoss_Photon_Cannon 4 15705
Protoss_Reaver 1 13467
Protoss_Nexus 1 16077
16077
