Protoss_Gateway 2 5958
Protoss_Zealot 15 13141
Protoss_Assimilator 1 10303
Protoss_Cybernetics_Core 1 11898
Protoss_Forge 1 12111
Protoss_Citadel_of_Adun 1 13409
Protoss_Templar_Archives 1 14993
Protoss_Photon_Cannon 2 15745
Protoss_Nexus 1 17007
17007
