Protoss_Forge 1 4215
Protoss_Photon_Cannon 7 14995
Protoss_Nexus 1 8957
Protoss_Gateway 2 13771
Protoss_Assimilator 1 8181
Protoss_Zealot 5 13480
Protoss_Cybernetics_Core 1 10060
Protoss_Citadel_of_Adun 1 11604
Protoss_Dragoon 1 11597
Protoss_Templar_Archives 1 13250
Protoss_Dark_Templar 2 15271
15271
