Protoss_Forge 1 4081
Protoss_Nexus 1 7711
Protoss_Photon_Cannon 4 15790
Protoss_Gateway 5 13946
Protoss_Assimilator 2 15279
Protoss_Zealot 13 15403
Protoss_Cybernetics_Core 1 11382
Protoss_Citadel_of_Adun 1 12842
Protoss_Templar_Archives 1 15735
15790
