Protoss_Forge 1 3750
Protoss_Nexus 1 7610
Protoss_Photon_Cannon 2 7349
Protoss_Gateway 1 8424
Protoss_Assimilator 1 8221
Protoss_Cybernetics_Core 1 9917
Protoss_Zealot 1 10561
10561
