Protoss_Gateway 2 5069
Protoss_Zealot 7 12895
Protoss_Assimilator 1 6752
Protoss_Forge 1 7950
Protoss_Cybernetics_Core 1 9356
Protoss_Photon_Cannon 4 15746
Protoss_Citadel_of_Adun 1 10808
Protoss_Templar_Archives 1 13116
Protoss_High_Templar 2 14322
Protoss_Nexus 1 16536
Protoss_Ground_Weapons_1 1 13842
Leg_Enhancements 1 13898
16536
