Protoss_Forge 2 9049
Protoss_Assimilator 2 8372
Protoss_Photon_Cannon 3 14981
Protoss_Gateway 2 12533
Protoss_Zealot 2 13641
Protoss_Cybernetics_Core 1 13924
Protoss_Citadel_of_Adun 1 15511
15511
