Protoss_Gateway 1 4514
Protoss_Assimilator 2 15231
Protoss_Cybernetics_Core 1 6219
Protoss_Robotics_Facility 1 8685
Protoss_Dragoon 1 8327
Protoss_Zealot 1 9851
Protoss_Robotics_Support_Bay 1 9629
Protoss_Reaver 2 15403
Protoss_Shuttle 1 12687
Protoss_Stargate 1 14506
Protoss_Nexus 1 16152
Gravitic_Drive 1 14109
16152
