Protoss_Gateway 3 13869
Protoss_Assimilator 1 4505
Protoss_Zealot 4 9668
Protoss_Cybernetics_Core 1 7979
Protoss_Dragoon 10 15522
Protoss_Forge 1 10376
Protoss_Citadel_of_Adun 1 15077
Singularity_Charge 1 14380
15522
