Protoss_Forge 1 4220
Protoss_Photon_Cannon 5 15524
Protoss_Nexus 1 9587
Protoss_Gateway 4 15507
Protoss_Assimilator 3 13657
Protoss_Cybernetics_Core 1 10223
Protoss_Citadel_of_Adun 1 11809
Protoss_Zealot 8 14557
Protoss_Robotics_Facility 1 16415
16415
