Protoss_Gateway 2 5168
Protoss_Zealot 17 14478
Protoss_Nexus 1 11952
Protoss_Forge 1 11399
Protoss_Assimilator 1 11907
Protoss_Photon_Cannon 2 15076
Protoss_Cybernetics_Core 1 14083
Protoss_Stargate 1 16262
16262
