Protoss_Forge 2 12027
Protoss_Photon_Cannon 4 13636
Protoss_Nexus 1 8797
Protoss_Gateway 4 14816
Protoss_Assimilator 1 8436
Protoss_Cybernetics_Core 1 9854
Protoss_Zealot 10 14973
Protoss_Dragoon 1 11092
Protoss_Citadel_of_Adun 1 11480
Protoss_Templar_Archives 1 15672
Leg_Enhancements 1 14504
15672
