Protoss_Forge 1 4447
Protoss_Photon_Cannon 8 15676
Protoss_Nexus 1 9338
Protoss_Gateway 1 8917
Protoss_Assimilator 2 12298
Protoss_Zealot 6 14590
Protoss_Cybernetics_Core 1 10391
Protoss_Citadel_of_Adun 1 12507
Protoss_Templar_Archives 1 13954
Protoss_High_Templar 1 15177
Protoss_Dark_Templar 1 15335
15676
