Protoss_Forge 1 4268
Protoss_Photon_Cannon 7 14808
Protoss_Nexus 1 9791
Protoss_Gateway 1 8904
Protoss_Assimilator 2 12087
Protoss_Zealot 3 14768
Protoss_Cybernetics_Core 1 10543
Protoss_Dragoon 2 13412
Protoss_Citadel_of_Adun 1 12468
Protoss_Templar_Archives 1 15482
15482
