Protoss_Gateway 2 5070
Protoss_Zealot 10 11753
Protoss_Assimilator 1 9911
Protoss_Cybernetics_Core 1 11755
Protoss_Forge 1 12147
Protoss_Citadel_of_Adun 1 13223
Protoss_Photon_Cannon 2 14237
Protoss_Templar_Archives 1 15008
15008
