Protoss_Gateway 2 5450
Protoss_Zealot 15 14585
Protoss_Assimilator 1 10079
Protoss_Cybernetics_Core 1 11633
Protoss_Citadel_of_Adun 1 14009
Protoss_Nexus 1 15619
Protoss_Templar_Archives 1 15694
15694
