Protoss_Gateway 2 5187
Protoss_Zealot 18 13694
Protoss_Assimilator 1 9927
Protoss_Cybernetics_Core 1 11663
Protoss_Citadel_of_Adun 1 13164
Protoss_Templar_Archives 1 14919
Protoss_Forge 1 14999
14999
