Protoss_Gateway 1 4243
Protoss_Assimilator 1 4960
Protoss_Zealot 3 7839
Protoss_Cybernetics_Core 1 7177
Protoss_Citadel_of_Adun 1 8734
Protoss_Dragoon 1 8959
Protoss_Forge 1 9378
Protoss_Templar_Archives 1 10550
Protoss_Photon_Cannon 3 14998
Protoss_Dark_Templar 2 12958
Protoss_Nexus 1 15688
Protoss_High_Templar 1 15585
15688
