Protoss_Forge 1 4833
Protoss_Photon_Cannon 7 15710
Protoss_Nexus 1 9283
Protoss_Gateway 1 8464
Protoss_Assimilator 2 12124
Protoss_Cybernetics_Core 1 9953
Protoss_Zealot 6 14572
Protoss_Stargate 1 11904
Protoss_Citadel_of_Adun 1 12475
Protoss_Corsair 2 13957
Protoss_Templar_Archives 1 15734
15734
