Protoss_Forge 1 4046
Protoss_Photon_Cannon 4 14783
Protoss_Nexus 1 8320
Protoss_Gateway 3 12358
Protoss_Zealot 11 14761
Protoss_Assimilator 2 12349
Protoss_Cybernetics_Core 1 11768
Protoss_Citadel_of_Adun 1 13309
Protoss_Templar_Archives 1 14816
14816
