Protoss_Nexus 1 6609
Protoss_Forge 1 5192
Protoss_Photon_Cannon 4 12970
Protoss_Gateway 1 7389
Protoss_Assimilator 2 10698
Protoss_Zealot 5 12936
Protoss_Cybernetics_Core 1 9087
Protoss_Stargate 1 10947
Protoss_Robotics_Facility 2 15058
Protoss_Corsair 3 15424
Protoss_Robotics_Support_Bay 1 13147
Protoss_Reaver 1 15231
15424
