Protoss_Assimilator 1 3542
Protoss_Forge 1 4518
Protoss_Gateway 3 8364
Protoss_Photon_Cannon 4 14984
Protoss_Zealot 8 11525
Protoss_Ground_Weapons_1 1 10807
Protoss_Cybernetics_Core 1 12763
Protoss_Dragoon 3 14012
Protoss_Stargate 1 14988
14988
