Protoss_Forge 1 4240
Protoss_Photon_Cannon 7 15693
Protoss_Gateway 2 14847
Protoss_Zealot 6 15353
Protoss_Nexus 1 10449
Protoss_Assimilator 2 12839
Protoss_Cybernetics_Core 1 11167
Protoss_Citadel_of_Adun 1 12710
Protoss_Templar_Archives 1 14434
Protoss_High_Templar 1 15783
15783
