Protoss_Gateway 1 4236
Protoss_Assimilator 1 4628
Protoss_Cybernetics_Core 1 5948
Protoss_Zealot 3 11271
Protoss_Stargate 1 7862
Protoss_Corsair 4 14344
Protoss_Robotics_Facility 1 10473
Protoss_Forge 1 10997
Protoss_Shuttle 1 11982
Protoss_Photon_Cannon 2 14155
Protoss_Robotics_Support_Bay 1 12335
Protoss_Reaver 2 15725
Protoss_Nexus 1 17437
17437
