Protoss_Gateway 2 5301
Protoss_Zealot 10 15149
Protoss_Assimilator 1 7211
Protoss_Cybernetics_Core 1 9179
Protoss_Citadel_of_Adun 1 10635
Protoss_Templar_Archives 1 12403
Protoss_Forge 1 12766
Protoss_High_Templar 3 15399
Protoss_Nexus 1 15950
Protoss_Photon_Cannon 2 14963
Leg_Enhancements 1 13687
Protoss_Archon 1 14478
15950
