Protoss_Gateway 2 13679
Protoss_Assimilator 1 4600
Protoss_Cybernetics_Core 1 6011
Protoss_Zealot 4 11607
Protoss_Citadel_of_Adun 1 8409
Protoss_Forge 1 9068
Protoss_Dragoon 2 10514
Protoss_Templar_Archives 1 11589
Protoss_Photon_Cannon 2 14479
Protoss_Dark_Templar 1 12783
Protoss_High_Templar 2 14984
Protoss_Nexus 1 17258
17258
