Protoss_Gateway 1 4477
Protoss_Assimilator 1 4791
Protoss_Zealot 4 10268
Protoss_Cybernetics_Core 1 7896
Protoss_Stargate 1 9670
Protoss_Dragoon 1 9314
Protoss_Citadel_of_Adun 1 10530
Protoss_Corsair 1 10619
Protoss_Templar_Archives 1 12172
Protoss_Dark_Templar 1 13397
Protoss_Nexus 1 15352
Protoss_Forge 1 14515
Protoss_High_Templar 1 14824
Protoss_Photon_Cannon 1 15781
15781
