Protoss_Forge 1 4325
Protoss_Nexus 1 7642
Protoss_Photon_Cannon 5 15762
Protoss_Gateway 3 14597
Protoss_Assimilator 2 11707
Protoss_Zealot 9 14771
Protoss_Cybernetics_Core 1 9383
Protoss_Citadel_of_Adun 1 11347
Protoss_Dragoon 1 11761
Protoss_Templar_Archives 1 14152
Leg_Enhancements 1 14615
15762
