Protoss_Forge 1 5041
Protoss_Photon_Cannon 6 14002
Protoss_Nexus 1 10325
Protoss_Gateway 1 9509
Protoss_Assimilator 2 11647
Protoss_Cybernetics_Core 1 11180
Protoss_Zealot 2 12027
Protoss_Stargate 1 12947
Protoss_Robotics_Facility 1 14224
Protoss_Corsair 2 14866
Protoss_Shuttle 1 15721
Protoss_Robotics_Support_Bay 1 15272
15721
