Protoss_Gateway 2 15026
Protoss_Zealot 8 13851
Protoss_Nexus 1 9464
Protoss_Forge 1 7941
Protoss_Photon_Cannon 4 10353
Protoss_Assimilator 2 15225
Protoss_Cybernetics_Core 1 13509
Protoss_Citadel_of_Adun 1 15116
15225
