Protoss_Forge 1 4211
Protoss_Photon_Cannon 6 14161
Protoss_Nexus 1 10942
Protoss_Gateway 2 15778
Protoss_Assimilator 2 12156
Protoss_Cybernetics_Core 1 11322
Protoss_Zealot 4 14979
Protoss_Citadel_of_Adun 1 13265
Protoss_Templar_Archives 1 14721
15778
