Protoss_Gateway 1 4233
Protoss_Assimilator 1 4498
Protoss_Zealot 7 12614
Protoss_Cybernetics_Core 1 8273
Protoss_Stargate 2 10639
Protoss_Dragoon 1 9856
Protoss_Citadel_of_Adun 1 11311
Protoss_Corsair 1 11578
Protoss_Forge 1 12157
Protoss_Templar_Archives 1 12983
Protoss_Nexus 1 16069
Protoss_Dark_Templar 1 14644
Protoss_Photon_Cannon 2 15459
Protoss_High_Templar 1 15753
16069
