Protoss_Forge 1 4132
Protoss_Photon_Cannon 3 7605
Protoss_Nexus 1 8898
Protoss_Gateway 4 12482
Protoss_Assimilator 2 15560
Protoss_Zealot 13 15273
Protoss_Cybernetics_Core 1 11165
Protoss_Citadel_of_Adun 1 12914
Protoss_Templar_Archives 1 15189
15560
