Protoss_Forge 1 4766
Protoss_Photon_Cannon 2 6117
Protoss_Nexus 1 9435
Protoss_Gateway 4 14200
Protoss_Assimilator 2 14121
Protoss_Zealot 9 15371
Protoss_Cybernetics_Core 1 10224
Protoss_Citadel_of_Adun 1 11892
Protoss_Dragoon 1 11736
Protoss_Templar_Archives 1 14541
15371
