Protoss_Forge 1 3886
Protoss_Photon_Cannon 5 13506
Protoss_Nexus 2 17238
Protoss_Gateway 1 7878
Protoss_Assimilator 2 9898
Protoss_Cybernetics_Core 1 9321
Protoss_Zealot 1 9184
Protoss_Stargate 1 11096
Protoss_Robotics_Facility 1 12597
Protoss_Corsair 2 14168
Protoss_Shuttle 1 14165
Protoss_Robotics_Support_Bay 1 14638
17238
