Protoss_Forge 1 3905
Protoss_Photon_Cannon 9 14807
Protoss_Nexus 1 11828
Protoss_Assimilator 1 10834
Protoss_Gateway 2 15557
Protoss_Zealot 3 14907
Protoss_Cybernetics_Core 1 13441
Protoss_Citadel_of_Adun 1 15453
15557
