Protoss_Forge 1 4414
Protoss_Photon_Cannon 4 15142
Protoss_Nexus 1 8973
Protoss_Gateway 2 12716
Protoss_Assimilator 1 8751
Protoss_Zealot 5 14935
Protoss_Cybernetics_Core 1 10193
Protoss_Dragoon 1 11618
15142
