Protoss_Nexus 1 7098
Protoss_Forge 1 5639
Protoss_Photon_Cannon 5 15825
Protoss_Gateway 4 13046
Protoss_Assimilator 2 10546
Protoss_Cybernetics_Core 1 12456
Protoss_Zealot 7 14110
Protoss_Citadel_of_Adun 1 14089
Protoss_Templar_Archives 1 15571
15825
