Protoss_Gateway 2 5032
Protoss_Zealot 8 10908
Protoss_Assimilator 1 6561
Protoss_Forge 1 7556
Protoss_Cybernetics_Core 1 9156
Protoss_Citadel_of_Adun 1 10726
Protoss_Dragoon 1 11297
Protoss_Photon_Cannon 5 15449
Protoss_Templar_Archives 1 12880
Protoss_Nexus 1 16332
Protoss_High_Templar 2 14839
Protoss_Ground_Weapons_1 1 13619
Leg_Enhancements 1 13670
16332
