Protoss_Forge 1 4400
Protoss_Nexus 1 7514
Protoss_Photon_Cannon 8 14922
Protoss_Gateway 1 7965
Protoss_Assimilator 2 12252
Protoss_Zealot 5 13574
Protoss_Cybernetics_Core 1 10586
Protoss_Dragoon 1 11831
Protoss_Citadel_of_Adun 1 12569
Protoss_Templar_Archives 1 14175
Protoss_Dark_Templar 1 15680
15680
