Protoss_Gateway 2 11556
Protoss_Assimilator 1 4634
Protoss_Zealot 9 15569
Protoss_Cybernetics_Core 1 8626
Protoss_Dragoon 1 9834
Protoss_Citadel_of_Adun 1 10498
Protoss_Robotics_Facility 1 12409
Protoss_Templar_Archives 1 12132
Protoss_Dark_Templar 2 13573
Protoss_Shuttle 1 13987
Protoss_High_Templar 2 14707
Leg_Enhancements 1 13860
Protoss_Forge 1 15206
15569
