Protoss_Gateway 1 3965
Protoss_Assimilator 2 15210
Protoss_Zealot 3 8895
Protoss_Cybernetics_Core 1 6819
Protoss_Dragoon 1 8034
Protoss_Stargate 1 9212
Protoss_Citadel_of_Adun 1 10094
Protoss_Forge 1 9766
Protoss_Corsair 1 10239
Protoss_Photon_Cannon 4 15202
Protoss_Templar_Archives 1 11578
Protoss_Dark_Templar 1 12885
Protoss_Robotics_Facility 1 13909
Protoss_Nexus 1 15886
Protoss_Robotics_Support_Bay 1 14663
15886
