Protoss_Forge 1 4174
Protoss_Photon_Cannon 4 8426
Protoss_Nexus 1 11437
Protoss_Assimilator 1 10069
Protoss_Gateway 2 12251
Protoss_Cybernetics_Core 1 13306
Protoss_Zealot 6 15274
Protoss_Citadel_of_Adun 1 15113
15274
