Protoss_Forge 1 4091
Protoss_Nexus 1 8057
Protoss_Photon_Cannon 4 15736
Protoss_Gateway 3 12828
Protoss_Assimilator 2 13596
Protoss_Zealot 9 14944
Protoss_Cybernetics_Core 1 10149
Protoss_Citadel_of_Adun 1 11666
Protoss_Dragoon 1 12238
15736
