Protoss_Forge 1 4141
Protoss_Nexus 1 7815
Protoss_Gateway 4 11977
Protoss_Photon_Cannon 5 15707
Protoss_Assimilator 2 12444
Protoss_Zealot 11 14819
Protoss_Cybernetics_Core 1 10678
Protoss_Citadel_of_Adun 1 12189
Protoss_Templar_Archives 1 14246
15707
