Protoss_Gateway 2 15727
Protoss_Assimilator 1 4600
Protoss_Zealot 5 14695
Protoss_Cybernetics_Core 1 7836
Protoss_Dragoon 1 9051
Protoss_Robotics_Facility 1 10222
Protoss_Forge 1 10632
Protoss_Robotics_Support_Bay 1 10975
Protoss_Shuttle 1 11821
Protoss_Reaver 1 13379
Protoss_Photon_Cannon 3 15674
Protoss_Citadel_of_Adun 1 14895
15727
