Protoss_Gateway 2 10075
Protoss_Assimilator 1 4565
Protoss_Zealot 5 13556
Protoss_Cybernetics_Core 1 7068
Protoss_Stargate 1 8887
Protoss_Dragoon 1 8883
Protoss_Citadel_of_Adun 1 9416
Protoss_Robotics_Facility 1 10975
Protoss_Templar_Archives 1 11480
Protoss_Shuttle 1 12384
Protoss_Dark_Templar 2 12695
Protoss_Forge 1 12591
Protoss_Nexus 1 16552
Protoss_Photon_Cannon 2 15712
Protoss_High_Templar 1 15066
16552
