Protoss_Gateway 2 15406
Protoss_Zealot 7 14329
Protoss_Assimilator 1 5571
Protoss_Cybernetics_Core 1 7287
Protoss_Stargate 1 9193
Protoss_Dragoon 1 9532
Protoss_Forge 1 9598
Protoss_Citadel_of_Adun 1 10360
Protoss_Corsair 2 11753
Protoss_Photon_Cannon 3 14758
Protoss_Nexus 1 15249
Protoss_Templar_Archives 1 14101
Protoss_Dark_Templar 1 15497
15497
