Protoss_Forge 1 4709
Protoss_Photon_Cannon 5 13574
Protoss_Gateway 3 15252
Protoss_Nexus 1 9732
Protoss_Assimilator 2 15228
Protoss_Zealot 3 14314
Protoss_Cybernetics_Core 1 11699
Protoss_Stargate 1 13437
Protoss_Corsair 2 15405
Protoss_Citadel_of_Adun 1 15529
15529
