Protoss_Gateway 2 5133
Protoss_Zealot 8 12336
Protoss_Assimilator 1 9430
Protoss_Forge 1 9869
Protoss_Photon_Cannon 2 15101
Protoss_Cybernetics_Core 1 12365
Protoss_Dragoon 1 13754
15101
