Protoss_Forge 1 5434
Protoss_Nexus 1 8242
Protoss_Photon_Cannon 5 15310
Protoss_Gateway 4 12607
Protoss_Assimilator 2 14096
Protoss_Cybernetics_Core 1 9541
Protoss_Zealot 8 15405
Protoss_Citadel_of_Adun 1 11535
Protoss_Dragoon 1 11539
Protoss_Templar_Archives 1 14307
Protoss_High_Templar 2 15585
Leg_Enhancements 1 14482
15585
