Protoss_Forge 1 4193
Protoss_Nexus 1 7994
Protoss_Photon_Cannon 3 14976
Protoss_Gateway 3 13192
Protoss_Assimilator 2 12983
Protoss_Zealot 8 15171
Protoss_Cybernetics_Core 1 10757
Protoss_Dragoon 1 12215
Protoss_Citadel_of_Adun 1 12694
15171
