Protoss_Forge 1 4227
Protoss_Nexus 1 8131
Protoss_Photon_Cannon 3 9758
Protoss_Gateway 3 15828
Protoss_Assimilator 2 12994
Protoss_Zealot 9 15292
Protoss_Cybernetics_Core 1 11265
Protoss_Citadel_of_Adun 1 12744
Protoss_Dragoon 1 12669
Protoss_Templar_Archives 1 14838
15828
