Protoss_Gateway 2 4695
Protoss_Zealot 15 13425
Protoss_Nexus 1 13805
Protoss_Forge 1 12282
Protoss_Assimilator 1 12438
Protoss_Photon_Cannon 2 14126
Protoss_Cybernetics_Core 1 15410
15410
