Protoss_Gateway 4 13726
Protoss_Zealot 9 10053
Protoss_Nexus 1 11428
Protoss_Assimilator 3 14461
Protoss_Cybernetics_Core 1 11203
Protoss_Dragoon 6 15636
Protoss_Forge 1 14862
15636
