Protoss_Forge 1 3996
Protoss_Nexus 1 7947
Protoss_Photon_Cannon 2 7108
Protoss_Gateway 4 12936
Protoss_Assimilator 2 14508
Protoss_Zealot 7 14058
Protoss_Cybernetics_Core 1 10916
Protoss_Citadel_of_Adun 1 12380
Protoss_Dragoon 1 12161
Protoss_Templar_Archives 1 14787
14787
