Protoss_Forge 1 3831
Protoss_Photon_Cannon 6 15562
Protoss_Nexus 1 9043
Protoss_Gateway 3 12184
Protoss_Assimilator 2 14991
Protoss_Zealot 9 14025
Protoss_Cybernetics_Core 1 10019
Protoss_Citadel_of_Adun 1 11686
Protoss_Templar_Archives 1 14654
15562
