Protoss_Nexus 1 7288
Protoss_Forge 1 6131
Protoss_Photon_Cannon 2 15686
Protoss_Gateway 4 15473
Protoss_Assimilator 2 12403
Protoss_Zealot 11 15053
Protoss_Cybernetics_Core 1 9683
Protoss_Citadel_of_Adun 1 11194
Protoss_Dragoon 1 12186
Protoss_Templar_Archives 1 13104
Protoss_High_Templar 2 15464
15686
