Protoss_Gateway 2 4719
Protoss_Zealot 14 15207
Protoss_Nexus 1 11298
Protoss_Forge 1 10337
Protoss_Photon_Cannon 1 11600
Protoss_Assimilator 2 14047
Protoss_Cybernetics_Core 1 13192
Protoss_Citadel_of_Adun 1 15358
15358
