Protoss_Gateway 2 12225
Protoss_Assimilator 1 4578
Protoss_Zealot 3 6945
Protoss_Cybernetics_Core 1 8189
Protoss_Stargate 1 9896
Protoss_Citadel_of_Adun 1 9855
Protoss_Dragoon 1 10053
Protoss_Corsair 1 10846
Protoss_Templar_Archives 1 11750
Protoss_Forge 1 12210
Protoss_Dark_Templar 2 13441
Protoss_High_Templar 2 14542
Protoss_Nexus 1 16361
16361
