Protoss_Gateway 2 4821
Protoss_Zealot 12 15288
Protoss_Nexus 1 11076
Protoss_Forge 1 9918
Protoss_Photon_Cannon 2 11769
Protoss_Assimilator 2 13937
Protoss_Cybernetics_Core 1 13624
Protoss_Citadel_of_Adun 1 15643
15643
