Protoss_Nexus 1 7579
Protoss_Gateway 3 8055
Protoss_Zealot 16 14629
Protoss_Assimilator 2 13450
Protoss_Forge 1 10395
Protoss_Cybernetics_Core 1 12782
Protoss_Photon_Cannon 1 13020
Protoss_Stargate 1 15067
Protoss_Citadel_of_Adun 1 14933
15067
