Protoss_Nexus 1 6634
Protoss_Forge 1 5271
Protoss_Photon_Cannon 5 15682
Protoss_Gateway 5 15514
Protoss_Assimilator 2 13306
Protoss_Zealot 13 15453
Protoss_Cybernetics_Core 1 10296
Protoss_Citadel_of_Adun 1 11851
Protoss_Dragoon 1 12505
Protoss_Templar_Archives 1 14829
15682
