Protoss_Forge 1 3910
Protoss_Nexus 1 7632
Protoss_Photon_Cannon 2 7203
Protoss_Gateway 4 13773
Protoss_Assimilator 2 10507
Protoss_Zealot 7 15039
Protoss_Cybernetics_Core 1 11206
Protoss_Citadel_of_Adun 1 12876
Protoss_Templar_Archives 1 14690
Protoss_Dragoon 1 15424
Protoss_Robotics_Facility 1 16440
16440
