Protoss_Gateway 2 5311
Protoss_Zealot 12 12737
Protoss_Assimilator 1 8112
Protoss_Cybernetics_Core 1 10351
Protoss_Forge 1 10987
Protoss_Dragoon 1 11875
Protoss_Photon_Cannon 3 14937
Protoss_Robotics_Facility 1 14261
Protoss_Citadel_of_Adun 1 14276
Protoss_Templar_Archives 1 15746
Protoss_Observatory 1 15266
15746
