Protoss_Forge 1 3907
Protoss_Photon_Cannon 4 14793
Protoss_Nexus 1 8839
Protoss_Gateway 1 8348
Protoss_Assimilator 2 10659
Protoss_Zealot 4 11989
Protoss_Cybernetics_Core 1 10480
Protoss_Stargate 1 12288
Protoss_Citadel_of_Adun 1 12285
Protoss_Corsair 3 15075
Protoss_Robotics_Facility 1 14448
Protoss_Shuttle 1 15882
15882
