Protoss_Forge 1 3993
Protoss_Nexus 2 15813
Protoss_Photon_Cannon 3 15303
Protoss_Gateway 2 14769
Protoss_Assimilator 2 11793
Protoss_Zealot 3 13597
Protoss_Cybernetics_Core 1 10347
Protoss_Citadel_of_Adun 1 11911
Protoss_Dragoon 1 11805
Protoss_Templar_Archives 1 13564
Protoss_Dark_Templar 1 14773
15813
