Protoss_Forge 1 4448
Protoss_Photon_Cannon 4 14940
Protoss_Nexus 1 9208
Protoss_Gateway 2 13799
Protoss_Assimilator 2 12532
Protoss_Cybernetics_Core 1 10401
Protoss_Dragoon 1 11594
Protoss_Citadel_of_Adun 1 12026
Protoss_Zealot 3 14347
Protoss_Stargate 2 14767
Protoss_Templar_Archives 1 15189
15189
