Protoss_Nexus 2 12665
Protoss_Forge 2 13002
Protoss_Photon_Cannon 5 14676
Protoss_Gateway 3 8186
Protoss_Zealot 12 13207
Protoss_Assimilator 1 14980
Protoss_Cybernetics_Core 1 16006
16006
