Protoss_Nexus 1 7032
Protoss_Forge 1 5617
Protoss_Photon_Cannon 1 6881
Protoss_Gateway 3 11553
Protoss_Assimilator 2 13827
Protoss_Zealot 11 14711
Protoss_Cybernetics_Core 1 10561
Protoss_Dragoon 1 11897
Protoss_Citadel_of_Adun 1 12286
Protoss_Templar_Archives 1 13748
Protoss_Ground_Weapons_1 1 14394
14711
