Protoss_Forge 1 3836
Protoss_Photon_Cannon 5 15780
Protoss_Nexus 1 8150
Protoss_Gateway 4 12115
Protoss_Assimilator 2 14825
Protoss_Zealot 16 15201
Protoss_Cybernetics_Core 1 8971
Protoss_Citadel_of_Adun 1 10805
Protoss_Templar_Archives 1 13416
Protoss_High_Templar 2 14905
Leg_Enhancements 1 14173
Protoss_Ground_Weapons_1 1 14232
15780
