Protoss_Forge 1 4052
Protoss_Nexus 1 8062
Protoss_Photon_Cannon 2 7847
Protoss_Gateway 2 9728
Protoss_Assimilator 1 10461
Protoss_Zealot 7 14175
Protoss_Cybernetics_Core 1 12696
14175
