Protoss_Gateway 1 4385
Protoss_Assimilator 1 4619
Protoss_Cybernetics_Core 1 5882
Protoss_Zealot 7 14730
Protoss_Stargate 1 7690
Protoss_Corsair 1 8631
Protoss_Scout 1 9791
Protoss_Dragoon 1 9540
Protoss_Nexus 1 15716
Protoss_Citadel_of_Adun 1 14835
15716
