Protoss_Forge 1 4013
Protoss_Photon_Cannon 4 15701
Protoss_Nexus 1 8332
Protoss_Gateway 4 13692
Protoss_Assimilator 2 13624
Protoss_Cybernetics_Core 1 9339
Protoss_Zealot 8 15368
Protoss_Citadel_of_Adun 1 12264
15701
