Protoss_Gateway 4 14989
Protoss_Zealot 10 15479
Protoss_Assimilator 1 6020
Protoss_Forge 1 6441
Protoss_Nexus 1 10653
Protoss_Photon_Cannon 2 9982
Protoss_Cybernetics_Core 1 11180
Protoss_Citadel_of_Adun 1 12822
Protoss_Dragoon 1 12742
15479
