Protoss_Forge 1 4637
Protoss_Photon_Cannon 6 14870
Protoss_Nexus 1 8692
Protoss_Gateway 2 15806
Protoss_Zealot 5 14856
Protoss_Assimilator 1 9342
Protoss_Cybernetics_Core 1 12269
Protoss_Citadel_of_Adun 1 14006
Protoss_Dragoon 1 13994
Protoss_Templar_Archives 1 15681
15806
