Protoss_Gateway 1 4138
Protoss_Assimilator 1 4193
Protoss_Cybernetics_Core 1 5895
Protoss_Zealot 5 13185
Protoss_Dragoon 1 7225
Protoss_Stargate 1 8491
Protoss_Corsair 1 9552
Protoss_Citadel_of_Adun 1 11398
Protoss_Templar_Archives 1 13012
Protoss_Forge 1 13078
Protoss_Dark_Templar 1 14305
Protoss_Photon_Cannon 1 14624
Protoss_High_Templar 1 15783
15783
