Protoss_Forge 1 4316
Protoss_Nexus 1 8276
Protoss_Photon_Cannon 3 15611
Protoss_Gateway 4 12378
Protoss_Assimilator 2 13720
Protoss_Cybernetics_Core 1 9602
Protoss_Zealot 13 15125
Protoss_Citadel_of_Adun 1 11129
Protoss_Templar_Archives 1 14964
Leg_Enhancements 1 14080
15611
