Protoss_Gateway 5 15304
Protoss_Zealot 14 14936
Protoss_Nexus 1 11187
Protoss_Forge 1 10823
Protoss_Assimilator 1 10932
Protoss_Photon_Cannon 2 12369
Protoss_Cybernetics_Core 1 13142
Protoss_Citadel_of_Adun 1 14635
Protoss_Stargate 1 15031
15304
