Protoss_Nexus 1 6937
Protoss_Forge 1 5904
Protoss_Gateway 4 11165
Protoss_Assimilator 2 13397
Protoss_Photon_Cannon 2 15287
Protoss_Cybernetics_Core 1 9394
Protoss_Citadel_of_Adun 1 10887
Protoss_Zealot 11 13941
Protoss_Templar_Archives 1 13442
Protoss_High_Templar 2 15446
Protoss_Ground_Weapons_1 1 14592
15446
