Protoss_Gateway 2 11279
Protoss_Assimilator 1 4612
Protoss_Zealot 11 14654
Protoss_Cybernetics_Core 1 7457
Protoss_Stargate 1 9403
Protoss_Dragoon 1 9704
Protoss_Citadel_of_Adun 1 10943
Protoss_Corsair 1 10943
Protoss_Templar_Archives 1 13770
Protoss_Forge 1 14110
Protoss_High_Templar 2 14998
Leg_Enhancements 1 14238
Protoss_Photon_Cannon 3 15720
15720
