Protoss_Nexus 1 7224
Protoss_Gateway 4 11891
Protoss_Forge 1 7173
Protoss_Zealot 15 14923
Protoss_Assimilator 1 7843
Protoss_Photon_Cannon 1 8549
Protoss_Cybernetics_Core 1 9811
Protoss_Citadel_of_Adun 1 11616
14923
