Protoss_Forge 1 4409
Protoss_Photon_Cannon 5 15098
Protoss_Nexus 1 8717
Protoss_Gateway 3 12302
Protoss_Assimilator 2 11091
Protoss_Cybernetics_Core 1 10186
Protoss_Zealot 6 14358
Protoss_Citadel_of_Adun 1 12008
Protoss_Dragoon 1 12307
Protoss_Templar_Archives 1 13578
Protoss_Robotics_Facility 1 15254
Protoss_High_Templar 2 14802
15254
