Protoss_Nexus 1 6988
Protoss_Forge 2 11639
Protoss_Photon_Cannon 5 15423
Protoss_Assimilator 2 9359
Protoss_Gateway 3 11644
Protoss_Cybernetics_Core 1 13056
Protoss_Zealot 6 14200
Protoss_Citadel_of_Adun 1 14794
Protoss_Robotics_Facility 1 15690
15690
