Protoss_Forge 1 4008
Protoss_Photon_Cannon 9 15142
Protoss_Nexus 1 7708
Protoss_Gateway 3 15920
Protoss_Assimilator 2 12068
Protoss_Zealot 3 11136
Protoss_Cybernetics_Core 1 11153
Protoss_Citadel_of_Adun 1 12817
Protoss_Templar_Archives 1 14585
15920
