Protoss_Forge 1 4161
Protoss_Nexus 1 7983
Protoss_Photon_Cannon 3 14757
Protoss_Gateway 4 14497
Protoss_Assimilator 2 10207
Protoss_Cybernetics_Core 1 10313
Protoss_Citadel_of_Adun 1 11860
Protoss_Robotics_Facility 1 13743
Protoss_Templar_Archives 1 13889
Protoss_Zealot 1 14607
Protoss_Observatory 1 14643
Protoss_High_Templar 2 15614
15614
