Protoss_Forge 1 4473
Protoss_Photon_Cannon 5 15822
Protoss_Nexus 1 8967
Protoss_Gateway 3 14876
Protoss_Zealot 4 15200
Protoss_Assimilator 2 12668
Protoss_Cybernetics_Core 1 13850
Protoss_Citadel_of_Adun 1 15506
15822
