Protoss_Forge 1 5132
Protoss_Photon_Cannon 6 15427
Protoss_Nexus 1 9944
Protoss_Assimilator 2 9918
Protoss_Gateway 3 15874
Protoss_Cybernetics_Core 1 10858
Protoss_Zealot 2 11266
Protoss_Citadel_of_Adun 1 12416
Protoss_Dragoon 1 12395
Protoss_Templar_Archives 1 13968
Protoss_High_Templar 2 15373
15874
