Protoss_Forge 1 4103
Protoss_Nexus 1 8317
Protoss_Photon_Cannon 6 15617
Protoss_Assimilator 2 9803
Protoss_Gateway 3 13302
Protoss_Cybernetics_Core 1 11802
Protoss_Zealot 10 15176
Protoss_Citadel_of_Adun 1 13777
15617
