Protoss_Assimilator 1 4062
Protoss_Gateway 2 13476
Protoss_Cybernetics_Core 1 6292
Protoss_Dragoon 9 15424
Protoss_Robotics_Facility 1 8460
Protoss_Observatory 1 9335
Protoss_Observer 1 10363
Protoss_Shuttle 1 11748
Protoss_Forge 1 12854
Protoss_Shield_Battery 1 13052
Singularity_Charge 1 12623
Protoss_Photon_Cannon 1 14117
Protoss_Citadel_of_Adun 1 15659
15659
