Protoss_Gateway 2 5338
Protoss_Zealot 11 14449
Protoss_Assimilator 1 6349
Protoss_Cybernetics_Core 1 8210
Protoss_Citadel_of_Adun 1 9927
Protoss_Templar_Archives 1 11878
Protoss_Forge 1 11764
Protoss_Photon_Cannon 2 14076
Protoss_High_Templar 4 15717
Leg_Enhancements 1 13245
Protoss_Archon 1 14067
15717
