Protoss_Forge 1 4454
Protoss_Photon_Cannon 6 8755
Protoss_Nexus 1 10326
Protoss_Gateway 4 14919
Protoss_Assimilator 1 9334
Protoss_Cybernetics_Core 1 10880
Protoss_Zealot 8 15152
Protoss_Dragoon 1 12502
Protoss_Citadel_of_Adun 1 13646
Protoss_Templar_Archives 1 15778
15778
