Protoss_Forge 1 4047
Protoss_Nexus 1 7837
Protoss_Photon_Cannon 4 14650
Protoss_Assimilator 2 9105
Protoss_Gateway 3 13056
Protoss_Zealot 7 14066
Protoss_Cybernetics_Core 1 10473
Protoss_Citadel_of_Adun 1 12124
Protoss_Templar_Archives 1 14117
Protoss_High_Templar 2 15651
15651
