Protoss_Forge 1 4172
Protoss_Photon_Cannon 2 6085
Protoss_Nexus 1 8749
Protoss_Gateway 1 7855
Protoss_Assimilator 2 11566
Protoss_Zealot 1 8907
Protoss_Cybernetics_Core 1 9861
11566
