Protoss_Forge 1 4234
Protoss_Nexus 1 7764
Protoss_Gateway 4 14136
Protoss_Photon_Cannon 1 7263
Protoss_Assimilator 2 11869
Protoss_Zealot 10 15207
Protoss_Cybernetics_Core 1 9137
Protoss_Citadel_of_Adun 1 10776
Protoss_Dragoon 1 11297
Protoss_Templar_Archives 1 13723
Leg_Enhancements 1 13750
Protoss_Robotics_Facility 1 15936
Protoss_High_Templar 2 15556
15936
