Protoss_Forge 1 5031
Protoss_Nexus 1 7999
Protoss_Photon_Cannon 1 6525
Protoss_Gateway 3 12460
Protoss_Assimilator 2 13432
Protoss_Zealot 11 15141
Protoss_Cybernetics_Core 1 10239
Protoss_Citadel_of_Adun 1 11796
Protoss_Templar_Archives 1 13919
Protoss_Ground_Weapons_1 1 14058
Protoss_High_Templar 2 15467
15467
