Protoss_Forge 1 3972
Protoss_Nexus 1 7764
Protoss_Photon_Cannon 7 15420
Protoss_Gateway 3 14633
Protoss_Zealot 6 14342
Protoss_Assimilator 2 15408
Protoss_Cybernetics_Core 1 11165
Protoss_Citadel_of_Adun 1 12943
Protoss_Templar_Archives 1 15432
15432
