Protoss_Gateway 1 4208
Protoss_Assimilator 1 4489
Protoss_Zealot 3 7267
Protoss_Cybernetics_Core 1 7425
Protoss_Stargate 1 9133
Protoss_Citadel_of_Adun 1 9466
Protoss_Dragoon 1 9751
Protoss_Corsair 1 10161
Protoss_Forge 1 10665
Protoss_Templar_Archives 1 11329
Protoss_Dark_Templar 1 12584
12584
