Protoss_Gateway 4 14629
Protoss_Zealot 5 12492
Protoss_Forge 1 5625
Protoss_Photon_Cannon 2 8758
Protoss_Nexus 1 10303
Protoss_Assimilator 2 13356
Protoss_Cybernetics_Core 1 10944
Protoss_Citadel_of_Adun 1 12640
Protoss_Dragoon 1 13778
Protoss_Templar_Archives 1 15841
15841
