Protoss_Forge 1 4394
Protoss_Nexus 1 8004
Protoss_Gateway 4 14085
Protoss_Assimilator 2 11437
Protoss_Photon_Cannon 2 12925
Protoss_Zealot 7 15441
Protoss_Cybernetics_Core 1 9274
Protoss_Citadel_of_Adun 1 10843
Protoss_Templar_Archives 1 13543
Leg_Enhancements 1 13867
Protoss_High_Templar 2 15200
Protoss_Dark_Templar 1 15146
15441
