Protoss_Forge 1 4152
Protoss_Photon_Cannon 3 15480
Protoss_Nexus 1 9539
Protoss_Gateway 4 14067
Protoss_Assimilator 2 11945
Protoss_Zealot 8 14753
Protoss_Cybernetics_Core 1 10253
Protoss_Citadel_of_Adun 1 11999
Protoss_Templar_Archives 1 14775
15480
