Protoss_Nexus 1 7121
Protoss_Gateway 2 14143
Protoss_Forge 1 6598
Protoss_Assimilator 2 10305
Protoss_Photon_Cannon 5 14280
Protoss_Zealot 5 15162
Protoss_Cybernetics_Core 1 9819
Protoss_Citadel_of_Adun 1 11418
Protoss_Stargate 1 12341
Protoss_Templar_Archives 1 13296
Protoss_Corsair 1 13488
Protoss_Ground_Weapons_1 1 14621
15162
