Protoss_Forge 1 4649
Protoss_Photon_Cannon 2 13776
Protoss_Nexus 1 8342
Protoss_Assimilator 2 14414
Protoss_Gateway 4 12987
Protoss_Cybernetics_Core 1 9716
Protoss_Zealot 12 14988
Protoss_Citadel_of_Adun 1 11304
Protoss_Dragoon 1 11363
Protoss_Ground_Armor_1 1 14328
Protoss_Templar_Archives 1 15776
Leg_Enhancements 1 14555
15776
