Protoss_Forge 1 3986
Protoss_Nexus 1 7596
Protoss_Photon_Cannon 4 15251
Protoss_Gateway 3 12170
Protoss_Assimilator 2 12127
Protoss_Zealot 7 14493
Protoss_Cybernetics_Core 1 10031
Protoss_Citadel_of_Adun 1 11633
Protoss_Templar_Archives 1 13722
Protoss_High_Templar 3 15613
15613
