Protoss_Forge 1 3785
Protoss_Nexus 1 7383
Protoss_Photon_Cannon 1 6186
Protoss_Gateway 6 13868
Protoss_Assimilator 1 7832
Protoss_Zealot 10 15163
Protoss_Cybernetics_Core 1 8726
Protoss_Stargate 1 10810
Protoss_Dragoon 3 15127
Protoss_Corsair 2 12291
Protoss_Citadel_of_Adun 1 14219
15163
