Protoss_Nexus 1 7072
Protoss_Forge 1 5756
Protoss_Gateway 3 15154
Protoss_Photon_Cannon 8 14785
Protoss_Assimilator 2 11256
Protoss_Zealot 4 12149
Protoss_Cybernetics_Core 1 10689
Protoss_Citadel_of_Adun 1 12211
Protoss_Templar_Archives 1 14363
Protoss_High_Templar 2 15585
Protoss_Ground_Weapons_1 1 14511
15585
