Protoss_Gateway 2 5317
Protoss_Zealot 12 14139
Protoss_Assimilator 1 6352
Protoss_Cybernetics_Core 1 8676
Protoss_Dragoon 1 10017
Protoss_Stargate 1 10715
Protoss_Citadel_of_Adun 1 11549
Protoss_Corsair 1 11834
Protoss_Forge 1 13622
Protoss_Templar_Archives 1 14979
Leg_Enhancements 1 14504
14979
