Protoss_Nexus 1 7152
Protoss_Forge 1 5632
Protoss_Photon_Cannon 4 15326
Protoss_Gateway 4 13660
Protoss_Assimilator 2 11054
Protoss_Zealot 8 14761
Protoss_Cybernetics_Core 1 10272
Protoss_Dragoon 1 11561
Protoss_Citadel_of_Adun 1 12756
Protoss_Templar_Archives 1 14311
Protoss_Dark_Templar 1 15731
15731
