Protoss_Forge 2 15510
Protoss_Photon_Cannon 4 12797
Protoss_Nexus 1 8335
Protoss_Gateway 4 15371
Protoss_Assimilator 2 11039
Protoss_Zealot 1 9514
Protoss_Cybernetics_Core 1 10455
Protoss_Dragoon 2 14290
Protoss_Stargate 1 12376
Protoss_Robotics_Facility 2 15336
Protoss_Scout 1 14426
15510
