Protoss_Gateway 3 10944
Protoss_Zealot 18 14871
Protoss_Assimilator 1 6137
Protoss_Cybernetics_Core 1 7375
Protoss_Citadel_of_Adun 1 9330
Protoss_Dragoon 1 9161
Leg_Enhancements 1 12521
Protoss_Templar_Archives 1 13976
14871
