Protoss_Forge 1 4469
Protoss_Photon_Cannon 5 15449
Protoss_Nexus 1 8898
Protoss_Gateway 4 13382
Protoss_Assimilator 2 12651
Protoss_Zealot 9 15375
Protoss_Cybernetics_Core 1 11278
Protoss_Citadel_of_Adun 1 13826
Protoss_Dragoon 1 14641
15449
