Protoss_Nexus 1 7325
Protoss_Gateway 3 14399
Protoss_Forge 1 6503
Protoss_Photon_Cannon 6 14776
Protoss_Zealot 7 13985
Protoss_Assimilator 2 13268
Protoss_Cybernetics_Core 1 11521
Protoss_Stargate 1 13740
Protoss_Corsair 1 14695
Protoss_Dragoon 2 15636
Protoss_Citadel_of_Adun 1 15794
15794
