Protoss_Gateway 2 5136
Protoss_Zealot 9 13049
Protoss_Assimilator 2 14647
Protoss_Forge 1 8957
Protoss_Cybernetics_Core 1 10195
Protoss_Citadel_of_Adun 1 11737
Protoss_Nexus 1 14326
Protoss_Photon_Cannon 3 15455
Protoss_Templar_Archives 1 14107
Protoss_High_Templar 2 15380
15455
