Protoss_Nexus 1 7072
Protoss_Gateway 1 6187
Protoss_Forge 1 6232
Protoss_Photon_Cannon 7 15688
Protoss_Assimilator 1 7499
Protoss_Zealot 7 15547
Protoss_Cybernetics_Core 1 9153
Protoss_Citadel_of_Adun 1 10723
Protoss_Templar_Archives 1 14992
15688
