Protoss_Nexus 1 6936
Protoss_Gateway 2 13792
Protoss_Forge 1 6400
Protoss_Photon_Cannon 5 15669
Protoss_Assimilator 2 9312
Protoss_Cybernetics_Core 1 9084
Protoss_Zealot 5 14127
Protoss_Stargate 2 12817
Protoss_Citadel_of_Adun 1 11197
Protoss_Corsair 6 15108
Protoss_Shield_Battery 1 14815
15669
