Protoss_Forge 1 3932
Protoss_Photon_Cannon 2 7898
Protoss_Nexus 1 8477
Protoss_Gateway 6 14513
Protoss_Assimilator 1 7918
Protoss_Cybernetics_Core 1 9457
Protoss_Zealot 12 15412
Protoss_Citadel_of_Adun 1 11212
Protoss_Dragoon 1 12249
Protoss_Templar_Archives 1 15241
Leg_Enhancements 1 14343
15412
