Protoss_Nexus 1 7300
Protoss_Forge 1 6156
Protoss_Photon_Cannon 5 9939
Protoss_Gateway 4 15175
Protoss_Assimilator 2 12618
Protoss_Zealot 8 15456
Protoss_Cybernetics_Core 1 12990
Protoss_Stargate 1 14688
Protoss_Citadel_of_Adun 1 14919
15456
