Protoss_Forge 1 4643
Protoss_Photon_Cannon 4 10672
Protoss_Nexus 1 8873
Protoss_Gateway 3 14026
Protoss_Zealot 7 15558
Protoss_Assimilator 2 13761
Protoss_Cybernetics_Core 1 13530
Protoss_Citadel_of_Adun 1 15235
Protoss_Dragoon 2 15673
15673
