Protoss_Gateway 1 4389
Protoss_Assimilator 2 6459
Protoss_Zealot 7 14756
Protoss_Cybernetics_Core 1 8099
Protoss_Stargate 1 10190
Protoss_Dragoon 1 9914
Protoss_Citadel_of_Adun 1 10445
Protoss_Forge 1 14230
Leg_Enhancements 1 13728
14756
