Protoss_Nexus 1 6966
Protoss_Gateway 4 12230
Protoss_Forge 1 6349
Protoss_Assimilator 2 13559
Protoss_Photon_Cannon 1 7670
Protoss_Zealot 14 15231
Protoss_Cybernetics_Core 1 8690
Protoss_Citadel_of_Adun 1 10324
Protoss_Templar_Archives 1 13275
Leg_Enhancements 1 13272
Protoss_High_Templar 2 14834
Protoss_Ground_Weapons_1 1 13986
Protoss_Robotics_Facility 1 16443
16443
