Protoss_Forge 1 4157
Protoss_Nexus 1 7833
Protoss_Gateway 4 13558
Protoss_Photon_Cannon 2 7822
Protoss_Assimilator 2 11361
Protoss_Cybernetics_Core 1 9201
Protoss_Zealot 7 15514
Protoss_Citadel_of_Adun 1 11534
Protoss_Templar_Archives 1 13092
Protoss_High_Templar 4 15285
Protoss_Archon 1 14913
15514
