Protoss_Gateway 2 4925
Protoss_Zealot 7 11834
Protoss_Nexus 1 10596
Protoss_Assimilator 2 14837
Protoss_Forge 1 9517
Protoss_Cybernetics_Core 1 10455
Protoss_Stargate 1 12343
Protoss_Photon_Cannon 3 15134
Protoss_Corsair 2 15002
Protoss_Citadel_of_Adun 1 14026
15134
