Protoss_Forge 1 4542
Protoss_Nexus 1 7604
Protoss_Photon_Cannon 8 15231
Protoss_Gateway 3 14948
Protoss_Assimilator 2 11474
Protoss_Cybernetics_Core 1 9548
Protoss_Zealot 2 12090
Protoss_Dragoon 1 10997
Protoss_Citadel_of_Adun 1 11611
Protoss_Templar_Archives 1 13894
Protoss_High_Templar 2 15410
15410
