Protoss_Forge 1 4354
Protoss_Photon_Cannon 4 14549
Protoss_Nexus 1 8949
Protoss_Gateway 2 13558
Protoss_Assimilator 2 9680
Protoss_Cybernetics_Core 1 9428
Protoss_Zealot 2 12134
Protoss_Dragoon 1 10792
Protoss_Stargate 1 11564
Protoss_Citadel_of_Adun 1 12255
Protoss_Corsair 2 13388
Protoss_Templar_Archives 1 14077
Protoss_Dark_Templar 2 15783
15783
