Protoss_Forge 1 4337
Protoss_Nexus 1 7588
Protoss_Photon_Cannon 6 15427
Protoss_Gateway 2 13736
Protoss_Assimilator 2 12266
Protoss_Zealot 3 12945
Protoss_Cybernetics_Core 1 10511
Protoss_Dragoon 1 11834
Protoss_Citadel_of_Adun 1 12154
Protoss_Templar_Archives 1 13628
Protoss_Dark_Templar 1 14823
Protoss_High_Templar 1 14931
15427
