Protoss_Gateway 1 4084
Protoss_Assimilator 1 4788
Protoss_Zealot 3 8186
Protoss_Cybernetics_Core 1 7272
Protoss_Stargate 1 9420
Protoss_Dragoon 1 9373
Protoss_Corsair 2 11376
11376
