Protoss_Forge 1 4009
Protoss_Nexus 1 7615
Protoss_Photon_Cannon 3 13500
Protoss_Gateway 5 14469
Protoss_Assimilator 2 12974
Protoss_Zealot 7 14511
Protoss_Cybernetics_Core 1 11589
Protoss_Dragoon 1 13649
Protoss_Citadel_of_Adun 1 14152
14511
