Protoss_Forge 1 5183
Protoss_Nexus 1 7979
Protoss_Photon_Cannon 4 13444
Protoss_Gateway 2 12833
Protoss_Assimilator 2 10025
Protoss_Cybernetics_Core 1 9580
Protoss_Zealot 1 9491
Protoss_Stargate 1 11308
Protoss_Citadel_of_Adun 1 11481
Protoss_Templar_Archives 1 12971
Protoss_Corsair 3 14821
Protoss_Dark_Templar 4 15607
Protoss_Robotics_Facility 1 15598
15607
