Protoss_Forge 1 5272
Protoss_Nexus 1 7961
Protoss_Photon_Cannon 5 15105
Protoss_Gateway 3 15131
Protoss_Assimilator 2 11187
Protoss_Zealot 3 12839
Protoss_Cybernetics_Core 1 10461
Protoss_Dragoon 1 11978
Protoss_Citadel_of_Adun 1 12636
15131
