Protoss_Nexus 1 7208
Protoss_Gateway 3 11333
Protoss_Assimilator 2 12415
Protoss_Cybernetics_Core 1 8260
Protoss_Forge 1 8127
Protoss_Photon_Cannon 1 9493
Protoss_Citadel_of_Adun 1 10302
Protoss_Zealot 13 15149
Protoss_Templar_Archives 1 14047
Leg_Enhancements 1 13362
Protoss_Ground_Weapons_1 1 14028
15149
