Protoss_Forge 1 4417
Protoss_Photon_Cannon 5 15459
Protoss_Nexus 1 8569
Protoss_Gateway 2 12864
Protoss_Assimilator 2 12728
Protoss_Zealot 5 13173
Protoss_Cybernetics_Core 1 9694
Protoss_Citadel_of_Adun 1 11462
Protoss_Templar_Archives 1 13338
Protoss_Dark_Templar 2 14729
15459
