Protoss_Forge 1 4101
Protoss_Photon_Cannon 4 12999
Protoss_Nexus 1 9404
Protoss_Gateway 3 15156
Protoss_Assimilator 2 13103
Protoss_Cybernetics_Core 1 10003
Protoss_Zealot 7 14031
Protoss_Citadel_of_Adun 1 11519
Protoss_Templar_Archives 1 14268
Protoss_High_Templar 2 15508
Leg_Enhancements 1 14454
15508
