Protoss_Forge 2 15490
Protoss_Nexus 1 8013
Protoss_Photon_Cannon 3 14918
Protoss_Assimilator 1 7303
Protoss_Gateway 4 14979
Protoss_Zealot 7 14064
Protoss_Cybernetics_Core 1 10136
Protoss_Dragoon 1 11417
Protoss_Citadel_of_Adun 1 11750
Protoss_Ground_Weapons_1 1 14211
15490
