Protoss_Nexus 1 6985
Protoss_Forge 1 5751
Protoss_Photon_Cannon 7 15332
Protoss_Gateway 2 14781
Protoss_Assimilator 2 12062
Protoss_Zealot 7 14584
Protoss_Cybernetics_Core 1 10707
Protoss_Stargate 1 12426
Protoss_Citadel_of_Adun 1 13515
Protoss_Corsair 2 15462
15462
