Protoss_Nexus 1 7132
Protoss_Forge 2 14427
Protoss_Gateway 3 13362
Protoss_Photon_Cannon 8 15815
Protoss_Assimilator 2 10182
Protoss_Cybernetics_Core 1 9476
Protoss_Zealot 3 13305
Protoss_Stargate 1 11286
Protoss_Dragoon 1 10874
Protoss_Citadel_of_Adun 1 12105
Protoss_Corsair 2 13486
Protoss_Templar_Archives 1 13591
Protoss_Robotics_Facility 1 15485
Protoss_Dark_Templar 3 15265
15815
