Protoss_Forge 2 14244
Protoss_Nexus 1 7742
Protoss_Photon_Cannon 1 7027
Protoss_Gateway 4 12358
Protoss_Assimilator 2 9898
Protoss_Zealot 13 15492
Protoss_Cybernetics_Core 1 9836
Protoss_Citadel_of_Adun 1 11328
Leg_Enhancements 1 14519
15492
