Protoss_Assimilator 2 7947
Protoss_Gateway 1 4830
Protoss_Cybernetics_Core 1 6333
Protoss_Stargate 3 15286
Protoss_Corsair 10 15162
Protoss_Dragoon 1 9278
Protoss_Forge 1 11772
Protoss_Shield_Battery 1 11653
Protoss_Photon_Cannon 1 13027
Protoss_Air_Weapons_1 1 12243
15286
