Protoss_Forge 1 4160
Protoss_Nexus 1 7727
Protoss_Gateway 2 14951
Protoss_Assimilator 2 10125
Protoss_Photon_Cannon 4 12551
Protoss_Cybernetics_Core 1 9238
Protoss_Zealot 3 14592
Protoss_Dragoon 1 10924
Protoss_Citadel_of_Adun 1 11278
14951
