Protoss_Forge 1 4047
Protoss_Nexus 1 7689
Protoss_Gateway 4 14355
Protoss_Assimilator 2 14377
Protoss_Photon_Cannon 1 8466
Protoss_Zealot 9 14633
Protoss_Cybernetics_Core 1 9915
Protoss_Dragoon 1 11123
Protoss_Citadel_of_Adun 1 11440
Protoss_Templar_Archives 1 14764
14764
