Protoss_Forge 1 4359
Protoss_Photon_Cannon 2 13449
Protoss_Nexus 1 8563
Protoss_Gateway 3 14063
Protoss_Assimilator 2 9877
Protoss_Cybernetics_Core 1 9400
Protoss_Zealot 1 9432
Protoss_Stargate 1 11127
Protoss_Citadel_of_Adun 1 11821
Protoss_Corsair 2 12953
Protoss_Templar_Archives 1 13423
Protoss_Dark_Templar 1 14811
Protoss_High_Templar 2 15431
Protoss_Robotics_Facility 1 16495
16495
