Protoss_Forge 1 3934
Protoss_Photon_Cannon 3 14805
Protoss_Nexus 1 8692
Protoss_Gateway 3 13646
Protoss_Assimilator 2 11424
Protoss_Zealot 9 14995
Protoss_Cybernetics_Core 1 10133
Protoss_Citadel_of_Adun 1 11780
Protoss_Templar_Archives 1 13924
14995
