Protoss_Forge 1 4283
Protoss_Nexus 1 7979
Protoss_Gateway 4 15308
Protoss_Photon_Cannon 2 14742
Protoss_Assimilator 2 12921
Protoss_Zealot 10 15244
Protoss_Cybernetics_Core 1 9036
Protoss_Citadel_of_Adun 1 10609
Protoss_Dragoon 1 13368
Leg_Enhancements 1 13662
Protoss_Templar_Archives 1 15396
Protoss_Ground_Weapons_1 1 14233
15396
