Protoss_Forge 1 3711
Protoss_Photon_Cannon 3 8041
Protoss_Nexus 1 8791
Protoss_Assimilator 2 14405
Protoss_Gateway 3 12470
Protoss_Zealot 11 15561
Protoss_Cybernetics_Core 1 11589
Protoss_Citadel_of_Adun 1 13089
Protoss_Dragoon 1 12938
Protoss_Templar_Archives 1 15204
15561
