Protoss_Forge 1 4148
Protoss_Photon_Cannon 4 15525
Protoss_Nexus 1 8576
Protoss_Gateway 4 13922
Protoss_Assimilator 2 11982
Protoss_Cybernetics_Core 1 9905
Protoss_Zealot 2 12883
Protoss_Citadel_of_Adun 1 11919
Protoss_Templar_Archives 1 13627
Protoss_High_Templar 4 15431
15525
