Protoss_Forge 1 4169
Protoss_Nexus 1 8254
Protoss_Gateway 4 12438
Protoss_Photon_Cannon 1 7195
Protoss_Assimilator 2 12621
Protoss_Zealot 11 14541
Protoss_Cybernetics_Core 1 9485
Protoss_Citadel_of_Adun 1 11146
Protoss_Templar_Archives 1 14588
Leg_Enhancements 1 14116
Protoss_Ground_Weapons_1 1 14606
14606
