Protoss_Forge 1 4091
Protoss_Photon_Cannon 2 13067
Protoss_Nexus 1 8318
Protoss_Gateway 3 15014
Protoss_Assimilator 2 13272
Protoss_Zealot 3 14219
Protoss_Cybernetics_Core 1 12124
Protoss_Stargate 1 14175
Protoss_Citadel_of_Adun 1 14398
Protoss_Templar_Archives 1 15980
15980
