Protoss_Gateway 3 15732
Protoss_Forge 1 5190
Protoss_Zealot 9 15302
Protoss_Photon_Cannon 2 11343
Protoss_Nexus 1 10151
Protoss_Assimilator 2 11290
Protoss_Cybernetics_Core 1 10155
Protoss_Stargate 1 12215
Protoss_Corsair 2 14410
Protoss_Citadel_of_Adun 1 14513
15732
