Protoss_Forge 1 3899
Protoss_Photon_Cannon 2 7307
Protoss_Nexus 1 8412
Protoss_Gateway 3 13653
Protoss_Assimilator 2 11044
Protoss_Zealot 7 15456
Protoss_Cybernetics_Core 1 10196
Protoss_Stargate 1 12650
Protoss_Citadel_of_Adun 1 13190
Protoss_Corsair 2 14513
Protoss_Templar_Archives 1 14654
15456
