Protoss_Gateway 2 14925
Protoss_Assimilator 1 4685
Protoss_Zealot 2 7151
Protoss_Cybernetics_Core 1 7130
Protoss_Stargate 1 9050
Protoss_Dragoon 1 9175
Protoss_Corsair 1 10012
Protoss_Citadel_of_Adun 1 10748
Protoss_Forge 1 11278
Protoss_Templar_Archives 1 13163
Protoss_Photon_Cannon 1 13430
Protoss_Nexus 1 16579
Protoss_Dark_Templar 1 14934
16579
