Protoss_Gateway 2 5049
Protoss_Zealot 9 15219
Protoss_Nexus 2 11765
Protoss_Forge 1 10474
Protoss_Photon_Cannon 2 12480
Protoss_Assimilator 2 14092
Protoss_Cybernetics_Core 1 13908
Protoss_Stargate 1 15776
15776
