Protoss_Forge 1 4643
Protoss_Nexus 1 7825
Protoss_Gateway 4 12350
Protoss_Assimilator 2 13700
Protoss_Photon_Cannon 1 7826
Protoss_Zealot 16 15251
Protoss_Cybernetics_Core 1 9403
Protoss_Citadel_of_Adun 1 10941
Leg_Enhancements 1 13955
Protoss_Ground_Weapons_1 1 14445
15251
