Protoss_Forge 1 3959
Protoss_Photon_Cannon 5 15559
Protoss_Nexus 2 14847
Protoss_Gateway 1 7799
Protoss_Zealot 5 14720
Protoss_Cybernetics_Core 1 9653
Protoss_Assimilator 2 13249
Protoss_Citadel_of_Adun 1 14146
Protoss_Stargate 1 15967
15967
