Protoss_Gateway 2 5229
Protoss_Zealot 16 15093
Protoss_Assimilator 1 5903
Protoss_Cybernetics_Core 1 8136
Protoss_Stargate 1 9830
Protoss_Dragoon 1 9424
Protoss_Corsair 1 10868
Protoss_Nexus 1 16039
Protoss_Forge 1 15124
16039
