Protoss_Forge 1 4821
Protoss_Nexus 1 7825
Protoss_Photon_Cannon 2 14302
Protoss_Gateway 2 15029
Protoss_Assimilator 2 11490
Protoss_Zealot 4 13632
Protoss_Cybernetics_Core 1 10654
Protoss_Dragoon 1 11890
Protoss_Stargate 1 12520
Protoss_Citadel_of_Adun 1 13256
Protoss_Corsair 2 14745
Protoss_Templar_Archives 1 14916
15029
