Protoss_Gateway 3 14377
Protoss_Assimilator 1 4556
Protoss_Zealot 3 11225
Protoss_Cybernetics_Core 1 6882
Protoss_Dragoon 7 15585
Protoss_Citadel_of_Adun 1 9845
Protoss_Robotics_Facility 1 10699
Protoss_Shuttle 1 12106
Protoss_Robotics_Support_Bay 1 11425
Protoss_Reaver 1 13664
Singularity_Charge 1 12499
15585
