Protoss_Nexus 1 7413
Protoss_Forge 1 5932
Protoss_Gateway 6 15656
Protoss_Photon_Cannon 2 15477
Protoss_Assimilator 2 10836
Protoss_Zealot 10 15444
Protoss_Cybernetics_Core 1 9990
Protoss_Citadel_of_Adun 1 11862
Protoss_Templar_Archives 1 14153
Protoss_Dark_Templar 1 15666
15666
