Protoss_Forge 1 4472
Protoss_Nexus 1 8106
Protoss_Photon_Cannon 5 15244
Protoss_Gateway 2 14919
Protoss_Assimilator 2 10867
Protoss_Zealot 2 14440
Protoss_Cybernetics_Core 1 9405
Protoss_Stargate 1 11312
Protoss_Robotics_Facility 1 12742
Protoss_Corsair 3 14118
Protoss_Citadel_of_Adun 1 13417
Protoss_Templar_Archives 1 15129
15244
