Protoss_Forge 1 4226
Protoss_Photon_Cannon 5 14883
Protoss_Nexus 1 8449
Protoss_Gateway 4 15728
Protoss_Assimilator 2 11029
Protoss_Zealot 5 13363
Protoss_Cybernetics_Core 1 9874
Protoss_Citadel_of_Adun 1 11360
Protoss_Templar_Archives 1 12926
Protoss_High_Templar 5 15689
15728
