Protoss_Gateway 2 10051
Protoss_Zealot 12 13731
Protoss_Assimilator 1 5464
Protoss_Cybernetics_Core 1 7217
Protoss_Dragoon 1 8831
Protoss_Citadel_of_Adun 1 9323
Protoss_Templar_Archives 1 13555
Leg_Enhancements 1 12375
Protoss_Dark_Templar 2 15366
Protoss_Forge 1 15298
15366
