Protoss_Nexus 1 7530
Protoss_Forge 1 6400
Protoss_Gateway 3 12555
Protoss_Photon_Cannon 4 14139
Protoss_Assimilator 2 10600
Protoss_Cybernetics_Core 1 9583
Protoss_Zealot 6 14410
Protoss_Stargate 1 11440
Protoss_Citadel_of_Adun 1 11862
Protoss_Corsair 3 15112
Protoss_Templar_Archives 1 15156
15156
