Protoss_Forge 1 4652
Protoss_Nexus 1 7881
Protoss_Photon_Cannon 4 15825
Protoss_Gateway 3 13470
Protoss_Assimilator 2 13638
Protoss_Zealot 8 14508
Protoss_Cybernetics_Core 1 10182
Protoss_Citadel_of_Adun 1 11729
Protoss_Dragoon 1 11495
Protoss_Templar_Archives 1 14348
15825
