Protoss_Forge 1 4259
Protoss_Photon_Cannon 2 7267
Protoss_Nexus 1 8298
Protoss_Gateway 4 13643
Protoss_Assimilator 2 14691
Protoss_Zealot 9 15317
Protoss_Cybernetics_Core 1 9800
Protoss_Citadel_of_Adun 1 11412
Protoss_Dragoon 1 12588
Protoss_Templar_Archives 1 15143
Leg_Enhancements 1 14358
15317
