Protoss_Forge 1 3725
Protoss_Photon_Cannon 6 11082
Protoss_Nexus 1 10735
Protoss_Gateway 1 9958
Protoss_Assimilator 2 13501
Protoss_Zealot 4 13805
Protoss_Cybernetics_Core 1 12067
Protoss_Stargate 1 13954
Protoss_Citadel_of_Adun 1 15002
15002
