Protoss_Forge 1 4160
Protoss_Nexus 2 17234
Protoss_Gateway 4 12871
Protoss_Photon_Cannon 1 7312
Protoss_Assimilator 2 12678
Protoss_Cybernetics_Core 1 9128
Protoss_Zealot 8 14161
Protoss_Dragoon 1 10441
Protoss_Citadel_of_Adun 1 11304
Protoss_Templar_Archives 1 13976
Protoss_High_Templar 2 15731
Protoss_Ground_Weapons_1 1 14577
17234
