Protoss_Gateway 1 4477
Protoss_Assimilator 1 4834
Protoss_Zealot 4 11512
Protoss_Cybernetics_Core 1 7331
Protoss_Stargate 1 9084
Protoss_Dragoon 1 9197
Protoss_Corsair 1 10034
Protoss_Citadel_of_Adun 1 11263
Protoss_Templar_Archives 1 12811
Protoss_Nexus 1 15628
Protoss_Dark_Templar 2 15383
15628
