Protoss_Forge 1 5484
Protoss_Nexus 1 8159
Protoss_Photon_Cannon 7 15581
Protoss_Gateway 1 9396
Protoss_Assimilator 2 11013
Protoss_Cybernetics_Core 1 10867
Protoss_Zealot 4 15064
Protoss_Stargate 1 12653
Protoss_Citadel_of_Adun 1 14251
Protoss_Corsair 2 14794
Protoss_Templar_Archives 1 15816
15816
