Protoss_Gateway 3 15955
Protoss_Assimilator 1 4672
Protoss_Cybernetics_Core 1 6046
Protoss_Zealot 7 14751
Protoss_Stargate 1 8094
Protoss_Corsair 2 10223
Protoss_Citadel_of_Adun 1 10135
15955
