Protoss_Gateway 2 4647
Protoss_Zealot 9 14156
Protoss_Assimilator 2 10110
Protoss_Nexus 1 11068
Protoss_Forge 1 9730
Protoss_Cybernetics_Core 1 11771
Protoss_Photon_Cannon 2 12540
Protoss_Citadel_of_Adun 1 14074
Protoss_Templar_Archives 1 15585
15585
