Protoss_Forge 1 3690
Protoss_Nexus 1 7376
Protoss_Photon_Cannon 9 14580
Protoss_Gateway 1 8202
Protoss_Assimilator 2 11139
Protoss_Zealot 4 13647
Protoss_Cybernetics_Core 1 10363
Protoss_Dragoon 1 14767
14767
