Protoss_Forge 1 4331
Protoss_Nexus 1 7515
Protoss_Photon_Cannon 3 15377
Protoss_Gateway 4 15791
Protoss_Assimilator 2 12937
Protoss_Zealot 12 14803
Protoss_Cybernetics_Core 1 11513
Protoss_Citadel_of_Adun 1 13070
Protoss_Templar_Archives 1 15491
Protoss_Robotics_Facility 1 16160
16160
