Protoss_Forge 1 4578
Protoss_Nexus 1 7881
Protoss_Photon_Cannon 2 8849
Protoss_Gateway 4 14225
Protoss_Assimilator 2 11982
Protoss_Zealot 7 15112
Protoss_Cybernetics_Core 1 10804
Protoss_Stargate 1 12591
Protoss_Citadel_of_Adun 1 13193
Protoss_Corsair 3 15308
Protoss_Templar_Archives 1 15178
15308
