Protoss_Forge 1 4675
Protoss_Photon_Cannon 1 6052
Protoss_Nexus 1 7951
Protoss_Gateway 5 12987
Protoss_Assimilator 2 13151
Protoss_Cybernetics_Core 1 9210
Protoss_Zealot 14 15503
Protoss_Citadel_of_Adun 1 10853
Protoss_Dragoon 1 11193
Protoss_Templar_Archives 1 15146
Leg_Enhancements 1 13889
Protoss_Ground_Weapons_1 1 14358
15503
