Protoss_Forge 1 4594
Protoss_Photon_Cannon 4 13231
Protoss_Nexus 1 8302
Protoss_Gateway 3 16015
Protoss_Zealot 6 15362
Protoss_Assimilator 2 10884
Protoss_Cybernetics_Core 1 11464
Protoss_Stargate 1 13259
Protoss_Citadel_of_Adun 1 13880
Protoss_Corsair 1 14215
Protoss_Robotics_Facility 1 15954
16015
