Protoss_Forge 1 3731
Protoss_Nexus 1 7451
Protoss_Photon_Cannon 4 15380
Protoss_Gateway 4 12296
Protoss_Assimilator 2 12550
Protoss_Cybernetics_Core 1 9765
Protoss_Zealot 11 14472
Protoss_Citadel_of_Adun 1 11285
Protoss_Dragoon 1 11120
Protoss_Templar_Archives 1 13798
Protoss_High_Templar 2 15098
Leg_Enhancements 1 14390
15380
