Protoss_Forge 1 4425
Protoss_Photon_Cannon 3 15674
Protoss_Nexus 1 8417
Protoss_Gateway 3 13193
Protoss_Assimilator 2 11249
Protoss_Zealot 9 14505
Protoss_Cybernetics_Core 1 9134
Protoss_Citadel_of_Adun 1 10929
Protoss_Templar_Archives 1 12778
Protoss_Dark_Templar 1 15613
Protoss_High_Templar 2 15625
Protoss_Ground_Weapons_1 1 14624
15674
