Protoss_Gateway 2 4493
Protoss_Zealot 5 13483
Protoss_Assimilator 1 6633
Protoss_Cybernetics_Core 1 7840
Protoss_Dragoon 1 9039
Protoss_Forge 1 9233
Protoss_Robotics_Facility 1 10851
Protoss_Photon_Cannon 3 14553
Protoss_Shuttle 1 12251
Protoss_Robotics_Support_Bay 1 11732
Protoss_Reaver 1 13809
Protoss_Stargate 1 13916
Protoss_Corsair 1 14853
14853
