Protoss_Nexus 1 7360
Protoss_Forge 1 5939
Protoss_Photon_Cannon 3 8373
Protoss_Gateway 6 14066
Protoss_Assimilator 1 8811
Protoss_Cybernetics_Core 1 10196
Protoss_Zealot 9 15112
Protoss_Citadel_of_Adun 1 11818
Protoss_Stargate 1 13774
Protoss_Templar_Archives 1 15724
15724
