Protoss_Forge 1 3892
Protoss_Photon_Cannon 9 15398
Protoss_Nexus 1 8657
Protoss_Gateway 3 14493
Protoss_Assimilator 2 12861
Protoss_Cybernetics_Core 1 9822
Protoss_Zealot 3 12807
Protoss_Citadel_of_Adun 1 11295
Protoss_Templar_Archives 1 13695
Protoss_High_Templar 2 15746
15746
