Protoss_Gateway 2 5077
Protoss_Zealot 9 11771
Protoss_Nexus 1 11283
Protoss_Assimilator 2 14499
Protoss_Cybernetics_Core 1 10580
Protoss_Forge 1 11385
Protoss_Photon_Cannon 1 12648
Protoss_Citadel_of_Adun 1 13954
Protoss_Dragoon 2 14861
14861
