Protoss_Gateway 2 4829
Protoss_Zealot 12 14966
Protoss_Assimilator 1 7754
Protoss_Cybernetics_Core 1 9631
Protoss_Dragoon 2 12527
Protoss_Citadel_of_Adun 1 11810
Protoss_Forge 1 11600
14966
