Protoss_Gateway 2 5142
Protoss_Zealot 8 10919
Protoss_Assimilator 1 7796
Protoss_Cybernetics_Core 1 9277
Protoss_Stargate 1 11074
Protoss_Dragoon 1 10756
Protoss_Citadel_of_Adun 1 11977
Protoss_Forge 1 12001
Protoss_Templar_Archives 1 13685
Protoss_Nexus 1 15557
Protoss_Photon_Cannon 2 15736
Protoss_Dark_Templar 1 15000
Protoss_High_Templar 1 15051
15736
