Protoss_Nexus 2 17336
Protoss_Forge 1 5669
Protoss_Photon_Cannon 2 7408
Protoss_Gateway 1 7989
Protoss_Assimilator 2 10008
Protoss_Cybernetics_Core 1 9738
Protoss_Robotics_Facility 1 11802
Protoss_Stargate 1 12559
Protoss_Shuttle 1 13204
Protoss_Robotics_Support_Bay 1 12705
Protoss_Dragoon 1 13368
Protoss_Corsair 1 13517
Protoss_Reaver 2 16301
17336
