Protoss_Forge 2 6329
Protoss_Nexus 1 7439
Protoss_Gateway 4 15990
Protoss_Photon_Cannon 5 14900
Protoss_Assimilator 2 10893
Protoss_Zealot 5 15383
Protoss_Cybernetics_Core 1 9530
Protoss_Citadel_of_Adun 1 11348
Protoss_Templar_Archives 1 12983
Protoss_High_Templar 3 15600
Protoss_Dark_Templar 1 14583
Protoss_Robotics_Facility 1 15882
Protoss_Ground_Weapons_1 1 14489
15990
