Protoss_Forge 1 4057
Protoss_Photon_Cannon 4 15601
Protoss_Gateway 2 14789
Protoss_Zealot 4 14783
Protoss_Assimilator 1 8326
Protoss_Cybernetics_Core 1 9582
Protoss_Stargate 1 11491
Protoss_Nexus 1 13047
Protoss_Dragoon 1 11618
Protoss_Corsair 1 12728
Protoss_Citadel_of_Adun 1 13400
Protoss_Templar_Archives 1 14932
15601
