Protoss_Forge 1 4412
Protoss_Nexus 1 7925
Protoss_Photon_Cannon 4 14673
Protoss_Gateway 1 8070
Protoss_Assimilator 2 10294
Protoss_Zealot 5 13764
Protoss_Cybernetics_Core 1 9950
Protoss_Stargate 1 11920
Protoss_Citadel_of_Adun 1 12222
Protoss_Dragoon 1 12022
Protoss_Corsair 2 14102
Protoss_Templar_Archives 1 15555
15555
