Protoss_Forge 1 4183
Protoss_Photon_Cannon 4 12800
Protoss_Nexus 1 8839
Protoss_Gateway 4 14955
Protoss_Assimilator 2 12172
Protoss_Zealot 8 15547
Protoss_Cybernetics_Core 1 11019
Protoss_Citadel_of_Adun 1 12746
Protoss_Dragoon 1 13068
Protoss_Templar_Archives 1 14870
15547
