Protoss_Forge 1 4814
Protoss_Nexus 1 7704
Protoss_Photon_Cannon 4 14505
Protoss_Gateway 2 11696
Protoss_Assimilator 2 10921
Protoss_Zealot 8 15324
Protoss_Cybernetics_Core 1 10360
Protoss_Citadel_of_Adun 1 11985
Protoss_Dragoon 1 11890
Protoss_Stargate 2 14397
Protoss_Corsair 2 15449
Protoss_Ground_Weapons_1 1 14482
15449
