Protoss_Forge 1 4460
Protoss_Photon_Cannon 2 5940
Protoss_Nexus 1 9059
Protoss_Gateway 4 15975
Protoss_Assimilator 2 10799
Protoss_Cybernetics_Core 1 9972
Protoss_Zealot 4 13498
Protoss_Stargate 1 11838
Protoss_Dragoon 1 11640
Protoss_Citadel_of_Adun 1 12194
Protoss_Corsair 3 14547
Protoss_Templar_Archives 1 13717
Protoss_Dark_Templar 2 15029
15975
