Protoss_Forge 1 5067
Protoss_Nexus 1 7846
Protoss_Photon_Cannon 3 9749
Protoss_Gateway 3 14709
Protoss_Zealot 5 13684
Protoss_Assimilator 2 11522
Protoss_Cybernetics_Core 1 10812
Protoss_Citadel_of_Adun 1 13498
14709
