Protoss_Forge 1 4477
Protoss_Photon_Cannon 7 15575
Protoss_Nexus 1 8717
Protoss_Assimilator 2 11335
Protoss_Gateway 3 14809
Protoss_Cybernetics_Core 1 9967
Protoss_Zealot 1 9713
Protoss_Stargate 1 11688
Protoss_Corsair 3 14724
Protoss_Citadel_of_Adun 1 13258
Protoss_Templar_Archives 1 14758
15575
