Protoss_Gateway 3 11767
Protoss_Assimilator 1 4962
Protoss_Zealot 9 14973
Protoss_Cybernetics_Core 1 7113
Protoss_Dragoon 1 8385
Protoss_Stargate 1 9054
Protoss_Citadel_of_Adun 1 9683
Protoss_Corsair 1 10985
Protoss_Templar_Archives 1 14114
14973
