Protoss_Nexus 1 7009
Protoss_Forge 1 5727
Protoss_Gateway 3 14699
Protoss_Assimilator 2 9333
Protoss_Photon_Cannon 8 15784
Protoss_Cybernetics_Core 1 8560
Protoss_Stargate 1 10383
Protoss_Dragoon 1 9982
Protoss_Citadel_of_Adun 1 10665
Protoss_Corsair 2 12634
Protoss_Templar_Archives 1 12422
Protoss_Robotics_Facility 1 14053
Protoss_Dark_Templar 1 13749
Protoss_High_Templar 1 14849
15784
