Protoss_Gateway 1 4138
Protoss_Assimilator 1 4155
Protoss_Zealot 3 8733
Protoss_Cybernetics_Core 1 6595
Protoss_Dragoon 1 7871
Protoss_Stargate 1 8715
Protoss_Citadel_of_Adun 1 9409
Protoss_Corsair 5 14856
Protoss_Templar_Archives 1 10861
Protoss_Forge 1 11076
Protoss_Dark_Templar 1 12885
Protoss_Photon_Cannon 2 14574
Protoss_Nexus 1 15628
Protoss_High_Templar 2 15385
15628
