Protoss_Gateway 4 14292
Protoss_Zealot 16 15485
Protoss_Assimilator 1 7719
Protoss_Cybernetics_Core 1 8758
Protoss_Citadel_of_Adun 1 10349
Protoss_Dragoon 1 10375
Protoss_Templar_Archives 1 13024
Leg_Enhancements 1 13509
Protoss_High_Templar 2 15295
15485
