Protoss_Forge 1 4637
Protoss_Photon_Cannon 8 14930
Protoss_Nexus 1 11718
Protoss_Gateway 2 15627
Protoss_Assimilator 2 13834
Protoss_Zealot 3 15134
Protoss_Cybernetics_Core 1 13291
Protoss_Citadel_of_Adun 1 14885
15627
