Protoss_Gateway 3 15873
Protoss_Zealot 13 14797
Protoss_Forge 2 12179
Protoss_Photon_Cannon 1 9500
Protoss_Nexus 1 12630
Protoss_Assimilator 2 14480
Protoss_Cybernetics_Core 1 14551
15873
