Protoss_Forge 1 4151
Protoss_Nexus 1 8040
Protoss_Gateway 2 13685
Protoss_Photon_Cannon 3 12164
Protoss_Assimilator 2 10697
Protoss_Zealot 4 14892
Protoss_Cybernetics_Core 1 10404
Protoss_Dragoon 1 11649
Protoss_Stargate 2 12965
Protoss_Citadel_of_Adun 1 13524
Protoss_Corsair 5 15293
Protoss_Templar_Archives 1 15102
15293
