Protoss_Nexus 1 7200
Protoss_Forge 1 5873
Protoss_Gateway 4 15017
Protoss_Photon_Cannon 4 12682
Protoss_Assimilator 2 9893
Protoss_Cybernetics_Core 1 9040
Protoss_Zealot 2 11358
Protoss_Stargate 1 10810
Protoss_Dragoon 1 10497
Protoss_Citadel_of_Adun 1 11604
Protoss_Corsair 4 14786
Protoss_Templar_Archives 1 13214
Protoss_Dark_Templar 2 14436
15017
