Protoss_Forge 1 3803
Protoss_Photon_Cannon 3 7759
Protoss_Nexus 1 9211
Protoss_Gateway 3 13243
Protoss_Assimilator 2 14862
Protoss_Zealot 9 15181
Protoss_Cybernetics_Core 1 10142
Protoss_Citadel_of_Adun 1 11922
Protoss_Dragoon 1 11890
Protoss_Templar_Archives 1 15225
15225
