Protoss_Forge 1 4284
Protoss_Photon_Cannon 3 14400
Protoss_Nexus 1 8357
Protoss_Gateway 3 15391
Protoss_Assimilator 2 12814
Protoss_Zealot 6 14563
Protoss_Cybernetics_Core 1 9431
Protoss_Citadel_of_Adun 1 11404
Protoss_Templar_Archives 1 14249
Protoss_High_Templar 2 15683
Leg_Enhancements 1 14387
15683
