Protoss_Forge 1 4628
Protoss_Photon_Cannon 5 15644
Protoss_Nexus 1 8276
Protoss_Gateway 1 7938
Protoss_Assimilator 2 10073
Protoss_Cybernetics_Core 1 9424
Protoss_Zealot 3 15046
Protoss_Stargate 1 11386
Protoss_Corsair 4 15339
Protoss_Robotics_Facility 1 14877
15644
