Protoss_Forge 1 4325
Protoss_Nexus 1 7954
Protoss_Photon_Cannon 5 15674
Protoss_Gateway 3 15735
Protoss_Assimilator 2 12203
Protoss_Zealot 4 15500
Protoss_Cybernetics_Core 1 10757
Protoss_Citadel_of_Adun 1 12479
Protoss_Templar_Archives 1 14568
15735
