Protoss_Forge 1 3870
Protoss_Photon_Cannon 4 13593
Protoss_Nexus 1 9600
Protoss_Gateway 4 15251
Protoss_Assimilator 2 11197
Protoss_Zealot 2 10451
Protoss_Cybernetics_Core 1 10815
Protoss_Citadel_of_Adun 1 12381
Protoss_Templar_Archives 1 14118
Protoss_High_Templar 2 15380
Protoss_Robotics_Facility 1 16207
16207
