Protoss_Forge 1 4567
Protoss_Nexus 1 8105
Protoss_Photon_Cannon 2 14821
Protoss_Gateway 3 12972
Protoss_Assimilator 2 13477
Protoss_Cybernetics_Core 1 9732
Protoss_Zealot 11 15569
Protoss_Citadel_of_Adun 1 12067
Protoss_Templar_Archives 1 14180
Protoss_Robotics_Facility 1 16075
16075
