Protoss_Forge 1 4019
Protoss_Photon_Cannon 4 9901
Protoss_Gateway 1 8159
Protoss_Nexus 1 10617
Protoss_Assimilator 2 11890
Protoss_Zealot 6 14778
Protoss_Cybernetics_Core 1 11077
Protoss_Stargate 1 13096
Protoss_Citadel_of_Adun 2 15116
Protoss_Corsair 2 14932
Protoss_Templar_Archives 1 15797
15797
