Protoss_Gateway 2 5183
Protoss_Zealot 12 13264
Protoss_Assimilator 1 6833
Protoss_Cybernetics_Core 1 8777
Protoss_Citadel_of_Adun 1 10469
Protoss_Templar_Archives 1 12102
Protoss_High_Templar 2 14384
14384
