Protoss_Gateway 3 15356
Protoss_Zealot 11 13188
Protoss_Forge 1 9478
Protoss_Photon_Cannon 1 10784
Protoss_Nexus 2 16076
Protoss_Assimilator 2 15334
Protoss_Cybernetics_Core 1 14039
16076
