Protoss_Forge 1 4403
Protoss_Photon_Cannon 5 15772
Protoss_Nexus 1 8512
Protoss_Gateway 2 13347
Protoss_Assimilator 2 10368
Protoss_Zealot 6 15024
Protoss_Cybernetics_Core 1 9334
Protoss_Dragoon 1 11136
Protoss_Citadel_of_Adun 2 12504
Protoss_Stargate 1 14144
Protoss_Templar_Archives 1 14080
Protoss_Corsair 1 15112
Protoss_High_Templar 2 15402
15772
