Protoss_Nexus 2 17305
Protoss_Forge 1 5914
Protoss_Photon_Cannon 1 7349
Protoss_Gateway 4 12475
Protoss_Assimilator 2 12166
Protoss_Zealot 12 14815
Protoss_Cybernetics_Core 1 10695
Protoss_Citadel_of_Adun 1 12160
Protoss_Templar_Archives 1 15106
17305
