Protoss_Gateway 2 5090
Protoss_Zealot 5 9010
Protoss_Assimilator 1 6228
Protoss_Cybernetics_Core 1 8219
Protoss_Forge 1 8717
Protoss_Nexus 1 14554
Protoss_Photon_Cannon 3 15170
15170
