Protoss_Forge 1 4242
Protoss_Photon_Cannon 5 15412
Protoss_Nexus 1 9827
Protoss_Gateway 4 12797
Protoss_Assimilator 2 13425
Protoss_Cybernetics_Core 1 10755
Protoss_Zealot 10 14797
Protoss_Citadel_of_Adun 1 12345
Protoss_Dragoon 1 14451
Protoss_Templar_Archives 1 14895
15412
