Protoss_Forge 1 4458
Protoss_Photon_Cannon 4 15014
Protoss_Nexus 2 14854
Protoss_Gateway 1 8641
Protoss_Assimilator 2 10555
Protoss_Cybernetics_Core 1 10269
Protoss_Zealot 1 10100
Protoss_Stargate 1 12091
Protoss_Robotics_Facility 1 13119
Protoss_Corsair 1 13275
Protoss_Robotics_Support_Bay 1 13831
Protoss_Reaver 1 15615
15615
