Protoss_Gateway 2 5174
Protoss_Zealot 4 10049
Protoss_Assimilator 1 6162
Protoss_Forge 1 6924
Protoss_Cybernetics_Core 1 8945
Protoss_Citadel_of_Adun 1 10495
Protoss_Ground_Weapons_1 1 13121
Protoss_Photon_Cannon 1 14630
14630
