Protoss_Forge 2 14998
Protoss_Nexus 1 7713
Protoss_Photon_Cannon 2 14193
Protoss_Gateway 4 12746
Protoss_Assimilator 2 9949
Protoss_Zealot 13 14595
Protoss_Cybernetics_Core 1 9105
Protoss_Citadel_of_Adun 1 10843
Leg_Enhancements 1 13801
Protoss_Templar_Archives 1 15292
Protoss_Ground_Weapons_1 1 14475
15292
