Protoss_Forge 2 12353
Protoss_Nexus 1 7399
Protoss_Photon_Cannon 2 8654
Protoss_Gateway 4 15608
Protoss_Assimilator 2 12185
Protoss_Zealot 5 15558
Protoss_Cybernetics_Core 1 10818
Protoss_Citadel_of_Adun 1 12532
Protoss_Dragoon 1 14466
15608
