Protoss_Gateway 2 5039
Protoss_Zealot 8 8955
Protoss_Assimilator 1 8323
Protoss_Cybernetics_Core 1 11120
Protoss_Dragoon 3 15253
Protoss_Stargate 1 14067
Protoss_Forge 1 14003
Protoss_Photon_Cannon 1 15329
15329
