Protoss_Forge 1 4217
Protoss_Photon_Cannon 6 15686
Protoss_Nexus 1 8753
Protoss_Gateway 1 7755
Protoss_Assimilator 2 11639
Protoss_Cybernetics_Core 1 9223
Protoss_Zealot 3 11092
Protoss_Stargate 2 14410
Protoss_Corsair 4 15353
Protoss_Robotics_Facility 1 13939
15686
