Protoss_Forge 1 5372
Protoss_Nexus 1 7521
Protoss_Photon_Cannon 2 7962
Protoss_Gateway 2 13935
Protoss_Assimilator 2 9428
Protoss_Zealot 4 15026
Protoss_Cybernetics_Core 1 10836
Protoss_Citadel_of_Adun 1 12664
Protoss_Templar_Archives 1 14660
15026
