Protoss_Gateway 2 13921
Protoss_Zealot 4 8294
Protoss_Assimilator 1 5607
Protoss_Cybernetics_Core 1 7166
Protoss_Stargate 1 9173
Protoss_Dragoon 1 9414
Protoss_Citadel_of_Adun 1 10310
Protoss_Forge 1 10106
Protoss_Corsair 1 10416
Protoss_Templar_Archives 1 11759
Protoss_Photon_Cannon 5 15560
Protoss_Dark_Templar 1 13236
Protoss_Nexus 1 16354
16354
