Protoss_Forge 2 6394
Protoss_Nexus 1 7325
Protoss_Gateway 4 14399
Protoss_Photon_Cannon 2 8082
Protoss_Zealot 3 10085
Protoss_Assimilator 2 10457
Protoss_Cybernetics_Core 1 10425
Protoss_Dragoon 8 14972
Protoss_Robotics_Facility 1 14700
Protoss_Citadel_of_Adun 1 14546
14972
