Protoss_Forge 1 4668
Protoss_Nexus 1 7720
Protoss_Photon_Cannon 2 12626
Protoss_Gateway 4 15871
Protoss_Assimilator 2 11092
Protoss_Zealot 4 12825
Protoss_Cybernetics_Core 1 9861
Protoss_Dragoon 2 12149
Protoss_Stargate 1 11915
Protoss_Citadel_of_Adun 1 13340
15871
