Protoss_Gateway 2 4965
Protoss_Zealot 9 11527
Protoss_Assimilator 1 8560
Protoss_Cybernetics_Core 1 10035
Protoss_Citadel_of_Adun 1 12209
Protoss_Forge 1 12858
Protoss_Templar_Archives 1 13733
13733
