Protoss_Forge 1 4350
Protoss_Nexus 1 7881
Protoss_Photon_Cannon 2 14262
Protoss_Gateway 4 13581
Protoss_Assimilator 2 11739
Protoss_Zealot 15 15539
Protoss_Cybernetics_Core 1 10771
Protoss_Citadel_of_Adun 1 12409
Protoss_Templar_Archives 1 14677
Protoss_Ground_Weapons_1 1 14628
15539
