Protoss_Forge 1 4347
Protoss_Nexus 1 7732
Protoss_Gateway 4 14285
Protoss_Assimilator 2 10407
Protoss_Zealot 9 15526
Protoss_Cybernetics_Core 1 8873
Protoss_Photon_Cannon 1 9434
Protoss_Stargate 1 10841
Protoss_Citadel_of_Adun 1 11538
Protoss_Corsair 2 12801
Protoss_Robotics_Facility 1 16498
16498
