Protoss_Forge 2 14585
Protoss_Nexus 1 7691
Protoss_Photon_Cannon 4 14660
Protoss_Gateway 3 15674
Protoss_Assimilator 2 10117
Protoss_Zealot 3 12371
Protoss_Cybernetics_Core 1 9999
Protoss_Stargate 1 11687
Protoss_Citadel_of_Adun 1 12213
Protoss_Corsair 3 15260
Protoss_Templar_Archives 1 13761
Protoss_Dark_Templar 2 15142
15674
