Protoss_Gateway 1 4264
Protoss_Assimilator 1 4742
Protoss_Zealot 5 15187
Protoss_Cybernetics_Core 1 7319
Protoss_Stargate 1 9057
Protoss_Dragoon 1 8928
Protoss_Citadel_of_Adun 1 9833
Protoss_Forge 1 10220
Protoss_Templar_Archives 1 11424
Protoss_Photon_Cannon 8 15253
Protoss_High_Templar 2 14305
15253
