Protoss_Gateway 2 4744
Protoss_Zealot 7 11314
Protoss_Nexus 1 12044
Protoss_Assimilator 2 14648
Protoss_Forge 1 11808
Protoss_Cybernetics_Core 1 12972
Protoss_Photon_Cannon 4 15673
Protoss_Stargate 1 14725
15673
