Protoss_Forge 2 15392
Protoss_Nexus 1 7875
Protoss_Photon_Cannon 2 7033
Protoss_Gateway 4 13249
Protoss_Assimilator 2 10521
Protoss_Zealot 11 15471
Protoss_Cybernetics_Core 1 10395
Protoss_Citadel_of_Adun 1 12061
Protoss_Templar_Archives 1 15804
15804
