Protoss_Forge 1 3848
Protoss_Photon_Cannon 3 14597
Protoss_Nexus 1 8847
Protoss_Gateway 1 7831
Protoss_Assimilator 2 12348
Protoss_Cybernetics_Core 1 9324
Protoss_Zealot 4 14876
Protoss_Stargate 1 11266
Protoss_Dragoon 1 11252
Protoss_Citadel_of_Adun 1 12643
Protoss_Corsair 4 15456
Protoss_Templar_Archives 1 14281
15456
