Protoss_Forge 1 4012
Protoss_Nexus 1 7773
Protoss_Gateway 3 15536
Protoss_Photon_Cannon 12 15654
Protoss_Assimilator 2 9545
Protoss_Zealot 1 8502
Protoss_Cybernetics_Core 1 9422
Protoss_Citadel_of_Adun 1 10909
Protoss_Templar_Archives 1 12468
Protoss_Dark_Templar 1 13693
Protoss_High_Templar 2 14808
15654
