Protoss_Nexus 1 7257
Protoss_Forge 2 13785
Protoss_Photon_Cannon 4 15573
Protoss_Gateway 3 13455
Protoss_Assimilator 2 11882
Protoss_Zealot 5 13649
Protoss_Cybernetics_Core 1 12029
Protoss_Citadel_of_Adun 1 13615
Protoss_Dragoon 1 13744
15573
