Protoss_Forge 1 4157
Protoss_Photon_Cannon 4 10051
Protoss_Nexus 1 9570
Protoss_Gateway 2 15901
Protoss_Zealot 6 15320
Protoss_Assimilator 2 12855
Protoss_Cybernetics_Core 1 12185
Protoss_Stargate 1 14125
Protoss_Citadel_of_Adun 1 14674
Protoss_Corsair 1 15090
15901
