Protoss_Forge 1 5190
Protoss_Nexus 1 7790
Protoss_Photon_Cannon 4 15054
Protoss_Gateway 4 12623
Protoss_Assimilator 2 10551
Protoss_Cybernetics_Core 1 9904
Protoss_Zealot 2 10685
Protoss_Citadel_of_Adun 1 11569
Protoss_Templar_Archives 1 13070
Protoss_Dragoon 1 13746
Protoss_High_Templar 5 15429
15429
