Protoss_Gateway 2 4994
Protoss_Zealot 9 14549
Protoss_Assimilator 1 7556
Protoss_Cybernetics_Core 2 10628
Protoss_Stargate 1 11187
Protoss_Dragoon 1 10795
Protoss_Citadel_of_Adun 1 11639
Protoss_Forge 1 12020
Protoss_Corsair 1 12447
Protoss_Templar_Archives 1 13466
Protoss_Photon_Cannon 2 15686
Protoss_Dark_Templar 1 14676
15686
