Protoss_Forge 1 4322
Protoss_Photon_Cannon 6 14900
Protoss_Nexus 1 8741
Protoss_Gateway 2 14118
Protoss_Assimilator 2 11871
Protoss_Zealot 2 9591
Protoss_Cybernetics_Core 1 9860
Protoss_Stargate 1 11582
Protoss_Citadel_of_Adun 1 12030
Protoss_Corsair 1 12532
Protoss_Templar_Archives 1 13908
Protoss_Dark_Templar 1 15156
15156
