Protoss_Gateway 2 12987
Protoss_Assimilator 2 13871
Protoss_Zealot 6 13758
Protoss_Cybernetics_Core 1 6760
Protoss_Stargate 1 8438
Protoss_Dragoon 1 7997
Protoss_Citadel_of_Adun 1 8889
Protoss_Forge 1 8850
Protoss_Corsair 2 10975
Protoss_Templar_Archives 1 10474
Protoss_Photon_Cannon 3 14284
Protoss_Dark_Templar 1 11694
Protoss_High_Templar 1 14466
Protoss_Nexus 1 16957
16957
