Protoss_Forge 2 13733
Protoss_Photon_Cannon 5 8798
Protoss_Nexus 1 8958
Protoss_Gateway 3 15213
Protoss_Assimilator 2 15157
Protoss_Zealot 4 15368
Protoss_Cybernetics_Core 1 13312
Protoss_Citadel_of_Adun 1 14787
15368
