Protoss_Gateway 3 13572
Protoss_Zealot 12 13539
Protoss_Assimilator 1 6349
Protoss_Cybernetics_Core 1 8215
Protoss_Citadel_of_Adun 1 9728
Protoss_Dragoon 1 9731
Protoss_Templar_Archives 1 13047
Leg_Enhancements 1 12821
Protoss_High_Templar 2 15066
Protoss_Dark_Templar 1 15497
15497
