Protoss_Forge 2 13928
Protoss_Nexus 1 8001
Protoss_Photon_Cannon 9 15816
Protoss_Gateway 4 15459
Protoss_Assimilator 2 12157
Protoss_Zealot 2 11013
Protoss_Cybernetics_Core 1 10723
Protoss_Citadel_of_Adun 1 12396
Protoss_Dragoon 1 12193
Protoss_Templar_Archives 1 14115
Protoss_High_Templar 1 15718
15816
