Protoss_Forge 1 4286
Protoss_Nexus 1 7720
Protoss_Photon_Cannon 4 14685
Protoss_Gateway 4 15819
Protoss_Assimilator 2 10912
Protoss_Cybernetics_Core 1 9487
Protoss_Zealot 4 14600
Protoss_Stargate 1 11391
Protoss_Citadel_of_Adun 1 11758
Protoss_Corsair 2 13510
Protoss_Templar_Archives 1 15192
15819
