Protoss_Gateway 3 13012
Protoss_Assimilator 2 7280
Protoss_Cybernetics_Core 1 6067
Protoss_Zealot 3 10173
Protoss_Stargate 1 7884
Protoss_Dragoon 6 15092
Protoss_Corsair 1 8835
15092
