Protoss_Assimilator 1 2689
Protoss_Gateway 1 4422
Protoss_Cybernetics_Core 1 6087
Protoss_Stargate 2 8301
Protoss_Corsair 9 15116
Protoss_Forge 1 11244
Protoss_Photon_Cannon 2 13235
Protoss_Air_Weapons_1 1 13289
15116
