Protoss_Forge 1 4044
Protoss_Nexus 1 7986
Protoss_Gateway 5 15129
Protoss_Photon_Cannon 1 7661
Protoss_Assimilator 2 10773
Protoss_Zealot 11 15564
Protoss_Cybernetics_Core 1 9236
Protoss_Dragoon 1 10435
Protoss_Stargate 1 11273
Protoss_Corsair 1 12216
Protoss_Citadel_of_Adun 1 13507
Protoss_Templar_Archives 1 16008
16008
