Protoss_Forge 1 4224
Protoss_Photon_Cannon 3 15822
Protoss_Nexus 1 12221
Protoss_Gateway 1 11800
Protoss_Assimilator 2 14060
Protoss_Cybernetics_Core 1 13243
Protoss_Zealot 2 13943
Protoss_Stargate 1 15122
Protoss_Dragoon 1 14668
15822
