Protoss_Forge 1 4167
Protoss_Nexus 1 7878
Protoss_Photon_Cannon 7 15013
Protoss_Gateway 1 7846
Protoss_Assimilator 2 13395
Protoss_Cybernetics_Core 1 9348
Protoss_Stargate 1 11047
Protoss_Robotics_Facility 1 12690
Protoss_Corsair 3 14944
Protoss_Shuttle 1 14238
Protoss_Robotics_Support_Bay 1 13956
Protoss_Reaver 1 16133
16133
