Protoss_Forge 1 3649
Protoss_Nexus 1 7269
Protoss_Photon_Cannon 2 6496
Protoss_Gateway 4 12949
Protoss_Assimilator 2 13110
Protoss_Zealot 13 15381
Protoss_Cybernetics_Core 1 10005
Protoss_Citadel_of_Adun 1 11613
Protoss_Templar_Archives 1 14205
Leg_Enhancements 1 14580
15381
