Protoss_Forge 1 4381
Protoss_Photon_Cannon 2 5880
Protoss_Nexus 1 9216
Protoss_Gateway 6 15134
Protoss_Assimilator 2 9792
Protoss_Cybernetics_Core 1 9807
Protoss_Zealot 3 12874
Protoss_Citadel_of_Adun 1 11357
Protoss_Dragoon 1 11510
Protoss_Templar_Archives 1 12857
Protoss_Dark_Templar 2 14425
Protoss_High_Templar 2 15789
15789
