Protoss_Nexus 1 7132
Protoss_Forge 1 5774
Protoss_Photon_Cannon 3 8545
Protoss_Gateway 1 8701
Protoss_Assimilator 2 13179
Protoss_Zealot 5 15269
Protoss_Cybernetics_Core 1 12541
Protoss_Stargate 2 16240
Protoss_Citadel_of_Adun 1 15094
16240
