Protoss_Gateway 3 14459
Protoss_Zealot 12 15220
Protoss_Assimilator 1 6128
Protoss_Cybernetics_Core 1 7732
Protoss_Dragoon 1 9183
Protoss_Stargate 1 9982
Protoss_Forge 1 9648
Protoss_Corsair 1 11102
Protoss_Citadel_of_Adun 1 12355
Protoss_Templar_Archives 1 15226
15226
