Protoss_Gateway 1 4202
Protoss_Zealot 11 15280
Protoss_Nexus 1 9286
Protoss_Assimilator 2 13618
Protoss_Forge 2 9296
Protoss_Cybernetics_Core 1 11963
Protoss_Photon_Cannon 2 12664
Protoss_Stargate 1 13780
Protoss_Dragoon 1 13538
Protoss_Citadel_of_Adun 1 14914
Protoss_Corsair 1 14827
15280
