Protoss_Nexus 1 6766
Protoss_Forge 1 5532
Protoss_Gateway 1 7255
Protoss_Photon_Cannon 2 14600
Protoss_Assimilator 2 10116
Protoss_Zealot 8 14753
Protoss_Cybernetics_Core 1 9655
Protoss_Stargate 1 11741
Protoss_Robotics_Facility 1 12785
Protoss_Corsair 4 15409
Protoss_Shuttle 1 14206
Protoss_Robotics_Support_Bay 1 13708
Protoss_Reaver 1 15764
15764
