Protoss_Gateway 2 13107
Protoss_Assimilator 1 4480
Protoss_Zealot 7 14600
Protoss_Forge 1 6525
Protoss_Cybernetics_Core 1 9118
Protoss_Stargate 1 10832
Protoss_Dragoon 1 10500
Protoss_Citadel_of_Adun 1 11383
Protoss_Corsair 1 11790
Protoss_Templar_Archives 1 13796
Protoss_Photon_Cannon 2 14469
Protoss_Ground_Weapons_1 1 12916
Protoss_Robotics_Facility 1 16002
Protoss_High_Templar 1 15329
Leg_Enhancements 1 14336
16002
