Protoss_Gateway 1 3637
Protoss_Zealot 5 9839
Protoss_Assimilator 1 5879
Protoss_Cybernetics_Core 1 8541
Protoss_Stargate 1 10412
Protoss_Dragoon 1 11428
Protoss_Corsair 4 15102
Protoss_Citadel_of_Adun 1 13129
Protoss_Templar_Archives 1 14629
Protoss_Forge 1 14177
Protoss_Photon_Cannon 1 15809
15809
