Protoss_Forge 1 4496
Protoss_Nexus 1 7680
Protoss_Gateway 1 6811
Protoss_Photon_Cannon 3 12920
Protoss_Assimilator 2 10502
Protoss_Cybernetics_Core 1 8821
Protoss_Zealot 1 8742
Protoss_Stargate 2 15350
Protoss_Robotics_Facility 1 12711
Protoss_Corsair 4 15067
Protoss_Shuttle 1 14197
Protoss_Robotics_Support_Bay 1 14198
Protoss_Reaver 1 16235
16235
