Protoss_Forge 1 5294
Protoss_Nexus 1 7875
Protoss_Photon_Cannon 4 15028
Protoss_Gateway 1 7631
Protoss_Assimilator 2 12175
Protoss_Zealot 7 14436
Protoss_Cybernetics_Core 1 9146
Protoss_Stargate 1 11421
Protoss_Citadel_of_Adun 1 12324
Protoss_Corsair 3 15514
Protoss_Templar_Archives 1 14319
15514
