Protoss_Gateway 2 5121
Protoss_Zealot 10 13553
Protoss_Forge 1 8487
Protoss_Photon_Cannon 4 15434
Protoss_Assimilator 1 9665
Protoss_Cybernetics_Core 1 10689
Protoss_Citadel_of_Adun 1 12618
Protoss_Stargate 2 15173
Protoss_Corsair 1 14834
15434
