Protoss_Forge 2 9702
Protoss_Photon_Cannon 8 15759
Protoss_Nexus 1 8554
Protoss_Assimilator 2 11912
Protoss_Gateway 2 12381
Protoss_Zealot 6 15229
Protoss_Cybernetics_Core 1 11095
Protoss_Citadel_of_Adun 1 12918
Protoss_Dragoon 1 12849
Protoss_Templar_Archives 1 14875
15759
