Protoss_Forge 1 3996
Protoss_Photon_Cannon 5 15412
Protoss_Nexus 1 8440
Protoss_Gateway 3 11930
Protoss_Assimilator 2 13132
Protoss_Cybernetics_Core 1 9836
Protoss_Zealot 9 13883
Protoss_Citadel_of_Adun 1 11568
Protoss_Templar_Archives 1 13829
Protoss_High_Templar 2 15117
Protoss_Dark_Templar 1 15278
15412
