Protoss_Forge 1 4196
Protoss_Photon_Cannon 3 15091
Protoss_Nexus 1 8993
Protoss_Gateway 4 15658
Protoss_Assimilator 2 13242
Protoss_Cybernetics_Core 1 9431
Protoss_Zealot 10 14622
Protoss_Citadel_of_Adun 1 11057
Protoss_Templar_Archives 1 14767
Leg_Enhancements 1 14226
15658
