Protoss_Forge 1 3929
Protoss_Nexus 2 14737
Protoss_Photon_Cannon 3 14536
Protoss_Assimilator 2 9607
Protoss_Gateway 1 8319
Protoss_Cybernetics_Core 1 9890
Protoss_Zealot 1 9888
Protoss_Robotics_Facility 1 12003
Protoss_Stargate 1 12448
Protoss_Shuttle 1 13635
Protoss_Corsair 2 14849
Protoss_Robotics_Support_Bay 1 13421
14849
