Protoss_Forge 1 4294
Protoss_Nexus 1 8081
Protoss_Photon_Cannon 1 7112
Protoss_Gateway 1 8101
Protoss_Assimilator 2 9588
Protoss_Zealot 2 10385
Protoss_Cybernetics_Core 1 9681
Protoss_Robotics_Facility 1 12556
12556
