Protoss_Gateway 3 14080
Protoss_Zealot 13 15522
Protoss_Nexus 1 9461
Protoss_Forge 1 8612
Protoss_Photon_Cannon 2 10536
Protoss_Assimilator 1 13044
Protoss_Cybernetics_Core 1 14862
15522
