Protoss_Nexus 1 7058
Protoss_Forge 1 5882
Protoss_Photon_Cannon 4 15470
Protoss_Gateway 4 14288
Protoss_Assimilator 2 13472
Protoss_Zealot 9 15321
Protoss_Cybernetics_Core 1 10047
Protoss_Citadel_of_Adun 1 11825
Protoss_Templar_Archives 1 13546
15470
