Protoss_Forge 1 4215
Protoss_Photon_Cannon 8 15576
Protoss_Nexus 1 8359
Protoss_Gateway 1 8499
Protoss_Assimilator 2 11601
Protoss_Zealot 5 13079
Protoss_Cybernetics_Core 1 10265
Protoss_Citadel_of_Adun 1 12280
Protoss_Templar_Archives 1 13850
Protoss_High_Templar 1 15063
15576
