Protoss_Gateway 1 4079
Protoss_Zealot 9 14739
Protoss_Forge 1 6441
Protoss_Photon_Cannon 3 14065
Protoss_Nexus 1 13620
Protoss_Assimilator 1 12116
Protoss_Cybernetics_Core 1 13949
Protoss_Dragoon 1 15288
15288
