Protoss_Nexus 1 6886
Protoss_Gateway 2 6593
Protoss_Zealot 14 15558
Protoss_Forge 1 8537
Protoss_Assimilator 2 12449
Protoss_Photon_Cannon 3 12932
Protoss_Cybernetics_Core 1 11647
Protoss_Stargate 1 13913
Protoss_Citadel_of_Adun 1 14696
Protoss_Corsair 1 14920
15558
