Protoss_Forge 1 4082
Protoss_Photon_Cannon 3 15758
Protoss_Nexus 1 9050
Protoss_Gateway 4 13010
Protoss_Assimilator 2 14339
Protoss_Cybernetics_Core 1 9548
Protoss_Zealot 10 14951
Protoss_Citadel_of_Adun 1 11891
Protoss_Templar_Archives 1 15314
15758
