Protoss_Forge 1 3958
Protoss_Photon_Cannon 1 6194
Protoss_Gateway 1 6828
Protoss_Zealot 9 15037
Protoss_Assimilator 1 8224
Protoss_Cybernetics_Core 1 11484
Protoss_Stargate 1 13657
Protoss_Citadel_of_Adun 1 14680
Protoss_Corsair 1 14619
15037
