Protoss_Forge 1 4106
Protoss_Nexus 1 7732
Protoss_Gateway 3 13760
Protoss_Assimilator 2 11287
Protoss_Zealot 10 14812
Protoss_Cybernetics_Core 1 8464
Protoss_Photon_Cannon 1 8697
Protoss_Stargate 1 10360
Protoss_Corsair 2 12392
Protoss_Citadel_of_Adun 1 12380
Protoss_Robotics_Facility 1 15532
Protoss_Templar_Archives 1 15770
15770
