Protoss_Forge 1 3989
Protoss_Photon_Cannon 4 15208
Protoss_Nexus 1 8532
Protoss_Gateway 4 13752
Protoss_Assimilator 2 11336
Protoss_Zealot 7 15288
Protoss_Cybernetics_Core 1 10422
Protoss_Stargate 1 12918
Protoss_Dragoon 1 12673
Protoss_Corsair 1 13868
Protoss_Citadel_of_Adun 1 15863
15863
