Protoss_Forge 1 4502
Protoss_Photon_Cannon 2 6026
Protoss_Nexus 1 8659
Protoss_Gateway 3 14054
Protoss_Assimilator 2 11361
Protoss_Zealot 5 13870
Protoss_Cybernetics_Core 1 10103
Protoss_Stargate 1 11808
Protoss_Citadel_of_Adun 1 12390
Protoss_Corsair 2 14481
Protoss_Templar_Archives 1 13861
Protoss_Dark_Templar 3 15396
15396
