Protoss_Forge 1 4916
Protoss_Nexus 1 7577
Protoss_Photon_Cannon 7 15808
Protoss_Gateway 2 14016
Protoss_Zealot 6 12471
Protoss_Assimilator 2 11126
Protoss_Cybernetics_Core 1 10445
Protoss_Stargate 1 12152
Protoss_Citadel_of_Adun 1 12737
Protoss_Corsair 3 15231
Protoss_Templar_Archives 1 14805
15808
