Protoss_Gateway 2 9994
Protoss_Assimilator 1 4710
Protoss_Zealot 7 15111
Protoss_Cybernetics_Core 1 7183
Protoss_Dragoon 1 8451
Protoss_Citadel_of_Adun 1 9007
Protoss_Templar_Archives 1 11913
Protoss_High_Templar 3 14249
Protoss_Forge 1 13038
Protoss_Archon 1 13609
Leg_Enhancements 1 13835
Protoss_Nexus 1 17368
17368
