Protoss_Gateway 1 4119
Protoss_Assimilator 1 4735
Protoss_Zealot 3 7290
Protoss_Cybernetics_Core 1 7353
Protoss_Stargate 1 9125
Protoss_Dragoon 1 9088
Protoss_Citadel_of_Adun 1 9873
Protoss_Corsair 1 10092
Protoss_Templar_Archives 1 11333
Protoss_Forge 1 11083
Protoss_Dark_Templar 1 12549
Protoss_Photon_Cannon 3 15749
Protoss_Nexus 1 15756
Protoss_High_Templar 2 15410
15756
