Protoss_Gateway 2 5134
Protoss_Zealot 10 12152
Protoss_Assimilator 1 7703
Protoss_Cybernetics_Core 1 10141
Protoss_Forge 1 10911
Protoss_Photon_Cannon 1 13299
Protoss_Citadel_of_Adun 1 14614
14614
