Protoss_Forge 1 4524
Protoss_Photon_Cannon 4 15633
Protoss_Nexus 1 9646
Protoss_Gateway 3 13397
Protoss_Assimilator 2 11162
Protoss_Cybernetics_Core 1 10433
Protoss_Zealot 3 14995
Protoss_Citadel_of_Adun 1 11933
Protoss_Stargate 1 13259
Protoss_Dragoon 1 12914
Protoss_Templar_Archives 1 13909
Protoss_Corsair 2 15144
Protoss_High_Templar 2 15556
15633
