Protoss_Forge 1 4296
Protoss_Photon_Cannon 5 15244
Protoss_Nexus 1 8800
Protoss_Gateway 5 16019
Protoss_Assimilator 2 10767
Protoss_Cybernetics_Core 1 9248
Protoss_Zealot 2 9848
Protoss_Citadel_of_Adun 1 10925
Protoss_Templar_Archives 1 12602
Protoss_Dark_Templar 2 13945
Protoss_High_Templar 2 15045
16019
