Protoss_Nexus 1 7540
Protoss_Forge 1 6159
Protoss_Gateway 4 14767
Protoss_Photon_Cannon 2 15712
Protoss_Assimilator 2 9788
Protoss_Zealot 7 14761
Protoss_Cybernetics_Core 1 9489
Protoss_Stargate 1 11227
Protoss_Citadel_of_Adun 1 11423
Protoss_Dragoon 1 12424
Protoss_Corsair 2 14256
Protoss_Templar_Archives 1 15277
Protoss_Robotics_Facility 1 16207
16207
