Protoss_Forge 1 4097
Protoss_Nexus 1 7991
Protoss_Gateway 4 13094
Protoss_Photon_Cannon 1 7261
Protoss_Assimilator 2 11257
Protoss_Zealot 8 14988
Protoss_Cybernetics_Core 1 9168
Protoss_Citadel_of_Adun 1 11152
Protoss_Dragoon 1 12105
Protoss_Templar_Archives 1 13609
Protoss_High_Templar 2 15124
Leg_Enhancements 1 14255
15124
