Protoss_Nexus 1 7370
Protoss_Forge 1 5954
Protoss_Photon_Cannon 2 12391
Protoss_Gateway 5 15949
Protoss_Assimilator 1 8001
Protoss_Zealot 5 15214
Protoss_Cybernetics_Core 1 11183
Protoss_Citadel_of_Adun 1 12959
Protoss_Robotics_Facility 1 15270
15949
