Protoss_Forge 1 4616
Protoss_Nexus 1 8490
Protoss_Assimilator 2 11209
Protoss_Gateway 2 8560
Protoss_Photon_Cannon 2 12496
Protoss_Cybernetics_Core 1 10155
Protoss_Zealot 5 13791
Protoss_Dragoon 2 11612
Protoss_Citadel_of_Adun 1 12263
Protoss_Robotics_Facility 1 14176
Protoss_Templar_Archives 1 13925
Protoss_Dark_Templar 2 15183
Protoss_Shuttle 1 15596
Protoss_Ground_Weapons_1 1 14380
15596
