Protoss_Forge 1 4486
Protoss_Nexus 1 7988
Protoss_Gateway 6 15356
Protoss_Assimilator 2 11074
Protoss_Photon_Cannon 2 9957
Protoss_Cybernetics_Core 1 9102
Protoss_Zealot 5 13837
Protoss_Citadel_of_Adun 1 11361
Protoss_Templar_Archives 1 13286
Protoss_Robotics_Facility 1 16096
Leg_Enhancements 1 14302
16096
