Protoss_Nexus 1 7471
Protoss_Gateway 2 13101
Protoss_Assimilator 2 9365
Protoss_Cybernetics_Core 1 8789
Protoss_Zealot 2 13635
Protoss_Stargate 1 10497
Protoss_Dragoon 1 10892
Protoss_Citadel_of_Adun 1 11393
Protoss_Corsair 4 14786
Protoss_Templar_Archives 1 12847
Protoss_Forge 1 13230
Protoss_Dark_Templar 2 14439
Protoss_Photon_Cannon 2 15815
15815
