Protoss_Forge 1 4252
Protoss_Photon_Cannon 2 7214
Protoss_Nexus 1 8383
Protoss_Gateway 4 15945
Protoss_Assimilator 1 8143
Protoss_Cybernetics_Core 1 9937
Protoss_Zealot 14 15522
Protoss_Citadel_of_Adun 1 11509
Protoss_Templar_Archives 1 14600
Leg_Enhancements 1 14460
15945
