Protoss_Forge 1 4005
Protoss_Photon_Cannon 5 15664
Protoss_Nexus 1 8695
Protoss_Gateway 3 13597
Protoss_Assimilator 1 7413
Protoss_Zealot 7 14654
Protoss_Cybernetics_Core 1 10707
Protoss_Citadel_of_Adun 1 12662
Protoss_Dragoon 1 13778
Protoss_Templar_Archives 1 15708
15708
