Protoss_Nexus 1 7170
Protoss_Forge 1 5575
Protoss_Photon_Cannon 2 7222
Protoss_Gateway 6 15438
Protoss_Assimilator 2 12111
Protoss_Zealot 6 15544
Protoss_Cybernetics_Core 1 9965
Protoss_Dragoon 1 11761
Protoss_Stargate 1 12486
Protoss_Citadel_of_Adun 1 13290
Protoss_Corsair 1 13442
15544
