Protoss_Forge 1 3785
Protoss_Photon_Cannon 3 13811
Protoss_Nexus 1 8913
Protoss_Gateway 2 12779
Protoss_Cybernetics_Core 1 9431
Protoss_Assimilator 2 11860
Protoss_Zealot 8 14759
Protoss_Stargate 1 12106
Protoss_Citadel_of_Adun 1 13278
Protoss_Corsair 1 13429
Protoss_Templar_Archives 1 15621
15621
