Protoss_Forge 1 3836
Protoss_Photon_Cannon 6 15607
Protoss_Gateway 1 8007
Protoss_Nexus 1 10029
Protoss_Assimilator 2 11241
Protoss_Cybernetics_Core 1 11607
Protoss_Zealot 2 14733
Protoss_Stargate 1 13537
Protoss_Dragoon 1 13374
Protoss_Citadel_of_Adun 1 14107
Protoss_Corsair 1 14701
Protoss_Templar_Archives 1 15639
15639
