Protoss_Forge 1 4151
Protoss_Photon_Cannon 3 11493
Protoss_Gateway 2 15999
Protoss_Nexus 1 8815
Protoss_Assimilator 2 13902
Protoss_Zealot 5 14780
Protoss_Cybernetics_Core 1 10283
Protoss_Stargate 1 13426
Protoss_Dragoon 1 13213
Protoss_Citadel_of_Adun 1 14099
Protoss_Corsair 1 14797
Protoss_Templar_Archives 1 15703
15999
