Protoss_Forge 1 4150
Protoss_Photon_Cannon 2 6451
Protoss_Nexus 1 9756
Protoss_Gateway 4 15920
Protoss_Assimilator 2 14737
Protoss_Cybernetics_Core 1 10207
Protoss_Dragoon 1 11422
Protoss_Zealot 10 15396
Protoss_Citadel_of_Adun 1 12197
Protoss_Templar_Archives 1 14658
15920
