Protoss_Forge 1 4625
Protoss_Nexus 1 7980
Protoss_Gateway 4 14491
Protoss_Assimilator 2 10793
Protoss_Photon_Cannon 2 8387
Protoss_Cybernetics_Core 1 9432
Protoss_Zealot 4 14347
Protoss_Stargate 1 11122
Protoss_Citadel_of_Adun 1 12064
Protoss_Dragoon 1 12306
Protoss_Corsair 1 12248
Protoss_Templar_Archives 1 13969
Protoss_Robotics_Facility 1 15657
Protoss_Dark_Templar 1 15467
Protoss_High_Templar 3 15771
15771
