Protoss_Forge 1 4423
Protoss_Nexus 1 7802
Protoss_Photon_Cannon 3 12569
Protoss_Gateway 4 14450
Protoss_Assimilator 2 10347
Protoss_Cybernetics_Core 1 9599
Protoss_Zealot 1 9526
Protoss_Dragoon 1 10801
Protoss_Stargate 1 11640
Protoss_Citadel_of_Adun 1 12100
Protoss_Corsair 1 12585
Protoss_Templar_Archives 1 13694
Protoss_Dark_Templar 2 15007
Protoss_Robotics_Facility 1 16327
16327
