Protoss_Gateway 2 9418
Protoss_Assimilator 2 15555
Protoss_Zealot 7 11294
Protoss_Cybernetics_Core 1 7015
Protoss_Dragoon 1 8211
Protoss_Citadel_of_Adun 1 8863
Protoss_Templar_Archives 1 11369
Protoss_Forge 1 12201
Protoss_High_Templar 4 13936
Leg_Enhancements 1 11864
Protoss_Archon 1 13297
Protoss_Nexus 1 15820
Protoss_Photon_Cannon 4 15000
15820
