Protoss_Nexus 1 7214
Protoss_Gateway 5 15563
Protoss_Forge 1 6722
Protoss_Photon_Cannon 4 12876
Protoss_Zealot 4 12152
Protoss_Assimilator 2 10703
Protoss_Cybernetics_Core 1 9948
Protoss_Dragoon 1 11196
Protoss_Stargate 1 12100
Protoss_Citadel_of_Adun 1 12367
Protoss_Corsair 1 13152
Protoss_Templar_Archives 1 13910
Protoss_Dark_Templar 1 15177
15563
