Protoss_Forge 1 4275
Protoss_Photon_Cannon 2 7157
Protoss_Nexus 1 8361
Protoss_Gateway 1 8268
Protoss_Assimilator 1 8263
Protoss_Cybernetics_Core 1 9832
Protoss_Zealot 3 12184
12184
