Protoss_Gateway 2 11851
Protoss_Zealot 5 13112
Protoss_Assimilator 1 5660
Protoss_Cybernetics_Core 1 7445
Protoss_Stargate 1 9382
Protoss_Dragoon 1 9660
Protoss_Citadel_of_Adun 1 10208
Protoss_Corsair 2 15131
Protoss_Templar_Archives 1 12264
Protoss_Forge 1 12809
Protoss_Dark_Templar 1 13497
Protoss_Photon_Cannon 1 14068
Protoss_High_Templar 1 14644
Protoss_Nexus 1 17198
17198
