Protoss_Forge 1 3658
Protoss_Nexus 1 7568
Protoss_Gateway 3 11669
Protoss_Photon_Cannon 2 12013
Protoss_Assimilator 2 15113
Protoss_Zealot 13 14941
Protoss_Cybernetics_Core 1 9343
Protoss_Citadel_of_Adun 1 10908
Protoss_Templar_Archives 1 13773
Leg_Enhancements 1 14144
15113
