Protoss_Gateway 2 13119
Protoss_Zealot 6 10474
Protoss_Assimilator 1 5993
Protoss_Cybernetics_Core 1 7621
Protoss_Stargate 1 9441
Protoss_Forge 1 9081
Protoss_Dragoon 1 9730
Protoss_Photon_Cannon 2 14053
Protoss_Citadel_of_Adun 1 12522
14053
