Protoss_Forge 1 5007
Protoss_Photon_Cannon 8 13213
Protoss_Nexus 1 9605
Protoss_Gateway 2 15902
Protoss_Assimilator 2 10812
Protoss_Cybernetics_Core 1 10529
Protoss_Zealot 2 11440
Protoss_Stargate 2 14119
Protoss_Corsair 4 15286
15902
