Protoss_Gateway 1 4182
Protoss_Assimilator 1 4308
Protoss_Zealot 8 12971
Protoss_Cybernetics_Core 1 6898
Protoss_Dragoon 1 8193
Protoss_Stargate 1 9072
Protoss_Citadel_of_Adun 1 9832
Protoss_Corsair 1 10287
Protoss_Templar_Archives 1 12011
Protoss_Forge 1 12131
Protoss_Dark_Templar 2 14357
Protoss_Photon_Cannon 3 14887
Protoss_High_Templar 1 15513
15513
