Protoss_Forge 1 3743
Protoss_Photon_Cannon 2 5995
Protoss_Gateway 1 5727
Protoss_Zealot 3 9672
Protoss_Assimilator 1 7164
Protoss_Cybernetics_Core 1 8993
Protoss_Stargate 1 10686
Protoss_Corsair 4 15509
Protoss_Nexus 1 14089
Protoss_Citadel_of_Adun 1 13022
15509
