Protoss_Forge 1 4060
Protoss_Photon_Cannon 1 5562
Protoss_Nexus 1 8529
Protoss_Gateway 4 14721
Protoss_Assimilator 2 13327
Protoss_Zealot 10 15113
Protoss_Cybernetics_Core 1 9429
Protoss_Dragoon 1 10743
Protoss_Citadel_of_Adun 1 11148
Protoss_Templar_Archives 1 14055
Leg_Enhancements 1 14091
15113
