Protoss_Forge 1 4335
Protoss_Nexus 1 8114
Protoss_Gateway 3 15842
Protoss_Photon_Cannon 3 13677
Protoss_Zealot 12 15055
Protoss_Assimilator 2 11000
Protoss_Cybernetics_Core 1 12007
Protoss_Citadel_of_Adun 1 13581
Protoss_Templar_Archives 1 15036
15842
