Protoss_Gateway 2 10441
Protoss_Assimilator 1 4410
Protoss_Zealot 7 13489
Protoss_Cybernetics_Core 1 6749
Protoss_Dragoon 1 7974
Protoss_Citadel_of_Adun 1 8999
Protoss_Templar_Archives 1 10823
Protoss_High_Templar 4 14673
Protoss_Nexus 1 14639
Protoss_Archon 1 12669
Protoss_Forge 1 13848
Leg_Enhancements 1 13763
Protoss_Photon_Cannon 2 15364
15364
