Protoss_Nexus 1 7246
Protoss_Forge 1 5933
Protoss_Gateway 2 8232
Protoss_Zealot 7 15143
Protoss_Assimilator 2 13125
Protoss_Cybernetics_Core 1 10937
Protoss_Stargate 2 13739
15143
