Protoss_Forge 1 4650
Protoss_Photon_Cannon 2 7137
Protoss_Nexus 1 8257
Protoss_Gateway 5 15358
Protoss_Assimilator 2 10982
Protoss_Zealot 5 15292
Protoss_Cybernetics_Core 1 10504
Protoss_Stargate 1 12293
Protoss_Dragoon 1 12069
Protoss_Citadel_of_Adun 1 12768
Protoss_Corsair 1 13375
15358
