Protoss_Forge 1 4114
Protoss_Nexus 1 7478
Protoss_Photon_Cannon 4 13724
Protoss_Gateway 3 15566
Protoss_Assimilator 2 11235
Protoss_Zealot 6 14256
Protoss_Cybernetics_Core 1 10337
Protoss_Stargate 1 12043
Protoss_Citadel_of_Adun 1 12914
Protoss_Corsair 2 13940
Protoss_Templar_Archives 1 14587
15566
