Protoss_Forge 1 3898
Protoss_Photon_Cannon 2 5694
Protoss_Nexus 1 8908
Protoss_Gateway 1 7878
Protoss_Assimilator 2 12873
Protoss_Zealot 2 12752
Protoss_Cybernetics_Core 1 9825
Protoss_Dragoon 1 11062
Protoss_Stargate 1 11863
Protoss_Robotics_Facility 1 13418
Protoss_Corsair 1 12912
Protoss_Robotics_Support_Bay 1 14448
14448
