Protoss_Forge 1 3801
Protoss_Photon_Cannon 2 5711
Protoss_Nexus 1 9072
Protoss_Gateway 4 15611
Protoss_Assimilator 2 10880
Protoss_Cybernetics_Core 1 10430
Protoss_Zealot 5 14294
Protoss_Stargate 1 12433
Protoss_Citadel_of_Adun 1 12934
Protoss_Corsair 1 13507
Protoss_Templar_Archives 1 14600
15611
