Protoss_Forge 2 13324
Protoss_Photon_Cannon 3 14697
Protoss_Nexus 1 8153
Protoss_Gateway 5 15675
Protoss_Assimilator 2 12201
Protoss_Zealot 5 13419
Protoss_Cybernetics_Core 1 9415
Protoss_Citadel_of_Adun 1 11150
Protoss_Templar_Archives 1 13714
Protoss_High_Templar 2 14925
15675
