Protoss_Gateway 3 15801
Protoss_Forge 1 4788
Protoss_Photon_Cannon 3 14782
Protoss_Nexus 1 10212
Protoss_Assimilator 2 11063
Protoss_Zealot 3 13249
Protoss_Cybernetics_Core 1 10278
Protoss_Stargate 1 12088
Protoss_Dragoon 1 12013
Protoss_Citadel_of_Adun 1 13259
Protoss_Corsair 3 14917
Protoss_Templar_Archives 1 14840
15801
