Protoss_Forge 1 4539
Protoss_Nexus 1 7841
Protoss_Gateway 1 7272
Protoss_Assimilator 2 10331
Protoss_Photon_Cannon 3 13813
Protoss_Zealot 3 13916
Protoss_Cybernetics_Core 1 10098
Protoss_Dragoon 1 11624
Protoss_Stargate 1 12182
Protoss_Robotics_Facility 1 13198
Protoss_Corsair 3 15476
Protoss_Shuttle 1 14622
Protoss_Robotics_Support_Bay 1 14594
15476
