Protoss_Forge 1 3861
Protoss_Photon_Cannon 5 15721
Protoss_Nexus 1 8727
Protoss_Gateway 3 15522
Protoss_Zealot 5 13521
Protoss_Assimilator 2 12891
Protoss_Cybernetics_Core 1 11347
Protoss_Citadel_of_Adun 1 13073
Protoss_Templar_Archives 1 14575
Protoss_High_Templar 1 15800
15800
