Protoss_Forge 1 3832
Protoss_Photon_Cannon 4 15279
Protoss_Nexus 1 7966
Protoss_Gateway 4 14257
Protoss_Assimilator 2 9547
Protoss_Cybernetics_Core 1 9756
Protoss_Zealot 3 13106
Protoss_Stargate 1 11485
Protoss_Citadel_of_Adun 1 11645
Protoss_Corsair 1 12544
Protoss_Templar_Archives 1 13152
Protoss_Dark_Templar 1 14346
Protoss_High_Templar 3 15692
15692
