Protoss_Forge 1 3888
Protoss_Photon_Cannon 5 14578
Protoss_Nexus 2 17238
Protoss_Gateway 1 8364
Protoss_Assimilator 2 11475
Protoss_Cybernetics_Core 1 9948
Protoss_Zealot 2 10372
Protoss_Stargate 1 11794
Protoss_Corsair 3 14654
Protoss_Robotics_Facility 1 14449
17238
