Protoss_Gateway 1 3945
Protoss_Zealot 12 15397
Protoss_Nexus 1 10211
Protoss_Forge 1 10150
Protoss_Assimilator 2 13002
Protoss_Photon_Cannon 6 15582
Protoss_Cybernetics_Core 1 13015
Protoss_Stargate 1 14823
Protoss_Citadel_of_Adun 1 15185
15582
