Protoss_Nexus 1 7304
Protoss_Gateway 5 14800
Protoss_Forge 1 6400
Protoss_Assimilator 2 9567
Protoss_Photon_Cannon 1 7757
Protoss_Zealot 2 9061
Protoss_Cybernetics_Core 1 9307
Protoss_Stargate 1 11061
Protoss_Citadel_of_Adun 1 11074
Protoss_Dragoon 1 10871
Protoss_Templar_Archives 1 12532
Protoss_Corsair 1 12219
Protoss_Dark_Templar 2 14975
Protoss_High_Templar 4 15733
15733
