Protoss_Gateway 1 4296
Protoss_Assimilator 2 14282
Protoss_Cybernetics_Core 1 5882
Protoss_Stargate 1 7606
Protoss_Corsair 7 14265
Protoss_Nexus 1 11930
Protoss_Robotics_Facility 1 12373
Protoss_Shield_Battery 1 13371
Protoss_Robotics_Support_Bay 1 13662
Protoss_Shuttle 1 15238
15238
