Protoss_Forge 1 3795
Protoss_Photon_Cannon 3 8995
Protoss_Nexus 1 9265
Protoss_Gateway 3 14374
Protoss_Assimilator 2 10821
Protoss_Cybernetics_Core 1 10050
Protoss_Zealot 5 14010
Protoss_Stargate 1 11988
Protoss_Citadel_of_Adun 1 12416
Protoss_Corsair 2 14285
Protoss_Templar_Archives 1 13921
Protoss_Dark_Templar 3 15595
15595
