Protoss_Gateway 2 10167
Protoss_Assimilator 1 4609
Protoss_Zealot 8 13548
Protoss_Cybernetics_Core 1 7644
Protoss_Dragoon 1 9189
Protoss_Citadel_of_Adun 1 9549
Protoss_Templar_Archives 1 11001
Protoss_Forge 1 12201
Protoss_High_Templar 4 14668
Protoss_Archon 1 13173
Leg_Enhancements 1 12724
Protoss_Photon_Cannon 4 14985
Protoss_Nexus 1 17463
17463
