Protoss_Forge 1 4217
Protoss_Nexus 1 8109
Protoss_Gateway 4 14534
Protoss_Photon_Cannon 3 12983
Protoss_Assimilator 2 10507
Protoss_Cybernetics_Core 1 10050
Protoss_Zealot 8 15512
Protoss_Stargate 1 11871
Protoss_Citadel_of_Adun 1 12579
Protoss_Corsair 1 12831
Protoss_Templar_Archives 1 15886
15886
