Protoss_Gateway 2 5165
Protoss_Zealot 11 15266
Protoss_Assimilator 1 7981
Protoss_Cybernetics_Core 1 10744
Protoss_Forge 1 11771
Protoss_Dragoon 4 14005
Protoss_Photon_Cannon 1 13775
15266
