Protoss_Forge 1 4161
Protoss_Photon_Cannon 4 14177
Protoss_Nexus 1 9151
Protoss_Gateway 3 15795
Protoss_Assimilator 2 11591
Protoss_Cybernetics_Core 1 9687
Protoss_Zealot 5 15059
Protoss_Stargate 1 11564
Protoss_Citadel_of_Adun 1 11862
Protoss_Corsair 1 13252
Protoss_Robotics_Facility 1 14545
Protoss_Templar_Archives 1 14856
15795
