Protoss_Gateway 2 11594
Protoss_Assimilator 1 4545
Protoss_Zealot 10 12681
Protoss_Cybernetics_Core 1 7524
Protoss_Citadel_of_Adun 1 9737
Protoss_Templar_Archives 1 12696
Protoss_Forge 1 13498
Leg_Enhancements 1 12683
Protoss_High_Templar 3 15253
Protoss_Dark_Templar 1 14152
Protoss_Photon_Cannon 1 15465
Protoss_Stargate 1 16130
16130
