Protoss_Gateway 2 11821
Protoss_Assimilator 1 4548
Protoss_Zealot 2 6869
Protoss_Cybernetics_Core 1 6883
Protoss_Stargate 1 8667
Protoss_Dragoon 1 8630
Protoss_Citadel_of_Adun 1 9612
Protoss_Corsair 1 9649
Protoss_Forge 1 10512
Protoss_Templar_Archives 1 11133
Protoss_Dark_Templar 2 13043
Protoss_Photon_Cannon 3 15691
Protoss_Nexus 1 16217
Protoss_High_Templar 2 15534
16217
