Protoss_Forge 1 4237
Protoss_Nexus 1 7541
Protoss_Gateway 4 15819
Protoss_Photon_Cannon 6 15259
Protoss_Assimilator 2 10071
Protoss_Cybernetics_Core 1 8683
Protoss_Zealot 5 14917
Protoss_Stargate 1 10587
Protoss_Dragoon 1 10459
Protoss_Corsair 2 13041
Protoss_Citadel_of_Adun 1 12427
Protoss_Templar_Archives 1 14484
Protoss_High_Templar 2 15768
15819
