Protoss_Forge 2 12642
Protoss_Photon_Cannon 3 14394
Protoss_Gateway 2 8767
Protoss_Assimilator 1 6942
Protoss_Cybernetics_Core 1 10223
Protoss_Zealot 3 11657
Protoss_Stargate 1 11920
Protoss_Citadel_of_Adun 1 12031
Protoss_Dragoon 1 12777
Protoss_Corsair 2 14085
Protoss_Templar_Archives 1 13512
Protoss_Dark_Templar 1 14711
Protoss_Nexus 1 17128
Protoss_High_Templar 1 15812
17128
