Protoss_Forge 1 4046
Protoss_Nexus 1 7398
Protoss_Photon_Cannon 3 10282
Protoss_Gateway 1 7679
Protoss_Assimilator 2 12708
Protoss_Zealot 4 14824
Protoss_Cybernetics_Core 1 9560
Protoss_Stargate 1 12250
Protoss_Dragoon 1 11960
Protoss_Corsair 3 15172
Protoss_Citadel_of_Adun 1 15012
15172
