Protoss_Forge 1 4975
Protoss_Photon_Cannon 4 14357
Protoss_Nexus 1 9078
Protoss_Gateway 1 8215
Protoss_Assimilator 2 10065
Protoss_Cybernetics_Core 1 9763
Protoss_Zealot 5 15295
Protoss_Dragoon 1 11381
Protoss_Stargate 1 12517
Protoss_Robotics_Facility 1 13936
Protoss_Corsair 3 15318
Protoss_Shuttle 1 16038
16038
