Protoss_Nexus 1 7051
Protoss_Forge 1 5809
Protoss_Photon_Cannon 2 12061
Protoss_Gateway 1 7723
Protoss_Assimilator 2 9286
Protoss_Cybernetics_Core 1 9192
Protoss_Zealot 3 15266
Protoss_Stargate 1 10873
Protoss_Dragoon 1 10939
Protoss_Robotics_Facility 1 12428
Protoss_Corsair 4 14780
Protoss_Shuttle 1 13861
Protoss_Robotics_Support_Bay 1 13327
Protoss_Reaver 1 15419
15419
