Protoss_Gateway 3 16047
Protoss_Assimilator 1 4413
Protoss_Cybernetics_Core 1 5767
Protoss_Zealot 2 6869
Protoss_Dragoon 10 15399
Protoss_Stargate 1 9581
Protoss_Robotics_Facility 1 10500
Protoss_Shuttle 1 12128
Protoss_Robotics_Support_Bay 1 12184
Protoss_Reaver 1 14432
Singularity_Charge 1 12768
16047
