Protoss_Forge 1 3936
Protoss_Photon_Cannon 6 15268
Protoss_Nexus 2 12859
Protoss_Gateway 1 9072
Protoss_Assimilator 2 12201
Protoss_Cybernetics_Core 1 10632
Protoss_Zealot 4 13553
Protoss_Stargate 1 12401
Protoss_Dragoon 1 12089
Protoss_Citadel_of_Adun 1 13196
Protoss_Corsair 2 14461
Protoss_Templar_Archives 1 14794
15268
