Protoss_Forge 1 4073
Protoss_Photon_Cannon 5 15196
Protoss_Nexus 1 8364
Protoss_Gateway 2 13956
Protoss_Assimilator 2 10834
Protoss_Zealot 3 12005
Protoss_Cybernetics_Core 1 10398
Protoss_Stargate 1 12362
Protoss_Citadel_of_Adun 1 13051
Protoss_Corsair 2 15295
Protoss_Templar_Archives 1 14556
15295
