Protoss_Forge 1 4151
Protoss_Photon_Cannon 5 15408
Protoss_Nexus 1 8089
Protoss_Gateway 1 8153
Protoss_Zealot 5 13694
Protoss_Assimilator 2 15036
Protoss_Cybernetics_Core 1 12948
Protoss_Stargate 1 14795
Protoss_Dragoon 1 15249
Protoss_Citadel_of_Adun 1 16053
16053
