Protoss_Forge 1 4207
Protoss_Photon_Cannon 3 9882
Protoss_Nexus 1 8657
Protoss_Gateway 1 8186
Protoss_Assimilator 2 12643
Protoss_Zealot 6 14303
Protoss_Cybernetics_Core 1 12039
Protoss_Stargate 1 13897
Protoss_Citadel_of_Adun 1 13998
Protoss_Corsair 1 14832
Protoss_Templar_Archives 1 15734
Protoss_Dragoon 1 15610
15734
