Protoss_Forge 1 4120
Protoss_Photon_Cannon 3 13617
Protoss_Nexus 1 8415
Protoss_Gateway 4 15823
Protoss_Assimilator 2 10357
Protoss_Cybernetics_Core 1 9277
Protoss_Zealot 4 14282
Protoss_Stargate 1 11487
Protoss_Citadel_of_Adun 1 12394
Protoss_Corsair 1 12617
Protoss_Templar_Archives 1 14004
Protoss_Robotics_Facility 1 14716
Protoss_Dark_Templar 1 15402
15823
