Protoss_Forge 2 14178
Protoss_Photon_Cannon 8 15420
Protoss_Gateway 2 15181
Protoss_Zealot 2 8464
Protoss_Nexus 1 9687
Protoss_Assimilator 1 8194
Protoss_Cybernetics_Core 1 10629
15420
