Protoss_Forge 1 4204
Protoss_Nexus 1 7519
Protoss_Gateway 1 6784
Protoss_Assimilator 2 9471
Protoss_Photon_Cannon 3 12898
Protoss_Cybernetics_Core 1 8554
Protoss_Zealot 3 15512
Protoss_Stargate 1 10420
Protoss_Dragoon 1 10105
Protoss_Robotics_Facility 1 11624
Protoss_Corsair 5 15310
Protoss_Shuttle 1 13354
Protoss_Robotics_Support_Bay 1 13059
Protoss_Reaver 1 15158
15512
