Protoss_Forge 1 4546
Protoss_Nexus 1 8077
Protoss_Gateway 4 15232
Protoss_Photon_Cannon 1 7725
Protoss_Zealot 14 15280
Protoss_Assimilator 2 10902
Protoss_Cybernetics_Core 1 10556
Protoss_Citadel_of_Adun 1 12743
Protoss_Templar_Archives 1 14724
Protoss_Robotics_Facility 1 16085
16085
