Protoss_Forge 1 3980
Protoss_Photon_Cannon 2 7074
Protoss_Nexus 1 8223
Protoss_Gateway 1 8022
Protoss_Assimilator 2 11748
Protoss_Zealot 6 14742
Protoss_Cybernetics_Core 1 10147
Protoss_Citadel_of_Adun 1 12866
Protoss_Dragoon 1 12871
14742
