Protoss_Forge 1 4109
Protoss_Nexus 1 7263
Protoss_Gateway 5 15962
Protoss_Assimilator 2 10352
Protoss_Cybernetics_Core 1 8129
Protoss_Photon_Cannon 3 14297
Protoss_Zealot 5 14174
Protoss_Stargate 1 10172
Protoss_Dragoon 1 10977
Protoss_Corsair 2 12223
Protoss_Citadel_of_Adun 1 12125
Protoss_Templar_Archives 1 13793
Protoss_Dark_Templar 2 15107
Protoss_Robotics_Facility 1 16476
16476
