Protoss_Forge 1 4259
Protoss_Photon_Cannon 4 15193
Protoss_Nexus 1 10656
Protoss_Gateway 1 9737
Protoss_Assimilator 3 15298
Protoss_Cybernetics_Core 1 11309
Protoss_Zealot 3 12842
Protoss_Stargate 1 13227
Protoss_Citadel_of_Adun 1 13697
Protoss_Dragoon 1 14562
Protoss_Corsair 1 14461
Protoss_Templar_Archives 1 15586
15586
