Protoss_Gateway 2 5246
Protoss_Zealot 11 12266
Protoss_Assimilator 1 6791
Protoss_Cybernetics_Core 1 10236
Protoss_Citadel_of_Adun 1 11699
Protoss_Forge 1 11701
Protoss_Templar_Archives 1 13365
Protoss_Photon_Cannon 3 14946
Protoss_High_Templar 2 14722
Protoss_Nexus 1 17078
17078
