Protoss_Gateway 2 5600
Protoss_Zealot 6 12024
Protoss_Assimilator 1 7030
Protoss_Cybernetics_Core 1 8993
Protoss_Forge 1 9424
Protoss_Dragoon 1 10200
Protoss_Stargate 1 11020
Protoss_Citadel_of_Adun 1 12080
Protoss_Photon_Cannon 4 15786
Protoss_Nexus 1 16211
Protoss_Templar_Archives 1 15147
16211
