Protoss_Gateway 1 4214
Protoss_Assimilator 1 4488
Protoss_Zealot 7 15053
Protoss_Cybernetics_Core 1 7163
Protoss_Stargate 1 8936
Protoss_Corsair 2 11534
Protoss_Citadel_of_Adun 1 10711
Protoss_Forge 1 12460
Protoss_Nexus 1 16019
Leg_Enhancements 1 13662
Protoss_Templar_Archives 1 15585
16019
