Protoss_Gateway 3 8875
Protoss_Zealot 14 15535
Protoss_Assimilator 1 5439
Protoss_Cybernetics_Core 1 7931
Protoss_Citadel_of_Adun 1 9424
Protoss_Forge 1 9649
Protoss_Photon_Cannon 3 13437
Leg_Enhancements 1 12360
Protoss_Templar_Archives 1 15555
15555
