Protoss_Gateway 2 5371
Protoss_Zealot 13 14234
Protoss_Assimilator 1 7073
Protoss_Cybernetics_Core 1 9542
Protoss_Forge 1 10932
Protoss_Photon_Cannon 2 13056
Protoss_Nexus 1 15653
Protoss_Citadel_of_Adun 1 15255
15653
