Protoss_Gateway 1 4041
Protoss_Zealot 8 14950
Protoss_Forge 1 5271
Protoss_Photon_Cannon 5 11990
Protoss_Assimilator 1 9251
Protoss_Cybernetics_Core 1 13679
Protoss_Citadel_of_Adun 1 15348
Protoss_Stargate 1 16080
16080
