Protoss_Forge 1 4117
Protoss_Nexus 1 7904
Protoss_Photon_Cannon 2 14780
Protoss_Assimilator 2 12863
Protoss_Gateway 3 9548
Protoss_Zealot 17 14939
Protoss_Cybernetics_Core 1 13575
14939
