Protoss_Gateway 2 5246
Protoss_Zealot 13 11134
Protoss_Assimilator 1 10000
Protoss_Cybernetics_Core 1 12226
Protoss_Forge 1 12348
Protoss_Robotics_Facility 1 14196
Protoss_Dragoon 1 13778
Protoss_Citadel_of_Adun 1 15048
Protoss_Shuttle 1 15611
15611
