Protoss_Assimilator 1 3400
Protoss_Gateway 1 4890
Protoss_Cybernetics_Core 1 6374
Protoss_Stargate 2 15130
Protoss_Robotics_Facility 1 8648
Protoss_Corsair 7 15491
Protoss_Shuttle 1 10226
Protoss_Fleet_Beacon 1 12153
Protoss_Forge 1 12033
Protoss_Photon_Cannon 1 13441
15491
