Protoss_Gateway 1 4264
Protoss_Assimilator 1 4526
Protoss_Zealot 8 13454
Protoss_Cybernetics_Core 1 7467
Protoss_Citadel_of_Adun 1 9100
Protoss_Forge 1 9198
Protoss_Templar_Archives 1 13005
Protoss_Photon_Cannon 3 14183
Leg_Enhancements 1 12031
Protoss_High_Templar 2 15704
15704
