Protoss_Gateway 2 5177
Protoss_Zealot 10 10561
Protoss_Assimilator 1 8657
Protoss_Nexus 1 14705
Protoss_Cybernetics_Core 1 13795
Protoss_Dragoon 1 15014
Protoss_Robotics_Facility 1 15944
Protoss_Stargate 1 15969
15969
