Protoss_Gateway 1 4142
Protoss_Forge 2 10965
Protoss_Zealot 6 14636
Protoss_Assimilator 1 6273
Protoss_Cybernetics_Core 1 7564
Protoss_Dragoon 1 8831
Protoss_Stargate 1 10698
Protoss_Corsair 2 12624
Protoss_Citadel_of_Adun 1 12282
Protoss_Photon_Cannon 2 14839
Protoss_Nexus 1 15447
Protoss_Templar_Archives 1 15538
Protoss_Shield_Battery 1 14987
15538
