Protoss_Nexus 1 7449
Protoss_Forge 1 5977
Protoss_Photon_Cannon 6 15683
Protoss_Assimilator 2 10312
Protoss_Gateway 1 9893
Protoss_Cybernetics_Core 1 11655
Protoss_Stargate 1 13743
Protoss_Robotics_Facility 1 14416
Protoss_Corsair 1 14732
Protoss_Shuttle 1 16021
16021
