Protoss_Gateway 2 5411
Protoss_Zealot 17 15427
Protoss_Assimilator 1 10098
Protoss_Cybernetics_Core 1 12485
Protoss_Citadel_of_Adun 1 14025
Protoss_Dragoon 1 13861
Protoss_Templar_Archives 1 15694
15694
