Protoss_Gateway 2 5070
Protoss_Zealot 5 10407
Protoss_Nexus 1 11026
Protoss_Assimilator 2 13286
Protoss_Cybernetics_Core 1 10366
Protoss_Stargate 1 12706
Protoss_Forge 1 12656
Protoss_Corsair 2 14790
Protoss_Photon_Cannon 3 15215
15215
