Protoss_Gateway 2 4997
Protoss_Zealot 15 13861
Protoss_Forge 1 8058
Protoss_Photon_Cannon 3 15054
Protoss_Assimilator 1 12353
Protoss_Cybernetics_Core 1 13949
Protoss_Robotics_Facility 1 16503
16503
