Protoss_Gateway 2 5516
Protoss_Assimilator 1 5647
Protoss_Cybernetics_Core 1 6994
Protoss_Zealot 5 12737
Protoss_Stargate 1 9363
Protoss_Citadel_of_Adun 1 10111
Protoss_Dragoon 1 10317
Leg_Enhancements 1 13260
13260
