Protoss_Assimilator 1 3561
Protoss_Gateway 1 4796
Protoss_Cybernetics_Core 1 6514
Protoss_Stargate 1 8220
Protoss_Robotics_Facility 1 9228
Protoss_Corsair 5 15134
Protoss_Shuttle 1 10635
Protoss_Robotics_Support_Bay 1 10178
Protoss_Reaver 2 16295
Protoss_Air_Weapons_1 1 12455
Protoss_Forge 1 13728
Protoss_Shield_Battery 1 14079
Protoss_Photon_Cannon 2 15167
Protoss_Nexus 1 17239
17239
