Protoss_Gateway 2 10237
Protoss_Assimilator 1 4889
Protoss_Zealot 8 13868
Protoss_Cybernetics_Core 1 7562
Protoss_Shield_Battery 1 7883
Protoss_Dragoon 1 9007
Protoss_Stargate 1 9559
Protoss_Citadel_of_Adun 1 10505
Protoss_Corsair 1 10502
Protoss_Templar_Archives 1 13963
Protoss_Forge 1 13603
Leg_Enhancements 1 13604
13963
