Protoss_Gateway 2 4978
Protoss_Zealot 7 7921
Protoss_Assimilator 1 9536
Protoss_Cybernetics_Core 1 10321
Protoss_Forge 1 11625
Protoss_Nexus 1 14244
Protoss_Photon_Cannon 3 14808
Protoss_Citadel_of_Adun 1 14546
14808
