Protoss_Gateway 2 14821
Protoss_Assimilator 1 4388
Protoss_Zealot 4 11076
Protoss_Cybernetics_Core 1 6703
Protoss_Stargate 1 8410
Protoss_Dragoon 1 8586
Protoss_Robotics_Facility 1 10375
Protoss_Shuttle 1 11923
Protoss_Robotics_Support_Bay 1 11226
Protoss_Reaver 1 13727
Protoss_Forge 1 13375
14821
