Protoss_Forge 1 4072
Protoss_Photon_Cannon 5 13929
Protoss_Nexus 1 9374
Protoss_Gateway 3 13723
Protoss_Assimilator 1 10016
Protoss_Cybernetics_Core 1 12146
Protoss_Zealot 4 14841
Protoss_Citadel_of_Adun 1 13723
Protoss_Templar_Archives 1 16051
16051
