Protoss_Assimilator 1 3501
Protoss_Gateway 1 4748
Protoss_Cybernetics_Core 1 6206
Protoss_Dragoon 1 7419
Protoss_Stargate 2 12967
Protoss_Robotics_Facility 1 9519
Protoss_Corsair 5 15283
Protoss_Shuttle 1 10935
Protoss_Forge 1 11259
Protoss_Robotics_Support_Bay 1 11736
Protoss_Photon_Cannon 3 14880
Protoss_Reaver 1 15651
Protoss_Air_Weapons_1 1 14080
15651
