Protoss_Assimilator 1 3569
Protoss_Gateway 1 4777
Protoss_Cybernetics_Core 1 6241
Protoss_Stargate 1 8052
Protoss_Dragoon 1 7646
Protoss_Robotics_Facility 1 9464
Protoss_Corsair 5 15266
Protoss_Zealot 2 11256
Protoss_Shuttle 1 11148
Protoss_Forge 1 11783
Protoss_Robotics_Support_Bay 1 12884
Protoss_Photon_Cannon 2 13952
Protoss_Reaver 1 15022
Protoss_Air_Weapons_1 1 14175
15266
