Protoss_Gateway 2 5269
Protoss_Zealot 12 15492
Protoss_Assimilator 1 8016
Protoss_Forge 1 8442
Protoss_Photon_Cannon 5 14966
Protoss_Cybernetics_Core 1 11297
Protoss_Citadel_of_Adun 1 13280
Protoss_Dragoon 1 14114
15492
