Protoss_Gateway 2 7280
Protoss_Assimilator 1 5012
Protoss_Zealot 14 15324
Protoss_Nexus 1 13881
Protoss_Forge 1 12255
Protoss_Cybernetics_Core 1 13325
Protoss_Photon_Cannon 1 13538
15324
