Protoss_Gateway 2 5256
Protoss_Zealot 4 10559
Protoss_Assimilator 1 5655
Protoss_Cybernetics_Core 1 7853
Protoss_Stargate 1 9533
Protoss_Citadel_of_Adun 1 10379
Protoss_Corsair 2 15072
Protoss_Forge 1 12406
Protoss_Photon_Cannon 1 15633
15633
