Protoss_Gateway 1 4533
Protoss_Assimilator 1 4644
Protoss_Zealot 6 14227
Protoss_Cybernetics_Core 1 7296
Protoss_Stargate 1 9448
Protoss_Corsair 1 10400
Protoss_Nexus 1 15893
15893
