Protoss_Gateway 2 15579
Protoss_Assimilator 1 4710
Protoss_Zealot 3 9792
Protoss_Cybernetics_Core 1 7591
Protoss_Dragoon 1 8890
Protoss_Stargate 1 9621
Protoss_Citadel_of_Adun 1 9589
Protoss_Corsair 1 10575
Protoss_Forge 1 11701
Protoss_Photon_Cannon 1 13084
Protoss_Nexus 1 16123
16123
