Protoss_Gateway 3 13498
Protoss_Assimilator 1 4755
Protoss_Cybernetics_Core 1 6194
Protoss_Zealot 11 15495
Protoss_Stargate 1 8087
Protoss_Forge 1 7755
Protoss_Corsair 2 10224
Protoss_Citadel_of_Adun 1 11538
Protoss_Ground_Weapons_1 1 13919
Leg_Enhancements 1 14628
15495
