Protoss_Gateway 2 8019
Protoss_Assimilator 1 5263
Protoss_Zealot 3 8534
Protoss_Cybernetics_Core 1 7596
Protoss_Dragoon 1 9066
Protoss_Citadel_of_Adun 1 9778
Protoss_Stargate 1 11387
Protoss_Templar_Archives 1 11313
Protoss_Forge 1 11674
Protoss_Dark_Templar 1 12819
Protoss_Photon_Cannon 3 15639
Protoss_Corsair 1 13392
Protoss_High_Templar 2 14078
Protoss_Nexus 1 15906
15906
