Protoss_Gateway 2 13268
Protoss_Assimilator 2 14881
Protoss_Zealot 3 7634
Protoss_Cybernetics_Core 1 7616
Protoss_Citadel_of_Adun 1 9229
Protoss_Dragoon 1 9241
Protoss_Forge 1 10167
Protoss_Templar_Archives 1 10733
Protoss_Dark_Templar 1 11971
Protoss_Nexus 1 14510
Protoss_High_Templar 3 14619
Protoss_Photon_Cannon 3 14739
14881
