Protoss_Gateway 2 5202
Protoss_Zealot 12 15097
Protoss_Assimilator 1 6814
Protoss_Cybernetics_Core 1 8082
Protoss_Dragoon 1 9344
Protoss_Stargate 1 10159
Protoss_Citadel_of_Adun 1 10660
Protoss_Corsair 1 11168
Protoss_Templar_Archives 1 14970
Leg_Enhancements 1 13926
15097
