Protoss_Gateway 2 5246
Protoss_Zealot 5 11958
Protoss_Assimilator 1 5805
Protoss_Cybernetics_Core 1 8289
Protoss_Robotics_Facility 1 10865
Protoss_Dragoon 4 13031
Protoss_Shuttle 1 13504
Protoss_Citadel_of_Adun 1 14028
Protoss_Robotics_Support_Bay 1 13706
Protoss_Reaver 1 15564
Protoss_Templar_Archives 1 15905
15905
