Protoss_Gateway 2 5180
Protoss_Assimilator 1 5269
Protoss_Zealot 5 8622
Protoss_Cybernetics_Core 1 10464
Protoss_Forge 1 11218
Protoss_Dragoon 4 15475
Protoss_Photon_Cannon 1 13023
15475
