Protoss_Gateway 2 5431
Protoss_Zealot 13 15017
Protoss_Assimilator 1 6989
Protoss_Cybernetics_Core 1 10397
Protoss_Dragoon 1 11802
Protoss_Citadel_of_Adun 1 12336
Protoss_Templar_Archives 1 14750
Protoss_Forge 1 14808
15017
