Protoss_Nexus 1 7151
Protoss_Gateway 3 13366
Protoss_Forge 1 6390
Protoss_Photon_Cannon 6 15822
Protoss_Assimilator 1 9269
Protoss_Zealot 7 15558
Protoss_Cybernetics_Core 1 10691
Protoss_Stargate 1 12493
Protoss_Corsair 2 14746
Protoss_Citadel_of_Adun 1 14875
Protoss_Robotics_Facility 1 16361
16361
