Protoss_Forge 1 4182
Protoss_Photon_Cannon 5 15215
Protoss_Nexus 1 8927
Protoss_Gateway 1 9811
Protoss_Assimilator 2 12111
Protoss_Zealot 2 12295
Protoss_Cybernetics_Core 1 11948
Protoss_Dragoon 1 13254
Protoss_Robotics_Facility 1 14127
Protoss_Stargate 1 14352
Protoss_Robotics_Support_Bay 1 14934
Protoss_Corsair 1 15302
15302
