Protoss_Gateway 2 12307
Protoss_Zealot 8 14446
Protoss_Assimilator 1 5818
Protoss_Cybernetics_Core 1 7382
Protoss_Dragoon 1 9892
Protoss_Robotics_Facility 1 10924
Protoss_Citadel_of_Adun 1 10872
Protoss_Shuttle 1 12977
Protoss_Robotics_Support_Bay 1 12711
Protoss_Reaver 1 14535
14535
