Protoss_Gateway 2 5019
Protoss_Zealot 12 12090
Protoss_Assimilator 1 7812
Protoss_Cybernetics_Core 1 10777
Protoss_Citadel_of_Adun 1 12241
Protoss_Nexus 1 15527
Protoss_Templar_Archives 1 14721
Protoss_Forge 1 15381
15527
