Protoss_Gateway 3 14320
Protoss_Zealot 11 15427
Protoss_Forge 1 6408
Protoss_Photon_Cannon 3 14732
Protoss_Nexus 1 11371
Protoss_Assimilator 2 15071
Protoss_Cybernetics_Core 1 12929
Protoss_Citadel_of_Adun 1 14759
Protoss_Dragoon 1 15044
15427
