Protoss_Nexus 1 7310
Protoss_Forge 1 6251
Protoss_Photon_Cannon 3 15156
Protoss_Gateway 4 14546
Protoss_Assimilator 2 11178
Protoss_Cybernetics_Core 1 10909
Protoss_Zealot 9 15302
Protoss_Dragoon 3 13747
Protoss_Citadel_of_Adun 1 14208
15302
