Protoss_Nexus 1 7597
Protoss_Forge 1 6485
Protoss_Assimilator 3 14385
Protoss_Photon_Cannon 1 7986
Protoss_Gateway 4 14626
Protoss_Zealot 15 14966
Protoss_Cybernetics_Core 1 10855
Protoss_Citadel_of_Adun 1 12671
Protoss_Templar_Archives 1 15728
15728
