Protoss_Gateway 2 5537
Protoss_Zealot 11 13634
Protoss_Assimilator 1 7044
Protoss_Cybernetics_Core 1 8616
Protoss_Dragoon 5 15673
Protoss_Stargate 1 10793
Protoss_Citadel_of_Adun 1 11964
Protoss_Corsair 3 14651
15673
