Protoss_Gateway 2 10429
Protoss_Assimilator 1 4593
Protoss_Zealot 9 14988
Protoss_Cybernetics_Core 1 7438
Protoss_Stargate 1 9250
Protoss_Dragoon 1 9310
Protoss_Citadel_of_Adun 1 10051
Protoss_Templar_Archives 1 13470
Protoss_Forge 1 13937
Leg_Enhancements 1 12989
14988
