Protoss_Gateway 2 10763
Protoss_Assimilator 1 4893
Protoss_Zealot 7 15487
Protoss_Cybernetics_Core 1 6936
Protoss_Citadel_of_Adun 1 8399
Protoss_Templar_Archives 1 11429
Protoss_Forge 1 11710
Leg_Enhancements 1 11336
Protoss_High_Templar 2 13744
Protoss_Photon_Cannon 2 14502
15487
