Protoss_Gateway 3 11904
Protoss_Assimilator 1 4444
Protoss_Zealot 12 14585
Protoss_Cybernetics_Core 1 6526
Protoss_Stargate 1 8397
Protoss_Citadel_of_Adun 1 9782
Protoss_Corsair 1 9610
Leg_Enhancements 1 12916
Protoss_Templar_Archives 1 15451
15451
