Protoss_Gateway 3 12816
Protoss_Assimilator 1 4717
Protoss_Zealot 3 7232
Protoss_Cybernetics_Core 1 7248
Protoss_Robotics_Facility 1 9493
Protoss_Dragoon 12 15376
Protoss_Observatory 1 10419
Protoss_Observer 1 11710
Singularity_Charge 1 13180
15376
