Protoss_Gateway 1 4123
Protoss_Assimilator 1 4631
Protoss_Zealot 8 14711
Protoss_Forge 1 6933
Protoss_Cybernetics_Core 1 9065
Protoss_Citadel_of_Adun 1 10521
Protoss_Dragoon 1 10400
Protoss_Robotics_Facility 1 12270
Protoss_Robotics_Support_Bay 1 13692
Leg_Enhancements 1 13787
Protoss_Ground_Weapons_1 1 14123
14711
