Protoss_Gateway 4 13331
Protoss_Zealot 15 15427
Protoss_Nexus 1 10559
Protoss_Assimilator 1 9048
Protoss_Forge 1 9572
Protoss_Photon_Cannon 1 11016
Protoss_Cybernetics_Core 1 11819
Protoss_Citadel_of_Adun 1 13622
15427
