Protoss_Gateway 2 5150
Protoss_Zealot 12 13956
Protoss_Assimilator 1 7938
Protoss_Forge 1 9674
Protoss_Cybernetics_Core 1 11289
Protoss_Citadel_of_Adun 1 12880
Protoss_Dragoon 1 13163
13956
