Protoss_Forge 1 4272
Protoss_Photon_Cannon 7 15036
Protoss_Gateway 2 9267
Protoss_Nexus 1 10142
Protoss_Assimilator 1 9166
Protoss_Zealot 10 15075
Protoss_Cybernetics_Core 1 11540
Protoss_Stargate 1 13251
Protoss_Corsair 2 15244
15244
