Protoss_Gateway 2 12965
Protoss_Forge 1 4773
Protoss_Zealot 9 14849
Protoss_Photon_Cannon 3 13886
Protoss_Assimilator 1 9396
Protoss_Cybernetics_Core 1 11585
Protoss_Dragoon 1 12914
Protoss_Citadel_of_Adun 1 15012
15012
