Protoss_Gateway 1 4250
Protoss_Assimilator 1 4234
Protoss_Cybernetics_Core 1 5797
Protoss_Stargate 1 7563
Protoss_Robotics_Facility 1 8796
Protoss_Corsair 8 15476
Protoss_Forge 1 9706
Protoss_Shuttle 1 10515
Protoss_Robotics_Support_Bay 1 10585
Protoss_Photon_Cannon 2 14968
Protoss_Reaver 1 14772
15476
