Protoss_Nexus 2 14260
Protoss_Forge 1 6043
Protoss_Assimilator 2 15277
Protoss_Gateway 1 8222
Protoss_Cybernetics_Core 1 10085
Protoss_Photon_Cannon 5 13788
Protoss_Stargate 1 11956
Protoss_Robotics_Facility 1 12714
Protoss_Corsair 2 14578
Protoss_Shuttle 2 15848
Protoss_Ground_Weapons_1 1 13626
15848
