Protoss_Gateway 1 4068
Protoss_Assimilator 1 4559
Protoss_Zealot 6 10773
Protoss_Cybernetics_Core 1 7447
Protoss_Stargate 1 9382
Protoss_Dragoon 1 9058
Protoss_Citadel_of_Adun 1 10233
Protoss_Scout 1 11345
Protoss_Forge 1 11120
Protoss_Templar_Archives 1 11904
Protoss_Photon_Cannon 4 15778
Protoss_Dark_Templar 1 13112
Protoss_High_Templar 1 15222
Protoss_Nexus 1 17232
17232
