Protoss_Gateway 3 13334
Protoss_Zealot 15 14995
Protoss_Assimilator 1 8683
Protoss_Cybernetics_Core 1 10271
Protoss_Citadel_of_Adun 1 12333
Protoss_Dragoon 1 12549
Protoss_Templar_Archives 1 14557
14995
