Protoss_Forge 1 5295
Protoss_Nexus 1 8159
Protoss_Photon_Cannon 5 15421
Protoss_Assimilator 1 12968
Protoss_Gateway 1 13511
Protoss_Cybernetics_Core 1 14985
Protoss_Zealot 1 14871
15421
