Protoss_Gateway 2 5063
Protoss_Zealot 14 14373
Protoss_Assimilator 1 10666
Protoss_Forge 1 10722
Protoss_Photon_Cannon 2 12200
Protoss_Cybernetics_Core 1 12994
Protoss_Citadel_of_Adun 1 14813
14813
