Protoss_Gateway 2 4565
Protoss_Zealot 7 8247
Protoss_Assimilator 1 7712
Protoss_Cybernetics_Core 1 9825
Protoss_Forge 1 10498
Protoss_Stargate 1 11852
Protoss_Photon_Cannon 2 12715
Protoss_Corsair 3 15207
15207
