Protoss_Gateway 2 5363
Protoss_Zealot 6 12833
Protoss_Assimilator 1 6160
Protoss_Forge 1 6655
Protoss_Photon_Cannon 1 7918
Protoss_Cybernetics_Core 1 8929
Protoss_Dragoon 1 10187
Protoss_Citadel_of_Adun 1 10599
Protoss_Ground_Weapons_1 1 13529
Leg_Enhancements 1 13570
Protoss_Nexus 1 16654
16654
