Protoss_Gateway 2 5209
Protoss_Zealot 12 13169
Protoss_Cybernetics_Core 1 8275
Protoss_Assimilator 1 8639
Protoss_Dragoon 1 10390
Protoss_Citadel_of_Adun 1 11411
Protoss_Templar_Archives 1 14092
Protoss_Forge 1 13861
Protoss_Nexus 1 16376
Leg_Enhancements 1 14365
16376
