Protoss_Forge 1 3759
Protoss_Nexus 1 8064
Protoss_Photon_Cannon 7 13211
Protoss_Gateway 3 14851
Protoss_Assimilator 2 14492
Protoss_Zealot 5 15010
Protoss_Cybernetics_Core 1 11752
Protoss_Citadel_of_Adun 1 13249
Protoss_Templar_Archives 1 15509
15509
