Protoss_Gateway 2 5219
Protoss_Zealot 14 15324
Protoss_Assimilator 1 8060
Protoss_Cybernetics_Core 1 10365
Protoss_Stargate 1 12242
Protoss_Citadel_of_Adun 1 12588
Protoss_Corsair 1 13188
Protoss_Forge 1 14888
15324
