Protoss_Gateway 2 5306
Protoss_Zealot 11 14761
Protoss_Assimilator 1 6870
Protoss_Cybernetics_Core 1 7978
Protoss_Forge 1 7995
Protoss_Dragoon 1 9739
Protoss_Citadel_of_Adun 1 11209
Protoss_Templar_Archives 1 13155
Protoss_Photon_Cannon 1 14230
Protoss_Ground_Weapons_1 1 13904
Leg_Enhancements 1 14358
Protoss_Nexus 1 17279
17279
