Protoss_Gateway 2 5011
Protoss_Zealot 10 13027
Protoss_Forge 1 8939
Protoss_Photon_Cannon 4 14158
Protoss_Nexus 1 13413
Protoss_Assimilator 1 12034
Protoss_Cybernetics_Core 1 15431
15431
