Protoss_Gateway 2 11098
Protoss_Zealot 9 13802
Protoss_Assimilator 1 5502
Protoss_Cybernetics_Core 1 6814
Protoss_Stargate 1 8702
Protoss_Dragoon 1 8466
Protoss_Citadel_of_Adun 1 9497
Protoss_Corsair 1 9814
Protoss_Forge 1 12125
Protoss_Templar_Archives 1 13461
Leg_Enhancements 1 13128
Protoss_High_Templar 2 15336
15336
