Protoss_Forge 1 3861
Protoss_Nexus 1 7969
Protoss_Photon_Cannon 7 15396
Protoss_Gateway 1 7818
Protoss_Assimilator 2 10890
Protoss_Cybernetics_Core 2 10960
Protoss_Stargate 2 14437
Protoss_Robotics_Facility 1 13444
Protoss_Corsair 3 15251
Protoss_Robotics_Support_Bay 1 14183
Protoss_Reaver 1 16149
16149
