Protoss_Gateway 2 5057
Protoss_Zealot 8 13436
Protoss_Forge 1 6305
Protoss_Photon_Cannon 4 14638
Protoss_Nexus 1 10947
Protoss_Assimilator 1 9727
Protoss_Cybernetics_Core 1 11695
Protoss_Stargate 1 13670
Protoss_Corsair 1 15061
15061
