Protoss_Gateway 2 4719
Protoss_Zealot 13 14790
Protoss_Forge 1 7052
Protoss_Photon_Cannon 2 10554
Protoss_Nexus 1 13135
Protoss_Assimilator 1 12056
Protoss_Cybernetics_Core 1 13763
Protoss_Stargate 1 16142
16142
