Protoss_Forge 1 5184
Protoss_Nexus 2 17162
Protoss_Photon_Cannon 3 15358
Protoss_Gateway 3 11791
Protoss_Assimilator 2 11655
Protoss_Cybernetics_Core 1 8838
Protoss_Zealot 2 11815
Protoss_Stargate 1 10730
Protoss_Citadel_of_Adun 1 11203
Protoss_Corsair 1 12017
Protoss_Templar_Archives 1 13091
Protoss_Dark_Templar 1 14354
Protoss_Robotics_Facility 1 16409
17162
