Protoss_Forge 1 3962
Protoss_Nexus 1 8181
Protoss_Photon_Cannon 7 12310
Protoss_Gateway 3 13252
Protoss_Zealot 9 15444
Protoss_Assimilator 1 12053
Protoss_Cybernetics_Core 1 14707
15444
