Protoss_Gateway 3 15061
Protoss_Assimilator 1 4512
Protoss_Zealot 10 14980
Protoss_Cybernetics_Core 1 7258
Protoss_Stargate 1 9530
Protoss_Dragoon 1 9300
Protoss_Forge 1 9749
Protoss_Corsair 1 10495
Protoss_Citadel_of_Adun 1 11897
Protoss_Photon_Cannon 1 14725
Protoss_Robotics_Facility 1 16402
16402
