Protoss_Forge 1 3898
Protoss_Photon_Cannon 4 14388
Protoss_Nexus 1 9369
Protoss_Gateway 2 12094
Protoss_Zealot 8 15339
Protoss_Assimilator 2 14614
Protoss_Cybernetics_Core 1 12511
Protoss_Citadel_of_Adun 1 14026
Protoss_Templar_Archives 1 15552
15552
