Protoss_Gateway 2 14086
Protoss_Assimilator 1 4652
Protoss_Zealot 6 12105
Protoss_Cybernetics_Core 1 7409
Protoss_Stargate 1 9310
Protoss_Dragoon 1 8992
Protoss_Corsair 1 10319
Protoss_Citadel_of_Adun 1 10872
Protoss_Forge 1 10567
Protoss_Photon_Cannon 1 12257
Protoss_Templar_Archives 1 13249
Protoss_Dark_Templar 2 15292
Protoss_High_Templar 1 15761
15761
