Protoss_Gateway 1 4111
Protoss_Assimilator 1 4353
Protoss_Zealot 6 11265
Protoss_Cybernetics_Core 1 7363
Protoss_Dragoon 1 8641
Protoss_Stargate 1 9176
Protoss_Citadel_of_Adun 1 9697
Protoss_Corsair 1 10144
Protoss_Templar_Archives 1 11729
Protoss_Forge 1 11667
Protoss_Dark_Templar 1 13017
Protoss_Photon_Cannon 1 13462
Protoss_High_Templar 1 14414
Protoss_Nexus 1 16553
16553
