Protoss_Gateway 1 4220
Protoss_Assimilator 2 5819
Protoss_Zealot 4 9286
Protoss_Forge 1 6740
Protoss_Cybernetics_Core 1 8982
Protoss_Citadel_of_Adun 1 10569
Protoss_Dragoon 1 10406
Protoss_Photon_Cannon 3 14155
Protoss_Templar_Archives 1 12315
Protoss_High_Templar 3 15794
Protoss_Nexus 1 16767
16767
