Protoss_Assimilator 1 3583
Protoss_Forge 1 4357
Protoss_Photon_Cannon 1 6070
Protoss_Gateway 3 8707
Protoss_Zealot 13 14872
Protoss_Ground_Weapons_1 1 10472
Protoss_Cybernetics_Core 1 12140
Protoss_Stargate 1 14731
14872
