Protoss_Forge 1 4147
Protoss_Photon_Cannon 6 15044
Protoss_Nexus 1 9467
Protoss_Gateway 2 15703
Protoss_Assimilator 2 10752
Protoss_Zealot 4 13732
Protoss_Cybernetics_Core 1 11298
Protoss_Stargate 1 13190
Protoss_Citadel_of_Adun 1 13843
Protoss_Robotics_Facility 1 14581
Protoss_Corsair 1 14139
Protoss_Templar_Archives 1 15548
15703
