Protoss_Forge 2 14742
Protoss_Nexus 1 8409
Protoss_Photon_Cannon 2 7986
Protoss_Assimilator 2 11995
Protoss_Gateway 4 14009
Protoss_Zealot 8 14054
Protoss_Cybernetics_Core 1 11279
Protoss_Citadel_of_Adun 1 13287
Protoss_Robotics_Facility 1 16377
16377
