Protoss_Gateway 2 5289
Protoss_Zealot 5 7371
Protoss_Assimilator 1 6829
Protoss_Cybernetics_Core 1 9492
Protoss_Forge 1 9869
Protoss_Citadel_of_Adun 1 11695
Protoss_Nexus 1 15254
Protoss_Photon_Cannon 1 13873
15254
