Protoss_Gateway 2 5341
Protoss_Zealot 11 12500
Protoss_Assimilator 1 6899
Protoss_Cybernetics_Core 1 9064
Protoss_Citadel_of_Adun 1 10984
Protoss_Shield_Battery 1 10604
Protoss_Templar_Archives 1 12593
Protoss_Forge 1 13163
Protoss_Dark_Templar 1 13814
Protoss_High_Templar 2 14915
Protoss_Photon_Cannon 1 14425
14915
