Protoss_Nexus 1 7227
Protoss_Forge 1 5753
Protoss_Gateway 3 11317
Protoss_Assimilator 2 10150
Protoss_Photon_Cannon 7 15554
Protoss_Zealot 10 13243
Protoss_Cybernetics_Core 1 9172
Protoss_Citadel_of_Adun 1 10906
Protoss_Templar_Archives 1 12350
Protoss_High_Templar 3 14981
Leg_Enhancements 1 13983
Protoss_Ground_Weapons_1 1 14235
15554
