Protoss_Forge 1 4092
Protoss_Nexus 1 7778
Protoss_Photon_Cannon 2 7833
Protoss_Gateway 5 12599
Protoss_Assimilator 2 9927
Protoss_Cybernetics_Core 1 10332
Protoss_Zealot 12 14995
Protoss_Citadel_of_Adun 1 12936
Protoss_Templar_Archives 1 14762
14995
