Protoss_Forge 1 4786
Protoss_Photon_Cannon 3 14553
Protoss_Nexus 2 15535
Protoss_Gateway 1 7981
Protoss_Assimilator 2 10946
Protoss_Cybernetics_Core 1 9489
Protoss_Stargate 1 11169
Protoss_Corsair 4 15005
Protoss_Robotics_Facility 1 13904
Protoss_Robotics_Support_Bay 1 14679
15535
