Protoss_Gateway 1 4394
Protoss_Assimilator 1 4615
Protoss_Zealot 4 10158
Protoss_Cybernetics_Core 1 7624
Protoss_Stargate 1 9310
Protoss_Citadel_of_Adun 1 9768
Protoss_Corsair 1 10261
Protoss_Templar_Archives 1 11224
Protoss_Dark_Templar 3 15168
Protoss_Forge 1 13698
Protoss_Nexus 1 15975
Protoss_Photon_Cannon 1 15371
15975
