Protoss_Nexus 1 7217
Protoss_Forge 1 6166
Protoss_Photon_Cannon 2 7956
Protoss_Gateway 4 11131
Protoss_Assimilator 2 12409
Protoss_Cybernetics_Core 1 10205
Protoss_Citadel_of_Adun 1 11802
Protoss_Dragoon 1 11650
Protoss_Zealot 12 14689
Protoss_Templar_Archives 1 15280
15280
