Protoss_Forge 1 3952
Protoss_Photon_Cannon 5 15808
Protoss_Nexus 1 9371
Protoss_Gateway 4 15238
Protoss_Assimilator 2 12599
Protoss_Zealot 2 13158
Protoss_Cybernetics_Core 1 10509
Protoss_Citadel_of_Adun 1 12579
Protoss_Templar_Archives 1 14169
Protoss_High_Templar 1 15600
15808
