Protoss_Nexus 1 7023
Protoss_Forge 1 5800
Protoss_Photon_Cannon 2 11486
Protoss_Gateway 4 12535
Protoss_Assimilator 2 10754
Protoss_Cybernetics_Core 1 9737
Protoss_Zealot 7 14607
Protoss_Citadel_of_Adun 1 11493
Protoss_Robotics_Facility 1 15374
15374
