Protoss_Forge 1 4572
Protoss_Photon_Cannon 2 15824
Protoss_Nexus 1 8294
Protoss_Gateway 4 13245
Protoss_Assimilator 2 15049
Protoss_Cybernetics_Core 1 9394
Protoss_Zealot 11 15342
Protoss_Citadel_of_Adun 1 11521
Protoss_Templar_Archives 1 14250
Protoss_Ground_Weapons_1 1 14287
Leg_Enhancements 1 14466
15824
