Protoss_Forge 1 4082
Protoss_Nexus 2 12617
Protoss_Gateway 1 7610
Protoss_Photon_Cannon 3 15414
Protoss_Assimilator 2 9831
Protoss_Cybernetics_Core 1 9722
Protoss_Stargate 1 11702
Protoss_Robotics_Facility 2 13631
Protoss_Zealot 1 12580
Protoss_Corsair 4 15567
Protoss_Robotics_Support_Bay 1 14097
Protoss_Shuttle 1 14813
15567
