Protoss_Forge 1 4783
Protoss_Photon_Cannon 8 14229
Protoss_Nexus 1 8791
Protoss_Gateway 1 8390
Protoss_Assimilator 2 12229
Protoss_Zealot 4 14794
Protoss_Cybernetics_Core 1 10864
Protoss_Stargate 1 12704
Protoss_Corsair 3 15576
Protoss_Citadel_of_Adun 1 15809
15809
