Protoss_Nexus 1 7079
Protoss_Forge 1 5778
Protoss_Gateway 2 9674
Protoss_Photon_Cannon 6 15799
Protoss_Assimilator 2 13362
Protoss_Zealot 10 15149
Protoss_Cybernetics_Core 1 10960
Protoss_Stargate 1 12856
Protoss_Citadel_of_Adun 1 12955
Protoss_Dragoon 1 12944
Protoss_Corsair 2 14849
15799
