Protoss_Forge 1 4068
Protoss_Photon_Cannon 3 12322
Protoss_Nexus 1 8402
Protoss_Gateway 2 13163
Protoss_Assimilator 2 12632
Protoss_Zealot 5 15532
Protoss_Cybernetics_Core 1 10668
Protoss_Stargate 1 12477
Protoss_Dragoon 1 12191
Protoss_Citadel_of_Adun 1 13886
Protoss_Corsair 1 13431
15532
