Protoss_Forge 2 12651
Protoss_Nexus 1 7852
Protoss_Photon_Cannon 7 15809
Protoss_Gateway 4 15454
Protoss_Assimilator 2 13382
Protoss_Zealot 6 15160
Protoss_Cybernetics_Core 1 10381
Protoss_Citadel_of_Adun 1 12918
Protoss_Templar_Archives 1 14623
15809
