Protoss_Forge 1 4313
Protoss_Nexus 1 7875
Protoss_Photon_Cannon 4 15265
Protoss_Gateway 3 13133
Protoss_Assimilator 2 10331
Protoss_Zealot 1 8730
Protoss_Cybernetics_Core 1 10256
Protoss_Dragoon 1 11454
Protoss_Citadel_of_Adun 1 11756
Protoss_Templar_Archives 1 13205
Protoss_High_Templar 4 15511
Protoss_Dark_Templar 1 14448
Protoss_Robotics_Facility 1 15529
Protoss_Archon 1 14882
15529
