Protoss_Forge 1 3757
Protoss_Photon_Cannon 4 15642
Protoss_Nexus 1 8425
Protoss_Gateway 3 12362
Protoss_Assimilator 1 7722
Protoss_Zealot 12 14800
Protoss_Cybernetics_Core 1 9593
Protoss_Citadel_of_Adun 1 11462
Protoss_Templar_Archives 1 14933
Leg_Enhancements 1 14416
15642
