Protoss_Forge 1 4590
Protoss_Photon_Cannon 3 12091
Protoss_Nexus 1 8329
Protoss_Gateway 2 13792
Protoss_Assimilator 2 9450
Protoss_Cybernetics_Core 1 9397
Protoss_Stargate 1 11146
Protoss_Citadel_of_Adun 1 11335
Protoss_Dragoon 1 11404
Protoss_Corsair 1 12087
Protoss_Templar_Archives 1 13420
Protoss_High_Templar 1 15241
15241
