Protoss_Forge 1 4381
Protoss_Nexus 1 8405
Protoss_Photon_Cannon 4 15418
Protoss_Gateway 4 15324
Protoss_Assimilator 2 11730
Protoss_Cybernetics_Core 1 9740
Protoss_Zealot 10 14584
Protoss_Citadel_of_Adun 1 11332
Protoss_Templar_Archives 1 13684
Leg_Enhancements 1 14261
Protoss_High_Templar 2 15704
15704
