Protoss_Nexus 1 6883
Protoss_Forge 1 5373
Protoss_Photon_Cannon 9 15730
Protoss_Gateway 3 10729
Protoss_Assimilator 2 13221
Protoss_Cybernetics_Core 1 8868
Protoss_Zealot 12 14497
Protoss_Citadel_of_Adun 1 10387
Protoss_Templar_Archives 1 13649
Leg_Enhancements 1 13316
Protoss_High_Templar 2 15189
Protoss_Ground_Weapons_1 1 14085
15730
