Protoss_Forge 1 4818
Protoss_Photon_Cannon 6 15727
Protoss_Gateway 5 15636
Protoss_Nexus 1 8978
Protoss_Assimilator 2 11155
Protoss_Zealot 2 10000
Protoss_Cybernetics_Core 1 10793
Protoss_Stargate 1 13067
Protoss_Citadel_of_Adun 1 13447
Protoss_Corsair 2 15214
Protoss_Templar_Archives 1 15226
15727
