Protoss_Gateway 1 4318
Protoss_Assimilator 1 4719
Protoss_Zealot 4 10195
Protoss_Cybernetics_Core 1 6826
Protoss_Dragoon 1 8341
Protoss_Stargate 1 9274
Protoss_Citadel_of_Adun 1 10110
Protoss_Corsair 1 10517
Protoss_Templar_Archives 1 11560
Protoss_Forge 1 11134
Protoss_High_Templar 1 15314
15314
