Protoss_Forge 1 4330
Protoss_Photon_Cannon 2 13591
Protoss_Nexus 1 8636
Protoss_Gateway 2 13518
Protoss_Assimilator 2 10050
Protoss_Zealot 1 8601
Protoss_Cybernetics_Core 1 9428
Protoss_Stargate 1 11321
Protoss_Citadel_of_Adun 1 11674
Protoss_Corsair 3 14420
Protoss_Templar_Archives 1 13166
Protoss_Robotics_Facility 1 13748
Protoss_Dark_Templar 1 14559
Protoss_High_Templar 1 14881
Protoss_Shuttle 1 15178
15178
