Protoss_Gateway 2 15453
Protoss_Assimilator 1 4357
Protoss_Zealot 5 13094
Protoss_Cybernetics_Core 1 8566
Protoss_Stargate 1 10304
Protoss_Dragoon 1 9982
Protoss_Citadel_of_Adun 1 10867
Protoss_Forge 1 11424
Protoss_Corsair 1 11546
Protoss_Templar_Archives 1 12870
Protoss_Photon_Cannon 2 14545
Protoss_Dark_Templar 2 15470
Protoss_Robotics_Facility 1 15128
15470
