Protoss_Forge 1 4128
Protoss_Nexus 1 7830
Protoss_Gateway 2 12604
Protoss_Photon_Cannon 7 14695
Protoss_Assimilator 2 10047
Protoss_Zealot 4 11153
Protoss_Cybernetics_Core 1 9481
Protoss_Citadel_of_Adun 1 10994
Protoss_Templar_Archives 1 12645
Protoss_High_Templar 3 15168
15168
