Protoss_Forge 1 4906
Protoss_Nexus 1 7762
Protoss_Photon_Cannon 3 14193
Protoss_Gateway 1 7457
Protoss_Assimilator 2 9626
Protoss_Cybernetics_Core 1 9304
Protoss_Stargate 1 11071
Protoss_Dragoon 1 10722
Protoss_Citadel_of_Adun 1 11676
Protoss_Zealot 1 11584
Protoss_Robotics_Facility 1 13666
14193
