Protoss_Nexus 1 6956
Protoss_Gateway 3 15468
Protoss_Forge 1 6374
Protoss_Assimilator 2 10903
Protoss_Photon_Cannon 2 15145
Protoss_Zealot 8 15093
Protoss_Cybernetics_Core 1 10089
Protoss_Dragoon 1 11387
Protoss_Stargate 1 12419
Protoss_Citadel_of_Adun 1 12220
Protoss_Corsair 2 15266
Protoss_Templar_Archives 1 14124
Protoss_Ground_Weapons_1 1 13872
15468
