Protoss_Forge 1 4337
Protoss_Photon_Cannon 3 15808
Protoss_Nexus 1 9820
Protoss_Gateway 3 13101
Protoss_Assimilator 2 14050
Protoss_Cybernetics_Core 1 10389
Protoss_Zealot 11 15471
Protoss_Citadel_of_Adun 1 12029
Protoss_Templar_Archives 1 15548
15808
