Protoss_Forge 1 4271
Protoss_Photon_Cannon 5 15259
Protoss_Nexus 1 9148
Protoss_Gateway 2 14042
Protoss_Assimilator 2 10592
Protoss_Cybernetics_Core 1 9772
Protoss_Zealot 3 11633
Protoss_Citadel_of_Adun 1 11287
Protoss_Templar_Archives 1 13265
Protoss_High_Templar 2 15569
15569
