Protoss_Gateway 1 4425
Protoss_Assimilator 2 14960
Protoss_Zealot 4 9017
Protoss_Cybernetics_Core 1 8206
Protoss_Citadel_of_Adun 1 9722
Protoss_Dragoon 1 10137
Protoss_Templar_Archives 1 11203
Protoss_Dark_Templar 1 12399
Protoss_Forge 1 12229
Protoss_Nexus 1 14564
Protoss_High_Templar 2 14726
Protoss_Photon_Cannon 4 15753
15753
