Protoss_Forge 1 4666
Protoss_Photon_Cannon 7 15666
Protoss_Nexus 1 9309
Protoss_Gateway 3 13079
Protoss_Assimilator 2 11074
Protoss_Zealot 1 9377
Protoss_Cybernetics_Core 1 9974
Protoss_Dragoon 1 11170
Protoss_Citadel_of_Adun 1 11430
Protoss_Templar_Archives 1 13438
Protoss_Dark_Templar 1 14641
Protoss_High_Templar 3 15783
15783
