Protoss_Gateway 3 15459
Protoss_Assimilator 1 4394
Protoss_Cybernetics_Core 1 5730
Protoss_Stargate 1 7578
Protoss_Forge 1 7281
Protoss_Photon_Cannon 3 14186
Protoss_Corsair 2 9917
Protoss_Zealot 6 13173
Protoss_Citadel_of_Adun 1 11332
Protoss_Templar_Archives 1 12975
Protoss_Dark_Templar 2 14627
Protoss_Ground_Weapons_1 1 13297
15459
