Protoss_Forge 1 4363
Protoss_Photon_Cannon 3 15262
Protoss_Nexus 1 9169
Protoss_Gateway 3 14450
Protoss_Assimilator 2 10804
Protoss_Cybernetics_Core 1 10122
Protoss_Zealot 2 10534
Protoss_Stargate 1 11822
Protoss_Dragoon 1 11663
Protoss_Citadel_of_Adun 1 12706
Protoss_Corsair 3 15332
Protoss_Templar_Archives 1 14184
Protoss_Dark_Templar 2 15439
15439
