Protoss_Forge 1 3953
Protoss_Nexus 1 7808
Protoss_Gateway 4 14238
Protoss_Photon_Cannon 2 13601
Protoss_Assimilator 2 9956
Protoss_Zealot 7 15419
Protoss_Cybernetics_Core 1 9446
Protoss_Dragoon 1 11132
Protoss_Robotics_Facility 1 12526
Protoss_Citadel_of_Adun 1 12561
Protoss_Shuttle 1 14491
Protoss_Robotics_Support_Bay 1 13933
Protoss_Templar_Archives 1 15118
Protoss_Reaver 1 16049
16049
