Protoss_Forge 1 4267
Protoss_Photon_Cannon 3 14581
Protoss_Nexus 1 8191
Protoss_Gateway 3 13498
Protoss_Assimilator 2 9653
Protoss_Cybernetics_Core 1 9396
Protoss_Zealot 5 13501
Protoss_Dragoon 1 10629
Protoss_Stargate 1 11263
Protoss_Citadel_of_Adun 1 11701
Protoss_Corsair 2 13158
Protoss_Templar_Archives 1 13207
Protoss_Dark_Templar 2 15824
Protoss_High_Templar 2 15004
15824
