Protoss_Forge 1 4117
Protoss_Photon_Cannon 5 15587
Protoss_Nexus 1 8412
Protoss_Gateway 1 8636
Protoss_Assimilator 2 12519
Protoss_Zealot 4 14710
Protoss_Cybernetics_Core 1 12011
Protoss_Stargate 1 13761
Protoss_Citadel_of_Adun 2 15337
Protoss_Corsair 1 14775
15587
