Protoss_Nexus 1 7519
Protoss_Forge 1 6115
Protoss_Gateway 2 12065
Protoss_Photon_Cannon 1 7662
Protoss_Assimilator 2 10764
Protoss_Zealot 6 14819
Protoss_Cybernetics_Core 1 10199
Protoss_Citadel_of_Adun 1 11917
Protoss_Templar_Archives 1 14764
14819
