Protoss_Nexus 1 7039
Protoss_Forge 1 5581
Protoss_Photon_Cannon 3 15041
Protoss_Gateway 3 14843
Protoss_Assimilator 2 10347
Protoss_Cybernetics_Core 1 8990
Protoss_Zealot 2 11124
Protoss_Stargate 1 10730
Protoss_Citadel_of_Adun 1 11266
Protoss_Corsair 2 12566
Protoss_Templar_Archives 1 14218
Protoss_Robotics_Facility 1 14837
Protoss_Dark_Templar 1 15549
Protoss_High_Templar 1 15592
15592
