Protoss_Assimilator 1 3664
Protoss_Gateway 1 4903
Protoss_Cybernetics_Core 1 6387
Protoss_Stargate 1 8099
Protoss_Dragoon 1 7697
Protoss_Robotics_Facility 1 9310
Protoss_Corsair 6 13932
Protoss_Forge 1 9302
Protoss_Shuttle 1 11543
Protoss_Photon_Cannon 3 14221
Protoss_Robotics_Support_Bay 1 13517
Protoss_Nexus 1 16449
Protoss_Reaver 1 15637
16449
