Protoss_Gateway 2 8654
Protoss_Zealot 3 6892
Protoss_Assimilator 1 5407
Protoss_Cybernetics_Core 1 8011
Protoss_Dragoon 8 13757
Protoss_Robotics_Facility 1 11596
Protoss_Observatory 1 12297
Singularity_Charge 1 11741
Protoss_Observer 1 13378
Protoss_Citadel_of_Adun 1 14611
Protoss_Nexus 1 16906
16906
