Protoss_Gateway 2 5133
Protoss_Zealot 7 10668
Protoss_Nexus 1 10705
Protoss_Assimilator 2 13512
Protoss_Cybernetics_Core 1 10912
Protoss_Citadel_of_Adun 1 12438
Protoss_Forge 1 12639
Protoss_Dragoon 2 13239
Protoss_Templar_Archives 1 14191
Protoss_Photon_Cannon 1 14169
Protoss_Dark_Templar 2 15393
15393
