Protoss_Gateway 3 11628
Protoss_Assimilator 1 5234
Protoss_Zealot 2 6327
Protoss_Cybernetics_Core 1 7331
Protoss_Dragoon 12 15601
Protoss_Robotics_Facility 1 10737
Protoss_Observatory 1 11527
Singularity_Charge 1 11176
Protoss_Observer 3 14961
15601
