Protoss_Gateway 3 15772
Protoss_Zealot 6 8756
Protoss_Assimilator 1 8050
Protoss_Shield_Battery 1 9026
Protoss_Cybernetics_Core 2 10549
Protoss_Nexus 1 12982
Protoss_Dragoon 5 14583
Protoss_Robotics_Facility 1 15025
15772
