Protoss_Gateway 3 15817
Protoss_Zealot 7 10027
Protoss_Nexus 1 10830
Protoss_Assimilator 1 9087
Protoss_Cybernetics_Core 1 10024
Protoss_Forge 1 11516
Protoss_Citadel_of_Adun 1 12039
Protoss_Photon_Cannon 1 13093
Protoss_Dragoon 4 15761
15817
