Protoss_Gateway 4 15421
Protoss_Assimilator 2 7984
Protoss_Zealot 9 10079
Protoss_Cybernetics_Core 1 9735
Protoss_Dragoon 8 15487
Protoss_Robotics_Facility 1 14076
Singularity_Charge 1 13927
Protoss_Observatory 1 15029
15487
