Protoss_Gateway 4 15977
Protoss_Zealot 6 14130
Protoss_Assimilator 1 7515
Protoss_Cybernetics_Core 1 8563
Protoss_Dragoon 9 15490
Protoss_Nexus 1 15119
Protoss_Robotics_Facility 1 14957
Singularity_Charge 1 14194
15977
