Protoss_Nexus 1 7882
Protoss_Gateway 6 14825
Protoss_Assimilator 1 7217
Protoss_Zealot 5 14768
Protoss_Cybernetics_Core 1 8496
Protoss_Dragoon 6 14963
Protoss_Robotics_Facility 1 11100
Protoss_Observatory 1 11991
Protoss_Observer 1 13136
Protoss_Citadel_of_Adun 1 14569
Singularity_Charge 1 14182
14963
