Protoss_Nexus 1 7416
Protoss_Gateway 2 9233
Protoss_Zealot 4 11001
Protoss_Assimilator 2 10861
Protoss_Cybernetics_Core 1 10580
Protoss_Forge 1 10729
Protoss_Dragoon 6 14872
Protoss_Photon_Cannon 3 13904
Protoss_Citadel_of_Adun 1 14352
Protoss_Templar_Archives 1 15892
15892
