Protoss_Nexus 1 7076
Protoss_Gateway 4 14434
Protoss_Assimilator 2 13603
Protoss_Cybernetics_Core 1 8069
Protoss_Dragoon 11 15642
Protoss_Robotics_Facility 1 12392
Protoss_Zealot 4 15497
Singularity_Charge 1 12268
Protoss_Observatory 1 13152
Protoss_Citadel_of_Adun 1 14551
Protoss_Observer 1 15257
15642
