Protoss_Nexus 1 7732
Protoss_Gateway 4 12165
Protoss_Assimilator 2 13921
Protoss_Cybernetics_Core 1 8494
Protoss_Zealot 3 15427
Protoss_Dragoon 11 14650
Protoss_Citadel_of_Adun 1 13596
Protoss_Forge 1 13783
Singularity_Charge 1 12997
Protoss_Photon_Cannon 1 15165
15427
