Protoss_Gateway 2 5186
Protoss_Zealot 5 8080
Protoss_Assimilator 1 7433
Protoss_Cybernetics_Core 1 8882
Protoss_Robotics_Facility 1 10961
Protoss_Dragoon 1 10749
Protoss_Shuttle 1 12377
Protoss_Robotics_Support_Bay 1 11709
Protoss_Nexus 1 14548
Protoss_Reaver 1 13935
Protoss_Observatory 1 13560
Protoss_Observer 1 14759
14759
