Protoss_Gateway 3 14651
Protoss_Assimilator 1 4660
Protoss_Zealot 3 7352
Protoss_Cybernetics_Core 1 8603
Protoss_Dragoon 7 14022
Protoss_Robotics_Facility 1 11378
Protoss_Observatory 1 12224
Protoss_Observer 2 14566
Singularity_Charge 1 13867
14651
