Protoss_Gateway 2 9409
Protoss_Zealot 6 15233
Protoss_Assimilator 1 5442
Protoss_Cybernetics_Core 1 8130
Protoss_Citadel_of_Adun 1 9611
Protoss_Dragoon 1 9563
Protoss_Templar_Archives 1 11054
Protoss_Forge 1 11667
Protoss_Dark_Templar 2 12268
Protoss_High_Templar 2 13368
Protoss_Photon_Cannon 4 15193
Protoss_Nexus 1 15406
15406
