Protoss_Nexus 1 7117
Protoss_Assimilator 1 5712
Protoss_Gateway 4 13909
Protoss_Cybernetics_Core 1 8614
Protoss_Dragoon 9 15139
Protoss_Robotics_Facility 1 12373
Protoss_Observatory 1 13506
Singularity_Charge 1 12938
Protoss_Forge 1 14153
Protoss_Observer 1 14849
Protoss_Photon_Cannon 2 15603
15603
