Protoss_Nexus 2 16137
Protoss_Gateway 3 12113
Protoss_Assimilator 2 14850
Protoss_Cybernetics_Core 1 7982
Protoss_Zealot 1 8104
Protoss_Dragoon 10 15768
Protoss_Robotics_Facility 1 14031
Singularity_Charge 1 12452
Protoss_Observatory 1 14758
Protoss_Forge 1 15065
16137
