Protoss_Gateway 2 10811
Protoss_Zealot 3 7041
Protoss_Assimilator 1 5532
Protoss_Cybernetics_Core 1 7185
Protoss_Dragoon 8 15821
Protoss_Robotics_Facility 1 12145
Singularity_Charge 1 11173
Protoss_Observatory 1 13018
Protoss_Observer 2 14914
Protoss_Nexus 1 16364
Protoss_Robotics_Support_Bay 1 15039
16364
