Protoss_Gateway 2 5061
Protoss_Zealot 5 7890
Protoss_Assimilator 1 5906
Protoss_Cybernetics_Core 1 9495
Protoss_Dragoon 10 15490
Protoss_Robotics_Facility 1 12294
Protoss_Shuttle 1 13814
Protoss_Observatory 1 13314
Singularity_Charge 1 13468
Protoss_Observer 1 14873
Protoss_Robotics_Support_Bay 1 15118
15490
