Protoss_Gateway 3 10736
Protoss_Assimilator 2 7864
Protoss_Zealot 5 8203
Protoss_Cybernetics_Core 1 9582
Protoss_Dragoon 11 14937
Singularity_Charge 1 13600
Protoss_Nexus 1 17062
17062
