Protoss_Gateway 2 9946
Protoss_Assimilator 1 4258
Protoss_Cybernetics_Core 1 6642
Protoss_Zealot 1 6792
Protoss_Dragoon 11 15206
Singularity_Charge 1 10494
Protoss_Robotics_Facility 1 12807
Protoss_Robotics_Support_Bay 1 14779
Protoss_Nexus 1 17253
17253
