Protoss_Gateway 3 15934
Protoss_Assimilator 1 4337
Protoss_Cybernetics_Core 1 5853
Protoss_Dragoon 6 15139
Protoss_Citadel_of_Adun 1 10548
Protoss_Nexus 1 12388
Singularity_Charge 1 10384
Protoss_Templar_Archives 1 12043
Protoss_Dark_Templar 3 15511
Protoss_Robotics_Facility 1 14773
15934
