Protoss_Gateway 2 8478
Protoss_Assimilator 1 4694
Protoss_Zealot 9 11259
Protoss_Cybernetics_Core 1 10133
Protoss_Dragoon 2 12344
Protoss_Robotics_Facility 1 13418
Protoss_Forge 1 13723
Protoss_Photon_Cannon 1 15335
15335
