Protoss_Gateway 2 7009
Protoss_Zealot 7 9668
Protoss_Assimilator 1 7755
Protoss_Cybernetics_Core 1 9374
Protoss_Dragoon 10 15339
Protoss_Robotics_Facility 1 15452
Singularity_Charge 1 13919
15452
