Protoss_Gateway 4 12059
Protoss_Assimilator 1 4666
Protoss_Cybernetics_Core 1 5948
Protoss_Dragoon 12 15819
Protoss_Robotics_Facility 1 9475
Protoss_Observatory 1 10172
Protoss_Observer 1 11190
Protoss_Zealot 6 14453
Singularity_Charge 1 14475
15819
