Protoss_Gateway 3 10293
Protoss_Zealot 10 13739
Protoss_Assimilator 1 7297
Protoss_Cybernetics_Core 1 9061
Protoss_Dragoon 8 15300
Protoss_Robotics_Facility 1 15055
Singularity_Charge 1 14248
15300
