Protoss_Gateway 3 12030
Protoss_Assimilator 1 4473
Protoss_Zealot 3 7489
Protoss_Cybernetics_Core 1 6624
Protoss_Dragoon 12 15677
Protoss_Robotics_Facility 1 12563
Singularity_Charge 1 11407
Protoss_Observatory 1 13775
15677
