Protoss_Gateway 3 15759
Protoss_Zealot 4 9986
Protoss_Assimilator 1 5434
Protoss_Cybernetics_Core 1 7151
Protoss_Robotics_Facility 1 9294
Protoss_Dragoon 5 14823
Protoss_Shuttle 1 10849
Protoss_Robotics_Support_Bay 1 10588
Protoss_Reaver 2 15764
Protoss_Observatory 1 11903
Protoss_Observer 1 14827
15764
