Protoss_Nexus 2 14617
Protoss_Gateway 3 9241
Protoss_Assimilator 1 6874
Protoss_Cybernetics_Core 1 7796
Protoss_Dragoon 5 13727
Protoss_Zealot 3 14285
Protoss_Robotics_Facility 1 12907
Protoss_Citadel_of_Adun 1 13572
Singularity_Charge 1 12148
Protoss_Observatory 1 13640
Protoss_Shuttle 1 14755
Protoss_Forge 1 15471
15471
