Protoss_Assimilator 1 3434
Protoss_Gateway 2 9513
Protoss_Cybernetics_Core 1 6329
Protoss_Robotics_Facility 1 8268
Protoss_Dragoon 8 14239
Protoss_Observatory 1 9001
Protoss_Observer 2 10900
Protoss_Shuttle 1 12345
Singularity_Charge 1 11343
Protoss_Robotics_Support_Bay 1 12370
Protoss_Reaver 2 15896
15896
