Protoss_Gateway 2 9939
Protoss_Assimilator 1 4701
Protoss_Cybernetics_Core 1 5947
Protoss_Zealot 1 6570
Protoss_Dragoon 12 15590
Singularity_Charge 1 10160
Protoss_Robotics_Facility 1 12693
Protoss_Shuttle 1 15309
Protoss_Robotics_Support_Bay 1 15045
Protoss_Observatory 1 15347
15590
