Protoss_Gateway 2 5254
Protoss_Zealot 6 10359
Protoss_Assimilator 1 7919
Protoss_Cybernetics_Core 1 8979
Protoss_Robotics_Facility 1 13194
Protoss_Dragoon 5 15598
Protoss_Robotics_Support_Bay 1 14360
15598
