Protoss_Gateway 2 12536
Protoss_Zealot 3 7561
Protoss_Assimilator 1 5740
Protoss_Cybernetics_Core 1 7476
Protoss_Dragoon 8 15332
Protoss_Robotics_Facility 1 11641
Protoss_Observatory 1 12524
Singularity_Charge 1 12806
Protoss_Observer 1 14146
Protoss_Robotics_Support_Bay 1 14404
15332
