Protoss_Gateway 2 12626
Protoss_Assimilator 1 5164
Protoss_Zealot 2 6932
Protoss_Cybernetics_Core 1 6823
Protoss_Dragoon 4 12146
Protoss_Robotics_Facility 2 16384
Protoss_Citadel_of_Adun 1 10678
Protoss_Templar_Archives 1 12264
Protoss_Dark_Templar 3 14637
Protoss_Forge 1 15305
16384
