Protoss_Gateway 2 7530
Protoss_Assimilator 1 4600
Protoss_Zealot 3 7473
Protoss_Cybernetics_Core 1 7009
Protoss_Dragoon 8 14092
Protoss_Citadel_of_Adun 1 12506
Protoss_Templar_Archives 1 13968
Singularity_Charge 1 13370
Protoss_Dark_Templar 2 15241
Protoss_Forge 1 15368
15368
