Protoss_Gateway 5 15579
Protoss_Assimilator 1 4659
Protoss_Cybernetics_Core 1 6176
Protoss_Dragoon 8 14966
Protoss_Robotics_Facility 1 9317
Protoss_Observatory 1 10311
Protoss_Nexus 1 12857
Protoss_Observer 2 13041
Singularity_Charge 1 12162
15579
