Protoss_Gateway 2 8970
Protoss_Zealot 3 7480
Protoss_Assimilator 1 6049
Protoss_Cybernetics_Core 1 7675
Protoss_Dragoon 11 15635
Protoss_Robotics_Facility 1 13807
Singularity_Charge 1 12082
Protoss_Robotics_Support_Bay 1 14592
Protoss_Shuttle 1 15318
Protoss_Observatory 1 14745
15635
