Protoss_Gateway 2 15286
Protoss_Zealot 3 7553
Protoss_Assimilator 1 6012
Protoss_Cybernetics_Core 1 7351
Protoss_Dragoon 6 15724
Protoss_Robotics_Facility 1 10470
Protoss_Shuttle 1 11989
Protoss_Observatory 1 11445
Protoss_Observer 1 12832
Protoss_Robotics_Support_Bay 1 13061
Singularity_Charge 1 13538
Protoss_Reaver 1 15417
Protoss_Nexus 1 17096
17096
