Protoss_Gateway 3 13666
Protoss_Assimilator 1 4373
Protoss_Cybernetics_Core 1 5606
Protoss_Dragoon 8 14012
Protoss_Nexus 1 12630
Singularity_Charge 1 9858
Protoss_Robotics_Facility 1 13238
Protoss_Robotics_Support_Bay 1 14435
Protoss_Zealot 2 14944
14944
