Protoss_Gateway 4 13425
Protoss_Zealot 13 14859
Protoss_Nexus 1 8978
Protoss_Assimilator 2 10608
Protoss_Cybernetics_Core 1 10283
Protoss_Dragoon 2 11673
Protoss_Citadel_of_Adun 1 12476
Protoss_Robotics_Facility 1 14804
Protoss_Forge 1 15102
15102
