Protoss_Gateway 4 15931
Protoss_Zealot 10 11351
Protoss_Nexus 1 11803
Protoss_Assimilator 2 13720
Protoss_Cybernetics_Core 1 11724
Protoss_Dragoon 6 15783
Protoss_Robotics_Facility 1 15989
15989
