Protoss_Gateway 2 5092
Protoss_Zealot 5 7634
Protoss_Assimilator 1 6539
Protoss_Cybernetics_Core 1 7580
Protoss_Dragoon 9 15705
Protoss_Forge 1 11038
Singularity_Charge 1 11460
Protoss_Nexus 1 14957
Protoss_Photon_Cannon 2 14103
15705
