Protoss_Gateway 2 9077
Protoss_Assimilator 1 4382
Protoss_Zealot 3 7012
Protoss_Cybernetics_Core 1 6991
Protoss_Dragoon 6 11831
Protoss_Citadel_of_Adun 1 12596
Protoss_Robotics_Facility 1 14198
Protoss_Templar_Archives 1 14036
Protoss_Shuttle 1 15593
Protoss_Dark_Templar 2 15505
Protoss_Observatory 1 15317
15593
