Protoss_Assimilator 1 3727
Protoss_Gateway 1 4748
Protoss_Cybernetics_Core 1 6494
Protoss_Robotics_Facility 1 8422
Protoss_Dragoon 4 14951
Protoss_Robotics_Support_Bay 1 9148
Protoss_Shuttle 4 15816
Protoss_Reaver 1 11722
Gravitic_Drive 1 12982
15816
