Protoss_Gateway 2 5061
Protoss_Zealot 11 12233
Protoss_Nexus 1 10322
Protoss_Assimilator 2 14414
Protoss_Cybernetics_Core 1 11900
Protoss_Shield_Battery 1 12452
Protoss_Dragoon 2 13804
Protoss_Citadel_of_Adun 1 14699
14699
