Protoss_Gateway 2 5156
Protoss_Zealot 14 14753
Protoss_Nexus 1 10468
Protoss_Assimilator 1 9510
Protoss_Cybernetics_Core 1 10829
Protoss_Citadel_of_Adun 1 12567
Protoss_Templar_Archives 1 14329
Protoss_Forge 1 13946
Protoss_Shield_Battery 1 14404
14753
