Protoss_Gateway 2 11349
Protoss_Zealot 3 7890
Protoss_Assimilator 1 5373
Protoss_Cybernetics_Core 1 7334
Protoss_Dragoon 7 14275
Protoss_Citadel_of_Adun 1 11156
Protoss_Robotics_Facility 1 12745
Protoss_Observatory 1 13683
Singularity_Charge 1 13412
Protoss_Observer 1 14727
Protoss_Nexus 1 17001
17001
