Protoss_Gateway 4 14383
Protoss_Zealot 5 10024
Protoss_Nexus 1 9876
Protoss_Assimilator 2 12283
Protoss_Cybernetics_Core 1 9914
Protoss_Dragoon 5 14937
Protoss_Forge 1 11809
Protoss_Robotics_Facility 1 14259
Protoss_Photon_Cannon 1 15101
Protoss_Shuttle 1 15672
15672
