Protoss_Gateway 4 13776
Protoss_Zealot 5 11276
Protoss_Nexus 2 16980
Protoss_Assimilator 2 11039
Protoss_Cybernetics_Core 1 9864
Protoss_Citadel_of_Adun 1 11475
Protoss_Dragoon 1 11384
Protoss_Templar_Archives 1 12927
Protoss_Robotics_Facility 1 13844
Protoss_Forge 1 13741
Protoss_Dark_Templar 2 14205
Protoss_Observatory 1 14574
Protoss_Photon_Cannon 2 15772
Protoss_High_Templar 2 15458
16980
