Protoss_Gateway 3 12579
Protoss_Assimilator 1 4578
Protoss_Zealot 1 5197
Protoss_Cybernetics_Core 1 7021
Protoss_Dragoon 9 15230
Protoss_Nexus 1 11842
Protoss_Robotics_Facility 1 12165
Singularity_Charge 1 10840
Protoss_Observatory 1 12936
Protoss_Observer 2 14914
Protoss_Citadel_of_Adun 1 14704
15230
