Protoss_Gateway 3 13827
Protoss_Assimilator 1 4738
Protoss_Zealot 2 7009
Protoss_Cybernetics_Core 1 7262
Protoss_Dragoon 10 15487
Protoss_Robotics_Facility 1 12652
Singularity_Charge 1 11861
Protoss_Shuttle 1 14077
Protoss_Robotics_Support_Bay 1 13986
Protoss_Observatory 1 14158
Protoss_Reaver 1 15729
15729
