Protoss_Gateway 4 15504
Protoss_Zealot 8 10729
Protoss_Nexus 1 11206
Protoss_Assimilator 2 13976
Protoss_Forge 1 10472
Protoss_Cybernetics_Core 1 11948
Protoss_Photon_Cannon 3 15800
Protoss_Dragoon 4 15585
15800
