Protoss_Gateway 4 15690
Protoss_Zealot 5 10044
Protoss_Nexus 1 9984
Protoss_Assimilator 2 10706
Protoss_Cybernetics_Core 1 9523
Protoss_Dragoon 6 15115
Protoss_Citadel_of_Adun 1 12412
Protoss_Robotics_Facility 1 13615
Protoss_Forge 1 13786
Protoss_Templar_Archives 1 14578
Protoss_Observatory 1 14552
Protoss_Photon_Cannon 1 15592
15690
