Protoss_Gateway 3 14044
Protoss_Assimilator 1 4359
Protoss_Cybernetics_Core 1 5958
Protoss_Dragoon 12 15812
Protoss_Robotics_Facility 1 10653
Singularity_Charge 1 10040
Protoss_Nexus 1 13574
Protoss_Observatory 1 11631
Protoss_Observer 2 13761
15812
