Protoss_Gateway 2 5133
Protoss_Zealot 11 13460
Protoss_Nexus 2 16416
Protoss_Assimilator 2 11540
Protoss_Cybernetics_Core 1 9858
Protoss_Dragoon 2 11088
Protoss_Citadel_of_Adun 1 11898
Protoss_Templar_Archives 1 13527
Protoss_Forge 1 13068
Protoss_Dark_Templar 2 15095
Protoss_Photon_Cannon 2 15660
16416
