Protoss_Gateway 3 15689
Protoss_Zealot 5 10507
Protoss_Nexus 1 10217
Protoss_Assimilator 2 9962
Protoss_Cybernetics_Core 1 9933
Protoss_Citadel_of_Adun 1 11988
Protoss_Robotics_Facility 1 13416
Protoss_Dragoon 4 14960
Protoss_Templar_Archives 1 13864
Protoss_Forge 1 14312
Protoss_Observatory 1 14255
Protoss_Photon_Cannon 1 15648
Protoss_Observer 1 15459
15689
