Protoss_Gateway 3 9945
Protoss_Zealot 5 9848
Protoss_Assimilator 2 15517
Protoss_Cybernetics_Core 1 7644
Protoss_Dragoon 6 15086
Protoss_Forge 1 11312
Protoss_Photon_Cannon 2 14343
Protoss_Nexus 1 14616
Singularity_Charge 1 12274
Protoss_Citadel_of_Adun 1 14023
Protoss_Robotics_Facility 1 15474
Protoss_Templar_Archives 1 15646
15646
