Protoss_Gateway 2 9811
Protoss_Zealot 3 6930
Protoss_Assimilator 1 7347
Protoss_Nexus 1 9406
Protoss_Cybernetics_Core 1 8887
Protoss_Forge 1 8862
Protoss_Dragoon 7 15648
Protoss_Photon_Cannon 3 15211
Protoss_Robotics_Facility 1 14220
Singularity_Charge 1 13614
Protoss_Observatory 1 14911
Protoss_Citadel_of_Adun 1 16028
16028
