Protoss_Gateway 2 4995
Protoss_Zealot 9 9453
Protoss_Assimilator 1 7846
Protoss_Cybernetics_Core 1 9525
Protoss_Dragoon 10 15683
Protoss_Robotics_Facility 1 14612
Singularity_Charge 1 14106
15683
