Protoss_Gateway 3 15702
Protoss_Zealot 5 12125
Protoss_Nexus 1 8876
Protoss_Forge 1 8080
Protoss_Assimilator 2 10422
Protoss_Cybernetics_Core 1 9754
Protoss_Photon_Cannon 3 13214
Protoss_Dragoon 5 15385
Protoss_Robotics_Facility 1 12826
Protoss_Observatory 1 13517
Protoss_Observer 1 14546
15702
