Protoss_Gateway 3 15153
Protoss_Assimilator 1 4496
Protoss_Zealot 2 6880
Protoss_Cybernetics_Core 1 6901
Protoss_Dragoon 8 15171
Protoss_Robotics_Facility 1 10608
Protoss_Robotics_Support_Bay 1 11316
Protoss_Observatory 1 11615
Singularity_Charge 1 11243
Protoss_Observer 1 12646
Protoss_Nexus 1 15257
Protoss_Reaver 1 14427
15257
