Protoss_Gateway 4 14748
Protoss_Zealot 11 14508
Protoss_Nexus 1 9979
Protoss_Assimilator 2 12651
Protoss_Cybernetics_Core 1 10561
Protoss_Citadel_of_Adun 1 12067
Protoss_Dragoon 2 12513
Protoss_Templar_Archives 1 13934
Protoss_Forge 1 14145
Protoss_Dark_Templar 2 15221
Protoss_Photon_Cannon 2 15641
15641
