Protoss_Gateway 2 12415
Protoss_Assimilator 1 4191
Protoss_Cybernetics_Core 1 5690
Protoss_Dragoon 8 14691
Protoss_Robotics_Facility 1 9537
Protoss_Observatory 1 10393
Singularity_Charge 1 9768
Protoss_Shuttle 1 11347
Protoss_Observer 2 13071
Protoss_Robotics_Support_Bay 1 12610
Protoss_Reaver 1 14842
14842
