Protoss_Gateway 2 4992
Protoss_Zealot 7 10425
Protoss_Nexus 1 9938
Protoss_Assimilator 2 12435
Protoss_Cybernetics_Core 1 10531
Protoss_Citadel_of_Adun 1 12162
Protoss_Dragoon 2 12221
Protoss_Templar_Archives 1 13627
Protoss_Forge 1 13801
Protoss_Dark_Templar 2 14831
Protoss_Photon_Cannon 2 15639
15639
