Protoss_Gateway 4 15323
Protoss_Zealot 2 6260
Protoss_Assimilator 1 5304
Protoss_Cybernetics_Core 1 6896
Protoss_Dragoon 11 15467
Protoss_Nexus 1 11897
Protoss_Robotics_Facility 1 12727
Singularity_Charge 1 11475
Protoss_Robotics_Support_Bay 1 13504
Protoss_Shuttle 1 14768
15467
