Protoss_Gateway 3 12795
Protoss_Assimilator 1 4483
Protoss_Zealot 2 6740
Protoss_Cybernetics_Core 1 6787
Protoss_Dragoon 11 15256
Protoss_Robotics_Facility 1 10216
Protoss_Observatory 1 11033
Singularity_Charge 1 10998
Protoss_Observer 3 13922
Protoss_Nexus 1 16342
16342
