Protoss_Gateway 2 11600
Protoss_Assimilator 1 4261
Protoss_Zealot 3 6933
Protoss_Cybernetics_Core 1 6912
Protoss_Dragoon 9 14346
Protoss_Robotics_Facility 1 11865
Singularity_Charge 1 11126
Protoss_Shuttle 1 13313
Protoss_Observatory 1 12696
Protoss_Robotics_Support_Bay 1 13561
Protoss_Observer 1 14156
Protoss_Reaver 1 15752
15752
