Protoss_Gateway 1 4141
Protoss_Assimilator 1 4401
Protoss_Cybernetics_Core 1 5745
Protoss_Zealot 1 5554
Protoss_Dragoon 7 14299
Protoss_Robotics_Facility 1 9490
Protoss_Robotics_Support_Bay 1 10283
Protoss_Observatory 1 10308
Protoss_Reaver 3 16165
Protoss_Nexus 1 14397
Protoss_Observer 1 12842
16165
