Protoss_Gateway 3 11344
Protoss_Zealot 16 15555
Protoss_Nexus 1 11785
Protoss_Assimilator 2 13647
Protoss_Cybernetics_Core 1 12182
Protoss_Dragoon 2 13509
Protoss_Citadel_of_Adun 1 14467
Protoss_Forge 1 14670
Protoss_Robotics_Facility 1 16138
16138
