Protoss_Gateway 2 6907
Protoss_Assimilator 1 4812
Protoss_Zealot 9 10788
Protoss_Cybernetics_Core 1 9945
Protoss_Dragoon 8 14692
Protoss_Robotics_Facility 1 14523
Protoss_Shuttle 1 16013
16013
