Protoss_Gateway 2 5030
Protoss_Zealot 9 10966
Protoss_Nexus 1 11155
Protoss_Assimilator 2 12901
Protoss_Cybernetics_Core 1 11963
Protoss_Dragoon 2 13511
Protoss_Citadel_of_Adun 1 14524
Protoss_Forge 1 14054
Protoss_Photon_Cannon 1 15591
Protoss_Templar_Archives 1 15965
15965
