Protoss_Gateway 2 4940
Protoss_Zealot 9 13079
Protoss_Assimilator 1 6411
Protoss_Cybernetics_Core 1 7479
Protoss_Dragoon 4 9844
Protoss_Citadel_of_Adun 1 12140
Protoss_Templar_Archives 1 13764
Protoss_Forge 1 13709
Singularity_Charge 1 12956
Protoss_Robotics_Facility 1 15665
Protoss_Photon_Cannon 2 15153
Protoss_Dark_Templar 2 15765
15765
