Protoss_Gateway 4 15915
Protoss_Assimilator 2 13577
Protoss_Cybernetics_Core 1 5509
Protoss_Zealot 1 5472
Protoss_Dragoon 12 15326
Protoss_Nexus 1 11112
Singularity_Charge 1 9783
Protoss_Robotics_Facility 1 13192
Protoss_Observatory 1 13915
Protoss_Observer 1 14932
15915
