Protoss_Gateway 3 14269
Protoss_Zealot 6 10229
Protoss_Nexus 1 9789
Protoss_Assimilator 2 11749
Protoss_Cybernetics_Core 1 10287
Protoss_Dragoon 2 11671
Protoss_Citadel_of_Adun 1 12489
Protoss_Forge 1 13482
Protoss_Templar_Archives 2 14316
Protoss_Robotics_Facility 1 14986
Protoss_Photon_Cannon 2 15137
15137
