Protoss_Gateway 2 5320
Protoss_Zealot 10 13515
Protoss_Nexus 1 10473
Protoss_Assimilator 2 12216
Protoss_Cybernetics_Core 1 11063
Protoss_Citadel_of_Adun 1 12533
Protoss_Robotics_Facility 1 14392
Protoss_Templar_Archives 1 14690
Protoss_Forge 1 15229
Protoss_Dragoon 2 15619
Protoss_Observatory 1 15155
15619
