Protoss_Gateway 4 16021
Protoss_Assimilator 1 4539
Protoss_Cybernetics_Core 1 5879
Protoss_Dragoon 7 14998
Protoss_Zealot 2 15295
Protoss_Nexus 1 11607
Protoss_Robotics_Facility 1 11002
Protoss_Observatory 1 11849
Protoss_Robotics_Support_Bay 1 11918
Protoss_Observer 3 14900
Singularity_Charge 1 14044
16021
