Protoss_Gateway 4 14919
Protoss_Zealot 5 14124
Protoss_Nexus 1 8970
Protoss_Assimilator 1 7512
Protoss_Cybernetics_Core 1 8630
Protoss_Dragoon 7 15273
Protoss_Robotics_Facility 1 13921
Protoss_Citadel_of_Adun 1 15503
Protoss_Shuttle 1 15950
15950
