Protoss_Gateway 4 15909
Protoss_Assimilator 1 4343
Protoss_Cybernetics_Core 1 5622
Protoss_Dragoon 14 15563
Protoss_Robotics_Facility 1 10930
Singularity_Charge 1 9806
Protoss_Observatory 1 11701
Protoss_Observer 2 13618
15909
