Protoss_Gateway 2 5174
Protoss_Zealot 12 12441
Protoss_Nexus 1 10966
Protoss_Assimilator 1 9463
Protoss_Cybernetics_Core 1 11941
Protoss_Forge 1 11898
Protoss_Photon_Cannon 5 15680
Protoss_Dragoon 4 15253
Protoss_Citadel_of_Adun 1 15031
15680
