Protoss_Gateway 4 15523
Protoss_Zealot 6 11642
Protoss_Nexus 1 10110
Protoss_Assimilator 2 12134
Protoss_Cybernetics_Core 1 9615
Protoss_Dragoon 1 11132
Protoss_Citadel_of_Adun 1 11724
Protoss_Forge 1 12277
Protoss_Templar_Archives 1 13331
Protoss_Photon_Cannon 1 14363
Protoss_Dark_Templar 2 14536
Protoss_Robotics_Facility 1 15746
15746
