Protoss_Gateway 2 11109
Protoss_Assimilator 1 4553
Protoss_Zealot 2 6292
Protoss_Cybernetics_Core 1 7034
Protoss_Dragoon 10 15540
Protoss_Robotics_Facility 1 10523
Protoss_Observatory 1 11290
Singularity_Charge 1 11235
Protoss_Observer 2 13226
Protoss_Robotics_Support_Bay 1 12701
Protoss_Shuttle 1 13969
Protoss_Reaver 1 15591
15591
