Protoss_Gateway 2 4975
Protoss_Zealot 19 15002
Protoss_Nexus 1 11055
Protoss_Assimilator 2 13634
Protoss_Cybernetics_Core 1 11584
Protoss_Citadel_of_Adun 1 13840
Protoss_Templar_Archives 1 15396
15396
