Protoss_Gateway 3 13771
Protoss_Zealot 3 7343
Protoss_Assimilator 1 5490
Protoss_Cybernetics_Core 1 6661
Protoss_Dragoon 10 15730
Protoss_Nexus 1 13017
Protoss_Robotics_Facility 1 12598
Singularity_Charge 1 11486
Protoss_Observatory 1 13337
Protoss_Observer 2 15427
15730
