Protoss_Gateway 2 4922
Protoss_Zealot 5 8107
Protoss_Assimilator 1 6244
Protoss_Cybernetics_Core 1 7872
Protoss_Dragoon 9 15546
Protoss_Robotics_Facility 1 13145
Singularity_Charge 1 12037
Protoss_Nexus 1 15510
Protoss_Observatory 1 13854
Protoss_Shuttle 1 14707
Protoss_Robotics_Support_Bay 1 14735
15546
