Protoss_Gateway 3 13861
Protoss_Assimilator 1 4337
Protoss_Cybernetics_Core 1 5730
Protoss_Zealot 1 5724
Protoss_Dragoon 9 15739
Singularity_Charge 1 9906
Protoss_Nexus 1 13470
Protoss_Robotics_Facility 1 14773
15739
