Protoss_Gateway 2 5019
Protoss_Zealot 5 7793
Protoss_Assimilator 1 7251
Protoss_Cybernetics_Core 1 8745
Protoss_Dragoon 12 15610
Singularity_Charge 1 12821
Protoss_Robotics_Facility 1 14957
15610
