Protoss_Gateway 4 14225
Protoss_Zealot 11 13703
Protoss_Nexus 1 9710
Protoss_Assimilator 2 12109
Protoss_Cybernetics_Core 1 12271
Protoss_Robotics_Facility 1 14624
Protoss_Citadel_of_Adun 1 14319
Protoss_Dragoon 3 14931
14931
