Protoss_Gateway 2 12971
Protoss_Assimilator 2 15550
Protoss_Zealot 1 5013
Protoss_Cybernetics_Core 1 5926
Protoss_Dragoon 5 15452
Protoss_Citadel_of_Adun 1 8139
Protoss_Templar_Archives 1 9722
Protoss_Dark_Templar 2 12048
Protoss_Nexus 1 13418
Protoss_Robotics_Facility 1 14237
Protoss_Observatory 1 15022
15550
