Protoss_Gateway 2 4853
Protoss_Zealot 6 9067
Protoss_Assimilator 1 6847
Protoss_Cybernetics_Core 1 8341
Protoss_Dragoon 7 15651
Protoss_Nexus 2 15532
Singularity_Charge 1 12057
Protoss_Robotics_Facility 1 14998
15651
