Protoss_Gateway 2 4714
Protoss_Zealot 12 13158
Protoss_Shield_Battery 2 8887
Protoss_Forge 1 8595
Protoss_Photon_Cannon 4 12740
Protoss_Assimilator 1 12282
Protoss_Cybernetics_Core 1 14210
Protoss_Stargate 1 16115
16115
