Protoss_Gateway 3 15996
Protoss_Assimilator 1 5060
Protoss_Zealot 3 7173
Protoss_Cybernetics_Core 1 6626
Protoss_Dragoon 10 15209
Singularity_Charge 1 10886
Protoss_Nexus 1 14115
Protoss_Robotics_Facility 1 13792
Protoss_Shuttle 1 15277
Protoss_Observatory 1 14798
15996
