Protoss_Gateway 4 9428
Protoss_Zealot 12 15236
Protoss_Shield_Battery 1 6471
Protoss_Forge 1 10306
Protoss_Assimilator 1 11092
Protoss_Photon_Cannon 4 15017
Protoss_Cybernetics_Core 1 13152
Protoss_Robotics_Facility 2 16122
16122
