Protoss_Gateway 3 12989
Protoss_Assimilator 2 14230
Protoss_Cybernetics_Core 1 5723
Protoss_Zealot 4 15432
Protoss_Dragoon 8 14217
Protoss_Nexus 1 12179
Protoss_Robotics_Facility 1 12033
Singularity_Charge 1 10155
Protoss_Observatory 1 12828
Protoss_Observer 2 14797
Protoss_Citadel_of_Adun 1 14954
15432
