Protoss_Gateway 2 10366
Protoss_Zealot 3 7047
Protoss_Assimilator 1 5869
Protoss_Cybernetics_Core 1 7027
Protoss_Dragoon 9 15654
Protoss_Robotics_Facility 1 12131
Singularity_Charge 1 11261
Protoss_Forge 1 12232
Protoss_Observatory 1 12895
Protoss_Photon_Cannon 5 14056
Protoss_Observer 2 15134
15654
