Protoss_Gateway 3 15023
Protoss_Zealot 11 14841
Protoss_Assimilator 2 10811
Protoss_Cybernetics_Core 1 9564
Protoss_Nexus 1 11428
Protoss_Citadel_of_Adun 1 11524
Protoss_Dragoon 2 11934
Protoss_Robotics_Facility 1 14028
Protoss_Templar_Archives 1 15877
15877
