Protoss_Gateway 4 15904
Protoss_Assimilator 1 5234
Protoss_Cybernetics_Core 1 6873
Protoss_Zealot 2 7199
Protoss_Dragoon 9 13968
Protoss_Robotics_Facility 1 11294
Protoss_Observatory 1 12077
Singularity_Charge 1 11480
Protoss_Observer 2 14323
Protoss_Nexus 1 15857
15904
