Protoss_Gateway 2 4994
Protoss_Zealot 4 9415
Protoss_Nexus 1 8809
Protoss_Assimilator 2 11412
Protoss_Cybernetics_Core 1 9252
Protoss_Dragoon 2 10711
Protoss_Citadel_of_Adun 1 11562
Protoss_Forge 1 11601
Protoss_Templar_Archives 1 13170
Protoss_Robotics_Facility 1 13791
Protoss_Photon_Cannon 5 15237
Protoss_Observatory 1 15009
Protoss_Dark_Templar 2 15525
15525
