Protoss_Gateway 3 14926
Protoss_Assimilator 1 4605
Protoss_Zealot 1 5183
Protoss_Cybernetics_Core 1 6067
Protoss_Dragoon 11 15575
Singularity_Charge 1 9727
Protoss_Nexus 1 14059
Protoss_Robotics_Facility 1 14486
Protoss_Observatory 1 15313
15575
