Protoss_Gateway 2 8326
Protoss_Assimilator 1 4267
Protoss_Zealot 3 7486
Protoss_Cybernetics_Core 1 7349
Protoss_Dragoon 10 15669
Protoss_Robotics_Facility 1 12987
Singularity_Charge 1 12221
Protoss_Nexus 1 16193
Protoss_Observatory 1 14359
Protoss_Citadel_of_Adun 1 15965
Protoss_Observer 1 15497
16193
