Protoss_Gateway 2 5136
Protoss_Zealot 5 12585
Protoss_Assimilator 1 6187
Protoss_Cybernetics_Core 1 7867
Protoss_Dragoon 10 15592
Protoss_Robotics_Facility 1 11290
Protoss_Observatory 1 12470
Protoss_Nexus 1 15138
Protoss_Observer 2 15058
Protoss_Forge 1 14432
Protoss_Photon_Cannon 1 15714
15714
