Protoss_Gateway 2 5010
Protoss_Zealot 19 14496
Protoss_Nexus 1 11648
Protoss_Assimilator 2 13902
Protoss_Cybernetics_Core 1 12280
Protoss_Citadel_of_Adun 1 14175
Protoss_Robotics_Facility 1 16014
Protoss_Forge 1 15561
16014
