Protoss_Gateway 2 5080
Protoss_Zealot 15 15175
Protoss_Nexus 1 9865
Protoss_Assimilator 2 14790
Protoss_Cybernetics_Core 1 10584
Protoss_Dragoon 2 12505
Protoss_Citadel_of_Adun 1 14155
Protoss_Forge 1 14192
Protoss_Templar_Archives 1 15785
15785
