Protoss_Gateway 2 9061
Protoss_Zealot 2 6324
Protoss_Assimilator 2 15191
Protoss_Cybernetics_Core 1 8009
Protoss_Dragoon 7 14182
Protoss_Nexus 1 13653
Protoss_Robotics_Facility 1 13323
Singularity_Charge 1 12356
Protoss_Observatory 1 14154
Protoss_Observer 1 15283
Protoss_Citadel_of_Adun 1 16059
16059
