Protoss_Gateway 2 7255
Protoss_Zealot 1 5089
Protoss_Assimilator 1 5309
Protoss_Cybernetics_Core 1 6667
Protoss_Dragoon 12 15516
Protoss_Robotics_Facility 1 12581
Singularity_Charge 1 12215
Protoss_Shuttle 1 14390
Protoss_Observatory 1 13782
Protoss_Nexus 1 16666
Protoss_Observer 1 14873
Protoss_Robotics_Support_Bay 1 14846
16666
