Protoss_Gateway 3 13575
Protoss_Assimilator 2 14492
Protoss_Zealot 3 7147
Protoss_Cybernetics_Core 1 7085
Protoss_Dragoon 8 15262
Protoss_Nexus 1 12464
Protoss_Robotics_Facility 1 12352
Singularity_Charge 1 11656
Protoss_Observatory 1 13317
Protoss_Citadel_of_Adun 1 14638
Protoss_Observer 2 15210
15262
