Protoss_Gateway 6 15972
Protoss_Assimilator 1 4442
Protoss_Cybernetics_Core 1 5759
Protoss_Dragoon 7 15247
Protoss_Nexus 2 16177
Protoss_Robotics_Facility 1 10974
Protoss_Observatory 1 11690
Protoss_Observer 3 14534
Singularity_Charge 1 13184
Protoss_Citadel_of_Adun 1 16047
16177
