Protoss_Gateway 4 14480
Protoss_Assimilator 1 4900
Protoss_Zealot 5 15163
Protoss_Cybernetics_Core 1 7037
Protoss_Dragoon 12 15692
Protoss_Robotics_Facility 1 11820
Protoss_Observatory 1 12505
Protoss_Observer 2 14712
Singularity_Charge 1 14463
15692
