Protoss_Gateway 2 14325
Protoss_Assimilator 2 14734
Protoss_Zealot 2 6708
Protoss_Cybernetics_Core 1 6795
Protoss_Dragoon 6 15549
Protoss_Citadel_of_Adun 1 8888
Protoss_Templar_Archives 1 10381
Protoss_Nexus 1 13082
Protoss_Dark_Templar 2 12906
Protoss_Robotics_Facility 1 14417
15549
