Protoss_Gateway 2 7529
Protoss_Zealot 1 5098
Protoss_Assimilator 1 5317
Protoss_Cybernetics_Core 1 6649
Protoss_Dragoon 10 14770
Protoss_Robotics_Facility 1 12266
Singularity_Charge 1 10860
Protoss_Shuttle 1 13761
Protoss_Observatory 1 13144
Protoss_Robotics_Support_Bay 1 14230
Protoss_Observer 1 14604
14770
