Protoss_Gateway 2 7903
Protoss_Assimilator 1 4210
Protoss_Zealot 2 5985
Protoss_Cybernetics_Core 1 7290
Protoss_Dragoon 10 14179
Protoss_Robotics_Facility 1 11823
Protoss_Observatory 1 12527
Singularity_Charge 1 12028
Protoss_Observer 2 14484
Protoss_Robotics_Support_Bay 1 14201
Protoss_Nexus 1 16894
Protoss_Reaver 1 16080
16894
