Protoss_Gateway 2 5133
Protoss_Zealot 7 11856
Protoss_Nexus 1 9944
Protoss_Assimilator 2 13239
Protoss_Forge 1 9529
Protoss_Photon_Cannon 5 13999
Protoss_Cybernetics_Core 1 11970
Protoss_Robotics_Facility 1 13933
Protoss_Dragoon 4 15566
Protoss_Observatory 1 14735
15566
