Protoss_Gateway 3 15292
Protoss_Assimilator 1 4158
Protoss_Cybernetics_Core 1 5566
Protoss_Zealot 2 11104
Protoss_Dragoon 8 14881
Protoss_Citadel_of_Adun 1 9413
Protoss_Templar_Archives 1 11001
Singularity_Charge 1 10664
Protoss_Dark_Templar 2 12224
Protoss_Nexus 1 14872
Protoss_Robotics_Facility 1 16252
16252
