Protoss_Gateway 2 13968
Protoss_Assimilator 1 5159
Protoss_Zealot 2 6687
Protoss_Cybernetics_Core 1 6725
Protoss_Dragoon 8 15414
Protoss_Nexus 1 11200
Protoss_Robotics_Facility 1 11746
Protoss_Observatory 1 12579
Protoss_Observer 1 13638
Protoss_Robotics_Support_Bay 1 13488
Protoss_Reaver 1 15773
Singularity_Charge 1 14170
15773
