Protoss_Gateway 2 10704
Protoss_Zealot 3 6851
Protoss_Assimilator 2 14802
Protoss_Cybernetics_Core 1 7360
Protoss_Dragoon 8 14328
Protoss_Nexus 1 13461
Protoss_Robotics_Facility 1 13347
Singularity_Charge 1 12171
Protoss_Observatory 1 14242
Protoss_Citadel_of_Adun 1 15650
15650
