Protoss_Gateway 2 10524
Protoss_Zealot 2 6017
Protoss_Assimilator 1 5374
Protoss_Cybernetics_Core 1 7246
Protoss_Citadel_of_Adun 1 8729
Protoss_Dragoon 5 15162
Protoss_Templar_Archives 1 10198
Protoss_Forge 1 10678
Protoss_Dark_Templar 4 12847
Protoss_Photon_Cannon 3 14890
Protoss_Nexus 1 16392
16392
