Protoss_Gateway 1 4167
Protoss_Zealot 2 6699
Protoss_Assimilator 1 5770
Protoss_Cybernetics_Core 1 6710
Protoss_Dragoon 7 15429
Protoss_Robotics_Facility 1 10336
Protoss_Shuttle 1 11733
Protoss_Observatory 1 11912
Protoss_Observer 1 12930
Protoss_Robotics_Support_Bay 1 13231
Protoss_Nexus 2 16762
Protoss_Reaver 1 16159
16762
