Protoss_Gateway 2 6011
Protoss_Zealot 4 8868
Protoss_Cybernetics_Core 1 7565
Protoss_Assimilator 1 7543
Protoss_Dragoon 12 15651
Protoss_Nexus 1 16680
Protoss_Robotics_Facility 1 15787
Singularity_Charge 1 14188
16680
