Protoss_Gateway 1 4369
Protoss_Assimilator 1 4412
Protoss_Cybernetics_Core 1 5876
Protoss_Robotics_Facility 1 8389
Protoss_Dragoon 5 14615
Protoss_Shuttle 1 9874
Protoss_Observatory 1 9268
Protoss_Observer 2 11598
Protoss_Nexus 1 14185
Protoss_Zealot 1 12722
14615
