Protoss_Gateway 1 4199
Protoss_Assimilator 1 4275
Protoss_Cybernetics_Core 1 5756
Protoss_Robotics_Facility 2 14967
Protoss_Zealot 2 8083
Protoss_Shuttle 2 14493
Protoss_Dragoon 5 14632
Protoss_Robotics_Support_Bay 1 9293
Protoss_Reaver 2 13124
Protoss_Observatory 1 14763
Gravitic_Drive 1 14167
14967
