Protoss_Gateway 2 8172
Protoss_Assimilator 2 4899
Protoss_Cybernetics_Core 1 6321
Protoss_Zealot 1 6160
Protoss_Dragoon 9 14053
Protoss_Citadel_of_Adun 1 12263
Singularity_Charge 1 10872
Protoss_Templar_Archives 1 14591
Protoss_Forge 1 14118
Protoss_Nexus 1 17018
17018
