Protoss_Gateway 3 14349
Protoss_Zealot 2 7071
Protoss_Assimilator 1 5771
Protoss_Cybernetics_Core 1 7422
Protoss_Dragoon 8 15688
Protoss_Robotics_Facility 1 9658
Protoss_Shuttle 1 11074
Protoss_Observatory 1 10608
Protoss_Robotics_Support_Bay 1 11441
Protoss_Observer 1 11929
Protoss_Reaver 2 15081
15688
