Protoss_Gateway 3 13514
Protoss_Assimilator 1 4719
Protoss_Cybernetics_Core 1 6409
Protoss_Dragoon 10 15168
Protoss_Robotics_Facility 1 10128
Protoss_Forge 1 10704
Protoss_Observatory 1 11065
Singularity_Charge 1 10706
Protoss_Observer 3 14332
15168
