Protoss_Gateway 3 14566
Protoss_Assimilator 1 4698
Protoss_Zealot 2 6778
Protoss_Cybernetics_Core 1 6880
Protoss_Dragoon 10 14881
Protoss_Nexus 1 13562
Protoss_Robotics_Facility 1 12985
Singularity_Charge 1 11337
Protoss_Observatory 1 13714
Protoss_Observer 1 14753
14881
