Protoss_Gateway 2 5049
Protoss_Zealot 10 10619
Protoss_Shield_Battery 1 8128
Protoss_Nexus 1 15400
Protoss_Assimilator 1 14129
Protoss_Forge 1 14295
Protoss_Photon_Cannon 1 15815
15815
