Protoss_Gateway 3 13916
Protoss_Assimilator 1 5398
Protoss_Zealot 3 14914
Protoss_Cybernetics_Core 1 6942
Protoss_Dragoon 8 15731
Protoss_Robotics_Facility 1 10870
Protoss_Nexus 1 13786
Singularity_Charge 1 11094
Protoss_Observatory 1 11849
Protoss_Observer 1 12968
Protoss_Shuttle 1 15172
15731
