Protoss_Gateway 3 13420
Protoss_Zealot 1 5592
Protoss_Assimilator 1 5852
Protoss_Cybernetics_Core 1 7272
Protoss_Dragoon 11 15768
Protoss_Robotics_Facility 1 12295
Singularity_Charge 1 10955
Protoss_Observatory 1 13241
Protoss_Observer 2 15144
Protoss_Nexus 1 16549
16549
