Protoss_Gateway 2 12593
Protoss_Zealot 3 7050
Protoss_Assimilator 2 13872
Protoss_Cybernetics_Core 1 7035
Protoss_Dragoon 8 14717
Protoss_Nexus 1 11910
Protoss_Robotics_Facility 1 11685
Singularity_Charge 1 11120
Protoss_Observatory 1 12452
Protoss_Observer 2 14347
Protoss_Citadel_of_Adun 1 14168
Protoss_Templar_Archives 1 15691
15691
