Protoss_Gateway 2 12509
Protoss_Assimilator 2 14032
Protoss_Zealot 2 6915
Protoss_Cybernetics_Core 1 6927
Protoss_Dragoon 8 15071
Protoss_Nexus 1 12202
Protoss_Robotics_Facility 1 12592
Singularity_Charge 1 11071
Protoss_Observatory 1 13307
Protoss_Citadel_of_Adun 1 14423
Protoss_Observer 2 15324
Protoss_Templar_Archives 1 15905
Protoss_Forge 1 15582
15905
