Protoss_Gateway 2 10081
Protoss_Zealot 7 13867
Protoss_Assimilator 1 7252
Protoss_Cybernetics_Core 1 9266
Protoss_Robotics_Facility 1 11246
Protoss_Dragoon 5 15271
Protoss_Shuttle 1 12655
Protoss_Robotics_Support_Bay 1 12022
Protoss_Reaver 1 14213
Protoss_Observatory 1 14716
15271
