Protoss_Gateway 2 12911
Protoss_Assimilator 1 4470
Protoss_Zealot 2 6795
Protoss_Cybernetics_Core 1 6867
Protoss_Dragoon 9 15426
Protoss_Nexus 1 12429
Protoss_Robotics_Facility 1 12841
Singularity_Charge 1 11153
Protoss_Observatory 1 14899
Protoss_Citadel_of_Adun 1 15756
15756
