Protoss_Gateway 2 7767
Protoss_Assimilator 1 4515
Protoss_Cybernetics_Core 1 5878
Protoss_Zealot 1 5724
Protoss_Dragoon 12 15572
Protoss_Nexus 1 13685
Singularity_Charge 1 11018
Protoss_Robotics_Facility 1 14722
Protoss_Citadel_of_Adun 1 14297
15572
