Protoss_Gateway 3 15343
Protoss_Assimilator 1 4392
Protoss_Cybernetics_Core 1 5641
Protoss_Dragoon 8 12282
Singularity_Charge 1 9830
Protoss_Citadel_of_Adun 1 12102
Protoss_Zealot 4 13313
Protoss_Templar_Archives 1 13749
Protoss_Dark_Templar 2 14954
15343
