Protoss_Gateway 2 10325
Protoss_Assimilator 1 4394
Protoss_Zealot 3 6787
Protoss_Cybernetics_Core 1 7046
Protoss_Dragoon 9 14390
Protoss_Robotics_Facility 1 10350
Protoss_Shuttle 1 11750
Protoss_Observatory 1 11444
Singularity_Charge 1 11059
Protoss_Robotics_Support_Bay 1 11782
Protoss_Observer 1 12646
Protoss_Reaver 2 16273
16273
