Protoss_Gateway 2 12072
Protoss_Assimilator 1 4505
Protoss_Zealot 2 6324
Protoss_Cybernetics_Core 1 7269
Protoss_Dragoon 7 15431
Protoss_Robotics_Facility 1 11414
Protoss_Observatory 1 12183
Protoss_Observer 3 14973
Protoss_Nexus 1 15511
Singularity_Charge 1 13313
15511
