Protoss_Gateway 2 12936
Protoss_Assimilator 1 4410
Protoss_Cybernetics_Core 1 5727
Protoss_Zealot 1 5692
Protoss_Dragoon 10 15513
Singularity_Charge 1 10128
Protoss_Nexus 1 13184
Protoss_Robotics_Facility 1 13040
Protoss_Shuttle 1 14633
Protoss_Robotics_Support_Bay 1 14574
15513
