Protoss_Gateway 3 11632
Protoss_Assimilator 1 4445
Protoss_Zealot 1 5121
Protoss_Cybernetics_Core 1 6953
Protoss_Dragoon 16 15727
Singularity_Charge 1 11270
Protoss_Robotics_Facility 1 15728
15728
