Protoss_Gateway 2 11111
Protoss_Assimilator 1 4552
Protoss_Zealot 1 5341
Protoss_Cybernetics_Core 1 6064
Protoss_Dragoon 10 15581
Protoss_Nexus 1 11765
Singularity_Charge 1 10000
Protoss_Robotics_Facility 1 12622
Protoss_Citadel_of_Adun 1 13965
Protoss_Observatory 1 14663
15581
