Protoss_Gateway 4 14241
Protoss_Zealot 7 15377
Protoss_Nexus 1 10247
Protoss_Assimilator 2 12283
Protoss_Cybernetics_Core 1 10542
Protoss_Dragoon 1 11998
Protoss_Forge 1 12700
Protoss_Robotics_Facility 1 14085
Protoss_Citadel_of_Adun 1 14237
Protoss_Photon_Cannon 2 14706
Protoss_Observatory 1 14832
Singularity_Charge 1 14217
Protoss_Templar_Archives 1 15788
15788
