Protoss_Gateway 3 15100
Protoss_Zealot 3 6994
Protoss_Assimilator 2 13842
Protoss_Cybernetics_Core 1 7019
Protoss_Dragoon 10 15472
Protoss_Nexus 1 12428
Protoss_Robotics_Facility 1 12800
Singularity_Charge 1 11071
Protoss_Observatory 1 13507
Protoss_Observer 2 15409
Protoss_Citadel_of_Adun 1 15391
15472
