Protoss_Gateway 3 14626
Protoss_Zealot 8 13395
Protoss_Nexus 1 9878
Protoss_Assimilator 2 11423
Protoss_Cybernetics_Core 1 10602
Protoss_Dragoon 1 11829
Protoss_Citadel_of_Adun 1 12200
Protoss_Robotics_Facility 1 13585
Protoss_Templar_Archives 1 13899
Protoss_Forge 1 13733
Protoss_Shuttle 1 14982
Protoss_Observatory 1 14344
Protoss_Dark_Templar 2 15162
Protoss_Photon_Cannon 2 15522
15522
