Protoss_Gateway 3 12652
Protoss_Zealot 3 9351
Protoss_Assimilator 1 7032
Protoss_Cybernetics_Core 1 9598
Protoss_Dragoon 8 14536
Protoss_Robotics_Facility 1 13606
Protoss_Observatory 1 14451
Singularity_Charge 1 13845
Protoss_Observer 1 15473
15473
