Protoss_Gateway 2 8086
Protoss_Assimilator 1 4188
Protoss_Cybernetics_Core 1 5952
Protoss_Zealot 1 6298
Protoss_Dragoon 12 15578
Protoss_Robotics_Facility 1 10238
Protoss_Shuttle 1 11701
Protoss_Robotics_Support_Bay 1 11889
Protoss_Reaver 2 15562
Protoss_Observatory 1 13307
Singularity_Charge 1 14325
15578
