Protoss_Gateway 2 13173
Protoss_Assimilator 1 4387
Protoss_Cybernetics_Core 1 5671
Protoss_Zealot 1 6403
Protoss_Dragoon 8 14747
Protoss_Robotics_Facility 1 10669
Singularity_Charge 1 9742
Protoss_Observatory 1 11376
Protoss_Nexus 1 14087
Protoss_Observer 1 12509
Protoss_Shuttle 1 14686
Protoss_Robotics_Support_Bay 1 14647
14747
