Protoss_Gateway 4 14398
Protoss_Zealot 13 15424
Protoss_Nexus 1 8777
Protoss_Assimilator 2 13041
Protoss_Cybernetics_Core 1 10960
Protoss_Citadel_of_Adun 1 12419
Protoss_Dragoon 4 13511
Protoss_Templar_Archives 1 13909
Protoss_Forge 1 13687
Protoss_Photon_Cannon 2 15244
Protoss_Dark_Templar 2 15434
15434
