Protoss_Gateway 2 12634
Protoss_Assimilator 1 4394
Protoss_Zealot 1 5107
Protoss_Cybernetics_Core 1 6918
Protoss_Dragoon 7 14340
Protoss_Nexus 1 11752
Protoss_Robotics_Facility 1 12297
Singularity_Charge 1 10702
Protoss_Observatory 1 12996
Protoss_Observer 1 14045
14340
