Protoss_Gateway 4 15883
Protoss_Assimilator 2 15067
Protoss_Cybernetics_Core 1 5856
Protoss_Zealot 1 5941
Protoss_Dragoon 10 15189
Protoss_Nexus 1 12997
Singularity_Charge 1 10304
Protoss_Robotics_Facility 1 12687
Protoss_Observatory 1 13415
Protoss_Observer 2 15552
15883
