Protoss_Gateway 2 11082
Protoss_Assimilator 1 5287
Protoss_Zealot 3 13571
Protoss_Cybernetics_Core 1 6798
Protoss_Dragoon 9 15224
Protoss_Robotics_Facility 1 10602
Protoss_Shuttle 1 12113
Protoss_Observatory 1 11485
Singularity_Charge 1 10971
Protoss_Observer 1 12956
Protoss_Robotics_Support_Bay 1 12960
Protoss_Reaver 1 14886
Protoss_Nexus 1 16392
16392
