Protoss_Gateway 3 13769
Protoss_Zealot 2 6670
Protoss_Assimilator 2 15535
Protoss_Cybernetics_Core 1 6664
Protoss_Dragoon 9 15329
Protoss_Nexus 1 12388
Protoss_Robotics_Facility 1 11981
Singularity_Charge 1 10717
Protoss_Observatory 1 12815
Protoss_Observer 2 15310
Protoss_Citadel_of_Adun 1 14951
15535
