Protoss_Gateway 3 10100
Protoss_Assimilator 1 4539
Protoss_Zealot 2 7003
Protoss_Cybernetics_Core 1 7073
Protoss_Dragoon 13 15818
Singularity_Charge 1 11138
Protoss_Nexus 1 16648
Protoss_Robotics_Facility 1 15802
16648
