Protoss_Gateway 4 14048
Protoss_Assimilator 2 15468
Protoss_Zealot 2 6643
Protoss_Cybernetics_Core 1 6608
Protoss_Dragoon 9 15323
Protoss_Robotics_Facility 1 10541
Protoss_Observatory 1 11234
Protoss_Nexus 1 13707
Singularity_Charge 1 10857
Protoss_Observer 2 13805
Protoss_Citadel_of_Adun 1 16059
16059
