Protoss_Gateway 3 13893
Protoss_Assimilator 1 4517
Protoss_Zealot 6 13729
Protoss_Cybernetics_Core 1 6825
Protoss_Dragoon 6 15294
Protoss_Nexus 1 13506
Singularity_Charge 1 11159
Protoss_Robotics_Facility 1 13252
Protoss_Observatory 1 14082
Protoss_Observer 1 15119
15294
