Protoss_Gateway 3 15362
Protoss_Assimilator 1 4501
Protoss_Zealot 3 7123
Protoss_Cybernetics_Core 1 7031
Protoss_Dragoon 8 15434
Protoss_Robotics_Facility 1 10700
Protoss_Shuttle 1 12181
Protoss_Observatory 1 11615
Singularity_Charge 1 11240
Protoss_Robotics_Support_Bay 1 12478
Protoss_Observer 1 13024
Protoss_Nexus 1 15183
Protoss_Reaver 2 16159
16159
