Protoss_Gateway 3 15605
Protoss_Assimilator 2 14480
Protoss_Zealot 5 11522
Protoss_Cybernetics_Core 1 6984
Protoss_Dragoon 2 15203
Protoss_Citadel_of_Adun 1 9792
Protoss_Robotics_Facility 1 10333
Protoss_Templar_Archives 1 11235
Protoss_Shuttle 1 11733
Singularity_Charge 1 10804
Protoss_Dark_Templar 2 13535
Protoss_Nexus 1 14782
Protoss_Observatory 1 13842
Protoss_Observer 1 15491
15605
