Protoss_Gateway 2 7943
Protoss_Assimilator 1 4515
Protoss_Cybernetics_Core 1 5686
Protoss_Zealot 1 5490
Protoss_Dragoon 10 13980
Protoss_Robotics_Facility 1 11048
Protoss_Observatory 1 11789
Singularity_Charge 1 11442
Protoss_Robotics_Support_Bay 1 12511
Protoss_Observer 1 12898
Protoss_Reaver 1 14863
14863
