Protoss_Gateway 3 14791
Protoss_Zealot 10 12520
Protoss_Nexus 1 9772
Protoss_Assimilator 2 11710
Protoss_Cybernetics_Core 1 10269
Protoss_Citadel_of_Adun 1 11835
Protoss_Dragoon 1 12478
Protoss_Templar_Archives 1 13490
Protoss_Forge 1 13565
Protoss_Dark_Templar 2 14697
Protoss_Photon_Cannon 3 15437
15437
