Protoss_Gateway 3 13593
Protoss_Assimilator 1 4217
Protoss_Cybernetics_Core 1 5702
Protoss_Dragoon 14 15470
Singularity_Charge 1 10099
Protoss_Robotics_Facility 1 12117
Protoss_Observatory 1 12833
Protoss_Zealot 2 14183
Protoss_Observer 2 15138
15470
