Protoss_Gateway 4 15386
Protoss_Zealot 5 8914
Protoss_Assimilator 2 12111
Protoss_Nexus 1 10408
Protoss_Cybernetics_Core 1 10299
Protoss_Dragoon 8 15587
Protoss_Citadel_of_Adun 1 12904
Protoss_Robotics_Facility 1 15027
Protoss_Templar_Archives 1 15336
Singularity_Charge 1 14144
15587
