Protoss_Gateway 2 5484
Protoss_Zealot 11 11512
Protoss_Assimilator 1 8230
Protoss_Cybernetics_Core 1 12307
Protoss_Citadel_of_Adun 1 13912
Protoss_Dragoon 4 15215
Protoss_Templar_Archives 1 15402
15402
