Protoss_Gateway 2 9607
Protoss_Assimilator 1 4275
Protoss_Zealot 2 6131
Protoss_Cybernetics_Core 1 6239
Protoss_Dragoon 11 14928
Protoss_Robotics_Facility 1 12307
Singularity_Charge 1 10482
Protoss_Nexus 1 14715
Protoss_Observatory 1 13299
Protoss_Observer 1 14347
14928
