Protoss_Gateway 5 15397
Protoss_Zealot 7 15512
Protoss_Nexus 1 10044
Protoss_Assimilator 2 13695
Protoss_Cybernetics_Core 1 10312
Protoss_Dragoon 7 14518
Protoss_Robotics_Facility 1 16194
16194
