Protoss_Gateway 3 13076
Protoss_Assimilator 1 4530
Protoss_Cybernetics_Core 1 5809
Protoss_Zealot 1 5944
Protoss_Dragoon 13 15569
Protoss_Citadel_of_Adun 1 9874
Protoss_Templar_Archives 1 11323
Singularity_Charge 1 10061
Protoss_Dark_Templar 2 13233
15569
