Protoss_Gateway 3 13549
Protoss_Zealot 11 11853
Protoss_Nexus 1 9731
Protoss_Assimilator 2 14980
Protoss_Cybernetics_Core 1 12132
Protoss_Dragoon 4 15478
Protoss_Citadel_of_Adun 1 14439
Protoss_Robotics_Facility 1 15639
15639
