Protoss_Gateway 3 13160
Protoss_Zealot 19 15204
Protoss_Nexus 1 11239
Protoss_Assimilator 1 9902
Protoss_Cybernetics_Core 1 12068
Protoss_Citadel_of_Adun 1 13556
Protoss_Forge 1 13511
Protoss_Photon_Cannon 1 15707
15707
