Protoss_Gateway 2 5107
Protoss_Zealot 9 9441
Protoss_Assimilator 1 7461
Protoss_Cybernetics_Core 1 9172
Protoss_Dragoon 8 14861
Protoss_Nexus 1 13620
Protoss_Robotics_Facility 1 14872
14872
