Protoss_Gateway 3 10864
Protoss_Assimilator 1 4480
Protoss_Cybernetics_Core 1 5709
Protoss_Zealot 1 6020
Protoss_Dragoon 16 15540
Singularity_Charge 1 10137
Protoss_Robotics_Facility 1 13504
Protoss_Shuttle 1 15538
Protoss_Robotics_Support_Bay 1 14840
15540
