Protoss_Gateway 2 8688
Protoss_Assimilator 1 4725
Protoss_Zealot 3 7341
Protoss_Cybernetics_Core 1 7271
Protoss_Dragoon 4 13544
Protoss_Citadel_of_Adun 1 9652
Protoss_Templar_Archives 1 11184
Protoss_Dark_Templar 2 12410
Singularity_Charge 1 12770
Protoss_Robotics_Facility 1 14833
Protoss_Forge 1 14726
14833
