Protoss_Gateway 2 7316
Protoss_Zealot 1 5124
Protoss_Assimilator 1 5391
Protoss_Cybernetics_Core 1 6907
Protoss_Dragoon 11 15329
Protoss_Nexus 1 13626
Singularity_Charge 1 11562
Protoss_Robotics_Facility 1 13865
Protoss_Citadel_of_Adun 1 14769
Protoss_Observatory 1 14908
15329
