Protoss_Gateway 3 15996
Protoss_Assimilator 2 15312
Protoss_Cybernetics_Core 1 5933
Protoss_Dragoon 5 11196
Protoss_Citadel_of_Adun 1 9705
Protoss_Templar_Archives 1 11189
Singularity_Charge 1 9830
Protoss_Forge 1 11871
Protoss_Dark_Templar 2 12402
Protoss_Photon_Cannon 2 13257
Protoss_Nexus 1 15810
Protoss_High_Templar 2 14311
15996
