Protoss_Gateway 3 15254
Protoss_Assimilator 1 4352
Protoss_Cybernetics_Core 1 5587
Protoss_Zealot 1 5917
Protoss_Dragoon 10 15291
Protoss_Nexus 1 11981
Singularity_Charge 1 9824
Protoss_Robotics_Facility 1 13179
Protoss_Observatory 1 13997
Protoss_Observer 1 15008
15291
