Protoss_Gateway 2 13275
Protoss_Assimilator 1 4261
Protoss_Zealot 2 6716
Protoss_Cybernetics_Core 1 6735
Protoss_Dragoon 10 15671
Protoss_Robotics_Facility 1 10292
Protoss_Observatory 1 11196
Protoss_Nexus 1 13656
Singularity_Charge 1 10933
Protoss_Observer 3 15471
15671
