Protoss_Gateway 2 14497
Protoss_Assimilator 1 4397
Protoss_Cybernetics_Core 1 5647
Protoss_Zealot 1 6008
Protoss_Dragoon 8 15601
Protoss_Robotics_Facility 1 10554
Protoss_Nexus 1 13105
Singularity_Charge 1 10398
Protoss_Shuttle 1 12494
Protoss_Robotics_Support_Bay 1 12200
Protoss_Reaver 2 16086
Protoss_Observatory 1 14518
16086
