Protoss_Gateway 2 10799
Protoss_Assimilator 1 4147
Protoss_Zealot 2 6626
Protoss_Cybernetics_Core 1 6662
Protoss_Dragoon 10 15429
Protoss_Robotics_Facility 1 10229
Protoss_Observatory 1 11215
Singularity_Charge 1 10787
Protoss_Observer 1 12239
Protoss_Robotics_Support_Bay 1 12099
Protoss_Reaver 1 14154
Protoss_Nexus 1 16620
16620
