Protoss_Gateway 3 11440
Protoss_Assimilator 1 4243
Protoss_Cybernetics_Core 1 5664
Protoss_Zealot 5 12907
Protoss_Dragoon 7 14556
Protoss_Robotics_Facility 1 10299
Singularity_Charge 1 9926
Protoss_Shuttle 1 11692
Protoss_Observatory 1 11153
Protoss_Robotics_Support_Bay 1 11851
Protoss_Observer 1 12535
Protoss_Reaver 2 15782
15782
