Protoss_Gateway 4 14765
Protoss_Assimilator 1 4463
Protoss_Cybernetics_Core 1 5860
Protoss_Zealot 1 5821
Protoss_Dragoon 8 14782
Protoss_Nexus 1 10284
Protoss_Robotics_Facility 1 10750
Protoss_Observatory 1 11537
Protoss_Observer 1 12605
Protoss_Shuttle 1 13963
Protoss_Robotics_Support_Bay 1 13563
Singularity_Charge 1 12967
Protoss_Reaver 1 15618
15618
