Protoss_Gateway 2 12023
Protoss_Assimilator 1 4580
Protoss_Zealot 2 7205
Protoss_Cybernetics_Core 1 7144
Protoss_Dragoon 10 15800
Protoss_Robotics_Facility 1 11228
Protoss_Observatory 1 11954
Singularity_Charge 1 11557
Protoss_Observer 2 13870
Protoss_Shuttle 1 15228
Protoss_Robotics_Support_Bay 1 14685
15800
