Protoss_Gateway 2 7289
Protoss_Assimilator 1 4438
Protoss_Zealot 2 7205
Protoss_Cybernetics_Core 1 7062
Protoss_Robotics_Facility 1 9300
Protoss_Dragoon 10 15648
Protoss_Observatory 1 10014
Protoss_Observer 3 13433
Protoss_Nexus 1 14237
Singularity_Charge 1 12634
Protoss_Shuttle 1 14992
Protoss_Robotics_Support_Bay 1 14754
15648
