Protoss_Gateway 2 12538
Protoss_Assimilator 2 14136
Protoss_Cybernetics_Core 1 6312
Protoss_Zealot 1 6362
Protoss_Dragoon 10 15628
Protoss_Nexus 1 12157
Singularity_Charge 1 10848
Protoss_Robotics_Facility 1 12834
Protoss_Citadel_of_Adun 1 13782
Protoss_Observatory 1 13529
Protoss_Observer 2 15430
Protoss_Templar_Archives 1 15567
15628
