Protoss_Gateway 3 15806
Protoss_Assimilator 1 4332
Protoss_Zealot 2 6775
Protoss_Cybernetics_Core 1 6819
Protoss_Dragoon 9 15095
Protoss_Robotics_Facility 1 11117
Singularity_Charge 1 10813
Protoss_Observatory 1 11858
Protoss_Robotics_Support_Bay 1 12514
Protoss_Observer 1 12910
Protoss_Reaver 1 14813
Protoss_Nexus 1 16184
16184
