Protoss_Gateway 2 11396
Protoss_Assimilator 1 4368
Protoss_Zealot 2 6646
Protoss_Cybernetics_Core 1 6532
Protoss_Dragoon 11 15680
Protoss_Robotics_Facility 1 10574
Protoss_Shuttle 1 11999
Singularity_Charge 1 10872
Protoss_Observatory 1 11685
Protoss_Observer 2 15447
Protoss_Robotics_Support_Bay 1 12891
Protoss_Reaver 1 14623
Protoss_Nexus 1 16922
16922
