Protoss_Gateway 4 14282
Protoss_Assimilator 1 4185
Protoss_Zealot 2 6406
Protoss_Cybernetics_Core 1 6814
Protoss_Dragoon 8 14589
Protoss_Citadel_of_Adun 1 10561
Protoss_Templar_Archives 1 12002
Singularity_Charge 1 10597
Protoss_Nexus 1 14434
Protoss_Dark_Templar 2 13421
14589
