Protoss_Gateway 2 13469
Protoss_Assimilator 2 13770
Protoss_Zealot 2 6620
Protoss_Cybernetics_Core 1 6800
Protoss_Dragoon 8 14823
Protoss_Nexus 1 12602
Singularity_Charge 1 10919
Protoss_Robotics_Facility 1 13036
Protoss_Citadel_of_Adun 1 12923
Protoss_Templar_Archives 1 14620
Protoss_Observatory 1 13992
Protoss_Observer 1 15081
15081
