Protoss_Gateway 4 14528
Protoss_Assimilator 1 4344
Protoss_Cybernetics_Core 1 5604
Protoss_Zealot 2 10884
Protoss_Dragoon 9 15730
Protoss_Citadel_of_Adun 1 9149
Protoss_Templar_Archives 1 10689
Singularity_Charge 1 9467
Protoss_Dark_Templar 2 12107
Protoss_Nexus 1 14577
15730
