Protoss_Gateway 2 10548
Protoss_Assimilator 1 4286
Protoss_Zealot 2 6550
Protoss_Cybernetics_Core 1 6599
Protoss_Dragoon 9 15481
Protoss_Robotics_Facility 1 10058
Protoss_Observatory 1 10772
Singularity_Charge 1 10676
Protoss_Robotics_Support_Bay 1 11577
Protoss_Observer 2 14554
Protoss_Reaver 1 13654
Protoss_Nexus 1 15704
15704
