Protoss_Gateway 4 13407
Protoss_Assimilator 1 4385
Protoss_Cybernetics_Core 1 5748
Protoss_Zealot 1 5575
Protoss_Dragoon 13 15701
Protoss_Nexus 1 11083
Protoss_Robotics_Facility 1 11489
Protoss_Observatory 1 12331
Protoss_Observer 2 14224
Singularity_Charge 1 14194
15701
