Protoss_Gateway 2 11041
Protoss_Assimilator 1 4308
Protoss_Zealot 2 6711
Protoss_Cybernetics_Core 1 6732
Protoss_Dragoon 8 13953
Protoss_Robotics_Facility 1 10571
Protoss_Shuttle 1 11967
Protoss_Observatory 1 11412
Singularity_Charge 1 10790
Protoss_Robotics_Support_Bay 1 12142
Protoss_Observer 2 15231
Protoss_Reaver 2 16068
Protoss_Nexus 1 16879
16879
