Protoss_Gateway 2 11272
Protoss_Assimilator 1 4366
Protoss_Zealot 2 6708
Protoss_Cybernetics_Core 1 6746
Protoss_Dragoon 8 14170
Protoss_Robotics_Facility 1 10484
Protoss_Shuttle 1 11961
Protoss_Observatory 1 11496
Singularity_Charge 1 10834
Protoss_Observer 2 15225
Protoss_Robotics_Support_Bay 1 12575
Protoss_Reaver 1 14400
Protoss_Nexus 1 17083
17083
