Protoss_Gateway 1 4188
Protoss_Assimilator 1 4435
Protoss_Cybernetics_Core 1 5974
Protoss_Zealot 2 11554
Protoss_Dragoon 7 15342
Protoss_Robotics_Facility 1 9926
Singularity_Charge 1 9868
Protoss_Shuttle 1 11382
Protoss_Observatory 1 10674
Protoss_Robotics_Support_Bay 1 11815
Protoss_Observer 2 14645
Protoss_Reaver 2 16241
16241
