Protoss_Gateway 3 14014
Protoss_Assimilator 1 4438
Protoss_Zealot 4 14560
Protoss_Cybernetics_Core 1 8080
Protoss_Dragoon 6 15238
Protoss_Nexus 1 11812
Protoss_Robotics_Facility 1 13078
Protoss_Observatory 1 13942
Protoss_Robotics_Support_Bay 1 14473
Singularity_Charge 1 14358
15238
