Protoss_Gateway 2 11379
Protoss_Assimilator 1 4615
Protoss_Zealot 2 7343
Protoss_Cybernetics_Core 1 7211
Protoss_Dragoon 10 15663
Protoss_Robotics_Facility 1 10838
Protoss_Observatory 1 11590
Protoss_Shuttle 1 12321
Singularity_Charge 1 11393
Protoss_Robotics_Support_Bay 2 14602
Protoss_Observer 1 13439
Protoss_Reaver 1 15834
15834
