Protoss_Gateway 4 13711
Protoss_Zealot 11 13796
Protoss_Nexus 1 10173
Protoss_Assimilator 2 11904
Protoss_Cybernetics_Core 1 10621
Protoss_Citadel_of_Adun 1 12279
Protoss_Templar_Archives 1 13793
Protoss_Dark_Templar 4 15288
Protoss_Forge 1 15397
15397
