Protoss_Gateway 2 11604
Protoss_Assimilator 1 4581
Protoss_Zealot 2 6945
Protoss_Cybernetics_Core 1 6986
Protoss_Dragoon 10 15511
Protoss_Robotics_Facility 1 11474
Singularity_Charge 1 11334
Protoss_Shuttle 1 12874
Protoss_Observatory 1 12275
Protoss_Robotics_Support_Bay 1 13220
Protoss_Observer 1 13717
Protoss_Reaver 1 15313
15511
