Protoss_Gateway 2 8797
Protoss_Assimilator 1 4460
Protoss_Zealot 4 13735
Protoss_Cybernetics_Core 1 6694
Protoss_Dragoon 10 15370
Protoss_Robotics_Facility 1 11287
Singularity_Charge 1 10450
Protoss_Shuttle 1 12757
Protoss_Observatory 1 12233
Protoss_Robotics_Support_Bay 1 13327
Protoss_Observer 1 13605
Protoss_Reaver 1 15527
15527
