Protoss_Gateway 2 4928
Protoss_Zealot 11 13211
Protoss_Assimilator 2 13761
Protoss_Nexus 1 11316
Protoss_Cybernetics_Core 1 10517
Protoss_Dragoon 2 12350
Protoss_Citadel_of_Adun 1 13441
Protoss_Robotics_Facility 1 15146
Protoss_Templar_Archives 1 15109
Protoss_Forge 1 15036
15146
