Protoss_Gateway 2 10346
Protoss_Assimilator 1 4278
Protoss_Cybernetics_Core 1 5872
Protoss_Zealot 1 5753
Protoss_Dragoon 10 14752
Protoss_Robotics_Facility 1 9913
Protoss_Observatory 1 10719
Singularity_Charge 1 10187
Protoss_Observer 2 13665
Protoss_Shuttle 1 12822
Protoss_Robotics_Support_Bay 1 12961
Protoss_Reaver 1 15281
15281
