Protoss_Gateway 4 13161
Protoss_Assimilator 1 4193
Protoss_Cybernetics_Core 1 5636
Protoss_Zealot 1 5537
Protoss_Dragoon 13 15522
Protoss_Citadel_of_Adun 1 8386
Singularity_Charge 1 9853
Protoss_Nexus 1 13335
15522
