Protoss_Gateway 2 10673
Protoss_Assimilator 1 4410
Protoss_Zealot 2 6716
Protoss_Cybernetics_Core 1 6787
Protoss_Dragoon 9 15467
Protoss_Robotics_Facility 1 10643
Singularity_Charge 1 10681
Protoss_Observatory 1 11507
Protoss_Shuttle 1 12558
Protoss_Robotics_Support_Bay 1 12879
Protoss_Observer 1 13401
Protoss_Reaver 1 14997
15467
