Protoss_Gateway 2 9989
Protoss_Assimilator 1 4309
Protoss_Zealot 3 7706
Protoss_Cybernetics_Core 1 7820
Protoss_Dragoon 10 15698
Protoss_Robotics_Facility 1 11606
Singularity_Charge 1 11797
Protoss_Shuttle 1 13419
Protoss_Robotics_Support_Bay 1 13099
Protoss_Reaver 1 15296
Protoss_Shield_Battery 1 15121
15698
