Protoss_Gateway 2 5108
Protoss_Zealot 7 8805
Protoss_Assimilator 1 6576
Protoss_Cybernetics_Core 1 8743
Protoss_Dragoon 4 12249
Protoss_Nexus 1 15201
Singularity_Charge 1 12733
15201
