Protoss_Gateway 3 15883
Protoss_Assimilator 2 13973
Protoss_Zealot 1 5312
Protoss_Cybernetics_Core 1 7154
Protoss_Dragoon 9 15004
Protoss_Nexus 1 12072
Protoss_Robotics_Facility 1 11875
Singularity_Charge 1 10834
Protoss_Observatory 1 12869
Protoss_Observer 2 15541
Protoss_Citadel_of_Adun 1 15331
15883
