Protoss_Gateway 3 15286
Protoss_Assimilator 1 4264
Protoss_Cybernetics_Core 1 5642
Protoss_Dragoon 14 15679
Protoss_Robotics_Facility 1 10946
Singularity_Charge 1 9440
Protoss_Observatory 1 11744
Protoss_Observer 2 13758
Protoss_Nexus 1 15625
15679
