Protoss_Gateway 4 15649
Protoss_Assimilator 1 4710
Protoss_Zealot 2 6807
Protoss_Cybernetics_Core 1 6847
Protoss_Dragoon 8 14583
Protoss_Robotics_Facility 1 11202
Singularity_Charge 1 10942
Protoss_Observatory 1 12001
Protoss_Nexus 1 14471
Protoss_Observer 2 14496
15649
