Protoss_Gateway 2 5007
Protoss_Assimilator 1 4987
Protoss_Cybernetics_Core 1 6830
Protoss_Zealot 2 7243
Protoss_Dragoon 13 15341
Protoss_Robotics_Facility 1 13072
Singularity_Charge 1 11331
Protoss_Observatory 1 13920
Protoss_Robotics_Support_Bay 1 13981
15341
