Protoss_Gateway 2 9184
Protoss_Assimilator 1 4407
Protoss_Cybernetics_Core 1 5614
Protoss_Zealot 1 5950
Protoss_Dragoon 9 13564
Singularity_Charge 1 9464
Protoss_Robotics_Facility 1 11905
Protoss_Observatory 1 12745
Protoss_Robotics_Support_Bay 1 13337
Protoss_Observer 1 13799
Protoss_Reaver 1 15395
Protoss_Nexus 1 17109
17109
