Protoss_Gateway 2 6710
Protoss_Assimilator 1 4210
Protoss_Zealot 5 8347
Protoss_Cybernetics_Core 1 8701
Protoss_Dragoon 6 14829
Protoss_Robotics_Facility 1 11375
Protoss_Nexus 1 13394
Protoss_Observatory 1 12074
Protoss_Shuttle 1 13185
Protoss_Robotics_Support_Bay 1 13700
Protoss_Observer 1 14028
Protoss_Reaver 1 15667
Singularity_Charge 1 14507
15667
