Protoss_Gateway 3 15637
Protoss_Assimilator 1 4384
Protoss_Zealot 2 6889
Protoss_Cybernetics_Core 1 6877
Protoss_Dragoon 7 14893
Protoss_Citadel_of_Adun 1 9251
Protoss_Templar_Archives 1 10771
Protoss_Forge 1 11148
Protoss_Dark_Templar 2 11975
Protoss_Photon_Cannon 1 12619
Protoss_Nexus 1 15739
15739
