Protoss_Gateway 4 14519
Protoss_Zealot 6 10056
Protoss_Nexus 1 10094
Protoss_Assimilator 1 8322
Protoss_Cybernetics_Core 1 9487
Protoss_Dragoon 8 15800
Protoss_Robotics_Facility 1 13561
Singularity_Charge 1 13550
Protoss_Shuttle 1 15655
Protoss_Observatory 1 15063
15800
