Protoss_Gateway 2 5099
Protoss_Zealot 13 14139
Protoss_Forge 1 9052
Protoss_Photon_Cannon 4 13749
Protoss_Assimilator 1 12389
Protoss_Cybernetics_Core 1 14484
Protoss_Robotics_Facility 1 16495
16495
