Protoss_Gateway 2 7433
Protoss_Assimilator 1 4905
Protoss_Zealot 1 5338
Protoss_Cybernetics_Core 1 6664
Protoss_Dragoon 6 14466
Protoss_Nexus 1 12375
Protoss_Robotics_Facility 1 11998
Singularity_Charge 1 10980
Protoss_Forge 1 11941
Protoss_Photon_Cannon 1 13251
Protoss_Observatory 1 12844
Protoss_Citadel_of_Adun 1 14383
Protoss_Observer 2 14865
14865
