Protoss_Gateway 2 10123
Protoss_Assimilator 1 4419
Protoss_Zealot 2 6646
Protoss_Cybernetics_Core 1 6713
Protoss_Dragoon 11 15525
Protoss_Robotics_Facility 1 9844
Protoss_Shuttle 1 11376
Protoss_Robotics_Support_Bay 1 11577
Singularity_Charge 1 11120
Protoss_Reaver 1 13349
Protoss_Observatory 1 13030
Protoss_Observer 1 14827
15525
