Protoss_Gateway 3 12213
Protoss_Assimilator 1 4512
Protoss_Zealot 2 6842
Protoss_Cybernetics_Core 1 6896
Protoss_Dragoon 9 15478
Protoss_Nexus 1 12596
Singularity_Charge 1 11156
Protoss_Citadel_of_Adun 1 13027
Protoss_Robotics_Facility 1 13656
Protoss_Observatory 1 14517
15478
