Protoss_Gateway 4 11829
Protoss_Assimilator 1 4412
Protoss_Cybernetics_Core 1 5625
Protoss_Zealot 3 14803
Protoss_Dragoon 12 14949
Protoss_Nexus 1 11730
Singularity_Charge 1 9991
Protoss_Robotics_Facility 1 16154
Protoss_Shield_Battery 1 15259
16154
