Protoss_Gateway 1 4540
Protoss_Assimilator 1 4581
Protoss_Cybernetics_Core 1 6034
Protoss_Robotics_Facility 1 8072
Protoss_Dragoon 4 15162
Protoss_Shuttle 1 9468
Protoss_Robotics_Support_Bay 1 9170
Protoss_Reaver 2 12565
Protoss_Observatory 1 12995
Protoss_Observer 1 14016
Protoss_Nexus 1 17112
17112
