Protoss_Gateway 2 10846
Protoss_Assimilator 1 4416
Protoss_Cybernetics_Core 1 5587
Protoss_Zealot 1 5756
Protoss_Dragoon 10 15171
Protoss_Robotics_Facility 1 10462
Singularity_Charge 1 10199
Protoss_Shuttle 1 11862
Protoss_Observatory 1 11286
Protoss_Robotics_Support_Bay 1 12434
Protoss_Observer 1 12705
Protoss_Reaver 1 14541
15171
