Protoss_Gateway 2 8477
Protoss_Assimilator 1 4512
Protoss_Cybernetics_Core 1 5745
Protoss_Zealot 1 5941
Protoss_Dragoon 9 14840
Protoss_Nexus 1 13699
Protoss_Robotics_Facility 1 13655
Singularity_Charge 1 12048
Protoss_Observatory 1 14514
Protoss_Observer 1 15561
15561
