Protoss_Gateway 2 15409
Protoss_Assimilator 1 4366
Protoss_Zealot 2 6769
Protoss_Cybernetics_Core 1 7000
Protoss_Dragoon 5 15607
Protoss_Robotics_Facility 1 9900
Protoss_Robotics_Support_Bay 1 10637
Protoss_Shuttle 1 11364
Singularity_Charge 1 11194
Protoss_Reaver 1 12922
Protoss_Observatory 1 12405
Protoss_Observer 1 13747
Protoss_Nexus 1 16117
16117
