Protoss_Gateway 2 10514
Protoss_Assimilator 1 4368
Protoss_Zealot 1 5025
Protoss_Cybernetics_Core 1 5964
Protoss_Dragoon 8 14621
Protoss_Robotics_Facility 1 9346
Protoss_Robotics_Support_Bay 1 10052
Singularity_Charge 1 9768
Protoss_Reaver 1 12021
Protoss_Observatory 1 11767
Protoss_Observer 2 15219
Protoss_Shuttle 1 14376
Protoss_Nexus 1 17276
17276
