Protoss_Gateway 4 15806
Protoss_Zealot 8 10507
Protoss_Nexus 1 9849
Protoss_Assimilator 2 11320
Protoss_Cybernetics_Core 1 10372
Protoss_Dragoon 9 15759
Protoss_Robotics_Facility 1 13822
Protoss_Shuttle 1 15225
Protoss_Observatory 1 14630
15806
