Protoss_Gateway 4 15680
Protoss_Zealot 7 13109
Protoss_Nexus 1 10113
Protoss_Assimilator 2 11054
Protoss_Cybernetics_Core 1 9713
Protoss_Dragoon 4 12168
Protoss_Citadel_of_Adun 1 11824
Protoss_Robotics_Facility 1 13731
Protoss_Templar_Archives 1 13846
Protoss_Dark_Templar 2 15115
Protoss_Shuttle 1 15403
Protoss_Observatory 1 15178
15680
