Protoss_Gateway 3 14385
Protoss_Assimilator 1 4564
Protoss_Cybernetics_Core 1 5781
Protoss_Dragoon 6 15300
Protoss_Robotics_Facility 1 8451
Protoss_Shuttle 1 9977
Protoss_Observatory 1 9565
Protoss_Observer 2 14935
Protoss_Robotics_Support_Bay 1 10690
Protoss_Reaver 2 14110
15300
