Protoss_Gateway 2 10302
Protoss_Assimilator 1 4423
Protoss_Cybernetics_Core 1 5718
Protoss_Zealot 1 5552
Protoss_Dragoon 5 15130
Protoss_Citadel_of_Adun 1 9039
Protoss_Templar_Archives 1 10776
Protoss_Dark_Templar 3 13422
Protoss_Nexus 1 16342
16342
