Protoss_Gateway 2 8961
Protoss_Assimilator 1 4429
Protoss_Cybernetics_Core 1 6219
Protoss_Zealot 5 14903
Protoss_Dragoon 9 14814
Protoss_Robotics_Facility 1 10263
Singularity_Charge 1 10052
Protoss_Observatory 1 11129
Protoss_Observer 2 14031
Protoss_Nexus 1 14829
Protoss_Citadel_of_Adun 1 13774
Protoss_Templar_Archives 1 15307
15307
