Protoss_Gateway 2 8692
Protoss_Assimilator 1 4382
Protoss_Zealot 2 6658
Protoss_Cybernetics_Core 1 6629
Protoss_Dragoon 11 15373
Protoss_Robotics_Facility 1 11884
Singularity_Charge 1 11112
Protoss_Observatory 1 12603
Protoss_Observer 2 14522
Protoss_Nexus 1 16863
16863
