Protoss_Gateway 4 15124
Protoss_Assimilator 1 4436
Protoss_Zealot 4 14876
Protoss_Cybernetics_Core 1 6980
Protoss_Dragoon 9 13146
Protoss_Robotics_Facility 1 11978
Singularity_Charge 1 11006
Protoss_Observatory 1 12701
Protoss_Nexus 1 15706
Protoss_Observer 2 14800
15706
