Protoss_Gateway 2 15236
Protoss_Assimilator 2 12510
Protoss_Cybernetics_Core 1 5742
Protoss_Zealot 1 5490
Protoss_Dragoon 7 15174
Protoss_Nexus 1 10986
Protoss_Forge 2 12927
Protoss_Photon_Cannon 2 11628
Protoss_Citadel_of_Adun 1 14941
15236
