Protoss_Gateway 3 14818
Protoss_Assimilator 1 4236
Protoss_Cybernetics_Core 1 5474
Protoss_Zealot 2 9836
Protoss_Dragoon 9 15382
Protoss_Citadel_of_Adun 1 8739
Protoss_Templar_Archives 1 10272
Singularity_Charge 1 9680
Protoss_Dark_Templar 2 11474
Protoss_Nexus 1 14043
Protoss_Robotics_Facility 1 14280
Protoss_Observatory 1 15101
15382
