Protoss_Gateway 2 12920
Protoss_Assimilator 1 4510
Protoss_Cybernetics_Core 1 5919
Protoss_Zealot 3 12602
Protoss_Dragoon 4 13831
Protoss_Robotics_Facility 1 8444
Protoss_Observatory 1 9645
Protoss_Shuttle 1 10659
Protoss_Robotics_Support_Bay 1 10932
Protoss_Observer 1 11502
Singularity_Charge 1 11498
Protoss_Reaver 1 13326
Protoss_Nexus 1 16073
16073
