Protoss_Gateway 1 4253
Protoss_Assimilator 1 4331
Protoss_Cybernetics_Core 1 5729
Protoss_Robotics_Facility 1 7921
Protoss_Dragoon 7 14764
Protoss_Observatory 1 9067
Protoss_Observer 2 11032
Protoss_Shuttle 1 12390
Protoss_Robotics_Support_Bay 1 12344
Singularity_Charge 1 11636
Protoss_Reaver 2 15932
15932
