Protoss_Gateway 2 15598
Protoss_Assimilator 1 4201
Protoss_Cybernetics_Core 1 5657
Protoss_Dragoon 7 15227
Protoss_Robotics_Facility 1 7965
Protoss_Shuttle 1 9485
Protoss_Observatory 1 9486
Protoss_Observer 2 12798
Protoss_Nexus 1 13454
Singularity_Charge 1 13125
Protoss_Forge 1 14376
Protoss_Photon_Cannon 1 15775
15775
