Protoss_Gateway 2 15296
Protoss_Assimilator 1 4442
Protoss_Cybernetics_Core 1 5791
Protoss_Zealot 1 5712
Protoss_Dragoon 7 14659
Protoss_Robotics_Facility 1 9806
Protoss_Shuttle 1 11256
Protoss_Robotics_Support_Bay 1 10648
Singularity_Charge 1 10052
Protoss_Reaver 1 12814
Protoss_Observatory 1 12032
Protoss_Observer 2 14519
Protoss_Nexus 1 16032
16032
