Protoss_Gateway 2 10729
Protoss_Assimilator 1 4438
Protoss_Zealot 2 6725
Protoss_Cybernetics_Core 1 6798
Protoss_Dragoon 9 13851
Protoss_Robotics_Facility 1 10204
Protoss_Shuttle 1 11677
Protoss_Observatory 1 11384
Singularity_Charge 1 11088
Protoss_Observer 1 12520
Protoss_Robotics_Support_Bay 1 12838
Protoss_Reaver 1 14699
Protoss_Citadel_of_Adun 1 15214
15214
