Protoss_Gateway 3 12743
Protoss_Assimilator 2 13215
Protoss_Zealot 2 6596
Protoss_Cybernetics_Core 1 6636
Protoss_Dragoon 8 14512
Protoss_Nexus 1 12265
Protoss_Robotics_Facility 1 11868
Singularity_Charge 1 10807
Protoss_Observatory 1 12603
Protoss_Citadel_of_Adun 1 13918
Protoss_Observer 2 14929
Protoss_Templar_Archives 1 15473
Protoss_Forge 1 15295
15473
