Protoss_Gateway 3 13744
Protoss_Assimilator 1 4845
Protoss_Cybernetics_Core 1 6138
Protoss_Dragoon 6 15434
Protoss_Nexus 1 12917
Singularity_Charge 1 10626
Protoss_Robotics_Facility 1 12907
15434
