Protoss_Gateway 1 4236
Protoss_Assimilator 1 4463
Protoss_Zealot 2 7076
Protoss_Cybernetics_Core 1 7170
Protoss_Dragoon 7 15402
Protoss_Robotics_Facility 1 9967
Protoss_Robotics_Support_Bay 1 10658
Protoss_Nexus 1 13660
Protoss_Reaver 1 12583
Protoss_Observatory 1 12205
Protoss_Observer 1 13407
Protoss_Shuttle 1 14791
15402
