Protoss_Gateway 3 12339
Protoss_Assimilator 1 4308
Protoss_Zealot 2 11973
Protoss_Cybernetics_Core 1 7028
Protoss_Citadel_of_Adun 1 8958
Protoss_Dragoon 9 15162
Protoss_Templar_Archives 1 12239
Protoss_Dark_Templar 3 13658
Singularity_Charge 1 13023
Protoss_Robotics_Facility 1 16457
16457
