Protoss_Gateway 2 5083
Protoss_Zealot 13 13589
Protoss_Nexus 1 10489
Protoss_Assimilator 2 14339
Protoss_Cybernetics_Core 1 12669
Protoss_Citadel_of_Adun 1 14333
Protoss_Dragoon 2 14761
Protoss_Templar_Archives 1 15956
Protoss_Forge 1 15523
15956
