Protoss_Nexus 1 7187
Protoss_Gateway 2 12552
Protoss_Assimilator 1 6327
Protoss_Zealot 2 8358
Protoss_Cybernetics_Core 1 10103
Protoss_Dragoon 6 15007
Protoss_Robotics_Facility 1 14839
Singularity_Charge 1 13780
15007
