Protoss_Gateway 3 10239
Protoss_Assimilator 1 4868
Protoss_Zealot 2 6582
Protoss_Cybernetics_Core 1 6590
Protoss_Dragoon 12 14659
Singularity_Charge 1 10813
Protoss_Robotics_Facility 1 15774
15774
