Protoss_Gateway 3 16038
Protoss_Assimilator 1 4129
Protoss_Zealot 1 5278
Protoss_Cybernetics_Core 1 7294
Protoss_Dragoon 3 12680
Protoss_Robotics_Facility 1 9434
Protoss_Shuttle 1 10848
Protoss_Robotics_Support_Bay 1 10677
Protoss_Reaver 2 14788
Protoss_Nexus 1 15264
Singularity_Charge 1 12521
16038
