Protoss_Gateway 2 10116
Protoss_Assimilator 1 4346
Protoss_Zealot 3 6702
Protoss_Cybernetics_Core 1 6855
Protoss_Dragoon 11 15238
Protoss_Robotics_Facility 1 12434
Singularity_Charge 1 10813
Protoss_Nexus 1 16170
Protoss_Shuttle 1 15380
16170
