Protoss_Gateway 5 14802
Protoss_Zealot 11 15336
Protoss_Nexus 1 8927
Protoss_Assimilator 2 13008
Protoss_Cybernetics_Core 1 10994
Protoss_Dragoon 3 13775
Protoss_Citadel_of_Adun 1 12999
Protoss_Templar_Archives 1 14913
Protoss_Forge 1 15138
15336
