Protoss_Nexus 1 7360
Protoss_Gateway 4 13981
Protoss_Forge 1 7865
Protoss_Zealot 14 15195
Protoss_Photon_Cannon 8 15774
Protoss_Assimilator 1 9999
Protoss_Cybernetics_Core 1 12841
Protoss_Citadel_of_Adun 1 15517
15774
