Protoss_Gateway 3 16015
Protoss_Zealot 2 5991
Protoss_Assimilator 1 5268
Protoss_Cybernetics_Core 1 6734
Protoss_Dragoon 11 15794
Protoss_Robotics_Facility 1 10776
Protoss_Nexus 1 12643
Singularity_Charge 1 10626
Protoss_Observatory 1 11501
Protoss_Observer 2 13395
16015
