Protoss_Gateway 3 13214
Protoss_Assimilator 1 4117
Protoss_Cybernetics_Core 1 5726
Protoss_Zealot 1 5455
Protoss_Dragoon 10 15613
Protoss_Robotics_Facility 1 9614
Protoss_Nexus 1 12365
Protoss_Observatory 1 10491
Singularity_Charge 1 9862
Protoss_Observer 3 13987
Protoss_Citadel_of_Adun 1 14095
15613
