Protoss_Gateway 3 15326
Protoss_Assimilator 1 4514
Protoss_Zealot 1 5388
Protoss_Cybernetics_Core 1 7097
Protoss_Dragoon 6 15124
Protoss_Robotics_Facility 1 10005
Protoss_Robotics_Support_Bay 1 10785
Singularity_Charge 1 10787
Protoss_Reaver 1 13368
Protoss_Nexus 1 15600
15600
