Protoss_Gateway 2 7785
Protoss_Assimilator 1 4452
Protoss_Zealot 3 15084
Protoss_Cybernetics_Core 1 7268
Protoss_Dragoon 10 14223
Protoss_Robotics_Facility 1 11656
Singularity_Charge 1 11182
Protoss_Robotics_Support_Bay 1 12426
Protoss_Shield_Battery 1 12751
Protoss_Reaver 1 14391
Protoss_Observatory 1 13959
Protoss_Observer 1 15277
15277
