Protoss_Gateway 2 9883
Protoss_Assimilator 2 14923
Protoss_Zealot 2 6983
Protoss_Cybernetics_Core 1 7053
Protoss_Dragoon 8 15557
Protoss_Nexus 1 13222
Singularity_Charge 1 11442
Protoss_Robotics_Facility 1 13741
Protoss_Citadel_of_Adun 1 15036
Protoss_Observatory 1 14486
Protoss_Observer 1 15567
15567
