Protoss_Gateway 2 11019
Protoss_Assimilator 1 4504
Protoss_Zealot 3 12055
Protoss_Cybernetics_Core 1 7255
Protoss_Dragoon 4 11764
Protoss_Citadel_of_Adun 1 10368
Protoss_Templar_Archives 1 11843
Singularity_Charge 1 11255
Protoss_Dark_Templar 4 14987
Protoss_Forge 1 12813
Protoss_Nexus 1 15450
Protoss_Photon_Cannon 2 14395
Protoss_High_Templar 1 15399
15450
