Protoss_Gateway 4 15371
Protoss_Assimilator 2 15457
Protoss_Zealot 2 6810
Protoss_Cybernetics_Core 1 6866
Protoss_Dragoon 11 14995
Protoss_Nexus 1 11885
Protoss_Robotics_Facility 1 12114
Singularity_Charge 1 10872
Protoss_Observatory 1 12900
Protoss_Observer 2 14803
15457
