Protoss_Gateway 3 14464
Protoss_Assimilator 1 4657
Protoss_Zealot 2 6874
Protoss_Cybernetics_Core 1 6931
Protoss_Dragoon 7 14492
Protoss_Robotics_Facility 1 11296
Protoss_Observatory 1 12083
Singularity_Charge 1 11624
Protoss_Observer 2 14420
Protoss_Nexus 1 15482
Protoss_Citadel_of_Adun 1 15763
15763
