Protoss_Gateway 3 14244
Protoss_Assimilator 1 5263
Protoss_Cybernetics_Core 1 6304
Protoss_Zealot 3 12105
Protoss_Dragoon 12 15721
Protoss_Robotics_Facility 1 10119
Protoss_Observatory 1 11161
Protoss_Observer 2 13229
Protoss_Nexus 1 14657
Singularity_Charge 1 13096
15721
