Protoss_Gateway 2 11938
Protoss_Assimilator 2 14363
Protoss_Cybernetics_Core 1 5648
Protoss_Zealot 1 5537
Protoss_Dragoon 9 15045
Protoss_Nexus 1 12338
Singularity_Charge 1 9871
Protoss_Robotics_Facility 1 12920
Protoss_Observatory 1 13819
Protoss_Observer 1 14830
15045
