Protoss_Gateway 2 9053
Protoss_Assimilator 1 4372
Protoss_Cybernetics_Core 1 5771
Protoss_Zealot 1 5642
Protoss_Dragoon 11 15470
Protoss_Robotics_Facility 1 10505
Singularity_Charge 1 9944
Protoss_Shuttle 1 11996
Protoss_Observatory 1 11393
Protoss_Robotics_Support_Bay 1 11761
Protoss_Observer 2 14300
15470
