Protoss_Gateway 2 13631
Protoss_Assimilator 2 13347
Protoss_Zealot 2 7164
Protoss_Cybernetics_Core 1 7284
Protoss_Dragoon 4 12133
Protoss_Nexus 1 12798
Protoss_Citadel_of_Adun 1 11841
Protoss_Robotics_Facility 1 13385
Singularity_Charge 1 11940
Protoss_Templar_Archives 1 13498
Protoss_Shuttle 1 14870
Protoss_Dark_Templar 2 14829
Protoss_Forge 1 14831
Protoss_Observatory 1 15331
15331
