Protoss_Gateway 3 15495
Protoss_Assimilator 2 14200
Protoss_Zealot 2 7097
Protoss_Cybernetics_Core 1 6991
Protoss_Dragoon 4 11518
Protoss_Citadel_of_Adun 1 9760
Protoss_Templar_Archives 1 11244
Protoss_Nexus 1 13694
Singularity_Charge 1 11059
Protoss_Forge 1 12293
Protoss_Dark_Templar 1 12619
Protoss_Photon_Cannon 2 14205
Protoss_High_Templar 2 14861
15495
