Protoss_Gateway 2 11058
Protoss_Assimilator 1 4325
Protoss_Zealot 2 6617
Protoss_Cybernetics_Core 1 6627
Protoss_Dragoon 8 14109
Protoss_Robotics_Facility 1 10140
Protoss_Shuttle 1 11709
Protoss_Observatory 1 11047
Singularity_Charge 1 10752
Protoss_Observer 1 12552
Protoss_Robotics_Support_Bay 1 12395
Protoss_Reaver 2 15995
Protoss_Nexus 1 16568
16568
