Protoss_Gateway 2 11069
Protoss_Assimilator 1 4274
Protoss_Zealot 2 6848
Protoss_Cybernetics_Core 1 6883
Protoss_Dragoon 7 14006
Protoss_Robotics_Facility 1 10409
Protoss_Shuttle 1 11947
Protoss_Observatory 1 11417
Singularity_Charge 1 10995
Protoss_Observer 1 12842
Protoss_Robotics_Support_Bay 1 12945
Protoss_Reaver 1 14819
Protoss_Nexus 1 17165
17165
