Protoss_Gateway 3 15725
Protoss_Assimilator 1 4366
Protoss_Zealot 2 6769
Protoss_Cybernetics_Core 1 6772
Protoss_Dragoon 11 15253
Protoss_Robotics_Facility 1 10059
Protoss_Observatory 1 11196
Singularity_Charge 1 10760
Protoss_Nexus 1 13983
Protoss_Observer 2 13179
Protoss_Robotics_Support_Bay 1 13198
Protoss_Reaver 1 14927
15725
