Protoss_Gateway 4 15880
Protoss_Assimilator 2 13473
Protoss_Zealot 2 5209
Protoss_Cybernetics_Core 1 6945
Protoss_Dragoon 8 14319
Protoss_Nexus 1 12401
Protoss_Robotics_Facility 1 11950
Singularity_Charge 1 10743
Protoss_Observatory 1 12639
Protoss_Citadel_of_Adun 1 13786
Protoss_Observer 2 14595
Protoss_Templar_Archives 1 15304
15880
