Protoss_Gateway 4 16003
Protoss_Zealot 2 6011
Protoss_Assimilator 1 5436
Protoss_Cybernetics_Core 1 7060
Protoss_Dragoon 8 13880
Protoss_Nexus 1 13193
Singularity_Charge 1 11914
Protoss_Robotics_Facility 1 13827
Protoss_Citadel_of_Adun 1 14986
Protoss_Observatory 1 14657
16003
