Protoss_Gateway 2 10949
Protoss_Zealot 2 6687
Protoss_Assimilator 2 14284
Protoss_Cybernetics_Core 1 6804
Protoss_Dragoon 8 15066
Protoss_Robotics_Facility 1 11089
Singularity_Charge 1 11080
Protoss_Observatory 1 11865
Protoss_Observer 2 13770
Protoss_Nexus 1 15321
Protoss_Citadel_of_Adun 1 14445
15321
