Protoss_Gateway 2 12614
Protoss_Assimilator 2 13594
Protoss_Zealot 2 6828
Protoss_Cybernetics_Core 1 6874
Protoss_Dragoon 7 14343
Protoss_Nexus 1 12451
Protoss_Robotics_Facility 1 12063
Singularity_Charge 1 10898
Protoss_Observatory 1 12762
Protoss_Robotics_Support_Bay 1 12831
Protoss_Observer 1 13846
Protoss_Reaver 1 15442
15442
