Protoss_Gateway 1 4073
Protoss_Assimilator 1 4420
Protoss_Cybernetics_Core 1 5815
Protoss_Zealot 1 5660
Protoss_Dragoon 7 15285
Protoss_Robotics_Facility 1 10066
Singularity_Charge 1 10026
Protoss_Shuttle 1 11689
Protoss_Observatory 1 11157
Protoss_Robotics_Support_Bay 1 12010
Protoss_Observer 1 12637
Protoss_Nexus 1 15208
Protoss_Reaver 2 15823
15823
