Protoss_Gateway 2 10943
Protoss_Assimilator 1 4363
Protoss_Zealot 2 6845
Protoss_Cybernetics_Core 1 7212
Protoss_Dragoon 10 15683
Protoss_Robotics_Facility 1 10432
Protoss_Shuttle 1 11827
Singularity_Charge 1 11065
Protoss_Observatory 1 11975
Protoss_Observer 1 13085
Protoss_Robotics_Support_Bay 1 12963
Protoss_Reaver 1 14719
Protoss_Nexus 1 17008
17008
