Protoss_Gateway 2 9187
Protoss_Assimilator 1 4338
Protoss_Cybernetics_Core 1 5819
Protoss_Zealot 1 5554
Protoss_Dragoon 9 15759
Protoss_Robotics_Facility 1 10444
Singularity_Charge 1 9754
Protoss_Shuttle 1 11847
Protoss_Observatory 1 11659
Protoss_Observer 1 12690
Protoss_Robotics_Support_Bay 1 12815
Protoss_Reaver 1 14868
Protoss_Nexus 1 16799
16799
