Protoss_Gateway 2 10928
Protoss_Assimilator 1 4161
Protoss_Zealot 2 6605
Protoss_Cybernetics_Core 1 6782
Protoss_Dragoon 10 15777
Protoss_Robotics_Facility 1 10598
Protoss_Observatory 1 11333
Singularity_Charge 1 10720
Protoss_Observer 2 13240
Protoss_Nexus 1 15116
Protoss_Robotics_Support_Bay 1 13722
Protoss_Reaver 1 15796
15796
