Protoss_Gateway 4 15476
Protoss_Assimilator 1 4227
Protoss_Zealot 2 6564
Protoss_Cybernetics_Core 1 6624
Protoss_Dragoon 8 14363
Protoss_Robotics_Facility 1 10530
Protoss_Observatory 1 11319
Singularity_Charge 1 10854
Protoss_Nexus 1 14008
Protoss_Observer 1 12345
Protoss_Robotics_Support_Bay 1 12250
Protoss_Reaver 2 15981
15981
