Protoss_Gateway 2 14786
Protoss_Assimilator 1 4422
Protoss_Zealot 2 6670
Protoss_Cybernetics_Core 1 6650
Protoss_Dragoon 7 15320
Protoss_Robotics_Facility 1 10027
Protoss_Robotics_Support_Bay 1 10737
Singularity_Charge 1 10790
Protoss_Shuttle 1 12289
Protoss_Nexus 1 14856
Protoss_Reaver 2 15574
Protoss_Observatory 1 13324
Gravitic_Drive 1 14454
15574
