Protoss_Gateway 2 9588
Protoss_Assimilator 1 5149
Protoss_Zealot 2 7337
Protoss_Cybernetics_Core 1 7029
Protoss_Dragoon 9 15557
Protoss_Robotics_Facility 1 11477
Singularity_Charge 1 11422
Protoss_Observatory 1 12281
Protoss_Observer 1 13606
Protoss_Shuttle 1 15271
Protoss_Robotics_Support_Bay 1 15074
15557
