Protoss_Gateway 5 14753
Protoss_Zealot 2 6558
Protoss_Assimilator 1 5434
Protoss_Cybernetics_Core 1 6699
Protoss_Dragoon 11 15674
Protoss_Nexus 1 11689
Protoss_Robotics_Facility 1 11228
Singularity_Charge 1 10977
Protoss_Observatory 1 12585
Protoss_Observer 2 14944
15674
