Protoss_Gateway 2 10413
Protoss_Assimilator 1 4390
Protoss_Zealot 2 6754
Protoss_Cybernetics_Core 1 6936
Protoss_Dragoon 8 15789
Protoss_Robotics_Facility 1 10175
Protoss_Shuttle 1 11721
Singularity_Charge 1 10860
Protoss_Robotics_Support_Bay 1 11829
Protoss_Observatory 1 11952
Protoss_Reaver 1 13961
Protoss_Observer 1 14786
Protoss_Nexus 1 16986
16986
