Protoss_Gateway 2 11718
Protoss_Zealot 2 6895
Protoss_Assimilator 2 14096
Protoss_Cybernetics_Core 1 7135
Protoss_Dragoon 10 15355
Protoss_Nexus 1 11957
Singularity_Charge 1 10921
Protoss_Robotics_Facility 1 13448
Protoss_Forge 1 14427
Protoss_Observatory 1 14300
Protoss_Observer 1 15324
15355
