Protoss_Gateway 2 11162
Protoss_Assimilator 1 4565
Protoss_Cybernetics_Core 1 5941
Protoss_Zealot 1 5762
Protoss_Dragoon 9 15031
Protoss_Robotics_Facility 1 10631
Singularity_Charge 1 10283
Protoss_Shuttle 1 12049
Protoss_Robotics_Support_Bay 1 12136
Protoss_Observatory 1 12282
Protoss_Observer 1 13296
Protoss_Reaver 1 15433
15433
