Protoss_Gateway 4 16043
Protoss_Assimilator 1 4414
Protoss_Zealot 2 6872
Protoss_Cybernetics_Core 1 6898
Protoss_Dragoon 11 15110
Protoss_Nexus 1 12722
Singularity_Charge 1 11033
Protoss_Robotics_Facility 1 15248
16043
