Protoss_Gateway 3 13171
Protoss_Assimilator 1 4483
Protoss_Zealot 2 6918
Protoss_Cybernetics_Core 1 6905
Protoss_Dragoon 14 15519
Protoss_Robotics_Facility 1 11885
Protoss_Observatory 1 12645
Singularity_Charge 1 11955
Protoss_Observer 2 14543
15519
