Protoss_Gateway 2 14604
Protoss_Assimilator 2 14594
Protoss_Zealot 2 6848
Protoss_Cybernetics_Core 1 7019
Protoss_Dragoon 4 11536
Protoss_Citadel_of_Adun 1 9816
Protoss_Templar_Archives 1 11306
Protoss_Nexus 1 13509
Protoss_Forge 1 11955
Singularity_Charge 1 11044
Protoss_Dark_Templar 1 12636
Protoss_Photon_Cannon 5 15715
Protoss_High_Templar 2 14837
15715
