Protoss_Gateway 4 13624
Protoss_Assimilator 1 4413
Protoss_Cybernetics_Core 1 5639
Protoss_Zealot 1 5774
Protoss_Dragoon 15 15707
Protoss_Robotics_Facility 1 9660
Singularity_Charge 1 9306
Protoss_Observatory 1 10469
Protoss_Observer 2 12368
15707
