Protoss_Gateway 3 15247
Protoss_Assimilator 1 4436
Protoss_Zealot 2 6298
Protoss_Cybernetics_Core 1 7691
Protoss_Dragoon 10 15516
Protoss_Robotics_Facility 1 10861
Protoss_Observatory 1 11656
Singularity_Charge 1 11615
Protoss_Observer 2 13864
Protoss_Nexus 1 15966
Protoss_Robotics_Support_Bay 1 14028
Protoss_Reaver 1 16080
16080
