Protoss_Gateway 3 15362
Protoss_Assimilator 2 14244
Protoss_Zealot 2 6860
Protoss_Cybernetics_Core 1 6940
Protoss_Dragoon 4 11436
Protoss_Citadel_of_Adun 1 10013
Protoss_Templar_Archives 1 11469
Protoss_Nexus 1 13571
Singularity_Charge 1 11071
Protoss_Forge 1 12026
Protoss_Dark_Templar 1 12666
Protoss_Photon_Cannon 2 13893
Protoss_High_Templar 2 14867
15362
