Protoss_Gateway 3 15462
Protoss_Zealot 5 9980
Protoss_Assimilator 1 9015
Protoss_Cybernetics_Core 1 10070
Protoss_Dragoon 7 15572
Protoss_Robotics_Facility 1 16020
Singularity_Charge 1 14504
16020
