Protoss_Gateway 2 10706
Protoss_Assimilator 1 4567
Protoss_Zealot 2 7319
Protoss_Cybernetics_Core 1 7340
Protoss_Dragoon 9 14878
Protoss_Robotics_Facility 1 10791
Protoss_Shuttle 1 12514
Singularity_Charge 1 11366
Protoss_Robotics_Support_Bay 1 12432
Protoss_Reaver 1 14181
Protoss_Observatory 1 13817
Protoss_Observer 1 15005
15005
