Protoss_Gateway 2 10224
Protoss_Assimilator 1 4495
Protoss_Zealot 2 6898
Protoss_Cybernetics_Core 1 6942
Protoss_Dragoon 11 15695
Protoss_Robotics_Facility 1 10321
Protoss_Shuttle 1 11756
Protoss_Robotics_Support_Bay 1 11638
Singularity_Charge 1 11238
Protoss_Observatory 1 12402
Protoss_Reaver 1 13768
Protoss_Observer 2 15473
Protoss_Forge 1 14676
15695
