Protoss_Gateway 3 10193
Protoss_Assimilator 1 4353
Protoss_Zealot 2 6795
Protoss_Cybernetics_Core 1 6892
Protoss_Dragoon 14 15317
Singularity_Charge 1 10980
Protoss_Forge 1 14472
Protoss_Robotics_Facility 1 15812
15812
