Protoss_Gateway 4 13799
Protoss_Assimilator 1 4180
Protoss_Cybernetics_Core 1 5588
Protoss_Zealot 1 5344
Protoss_Citadel_of_Adun 1 7038
Protoss_Dragoon 11 15537
Protoss_Templar_Archives 1 8529
Protoss_Dark_Templar 1 9865
Protoss_Nexus 1 12157
Protoss_Robotics_Facility 1 15702
Singularity_Charge 1 14243
15702
