Protoss_Gateway 2 11363
Protoss_Assimilator 1 4186
Protoss_Zealot 2 6869
Protoss_Cybernetics_Core 1 6869
Protoss_Dragoon 10 15335
Protoss_Robotics_Facility 1 10937
Singularity_Charge 1 10702
Protoss_Shuttle 1 12368
Protoss_Observatory 1 12205
Protoss_Observer 1 13281
Protoss_Robotics_Support_Bay 1 13169
Protoss_Reaver 1 15152
15335
