Protoss_Gateway 2 11189
Protoss_Assimilator 1 4302
Protoss_Zealot 2 6980
Protoss_Cybernetics_Core 1 6914
Protoss_Dragoon 10 15475
Protoss_Robotics_Facility 1 12818
Singularity_Charge 1 11849
Protoss_Shuttle 1 14355
Protoss_Observatory 1 13930
Protoss_Robotics_Support_Bay 1 14728
Protoss_Observer 1 15198
15475
