Protoss_Gateway 2 14838
Protoss_Assimilator 2 13805
Protoss_Zealot 2 7041
Protoss_Cybernetics_Core 1 6892
Protoss_Dragoon 4 11632
Protoss_Citadel_of_Adun 1 9406
Protoss_Templar_Archives 1 11221
Protoss_Nexus 1 13604
Singularity_Charge 1 11123
Protoss_Dark_Templar 1 12733
Protoss_Forge 1 12494
Protoss_Photon_Cannon 2 14278
Protoss_High_Templar 2 14934
14934
