Protoss_Gateway 2 10858
Protoss_Assimilator 1 4227
Protoss_Zealot 2 6664
Protoss_Cybernetics_Core 1 6747
Protoss_Dragoon 7 14773
Protoss_Robotics_Facility 1 10459
Protoss_Observatory 1 11179
Singularity_Charge 1 11041
Protoss_Observer 2 13188
Protoss_Nexus 1 14703
Protoss_Robotics_Support_Bay 1 13090
Protoss_Reaver 1 14974
Protoss_Citadel_of_Adun 1 15797
15797
