Protoss_Gateway 2 14674
Protoss_Assimilator 2 14720
Protoss_Zealot 2 6819
Protoss_Cybernetics_Core 1 6869
Protoss_Dragoon 4 11390
Protoss_Citadel_of_Adun 1 9804
Protoss_Templar_Archives 1 11253
Protoss_Nexus 1 13495
Singularity_Charge 1 10957
Protoss_Forge 1 12096
Protoss_Dark_Templar 1 12578
Protoss_Photon_Cannon 4 15458
Protoss_High_Templar 2 14872
15458
