Protoss_Gateway 2 10349
Protoss_Assimilator 1 4567
Protoss_Zealot 2 7000
Protoss_Cybernetics_Core 1 6971
Protoss_Dragoon 11 15414
Protoss_Robotics_Facility 1 10353
Protoss_Shuttle 1 11847
Singularity_Charge 1 11088
Protoss_Robotics_Support_Bay 1 12066
Protoss_Reaver 1 13806
Protoss_Observatory 1 13443
Protoss_Observer 1 14631
15414
