Protoss_Gateway 2 9892
Protoss_Zealot 2 6672
Protoss_Assimilator 1 5667
Protoss_Cybernetics_Core 1 6923
Protoss_Dragoon 11 14908
Protoss_Robotics_Facility 1 11725
Singularity_Charge 1 11211
Protoss_Observatory 1 12550
Protoss_Observer 1 14156
Protoss_Nexus 1 17269
17269
