Protoss_Gateway 2 15213
Protoss_Assimilator 2 14405
Protoss_Zealot 2 6933
Protoss_Cybernetics_Core 1 6983
Protoss_Dragoon 4 11802
Protoss_Citadel_of_Adun 1 10410
Protoss_Templar_Archives 1 11947
Protoss_Nexus 1 14171
Singularity_Charge 1 11399
Protoss_Forge 1 12693
Protoss_Dark_Templar 1 13143
Protoss_Photon_Cannon 3 15811
Protoss_High_Templar 2 15414
15811
