Protoss_Gateway 3 14161
Protoss_Assimilator 1 4635
Protoss_Zealot 8 14669
Protoss_Cybernetics_Core 1 7076
Protoss_Shield_Battery 1 8343
Protoss_Dragoon 6 15669
Protoss_Robotics_Facility 1 13383
Protoss_Observatory 1 14120
Singularity_Charge 1 14138
Protoss_Observer 1 15131
15669
