Protoss_Gateway 2 4902
Protoss_Assimilator 1 5459
Protoss_Cybernetics_Core 1 6873
Protoss_Zealot 3 14209
Protoss_Citadel_of_Adun 1 8947
Protoss_Forge 1 9356
Protoss_Templar_Archives 1 10823
Protoss_High_Templar 2 12370
Protoss_Nexus 1 14791
Protoss_Photon_Cannon 3 15484
Protoss_Dark_Templar 1 13649
Protoss_Archon 1 12934
15484
