Protoss_Gateway 4 15974
Protoss_Assimilator 1 5091
Protoss_Cybernetics_Core 1 6852
Protoss_Zealot 2 7431
Protoss_Dragoon 9 14246
Protoss_Robotics_Facility 1 10014
Protoss_Observatory 1 11239
Singularity_Charge 1 11077
Protoss_Observer 2 13305
Protoss_Nexus 1 16865
16865
