Protoss_Gateway 2 5167
Protoss_Zealot 5 8329
Protoss_Assimilator 1 6112
Protoss_Cybernetics_Core 1 8484
Protoss_Dragoon 8 15499
Protoss_Robotics_Facility 1 12867
Singularity_Charge 1 12186
Protoss_Nexus 1 15495
Protoss_Observatory 1 13686
Protoss_Robotics_Support_Bay 1 14082
Protoss_Observer 1 14961
15499
