Protoss_Gateway 2 7931
Protoss_Assimilator 1 4562
Protoss_Zealot 3 7712
Protoss_Cybernetics_Core 1 6801
Protoss_Dragoon 8 14035
Protoss_Robotics_Facility 1 11401
Singularity_Charge 1 11317
Protoss_Observatory 1 12348
Protoss_Observer 2 14241
Protoss_Robotics_Support_Bay 1 13819
Protoss_Nexus 1 17004
Protoss_Reaver 1 16279
17004
