Protoss_Gateway 2 15242
Protoss_Forge 1 5530
Protoss_Photon_Cannon 7 11776
Protoss_Zealot 2 10551
Protoss_Nexus 1 12160
Protoss_Assimilator 1 11104
Protoss_Cybernetics_Core 1 12883
Protoss_Dragoon 2 15417
Protoss_Robotics_Facility 1 15082
Protoss_Citadel_of_Adun 1 15902
15902
