Protoss_Gateway 3 13106
Protoss_Assimilator 2 5944
Protoss_Zealot 7 11350
Protoss_Cybernetics_Core 1 8385
Protoss_Dragoon 4 14992
Protoss_Citadel_of_Adun 1 11313
Protoss_Forge 1 12118
Protoss_Templar_Archives 1 12980
Protoss_Photon_Cannon 1 14015
Protoss_Dark_Templar 3 14442
Singularity_Charge 1 13409
Protoss_High_Templar 1 14735
Protoss_Nexus 1 17109
17109
