Protoss_Gateway 3 13938
Protoss_Zealot 6 14970
Protoss_Nexus 1 10768
Protoss_Forge 2 10003
Protoss_Assimilator 2 14765
Protoss_Photon_Cannon 3 12493
Protoss_Cybernetics_Core 1 12312
Protoss_Dragoon 2 14419
Protoss_Robotics_Facility 1 15945
15945
