Protoss_Gateway 2 15090
Protoss_Assimilator 1 4136
Protoss_Zealot 3 10354
Protoss_Cybernetics_Core 1 6999
Protoss_Dragoon 6 15493
Protoss_Nexus 3 17434
Protoss_Robotics_Facility 1 13129
Singularity_Charge 1 11396
Protoss_Observatory 1 13877
17434
