Protoss_Gateway 4 15389
Protoss_Assimilator 1 4196
Protoss_Zealot 2 6795
Protoss_Cybernetics_Core 1 6845
Protoss_Dragoon 12 15338
Protoss_Robotics_Facility 1 9908
Protoss_Observatory 1 11395
Singularity_Charge 1 11015
Protoss_Observer 2 13343
15389
