Protoss_Gateway 2 11253
Protoss_Assimilator 2 13612
Protoss_Zealot 2 6593
Protoss_Cybernetics_Core 1 6811
Protoss_Dragoon 3 10432
Protoss_Citadel_of_Adun 1 9627
Protoss_Nexus 1 11746
Protoss_Templar_Archives 1 11349
Protoss_Forge 1 11938
Protoss_Dark_Templar 2 12572
Protoss_Photon_Cannon 2 13547
Protoss_High_Templar 4 15610
15610
