Protoss_Gateway 2 4976
Protoss_Zealot 6 7969
Protoss_Assimilator 1 9277
Protoss_Cybernetics_Core 1 10103
Protoss_Nexus 1 12772
Protoss_Dragoon 6 14741
Protoss_Forge 1 12539
Protoss_Photon_Cannon 1 14141
Protoss_Robotics_Facility 1 16201
16201
