Protoss_Gateway 2 9962
Protoss_Assimilator 1 4445
Protoss_Zealot 2 6362
Protoss_Cybernetics_Core 1 6637
Protoss_Dragoon 9 15610
Protoss_Robotics_Facility 1 10181
Protoss_Observatory 1 11034
Singularity_Charge 1 10679
Protoss_Observer 2 13981
Protoss_Nexus 1 15287
Protoss_Robotics_Support_Bay 1 13636
Protoss_Reaver 1 16036
16036
