Protoss_Gateway 2 11256
Protoss_Assimilator 1 4325
Protoss_Zealot 2 6716
Protoss_Cybernetics_Core 1 6661
Protoss_Dragoon 8 15560
Protoss_Robotics_Facility 1 10479
Protoss_Shuttle 1 11999
Protoss_Observatory 1 11713
Singularity_Charge 1 11153
Protoss_Observer 1 12842
Protoss_Robotics_Support_Bay 1 13131
Protoss_Nexus 1 16146
Protoss_Reaver 1 15518
16146
