Protoss_Gateway 2 7433
Protoss_Assimilator 1 4376
Protoss_Zealot 3 13290
Protoss_Cybernetics_Core 1 6391
Protoss_Dragoon 11 15431
Protoss_Robotics_Facility 1 11465
Singularity_Charge 1 10330
Protoss_Observatory 1 12159
Protoss_Robotics_Support_Bay 1 12878
Protoss_Observer 1 13264
Protoss_Nexus 1 15707
Protoss_Reaver 1 15196
15707
