Protoss_Gateway 3 10896
Protoss_Zealot 6 8876
Protoss_Assimilator 1 8003
Protoss_Cybernetics_Core 1 9950
Protoss_Dragoon 5 13365
Protoss_Citadel_of_Adun 1 11765
Protoss_Templar_Archives 1 13274
Protoss_Forge 1 13568
Protoss_Dark_Templar 2 14656
Protoss_Photon_Cannon 1 15066
15066
