Protoss_Gateway 2 9084
Protoss_Assimilator 1 4211
Protoss_Cybernetics_Core 1 5696
Protoss_Dragoon 9 12882
Singularity_Charge 1 9918
Protoss_Robotics_Facility 1 13154
Protoss_Observatory 1 13911
Protoss_Zealot 1 14273
Protoss_Nexus 1 16497
Protoss_Observer 1 14926
Protoss_Robotics_Support_Bay 1 14930
16497
