Protoss_Gateway 3 11709
Protoss_Assimilator 2 14363
Protoss_Zealot 2 6699
Protoss_Cybernetics_Core 1 6773
Protoss_Dragoon 10 15669
Protoss_Nexus 1 11715
Protoss_Robotics_Facility 1 11490
Singularity_Charge 1 10816
Protoss_Observatory 1 12271
Protoss_Observer 2 15289
Protoss_Citadel_of_Adun 1 14430
15669
