Protoss_Gateway 3 13322
Protoss_Assimilator 2 15026
Protoss_Cybernetics_Core 1 5666
Protoss_Zealot 1 5449
Protoss_Dragoon 10 15701
Protoss_Robotics_Facility 1 10789
Protoss_Nexus 1 13332
Protoss_Observatory 1 12001
Singularity_Charge 1 11372
Protoss_Observer 2 13899
Protoss_Citadel_of_Adun 1 15732
15732
