Protoss_Gateway 3 14566
Protoss_Assimilator 1 4116
Protoss_Zealot 2 6392
Protoss_Cybernetics_Core 1 6451
Protoss_Dragoon 10 15774
Protoss_Robotics_Facility 1 9226
Protoss_Robotics_Support_Bay 1 9920
Protoss_Reaver 2 13791
Protoss_Observatory 1 11381
Singularity_Charge 1 11639
Protoss_Observer 1 12702
Protoss_Shuttle 1 15309
15774
