Protoss_Gateway 3 13723
Protoss_Assimilator 1 4335
Protoss_Zealot 4 14607
Protoss_Cybernetics_Core 1 6462
Protoss_Dragoon 11 14949
Protoss_Robotics_Facility 1 10422
Singularity_Charge 1 10766
Protoss_Observatory 1 11782
Protoss_Observer 1 12945
Protoss_Robotics_Support_Bay 1 13863
Protoss_Shuttle 1 15845
15845
