Protoss_Gateway 2 11390
Protoss_Assimilator 2 13047
Protoss_Cybernetics_Core 1 6245
Protoss_Zealot 2 14080
Protoss_Dragoon 8 15584
Protoss_Nexus 1 11681
Singularity_Charge 1 11006
Protoss_Citadel_of_Adun 1 13166
Protoss_Robotics_Facility 1 14588
Protoss_Templar_Archives 1 15261
Protoss_Observatory 1 15306
15584
