Protoss_Gateway 2 7448
Protoss_Assimilator 1 4574
Protoss_Zealot 2 15169
Protoss_Cybernetics_Core 1 6789
Protoss_Dragoon 12 15727
Protoss_Robotics_Facility 1 10731
Singularity_Charge 1 10717
Protoss_Shuttle 1 12181
Protoss_Robotics_Support_Bay 1 11577
Protoss_Reaver 2 15278
Protoss_Observatory 1 14739
15727
