Protoss_Gateway 2 9236
Protoss_Assimilator 2 15207
Protoss_Zealot 2 6696
Protoss_Cybernetics_Core 1 6693
Protoss_Dragoon 3 12414
Protoss_Citadel_of_Adun 1 8505
Protoss_Templar_Archives 1 9948
Protoss_Dark_Templar 4 12964
Protoss_Nexus 1 13843
Protoss_Forge 1 12372
Protoss_Photon_Cannon 4 14508
Protoss_High_Templar 2 15197
15207
