Protoss_Gateway 2 10738
Protoss_Assimilator 1 4170
Protoss_Zealot 2 6722
Protoss_Cybernetics_Core 1 6800
Protoss_Dragoon 8 15657
Protoss_Robotics_Facility 1 9987
Protoss_Observatory 1 10879
Protoss_Robotics_Support_Bay 1 11169
Singularity_Charge 1 11164
Protoss_Observer 1 12233
Protoss_Shuttle 1 13815
Protoss_Reaver 1 15373
Protoss_Nexus 1 17083
17083
