Protoss_Gateway 4 15368
Protoss_Forge 1 4782
Protoss_Zealot 9 13147
Protoss_Photon_Cannon 8 11240
Protoss_Assimilator 1 12604
Protoss_Cybernetics_Core 1 14272
Protoss_Dragoon 1 15560
15560
