Protoss_Gateway 3 12289
Protoss_Zealot 5 8373
Protoss_Assimilator 1 6444
Protoss_Cybernetics_Core 1 7922
Protoss_Dragoon 8 15683
Protoss_Robotics_Facility 1 13860
Singularity_Charge 1 12259
Protoss_Shuttle 1 15257
Protoss_Robotics_Support_Bay 1 14867
15683
