Protoss_Gateway 3 13887
Protoss_Assimilator 1 4410
Protoss_Zealot 4 14110
Protoss_Cybernetics_Core 1 7097
Protoss_Dragoon 8 15180
Protoss_Robotics_Facility 1 10769
Protoss_Shuttle 1 12257
Protoss_Observatory 1 11988
Singularity_Charge 1 11437
Protoss_Robotics_Support_Bay 1 12777
Protoss_Observer 1 13100
Protoss_Reaver 1 15155
15180
