Protoss_Gateway 3 12438
Protoss_Assimilator 1 4700
Protoss_Zealot 3 13829
Protoss_Cybernetics_Core 1 6454
Protoss_Dragoon 11 15317
Protoss_Nexus 1 12726
Singularity_Charge 1 10954
Protoss_Robotics_Facility 1 13912
Protoss_Observatory 1 14761
15317
