Protoss_Gateway 3 11411
Protoss_Assimilator 1 4488
Protoss_Cybernetics_Core 1 5818
Protoss_Dragoon 14 15610
Protoss_Robotics_Facility 1 10776
Singularity_Charge 1 10000
Protoss_Observatory 1 12010
Protoss_Observer 1 13463
Protoss_Nexus 1 16524
16524
