Protoss_Gateway 3 12690
Protoss_Assimilator 1 4555
Protoss_Zealot 2 6465
Protoss_Cybernetics_Core 1 6807
Protoss_Dragoon 11 15238
Protoss_Robotics_Facility 1 11363
Singularity_Charge 1 10693
Protoss_Robotics_Support_Bay 1 12449
Protoss_Reaver 1 14181
Protoss_Observatory 1 13771
Protoss_Observer 1 15514
15514
