Protoss_Gateway 2 13272
Protoss_Assimilator 1 4376
Protoss_Zealot 2 7144
Protoss_Cybernetics_Core 1 6744
Protoss_Dragoon 8 15388
Protoss_Robotics_Facility 1 9314
Protoss_Shuttle 1 10720
Protoss_Robotics_Support_Bay 1 10310
Protoss_Reaver 1 12278
Protoss_Observatory 1 12688
Protoss_Observer 2 14651
Protoss_Nexus 1 16530
Singularity_Charge 1 14369
16530
