Protoss_Gateway 2 10231
Protoss_Assimilator 1 4252
Protoss_Zealot 2 6915
Protoss_Cybernetics_Core 1 6965
Protoss_Dragoon 9 15235
Protoss_Robotics_Facility 1 10277
Protoss_Observatory 1 11368
Singularity_Charge 1 10927
Protoss_Observer 1 12415
Protoss_Robotics_Support_Bay 1 12708
Protoss_Nexus 1 15467
Protoss_Reaver 1 14810
15467
