Protoss_Gateway 2 10092
Protoss_Assimilator 1 4172
Protoss_Zealot 2 6629
Protoss_Cybernetics_Core 1 6912
Protoss_Dragoon 11 14995
Protoss_Robotics_Facility 1 12405
Singularity_Charge 1 10930
Protoss_Robotics_Support_Bay 1 14414
Protoss_Shuttle 1 15260
Protoss_Observatory 1 14988
15260
