Protoss_Gateway 2 7963
Protoss_Assimilator 1 4195
Protoss_Zealot 1 5104
Protoss_Cybernetics_Core 1 6959
Protoss_Dragoon 10 14905
Protoss_Robotics_Facility 1 11356
Protoss_Observatory 1 12212
Singularity_Charge 1 12329
Protoss_Observer 1 13290
Protoss_Shuttle 1 14648
Protoss_Nexus 1 16133
Protoss_Robotics_Support_Bay 1 14189
16133
