Protoss_Gateway 3 15596
Protoss_Assimilator 1 4515
Protoss_Zealot 1 5256
Protoss_Cybernetics_Core 1 6175
Protoss_Dragoon 10 14905
Protoss_Robotics_Facility 1 11667
Singularity_Charge 1 10231
Protoss_Observatory 1 12391
Protoss_Observer 2 14420
Protoss_Nexus 1 15763
15763
