Protoss_Gateway 4 12880
Protoss_Zealot 2 7129
Protoss_Nexus 1 8665
Protoss_Assimilator 1 7378
Protoss_Forge 1 8260
Protoss_Cybernetics_Core 1 9213
Protoss_Photon_Cannon 4 15511
Protoss_Dragoon 10 15367
Singularity_Charge 1 13439
15511
