Protoss_Gateway 2 11234
Protoss_Assimilator 2 15233
Protoss_Zealot 2 7641
Protoss_Cybernetics_Core 1 7719
Protoss_Dragoon 6 15657
Protoss_Robotics_Facility 1 11021
Protoss_Observatory 1 11712
Protoss_Robotics_Support_Bay 1 11946
Singularity_Charge 1 11685
Protoss_Observer 1 12737
Protoss_Nexus 1 15137
Protoss_Reaver 1 15392
15657
