Protoss_Gateway 2 9981
Protoss_Assimilator 1 4318
Protoss_Zealot 2 6541
Protoss_Cybernetics_Core 1 6529
Protoss_Citadel_of_Adun 1 8589
Protoss_Dragoon 3 15480
Protoss_Templar_Archives 1 10097
Protoss_Dark_Templar 2 11548
Protoss_Forge 1 11215
Protoss_Nexus 1 14504
Protoss_Photon_Cannon 2 14129
Protoss_High_Templar 2 14346
15480
