Protoss_Gateway 2 6803
Protoss_Assimilator 2 12989
Protoss_Zealot 1 5072
Protoss_Cybernetics_Core 1 6197
Protoss_Dragoon 13 15437
Protoss_Nexus 1 12251
Singularity_Charge 1 10160
Protoss_Citadel_of_Adun 1 12573
Protoss_Templar_Archives 1 14669
Protoss_Robotics_Facility 1 16372
16372
