Protoss_Gateway 2 10349
Protoss_Assimilator 1 4527
Protoss_Zealot 2 6953
Protoss_Cybernetics_Core 1 7053
Protoss_Dragoon 7 15086
Protoss_Citadel_of_Adun 1 9855
Protoss_Templar_Archives 1 11344
Singularity_Charge 1 11138
Protoss_Dark_Templar 4 13986
Protoss_Forge 1 12623
Protoss_Nexus 1 17001
17001
