Protoss_Gateway 3 14145
Protoss_Assimilator 1 4644
Protoss_Cybernetics_Core 1 6102
Protoss_Dragoon 13 15644
Protoss_Robotics_Facility 1 11026
Protoss_Observatory 1 11734
Singularity_Charge 1 11701
Protoss_Observer 1 12756
Protoss_Robotics_Support_Bay 1 15320
15644
