Protoss_Gateway 3 15709
Protoss_Assimilator 1 4428
Protoss_Cybernetics_Core 1 5977
Protoss_Robotics_Facility 1 8136
Protoss_Dragoon 5 15739
Protoss_Shuttle 1 9545
Protoss_Robotics_Support_Bay 1 8987
Protoss_Reaver 3 14349
Gravitic_Drive 1 13392
Protoss_Observatory 1 14277
Protoss_Nexus 1 16910
16910
