Protoss_Gateway 2 15043
Protoss_Assimilator 1 4821
Protoss_Cybernetics_Core 1 6269
Protoss_Robotics_Facility 1 8356
Protoss_Dragoon 6 15395
Protoss_Shuttle 1 9757
Protoss_Observatory 1 9345
Protoss_Observer 1 11256
Protoss_Robotics_Support_Bay 1 11205
Protoss_Reaver 2 15176
Singularity_Charge 1 12601
15395
