Protoss_Gateway 3 15813
Protoss_Assimilator 1 4472
Protoss_Zealot 2 6807
Protoss_Cybernetics_Core 1 6912
Protoss_Dragoon 10 15692
Protoss_Robotics_Facility 1 10522
Protoss_Observatory 1 11314
Singularity_Charge 1 10933
Protoss_Observer 1 12558
Protoss_Robotics_Support_Bay 1 12436
Protoss_Reaver 1 14611
Protoss_Nexus 1 16530
16530
