Protoss_Gateway 2 7624
Protoss_Assimilator 1 4719
Protoss_Cybernetics_Core 1 6197
Protoss_Dragoon 10 14963
Protoss_Robotics_Facility 1 10981
Protoss_Observatory 1 11840
Protoss_Observer 1 12873
Protoss_Robotics_Support_Bay 1 12865
Protoss_Shuttle 1 14528
Singularity_Charge 1 13780
14963
