Protoss_Gateway 2 9217
Protoss_Zealot 2 6790
Protoss_Assimilator 2 15550
Protoss_Cybernetics_Core 1 7274
Protoss_Dragoon 12 15587
Protoss_Robotics_Facility 1 11512
Singularity_Charge 1 10851
Protoss_Observatory 1 12360
Protoss_Observer 2 14186
Protoss_Nexus 1 15499
Protoss_Citadel_of_Adun 1 15217
15587
