Protoss_Gateway 2 9400
Protoss_Assimilator 1 4777
Protoss_Zealot 1 4943
Protoss_Cybernetics_Core 1 7040
Protoss_Dragoon 7 15317
Protoss_Citadel_of_Adun 1 8382
Protoss_Templar_Archives 1 9727
Protoss_Forge 1 9700
Protoss_Dark_Templar 4 12686
Protoss_Photon_Cannon 5 12916
Protoss_Nexus 1 16808
16808
