Protoss_Gateway 2 5200
Protoss_Assimilator 2 6757
Protoss_Zealot 5 7129
Protoss_Cybernetics_Core 1 8420
Protoss_Dragoon 9 14565
Protoss_Forge 1 11292
Protoss_Nexus 1 15097
Singularity_Charge 1 12537
15097
