Protoss_Gateway 2 11737
Protoss_Assimilator 1 4382
Protoss_Zealot 2 6588
Protoss_Cybernetics_Core 1 6653
Protoss_Dragoon 9 15440
Protoss_Robotics_Facility 1 10514
Protoss_Shuttle 1 12023
Singularity_Charge 1 10717
Protoss_Observatory 1 11439
Protoss_Observer 1 12986
Protoss_Robotics_Support_Bay 1 13090
Protoss_Reaver 1 14904
15440
