Protoss_Gateway 2 10946
Protoss_Assimilator 1 4489
Protoss_Zealot 2 6848
Protoss_Cybernetics_Core 1 6961
Protoss_Dragoon 9 15241
Protoss_Robotics_Facility 1 10166
Protoss_Shuttle 1 11789
Protoss_Observatory 1 11297
Singularity_Charge 1 11501
Protoss_Robotics_Support_Bay 1 12353
Protoss_Observer 1 12632
Protoss_Reaver 1 14227
Protoss_Nexus 1 16597
16597
