Protoss_Gateway 2 7865
Protoss_Assimilator 1 4549
Protoss_Cybernetics_Core 1 5875
Protoss_Dragoon 14 15332
Singularity_Charge 1 11131
Protoss_Forge 1 12377
Protoss_Photon_Cannon 1 13931
Protoss_Robotics_Facility 1 15964
15964
