Protoss_Gateway 2 10572
Protoss_Assimilator 1 4761
Protoss_Zealot 3 9595
Protoss_Cybernetics_Core 1 7905
Protoss_Nexus 1 11234
Protoss_Dragoon 8 15254
Protoss_Shield_Battery 1 11201
Protoss_Citadel_of_Adun 1 14546
Protoss_Robotics_Facility 1 15459
Protoss_Templar_Archives 1 16021
16021
