Protoss_Gateway 3 13267
Protoss_Assimilator 1 4632
Protoss_Cybernetics_Core 1 6087
Protoss_Dragoon 14 15639
Singularity_Charge 1 9909
Protoss_Robotics_Facility 1 12351
Protoss_Observatory 1 13112
Protoss_Observer 1 14775
Protoss_Robotics_Support_Bay 1 15345
15639
