Protoss_Gateway 2 5209
Protoss_Zealot 7 9632
Protoss_Assimilator 1 6850
Protoss_Cybernetics_Core 1 9119
Protoss_Dragoon 8 14744
Protoss_Robotics_Facility 1 13536
Singularity_Charge 1 13048
Protoss_Observatory 1 14774
14774
