Protoss_Gateway 4 14357
Protoss_Zealot 8 15449
Protoss_Assimilator 1 5317
Protoss_Cybernetics_Core 1 7151
Protoss_Robotics_Facility 1 9102
Protoss_Dragoon 4 12410
Protoss_Observatory 1 9819
Protoss_Observer 1 10853
Protoss_Nexus 1 13632
Singularity_Charge 1 13019
Protoss_Citadel_of_Adun 1 15307
15449
