Protoss_Gateway 3 14218
Protoss_Zealot 6 9010
Protoss_Assimilator 1 7518
Protoss_Cybernetics_Core 1 9270
Protoss_Dragoon 8 15783
Protoss_Robotics_Facility 1 12329
Protoss_Observatory 1 13333
Protoss_Observer 2 15332
15783
