Protoss_Gateway 3 12405
Protoss_Assimilator 1 4682
Protoss_Cybernetics_Core 1 6084
Protoss_Dragoon 12 15124
Protoss_Robotics_Facility 1 8663
Protoss_Observatory 1 9462
Protoss_Observer 2 15032
Singularity_Charge 1 14123
15124
