Protoss_Nexus 1 6565
Protoss_Gateway 4 15712
Protoss_Assimilator 2 6302
Protoss_Cybernetics_Core 1 7782
Protoss_Dragoon 9 13700
Protoss_Robotics_Facility 1 13295
Singularity_Charge 1 11833
Protoss_Zealot 2 13856
Protoss_Observatory 1 14049
Protoss_Observer 1 15229
15712
