Protoss_Gateway 3 15131
Protoss_Assimilator 1 4586
Protoss_Zealot 3 7502
Protoss_Cybernetics_Core 1 7514
Protoss_Dragoon 8 15673
Protoss_Nexus 2 13354
Singularity_Charge 1 11504
Protoss_Robotics_Facility 1 14026
Protoss_Shield_Battery 1 13084
Protoss_Observatory 1 15029
15673
