Protoss_Nexus 1 6969
Protoss_Gateway 5 15463
Protoss_Assimilator 2 11976
Protoss_Zealot 8 11032
Protoss_Cybernetics_Core 1 9877
Protoss_Citadel_of_Adun 1 11831
Protoss_Dragoon 2 13705
Protoss_Forge 1 12093
Protoss_Templar_Archives 1 13335
Protoss_Photon_Cannon 4 14286
Protoss_Dark_Templar 2 14619
15463
