Protoss_Gateway 3 15929
Protoss_Zealot 6 9127
Protoss_Assimilator 1 8003
Protoss_Cybernetics_Core 1 10714
Protoss_Citadel_of_Adun 1 12282
Protoss_Dragoon 2 12183
Protoss_Templar_Archives 1 13818
Protoss_Forge 1 14623
Protoss_Dark_Templar 2 15205
15929
