Protoss_Gateway 2 6879
Protoss_Zealot 7 10473
Protoss_Assimilator 1 8434
Protoss_Cybernetics_Core 1 10331
Protoss_Dragoon 7 15351
Protoss_Robotics_Facility 1 14922
Singularity_Charge 1 14101
15351
