Protoss_Gateway 3 10745
Protoss_Zealot 17 14145
Protoss_Shield_Battery 1 9865
Protoss_Assimilator 1 12431
Protoss_Cybernetics_Core 1 13609
Protoss_Dragoon 2 15265
Protoss_Citadel_of_Adun 1 15978
15978
