Protoss_Gateway 2 12235
Protoss_Assimilator 1 5619
Protoss_Zealot 1 5739
Protoss_Cybernetics_Core 1 7732
Protoss_Dragoon 8 15121
Protoss_Robotics_Facility 1 9834
Protoss_Observatory 1 10646
Protoss_Observer 1 11809
Protoss_Shuttle 1 13492
Protoss_Robotics_Support_Bay 1 13954
Singularity_Charge 1 13248
Protoss_Reaver 1 15700
15700
