Protoss_Gateway 1 4294
Protoss_Assimilator 1 4565
Protoss_Cybernetics_Core 1 6029
Protoss_Zealot 1 5856
Protoss_Dragoon 4 15250
Protoss_Robotics_Facility 1 8736
Protoss_Shuttle 1 10170
Protoss_Observatory 1 9562
Protoss_Robotics_Support_Bay 1 10039
Protoss_Observer 2 15567
Protoss_Reaver 2 14743
Gravitic_Drive 1 13951
15567
