Protoss_Gateway 2 10529
Protoss_Assimilator 1 5180
Protoss_Zealot 3 14351
Protoss_Cybernetics_Core 1 7126
Protoss_Dragoon 8 14597
Protoss_Robotics_Facility 1 13039
Singularity_Charge 1 11343
Protoss_Observatory 1 13757
Protoss_Robotics_Support_Bay 1 13889
Protoss_Observer 1 14783
14783
