Protoss_Gateway 3 11626
Protoss_Zealot 5 7758
Protoss_Assimilator 1 6396
Protoss_Cybernetics_Core 1 7572
Protoss_Dragoon 9 14510
Protoss_Forge 1 11294
Singularity_Charge 1 12250
Protoss_Photon_Cannon 1 13912
Protoss_Robotics_Facility 1 16181
16181
