Protoss_Gateway 3 15188
Protoss_Zealot 5 15479
Protoss_Assimilator 1 7103
Protoss_Cybernetics_Core 1 8487
Protoss_Dragoon 10 14618
Protoss_Forge 1 12302
Protoss_Citadel_of_Adun 1 15446
Protoss_Photon_Cannon 1 15535
15535
