Protoss_Gateway 3 15965
Protoss_Assimilator 1 5398
Protoss_Zealot 3 8095
Protoss_Cybernetics_Core 1 9940
Protoss_Dragoon 5 15417
Protoss_Robotics_Facility 1 13024
Protoss_Nexus 1 15297
Protoss_Observatory 1 13775
Singularity_Charge 1 13728
Protoss_Observer 1 14812
15965
