Protoss_Gateway 2 5238
Protoss_Zealot 7 9873
Protoss_Assimilator 1 6804
Protoss_Cybernetics_Core 1 9327
Protoss_Citadel_of_Adun 1 11111
Protoss_Dragoon 3 15614
Protoss_Robotics_Facility 1 12392
Protoss_Templar_Archives 1 12746
Protoss_Shuttle 1 13804
Protoss_Forge 1 13549
Protoss_Dark_Templar 2 13983
Protoss_Photon_Cannon 2 14908
15614
