Protoss_Gateway 2 13489
Protoss_Assimilator 1 4390
Protoss_Zealot 2 6775
Protoss_Cybernetics_Core 1 6637
Protoss_Robotics_Facility 1 8556
Protoss_Dragoon 7 15759
Protoss_Shuttle 1 9956
Protoss_Observatory 1 9607
Protoss_Robotics_Support_Bay 1 10346
Protoss_Observer 2 15001
Protoss_Reaver 2 14131
Singularity_Charge 1 13699
15759
