Protoss_Gateway 2 5051
Protoss_Zealot 6 10605
Protoss_Assimilator 1 6250
Protoss_Cybernetics_Core 1 7992
Protoss_Dragoon 3 12395
Protoss_Citadel_of_Adun 2 11004
Protoss_Templar_Archives 1 12460
Protoss_Dark_Templar 2 13675
Protoss_Forge 1 13546
Protoss_Nexus 1 16149
Protoss_High_Templar 1 15483
16149
