Protoss_Gateway 3 14189
Protoss_Assimilator 1 4390
Protoss_Zealot 4 11190
Protoss_Cybernetics_Core 1 7397
Protoss_Dragoon 8 14195
Protoss_Robotics_Facility 1 11865
Protoss_Observatory 1 12653
Protoss_Observer 2 15119
Protoss_Nexus 1 16991
Singularity_Charge 1 14153
16991
