Protoss_Gateway 2 5174
Protoss_Zealot 8 10027
Protoss_Assimilator 1 8369
Protoss_Cybernetics_Core 1 9798
Protoss_Dragoon 6 15066
Protoss_Robotics_Facility 1 13083
Protoss_Shuttle 1 14689
Protoss_Robotics_Support_Bay 1 14275
Protoss_Forge 1 14651
15066
