Protoss_Gateway 2 5083
Protoss_Zealot 7 13805
Protoss_Assimilator 1 6200
Protoss_Cybernetics_Core 1 8604
Protoss_Dragoon 8 14963
Protoss_Robotics_Facility 1 11439
Protoss_Observatory 1 12603
Protoss_Observer 1 14115
Protoss_Shuttle 1 16003
16003
