Protoss_Gateway 2 6908
Protoss_Assimilator 1 4599
Protoss_Zealot 4 7870
Protoss_Cybernetics_Core 1 7669
Protoss_Dragoon 11 15625
Protoss_Robotics_Facility 1 13189
Protoss_Observatory 1 13913
Singularity_Charge 1 13298
Protoss_Observer 1 15403
15625
