Protoss_Gateway 3 14550
Protoss_Zealot 5 8373
Protoss_Assimilator 1 7527
Protoss_Cybernetics_Core 1 9432
Protoss_Dragoon 8 14583
Protoss_Robotics_Facility 1 13536
Singularity_Charge 1 13362
Protoss_Observatory 1 14401
Protoss_Observer 1 15419
15419
