Protoss_Gateway 2 9576
Protoss_Assimilator 1 4622
Protoss_Zealot 3 6902
Protoss_Cybernetics_Core 1 7133
Protoss_Dragoon 12 15592
Protoss_Robotics_Facility 1 13185
Singularity_Charge 1 12009
Protoss_Observatory 1 14035
Protoss_Shuttle 1 15274
15592
