Protoss_Gateway 2 5265
Protoss_Zealot 7 8739
Protoss_Assimilator 1 6661
Protoss_Cybernetics_Core 1 8508
Protoss_Dragoon 10 15475
Protoss_Robotics_Facility 1 13792
Singularity_Charge 1 12887
Protoss_Observatory 1 14935
15475
