Protoss_Gateway 4 15516
Protoss_Zealot 6 8190
Protoss_Assimilator 1 5871
Protoss_Cybernetics_Core 1 8049
Protoss_Dragoon 13 15805
Protoss_Robotics_Facility 1 13309
Singularity_Charge 1 12265
Protoss_Observatory 1 14054
Protoss_Observer 1 15097
15805
