Protoss_Gateway 3 13350
Protoss_Zealot 3 6763
Protoss_Assimilator 1 5178
Protoss_Cybernetics_Core 1 6961
Protoss_Dragoon 9 15666
Protoss_Robotics_Facility 1 9446
Protoss_Shuttle 1 11074
Protoss_Observatory 1 10670
Protoss_Observer 1 11917
Protoss_Robotics_Support_Bay 1 12231
Protoss_Reaver 2 15527
Singularity_Charge 1 12682
15666
