Protoss_Gateway 1 4302
Protoss_Assimilator 1 4587
Protoss_Zealot 4 9289
Protoss_Cybernetics_Core 1 9364
Protoss_Dragoon 3 14591
Protoss_Robotics_Facility 1 12085
Protoss_Shuttle 1 13548
Protoss_Observatory 1 12934
Protoss_Observer 1 14391
Protoss_Robotics_Support_Bay 1 14224
Protoss_Reaver 1 15989
15989
