Protoss_Gateway 3 13199
Protoss_Assimilator 1 4725
Protoss_Zealot 1 5424
Protoss_Cybernetics_Core 1 7267
Protoss_Dragoon 9 15190
Protoss_Robotics_Facility 1 11875
Protoss_Observatory 1 12821
Singularity_Charge 1 12623
Protoss_Observer 2 15288
Protoss_Nexus 1 16588
16588
