Protoss_Gateway 2 9724
Protoss_Zealot 7 10814
Protoss_Assimilator 1 8175
Protoss_Cybernetics_Core 1 9776
Protoss_Citadel_of_Adun 1 11888
Protoss_Dragoon 4 13711
Protoss_Templar_Archives 1 13331
Protoss_Forge 1 13272
Protoss_Dark_Templar 2 14811
Protoss_Photon_Cannon 1 14817
Protoss_Nexus 1 17425
17425
