Protoss_Gateway 3 15526
Protoss_Zealot 4 10296
Protoss_Assimilator 1 7371
Protoss_Cybernetics_Core 1 10170
Protoss_Citadel_of_Adun 1 11780
Protoss_Dragoon 1 11714
Protoss_Templar_Archives 1 13378
Protoss_Forge 1 14099
Protoss_Dark_Templar 2 14902
Protoss_Photon_Cannon 1 15557
15557
