Protoss_Gateway 2 14294
Protoss_Assimilator 1 4644
Protoss_Cybernetics_Core 1 6132
Protoss_Dragoon 7 15702
Protoss_Robotics_Facility 1 11420
Protoss_Nexus 1 13225
Singularity_Charge 1 10487
Protoss_Robotics_Support_Bay 1 12259
Protoss_Reaver 1 14298
Protoss_Observatory 1 13715
Protoss_Shield_Battery 1 14679
Protoss_Observer 1 15122
15702
