Protoss_Gateway 2 8689
Protoss_Zealot 9 14666
Protoss_Assimilator 1 8310
Protoss_Cybernetics_Core 1 9766
Protoss_Dragoon 5 14829
Protoss_Robotics_Facility 1 13214
Protoss_Shuttle 1 14613
Protoss_Observatory 1 14303
Protoss_Robotics_Support_Bay 1 15306
15306
