Protoss_Gateway 2 10629
Protoss_Zealot 4 9061
Protoss_Nexus 1 10780
Protoss_Assimilator 2 15081
Protoss_Cybernetics_Core 1 10250
Protoss_Forge 1 11003
Protoss_Dragoon 5 15146
Protoss_Photon_Cannon 2 15581
Protoss_Robotics_Facility 1 14463
Protoss_Observatory 1 15230
15581
