Protoss_Gateway 4 13865
Protoss_Assimilator 2 6656
Protoss_Zealot 4 9156
Protoss_Cybernetics_Core 1 8730
Protoss_Citadel_of_Adun 1 10426
Protoss_Templar_Archives 1 11882
Protoss_Robotics_Facility 1 13217
Protoss_Dark_Templar 4 14246
Protoss_Shuttle 1 14674
Protoss_Observatory 1 14638
Protoss_Dragoon 1 15702
15702
