Protoss_Gateway 2 12225
Protoss_Assimilator 1 4344
Protoss_Cybernetics_Core 1 5911
Protoss_Dragoon 9 14744
Protoss_Robotics_Facility 1 11984
Protoss_Observatory 1 12740
Protoss_Observer 1 13766
Protoss_Nexus 1 17264
17264
