Protoss_Gateway 2 6936
Protoss_Zealot 8 10571
Protoss_Assimilator 1 10169
Protoss_Cybernetics_Core 1 12115
Protoss_Forge 1 12330
Protoss_Dragoon 4 14793
Protoss_Photon_Cannon 1 13831
14793
