Protoss_Gateway 2 5856
Protoss_Zealot 6 10094
Protoss_Assimilator 1 7246
Protoss_Cybernetics_Core 1 9353
Protoss_Robotics_Facility 1 11479
Protoss_Shield_Battery 1 10632
Protoss_Dragoon 2 13356
Protoss_Shuttle 1 12874
Protoss_Robotics_Support_Bay 1 12598
Protoss_Reaver 1 15062
15062
