Protoss_Gateway 2 8411
Protoss_Assimilator 1 4520
Protoss_Zealot 2 6109
Protoss_Cybernetics_Core 1 7249
Protoss_Dragoon 11 14995
Protoss_Robotics_Facility 1 12723
Singularity_Charge 1 11966
Protoss_Shuttle 1 14496
Protoss_Observatory 1 13870
Protoss_Robotics_Support_Bay 1 14990
Protoss_Observer 1 15339
15339
