Protoss_Gateway 2 7628
Protoss_Assimilator 1 4413
Protoss_Cybernetics_Core 1 5870
Protoss_Dragoon 12 15259
Protoss_Robotics_Facility 1 13138
Singularity_Charge 1 12303
Protoss_Observatory 1 13831
Protoss_Observer 1 15090
15259
