Protoss_Gateway 2 11253
Protoss_Assimilator 1 4293
Protoss_Zealot 2 6675
Protoss_Cybernetics_Core 1 6681
Protoss_Dragoon 10 15563
Protoss_Robotics_Facility 1 9660
Protoss_Observatory 1 10725
Protoss_Observer 2 12627
Protoss_Shuttle 1 13985
Protoss_Robotics_Support_Bay 1 13772
Singularity_Charge 1 13223
Protoss_Reaver 1 15578
15578
