Protoss_Gateway 4 15529
Protoss_Zealot 10 15585
Protoss_Nexus 1 9972
Protoss_Assimilator 1 8803
Protoss_Cybernetics_Core 1 10518
Protoss_Citadel_of_Adun 1 12665
Protoss_Dragoon 1 12654
Protoss_Forge 1 13087
15585
