Protoss_Gateway 2 10454
Protoss_Zealot 10 13697
Protoss_Nexus 1 10657
Protoss_Assimilator 1 9152
Protoss_Cybernetics_Core 1 10978
Protoss_Citadel_of_Adun 1 12579
Protoss_Dragoon 2 12827
Protoss_Templar_Archives 1 14067
Protoss_Forge 1 13669
Protoss_Photon_Cannon 1 15033
Protoss_Dark_Templar 2 15288
15288
