Protoss_Gateway 3 10132
Protoss_Assimilator 1 4316
Protoss_Cybernetics_Core 1 5729
Protoss_Dragoon 9 15783
Protoss_Forge 1 11347
Singularity_Charge 1 10648
Protoss_Nexus 1 15767
Protoss_Photon_Cannon 2 15339
15783
