Protoss_Gateway 2 9033
Protoss_Assimilator 1 4564
Protoss_Zealot 3 7224
Protoss_Cybernetics_Core 1 8275
Protoss_Robotics_Facility 1 10207
Protoss_Dragoon 11 15582
Protoss_Observatory 1 10946
Protoss_Observer 2 12854
Protoss_Shuttle 1 14301
Singularity_Charge 1 13062
Protoss_Robotics_Support_Bay 1 14937
15582
