Protoss_Gateway 2 10670
Protoss_Assimilator 1 4482
Protoss_Zealot 2 6503
Protoss_Cybernetics_Core 1 7286
Protoss_Dragoon 9 15600
Protoss_Robotics_Facility 1 9731
Protoss_Observatory 1 10472
Protoss_Observer 2 12479
Protoss_Robotics_Support_Bay 1 12427
Protoss_Reaver 2 15757
Singularity_Charge 1 13143
Protoss_Nexus 1 16757
16757
