Protoss_Gateway 2 12333
Protoss_Assimilator 1 4924
Protoss_Zealot 2 7122
Protoss_Cybernetics_Core 1 6964
Protoss_Dragoon 7 15118
Protoss_Robotics_Facility 1 9920
Protoss_Forge 1 9542
Protoss_Observatory 1 10643
Protoss_Observer 2 13978
Singularity_Charge 1 13604
Protoss_Shuttle 1 15336
Protoss_Robotics_Support_Bay 1 15019
15336
