Protoss_Gateway 4 14942
Protoss_Zealot 8 12491
Protoss_Nexus 2 16982
Protoss_Assimilator 4 12831
Protoss_Cybernetics_Core 1 10580
Protoss_Citadel_of_Adun 1 12069
Protoss_Templar_Archives 1 13586
Protoss_Forge 1 14732
Protoss_Dark_Templar 3 15765
16982
