Protoss_Gateway 2 5559
Protoss_Zealot 8 10937
Protoss_Nexus 1 10559
Protoss_Assimilator 2 13034
Protoss_Cybernetics_Core 1 11856
Protoss_Citadel_of_Adun 1 13340
Protoss_Dragoon 2 13997
Protoss_Forge 1 14291
Protoss_Templar_Archives 1 15624
Protoss_Photon_Cannon 2 15622
15624
