Protoss_Gateway 3 13815
Protoss_Zealot 8 10676
Protoss_Nexus 1 10571
Protoss_Assimilator 2 13419
Protoss_Cybernetics_Core 1 10599
Protoss_Dragoon 8 15710
Protoss_Robotics_Facility 1 15862
15862
