Protoss_Gateway 2 15778
Protoss_Assimilator 1 4294
Protoss_Zealot 2 7217
Protoss_Cybernetics_Core 1 6804
Protoss_Robotics_Facility 1 9196
Protoss_Dragoon 6 15153
Protoss_Robotics_Support_Bay 1 9960
Protoss_Reaver 1 12329
Protoss_Observatory 1 11622
Singularity_Charge 1 11072
Protoss_Nexus 1 16339
Protoss_Observer 1 14973
16339
