Protoss_Gateway 3 11711
Protoss_Zealot 7 9690
Protoss_Nexus 1 10746
Protoss_Assimilator 2 13577
Protoss_Cybernetics_Core 1 10875
Protoss_Forge 1 11578
Protoss_Dragoon 2 12323
Protoss_Citadel_of_Adun 1 12967
Protoss_Templar_Archives 1 14420
Protoss_Photon_Cannon 2 15263
Protoss_Dark_Templar 2 15645
15645
