Protoss_Gateway 4 14199
Protoss_Zealot 14 15178
Protoss_Nexus 1 9103
Protoss_Assimilator 2 12024
Protoss_Cybernetics_Core 1 10375
Protoss_Citadel_of_Adun 1 13492
Protoss_Forge 1 14470
Protoss_Templar_Archives 1 15146
15178
