Protoss_Nexus 1 6924
Protoss_Gateway 3 15184
Protoss_Zealot 6 12522
Protoss_Assimilator 1 9659
Protoss_Cybernetics_Core 1 12911
Protoss_Forge 1 12637
Protoss_Photon_Cannon 2 15149
Protoss_Dragoon 4 15571
15571
