Protoss_Gateway 3 11581
Protoss_Zealot 11 14674
Protoss_Nexus 1 10341
Protoss_Forge 1 9103
Protoss_Photon_Cannon 7 15464
Protoss_Assimilator 2 13537
Protoss_Cybernetics_Core 1 15189
15464
