Protoss_Gateway 2 9880
Protoss_Assimilator 2 6640
Protoss_Cybernetics_Core 1 5910
Protoss_Zealot 1 6105
Protoss_Dragoon 10 15180
Singularity_Charge 1 10585
Protoss_Nexus 1 15286
Protoss_Robotics_Facility 1 16456
16456
