Protoss_Gateway 2 8376
Protoss_Zealot 2 6453
Protoss_Assimilator 1 5527
Protoss_Cybernetics_Core 1 7635
Protoss_Dragoon 9 15484
Protoss_Robotics_Facility 1 11967
Singularity_Charge 1 11770
Protoss_Nexus 1 15098
Protoss_Observatory 1 13166
Protoss_Observer 2 15157
15484
