Protoss_Gateway 4 14954
Protoss_Assimilator 1 4606
Protoss_Zealot 4 13846
Protoss_Cybernetics_Core 1 7016
Protoss_Dragoon 8 15200
Protoss_Nexus 1 14373
Singularity_Charge 1 12258
Protoss_Robotics_Facility 1 14492
15200
