Protoss_Gateway 1 4012
Protoss_Zealot 3 6994
Protoss_Assimilator 1 5493
Protoss_Cybernetics_Core 1 7053
Protoss_Dragoon 7 15431
Protoss_Robotics_Facility 1 9952
Protoss_Shuttle 1 11420
Protoss_Robotics_Support_Bay 1 11114
Protoss_Reaver 1 12992
Protoss_Observatory 1 13046
Singularity_Charge 1 13058
Protoss_Observer 1 14224
15431
