Protoss_Gateway 2 8006
Protoss_Assimilator 1 5295
Protoss_Zealot 1 6040
Protoss_Cybernetics_Core 1 7040
Protoss_Dragoon 13 15584
Protoss_Robotics_Facility 1 13309
Singularity_Charge 1 12692
Protoss_Shuttle 1 14762
Protoss_Robotics_Support_Bay 1 14464
15584
