Protoss_Gateway 2 9021
Protoss_Zealot 5 13981
Protoss_Assimilator 1 5715
Protoss_Cybernetics_Core 1 7063
Protoss_Dragoon 9 15812
Protoss_Robotics_Facility 1 11995
Singularity_Charge 1 11533
Protoss_Observatory 1 12799
Protoss_Observer 2 14727
Protoss_Nexus 1 16828
16828
