Protoss_Gateway 3 12247
Protoss_Zealot 13 15141
Protoss_Nexus 1 11188
Protoss_Assimilator 1 10081
Protoss_Cybernetics_Core 1 12055
Protoss_Forge 1 12971
Protoss_Citadel_of_Adun 1 13668
Protoss_Templar_Archives 1 15160
15160
