Protoss_Gateway 3 12671
Protoss_Zealot 8 11732
Protoss_Nexus 1 10852
Protoss_Assimilator 1 9400
Protoss_Cybernetics_Core 1 11663
Protoss_Dragoon 6 15351
Protoss_Shield_Battery 1 13421
15351
