Protoss_Gateway 2 5092
Protoss_Zealot 10 12159
Protoss_Nexus 1 10493
Protoss_Assimilator 1 9678
Protoss_Cybernetics_Core 1 11477
Protoss_Citadel_of_Adun 1 13589
Protoss_Forge 1 13343
Protoss_Dragoon 4 15391
Protoss_Photon_Cannon 1 15317
Protoss_Templar_Archives 1 16016
16016
