Protoss_Gateway 3 15168
Protoss_Zealot 14 13744
Protoss_Nexus 1 10480
Protoss_Assimilator 1 10524
Protoss_Cybernetics_Core 1 12946
Protoss_Citadel_of_Adun 1 15026
Protoss_Dragoon 2 14864
Protoss_Shield_Battery 1 15156
15168
