Protoss_Nexus 1 7053
Protoss_Gateway 3 8275
Protoss_Zealot 8 10539
Protoss_Assimilator 1 8672
Protoss_Cybernetics_Core 1 12207
Protoss_Forge 1 12494
Protoss_Shield_Battery 1 12446
Protoss_Dragoon 4 14682
14682
