Protoss_Gateway 3 12709
Protoss_Zealot 11 11358
Protoss_Nexus 1 11642
Protoss_Assimilator 2 14427
Protoss_Forge 1 11492
Protoss_Cybernetics_Core 1 12153
Protoss_Photon_Cannon 4 14870
Protoss_Citadel_of_Adun 1 13820
Protoss_Dragoon 2 14495
Protoss_Templar_Archives 1 15314
15314
