Protoss_Gateway 3 15198
Protoss_Assimilator 1 4527
Protoss_Zealot 1 5221
Protoss_Cybernetics_Core 1 7059
Protoss_Dragoon 11 15472
Singularity_Charge 1 10948
Protoss_Nexus 1 14256
Protoss_Robotics_Facility 1 15390
15472
