Protoss_Gateway 4 12084
Protoss_Zealot 1 5194
Protoss_Nexus 1 8468
Protoss_Assimilator 1 6753
Protoss_Cybernetics_Core 1 7741
Protoss_Dragoon 15 15794
Singularity_Charge 1 11940
Protoss_Forge 1 15386
15794
