Protoss_Gateway 4 13944
Protoss_Assimilator 1 4565
Protoss_Cybernetics_Core 1 5922
Protoss_Dragoon 12 15541
Protoss_Nexus 1 11766
Singularity_Charge 1 10084
Protoss_Robotics_Facility 1 15414
15541
