Protoss_Gateway 3 13409
Protoss_Assimilator 1 4987
Protoss_Zealot 4 15128
Protoss_Cybernetics_Core 1 6734
Protoss_Dragoon 7 12355
Protoss_Citadel_of_Adun 1 11402
Singularity_Charge 1 10643
Protoss_Templar_Archives 1 13024
Protoss_Forge 1 13978
Protoss_Dark_Templar 2 14267
15128
