Protoss_Gateway 2 6677
Protoss_Assimilator 1 4423
Protoss_Zealot 7 9456
Protoss_Cybernetics_Core 1 9002
Protoss_Dragoon 8 14649
Protoss_Nexus 1 14305
Singularity_Charge 1 12784
Protoss_Citadel_of_Adun 1 14843
Protoss_Robotics_Facility 1 15749
15749
