Protoss_Gateway 4 15302
Protoss_Zealot 14 14380
Protoss_Nexus 1 10105
Protoss_Assimilator 2 13251
Protoss_Shield_Battery 1 9998
Protoss_Cybernetics_Core 1 11933
Protoss_Dragoon 3 14890
Protoss_Robotics_Facility 1 15077
15302
