Protoss_Gateway 4 15020
Protoss_Zealot 14 13037
Protoss_Nexus 1 11076
Protoss_Assimilator 2 14253
Protoss_Cybernetics_Core 1 11901
Protoss_Citadel_of_Adun 1 13548
Protoss_Robotics_Facility 1 15636
Protoss_Dragoon 1 15453
15636
