Protoss_Gateway 4 11791
Protoss_Assimilator 1 4549
Protoss_Zealot 2 6690
Protoss_Cybernetics_Core 1 6746
Protoss_Dragoon 11 13273
Singularity_Charge 1 11665
Protoss_Forge 1 13728
Protoss_Robotics_Facility 1 15584
Protoss_Photon_Cannon 2 15117
15584
