Protoss_Gateway 2 11721
Protoss_Assimilator 1 4510
Protoss_Zealot 2 6961
Protoss_Cybernetics_Core 1 7120
Protoss_Dragoon 2 9922
Protoss_Citadel_of_Adun 1 9479
Protoss_Templar_Archives 1 11086
Protoss_Forge 1 11317
Protoss_Dark_Templar 4 14071
Protoss_High_Templar 2 15761
Protoss_Photon_Cannon 2 14991
Protoss_Nexus 1 17023
17023
