Protoss_Gateway 3 13594
Protoss_Zealot 9 9500
Protoss_Forge 1 7641
Protoss_Photon_Cannon 4 12888
Protoss_Nexus 1 12227
Protoss_Assimilator 1 10849
Protoss_Cybernetics_Core 1 12140
Protoss_Dragoon 3 14795
14795
