Protoss_Gateway 2 6435
Protoss_Assimilator 1 4414
Protoss_Cybernetics_Core 1 5765
Protoss_Dragoon 5 10507
Singularity_Charge 1 10311
Protoss_Robotics_Facility 1 12338
Protoss_Citadel_of_Adun 1 12576
Protoss_Shuttle 1 13752
Protoss_Zealot 1 13436
Protoss_Templar_Archives 1 14990
Protoss_Nexus 1 17269
17269
