Protoss_Gateway 3 10662
Protoss_Zealot 13 13653
Protoss_Assimilator 1 10710
Protoss_Cybernetics_Core 1 11787
Protoss_Citadel_of_Adun 1 13435
Protoss_Templar_Archives 1 15007
Protoss_Nexus 1 16817
16817
