Protoss_Gateway 3 10728
Protoss_Assimilator 1 4398
Protoss_Zealot 3 6934
Protoss_Cybernetics_Core 1 7029
Protoss_Dragoon 13 15314
Singularity_Charge 1 11284
Protoss_Forge 1 13346
Protoss_Robotics_Facility 1 14894
Protoss_Photon_Cannon 3 15193
15314
