Protoss_Gateway 3 11486
Protoss_Assimilator 1 4504
Protoss_Zealot 9 14543
Protoss_Cybernetics_Core 1 6765
Protoss_Dragoon 2 9982
Protoss_Nexus 1 11298
Protoss_Citadel_of_Adun 1 11835
Protoss_Forge 1 13830
Protoss_Templar_Archives 1 15359
Protoss_Photon_Cannon 1 15335
15359
