Protoss_Gateway 2 13489
Protoss_Zealot 3 7106
Protoss_Assimilator 1 5552
Protoss_Cybernetics_Core 1 7293
Protoss_Robotics_Facility 1 9559
Protoss_Dragoon 7 15698
Protoss_Shuttle 1 11080
Protoss_Robotics_Support_Bay 1 11100
Protoss_Reaver 2 14368
Protoss_Observatory 1 12708
Singularity_Charge 1 12800
15698
