Protoss_Gateway 2 5462
Protoss_Zealot 9 11329
Protoss_Assimilator 1 10038
Protoss_Cybernetics_Core 1 10849
Protoss_Dragoon 6 14984
Protoss_Forge 1 13682
Protoss_Photon_Cannon 1 15464
15464
