Protoss_Gateway 3 12230
Protoss_Assimilator 1 5306
Protoss_Zealot 3 8194
Protoss_Cybernetics_Core 1 7501
Protoss_Dragoon 11 15183
Protoss_Nexus 1 12666
Singularity_Charge 1 13026
Protoss_Shield_Battery 1 14245
15183
