Protoss_Gateway 2 8161
Protoss_Zealot 5 11189
Protoss_Assimilator 1 11319
Protoss_Cybernetics_Core 1 12460
Protoss_Nexus 1 15447
Protoss_Dragoon 3 15124
Protoss_Forge 1 14203
Protoss_Shield_Battery 1 15036
Protoss_Photon_Cannon 1 15582
15582
