Protoss_Gateway 3 10091
Protoss_Assimilator 2 15364
Protoss_Zealot 4 14920
Protoss_Nexus 1 9652
Protoss_Cybernetics_Core 1 8581
Protoss_Dragoon 9 15098
Protoss_Robotics_Facility 1 12203
Protoss_Observatory 1 13149
Singularity_Charge 1 12806
Protoss_Observer 2 15550
15550
