Protoss_Gateway 2 7250
Protoss_Assimilator 1 4498
Protoss_Cybernetics_Core 1 5818
Protoss_Zealot 1 6146
Protoss_Dragoon 7 13473
Protoss_Shield_Battery 1 8144
Singularity_Charge 1 10283
13473
