Protoss_Gateway 3 15718
Protoss_Zealot 8 11168
Protoss_Assimilator 2 7208
Protoss_Cybernetics_Core 1 10149
Protoss_Dragoon 5 14944
Protoss_Citadel_of_Adun 1 12791
Protoss_Templar_Archives 1 14524
Protoss_Dark_Templar 2 15739
15739
