Protoss_Gateway 2 5210
Protoss_Zealot 9 10897
Protoss_Nexus 1 10764
Protoss_Assimilator 2 12784
Protoss_Cybernetics_Core 1 11570
Protoss_Dragoon 4 14649
Protoss_Forge 1 12612
Protoss_Photon_Cannon 1 14510
14649
