Protoss_Gateway 2 9058
Protoss_Zealot 11 15375
Protoss_Nexus 1 10149
Protoss_Assimilator 2 12899
Protoss_Cybernetics_Core 1 11768
Protoss_Forge 1 12623
Protoss_Citadel_of_Adun 1 13274
Protoss_Dragoon 2 13792
Protoss_Photon_Cannon 1 14255
Protoss_Templar_Archives 1 15652
15652
