Protoss_Gateway 3 15926
Protoss_Zealot 8 9792
Protoss_Assimilator 1 6773
Protoss_Cybernetics_Core 1 9102
Protoss_Dragoon 8 15142
Protoss_Forge 1 11866
Protoss_Photon_Cannon 1 13380
Protoss_Robotics_Facility 1 14524
Singularity_Charge 1 12821
Protoss_Citadel_of_Adun 1 15402
Protoss_Shuttle 1 15955
15955
