Protoss_Gateway 2 7659
Protoss_Assimilator 1 4491
Protoss_Zealot 7 9961
Protoss_Cybernetics_Core 1 6933
Protoss_Citadel_of_Adun 1 9242
Protoss_Dragoon 1 10115
Protoss_Templar_Archives 1 10916
Protoss_Dark_Templar 3 13232
Protoss_Forge 1 13590
Protoss_Nexus 1 15622
Protoss_High_Templar 2 14466
Protoss_Photon_Cannon 1 15745
15745
