Protoss_Gateway 3 13366
Protoss_Assimilator 1 4657
Protoss_Zealot 3 15435
Protoss_Cybernetics_Core 1 6909
Protoss_Dragoon 8 14685
Protoss_Robotics_Facility 1 10971
Protoss_Nexus 1 13762
Protoss_Observatory 1 11878
Singularity_Charge 1 11802
Protoss_Observer 2 14124
15435
