Protoss_Gateway 2 10505
Protoss_Assimilator 1 4600
Protoss_Zealot 2 7009
Protoss_Cybernetics_Core 1 7038
Protoss_Dragoon 9 15411
Protoss_Robotics_Facility 1 12200
Singularity_Charge 1 11832
Protoss_Observatory 1 13305
Protoss_Observer 2 15225
Protoss_Nexus 1 16489
16489
