Protoss_Gateway 3 15959
Protoss_Assimilator 1 4586
Protoss_Zealot 1 5262
Protoss_Cybernetics_Core 1 7196
Protoss_Dragoon 10 15311
Protoss_Robotics_Facility 1 11925
Protoss_Observatory 1 12868
Singularity_Charge 1 12397
Protoss_Observer 2 14759
Protoss_Nexus 1 16840
16840
