Protoss_Gateway 2 9640
Protoss_Zealot 2 6790
Protoss_Assimilator 1 5595
Protoss_Cybernetics_Core 1 6953
Protoss_Dragoon 10 15437
Protoss_Robotics_Facility 1 12462
Singularity_Charge 1 11571
Protoss_Observatory 1 13214
Protoss_Shuttle 1 13954
Protoss_Nexus 1 16034
Protoss_Robotics_Support_Bay 1 14390
Protoss_Observer 1 14797
16034
