Protoss_Gateway 4 15280
Protoss_Zealot 2 6351
Protoss_Assimilator 1 5232
Protoss_Cybernetics_Core 1 6470
Protoss_Dragoon 12 15534
Singularity_Charge 1 11416
Protoss_Robotics_Facility 1 13356
Protoss_Nexus 1 16380
16380
