Protoss_Gateway 3 15539
Protoss_Zealot 2 11446
Protoss_Assimilator 1 5440
Protoss_Cybernetics_Core 1 6929
Protoss_Dragoon 10 14846
Protoss_Robotics_Facility 1 12177
Singularity_Charge 1 10907
Protoss_Nexus 1 14755
Protoss_Observatory 1 12901
Protoss_Observer 1 14168
Protoss_Shuttle 1 15760
15760
