Protoss_Gateway 3 12929
Protoss_Assimilator 1 4464
Protoss_Zealot 1 5092
Protoss_Cybernetics_Core 1 6886
Protoss_Dragoon 12 15238
Singularity_Charge 1 10676
Protoss_Nexus 1 13761
Protoss_Robotics_Facility 1 13968
Protoss_Observatory 1 15007
15238
