Protoss_Nexus 1 7157
Protoss_Gateway 3 10673
Protoss_Zealot 4 13916
Protoss_Assimilator 2 11764
Protoss_Cybernetics_Core 1 10109
Protoss_Dragoon 6 13195
Protoss_Citadel_of_Adun 1 14060
Protoss_Forge 1 14433
Protoss_Shield_Battery 1 14515
Protoss_Templar_Archives 1 15838
Protoss_Photon_Cannon 1 15727
15838
