Protoss_Gateway 2 10193
Protoss_Assimilator 1 4817
Protoss_Cybernetics_Core 1 6061
Protoss_Dragoon 7 15806
Protoss_Robotics_Facility 1 10248
Singularity_Charge 1 10526
Protoss_Shuttle 1 11985
Protoss_Robotics_Support_Bay 1 11363
Protoss_Observatory 1 12789
Protoss_Reaver 2 15416
15806
