Protoss_Gateway 6 12955
Protoss_Forge 1 7966
Protoss_Zealot 7 11552
Protoss_Assimilator 1 9667
Protoss_Cybernetics_Core 2 11361
Protoss_Citadel_of_Adun 1 11999
Protoss_Templar_Archives 1 13571
Protoss_Photon_Cannon 1 13526
Protoss_Nexus 1 16587
Protoss_Dark_Templar 1 14925
16587
