Protoss_Nexus 1 6845
Protoss_Gateway 2 7973
Protoss_Assimilator 3 14947
Protoss_Zealot 8 11598
Protoss_Cybernetics_Core 1 13430
Protoss_Forge 1 13445
Protoss_Citadel_of_Adun 1 15011
Protoss_Photon_Cannon 4 15657
15657
