Protoss_Gateway 3 12751
Protoss_Assimilator 1 4615
Protoss_Cybernetics_Core 1 6197
Protoss_Dragoon 15 15585
Protoss_Robotics_Facility 1 11316
Singularity_Charge 1 10640
Protoss_Observatory 1 12074
Protoss_Observer 1 13356
Protoss_Zealot 1 14373
15585
