Protoss_Gateway 3 15729
Protoss_Assimilator 1 4505
Protoss_Cybernetics_Core 1 5941
Protoss_Dragoon 12 14978
Protoss_Robotics_Facility 1 10848
Singularity_Charge 1 9982
Protoss_Observatory 1 11612
Protoss_Observer 1 13144
Protoss_Nexus 1 15659
15729
