Protoss_Gateway 2 5098
Protoss_Zealot 11 13583
Protoss_Nexus 1 12172
Protoss_Assimilator 2 13792
Protoss_Cybernetics_Core 1 12330
Protoss_Dragoon 4 14843
Protoss_Robotics_Facility 1 14593
14843
