Protoss_Gateway 4 15920
Protoss_Zealot 13 12886
Protoss_Nexus 1 11377
Protoss_Assimilator 2 13691
Protoss_Cybernetics_Core 1 12533
Protoss_Citadel_of_Adun 1 14073
Protoss_Dragoon 1 14117
Protoss_Templar_Archives 1 15677
15920
