Protoss_Gateway 3 15144
Protoss_Zealot 11 15576
Protoss_Nexus 1 10085
Protoss_Assimilator 2 11585
Protoss_Cybernetics_Core 1 11118
Protoss_Dragoon 6 14714
Protoss_Robotics_Facility 1 13854
Protoss_Observatory 1 14779
Protoss_Shuttle 1 15857
15857
