Protoss_Gateway 2 10275
Protoss_Assimilator 1 4249
Protoss_Zealot 7 10505
Protoss_Cybernetics_Core 1 8373
Protoss_Dragoon 8 15221
Protoss_Robotics_Facility 1 12376
Protoss_Observatory 1 13121
Singularity_Charge 1 12645
Protoss_Observer 1 14885
15221
