Protoss_Gateway 1 4229
Protoss_Assimilator 1 5115
Protoss_Zealot 4 8849
Protoss_Cybernetics_Core 1 8374
Protoss_Robotics_Facility 1 10669
Protoss_Dragoon 4 14700
Protoss_Shuttle 1 12077
Protoss_Robotics_Support_Bay 1 11776
Protoss_Reaver 2 15271
15271
