Protoss_Assimilator 1 3364
Protoss_Gateway 2 9835
Protoss_Cybernetics_Core 1 6115
Protoss_Citadel_of_Adun 1 7700
Protoss_Robotics_Facility 1 8682
Protoss_Dragoon 6 14539
Protoss_Templar_Archives 1 10015
Protoss_Shuttle 1 10460
Protoss_Dark_Templar 3 14624
14624
