Protoss_Gateway 1 4160
Protoss_Assimilator 1 4416
Protoss_Cybernetics_Core 1 5648
Protoss_Robotics_Facility 2 15957
Protoss_Shuttle 1 9318
Protoss_Robotics_Support_Bay 1 8638
Protoss_Reaver 2 12416
Protoss_Zealot 1 10392
Protoss_Observatory 1 11837
Protoss_Dragoon 2 13766
Protoss_Observer 1 13240
Gravitic_Drive 1 12356
15957
