Protoss_Gateway 3 11843
Protoss_Assimilator 1 4420
Protoss_Cybernetics_Core 1 5885
Protoss_Zealot 1 5780
Protoss_Dragoon 17 15551
Singularity_Charge 1 12522
Protoss_Robotics_Facility 1 15802
15802
