Protoss_Nexus 1 6637
Protoss_Gateway 2 6276
Protoss_Zealot 5 10738
Protoss_Assimilator 2 13981
Protoss_Forge 1 9112
Protoss_Cybernetics_Core 1 9971
Protoss_Photon_Cannon 10 15481
Protoss_Citadel_of_Adun 1 11692
Protoss_Templar_Archives 1 13362
Protoss_Dark_Templar 2 14568
15481
