Protoss_Gateway 2 10248
Protoss_Assimilator 1 4236
Protoss_Zealot 4 15333
Protoss_Cybernetics_Core 1 7050
Protoss_Dragoon 6 12712
Protoss_Robotics_Facility 1 9396
Protoss_Shuttle 1 11054
Protoss_Observatory 1 10526
Protoss_Observer 1 11897
Protoss_Robotics_Support_Bay 1 11893
Protoss_Nexus 1 15608
Protoss_Reaver 1 14880
Protoss_Citadel_of_Adun 1 14914
15608
