Protoss_Gateway 3 15943
Protoss_Assimilator 1 4485
Protoss_Zealot 7 14189
Protoss_Cybernetics_Core 1 7469
Protoss_Citadel_of_Adun 1 8944
Protoss_Dragoon 1 9124
Protoss_Templar_Archives 1 10398
Protoss_Dark_Templar 1 11591
Protoss_High_Templar 3 15309
Protoss_Forge 1 12825
Leg_Enhancements 1 12268
Protoss_Nexus 1 16503
Protoss_Photon_Cannon 1 15377
16503
