Protoss_Gateway 2 4975
Protoss_Zealot 5 15190
Protoss_Assimilator 1 5894
Protoss_Cybernetics_Core 1 7056
Protoss_Dragoon 11 15434
Protoss_Robotics_Facility 1 12105
Singularity_Charge 1 11849
Protoss_Shuttle 1 13662
Protoss_Robotics_Support_Bay 1 13810
Protoss_Reaver 1 15539
15539
