Protoss_Gateway 2 11464
Protoss_Assimilator 1 4539
Protoss_Zealot 2 6845
Protoss_Cybernetics_Core 1 6901
Protoss_Dragoon 8 15294
Protoss_Robotics_Facility 1 10661
Protoss_Observatory 1 11472
Singularity_Charge 1 11041
Protoss_Nexus 1 14355
Protoss_Observer 1 12550
Protoss_Robotics_Support_Bay 1 12720
Protoss_Reaver 2 16074
16074
