Protoss_Gateway 2 11988
Protoss_Assimilator 1 4504
Protoss_Cybernetics_Core 1 5787
Protoss_Zealot 1 5774
Protoss_Dragoon 9 15004
Protoss_Shield_Battery 2 12672
Protoss_Nexus 1 12660
Singularity_Charge 1 10313
Protoss_Robotics_Facility 1 13630
Protoss_Observatory 1 14325
Protoss_Robotics_Support_Bay 1 14960
Protoss_Observer 1 15336
15336
