Protoss_Gateway 2 8739
Protoss_Assimilator 1 4397
Protoss_Zealot 2 6345
Protoss_Cybernetics_Core 1 7843
Protoss_Dragoon 10 15768
Protoss_Robotics_Facility 1 10681
Protoss_Observatory 1 11372
Protoss_Observer 3 14768
Singularity_Charge 1 11890
Protoss_Nexus 1 17077
17077
