Protoss_Gateway 4 15684
Protoss_Assimilator 1 4552
Protoss_Cybernetics_Core 1 5935
Protoss_Dragoon 9 14990
Protoss_Robotics_Facility 1 11670
Singularity_Charge 1 10076
Protoss_Observatory 1 12376
Protoss_Observer 2 14273
Protoss_Nexus 1 15758
Protoss_Robotics_Support_Bay 1 15225
15758
