Protoss_Gateway 2 10697
Protoss_Assimilator 1 4334
Protoss_Zealot 2 6678
Protoss_Cybernetics_Core 1 6725
Protoss_Dragoon 10 15712
Protoss_Robotics_Facility 1 10093
Protoss_Shuttle 1 11528
Protoss_Observatory 1 11356
Singularity_Charge 1 10816
Protoss_Observer 2 14818
Protoss_Robotics_Support_Bay 1 12197
Protoss_Reaver 1 13993
Protoss_Nexus 1 16866
16866
