Protoss_Gateway 2 5080
Protoss_Zealot 8 11320
Protoss_Nexus 1 10089
Protoss_Assimilator 2 13818
Protoss_Cybernetics_Core 1 9593
Protoss_Citadel_of_Adun 1 12255
Protoss_Forge 1 13176
Protoss_Templar_Archives 1 13906
Protoss_Photon_Cannon 4 15619
Protoss_Dark_Templar 2 15607
15619
