Protoss_Gateway 4 15086
Protoss_Assimilator 1 4133
Protoss_Cybernetics_Core 1 5525
Protoss_Zealot 1 5458
Protoss_Dragoon 7 15332
Protoss_Citadel_of_Adun 1 9462
Protoss_Robotics_Facility 1 9971
Protoss_Templar_Archives 1 10916
Protoss_Shuttle 1 11434
Protoss_Dark_Templar 2 12121
Protoss_Nexus 1 14899
Protoss_Observatory 1 15154
15332
