Protoss_Gateway 3 15542
Protoss_Assimilator 1 4176
Protoss_Zealot 1 5192
Protoss_Cybernetics_Core 1 6858
Protoss_Dragoon 8 15478
Protoss_Robotics_Facility 1 10620
Protoss_Observatory 1 11501
Protoss_Robotics_Support_Bay 1 11551
Singularity_Charge 1 10960
Protoss_Observer 1 12576
Protoss_Reaver 1 14172
Protoss_Nexus 1 16064
Protoss_Shuttle 1 15473
16064
