Protoss_Gateway 2 11156
Protoss_Assimilator 1 4539
Protoss_Cybernetics_Core 1 6039
Protoss_Dragoon 8 15206
Protoss_Robotics_Facility 1 10557
Protoss_Observatory 1 11463
Singularity_Charge 1 10769
Protoss_Shuttle 1 12418
Protoss_Robotics_Support_Bay 1 12856
Protoss_Observer 1 13261
Protoss_Nexus 1 15921
Protoss_Reaver 1 15129
15921
