Protoss_Gateway 3 10166
Protoss_Assimilator 1 5322
Protoss_Cybernetics_Core 1 6270
Protoss_Zealot 1 5999
Protoss_Dragoon 13 14662
Singularity_Charge 1 10541
Protoss_Forge 1 12908
Protoss_Photon_Cannon 3 15016
Protoss_Robotics_Facility 1 16371
16371
