Protoss_Gateway 2 5036
Protoss_Zealot 3 8432
Protoss_Nexus 1 8837
Protoss_Assimilator 2 13460
Protoss_Cybernetics_Core 1 8323
Protoss_Dragoon 8 15209
Protoss_Forge 1 10956
Protoss_Citadel_of_Adun 1 12520
Protoss_Photon_Cannon 3 14567
Protoss_Robotics_Facility 1 13716
Protoss_Observatory 1 14416
Protoss_Observer 1 15471
15471
