Protoss_Gateway 2 4978
Protoss_Zealot 10 13738
Protoss_Nexus 2 17297
Protoss_Assimilator 2 12498
Protoss_Cybernetics_Core 1 11629
Protoss_Dragoon 3 15130
Protoss_Citadel_of_Adun 1 13306
Protoss_Forge 1 13095
Protoss_Templar_Archives 1 15424
Protoss_Photon_Cannon 1 15787
17297
