Protoss_Gateway 3 10027
Protoss_Zealot 2 7782
Protoss_Assimilator 1 7248
Protoss_Cybernetics_Core 1 9359
Protoss_Dragoon 7 15434
Protoss_Robotics_Facility 1 11954
Protoss_Shuttle 1 13363
Protoss_Robotics_Support_Bay 1 13547
Protoss_Reaver 1 15275
15434
