Protoss_Gateway 2 5011
Protoss_Zealot 12 12946
Protoss_Assimilator 1 8609
Protoss_Cybernetics_Core 1 10799
Protoss_Citadel_of_Adun 1 14295
Protoss_Templar_Archives 1 15920
Protoss_Forge 1 15533
15920
