Protoss_Gateway 2 9342
Protoss_Zealot 2 6591
Protoss_Assimilator 1 6324
Protoss_Cybernetics_Core 1 8382
Protoss_Dragoon 11 15648
Protoss_Robotics_Facility 1 14420
Singularity_Charge 1 12923
Protoss_Observatory 1 15241
15648
