Protoss_Gateway 2 10741
Protoss_Assimilator 1 4469
Protoss_Zealot 2 6813
Protoss_Cybernetics_Core 1 6929
Protoss_Dragoon 9 14135
Protoss_Robotics_Facility 1 10347
Protoss_Shuttle 1 11777
Singularity_Charge 1 10857
Protoss_Robotics_Support_Bay 1 11736
Protoss_Reaver 1 13496
Protoss_Observatory 1 12854
Protoss_Observer 2 15386
Protoss_Nexus 1 17048
17048
