Protoss_Gateway 2 7537
Protoss_Assimilator 1 4644
Protoss_Zealot 3 14850
Protoss_Cybernetics_Core 1 6646
Protoss_Dragoon 5 11173
Protoss_Citadel_of_Adun 1 9446
Protoss_Forge 1 10346
Protoss_Templar_Archives 1 10896
Protoss_Dark_Templar 2 12273
Protoss_Photon_Cannon 3 15770
Protoss_Nexus 1 15236
Protoss_High_Templar 2 13705
Protoss_Archon 1 14976
15770
