Protoss_Gateway 3 6503
Protoss_Zealot 4 14721
Protoss_Assimilator 1 6910
Protoss_Cybernetics_Core 1 8414
Protoss_Dragoon 9 15183
Protoss_Robotics_Facility 1 13914
Singularity_Charge 1 12742
Protoss_Observatory 1 14931
15183
