Protoss_Gateway 2 6468
Protoss_Assimilator 1 4234
Protoss_Cybernetics_Core 1 5667
Protoss_Dragoon 15 15724
Protoss_Robotics_Facility 1 12427
Singularity_Charge 1 10889
Protoss_Shuttle 1 13943
Protoss_Observatory 1 13825
Protoss_Observer 1 14856
15724
