Protoss_Gateway 2 7691
Protoss_Zealot 10 11958
Protoss_Assimilator 1 7571
Protoss_Cybernetics_Core 1 8787
Protoss_Citadel_of_Adun 1 10438
Protoss_Robotics_Facility 1 11846
Protoss_Forge 1 11297
Protoss_Photon_Cannon 1 12576
Protoss_Templar_Archives 1 13205
Protoss_Shuttle 1 13635
Protoss_Observatory 1 13844
Protoss_Dark_Templar 2 14422
Protoss_Observer 1 14951
Protoss_Nexus 1 17122
17122
