Protoss_Gateway 2 12372
Protoss_Assimilator 3 7751
Protoss_Zealot 3 8010
Protoss_Cybernetics_Core 1 7711
Protoss_Dragoon 8 15502
Protoss_Robotics_Facility 1 11823
Singularity_Charge 1 11896
Protoss_Shuttle 1 13591
Protoss_Robotics_Support_Bay 1 14012
Protoss_Observatory 1 14100
Protoss_Observer 1 15307
15502
