Protoss_Gateway 4 15829
Protoss_Zealot 9 12192
Protoss_Nexus 1 10152
Protoss_Assimilator 2 11031
Protoss_Cybernetics_Core 1 9964
Protoss_Dragoon 4 14875
Protoss_Forge 1 14383
15829
