Protoss_Gateway 2 5052
Protoss_Zealot 8 12936
Protoss_Nexus 2 16079
Protoss_Assimilator 2 13223
Protoss_Cybernetics_Core 1 10117
Protoss_Dragoon 1 11354
Protoss_Citadel_of_Adun 1 11963
Protoss_Templar_Archives 1 13463
Protoss_Forge 1 13706
Protoss_Dark_Templar 2 14726
Protoss_Photon_Cannon 2 15440
16079
