Protoss_Gateway 4 14522
Protoss_Zealot 5 9037
Protoss_Nexus 1 9984
Protoss_Assimilator 2 11897
Protoss_Cybernetics_Core 1 10269
Protoss_Dragoon 8 15803
Protoss_Robotics_Facility 1 13675
Protoss_Forge 1 12762
Protoss_Photon_Cannon 2 15183
Protoss_Observatory 1 14425
Singularity_Charge 1 14287
15803
