Protoss_Gateway 2 9457
Protoss_Zealot 5 13495
Protoss_Cybernetics_Core 1 7351
Protoss_Assimilator 1 8793
Protoss_Dragoon 7 15715
Protoss_Nexus 1 13203
Protoss_Robotics_Facility 1 14313
Singularity_Charge 1 14407
15715
