Protoss_Gateway 3 15977
Protoss_Assimilator 3 14256
Protoss_Zealot 3 10486
Protoss_Cybernetics_Core 1 7038
Protoss_Citadel_of_Adun 1 8494
Protoss_Dragoon 2 9625
Protoss_Templar_Archives 1 10009
Protoss_Dark_Templar 2 12325
Protoss_Nexus 1 13127
Protoss_Forge 1 12188
Protoss_Photon_Cannon 3 14390
Protoss_High_Templar 2 15717
15977
