Protoss_Gateway 3 12271
Protoss_Zealot 4 14603
Protoss_Assimilator 1 5831
Protoss_Cybernetics_Core 1 7221
Protoss_Dragoon 11 15556
Protoss_Robotics_Facility 1 11539
Singularity_Charge 1 11423
Protoss_Observatory 1 12852
Protoss_Observer 2 15039
15556
