Protoss_Gateway 2 9530
Protoss_Assimilator 1 4264
Protoss_Zealot 2 6833
Protoss_Cybernetics_Core 1 6971
Protoss_Dragoon 9 15648
Protoss_Robotics_Facility 1 10564
Protoss_Observatory 1 11308
Singularity_Charge 1 10898
Protoss_Observer 2 13205
Protoss_Nexus 1 14689
Protoss_Shuttle 1 15122
Protoss_Robotics_Support_Bay 1 14507
15648
