Protoss_Gateway 3 13725
Protoss_Assimilator 1 4403
Protoss_Zealot 2 7097
Protoss_Cybernetics_Core 1 7110
Protoss_Dragoon 11 15194
Protoss_Nexus 1 14118
Singularity_Charge 1 11551
Protoss_Robotics_Facility 1 15352
15352
