Protoss_Gateway 3 13884
Protoss_Zealot 5 9389
Protoss_Nexus 2 17487
Protoss_Assimilator 2 11083
Protoss_Cybernetics_Core 1 9536
Protoss_Dragoon 9 15098
Protoss_Robotics_Facility 1 12692
Protoss_Shuttle 1 14089
Protoss_Observatory 1 13484
Protoss_Observer 1 15111
17487
