Protoss_Gateway 2 4831
Protoss_Zealot 13 12222
Protoss_Nexus 1 12248
Protoss_Assimilator 2 14677
Protoss_Forge 1 11045
Protoss_Cybernetics_Core 1 13215
Protoss_Photon_Cannon 2 15357
Protoss_Citadel_of_Adun 1 15257
Protoss_Robotics_Facility 1 16399
16399
