Protoss_Gateway 5 15470
Protoss_Zealot 6 14186
Protoss_Nexus 2 12858
Protoss_Assimilator 2 13414
Protoss_Cybernetics_Core 1 9314
Protoss_Dragoon 4 14454
Protoss_Robotics_Facility 1 13655
Protoss_Observatory 1 14464
Protoss_Observer 1 15500
15500
