Protoss_Gateway 2 5003
Protoss_Zealot 7 10679
Protoss_Nexus 1 10538
Protoss_Assimilator 2 11453
Protoss_Cybernetics_Core 1 10757
Protoss_Citadel_of_Adun 1 12434
Protoss_Dragoon 4 13699
Protoss_Templar_Archives 1 13987
Protoss_Forge 1 13603
Protoss_Robotics_Facility 1 15213
Protoss_Photon_Cannon 1 15297
Protoss_Dark_Templar 2 15546
15546
