Protoss_Gateway 2 4864
Protoss_Zealot 15 13530
Protoss_Nexus 1 11680
Protoss_Assimilator 2 13846
Protoss_Cybernetics_Core 1 11774
Protoss_Forge 1 12854
Protoss_Citadel_of_Adun 1 13679
Protoss_Photon_Cannon 2 14504
Protoss_Robotics_Facility 1 15560
15560
