Protoss_Gateway 2 5096
Protoss_Zealot 7 10738
Protoss_Nexus 1 10328
Protoss_Assimilator 2 11489
Protoss_Cybernetics_Core 1 10795
Protoss_Dragoon 2 12159
Protoss_Citadel_of_Adun 1 12549
Protoss_Templar_Archives 1 14060
Protoss_Forge 1 13728
Protoss_Photon_Cannon 2 15080
Protoss_Dark_Templar 2 15276
Protoss_Robotics_Facility 1 16185
16185
