Protoss_Gateway 4 14142
Protoss_Zealot 6 15263
Protoss_Assimilator 1 5325
Protoss_Cybernetics_Core 1 6867
Protoss_Dragoon 8 14337
Protoss_Nexus 1 11390
Protoss_Robotics_Facility 1 11629
Protoss_Observatory 1 12355
Protoss_Observer 2 14414
Protoss_Citadel_of_Adun 1 15523
Singularity_Charge 1 14401
15523
