Protoss_Assimilator 1 3951
Protoss_Gateway 1 5117
Protoss_Cybernetics_Core 1 6750
Protoss_Robotics_Facility 2 9745
Protoss_Shuttle 2 15662
Protoss_Observatory 1 9499
Protoss_Robotics_Support_Bay 1 10169
Protoss_Observer 2 13044
Protoss_Reaver 3 14102
Protoss_Dragoon 2 14297
Protoss_Nexus 1 14538
Protoss_Shield_Battery 2 14555
15662
