Protoss_Gateway 4 15781
Protoss_Assimilator 1 5145
Protoss_Cybernetics_Core 1 6071
Protoss_Zealot 1 6397
Protoss_Dragoon 7 14603
Protoss_Nexus 2 15347
Protoss_Robotics_Facility 1 11825
Protoss_Observatory 1 12714
Protoss_Observer 2 14636
Protoss_Robotics_Support_Bay 1 14545
15781
