Protoss_Gateway 3 12907
Protoss_Assimilator 1 4169
Protoss_Cybernetics_Core 1 5835
Protoss_Citadel_of_Adun 1 7325
Protoss_Robotics_Facility 1 8738
Protoss_Templar_Archives 1 9311
Protoss_Shuttle 1 10145
Protoss_Dark_Templar 2 10931
Protoss_Observatory 1 10690
Protoss_Dragoon 6 14685
Protoss_Observer 1 11732
14685
