Protoss_Gateway 1 4289
Protoss_Assimilator 1 4381
Protoss_Cybernetics_Core 1 5818
Protoss_Robotics_Facility 1 7950
Protoss_Zealot 2 8032
Protoss_Shuttle 1 9362
Protoss_Dragoon 2 11890
Protoss_Robotics_Support_Bay 1 10026
Protoss_Reaver 1 11766
11890
