Protoss_Gateway 3 14701
Protoss_Assimilator 1 4441
Protoss_Cybernetics_Core 1 5750
Protoss_Zealot 1 5549
Protoss_Dragoon 10 15379
Singularity_Charge 1 9967
Protoss_Robotics_Facility 1 12999
Protoss_Observatory 1 13731
Protoss_Observer 1 14774
15379
