Protoss_Gateway 3 12633
Protoss_Zealot 7 12409
Protoss_Assimilator 1 6904
Protoss_Cybernetics_Core 1 9239
Protoss_Dragoon 10 15511
Protoss_Robotics_Facility 1 12958
Singularity_Charge 1 12923
Protoss_Observatory 1 13658
Protoss_Observer 1 14677
15511
