Protoss_Gateway 2 9589
Protoss_Assimilator 1 4804
Protoss_Zealot 3 14124
Protoss_Cybernetics_Core 1 6668
Protoss_Dragoon 12 15566
Protoss_Robotics_Facility 1 12370
Protoss_Observatory 1 13075
Singularity_Charge 1 12370
Protoss_Observer 2 14970
15566
