Protoss_Gateway 2 4987
Protoss_Zealot 11 11853
Protoss_Nexus 1 11346
Protoss_Assimilator 2 13024
Protoss_Cybernetics_Core 1 10808
Protoss_Citadel_of_Adun 1 12686
Protoss_Dragoon 2 13652
Protoss_Templar_Archives 1 14329
Protoss_Forge 1 14391
Protoss_Dark_Templar 2 15590
15590
