Protoss_Gateway 2 14472
Protoss_Assimilator 1 4242
Protoss_Cybernetics_Core 1 5876
Protoss_Stargate 1 7595
Protoss_Robotics_Facility 1 8353
Protoss_Dragoon 7 14802
Protoss_Observatory 1 9178
Protoss_Observer 3 14424
Protoss_Shuttle 1 12785
Singularity_Charge 1 12192
Protoss_Robotics_Support_Bay 1 14098
Protoss_Reaver 1 16020
16020
