Protoss_Gateway 2 7741
Protoss_Assimilator 1 4537
Protoss_Cybernetics_Core 1 5920
Protoss_Zealot 2 15310
Protoss_Dragoon 9 14744
Protoss_Robotics_Facility 1 12373
Protoss_Shuttle 1 13831
Protoss_Observatory 1 13355
Singularity_Charge 1 12973
Protoss_Robotics_Support_Bay 1 14436
Protoss_Reaver 1 16177
16177
