Protoss_Gateway 1 4136
Protoss_Zealot 4 7755
Protoss_Assimilator 2 8260
Protoss_Cybernetics_Core 1 7976
Protoss_Dragoon 6 14776
Protoss_Robotics_Facility 1 10561
Protoss_Shuttle 1 12002
Protoss_Robotics_Support_Bay 1 11597
Protoss_Reaver 2 15790
15790
