Protoss_Gateway 3 9788
Protoss_Assimilator 1 4444
Protoss_Zealot 1 5306
Protoss_Cybernetics_Core 1 7709
Protoss_Dragoon 11 14820
Singularity_Charge 1 11504
Protoss_Robotics_Facility 1 14234
Protoss_Observatory 1 15004
15004
