Protoss_Gateway 2 10343
Protoss_Assimilator 1 4892
Protoss_Zealot 6 14800
Protoss_Cybernetics_Core 1 7681
Protoss_Dragoon 5 15066
Protoss_Robotics_Facility 1 11392
Protoss_Shuttle 1 12789
Protoss_Robotics_Support_Bay 1 12200
Protoss_Observatory 1 12241
Protoss_Observer 1 13632
Protoss_Reaver 1 15228
Protoss_Citadel_of_Adun 1 16038
16038
