Protoss_Assimilator 1 3716
Protoss_Gateway 4 14386
Protoss_Cybernetics_Core 1 6331
Protoss_Robotics_Facility 1 8307
Protoss_Dragoon 10 15483
Protoss_Observatory 1 9017
Protoss_Observer 2 12610
Protoss_Shuttle 1 11652
Singularity_Charge 1 10743
15483
