Protoss_Gateway 2 4978
Protoss_Zealot 9 11326
Protoss_Nexus 1 10364
Protoss_Assimilator 2 13000
Protoss_Cybernetics_Core 1 11180
Protoss_Dragoon 6 15478
Protoss_Robotics_Facility 1 14547
Protoss_Shuttle 1 16056
16056
