Protoss_Gateway 2 11446
Protoss_Assimilator 1 4467
Protoss_Zealot 2 6956
Protoss_Cybernetics_Core 1 6826
Protoss_Dragoon 9 15118
Protoss_Robotics_Facility 1 10707
Protoss_Shuttle 1 12295
Singularity_Charge 1 11161
Protoss_Robotics_Support_Bay 1 12291
Protoss_Reaver 1 14078
Protoss_Observatory 1 13945
15118
