Protoss_Gateway 2 7047
Protoss_Assimilator 1 4324
Protoss_Zealot 7 14756
Protoss_Cybernetics_Core 2 8461
Protoss_Dragoon 8 13895
Protoss_Robotics_Facility 1 12630
Protoss_Shuttle 1 14025
Singularity_Charge 1 12874
Protoss_Robotics_Support_Bay 1 13623
Protoss_Observatory 1 14194
Protoss_Reaver 1 15747
15747
