Protoss_Gateway 2 5076
Protoss_Zealot 10 12318
Protoss_Assimilator 1 7600
Protoss_Cybernetics_Core 1 9029
Protoss_Dragoon 7 15607
Protoss_Robotics_Facility 1 11903
Protoss_Observatory 1 12607
Protoss_Observer 1 13700
Protoss_Shuttle 1 15058
Protoss_Robotics_Support_Bay 1 14861
15607
