Protoss_Gateway 2 9686
Protoss_Assimilator 1 4201
Protoss_Zealot 3 6994
Protoss_Cybernetics_Core 1 7161
Protoss_Dragoon 7 12947
Protoss_Robotics_Facility 1 12226
Singularity_Charge 1 10842
Protoss_Nexus 1 13999
Protoss_Shuttle 1 13820
Protoss_Robotics_Support_Bay 1 13621
Protoss_Observatory 1 14217
Protoss_Reaver 1 15779
15779
