Protoss_Gateway 2 5266
Protoss_Zealot 14 13312
Protoss_Assimilator 1 10820
Protoss_Cybernetics_Core 1 12554
Protoss_Dragoon 2 14714
Protoss_Robotics_Facility 1 15652
Protoss_Nexus 1 17153
17153
