Protoss_Gateway 2 7593
Protoss_Assimilator 1 4698
Protoss_Zealot 7 13085
Protoss_Cybernetics_Core 2 12269
Protoss_Shield_Battery 1 8125
Protoss_Dragoon 1 13778
Protoss_Robotics_Facility 1 15545
15545
