Protoss_Gateway 2 14177
Protoss_Assimilator 1 4229
Protoss_Zealot 2 6845
Protoss_Cybernetics_Core 1 6962
Protoss_Dragoon 7 15414
Protoss_Nexus 1 13552
Singularity_Charge 1 11141
Protoss_Robotics_Facility 1 13500
Protoss_Observatory 1 14284
Protoss_Robotics_Support_Bay 1 15095
15414
