Protoss_Gateway 2 6749
Protoss_Assimilator 1 4865
Protoss_Zealot 9 10152
Protoss_Shield_Battery 1 7298
Protoss_Cybernetics_Core 1 9400
Protoss_Dragoon 8 14574
Protoss_Citadel_of_Adun 1 12369
Protoss_Templar_Archives 1 14189
Protoss_Forge 1 14516
Protoss_Dark_Templar 2 15414
Protoss_Photon_Cannon 2 15783
15783
