Protoss_Gateway 2 7445
Protoss_Assimilator 2 13256
Protoss_Zealot 3 14361
Protoss_Cybernetics_Core 1 6700
Protoss_Dragoon 7 12423
Protoss_Robotics_Facility 1 10399
Protoss_Nexus 1 13161
Protoss_Observatory 1 11185
Protoss_Observer 2 15160
Protoss_Robotics_Support_Bay 1 12584
Protoss_Reaver 1 14336
15160
