Protoss_Gateway 2 10908
Protoss_Assimilator 1 4179
Protoss_Zealot 2 7132
Protoss_Cybernetics_Core 1 6965
Protoss_Dragoon 10 15683
Protoss_Robotics_Facility 1 10643
Protoss_Shuttle 1 12312
Singularity_Charge 1 10957
Protoss_Robotics_Support_Bay 1 12313
Protoss_Observatory 1 12334
Protoss_Reaver 1 14055
Protoss_Observer 1 14879
15683
