Protoss_Gateway 4 15008
Protoss_Assimilator 2 15283
Protoss_Cybernetics_Core 1 5607
Protoss_Zealot 1 5610
Protoss_Dragoon 9 14840
Protoss_Nexus 1 12798
Protoss_Robotics_Facility 1 12709
Singularity_Charge 1 11205
Protoss_Observatory 1 13656
Protoss_Observer 1 14885
15283
