Protoss_Gateway 3 12489
Protoss_Zealot 7 7843
Protoss_Assimilator 1 7237
Protoss_Cybernetics_Core 1 9459
Protoss_Dragoon 9 14231
Singularity_Charge 1 13649
Protoss_Forge 1 14986
14986
