Protoss_Gateway 2 10479
Protoss_Assimilator 1 4442
Protoss_Zealot 2 6459
Protoss_Cybernetics_Core 1 6608
Protoss_Dragoon 10 15209
Protoss_Robotics_Facility 1 10131
Protoss_Observatory 1 10844
Singularity_Charge 1 10910
Protoss_Observer 2 13861
Protoss_Nexus 1 16108
Protoss_Robotics_Support_Bay 1 14474
16108
