Protoss_Gateway 3 15725
Protoss_Zealot 8 13261
Protoss_Assimilator 1 7618
Protoss_Cybernetics_Core 1 9106
Protoss_Robotics_Facility 1 11912
Protoss_Dragoon 5 15044
Protoss_Observatory 1 13523
15725
