Protoss_Gateway 2 11158
Protoss_Assimilator 1 4188
Protoss_Zealot 2 6760
Protoss_Cybernetics_Core 1 6814
Protoss_Dragoon 8 15677
Protoss_Robotics_Facility 1 10438
Protoss_Shuttle 1 12008
Protoss_Observatory 1 11510
Singularity_Charge 1 11264
Protoss_Observer 1 12851
Protoss_Robotics_Support_Bay 1 12756
Protoss_Reaver 1 14579
Protoss_Nexus 1 17136
17136
