Protoss_Gateway 2 11029
Protoss_Assimilator 1 4337
Protoss_Zealot 3 6994
Protoss_Cybernetics_Core 1 6929
Protoss_Dragoon 9 14305
Protoss_Robotics_Facility 1 9390
Protoss_Shuttle 1 10934
Protoss_Observatory 2 11540
Protoss_Observer 2 15333
Protoss_Robotics_Support_Bay 1 12446
Singularity_Charge 1 11753
Protoss_Reaver 1 14508
15333
