Protoss_Gateway 2 12766
Protoss_Assimilator 1 4577
Protoss_Cybernetics_Core 1 6195
Protoss_Zealot 1 6152
Protoss_Dragoon 9 15721
Protoss_Nexus 1 12387
Singularity_Charge 1 10503
Protoss_Forge 1 11508
Protoss_Photon_Cannon 2 14343
15721
