Protoss_Gateway 2 11338
Protoss_Zealot 2 6075
Protoss_Assimilator 1 5443
Protoss_Cybernetics_Core 1 7237
Protoss_Dragoon 8 14788
Protoss_Robotics_Facility 1 12706
Singularity_Charge 1 11545
Protoss_Nexus 1 14898
Protoss_Shuttle 1 14115
Protoss_Robotics_Support_Bay 1 13500
Protoss_Reaver 1 15700
Protoss_Observatory 1 15203
15700
