Protoss_Gateway 2 11683
Protoss_Zealot 4 7782
Protoss_Assimilator 1 5651
Protoss_Cybernetics_Core 1 7916
Protoss_Dragoon 6 15821
Protoss_Citadel_of_Adun 1 11516
Protoss_Templar_Archives 1 12964
Singularity_Charge 1 12151
Protoss_Dark_Templar 2 14384
15821
