Protoss_Gateway 3 14666
Protoss_Assimilator 2 15434
Protoss_Zealot 2 6517
Protoss_Cybernetics_Core 1 6675
Protoss_Dragoon 12 15253
Protoss_Robotics_Facility 1 11391
Singularity_Charge 1 10772
Protoss_Observatory 1 12294
Protoss_Nexus 1 15183
Protoss_Observer 2 14253
Protoss_Citadel_of_Adun 1 15756
15756
