Protoss_Gateway 4 15326
Protoss_Assimilator 1 4527
Protoss_Zealot 2 6626
Protoss_Cybernetics_Core 1 6504
Protoss_Dragoon 6 13564
Protoss_Citadel_of_Adun 1 9576
Protoss_Templar_Archives 1 11098
Protoss_Forge 1 11281
Singularity_Charge 1 10755
Protoss_Dark_Templar 1 12291
Protoss_Photon_Cannon 1 13017
Protoss_Nexus 1 15874
Protoss_High_Templar 2 14665
15874
