Protoss_Gateway 3 13132
Protoss_Assimilator 2 14942
Protoss_Zealot 2 6652
Protoss_Cybernetics_Core 1 6727
Protoss_Dragoon 11 15712
Protoss_Nexus 1 12347
Protoss_Robotics_Facility 1 12247
Singularity_Charge 1 10755
Protoss_Observatory 1 12986
Protoss_Observer 2 14903
Protoss_Citadel_of_Adun 1 14930
15712
