Protoss_Gateway 3 15792
Protoss_Assimilator 1 4442
Protoss_Zealot 1 5124
Protoss_Cybernetics_Core 1 6645
Protoss_Dragoon 10 15200
Protoss_Robotics_Facility 1 12633
Singularity_Charge 1 11442
Protoss_Observatory 1 13424
Protoss_Nexus 1 16252
Protoss_Observer 2 15392
16252
