Protoss_Gateway 2 12062
Protoss_Zealot 11 13998
Protoss_Nexus 1 10284
Protoss_Forge 1 9538
Protoss_Photon_Cannon 11 15771
Protoss_Assimilator 1 12093
Protoss_Cybernetics_Core 1 13910
Protoss_Dragoon 2 15320
15771
