Protoss_Gateway 3 8604
Protoss_Zealot 4 8347
Protoss_Assimilator 1 7564
Protoss_Cybernetics_Core 1 8156
Protoss_Dragoon 8 14796
Protoss_Nexus 1 15412
Protoss_Robotics_Facility 1 14855
Singularity_Charge 1 14109
15412
