Protoss_Gateway 2 12953
Protoss_Assimilator 2 14132
Protoss_Cybernetics_Core 1 5888
Protoss_Zealot 1 5672
Protoss_Dragoon 8 14671
Protoss_Nexus 1 12434
Protoss_Robotics_Facility 1 12326
Singularity_Charge 1 10564
Protoss_Observatory 1 13067
Protoss_Observer 2 14970
14970
