Protoss_Gateway 2 11130
Protoss_Assimilator 1 4433
Protoss_Zealot 2 6807
Protoss_Cybernetics_Core 1 6825
Protoss_Dragoon 10 15765
Protoss_Robotics_Facility 1 10036
Protoss_Shuttle 1 11522
Protoss_Observatory 1 11425
Singularity_Charge 1 10983
Protoss_Observer 2 14976
Protoss_Robotics_Support_Bay 1 12423
Protoss_Reaver 1 14151
Protoss_Nexus 1 17179
17179
