Protoss_Gateway 2 15406
Protoss_Assimilator 2 14904
Protoss_Zealot 2 7182
Protoss_Cybernetics_Core 1 7107
Protoss_Dragoon 4 11899
Protoss_Citadel_of_Adun 1 10076
Protoss_Templar_Archives 1 11563
Protoss_Forge 1 11115
Singularity_Charge 1 10872
Protoss_Photon_Cannon 2 13778
Protoss_Dark_Templar 1 12999
Protoss_Nexus 1 15017
Protoss_High_Templar 1 14539
15406
