Protoss_Gateway 3 13250
Protoss_Assimilator 1 4401
Protoss_Zealot 2 6769
Protoss_Cybernetics_Core 1 6864
Protoss_Dragoon 11 15762
Protoss_Nexus 1 12559
Protoss_Robotics_Facility 1 12379
Singularity_Charge 1 10977
Protoss_Observatory 1 13225
Protoss_Observer 1 14238
Protoss_Robotics_Support_Bay 1 14025
Protoss_Reaver 1 16039
16039
