Protoss_Gateway 2 5232
Protoss_Zealot 8 12339
Protoss_Nexus 1 9783
Protoss_Assimilator 2 11755
Protoss_Cybernetics_Core 1 9675
Protoss_Dragoon 4 15736
Protoss_Citadel_of_Adun 1 11497
Protoss_Templar_Archives 1 12983
Protoss_Forge 1 13013
Protoss_Dark_Templar 2 14272
Protoss_Photon_Cannon 2 15382
Protoss_High_Templar 1 15534
15736
