Protoss_Gateway 2 13471
Protoss_Assimilator 2 15181
Protoss_Zealot 2 6699
Protoss_Cybernetics_Core 1 6746
Protoss_Dragoon 5 12745
Protoss_Nexus 1 12388
Protoss_Citadel_of_Adun 1 11695
Singularity_Charge 1 10804
Protoss_Forge 1 11964
Protoss_Templar_Archives 1 13474
Protoss_Photon_Cannon 2 14117
Protoss_Dark_Templar 2 14697
Protoss_High_Templar 2 15797
15797
