Protoss_Gateway 2 5129
Protoss_Zealot 3 9813
Protoss_Assimilator 3 10455
Protoss_Nexus 1 9810
Protoss_Cybernetics_Core 1 9089
Protoss_Dragoon 9 15414
Protoss_Robotics_Facility 1 13069
Protoss_Shuttle 1 14563
Protoss_Observatory 1 13986
Singularity_Charge 1 13272
Protoss_Robotics_Support_Bay 1 14614
Protoss_Observer 1 15430
15430
