Protoss_Gateway 3 10114
Protoss_Assimilator 1 4315
Protoss_Zealot 2 6298
Protoss_Cybernetics_Core 1 6443
Protoss_Dragoon 15 15241
Protoss_Robotics_Facility 1 9464
Protoss_Observatory 1 10169
Protoss_Observer 2 12108
Singularity_Charge 1 10649
Protoss_Shuttle 1 16027
16027
