Protoss_Gateway 2 7312
Protoss_Assimilator 1 4612
Protoss_Zealot 2 6945
Protoss_Cybernetics_Core 1 6090
Protoss_Dragoon 13 15777
Singularity_Charge 1 11949
Protoss_Robotics_Facility 1 14448
15777
