Protoss_Gateway 2 5386
Protoss_Zealot 5 8528
Protoss_Assimilator 1 5958
Protoss_Cybernetics_Core 1 8123
Protoss_Dragoon 10 15531
Protoss_Robotics_Facility 1 13690
Singularity_Charge 1 12739
Protoss_Observatory 1 14422
15531
