Protoss_Gateway 4 14688
Protoss_Assimilator 2 15072
Protoss_Cybernetics_Core 1 5764
Protoss_Dragoon 14 15168
Protoss_Nexus 1 12482
Protoss_Robotics_Facility 1 12004
Protoss_Observatory 1 12711
Singularity_Charge 1 12016
Protoss_Observer 1 14958
15168
