Protoss_Gateway 1 4594
Protoss_Assimilator 1 4704
Protoss_Zealot 2 13944
Protoss_Cybernetics_Core 1 7457
Protoss_Robotics_Facility 1 9478
Protoss_Dragoon 2 10005
Protoss_Citadel_of_Adun 1 10346
Protoss_Shuttle 1 10994
Protoss_Robotics_Support_Bay 1 10626
Protoss_Templar_Archives 1 11809
Protoss_Reaver 3 15725
Protoss_Dark_Templar 1 13083
Protoss_Nexus 1 17364
17364
