Protoss_Gateway 3 11221
Protoss_Assimilator 1 4223
Protoss_Cybernetics_Core 1 5633
Protoss_Dragoon 12 14878
Protoss_Nexus 1 11037
Singularity_Charge 1 12119
Protoss_Robotics_Facility 2 16229
Protoss_Observatory 1 15173
16229
