Protoss_Gateway 1 4419
Protoss_Assimilator 1 4483
Protoss_Cybernetics_Core 1 5999
Protoss_Dragoon 6 14334
Protoss_Robotics_Facility 1 8461
Protoss_Robotics_Support_Bay 1 9193
Protoss_Shield_Battery 1 9497
Protoss_Reaver 2 15482
Protoss_Observatory 1 11641
Protoss_Shuttle 1 13043
Protoss_Observer 1 13886
Singularity_Charge 1 13955
Protoss_Nexus 1 17057
17057
