Protoss_Gateway 3 15563
Protoss_Zealot 7 10078
Protoss_Assimilator 1 9020
Protoss_Cybernetics_Core 1 9867
Protoss_Dragoon 7 14883
Protoss_Robotics_Facility 1 14992
Protoss_Nexus 1 16749
16749
