Protoss_Gateway 1 4332
Protoss_Assimilator 1 4925
Protoss_Zealot 3 7883
Protoss_Shield_Battery 1 6587
Protoss_Cybernetics_Core 1 7902
Protoss_Dragoon 2 13822
Protoss_Robotics_Facility 2 11044
Protoss_Observatory 1 11395
Protoss_Shuttle 1 12121
Protoss_Robotics_Support_Bay 1 11811
Protoss_Observer 1 12492
Protoss_Reaver 2 14088
14088
