Protoss_Gateway 3 12144
Protoss_Zealot 12 13330
Protoss_Forge 1 8639
Protoss_Assimilator 1 10008
Protoss_Cybernetics_Core 1 11225
Protoss_Nexus 1 13145
Protoss_Photon_Cannon 3 15775
Protoss_Dragoon 2 15790
15790
