Protoss_Gateway 4 13918
Protoss_Zealot 5 9127
Protoss_Assimilator 2 7158
Protoss_Cybernetics_Core 1 8645
Protoss_Dragoon 4 11919
Protoss_Citadel_of_Adun 1 11325
Protoss_Templar_Archives 1 12860
Protoss_Dark_Templar 2 14107
Protoss_Nexus 1 16872
Protoss_Forge 1 15220
16872
