Protoss_Gateway 2 6036
Protoss_Assimilator 2 6214
Protoss_Zealot 11 11366
Protoss_Cybernetics_Core 1 11161
Protoss_Citadel_of_Adun 1 12621
Protoss_Templar_Archives 1 14080
Protoss_Forge 1 14325
Protoss_Dark_Templar 2 15307
15307
