Protoss_Gateway 3 13445
Protoss_Zealot 8 12529
Protoss_Assimilator 1 7647
Protoss_Cybernetics_Core 1 8749
Protoss_Forge 1 9825
Protoss_Shield_Battery 1 9960
Protoss_Dragoon 6 15527
Protoss_Photon_Cannon 2 14075
Protoss_Robotics_Facility 1 15265
15527
