Protoss_Gateway 2 8494
Protoss_Assimilator 1 4410
Protoss_Zealot 3 7180
Protoss_Cybernetics_Core 1 6677
Protoss_Shield_Battery 1 6579
Protoss_Dragoon 7 15578
Protoss_Robotics_Facility 1 12316
Protoss_Shuttle 1 13943
Protoss_Robotics_Support_Bay 1 13621
Protoss_Reaver 1 15501
15578
