Protoss_Gateway 2 5385
Protoss_Zealot 9 10050
Protoss_Assimilator 1 8139
Protoss_Cybernetics_Core 1 10051
Protoss_Robotics_Facility 1 12323
Protoss_Shield_Battery 1 11925
Protoss_Dragoon 6 14697
Protoss_Shuttle 1 14153
Protoss_Robotics_Support_Bay 1 13728
Protoss_Reaver 1 15934
15934
