Protoss_Gateway 3 7910
Protoss_Zealot 9 11033
Protoss_Forge 2 8600
Protoss_Photon_Cannon 3 12691
Protoss_Assimilator 1 10012
Protoss_Cybernetics_Core 1 11061
Protoss_Dragoon 4 15288
Protoss_Citadel_of_Adun 1 13823
Protoss_Templar_Archives 1 15271
15288
