Protoss_Gateway 2 8592
Protoss_Assimilator 1 4608
Protoss_Zealot 2 6699
Protoss_Cybernetics_Core 1 6917
Protoss_Shield_Battery 1 7146
Protoss_Dragoon 4 15361
Protoss_Robotics_Facility 1 15534
15534
