Protoss_Gateway 3 14268
Protoss_Assimilator 1 4561
Protoss_Cybernetics_Core 1 6484
Protoss_Dragoon 3 15712
Protoss_Citadel_of_Adun 1 8175
Protoss_Templar_Archives 1 10214
Protoss_Zealot 4 15280
Protoss_Dark_Templar 2 14289
Protoss_High_Templar 2 12573
Protoss_Archon 1 13685
Protoss_Forge 1 14674
Psionic_Storm 1 14358
15712
