Protoss_Gateway 2 5494
Protoss_Zealot 7 9902
Protoss_Assimilator 1 7331
Protoss_Cybernetics_Core 1 9127
Protoss_Dragoon 1 11041
Protoss_Citadel_of_Adun 1 11743
Protoss_Templar_Archives 1 13243
Protoss_Dark_Templar 2 14875
Protoss_Forge 1 15169
15169
