Protoss_Nexus 2 16553
Protoss_Assimilator 2 9023
Protoss_Gateway 3 13141
Protoss_Cybernetics_Core 1 8209
Protoss_Stargate 1 10020
Protoss_Citadel_of_Adun 1 9984
Protoss_Forge 1 9920
Protoss_Photon_Cannon 3 12127
Protoss_Corsair 2 12134
Protoss_Templar_Archives 1 12007
Protoss_Robotics_Facility 1 14204
Protoss_High_Templar 1 13719
Protoss_Shuttle 1 15662
Protoss_Robotics_Support_Bay 1 15102
16553
