Protoss_Nexus 2 17174
Protoss_Gateway 2 9293
Protoss_Assimilator 2 8470
Protoss_Cybernetics_Core 1 8319
Protoss_Robotics_Facility 1 10851
Protoss_Dragoon 6 13807
Protoss_Observatory 1 11577
Protoss_Shuttle 1 12874
Protoss_Robotics_Support_Bay 1 12404
Protoss_Observer 2 14598
Singularity_Charge 1 13516
Protoss_Forge 1 15267
17174
