Protoss_Gateway 3 14705
Protoss_Zealot 15 12741
Protoss_Assimilator 1 10417
Protoss_Cybernetics_Core 1 11319
Protoss_Citadel_of_Adun 1 13470
Protoss_Forge 1 13300
Protoss_Templar_Archives 1 15465
Protoss_Photon_Cannon 2 15770
15770
