Protoss_Gateway 2 7486
Protoss_Assimilator 1 4695
Protoss_Cybernetics_Core 1 6175
Protoss_Zealot 2 7290
Protoss_Dragoon 5 10759
Protoss_Citadel_of_Adun 1 11500
Protoss_Templar_Archives 1 13719
Protoss_Forge 1 13309
Protoss_Dark_Templar 2 15373
15373
