Protoss_Gateway 2 7398
Protoss_Assimilator 1 4754
Protoss_Zealot 3 8732
Protoss_Cybernetics_Core 1 7807
Protoss_Dragoon 10 15196
Protoss_Robotics_Facility 1 13236
Protoss_Observatory 1 13986
Protoss_Shuttle 1 14835
Singularity_Charge 1 13414
15196
