Protoss_Gateway 2 14699
Protoss_Assimilator 1 4498
Protoss_Zealot 2 6427
Protoss_Cybernetics_Core 1 7419
Protoss_Dragoon 6 15702
Protoss_Robotics_Facility 1 10261
Protoss_Shuttle 1 11682
Protoss_Robotics_Support_Bay 1 10999
Protoss_Shield_Battery 1 12234
Protoss_Reaver 1 13332
Singularity_Charge 1 12528
15702
