Protoss_Gateway 2 5363
Protoss_Zealot 11 11973
Protoss_Nexus 1 13237
Protoss_Assimilator 1 11910
Protoss_Forge 1 13322
Protoss_Cybernetics_Core 1 13878
Protoss_Photon_Cannon 2 15009
Protoss_Dragoon 2 15351
15351
