Protoss_Assimilator 1 3580
Protoss_Gateway 3 13141
Protoss_Cybernetics_Core 1 6389
Protoss_Robotics_Facility 1 8404
Protoss_Dragoon 12 15731
Protoss_Shuttle 1 9867
Protoss_Observatory 1 9407
Protoss_Observer 2 12873
Singularity_Charge 1 11262
Protoss_Robotics_Support_Bay 1 13500
15731
