Protoss_Assimilator 1 3327
Protoss_Gateway 3 15247
Protoss_Cybernetics_Core 1 6219
Protoss_Robotics_Facility 1 8297
Protoss_Dragoon 7 15161
Protoss_Shuttle 1 9904
Protoss_Observatory 1 9733
Protoss_Observer 1 11153
Protoss_Robotics_Support_Bay 1 11050
Singularity_Charge 1 10458
Protoss_Reaver 2 14832
15247
