Protoss_Gateway 3 15848
Protoss_Zealot 5 8812
Protoss_Assimilator 1 6732
Protoss_Cybernetics_Core 1 8682
Protoss_Dragoon 6 13083
Protoss_Robotics_Facility 1 11678
Protoss_Observatory 1 13257
Protoss_Observer 1 14424
15848
