Protoss_Gateway 3 10189
Protoss_Zealot 9 13290
Protoss_Assimilator 1 8281
Protoss_Cybernetics_Core 1 9789
Protoss_Citadel_of_Adun 1 11598
Protoss_Templar_Archives 1 13373
Protoss_Dragoon 2 13997
Protoss_Dark_Templar 4 15753
15753
