Protoss_Gateway 2 5408
Protoss_Zealot 7 15134
Protoss_Assimilator 1 6814
Protoss_Cybernetics_Core 1 8692
Protoss_Dragoon 10 15484
Protoss_Robotics_Facility 1 12518
Protoss_Observatory 1 13394
Singularity_Charge 1 12784
Protoss_Observer 1 14475
15484
