Protoss_Gateway 3 13142
Protoss_Zealot 5 9046
Protoss_Assimilator 1 7558
Protoss_Cybernetics_Core 1 8906
Protoss_Dragoon 10 15581
Protoss_Robotics_Facility 1 14385
Singularity_Charge 1 13070
Protoss_Observatory 1 15249
15581
