Protoss_Gateway 3 14806
Protoss_Zealot 5 8992
Protoss_Assimilator 1 7616
Protoss_Cybernetics_Core 1 9795
Protoss_Dragoon 9 15436
Singularity_Charge 1 13677
Protoss_Robotics_Facility 1 16333
16333
