Protoss_Gateway 3 14076
Protoss_Zealot 7 9178
Protoss_Assimilator 2 7673
Protoss_Cybernetics_Core 1 9320
Protoss_Dragoon 11 15639
Protoss_Robotics_Facility 1 14935
Singularity_Charge 1 13392
15639
