Protoss_Gateway 3 14528
Protoss_Zealot 11 15406
Protoss_Assimilator 1 8610
Protoss_Cybernetics_Core 1 9983
Protoss_Dragoon 8 15797
Protoss_Robotics_Facility 1 15297
Singularity_Charge 1 14328
15797
