Protoss_Gateway 3 12072
Protoss_Assimilator 1 4331
Protoss_Zealot 2 6829
Protoss_Cybernetics_Core 1 6886
Protoss_Dragoon 9 15512
Protoss_Robotics_Facility 1 10091
Protoss_Observatory 1 10858
Protoss_Observer 3 13684
Singularity_Charge 1 13019
Protoss_Nexus 1 16525
Protoss_Robotics_Support_Bay 1 14706
16525
