Protoss_Gateway 3 14330
Protoss_Assimilator 1 4267
Protoss_Zealot 2 6749
Protoss_Cybernetics_Core 1 6702
Protoss_Dragoon 11 15607
Protoss_Robotics_Facility 1 11722
Singularity_Charge 1 11482
Protoss_Observatory 1 12499
Protoss_Observer 2 14412
15607
