Protoss_Gateway 2 8246
Protoss_Assimilator 1 4555
Protoss_Zealot 3 6961
Protoss_Cybernetics_Core 1 7125
Protoss_Dragoon 11 14875
Protoss_Robotics_Facility 1 12424
Singularity_Charge 1 11343
Protoss_Observatory 1 13168
Protoss_Observer 1 14205
14875
