Protoss_Gateway 4 15567
Protoss_Assimilator 1 4395
Protoss_Zealot 2 6712
Protoss_Cybernetics_Core 1 6845
Protoss_Dragoon 10 15271
Protoss_Robotics_Facility 1 12273
Singularity_Charge 1 11343
Protoss_Nexus 1 14895
Protoss_Observatory 1 13225
15567
