Protoss_Gateway 3 13616
Protoss_Assimilator 1 4234
Protoss_Cybernetics_Core 1 5838
Protoss_Robotics_Facility 1 7917
Protoss_Dragoon 7 15585
Protoss_Shuttle 1 9413
Protoss_Robotics_Support_Bay 1 9126
Protoss_Observatory 1 9811
Protoss_Reaver 2 13411
Protoss_Observer 2 15222
Protoss_Nexus 1 16237
16237
