Protoss_Assimilator 1 3601
Protoss_Gateway 1 4646
Protoss_Cybernetics_Core 1 6169
Protoss_Robotics_Facility 1 8100
Protoss_Zealot 2 8120
Protoss_Shuttle 1 9509
Protoss_Dragoon 6 15748
Protoss_Robotics_Support_Bay 1 9374
Protoss_Reaver 2 12932
Protoss_Forge 1 12933
Protoss_Observatory 1 13411
Gravitic_Drive 1 13201
Protoss_Photon_Cannon 1 14417
Protoss_Observer 2 15312
15748
