Protoss_Gateway 2 8254
Protoss_Assimilator 1 4381
Protoss_Cybernetics_Core 1 5835
Protoss_Dragoon 11 14758
Protoss_Robotics_Facility 1 11269
Protoss_Zealot 1 10697
Singularity_Charge 1 9891
Protoss_Robotics_Support_Bay 1 12209
Protoss_Reaver 2 15662
Protoss_Nexus 1 15971
15971
