Protoss_Gateway 2 7833
Protoss_Assimilator 1 4395
Protoss_Cybernetics_Core 1 5827
Protoss_Dragoon 12 15443
Protoss_Robotics_Facility 1 11502
Singularity_Charge 1 10450
Protoss_Shuttle 1 12901
Protoss_Observatory 1 12244
Protoss_Robotics_Support_Bay 1 13471
Protoss_Observer 1 13837
Protoss_Reaver 1 15433
15443
