Protoss_Gateway 2 13173
Protoss_Zealot 5 10079
Protoss_Nexus 2 15561
Protoss_Assimilator 2 11765
Protoss_Cybernetics_Core 1 9607
Protoss_Citadel_of_Adun 1 11292
Protoss_Dragoon 1 11246
Protoss_Templar_Archives 1 12907
Protoss_Forge 1 13315
Protoss_Dark_Templar 2 14366
Protoss_Photon_Cannon 2 14802
Protoss_High_Templar 2 15467
Protoss_Robotics_Facility 1 16410
16410
