Protoss_Gateway 3 14399
Protoss_Zealot 2 7954
Protoss_Nexus 1 7989
Protoss_Assimilator 2 13865
Protoss_Cybernetics_Core 1 8007
Protoss_Dragoon 11 15352
Protoss_Shield_Battery 1 11584
Singularity_Charge 1 11674
Protoss_Robotics_Facility 1 13817
Protoss_Observatory 1 14688
Protoss_Forge 1 15250
15352
