Protoss_Gateway 1 4360
Protoss_Assimilator 1 4454
Protoss_Cybernetics_Core 1 6072
Protoss_Dragoon 5 12496
Protoss_Robotics_Facility 1 10419
Protoss_Observatory 1 11211
Singularity_Charge 1 10523
12496
