Protoss_Assimilator 2 7505
Protoss_Gateway 2 8671
Protoss_Cybernetics_Core 1 6232
Protoss_Robotics_Facility 1 8206
Protoss_Dragoon 7 12592
Protoss_Observatory 1 9129
Protoss_Observer 2 11091
Singularity_Charge 1 11087
Protoss_Shuttle 1 12630
12630
