Protoss_Gateway 2 11433
Protoss_Assimilator 1 4710
Protoss_Cybernetics_Core 1 6099
Protoss_Dragoon 4 11073
Protoss_Robotics_Facility 1 8966
Protoss_Observatory 1 9865
Protoss_Observer 1 10971
11433
