Protoss_Assimilator 1 3320
Protoss_Gateway 3 10580
Protoss_Cybernetics_Core 1 6219
Protoss_Robotics_Facility 1 8209
Protoss_Dragoon 3 10848
Protoss_Observatory 1 8944
Protoss_Observer 2 10856
Protoss_Shuttle 1 12214
Protoss_Zealot 3 12127
12214
