Protoss_Gateway 2 12468
Protoss_Assimilator 1 4433
Protoss_Cybernetics_Core 1 6084
Protoss_Dragoon 4 11422
Protoss_Robotics_Facility 1 8701
Protoss_Nexus 1 11978
Protoss_Observatory 1 10124
Protoss_Observer 2 12141
12468
