Protoss_Gateway 3 12352
Protoss_Assimilator 1 4681
Protoss_Cybernetics_Core 1 6798
Protoss_Dragoon 4 11344
Protoss_Robotics_Facility 1 10368
Protoss_Observatory 1 11151
Singularity_Charge 1 10472
Protoss_Observer 1 12229
12352
