Protoss_Gateway 2 7111
Protoss_Assimilator 1 4419
Protoss_Cybernetics_Core 1 5963
Protoss_Dragoon 6 11517
Protoss_Nexus 1 12492
Singularity_Charge 1 10384
Protoss_Robotics_Facility 1 13112
13112
