Protoss_Assimilator 1 3583
Protoss_Gateway 2 9672
Protoss_Cybernetics_Core 1 6334
Protoss_Dragoon 5 12310
Protoss_Robotics_Facility 1 8900
Protoss_Observatory 1 9748
Protoss_Observer 2 12266
Singularity_Charge 1 11372
12310
