Protoss_Gateway 2 10827
Protoss_Assimilator 1 4542
Protoss_Cybernetics_Core 1 5977
Protoss_Zealot 1 6383
Protoss_Dragoon 5 12410
Protoss_Robotics_Facility 1 11907
Singularity_Charge 1 10589
12410
