Protoss_Gateway 2 10612
Protoss_Assimilator 1 4630
Protoss_Cybernetics_Core 1 5948
Protoss_Dragoon 5 12263
Protoss_Robotics_Facility 1 8821
Protoss_Observatory 1 9613
Protoss_Observer 1 10934
Protoss_Zealot 1 11007
12263
