Protoss_Gateway 1 4375
Protoss_Assimilator 1 4410
Protoss_Cybernetics_Core 1 6094
Protoss_Zealot 1 6310
Protoss_Dragoon 5 11927
Protoss_Robotics_Facility 1 11217
Singularity_Charge 1 9858
11927
