Protoss_Gateway 2 12653
Protoss_Assimilator 1 4489
Protoss_Cybernetics_Core 1 6189
Protoss_Dragoon 2 10031
Protoss_Robotics_Facility 1 9314
Protoss_Robotics_Support_Bay 1 10040
Protoss_Shuttle 1 10957
Protoss_Reaver 1 12515
Protoss_Observatory 1 11732
12653
