Protoss_Gateway 1 4310
Protoss_Assimilator 1 4349
Protoss_Cybernetics_Core 1 6068
Protoss_Robotics_Facility 1 8063
Protoss_Dragoon 2 11551
Protoss_Zealot 4 10431
Protoss_Shuttle 1 11228
11551
