Protoss_Gateway 2 9604
Protoss_Assimilator 1 4527
Protoss_Cybernetics_Core 1 6140
Protoss_Dragoon 6 12300
Protoss_Robotics_Facility 1 9534
Protoss_Observatory 1 10283
Protoss_Observer 1 11379
12300
