Protoss_Nexus 1 7240
Protoss_Gateway 3 12435
Protoss_Assimilator 1 6359
Protoss_Cybernetics_Core 1 7788
Protoss_Dragoon 2 10178
Protoss_Robotics_Facility 1 10579
Protoss_Forge 1 11009
Protoss_Observatory 1 11381
Protoss_Photon_Cannon 1 12284
12435
