Protoss_Gateway 2 12754
Protoss_Assimilator 1 4731
Protoss_Cybernetics_Core 1 6277
Protoss_Dragoon 5 12110
Protoss_Robotics_Facility 1 10263
Protoss_Observatory 1 11062
Protoss_Observer 1 12112
12754
