Protoss_Gateway 3 10479
Protoss_Assimilator 1 4681
Protoss_Cybernetics_Core 1 6213
Protoss_Robotics_Facility 1 8370
Protoss_Dragoon 6 12373
Protoss_Observatory 1 9394
Protoss_Observer 2 12185
Singularity_Charge 1 11182
12373
