Protoss_Gateway 2 9244
Protoss_Assimilator 1 4425
Protoss_Cybernetics_Core 1 5897
Protoss_Robotics_Facility 1 8205
Protoss_Dragoon 4 10866
Protoss_Observatory 1 9882
Protoss_Observer 2 11982
Singularity_Charge 1 11068
11982
