Protoss_Gateway 2 12459
Protoss_Assimilator 1 4454
Protoss_Cybernetics_Core 1 6469
Protoss_Dragoon 5 12165
Protoss_Robotics_Facility 1 10372
Singularity_Charge 1 10165
Protoss_Observatory 1 11322
12459
