Protoss_Gateway 2 10685
Protoss_Assimilator 1 4690
Protoss_Cybernetics_Core 1 6080
Protoss_Dragoon 5 11941
Protoss_Robotics_Facility 1 8765
Protoss_Observatory 1 9740
Protoss_Observer 2 11647
11941
