Protoss_Gateway 2 8254
Protoss_Assimilator 1 4365
Protoss_Cybernetics_Core 1 5774
Protoss_Zealot 1 6478
Protoss_Dragoon 6 10653
Protoss_Citadel_of_Adun 1 11450
Protoss_Robotics_Facility 1 12935
12935
