Protoss_Gateway 2 10237
Protoss_Assimilator 1 4483
Protoss_Cybernetics_Core 1 6195
Protoss_Dragoon 5 11722
Protoss_Robotics_Facility 1 8956
Protoss_Observatory 1 9759
Protoss_Observer 2 12149
12149
