Protoss_Gateway 2 10543
Protoss_Assimilator 1 4555
Protoss_Cybernetics_Core 1 6087
Protoss_Dragoon 1 7478
Protoss_Robotics_Facility 1 8574
Protoss_Citadel_of_Adun 1 9536
Protoss_Shuttle 1 10006
Protoss_Templar_Archives 1 10989
Protoss_Dark_Templar 2 12227
12227
