Protoss_Gateway 1 4347
Protoss_Assimilator 1 4432
Protoss_Cybernetics_Core 1 6055
Protoss_Dragoon 5 11949
Protoss_Robotics_Facility 1 8780
Protoss_Shuttle 1 10467
Protoss_Observatory 1 10008
Protoss_Robotics_Support_Bay 1 10355
Protoss_Observer 1 11600
11949
