Protoss_Gateway 1 4274
Protoss_Assimilator 1 4315
Protoss_Cybernetics_Core 1 5831
Protoss_Robotics_Facility 1 7997
Protoss_Dragoon 4 12022
Protoss_Observatory 1 8889
Protoss_Observer 1 10041
Protoss_Nexus 1 13272
Protoss_Shuttle 1 12560
13272
