Protoss_Gateway 2 9115
Protoss_Assimilator 1 4779
Protoss_Cybernetics_Core 1 6236
Protoss_Dragoon 6 11872
Protoss_Robotics_Facility 1 11051
Singularity_Charge 1 10120
Protoss_Observatory 1 11985
11985
