Protoss_Gateway 1 4442
Protoss_Assimilator 1 4788
Protoss_Cybernetics_Core 1 6134
Protoss_Dragoon 5 11896
Protoss_Robotics_Facility 1 10554
Singularity_Charge 1 10286
Protoss_Observatory 1 11262
Protoss_Nexus 1 14045
Protoss_Observer 1 12283
14045
