Protoss_Gateway 2 12312
Protoss_Zealot 1 5168
Protoss_Assimilator 1 6612
Protoss_Cybernetics_Core 1 8554
Protoss_Nexus 1 11140
Protoss_Citadel_of_Adun 1 10130
Protoss_Templar_Archives 1 11652
12312
