Protoss_Gateway 2 9031
Protoss_Assimilator 1 4855
Protoss_Cybernetics_Core 1 6209
Protoss_Dragoon 6 11946
Protoss_Robotics_Facility 1 11022
Singularity_Charge 1 10128
Protoss_Observatory 1 12118
12118
