Protoss_Gateway 2 12358
Protoss_Assimilator 1 4485
Protoss_Cybernetics_Core 1 5963
Protoss_Dragoon 4 11791
Protoss_Robotics_Facility 1 8626
Protoss_Nexus 1 11627
Protoss_Observatory 1 9775
Protoss_Observer 2 12269
12358
