Protoss_Gateway 1 4411
Protoss_Assimilator 1 4688
Protoss_Cybernetics_Core 1 6138
Protoss_Robotics_Facility 1 8158
Protoss_Dragoon 3 12066
Protoss_Zealot 2 9586
Protoss_Shuttle 1 9574
Protoss_Robotics_Support_Bay 1 9837
Protoss_Reaver 1 11583
12066
