Protoss_Gateway 2 11928
Protoss_Assimilator 1 4403
Protoss_Cybernetics_Core 1 6108
Protoss_Dragoon 4 11644
Protoss_Robotics_Facility 1 10061
Protoss_Observatory 1 10942
Singularity_Charge 1 10970
11928
