Protoss_Gateway 2 11977
Protoss_Assimilator 1 4403
Protoss_Cybernetics_Core 1 5828
Protoss_Dragoon 2 8795
Protoss_Robotics_Facility 1 8727
Protoss_Observatory 1 9560
Protoss_Citadel_of_Adun 1 10420
Protoss_Zealot 2 11200
Protoss_Observer 2 11578
11977
