Protoss_Gateway 2 10606
Protoss_Assimilator 1 4618
Protoss_Cybernetics_Core 1 6039
Protoss_Dragoon 5 12029
Protoss_Robotics_Facility 1 8751
Protoss_Observatory 1 9455
Protoss_Observer 2 11380
12029
