Protoss_Gateway 2 9089
Protoss_Assimilator 1 4357
Protoss_Cybernetics_Core 1 5869
Protoss_Robotics_Facility 1 7927
Protoss_Dragoon 4 10570
Protoss_Observatory 1 8789
Protoss_Observer 1 9810
Protoss_Shuttle 1 12175
12175
