Protoss_Gateway 1 4376
Protoss_Assimilator 1 4747
Protoss_Cybernetics_Core 1 6147
Protoss_Dragoon 2 8861
Protoss_Robotics_Facility 1 8722
Protoss_Shuttle 1 10138
Protoss_Robotics_Support_Bay 1 9762
Protoss_Zealot 2 11446
Protoss_Reaver 1 11890
Protoss_Observatory 1 11864
11890
