Protoss_Gateway 2 9596
Protoss_Assimilator 1 4671
Protoss_Cybernetics_Core 1 6191
Protoss_Dragoon 7 12549
Protoss_Robotics_Facility 1 11044
Singularity_Charge 1 10374
Protoss_Observatory 1 11754
12549
