Protoss_Gateway 2 9185
Protoss_Assimilator 1 4412
Protoss_Cybernetics_Core 1 5720
Protoss_Dragoon 7 12336
Protoss_Robotics_Facility 1 10748
Singularity_Charge 1 9887
Protoss_Observatory 1 11559
12336
