Protoss_Gateway 2 11363
Protoss_Assimilator 1 4461
Protoss_Cybernetics_Core 1 5789
Protoss_Dragoon 5 12600
Protoss_Robotics_Facility 1 10141
Singularity_Charge 1 10033
Protoss_Observatory 1 11002
12600
