Protoss_Assimilator 2 5360
Protoss_Gateway 2 9078
Protoss_Cybernetics_Core 1 6674
Protoss_Dragoon 4 11612
Protoss_Citadel_of_Adun 1 10038
Protoss_Templar_Archives 1 11502
Singularity_Charge 1 11204
11612
