Protoss_Gateway 2 9612
Protoss_Assimilator 1 4540
Protoss_Cybernetics_Core 1 5780
Protoss_Dragoon 3 11385
Protoss_Robotics_Facility 1 8597
Protoss_Zealot 2 9236
Protoss_Shuttle 2 12201
Protoss_Observatory 1 10318
Protoss_Robotics_Support_Bay 1 10921
12201
