Protoss_Gateway 2 10953
Protoss_Assimilator 1 4657
Protoss_Cybernetics_Core 1 6018
Protoss_Dragoon 4 11605
Protoss_Robotics_Facility 1 8688
Protoss_Observatory 1 9506
Protoss_Observer 2 12258
12258
