Protoss_Assimilator 1 3479
Protoss_Gateway 2 12509
Protoss_Cybernetics_Core 1 6283
Protoss_Robotics_Facility 1 8225
Protoss_Dragoon 4 11992
Protoss_Shuttle 2 12280
Singularity_Charge 1 10655
Protoss_Observatory 1 11832
12509
