Protoss_Gateway 3 11174
Protoss_Assimilator 1 4691
Protoss_Cybernetics_Core 1 6122
Protoss_Dragoon 4 11129
Protoss_Robotics_Facility 1 9194
Protoss_Observatory 1 9914
Protoss_Observer 2 11868
11868
