Protoss_Gateway 2 10981
Protoss_Assimilator 1 5057
Protoss_Cybernetics_Core 1 6424
Protoss_Dragoon 5 12190
Protoss_Robotics_Facility 1 10470
Singularity_Charge 1 10399
Protoss_Observatory 1 11245
12190
