Protoss_Gateway 1 4413
Protoss_Assimilator 1 4520
Protoss_Cybernetics_Core 1 6080
Protoss_Zealot 1 5980
Protoss_Robotics_Facility 1 8539
Protoss_Dragoon 4 11962
Protoss_Observatory 1 9459
Protoss_Observer 2 11383
11962
