Protoss_Gateway 2 11115
Protoss_Assimilator 1 4830
Protoss_Cybernetics_Core 1 5869
Protoss_Dragoon 5 11978
Protoss_Robotics_Facility 1 10668
Singularity_Charge 1 10231
Protoss_Observatory 1 11372
Protoss_Zealot 1 12141
12141
