Protoss_Gateway 2 9986
Protoss_Assimilator 3 5273
Protoss_Cybernetics_Core 1 6295
Protoss_Dragoon 6 12527
Protoss_Nexus 1 12236
Singularity_Charge 1 10311
Protoss_Robotics_Facility 1 12644
12644
