Protoss_Gateway 1 4454
Protoss_Assimilator 1 4769
Protoss_Cybernetics_Core 1 6096
Protoss_Dragoon 3 12329
Protoss_Robotics_Facility 1 9058
Protoss_Zealot 2 10349
Protoss_Shuttle 1 10518
Protoss_Robotics_Support_Bay 1 10008
Protoss_Reaver 1 12076
12329
