Protoss_Gateway 2 9607
Protoss_Assimilator 1 4710
Protoss_Cybernetics_Core 1 6279
Protoss_Dragoon 6 11956
Protoss_Robotics_Facility 1 11155
Singularity_Charge 1 10487
Protoss_Observatory 1 11935
11956
