Protoss_Gateway 2 10994
Protoss_Assimilator 1 4652
Protoss_Zealot 1 5373
Protoss_Cybernetics_Core 1 6646
Protoss_Dragoon 6 12591
Protoss_Robotics_Facility 1 8825
Protoss_Observatory 1 9601
Protoss_Observer 2 11695
12591
