Protoss_Gateway 2 10638
Protoss_Assimilator 1 4717
Protoss_Cybernetics_Core 1 6030
Protoss_Dragoon 6 12000
Protoss_Robotics_Facility 1 8918
Protoss_Observatory 1 10059
Protoss_Observer 2 12288
12288
