Protoss_Gateway 1 4656
Protoss_Assimilator 1 4637
Protoss_Cybernetics_Core 1 6131
Protoss_Dragoon 4 11319
Protoss_Robotics_Facility 1 10220
Protoss_Shuttle 1 11791
Singularity_Charge 1 10801
Protoss_Robotics_Support_Bay 1 11590
11791
