Protoss_Gateway 2 9134
Protoss_Assimilator 1 4473
Protoss_Cybernetics_Core 1 6134
Protoss_Dragoon 5 12168
Protoss_Robotics_Facility 1 8941
Protoss_Observatory 1 9645
Protoss_Observer 2 11552
12168
