Protoss_Gateway 2 12718
Protoss_Assimilator 1 4578
Protoss_Cybernetics_Core 1 5926
Protoss_Dragoon 4 11071
Protoss_Nexus 1 12242
Singularity_Charge 1 10209
Protoss_Robotics_Facility 1 12497
12718
