Protoss_Assimilator 2 5351
Protoss_Gateway 1 4934
Protoss_Zealot 3 8013
Protoss_Cybernetics_Core 1 7170
Protoss_Robotics_Facility 1 9601
Protoss_Dragoon 3 10971
Protoss_Shuttle 1 11004
Protoss_Robotics_Support_Bay 1 10588
Protoss_Reaver 1 12334
12334
