Protoss_Assimilator 1 3753
Protoss_Gateway 1 4931
Protoss_Cybernetics_Core 1 6431
Protoss_Robotics_Facility 1 8435
Protoss_Dragoon 4 12534
Protoss_Robotics_Support_Bay 1 9186
Protoss_Observatory 1 9269
Protoss_Observer 1 10524
Protoss_Shuttle 1 12084
12534
