Protoss_Gateway 2 10056
Protoss_Assimilator 1 4738
Protoss_Cybernetics_Core 1 6049
Protoss_Robotics_Facility 1 8331
Protoss_Dragoon 5 12071
Protoss_Observatory 1 9069
Protoss_Observer 2 11086
12071
