Protoss_Gateway 2 11067
Protoss_Assimilator 1 4862
Protoss_Cybernetics_Core 1 6206
Protoss_Dragoon 6 12358
Protoss_Robotics_Facility 1 10887
Singularity_Charge 1 10597
Protoss_Observatory 1 11735
12358
