Protoss_Gateway 2 9674
Protoss_Assimilator 1 4150
Protoss_Zealot 3 7432
Protoss_Cybernetics_Core 1 6694
Protoss_Robotics_Facility 1 8913
Protoss_Dragoon 2 11078
Protoss_Shuttle 1 11813
Protoss_Robotics_Support_Bay 1 11630
11813
