Protoss_Gateway 2 10217
Protoss_Assimilator 1 4385
Protoss_Cybernetics_Core 1 5743
Protoss_Zealot 1 5688
Protoss_Dragoon 5 12556
Singularity_Charge 1 10143
Protoss_Nexus 1 13439
Protoss_Robotics_Facility 1 13085
13439
