Protoss_Gateway 2 10621
Protoss_Assimilator 1 4747
Protoss_Cybernetics_Core 1 6097
Protoss_Dragoon 4 11136
Protoss_Citadel_of_Adun 1 9605
Protoss_Templar_Archives 1 11156
Singularity_Charge 1 10011
11156
