Protoss_Gateway 2 10331
Protoss_Assimilator 1 4646
Protoss_Cybernetics_Core 1 6102
Protoss_Robotics_Facility 1 8411
Protoss_Dragoon 5 11927
Protoss_Observatory 1 9418
Protoss_Observer 2 11461
11927
