Protoss_Gateway 2 8385
Protoss_Assimilator 2 6400
Protoss_Cybernetics_Core 1 5963
Protoss_Dragoon 6 12497
Protoss_Forge 1 8636
Protoss_Robotics_Facility 1 11744
Singularity_Charge 1 10267
Protoss_Photon_Cannon 1 12354
12497
