Protoss_Gateway 2 11436
Protoss_Assimilator 1 4586
Protoss_Cybernetics_Core 1 6062
Protoss_Dragoon 5 11673
Protoss_Robotics_Facility 1 9840
Protoss_Observatory 1 10560
Protoss_Observer 1 11680
11680
