Protoss_Gateway 1 4245
Protoss_Assimilator 1 4543
Protoss_Cybernetics_Core 1 6014
Protoss_Dragoon 5 12131
Protoss_Nexus 1 12059
Singularity_Charge 1 10143
Protoss_Robotics_Facility 1 12168
12168
