Protoss_Gateway 1 4199
Protoss_Assimilator 1 4666
Protoss_Cybernetics_Core 1 5793
Protoss_Zealot 1 5710
Protoss_Dragoon 4 12410
Protoss_Robotics_Facility 1 8744
Protoss_Shuttle 1 10204
Protoss_Robotics_Support_Bay 1 9982
Protoss_Reaver 1 12168
12410
