Protoss_Gateway 2 12138
Protoss_Assimilator 1 5077
Protoss_Zealot 1 5900
Protoss_Cybernetics_Core 1 7255
Protoss_Dragoon 4 11870
Protoss_Robotics_Facility 1 10968
Protoss_Observatory 1 11821
12138
