Protoss_Gateway 2 9810
Protoss_Assimilator 1 4571
Protoss_Cybernetics_Core 1 5875
Protoss_Robotics_Facility 1 8208
Protoss_Dragoon 4 11539
Protoss_Observatory 1 9257
Protoss_Observer 1 10378
11539
