Protoss_Gateway 2 9943
Protoss_Assimilator 1 4498
Protoss_Cybernetics_Core 1 6102
Protoss_Robotics_Facility 1 8144
Protoss_Dragoon 5 11671
Protoss_Observatory 1 8979
Protoss_Observer 1 10012
11671
