Protoss_Gateway 2 10471
Protoss_Assimilator 1 4731
Protoss_Cybernetics_Core 1 6380
Protoss_Robotics_Facility 1 8461
Protoss_Dragoon 4 11810
Protoss_Observatory 1 9320
Protoss_Observer 2 11288
11810
