Protoss_Gateway 2 10157
Protoss_Assimilator 1 4777
Protoss_Zealot 1 5395
Protoss_Cybernetics_Core 1 6640
Protoss_Dragoon 4 11311
Protoss_Robotics_Facility 1 11751
Singularity_Charge 1 10933
11751
