Protoss_Gateway 1 4354
Protoss_Assimilator 1 4637
Protoss_Cybernetics_Core 1 5992
Protoss_Zealot 1 5980
Protoss_Dragoon 4 11351
Protoss_Robotics_Facility 1 10492
Singularity_Charge 1 10370
Protoss_Shuttle 1 12391
Protoss_Robotics_Support_Bay 1 11918
12391
