Protoss_Gateway 3 11933
Protoss_Assimilator 1 4578
Protoss_Cybernetics_Core 1 5900
Protoss_Dragoon 5 12219
Protoss_Robotics_Facility 1 10053
Singularity_Charge 1 9982
Protoss_Observatory 1 10757
Protoss_Observer 1 11783
12219
