Protoss_Gateway 3 12773
Protoss_Assimilator 1 4530
Protoss_Cybernetics_Core 1 5999
Protoss_Dragoon 5 12549
Protoss_Nexus 1 11949
Protoss_Robotics_Facility 1 12153
Singularity_Charge 1 10319
12773
