Protoss_Gateway 2 10985
Protoss_Assimilator 1 4551
Protoss_Cybernetics_Core 1 6017
Protoss_Dragoon 2 9571
Protoss_Robotics_Facility 1 8758
Protoss_Citadel_of_Adun 1 9358
Protoss_Observatory 1 9496
Protoss_Observer 1 10524
Protoss_Templar_Archives 1 11885
Protoss_Shuttle 1 12048
12048
