Protoss_Gateway 1 4430
Protoss_Assimilator 1 4507
Protoss_Cybernetics_Core 1 6153
Protoss_Zealot 1 5944
Protoss_Dragoon 3 11663
Protoss_Robotics_Facility 1 10229
Protoss_Observatory 1 11126
Protoss_Nexus 1 13334
Protoss_Observer 1 12156
13334
