Protoss_Gateway 2 9062
Protoss_Assimilator 1 4417
Protoss_Cybernetics_Core 1 6184
Protoss_Dragoon 1 7441
Protoss_Citadel_of_Adun 1 8093
Protoss_Templar_Archives 1 9662
Protoss_Dark_Templar 4 12278
Protoss_Forge 1 11742
12278
