Protoss_Gateway 2 10820
Protoss_Assimilator 1 4511
Protoss_Cybernetics_Core 1 6181
Protoss_Dragoon 6 12120
Protoss_Robotics_Facility 1 10342
Singularity_Charge 1 10223
Protoss_Observatory 1 11186
Protoss_Observer 1 12353
12353
