Protoss_Nexus 1 7342
Protoss_Gateway 2 11203
Protoss_Forge 1 7327
Protoss_Zealot 2 8537
Protoss_Photon_Cannon 2 11220
Protoss_Assimilator 1 9561
Protoss_Cybernetics_Core 1 10580
Protoss_Dragoon 2 12410
12410
