Protoss_Gateway 2 9949
Protoss_Assimilator 1 4400
Protoss_Cybernetics_Core 1 5655
Protoss_Dragoon 6 11327
Protoss_Robotics_Facility 1 8397
Protoss_Observatory 1 9562
Protoss_Observer 2 11800
Protoss_Nexus 1 14144
14144
