Protoss_Gateway 2 10831
Protoss_Assimilator 1 4527
Protoss_Cybernetics_Core 1 5944
Protoss_Dragoon 6 12054
Protoss_Robotics_Facility 1 10554
Singularity_Charge 1 10067
Protoss_Observatory 1 11252
Protoss_Observer 1 12266
12266
