Protoss_Gateway 2 12037
Protoss_Assimilator 1 4725
Protoss_Cybernetics_Core 1 6036
Protoss_Dragoon 5 12273
Protoss_Robotics_Facility 1 10356
Singularity_Charge 1 10340
Protoss_Observatory 1 11174
Protoss_Observer 1 12214
12273
