Protoss_Gateway 2 8623
Protoss_Assimilator 1 4536
Protoss_Cybernetics_Core 1 5853
Protoss_Zealot 1 5710
Protoss_Dragoon 2 8685
Protoss_Citadel_of_Adun 1 9977
Protoss_Robotics_Facility 1 11780
Protoss_Templar_Archives 1 11456
11780
