Protoss_Gateway 2 9596
Protoss_Assimilator 1 4602
Protoss_Cybernetics_Core 1 6149
Protoss_Dragoon 5 11553
Protoss_Robotics_Facility 1 11546
Singularity_Charge 1 10231
Protoss_Citadel_of_Adun 1 12621
12621
