Protoss_Assimilator 1 3725
Protoss_Gateway 2 8380
Protoss_Cybernetics_Core 1 6295
Protoss_Robotics_Facility 1 8247
Protoss_Shuttle 1 9649
Protoss_Observatory 1 9449
Protoss_Dragoon 4 11735
Protoss_Observer 2 11581
Singularity_Charge 1 11018
11735
