Protoss_Gateway 3 12149
Protoss_Assimilator 1 4436
Protoss_Cybernetics_Core 1 5679
Protoss_Dragoon 5 10991
Protoss_Robotics_Facility 1 11290
Singularity_Charge 1 9760
Protoss_Zealot 2 11996
12149
