Protoss_Gateway 1 4308
Protoss_Assimilator 1 4656
Protoss_Cybernetics_Core 1 6160
Protoss_Dragoon 5 12417
Protoss_Robotics_Facility 1 10517
Singularity_Charge 1 10267
Protoss_Shuttle 1 11923
Protoss_Robotics_Support_Bay 1 11900
12417
