Protoss_Gateway 1 4274
Protoss_Assimilator 1 4619
Protoss_Zealot 1 5505
Protoss_Cybernetics_Core 1 7158
Protoss_Dragoon 2 12366
Protoss_Citadel_of_Adun 1 8765
Singularity_Charge 1 11036
12366
