Protoss_Gateway 2 11695
Protoss_Assimilator 1 4758
Protoss_Cybernetics_Core 1 6102
Protoss_Dragoon 5 11744
Protoss_Nexus 1 12795
Singularity_Charge 1 10428
Protoss_Robotics_Facility 1 13106
13106
