Protoss_Gateway 2 11800
Protoss_Assimilator 1 4911
Protoss_Cybernetics_Core 1 6292
Protoss_Dragoon 6 12584
Protoss_Robotics_Facility 1 8918
Protoss_Observatory 1 9676
Protoss_Observer 2 11929
12584
