Protoss_Assimilator 1 3377
Protoss_Gateway 1 4815
Protoss_Cybernetics_Core 1 6302
Protoss_Zealot 4 9529
Protoss_Robotics_Facility 1 8277
Protoss_Shuttle 1 9684
Protoss_Robotics_Support_Bay 1 9996
Protoss_Observatory 1 10114
Protoss_Dragoon 2 12149
Protoss_Reaver 1 11993
12149
