Protoss_Gateway 2 11363
Protoss_Assimilator 1 4419
Protoss_Cybernetics_Core 1 6058
Protoss_Dragoon 4 10574
Protoss_Robotics_Facility 1 10413
Singularity_Charge 1 10340
Protoss_Shuttle 1 11828
Protoss_Zealot 1 11436
Protoss_Observatory 1 11472
11828
