Protoss_Assimilator 1 3576
Protoss_Gateway 2 10267
Protoss_Cybernetics_Core 1 6277
Protoss_Robotics_Facility 1 8370
Protoss_Dragoon 5 12017
Protoss_Observatory 1 9196
Protoss_Observer 2 11164
Protoss_Shuttle 1 12633
12633
