Protoss_Gateway 2 12738
Protoss_Assimilator 1 4668
Protoss_Cybernetics_Core 1 6094
Protoss_Robotics_Facility 1 8283
Protoss_Dragoon 4 12234
Protoss_Observatory 1 9269
Protoss_Nexus 1 12157
Protoss_Observer 2 11453
12738
