Protoss_Gateway 2 9806
Protoss_Assimilator 1 4789
Protoss_Cybernetics_Core 1 6340
Protoss_Dragoon 5 11798
Protoss_Robotics_Facility 1 9608
Protoss_Observatory 1 10740
Protoss_Observer 1 11775
11798
