Protoss_Gateway 1 4616
Protoss_Assimilator 1 4769
Protoss_Cybernetics_Core 1 6257
Protoss_Dragoon 3 10188
Protoss_Robotics_Facility 1 8991
Protoss_Zealot 1 12266
Protoss_Shuttle 1 12830
12830
