Protoss_Gateway 2 10953
Protoss_Assimilator 1 4512
Protoss_Cybernetics_Core 1 6150
Protoss_Robotics_Facility 1 8182
Protoss_Observatory 1 8933
Protoss_Dragoon 4 12218
Protoss_Observer 1 10112
Protoss_Shuttle 1 11704
Singularity_Charge 1 11033
12218
