Protoss_Gateway 2 10002
Protoss_Assimilator 1 4687
Protoss_Cybernetics_Core 1 5889
Protoss_Dragoon 3 10125
Protoss_Robotics_Facility 1 9742
Protoss_Shuttle 1 11148
Protoss_Robotics_Support_Bay 1 10661
Protoss_Reaver 1 12827
12827
