Protoss_Gateway 2 9580
Protoss_Assimilator 1 4747
Protoss_Cybernetics_Core 1 6116
Protoss_Dragoon 3 9907
Protoss_Citadel_of_Adun 1 8189
Protoss_Templar_Archives 1 9741
Protoss_Dark_Templar 2 11114
Protoss_Robotics_Facility 1 12884
12884
