Protoss_Gateway 1 4315
Protoss_Assimilator 1 4673
Protoss_Cybernetics_Core 1 5979
Protoss_Dragoon 5 12369
Protoss_Nexus 1 12469
Singularity_Charge 1 10106
Protoss_Robotics_Facility 1 12512
12512
