Protoss_Gateway 2 11721
Protoss_Assimilator 1 4912
Protoss_Zealot 1 5461
Protoss_Cybernetics_Core 1 6409
Protoss_Dragoon 3 10661
Protoss_Robotics_Facility 1 10915
Singularity_Charge 1 10531
Protoss_Observatory 1 11672
11721
