Protoss_Gateway 2 10388
Protoss_Assimilator 1 4952
Protoss_Cybernetics_Core 1 6255
Protoss_Dragoon 5 12110
Protoss_Robotics_Facility 1 10331
Protoss_Shuttle 1 11740
Singularity_Charge 1 10326
Protoss_Observatory 1 11142
12110
