Protoss_Gateway 3 11133
Protoss_Assimilator 1 4593
Protoss_Cybernetics_Core 1 5989
Protoss_Dragoon 4 11100
Protoss_Robotics_Facility 1 10025
Protoss_Observatory 1 10874
Protoss_Zealot 3 12339
Protoss_Observer 1 12149
12339
