Protoss_Gateway 2 12141
Protoss_Assimilator 1 4564
Protoss_Cybernetics_Core 1 6065
Protoss_Dragoon 5 12044
Protoss_Robotics_Facility 1 8827
Protoss_Observatory 1 9711
Protoss_Observer 2 11995
12141
