Protoss_Gateway 2 8427
Protoss_Assimilator 1 4366
Protoss_Cybernetics_Core 1 5873
Protoss_Robotics_Facility 1 7803
Protoss_Dragoon 7 11591
Protoss_Observatory 1 8568
Protoss_Observer 2 11871
Protoss_Shuttle 1 11028
11871
