Protoss_Gateway 1 4302
Protoss_Assimilator 1 4609
Protoss_Cybernetics_Core 1 5891
Protoss_Dragoon 1 7156
Protoss_Robotics_Facility 1 8707
Protoss_Shuttle 1 10277
Protoss_Robotics_Support_Bay 1 9843
Protoss_Reaver 1 11905
11905
