Protoss_Gateway 2 10653
Protoss_Assimilator 1 4518
Protoss_Cybernetics_Core 1 5846
Protoss_Dragoon 6 12131
Protoss_Robotics_Facility 1 10308
Singularity_Charge 1 10040
Protoss_Observatory 1 11044
Protoss_Observer 1 12149
12149
