Protoss_Gateway 2 11465
Protoss_Assimilator 1 4653
Protoss_Cybernetics_Core 1 6065
Protoss_Dragoon 4 11622
Protoss_Robotics_Facility 1 8859
Protoss_Observatory 1 9664
Protoss_Observer 2 11680
11680
