Protoss_Gateway 2 9646
Protoss_Assimilator 1 4659
Protoss_Zealot 4 11792
Protoss_Cybernetics_Core 1 6159
Protoss_Dragoon 4 10930
Protoss_Robotics_Facility 1 8940
Protoss_Observatory 1 9636
Protoss_Observer 1 10659
Protoss_Shuttle 1 12377
12377
