Protoss_Assimilator 1 3561
Protoss_Gateway 1 4771
Protoss_Cybernetics_Core 1 6216
Protoss_Robotics_Facility 1 8212
Protoss_Dragoon 4 12050
Protoss_Shuttle 1 9640
Protoss_Observatory 1 9389
Protoss_Observer 2 11364
12050
