Protoss_Gateway 1 4507
Protoss_Assimilator 1 4729
Protoss_Cybernetics_Core 1 6406
Protoss_Dragoon 4 11176
Protoss_Robotics_Facility 1 8872
Protoss_Shuttle 1 10334
Protoss_Observatory 1 9917
Protoss_Observer 2 12058
Protoss_Robotics_Support_Bay 1 11135
Protoss_Reaver 1 13057
13057
