Protoss_Gateway 1 4422
Protoss_Assimilator 1 4508
Protoss_Cybernetics_Core 1 5906
Protoss_Dragoon 5 11969
Protoss_Robotics_Facility 1 8615
Protoss_Shuttle 1 10416
Protoss_Observatory 1 9985
11969
