Protoss_Gateway 2 7748
Protoss_Assimilator 1 4644
Protoss_Cybernetics_Core 1 5853
Protoss_Zealot 1 6456
Protoss_Dragoon 3 8971
Protoss_Citadel_of_Adun 1 10409
Protoss_Robotics_Facility 1 11853
Protoss_Templar_Archives 1 12012
12012
