Protoss_Gateway 2 9102
Protoss_Assimilator 1 4502
Protoss_Cybernetics_Core 1 6270
Protoss_Dragoon 5 11893
Protoss_Robotics_Facility 1 9086
Protoss_Observatory 1 9890
Protoss_Observer 2 11815
11893
