Protoss_Gateway 2 10015
Protoss_Assimilator 1 4537
Protoss_Cybernetics_Core 1 6055
Protoss_Dragoon 4 11214
Protoss_Robotics_Facility 1 8934
Protoss_Observatory 1 10097
Protoss_Observer 1 11338
11338
