Protoss_Assimilator 1 3727
Protoss_Gateway 1 4934
Protoss_Cybernetics_Core 1 6460
Protoss_Zealot 4 9850
Protoss_Robotics_Facility 1 8451
Protoss_Shuttle 1 9867
Protoss_Citadel_of_Adun 1 10774
Protoss_Observatory 1 10165
Protoss_Observer 2 12276
Protoss_Dragoon 1 11744
Protoss_Templar_Archives 1 12355
Protoss_Forge 1 11916
12355
