Protoss_Gateway 2 11328
Protoss_Assimilator 3 6459
Protoss_Zealot 2 6961
Protoss_Cybernetics_Core 1 8677
Protoss_Citadel_of_Adun 1 10192
Protoss_Dragoon 1 10236
Protoss_Templar_Archives 1 12182
12182
