Protoss_Gateway 1 4470
Protoss_Assimilator 1 4742
Protoss_Cybernetics_Core 1 6292
Protoss_Dragoon 2 9227
Protoss_Robotics_Facility 1 9004
Protoss_Shuttle 1 10584
Protoss_Zealot 2 11571
Protoss_Robotics_Support_Bay 1 10662
Protoss_Reaver 1 12439
Protoss_Observatory 1 12050
12439
