Protoss_Gateway 1 4242
Protoss_Assimilator 1 4379
Protoss_Cybernetics_Core 1 5783
Protoss_Robotics_Facility 1 8079
Protoss_Dragoon 3 11109
Protoss_Shuttle 2 11311
Protoss_Observatory 1 9553
Protoss_Nexus 1 13132
Protoss_Observer 1 12327
13132
