Protoss_Gateway 2 11973
Protoss_Assimilator 1 4659
Protoss_Cybernetics_Core 1 5960
Protoss_Zealot 1 6595
Protoss_Dragoon 5 12326
Protoss_Robotics_Facility 1 10353
Singularity_Charge 1 10143
Protoss_Observatory 1 11205
12326
