Protoss_Gateway 1 4332
Protoss_Assimilator 1 4533
Protoss_Cybernetics_Core 1 5948
Protoss_Dragoon 4 12095
Protoss_Robotics_Facility 1 9175
Protoss_Shuttle 1 10621
Protoss_Robotics_Support_Bay 1 10055
Protoss_Observatory 1 10165
Protoss_Reaver 1 12179
12179
