Protoss_Gateway 1 4258
Protoss_Assimilator 1 4352
Protoss_Cybernetics_Core 1 5824
Protoss_Zealot 2 9178
Protoss_Robotics_Facility 1 7917
Protoss_Dragoon 3 12153
Protoss_Shuttle 1 9355
Protoss_Robotics_Support_Bay 1 10485
Protoss_Reaver 1 12615
12615
