Protoss_Gateway 1 4488
Protoss_Assimilator 1 4404
Protoss_Cybernetics_Core 1 6163
Protoss_Robotics_Facility 1 8672
Protoss_Dragoon 3 11729
Protoss_Robotics_Support_Bay 1 9480
Protoss_Reaver 1 11232
Protoss_Shuttle 1 12533
12533
