Protoss_Gateway 3 12538
Protoss_Assimilator 1 4360
Protoss_Cybernetics_Core 1 5569
Protoss_Dragoon 4 12197
Protoss_Robotics_Facility 1 8312
Protoss_Shuttle 1 9845
Protoss_Observatory 1 9824
Protoss_Observer 1 10846
12538
