Protoss_Gateway 1 4199
Protoss_Assimilator 1 4599
Protoss_Zealot 4 8477
Protoss_Cybernetics_Core 1 7809
Protoss_Dragoon 3 12336
Protoss_Robotics_Facility 1 10508
Protoss_Shuttle 1 11923
Protoss_Robotics_Support_Bay 1 11700
12336
