Protoss_Gateway 1 4277
Protoss_Assimilator 1 4567
Protoss_Cybernetics_Core 1 6043
Protoss_Dragoon 5 12271
Protoss_Robotics_Facility 1 8605
Protoss_Shuttle 1 10028
Protoss_Robotics_Support_Bay 1 9835
Protoss_Reaver 1 11898
12271
