Protoss_Gateway 1 4492
Protoss_Assimilator 1 4583
Protoss_Cybernetics_Core 1 5948
Protoss_Zealot 1 5695
Protoss_Dragoon 5 12153
Protoss_Robotics_Facility 1 10470
Singularity_Charge 1 10121
Protoss_Shuttle 1 11887
Protoss_Robotics_Support_Bay 1 11321
12153
