Protoss_Gateway 2 9882
Protoss_Assimilator 1 4719
Protoss_Cybernetics_Core 1 6112
Protoss_Dragoon 2 8627
Protoss_Citadel_of_Adun 1 8524
Protoss_Templar_Archives 1 10294
Protoss_Dark_Templar 2 11583
Protoss_Robotics_Facility 1 12889
12889
