Protoss_Gateway 1 4550
Protoss_Assimilator 1 4315
Protoss_Cybernetics_Core 1 6039
Protoss_Dragoon 3 12592
Protoss_Robotics_Facility 1 8411
Protoss_Zealot 2 9222
Protoss_Shuttle 1 9830
Protoss_Robotics_Support_Bay 1 9382
Protoss_Reaver 2 12928
12928
