Protoss_Assimilator 1 3705
Protoss_Gateway 2 12127
Protoss_Cybernetics_Core 1 6792
Protoss_Dragoon 2 9891
Protoss_Robotics_Facility 1 9232
Protoss_Citadel_of_Adun 1 10068
Protoss_Shuttle 1 10714
Protoss_Templar_Archives 1 11769
12127
