Protoss_Gateway 1 4445
Protoss_Assimilator 1 4469
Protoss_Cybernetics_Core 1 6014
Protoss_Dragoon 4 11810
Protoss_Robotics_Facility 1 9799
Protoss_Observatory 1 10765
Protoss_Shuttle 1 11784
11810
