Protoss_Gateway 2 12649
Protoss_Assimilator 1 4631
Protoss_Cybernetics_Core 1 5721
Protoss_Robotics_Facility 1 8414
Protoss_Forge 1 7890
Protoss_Dragoon 4 12310
Protoss_Shuttle 1 9845
Protoss_Observatory 1 9275
Protoss_Observer 2 11688
Protoss_Photon_Cannon 1 12566
12649
