Protoss_Gateway 1 4375
Protoss_Assimilator 1 4717
Protoss_Cybernetics_Core 1 6194
Protoss_Dragoon 5 11836
Protoss_Robotics_Facility 1 9753
Protoss_Observatory 1 10487
Protoss_Observer 1 11995
11995
