Protoss_Gateway 3 12454
Protoss_Assimilator 1 4169
Protoss_Cybernetics_Core 1 5648
Protoss_Robotics_Facility 1 7706
Protoss_Citadel_of_Adun 1 7946
Protoss_Shuttle 1 9121
Protoss_Templar_Archives 1 9482
Protoss_Dark_Templar 3 12117
Protoss_Dragoon 1 12102
12454
