Protoss_Gateway 2 11189
Protoss_Assimilator 1 4441
Protoss_Cybernetics_Core 1 5838
Protoss_Zealot 1 5859
Protoss_Dragoon 4 11299
Protoss_Robotics_Facility 1 9042
Protoss_Observatory 1 9841
Protoss_Observer 1 10984
Protoss_Nexus 1 14258
14258
