Protoss_Gateway 1 4338
Protoss_Assimilator 1 4483
Protoss_Cybernetics_Core 1 5977
Protoss_Zealot 1 5841
Protoss_Dragoon 5 12175
Protoss_Robotics_Facility 1 10353
Singularity_Charge 1 10172
Protoss_Shuttle 1 12135
Protoss_Observatory 1 12013
12175
