Protoss_Gateway 2 10265
Protoss_Assimilator 1 4761
Protoss_Cybernetics_Core 1 6415
Protoss_Citadel_of_Adun 1 8102
Protoss_Dragoon 1 8078
Protoss_Templar_Archives 1 9961
Protoss_Dark_Templar 4 12595
12595
