Protoss_Gateway 2 8512
Protoss_Assimilator 1 4605
Protoss_Cybernetics_Core 1 5882
Protoss_Dragoon 5 11217
Protoss_Citadel_of_Adun 1 10141
Singularity_Charge 1 10084
Protoss_Templar_Archives 1 11911
11911
