Protoss_Gateway 1 4275
Protoss_Assimilator 1 4388
Protoss_Cybernetics_Core 1 5911
Protoss_Dragoon 2 7690
Protoss_Robotics_Facility 1 8187
Protoss_Shuttle 1 9589
Protoss_Robotics_Support_Bay 1 9345
Protoss_Reaver 2 12888
Protoss_Zealot 1 11000
12888
