Protoss_Gateway 1 4388
Protoss_Assimilator 1 4608
Protoss_Cybernetics_Core 1 6072
Protoss_Dragoon 5 12424
Protoss_Robotics_Facility 1 10685
Singularity_Charge 1 10348
Protoss_Nexus 1 13705
Protoss_Observatory 1 11691
13705
