Protoss_Gateway 2 8319
Protoss_Assimilator 1 4695
Protoss_Cybernetics_Core 1 6160
Protoss_Dragoon 7 12581
Protoss_Robotics_Facility 1 10763
Protoss_Observatory 1 11556
Singularity_Charge 1 11299
12581
