Protoss_Gateway 2 8963
Protoss_Assimilator 1 4652
Protoss_Cybernetics_Core 1 6285
Protoss_Dragoon 5 11751
Protoss_Robotics_Facility 1 8782
Protoss_Observatory 1 9554
Protoss_Observer 2 12046
12046
