Protoss_Gateway 2 10669
Protoss_Assimilator 1 4261
Protoss_Cybernetics_Core 1 5816
Protoss_Dragoon 6 11934
Protoss_Robotics_Facility 1 10362
Singularity_Charge 1 10062
Protoss_Observatory 1 11151
11934
