Protoss_Gateway 2 9519
Protoss_Assimilator 1 4565
Protoss_Cybernetics_Core 1 6039
Protoss_Dragoon 5 12036
Protoss_Robotics_Facility 1 8524
Protoss_Observatory 1 9336
Protoss_Observer 1 10363
Protoss_Citadel_of_Adun 1 12646
12646
