Protoss_Gateway 1 4376
Protoss_Assimilator 1 4549
Protoss_Cybernetics_Core 1 5888
Protoss_Dragoon 3 11758
Protoss_Robotics_Facility 1 9051
Protoss_Shuttle 1 10474
Protoss_Robotics_Support_Bay 1 9863
Protoss_Observatory 1 10254
Protoss_Reaver 1 12032
Protoss_Citadel_of_Adun 1 12806
12806
