Protoss_Gateway 2 11175
Protoss_Assimilator 1 4524
Protoss_Cybernetics_Core 1 5970
Protoss_Dragoon 6 12600
Protoss_Robotics_Facility 1 10785
Singularity_Charge 1 10348
Protoss_Observatory 1 12104
12600
