Protoss_Gateway 1 4170
Protoss_Assimilator 1 4385
Protoss_Cybernetics_Core 1 5736
Protoss_Dragoon 5 11685
Protoss_Robotics_Facility 1 10500
Singularity_Charge 1 10019
Protoss_Citadel_of_Adun 1 12100
Protoss_Observatory 1 11627
12100
