Protoss_Gateway 1 4302
Protoss_Assimilator 1 4469
Protoss_Cybernetics_Core 1 5889
Protoss_Dragoon 5 11978
Protoss_Robotics_Facility 1 8667
Protoss_Observatory 1 9408
Protoss_Observer 2 11827
Protoss_Nexus 1 13357
13357
