Protoss_Gateway 2 5607
Protoss_Assimilator 2 6413
Protoss_Zealot 2 7527
Protoss_Cybernetics_Core 1 7713
Protoss_Dragoon 5 11073
Protoss_Robotics_Facility 1 10321
Protoss_Shuttle 1 11882
Protoss_Robotics_Support_Bay 1 11672
11882
