Protoss_Gateway 1 4234
Protoss_Assimilator 1 4442
Protoss_Cybernetics_Core 1 6062
Protoss_Dragoon 4 11897
Protoss_Robotics_Facility 1 8802
Protoss_Shuttle 1 10248
Protoss_Observatory 1 10274
Protoss_Nexus 1 13948
13948
