Protoss_Gateway 2 12001
Protoss_Assimilator 1 4482
Protoss_Cybernetics_Core 1 5502
Protoss_Dragoon 5 11400
Protoss_Robotics_Facility 1 10548
Singularity_Charge 1 9733
Protoss_Zealot 1 11600
Protoss_Shuttle 1 12091
Protoss_Robotics_Support_Bay 1 11941
12091
