Protoss_Gateway 2 12662
Protoss_Assimilator 1 4638
Protoss_Cybernetics_Core 1 6080
Protoss_Dragoon 5 11814
Protoss_Robotics_Facility 1 10639
Singularity_Charge 1 10458
Protoss_Shuttle 1 12450
12662
