Protoss_Gateway 1 4381
Protoss_Assimilator 4 6310
Protoss_Cybernetics_Core 1 6324
Protoss_Dragoon 3 10792
Protoss_Robotics_Facility 1 10352
Protoss_Shuttle 1 11955
Protoss_Robotics_Support_Bay 1 11799
11955
