Protoss_Gateway 1 4215
Protoss_Assimilator 1 4300
Protoss_Cybernetics_Core 1 5963
Protoss_Dragoon 3 9695
Protoss_Robotics_Facility 1 8653
Protoss_Observatory 1 9606
Protoss_Citadel_of_Adun 1 10366
Protoss_Observer 2 12141
Protoss_Nexus 1 13664
Protoss_Templar_Archives 1 12350
13664
