Protoss_Gateway 2 12440
Protoss_Assimilator 1 5070
Protoss_Cybernetics_Core 1 6064
Protoss_Zealot 1 5812
Protoss_Dragoon 5 12079
Protoss_Robotics_Facility 1 11479
Singularity_Charge 1 10355
12440
