Protoss_Gateway 2 11748
Protoss_Assimilator 1 4530
Protoss_Cybernetics_Core 1 5856
Protoss_Dragoon 5 12572
Protoss_Robotics_Facility 1 10153
Protoss_Observatory 1 10851
Singularity_Charge 1 10234
Protoss_Observer 1 12093
12572
