Protoss_Gateway 2 10125
Protoss_Assimilator 1 4729
Protoss_Cybernetics_Core 1 6292
Protoss_Robotics_Facility 1 8345
Protoss_Dragoon 5 12016
Protoss_Observatory 1 9088
Protoss_Observer 1 10202
Protoss_Shuttle 1 11718
12016
