Protoss_Gateway 1 4363
Protoss_Assimilator 1 4603
Protoss_Cybernetics_Core 1 5948
Protoss_Dragoon 5 11688
Protoss_Robotics_Facility 1 11223
Singularity_Charge 1 10143
Protoss_Shuttle 1 12809
12809
