Protoss_Gateway 1 4438
Protoss_Assimilator 2 5112
Protoss_Cybernetics_Core 1 6629
Protoss_Robotics_Facility 1 8846
Protoss_Dragoon 1 8678
Protoss_Shuttle 1 10277
Protoss_Robotics_Support_Bay 1 9945
Protoss_Reaver 1 11934
Protoss_Zealot 1 11688
11934
