Protoss_Gateway 2 12143
Protoss_Assimilator 1 4416
Protoss_Cybernetics_Core 1 5933
Protoss_Dragoon 5 11659
Protoss_Robotics_Facility 1 10596
Singularity_Charge 1 10384
Protoss_Observatory 1 11368
12143
