Protoss_Gateway 2 11285
Protoss_Assimilator 1 4659
Protoss_Cybernetics_Core 1 6021
Protoss_Robotics_Facility 1 8283
Protoss_Dragoon 3 11217
Protoss_Observatory 1 9083
Protoss_Observer 2 11607
11607
