Protoss_Gateway 3 11729
Protoss_Assimilator 1 4425
Protoss_Cybernetics_Core 1 6036
Protoss_Dragoon 4 11546
Protoss_Robotics_Facility 1 8214
Protoss_Shuttle 1 9618
Protoss_Observatory 1 9162
Protoss_Observer 2 11666
11729
