Protoss_Gateway 2 12830
Protoss_Assimilator 1 4637
Protoss_Cybernetics_Core 1 6402
Protoss_Dragoon 3 10741
Protoss_Robotics_Facility 1 9900
Protoss_Nexus 1 12434
Protoss_Robotics_Support_Bay 1 10686
Protoss_Observatory 1 10955
Protoss_Observer 1 12288
12830
