Protoss_Gateway 2 10751
Protoss_Assimilator 1 4571
Protoss_Cybernetics_Core 1 6052
Protoss_Dragoon 1 7302
Protoss_Robotics_Facility 1 8877
Protoss_Citadel_of_Adun 1 9255
Protoss_Observatory 1 9661
Protoss_Templar_Archives 1 10903
Protoss_Observer 1 10934
Protoss_Shuttle 1 12292
Protoss_Dark_Templar 2 12388
12388
