Protoss_Gateway 2 11345
Protoss_Assimilator 1 4498
Protoss_Cybernetics_Core 1 6024
Protoss_Dragoon 5 11748
Protoss_Nexus 1 12830
Singularity_Charge 1 10040
Protoss_Robotics_Facility 1 13126
13126
