Protoss_Gateway 3 12768
Protoss_Assimilator 1 4483
Protoss_Cybernetics_Core 1 6080
Protoss_Dragoon 3 11510
Protoss_Robotics_Facility 1 9614
Protoss_Nexus 1 13104
Protoss_Observatory 1 11215
13104
