Protoss_Gateway 2 12087
Protoss_Assimilator 1 4830
Protoss_Cybernetics_Core 1 6444
Protoss_Robotics_Facility 1 8433
Protoss_Dragoon 2 10763
Protoss_Shuttle 1 9882
Protoss_Citadel_of_Adun 1 10391
Protoss_Templar_Archives 1 11873
12087
