Protoss_Gateway 2 10659
Protoss_Assimilator 1 4587
Protoss_Cybernetics_Core 1 6062
Protoss_Dragoon 5 12061
Protoss_Robotics_Facility 1 9352
Protoss_Observatory 1 10874
Protoss_Observer 1 12192
12192
