Protoss_Gateway 2 9295
Protoss_Assimilator 1 4684
Protoss_Cybernetics_Core 1 6045
Protoss_Dragoon 6 11886
Protoss_Robotics_Facility 1 11021
Singularity_Charge 1 9814
Protoss_Observatory 1 11900
11900
