Protoss_Gateway 1 4283
Protoss_Assimilator 1 4271
Protoss_Cybernetics_Core 1 6113
Protoss_Dragoon 4 11444
Protoss_Stargate 1 9880
Protoss_Fleet_Beacon 1 11408
Singularity_Charge 1 10150
11444
