Protoss_Gateway 2 11876
Protoss_Assimilator 1 4637
Protoss_Cybernetics_Core 1 6024
Protoss_Dragoon 4 11912
Protoss_Robotics_Facility 1 9131
Protoss_Observatory 1 9979
Protoss_Observer 2 11954
11954
