Protoss_Gateway 3 11935
Protoss_Assimilator 1 4571
Protoss_Cybernetics_Core 1 6189
Protoss_Dragoon 4 12295
Protoss_Nexus 1 11305
Protoss_Robotics_Facility 1 10955
Protoss_Observatory 1 11894
12295
