Protoss_Gateway 2 10703
Protoss_Assimilator 1 4821
Protoss_Cybernetics_Core 1 6841
Protoss_Dragoon 3 11473
Protoss_Robotics_Facility 1 9727
Protoss_Citadel_of_Adun 1 9646
Protoss_Observatory 1 10485
Protoss_Templar_Archives 1 11421
Protoss_Observer 1 11607
Protoss_Zealot 1 11841
11841
