Protoss_Gateway 1 4313
Protoss_Assimilator 1 4556
Protoss_Cybernetics_Core 1 5868
Protoss_Dragoon 5 11536
Protoss_Stargate 1 10273
Protoss_Fleet_Beacon 1 11887
Singularity_Charge 1 10458
11887
