Protoss_Gateway 1 4353
Protoss_Assimilator 1 4701
Protoss_Cybernetics_Core 1 6109
Protoss_Robotics_Facility 1 8569
Protoss_Dragoon 4 12029
Protoss_Shuttle 1 9999
Protoss_Robotics_Support_Bay 1 9616
Protoss_Reaver 1 12132
12132
