Protoss_Gateway 2 9987
Protoss_Assimilator 1 4477
Protoss_Cybernetics_Core 1 5748
Protoss_Dragoon 6 12303
Protoss_Robotics_Facility 1 8738
Protoss_Observatory 1 9603
Protoss_Observer 1 10649
Singularity_Charge 1 11138
12303
