Protoss_Gateway 1 4215
Protoss_Assimilator 1 4300
Protoss_Cybernetics_Core 1 5783
Protoss_Dragoon 5 12417
Protoss_Robotics_Facility 1 10192
Protoss_Observatory 1 11033
Singularity_Charge 1 10326
Protoss_Nexus 1 13698
Protoss_Observer 1 12083
13698
