Protoss_Gateway 2 10302
Protoss_Assimilator 1 4609
Protoss_Cybernetics_Core 1 6138
Protoss_Dragoon 6 12551
Protoss_Robotics_Facility 1 10124
Protoss_Observatory 1 10845
Singularity_Charge 1 10194
12551
