Protoss_Gateway 1 4419
Protoss_Assimilator 1 4644
Protoss_Cybernetics_Core 1 5906
Protoss_Dragoon 4 11444
Protoss_Robotics_Facility 1 8647
Protoss_Observatory 1 9407
Protoss_Observer 2 11819
Protoss_Robotics_Support_Bay 1 11988
11988
