Protoss_Gateway 2 10553
Protoss_Assimilator 1 4578
Protoss_Cybernetics_Core 1 6109
Protoss_Dragoon 2 8447
Protoss_Citadel_of_Adun 1 9406
Protoss_Robotics_Facility 1 10741
Protoss_Templar_Archives 1 10902
Protoss_Dark_Templar 1 12373
Protoss_Observatory 1 12054
12373
