Protoss_Gateway 3 12770
Protoss_Assimilator 1 4546
Protoss_Cybernetics_Core 1 5914
Protoss_Dragoon 4 11725
Protoss_Robotics_Facility 1 8606
Protoss_Shuttle 1 10013
Protoss_Observatory 1 9617
Protoss_Observer 2 11941
Singularity_Charge 1 11182
12770
