Protoss_Gateway 2 12247
Protoss_Assimilator 1 4527
Protoss_Cybernetics_Core 1 5829
Protoss_Dragoon 5 12212
Protoss_Robotics_Facility 1 8495
Protoss_Observatory 1 9276
Protoss_Nexus 1 12052
Protoss_Observer 2 11402
12247
