Protoss_Gateway 2 9573
Protoss_Assimilator 1 4856
Protoss_Cybernetics_Core 1 6491
Protoss_Dragoon 3 12022
Protoss_Robotics_Facility 1 9172
Protoss_Observatory 1 10059
Protoss_Observer 2 12105
12105
