Protoss_Gateway 3 12075
Protoss_Assimilator 1 4575
Protoss_Cybernetics_Core 1 6067
Protoss_Dragoon 6 12205
Protoss_Robotics_Facility 1 11000
Singularity_Charge 1 10150
Protoss_Observatory 1 11934
12205
