Protoss_Nexus 1 7044
Protoss_Gateway 3 9475
Protoss_Assimilator 2 12337
Protoss_Cybernetics_Core 1 7959
Protoss_Zealot 1 8285
Protoss_Dragoon 5 12066
Protoss_Robotics_Facility 1 12496
12496
