Protoss_Gateway 1 4461
Protoss_Assimilator 1 4564
Protoss_Cybernetics_Core 1 6326
Protoss_Robotics_Facility 1 8875
Protoss_Zealot 1 8461
Protoss_Robotics_Support_Bay 1 10645
Protoss_Dragoon 1 12307
12307
