Protoss_Assimilator 1 3497
Protoss_Gateway 1 4697
Protoss_Cybernetics_Core 1 6153
Protoss_Robotics_Facility 1 8136
Protoss_Dragoon 4 12044
Protoss_Shuttle 1 9545
Protoss_Observatory 1 10984
Protoss_Observer 1 12163
12163
