Protoss_Gateway 1 4577
Protoss_Assimilator 1 4474
Protoss_Cybernetics_Core 1 6058
Protoss_Dragoon 4 11984
Protoss_Robotics_Facility 1 8754
Protoss_Shuttle 1 10167
Protoss_Observatory 1 10260
Protoss_Observer 1 11446
Protoss_Nexus 1 13937
13937
