Protoss_Gateway 2 8600
Protoss_Assimilator 1 4286
Protoss_Cybernetics_Core 1 5619
Protoss_Dragoon 1 6944
Protoss_Citadel_of_Adun 1 8003
Protoss_Templar_Archives 1 9576
Protoss_Dark_Templar 4 11900
11900
