Protoss_Gateway 2 6759
Protoss_Assimilator 1 4625
Protoss_Cybernetics_Core 1 5900
Protoss_Dragoon 6 12088
Protoss_Zealot 2 10322
Protoss_Robotics_Facility 1 12219
Singularity_Charge 1 10750
12219
