Protoss_Gateway 1 4463
Protoss_Assimilator 1 4472
Protoss_Cybernetics_Core 1 6118
Protoss_Dragoon 2 10427
Protoss_Robotics_Facility 1 8641
Protoss_Shuttle 1 10335
Protoss_Robotics_Support_Bay 1 10829
Protoss_Citadel_of_Adun 1 12050
Protoss_Reaver 1 12725
12725
