Protoss_Gateway 2 9585
Protoss_Assimilator 1 4602
Protoss_Cybernetics_Core 1 6058
Protoss_Dragoon 7 12130
Protoss_Robotics_Facility 1 11060
Singularity_Charge 1 10033
Protoss_Observatory 1 12110
12130
