Protoss_Gateway 3 11562
Protoss_Assimilator 1 4700
Protoss_Cybernetics_Core 1 6072
Protoss_Dragoon 6 12161
Protoss_Robotics_Facility 1 9436
Protoss_Observatory 1 10425
Protoss_Observer 1 11468
12161
