Protoss_Gateway 1 4362
Protoss_Assimilator 2 4924
Protoss_Zealot 2 6975
Protoss_Cybernetics_Core 1 7293
Protoss_Dragoon 4 12571
Protoss_Robotics_Facility 1 9449
Protoss_Shuttle 1 10862
Protoss_Robotics_Support_Bay 1 10779
Protoss_Reaver 1 12973
12973
