Protoss_Gateway 2 9898
Protoss_Assimilator 1 4578
Protoss_Cybernetics_Core 1 5963
Protoss_Dragoon 5 12117
Protoss_Robotics_Facility 1 8612
Protoss_Observatory 1 9704
Protoss_Observer 1 10971
12117
