Protoss_Gateway 2 9579
Protoss_Assimilator 1 4457
Protoss_Cybernetics_Core 1 6127
Protoss_Dragoon 7 12503
Protoss_Robotics_Facility 1 9651
Protoss_Observatory 1 10460
Protoss_Observer 1 11753
12503
