Protoss_Gateway 2 10501
Protoss_Assimilator 1 4641
Protoss_Cybernetics_Core 1 5999
Protoss_Dragoon 5 12029
Protoss_Robotics_Facility 1 8783
Protoss_Observatory 1 9604
Protoss_Observer 2 11632
12029
