Protoss_Gateway 2 10458
Protoss_Assimilator 1 4769
Protoss_Cybernetics_Core 1 6108
Protoss_Dragoon 5 11861
Protoss_Robotics_Facility 1 9044
Protoss_Observatory 1 9897
Protoss_Observer 2 12027
12027
