Protoss_Gateway 1 4419
Protoss_Assimilator 1 4710
Protoss_Cybernetics_Core 1 6087
Protoss_Dragoon 3 11875
Protoss_Robotics_Facility 1 8814
Protoss_Shuttle 1 10343
Protoss_Robotics_Support_Bay 1 10330
Protoss_Reaver 1 12066
12066
