Protoss_Gateway 3 11628
Protoss_Assimilator 1 4477
Protoss_Cybernetics_Core 1 5887
Protoss_Dragoon 6 11916
Protoss_Robotics_Facility 1 10342
Singularity_Charge 1 9932
Protoss_Observatory 1 11101
Protoss_Observer 1 12233
12233
