Protoss_Gateway 1 4287
Protoss_Assimilator 1 4392
Protoss_Cybernetics_Core 1 5979
Protoss_Dragoon 5 11827
Protoss_Robotics_Facility 1 9990
Protoss_Nexus 1 12141
Protoss_Observatory 1 10822
Protoss_Observer 1 12017
12141
