Protoss_Gateway 2 11417
Protoss_Assimilator 1 4600
Protoss_Cybernetics_Core 1 6039
Protoss_Robotics_Facility 1 8246
Protoss_Dragoon 4 12073
Protoss_Observatory 1 9304
Protoss_Observer 1 10356
Protoss_Shuttle 1 11714
12073
