Protoss_Gateway 2 10689
Protoss_Assimilator 1 4205
Protoss_Cybernetics_Core 1 5647
Protoss_Robotics_Facility 1 7719
Protoss_Zealot 1 7532
Protoss_Dragoon 5 12000
Protoss_Observatory 1 8435
Protoss_Observer 1 9712
Protoss_Shuttle 1 11964
12000
