Protoss_Gateway 2 12312
Protoss_Assimilator 1 4558
Protoss_Cybernetics_Core 1 6001
Protoss_Zealot 1 5717
Protoss_Dragoon 5 11812
Singularity_Charge 1 9997
Protoss_Robotics_Facility 1 11978
12312
