Protoss_Gateway 3 11351
Protoss_Assimilator 1 4338
Protoss_Zealot 1 5278
Protoss_Cybernetics_Core 1 6427
Protoss_Robotics_Facility 1 8678
Protoss_Dragoon 3 12505
Protoss_Observatory 1 9563
Protoss_Observer 2 11834
Protoss_Nexus 1 14005
14005
