Protoss_Gateway 3 10574
Protoss_Assimilator 1 4635
Protoss_Zealot 1 5271
Protoss_Cybernetics_Core 1 6907
Protoss_Dragoon 4 11817
Protoss_Robotics_Facility 1 9281
Protoss_Observatory 1 10007
Protoss_Shuttle 1 11177
11817
