Protoss_Assimilator 1 3506
Protoss_Gateway 2 10878
Protoss_Cybernetics_Core 1 6175
Protoss_Dragoon 4 11114
Protoss_Robotics_Facility 1 8679
Protoss_Observatory 1 9448
Protoss_Citadel_of_Adun 1 10274
Protoss_Observer 2 11369
Protoss_Templar_Archives 1 11888
Protoss_Zealot 1 11951
11951
