Protoss_Assimilator 2 5317
Protoss_Gateway 1 5026
Protoss_Zealot 2 7488
Protoss_Cybernetics_Core 1 7470
Protoss_Dragoon 1 8692
Protoss_Citadel_of_Adun 1 10229
Protoss_Nexus 1 12549
Protoss_Templar_Archives 1 11758
Protoss_Robotics_Facility 1 12886
12886
