Protoss_Gateway 2 9588
Protoss_Assimilator 1 4596
Protoss_Cybernetics_Core 1 5892
Protoss_Zealot 1 5636
Protoss_Dragoon 5 12139
Protoss_Robotics_Facility 1 11631
Singularity_Charge 1 10114
12139
