Protoss_Gateway 2 11393
Protoss_Assimilator 4 6212
Protoss_Cybernetics_Core 1 6475
Protoss_Dragoon 3 10184
Protoss_Citadel_of_Adun 1 9779
Protoss_Robotics_Facility 1 11490
Protoss_Zealot 1 11212
Singularity_Charge 1 10509
Protoss_Templar_Archives 1 12416
12416
