Protoss_Gateway 1 4306
Protoss_Assimilator 1 4663
Protoss_Zealot 2 6983
Protoss_Cybernetics_Core 1 7082
Protoss_Dragoon 3 11144
Protoss_Robotics_Facility 1 9930
Protoss_Shuttle 1 11704
Protoss_Robotics_Support_Bay 1 11283
11704
