Protoss_Gateway 1 4533
Protoss_Assimilator 1 4637
Protoss_Cybernetics_Core 1 6058
Protoss_Robotics_Facility 1 8246
Protoss_Shuttle 1 9655
Protoss_Observatory 1 8979
Protoss_Dragoon 3 12076
Protoss_Observer 2 11710
Protoss_Nexus 1 13778
13778
