Protoss_Gateway 2 10161
Protoss_Assimilator 1 4592
Protoss_Cybernetics_Core 1 6049
Protoss_Dragoon 6 11928
Protoss_Robotics_Facility 1 9935
Protoss_Observatory 1 10728
Protoss_Observer 1 11748
11928
