Protoss_Gateway 1 4350
Protoss_Assimilator 1 4915
Protoss_Zealot 5 12134
Protoss_Cybernetics_Core 1 7413
Protoss_Dragoon 2 9786
Protoss_Robotics_Facility 1 9791
Protoss_Shuttle 1 11206
Protoss_Robotics_Support_Bay 1 11022
Protoss_Reaver 1 12907
12907
