Protoss_Gateway 2 12721
Protoss_Assimilator 1 4783
Protoss_Cybernetics_Core 1 6131
Protoss_Dragoon 4 11632
Protoss_Robotics_Facility 1 9169
Protoss_Observatory 1 10078
Protoss_Observer 2 12012
12721
