Protoss_Gateway 1 4312
Protoss_Assimilator 1 4600
Protoss_Zealot 3 6771
Protoss_Cybernetics_Core 1 7010
Protoss_Dragoon 3 10598
Protoss_Robotics_Facility 1 9870
Protoss_Shuttle 1 11601
Protoss_Robotics_Support_Bay 1 11147
11601
