Protoss_Gateway 1 4439
Protoss_Assimilator 1 4793
Protoss_Cybernetics_Core 1 6321
Protoss_Dragoon 4 11226
Protoss_Nexus 1 12688
Singularity_Charge 1 10040
Protoss_Robotics_Facility 1 12929
12929
