Protoss_Gateway 1 4261
Protoss_Assimilator 1 4574
Protoss_Cybernetics_Core 1 5961
Protoss_Zealot 1 5651
Protoss_Dragoon 4 11531
Protoss_Robotics_Facility 1 9247
Protoss_Observatory 1 10225
Protoss_Observer 2 12181
12181
