Protoss_Gateway 2 10940
Protoss_Assimilator 1 4593
Protoss_Cybernetics_Core 1 5942
Protoss_Dragoon 1 7288
Protoss_Robotics_Facility 1 9199
Protoss_Citadel_of_Adun 1 9203
Protoss_Templar_Archives 1 10692
Protoss_Observatory 1 10605
Protoss_Observer 1 11636
Protoss_Dark_Templar 2 12271
12271
