Protoss_Gateway 2 5241
Protoss_Zealot 9 12017
Protoss_Assimilator 1 6296
Protoss_Cybernetics_Core 1 7834
Protoss_Dragoon 1 9044
Protoss_Stargate 1 10134
Protoss_Corsair 1 11197
Protoss_Forge 1 11794
12017
