Protoss_Forge 1 4466
Protoss_Photon_Cannon 4 12603
Protoss_Nexus 1 9000
Protoss_Gateway 1 8651
Protoss_Assimilator 1 9380
Protoss_Zealot 2 11336
Protoss_Cybernetics_Core 1 11049
Protoss_Citadel_of_Adun 1 12504
12603
