Protoss_Nexus 1 6868
Protoss_Forge 1 5464
Protoss_Photon_Cannon 1 6727
Protoss_Gateway 1 7668
Protoss_Assimilator 2 9617
Protoss_Zealot 3 10392
Protoss_Cybernetics_Core 1 9788
Protoss_Stargate 1 11494
Protoss_Dragoon 1 11512
Protoss_Robotics_Facility 1 12352
12352
