Protoss_Gateway 3 11990
Protoss_Assimilator 1 4196
Protoss_Cybernetics_Core 1 5689
Protoss_Stargate 1 7475
Protoss_Zealot 6 12119
Protoss_Dragoon 1 7345
Protoss_Corsair 2 9713
Protoss_Citadel_of_Adun 1 9487
12119
