Protoss_Forge 1 4110
Protoss_Photon_Cannon 2 6215
Protoss_Nexus 1 9388
Protoss_Gateway 1 8282
Protoss_Assimilator 1 8281
Protoss_Zealot 4 12312
Protoss_Cybernetics_Core 1 9885
12312
