Protoss_Forge 1 4337
Protoss_Photon_Cannon 2 11922
Protoss_Nexus 2 12396
Protoss_Gateway 1 7616
Protoss_Assimilator 2 11379
Protoss_Zealot 2 11512
Protoss_Cybernetics_Core 1 11069
Protoss_Stargate 1 13019
13019
