Protoss_Forge 1 3655
Protoss_Photon_Cannon 3 10031
Protoss_Nexus 1 9788
Protoss_Gateway 1 8550
Protoss_Assimilator 2 11484
Protoss_Cybernetics_Core 1 10022
Protoss_Dragoon 2 12429
Protoss_Stargate 1 11978
12429
