Protoss_Forge 1 4327
Protoss_Nexus 1 7896
Protoss_Gateway 1 7419
Protoss_Photon_Cannon 2 8030
Protoss_Assimilator 2 9855
Protoss_Zealot 2 10136
Protoss_Cybernetics_Core 1 9943
Protoss_Dragoon 1 11729
Protoss_Stargate 2 12613
12613
