Protoss_Gateway 1 4420
Protoss_Assimilator 1 4401
Protoss_Zealot 4 12046
Protoss_Cybernetics_Core 1 7473
Protoss_Stargate 1 10073
Protoss_Dragoon 1 10097
Protoss_Forge 1 10005
Protoss_Corsair 1 11044
Protoss_Nexus 1 13617
13617
