Protoss_Gateway 1 3886
Protoss_Zealot 3 7925
Protoss_Assimilator 1 6305
Protoss_Cybernetics_Core 1 7804
Protoss_Dragoon 1 9306
Protoss_Stargate 1 9899
Protoss_Robotics_Facility 1 11477
Protoss_Corsair 1 11189
11477
