Protoss_Forge 1 4656
Protoss_Photon_Cannon 2 7201
Protoss_Nexus 1 8545
Protoss_Gateway 1 7975
Protoss_Assimilator 2 11164
Protoss_Zealot 4 11815
Protoss_Cybernetics_Core 1 12810
12810
