Protoss_Nexus 1 6760
Protoss_Forge 1 5926
Protoss_Photon_Cannon 1 7269
Protoss_Gateway 4 12219
Protoss_Assimilator 2 10458
Protoss_Cybernetics_Core 1 9528
Protoss_Zealot 2 10229
Protoss_Citadel_of_Adun 1 11247
Protoss_Dragoon 1 12189
12219
