Protoss_Gateway 1 4041
Protoss_Zealot 3 6792
Protoss_Assimilator 1 5652
Protoss_Cybernetics_Core 1 7812
Protoss_Stargate 1 9498
Protoss_Forge 1 8879
Protoss_Photon_Cannon 3 12209
Protoss_Corsair 2 11633
Protoss_Robotics_Facility 1 11710
12209
