Protoss_Forge 1 4848
Protoss_Photon_Cannon 2 7093
Protoss_Nexus 1 8342
Protoss_Gateway 1 8001
Protoss_Assimilator 2 11619
Protoss_Zealot 3 10971
Protoss_Cybernetics_Core 1 10144
Protoss_Dragoon 1 11349
Protoss_Stargate 1 12247
12247
