Protoss_Nexus 1 7171
Protoss_Forge 1 5718
Protoss_Photon_Cannon 2 7115
Protoss_Gateway 3 12248
Protoss_Assimilator 2 10063
Protoss_Zealot 3 10852
Protoss_Cybernetics_Core 1 10119
Protoss_Citadel_of_Adun 1 11686
Protoss_Dragoon 1 11972
12248
