Protoss_Forge 1 4224
Protoss_Nexus 1 7795
Protoss_Photon_Cannon 2 7157
Protoss_Gateway 1 7867
Protoss_Assimilator 2 10714
Protoss_Cybernetics_Core 1 9563
Protoss_Zealot 2 12081
Protoss_Stargate 1 11576
Protoss_Citadel_of_Adun 1 12438
12438
