Protoss_Gateway 1 4094
Protoss_Assimilator 1 4353
Protoss_Cybernetics_Core 1 5718
Protoss_Zealot 3 10826
Protoss_Stargate 1 7819
Protoss_Dragoon 1 7766
Protoss_Corsair 2 9942
Protoss_Citadel_of_Adun 1 9920
Protoss_Templar_Archives 1 11859
Protoss_Forge 1 12077
12077
