Protoss_Forge 1 4398
Protoss_Nexus 1 7945
Protoss_Photon_Cannon 1 6405
Protoss_Gateway 1 7272
Protoss_Assimilator 2 11134
Protoss_Cybernetics_Core 1 9437
Protoss_Zealot 4 11724
Protoss_Citadel_of_Adun 1 11257
Protoss_Dragoon 1 12000
12000
