Protoss_Gateway 1 4136
Protoss_Zealot 4 9757
Protoss_Assimilator 1 5756
Protoss_Cybernetics_Core 1 7149
Protoss_Stargate 1 8937
Protoss_Dragoon 1 8896
Protoss_Forge 1 10049
Protoss_Corsair 1 10191
Protoss_Photon_Cannon 1 12320
Protoss_Nexus 1 14194
14194
