Protoss_Forge 1 4533
Protoss_Photon_Cannon 1 6085
Protoss_Nexus 1 8763
Protoss_Gateway 1 7843
Protoss_Assimilator 2 8354
Protoss_Zealot 2 9880
Protoss_Cybernetics_Core 1 9749
Protoss_Stargate 1 11655
Protoss_Dragoon 1 11831
Protoss_Robotics_Facility 1 13047
13047
