Protoss_Forge 1 4347
Protoss_Photon_Cannon 3 10435
Protoss_Nexus 1 9381
Protoss_Gateway 1 8414
Protoss_Assimilator 2 11003
Protoss_Cybernetics_Core 1 10089
Protoss_Zealot 1 9961
Protoss_Stargate 1 11882
Protoss_Dragoon 1 11495
Protoss_Citadel_of_Adun 1 12716
12716
