Protoss_Gateway 1 4305
Protoss_Zealot 7 12272
Protoss_Forge 1 5923
Protoss_Nexus 1 10252
Protoss_Photon_Cannon 2 10093
Protoss_Assimilator 2 11743
Protoss_Cybernetics_Core 1 11775
12272
