Protoss_Forge 1 4003
Protoss_Photon_Cannon 2 7239
Protoss_Nexus 1 7954
Protoss_Gateway 1 7100
Protoss_Assimilator 2 10233
Protoss_Zealot 3 10761
Protoss_Cybernetics_Core 1 10179
Protoss_Stargate 1 12010
Protoss_Dragoon 1 11881
Protoss_Citadel_of_Adun 1 12276
12276
