Protoss_Gateway 2 10316
Protoss_Assimilator 1 4533
Protoss_Zealot 5 10568
Protoss_Cybernetics_Core 1 6848
Protoss_Stargate 1 8721
Protoss_Citadel_of_Adun 1 9069
Protoss_Corsair 1 9668
Protoss_Templar_Archives 1 10682
Protoss_Dark_Templar 2 12051
12051
