Protoss_Forge 1 5045
Protoss_Nexus 1 7825
Protoss_Photon_Cannon 3 8594
Protoss_Gateway 1 8430
Protoss_Assimilator 2 11648
Protoss_Cybernetics_Core 1 10410
Protoss_Zealot 3 12359
Protoss_Stargate 1 12272
Protoss_Citadel_of_Adun 1 12667
12667
