Protoss_Gateway 1 4199
Protoss_Assimilator 1 4512
Protoss_Zealot 2 6895
Protoss_Cybernetics_Core 1 7075
Protoss_Dragoon 3 12395
Protoss_Stargate 1 9722
Protoss_Corsair 1 10692
Protoss_Robotics_Facility 1 11926
12395
