Protoss_Forge 2 6655
Protoss_Nexus 1 7249
Protoss_Gateway 1 6623
Protoss_Assimilator 2 11168
Protoss_Photon_Cannon 2 12402
Protoss_Zealot 3 11900
Protoss_Cybernetics_Core 1 9713
Protoss_Dragoon 1 10933
Protoss_Stargate 1 11517
Protoss_Citadel_of_Adun 1 11688
12402
