Protoss_Forge 2 6064
Protoss_Nexus 1 7026
Protoss_Gateway 1 7024
Protoss_Photon_Cannon 1 7348
Protoss_Assimilator 2 11628
Protoss_Zealot 3 12192
Protoss_Cybernetics_Core 1 9459
Protoss_Stargate 1 11429
Protoss_Dragoon 1 11331
12192
