Protoss_Forge 1 4755
Protoss_Photon_Cannon 6 12396
Protoss_Nexus 1 8302
Protoss_Gateway 1 7843
Protoss_Assimilator 2 10274
Protoss_Zealot 2 10638
Protoss_Cybernetics_Core 1 10349
Protoss_Stargate 1 12164
12396
