Protoss_Forge 1 4327
Protoss_Nexus 1 7749
Protoss_Gateway 3 12842
Protoss_Photon_Cannon 2 8330
Protoss_Assimilator 2 10856
Protoss_Zealot 4 12053
Protoss_Cybernetics_Core 1 10053
Protoss_Citadel_of_Adun 1 11936
12842
