Protoss_Forge 1 4322
Protoss_Photon_Cannon 2 5930
Protoss_Nexus 1 8892
Protoss_Gateway 1 8376
Protoss_Assimilator 2 10258
Protoss_Zealot 2 10978
Protoss_Cybernetics_Core 1 10155
Protoss_Citadel_of_Adun 1 11674
Protoss_Dragoon 1 12131
12131
