Protoss_Gateway 1 4777
Protoss_Assimilator 1 4673
Protoss_Zealot 2 7444
Protoss_Cybernetics_Core 1 7170
Protoss_Robotics_Facility 1 9125
Protoss_Dragoon 2 10002
Protoss_Shuttle 1 10635
Protoss_Robotics_Support_Bay 1 10450
Protoss_Reaver 1 12373
12373
