Protoss_Nexus 1 6842
Protoss_Forge 1 5759
Protoss_Gateway 1 7419
Protoss_Assimilator 2 9715
Protoss_Photon_Cannon 2 8695
Protoss_Cybernetics_Core 1 9605
Protoss_Zealot 3 11622
Protoss_Stargate 1 11525
Protoss_Robotics_Facility 1 12865
12865
