Protoss_Gateway 1 3904
Protoss_Assimilator 1 4852
Protoss_Zealot 3 6659
Protoss_Cybernetics_Core 1 7821
Protoss_Dragoon 1 9029
Protoss_Forge 1 9634
Protoss_Photon_Cannon 1 11185
Protoss_Nexus 1 14045
14045
