Protoss_Forge 1 3864
Protoss_Nexus 1 8090
Protoss_Photon_Cannon 3 9895
Protoss_Gateway 2 8903
Protoss_Assimilator 2 9528
Protoss_Cybernetics_Core 1 10493
Protoss_Robotics_Facility 1 12465
Protoss_Stargate 1 12391
12465
