Protoss_Assimilator 1 3428
Protoss_Forge 1 4095
Protoss_Gateway 2 7389
Protoss_Photon_Cannon 1 6221
Protoss_Zealot 11 12285
Protoss_Cybernetics_Core 1 9822
Protoss_Citadel_of_Adun 1 11276
Protoss_Ground_Weapons_1 1 10158
12285
