Protoss_Gateway 1 4394
Protoss_Assimilator 1 4710
Protoss_Zealot 4 12032
Protoss_Cybernetics_Core 1 7207
Protoss_Dragoon 1 8571
Protoss_Robotics_Facility 1 10829
Protoss_Forge 1 10842
Protoss_Shuttle 1 12252
Protoss_Robotics_Support_Bay 1 11666
12252
