Protoss_Forge 1 3937
Protoss_Photon_Cannon 6 12069
Protoss_Nexus 1 9388
Protoss_Gateway 1 8458
Protoss_Assimilator 1 8350
Protoss_Zealot 2 11966
Protoss_Cybernetics_Core 1 11666
12069
