Protoss_Gateway 2 12563
Protoss_Forge 1 4780
Protoss_Zealot 4 11666
Protoss_Photon_Cannon 3 11849
Protoss_Nexus 1 10297
Protoss_Assimilator 1 8837
Protoss_Cybernetics_Core 1 10779
Protoss_Dragoon 1 11995
12563
