Protoss_Gateway 2 11854
Protoss_Assimilator 1 4429
Protoss_Zealot 3 12112
Protoss_Cybernetics_Core 1 6386
Protoss_Stargate 1 8825
Protoss_Dragoon 2 12175
Protoss_Scout 1 11236
Protoss_Forge 1 10937
12175
