Protoss_Forge 1 5455
Protoss_Photon_Cannon 1 6720
Protoss_Nexus 1 8858
Protoss_Gateway 1 8131
Protoss_Assimilator 1 8448
Protoss_Zealot 2 10180
Protoss_Cybernetics_Core 1 10141
Protoss_Dragoon 1 11458
Protoss_Citadel_of_Adun 1 12349
12349
