Protoss_Gateway 1 4201
Protoss_Assimilator 1 4498
Protoss_Zealot 3 9342
Protoss_Cybernetics_Core 1 6923
Protoss_Stargate 1 8895
Protoss_Dragoon 1 8480
Protoss_Citadel_of_Adun 1 9327
Protoss_Corsair 1 9968
Protoss_Templar_Archives 1 10850
Protoss_Forge 1 11117
Protoss_Dark_Templar 1 12344
Protoss_Photon_Cannon 1 12449
12449
