Protoss_Forge 1 3990
Protoss_Nexus 1 7879
Protoss_Gateway 1 7218
Protoss_Photon_Cannon 2 11469
Protoss_Assimilator 2 10634
Protoss_Zealot 3 11935
Protoss_Cybernetics_Core 1 9487
Protoss_Dragoon 1 10819
Protoss_Stargate 1 11402
Protoss_Citadel_of_Adun 1 11892
11935
