Protoss_Nexus 1 6924
Protoss_Gateway 1 6097
Protoss_Assimilator 2 11544
Protoss_Forge 1 6932
Protoss_Zealot 4 11999
Protoss_Photon_Cannon 2 11392
Protoss_Cybernetics_Core 1 9412
Protoss_Citadel_of_Adun 1 11237
Protoss_Templar_Archives 1 12807
12807
