Protoss_Forge 1 3760
Protoss_Photon_Cannon 2 6036
Protoss_Nexus 1 8829
Protoss_Gateway 1 7925
Protoss_Assimilator 2 10972
Protoss_Zealot 1 8947
Protoss_Cybernetics_Core 1 9781
Protoss_Stargate 1 11896
Protoss_Dragoon 1 12183
12183
