Protoss_Nexus 1 6783
Protoss_Forge 1 5554
Protoss_Gateway 5 11692
Protoss_Photon_Cannon 1 7378
Protoss_Assimilator 1 7495
Protoss_Zealot 7 12289
Protoss_Cybernetics_Core 1 9216
Protoss_Citadel_of_Adun 1 10659
12289
