Protoss_Assimilator 1 3485
Protoss_Forge 1 4211
Protoss_Photon_Cannon 2 11911
Protoss_Gateway 3 7947
Protoss_Zealot 10 12169
Protoss_Ground_Weapons_1 1 10275
Protoss_Nexus 1 13325
13325
