Protoss_Forge 1 4881
Protoss_Nexus 1 7720
Protoss_Photon_Cannon 2 7157
Protoss_Gateway 1 8313
Protoss_Assimilator 2 11650
Protoss_Zealot 1 9348
Protoss_Cybernetics_Core 1 10738
Protoss_Dragoon 1 11981
Protoss_Stargate 1 12751
12751
