Protoss_Nexus 1 6886
Protoss_Forge 1 5490
Protoss_Photon_Cannon 2 6897
Protoss_Gateway 1 7849
Protoss_Zealot 3 12140
Protoss_Assimilator 2 10754
Protoss_Cybernetics_Core 1 10798
12140
