Protoss_Forge 1 4654
Protoss_Nexus 1 7872
Protoss_Photon_Cannon 1 6592
Protoss_Gateway 1 7322
Protoss_Assimilator 2 9547
Protoss_Zealot 3 11247
Protoss_Cybernetics_Core 1 9838
Protoss_Stargate 1 11688
Protoss_Dragoon 1 11545
Protoss_Citadel_of_Adun 1 12317
12317
