Protoss_Forge 1 3895
Protoss_Photon_Cannon 2 10918
Protoss_Gateway 1 6214
Protoss_Nexus 1 9599
Protoss_Zealot 3 9883
Protoss_Assimilator 2 12247
Protoss_Cybernetics_Core 1 10006
Protoss_Citadel_of_Adun 1 11620
Protoss_Dragoon 1 12364
12364
