Protoss_Forge 1 4450
Protoss_Photon_Cannon 2 7485
Protoss_Nexus 1 8270
Protoss_Gateway 1 8227
Protoss_Assimilator 2 10292
Protoss_Cybernetics_Core 1 9803
Protoss_Zealot 2 11935
Protoss_Dragoon 1 10994
Protoss_Stargate 1 11794
Protoss_Robotics_Facility 1 12771
12771
