Protoss_Gateway 2 11750
Protoss_Assimilator 1 4622
Protoss_Zealot 5 10385
Protoss_Cybernetics_Core 1 7009
Protoss_Stargate 1 9142
Protoss_Dragoon 1 9263
Protoss_Citadel_of_Adun 1 10548
Protoss_Corsair 1 10100
Protoss_Templar_Archives 1 12813
12813
