Protoss_Forge 1 3867
Protoss_Nexus 1 7771
Protoss_Photon_Cannon 2 7772
Protoss_Gateway 3 12773
Protoss_Assimilator 1 7862
Protoss_Zealot 4 12225
Protoss_Cybernetics_Core 1 9984
Protoss_Citadel_of_Adun 1 11529
Protoss_Dragoon 1 11363
12773
