Protoss_Forge 1 4278
Protoss_Nexus 1 7796
Protoss_Photon_Cannon 2 7519
Protoss_Gateway 3 12517
Protoss_Assimilator 1 7928
Protoss_Cybernetics_Core 1 9874
Protoss_Zealot 2 11209
Protoss_Citadel_of_Adun 1 11680
Protoss_Dragoon 1 11512
12517
