Protoss_Nexus 1 6878
Protoss_Forge 1 5446
Protoss_Photon_Cannon 3 9528
Protoss_Gateway 3 12743
Protoss_Assimilator 2 10556
Protoss_Cybernetics_Core 1 10698
Protoss_Citadel_of_Adun 1 12140
Protoss_Dragoon 1 11987
12743
