Protoss_Forge 1 4390
Protoss_Nexus 1 7474
Protoss_Photon_Cannon 2 6625
Protoss_Gateway 1 7523
Protoss_Assimilator 1 7709
Protoss_Cybernetics_Core 1 9179
Protoss_Zealot 2 11253
Protoss_Stargate 1 11097
Protoss_Citadel_of_Adun 1 11535
Protoss_Corsair 1 12219
12219
