Protoss_Forge 1 3929
Protoss_Photon_Cannon 3 8177
Protoss_Nexus 1 8825
Protoss_Gateway 1 7864
Protoss_Assimilator 2 11412
Protoss_Zealot 2 10532
Protoss_Cybernetics_Core 1 10722
Protoss_Stargate 1 12555
12555
