Protoss_Gateway 2 9602
Protoss_Zealot 5 12017
Protoss_Assimilator 1 5705
Protoss_Cybernetics_Core 1 7353
Protoss_Stargate 1 9299
Protoss_Corsair 1 10363
Protoss_Dragoon 1 10712
Protoss_Robotics_Facility 1 11824
Protoss_Citadel_of_Adun 1 12506
12506
