Protoss_Forge 1 4562
Protoss_Nexus 1 7872
Protoss_Photon_Cannon 2 7596
Protoss_Gateway 1 7249
Protoss_Zealot 2 10574
Protoss_Assimilator 1 8809
Protoss_Cybernetics_Core 1 10799
10799
