Protoss_Forge 1 3719
Protoss_Photon_Cannon 4 8861
Protoss_Nexus 1 8971
Protoss_Gateway 3 12570
Protoss_Assimilator 1 8988
Protoss_Cybernetics_Core 1 10616
Protoss_Zealot 3 12277
Protoss_Citadel_of_Adun 1 12276
12570
