Protoss_Forge 1 3790
Protoss_Photon_Cannon 2 5799
Protoss_Nexus 1 8712
Protoss_Gateway 1 8251
Protoss_Assimilator 2 10455
Protoss_Zealot 4 12111
Protoss_Cybernetics_Core 1 9974
Protoss_Stargate 1 11753
Protoss_Citadel_of_Adun 1 12367
12367
