Protoss_Forge 1 4189
Protoss_Nexus 1 7577
Protoss_Photon_Cannon 2 6821
Protoss_Gateway 1 7953
Protoss_Zealot 1 8988
Protoss_Assimilator 1 9226
Protoss_Cybernetics_Core 1 12157
12157
