Protoss_Forge 1 4609
Protoss_Nexus 1 8073
Protoss_Photon_Cannon 2 7149
Protoss_Gateway 1 8007
Protoss_Zealot 4 11961
Protoss_Assimilator 1 9573
Protoss_Cybernetics_Core 1 11206
11961
