Protoss_Gateway 1 4046
Protoss_Assimilator 1 4147
Protoss_Zealot 5 11563
Protoss_Cybernetics_Core 1 6418
Protoss_Stargate 1 8579
Protoss_Corsair 2 10425
Protoss_Citadel_of_Adun 1 11563
11563
