Protoss_Nexus 1 7477
Protoss_Forge 1 6589
Protoss_Photon_Cannon 4 8744
Protoss_Gateway 1 8797
Protoss_Assimilator 2 11797
Protoss_Cybernetics_Core 1 10575
Protoss_Zealot 1 11399
Protoss_Stargate 1 12692
Protoss_Dragoon 1 12537
12692
