Protoss_Gateway 4 12052
Protoss_Nexus 1 7249
Protoss_Forge 1 6020
Protoss_Photon_Cannon 1 8242
Protoss_Assimilator 1 8805
Protoss_Cybernetics_Core 1 9823
Protoss_Zealot 3 12339
Protoss_Stargate 1 11784
12339
