Protoss_Forge 1 4947
Protoss_Nexus 1 7585
Protoss_Photon_Cannon 1 6471
Protoss_Gateway 3 11764
Protoss_Assimilator 1 7966
Protoss_Zealot 4 11449
Protoss_Cybernetics_Core 1 10940
Protoss_Dragoon 1 12569
12569
