Protoss_Forge 3 6648
Protoss_Nexus 1 7451
Protoss_Gateway 1 6879
Protoss_Photon_Cannon 1 8319
Protoss_Assimilator 2 10965
Protoss_Zealot 3 11133
Protoss_Cybernetics_Core 1 10837
Protoss_Stargate 1 12586
Protoss_Dragoon 1 12253
Protoss_Citadel_of_Adun 1 12811
12811
