Protoss_Nexus 1 7038
Protoss_Gateway 1 6500
Protoss_Forge 1 6749
Protoss_Assimilator 2 10555
Protoss_Zealot 4 11016
Protoss_Photon_Cannon 1 8114
Protoss_Cybernetics_Core 1 9933
Protoss_Stargate 1 11658
Protoss_Citadel_of_Adun 1 11939
11939
