Protoss_Forge 1 4297
Protoss_Photon_Cannon 2 7020
Protoss_Nexus 1 8314
Protoss_Gateway 3 12768
Protoss_Assimilator 1 8373
Protoss_Cybernetics_Core 1 10050
Protoss_Zealot 2 10606
Protoss_Dragoon 1 11726
Protoss_Citadel_of_Adun 1 12012
12768
