Protoss_Forge 1 4191
Protoss_Photon_Cannon 2 7937
Protoss_Nexus 1 8174
Protoss_Gateway 2 12255
Protoss_Assimilator 2 9860
Protoss_Zealot 2 10272
Protoss_Cybernetics_Core 1 9907
Protoss_Stargate 1 11605
Protoss_Citadel_of_Adun 1 11774
12255
