Protoss_Gateway 1 4034
Protoss_Zealot 8 12201
Protoss_Assimilator 1 5472
Protoss_Forge 1 7397
Protoss_Cybernetics_Core 1 10258
Protoss_Citadel_of_Adun 1 12103
Protoss_Photon_Cannon 1 12235
12235
