Protoss_Forge 1 3839
Protoss_Nexus 1 7997
Protoss_Gateway 1 7034
Protoss_Photon_Cannon 4 11120
Protoss_Assimilator 2 10016
Protoss_Zealot 2 11314
Protoss_Cybernetics_Core 1 9541
Protoss_Stargate 1 11264
Protoss_Robotics_Facility 1 12663
Protoss_Corsair 1 12198
12663
