Protoss_Gateway 1 4327
Protoss_Assimilator 1 4491
Protoss_Zealot 6 12365
Protoss_Cybernetics_Core 1 6899
Protoss_Stargate 1 9076
Protoss_Dragoon 1 9086
Protoss_Forge 1 9738
Protoss_Corsair 1 10495
Protoss_Photon_Cannon 1 12205
12365
