Protoss_Forge 1 3652
Protoss_Nexus 1 7699
Protoss_Gateway 1 6899
Protoss_Zealot 6 12353
Protoss_Photon_Cannon 4 11433
Protoss_Assimilator 1 10319
Protoss_Cybernetics_Core 1 11837
12353
