Protoss_Forge 1 4308
Protoss_Photon_Cannon 2 7288
Protoss_Nexus 1 8585
Protoss_Gateway 1 8332
Protoss_Assimilator 2 11041
Protoss_Cybernetics_Core 1 9845
Protoss_Zealot 4 12096
Protoss_Stargate 2 12468
12468
