Protoss_Forge 1 3970
Protoss_Photon_Cannon 2 6604
Protoss_Nexus 1 8762
Protoss_Gateway 1 7786
Protoss_Assimilator 2 11107
Protoss_Cybernetics_Core 1 9356
Protoss_Zealot 3 11780
Protoss_Stargate 1 11167
Protoss_Citadel_of_Adun 1 11909
Protoss_Corsair 1 12157
12157
