Protoss_Nexus 1 7012
Protoss_Forge 1 5680
Protoss_Gateway 2 12760
Protoss_Assimilator 2 9885
Protoss_Photon_Cannon 1 7959
Protoss_Zealot 3 10549
Protoss_Cybernetics_Core 1 9833
Protoss_Stargate 1 11583
Protoss_Dragoon 1 11669
Protoss_Citadel_of_Adun 1 11955
12760
