Protoss_Forge 1 3997
Protoss_Photon_Cannon 2 5600
Protoss_Nexus 1 8858
Protoss_Gateway 1 7931
Protoss_Assimilator 2 11458
Protoss_Zealot 3 11253
Protoss_Cybernetics_Core 1 9830
Protoss_Stargate 1 11671
Protoss_Citadel_of_Adun 1 12089
12089
