Protoss_Forge 1 4163
Protoss_Nexus 1 7574
Protoss_Photon_Cannon 4 12505
Protoss_Gateway 1 7861
Protoss_Assimilator 2 10193
Protoss_Cybernetics_Core 1 10002
Protoss_Zealot 2 10899
Protoss_Stargate 1 11927
Protoss_Robotics_Facility 1 12733
12733
