Protoss_Gateway 1 4366
Protoss_Zealot 8 11616
Protoss_Nexus 1 9788
Protoss_Assimilator 1 8565
Protoss_Forge 1 9588
Protoss_Cybernetics_Core 1 10716
Protoss_Photon_Cannon 2 12000
12000
