Protoss_Gateway 1 4009
Protoss_Zealot 7 11508
Protoss_Assimilator 1 8237
Protoss_Cybernetics_Core 1 9168
Protoss_Stargate 1 11367
Protoss_Citadel_of_Adun 1 12561
Protoss_Corsair 1 12317
12561
