Protoss_Forge 1 4562
Protoss_Nexus 1 7967
Protoss_Gateway 1 7100
Protoss_Photon_Cannon 3 9306
Protoss_Assimilator 2 11991
Protoss_Zealot 2 11130
Protoss_Cybernetics_Core 1 10723
Protoss_Stargate 1 12460
12460
