Protoss_Forge 1 4313
Protoss_Photon_Cannon 3 12404
Protoss_Nexus 1 9415
Protoss_Gateway 1 8500
Protoss_Assimilator 2 10191
Protoss_Cybernetics_Core 1 10130
Protoss_Zealot 2 10992
Protoss_Stargate 1 11844
Protoss_Dragoon 1 11372
Protoss_Citadel_of_Adun 1 12138
12404
