Protoss_Forge 1 4161
Protoss_Nexus 1 7888
Protoss_Gateway 1 6836
Protoss_Photon_Cannon 2 8030
Protoss_Zealot 3 11783
Protoss_Assimilator 2 11003
Protoss_Cybernetics_Core 1 11077
Protoss_Stargate 1 12921
Protoss_Citadel_of_Adun 1 12842
12921
