Protoss_Forge 1 4208
Protoss_Photon_Cannon 2 5834
Protoss_Nexus 1 8349
Protoss_Gateway 2 12255
Protoss_Assimilator 2 9854
Protoss_Cybernetics_Core 1 9719
Protoss_Zealot 1 9459
Protoss_Stargate 1 11400
Protoss_Citadel_of_Adun 1 11411
Protoss_Dragoon 1 11451
Protoss_Corsair 1 12362
12362
