Protoss_Forge 1 4019
Protoss_Nexus 1 7628
Protoss_Photon_Cannon 2 6869
Protoss_Gateway 1 7577
Protoss_Assimilator 2 12315
Protoss_Zealot 1 8601
Protoss_Cybernetics_Core 1 10078
Protoss_Stargate 1 11877
Protoss_Robotics_Facility 1 12742
12742
