Protoss_Forge 1 4079
Protoss_Nexus 1 7604
Protoss_Photon_Cannon 2 6892
Protoss_Gateway 1 8001
Protoss_Assimilator 2 10248
Protoss_Zealot 2 11007
Protoss_Cybernetics_Core 1 10024
Protoss_Dragoon 1 11308
Protoss_Citadel_of_Adun 1 11809
11809
