Protoss_Forge 1 4129
Protoss_Photon_Cannon 2 5548
Protoss_Nexus 1 9188
Protoss_Gateway 1 8326
Protoss_Assimilator 1 8265
Protoss_Cybernetics_Core 1 9775
Protoss_Zealot 3 12087
Protoss_Citadel_of_Adun 1 11475
12087
