Protoss_Forge 2 6307
Protoss_Nexus 1 7597
Protoss_Gateway 3 12629
Protoss_Photon_Cannon 1 7819
Protoss_Assimilator 2 10047
Protoss_Zealot 3 11396
Protoss_Cybernetics_Core 1 10236
Protoss_Citadel_of_Adun 1 11963
12629
