Protoss_Forge 1 4423
Protoss_Nexus 1 7650
Protoss_Photon_Cannon 2 6876
Protoss_Gateway 1 8121
Protoss_Assimilator 1 8089
Protoss_Zealot 3 11437
Protoss_Cybernetics_Core 1 11563
11563
