Protoss_Forge 1 4202
Protoss_Photon_Cannon 2 5744
Protoss_Nexus 1 9432
Protoss_Gateway 1 8674
Protoss_Assimilator 2 11941
Protoss_Zealot 3 11622
Protoss_Cybernetics_Core 1 10176
Protoss_Stargate 1 11917
Protoss_Citadel_of_Adun 1 12667
12667
