Protoss_Forge 1 4003
Protoss_Photon_Cannon 2 6888
Protoss_Nexus 1 8288
Protoss_Gateway 1 7749
Protoss_Assimilator 2 10038
Protoss_Zealot 2 10375
Protoss_Cybernetics_Core 1 9968
Protoss_Stargate 1 11936
Protoss_Citadel_of_Adun 1 12365
12365
