Protoss_Forge 1 4498
Protoss_Photon_Cannon 2 11640
Protoss_Nexus 1 8355
Protoss_Gateway 1 7807
Protoss_Assimilator 2 9560
Protoss_Cybernetics_Core 1 9333
Protoss_Zealot 1 9810
Protoss_Stargate 1 11045
Protoss_Robotics_Facility 1 12106
Protoss_Corsair 1 12143
12143
