Protoss_Forge 1 4281
Protoss_Photon_Cannon 2 5820
Protoss_Nexus 1 8607
Protoss_Gateway 1 7878
Protoss_Assimilator 2 11012
Protoss_Cybernetics_Core 1 9678
Protoss_Zealot 1 9754
Protoss_Dragoon 1 11032
Protoss_Citadel_of_Adun 1 11827
11827
