Protoss_Forge 1 4223
Protoss_Photon_Cannon 2 7154
Protoss_Nexus 1 8373
Protoss_Gateway 1 7975
Protoss_Assimilator 2 10552
Protoss_Cybernetics_Core 1 9782
Protoss_Zealot 2 11335
Protoss_Stargate 1 11614
Protoss_Citadel_of_Adun 1 12315
12315
