Protoss_Gateway 2 10564
Protoss_Assimilator 1 4512
Protoss_Zealot 7 12207
Protoss_Cybernetics_Core 1 7243
Protoss_Dragoon 1 8700
Protoss_Citadel_of_Adun 1 9586
Protoss_Templar_Archives 1 11926
12207
