Protoss_Nexus 1 6962
Protoss_Forge 1 5838
Protoss_Gateway 2 12715
Protoss_Assimilator 2 9564
Protoss_Photon_Cannon 2 12224
Protoss_Zealot 3 11701
Protoss_Cybernetics_Core 1 9336
Protoss_Stargate 1 11081
Protoss_Dragoon 1 10839
Protoss_Citadel_of_Adun 1 11949
12715
