Protoss_Forge 1 4062
Protoss_Photon_Cannon 3 9063
Protoss_Nexus 1 9549
Protoss_Gateway 1 8633
Protoss_Zealot 3 12324
Protoss_Assimilator 2 11505
Protoss_Cybernetics_Core 1 12450
12450
