Protoss_Gateway 2 5284
Protoss_Zealot 8 11230
Protoss_Assimilator 1 6238
Protoss_Cybernetics_Core 1 8461
Protoss_Stargate 1 10641
Protoss_Dragoon 2 12235
Protoss_Citadel_of_Adun 1 11522
Protoss_Corsair 1 11581
12235
