Protoss_Forge 1 4151
Protoss_Photon_Cannon 2 8346
Protoss_Nexus 1 8753
Protoss_Gateway 1 8010
Protoss_Assimilator 2 9888
Protoss_Cybernetics_Core 1 9639
Protoss_Stargate 1 11541
Protoss_Zealot 2 12184
Protoss_Citadel_of_Adun 1 12068
12184
