Protoss_Forge 1 4248
Protoss_Photon_Cannon 4 9710
Protoss_Nexus 1 9317
Protoss_Gateway 1 8759
Protoss_Assimilator 2 11952
Protoss_Cybernetics_Core 1 11036
Protoss_Zealot 2 11917
11952
