Protoss_Forge 1 4234
Protoss_Photon_Cannon 2 10179
Protoss_Nexus 1 8554
Protoss_Gateway 1 7616
Protoss_Assimilator 2 10337
Protoss_Zealot 3 12260
Protoss_Cybernetics_Core 1 9789
Protoss_Stargate 1 11715
Protoss_Dragoon 1 11278
Protoss_Citadel_of_Adun 1 12368
12368
