Protoss_Forge 1 5028
Protoss_Nexus 1 7562
Protoss_Photon_Cannon 2 6721
Protoss_Gateway 1 8178
Protoss_Assimilator 2 10268
Protoss_Cybernetics_Core 1 9671
Protoss_Zealot 2 10524
Protoss_Stargate 1 11371
Protoss_Citadel_of_Adun 1 11850
Protoss_Corsair 1 12348
12348
