Protoss_Forge 1 4401
Protoss_Nexus 1 7565
Protoss_Photon_Cannon 3 11470
Protoss_Gateway 1 7812
Protoss_Zealot 3 10551
Protoss_Assimilator 1 11039
Protoss_Cybernetics_Core 1 12103
12103
