Protoss_Nexus 1 7187
Protoss_Forge 1 5996
Protoss_Gateway 1 7896
Protoss_Photon_Cannon 1 7743
Protoss_Assimilator 2 9711
Protoss_Zealot 4 12272
Protoss_Cybernetics_Core 1 10553
Protoss_Stargate 1 12265
Protoss_Citadel_of_Adun 1 12697
12697
