Protoss_Forge 1 4521
Protoss_Photon_Cannon 2 6180
Protoss_Nexus 1 9006
Protoss_Gateway 1 8834
Protoss_Assimilator 2 11423
Protoss_Zealot 2 10826
Protoss_Cybernetics_Core 1 10946
Protoss_Stargate 1 12676
12676
