Protoss_Nexus 1 7061
Protoss_Forge 1 5748
Protoss_Photon_Cannon 3 8071
Protoss_Gateway 1 9438
Protoss_Assimilator 1 9422
Protoss_Cybernetics_Core 1 11654
Protoss_Zealot 2 12119
12119
