Protoss_Forge 1 5000
Protoss_Photon_Cannon 1 6347
Protoss_Nexus 1 8677
Protoss_Gateway 1 7814
Protoss_Assimilator 2 11963
Protoss_Zealot 3 12096
Protoss_Cybernetics_Core 1 10167
Protoss_Stargate 1 12327
12327
