Protoss_Forge 1 4548
Protoss_Photon_Cannon 2 6177
Protoss_Nexus 1 8703
Protoss_Gateway 2 12801
Protoss_Assimilator 2 10553
Protoss_Cybernetics_Core 1 9326
Protoss_Zealot 1 8944
Protoss_Dragoon 1 10602
Protoss_Citadel_of_Adun 1 11709
Protoss_Stargate 1 12678
12801
