Protoss_Forge 1 4442
Protoss_Nexus 1 7658
Protoss_Photon_Cannon 2 7188
Protoss_Gateway 2 11701
Protoss_Assimilator 1 8932
Protoss_Zealot 4 12257
Protoss_Cybernetics_Core 1 10635
Protoss_Citadel_of_Adun 1 12204
12257
