Protoss_Forge 1 4255
Protoss_Photon_Cannon 2 7374
Protoss_Nexus 1 8455
Protoss_Gateway 1 8380
Protoss_Assimilator 2 9955
Protoss_Zealot 3 11815
Protoss_Cybernetics_Core 1 9959
Protoss_Stargate 1 11845
Protoss_Robotics_Facility 1 12572
12572
