Protoss_Nexus 1 7405
Protoss_Forge 1 6269
Protoss_Gateway 1 7076
Protoss_Photon_Cannon 3 12354
Protoss_Assimilator 2 9449
Protoss_Cybernetics_Core 1 10804
Protoss_Stargate 1 12534
Protoss_Citadel_of_Adun 1 12355
12534
