Protoss_Forge 1 3722
Protoss_Photon_Cannon 3 10071
Protoss_Nexus 1 8731
Protoss_Gateway 1 8073
Protoss_Assimilator 1 8051
Protoss_Zealot 3 12201
Protoss_Cybernetics_Core 1 12266
12266
