Protoss_Nexus 1 7114
Protoss_Gateway 2 12450
Protoss_Forge 1 6465
Protoss_Assimilator 2 10059
Protoss_Photon_Cannon 2 11095
Protoss_Zealot 5 12125
Protoss_Cybernetics_Core 1 10344
Protoss_Stargate 1 12168
Protoss_Citadel_of_Adun 1 12195
12450
