Protoss_Gateway 1 4660
Protoss_Assimilator 1 4805
Protoss_Zealot 4 10853
Protoss_Cybernetics_Core 1 7331
Protoss_Dragoon 1 8539
Protoss_Stargate 1 9542
Protoss_Robotics_Facility 1 11136
Protoss_Corsair 2 11651
Protoss_Forge 1 11120
Protoss_Shuttle 1 12816
12816
