Protoss_Forge 1 4167
Protoss_Photon_Cannon 3 8439
Protoss_Nexus 1 8130
Protoss_Gateway 1 7697
Protoss_Assimilator 2 10618
Protoss_Cybernetics_Core 1 10229
Protoss_Zealot 1 10056
Protoss_Stargate 1 11931
Protoss_Dragoon 1 11583
Protoss_Citadel_of_Adun 1 12598
12598
