Protoss_Gateway 1 4138
Protoss_Zealot 7 12081
Protoss_Assimilator 1 5306
Protoss_Cybernetics_Core 1 7069
Protoss_Dragoon 1 8480
Protoss_Stargate 1 9249
Protoss_Forge 1 8841
Protoss_Citadel_of_Adun 1 10043
Protoss_Corsair 1 10188
Protoss_Photon_Cannon 1 11796
12081
