Protoss_Forge 1 4476
Protoss_Nexus 1 7708
Protoss_Photon_Cannon 2 12553
Protoss_Gateway 1 8241
Protoss_Assimilator 1 8578
Protoss_Zealot 2 11894
Protoss_Cybernetics_Core 1 10840
12553
