Protoss_Forge 1 4128
Protoss_Photon_Cannon 1 5660
Protoss_Nexus 1 7957
Protoss_Gateway 1 7246
Protoss_Assimilator 2 9959
Protoss_Zealot 5 12222
Protoss_Cybernetics_Core 1 9620
Protoss_Stargate 1 11479
Protoss_Citadel_of_Adun 1 12280
12280
