Protoss_Forge 1 4308
Protoss_Photon_Cannon 2 5789
Protoss_Nexus 1 8510
Protoss_Gateway 1 7653
Protoss_Assimilator 2 12078
Protoss_Zealot 3 10457
Protoss_Cybernetics_Core 1 9564
Protoss_Dragoon 2 11267
Protoss_Stargate 1 11375
Protoss_Citadel_of_Adun 1 12011
12078
