Protoss_Nexus 1 7038
Protoss_Gateway 1 6213
Protoss_Assimilator 2 11085
Protoss_Zealot 5 11595
Protoss_Forge 1 7685
Protoss_Cybernetics_Core 1 9321
Protoss_Photon_Cannon 1 10492
Protoss_Stargate 1 11456
Protoss_Robotics_Facility 1 11924
11924
