Protoss_Forge 1 4191
Protoss_Nexus 1 7512
Protoss_Photon_Cannon 2 6875
Protoss_Gateway 1 7653
Protoss_Assimilator 1 8159
Protoss_Zealot 4 11470
Protoss_Cybernetics_Core 1 10050
Protoss_Stargate 1 11782
Protoss_Dragoon 1 12590
Protoss_Citadel_of_Adun 1 12833
12833
