Protoss_Gateway 1 3662
Protoss_Zealot 5 11086
Protoss_Assimilator 1 5989
Protoss_Cybernetics_Core 1 7255
Protoss_Stargate 1 10393
Protoss_Dragoon 1 10225
Protoss_Citadel_of_Adun 1 11433
Protoss_Corsair 1 11440
Protoss_Forge 1 11938
11938
