Protoss_Nexus 1 7007
Protoss_Gateway 2 12102
Protoss_Forge 1 6671
Protoss_Assimilator 2 8584
Protoss_Photon_Cannon 2 12551
Protoss_Cybernetics_Core 1 8385
Protoss_Stargate 1 10336
Protoss_Zealot 1 9754
Protoss_Citadel_of_Adun 1 10703
Protoss_Corsair 1 11437
Protoss_Templar_Archives 1 12579
12579
