Protoss_Forge 1 4267
Protoss_Photon_Cannon 2 6227
Protoss_Nexus 1 9318
Protoss_Gateway 3 11594
Protoss_Zealot 4 12083
Protoss_Assimilator 1 9544
Protoss_Cybernetics_Core 1 10725
Protoss_Citadel_of_Adun 1 12307
12307
