Protoss_Forge 1 4979
Protoss_Nexus 1 7544
Protoss_Photon_Cannon 2 6903
Protoss_Gateway 1 8210
Protoss_Assimilator 2 11720
Protoss_Zealot 2 11420
Protoss_Cybernetics_Core 1 10504
Protoss_Stargate 1 12294
Protoss_Dragoon 1 12540
12540
