Protoss_Forge 1 3763
Protoss_Photon_Cannon 1 6319
Protoss_Nexus 1 8275
Protoss_Gateway 1 7337
Protoss_Assimilator 2 10868
Protoss_Zealot 4 11884
Protoss_Cybernetics_Core 1 9182
Protoss_Stargate 1 10961
11884
