Protoss_Nexus 1 6861
Protoss_Gateway 1 6348
Protoss_Forge 1 6359
Protoss_Photon_Cannon 1 7605
Protoss_Assimilator 2 9795
Protoss_Zealot 4 11894
Protoss_Cybernetics_Core 1 9893
11894
