Protoss_Forge 1 4019
Protoss_Nexus 1 7761
Protoss_Gateway 2 12727
Protoss_Photon_Cannon 1 7195
Protoss_Assimilator 2 10240
Protoss_Cybernetics_Core 1 9580
Protoss_Zealot 1 9646
Protoss_Citadel_of_Adun 1 11584
Protoss_Stargate 1 11939
12727
