Protoss_Forge 1 4053
Protoss_Nexus 1 8188
Protoss_Gateway 1 6909
Protoss_Assimilator 2 9579
Protoss_Photon_Cannon 1 7800
Protoss_Cybernetics_Core 1 8736
Protoss_Zealot 3 12111
Protoss_Stargate 1 10806
Protoss_Dragoon 1 10667
Protoss_Robotics_Facility 1 12055
Protoss_Corsair 1 11751
12111
