Protoss_Forge 1 4669
Protoss_Photon_Cannon 2 6016
Protoss_Nexus 1 9475
Protoss_Gateway 1 8502
Protoss_Assimilator 2 11745
Protoss_Zealot 4 12312
Protoss_Cybernetics_Core 1 9956
Protoss_Stargate 1 11672
Protoss_Robotics_Facility 1 13020
13020
