Protoss_Forge 1 4300
Protoss_Nexus 1 7651
Protoss_Photon_Cannon 1 6347
Protoss_Gateway 2 12292
Protoss_Assimilator 2 9677
Protoss_Cybernetics_Core 1 8856
Protoss_Zealot 4 12304
Protoss_Stargate 1 10680
Protoss_Citadel_of_Adun 1 11537
Protoss_Corsair 1 11710
12304
