Protoss_Forge 1 4344
Protoss_Photon_Cannon 1 5681
Protoss_Nexus 1 8298
Protoss_Gateway 2 12450
Protoss_Assimilator 2 9912
Protoss_Cybernetics_Core 1 9330
Protoss_Zealot 2 11133
Protoss_Stargate 1 11290
Protoss_Citadel_of_Adun 1 11846
Protoss_Corsair 1 12304
12450
