Protoss_Forge 1 3994
Protoss_Photon_Cannon 2 12511
Protoss_Nexus 1 8206
Protoss_Gateway 1 7229
Protoss_Assimilator 2 9301
Protoss_Zealot 2 9552
Protoss_Cybernetics_Core 1 8904
Protoss_Stargate 1 10885
Protoss_Dragoon 1 11489
Protoss_Citadel_of_Adun 1 12331
Protoss_Corsair 1 12181
12511
