Protoss_Gateway 1 4091
Protoss_Zealot 8 11130
Protoss_Forge 1 7041
Protoss_Photon_Cannon 2 12224
Protoss_Nexus 1 10556
Protoss_Assimilator 2 12203
Protoss_Cybernetics_Core 1 10457
12224
