Protoss_Assimilator 1 3700
Protoss_Gateway 1 4635
Protoss_Cybernetics_Core 1 6249
Protoss_Stargate 1 8011
Protoss_Robotics_Facility 1 9272
Protoss_Corsair 2 10144
Protoss_Forge 1 10331
Protoss_Shuttle 2 12722
Protoss_Photon_Cannon 1 11877
Protoss_Dragoon 1 12039
12722
