Protoss_Gateway 1 4051
Protoss_Zealot 4 10000
Protoss_Nexus 1 9394
Protoss_Assimilator 1 7934
Protoss_Cybernetics_Core 1 8882
Protoss_Stargate 1 10841
Protoss_Dragoon 1 11855
Protoss_Forge 1 11631
Protoss_Corsair 1 11815
11855
