Protoss_Forge 1 3921
Protoss_Nexus 1 7793
Protoss_Gateway 1 7000
Protoss_Photon_Cannon 3 12265
Protoss_Zealot 3 11677
Protoss_Assimilator 2 10571
Protoss_Cybernetics_Core 1 9649
Protoss_Stargate 2 13027
13027
