Protoss_Forge 1 4199
Protoss_Photon_Cannon 2 5725
Protoss_Nexus 1 8643
Protoss_Gateway 1 7916
Protoss_Assimilator 1 7843
Protoss_Cybernetics_Core 1 9438
Protoss_Zealot 3 11004
Protoss_Stargate 1 11703
11703
