Protoss_Forge 1 4164
Protoss_Nexus 1 7998
Protoss_Gateway 1 7076
Protoss_Assimilator 2 10455
Protoss_Photon_Cannon 1 7803
Protoss_Cybernetics_Core 1 8928
Protoss_Zealot 1 9620
Protoss_Dragoon 1 10201
Protoss_Stargate 1 10791
Protoss_Citadel_of_Adun 1 11361
Protoss_Corsair 1 11827
11827
