Protoss_Forge 1 4188
Protoss_Photon_Cannon 2 6052
Protoss_Nexus 1 8459
Protoss_Gateway 1 7804
Protoss_Assimilator 2 11755
Protoss_Zealot 4 12144
Protoss_Cybernetics_Core 1 9791
Protoss_Stargate 1 11949
12144
