Protoss_Forge 1 4091
Protoss_Nexus 1 7345
Protoss_Photon_Cannon 3 7620
Protoss_Gateway 1 7498
Protoss_Assimilator 2 11036
Protoss_Cybernetics_Core 1 9863
Protoss_Zealot 2 11145
Protoss_Stargate 1 11614
Protoss_Robotics_Facility 1 12756
Protoss_Dragoon 1 12519
12756
