Protoss_Forge 1 4659
Protoss_Photon_Cannon 2 6642
Protoss_Nexus 1 7982
Protoss_Gateway 1 7650
Protoss_Assimilator 2 10763
Protoss_Zealot 3 11601
Protoss_Cybernetics_Core 1 10158
Protoss_Stargate 1 11983
11983
