Protoss_Nexus 1 6974
Protoss_Gateway 1 5999
Protoss_Forge 1 6406
Protoss_Zealot 5 12128
Protoss_Assimilator 1 7100
Protoss_Photon_Cannon 2 9718
Protoss_Cybernetics_Core 1 10711
Protoss_Stargate 1 12550
12550
