Protoss_Forge 1 4520
Protoss_Photon_Cannon 2 6041
Protoss_Nexus 1 9218
Protoss_Gateway 1 8469
Protoss_Assimilator 2 11871
Protoss_Cybernetics_Core 1 9918
Protoss_Zealot 2 10562
Protoss_Stargate 1 11667
Protoss_Dragoon 1 11682
Protoss_Robotics_Facility 1 13309
13309
