Protoss_Forge 2 6503
Protoss_Nexus 1 7563
Protoss_Gateway 2 12710
Protoss_Photon_Cannon 1 7754
Protoss_Assimilator 2 11227
Protoss_Zealot 2 9716
Protoss_Cybernetics_Core 1 9801
Protoss_Dragoon 1 11003
Protoss_Stargate 1 11776
Protoss_Citadel_of_Adun 1 11572
12710
