Protoss_Nexus 1 7000
Protoss_Gateway 2 11832
Protoss_Forge 1 6454
Protoss_Assimilator 2 9296
Protoss_Photon_Cannon 1 7702
Protoss_Cybernetics_Core 1 8294
Protoss_Zealot 1 8598
Protoss_Stargate 1 10393
Protoss_Dragoon 1 10181
Protoss_Citadel_of_Adun 1 11158
Protoss_Corsair 1 11332
Protoss_Templar_Archives 1 12787
12787
