Protoss_Forge 1 4150
Protoss_Nexus 1 7928
Protoss_Photon_Cannon 4 8495
Protoss_Gateway 1 10120
Protoss_Assimilator 2 10871
Protoss_Cybernetics_Core 1 11569
Protoss_Zealot 2 12002
12002
