Protoss_Gateway 1 4223
Protoss_Assimilator 1 4504
Protoss_Zealot 2 6232
Protoss_Cybernetics_Core 1 7293
Protoss_Stargate 1 8980
Protoss_Dragoon 1 8644
Protoss_Citadel_of_Adun 1 9541
Protoss_Corsair 1 9977
Protoss_Templar_Archives 1 10987
Protoss_Forge 1 10925
Protoss_Dark_Templar 1 12189
Protoss_Photon_Cannon 1 12352
12352
