Protoss_Forge 1 4305
Protoss_Nexus 1 7975
Protoss_Gateway 1 7272
Protoss_Assimilator 2 9473
Protoss_Photon_Cannon 2 11969
Protoss_Cybernetics_Core 1 8870
Protoss_Zealot 2 12321
Protoss_Stargate 1 10925
Protoss_Dragoon 1 10772
Protoss_Robotics_Facility 1 12257
Protoss_Corsair 1 11862
12321
