Protoss_Gateway 2 10167
Protoss_Assimilator 1 4609
Protoss_Zealot 6 11192
Protoss_Cybernetics_Core 1 7644
Protoss_Dragoon 1 9189
Protoss_Citadel_of_Adun 1 9549
Protoss_Templar_Archives 1 11001
Protoss_Forge 1 12201
12201
