Protoss_Gateway 1 4325
Protoss_Assimilator 1 4366
Protoss_Zealot 4 10261
Protoss_Cybernetics_Core 1 7852
Protoss_Dragoon 1 9080
Protoss_Stargate 1 9802
Protoss_Citadel_of_Adun 1 11414
11414
