Protoss_Forge 1 3956
Protoss_Photon_Cannon 3 8467
Protoss_Nexus 1 8210
Protoss_Gateway 1 7694
Protoss_Assimilator 2 11955
Protoss_Zealot 4 12289
Protoss_Cybernetics_Core 1 10319
Protoss_Citadel_of_Adun 1 11860
12289
