Protoss_Forge 1 3640
Protoss_Nexus 1 7757
Protoss_Photon_Cannon 2 12089
Protoss_Gateway 3 9485
Protoss_Assimilator 1 8129
Protoss_Zealot 7 12298
Protoss_Cybernetics_Core 1 11376
12298
