Protoss_Nexus 1 6745
Protoss_Forge 1 5262
Protoss_Gateway 2 7572
Protoss_Assimilator 2 12023
Protoss_Zealot 8 11714
Protoss_Photon_Cannon 1 10102
Protoss_Cybernetics_Core 1 11216
12023
