Protoss_Forge 1 4120
Protoss_Photon_Cannon 2 11906
Protoss_Nexus 1 8311
Protoss_Gateway 1 7507
Protoss_Assimilator 2 11218
Protoss_Zealot 3 11900
Protoss_Cybernetics_Core 1 9732
Protoss_Stargate 1 11438
Protoss_Dragoon 1 11038
Protoss_Citadel_of_Adun 1 12668
12668
