Protoss_Nexus 1 7025
Protoss_Gateway 3 11941
Protoss_Forge 1 6715
Protoss_Assimilator 1 7150
Protoss_Photon_Cannon 1 8303
Protoss_Cybernetics_Core 1 9358
Protoss_Zealot 2 11614
Protoss_Dragoon 1 10734
Protoss_Citadel_of_Adun 1 11250
11941
