Protoss_Forge 1 3850
Protoss_Nexus 1 7574
Protoss_Photon_Cannon 2 7591
Protoss_Gateway 1 8426
Protoss_Assimilator 2 10166
Protoss_Cybernetics_Core 1 9866
Protoss_Zealot 2 10486
Protoss_Stargate 1 11577
Protoss_Citadel_of_Adun 1 12151
Protoss_Dragoon 1 12415
12415
