Protoss_Forge 1 4120
Protoss_Nexus 1 7420
Protoss_Gateway 4 12266
Protoss_Photon_Cannon 1 7539
Protoss_Assimilator 1 7597
Protoss_Zealot 5 12143
Protoss_Cybernetics_Core 1 9116
Protoss_Stargate 1 10837
Protoss_Citadel_of_Adun 1 11696
Protoss_Corsair 1 11988
12266
