Protoss_Forge 1 4169
Protoss_Photon_Cannon 4 9827
Protoss_Nexus 1 9988
Protoss_Gateway 1 9014
Protoss_Assimilator 2 11824
Protoss_Cybernetics_Core 1 10562
Protoss_Zealot 2 11490
Protoss_Stargate 1 12348
12348
