Protoss_Forge 1 4913
Protoss_Nexus 1 7836
Protoss_Gateway 1 7656
Protoss_Photon_Cannon 1 7743
Protoss_Assimilator 2 9567
Protoss_Cybernetics_Core 1 9214
Protoss_Zealot 1 9143
Protoss_Stargate 1 11023
11023
