Protoss_Gateway 2 12747
Protoss_Zealot 5 10590
Protoss_Assimilator 1 6182
Protoss_Forge 1 6968
Protoss_Photon_Cannon 1 8258
Protoss_Cybernetics_Core 1 10496
Protoss_Dragoon 1 11736
Protoss_Citadel_of_Adun 1 11998
12747
