Protoss_Gateway 1 4111
Protoss_Zealot 3 6842
Protoss_Nexus 1 9675
Protoss_Forge 1 8841
Protoss_Assimilator 1 8957
Protoss_Cybernetics_Core 1 10353
Protoss_Photon_Cannon 4 12377
Protoss_Dragoon 1 11971
12377
