Protoss_Gateway 2 11234
Protoss_Zealot 6 11262
Protoss_Forge 1 7409
Protoss_Photon_Cannon 1 8725
Protoss_Nexus 1 11051
Protoss_Assimilator 1 9891
Protoss_Cybernetics_Core 1 12583
12583
