Protoss_Forge 1 4125
Protoss_Nexus 1 7439
Protoss_Photon_Cannon 2 7242
Protoss_Gateway 1 6953
Protoss_Assimilator 2 9869
Protoss_Zealot 3 11827
Protoss_Cybernetics_Core 1 9652
Protoss_Dragoon 1 10942
Protoss_Stargate 1 11529
Protoss_Citadel_of_Adun 1 11854
11854
