Protoss_Forge 1 4770
Protoss_Nexus 1 7575
Protoss_Photon_Cannon 2 6815
Protoss_Gateway 1 8107
Protoss_Assimilator 2 12200
Protoss_Zealot 2 11402
Protoss_Cybernetics_Core 1 10264
12200
