Protoss_Gateway 2 12124
Protoss_Assimilator 1 4570
Protoss_Zealot 6 12214
Protoss_Cybernetics_Core 1 7755
Protoss_Dragoon 1 9058
Protoss_Citadel_of_Adun 1 9577
Protoss_Templar_Archives 1 11322
Protoss_Dark_Templar 1 12534
12534
