Protoss_Gateway 2 5424
Protoss_Zealot 5 11871
Protoss_Assimilator 1 6523
Protoss_Cybernetics_Core 1 8041
Protoss_Dragoon 1 9446
Protoss_Stargate 1 10420
Protoss_Citadel_of_Adun 1 10839
Protoss_Forge 1 12361
12361
