Protoss_Gateway 2 5253
Protoss_Zealot 7 11673
Protoss_Assimilator 1 7971
Protoss_Cybernetics_Core 1 9239
Protoss_Dragoon 1 10456
Protoss_Stargate 1 11833
Protoss_Citadel_of_Adun 1 12686
12686
