Protoss_Gateway 1 4591
Protoss_Assimilator 1 5146
Protoss_Zealot 3 7590
Protoss_Cybernetics_Core 1 7561
Protoss_Citadel_of_Adun 1 9501
Protoss_Dragoon 1 9527
Protoss_Forge 1 9956
Protoss_Templar_Archives 1 11155
Protoss_Photon_Cannon 1 11820
11820
