Protoss_Gateway 2 10697
Protoss_Assimilator 1 4649
Protoss_Zealot 6 11871
Protoss_Cybernetics_Core 1 7221
Protoss_Dragoon 1 8444
Protoss_Citadel_of_Adun 1 9905
Protoss_Templar_Archives 1 12168
12168
