Protoss_Gateway 1 4180
Protoss_Assimilator 1 4404
Protoss_Zealot 3 9219
Protoss_Cybernetics_Core 1 7063
Protoss_Stargate 1 8759
Protoss_Dragoon 1 8357
Protoss_Citadel_of_Adun 1 9274
Protoss_Corsair 1 9898
Protoss_Templar_Archives 1 11114
Protoss_Forge 1 11499
11499
