Protoss_Gateway 2 5311
Protoss_Zealot 9 10868
Protoss_Assimilator 1 7052
Protoss_Cybernetics_Core 1 8304
Protoss_Stargate 1 11023
Protoss_Citadel_of_Adun 1 11882
Protoss_Corsair 1 12097
12097
