Protoss_Gateway 2 4981
Protoss_Zealot 8 11513
Protoss_Nexus 1 9924
Protoss_Assimilator 1 9024
Protoss_Cybernetics_Core 1 10989
Protoss_Dragoon 1 12408
Protoss_Citadel_of_Adun 1 12789
12789
