Protoss_Gateway 2 8633
Protoss_Assimilator 1 5196
Protoss_Forge 1 5437
Protoss_Photon_Cannon 1 6932
Protoss_Zealot 9 11871
Protoss_Cybernetics_Core 1 11070
Protoss_Citadel_of_Adun 1 12844
12844
