Protoss_Assimilator 1 3585
Protoss_Gateway 1 4771
Protoss_Cybernetics_Core 1 6216
Protoss_Stargate 1 7911
Protoss_Dragoon 2 10078
Protoss_Robotics_Facility 1 9652
Protoss_Corsair 3 11999
Protoss_Shuttle 1 11048
Protoss_Forge 1 11541
11999
