Protoss_Gateway 1 4621
Protoss_Assimilator 1 4590
Protoss_Cybernetics_Core 1 6232
Protoss_Stargate 1 7966
Protoss_Forge 1 7556
Protoss_Photon_Cannon 1 8877
Protoss_Corsair 1 8914
Protoss_Zealot 3 12332
Protoss_Citadel_of_Adun 1 10957
12332
