Protoss_Assimilator 1 3572
Protoss_Gateway 1 4621
Protoss_Cybernetics_Core 1 6184
Protoss_Dragoon 1 7514
Protoss_Stargate 1 8047
Protoss_Corsair 4 11935
Protoss_Robotics_Facility 1 10387
Protoss_Forge 1 10343
Protoss_Shuttle 1 12470
12470
