Protoss_Gateway 1 4207
Protoss_Assimilator 1 4619
Protoss_Zealot 3 9485
Protoss_Cybernetics_Core 1 7114
Protoss_Dragoon 1 8436
Protoss_Robotics_Facility 1 10204
Protoss_Forge 1 10622
Protoss_Robotics_Support_Bay 1 11398
11398
