Protoss_Gateway 3 12015
Protoss_Assimilator 1 4586
Protoss_Cybernetics_Core 1 5911
Protoss_Zealot 3 9653
Protoss_Stargate 1 7857
Protoss_Citadel_of_Adun 1 8606
Protoss_Corsair 1 8805
Protoss_Templar_Archives 1 10748
Protoss_Dark_Templar 1 11956
12015
