Protoss_Forge 1 5186
Protoss_Nexus 1 7917
Protoss_Photon_Cannon 3 11848
Protoss_Gateway 1 8787
Protoss_Assimilator 2 10608
Protoss_Cybernetics_Core 1 10243
Protoss_Zealot 2 11490
Protoss_Stargate 1 12062
12062
