Protoss_Gateway 2 5180
Protoss_Zealot 8 11673
Protoss_Assimilator 1 6883
Protoss_Cybernetics_Core 1 8298
Protoss_Stargate 1 10227
Protoss_Dragoon 1 9797
Protoss_Corsair 1 11175
Protoss_Citadel_of_Adun 1 11847
Protoss_Forge 1 11999
11999
