Protoss_Gateway 1 4616
Protoss_Zealot 4 9192
Protoss_Nexus 1 9002
Protoss_Assimilator 1 8793
Protoss_Cybernetics_Core 1 9511
Protoss_Dragoon 1 10778
Protoss_Forge 1 10777
Protoss_Robotics_Facility 1 13163
13163
