Protoss_Gateway 2 5083
Protoss_Zealot 8 12075
Protoss_Assimilator 1 6778
Protoss_Cybernetics_Core 1 8933
Protoss_Citadel_of_Adun 1 10449
Protoss_Dragoon 1 10390
Protoss_Templar_Archives 1 11998
12075
