Protoss_Forge 1 4832
Protoss_Photon_Cannon 2 6121
Protoss_Nexus 1 9341
Protoss_Gateway 2 12763
Protoss_Assimilator 2 10312
Protoss_Cybernetics_Core 1 9946
Protoss_Zealot 3 12081
Protoss_Dragoon 1 11147
Protoss_Stargate 1 11772
Protoss_Citadel_of_Adun 1 11958
12763
