Protoss_Forge 1 4050
Protoss_Nexus 1 7806
Protoss_Gateway 1 6950
Protoss_Photon_Cannon 2 8107
Protoss_Assimilator 2 11481
Protoss_Cybernetics_Core 1 9719
Protoss_Zealot 4 12304
Protoss_Stargate 1 11863
Protoss_Citadel_of_Adun 1 12345
12345
