Protoss_Gateway 2 5172
Protoss_Zealot 8 12185
Protoss_Assimilator 1 6204
Protoss_Cybernetics_Core 1 7869
Protoss_Forge 1 8184
Protoss_Stargate 1 9947
Protoss_Corsair 1 11132
Protoss_Photon_Cannon 1 11900
12185
