Protoss_Forge 1 4413
Protoss_Photon_Cannon 2 6151
Protoss_Nexus 1 9175
Protoss_Gateway 1 8393
Protoss_Assimilator 2 10536
Protoss_Zealot 3 11680
Protoss_Cybernetics_Core 1 9968
Protoss_Stargate 1 11836
Protoss_Citadel_of_Adun 1 11750
11836
