Protoss_Gateway 1 3950
Protoss_Zealot 8 11449
Protoss_Assimilator 1 6371
Protoss_Cybernetics_Core 1 8619
Protoss_Stargate 1 10649
Protoss_Citadel_of_Adun 1 11489
Protoss_Corsair 1 11600
11600
