Protoss_Forge 1 4037
Protoss_Nexus 1 8196
Protoss_Photon_Cannon 2 8046
Protoss_Gateway 2 12517
Protoss_Assimilator 2 10837
Protoss_Cybernetics_Core 1 10199
Protoss_Zealot 2 11205
Protoss_Citadel_of_Adun 1 12157
12517
