Protoss_Gateway 1 4192
Protoss_Forge 1 4973
Protoss_Zealot 4 11527
Protoss_Photon_Cannon 2 8593
Protoss_Nexus 1 11826
Protoss_Assimilator 1 10100
Protoss_Cybernetics_Core 1 11597
11826
