Protoss_Gateway 2 11317
Protoss_Assimilator 1 4410
Protoss_Zealot 5 11527
Protoss_Cybernetics_Core 1 7021
Protoss_Stargate 1 8839
Protoss_Dragoon 1 9000
Protoss_Citadel_of_Adun 1 9708
11527
