Protoss_Gateway 1 4313
Protoss_Assimilator 1 4455
Protoss_Zealot 5 11541
Protoss_Cybernetics_Core 1 7223
Protoss_Dragoon 1 8568
Protoss_Citadel_of_Adun 1 8979
Protoss_Robotics_Facility 1 10088
Protoss_Shuttle 1 11513
Protoss_Templar_Archives 1 11528
Protoss_Forge 1 11244
Protoss_Robotics_Support_Bay 1 11570
Protoss_Photon_Cannon 1 12544
12544
