Protoss_Forge 1 4024
Protoss_Nexus 1 8108
Protoss_Photon_Cannon 2 8082
Protoss_Gateway 2 12627
Protoss_Assimilator 1 8985
Protoss_Zealot 2 10985
Protoss_Cybernetics_Core 1 10897
Protoss_Stargate 1 13023
13023
