Protoss_Gateway 2 5279
Protoss_Zealot 7 11278
Protoss_Assimilator 1 6235
Protoss_Cybernetics_Core 1 7812
Protoss_Dragoon 1 9102
Protoss_Citadel_of_Adun 1 9542
Protoss_Templar_Archives 1 12501
12501
