Protoss_Gateway 3 12816
Protoss_Assimilator 1 4622
Protoss_Zealot 2 6880
Protoss_Cybernetics_Core 1 7038
Protoss_Dragoon 2 11210
Protoss_Robotics_Facility 1 9665
Protoss_Shuttle 1 11074
Protoss_Robotics_Support_Bay 1 10457
Protoss_Reaver 1 12632
12816
