Protoss_Forge 1 4027
Protoss_Nexus 1 8095
Protoss_Gateway 4 12263
Protoss_Photon_Cannon 1 7681
Protoss_Assimilator 1 7769
Protoss_Zealot 4 11970
Protoss_Cybernetics_Core 1 9184
12263
