Protoss_Gateway 2 12806
Protoss_Assimilator 1 4890
Protoss_Zealot 4 10634
Protoss_Forge 1 6561
Protoss_Cybernetics_Core 1 8768
Protoss_Stargate 1 10585
Protoss_Citadel_of_Adun 1 10550
Protoss_Templar_Archives 1 12014
Protoss_Corsair 1 11585
12806
