Protoss_Gateway 1 4256
Protoss_Assimilator 1 4527
Protoss_Zealot 4 8380
Protoss_Cybernetics_Core 1 8450
Protoss_Forge 1 9061
Protoss_Dragoon 1 9768
Protoss_Citadel_of_Adun 1 10324
Protoss_Photon_Cannon 1 11694
Protoss_Templar_Archives 1 12252
12252
