Protoss_Gateway 1 4199
Protoss_Assimilator 1 4432
Protoss_Forge 1 5148
Protoss_Cybernetics_Core 1 7024
Protoss_Photon_Cannon 1 7422
Protoss_Dragoon 1 8517
Protoss_Robotics_Facility 1 10710
Protoss_Observatory 1 11881
11881
