Protoss_Gateway 1 4212
Protoss_Assimilator 1 4256
Protoss_Cybernetics_Core 1 5837
Protoss_Forge 1 6624
Protoss_Stargate 1 7964
Protoss_Photon_Cannon 3 11572
Protoss_Corsair 1 8914
11572
