Protoss_Forge 1 4141
Protoss_Photon_Cannon 2 8000
Protoss_Nexus 1 8860
Protoss_Gateway 1 7767
Protoss_Assimilator 2 11636
Protoss_Zealot 2 10662
Protoss_Cybernetics_Core 1 10788
11636
