Protoss_Gateway 2 4852
Protoss_Zealot 7 9317
Protoss_Assimilator 1 8051
Protoss_Cybernetics_Core 1 9053
Protoss_Citadel_of_Adun 1 10831
Protoss_Dragoon 1 10829
Protoss_Forge 1 11042
Protoss_Photon_Cannon 1 12500
12500
