Protoss_Gateway 1 4329
Protoss_Assimilator 1 4652
Protoss_Zealot 6 11271
Protoss_Cybernetics_Core 1 6870
Protoss_Dragoon 1 9051
Protoss_Robotics_Facility 1 10085
Protoss_Robotics_Support_Bay 1 10804
Protoss_Shuttle 1 11521
11521
