Protoss_Forge 1 4280
Protoss_Nexus 1 7852
Protoss_Photon_Cannon 3 10975
Protoss_Gateway 1 7969
Protoss_Assimilator 1 7918
Protoss_Zealot 3 11168
Protoss_Cybernetics_Core 1 10236
Protoss_Robotics_Facility 1 13107
13107
