Protoss_Gateway 2 9530
Protoss_Assimilator 1 4716
Protoss_Zealot 8 11592
Protoss_Cybernetics_Core 1 7119
Protoss_Citadel_of_Adun 1 8778
Protoss_Templar_Archives 1 11180
Protoss_Forge 1 11281
Protoss_Dark_Templar 1 12475
12475
