Protoss_Gateway 4 12564
Protoss_Zealot 5 9990
Protoss_Forge 1 6583
Protoss_Photon_Cannon 2 8546
Protoss_Nexus 1 11594
Protoss_Assimilator 1 10079
Protoss_Cybernetics_Core 1 11256
Protoss_Citadel_of_Adun 1 12770
12770
