Protoss_Gateway 2 9451
Protoss_Assimilator 1 4450
Protoss_Zealot 6 10678
Protoss_Cybernetics_Core 1 6958
Protoss_Dragoon 1 8166
Protoss_Citadel_of_Adun 1 9046
Protoss_Templar_Archives 1 10918
Protoss_High_Templar 2 12285
12285
