Protoss_Gateway 1 4287
Protoss_Assimilator 1 4571
Protoss_Zealot 5 11732
Protoss_Cybernetics_Core 1 6980
Protoss_Dragoon 1 8283
Protoss_Citadel_of_Adun 1 10126
Protoss_Forge 1 10234
Protoss_Templar_Archives 1 11913
Protoss_Photon_Cannon 1 11747
11913
