Protoss_Forge 1 4507
Protoss_Photon_Cannon 4 8807
Protoss_Nexus 1 10098
Protoss_Gateway 1 9513
Protoss_Assimilator 1 9472
Protoss_Zealot 2 11888
Protoss_Cybernetics_Core 1 11636
11888
