Protoss_Forge 1 3810
Protoss_Nexus 1 9017
Protoss_Photon_Cannon 3 8008
Protoss_Gateway 2 11850
Protoss_Assimilator 2 10338
Protoss_Cybernetics_Core 1 10632
Protoss_Zealot 2 11127
Protoss_Citadel_of_Adun 1 12080
12080
