Protoss_Forge 1 4341
Protoss_Nexus 1 7878
Protoss_Gateway 3 12204
Protoss_Photon_Cannon 3 9914
Protoss_Assimilator 1 8077
Protoss_Zealot 4 12245
Protoss_Cybernetics_Core 1 10875
Protoss_Citadel_of_Adun 1 12532
12532
