Protoss_Gateway 2 10924
Protoss_Assimilator 1 4732
Protoss_Zealot 6 11768
Protoss_Cybernetics_Core 1 7409
Protoss_Dragoon 1 9003
Protoss_Citadel_of_Adun 1 10300
Protoss_Templar_Archives 1 11853
11853
