Protoss_Forge 1 3912
Protoss_Nexus 1 8146
Protoss_Gateway 3 12694
Protoss_Photon_Cannon 1 7462
Protoss_Assimilator 1 7662
Protoss_Cybernetics_Core 1 9169
Protoss_Zealot 3 12090
Protoss_Citadel_of_Adun 1 11082
Protoss_Dragoon 1 11117
12694
