Protoss_Forge 1 4472
Protoss_Nexus 1 7925
Protoss_Photon_Cannon 4 12244
Protoss_Gateway 1 8004
Protoss_Assimilator 1 7938
Protoss_Cybernetics_Core 1 9552
Protoss_Zealot 2 10758
Protoss_Stargate 1 11340
Protoss_Corsair 1 12288
12288
