Protoss_Gateway 1 4230
Protoss_Assimilator 1 4242
Protoss_Zealot 2 6924
Protoss_Cybernetics_Core 1 6814
Protoss_Stargate 1 8552
Protoss_Citadel_of_Adun 1 8945
Protoss_Corsair 1 9522
Protoss_Dragoon 1 9922
Protoss_Templar_Archives 1 10709
Protoss_Dark_Templar 1 11919
Protoss_Nexus 1 13894
13894
