Protoss_Forge 1 4072
Protoss_Photon_Cannon 2 6194
Protoss_Gateway 1 7177
Protoss_Nexus 1 10154
Protoss_Assimilator 1 8986
Protoss_Zealot 3 11292
Protoss_Cybernetics_Core 1 10676
Protoss_Stargate 1 12646
12646
