Protoss_Gateway 1 4400
Protoss_Assimilator 1 4644
Protoss_Zealot 6 10900
Protoss_Cybernetics_Core 1 7250
Protoss_Stargate 1 9107
Protoss_Dragoon 1 9158
Protoss_Corsair 2 11025
Protoss_Nexus 1 14258
14258
