Protoss_Forge 1 4053
Protoss_Nexus 1 7698
Protoss_Gateway 4 12065
Protoss_Photon_Cannon 1 7532
Protoss_Assimilator 1 7532
Protoss_Zealot 3 11822
Protoss_Cybernetics_Core 1 9529
Protoss_Citadel_of_Adun 1 11014
Protoss_Dragoon 1 10961
12065
