Protoss_Gateway 1 4442
Protoss_Assimilator 1 4493
Protoss_Zealot 4 10864
Protoss_Cybernetics_Core 1 7047
Protoss_Stargate 1 8950
Protoss_Citadel_of_Adun 1 9514
Protoss_Dragoon 1 9511
Protoss_Corsair 1 9977
Protoss_Templar_Archives 1 11086
Protoss_Forge 1 11306
11306
