Protoss_Gateway 1 4085
Protoss_Assimilator 1 4470
Protoss_Zealot 4 11834
Protoss_Cybernetics_Core 1 7037
Protoss_Dragoon 1 8253
Protoss_Stargate 1 9258
Protoss_Forge 1 9667
Protoss_Corsair 1 10290
Protoss_Photon_Cannon 1 10927
Protoss_Citadel_of_Adun 1 11611
11834
