Protoss_Gateway 1 4272
Protoss_Assimilator 1 4575
Protoss_Zealot 3 9383
Protoss_Cybernetics_Core 1 7068
Protoss_Dragoon 1 8268
Protoss_Robotics_Facility 1 10151
Protoss_Citadel_of_Adun 1 10783
Protoss_Shuttle 1 11565
Protoss_Robotics_Support_Bay 1 10933
11565
