Protoss_Nexus 1 6937
Protoss_Forge 1 5641
Protoss_Photon_Cannon 2 7173
Protoss_Gateway 2 9782
Protoss_Assimilator 2 10207
Protoss_Zealot 3 11483
Protoss_Cybernetics_Core 1 11354
11483
