Protoss_Gateway 2 5515
Protoss_Zealot 8 11549
Protoss_Assimilator 1 6803
Protoss_Cybernetics_Core 1 8289
Protoss_Forge 1 8715
Protoss_Dragoon 1 9541
Protoss_Citadel_of_Adun 1 10627
Protoss_Templar_Archives 1 12362
12362
