Protoss_Forge 2 6112
Protoss_Nexus 1 7473
Protoss_Photon_Cannon 1 7459
Protoss_Gateway 6 12248
Protoss_Assimilator 1 8323
Protoss_Cybernetics_Core 1 9863
Protoss_Zealot 2 12134
Protoss_Citadel_of_Adun 1 11569
12248
