Protoss_Gateway 2 11055
Protoss_Assimilator 1 4666
Protoss_Zealot 4 8483
Protoss_Cybernetics_Core 1 8361
Protoss_Stargate 1 10361
Protoss_Dragoon 1 10185
Protoss_Corsair 1 11307
Protoss_Citadel_of_Adun 1 12045
12045
