Protoss_Gateway 2 5175
Protoss_Zealot 10 11614
Protoss_Assimilator 1 6554
Protoss_Cybernetics_Core 1 9349
Protoss_Citadel_of_Adun 1 10912
Protoss_Dragoon 1 11802
Protoss_Templar_Archives 1 12438
Protoss_Forge 1 12258
12438
