Protoss_Gateway 2 9648
Protoss_Assimilator 1 4707
Protoss_Zealot 7 12295
Protoss_Cybernetics_Core 1 7328
Protoss_Dragoon 1 8539
Protoss_Forge 1 8628
Protoss_Citadel_of_Adun 1 10956
12295
