Protoss_Gateway 3 11238
Protoss_Assimilator 1 4496
Protoss_Zealot 5 10012
Protoss_Cybernetics_Core 1 7141
Protoss_Stargate 1 9706
Protoss_Citadel_of_Adun 1 10029
Protoss_Corsair 1 11658
11658
