Protoss_Forge 1 4741
Protoss_Photon_Cannon 3 10781
Protoss_Nexus 1 8856
Protoss_Gateway 2 12709
Protoss_Assimilator 2 11140
Protoss_Cybernetics_Core 1 9972
Protoss_Citadel_of_Adun 1 11436
Protoss_Dragoon 1 11685
12709
