Protoss_Forge 1 4463
Protoss_Photon_Cannon 2 5820
Protoss_Nexus 1 9425
Protoss_Gateway 1 8904
Protoss_Assimilator 2 11134
Protoss_Zealot 3 11796
Protoss_Cybernetics_Core 1 11028
Protoss_Robotics_Facility 1 12977
12977
