Protoss_Gateway 2 10054
Protoss_Assimilator 1 4783
Protoss_Zealot 6 11446
Protoss_Cybernetics_Core 1 7060
Protoss_Dragoon 1 8444
Protoss_Citadel_of_Adun 1 9226
Protoss_Templar_Archives 1 12389
12389
