Protoss_Gateway 2 12402
Protoss_Assimilator 1 4703
Protoss_Zealot 4 11702
Protoss_Cybernetics_Core 1 7369
Protoss_Citadel_of_Adun 1 8989
Protoss_Dragoon 1 8949
Protoss_Robotics_Facility 1 10696
Protoss_Shuttle 1 12662
12662
