Protoss_Forge 1 5058
Protoss_Nexus 1 7841
Protoss_Photon_Cannon 3 12530
Protoss_Gateway 3 11882
Protoss_Assimilator 2 10682
Protoss_Zealot 2 9447
Protoss_Cybernetics_Core 1 9137
Protoss_Citadel_of_Adun 1 10840
Protoss_Templar_Archives 1 12422
12530
