Protoss_Nexus 1 7190
Protoss_Forge 1 5748
Protoss_Photon_Cannon 3 8834
Protoss_Gateway 3 11868
Protoss_Assimilator 1 7843
Protoss_Zealot 2 10480
Protoss_Cybernetics_Core 1 10568
Protoss_Citadel_of_Adun 1 12187
12187
