Protoss_Assimilator 1 3626
Protoss_Gateway 1 4985
Protoss_Cybernetics_Core 1 6429
Protoss_Stargate 1 8147
Protoss_Dragoon 1 7989
Protoss_Robotics_Facility 1 9914
Protoss_Corsair 2 10021
Protoss_Shuttle 1 11314
Protoss_Robotics_Support_Bay 1 11113
Protoss_Reaver 1 12872
12872
