Protoss_Forge 1 5132
Protoss_Nexus 1 7947
Protoss_Photon_Cannon 2 10557
Protoss_Gateway 1 7668
Protoss_Assimilator 2 11472
Protoss_Cybernetics_Core 1 9595
Protoss_Zealot 2 11768
Protoss_Dragoon 1 10814
Protoss_Stargate 1 11535
11768
