Protoss_Assimilator 1 3634
Protoss_Gateway 1 4689
Protoss_Cybernetics_Core 1 6146
Protoss_Stargate 1 7916
Protoss_Robotics_Facility 1 8678
Protoss_Citadel_of_Adun 1 8982
Protoss_Corsair 1 8871
Protoss_Shuttle 1 10087
Protoss_Templar_Archives 1 10631
Protoss_Forge 1 10739
Protoss_High_Templar 1 11846
Protoss_Nexus 1 14042
14042
