Protoss_Nexus 1 7003
Protoss_Gateway 3 11685
Protoss_Assimilator 1 6577
Protoss_Forge 1 7066
Protoss_Photon_Cannon 1 8417
Protoss_Zealot 3 10710
Protoss_Cybernetics_Core 1 10372
Protoss_Citadel_of_Adun 1 11942
Protoss_Dragoon 1 11927
11942
