Protoss_Gateway 1 4455
Protoss_Assimilator 1 4359
Protoss_Zealot 5 11496
Protoss_Cybernetics_Core 1 8493
Protoss_Dragoon 1 9753
Protoss_Citadel_of_Adun 1 10340
Protoss_Forge 1 10779
Protoss_Templar_Archives 1 11909
11909
