Protoss_Forge 1 4150
Protoss_Nexus 1 7931
Protoss_Photon_Cannon 2 7323
Protoss_Gateway 3 12710
Protoss_Assimilator 1 8892
Protoss_Cybernetics_Core 1 10416
Protoss_Zealot 2 11019
Protoss_Citadel_of_Adun 1 12141
12710
