Protoss_Nexus 1 7003
Protoss_Forge 1 5973
Protoss_Photon_Cannon 3 9247
Protoss_Gateway 1 8047
Protoss_Assimilator 2 11813
Protoss_Zealot 3 12081
Protoss_Cybernetics_Core 1 10455
Protoss_Citadel_of_Adun 1 12350
12350
