Protoss_Forge 1 4081
Protoss_Nexus 1 7711
Protoss_Photon_Cannon 3 10080
Protoss_Gateway 3 12674
Protoss_Assimilator 1 7552
Protoss_Zealot 4 11443
Protoss_Cybernetics_Core 1 11382
Protoss_Citadel_of_Adun 1 12842
12842
