Protoss_Forge 1 4215
Protoss_Photon_Cannon 5 12322
Protoss_Nexus 1 8957
Protoss_Gateway 1 8304
Protoss_Assimilator 1 8181
Protoss_Zealot 3 11256
Protoss_Cybernetics_Core 1 10060
Protoss_Citadel_of_Adun 1 11604
Protoss_Dragoon 1 11597
12322
