Protoss_Gateway 2 5069
Protoss_Zealot 5 10656
Protoss_Assimilator 1 6752
Protoss_Forge 1 7950
Protoss_Cybernetics_Core 1 9356
Protoss_Photon_Cannon 3 11990
Protoss_Citadel_of_Adun 1 10808
11990
