Protoss_Gateway 1 4514
Protoss_Assimilator 1 4672
Protoss_Cybernetics_Core 1 6219
Protoss_Robotics_Facility 1 8685
Protoss_Dragoon 1 8327
Protoss_Zealot 1 9851
Protoss_Robotics_Support_Bay 1 9629
Protoss_Reaver 1 11386
Protoss_Shuttle 1 12687
12687
