Protoss_Forge 2 12027
Protoss_Photon_Cannon 2 6354
Protoss_Nexus 1 8797
Protoss_Gateway 3 12020
Protoss_Assimilator 1 8436
Protoss_Cybernetics_Core 1 9854
Protoss_Zealot 4 12258
Protoss_Dragoon 1 11092
Protoss_Citadel_of_Adun 1 11480
12258
