Protoss_Forge 1 4220
Protoss_Photon_Cannon 4 12377
Protoss_Nexus 1 9587
Protoss_Gateway 3 11385
Protoss_Assimilator 1 8667
Protoss_Cybernetics_Core 1 10223
Protoss_Citadel_of_Adun 1 11809
Protoss_Zealot 2 12242
12377
