Protoss_Forge 1 4447
Protoss_Photon_Cannon 2 6253
Protoss_Nexus 1 9338
Protoss_Gateway 1 8917
Protoss_Assimilator 2 12298
Protoss_Zealot 3 11695
Protoss_Cybernetics_Core 1 10391
Protoss_Citadel_of_Adun 1 12507
12507
