Protoss_Forge 1 4268
Protoss_Photon_Cannon 2 6376
Protoss_Nexus 1 9791
Protoss_Gateway 1 8904
Protoss_Assimilator 2 12087
Protoss_Zealot 2 10861
Protoss_Cybernetics_Core 1 10543
Protoss_Dragoon 1 11981
Protoss_Citadel_of_Adun 1 12468
12468
