Protoss_Forge 1 4240
Protoss_Photon_Cannon 2 7605
Protoss_Gateway 1 7173
Protoss_Zealot 4 11888
Protoss_Nexus 1 10449
Protoss_Assimilator 1 9763
Protoss_Cybernetics_Core 1 11167
Protoss_Citadel_of_Adun 1 12710
12710
