Protoss_Gateway 1 4236
Protoss_Assimilator 1 4628
Protoss_Cybernetics_Core 1 5948
Protoss_Zealot 3 11271
Protoss_Stargate 1 7862
Protoss_Corsair 3 11241
Protoss_Robotics_Facility 1 10473
Protoss_Forge 1 10997
Protoss_Shuttle 1 11982
11982
