Protoss_Forge 1 4046
Protoss_Photon_Cannon 2 7042
Protoss_Nexus 1 8320
Protoss_Gateway 3 12358
Protoss_Zealot 5 11917
Protoss_Assimilator 2 12349
Protoss_Cybernetics_Core 1 11768
12358
