Protoss_Nexus 1 6609
Protoss_Forge 1 5192
Protoss_Photon_Cannon 3 11979
Protoss_Gateway 1 7389
Protoss_Assimilator 2 10698
Protoss_Zealot 4 12055
Protoss_Cybernetics_Core 1 9087
Protoss_Stargate 1 10947
Protoss_Robotics_Facility 1 12209
Protoss_Corsair 1 11894
12209
