Protoss_Gateway 1 4243
Protoss_Assimilator 1 4960
Protoss_Zealot 3 7839
Protoss_Cybernetics_Core 1 7177
Protoss_Citadel_of_Adun 1 8734
Protoss_Dragoon 1 8959
Protoss_Forge 1 9378
Protoss_Templar_Archives 1 10550
Protoss_Photon_Cannon 1 10869
Protoss_Dark_Templar 1 11839
11839
