Protoss_Assimilator 1 3542
Protoss_Forge 1 4518
Protoss_Gateway 3 8364
Protoss_Photon_Cannon 2 12107
Protoss_Zealot 8 11525
Protoss_Ground_Weapons_1 1 10807
Protoss_Cybernetics_Core 1 12763
12763
