Protoss_Gateway 1 4397
Protoss_Assimilator 1 4600
Protoss_Cybernetics_Core 1 6011
Protoss_Zealot 4 11607
Protoss_Citadel_of_Adun 1 8409
Protoss_Forge 1 9068
Protoss_Dragoon 2 10514
Protoss_Templar_Archives 1 11589
Protoss_Photon_Cannon 1 12241
12241
