Protoss_Gateway 2 12027
Protoss_Zealot 7 10439
Protoss_Assimilator 1 6156
Protoss_Cybernetics_Core 1 9160
Protoss_Stargate 1 11065
Protoss_Dragoon 1 11559
Protoss_Citadel_of_Adun 1 11835
Protoss_Forge 1 11897
Protoss_Corsair 1 12014
12027
