Protoss_Forge 1 4132
Protoss_Photon_Cannon 3 7605
Protoss_Nexus 1 8898
Protoss_Gateway 4 12482
Protoss_Assimilator 1 8625
Protoss_Zealot 3 11080
Protoss_Cybernetics_Core 1 11165
12482
