Protoss_Forge 1 4325
Protoss_Nexus 1 7642
Protoss_Photon_Cannon 2 12414
Protoss_Gateway 2 10548
Protoss_Assimilator 2 11707
Protoss_Zealot 4 11938
Protoss_Cybernetics_Core 1 9383
Protoss_Citadel_of_Adun 1 11347
Protoss_Dragoon 1 11761
12414
