Protoss_Forge 1 4211
Protoss_Photon_Cannon 4 11911
Protoss_Nexus 1 10942
Protoss_Gateway 1 9696
Protoss_Assimilator 2 12156
Protoss_Cybernetics_Core 1 11322
Protoss_Zealot 1 12214
12214
