Protoss_Forge 1 4766
Protoss_Photon_Cannon 2 6117
Protoss_Nexus 1 9435
Protoss_Gateway 2 12372
Protoss_Assimilator 1 8281
Protoss_Zealot 2 10583
Protoss_Cybernetics_Core 1 10224
Protoss_Citadel_of_Adun 1 11892
Protoss_Dragoon 1 11736
12372
