Protoss_Gateway 2 5032
Protoss_Zealot 8 10908
Protoss_Assimilator 1 6561
Protoss_Forge 1 7556
Protoss_Cybernetics_Core 1 9156
Protoss_Citadel_of_Adun 1 10726
Protoss_Dragoon 1 11297
Protoss_Photon_Cannon 1 12371
12371
