Protoss_Nexus 1 7098
Protoss_Forge 1 5639
Protoss_Photon_Cannon 2 7012
Protoss_Gateway 3 12693
Protoss_Assimilator 2 10546
Protoss_Cybernetics_Core 1 12456
Protoss_Zealot 1 12075
12693
