Protoss_Forge 1 3886
Protoss_Photon_Cannon 1 6055
Protoss_Nexus 1 8544
Protoss_Gateway 1 7878
Protoss_Assimilator 2 9898
Protoss_Cybernetics_Core 1 9321
Protoss_Zealot 1 9184
Protoss_Stargate 1 11096
Protoss_Robotics_Facility 1 12597
Protoss_Corsair 1 12037
12597
