Protoss_Forge 1 4091
Protoss_Nexus 1 8057
Protoss_Photon_Cannon 2 7023
Protoss_Gateway 3 12828
Protoss_Assimilator 1 8391
Protoss_Zealot 3 11118
Protoss_Cybernetics_Core 1 10149
Protoss_Citadel_of_Adun 1 11666
Protoss_Dragoon 1 12238
12828
