Protoss_Assimilator 1 3545
Protoss_Gateway 1 4921
Protoss_Cybernetics_Core 1 6371
Protoss_Stargate 2 8775
Protoss_Corsair 6 12140
Protoss_Forge 1 10829
Protoss_Photon_Cannon 1 12080
12140
