Protoss_Forge 1 4141
Protoss_Nexus 1 7815
Protoss_Gateway 4 11977
Protoss_Photon_Cannon 2 12459
Protoss_Assimilator 1 7695
Protoss_Zealot 3 9697
Protoss_Cybernetics_Core 1 10678
Protoss_Citadel_of_Adun 1 12189
12459
