Protoss_Forge 1 3920
Protoss_Nexus 1 8157
Protoss_Photon_Cannon 2 7154
Protoss_Gateway 3 12803
Protoss_Assimilator 1 8992
Protoss_Zealot 2 11186
Protoss_Cybernetics_Core 1 10940
Protoss_Citadel_of_Adun 1 12500
Protoss_Dragoon 1 12306
12803
