Protoss_Forge 1 4400
Protoss_Nexus 1 7514
Protoss_Photon_Cannon 2 6830
Protoss_Gateway 1 7965
Protoss_Assimilator 2 12252
Protoss_Zealot 3 11402
Protoss_Cybernetics_Core 1 10586
Protoss_Dragoon 1 11831
Protoss_Citadel_of_Adun 1 12569
12569
