Protoss_Forge 1 5434
Protoss_Nexus 1 8242
Protoss_Photon_Cannon 2 7071
Protoss_Gateway 4 12607
Protoss_Assimilator 1 8415
Protoss_Cybernetics_Core 1 9541
Protoss_Zealot 1 9273
Protoss_Citadel_of_Adun 1 11535
Protoss_Dragoon 1 11539
12607
