Protoss_Gateway 1 4084
Protoss_Assimilator 1 4600
Protoss_Zealot 3 9912
Protoss_Cybernetics_Core 1 7836
Protoss_Dragoon 1 9051
Protoss_Robotics_Facility 1 10222
Protoss_Forge 1 10632
Protoss_Robotics_Support_Bay 1 10975
Protoss_Shuttle 1 11821
11821
