Protoss_Gateway 2 10075
Protoss_Assimilator 1 4565
Protoss_Zealot 3 7483
Protoss_Cybernetics_Core 1 7068
Protoss_Stargate 1 8887
Protoss_Dragoon 1 8883
Protoss_Citadel_of_Adun 1 9416
Protoss_Robotics_Facility 1 10975
Protoss_Templar_Archives 1 11480
Protoss_Shuttle 1 12384
12384
