Protoss_Forge 1 4709
Protoss_Photon_Cannon 3 12295
Protoss_Gateway 1 6381
Protoss_Nexus 1 9732
Protoss_Assimilator 1 8208
Protoss_Zealot 2 9741
Protoss_Cybernetics_Core 1 11699
12295
