Protoss_Gateway 1 4265
Protoss_Zealot 6 11275
Protoss_Assimilator 1 5571
Protoss_Cybernetics_Core 1 7287
Protoss_Stargate 1 9193
Protoss_Dragoon 1 9532
Protoss_Forge 1 9598
Protoss_Citadel_of_Adun 1 10360
Protoss_Corsair 2 11753
Protoss_Photon_Cannon 1 11189
11753
