Protoss_Forge 1 3831
Protoss_Photon_Cannon 2 6516
Protoss_Nexus 1 9043
Protoss_Gateway 3 12184
Protoss_Assimilator 1 8118
Protoss_Zealot 3 12067
Protoss_Cybernetics_Core 1 10019
Protoss_Citadel_of_Adun 1 11686
12184
