Protoss_Forge 1 4227
Protoss_Nexus 1 8131
Protoss_Photon_Cannon 3 9758
Protoss_Gateway 2 12387
Protoss_Assimilator 1 8412
Protoss_Zealot 3 11549
Protoss_Cybernetics_Core 1 11265
Protoss_Citadel_of_Adun 1 12744
12744
