Protoss_Forge 1 3996
Protoss_Nexus 1 7947
Protoss_Photon_Cannon 2 7108
Protoss_Gateway 3 12753
Protoss_Assimilator 1 8538
Protoss_Zealot 2 10736
Protoss_Cybernetics_Core 1 10916
Protoss_Citadel_of_Adun 1 12380
Protoss_Dragoon 1 12161
12753
