Protoss_Forge 1 4193
Protoss_Nexus 1 7994
Protoss_Photon_Cannon 2 7285
Protoss_Gateway 2 12743
Protoss_Assimilator 1 8854
Protoss_Zealot 2 11095
Protoss_Cybernetics_Core 1 10757
Protoss_Dragoon 1 12215
Protoss_Citadel_of_Adun 1 12694
12743
