Protoss_Forge 1 4578
Protoss_Photon_Cannon 2 5937
Protoss_Nexus 1 8803
Protoss_Gateway 1 8168
Protoss_Assimilator 1 7930
Protoss_Cybernetics_Core 1 9637
Protoss_Zealot 3 11856
Protoss_Stargate 1 11482
11856
