Protoss_Nexus 1 7288
Protoss_Forge 1 6131
Protoss_Photon_Cannon 1 7408
Protoss_Gateway 3 12144
Protoss_Assimilator 1 7947
Protoss_Zealot 4 12171
Protoss_Cybernetics_Core 1 9683
Protoss_Citadel_of_Adun 1 11194
Protoss_Dragoon 1 12186
12186
