Protoss_Nexus 1 6634
Protoss_Forge 1 5271
Protoss_Photon_Cannon 2 6914
Protoss_Gateway 4 12725
Protoss_Assimilator 1 8516
Protoss_Zealot 3 11350
Protoss_Cybernetics_Core 1 10296
Protoss_Citadel_of_Adun 1 11851
Protoss_Dragoon 1 12505
12725
