Protoss_Gateway 2 12034
Protoss_Assimilator 1 4491
Protoss_Zealot 4 10627
Protoss_Cybernetics_Core 1 6067
Protoss_Stargate 1 7862
Protoss_Dragoon 1 7566
Protoss_Corsair 1 8827
Protoss_Citadel_of_Adun 1 10316
Protoss_Templar_Archives 1 11897
Protoss_Forge 1 12135
12135
