Protoss_Forge 1 3910
Protoss_Nexus 1 7632
Protoss_Photon_Cannon 2 7203
Protoss_Gateway 1 9299
Protoss_Assimilator 2 10507
Protoss_Zealot 3 12125
Protoss_Cybernetics_Core 1 11206
12125
