Protoss_Forge 1 3993
Protoss_Nexus 1 8867
Protoss_Photon_Cannon 1 7476
Protoss_Gateway 1 8715
Protoss_Assimilator 2 11793
Protoss_Zealot 2 10685
Protoss_Cybernetics_Core 1 10347
Protoss_Citadel_of_Adun 1 11911
Protoss_Dragoon 1 11805
11911
