Protoss_Nexus 1 6965
Protoss_Forge 1 5794
Protoss_Photon_Cannon 2 7630
Protoss_Gateway 3 11685
Protoss_Assimilator 2 10015
Protoss_Cybernetics_Core 1 10229
Protoss_Zealot 3 11900
Protoss_Citadel_of_Adun 1 11860
11900
