Protoss_Gateway 1 4385
Protoss_Assimilator 1 4619
Protoss_Cybernetics_Core 1 5882
Protoss_Zealot 5 12163
Protoss_Stargate 1 7690
Protoss_Corsair 1 8631
Protoss_Scout 1 9791
Protoss_Dragoon 1 9540
12163
