Protoss_Gateway 1 4226
Protoss_Assimilator 1 4520
Protoss_Zealot 3 7649
Protoss_Cybernetics_Core 1 7389
Protoss_Dragoon 1 8769
Protoss_Stargate 1 9391
Protoss_Citadel_of_Adun 1 9885
Protoss_Corsair 1 10671
Protoss_Templar_Archives 1 11341
Protoss_Forge 1 11890
11890
