Protoss_Forge 1 4448
Protoss_Photon_Cannon 2 7757
Protoss_Nexus 1 9208
Protoss_Gateway 1 8849
Protoss_Assimilator 1 8617
Protoss_Cybernetics_Core 1 10401
Protoss_Dragoon 1 11594
Protoss_Citadel_of_Adun 1 12026
12026
