Protoss_Nexus 1 7032
Protoss_Forge 1 5617
Protoss_Photon_Cannon 1 6881
Protoss_Gateway 3 11553
Protoss_Assimilator 1 7313
Protoss_Zealot 3 10107
Protoss_Cybernetics_Core 1 10561
Protoss_Dragoon 1 11897
Protoss_Citadel_of_Adun 1 12286
12286
