Protoss_Gateway 2 10988
Protoss_Assimilator 1 4455
Protoss_Zealot 3 7612
Protoss_Cybernetics_Core 1 7470
Protoss_Robotics_Facility 1 9746
Protoss_Dragoon 2 10463
Protoss_Robotics_Support_Bay 1 11050
Protoss_Shield_Battery 1 11220
11220
