Protoss_Forge 1 3836
Protoss_Photon_Cannon 1 5616
Protoss_Nexus 1 8150
Protoss_Gateway 4 12115
Protoss_Assimilator 1 7501
Protoss_Zealot 5 11979
Protoss_Cybernetics_Core 1 8971
Protoss_Citadel_of_Adun 1 10805
12115
