Protoss_Gateway 1 4325
Protoss_Assimilator 1 4597
Protoss_Zealot 3 7934
Protoss_Cybernetics_Core 1 7100
Protoss_Stargate 1 9353
Protoss_Dragoon 1 9190
Protoss_Citadel_of_Adun 1 10003
Protoss_Corsair 1 10341
Protoss_Forge 1 10851
Protoss_Templar_Archives 1 11465
Protoss_Photon_Cannon 1 12105
12105
