Protoss_Gateway 1 4138
Protoss_Assimilator 1 4193
Protoss_Cybernetics_Core 1 5895
Protoss_Zealot 4 12043
Protoss_Dragoon 1 7225
Protoss_Stargate 1 8491
Protoss_Corsair 1 9552
Protoss_Citadel_of_Adun 1 11398
12043
