Protoss_Gateway 2 11279
Protoss_Assimilator 1 4612
Protoss_Zealot 6 12067
Protoss_Cybernetics_Core 1 7457
Protoss_Stargate 1 9403
Protoss_Dragoon 1 9704
Protoss_Citadel_of_Adun 1 10943
Protoss_Corsair 1 10943
12067
