Protoss_Forge 1 4274
Protoss_Photon_Cannon 1 5725
Protoss_Nexus 1 8583
Protoss_Gateway 1 7572
Protoss_Assimilator 1 7966
Protoss_Zealot 4 11358
Protoss_Cybernetics_Core 1 11238
Protoss_Stargate 1 12935
12935
