Protoss_Forge 1 4637
Protoss_Photon_Cannon 3 8947
Protoss_Nexus 1 8692
Protoss_Gateway 1 8146
Protoss_Zealot 3 11048
Protoss_Assimilator 1 9342
Protoss_Cybernetics_Core 1 12269
12269
