Protoss_Nexus 1 6937
Protoss_Forge 1 5904
Protoss_Gateway 4 11165
Protoss_Assimilator 1 7207
Protoss_Photon_Cannon 1 7788
Protoss_Cybernetics_Core 1 9394
Protoss_Citadel_of_Adun 1 10887
Protoss_Zealot 6 12310
12310
