Protoss_Forge 1 4013
Protoss_Photon_Cannon 3 10637
Protoss_Nexus 1 8332
Protoss_Gateway 1 7469
Protoss_Assimilator 1 7608
Protoss_Cybernetics_Core 1 9339
Protoss_Zealot 4 12187
Protoss_Citadel_of_Adun 1 12264
12264
