Protoss_Assimilator 1 3283
Protoss_Gateway 1 4931
Protoss_Cybernetics_Core 1 6421
Protoss_Stargate 1 8191
Protoss_Dragoon 2 9251
Protoss_Corsair 3 11683
Protoss_Forge 1 12219
12219
