Protoss_Forge 1 4316
Protoss_Nexus 1 8276
Protoss_Photon_Cannon 1 6917
Protoss_Gateway 4 12378
Protoss_Assimilator 1 7952
Protoss_Cybernetics_Core 1 9602
Protoss_Zealot 1 9273
Protoss_Citadel_of_Adun 1 11129
12378
