Protoss_Forge 1 4409
Protoss_Photon_Cannon 2 12522
Protoss_Nexus 1 8717
Protoss_Gateway 3 12302
Protoss_Assimilator 2 11091
Protoss_Cybernetics_Core 1 10186
Protoss_Zealot 2 10971
Protoss_Citadel_of_Adun 1 12008
Protoss_Dragoon 1 12307
12522
