Protoss_Forge 1 4103
Protoss_Nexus 1 8317
Protoss_Photon_Cannon 3 12231
Protoss_Assimilator 2 9803
Protoss_Gateway 2 11061
Protoss_Cybernetics_Core 1 11802
Protoss_Zealot 2 12046
12231
