Protoss_Gateway 3 11203
Protoss_Assimilator 1 4673
Protoss_Zealot 3 7308
Protoss_Cybernetics_Core 1 7303
Protoss_Stargate 1 9132
Protoss_Dragoon 5 12541
Protoss_Corsair 1 10107
12541
