Protoss_Forge 1 4454
Protoss_Photon_Cannon 6 8755
Protoss_Nexus 1 10326
Protoss_Gateway 2 12482
Protoss_Assimilator 1 9334
Protoss_Cybernetics_Core 1 10880
Protoss_Zealot 2 11382
Protoss_Dragoon 1 12502
12502
