Protoss_Forge 1 5132
Protoss_Photon_Cannon 2 6512
Protoss_Nexus 1 9944
Protoss_Assimilator 2 9918
Protoss_Gateway 1 9165
Protoss_Cybernetics_Core 1 10858
Protoss_Zealot 2 11266
Protoss_Citadel_of_Adun 1 12416
Protoss_Dragoon 1 12395
12416
