Protoss_Forge 1 4047
Protoss_Nexus 1 7837
Protoss_Photon_Cannon 2 9282
Protoss_Assimilator 2 9105
Protoss_Gateway 2 11926
Protoss_Zealot 3 12039
Protoss_Cybernetics_Core 1 10473
Protoss_Citadel_of_Adun 1 12124
12124
