Protoss_Assimilator 1 4062
Protoss_Gateway 1 4763
Protoss_Cybernetics_Core 1 6292
Protoss_Dragoon 5 11913
Protoss_Robotics_Facility 1 8460
Protoss_Observatory 1 9335
Protoss_Observer 1 10363
Protoss_Shuttle 1 11748
11913
