Protoss_Forge 1 4161
Protoss_Nexus 1 7983
Protoss_Photon_Cannon 2 8227
Protoss_Gateway 3 12541
Protoss_Assimilator 2 10207
Protoss_Cybernetics_Core 1 10313
Protoss_Citadel_of_Adun 1 11860
12541
