Protoss_Gateway 2 5338
Protoss_Zealot 9 12280
Protoss_Assimilator 1 6349
Protoss_Cybernetics_Core 1 8210
Protoss_Citadel_of_Adun 1 9927
Protoss_Templar_Archives 1 11878
Protoss_Forge 1 11764
12280
