Protoss_Gateway 2 5560
Protoss_Zealot 4 8014
Protoss_Assimilator 1 6419
Protoss_Cybernetics_Core 1 8872
Protoss_Forge 1 9125
Protoss_Stargate 1 10630
Protoss_Dragoon 1 10310
Protoss_Citadel_of_Adun 1 11197
Protoss_Scout 1 12838
12838
