Protoss_Gateway 2 9394
Protoss_Zealot 4 11095
Protoss_Forge 1 5625
Protoss_Photon_Cannon 2 8758
Protoss_Nexus 1 10303
Protoss_Assimilator 1 9920
Protoss_Cybernetics_Core 1 10944
Protoss_Citadel_of_Adun 1 12640
12640
