Protoss_Forge 1 3972
Protoss_Nexus 1 7764
Protoss_Photon_Cannon 4 10364
Protoss_Gateway 1 7609
Protoss_Zealot 3 11168
Protoss_Assimilator 1 9525
Protoss_Cybernetics_Core 1 11165
11168
