Protoss_Forge 1 5031
Protoss_Nexus 1 7999
Protoss_Photon_Cannon 1 6525
Protoss_Gateway 3 12460
Protoss_Assimilator 1 7142
Protoss_Zealot 4 11490
Protoss_Cybernetics_Core 1 10239
Protoss_Citadel_of_Adun 1 11796
12460
