Protoss_Forge 1 4234
Protoss_Nexus 1 7764
Protoss_Gateway 2 11114
Protoss_Photon_Cannon 1 7263
Protoss_Assimilator 2 11869
Protoss_Zealot 4 12273
Protoss_Cybernetics_Core 1 9137
Protoss_Citadel_of_Adun 1 10776
Protoss_Dragoon 1 11297
12273
