Protoss_Nexus 1 7121
Protoss_Gateway 1 6380
Protoss_Forge 1 6598
Protoss_Assimilator 2 10305
Protoss_Photon_Cannon 2 11366
Protoss_Zealot 2 10546
Protoss_Cybernetics_Core 1 9819
Protoss_Citadel_of_Adun 1 11418
Protoss_Stargate 1 12341
12341
