Protoss_Forge 1 4152
Protoss_Photon_Cannon 2 5886
Protoss_Nexus 1 9539
Protoss_Gateway 1 8635
Protoss_Assimilator 2 11945
Protoss_Zealot 4 12340
Protoss_Cybernetics_Core 1 10253
Protoss_Citadel_of_Adun 1 11999
12340
