Protoss_Forge 1 4394
Protoss_Nexus 1 8004
Protoss_Gateway 3 12804
Protoss_Assimilator 2 11437
Protoss_Photon_Cannon 1 8081
Protoss_Zealot 3 11717
Protoss_Cybernetics_Core 1 9274
Protoss_Citadel_of_Adun 1 10843
12804
