Protoss_Forge 1 4649
Protoss_Photon_Cannon 1 6091
Protoss_Nexus 1 8342
Protoss_Assimilator 1 7542
Protoss_Gateway 3 12690
Protoss_Cybernetics_Core 1 9716
Protoss_Zealot 3 12225
Protoss_Citadel_of_Adun 1 11304
Protoss_Dragoon 1 11363
12690
