Protoss_Nexus 1 7072
Protoss_Gateway 1 6187
Protoss_Forge 1 6232
Protoss_Photon_Cannon 4 11473
Protoss_Assimilator 1 7499
Protoss_Zealot 3 10385
Protoss_Cybernetics_Core 1 9153
Protoss_Citadel_of_Adun 1 10723
11473
