Protoss_Forge 1 4469
Protoss_Photon_Cannon 2 5798
Protoss_Nexus 1 8898
Protoss_Gateway 2 12182
Protoss_Assimilator 1 7952
Protoss_Zealot 2 11227
Protoss_Cybernetics_Core 1 11278
12182
