Protoss_Forge 1 3986
Protoss_Nexus 1 7596
Protoss_Photon_Cannon 2 7605
Protoss_Gateway 3 12170
Protoss_Assimilator 2 12127
Protoss_Zealot 1 8673
Protoss_Cybernetics_Core 1 10031
Protoss_Citadel_of_Adun 1 11633
12170
