Protoss_Nexus 1 7072
Protoss_Forge 1 5756
Protoss_Gateway 2 11178
Protoss_Photon_Cannon 2 9003
Protoss_Assimilator 2 11256
Protoss_Zealot 4 12149
Protoss_Cybernetics_Core 1 10689
Protoss_Citadel_of_Adun 1 12211
12211
