Protoss_Nexus 1 7325
Protoss_Gateway 1 6358
Protoss_Forge 1 6503
Protoss_Photon_Cannon 2 9332
Protoss_Zealot 5 12090
Protoss_Assimilator 1 9651
Protoss_Cybernetics_Core 1 11521
12090
