Protoss_Forge 1 3785
Protoss_Nexus 1 7383
Protoss_Photon_Cannon 1 6186
Protoss_Gateway 1 7111
Protoss_Assimilator 1 7832
Protoss_Zealot 5 11916
Protoss_Cybernetics_Core 1 8726
Protoss_Stargate 1 10810
Protoss_Dragoon 1 10612
Protoss_Corsair 2 12291
12291
