Protoss_Forge 1 3851
Protoss_Photon_Cannon 3 7715
Protoss_Nexus 1 8335
Protoss_Gateway 1 8521
Protoss_Assimilator 2 11039
Protoss_Zealot 1 9514
Protoss_Cybernetics_Core 1 10455
Protoss_Dragoon 1 11736
Protoss_Stargate 1 12376
12376
