Protoss_Nexus 1 7152
Protoss_Forge 1 5632
Protoss_Photon_Cannon 2 6999
Protoss_Gateway 1 8026
Protoss_Assimilator 2 11054
Protoss_Zealot 3 12017
Protoss_Cybernetics_Core 1 10272
Protoss_Dragoon 1 11561
Protoss_Citadel_of_Adun 1 12756
12756
