Protoss_Gateway 2 5317
Protoss_Zealot 8 11432
Protoss_Assimilator 1 6352
Protoss_Cybernetics_Core 1 8676
Protoss_Dragoon 1 10017
Protoss_Stargate 1 10715
Protoss_Citadel_of_Adun 1 11549
Protoss_Corsair 1 11834
11834
