Protoss_Forge 1 4157
Protoss_Nexus 1 7833
Protoss_Gateway 3 12503
Protoss_Photon_Cannon 2 7822
Protoss_Assimilator 2 11361
Protoss_Cybernetics_Core 1 9201
Protoss_Zealot 2 10106
Protoss_Citadel_of_Adun 1 11534
12503
