Protoss_Nexus 1 6936
Protoss_Gateway 1 6359
Protoss_Forge 1 6400
Protoss_Photon_Cannon 2 12461
Protoss_Assimilator 2 9312
Protoss_Cybernetics_Core 1 9084
Protoss_Zealot 3 11273
Protoss_Stargate 2 12817
Protoss_Citadel_of_Adun 1 11197
Protoss_Corsair 1 11938
12817
