Protoss_Forge 1 3932
Protoss_Photon_Cannon 2 7898
Protoss_Nexus 1 8477
Protoss_Gateway 3 12326
Protoss_Assimilator 1 7918
Protoss_Cybernetics_Core 1 9457
Protoss_Zealot 3 10995
Protoss_Citadel_of_Adun 1 11212
Protoss_Dragoon 1 12249
12326
