Protoss_Nexus 1 6966
Protoss_Gateway 4 12230
Protoss_Forge 1 6349
Protoss_Assimilator 1 6749
Protoss_Photon_Cannon 1 7670
Protoss_Zealot 6 11511
Protoss_Cybernetics_Core 1 8690
Protoss_Citadel_of_Adun 1 10324
12230
