Protoss_Forge 1 5272
Protoss_Nexus 1 7961
Protoss_Photon_Cannon 3 9032
Protoss_Gateway 1 8109
Protoss_Assimilator 2 11187
Protoss_Zealot 2 10217
Protoss_Cybernetics_Core 1 10461
Protoss_Dragoon 1 11978
Protoss_Citadel_of_Adun 1 12636
12636
