Protoss_Forge 1 4354
Protoss_Photon_Cannon 2 6227
Protoss_Nexus 1 8949
Protoss_Gateway 1 7909
Protoss_Assimilator 2 9680
Protoss_Cybernetics_Core 1 9428
Protoss_Zealot 2 12134
Protoss_Dragoon 1 10792
Protoss_Stargate 1 11564
Protoss_Citadel_of_Adun 1 12255
12255
