Protoss_Nexus 1 6985
Protoss_Forge 1 5751
Protoss_Photon_Cannon 4 12489
Protoss_Gateway 1 7829
Protoss_Assimilator 2 12062
Protoss_Zealot 4 11598
Protoss_Cybernetics_Core 1 10707
Protoss_Stargate 1 12426
12489
