Protoss_Forge 1 4542
Protoss_Nexus 1 7604
Protoss_Photon_Cannon 2 6971
Protoss_Gateway 1 7821
Protoss_Assimilator 2 11474
Protoss_Cybernetics_Core 1 9548
Protoss_Zealot 2 12090
Protoss_Dragoon 1 10997
Protoss_Citadel_of_Adun 1 11611
12090
