Protoss_Forge 1 4417
Protoss_Photon_Cannon 2 7052
Protoss_Nexus 1 8569
Protoss_Gateway 1 8158
Protoss_Assimilator 1 7937
Protoss_Zealot 4 12152
Protoss_Cybernetics_Core 1 9694
Protoss_Citadel_of_Adun 1 11462
12152
