Protoss_Forge 1 4337
Protoss_Nexus 1 7588
Protoss_Photon_Cannon 4 11318
Protoss_Gateway 1 8104
Protoss_Assimilator 2 12266
Protoss_Zealot 2 10618
Protoss_Cybernetics_Core 1 10511
Protoss_Dragoon 1 11834
Protoss_Citadel_of_Adun 1 12154
12266
