Protoss_Forge 1 4296
Protoss_Nexus 1 7742
Protoss_Photon_Cannon 1 7027
Protoss_Gateway 4 12358
Protoss_Assimilator 2 9898
Protoss_Zealot 4 12310
Protoss_Cybernetics_Core 1 9836
Protoss_Citadel_of_Adun 1 11328
12358
