Protoss_Forge 1 5183
Protoss_Nexus 1 7979
Protoss_Photon_Cannon 3 11382
Protoss_Gateway 2 12833
Protoss_Assimilator 2 10025
Protoss_Cybernetics_Core 1 9580
Protoss_Zealot 1 9491
Protoss_Stargate 1 11308
Protoss_Citadel_of_Adun 1 11481
12833
