Protoss_Gateway 2 4925
Protoss_Zealot 7 11834
Protoss_Nexus 1 10596
Protoss_Assimilator 1 9017
Protoss_Forge 1 9517
Protoss_Cybernetics_Core 1 10455
Protoss_Stargate 1 12343
12343
