Protoss_Assimilator 2 7947
Protoss_Gateway 1 4830
Protoss_Cybernetics_Core 1 6333
Protoss_Stargate 2 10193
Protoss_Corsair 6 12034
Protoss_Dragoon 1 9278
Protoss_Forge 1 11772
Protoss_Shield_Battery 1 11653
12034
