Protoss_Forge 1 4101
Protoss_Photon_Cannon 2 6996
Protoss_Nexus 1 9404
Protoss_Gateway 2 11765
Protoss_Assimilator 1 8332
Protoss_Cybernetics_Core 1 10003
Protoss_Zealot 3 11689
Protoss_Citadel_of_Adun 1 11519
11765
