Protoss_Forge 1 4009
Protoss_Nexus 1 7615
Protoss_Photon_Cannon 2 6982
Protoss_Gateway 2 8916
Protoss_Assimilator 1 8909
Protoss_Zealot 3 11648
Protoss_Cybernetics_Core 1 11589
11648
