Protoss_Nexus 1 7208
Protoss_Gateway 3 11333
Protoss_Assimilator 1 6911
Protoss_Cybernetics_Core 1 8260
Protoss_Forge 1 8127
Protoss_Photon_Cannon 1 9493
Protoss_Citadel_of_Adun 1 10302
Protoss_Zealot 5 12302
12302
