Protoss_Forge 1 4034
Protoss_Nexus 1 8013
Protoss_Photon_Cannon 2 7151
Protoss_Assimilator 1 7303
Protoss_Gateway 3 11945
Protoss_Zealot 3 12302
Protoss_Cybernetics_Core 1 10136
Protoss_Dragoon 1 11417
Protoss_Citadel_of_Adun 1 11750
12302
