Protoss_Nexus 1 7132
Protoss_Forge 1 5925
Protoss_Gateway 1 6895
Protoss_Photon_Cannon 2 7811
Protoss_Assimilator 2 10182
Protoss_Cybernetics_Core 1 9476
Protoss_Zealot 2 11970
Protoss_Stargate 1 11286
Protoss_Dragoon 1 10874
Protoss_Citadel_of_Adun 1 12105
Protoss_Corsair 1 12242
12242
