Protoss_Gateway 1 4268
Protoss_Assimilator 1 5031
Protoss_Zealot 5 11417
Protoss_Cybernetics_Core 1 6460
Protoss_Stargate 1 9018
Protoss_Citadel_of_Adun 1 9501
Protoss_Corsair 1 10114
11417
