Protoss_Forge 1 3934
Protoss_Photon_Cannon 2 7254
Protoss_Nexus 1 8692
Protoss_Gateway 1 8165
Protoss_Assimilator 2 11424
Protoss_Zealot 4 11964
Protoss_Cybernetics_Core 1 10133
Protoss_Citadel_of_Adun 1 11780
11964
