Protoss_Forge 1 3711
Protoss_Photon_Cannon 3 8041
Protoss_Nexus 1 8791
Protoss_Assimilator 1 8099
Protoss_Gateway 3 12470
Protoss_Zealot 2 10758
Protoss_Cybernetics_Core 1 11589
12470
