Protoss_Forge 1 4359
Protoss_Photon_Cannon 1 5791
Protoss_Nexus 1 8563
Protoss_Gateway 1 7730
Protoss_Assimilator 2 9877
Protoss_Cybernetics_Core 1 9400
Protoss_Zealot 1 9432
Protoss_Stargate 1 11127
Protoss_Citadel_of_Adun 1 11821
Protoss_Corsair 1 12072
12072
