Protoss_Forge 1 4047
Protoss_Nexus 1 7689
Protoss_Gateway 3 12371
Protoss_Assimilator 1 6765
Protoss_Photon_Cannon 1 8466
Protoss_Zealot 3 12184
Protoss_Cybernetics_Core 1 9915
Protoss_Dragoon 1 11123
Protoss_Citadel_of_Adun 1 11440
12371
