Protoss_Forge 1 4283
Protoss_Nexus 1 7979
Protoss_Gateway 3 11787
Protoss_Photon_Cannon 1 7191
Protoss_Assimilator 1 7294
Protoss_Zealot 4 11827
Protoss_Cybernetics_Core 1 9036
Protoss_Citadel_of_Adun 1 10609
11827
