Protoss_Gateway 2 6529
Protoss_Assimilator 1 4447
Protoss_Cybernetics_Core 1 5875
Protoss_Stargate 1 8033
Protoss_Zealot 6 11746
Protoss_Citadel_of_Adun 1 9293
Protoss_Corsair 1 9134
Protoss_Templar_Archives 1 11041
Protoss_Robotics_Facility 1 12455
Protoss_Dark_Templar 2 12300
Protoss_Forge 1 12217
12455
