Protoss_Forge 1 4091
Protoss_Photon_Cannon 1 5571
Protoss_Nexus 1 8318
Protoss_Gateway 1 7470
Protoss_Assimilator 1 7922
Protoss_Zealot 2 12112
Protoss_Cybernetics_Core 1 12124
12124
