Protoss_Forge 1 4245
Protoss_Nexus 1 7976
Protoss_Photon_Cannon 1 6830
Protoss_Gateway 1 7868
Protoss_Assimilator 2 11184
Protoss_Cybernetics_Core 1 9820
Protoss_Zealot 2 10578
Protoss_Robotics_Facility 1 12036
Protoss_Stargate 1 12223
Protoss_Dragoon 1 12219
12223
