Protoss_Gateway 1 4590
Protoss_Forge 1 5190
Protoss_Zealot 6 11863
Protoss_Photon_Cannon 2 11343
Protoss_Nexus 1 10151
Protoss_Assimilator 2 11290
Protoss_Cybernetics_Core 1 10155
Protoss_Stargate 1 12215
12215
