Protoss_Gateway 1 4447
Protoss_Assimilator 1 4685
Protoss_Zealot 2 7151
Protoss_Cybernetics_Core 1 7130
Protoss_Stargate 1 9050
Protoss_Dragoon 1 9175
Protoss_Corsair 1 10012
Protoss_Citadel_of_Adun 1 10748
Protoss_Forge 1 11278
11278
