Protoss_Forge 1 4169
Protoss_Nexus 1 8254
Protoss_Gateway 4 12438
Protoss_Photon_Cannon 1 7195
Protoss_Assimilator 1 7725
Protoss_Zealot 2 11585
Protoss_Cybernetics_Core 1 9485
Protoss_Citadel_of_Adun 1 11146
12438
