Protoss_Forge 1 3899
Protoss_Photon_Cannon 2 7307
Protoss_Nexus 1 8412
Protoss_Gateway 1 8437
Protoss_Assimilator 2 11044
Protoss_Zealot 4 12204
Protoss_Cybernetics_Core 1 10196
Protoss_Stargate 1 12650
12650
