Protoss_Forge 1 4371
Protoss_Nexus 1 7764
Protoss_Gateway 2 11900
Protoss_Assimilator 2 9570
Protoss_Photon_Cannon 1 7675
Protoss_Cybernetics_Core 1 8920
Protoss_Zealot 1 9090
Protoss_Dragoon 1 10175
Protoss_Stargate 1 10813
Protoss_Citadel_of_Adun 1 11493
Protoss_Corsair 1 11774
11900
