Protoss_Forge 1 4148
Protoss_Photon_Cannon 2 7149
Protoss_Nexus 1 8576
Protoss_Gateway 2 11392
Protoss_Assimilator 2 11982
Protoss_Cybernetics_Core 1 9905
Protoss_Zealot 1 9951
Protoss_Citadel_of_Adun 1 11919
11982
