Protoss_Forge 1 4821
Protoss_Nexus 1 7825
Protoss_Photon_Cannon 1 6294
Protoss_Gateway 1 7343
Protoss_Assimilator 2 11490
Protoss_Zealot 2 9640
Protoss_Cybernetics_Core 1 10654
Protoss_Dragoon 1 11890
Protoss_Stargate 1 12520
12520
