Protoss_Forge 1 4618
Protoss_Photon_Cannon 2 7086
Protoss_Nexus 1 8045
Protoss_Gateway 1 7793
Protoss_Assimilator 2 10340
Protoss_Zealot 2 9570
Protoss_Cybernetics_Core 1 9664
Protoss_Dragoon 1 11000
Protoss_Stargate 1 11807
11807
