Protoss_Forge 1 3959
Protoss_Photon_Cannon 3 10891
Protoss_Nexus 1 8869
Protoss_Gateway 1 7799
Protoss_Zealot 3 10817
Protoss_Cybernetics_Core 1 9653
Protoss_Assimilator 1 11054
11054
