Protoss_Gateway 1 4441
Protoss_Assimilator 1 4698
Protoss_Zealot 2 7414
Protoss_Cybernetics_Core 1 7370
Protoss_Citadel_of_Adun 1 9211
Protoss_Dragoon 1 9183
Protoss_Forge 1 10053
Protoss_Templar_Archives 1 10909
Protoss_Photon_Cannon 1 11827
Protoss_High_Templar 1 12600
12600
