Protoss_Forge 1 4643
Protoss_Nexus 1 7825
Protoss_Gateway 4 12350
Protoss_Assimilator 1 7243
Protoss_Photon_Cannon 1 7826
Protoss_Zealot 5 12214
Protoss_Cybernetics_Core 1 9403
Protoss_Citadel_of_Adun 1 10941
12350
