Protoss_Gateway 2 5229
Protoss_Zealot 10 12130
Protoss_Assimilator 1 5903
Protoss_Cybernetics_Core 1 8136
Protoss_Stargate 1 9830
Protoss_Dragoon 1 9424
Protoss_Corsair 1 10868
12130
