Protoss_Nexus 1 7413
Protoss_Forge 1 5932
Protoss_Gateway 2 12197
Protoss_Photon_Cannon 1 7349
Protoss_Assimilator 2 10836
Protoss_Zealot 4 11651
Protoss_Cybernetics_Core 1 9990
Protoss_Citadel_of_Adun 1 11862
12197
