Protoss_Forge 1 4472
Protoss_Nexus 1 8106
Protoss_Photon_Cannon 2 11698
Protoss_Gateway 1 7299
Protoss_Assimilator 2 10867
Protoss_Zealot 1 8352
Protoss_Cybernetics_Core 1 9405
Protoss_Stargate 1 11312
Protoss_Robotics_Facility 1 12742
Protoss_Corsair 1 12292
12742
