Protoss_Forge 1 4652
Protoss_Nexus 1 7881
Protoss_Photon_Cannon 2 8403
Protoss_Gateway 2 12653
Protoss_Assimilator 1 7829
Protoss_Zealot 2 10188
Protoss_Cybernetics_Core 1 10182
Protoss_Citadel_of_Adun 1 11729
Protoss_Dragoon 1 11495
12653
