Protoss_Forge 1 3725
Protoss_Photon_Cannon 6 11082
Protoss_Nexus 1 10735
Protoss_Gateway 1 9958
Protoss_Assimilator 1 9912
Protoss_Zealot 2 12043
Protoss_Cybernetics_Core 1 12067
12067
