Protoss_Nexus 1 7530
Protoss_Forge 1 6400
Protoss_Gateway 3 12555
Protoss_Photon_Cannon 1 7678
Protoss_Assimilator 2 10600
Protoss_Cybernetics_Core 1 9583
Protoss_Zealot 3 11102
Protoss_Stargate 1 11440
Protoss_Citadel_of_Adun 1 11862
12555
