Protoss_Forge 1 4226
Protoss_Photon_Cannon 2 7181
Protoss_Nexus 1 8449
Protoss_Gateway 2 12775
Protoss_Assimilator 2 11029
Protoss_Zealot 3 11309
Protoss_Cybernetics_Core 1 9874
Protoss_Citadel_of_Adun 1 11360
12775
