Protoss_Forge 1 4259
Protoss_Photon_Cannon 2 7267
Protoss_Nexus 1 8298
Protoss_Gateway 2 12740
Protoss_Assimilator 1 8197
Protoss_Zealot 3 11468
Protoss_Cybernetics_Core 1 9800
Protoss_Citadel_of_Adun 1 11412
Protoss_Dragoon 1 12588
12740
