Protoss_Forge 1 4160
Protoss_Nexus 1 7947
Protoss_Gateway 3 12036
Protoss_Photon_Cannon 1 7312
Protoss_Assimilator 1 7426
Protoss_Cybernetics_Core 1 9128
Protoss_Zealot 3 12118
Protoss_Dragoon 1 10441
Protoss_Citadel_of_Adun 1 11304
12118
