Protoss_Nexus 1 7612
Protoss_Forge 1 6140
Protoss_Gateway 3 12506
Protoss_Photon_Cannon 1 7406
Protoss_Assimilator 2 10114
Protoss_Cybernetics_Core 1 8958
Protoss_Zealot 2 10875
Protoss_Stargate 1 10660
Protoss_Citadel_of_Adun 1 11069
Protoss_Corsair 1 11633
Protoss_Templar_Archives 1 12729
12729
