Protoss_Gateway 1 4291
Protoss_Assimilator 1 4672
Protoss_Cybernetics_Core 1 6046
Protoss_Zealot 5 11373
Protoss_Stargate 1 8094
Protoss_Corsair 2 10223
Protoss_Citadel_of_Adun 1 10135
11373
