Protoss_Forge 1 4331
Protoss_Nexus 1 7515
Protoss_Photon_Cannon 2 7192
Protoss_Gateway 2 10066
Protoss_Assimilator 1 8300
Protoss_Zealot 5 11792
Protoss_Cybernetics_Core 1 11513
11792
