Protoss_Gateway 2 4493
Protoss_Zealot 4 7913
Protoss_Assimilator 1 6633
Protoss_Cybernetics_Core 1 7840
Protoss_Dragoon 1 9039
Protoss_Forge 1 9233
Protoss_Robotics_Facility 1 10851
Protoss_Photon_Cannon 1 11015
Protoss_Shuttle 1 12251
Protoss_Robotics_Support_Bay 1 11732
12251
