Protoss_Forge 1 4675
Protoss_Photon_Cannon 1 6052
Protoss_Nexus 1 7951
Protoss_Gateway 4 12245
Protoss_Assimilator 1 7356
Protoss_Cybernetics_Core 1 9210
Protoss_Zealot 2 9822
Protoss_Citadel_of_Adun 1 10853
Protoss_Dragoon 1 11193
12245
