Protoss_Forge 1 4425
Protoss_Photon_Cannon 1 5779
Protoss_Nexus 1 8417
Protoss_Gateway 2 11235
Protoss_Assimilator 2 11249
Protoss_Zealot 2 9450
Protoss_Cybernetics_Core 1 9134
Protoss_Citadel_of_Adun 1 10929
Protoss_Templar_Archives 1 12778
12778
