Protoss_Forge 1 5484
Protoss_Nexus 1 8159
Protoss_Photon_Cannon 4 11726
Protoss_Gateway 1 9396
Protoss_Assimilator 2 11013
Protoss_Cybernetics_Core 1 10867
Protoss_Zealot 2 11581
Protoss_Stargate 1 12653
12653
