Protoss_Nexus 1 7360
Protoss_Forge 1 5939
Protoss_Photon_Cannon 3 8373
Protoss_Gateway 1 8092
Protoss_Assimilator 1 8811
Protoss_Cybernetics_Core 1 10196
Protoss_Zealot 2 11417
Protoss_Citadel_of_Adun 1 11818
11818
