Protoss_Forge 1 3731
Protoss_Nexus 1 7451
Protoss_Photon_Cannon 2 6985
Protoss_Gateway 4 12296
Protoss_Assimilator 1 7934
Protoss_Cybernetics_Core 1 9765
Protoss_Zealot 4 11982
Protoss_Citadel_of_Adun 1 11285
Protoss_Dragoon 1 11120
12296
