Protoss_Forge 1 3690
Protoss_Nexus 1 7376
Protoss_Photon_Cannon 7 12556
Protoss_Gateway 1 8202
Protoss_Assimilator 2 11139
Protoss_Zealot 2 11885
Protoss_Cybernetics_Core 1 10363
12556
