Protoss_Forge 1 4594
Protoss_Photon_Cannon 3 8534
Protoss_Nexus 1 8302
Protoss_Gateway 1 8206
Protoss_Zealot 3 12034
Protoss_Assimilator 2 10884
Protoss_Cybernetics_Core 1 11464
12034
