Protoss_Nexus 1 7113
Protoss_Forge 1 5669
Protoss_Photon_Cannon 2 7408
Protoss_Gateway 1 7989
Protoss_Assimilator 2 10008
Protoss_Cybernetics_Core 1 9738
Protoss_Robotics_Facility 1 11802
Protoss_Stargate 1 12559
12559
