Protoss_Forge 2 6329
Protoss_Nexus 1 7439
Protoss_Gateway 2 12804
Protoss_Photon_Cannon 1 7731
Protoss_Assimilator 2 10893
Protoss_Zealot 3 10927
Protoss_Cybernetics_Core 1 9530
Protoss_Citadel_of_Adun 1 11348
12804
