Protoss_Forge 1 3892
Protoss_Photon_Cannon 5 12105
Protoss_Nexus 1 8657
Protoss_Gateway 1 8150
Protoss_Assimilator 1 8156
Protoss_Cybernetics_Core 1 9822
Protoss_Zealot 2 11271
Protoss_Citadel_of_Adun 1 11295
12105
