Protoss_Nexus 1 6981
Protoss_Forge 1 5464
Protoss_Photon_Cannon 2 6859
Protoss_Gateway 1 7903
Protoss_Assimilator 2 9708
Protoss_Cybernetics_Core 1 9431
Protoss_Zealot 1 9522
Protoss_Dragoon 1 10668
10668
