Protoss_Gateway 2 5142
Protoss_Zealot 8 10919
Protoss_Assimilator 1 7796
Protoss_Cybernetics_Core 1 9277
Protoss_Stargate 1 11074
Protoss_Dragoon 1 10756
Protoss_Citadel_of_Adun 1 11977
Protoss_Forge 1 12001
12001
