Protoss_Forge 1 4460
Protoss_Photon_Cannon 2 5940
Protoss_Nexus 1 9059
Protoss_Gateway 1 8392
Protoss_Assimilator 2 10799
Protoss_Cybernetics_Core 1 9972
Protoss_Zealot 2 10520
Protoss_Stargate 1 11838
Protoss_Dragoon 1 11640
Protoss_Citadel_of_Adun 1 12194
12194
