Protoss_Forge 1 4057
Protoss_Photon_Cannon 2 5565
Protoss_Gateway 1 6255
Protoss_Zealot 1 7466
Protoss_Assimilator 1 8326
Protoss_Cybernetics_Core 1 9582
Protoss_Stargate 1 11491
Protoss_Nexus 1 13047
Protoss_Dragoon 1 11618
13047
