Protoss_Forge 1 4412
Protoss_Nexus 1 7925
Protoss_Photon_Cannon 1 6890
Protoss_Gateway 1 8070
Protoss_Assimilator 2 10294
Protoss_Zealot 3 10801
Protoss_Cybernetics_Core 1 9950
Protoss_Stargate 1 11920
Protoss_Citadel_of_Adun 1 12222
Protoss_Dragoon 1 12022
12222
