Protoss_Forge 1 4814
Protoss_Nexus 1 7704
Protoss_Photon_Cannon 2 9508
Protoss_Gateway 2 11696
Protoss_Assimilator 2 10921
Protoss_Zealot 2 10114
Protoss_Cybernetics_Core 1 10360
Protoss_Citadel_of_Adun 1 11985
Protoss_Dragoon 1 11890
11985
