Protoss_Forge 1 4183
Protoss_Photon_Cannon 3 9112
Protoss_Nexus 1 8839
Protoss_Gateway 1 8516
Protoss_Assimilator 2 12172
Protoss_Zealot 3 11292
Protoss_Cybernetics_Core 1 11019
Protoss_Citadel_of_Adun 1 12746
12746
