Protoss_Nexus 1 7127
Protoss_Forge 1 5988
Protoss_Gateway 1 6918
Protoss_Assimilator 2 9065
Protoss_Photon_Cannon 1 7334
Protoss_Cybernetics_Core 1 8546
Protoss_Zealot 2 11468
Protoss_Stargate 1 10308
Protoss_Dragoon 1 10010
11468
