Protoss_Forge 1 5067
Protoss_Nexus 1 7846
Protoss_Photon_Cannon 3 9749
Protoss_Gateway 1 8619
Protoss_Zealot 3 11922
Protoss_Assimilator 2 11522
Protoss_Cybernetics_Core 1 10812
11922
