Protoss_Nexus 1 7246
Protoss_Forge 1 5812
Protoss_Photon_Cannon 2 9772
Protoss_Assimilator 2 8230
Protoss_Gateway 1 9579
Protoss_Zealot 2 11614
Protoss_Cybernetics_Core 1 11553
11614
