Protoss_Forge 1 4151
Protoss_Nexus 1 8040
Protoss_Gateway 1 7815
Protoss_Photon_Cannon 3 12164
Protoss_Assimilator 2 10697
Protoss_Zealot 1 9163
Protoss_Cybernetics_Core 1 10404
Protoss_Dragoon 1 11649
Protoss_Stargate 2 12965
12965
