Protoss_Gateway 2 10647
Protoss_Assimilator 1 4704
Protoss_Zealot 6 11876
Protoss_Cybernetics_Core 1 7698
Protoss_Dragoon 1 9227
Protoss_Citadel_of_Adun 1 10051
Protoss_Templar_Archives 1 12210
12210
