Protoss_Nexus 1 7009
Protoss_Forge 1 5727
Protoss_Gateway 1 6828
Protoss_Assimilator 2 9333
Protoss_Photon_Cannon 3 11287
Protoss_Cybernetics_Core 1 8560
Protoss_Stargate 1 10383
Protoss_Dragoon 1 9982
Protoss_Citadel_of_Adun 1 10665
Protoss_Corsair 1 11376
Protoss_Templar_Archives 1 12422
12422
