Protoss_Nexus 1 7200
Protoss_Forge 1 5873
Protoss_Gateway 2 12383
Protoss_Photon_Cannon 3 12026
Protoss_Assimilator 2 9893
Protoss_Cybernetics_Core 1 9040
Protoss_Zealot 2 11358
Protoss_Stargate 1 10810
Protoss_Dragoon 1 10497
Protoss_Citadel_of_Adun 1 11604
Protoss_Corsair 1 11780
12383
