Protoss_Forge 1 4084
Protoss_Nexus 1 8313
Protoss_Photon_Cannon 1 7229
Protoss_Assimilator 1 7972
Protoss_Gateway 3 12460
Protoss_Zealot 3 11636
Protoss_Cybernetics_Core 1 10214
Protoss_Citadel_of_Adun 1 11897
12460
