Protoss_Forge 1 4477
Protoss_Photon_Cannon 6 12474
Protoss_Nexus 1 8717
Protoss_Assimilator 2 11335
Protoss_Gateway 1 8133
Protoss_Cybernetics_Core 1 9967
Protoss_Zealot 1 9713
Protoss_Stargate 1 11688
12474
