Protoss_Forge 1 3803
Protoss_Photon_Cannon 3 7759
Protoss_Nexus 1 9211
Protoss_Gateway 1 8436
Protoss_Assimilator 1 8506
Protoss_Zealot 2 10627
Protoss_Cybernetics_Core 1 10142
Protoss_Citadel_of_Adun 1 11922
Protoss_Dragoon 1 11890
11922
