Protoss_Forge 1 4567
Protoss_Nexus 1 8105
Protoss_Photon_Cannon 1 7068
Protoss_Gateway 1 8253
Protoss_Assimilator 1 8698
Protoss_Cybernetics_Core 1 9732
Protoss_Zealot 3 11775
Protoss_Citadel_of_Adun 1 12067
12067
