Protoss_Forge 1 3870
Protoss_Photon_Cannon 2 6339
Protoss_Nexus 1 9600
Protoss_Gateway 1 8575
Protoss_Assimilator 2 11197
Protoss_Zealot 2 10451
Protoss_Cybernetics_Core 1 10815
Protoss_Citadel_of_Adun 1 12381
12381
