Protoss_Forge 1 4325
Protoss_Nexus 1 7954
Protoss_Photon_Cannon 1 6691
Protoss_Gateway 1 8033
Protoss_Assimilator 2 12203
Protoss_Zealot 2 9883
Protoss_Cybernetics_Core 1 10757
Protoss_Citadel_of_Adun 1 12479
12479
