Protoss_Forge 1 4628
Protoss_Photon_Cannon 3 12285
Protoss_Nexus 1 8276
Protoss_Gateway 1 7938
Protoss_Assimilator 2 10073
Protoss_Cybernetics_Core 1 9424
Protoss_Zealot 2 11658
Protoss_Stargate 1 11386
12285
