Protoss_Forge 1 4284
Protoss_Photon_Cannon 1 5697
Protoss_Nexus 1 8357
Protoss_Gateway 1 7331
Protoss_Assimilator 1 8212
Protoss_Zealot 5 11825
Protoss_Cybernetics_Core 1 9431
Protoss_Citadel_of_Adun 1 11404
11825
