Protoss_Forge 1 4019
Protoss_Photon_Cannon 4 9901
Protoss_Gateway 1 8159
Protoss_Nexus 1 10617
Protoss_Assimilator 2 11890
Protoss_Zealot 3 11973
Protoss_Cybernetics_Core 1 11077
11973
