Protoss_Forge 1 4403
Protoss_Photon_Cannon 1 6061
Protoss_Nexus 1 8512
Protoss_Gateway 1 7741
Protoss_Assimilator 2 10368
Protoss_Zealot 4 12324
Protoss_Cybernetics_Core 1 9334
Protoss_Dragoon 1 11136
Protoss_Citadel_of_Adun 2 12504
12504
