Protoss_Forge 1 4458
Protoss_Photon_Cannon 2 5951
Protoss_Nexus 1 9037
Protoss_Gateway 1 8641
Protoss_Assimilator 2 10555
Protoss_Cybernetics_Core 1 10269
Protoss_Zealot 1 10100
Protoss_Stargate 1 12091
Protoss_Robotics_Facility 1 13119
13119
