Protoss_Forge 1 4117
Protoss_Nexus 1 7713
Protoss_Photon_Cannon 1 6354
Protoss_Gateway 4 12746
Protoss_Assimilator 2 9949
Protoss_Zealot 4 11622
Protoss_Cybernetics_Core 1 9105
Protoss_Citadel_of_Adun 1 10843
12746
