Protoss_Nexus 1 7408
Protoss_Forge 1 5914
Protoss_Photon_Cannon 1 7349
Protoss_Gateway 4 12475
Protoss_Assimilator 2 12166
Protoss_Zealot 2 10912
Protoss_Cybernetics_Core 1 10695
Protoss_Citadel_of_Adun 1 12160
12475
