Protoss_Forge 2 12353
Protoss_Nexus 1 7399
Protoss_Photon_Cannon 2 8654
Protoss_Gateway 1 6961
Protoss_Assimilator 2 12185
Protoss_Zealot 2 9324
Protoss_Cybernetics_Core 1 10818
Protoss_Citadel_of_Adun 1 12532
12532
