Protoss_Forge 1 4242
Protoss_Photon_Cannon 3 7577
Protoss_Nexus 1 9827
Protoss_Gateway 4 12797
Protoss_Assimilator 1 8875
Protoss_Cybernetics_Core 1 10755
Protoss_Zealot 3 12203
Protoss_Citadel_of_Adun 1 12345
12797
