Protoss_Forge 1 4217
Protoss_Photon_Cannon 3 12528
Protoss_Nexus 1 8753
Protoss_Gateway 1 7755
Protoss_Assimilator 2 11639
Protoss_Cybernetics_Core 1 9223
Protoss_Zealot 3 11092
Protoss_Stargate 1 11427
12528
