Protoss_Forge 1 5372
Protoss_Nexus 1 7521
Protoss_Photon_Cannon 2 7962
Protoss_Gateway 1 7366
Protoss_Assimilator 2 9428
Protoss_Zealot 2 11452
Protoss_Cybernetics_Core 1 10836
Protoss_Citadel_of_Adun 1 12664
12664
