Protoss_Gateway 2 5304
Protoss_Zealot 5 11878
Protoss_Assimilator 1 6345
Protoss_Cybernetics_Core 1 7894
Protoss_Dragoon 1 9329
Protoss_Citadel_of_Adun 1 10463
Protoss_Forge 1 11420
11878
