Protoss_Forge 2 6394
Protoss_Nexus 1 7325
Protoss_Gateway 3 12576
Protoss_Photon_Cannon 2 8082
Protoss_Zealot 3 10085
Protoss_Assimilator 2 10457
Protoss_Cybernetics_Core 1 10425
Protoss_Dragoon 1 11671
12576
