Protoss_Nexus 1 7304
Protoss_Forge 1 5917
Protoss_Photon_Cannon 3 9830
Protoss_Gateway 2 12305
Protoss_Assimilator 2 12232
Protoss_Zealot 2 10480
Protoss_Cybernetics_Core 1 10628
Protoss_Citadel_of_Adun 1 12137
Protoss_Dragoon 1 12117
12305
