Protoss_Forge 1 4350
Protoss_Nexus 1 7881
Protoss_Photon_Cannon 1 6691
Protoss_Gateway 2 11758
Protoss_Assimilator 2 11739
Protoss_Zealot 4 11808
Protoss_Cybernetics_Core 1 10771
Protoss_Citadel_of_Adun 1 12409
12409
