Protoss_Forge 1 4668
Protoss_Nexus 1 7720
Protoss_Photon_Cannon 1 6500
Protoss_Gateway 1 7874
Protoss_Assimilator 2 11092
Protoss_Zealot 3 11944
Protoss_Cybernetics_Core 1 9861
Protoss_Dragoon 2 12149
Protoss_Stargate 1 11915
12149
