Protoss_Gateway 1 4329
Protoss_Assimilator 1 4552
Protoss_Zealot 3 7267
Protoss_Cybernetics_Core 1 7193
Protoss_Dragoon 1 8861
Protoss_Stargate 1 9622
Protoss_Citadel_of_Adun 1 10155
Protoss_Scout 1 11741
Protoss_Templar_Archives 1 11791
Protoss_Forge 1 12185
12185
