Protoss_Forge 1 4012
Protoss_Nexus 1 7773
Protoss_Gateway 2 11942
Protoss_Photon_Cannon 3 11820
Protoss_Assimilator 2 9545
Protoss_Zealot 1 8502
Protoss_Cybernetics_Core 1 9422
Protoss_Citadel_of_Adun 1 10909
Protoss_Templar_Archives 1 12468
12468
