Protoss_Forge 1 4132
Protoss_Nexus 1 7875
Protoss_Photon_Cannon 2 7033
Protoss_Gateway 2 12817
Protoss_Assimilator 2 10521
Protoss_Zealot 2 11600
Protoss_Cybernetics_Core 1 10395
Protoss_Citadel_of_Adun 1 12061
12817
