Protoss_Forge 1 4278
Protoss_Nexus 1 7691
Protoss_Photon_Cannon 2 7552
Protoss_Gateway 2 11607
Protoss_Assimilator 2 10117
Protoss_Zealot 2 10565
Protoss_Cybernetics_Core 1 9999
Protoss_Stargate 1 11687
Protoss_Citadel_of_Adun 1 12213
12213
