Protoss_Forge 1 3848
Protoss_Photon_Cannon 2 8738
Protoss_Nexus 1 8847
Protoss_Gateway 1 7831
Protoss_Assimilator 2 12348
Protoss_Cybernetics_Core 1 9324
Protoss_Zealot 2 9971
Protoss_Stargate 1 11266
Protoss_Dragoon 1 11252
Protoss_Citadel_of_Adun 1 12643
12643
