Protoss_Forge 1 5190
Protoss_Nexus 1 7790
Protoss_Photon_Cannon 2 7787
Protoss_Gateway 4 12623
Protoss_Assimilator 2 10551
Protoss_Cybernetics_Core 1 9904
Protoss_Zealot 2 10685
Protoss_Citadel_of_Adun 1 11569
12623
