Protoss_Nexus 1 7257
Protoss_Forge 1 5875
Protoss_Photon_Cannon 2 8015
Protoss_Gateway 2 11483
Protoss_Assimilator 2 11882
Protoss_Zealot 2 11171
Protoss_Cybernetics_Core 1 12029
12029
