Protoss_Gateway 1 3994
Protoss_Zealot 6 10896
Protoss_Nexus 1 8913
Protoss_Assimilator 1 7313
Protoss_Cybernetics_Core 1 9359
Protoss_Stargate 1 11293
Protoss_Citadel_of_Adun 1 11560
Protoss_Forge 1 11587
11587
