Protoss_Forge 1 4157
Protoss_Photon_Cannon 4 10051
Protoss_Nexus 1 9570
Protoss_Gateway 1 8758
Protoss_Zealot 3 11849
Protoss_Assimilator 1 10335
Protoss_Cybernetics_Core 1 12185
12185
