Protoss_Forge 1 4125
Protoss_Photon_Cannon 3 11698
Protoss_Nexus 1 8048
Protoss_Gateway 2 12696
Protoss_Assimilator 2 9907
Protoss_Cybernetics_Core 1 10220
Protoss_Zealot 1 11686
12696
