Protoss_Forge 1 4397
Protoss_Photon_Cannon 2 6862
Protoss_Nexus 1 8109
Protoss_Gateway 1 8155
Protoss_Assimilator 2 10553
Protoss_Cybernetics_Core 1 9789
Protoss_Zealot 1 9684
10553
