Protoss_Forge 1 4322
Protoss_Photon_Cannon 3 12281
Protoss_Nexus 1 8741
Protoss_Gateway 1 7499
Protoss_Assimilator 2 11871
Protoss_Zealot 2 9591
Protoss_Cybernetics_Core 1 9860
Protoss_Stargate 1 11582
Protoss_Citadel_of_Adun 1 12030
12281
