Protoss_Gateway 2 4994
Protoss_Zealot 8 9602
Protoss_Assimilator 1 7556
Protoss_Cybernetics_Core 2 10628
Protoss_Stargate 1 11187
Protoss_Dragoon 1 10795
Protoss_Citadel_of_Adun 1 11639
Protoss_Forge 1 12020
12020
