Protoss_Assimilator 1 2689
Protoss_Gateway 1 4422
Protoss_Cybernetics_Core 1 6087
Protoss_Stargate 2 8301
Protoss_Corsair 7 11912
Protoss_Forge 1 11244
Protoss_Photon_Cannon 1 12496
12496
