Protoss_Gateway 1 4130
Protoss_Assimilator 1 4373
Protoss_Zealot 5 11256
Protoss_Cybernetics_Core 1 6760
Protoss_Stargate 1 8438
Protoss_Dragoon 1 7997
Protoss_Citadel_of_Adun 1 8889
Protoss_Forge 1 8850
Protoss_Corsair 2 10975
Protoss_Templar_Archives 1 10474
Protoss_Photon_Cannon 1 11575
Protoss_Dark_Templar 1 11694
11694
