Protoss_Gateway 2 10577
Protoss_Assimilator 2 7280
Protoss_Cybernetics_Core 1 6067
Protoss_Zealot 3 10173
Protoss_Stargate 1 7884
Protoss_Dragoon 3 11621
Protoss_Corsair 1 8835
11621
