Protoss_Forge 1 3831
Protoss_Nexus 1 8001
Protoss_Photon_Cannon 3 8706
Protoss_Gateway 1 8469
Protoss_Assimilator 2 12157
Protoss_Zealot 2 11013
Protoss_Cybernetics_Core 1 10723
Protoss_Citadel_of_Adun 1 12396
Protoss_Dragoon 1 12193
12396
