Protoss_Forge 1 4286
Protoss_Nexus 1 7720
Protoss_Photon_Cannon 1 6486
Protoss_Gateway 1 7507
Protoss_Assimilator 2 10912
Protoss_Cybernetics_Core 1 9487
Protoss_Zealot 2 10352
Protoss_Stargate 1 11391
Protoss_Citadel_of_Adun 1 11758
11758
