Protoss_Forge 1 4167
Protoss_Nexus 1 7878
Protoss_Photon_Cannon 4 12054
Protoss_Gateway 1 7846
Protoss_Assimilator 1 7498
Protoss_Cybernetics_Core 1 9348
Protoss_Stargate 1 11047
Protoss_Robotics_Facility 1 12690
Protoss_Corsair 1 12052
12690
