Protoss_Forge 1 4352
Protoss_Photon_Cannon 2 5951
Protoss_Nexus 1 9586
Protoss_Gateway 1 8985
Protoss_Assimilator 2 10887
Protoss_Zealot 2 10973
Protoss_Cybernetics_Core 1 10711
Protoss_Stargate 1 12618
Protoss_Citadel_of_Adun 1 12656
12656
