Protoss_Forge 1 4439
Protoss_Photon_Cannon 2 5750
Protoss_Nexus 1 9093
Protoss_Gateway 1 8218
Protoss_Assimilator 1 8117
Protoss_Zealot 3 11999
Protoss_Cybernetics_Core 1 10031
11999
