Protoss_Forge 1 3649
Protoss_Nexus 1 7269
Protoss_Photon_Cannon 2 6496
Protoss_Gateway 3 12570
Protoss_Assimilator 1 8537
Protoss_Zealot 3 11490
Protoss_Cybernetics_Core 1 10005
Protoss_Citadel_of_Adun 1 11613
12570
