Protoss_Gateway 1 4313
Protoss_Assimilator 1 4480
Protoss_Zealot 5 12134
Protoss_Forge 1 6525
Protoss_Cybernetics_Core 1 9118
Protoss_Stargate 1 10832
Protoss_Dragoon 1 10500
Protoss_Citadel_of_Adun 1 11383
Protoss_Corsair 1 11790
12134
