Protoss_Gateway 2 5361
Protoss_Zealot 7 12024
Protoss_Assimilator 1 6194
Protoss_Cybernetics_Core 1 7438
Protoss_Stargate 1 9527
Protoss_Dragoon 1 9885
Protoss_Corsair 1 10473
Protoss_Citadel_of_Adun 1 11388
Protoss_Templar_Archives 1 12841
12841
