Protoss_Forge 1 4381
Protoss_Photon_Cannon 2 5880
Protoss_Nexus 1 9216
Protoss_Gateway 1 8279
Protoss_Assimilator 2 9792
Protoss_Cybernetics_Core 1 9807
Protoss_Zealot 2 10390
Protoss_Citadel_of_Adun 1 11357
Protoss_Dragoon 1 11510
11510
