Protoss_Gateway 1 4202
Protoss_Zealot 9 12301
Protoss_Nexus 1 9286
Protoss_Assimilator 1 8310
Protoss_Forge 2 9296
Protoss_Cybernetics_Core 1 11963
Protoss_Photon_Cannon 1 12424
12424
