Protoss_Nexus 1 7274
Protoss_Gateway 1 6511
Protoss_Assimilator 2 8666
Protoss_Cybernetics_Core 1 8033
Protoss_Stargate 2 10547
Protoss_Forge 1 10606
Protoss_Corsair 3 11863
Protoss_Photon_Cannon 2 12566
12566
