Protoss_Nexus 1 7132
Protoss_Forge 1 5774
Protoss_Photon_Cannon 3 8545
Protoss_Gateway 1 8701
Protoss_Assimilator 1 8629
Protoss_Zealot 2 10928
Protoss_Cybernetics_Core 1 12541
12541
