Protoss_Forge 1 5294
Protoss_Nexus 1 7875
Protoss_Photon_Cannon 2 11810
Protoss_Gateway 1 7631
Protoss_Assimilator 2 12175
Protoss_Zealot 4 11352
Protoss_Cybernetics_Core 1 9146
Protoss_Stargate 1 11421
Protoss_Citadel_of_Adun 1 12324
12324
