Protoss_Gateway 2 5121
Protoss_Zealot 8 12010
Protoss_Forge 1 8487
Protoss_Photon_Cannon 1 9756
Protoss_Assimilator 1 9665
Protoss_Cybernetics_Core 1 10689
Protoss_Citadel_of_Adun 1 12618
12618
