Protoss_Forge 1 4496
Protoss_Nexus 1 7680
Protoss_Gateway 1 6811
Protoss_Photon_Cannon 2 11224
Protoss_Assimilator 2 10502
Protoss_Cybernetics_Core 1 8821
Protoss_Zealot 1 8742
Protoss_Stargate 1 10768
Protoss_Robotics_Facility 1 12711
Protoss_Corsair 1 11818
12711
