Protoss_Gateway 1 3955
Protoss_Zealot 7 12334
Protoss_Assimilator 1 6128
Protoss_Cybernetics_Core 1 7732
Protoss_Dragoon 1 9183
Protoss_Stargate 1 9982
Protoss_Forge 1 9648
Protoss_Corsair 1 11102
Protoss_Citadel_of_Adun 1 12355
12355
