Protoss_Nexus 1 6766
Protoss_Forge 1 5532
Protoss_Gateway 1 7255
Protoss_Photon_Cannon 1 7500
Protoss_Assimilator 2 10116
Protoss_Zealot 5 12111
Protoss_Cybernetics_Core 1 9655
Protoss_Stargate 1 11741
Protoss_Robotics_Facility 1 12785
12785
