Protoss_Gateway 1 3637
Protoss_Zealot 5 9839
Protoss_Assimilator 1 5879
Protoss_Cybernetics_Core 1 8541
Protoss_Stargate 1 10412
Protoss_Dragoon 1 11428
Protoss_Corsair 1 11475
11475
