Protoss_Nexus 1 7508
Protoss_Forge 1 6269
Protoss_Photon_Cannon 2 8191
Protoss_Assimilator 1 8373
Protoss_Gateway 3 12822
Protoss_Cybernetics_Core 1 10947
Protoss_Zealot 2 11629
Protoss_Citadel_of_Adun 1 12667
12822
