Protoss_Gateway 2 8711
Protoss_Assimilator 1 4719
Protoss_Zealot 6 11490
Protoss_Cybernetics_Core 1 7682
Protoss_Citadel_of_Adun 1 9888
Protoss_Dragoon 1 10024
Protoss_Templar_Archives 1 11827
Protoss_Forge 1 12351
12351
