Protoss_Forge 2 9702
Protoss_Photon_Cannon 3 7320
Protoss_Nexus 1 8554
Protoss_Assimilator 2 11912
Protoss_Gateway 2 12381
Protoss_Zealot 2 11124
Protoss_Cybernetics_Core 1 11095
12381
