Protoss_Nexus 1 7015
Protoss_Forge 1 5530
Protoss_Gateway 3 12365
Protoss_Photon_Cannon 1 7261
Protoss_Assimilator 1 7343
Protoss_Zealot 4 12089
Protoss_Cybernetics_Core 1 9269
Protoss_Citadel_of_Adun 1 10726
12365
