Protoss_Forge 1 4196
Protoss_Photon_Cannon 2 5902
Protoss_Nexus 1 8993
Protoss_Gateway 3 11816
Protoss_Assimilator 1 8076
Protoss_Cybernetics_Core 1 9431
Protoss_Zealot 2 11717
Protoss_Citadel_of_Adun 1 11057
11816
