Protoss_Forge 1 4524
Protoss_Photon_Cannon 2 6025
Protoss_Nexus 1 9646
Protoss_Gateway 1 8828
Protoss_Assimilator 2 11162
Protoss_Cybernetics_Core 1 10433
Protoss_Zealot 2 11527
Protoss_Citadel_of_Adun 1 11933
11933
