Protoss_Forge 1 4215
Protoss_Photon_Cannon 2 7154
Protoss_Nexus 1 8359
Protoss_Gateway 1 8499
Protoss_Assimilator 2 11601
Protoss_Zealot 4 12198
Protoss_Cybernetics_Core 1 10265
Protoss_Citadel_of_Adun 1 12280
12280
