Protoss_Forge 1 3989
Protoss_Photon_Cannon 2 7415
Protoss_Nexus 1 8532
Protoss_Gateway 1 8231
Protoss_Assimilator 2 11336
Protoss_Zealot 3 10998
Protoss_Cybernetics_Core 1 10422
Protoss_Stargate 1 12918
12918
