Protoss_Gateway 2 9994
Protoss_Assimilator 1 4710
Protoss_Zealot 5 11834
Protoss_Cybernetics_Core 1 7183
Protoss_Dragoon 1 8451
Protoss_Citadel_of_Adun 1 9007
Protoss_Templar_Archives 1 11913
11913
