Protoss_Forge 1 3929
Protoss_Nexus 1 8020
Protoss_Photon_Cannon 2 10583
Protoss_Assimilator 2 9607
Protoss_Gateway 1 8319
Protoss_Cybernetics_Core 1 9890
Protoss_Zealot 1 9888
Protoss_Robotics_Facility 1 12003
Protoss_Stargate 1 12448
12448
