Protoss_Forge 1 4502
Protoss_Photon_Cannon 2 6026
Protoss_Nexus 1 8659
Protoss_Gateway 1 8278
Protoss_Assimilator 2 11361
Protoss_Zealot 3 11475
Protoss_Cybernetics_Core 1 10103
Protoss_Stargate 1 11808
Protoss_Citadel_of_Adun 1 12390
12390
