Protoss_Forge 1 4296
Protoss_Photon_Cannon 2 5918
Protoss_Nexus 1 8800
Protoss_Gateway 2 12735
Protoss_Assimilator 2 10767
Protoss_Cybernetics_Core 1 9248
Protoss_Zealot 2 9848
Protoss_Citadel_of_Adun 1 10925
Protoss_Templar_Archives 1 12602
12735
