Protoss_Forge 1 4916
Protoss_Nexus 1 7577
Protoss_Photon_Cannon 3 9487
Protoss_Gateway 1 7474
Protoss_Zealot 5 11552
Protoss_Assimilator 2 11126
Protoss_Cybernetics_Core 1 10445
Protoss_Stargate 1 12152
Protoss_Citadel_of_Adun 1 12737
12737
