Protoss_Nexus 1 7058
Protoss_Forge 1 5882
Protoss_Photon_Cannon 2 12017
Protoss_Gateway 1 7749
Protoss_Assimilator 1 8284
Protoss_Zealot 3 10832
Protoss_Cybernetics_Core 1 10047
Protoss_Citadel_of_Adun 1 11825
12017
