Protoss_Forge 1 4082
Protoss_Photon_Cannon 2 6338
Protoss_Nexus 1 9050
Protoss_Gateway 3 12460
Protoss_Assimilator 1 8426
Protoss_Cybernetics_Core 1 9548
Protoss_Zealot 2 10422
Protoss_Citadel_of_Adun 1 11891
12460
