Protoss_Nexus 1 6886
Protoss_Gateway 2 6593
Protoss_Zealot 7 11449
Protoss_Forge 1 8537
Protoss_Assimilator 1 10002
Protoss_Photon_Cannon 2 10980
Protoss_Cybernetics_Core 1 11647
11647
