Protoss_Forge 1 3996
Protoss_Photon_Cannon 1 5908
Protoss_Nexus 1 8440
Protoss_Gateway 3 11930
Protoss_Assimilator 1 7834
Protoss_Cybernetics_Core 1 9836
Protoss_Zealot 4 11849
Protoss_Citadel_of_Adun 1 11568
11930
