Protoss_Nexus 1 7370
Protoss_Forge 1 5954
Protoss_Photon_Cannon 2 12391
Protoss_Gateway 1 7982
Protoss_Assimilator 1 8001
Protoss_Zealot 3 11793
Protoss_Cybernetics_Core 1 11183
12391
