Protoss_Forge 1 4106
Protoss_Nexus 1 7732
Protoss_Gateway 1 6883
Protoss_Assimilator 2 11287
Protoss_Zealot 5 12023
Protoss_Cybernetics_Core 1 8464
Protoss_Photon_Cannon 1 8697
Protoss_Stargate 1 10360
Protoss_Corsair 1 11335
Protoss_Citadel_of_Adun 1 12380
12380
