Protoss_Forge 1 4097
Protoss_Nexus 1 7991
Protoss_Gateway 3 12541
Protoss_Photon_Cannon 1 7261
Protoss_Assimilator 2 11257
Protoss_Zealot 4 10985
Protoss_Cybernetics_Core 1 9168
Protoss_Citadel_of_Adun 1 11152
Protoss_Dragoon 1 12105
12541
