Protoss_Nexus 1 7540
Protoss_Forge 1 6159
Protoss_Gateway 2 12753
Protoss_Photon_Cannon 1 7617
Protoss_Assimilator 2 9788
Protoss_Zealot 3 10289
Protoss_Cybernetics_Core 1 9489
Protoss_Stargate 1 11227
Protoss_Citadel_of_Adun 1 11423
Protoss_Dragoon 1 12424
Protoss_Corsair 1 12229
12753
