Protoss_Forge 1 4252
Protoss_Photon_Cannon 2 7214
Protoss_Nexus 1 8383
Protoss_Gateway 3 11977
Protoss_Assimilator 1 8143
Protoss_Cybernetics_Core 1 9937
Protoss_Zealot 3 11797
Protoss_Citadel_of_Adun 1 11509
11977
