Protoss_Nexus 1 7214
Protoss_Gateway 1 6383
Protoss_Forge 1 6722
Protoss_Photon_Cannon 2 10631
Protoss_Zealot 4 12152
Protoss_Assimilator 2 10703
Protoss_Cybernetics_Core 1 9948
Protoss_Dragoon 1 11196
Protoss_Stargate 1 12100
Protoss_Citadel_of_Adun 1 12367
12367
