Protoss_Forge 1 3785
Protoss_Photon_Cannon 2 5899
Protoss_Nexus 1 8913
Protoss_Gateway 2 12779
Protoss_Cybernetics_Core 1 9431
Protoss_Assimilator 2 11860
Protoss_Zealot 3 11995
Protoss_Stargate 1 12106
12779
