Protoss_Nexus 1 7073
Protoss_Gateway 3 11923
Protoss_Forge 1 6274
Protoss_Assimilator 1 6825
Protoss_Photon_Cannon 2 10905
Protoss_Cybernetics_Core 1 8875
Protoss_Zealot 1 8830
Protoss_Dragoon 1 10289
Protoss_Citadel_of_Adun 1 10745
11923
