Protoss_Gateway 1 4252
Protoss_Assimilator 1 4537
Protoss_Cybernetics_Core 1 5824
Protoss_Zealot 3 9447
Protoss_Citadel_of_Adun 1 7924
Protoss_Templar_Archives 1 9429
Protoss_Stargate 1 10366
Protoss_Dark_Templar 2 12033
Protoss_Corsair 1 11511
12033
