Protoss_Nexus 1 7098
Protoss_Forge 1 6059
Protoss_Gateway 1 7053
Protoss_Assimilator 2 9664
Protoss_Photon_Cannon 2 9339
Protoss_Cybernetics_Core 1 9021
Protoss_Zealot 1 10041
Protoss_Stargate 2 12915
Protoss_Robotics_Facility 1 12585
Protoss_Citadel_of_Adun 1 12766
Protoss_Corsair 1 12339
12915
