Protoss_Gateway 2 9418
Protoss_Assimilator 1 4375
Protoss_Zealot 7 11294
Protoss_Cybernetics_Core 1 7015
Protoss_Dragoon 1 8211
Protoss_Citadel_of_Adun 1 8863
Protoss_Templar_Archives 1 11369
Protoss_Forge 1 12201
12201
