Protoss_Nexus 1 7170
Protoss_Forge 1 5575
Protoss_Photon_Cannon 2 7222
Protoss_Gateway 1 7943
Protoss_Assimilator 2 12111
Protoss_Zealot 1 9008
Protoss_Cybernetics_Core 1 9965
Protoss_Dragoon 1 11761
Protoss_Stargate 1 12486
12486
