Protoss_Forge 1 4625
Protoss_Nexus 1 7980
Protoss_Gateway 1 7401
Protoss_Assimilator 2 10793
Protoss_Photon_Cannon 2 8387
Protoss_Cybernetics_Core 1 9432
Protoss_Zealot 2 10334
Protoss_Stargate 1 11122
Protoss_Citadel_of_Adun 1 12064
Protoss_Dragoon 1 12306
Protoss_Corsair 1 12248
12306
