Protoss_Forge 1 3836
Protoss_Photon_Cannon 4 9272
Protoss_Gateway 1 8007
Protoss_Nexus 1 10029
Protoss_Assimilator 2 11241
Protoss_Cybernetics_Core 1 11607
Protoss_Zealot 1 11923
11923
