Protoss_Forge 1 3658
Protoss_Nexus 1 7568
Protoss_Gateway 3 11669
Protoss_Photon_Cannon 2 12013
Protoss_Assimilator 1 7040
Protoss_Zealot 5 12362
Protoss_Cybernetics_Core 1 9343
Protoss_Citadel_of_Adun 1 10908
12362
