Protoss_Forge 1 4150
Protoss_Photon_Cannon 2 6451
Protoss_Nexus 1 9756
Protoss_Gateway 3 12668
Protoss_Assimilator 1 8486
Protoss_Cybernetics_Core 1 10207
Protoss_Dragoon 1 11422
Protoss_Zealot 1 11234
Protoss_Citadel_of_Adun 1 12197
12668
