Protoss_Forge 1 4005
Protoss_Photon_Cannon 2 5805
Protoss_Nexus 1 8695
Protoss_Gateway 1 7530
Protoss_Assimilator 1 7413
Protoss_Zealot 2 9924
Protoss_Cybernetics_Core 1 10707
Protoss_Citadel_of_Adun 1 12662
12662
