Protoss_Forge 1 4151
Protoss_Photon_Cannon 3 11493
Protoss_Gateway 1 6971
Protoss_Nexus 1 8815
Protoss_Assimilator 1 8528
Protoss_Zealot 4 11581
Protoss_Cybernetics_Core 1 10283
11581
