Protoss_Forge 1 4486
Protoss_Nexus 1 7988
Protoss_Gateway 1 7631
Protoss_Assimilator 2 11074
Protoss_Photon_Cannon 2 9957
Protoss_Cybernetics_Core 1 9102
Protoss_Zealot 3 11265
Protoss_Citadel_of_Adun 1 11361
11361
