Protoss_Nexus 1 7471
Protoss_Gateway 1 7051
Protoss_Assimilator 2 9365
Protoss_Cybernetics_Core 1 8789
Protoss_Zealot 1 8619
Protoss_Stargate 1 10497
Protoss_Dragoon 1 10892
Protoss_Citadel_of_Adun 1 11393
Protoss_Corsair 1 11461
11461
