Protoss_Forge 1 5007
Protoss_Photon_Cannon 5 12474
Protoss_Nexus 1 9605
Protoss_Gateway 1 8989
Protoss_Assimilator 2 10812
Protoss_Cybernetics_Core 1 10529
Protoss_Zealot 2 11440
Protoss_Stargate 1 12316
12474
