Protoss_Gateway 2 11851
Protoss_Zealot 4 8540
Protoss_Assimilator 1 5660
Protoss_Cybernetics_Core 1 7445
Protoss_Stargate 1 9382
Protoss_Dragoon 1 9660
Protoss_Citadel_of_Adun 1 10208
Protoss_Corsair 1 10416
Protoss_Templar_Archives 1 12264
12264
