Protoss_Gateway 1 4306
Protoss_Zealot 3 10492
Protoss_Assimilator 1 5733
Protoss_Cybernetics_Core 1 7401
Protoss_Dragoon 1 8594
Protoss_Stargate 1 9258
Protoss_Forge 1 9725
Protoss_Corsair 1 10255
Protoss_Photon_Cannon 1 12061
12061
