Protoss_Forge 1 4335
Protoss_Nexus 1 7822
Protoss_Photon_Cannon 1 6584
Protoss_Gateway 1 7776
Protoss_Assimilator 2 10090
Protoss_Cybernetics_Core 1 9601
Protoss_Zealot 3 12105
12105
