Protoss_Forge 1 4423
Protoss_Nexus 1 7802
Protoss_Photon_Cannon 3 12569
Protoss_Gateway 1 8089
Protoss_Assimilator 2 10347
Protoss_Cybernetics_Core 1 9599
Protoss_Zealot 1 9526
Protoss_Dragoon 1 10801
Protoss_Stargate 1 11640
Protoss_Citadel_of_Adun 1 12100
12569
