Protoss_Gateway 1 3669
Protoss_Zealot 6 10474
Protoss_Assimilator 1 5993
Protoss_Cybernetics_Core 1 7621
Protoss_Stargate 1 9441
Protoss_Forge 1 9081
Protoss_Dragoon 1 9730
Protoss_Photon_Cannon 1 10394
Protoss_Citadel_of_Adun 1 12522
12522
