Protoss_Forge 1 3832
Protoss_Photon_Cannon 3 8275
Protoss_Nexus 1 7966
Protoss_Gateway 2 12058
Protoss_Assimilator 2 9547
Protoss_Cybernetics_Core 1 9756
Protoss_Zealot 2 10843
Protoss_Stargate 1 11485
Protoss_Citadel_of_Adun 1 11645
12058
