Protoss_Forge 1 3861
Protoss_Photon_Cannon 2 7956
Protoss_Nexus 1 8727
Protoss_Gateway 1 7697
Protoss_Zealot 3 11391
Protoss_Assimilator 1 9383
Protoss_Cybernetics_Core 1 11347
11391
