Protoss_Forge 1 3888
Protoss_Photon_Cannon 2 5843
Protoss_Nexus 1 9161
Protoss_Gateway 1 8364
Protoss_Assimilator 2 11475
Protoss_Cybernetics_Core 1 9948
Protoss_Zealot 2 10372
Protoss_Stargate 1 11794
11794
