Protoss_Nexus 1 7007
Protoss_Gateway 2 11717
Protoss_Assimilator 2 9757
Protoss_Forge 1 7419
Protoss_Cybernetics_Core 1 8306
Protoss_Photon_Cannon 1 8668
Protoss_Zealot 2 11657
Protoss_Stargate 1 10052
Protoss_Dragoon 1 10310
Protoss_Citadel_of_Adun 1 11007
Protoss_Corsair 2 12075
Protoss_Templar_Archives 1 12456
12456
