Protoss_Gateway 1 4296
Protoss_Assimilator 1 4571
Protoss_Cybernetics_Core 1 5882
Protoss_Stargate 1 7606
Protoss_Corsair 4 11622
Protoss_Nexus 1 11930
Protoss_Robotics_Facility 1 12373
12373
