Protoss_Gateway 1 4243
Protoss_Assimilator 1 4191
Protoss_Zealot 8 12295
Protoss_Cybernetics_Core 1 7856
Protoss_Citadel_of_Adun 1 9526
Protoss_Templar_Archives 1 11573
Protoss_Forge 1 12081
12295
