Protoss_Forge 1 3801
Protoss_Photon_Cannon 2 5711
Protoss_Nexus 1 9072
Protoss_Gateway 1 8973
Protoss_Assimilator 2 10880
Protoss_Cybernetics_Core 1 10430
Protoss_Zealot 3 12008
Protoss_Stargate 1 12433
12433
