Protoss_Gateway 2 10441
Protoss_Assimilator 1 4410
Protoss_Zealot 5 10720
Protoss_Cybernetics_Core 1 6749
Protoss_Dragoon 1 7974
Protoss_Citadel_of_Adun 1 8999
Protoss_Templar_Archives 1 10823
Protoss_High_Templar 2 12130
12130
