Protoss_Forge 1 4138
Protoss_Photon_Cannon 1 5492
Protoss_Nexus 1 8153
Protoss_Gateway 3 12844
Protoss_Assimilator 2 12201
Protoss_Zealot 4 11935
Protoss_Cybernetics_Core 1 9415
Protoss_Citadel_of_Adun 1 11150
12844
