Protoss_Forge 1 3795
Protoss_Photon_Cannon 3 8995
Protoss_Nexus 1 9265
Protoss_Gateway 1 8408
Protoss_Assimilator 2 10821
Protoss_Cybernetics_Core 1 10050
Protoss_Zealot 3 11481
Protoss_Stargate 1 11988
Protoss_Citadel_of_Adun 1 12416
12416
