Protoss_Forge 1 4060
Protoss_Photon_Cannon 1 5562
Protoss_Nexus 1 8529
Protoss_Gateway 3 11985
Protoss_Assimilator 1 7640
Protoss_Zealot 1 8879
Protoss_Cybernetics_Core 1 9429
Protoss_Dragoon 1 10743
Protoss_Citadel_of_Adun 1 11148
11985
