Protoss_Gateway 1 4335
Protoss_Forge 1 4788
Protoss_Photon_Cannon 2 7138
Protoss_Nexus 1 10212
Protoss_Assimilator 2 11063
Protoss_Zealot 2 10472
Protoss_Cybernetics_Core 1 10278
Protoss_Stargate 1 12088
Protoss_Dragoon 1 12013
12088
