Protoss_Nexus 1 7246
Protoss_Forge 1 5933
Protoss_Gateway 2 8232
Protoss_Zealot 6 11110
Protoss_Assimilator 1 8636
Protoss_Cybernetics_Core 1 10937
Protoss_Stargate 1 13070
13070
