Protoss_Forge 1 3898
Protoss_Photon_Cannon 2 5694
Protoss_Nexus 1 8908
Protoss_Gateway 1 7878
Protoss_Assimilator 1 7586
Protoss_Zealot 1 8938
Protoss_Cybernetics_Core 1 9825
Protoss_Dragoon 1 11062
Protoss_Stargate 1 11863
11863
