Protoss_Forge 1 4114
Protoss_Nexus 1 7478
Protoss_Photon_Cannon 2 6832
Protoss_Gateway 1 8006
Protoss_Assimilator 2 11235
Protoss_Zealot 4 12248
Protoss_Cybernetics_Core 1 10337
Protoss_Stargate 1 12043
12248
