Protoss_Forge 1 4335
Protoss_Nexus 1 8114
Protoss_Gateway 2 8563
Protoss_Photon_Cannon 1 7348
Protoss_Zealot 7 11838
Protoss_Assimilator 2 11000
Protoss_Cybernetics_Core 1 12007
12007
