Protoss_Forge 1 4122
Protoss_Assimilator 1 4331
Protoss_Photon_Cannon 1 5548
Protoss_Gateway 2 7960
Protoss_Zealot 7 11718
Protoss_Cybernetics_Core 1 8897
Protoss_Citadel_of_Adun 1 10609
Protoss_Templar_Archives 1 12192
Protoss_Ground_Weapons_1 1 11322
12192
