Protoss_Forge 1 4539
Protoss_Nexus 1 7841
Protoss_Gateway 1 7272
Protoss_Assimilator 2 10331
Protoss_Photon_Cannon 1 8005
Protoss_Zealot 1 8701
Protoss_Cybernetics_Core 1 10098
Protoss_Dragoon 1 11624
Protoss_Stargate 1 12182
Protoss_Robotics_Facility 1 13198
13198
