Protoss_Forge 1 3997
Protoss_Photon_Cannon 6 11354
Protoss_Gateway 1 5759
Protoss_Zealot 2 8464
Protoss_Nexus 1 9687
Protoss_Assimilator 1 8194
Protoss_Cybernetics_Core 1 10629
11354
