Protoss_Forge 1 4207
Protoss_Photon_Cannon 3 9882
Protoss_Nexus 1 8657
Protoss_Gateway 1 8186
Protoss_Assimilator 1 8499
Protoss_Zealot 4 11885
Protoss_Cybernetics_Core 1 12039
12039
