Protoss_Forge 1 4546
Protoss_Nexus 1 8077
Protoss_Gateway 2 8503
Protoss_Photon_Cannon 1 7725
Protoss_Zealot 7 11660
Protoss_Assimilator 2 10902
Protoss_Cybernetics_Core 1 10556
Protoss_Citadel_of_Adun 1 12743
12743
