Protoss_Forge 1 4204
Protoss_Nexus 1 7519
Protoss_Gateway 1 6784
Protoss_Assimilator 2 9471
Protoss_Photon_Cannon 2 11387
Protoss_Cybernetics_Core 1 8554
Protoss_Zealot 2 10182
Protoss_Stargate 1 10420
Protoss_Dragoon 1 10105
Protoss_Robotics_Facility 1 11624
Protoss_Corsair 2 12242
12242
