Protoss_Forge 1 4073
Protoss_Photon_Cannon 2 10690
Protoss_Nexus 1 8364
Protoss_Gateway 1 7565
Protoss_Assimilator 2 10834
Protoss_Zealot 3 12005
Protoss_Cybernetics_Core 1 10398
Protoss_Stargate 1 12362
12362
