Protoss_Forge 1 4237
Protoss_Nexus 1 7541
Protoss_Gateway 1 6816
Protoss_Photon_Cannon 2 10996
Protoss_Assimilator 2 10071
Protoss_Cybernetics_Core 1 8683
Protoss_Zealot 2 11475
Protoss_Stargate 1 10587
Protoss_Dragoon 1 10459
Protoss_Corsair 1 11534
Protoss_Citadel_of_Adun 1 12427
12427
