Protoss_Forge 1 4217
Protoss_Nexus 1 8109
Protoss_Gateway 1 7470
Protoss_Photon_Cannon 2 8385
Protoss_Assimilator 2 10507
Protoss_Cybernetics_Core 1 10050
Protoss_Zealot 3 12242
Protoss_Stargate 1 11871
Protoss_Citadel_of_Adun 1 12579
12579
