Protoss_Forge 1 4046
Protoss_Nexus 1 7398
Protoss_Photon_Cannon 3 10282
Protoss_Gateway 1 7679
Protoss_Assimilator 1 7559
Protoss_Zealot 2 9520
Protoss_Cybernetics_Core 1 9560
Protoss_Stargate 1 12250
Protoss_Dragoon 1 11960
12250
