Protoss_Forge 1 4161
Protoss_Photon_Cannon 2 6391
Protoss_Nexus 1 9151
Protoss_Gateway 1 8117
Protoss_Assimilator 2 11591
Protoss_Cybernetics_Core 1 9687
Protoss_Zealot 2 10527
Protoss_Stargate 1 11564
Protoss_Citadel_of_Adun 1 11862
11862
