Protoss_Forge 1 4975
Protoss_Photon_Cannon 2 6364
Protoss_Nexus 1 9078
Protoss_Gateway 1 8215
Protoss_Assimilator 2 10065
Protoss_Cybernetics_Core 1 9763
Protoss_Zealot 3 12272
Protoss_Dragoon 1 11381
Protoss_Stargate 1 12517
12517
