Protoss_Gateway 2 11054
Protoss_Assimilator 1 4413
Protoss_Cybernetics_Core 1 5767
Protoss_Zealot 2 6869
Protoss_Dragoon 5 12250
Protoss_Stargate 1 9581
Protoss_Robotics_Facility 1 10500
Protoss_Shuttle 1 12128
12250
