Protoss_Forge 1 4455
Protoss_Photon_Cannon 2 6521
Protoss_Gateway 2 8767
Protoss_Assimilator 1 6942
Protoss_Cybernetics_Core 1 10223
Protoss_Zealot 3 11657
Protoss_Stargate 1 11920
Protoss_Citadel_of_Adun 1 12031
12031
