Protoss_Forge 1 3936
Protoss_Photon_Cannon 3 7058
Protoss_Nexus 2 12859
Protoss_Gateway 1 9072
Protoss_Assimilator 2 12201
Protoss_Cybernetics_Core 1 10632
Protoss_Zealot 3 11944
Protoss_Stargate 1 12401
Protoss_Dragoon 1 12089
12859
