Protoss_Forge 1 3980
Protoss_Photon_Cannon 2 7074
Protoss_Nexus 1 8223
Protoss_Gateway 1 8022
Protoss_Assimilator 2 11748
Protoss_Zealot 4 11751
Protoss_Cybernetics_Core 1 10147
11751
