Protoss_Forge 1 4120
Protoss_Photon_Cannon 2 7150
Protoss_Nexus 1 8415
Protoss_Gateway 1 7726
Protoss_Assimilator 2 10357
Protoss_Cybernetics_Core 1 9277
Protoss_Zealot 2 10542
Protoss_Stargate 1 11487
Protoss_Citadel_of_Adun 1 12394
12394
