Protoss_Forge 1 4259
Protoss_Photon_Cannon 3 7267
Protoss_Nexus 1 10656
Protoss_Gateway 1 9737
Protoss_Assimilator 2 12293
Protoss_Cybernetics_Core 1 11309
Protoss_Zealot 2 11961
12293
