Protoss_Forge 1 4109
Protoss_Nexus 1 7263
Protoss_Gateway 1 6678
Protoss_Assimilator 2 10352
Protoss_Cybernetics_Core 1 8129
Protoss_Photon_Cannon 1 8100
Protoss_Zealot 2 9792
Protoss_Stargate 1 10172
Protoss_Dragoon 1 10977
Protoss_Corsair 2 12223
Protoss_Citadel_of_Adun 1 12125
12223
