Protoss_Gateway 2 5600
Protoss_Zealot 6 12024
Protoss_Assimilator 1 7030
Protoss_Cybernetics_Core 1 8993
Protoss_Forge 1 9424
Protoss_Dragoon 1 10200
Protoss_Stargate 1 11020
Protoss_Citadel_of_Adun 1 12080
12080
