Protoss_Gateway 2 5041
Protoss_Zealot 4 11819
Protoss_Assimilator 1 6768
Protoss_Cybernetics_Core 1 8411
Protoss_Citadel_of_Adun 1 10186
Protoss_Dragoon 1 10031
Protoss_Templar_Archives 1 11964
Protoss_Forge 1 11701
11964
