Protoss_Gateway 1 4214
Protoss_Assimilator 1 4488
Protoss_Zealot 6 11470
Protoss_Cybernetics_Core 1 7163
Protoss_Stargate 1 8936
Protoss_Corsair 2 11534
Protoss_Citadel_of_Adun 1 10711
11534
