Protoss_Gateway 3 8875
Protoss_Zealot 6 11161
Protoss_Assimilator 1 5439
Protoss_Cybernetics_Core 1 7931
Protoss_Citadel_of_Adun 1 9424
Protoss_Forge 1 9649
Protoss_Photon_Cannon 1 11886
11886
