Protoss_Gateway 1 4192
Protoss_Assimilator 1 4249
Protoss_Cybernetics_Core 1 5685
Protoss_Stargate 1 7393
Protoss_Corsair 2 9225
Protoss_Forge 1 9285
Protoss_Robotics_Facility 1 10829
Protoss_Photon_Cannon 1 11073
Protoss_Robotics_Support_Bay 1 11659
Protoss_Shuttle 1 12377
Protoss_Dragoon 1 12453
12453
