Protoss_Assimilator 1 3400
Protoss_Gateway 1 4890
Protoss_Cybernetics_Core 1 6374
Protoss_Stargate 1 8087
Protoss_Robotics_Facility 1 8648
Protoss_Corsair 3 10853
Protoss_Shuttle 1 10226
Protoss_Fleet_Beacon 1 12153
Protoss_Forge 1 12033
12153
