Protoss_Gateway 1 4142
Protoss_Forge 2 10965
Protoss_Zealot 4 10710
Protoss_Assimilator 1 6273
Protoss_Cybernetics_Core 1 7564
Protoss_Dragoon 1 8831
Protoss_Stargate 1 10698
Protoss_Corsair 1 11651
Protoss_Citadel_of_Adun 1 12282
Protoss_Photon_Cannon 1 12379
12379
