Protoss_Gateway 1 4126
Protoss_Assimilator 2 6261
Protoss_Zealot 5 10656
Protoss_Cybernetics_Core 1 8385
Protoss_Stargate 1 10263
Protoss_Forge 1 9885
Protoss_Corsair 1 11212
Protoss_Citadel_of_Adun 1 12094
12094
