Protoss_Gateway 1 4310
Protoss_Assimilator 1 4615
Protoss_Zealot 2 7202
Protoss_Cybernetics_Core 1 6835
Protoss_Stargate 1 8601
Protoss_Robotics_Facility 1 9450
Protoss_Dragoon 1 9022
Protoss_Corsair 1 9551
Protoss_Citadel_of_Adun 1 10725
Protoss_Robotics_Support_Bay 1 10465
10725
