Protoss_Nexus 1 7217
Protoss_Gateway 1 6343
Protoss_Forge 1 6298
Protoss_Zealot 2 8727
Protoss_Photon_Cannon 2 10798
Protoss_Assimilator 2 10053
Protoss_Cybernetics_Core 1 10008
Protoss_Stargate 1 11857
11857
