Protoss_Assimilator 1 3561
Protoss_Gateway 1 4796
Protoss_Cybernetics_Core 1 6514
Protoss_Stargate 1 8220
Protoss_Robotics_Facility 1 9228
Protoss_Corsair 2 10052
Protoss_Shuttle 1 10635
Protoss_Robotics_Support_Bay 1 10178
Protoss_Reaver 1 12468
12468
