Protoss_Gateway 1 4397
Protoss_Assimilator 1 4698
Protoss_Zealot 2 7151
Protoss_Forge 1 7078
Protoss_Photon_Cannon 1 8448
Protoss_Cybernetics_Core 1 9702
Protoss_Stargate 1 11577
Protoss_Citadel_of_Adun 1 11420
Protoss_Dragoon 1 11246
11577
