Protoss_Assimilator 1 3618
Protoss_Gateway 1 4736
Protoss_Cybernetics_Core 1 6197
Protoss_Dragoon 1 7405
Protoss_Stargate 1 7986
Protoss_Robotics_Facility 1 9085
Protoss_Corsair 2 9971
Protoss_Zealot 3 12228
Protoss_Robotics_Support_Bay 1 11114
12228
