Protoss_Forge 1 4072
Protoss_Photon_Cannon 4 10803
Protoss_Nexus 1 9374
Protoss_Gateway 1 9893
Protoss_Assimilator 1 10016
Protoss_Cybernetics_Core 1 12146
Protoss_Zealot 1 11892
12146
