Protoss_Assimilator 1 3582
Protoss_Gateway 1 4924
Protoss_Cybernetics_Core 1 6416
Protoss_Stargate 1 8162
Protoss_Robotics_Facility 1 9560
Protoss_Corsair 3 10874
Protoss_Forge 1 10259
Protoss_Shuttle 1 12194
Protoss_Robotics_Support_Bay 1 11643
12194
