Protoss_Assimilator 1 3569
Protoss_Gateway 1 4777
Protoss_Cybernetics_Core 1 6241
Protoss_Stargate 1 8052
Protoss_Dragoon 1 7646
Protoss_Robotics_Facility 1 9464
Protoss_Corsair 3 11073
Protoss_Zealot 2 11256
Protoss_Shuttle 1 11148
Protoss_Forge 1 11783
11783
