Protoss_Forge 1 3951
Protoss_Photon_Cannon 2 5849
Protoss_Nexus 1 9235
Protoss_Gateway 2 10924
Protoss_Assimilator 1 9595
Protoss_Zealot 3 11871
Protoss_Cybernetics_Core 1 11380
11871
