Protoss_Gateway 1 4309
Protoss_Assimilator 1 4710
Protoss_Zealot 3 9792
Protoss_Cybernetics_Core 1 7591
Protoss_Dragoon 1 8890
Protoss_Stargate 1 9621
Protoss_Citadel_of_Adun 1 9589
Protoss_Corsair 1 10575
Protoss_Forge 1 11701
11701
