Protoss_Gateway 2 11136
Protoss_Assimilator 1 4755
Protoss_Cybernetics_Core 1 6194
Protoss_Zealot 4 11336
Protoss_Stargate 1 8087
Protoss_Forge 1 7755
Protoss_Corsair 2 10224
Protoss_Citadel_of_Adun 1 11538
11538
