Protoss_Gateway 2 8019
Protoss_Assimilator 1 5263
Protoss_Zealot 3 8534
Protoss_Cybernetics_Core 1 7596
Protoss_Dragoon 1 9066
Protoss_Citadel_of_Adun 1 9778
Protoss_Stargate 1 11387
Protoss_Templar_Archives 1 11313
Protoss_Forge 1 11674
11674
