Protoss_Nexus 1 7151
Protoss_Gateway 2 9175
Protoss_Forge 1 6390
Protoss_Photon_Cannon 3 11812
Protoss_Assimilator 1 9269
Protoss_Zealot 3 11995
Protoss_Cybernetics_Core 1 10691
Protoss_Stargate 1 12493
12493
