Protoss_Forge 1 4182
Protoss_Photon_Cannon 4 9278
Protoss_Nexus 1 8927
Protoss_Gateway 1 9811
Protoss_Assimilator 2 12111
Protoss_Zealot 2 12295
Protoss_Cybernetics_Core 1 11948
12295
