Protoss_Nexus 1 7310
Protoss_Forge 1 6251
Protoss_Photon_Cannon 2 8047
Protoss_Gateway 3 12626
Protoss_Assimilator 2 11178
Protoss_Cybernetics_Core 1 10909
Protoss_Zealot 4 12086
12626
