Protoss_Nexus 1 7597
Protoss_Forge 1 6485
Protoss_Assimilator 2 8919
Protoss_Photon_Cannon 1 7986
Protoss_Gateway 3 10439
Protoss_Zealot 6 12203
Protoss_Cybernetics_Core 1 10855
Protoss_Citadel_of_Adun 1 12671
12671
