Protoss_Gateway 2 5537
Protoss_Zealot 9 12302
Protoss_Assimilator 1 7044
Protoss_Cybernetics_Core 1 8616
Protoss_Dragoon 1 9856
Protoss_Stargate 1 10793
Protoss_Citadel_of_Adun 1 11964
Protoss_Corsair 1 11834
12302
