Protoss_Gateway 2 10763
Protoss_Assimilator 1 4893
Protoss_Zealot 5 11991
Protoss_Cybernetics_Core 1 6936
Protoss_Citadel_of_Adun 1 8399
Protoss_Templar_Archives 1 11429
Protoss_Forge 1 11710
Leg_Enhancements 1 11336
11991
