Protoss_Gateway 3 11904
Protoss_Assimilator 1 4444
Protoss_Zealot 5 12149
Protoss_Cybernetics_Core 1 6526
Protoss_Stargate 1 8397
Protoss_Citadel_of_Adun 1 9782
Protoss_Corsair 1 9610
12149
