Protoss_Gateway 1 4123
Protoss_Assimilator 1 4631
Protoss_Zealot 5 12068
Protoss_Forge 1 6933
Protoss_Cybernetics_Core 1 9065
Protoss_Citadel_of_Adun 1 10521
Protoss_Dragoon 1 10400
Protoss_Robotics_Facility 1 12270
12270
