Protoss_Gateway 2 5260
Protoss_Zealot 6 11988
Protoss_Nexus 1 10559
Protoss_Assimilator 1 9048
Protoss_Forge 1 9572
Protoss_Photon_Cannon 1 11016
Protoss_Cybernetics_Core 1 11819
11988
