Protoss_Gateway 2 5339
Protoss_Zealot 7 11819
Protoss_Assimilator 1 6773
Protoss_Cybernetics_Core 1 8263
Protoss_Dragoon 1 9549
Protoss_Citadel_of_Adun 1 9969
Protoss_Templar_Archives 1 12563
12563
