Protoss_Forge 1 4272
Protoss_Photon_Cannon 3 10561
Protoss_Gateway 2 9267
Protoss_Nexus 1 10142
Protoss_Assimilator 1 9166
Protoss_Zealot 4 12039
Protoss_Cybernetics_Core 1 11540
12039
