Protoss_Gateway 2 11130
Protoss_Assimilator 1 4448
Protoss_Zealot 4 8976
Protoss_Cybernetics_Core 1 6860
Protoss_Stargate 1 9003
Protoss_Corsair 1 9953
Protoss_Dragoon 3 12351
Protoss_Robotics_Facility 1 12159
Protoss_Forge 1 11932
12351
