Protoss_Nexus 2 14260
Protoss_Forge 1 6043
Protoss_Assimilator 1 6686
Protoss_Gateway 1 8222
Protoss_Cybernetics_Core 1 10085
Protoss_Photon_Cannon 2 10636
Protoss_Stargate 1 11956
Protoss_Robotics_Facility 1 12714
14260
