Protoss_Gateway 2 5363
Protoss_Zealot 5 12002
Protoss_Assimilator 1 6160
Protoss_Forge 1 6655
Protoss_Photon_Cannon 1 7918
Protoss_Cybernetics_Core 1 8929
Protoss_Dragoon 1 10187
Protoss_Citadel_of_Adun 1 10599
12002
