Protoss_Forge 1 3759
Protoss_Nexus 1 8064
Protoss_Photon_Cannon 6 10475
Protoss_Gateway 1 9176
Protoss_Assimilator 1 9943
Protoss_Zealot 2 11527
Protoss_Cybernetics_Core 1 11752
11752
