Protoss_Gateway 2 5306
Protoss_Zealot 7 11285
Protoss_Assimilator 1 6870
Protoss_Cybernetics_Core 1 7978
Protoss_Forge 1 7995
Protoss_Dragoon 1 9739
Protoss_Citadel_of_Adun 1 11209
11285
