Protoss_Gateway 2 11098
Protoss_Zealot 6 12346
Protoss_Assimilator 1 5502
Protoss_Cybernetics_Core 1 6814
Protoss_Stargate 1 8702
Protoss_Dragoon 1 8466
Protoss_Citadel_of_Adun 1 9497
Protoss_Corsair 1 9814
Protoss_Forge 1 12125
12346
