Protoss_Forge 1 3861
Protoss_Nexus 1 7969
Protoss_Photon_Cannon 3 12319
Protoss_Gateway 1 7818
Protoss_Assimilator 2 10890
Protoss_Cybernetics_Core 2 10960
Protoss_Stargate 1 11994
12319
