Protoss_Gateway 2 4669
Protoss_Zealot 8 11044
Protoss_Assimilator 1 7308
Protoss_Cybernetics_Core 1 9987
Protoss_Forge 1 10755
Protoss_Dragoon 1 11224
Protoss_Citadel_of_Adun 1 12320
12320
