Protoss_Gateway 2 5057
Protoss_Zealot 6 10114
Protoss_Forge 1 6305
Protoss_Photon_Cannon 2 12405
Protoss_Nexus 1 10947
Protoss_Assimilator 1 9727
Protoss_Cybernetics_Core 1 11695
12405
