Protoss_Forge 1 5184
Protoss_Nexus 1 7657
Protoss_Photon_Cannon 1 6449
Protoss_Gateway 3 11791
Protoss_Assimilator 2 11655
Protoss_Cybernetics_Core 1 8838
Protoss_Zealot 2 11815
Protoss_Stargate 1 10730
Protoss_Citadel_of_Adun 1 11203
Protoss_Corsair 1 12017
12017
