Protoss_Gateway 1 4451
Protoss_Assimilator 1 4739
Protoss_Zealot 3 9888
Protoss_Cybernetics_Core 1 7211
Protoss_Robotics_Facility 1 9234
Protoss_Dragoon 1 8795
Protoss_Citadel_of_Adun 1 10572
Protoss_Robotics_Support_Bay 1 9992
Protoss_Reaver 1 11737
Protoss_Templar_Archives 1 12286
Protoss_Forge 1 12011
12286
