Protoss_Gateway 2 12599
Protoss_Assimilator 1 4512
Protoss_Zealot 5 11636
Protoss_Cybernetics_Core 1 7258
Protoss_Stargate 1 9530
Protoss_Dragoon 1 9300
Protoss_Forge 1 9749
Protoss_Corsair 1 10495
Protoss_Citadel_of_Adun 1 11897
12599
