Protoss_Gateway 1 4318
Protoss_Zealot 3 8022
Protoss_Assimilator 1 5588
Protoss_Cybernetics_Core 1 9981
Protoss_Forge 1 10251
Protoss_Citadel_of_Adun 1 11609
Protoss_Photon_Cannon 1 11821
Protoss_Dragoon 1 12183
12183
