Protoss_Forge 1 3898
Protoss_Photon_Cannon 1 6427
Protoss_Nexus 1 9369
Protoss_Gateway 2 12094
Protoss_Zealot 3 11490
Protoss_Assimilator 1 9847
Protoss_Cybernetics_Core 1 12511
12511
