Protoss_Gateway 1 4343
Protoss_Assimilator 1 4652
Protoss_Zealot 6 12105
Protoss_Cybernetics_Core 1 7409
Protoss_Stargate 1 9310
Protoss_Dragoon 1 8992
Protoss_Corsair 1 10319
Protoss_Citadel_of_Adun 1 10872
Protoss_Forge 1 10567
Protoss_Photon_Cannon 1 12257
12257
