Protoss_Gateway 2 11743
Protoss_Assimilator 1 4549
Protoss_Zealot 3 9276
Protoss_Cybernetics_Core 1 6848
Protoss_Stargate 1 8672
Protoss_Dragoon 1 8414
Protoss_Corsair 1 9639
Protoss_Citadel_of_Adun 1 10170
Protoss_Templar_Archives 1 11633
Protoss_Forge 1 12103
12103
