Protoss_Forge 1 4205
Protoss_Nexus 1 8409
Protoss_Photon_Cannon 2 7986
Protoss_Assimilator 2 11995
Protoss_Gateway 2 10294
Protoss_Zealot 4 12152
Protoss_Cybernetics_Core 1 11279
12152
