Protoss_Forge 1 4147
Protoss_Photon_Cannon 5 8739
Protoss_Nexus 1 9467
Protoss_Gateway 1 9712
Protoss_Assimilator 2 10752
Protoss_Zealot 2 11695
Protoss_Cybernetics_Core 1 11298
11695
