Protoss_Gateway 2 10321
Protoss_Assimilator 1 4381
Protoss_Zealot 3 10363
Protoss_Cybernetics_Core 1 6933
Protoss_Citadel_of_Adun 1 8663
Protoss_Dragoon 1 8758
Protoss_Templar_Archives 1 10171
Protoss_Robotics_Facility 1 12073
Protoss_Dark_Templar 1 11488
12073
