Protoss_Forge 1 4439
Protoss_Nexus 1 7991
Protoss_Photon_Cannon 3 11593
Protoss_Gateway 1 7536
Protoss_Assimilator 2 11778
Protoss_Zealot 3 11988
Protoss_Cybernetics_Core 1 10258
Protoss_Citadel_of_Adun 1 11841
11988
