Protoss_Gateway 2 5341
Protoss_Zealot 9 11410
Protoss_Assimilator 1 6899
Protoss_Cybernetics_Core 1 9064
Protoss_Citadel_of_Adun 1 10984
Protoss_Shield_Battery 1 10604
Protoss_Templar_Archives 1 12593
12593
