Protoss_Gateway 1 4207
Protoss_Assimilator 1 4476
Protoss_Zealot 2 6851
Protoss_Cybernetics_Core 1 6877
Protoss_Stargate 1 8579
Protoss_Citadel_of_Adun 1 8619
Protoss_Dragoon 1 9563
Protoss_Corsair 1 9573
Protoss_Templar_Archives 1 10265
Protoss_Dark_Templar 1 11824
Protoss_Forge 1 11792
Protoss_Nexus 1 14124
14124
