Protoss_Gateway 1 4177
Protoss_Assimilator 1 4387
Protoss_Cybernetics_Core 1 5699
Protoss_Zealot 2 8091
Protoss_Dragoon 1 7229
Protoss_Robotics_Facility 1 8392
Protoss_Shuttle 1 9918
Protoss_Robotics_Support_Bay 1 9389
Protoss_Reaver 1 11576
Protoss_Citadel_of_Adun 1 11889
Protoss_Forge 1 11698
11889
