Protoss_Nexus 1 7227
Protoss_Forge 1 5753
Protoss_Gateway 3 11317
Protoss_Assimilator 2 10150
Protoss_Photon_Cannon 1 7870
Protoss_Zealot 7 12362
Protoss_Cybernetics_Core 1 9172
Protoss_Citadel_of_Adun 1 10906
Protoss_Templar_Archives 1 12350
12362
