Protoss_Forge 1 4786
Protoss_Photon_Cannon 1 6449
Protoss_Nexus 1 9068
Protoss_Gateway 1 7981
Protoss_Assimilator 2 10946
Protoss_Cybernetics_Core 1 9489
Protoss_Stargate 1 11169
Protoss_Corsair 1 12105
12105
