Protoss_Gateway 2 11127
Protoss_Assimilator 1 4315
Protoss_Zealot 3 11227
Protoss_Cybernetics_Core 1 6833
Protoss_Stargate 1 8662
Protoss_Dragoon 1 8605
Protoss_Citadel_of_Adun 1 9857
Protoss_Corsair 1 9807
Protoss_Templar_Archives 1 11443
11443
