Protoss_Forge 1 4270
Protoss_Photon_Cannon 2 11897
Protoss_Nexus 1 8569
Protoss_Gateway 1 7559
Protoss_Assimilator 2 10915
Protoss_Cybernetics_Core 1 9080
Protoss_Zealot 1 9084
Protoss_Citadel_of_Adun 1 10951
Protoss_Dragoon 1 12110
Protoss_Templar_Archives 1 12683
12683
