Protoss_Forge 1 3952
Protoss_Photon_Cannon 2 6481
Protoss_Nexus 1 9371
Protoss_Gateway 1 8772
Protoss_Assimilator 1 8797
Protoss_Zealot 1 9924
Protoss_Cybernetics_Core 1 10509
Protoss_Citadel_of_Adun 1 12579
12579
