Protoss_Forge 1 4082
Protoss_Nexus 2 12617
Protoss_Gateway 1 7610
Protoss_Photon_Cannon 1 7825
Protoss_Assimilator 2 9831
Protoss_Cybernetics_Core 1 9722
Protoss_Stargate 1 11702
Protoss_Robotics_Facility 1 13192
13192
