Protoss_Forge 1 4572
Protoss_Photon_Cannon 1 5944
Protoss_Nexus 1 8294
Protoss_Gateway 2 11149
Protoss_Assimilator 1 7461
Protoss_Cybernetics_Core 1 9394
Protoss_Zealot 5 12295
Protoss_Citadel_of_Adun 1 11521
12295
