Protoss_Forge 1 4783
Protoss_Photon_Cannon 4 12565
Protoss_Nexus 1 8791
Protoss_Gateway 1 8390
Protoss_Assimilator 2 12229
Protoss_Zealot 3 11414
Protoss_Cybernetics_Core 1 10864
Protoss_Stargate 1 12704
12704
