Protoss_Nexus 1 7079
Protoss_Forge 1 5778
Protoss_Gateway 2 9674
Protoss_Photon_Cannon 4 11556
Protoss_Assimilator 1 7750
Protoss_Zealot 6 11636
Protoss_Cybernetics_Core 1 10960
Protoss_Stargate 1 12856
12856
