Protoss_Forge 1 4068
Protoss_Photon_Cannon 3 12322
Protoss_Nexus 1 8402
Protoss_Gateway 1 8742
Protoss_Assimilator 1 8702
Protoss_Zealot 3 11475
Protoss_Cybernetics_Core 1 10668
Protoss_Stargate 1 12477
Protoss_Dragoon 1 12191
12477
