Protoss_Forge 1 4313
Protoss_Nexus 1 7875
Protoss_Photon_Cannon 1 6604
Protoss_Gateway 1 7733
Protoss_Assimilator 2 10331
Protoss_Zealot 1 8730
Protoss_Cybernetics_Core 1 10256
Protoss_Dragoon 1 11454
Protoss_Citadel_of_Adun 1 11756
11756
