Protoss_Forge 1 4315
Protoss_Nexus 1 7852
Protoss_Photon_Cannon 4 12550
Protoss_Gateway 1 7366
Protoss_Assimilator 1 8042
Protoss_Zealot 4 11437
Protoss_Cybernetics_Core 1 10381
12550
