Protoss_Nexus 1 6883
Protoss_Forge 1 5373
Protoss_Photon_Cannon 2 12379
Protoss_Gateway 3 10729
Protoss_Assimilator 1 7337
Protoss_Cybernetics_Core 1 8868
Protoss_Zealot 6 11704
Protoss_Citadel_of_Adun 1 10387
12379
