Protoss_Forge 1 4381
Protoss_Nexus 1 8405
Protoss_Photon_Cannon 2 12341
Protoss_Gateway 2 11547
Protoss_Assimilator 2 11730
Protoss_Cybernetics_Core 1 9740
Protoss_Zealot 4 11756
Protoss_Citadel_of_Adun 1 11332
12341
