Protoss_Forge 1 3757
Protoss_Photon_Cannon 3 11492
Protoss_Nexus 1 8425
Protoss_Gateway 3 12362
Protoss_Assimilator 1 7722
Protoss_Zealot 5 12157
Protoss_Cybernetics_Core 1 9593
Protoss_Citadel_of_Adun 1 11462
12362
