Protoss_Forge 1 4818
Protoss_Photon_Cannon 3 8066
Protoss_Gateway 1 6715
Protoss_Nexus 1 8978
Protoss_Assimilator 2 11155
Protoss_Zealot 2 10000
Protoss_Cybernetics_Core 1 10793
Protoss_Stargate 1 13067
13067
