Protoss_Gateway 1 4269
Protoss_Assimilator 1 4357
Protoss_Zealot 4 8566
Protoss_Cybernetics_Core 1 8566
Protoss_Stargate 1 10304
Protoss_Dragoon 1 9982
Protoss_Citadel_of_Adun 1 10867
Protoss_Forge 1 11424
Protoss_Corsair 1 11546
11546
