Protoss_Forge 1 4330
Protoss_Photon_Cannon 1 5660
Protoss_Nexus 1 8636
Protoss_Gateway 1 7589
Protoss_Assimilator 2 10050
Protoss_Zealot 1 8601
Protoss_Cybernetics_Core 1 9428
Protoss_Stargate 1 11321
Protoss_Citadel_of_Adun 1 11674
11674
