Protoss_Forge 1 3886
Protoss_Photon_Cannon 2 5736
Protoss_Nexus 1 9327
Protoss_Gateway 3 12725
Protoss_Assimilator 2 11373
Protoss_Zealot 3 12061
Protoss_Cybernetics_Core 1 10567
Protoss_Citadel_of_Adun 1 12213
12725
