Protoss_Nexus 1 6956
Protoss_Gateway 1 6330
Protoss_Forge 1 6374
Protoss_Assimilator 2 10903
Protoss_Photon_Cannon 1 7620
Protoss_Zealot 5 12248
Protoss_Cybernetics_Core 1 10089
Protoss_Dragoon 1 11387
Protoss_Stargate 1 12419
Protoss_Citadel_of_Adun 1 12220
12419
