Protoss_Forge 1 4565
Protoss_Nexus 1 7745
Protoss_Gateway 1 7287
Protoss_Assimilator 1 7217
Protoss_Photon_Cannon 1 7953
Protoss_Zealot 2 11133
Protoss_Cybernetics_Core 1 9901
Protoss_Stargate 2 12972
12972
