Protoss_Forge 1 4906
Protoss_Nexus 1 7762
Protoss_Photon_Cannon 1 6420
Protoss_Gateway 1 7457
Protoss_Assimilator 2 9626
Protoss_Cybernetics_Core 1 9304
Protoss_Stargate 1 11071
Protoss_Dragoon 1 10722
Protoss_Citadel_of_Adun 1 11676
Protoss_Zealot 1 11584
11676
