Protoss_Forge 1 4271
Protoss_Photon_Cannon 2 6224
Protoss_Nexus 1 9148
Protoss_Gateway 1 8314
Protoss_Assimilator 2 10592
Protoss_Cybernetics_Core 1 9772
Protoss_Zealot 3 11633
Protoss_Citadel_of_Adun 1 11287
11633
