Protoss_Forge 1 4337
Protoss_Photon_Cannon 2 6560
Protoss_Nexus 1 9820
Protoss_Gateway 1 8816
Protoss_Assimilator 1 8723
Protoss_Cybernetics_Core 1 10389
Protoss_Zealot 3 12010
Protoss_Citadel_of_Adun 1 12029
12029
