Protoss_Forge 1 4666
Protoss_Photon_Cannon 2 6069
Protoss_Nexus 1 9309
Protoss_Gateway 1 8423
Protoss_Assimilator 2 11074
Protoss_Zealot 1 9377
Protoss_Cybernetics_Core 1 9974
Protoss_Dragoon 1 11170
Protoss_Citadel_of_Adun 1 11430
11430
