Protoss_Gateway 2 10905
Protoss_Assimilator 1 4394
Protoss_Cybernetics_Core 1 5730
Protoss_Stargate 1 7578
Protoss_Forge 1 7281
Protoss_Photon_Cannon 2 8729
Protoss_Corsair 2 9917
Protoss_Zealot 4 12010
Protoss_Citadel_of_Adun 1 11332
12010
