Protoss_Gateway 1 4425
Protoss_Assimilator 1 4676
Protoss_Zealot 4 9017
Protoss_Cybernetics_Core 1 8206
Protoss_Citadel_of_Adun 1 9722
Protoss_Dragoon 1 10137
Protoss_Templar_Archives 1 11203
Protoss_Dark_Templar 1 12399
Protoss_Forge 1 12229
12399
