Protoss_Forge 1 4363
Protoss_Photon_Cannon 2 6013
Protoss_Nexus 1 9169
Protoss_Gateway 2 12832
Protoss_Assimilator 2 10804
Protoss_Cybernetics_Core 1 10122
Protoss_Zealot 2 10534
Protoss_Stargate 1 11822
Protoss_Dragoon 1 11663
Protoss_Citadel_of_Adun 1 12706
12832
