Protoss_Forge 1 3953
Protoss_Nexus 1 7808
Protoss_Gateway 1 7177
Protoss_Photon_Cannon 1 7817
Protoss_Assimilator 2 9956
Protoss_Zealot 2 10012
Protoss_Cybernetics_Core 1 9446
Protoss_Dragoon 1 11132
Protoss_Robotics_Facility 1 12526
Protoss_Citadel_of_Adun 1 12561
12561
