Protoss_Gateway 1 4188
Protoss_Assimilator 1 4505
Protoss_Cybernetics_Core 1 5860
Protoss_Stargate 1 7701
Protoss_Dragoon 1 7591
Protoss_Corsair 1 8654
Protoss_Citadel_of_Adun 1 9482
Protoss_Forge 1 9652
Protoss_Nexus 1 12657
Protoss_Templar_Archives 1 11554
12657
