Protoss_Nexus 1 7113
Protoss_Forge 1 6048
Protoss_Gateway 3 12307
Protoss_Assimilator 2 9349
Protoss_Cybernetics_Core 1 8885
Protoss_Photon_Cannon 1 8953
Protoss_Zealot 1 9434
Protoss_Stargate 1 11154
Protoss_Dragoon 1 11019
Protoss_Citadel_of_Adun 1 11522
Protoss_Corsair 1 12163
12307
