Protoss_Forge 1 4267
Protoss_Photon_Cannon 1 5988
Protoss_Nexus 1 8191
Protoss_Gateway 1 7796
Protoss_Assimilator 2 9653
Protoss_Cybernetics_Core 1 9396
Protoss_Zealot 3 11560
Protoss_Dragoon 1 10629
Protoss_Stargate 1 11263
Protoss_Citadel_of_Adun 1 11701
Protoss_Corsair 1 12201
12201
