Protoss_Nexus 1 7157
Protoss_Gateway 1 6473
Protoss_Assimilator 2 9510
Protoss_Cybernetics_Core 1 8090
Protoss_Stargate 1 9874
Protoss_Forge 1 10293
Protoss_Corsair 2 11914
Protoss_Robotics_Facility 1 11947
Protoss_Photon_Cannon 2 12020
12020
