Protoss_Nexus 1 7519
Protoss_Forge 1 6115
Protoss_Gateway 2 12065
Protoss_Photon_Cannon 1 7662
Protoss_Assimilator 2 10764
Protoss_Zealot 3 10766
Protoss_Cybernetics_Core 1 10199
Protoss_Citadel_of_Adun 1 11917
12065
