Protoss_Forge 1 4117
Protoss_Photon_Cannon 4 10291
Protoss_Nexus 1 8412
Protoss_Gateway 1 8636
Protoss_Assimilator 1 9203
Protoss_Zealot 2 11900
Protoss_Cybernetics_Core 1 12011
12011
