Protoss_Nexus 1 7039
Protoss_Forge 1 5581
Protoss_Photon_Cannon 2 12576
Protoss_Gateway 1 7499
Protoss_Assimilator 2 10347
Protoss_Cybernetics_Core 1 8990
Protoss_Zealot 2 11124
Protoss_Stargate 1 10730
Protoss_Citadel_of_Adun 1 11266
Protoss_Corsair 1 11680
12576
