Protoss_Gateway 2 10142
Protoss_Assimilator 1 4188
Protoss_Cybernetics_Core 1 5626
Protoss_Dragoon 9 15490
Protoss_Robotics_Facility 1 9307
Protoss_Shuttle 1 11806
Protoss_Robotics_Support_Bay 1 11132
Protoss_Reaver 2 15084
Singularity_Charge 1 12214
Protoss_Nexus 1 16500
16500
