Protoss_Gateway 2 12314
Protoss_Assimilator 1 4293
Protoss_Cybernetics_Core 1 5729
Protoss_Dragoon 6 15417
Protoss_Citadel_of_Adun 1 8797
Protoss_Templar_Archives 1 10395
Protoss_Nexus 2 15956
Singularity_Charge 1 9947
Protoss_Dark_Templar 2 12739
Protoss_High_Templar 2 13839
Protoss_Forge 1 14863
15956
