Protoss_Gateway 3 15609
Protoss_Zealot 3 7709
Protoss_Assimilator 1 5553
Protoss_Cybernetics_Core 1 7387
Protoss_Dragoon 6 15478
Protoss_Nexus 1 13000
Protoss_Robotics_Facility 1 12395
Protoss_Observatory 1 13166
Protoss_Observer 1 14420
15609
