Protoss_Gateway 4 15867
Protoss_Zealot 3 6997
Protoss_Assimilator 1 5436
Protoss_Cybernetics_Core 1 7018
Protoss_Dragoon 8 14984
Protoss_Nexus 1 12090
Protoss_Robotics_Facility 1 12259
Singularity_Charge 1 11097
Protoss_Observatory 1 12980
Protoss_Observer 1 14472
Protoss_Shuttle 1 15989
15989
