Protoss_Gateway 2 12276
Protoss_Zealot 2 6263
Protoss_Assimilator 1 5472
Protoss_Cybernetics_Core 1 7202
Protoss_Dragoon 9 15712
Protoss_Nexus 2 16860
Protoss_Robotics_Facility 1 11708
Protoss_Observatory 1 12415
Protoss_Observer 1 13454
Protoss_Robotics_Support_Bay 1 13351
Protoss_Reaver 1 15293
Singularity_Charge 1 13684
16860
