Protoss_Gateway 3 13433
Protoss_Assimilator 1 4271
Protoss_Cybernetics_Core 1 5614
Protoss_Zealot 4 9134
Protoss_Robotics_Facility 1 7902
Protoss_Shuttle 1 9311
Protoss_Observatory 1 9691
Protoss_Dragoon 7 14992
Protoss_Observer 3 13698
Singularity_Charge 1 13977
14992
