Protoss_Assimilator 1 3634
Protoss_Gateway 1 4836
Protoss_Cybernetics_Core 1 6314
Protoss_Robotics_Facility 1 8253
Protoss_Dragoon 4 14502
Protoss_Shuttle 1 9757
Protoss_Robotics_Support_Bay 1 9184
Protoss_Observatory 1 9396
Protoss_Observer 1 10600
Protoss_Reaver 2 13964
Gravitic_Drive 1 12916
Protoss_Nexus 1 16759
16759
