Protoss_Assimilator 1 3408
Protoss_Gateway 2 12791
Protoss_Cybernetics_Core 1 6465
Protoss_Robotics_Facility 1 8445
Protoss_Dragoon 9 15115
Protoss_Shuttle 2 13657
Protoss_Nexus 1 13642
Protoss_Observatory 1 11815
Protoss_Robotics_Support_Bay 1 13364
Protoss_Observer 1 14988
15115
