Protoss_Gateway 2 14295
Protoss_Assimilator 1 4223
Protoss_Cybernetics_Core 1 5648
Protoss_Robotics_Facility 1 7918
Protoss_Dragoon 3 15527
Protoss_Shuttle 1 9355
Protoss_Zealot 3 11186
Protoss_Robotics_Support_Bay 1 9492
Protoss_Reaver 2 13799
Protoss_Forge 1 13733
Gravitic_Drive 1 14087
Protoss_Photon_Cannon 3 15774
15774
