Protoss_Gateway 1 4324
Protoss_Assimilator 1 4425
Protoss_Cybernetics_Core 1 6083
Protoss_Zealot 3 11710
Protoss_Robotics_Facility 1 8470
Protoss_Dragoon 2 9446
Protoss_Shuttle 1 10065
Protoss_Robotics_Support_Bay 1 9830
Protoss_Reaver 2 15725
Protoss_Nexus 1 15179
Gravitic_Drive 1 14621
15725
