Protoss_Nexus 1 7252
Protoss_Gateway 3 15207
Protoss_Assimilator 1 6582
Protoss_Cybernetics_Core 1 8150
Protoss_Dragoon 8 15464
Protoss_Forge 1 11632
Protoss_Robotics_Facility 1 13513
Protoss_Photon_Cannon 4 13945
Singularity_Charge 1 13355
15464
