Protoss_Gateway 2 11158
Protoss_Assimilator 1 4593
Protoss_Zealot 5 14885
Protoss_Cybernetics_Core 1 7771
Protoss_Dragoon 2 10149
Protoss_Citadel_of_Adun 1 10151
Protoss_Robotics_Facility 1 11275
Protoss_Templar_Archives 1 11743
Protoss_Observatory 1 12148
Protoss_Shuttle 2 15094
Protoss_Dark_Templar 3 14095
Protoss_Observer 1 13736
Protoss_Forge 1 14389
15094
