Protoss_Gateway 2 9192
Protoss_Assimilator 1 4783
Protoss_Zealot 1 5534
Protoss_Cybernetics_Core 1 7269
Protoss_Dragoon 10 15563
Protoss_Robotics_Facility 1 11877
Singularity_Charge 1 11562
Protoss_Shuttle 1 13577
Protoss_Robotics_Support_Bay 1 13377
Protoss_Reaver 1 15388
15563
