Protoss_Gateway 2 11787
Protoss_Assimilator 1 4331
Protoss_Cybernetics_Core 1 6001
Protoss_Robotics_Facility 1 8035
Protoss_Dragoon 8 14095
Protoss_Observatory 1 8930
Protoss_Observer 2 12792
Protoss_Nexus 2 17064
Protoss_Forge 1 13050
Protoss_Photon_Cannon 1 14631
17064
