Protoss_Gateway 4 15181
Protoss_Assimilator 1 4578
Protoss_Zealot 1 5271
Protoss_Cybernetics_Core 1 7060
Protoss_Dragoon 10 14766
Singularity_Charge 1 11080
Protoss_Robotics_Facility 1 13141
Protoss_Observatory 1 13879
Protoss_Observer 1 14907
15181
