Protoss_Gateway 2 15725
Protoss_Assimilator 1 4474
Protoss_Zealot 2 7173
Protoss_Cybernetics_Core 1 7148
Protoss_Dragoon 2 10119
Protoss_Citadel_of_Adun 1 9402
Protoss_Templar_Archives 1 11177
Protoss_Robotics_Facility 1 12153
Protoss_Dark_Templar 1 12410
Protoss_Forge 1 12349
Protoss_High_Templar 3 15815
Protoss_Shuttle 1 14323
Protoss_Photon_Cannon 1 14637
Psionic_Storm 1 14365
15815
