Protoss_Gateway 3 14595
Protoss_Assimilator 1 4763
Protoss_Zealot 2 6759
Protoss_Cybernetics_Core 1 8029
Protoss_Dragoon 8 15032
Protoss_Robotics_Facility 1 10426
Protoss_Observatory 1 11248
Protoss_Observer 3 14366
Singularity_Charge 1 13377
Protoss_Shuttle 1 15724
15724
