Protoss_Assimilator 1 3661
Protoss_Gateway 3 10795
Protoss_Cybernetics_Core 1 6432
Protoss_Dragoon 1 7705
Protoss_Citadel_of_Adun 1 8190
Protoss_Zealot 11 14871
Leg_Enhancements 1 11233
Protoss_Templar_Archives 1 15087
15087
