Protoss_Gateway 2 15538
Protoss_Assimilator 1 4732
Protoss_Cybernetics_Core 1 6911
Protoss_Zealot 1 6858
Protoss_Dragoon 4 14542
Protoss_Robotics_Facility 1 9556
Protoss_Shuttle 1 11067
Protoss_Observatory 1 10589
Protoss_Robotics_Support_Bay 1 11123
Protoss_Observer 1 11910
Protoss_Reaver 2 15710
15710
