Protoss_Gateway 2 10211
Protoss_Assimilator 1 4763
Protoss_Zealot 1 5622
Protoss_Cybernetics_Core 1 7003
Protoss_Dragoon 7 14458
Protoss_Robotics_Facility 1 9000
Protoss_Shuttle 1 10452
Protoss_Observatory 1 9872
Protoss_Observer 1 11295
Protoss_Robotics_Support_Bay 1 11870
Protoss_Reaver 2 15644
Singularity_Charge 1 13340
15644
