Protoss_Gateway 1 4269
Protoss_Assimilator 1 4426
Protoss_Zealot 2 6649
Protoss_Cybernetics_Core 1 6760
Protoss_Dragoon 2 9911
Protoss_Citadel_of_Adun 1 8446
Protoss_Templar_Archives 1 9895
Protoss_Forge 1 10559
Protoss_Dark_Templar 2 12262
Protoss_High_Templar 3 15783
Protoss_Nexus 1 15624
Protoss_Photon_Cannon 5 15578
Psionic_Storm 1 14041
15783
