Protoss_Gateway 2 9201
Protoss_Assimilator 1 4191
Protoss_Cybernetics_Core 1 5663
Protoss_Dragoon 13 15367
Protoss_Robotics_Facility 1 10817
Singularity_Charge 1 9590
Protoss_Observatory 1 11513
Protoss_Observer 3 15152
Protoss_Nexus 1 16617
16617
