Protoss_Gateway 2 14673
Protoss_Assimilator 1 4474
Protoss_Cybernetics_Core 1 5733
Protoss_Robotics_Facility 1 7988
Protoss_Zealot 2 9014
Protoss_Shuttle 1 9391
Protoss_Observatory 1 8933
Protoss_Observer 3 14812
Protoss_Dragoon 5 15751
Protoss_Nexus 1 13849
15751
