Protoss_Gateway 3 12773
Protoss_Assimilator 1 4564
Protoss_Zealot 4 9302
Protoss_Cybernetics_Core 1 9598
Protoss_Dragoon 9 15724
Singularity_Charge 1 13333
Protoss_Nexus 1 17102
17102
