Protoss_Gateway 3 15434
Protoss_Zealot 5 8863
Protoss_Assimilator 1 6105
Protoss_Cybernetics_Core 1 8524
Protoss_Dragoon 5 15000
Protoss_Robotics_Facility 1 11720
Protoss_Observatory 1 12576
Protoss_Robotics_Support_Bay 1 12727
Protoss_Shuttle 1 13621
Protoss_Observer 2 15345
15434
