Protoss_Gateway 2 4997
Protoss_Zealot 9 10041
Protoss_Assimilator 1 7669
Protoss_Cybernetics_Core 1 9640
Protoss_Dragoon 8 15512
Protoss_Robotics_Facility 1 13702
Protoss_Forge 1 13796
Protoss_Observatory 1 14469
Protoss_Observer 1 15522
15522
