Protoss_Gateway 2 8658
Protoss_Zealot 5 12822
Protoss_Assimilator 1 5200
Protoss_Cybernetics_Core 1 6977
Protoss_Dragoon 1 8902
Protoss_Citadel_of_Adun 1 11371
Protoss_Templar_Archives 1 12833
Protoss_Forge 1 12548
Protoss_High_Templar 2 14531
Protoss_Nexus 1 16735
Protoss_Photon_Cannon 1 15610
16735
