Protoss_Gateway 3 12781
Protoss_Zealot 3 6968
Protoss_Assimilator 1 5386
Protoss_Cybernetics_Core 1 7160
Protoss_Dragoon 8 15388
Protoss_Nexus 1 11839
Protoss_Robotics_Facility 1 12117
Protoss_Observatory 1 12854
Protoss_Observer 2 14800
Protoss_Robotics_Support_Bay 1 13863
Singularity_Charge 1 14194
15388
