Protoss_Gateway 4 16040
Protoss_Assimilator 2 14822
Protoss_Zealot 2 6866
Protoss_Cybernetics_Core 1 6936
Protoss_Citadel_of_Adun 1 8392
Protoss_Dragoon 3 13702
Protoss_Templar_Archives 1 9848
Protoss_Nexus 1 12630
Protoss_Dark_Templar 2 12461
Protoss_High_Templar 1 14180
Protoss_Robotics_Facility 1 15285
16040
