Protoss_Gateway 3 15980
Protoss_Assimilator 2 15146
Protoss_Cybernetics_Core 1 5910
Protoss_Dragoon 5 14963
Protoss_Nexus 2 15425
Protoss_Forge 1 11275
Protoss_Photon_Cannon 1 12667
Singularity_Charge 1 12960
Protoss_Robotics_Facility 1 15007
15980
