Protoss_Gateway 3 15042
Protoss_Zealot 7 10003
Protoss_Assimilator 2 7174
Protoss_Cybernetics_Core 1 8892
Protoss_Dragoon 6 15818
Protoss_Robotics_Facility 1 14067
Singularity_Charge 1 14592
15818
