Protoss_Gateway 1 4280
Protoss_Assimilator 1 4586
Protoss_Zealot 2 6778
Protoss_Cybernetics_Core 1 7868
Protoss_Robotics_Facility 1 9867
Protoss_Dragoon 3 13122
Protoss_Shuttle 1 11528
Protoss_Robotics_Support_Bay 1 10898
Protoss_Citadel_of_Adun 1 12746
Protoss_Reaver 2 14642
Protoss_Forge 1 13095
Protoss_Templar_Archives 1 14203
Protoss_Dark_Templar 1 15461
15461
