Protoss_Gateway 3 11838
Protoss_Assimilator 1 4373
Protoss_Cybernetics_Core 1 5611
Protoss_Robotics_Facility 1 7822
Protoss_Dragoon 12 15442
Protoss_Shuttle 2 14857
Protoss_Observatory 1 8952
Protoss_Observer 2 15349
Protoss_Shield_Battery 1 11644
Singularity_Charge 1 11621
15442
