Protoss_Assimilator 1 3598
Protoss_Gateway 1 4975
Protoss_Cybernetics_Core 1 6438
Protoss_Dragoon 5 12140
Protoss_Robotics_Facility 1 9065
Protoss_Shuttle 1 10526
Protoss_Observatory 1 10836
Protoss_Observer 2 13072
Protoss_Robotics_Support_Bay 1 12437
Singularity_Charge 1 12060
Protoss_Reaver 2 16207
Protoss_Nexus 1 16664
16664
