Protoss_Gateway 3 11815
Protoss_Assimilator 1 4220
Protoss_Cybernetics_Core 1 5645
Protoss_Robotics_Facility 1 7697
Protoss_Dragoon 12 15717
Protoss_Shuttle 1 9113
Protoss_Observatory 1 9938
Protoss_Observer 2 14541
Singularity_Charge 1 11723
Protoss_Nexus 1 15293
15717
