Protoss_Assimilator 1 3589
Protoss_Gateway 2 11420
Protoss_Cybernetics_Core 1 6446
Protoss_Stargate 1 8147
Protoss_Citadel_of_Adun 1 8370
Protoss_Robotics_Facility 1 9570
Protoss_Corsair 2 11197
Protoss_Templar_Archives 1 10741
Protoss_Forge 1 10472
Protoss_Shuttle 1 10987
Protoss_Dark_Templar 3 13100
Protoss_Nexus 1 15652
Protoss_Dragoon 4 15734
15734
