Protoss_Assimilator 1 3681
Protoss_Gateway 1 4903
Protoss_Cybernetics_Core 1 6457
Protoss_Robotics_Facility 1 8446
Protoss_Observatory 1 9225
Protoss_Dragoon 5 14671
Singularity_Charge 1 12828
14671
