Protoss_Assimilator 1 3658
Protoss_Gateway 1 4748
Protoss_Cybernetics_Core 1 6211
Protoss_Robotics_Facility 2 9944
Protoss_Zealot 4 10327
Protoss_Observatory 1 9674
Protoss_Robotics_Support_Bay 1 10627
Protoss_Forge 1 13698
Protoss_Photon_Cannon 1 14997
14997
