Protoss_Gateway 1 4110
Protoss_Assimilator 1 4176
Protoss_Cybernetics_Core 1 5709
Protoss_Zealot 4 9154
Protoss_Robotics_Facility 2 15052
Protoss_Shuttle 2 15007
Protoss_Robotics_Support_Bay 1 9389
Protoss_Reaver 2 13705
Protoss_Dragoon 4 15322
Gravitic_Drive 1 14233
15322
