Protoss_Assimilator 1 3627
Protoss_Gateway 3 14957
Protoss_Cybernetics_Core 1 6285
Protoss_Robotics_Facility 1 8224
Protoss_Shuttle 1 9633
Protoss_Observatory 1 8959
Protoss_Robotics_Support_Bay 1 9091
Protoss_Dragoon 3 14371
Protoss_Observer 1 10476
Protoss_Reaver 2 14817
Protoss_Zealot 1 12251
Gravitic_Drive 1 12828
Protoss_Nexus 1 16939
16939
