Protoss_Assimilator 1 3895
Protoss_Gateway 3 14733
Protoss_Cybernetics_Core 1 6557
Protoss_Robotics_Facility 1 8528
Protoss_Dragoon 6 15393
Protoss_Observatory 1 9269
Protoss_Robotics_Support_Bay 1 9376
Protoss_Observer 2 14912
Protoss_Shuttle 1 11645
Protoss_Reaver 1 13589
Protoss_Nexus 1 14976
Gravitic_Drive 1 14281
15393
