Protoss_Assimilator 1 4631
Protoss_Gateway 1 5203
Protoss_Cybernetics_Core 1 6646
Protoss_Robotics_Facility 1 8577
Protoss_Dragoon 5 15042
Protoss_Shuttle 2 15839
Protoss_Observatory 1 9294
Protoss_Robotics_Support_Bay 1 10399
Protoss_Observer 1 10820
Protoss_Reaver 2 14008
15839
