Protoss_Assimilator 1 3665
Protoss_Gateway 2 9409
Protoss_Cybernetics_Core 1 6361
Protoss_Citadel_of_Adun 1 7843
Protoss_Forge 1 8707
Protoss_Templar_Archives 1 9624
Protoss_Photon_Cannon 3 12701
Protoss_Dark_Templar 6 13081
Protoss_Dark_Archon 2 12495
Protoss_Robotics_Facility 1 14100
Protoss_Dragoon 2 15153
Protoss_Shuttle 1 15552
15552
