Protoss_Assimilator 1 3632
Protoss_Gateway 1 4921
Protoss_Cybernetics_Core 1 6488
Protoss_Dragoon 3 13324
Protoss_Robotics_Facility 1 8792
Protoss_Shuttle 1 10350
Protoss_Robotics_Support_Bay 1 9721
Protoss_Observatory 1 9831
Protoss_Observer 3 14635
Singularity_Charge 1 11277
Protoss_Forge 1 13044
Protoss_Reaver 1 13810
Protoss_Nexus 1 15776
Protoss_Photon_Cannon 3 15808
Gravitic_Drive 1 14116
15808
