Protoss_Nexus 1 7301
Protoss_Gateway 5 15602
Protoss_Zealot 9 15288
Protoss_Assimilator 1 10073
Protoss_Forge 1 10621
Protoss_Cybernetics_Core 1 11731
Protoss_Photon_Cannon 1 12778
Protoss_Dragoon 4 14766
Protoss_Citadel_of_Adun 1 14057
15602
