Protoss_Gateway 3 15308
Protoss_Zealot 15 13129
Protoss_Assimilator 1 7791
Protoss_Forge 1 9842
Protoss_Cybernetics_Core 1 10919
Protoss_Photon_Cannon 2 14624
Protoss_Citadel_of_Adun 1 12806
Protoss_Templar_Archives 1 14260
Protoss_Dark_Templar 2 15475
15475
