Protoss_Gateway 2 8162
Protoss_Assimilator 1 4609
Protoss_Cybernetics_Core 1 5970
Protoss_Zealot 1 5805
Protoss_Dragoon 7 13375
Protoss_Robotics_Facility 1 13181
Singularity_Charge 1 13004
Protoss_Observatory 1 13992
Protoss_Robotics_Support_Bay 1 14390
Protoss_Observer 1 15053
Protoss_Nexus 1 17342
17342
