Protoss_Assimilator 1 3620
Protoss_Gateway 3 13397
Protoss_Cybernetics_Core 1 6226
Protoss_Zealot 11 15456
Protoss_Dragoon 1 7727
Protoss_Citadel_of_Adun 1 8282
Protoss_Templar_Archives 1 10183
Protoss_Dark_Templar 1 11392
Protoss_High_Templar 3 13580
Psionic_Storm 1 13904
15456
