Protoss_Gateway 2 6410
Protoss_Assimilator 1 4551
Protoss_Cybernetics_Core 1 5872
Protoss_Dragoon 11 15563
Protoss_Robotics_Facility 1 10222
Protoss_Observatory 1 10951
Protoss_Observer 3 14768
Singularity_Charge 1 12521
Protoss_Forge 1 14873
Protoss_Robotics_Support_Bay 1 15303
15563
