Protoss_Gateway 2 15179
Protoss_Assimilator 1 4387
Protoss_Cybernetics_Core 1 5818
Protoss_Zealot 1 6157
Protoss_Dragoon 7 15098
Protoss_Robotics_Facility 1 8410
Protoss_Shuttle 1 9895
Protoss_Observatory 1 9382
Protoss_Observer 2 11619
Singularity_Charge 1 13228
Protoss_Nexus 1 17210
Protoss_Forge 1 15419
17210
