Protoss_Gateway 3 14386
Protoss_Assimilator 1 4362
Protoss_Zealot 7 14350
Protoss_Cybernetics_Core 1 6787
Protoss_Citadel_of_Adun 1 8268
Protoss_Robotics_Facility 1 9256
Protoss_Templar_Archives 1 9860
Protoss_Shuttle 2 15429
Protoss_Dark_Templar 2 11182
Protoss_Forge 1 11294
Protoss_Photon_Cannon 1 12882
Leg_Enhancements 1 13597
Protoss_High_Templar 1 14916
15429
