Protoss_Gateway 3 15728
Protoss_Assimilator 1 4474
Protoss_Cybernetics_Core 1 5737
Protoss_Zealot 4 9612
Protoss_Dragoon 9 15768
Protoss_Robotics_Facility 1 12256
Protoss_Observatory 1 13362
Protoss_Observer 2 15397
15768
