Protoss_Gateway 4 15541
Protoss_Assimilator 2 14456
Protoss_Zealot 2 6465
Protoss_Cybernetics_Core 1 6573
Protoss_Robotics_Facility 1 8653
Protoss_Dragoon 10 15604
Protoss_Observatory 1 9483
Protoss_Observer 4 13684
Protoss_Nexus 1 14150
Singularity_Charge 1 11873
15604
