Protoss_Nexus 1 6804
Protoss_Forge 1 6481
Protoss_Gateway 1 7739
Protoss_Assimilator 2 10780
Protoss_Photon_Cannon 3 12426
Protoss_Cybernetics_Core 1 9766
Protoss_Zealot 1 9749
Protoss_Dragoon 2 12080
Protoss_Stargate 1 11804
12426
