Protoss_Forge 1 4148
Protoss_Nexus 1 7874
Protoss_Gateway 1 7316
Protoss_Photon_Cannon 2 8864
Protoss_Assimilator 1 7851
Protoss_Zealot 3 10407
Protoss_Cybernetics_Core 1 10679
Protoss_Citadel_of_Adun 1 12292
Protoss_Stargate 1 13030
13030
