Protoss_Forge 1 4872
Protoss_Photon_Cannon 2 6456
Protoss_Nexus 2 11393
Protoss_Gateway 1 9094
Protoss_Assimilator 2 11363
Protoss_Cybernetics_Core 1 11417
Protoss_Zealot 1 11812
11812
