Protoss_Forge 1 4735
Protoss_Photon_Cannon 4 12076
Protoss_Nexus 1 8921
Protoss_Gateway 2 12672
Protoss_Zealot 3 11250
Protoss_Assimilator 1 10032
Protoss_Cybernetics_Core 1 11393
12672
