Protoss_Gateway 2 5294
Protoss_Zealot 9 9463
Protoss_Forge 1 9885
Protoss_Photon_Cannon 1 11212
Protoss_Nexus 1 13454
Protoss_Assimilator 1 11603
Protoss_Cybernetics_Core 1 12690
13454
