Protoss_Nexus 1 7432
Protoss_Forge 1 5929
Protoss_Gateway 4 12067
Protoss_Assimilator 1 7293
Protoss_Photon_Cannon 1 7708
Protoss_Cybernetics_Core 1 9056
Protoss_Zealot 5 12353
Protoss_Citadel_of_Adun 1 10843
12353
