Protoss_Gateway 3 11067
Protoss_Zealot 7 10805
Protoss_Assimilator 1 6759
Protoss_Cybernetics_Core 1 8560
Protoss_Citadel_of_Adun 1 10101
Protoss_Dragoon 1 9944
Protoss_Templar_Archives 1 12157
12157
