Protoss_Forge 1 4472
Protoss_Nexus 1 7654
Protoss_Photon_Cannon 2 6876
Protoss_Gateway 1 8323
Protoss_Assimilator 2 9968
Protoss_Cybernetics_Core 1 10038
Protoss_Zealot 2 11003
Protoss_Stargate 1 11798
Protoss_Citadel_of_Adun 1 12146
12146
