Protoss_Forge 1 3844
Protoss_Photon_Cannon 3 10295
Protoss_Nexus 1 9417
Protoss_Gateway 2 12573
Protoss_Assimilator 1 8456
Protoss_Cybernetics_Core 1 10182
Protoss_Zealot 2 10868
Protoss_Citadel_of_Adun 1 12009
Protoss_Dragoon 1 11988
12573
