Protoss_Forge 1 3923
Protoss_Nexus 1 8078
Protoss_Photon_Cannon 3 10684
Protoss_Gateway 1 8048
Protoss_Assimilator 2 12197
Protoss_Zealot 3 11666
Protoss_Cybernetics_Core 1 11736
12197
