Protoss_Forge 1 4015
Protoss_Nexus 1 7805
Protoss_Gateway 1 7569
Protoss_Photon_Cannon 2 8909
Protoss_Assimilator 1 8039
Protoss_Zealot 3 10893
Protoss_Cybernetics_Core 1 10021
Protoss_Citadel_of_Adun 1 11724
11724
