Protoss_Gateway 3 10656
Protoss_Assimilator 1 4498
Protoss_Zealot 9 12269
Protoss_Cybernetics_Core 1 6950
Protoss_Dragoon 1 8510
Protoss_Citadel_of_Adun 1 9772
Protoss_Templar_Archives 1 11676
12269
