Protoss_Forge 1 4343
Protoss_Photon_Cannon 6 10460
Protoss_Nexus 1 9835
Protoss_Gateway 1 9277
Protoss_Assimilator 1 8991
Protoss_Zealot 1 10270
Protoss_Cybernetics_Core 1 11268
Protoss_Stargate 1 12976
12976
