Protoss_Forge 1 4094
Protoss_Photon_Cannon 2 7078
Protoss_Nexus 1 8121
Protoss_Gateway 1 7761
Protoss_Assimilator 2 9634
Protoss_Zealot 2 11446
Protoss_Cybernetics_Core 1 11390
11446
