Protoss_Gateway 1 4272
Protoss_Assimilator 1 4755
Protoss_Zealot 3 7798
Protoss_Cybernetics_Core 1 7025
Protoss_Stargate 1 8776
Protoss_Robotics_Facility 1 10511
Protoss_Scout 1 11045
Protoss_Dragoon 1 10741
Protoss_Shuttle 1 12069
Protoss_Robotics_Support_Bay 1 11774
12069
