Protoss_Gateway 1 4308
Protoss_Assimilator 1 4316
Protoss_Zealot 5 9339
Protoss_Cybernetics_Core 1 7120
Protoss_Stargate 1 9356
Protoss_Dragoon 2 11738
Protoss_Corsair 1 10580
11738
