Protoss_Forge 1 3867
Protoss_Photon_Cannon 2 5711
Protoss_Nexus 1 8997
Protoss_Gateway 1 8088
Protoss_Assimilator 2 10774
Protoss_Cybernetics_Core 1 9544
Protoss_Zealot 2 11686
Protoss_Stargate 1 11860
11860
