Protoss_Forge 1 3904
Protoss_Photon_Cannon 3 8891
Protoss_Nexus 1 9573
Protoss_Gateway 1 8458
Protoss_Zealot 3 11291
Protoss_Cybernetics_Core 1 10062
Protoss_Assimilator 1 9667
Protoss_Citadel_of_Adun 1 12118
12118
