Protoss_Forge 1 4144
Protoss_Gateway 1 5469
Protoss_Photon_Cannon 1 6146
Protoss_Zealot 4 12178
Protoss_Nexus 1 9688
Protoss_Assimilator 2 9535
Protoss_Cybernetics_Core 1 9415
Protoss_Stargate 1 11567
Protoss_Citadel_of_Adun 1 11689
12178
