Protoss_Nexus 1 7124
Protoss_Gateway 1 6230
Protoss_Forge 1 6769
Protoss_Zealot 2 9394
Protoss_Photon_Cannon 2 10699
Protoss_Assimilator 2 10947
Protoss_Cybernetics_Core 1 10349
Protoss_Stargate 1 12076
Protoss_Citadel_of_Adun 1 12604
12604
