Protoss_Nexus 1 7010
Protoss_Gateway 2 12067
Protoss_Forge 1 6510
Protoss_Assimilator 2 9558
Protoss_Photon_Cannon 1 7785
Protoss_Zealot 4 12125
Protoss_Cybernetics_Core 1 9877
Protoss_Stargate 1 11582
Protoss_Citadel_of_Adun 1 11464
12125
