Protoss_Forge 1 4632
Protoss_Photon_Cannon 6 12502
Protoss_Nexus 1 8364
Protoss_Gateway 1 8342
Protoss_Assimilator 1 8129
Protoss_Zealot 2 10205
Protoss_Cybernetics_Core 1 10148
12502
