Protoss_Gateway 1 4324
Protoss_Zealot 8 11663
Protoss_Forge 1 5739
Protoss_Nexus 1 10427
Protoss_Photon_Cannon 1 9208
Protoss_Assimilator 2 11708
Protoss_Cybernetics_Core 1 10842
11708
