Protoss_Forge 1 3889
Protoss_Photon_Cannon 2 6025
Protoss_Nexus 1 8788
Protoss_Gateway 1 7805
Protoss_Assimilator 2 11818
Protoss_Zealot 3 11472
Protoss_Cybernetics_Core 1 11469
11818
