Protoss_Forge 1 3753
Protoss_Photon_Cannon 2 5962
Protoss_Nexus 1 9321
Protoss_Gateway 1 8446
Protoss_Assimilator 2 11576
Protoss_Zealot 3 12152
Protoss_Cybernetics_Core 1 10606
Protoss_Stargate 1 12427
Protoss_Citadel_of_Adun 1 12489
12489
