Protoss_Nexus 1 6994
Protoss_Forge 1 5549
Protoss_Photon_Cannon 3 10599
Protoss_Gateway 1 8124
Protoss_Assimilator 2 10150
Protoss_Cybernetics_Core 1 9590
Protoss_Zealot 2 12090
Protoss_Stargate 1 11397
Protoss_Dragoon 1 11199
Protoss_Robotics_Facility 1 12980
Protoss_Corsair 1 12336
12980
