Protoss_Forge 1 3951
Protoss_Nexus 1 7840
Protoss_Gateway 1 6972
Protoss_Photon_Cannon 2 10775
Protoss_Assimilator 2 10861
Protoss_Cybernetics_Core 1 9156
Protoss_Zealot 2 11522
Protoss_Stargate 1 10917
Protoss_Citadel_of_Adun 1 11702
Protoss_Corsair 1 11941
11941
