Protoss_Forge 1 4741
Protoss_Nexus 1 7473
Protoss_Photon_Cannon 2 7734
Protoss_Gateway 1 7240
Protoss_Assimilator 2 11770
Protoss_Cybernetics_Core 1 9258
Protoss_Zealot 3 11339
Protoss_Stargate 1 10955
Protoss_Corsair 1 11903
Protoss_Robotics_Facility 1 13295
13295
