Protoss_Forge 1 4965
Protoss_Nexus 1 7527
Protoss_Photon_Cannon 2 7753
Protoss_Gateway 1 7621
Protoss_Assimilator 2 10429
Protoss_Cybernetics_Core 1 10167
Protoss_Zealot 2 11695
Protoss_Stargate 1 11902
Protoss_Citadel_of_Adun 1 11903
11903
