Protoss_Forge 1 5174
Protoss_Photon_Cannon 3 9393
Protoss_Nexus 1 9769
Protoss_Gateway 1 8610
Protoss_Assimilator 1 8775
Protoss_Cybernetics_Core 1 10325
Protoss_Zealot 2 11033
Protoss_Stargate 1 12176
Protoss_Citadel_of_Adun 1 12422
12422
