Protoss_Forge 1 4621
Protoss_Photon_Cannon 3 11283
Protoss_Nexus 1 8648
Protoss_Gateway 1 8156
Protoss_Assimilator 2 10139
Protoss_Cybernetics_Core 1 9687
Protoss_Zealot 3 11777
Protoss_Citadel_of_Adun 1 12175
12175
