Protoss_Gateway 1 4122
Protoss_Assimilator 1 4198
Protoss_Cybernetics_Core 1 5636
Protoss_Zealot 7 12002
Protoss_Stargate 1 7543
Protoss_Corsair 1 8631
Protoss_Citadel_of_Adun 1 11837
12002
