Protoss_Forge 1 4229
Protoss_Nexus 1 7591
Protoss_Photon_Cannon 2 7886
Protoss_Gateway 1 7809
Protoss_Zealot 3 11063
Protoss_Assimilator 2 10883
Protoss_Cybernetics_Core 1 11070
Protoss_Citadel_of_Adun 1 12738
12738
