Protoss_Forge 1 4590
Protoss_Photon_Cannon 3 12453
Protoss_Nexus 1 8226
Protoss_Gateway 1 7672
Protoss_Assimilator 2 11691
Protoss_Zealot 4 11952
Protoss_Cybernetics_Core 1 11319
12453
