Protoss_Forge 1 4242
Protoss_Photon_Cannon 3 11300
Protoss_Nexus 1 8654
Protoss_Gateway 1 7583
Protoss_Assimilator 1 7529
Protoss_Cybernetics_Core 1 9153
Protoss_Zealot 3 11317
Protoss_Stargate 1 11242
Protoss_Citadel_of_Adun 1 12040
Protoss_Corsair 1 12225
12225
