Protoss_Gateway 1 4035
Protoss_Zealot 8 12304
Protoss_Assimilator 2 7009
Protoss_Cybernetics_Core 1 8671
Protoss_Stargate 1 10601
Protoss_Citadel_of_Adun 1 11193
Protoss_Corsair 1 12315
12315
