Protoss_Forge 1 4313
Protoss_Photon_Cannon 6 11711
Protoss_Nexus 1 8513
Protoss_Gateway 1 8711
Protoss_Assimilator 1 8620
Protoss_Zealot 3 11917
Protoss_Cybernetics_Core 1 12794
12794
