Protoss_Gateway 1 4198
Protoss_Zealot 4 11513
Protoss_Nexus 1 8917
Protoss_Assimilator 1 7681
Protoss_Cybernetics_Core 1 9075
Protoss_Forge 1 8914
Protoss_Stargate 1 10765
Protoss_Dragoon 1 10652
Protoss_Photon_Cannon 1 11473
11513
