Protoss_Forge 1 3930
Protoss_Photon_Cannon 2 5767
Protoss_Nexus 1 8964
Protoss_Gateway 1 8095
Protoss_Assimilator 2 9822
Protoss_Cybernetics_Core 1 9629
Protoss_Zealot 2 10375
Protoss_Dragoon 1 10965
Protoss_Citadel_of_Adun 1 11549
11549
