Protoss_Forge 1 4129
Protoss_Nexus 1 7483
Protoss_Photon_Cannon 2 6765
Protoss_Gateway 1 7728
Protoss_Assimilator 2 10297
Protoss_Cybernetics_Core 1 9462
Protoss_Zealot 1 9971
Protoss_Stargate 1 11318
Protoss_Citadel_of_Adun 1 11601
Protoss_Dragoon 1 11761
11761
