Protoss_Forge 1 4356
Protoss_Photon_Cannon 2 8270
Protoss_Nexus 1 8908
Protoss_Gateway 1 8047
Protoss_Assimilator 2 10628
Protoss_Zealot 2 9989
Protoss_Cybernetics_Core 1 10299
Protoss_Stargate 1 12019
Protoss_Dragoon 1 11867
12019
