Protoss_Forge 1 4634
Protoss_Nexus 1 7585
Protoss_Photon_Cannon 3 12568
Protoss_Gateway 3 11916
Protoss_Assimilator 2 10296
Protoss_Zealot 3 11648
Protoss_Cybernetics_Core 1 9535
Protoss_Dragoon 1 10734
Protoss_Citadel_of_Adun 1 11285
12568
