Protoss_Forge 1 4839
Protoss_Nexus 1 7808
Protoss_Photon_Cannon 2 6881
Protoss_Gateway 1 7662
Protoss_Zealot 3 11917
Protoss_Assimilator 1 9400
Protoss_Cybernetics_Core 1 11205
Protoss_Stargate 1 13022
13022
