Protoss_Forge 1 4559
Protoss_Photon_Cannon 2 5894
Protoss_Nexus 1 8782
Protoss_Gateway 1 7755
Protoss_Assimilator 2 11691
Protoss_Cybernetics_Core 1 9233
Protoss_Zealot 3 11923
Protoss_Citadel_of_Adun 1 10782
Protoss_Dragoon 1 11062
11923
