Protoss_Gateway 1 3918
Protoss_Zealot 7 11710
Protoss_Forge 1 5183
Protoss_Photon_Cannon 3 7201
Protoss_Assimilator 1 7328
Protoss_Cybernetics_Core 1 11249
Protoss_Dragoon 1 12461
Protoss_Citadel_of_Adun 1 12826
12826
