Protoss_Forge 1 4450
Protoss_Nexus 1 7650
Protoss_Photon_Cannon 3 9660
Protoss_Gateway 1 7799
Protoss_Assimilator 1 8158
Protoss_Zealot 2 10665
Protoss_Cybernetics_Core 1 10742
Protoss_Stargate 1 12505
Protoss_Dragoon 1 12291
12505
