Protoss_Forge 1 3936
Protoss_Photon_Cannon 2 7582
Protoss_Nexus 1 8427
Protoss_Gateway 1 7305
Protoss_Zealot 3 11522
Protoss_Assimilator 2 11083
Protoss_Cybernetics_Core 1 10789
Protoss_Stargate 1 12511
12511
