Protoss_Forge 1 4609
Protoss_Photon_Cannon 3 8113
Protoss_Nexus 1 9172
Protoss_Gateway 1 9463
Protoss_Assimilator 2 11054
Protoss_Zealot 2 11487
Protoss_Cybernetics_Core 1 11080
Protoss_Citadel_of_Adun 1 12614
12614
