Protoss_Forge 1 4068
Protoss_Photon_Cannon 2 5668
Protoss_Nexus 1 8569
Protoss_Gateway 2 12248
Protoss_Assimilator 2 11650
Protoss_Zealot 3 12277
Protoss_Cybernetics_Core 1 9668
Protoss_Dragoon 1 11135
Protoss_Citadel_of_Adun 1 11828
12277
