Protoss_Forge 1 4132
Protoss_Photon_Cannon 3 9591
Protoss_Nexus 1 8902
Protoss_Gateway 1 7887
Protoss_Assimilator 2 11680
Protoss_Zealot 4 11909
Protoss_Cybernetics_Core 1 11003
Protoss_Stargate 1 13071
13071
