Protoss_Gateway 2 9535
Protoss_Assimilator 1 4615
Protoss_Zealot 8 11973
Protoss_Cybernetics_Core 1 6447
Protoss_Dragoon 1 7740
Protoss_Citadel_of_Adun 1 8499
Protoss_Templar_Archives 1 11153
11973
