Protoss_Forge 1 3734
Protoss_Photon_Cannon 2 5671
Protoss_Nexus 1 9175
Protoss_Gateway 1 8256
Protoss_Assimilator 2 11291
Protoss_Cybernetics_Core 1 9788
Protoss_Zealot 2 11952
Protoss_Dragoon 1 11091
Protoss_Stargate 1 11718
Protoss_Citadel_of_Adun 1 12560
12560
