Protoss_Forge 1 4204
Protoss_Photon_Cannon 2 6355
Protoss_Nexus 1 8721
Protoss_Gateway 1 7839
Protoss_Assimilator 2 11543
Protoss_Zealot 3 11803
Protoss_Cybernetics_Core 1 9639
Protoss_Stargate 1 11762
Protoss_Citadel_of_Adun 1 11815
11815
