Protoss_Nexus 1 6991
Protoss_Forge 1 5707
Protoss_Gateway 1 7060
Protoss_Photon_Cannon 2 12254
Protoss_Assimilator 2 10592
Protoss_Zealot 3 11007
Protoss_Cybernetics_Core 1 9342
Protoss_Stargate 1 11282
Protoss_Citadel_of_Adun 1 11897
Protoss_Dragoon 1 12115
Protoss_Corsair 1 12362
12362
