Protoss_Forge 1 4264
Protoss_Photon_Cannon 2 8603
Protoss_Nexus 1 8920
Protoss_Gateway 4 12090
Protoss_Assimilator 1 8234
Protoss_Zealot 2 11894
Protoss_Cybernetics_Core 1 10878
12090
