Protoss_Forge 1 4120
Protoss_Photon_Cannon 2 8040
Protoss_Nexus 1 8370
Protoss_Gateway 2 12781
Protoss_Assimilator 2 11642
Protoss_Cybernetics_Core 1 9943
Protoss_Zealot 3 11824
Protoss_Stargate 1 11637
Protoss_Citadel_of_Adun 1 11868
12781
