Protoss_Forge 1 4571
Protoss_Photon_Cannon 3 8103
Protoss_Nexus 1 9116
Protoss_Gateway 1 8812
Protoss_Assimilator 2 12081
Protoss_Zealot 1 10653
Protoss_Cybernetics_Core 1 11680
12081
