Protoss_Forge 1 4000
Protoss_Photon_Cannon 5 8706
Protoss_Nexus 1 9549
Protoss_Gateway 1 9709
Protoss_Assimilator 2 10606
Protoss_Cybernetics_Core 1 11260
Protoss_Zealot 2 11909
Protoss_Citadel_of_Adun 1 12809
12809
