Protoss_Forge 1 5187
Protoss_Nexus 1 8005
Protoss_Photon_Cannon 4 12148
Protoss_Gateway 1 8311
Protoss_Assimilator 2 11200
Protoss_Cybernetics_Core 1 10430
Protoss_Zealot 3 11903
Protoss_Stargate 1 12205
12205
