Protoss_Gateway 1 4070
Protoss_Assimilator 1 4391
Protoss_Zealot 5 10925
Protoss_Cybernetics_Core 1 6869
Protoss_Stargate 1 8602
Protoss_Dragoon 1 8474
Protoss_Citadel_of_Adun 1 9242
Protoss_Corsair 1 9579
Protoss_Templar_Archives 1 10922
Protoss_Forge 1 11388
Protoss_Dark_Templar 1 12148
12148
