Protoss_Forge 2 5655
Protoss_Nexus 1 7174
Protoss_Photon_Cannon 5 12303
Protoss_Gateway 1 7726
Protoss_Assimilator 2 11032
Protoss_Zealot 3 12263
Protoss_Cybernetics_Core 1 10275
Protoss_Stargate 1 12230
12303
