Protoss_Forge 1 3728
Protoss_Photon_Cannon 4 12026
Protoss_Nexus 1 9325
Protoss_Gateway 1 8232
Protoss_Assimilator 2 11500
Protoss_Cybernetics_Core 1 9734
Protoss_Zealot 2 10600
Protoss_Stargate 1 11620
Protoss_Robotics_Facility 1 13219
13219
