Protoss_Gateway 2 11066
Protoss_Assimilator 1 4400
Protoss_Zealot 4 10103
Protoss_Cybernetics_Core 1 6712
Protoss_Dragoon 1 7930
Protoss_Stargate 1 8653
Protoss_Citadel_of_Adun 1 9090
Protoss_Corsair 3 11985
Protoss_Templar_Archives 1 11273
Protoss_Dark_Templar 1 12563
12563
