Protoss_Forge 1 4707
Protoss_Nexus 1 7637
Protoss_Photon_Cannon 2 9816
Protoss_Gateway 1 7596
Protoss_Assimilator 2 10155
Protoss_Cybernetics_Core 1 9058
Protoss_Zealot 4 11841
Protoss_Stargate 1 11110
Protoss_Citadel_of_Adun 1 11966
Protoss_Corsair 1 12046
12046
