Protoss_Forge 1 4428
Protoss_Nexus 1 7568
Protoss_Photon_Cannon 2 6724
Protoss_Assimilator 2 9891
Protoss_Gateway 1 7684
Protoss_Zealot 4 12315
Protoss_Cybernetics_Core 1 9307
Protoss_Dragoon 1 10503
Protoss_Stargate 1 11266
Protoss_Citadel_of_Adun 1 12615
Protoss_Corsair 1 12254
12615
