Protoss_Forge 1 3972
Protoss_Nexus 1 7512
Protoss_Photon_Cannon 2 7520
Protoss_Gateway 1 8161
Protoss_Assimilator 1 7874
Protoss_Zealot 3 11680
Protoss_Cybernetics_Core 1 10634
Protoss_Stargate 1 12325
Protoss_Citadel_of_Adun 1 12380
12380
