Protoss_Gateway 1 4243
Protoss_Assimilator 1 4512
Protoss_Zealot 4 11531
Protoss_Cybernetics_Core 1 6892
Protoss_Dragoon 1 8188
Protoss_Stargate 1 9198
Protoss_Citadel_of_Adun 1 9485
Protoss_Corsair 1 10354
Protoss_Templar_Archives 1 11168
Protoss_Forge 1 11988
11988
