Protoss_Forge 1 4125
Protoss_Nexus 1 7664
Protoss_Gateway 1 6794
Protoss_Photon_Cannon 1 7561
Protoss_Assimilator 2 9905
Protoss_Zealot 2 9269
Protoss_Cybernetics_Core 1 9023
Protoss_Stargate 1 11008
Protoss_Dragoon 1 10822
Protoss_Citadel_of_Adun 1 11717
Protoss_Corsair 1 12336
12336
