Protoss_Forge 1 4128
Protoss_Photon_Cannon 2 5834
Protoss_Nexus 1 8844
Protoss_Gateway 1 7829
Protoss_Assimilator 2 11175
Protoss_Zealot 2 10117
Protoss_Cybernetics_Core 1 9500
Protoss_Stargate 1 11349
Protoss_Citadel_of_Adun 1 12213
Protoss_Dragoon 1 12402
12402
