Protoss_Gateway 1 4202
Protoss_Assimilator 1 4454
Protoss_Zealot 5 10416
Protoss_Cybernetics_Core 1 6912
Protoss_Stargate 1 8729
Protoss_Dragoon 1 8673
Protoss_Corsair 3 12204
Protoss_Citadel_of_Adun 1 10212
Protoss_Templar_Archives 1 11840
Protoss_Forge 1 11954
12204
