Protoss_Forge 1 4723
Protoss_Photon_Cannon 3 11359
Protoss_Nexus 1 8718
Protoss_Gateway 2 12631
Protoss_Assimilator 2 10612
Protoss_Cybernetics_Core 1 9163
Protoss_Zealot 2 9646
Protoss_Stargate 1 10862
Protoss_Citadel_of_Adun 1 11914
Protoss_Corsair 1 11830
12631
