Protoss_Nexus 1 7072
Protoss_Gateway 3 12244
Protoss_Forge 1 6272
Protoss_Assimilator 1 6700
Protoss_Photon_Cannon 2 10370
Protoss_Cybernetics_Core 1 8156
Protoss_Zealot 3 12175
Protoss_Dragoon 1 9777
Protoss_Stargate 1 10308
Protoss_Citadel_of_Adun 1 11638
Protoss_Corsair 2 12207
12244
