Protoss_Gateway 2 10334
Protoss_Zealot 6 11429
Protoss_Assimilator 1 5562
Protoss_Cybernetics_Core 1 7135
Protoss_Dragoon 1 8442
Protoss_Citadel_of_Adun 1 9172
Protoss_Templar_Archives 1 10695
Protoss_Forge 1 11958
Protoss_High_Templar 2 12549
12549
