Protoss_Forge 2 6096
Protoss_Nexus 1 7559
Protoss_Gateway 1 7229
Protoss_Photon_Cannon 2 7822
Protoss_Zealot 3 12163
Protoss_Assimilator 1 10069
Protoss_Cybernetics_Core 1 11742
12163
