Protoss_Forge 3 7261
Protoss_Nexus 1 7347
Protoss_Gateway 2 7286
Protoss_Assimilator 1 8165
Protoss_Zealot 8 12239
Protoss_Photon_Cannon 1 9759
Protoss_Cybernetics_Core 1 11657
12239
