Protoss_Gateway 1 4291
Protoss_Assimilator 1 4545
Protoss_Zealot 4 9833
Protoss_Cybernetics_Core 1 7328
Protoss_Dragoon 1 8542
Protoss_Robotics_Facility 1 9651
Protoss_Forge 1 10548
Protoss_Shuttle 1 11077
Protoss_Robotics_Support_Bay 1 10997
Protoss_Citadel_of_Adun 1 11853
Protoss_Reaver 1 12729
12729
