Protoss_Forge 1 4567
Protoss_Nexus 1 7607
Protoss_Photon_Cannon 2 6932
Protoss_Gateway 1 7951
Protoss_Assimilator 2 10856
Protoss_Cybernetics_Core 1 9655
Protoss_Zealot 2 11742
Protoss_Dragoon 1 10880
Protoss_Stargate 1 11387
Protoss_Citadel_of_Adun 1 11648
Protoss_Corsair 1 12359
12359
