Protoss_Forge 1 4139
Protoss_Photon_Cannon 2 5971
Protoss_Nexus 1 8810
Protoss_Gateway 1 7820
Protoss_Assimilator 2 10523
Protoss_Cybernetics_Core 1 9277
Protoss_Zealot 1 8923
Protoss_Stargate 1 10964
Protoss_Dragoon 1 11556
Protoss_Robotics_Facility 1 12765
Protoss_Corsair 1 12102
12765
