Protoss_Nexus 1 7410
Protoss_Forge 1 6115
Protoss_Gateway 2 12432
Protoss_Photon_Cannon 2 8600
Protoss_Assimilator 2 9719
Protoss_Cybernetics_Core 1 9680
Protoss_Zealot 3 11402
Protoss_Stargate 1 11454
Protoss_Citadel_of_Adun 1 11730
12432
