Protoss_Forge 1 4428
Protoss_Photon_Cannon 3 8003
Protoss_Nexus 1 8999
Protoss_Gateway 1 7752
Protoss_Assimilator 2 11554
Protoss_Cybernetics_Core 1 9400
Protoss_Zealot 3 11145
Protoss_Stargate 1 11503
Protoss_Citadel_of_Adun 1 12555
12555
