Protoss_Forge 1 4198
Protoss_Photon_Cannon 3 6783
Protoss_Nexus 1 8057
Protoss_Gateway 4 12137
Protoss_Assimilator 1 8044
Protoss_Zealot 3 11988
Protoss_Cybernetics_Core 1 9770
Protoss_Dragoon 1 11126
Protoss_Citadel_of_Adun 1 11623
12137
