Protoss_Forge 1 4229
Protoss_Photon_Cannon 2 5767
Protoss_Nexus 1 8671
Protoss_Gateway 1 8095
Protoss_Assimilator 2 9926
Protoss_Cybernetics_Core 1 9544
Protoss_Zealot 3 11666
Protoss_Dragoon 1 10775
Protoss_Stargate 1 11498
Protoss_Robotics_Facility 1 12509
12509
