Protoss_Forge 2 6140
Protoss_Nexus 1 7278
Protoss_Gateway 3 12029
Protoss_Photon_Cannon 1 7453
Protoss_Assimilator 2 9816
Protoss_Zealot 3 11405
Protoss_Cybernetics_Core 1 9037
Protoss_Stargate 1 10822
Protoss_Citadel_of_Adun 1 11083
Protoss_Templar_Archives 1 12624
Protoss_Corsair 1 12216
12624
