Protoss_Forge 1 4353
Protoss_Photon_Cannon 2 7380
Protoss_Nexus 1 8358
Protoss_Gateway 1 7265
Protoss_Assimilator 2 11376
Protoss_Zealot 4 12058
Protoss_Cybernetics_Core 1 9541
Protoss_Stargate 1 11702
12058
