Protoss_Forge 1 3910
Protoss_Photon_Cannon 3 10672
Protoss_Nexus 1 9306
Protoss_Gateway 1 8380
Protoss_Assimilator 2 11029
Protoss_Zealot 2 11367
Protoss_Cybernetics_Core 1 10325
Protoss_Citadel_of_Adun 1 12037
12037
