Protoss_Forge 1 3740
Protoss_Photon_Cannon 4 10201
Protoss_Nexus 1 8390
Protoss_Gateway 1 7392
Protoss_Zealot 4 11083
Protoss_Assimilator 2 11601
Protoss_Cybernetics_Core 1 11190
Protoss_Stargate 1 12960
12960
