Protoss_Forge 1 4141
Protoss_Nexus 1 7547
Protoss_Photon_Cannon 1 6297
Protoss_Gateway 3 12576
Protoss_Assimilator 2 10474
Protoss_Cybernetics_Core 1 9002
Protoss_Zealot 2 10659
Protoss_Stargate 1 10704
Protoss_Citadel_of_Adun 1 10701
Protoss_Corsair 1 11674
Protoss_Templar_Archives 1 12460
12576
