Protoss_Forge 1 4272
Protoss_Nexus 1 7597
Protoss_Photon_Cannon 3 12506
Protoss_Gateway 2 12364
Protoss_Assimilator 2 10340
Protoss_Cybernetics_Core 1 8919
Protoss_Zealot 1 8786
Protoss_Stargate 1 10759
Protoss_Dragoon 1 10418
Protoss_Citadel_of_Adun 1 11309
Protoss_Corsair 1 12307
12506
