Protoss_Forge 1 4460
Protoss_Photon_Cannon 4 9066
Protoss_Nexus 1 8882
Protoss_Gateway 1 8069
Protoss_Assimilator 2 11054
Protoss_Zealot 2 10793
Protoss_Cybernetics_Core 1 10688
Protoss_Stargate 1 12401
Protoss_Dragoon 1 12244
12401
