Protoss_Gateway 2 5171
Protoss_Zealot 7 11973
Protoss_Assimilator 1 6990
Protoss_Cybernetics_Core 2 8329
Protoss_Forge 1 8745
Protoss_Photon_Cannon 2 11144
Protoss_Citadel_of_Adun 1 11862
11973
