Protoss_Nexus 1 7808
Protoss_Forge 1 6372
Protoss_Gateway 1 6956
Protoss_Photon_Cannon 3 10479
Protoss_Assimilator 2 11925
Protoss_Cybernetics_Core 1 9946
Protoss_Zealot 3 12213
Protoss_Stargate 1 12087
Protoss_Citadel_of_Adun 1 12232
12232
