Protoss_Gateway 1 3716
Protoss_Zealot 3 7092
Protoss_Assimilator 1 6548
Protoss_Forge 1 7792
Protoss_Photon_Cannon 1 9129
Protoss_Cybernetics_Core 1 9609
Protoss_Dragoon 1 10888
Protoss_Stargate 1 11664
Protoss_Robotics_Facility 1 13094
13094
