Protoss_Forge 1 3813
Protoss_Nexus 1 7705
Protoss_Gateway 1 7038
Protoss_Photon_Cannon 2 8594
Protoss_Assimilator 2 10431
Protoss_Cybernetics_Core 1 8519
Protoss_Zealot 1 9591
Protoss_Stargate 1 10753
Protoss_Citadel_of_Adun 1 11229
Protoss_Dragoon 1 11425
Protoss_Corsair 1 11692
11692
