Protoss_Forge 1 4429
Protoss_Photon_Cannon 2 6102
Protoss_Nexus 1 8958
Protoss_Gateway 1 7949
Protoss_Assimilator 2 9876
Protoss_Cybernetics_Core 1 9403
Protoss_Stargate 1 11129
Protoss_Citadel_of_Adun 1 11565
Protoss_Corsair 1 12090
12090
