Protoss_Forge 1 4230
Protoss_Photon_Cannon 2 7061
Protoss_Nexus 1 7828
Protoss_Gateway 1 7015
Protoss_Assimilator 2 9891
Protoss_Cybernetics_Core 1 9308
Protoss_Zealot 3 12032
Protoss_Stargate 1 11375
Protoss_Citadel_of_Adun 1 11831
Protoss_Corsair 1 12312
12312
