Protoss_Gateway 2 5250
Protoss_Zealot 11 11516
Protoss_Forge 1 8576
Protoss_Photon_Cannon 1 10634
Protoss_Nexus 1 12947
Protoss_Assimilator 1 11841
Protoss_Cybernetics_Core 1 12754
12947
