Protoss_Forge 2 6857
Protoss_Nexus 1 7304
Protoss_Gateway 1 6838
Protoss_Assimilator 2 10830
Protoss_Photon_Cannon 2 12263
Protoss_Zealot 3 11156
Protoss_Cybernetics_Core 1 9626
Protoss_Stargate 1 11601
Protoss_Citadel_of_Adun 1 12841
12841
