Protoss_Forge 1 4155
Protoss_Nexus 1 8017
Protoss_Photon_Cannon 1 6707
Protoss_Gateway 1 7745
Protoss_Assimilator 2 10641
Protoss_Zealot 4 11639
Protoss_Cybernetics_Core 1 9295
Protoss_Stargate 1 11188
Protoss_Citadel_of_Adun 1 11793
11793
