Protoss_Forge 1 4501
Protoss_Nexus 1 7755
Protoss_Assimilator 2 10510
Protoss_Gateway 1 7489
Protoss_Photon_Cannon 2 8122
Protoss_Cybernetics_Core 1 9631
Protoss_Zealot 2 11724
Protoss_Dragoon 1 10863
Protoss_Stargate 1 11479
Protoss_Robotics_Facility 1 12869
12869
