Protoss_Forge 1 5036
Protoss_Nexus 1 7366
Protoss_Photon_Cannon 4 11097
Protoss_Gateway 1 7665
Protoss_Assimilator 3 12178
Protoss_Cybernetics_Core 1 9179
Protoss_Zealot 2 11057
Protoss_Stargate 1 10979
Protoss_Corsair 1 12067
12178
