Protoss_Forge 1 3959
Protoss_Photon_Cannon 5 11289
Protoss_Nexus 1 8484
Protoss_Gateway 1 7745
Protoss_Assimilator 2 11219
Protoss_Cybernetics_Core 1 11632
Protoss_Zealot 1 11996
11996
