Protoss_Forge 1 4594
Protoss_Photon_Cannon 5 12177
Protoss_Nexus 1 9141
Protoss_Gateway 1 8361
Protoss_Assimilator 2 11578
Protoss_Cybernetics_Core 1 10334
Protoss_Zealot 1 10448
Protoss_Stargate 1 12054
12177
