Protoss_Forge 1 4681
Protoss_Nexus 1 7511
Protoss_Photon_Cannon 3 9440
Protoss_Gateway 1 7975
Protoss_Assimilator 2 10902
Protoss_Cybernetics_Core 1 10622
Protoss_Zealot 1 10308
Protoss_Stargate 1 12331
Protoss_Dragoon 1 12022
12331
