Protoss_Nexus 1 7108
Protoss_Forge 1 6324
Protoss_Gateway 1 7550
Protoss_Photon_Cannon 3 9685
Protoss_Assimilator 2 10940
Protoss_Zealot 2 10512
Protoss_Cybernetics_Core 1 10594
Protoss_Stargate 1 12287
Protoss_Dragoon 1 12098
12287
