Protoss_Forge 1 4997
Protoss_Nexus 1 7369
Protoss_Photon_Cannon 1 6284
Protoss_Gateway 3 12438
Protoss_Assimilator 2 9844
Protoss_Zealot 3 10234
Protoss_Cybernetics_Core 1 9378
Protoss_Stargate 1 11356
Protoss_Citadel_of_Adun 1 12602
12602
