Protoss_Forge 1 4416
Protoss_Photon_Cannon 2 5924
Protoss_Nexus 1 8680
Protoss_Gateway 1 7675
Protoss_Assimilator 2 11153
Protoss_Cybernetics_Core 1 9192
Protoss_Zealot 2 10571
Protoss_Stargate 1 10882
Protoss_Citadel_of_Adun 1 11396
Protoss_Corsair 1 12087
12087
