Protoss_Forge 1 3719
Protoss_Nexus 1 7454
Protoss_Gateway 2 11417
Protoss_Assimilator 2 9201
Protoss_Photon_Cannon 2 9916
Protoss_Cybernetics_Core 1 8784
Protoss_Citadel_of_Adun 1 10398
Protoss_Dragoon 1 10588
Protoss_Templar_Archives 1 11849
Protoss_Zealot 1 11502
11849
