Protoss_Gateway 1 4286
Protoss_Zealot 5 11326
Protoss_Nexus 1 8796
Protoss_Assimilator 1 7104
Protoss_Cybernetics_Core 1 8592
Protoss_Forge 1 8695
Protoss_Photon_Cannon 2 11649
Protoss_Stargate 1 10788
Protoss_Corsair 1 11991
11991
