Protoss_Forge 1 4783
Protoss_Photon_Cannon 5 10475
Protoss_Nexus 1 10888
Protoss_Gateway 1 9854
Protoss_Assimilator 2 12308
Protoss_Cybernetics_Core 1 11306
Protoss_Zealot 1 11765
12308
