Protoss_Forge 1 3753
Protoss_Nexus 1 7339
Protoss_Photon_Cannon 1 6121
Protoss_Gateway 1 6863
Protoss_Assimilator 2 11212
Protoss_Zealot 3 11780
Protoss_Cybernetics_Core 1 9216
Protoss_Stargate 1 10993
Protoss_Citadel_of_Adun 1 10932
Protoss_Corsair 1 11929
11929
