Protoss_Forge 1 4735
Protoss_Nexus 1 7809
Protoss_Photon_Cannon 3 12311
Protoss_Gateway 1 7811
Protoss_Assimilator 2 11708
Protoss_Zealot 2 10384
Protoss_Cybernetics_Core 1 10018
Protoss_Stargate 1 11962
Protoss_Dragoon 1 12063
12311
