Protoss_Gateway 1 4170
Protoss_Zealot 5 11590
Protoss_Nexus 1 8759
Protoss_Forge 1 7615
Protoss_Cybernetics_Core 1 9286
Protoss_Assimilator 2 10627
Protoss_Photon_Cannon 2 12052
Protoss_Dragoon 1 10705
Protoss_Stargate 1 12154
12154
