Protoss_Nexus 1 7104
Protoss_Gateway 1 6236
Protoss_Forge 1 6386
Protoss_Assimilator 2 10733
Protoss_Photon_Cannon 2 11700
Protoss_Cybernetics_Core 1 8344
Protoss_Zealot 3 10035
Protoss_Stargate 1 10788
Protoss_Citadel_of_Adun 1 12100
Protoss_Corsair 1 11926
12100
