Protoss_Forge 1 4905
Protoss_Nexus 1 7661
Protoss_Photon_Cannon 2 9528
Protoss_Gateway 1 7543
Protoss_Assimilator 2 10082
Protoss_Cybernetics_Core 1 9375
Protoss_Stargate 1 11232
Protoss_Zealot 1 11481
Protoss_Citadel_of_Adun 1 12582
Protoss_Corsair 1 12172
12582
