Protoss_Forge 1 4668
Protoss_Nexus 1 7759
Protoss_Photon_Cannon 2 6838
Protoss_Gateway 1 7559
Protoss_Assimilator 2 11282
Protoss_Zealot 2 10334
Protoss_Cybernetics_Core 1 9429
Protoss_Dragoon 1 11638
Protoss_Citadel_of_Adun 1 12576
12576
