Protoss_Forge 1 4761
Protoss_Photon_Cannon 5 11356
Protoss_Nexus 1 10711
Protoss_Gateway 1 9561
Protoss_Assimilator 2 11954
Protoss_Cybernetics_Core 1 11010
Protoss_Zealot 2 11502
Protoss_Stargate 1 12966
12966
