Protoss_Nexus 1 6977
Protoss_Gateway 1 6178
Protoss_Forge 1 6583
Protoss_Photon_Cannon 2 11997
Protoss_Assimilator 2 10078
Protoss_Zealot 3 11830
Protoss_Cybernetics_Core 1 8808
Protoss_Stargate 1 10903
Protoss_Dragoon 1 10836
Protoss_Citadel_of_Adun 1 11660
Protoss_Corsair 1 11868
11997
