Protoss_Forge 1 4167
Protoss_Nexus 1 7615
Protoss_Gateway 1 7363
Protoss_Photon_Cannon 1 7408
Protoss_Assimilator 2 9081
Protoss_Cybernetics_Core 1 8887
Protoss_Zealot 2 11633
Protoss_Stargate 1 10786
Protoss_Dragoon 1 10348
Protoss_Citadel_of_Adun 1 10916
Protoss_Corsair 1 11724
11724
