Protoss_Forge 1 3804
Protoss_Photon_Cannon 3 6271
Protoss_Nexus 1 9780
Protoss_Gateway 1 8783
Protoss_Assimilator 2 10624
Protoss_Zealot 2 10808
Protoss_Cybernetics_Core 1 10332
Protoss_Stargate 1 12070
Protoss_Citadel_of_Adun 1 12245
Protoss_Dragoon 1 12203
12245
