Protoss_Forge 1 4710
Protoss_Nexus 1 7661
Protoss_Photon_Cannon 2 6932
Protoss_Gateway 2 11652
Protoss_Assimilator 2 9239
Protoss_Cybernetics_Core 1 9175
Protoss_Zealot 3 11376
Protoss_Stargate 1 10859
Protoss_Citadel_of_Adun 1 11509
Protoss_Corsair 1 11797
11797
