Protoss_Forge 1 3992
Protoss_Nexus 1 7767
Protoss_Gateway 1 7065
Protoss_Photon_Cannon 2 9815
Protoss_Assimilator 2 10100
Protoss_Cybernetics_Core 1 8753
Protoss_Zealot 3 11590
Protoss_Stargate 1 10642
Protoss_Citadel_of_Adun 1 11522
Protoss_Corsair 1 11686
11686
