Protoss_Nexus 1 7184
Protoss_Forge 1 6152
Protoss_Gateway 2 12735
Protoss_Photon_Cannon 2 7842
Protoss_Assimilator 2 9438
Protoss_Zealot 2 10012
Protoss_Cybernetics_Core 1 10252
Protoss_Stargate 1 12025
Protoss_Citadel_of_Adun 1 11887
12735
