Protoss_Forge 1 3809
Protoss_Photon_Cannon 3 8217
Protoss_Nexus 1 7670
Protoss_Gateway 1 7877
Protoss_Assimilator 2 10027
Protoss_Cybernetics_Core 1 9350
Protoss_Zealot 3 11696
Protoss_Stargate 1 11056
Protoss_Citadel_of_Adun 1 12197
Protoss_Corsair 1 12043
12197
