Protoss_Forge 1 4214
Protoss_Nexus 1 8017
Protoss_Photon_Cannon 1 7015
Protoss_Gateway 1 7649
Protoss_Assimilator 2 10281
Protoss_Cybernetics_Core 1 9277
Protoss_Zealot 2 10700
Protoss_Stargate 1 11134
Protoss_Citadel_of_Adun 1 12309
Protoss_Dragoon 1 12329
12329
