Protoss_Forge 1 3953
Protoss_Photon_Cannon 3 8469
Protoss_Gateway 1 7900
Protoss_Zealot 3 10791
Protoss_Nexus 1 12368
Protoss_Assimilator 1 11316
Protoss_Cybernetics_Core 1 12428
12428
