Protoss_Forge 1 4347
Protoss_Nexus 1 7661
Protoss_Photon_Cannon 2 6914
Protoss_Gateway 1 7811
Protoss_Assimilator 2 9838
Protoss_Cybernetics_Core 1 9646
Protoss_Zealot 2 11912
Protoss_Dragoon 1 11050
Protoss_Stargate 1 11612
Protoss_Citadel_of_Adun 1 12684
12684
