Protoss_Forge 1 4268
Protoss_Photon_Cannon 2 5846
Protoss_Nexus 1 8964
Protoss_Gateway 1 7919
Protoss_Assimilator 2 11317
Protoss_Cybernetics_Core 1 9466
Protoss_Zealot 1 9324
Protoss_Dragoon 1 10895
Protoss_Citadel_of_Adun 1 11546
11546
