Protoss_Gateway 2 4829
Protoss_Zealot 8 11871
Protoss_Assimilator 1 6848
Protoss_Cybernetics_Core 1 8380
Protoss_Stargate 1 10188
Protoss_Dragoon 1 10149
Protoss_Citadel_of_Adun 1 11186
Protoss_Corsair 1 11215
11871
