Protoss_Nexus 1 6936
Protoss_Forge 1 5276
Protoss_Photon_Cannon 3 12373
Protoss_Gateway 1 7609
Protoss_Zealot 3 11423
Protoss_Cybernetics_Core 1 9763
Protoss_Assimilator 1 11203
12373
