Protoss_Nexus 1 7057
Protoss_Gateway 3 12450
Protoss_Forge 1 6662
Protoss_Photon_Cannon 2 10026
Protoss_Zealot 3 11546
Protoss_Assimilator 2 10802
Protoss_Cybernetics_Core 1 9602
Protoss_Stargate 1 11901
Protoss_Citadel_of_Adun 1 12826
12826
