Protoss_Forge 1 4335
Protoss_Nexus 1 7740
Protoss_Gateway 1 7521
Protoss_Photon_Cannon 1 7782
Protoss_Assimilator 2 9775
Protoss_Cybernetics_Core 1 9311
Protoss_Zealot 1 9181
Protoss_Stargate 1 11045
Protoss_Dragoon 2 11682
Protoss_Robotics_Facility 1 12560
Protoss_Corsair 1 12017
12560
