Protoss_Gateway 1 4018
Protoss_Assimilator 1 4098
Protoss_Zealot 5 10632
Protoss_Cybernetics_Core 1 5764
Protoss_Stargate 1 7541
Protoss_Dragoon 1 7242
Protoss_Corsair 2 10849
Protoss_Citadel_of_Adun 1 9620
Protoss_Templar_Archives 1 11297
Protoss_Forge 1 11601
11601
