Protoss_Forge 1 3857
Protoss_Photon_Cannon 4 9802
Protoss_Nexus 1 10023
Protoss_Gateway 1 8985
Protoss_Assimilator 3 11960
Protoss_Zealot 3 12157
Protoss_Cybernetics_Core 1 11175
12157
