Protoss_Forge 1 4867
Protoss_Nexus 1 7866
Protoss_Photon_Cannon 2 7866
Protoss_Gateway 1 7246
Protoss_Assimilator 2 10031
Protoss_Cybernetics_Core 1 9716
Protoss_Stargate 1 11437
Protoss_Citadel_of_Adun 1 11683
11683
