Protoss_Gateway 1 4267
Protoss_Assimilator 1 4611
Protoss_Zealot 3 7685
Protoss_Cybernetics_Core 1 6026
Protoss_Robotics_Facility 1 8202
Protoss_Shuttle 1 9611
Protoss_Robotics_Support_Bay 1 8950
Protoss_Dragoon 1 9891
Protoss_Reaver 1 11415
Protoss_Stargate 1 12498
12498
