Protoss_Forge 1 4647
Protoss_Photon_Cannon 2 6249
Protoss_Nexus 1 8686
Protoss_Gateway 3 12715
Protoss_Assimilator 1 7848
Protoss_Cybernetics_Core 1 9179
Protoss_Zealot 2 9672
Protoss_Citadel_of_Adun 1 11082
Protoss_Dragoon 1 10948
12715
