Protoss_Forge 1 4325
Protoss_Photon_Cannon 2 5884
Protoss_Nexus 1 8823
Protoss_Gateway 1 7758
Protoss_Assimilator 2 12007
Protoss_Cybernetics_Core 1 9273
Protoss_Zealot 3 10630
Protoss_Stargate 1 11146
Protoss_Corsair 1 12195
Protoss_Citadel_of_Adun 1 12770
12770
