Protoss_Forge 1 4760
Protoss_Nexus 1 7606
Protoss_Photon_Cannon 3 12151
Protoss_Gateway 1 7130
Protoss_Assimilator 1 7192
Protoss_Zealot 1 8168
Protoss_Cybernetics_Core 1 9045
Protoss_Stargate 1 11251
Protoss_Dragoon 1 11615
Protoss_Citadel_of_Adun 1 12216
Protoss_Corsair 1 12187
12216
