Protoss_Forge 1 4248
Protoss_Photon_Cannon 4 10394
Protoss_Nexus 1 9257
Protoss_Gateway 1 8177
Protoss_Assimilator 2 11897
Protoss_Zealot 2 11194
Protoss_Cybernetics_Core 1 11469
11897
