Protoss_Nexus 1 6912
Protoss_Forge 1 5789
Protoss_Gateway 1 6807
Protoss_Photon_Cannon 1 7640
Protoss_Assimilator 2 9924
Protoss_Zealot 4 11961
Protoss_Cybernetics_Core 1 9697
Protoss_Stargate 1 11620
Protoss_Citadel_of_Adun 1 12664
12664
