Protoss_Forge 1 4845
Protoss_Nexus 1 7509
Protoss_Photon_Cannon 3 11979
Protoss_Gateway 1 7802
Protoss_Assimilator 2 11338
Protoss_Cybernetics_Core 1 9535
Protoss_Zealot 1 9951
Protoss_Stargate 1 11216
Protoss_Dragoon 1 11202
Protoss_Citadel_of_Adun 1 12437
Protoss_Corsair 1 12269
12437
