Protoss_Forge 1 4012
Protoss_Nexus 1 8030
Protoss_Gateway 1 7331
Protoss_Photon_Cannon 2 11586
Protoss_Assimilator 2 12087
Protoss_Cybernetics_Core 1 9314
Protoss_Zealot 2 11584
Protoss_Stargate 1 11143
Protoss_Corsair 1 12219
12219
