Protoss_Forge 2 12029
Protoss_Photon_Cannon 3 8293
Protoss_Gateway 2 7398
Protoss_Zealot 4 10747
Protoss_Assimilator 1 8592
Protoss_Cybernetics_Core 1 10204
Protoss_Stargate 1 12057
Protoss_Dragoon 1 11867
12057
