Protoss_Forge 1 5238
Protoss_Nexus 1 7522
Protoss_Gateway 1 6772
Protoss_Photon_Cannon 1 6885
Protoss_Assimilator 2 10489
Protoss_Cybernetics_Core 1 8780
Protoss_Zealot 3 10785
Protoss_Stargate 1 10698
Protoss_Citadel_of_Adun 1 11505
Protoss_Corsair 1 11639
11639
