Protoss_Forge 1 4498
Protoss_Nexus 1 7656
Protoss_Photon_Cannon 2 6891
Protoss_Gateway 1 7834
Protoss_Assimilator 2 10381
Protoss_Cybernetics_Core 1 9969
Protoss_Zealot 1 10003
Protoss_Citadel_of_Adun 1 11856
Protoss_Stargate 1 12303
12303
