Protoss_Forge 1 4747
Protoss_Nexus 1 7637
Protoss_Photon_Cannon 1 6405
Protoss_Gateway 1 7264
Protoss_Assimilator 2 9709
Protoss_Cybernetics_Core 1 8897
Protoss_Zealot 3 12359
Protoss_Stargate 1 10791
Protoss_Citadel_of_Adun 1 11364
Protoss_Corsair 1 11727
12359
