Protoss_Forge 1 4517
Protoss_Photon_Cannon 6 11681
Protoss_Nexus 1 9265
Protoss_Gateway 1 8461
Protoss_Assimilator 1 8669
Protoss_Cybernetics_Core 1 10046
Protoss_Zealot 3 11680
11681
