Protoss_Forge 1 4242
Protoss_Photon_Cannon 2 9396
Protoss_Nexus 1 8741
Protoss_Gateway 2 12178
Protoss_Assimilator 1 7760
Protoss_Cybernetics_Core 1 9292
Protoss_Zealot 3 11569
Protoss_Stargate 1 11018
Protoss_Citadel_of_Adun 1 11461
Protoss_Corsair 2 12157
12178
