Protoss_Forge 1 4429
Protoss_Photon_Cannon 3 11423
Protoss_Nexus 1 8861
Protoss_Gateway 2 12324
Protoss_Assimilator 1 7567
Protoss_Cybernetics_Core 1 9266
Protoss_Zealot 3 11973
Protoss_Stargate 1 11222
Protoss_Dragoon 1 11111
Protoss_Corsair 1 12304
12324
