Protoss_Forge 1 4868
Protoss_Nexus 1 7781
Protoss_Photon_Cannon 3 12377
Protoss_Gateway 1 7485
Protoss_Assimilator 1 7163
Protoss_Zealot 3 12274
Protoss_Cybernetics_Core 1 11519
12377
