Protoss_Forge 1 4239
Protoss_Nexus 1 7692
Protoss_Gateway 1 6678
Protoss_Assimilator 1 6552
Protoss_Photon_Cannon 3 11632
Protoss_Cybernetics_Core 1 8446
Protoss_Stargate 1 10212
Protoss_Zealot 2 12049
Protoss_Corsair 1 11247
Protoss_Citadel_of_Adun 1 12219
12219
