Protoss_Nexus 1 7085
Protoss_Forge 1 5906
Protoss_Gateway 1 7520
Protoss_Photon_Cannon 2 10345
Protoss_Assimilator 2 9585
Protoss_Cybernetics_Core 1 9232
Protoss_Zealot 1 9049
Protoss_Dragoon 1 10471
Protoss_Stargate 1 11151
Protoss_Citadel_of_Adun 1 12053
Protoss_Corsair 1 12149
12149
