Protoss_Forge 1 4747
Protoss_Nexus 1 7755
Protoss_Gateway 1 6819
Protoss_Assimilator 2 11462
Protoss_Photon_Cannon 1 7514
Protoss_Cybernetics_Core 1 8622
Protoss_Zealot 2 11036
Protoss_Dragoon 1 9920
Protoss_Stargate 1 10800
Protoss_Citadel_of_Adun 1 10975
Protoss_Corsair 1 11786
Protoss_Templar_Archives 1 12749
12749
