Protoss_Forge 1 4722
Protoss_Nexus 1 7846
Protoss_Photon_Cannon 2 7067
Protoss_Assimilator 3 11511
Protoss_Gateway 1 8016
Protoss_Cybernetics_Core 1 9503
Protoss_Zealot 4 11944
Protoss_Stargate 1 11220
Protoss_Citadel_of_Adun 1 11827
Protoss_Corsair 1 12339
12339
