Protoss_Forge 1 4138
Protoss_Photon_Cannon 2 5811
Protoss_Nexus 1 8784
Protoss_Gateway 1 7706
Protoss_Assimilator 2 9915
Protoss_Cybernetics_Core 1 9298
Protoss_Zealot 1 9380
Protoss_Stargate 1 11140
Protoss_Dragoon 1 11100
Protoss_Citadel_of_Adun 1 11909
Protoss_Corsair 1 12327
12327
