Protoss_Forge 1 4272
Protoss_Nexus 1 7802
Protoss_Photon_Cannon 2 7072
Protoss_Gateway 1 7688
Protoss_Assimilator 1 7703
Protoss_Cybernetics_Core 1 9214
Protoss_Zealot 3 11562
Protoss_Stargate 1 11014
Protoss_Citadel_of_Adun 1 11730
Protoss_Corsair 1 12055
12055
