Protoss_Forge 1 4144
Protoss_Nexus 1 7597
Protoss_Photon_Cannon 3 11264
Protoss_Gateway 1 8440
Protoss_Assimilator 2 10100
Protoss_Cybernetics_Core 1 10111
Protoss_Zealot 1 10261
Protoss_Stargate 2 12861
12861
