Protoss_Forge 1 4479
Protoss_Photon_Cannon 3 8596
Protoss_Nexus 1 9281
Protoss_Gateway 1 9017
Protoss_Assimilator 1 8873
Protoss_Zealot 3 11863
Protoss_Cybernetics_Core 1 10594
Protoss_Stargate 1 12429
Protoss_Citadel_of_Adun 1 12349
12429
