Protoss_Forge 1 4829
Protoss_Photon_Cannon 2 6448
Protoss_Nexus 1 8602
Protoss_Gateway 1 7700
Protoss_Assimilator 2 11730
Protoss_Cybernetics_Core 1 9197
Protoss_Zealot 4 11756
Protoss_Stargate 1 11056
Protoss_Citadel_of_Adun 1 11990
Protoss_Corsair 1 12011
12011
