Protoss_Forge 1 4590
Protoss_Photon_Cannon 4 12405
Protoss_Nexus 1 8993
Protoss_Gateway 1 8317
Protoss_Assimilator 2 10214
Protoss_Zealot 4 12283
Protoss_Cybernetics_Core 1 9880
Protoss_Stargate 1 11561
Protoss_Citadel_of_Adun 1 12097
12405
