Protoss_Forge 1 4543
Protoss_Photon_Cannon 2 5840
Protoss_Nexus 1 8741
Protoss_Gateway 2 11944
Protoss_Assimilator 2 10640
Protoss_Cybernetics_Core 1 9156
Protoss_Zealot 2 9749
Protoss_Stargate 1 10844
Protoss_Corsair 1 11879
Protoss_Citadel_of_Adun 1 12744
12744
