Protoss_Forge 1 4733
Protoss_Photon_Cannon 2 7751
Protoss_Nexus 1 8396
Protoss_Gateway 2 12579
Protoss_Assimilator 2 11025
Protoss_Cybernetics_Core 1 9633
Protoss_Zealot 3 11859
Protoss_Stargate 1 11517
Protoss_Citadel_of_Adun 1 12055
12579
