Protoss_Gateway 2 4793
Protoss_Zealot 8 10905
Protoss_Assimilator 1 8045
Protoss_Cybernetics_Core 1 9427
Protoss_Stargate 1 11208
Protoss_Forge 1 11538
Protoss_Corsair 1 12304
12304
