Protoss_Forge 1 3959
Protoss_Photon_Cannon 4 8264
Protoss_Nexus 1 9580
Protoss_Gateway 1 9031
Protoss_Assimilator 2 11926
Protoss_Cybernetics_Core 1 10812
Protoss_Zealot 3 12345
12345
