Protoss_Forge 1 4897
Protoss_Photon_Cannon 2 6796
Protoss_Nexus 1 8961
Protoss_Gateway 1 7903
Protoss_Assimilator 2 11481
Protoss_Cybernetics_Core 1 9403
Protoss_Zealot 2 9895
Protoss_Stargate 1 11132
Protoss_Dragoon 1 11015
Protoss_Citadel_of_Adun 1 12623
12623
