Protoss_Forge 1 3929
Protoss_Nexus 1 7521
Protoss_Gateway 2 12677
Protoss_Assimilator 2 10416
Protoss_Photon_Cannon 1 7804
Protoss_Zealot 2 8900
Protoss_Cybernetics_Core 1 8850
Protoss_Dragoon 1 10055
Protoss_Stargate 1 10686
Protoss_Citadel_of_Adun 1 11320
Protoss_Corsair 1 11686
12677
