Protoss_Nexus 1 7275
Protoss_Forge 1 6315
Protoss_Gateway 1 7354
Protoss_Photon_Cannon 1 7898
Protoss_Assimilator 2 10632
Protoss_Cybernetics_Core 1 9501
Protoss_Zealot 2 10106
Protoss_Dragoon 1 11226
Protoss_Stargate 1 12530
12530
