Protoss_Gateway 1 4264
Protoss_Assimilator 1 4548
Protoss_Zealot 3 7191
Protoss_Cybernetics_Core 1 7196
Protoss_Dragoon 3 10866
Protoss_Robotics_Facility 1 9702
Protoss_Robotics_Support_Bay 1 10541
Protoss_Reaver 1 12307
Protoss_Nexus 1 13661
13661
