Protoss_Forge 1 4665
Protoss_Photon_Cannon 1 5937
Protoss_Nexus 1 8144
Protoss_Gateway 1 7085
Protoss_Assimilator 2 9749
Protoss_Zealot 3 10992
Protoss_Cybernetics_Core 1 9778
Protoss_Stargate 1 11907
Protoss_Citadel_of_Adun 1 12099
12099
