Protoss_Forge 1 4116
Protoss_Photon_Cannon 2 6117
Protoss_Nexus 1 8910
Protoss_Gateway 1 8013
Protoss_Assimilator 2 10864
Protoss_Cybernetics_Core 1 9694
Protoss_Zealot 4 12355
Protoss_Stargate 1 11680
12355
