Protoss_Gateway 1 4212
Protoss_Zealot 8 11739
Protoss_Nexus 1 9798
Protoss_Assimilator 1 8519
Protoss_Cybernetics_Core 1 9838
Protoss_Forge 1 10069
Protoss_Stargate 1 11561
Protoss_Photon_Cannon 2 12546
Protoss_Citadel_of_Adun 1 12460
12546
