Protoss_Forge 1 5254
Protoss_Nexus 1 7577
Protoss_Photon_Cannon 2 6935
Protoss_Gateway 2 12238
Protoss_Assimilator 2 10467
Protoss_Cybernetics_Core 1 9627
Protoss_Zealot 3 12190
Protoss_Stargate 1 11514
Protoss_Citadel_of_Adun 1 11818
12238
