Protoss_Forge 1 4766
Protoss_Nexus 1 7625
Protoss_Photon_Cannon 2 6794
Protoss_Gateway 1 7758
Protoss_Assimilator 2 11013
Protoss_Cybernetics_Core 1 9201
Protoss_Zealot 3 12210
Protoss_Stargate 1 10882
Protoss_Corsair 1 11827
Protoss_Citadel_of_Adun 1 12601
12601
