Protoss_Forge 1 4129
Protoss_Photon_Cannon 2 7031
Protoss_Nexus 1 8223
Protoss_Gateway 1 7668
Protoss_Assimilator 2 10226
Protoss_Cybernetics_Core 1 9235
Protoss_Zealot 2 9667
Protoss_Stargate 1 11157
Protoss_Citadel_of_Adun 1 11683
Protoss_Corsair 1 12096
12096
