Protoss_Gateway 2 4656
Protoss_Zealot 8 12058
Protoss_Assimilator 1 6952
Protoss_Cybernetics_Core 1 9005
Protoss_Stargate 1 11365
Protoss_Dragoon 1 11451
Protoss_Citadel_of_Adun 1 12149
12149
