Protoss_Forge 1 4325
Protoss_Photon_Cannon 3 6290
Protoss_Nexus 1 9156
Protoss_Gateway 2 12708
Protoss_Assimilator 1 8016
Protoss_Cybernetics_Core 1 9715
Protoss_Zealot 4 12277
Protoss_Stargate 1 11443
Protoss_Citadel_of_Adun 1 12166
12708
