Protoss_Gateway 1 4291
Protoss_Forge 1 4837
Protoss_Assimilator 1 5143
Protoss_Photon_Cannon 2 7763
Protoss_Cybernetics_Core 1 7095
Protoss_Dragoon 1 8325
Protoss_Stargate 1 9357
Protoss_Corsair 1 10668
Protoss_Zealot 1 11903
11903
