Protoss_Forge 1 3888
Protoss_Photon_Cannon 2 5845
Protoss_Nexus 1 9524
Protoss_Gateway 1 8553
Protoss_Assimilator 2 11478
Protoss_Cybernetics_Core 1 10075
Protoss_Zealot 3 12213
Protoss_Stargate 1 11857
12213
