Protoss_Forge 1 4227
Protoss_Nexus 1 8061
Protoss_Gateway 1 7264
Protoss_Assimilator 2 9784
Protoss_Photon_Cannon 1 8027
Protoss_Cybernetics_Core 1 9011
Protoss_Zealot 2 11672
Protoss_Stargate 1 10846
Protoss_Dragoon 1 10810
Protoss_Robotics_Facility 1 12262
Protoss_Corsair 1 11844
12262
