Protoss_Forge 1 4112
Protoss_Photon_Cannon 3 7446
Protoss_Nexus 1 8665
Protoss_Gateway 1 8177
Protoss_Assimilator 2 11133
Protoss_Zealot 2 11291
Protoss_Cybernetics_Core 1 10556
Protoss_Stargate 1 12553
Protoss_Citadel_of_Adun 1 12775
12775
