Protoss_Nexus 1 7137
Protoss_Gateway 3 12569
Protoss_Forge 1 6680
Protoss_Assimilator 1 7226
Protoss_Zealot 4 10299
Protoss_Photon_Cannon 1 8565
Protoss_Cybernetics_Core 1 9421
Protoss_Citadel_of_Adun 1 11328
Protoss_Dragoon 1 11548
12569
