Protoss_Forge 1 4732
Protoss_Photon_Cannon 2 6247
Protoss_Nexus 1 8724
Protoss_Gateway 1 7732
Protoss_Assimilator 1 7719
Protoss_Cybernetics_Core 1 9311
Protoss_Zealot 2 11645
Protoss_Dragoon 1 10716
Protoss_Stargate 1 11667
Protoss_Citadel_of_Adun 1 12503
12503
