Protoss_Forge 1 4501
Protoss_Photon_Cannon 2 6054
Protoss_Nexus 1 9213
Protoss_Gateway 1 8294
Protoss_Assimilator 2 9497
Protoss_Cybernetics_Core 1 9787
Protoss_Zealot 2 11991
Protoss_Stargate 2 12998
Protoss_Dragoon 1 11021
Protoss_Robotics_Facility 1 12469
12998
