Protoss_Forge 1 4311
Protoss_Photon_Cannon 1 5613
Protoss_Nexus 1 8239
Protoss_Gateway 1 7324
Protoss_Assimilator 2 9349
Protoss_Zealot 4 11717
Protoss_Cybernetics_Core 1 9109
Protoss_Stargate 2 12893
Protoss_Robotics_Facility 1 12292
12893
