Protoss_Gateway 1 4024
Protoss_Assimilator 1 4230
Protoss_Zealot 6 11912
Protoss_Cybernetics_Core 1 6519
Protoss_Dragoon 1 7754
Protoss_Stargate 1 8719
Protoss_Corsair 2 11194
Protoss_Nexus 1 12685
Protoss_Forge 1 12219
12685
