Protoss_Gateway 2 12456
Protoss_Zealot 4 10656
Protoss_Nexus 1 8762
Protoss_Assimilator 2 9270
Protoss_Cybernetics_Core 1 8364
Protoss_Stargate 1 10127
Protoss_Citadel_of_Adun 1 10720
Protoss_Forge 1 10928
Protoss_Corsair 1 11086
Protoss_Templar_Archives 1 12198
12456
