Protoss_Forge 1 4347
Protoss_Nexus 1 7629
Protoss_Photon_Cannon 2 6970
Protoss_Gateway 2 11547
Protoss_Assimilator 1 7871
Protoss_Cybernetics_Core 1 9601
Protoss_Zealot 2 11631
Protoss_Stargate 1 11388
Protoss_Citadel_of_Adun 1 11812
11812
