Protoss_Gateway 1 4068
Protoss_Assimilator 1 4514
Protoss_Zealot 4 11607
Protoss_Cybernetics_Core 1 7022
Protoss_Dragoon 1 8341
Protoss_Robotics_Facility 1 10069
Protoss_Shuttle 1 11513
Protoss_Robotics_Support_Bay 1 10952
Protoss_Reaver 1 13071
13071
