Protoss_Forge 1 4354
Protoss_Photon_Cannon 2 6019
Protoss_Nexus 1 9245
Protoss_Gateway 3 12544
Protoss_Assimilator 1 8377
Protoss_Zealot 1 9617
Protoss_Cybernetics_Core 1 10201
Protoss_Dragoon 1 11398
Protoss_Citadel_of_Adun 1 11909
12544
