Protoss_Forge 1 4578
Protoss_Nexus 1 7887
Protoss_Gateway 1 6857
Protoss_Photon_Cannon 2 7769
Protoss_Assimilator 2 9869
Protoss_Cybernetics_Core 1 9263
Protoss_Zealot 1 10340
Protoss_Stargate 1 11488
Protoss_Citadel_of_Adun 1 11865
11865
