Protoss_Forge 1 4652
Protoss_Nexus 1 7878
Protoss_Photon_Cannon 3 11785
Protoss_Gateway 1 8758
Protoss_Assimilator 2 10186
Protoss_Zealot 2 10665
Protoss_Cybernetics_Core 1 10467
Protoss_Stargate 1 12209
Protoss_Citadel_of_Adun 1 12595
12595
