Protoss_Forge 1 4565
Protoss_Photon_Cannon 2 5924
Protoss_Nexus 1 8872
Protoss_Gateway 2 12795
Protoss_Assimilator 2 10770
Protoss_Zealot 2 10056
Protoss_Cybernetics_Core 1 9980
Protoss_Stargate 1 11807
Protoss_Dragoon 1 11524
Protoss_Citadel_of_Adun 1 12321
12795
