Protoss_Forge 1 4071
Protoss_Photon_Cannon 2 7731
Protoss_Nexus 1 8441
Protoss_Gateway 1 8756
Protoss_Assimilator 2 10919
Protoss_Cybernetics_Core 1 10466
Protoss_Zealot 1 10416
Protoss_Stargate 1 12300
Protoss_Dragoon 1 11934
12300
