Protoss_Forge 1 4792
Protoss_Nexus 1 7395
Protoss_Photon_Cannon 1 6218
Protoss_Gateway 1 7291
Protoss_Assimilator 2 9252
Protoss_Cybernetics_Core 1 9122
Protoss_Zealot 1 9541
Protoss_Stargate 1 10919
Protoss_Citadel_of_Adun 1 11949
Protoss_Corsair 1 11865
11949
