Protoss_Forge 1 4205
Protoss_Photon_Cannon 2 5725
Protoss_Nexus 1 8873
Protoss_Gateway 1 8095
Protoss_Assimilator 2 12143
Protoss_Cybernetics_Core 1 9576
Protoss_Zealot 3 11443
Protoss_Stargate 1 11473
Protoss_Citadel_of_Adun 1 11420
12143
