Protoss_Forge 1 4407
Protoss_Nexus 1 7527
Protoss_Photon_Cannon 1 6265
Protoss_Gateway 1 7277
Protoss_Assimilator 2 9389
Protoss_Cybernetics_Core 1 8812
Protoss_Zealot 2 11929
Protoss_Stargate 1 10601
Protoss_Dragoon 1 10476
Protoss_Citadel_of_Adun 1 11532
Protoss_Corsair 1 11686
11929
