Protoss_Forge 1 4021
Protoss_Photon_Cannon 1 6591
Protoss_Nexus 1 8381
Protoss_Gateway 1 7395
Protoss_Assimilator 2 11158
Protoss_Cybernetics_Core 1 9068
Protoss_Zealot 3 10492
Protoss_Stargate 1 10786
Protoss_Citadel_of_Adun 1 11379
Protoss_Corsair 1 12356
12356
