Protoss_Gateway 2 9984
Protoss_Assimilator 1 4155
Protoss_Zealot 2 6883
Protoss_Cybernetics_Core 1 6087
Protoss_Stargate 1 7895
Protoss_Dragoon 5 12443
Protoss_Corsair 2 11619
12443
