Protoss_Gateway 1 4111
Protoss_Assimilator 1 4445
Protoss_Cybernetics_Core 1 5944
Protoss_Zealot 2 7082
Protoss_Stargate 1 7723
Protoss_Citadel_of_Adun 1 8339
Protoss_Dragoon 2 9376
Protoss_Corsair 1 8871
Protoss_Templar_Archives 1 10313
Protoss_Nexus 1 13035
Protoss_Dark_Templar 1 11668
13035
