Protoss_Nexus 1 7102
Protoss_Gateway 1 6624
Protoss_Forge 1 6315
Protoss_Assimilator 2 9623
Protoss_Photon_Cannon 2 11445
Protoss_Cybernetics_Core 1 8794
Protoss_Zealot 2 11279
Protoss_Dragoon 1 10034
Protoss_Stargate 1 10765
Protoss_Citadel_of_Adun 1 11469
Protoss_Corsair 1 11888
11888
