Protoss_Forge 1 4796
Protoss_Gateway 1 6264
Protoss_Photon_Cannon 2 6499
Protoss_Assimilator 1 5986
Protoss_Cybernetics_Core 1 8251
Protoss_Stargate 1 10001
Protoss_Dragoon 1 9818
Protoss_Nexus 1 12464
Protoss_Corsair 2 11952
Protoss_Citadel_of_Adun 1 12118
12464
