Protoss_Forge 1 4832
Protoss_Nexus 1 7716
Protoss_Photon_Cannon 2 10921
Protoss_Gateway 1 7252
Protoss_Assimilator 2 9219
Protoss_Cybernetics_Core 1 8718
Protoss_Zealot 3 11244
Protoss_Stargate 1 10587
Protoss_Citadel_of_Adun 1 11424
Protoss_Corsair 1 11560
11560
