Protoss_Forge 1 4412
Protoss_Photon_Cannon 3 12361
Protoss_Nexus 1 8455
Protoss_Gateway 1 8461
Protoss_Assimilator 2 9617
Protoss_Cybernetics_Core 1 9904
Protoss_Stargate 1 11709
Protoss_Zealot 1 11399
Protoss_Robotics_Facility 1 12440
12440
