Protoss_Forge 1 4883
Protoss_Nexus 1 7562
Protoss_Gateway 2 11797
Protoss_Photon_Cannon 1 7031
Protoss_Assimilator 1 7098
Protoss_Cybernetics_Core 1 8370
Protoss_Zealot 5 12345
Protoss_Stargate 1 10071
Protoss_Citadel_of_Adun 1 10975
Protoss_Corsair 2 11947
12345
