Protoss_Forge 1 4804
Protoss_Nexus 1 7663
Protoss_Photon_Cannon 2 6768
Protoss_Gateway 1 7738
Protoss_Assimilator 2 9882
Protoss_Cybernetics_Core 1 9365
Protoss_Stargate 1 11096
Protoss_Citadel_of_Adun 1 11288
Protoss_Dragoon 1 11630
Protoss_Corsair 1 12242
12242
