Protoss_Gateway 2 4985
Protoss_Zealot 8 11604
Protoss_Nexus 1 10432
Protoss_Assimilator 1 9061
Protoss_Cybernetics_Core 1 10193
Protoss_Stargate 1 12051
Protoss_Dragoon 1 11808
12051
