Protoss_Forge 1 4302
Protoss_Photon_Cannon 2 5990
Protoss_Nexus 1 8721
Protoss_Gateway 3 12244
Protoss_Assimilator 2 9920
Protoss_Zealot 3 12160
Protoss_Cybernetics_Core 1 9314
Protoss_Citadel_of_Adun 1 10925
Protoss_Dragoon 1 10813
12244
