Protoss_Gateway 1 4149
Protoss_Assimilator 1 4193
Protoss_Cybernetics_Core 1 5780
Protoss_Zealot 7 11502
Protoss_Stargate 1 8087
Protoss_Corsair 3 10978
Protoss_Citadel_of_Adun 1 12529
12529
