Protoss_Forge 2 4761
Protoss_Photon_Cannon 3 8278
Protoss_Gateway 1 6681
Protoss_Zealot 1 7638
Protoss_Nexus 1 12188
Protoss_Assimilator 2 12222
Protoss_Cybernetics_Core 1 11566
12222
