Protoss_Nexus 1 6988
Protoss_Gateway 2 11816
Protoss_Assimilator 2 9122
Protoss_Zealot 6 12175
Protoss_Cybernetics_Core 1 8714
Protoss_Stargate 1 10402
Protoss_Citadel_of_Adun 1 10698
Protoss_Corsair 1 11432
12175
