Protoss_Forge 1 3835
Protoss_Photon_Cannon 3 11126
Protoss_Nexus 1 9169
Protoss_Gateway 1 8203
Protoss_Assimilator 2 12190
Protoss_Zealot 2 10255
Protoss_Cybernetics_Core 1 10139
Protoss_Stargate 1 12067
Protoss_Dragoon 1 11902
12190
