Protoss_Forge 1 4429
Protoss_Photon_Cannon 2 5896
Protoss_Nexus 1 8554
Protoss_Gateway 1 7524
Protoss_Assimilator 2 10480
Protoss_Cybernetics_Core 1 9102
Protoss_Zealot 4 12178
Protoss_Stargate 1 10926
Protoss_Corsair 1 11865
Protoss_Citadel_of_Adun 1 12639
12639
