Protoss_Forge 1 4158
Protoss_Photon_Cannon 2 7252
Protoss_Nexus 1 8241
Protoss_Gateway 1 7811
Protoss_Assimilator 2 10684
Protoss_Cybernetics_Core 1 9406
Protoss_Zealot 4 12315
Protoss_Stargate 1 11132
Protoss_Citadel_of_Adun 1 11704
Protoss_Corsair 1 12081
12315
