Protoss_Gateway 1 4158
Protoss_Zealot 4 12169
Protoss_Nexus 1 8408
Protoss_Assimilator 2 8970
Protoss_Cybernetics_Core 1 8373
Protoss_Stargate 1 10159
Protoss_Dragoon 1 10365
Protoss_Forge 1 10635
Protoss_Corsair 2 11993
Protoss_Citadel_of_Adun 1 12108
12169
