Protoss_Forge 1 4486
Protoss_Photon_Cannon 1 5807
Protoss_Nexus 1 8054
Protoss_Gateway 1 7073
Protoss_Assimilator 2 9456
Protoss_Cybernetics_Core 1 8516
Protoss_Zealot 4 11996
Protoss_Stargate 1 10467
Protoss_Corsair 1 11399
Protoss_Citadel_of_Adun 1 12119
12119
