Protoss_Gateway 1 3986
Protoss_Zealot 7 11268
Protoss_Nexus 1 8554
Protoss_Assimilator 2 11417
Protoss_Cybernetics_Core 1 9307
Protoss_Forge 1 9975
Protoss_Stargate 1 11169
Protoss_Citadel_of_Adun 1 12307
12307
