Protoss_Forge 1 4425
Protoss_Photon_Cannon 3 9036
Protoss_Nexus 1 9131
Protoss_Gateway 1 8414
Protoss_Assimilator 2 11519
Protoss_Cybernetics_Core 1 10070
Protoss_Zealot 3 11686
Protoss_Stargate 1 12041
12041
