Protoss_Forge 1 4166
Protoss_Photon_Cannon 2 7024
Protoss_Nexus 1 8216
Protoss_Gateway 1 8528
Protoss_Assimilator 2 11892
Protoss_Cybernetics_Core 1 9974
Protoss_Zealot 2 10676
Protoss_Stargate 1 11791
Protoss_Dragoon 1 11957
Protoss_Citadel_of_Adun 1 12766
12766
