Protoss_Forge 1 4612
Protoss_Nexus 1 7632
Protoss_Photon_Cannon 3 10696
Protoss_Gateway 1 7015
Protoss_Assimilator 1 7126
Protoss_Cybernetics_Core 1 8455
Protoss_Zealot 3 11818
Protoss_Stargate 1 10139
Protoss_Dragoon 1 10956
Protoss_Corsair 2 12210
12210
