Protoss_Forge 1 4488
Protoss_Photon_Cannon 2 6193
Protoss_Nexus 1 9207
Protoss_Gateway 1 8200
Protoss_Assimilator 2 10567
Protoss_Cybernetics_Core 1 9756
Protoss_Zealot 2 11575
Protoss_Stargate 1 11470
Protoss_Citadel_of_Adun 1 11717
11717
