Protoss_Forge 1 3792
Protoss_Photon_Cannon 3 8198
Protoss_Nexus 1 8815
Protoss_Gateway 1 7987
Protoss_Assimilator 2 10776
Protoss_Cybernetics_Core 1 9789
Protoss_Zealot 1 10062
Protoss_Stargate 1 11810
Protoss_Dragoon 1 11641
Protoss_Citadel_of_Adun 1 12522
12522
