Protoss_Gateway 2 4846
Protoss_Zealot 8 12321
Protoss_Assimilator 1 7079
Protoss_Cybernetics_Core 1 8320
Protoss_Stargate 1 10032
Protoss_Dragoon 1 10228
Protoss_Citadel_of_Adun 1 10874
Protoss_Corsair 1 11013
12321
