Protoss_Forge 1 4725
Protoss_Photon_Cannon 2 6130
Protoss_Nexus 1 8937
Protoss_Gateway 1 8266
Protoss_Assimilator 2 11407
Protoss_Cybernetics_Core 1 9809
Protoss_Zealot 3 11484
Protoss_Stargate 1 11895
Protoss_Citadel_of_Adun 1 12274
12274
