Protoss_Nexus 1 7369
Protoss_Forge 1 6122
Protoss_Gateway 4 12478
Protoss_Photon_Cannon 3 8732
Protoss_Zealot 4 12207
Protoss_Cybernetics_Core 1 10161
Protoss_Assimilator 2 10220
Protoss_Citadel_of_Adun 1 12068
12478
