Protoss_Gateway 1 4149
Protoss_Zealot 5 11162
Protoss_Assimilator 1 5468
Protoss_Cybernetics_Core 1 6570
Protoss_Stargate 1 8448
Protoss_Dragoon 1 8272
Protoss_Forge 1 8793
Protoss_Corsair 1 9386
Protoss_Photon_Cannon 1 10204
Protoss_Nexus 1 14097
14097
