Protoss_Forge 1 4081
Protoss_Nexus 1 7882
Protoss_Photon_Cannon 1 6249
Protoss_Gateway 4 12754
Protoss_Assimilator 1 7308
Protoss_Cybernetics_Core 1 9652
Protoss_Zealot 3 11446
Protoss_Citadel_of_Adun 1 11352
12754
