Protoss_Gateway 2 9671
Protoss_Assimilator 1 4464
Protoss_Zealot 5 10641
Protoss_Cybernetics_Core 1 7398
Protoss_Dragoon 1 8741
Protoss_Citadel_of_Adun 1 9293
Protoss_Templar_Archives 1 10747
Protoss_High_Templar 2 12124
12124
