Protoss_Gateway 1 4068
Protoss_Assimilator 1 4477
Protoss_Zealot 5 9971
Protoss_Cybernetics_Core 1 6658
Protoss_Stargate 1 8355
Protoss_Dragoon 1 8006
Protoss_Citadel_of_Adun 1 9172
Protoss_Corsair 1 9362
Protoss_Templar_Archives 1 10776
Protoss_Forge 1 11493
Protoss_Dark_Templar 1 12016
12016
