Protoss_Gateway 1 4255
Protoss_Assimilator 1 4479
Protoss_Zealot 3 7113
Protoss_Cybernetics_Core 1 7085
Protoss_Dragoon 4 12007
Protoss_Robotics_Facility 1 10050
Protoss_Shuttle 1 11455
Protoss_Robotics_Support_Bay 1 11393
12007
