Protoss_Forge 1 4833
Protoss_Nexus 1 7868
Protoss_Gateway 2 10128
Protoss_Assimilator 2 11894
Protoss_Photon_Cannon 2 10983
Protoss_Cybernetics_Core 1 9121
Protoss_Zealot 5 12351
Protoss_Dragoon 1 10327
Protoss_Citadel_of_Adun 1 10830
12351
