Protoss_Nexus 1 7334
Protoss_Gateway 1 6320
Protoss_Assimilator 2 9141
Protoss_Cybernetics_Core 1 7909
Protoss_Stargate 1 9700
Protoss_Robotics_Facility 1 11648
Protoss_Corsair 2 11732
Protoss_Forge 1 11164
11732
