Protoss_Forge 1 4432
Protoss_Photon_Cannon 3 7271
Protoss_Nexus 1 8535
Protoss_Gateway 1 8086
Protoss_Assimilator 2 11083
Protoss_Zealot 2 10823
Protoss_Cybernetics_Core 1 10698
Protoss_Dragoon 1 11957
Protoss_Stargate 1 12862
12862
