Protoss_Gateway 2 5101
Protoss_Zealot 6 8859
Protoss_Assimilator 1 6996
Protoss_Cybernetics_Core 1 8335
Protoss_Stargate 1 10066
Protoss_Forge 1 9951
Protoss_Citadel_of_Adun 1 10937
Protoss_Photon_Cannon 3 12231
Protoss_Corsair 2 12198
12231
