Protoss_Gateway 1 4269
Protoss_Zealot 8 12365
Protoss_Forge 1 7394
Protoss_Nexus 1 10354
Protoss_Assimilator 2 11499
Protoss_Photon_Cannon 2 12026
Protoss_Cybernetics_Core 1 10384
Protoss_Stargate 1 12872
12872
