Protoss_Forge 1 4748
Protoss_Nexus 1 7661
Protoss_Photon_Cannon 2 7012
Protoss_Gateway 1 7796
Protoss_Assimilator 2 10428
Protoss_Cybernetics_Core 1 9345
Protoss_Zealot 3 11688
Protoss_Stargate 1 11094
Protoss_Robotics_Facility 1 12920
Protoss_Corsair 1 12137
12920
