Protoss_Forge 1 4826
Protoss_Photon_Cannon 2 6193
Protoss_Nexus 1 8819
Protoss_Gateway 1 7735
Protoss_Assimilator 2 11127
Protoss_Cybernetics_Core 1 9387
Protoss_Zealot 2 11437
Protoss_Stargate 1 11539
Protoss_Citadel_of_Adun 1 12367
12367
