Protoss_Forge 1 4584
Protoss_Photon_Cannon 2 6945
Protoss_Nexus 1 8171
Protoss_Gateway 1 7916
Protoss_Assimilator 1 8247
Protoss_Cybernetics_Core 1 10306
Protoss_Zealot 1 10264
Protoss_Stargate 1 12054
Protoss_Dragoon 1 11659
12054
