Protoss_Forge 1 3892
Protoss_Nexus 1 7790
Protoss_Photon_Cannon 2 7816
Protoss_Gateway 2 11469
Protoss_Assimilator 2 11636
Protoss_Zealot 4 12146
Protoss_Cybernetics_Core 1 9690
Protoss_Citadel_of_Adun 1 11136
12146
