Protoss_Forge 1 4306
Protoss_Photon_Cannon 2 6156
Protoss_Nexus 1 9005
Protoss_Gateway 1 8162
Protoss_Assimilator 2 10119
Protoss_Cybernetics_Core 1 9608
Protoss_Zealot 2 10758
Protoss_Stargate 1 11342
Protoss_Citadel_of_Adun 1 11949
11949
