Protoss_Forge 1 4319
Protoss_Nexus 1 7694
Protoss_Photon_Cannon 2 7705
Protoss_Gateway 1 7410
Protoss_Assimilator 1 7930
Protoss_Zealot 3 11528
Protoss_Cybernetics_Core 1 9602
Protoss_Stargate 1 11703
11703
