Protoss_Forge 1 4644
Protoss_Photon_Cannon 1 6031
Protoss_Nexus 1 9052
Protoss_Gateway 3 12637
Protoss_Assimilator 2 10875
Protoss_Zealot 4 12023
Protoss_Cybernetics_Core 1 9754
Protoss_Citadel_of_Adun 1 11238
12637
