Protoss_Gateway 1 4280
Protoss_Zealot 7 11505
Protoss_Nexus 1 8902
Protoss_Forge 1 7668
Protoss_Assimilator 1 9213
Protoss_Photon_Cannon 3 12522
Protoss_Cybernetics_Core 1 12450
12522
