Protoss_Gateway 1 4135
Protoss_Zealot 4 10248
Protoss_Assimilator 1 5341
Protoss_Cybernetics_Core 1 6662
Protoss_Stargate 1 8380
Protoss_Dragoon 1 8147
Protoss_Forge 1 8800
Protoss_Corsair 1 9315
Protoss_Photon_Cannon 2 11802
Protoss_Nexus 1 14089
14089
