Protoss_Nexus 1 7217
Protoss_Forge 1 5753
Protoss_Gateway 3 12664
Protoss_Photon_Cannon 2 7722
Protoss_Assimilator 2 10208
Protoss_Zealot 3 11408
Protoss_Cybernetics_Core 1 9652
Protoss_Stargate 1 11443
Protoss_Citadel_of_Adun 1 11750
12664
