Protoss_Gateway 2 4725
Protoss_Zealot 9 10685
Protoss_Nexus 1 10751
Protoss_Assimilator 1 8973
Protoss_Cybernetics_Core 1 10428
Protoss_Stargate 1 12741
Protoss_Citadel_of_Adun 1 12680
12741
