Protoss_Forge 1 4293
Protoss_Photon_Cannon 3 8287
Protoss_Nexus 1 8111
Protoss_Gateway 1 7104
Protoss_Assimilator 2 10814
Protoss_Zealot 4 12195
Protoss_Cybernetics_Core 1 9454
Protoss_Stargate 1 11188
Protoss_Citadel_of_Adun 1 11979
12195
