Protoss_Forge 1 4075
Protoss_Photon_Cannon 2 6145
Protoss_Nexus 1 8838
Protoss_Gateway 1 7826
Protoss_Assimilator 2 10486
Protoss_Cybernetics_Core 1 9308
Protoss_Zealot 3 11712
Protoss_Stargate 1 11065
Protoss_Citadel_of_Adun 1 11809
Protoss_Corsair 1 12014
12014
