Protoss_Forge 1 5110
Protoss_Photon_Cannon 2 6647
Protoss_Nexus 1 8864
Protoss_Gateway 2 12453
Protoss_Assimilator 2 10672
Protoss_Cybernetics_Core 1 9781
Protoss_Zealot 3 11508
Protoss_Stargate 1 11671
Protoss_Citadel_of_Adun 1 11790
12453
