Protoss_Gateway 2 4474
Protoss_Zealot 12 11429
Protoss_Assimilator 1 6386
Protoss_Cybernetics_Core 1 9624
Protoss_Stargate 1 11384
Protoss_Citadel_of_Adun 1 12459
Protoss_Corsair 1 12351
12459
