Protoss_Forge 1 4243
Protoss_Nexus 1 7617
Protoss_Photon_Cannon 2 8082
Protoss_Gateway 1 7253
Protoss_Assimilator 2 10760
Protoss_Zealot 2 11288
Protoss_Cybernetics_Core 1 10420
Protoss_Robotics_Facility 1 12452
Protoss_Stargate 1 12370
12452
