Protoss_Forge 1 4593
Protoss_Nexus 1 7421
Protoss_Photon_Cannon 3 10441
Protoss_Gateway 1 7739
Protoss_Assimilator 3 11133
Protoss_Cybernetics_Core 1 9296
Protoss_Stargate 1 10996
Protoss_Zealot 2 11677
Protoss_Corsair 1 11935
11935
