Protoss_Forge 1 4780
Protoss_Photon_Cannon 2 6099
Protoss_Nexus 1 9049
Protoss_Gateway 2 12634
Protoss_Assimilator 2 10704
Protoss_Zealot 2 9974
Protoss_Cybernetics_Core 1 9877
Protoss_Stargate 1 11607
Protoss_Dragoon 1 11272
Protoss_Citadel_of_Adun 1 12428
12634
