Protoss_Forge 1 4792
Protoss_Photon_Cannon 2 6244
Protoss_Nexus 1 8826
Protoss_Gateway 1 7966
Protoss_Assimilator 1 7741
Protoss_Cybernetics_Core 1 9509
Protoss_Zealot 3 12236
Protoss_Stargate 1 11274
Protoss_Dragoon 1 11375
Protoss_Citadel_of_Adun 1 12296
12296
