Protoss_Forge 1 4739
Protoss_Nexus 1 7593
Protoss_Photon_Cannon 4 11182
Protoss_Gateway 1 7534
Protoss_Assimilator 2 11082
Protoss_Zealot 3 11812
Protoss_Cybernetics_Core 1 10171
Protoss_Stargate 1 11904
Protoss_Citadel_of_Adun 1 12593
12593
