Protoss_Forge 1 4262
Protoss_Nexus 1 7773
Protoss_Photon_Cannon 1 6554
Protoss_Gateway 3 12541
Protoss_Assimilator 2 10878
Protoss_Cybernetics_Core 1 8879
Protoss_Stargate 1 10619
Protoss_Zealot 2 10946
Protoss_Citadel_of_Adun 1 10987
Protoss_Corsair 1 11563
12541
