Protoss_Forge 1 4062
Protoss_Nexus 1 7720
Protoss_Photon_Cannon 1 6399
Protoss_Gateway 1 7066
Protoss_Assimilator 1 6962
Protoss_Zealot 2 10542
Protoss_Cybernetics_Core 1 10032
Protoss_Stargate 1 11867
Protoss_Dragoon 1 11673
Protoss_Citadel_of_Adun 1 12273
12273
