Protoss_Forge 1 4934
Protoss_Nexus 1 7612
Protoss_Photon_Cannon 1 6355
Protoss_Gateway 2 12825
Protoss_Zealot 3 12356
Protoss_Assimilator 2 10931
Protoss_Cybernetics_Core 2 10717
Protoss_Stargate 1 11889
Protoss_Citadel_of_Adun 1 12762
12825
