Protoss_Forge 1 3713
Protoss_Nexus 1 7465
Protoss_Photon_Cannon 2 11246
Protoss_Gateway 2 12826
Protoss_Assimilator 2 9920
Protoss_Zealot 2 10779
Protoss_Cybernetics_Core 1 9289
Protoss_Stargate 1 11138
Protoss_Citadel_of_Adun 1 11712
Protoss_Corsair 1 12078
12826
