Protoss_Forge 1 3760
Protoss_Nexus 1 7904
Protoss_Photon_Cannon 2 7435
Protoss_Gateway 1 7085
Protoss_Assimilator 2 11323
Protoss_Cybernetics_Core 1 9075
Protoss_Zealot 2 11464
Protoss_Dragoon 1 10365
Protoss_Stargate 1 10853
Protoss_Citadel_of_Adun 1 11098
Protoss_Corsair 1 11797
11797
