Protoss_Forge 1 3907
Protoss_Nexus 1 7900
Protoss_Gateway 2 12596
Protoss_Assimilator 2 11452
Protoss_Photon_Cannon 1 7798
Protoss_Cybernetics_Core 1 9108
Protoss_Zealot 3 11699
Protoss_Stargate 1 10806
Protoss_Corsair 1 11821
Protoss_Citadel_of_Adun 1 12476
12596
