Protoss_Forge 1 4261
Protoss_Photon_Cannon 2 5834
Protoss_Nexus 1 8721
Protoss_Gateway 1 8243
Protoss_Assimilator 2 11377
Protoss_Cybernetics_Core 1 9974
Protoss_Zealot 3 11522
Protoss_Stargate 1 11886
Protoss_Citadel_of_Adun 1 12298
12298
