Protoss_Forge 1 5095
Protoss_Photon_Cannon 2 6389
Protoss_Nexus 1 8987
Protoss_Gateway 1 8169
Protoss_Assimilator 2 10160
Protoss_Cybernetics_Core 1 9642
Protoss_Zealot 3 12108
Protoss_Stargate 1 11435
Protoss_Citadel_of_Adun 1 12116
12116
