Protoss_Forge 1 4539
Protoss_Photon_Cannon 2 5997
Protoss_Nexus 1 8496
Protoss_Gateway 1 7869
Protoss_Assimilator 1 7881
Protoss_Cybernetics_Core 1 9365
Protoss_Zealot 4 11945
Protoss_Stargate 1 11194
Protoss_Citadel_of_Adun 1 12263
Protoss_Corsair 1 12254
12263
