Protoss_Forge 1 4044
Protoss_Nexus 1 7468
Protoss_Photon_Cannon 1 6311
Protoss_Gateway 1 7423
Protoss_Assimilator 2 12273
Protoss_Zealot 4 12143
Protoss_Cybernetics_Core 1 9511
Protoss_Stargate 1 11287
Protoss_Citadel_of_Adun 1 11973
Protoss_Corsair 1 12280
12280
