Protoss_Forge 1 4754
Protoss_Nexus 1 7691
Protoss_Photon_Cannon 2 6952
Protoss_Gateway 2 12813
Protoss_Assimilator 2 10609
Protoss_Cybernetics_Core 1 9331
Protoss_Zealot 3 11780
Protoss_Stargate 1 11078
Protoss_Citadel_of_Adun 1 12175
Protoss_Corsair 1 12052
12813
