Protoss_Forge 1 4956
Protoss_Nexus 1 7433
Protoss_Gateway 4 11898
Protoss_Assimilator 2 11631
Protoss_Photon_Cannon 1 7525
Protoss_Cybernetics_Core 1 8297
Protoss_Zealot 3 12111
Protoss_Citadel_of_Adun 1 11071
12111
