Protoss_Forge 1 4529
Protoss_Photon_Cannon 3 7055
Protoss_Nexus 1 9953
Protoss_Gateway 1 8993
Protoss_Assimilator 2 11906
Protoss_Cybernetics_Core 1 10511
Protoss_Zealot 3 12029
Protoss_Stargate 1 12237
Protoss_Citadel_of_Adun 1 12715
12715
