Protoss_Forge 1 4562
Protoss_Photon_Cannon 1 6178
Protoss_Nexus 1 8443
Protoss_Gateway 1 7697
Protoss_Assimilator 2 10613
Protoss_Zealot 3 11543
Protoss_Cybernetics_Core 1 10226
Protoss_Citadel_of_Adun 1 11969
11969
