Protoss_Forge 1 4650
Protoss_Nexus 1 7483
Protoss_Photon_Cannon 1 6329
Protoss_Gateway 1 7073
Protoss_Assimilator 2 9809
Protoss_Cybernetics_Core 1 8519
Protoss_Zealot 4 11868
Protoss_Stargate 1 10227
Protoss_Citadel_of_Adun 1 10861
Protoss_Corsair 1 11300
Protoss_Templar_Archives 1 12446
12446
