Protoss_Gateway 2 11098
Protoss_Assimilator 1 4769
Protoss_Zealot 3 7132
Protoss_Cybernetics_Core 1 7174
Protoss_Dragoon 3 11161
Protoss_Stargate 1 9416
Protoss_Corsair 2 11262
11262
