Protoss_Nexus 1 7284
Protoss_Forge 1 5835
Protoss_Photon_Cannon 3 12598
Protoss_Gateway 1 8259
Protoss_Assimilator 2 11904
Protoss_Cybernetics_Core 1 9838
Protoss_Zealot 2 11306
Protoss_Stargate 1 11936
Protoss_Citadel_of_Adun 1 12235
12598
