Protoss_Forge 1 4865
Protoss_Nexus 1 7448
Protoss_Photon_Cannon 2 11230
Protoss_Gateway 1 7038
Protoss_Assimilator 2 9790
Protoss_Cybernetics_Core 1 8496
Protoss_Zealot 3 11566
Protoss_Stargate 1 10188
Protoss_Corsair 2 12128
12128
