Protoss_Forge 1 4060
Protoss_Photon_Cannon 3 8976
Protoss_Nexus 1 8436
Protoss_Gateway 1 7395
Protoss_Assimilator 2 10820
Protoss_Cybernetics_Core 1 8851
Protoss_Zealot 3 11490
Protoss_Stargate 1 10718
Protoss_Citadel_of_Adun 1 11746
Protoss_Corsair 1 11762
11762
