Protoss_Forge 1 3731
Protoss_Photon_Cannon 2 5684
Protoss_Nexus 1 8554
Protoss_Gateway 3 12432
Protoss_Assimilator 1 7843
Protoss_Zealot 4 11341
Protoss_Cybernetics_Core 1 9312
Protoss_Stargate 1 11055
Protoss_Citadel_of_Adun 1 11396
Protoss_Corsair 1 12034
12432
