Protoss_Forge 1 4524
Protoss_Nexus 1 7773
Protoss_Photon_Cannon 1 6537
Protoss_Gateway 2 12409
Protoss_Assimilator 2 11480
Protoss_Cybernetics_Core 1 8774
Protoss_Zealot 3 12336
Protoss_Stargate 1 10569
Protoss_Dragoon 1 10523
Protoss_Citadel_of_Adun 1 11174
Protoss_Corsair 1 11563
12409
