Protoss_Gateway 2 11107
Protoss_Assimilator 1 4315
Protoss_Zealot 4 11019
Protoss_Cybernetics_Core 1 6634
Protoss_Stargate 1 8396
Protoss_Citadel_of_Adun 1 9131
Protoss_Corsair 1 9825
Protoss_Dragoon 1 10157
Protoss_Templar_Archives 1 12209
12209
