Protoss_Forge 1 4750
Protoss_Nexus 1 7661
Protoss_Photon_Cannon 2 6752
Protoss_Gateway 1 7562
Protoss_Assimilator 2 11595
Protoss_Zealot 4 12058
Protoss_Cybernetics_Core 1 10183
Protoss_Stargate 1 11876
Protoss_Citadel_of_Adun 1 12832
12832
