Protoss_Forge 1 3986
Protoss_Photon_Cannon 3 8431
Protoss_Nexus 1 9098
Protoss_Gateway 1 8139
Protoss_Assimilator 2 11459
Protoss_Zealot 2 11189
Protoss_Cybernetics_Core 1 9983
Protoss_Stargate 1 11776
11776
