Protoss_Forge 1 4899
Protoss_Nexus 1 7638
Protoss_Photon_Cannon 2 6873
Protoss_Gateway 3 12648
Protoss_Assimilator 1 8028
Protoss_Cybernetics_Core 1 9640
Protoss_Zealot 4 12222
Protoss_Stargate 1 11349
Protoss_Citadel_of_Adun 1 11756
Protoss_Corsair 1 12298
12648
