Protoss_Forge 1 4289
Protoss_Photon_Cannon 2 6044
Protoss_Nexus 1 9043
Protoss_Gateway 1 8019
Protoss_Assimilator 2 11546
Protoss_Cybernetics_Core 1 9476
Protoss_Zealot 4 12154
Protoss_Stargate 1 11475
Protoss_Citadel_of_Adun 1 12544
12544
