Protoss_Forge 1 4343
Protoss_Nexus 1 7664
Protoss_Photon_Cannon 2 6800
Protoss_Assimilator 2 11232
Protoss_Gateway 1 8429
Protoss_Cybernetics_Core 1 10073
Protoss_Zealot 3 11610
Protoss_Stargate 1 11826
Protoss_Citadel_of_Adun 1 12677
12677
