Protoss_Forge 1 4234
Protoss_Photon_Cannon 2 5804
Protoss_Nexus 1 8695
Protoss_Assimilator 3 11114
Protoss_Gateway 1 8051
Protoss_Cybernetics_Core 1 9648
Protoss_Zealot 3 11748
Protoss_Citadel_of_Adun 1 11194
Protoss_Templar_Archives 1 12741
12741
