Protoss_Forge 1 4316
Protoss_Photon_Cannon 2 5720
Protoss_Nexus 1 8531
Protoss_Gateway 1 7890
Protoss_Assimilator 2 10239
Protoss_Cybernetics_Core 1 9353
Protoss_Zealot 2 10776
Protoss_Stargate 1 11157
Protoss_Citadel_of_Adun 1 11907
Protoss_Dragoon 1 12069
Protoss_Corsair 1 12099
12099
