Protoss_Gateway 2 4960
Protoss_Zealot 5 9090
Protoss_Nexus 1 9407
Protoss_Assimilator 1 7668
Protoss_Cybernetics_Core 1 9055
Protoss_Stargate 1 11040
Protoss_Dragoon 1 10910
Protoss_Corsair 1 11996
11996
