Protoss_Forge 1 4082
Protoss_Photon_Cannon 4 9628
Protoss_Nexus 1 8604
Protoss_Gateway 1 7685
Protoss_Assimilator 2 11437
Protoss_Zealot 3 10911
Protoss_Cybernetics_Core 2 11153
Protoss_Dragoon 1 12431
12431
