Protoss_Forge 1 4135
Protoss_Nexus 1 7695
Protoss_Photon_Cannon 1 6437
Protoss_Gateway 1 7590
Protoss_Assimilator 2 11342
Protoss_Zealot 3 11882
Protoss_Cybernetics_Core 1 9788
Protoss_Dragoon 1 10983
Protoss_Stargate 1 11527
Protoss_Citadel_of_Adun 1 12551
12551
