Protoss_Forge 1 5402
Protoss_Photon_Cannon 2 6693
Protoss_Nexus 1 8727
Protoss_Gateway 2 10328
Protoss_Assimilator 1 7902
Protoss_Cybernetics_Core 1 9845
Protoss_Zealot 5 12166
Protoss_Citadel_of_Adun 1 11423
12166
