Protoss_Nexus 1 7388
Protoss_Forge 1 5767
Protoss_Gateway 1 7218
Protoss_Photon_Cannon 2 7740
Protoss_Assimilator 2 10145
Protoss_Zealot 2 9345
Protoss_Cybernetics_Core 1 9948
Protoss_Dragoon 1 11591
Protoss_Stargate 1 12239
Protoss_Robotics_Facility 1 12935
12935
