Protoss_Forge 1 4836
Protoss_Photon_Cannon 3 9456
Protoss_Nexus 1 9161
Protoss_Gateway 1 8661
Protoss_Assimilator 2 10306
Protoss_Zealot 1 9722
Protoss_Cybernetics_Core 1 10331
Protoss_Stargate 2 12880
12880
