Protoss_Gateway 1 4223
Protoss_Assimilator 1 4230
Protoss_Cybernetics_Core 1 5868
Protoss_Zealot 4 10144
Protoss_Dragoon 1 7067
Protoss_Stargate 1 7733
Protoss_Corsair 2 11016
Protoss_Robotics_Facility 1 11445
Protoss_Forge 1 12075
12075
