Protoss_Forge 1 4255
Protoss_Photon_Cannon 2 6314
Protoss_Nexus 1 8917
Protoss_Gateway 1 7954
Protoss_Assimilator 2 9905
Protoss_Cybernetics_Core 1 9523
Protoss_Zealot 2 11888
Protoss_Stargate 1 11380
Protoss_Dragoon 1 11027
Protoss_Citadel_of_Adun 1 12160
Protoss_Corsair 1 12318
12318
