Protoss_Forge 1 5105
Protoss_Nexus 1 7664
Protoss_Photon_Cannon 2 7450
Protoss_Gateway 3 12778
Protoss_Assimilator 2 8898
Protoss_Zealot 4 11625
Protoss_Cybernetics_Core 1 10261
Protoss_Citadel_of_Adun 1 11712
12778
