Protoss_Forge 1 4536
Protoss_Nexus 1 7740
Protoss_Photon_Cannon 1 6395
Protoss_Gateway 2 11671
Protoss_Assimilator 1 7675
Protoss_Cybernetics_Core 1 9327
Protoss_Zealot 4 11967
Protoss_Stargate 1 11219
Protoss_Citadel_of_Adun 1 12156
Protoss_Corsair 1 12351
12351
