Protoss_Gateway 2 11225
Protoss_Assimilator 1 4592
Protoss_Zealot 4 11642
Protoss_Cybernetics_Core 1 7147
Protoss_Stargate 1 8879
Protoss_Dragoon 4 11565
Protoss_Corsair 4 12216
12216
