Protoss_Forge 1 4602
Protoss_Photon_Cannon 3 12364
Protoss_Nexus 1 8752
Protoss_Gateway 1 7814
Protoss_Assimilator 1 8437
Protoss_Cybernetics_Core 1 9588
Protoss_Zealot 3 11704
Protoss_Stargate 1 11456
12364
