Protoss_Nexus 1 6991
Protoss_Forge 1 5957
Protoss_Gateway 1 7706
Protoss_Photon_Cannon 2 9736
Protoss_Assimilator 2 9209
Protoss_Zealot 3 11976
Protoss_Cybernetics_Core 1 9624
Protoss_Stargate 2 12903
Protoss_Robotics_Facility 1 12456
12903
