Protoss_Forge 1 4008
Protoss_Photon_Cannon 1 5368
Protoss_Nexus 1 8138
Protoss_Gateway 1 7392
Protoss_Assimilator 2 11120
Protoss_Zealot 4 11832
Protoss_Cybernetics_Core 1 9361
Protoss_Stargate 1 11084
Protoss_Citadel_of_Adun 1 11518
Protoss_Corsair 1 12166
12166
