Protoss_Forge 1 4267
Protoss_Nexus 1 7808
Protoss_Gateway 3 12037
Protoss_Photon_Cannon 1 7686
Protoss_Assimilator 2 8493
Protoss_Cybernetics_Core 1 9419
Protoss_Stargate 1 11096
Protoss_Citadel_of_Adun 1 11429
Protoss_Corsair 1 12072
12072
