Protoss_Forge 1 4875
Protoss_Photon_Cannon 2 6253
Protoss_Nexus 1 8762
Protoss_Gateway 1 8450
Protoss_Assimilator 2 10071
Protoss_Cybernetics_Core 1 10098
Protoss_Zealot 3 12137
Protoss_Stargate 1 11952
Protoss_Citadel_of_Adun 1 12286
12286
