Protoss_Forge 1 4384
Protoss_Photon_Cannon 2 5928
Protoss_Nexus 1 8630
Protoss_Gateway 1 7764
Protoss_Assimilator 2 10536
Protoss_Cybernetics_Core 1 9245
Protoss_Zealot 3 10984
Protoss_Stargate 1 10966
Protoss_Citadel_of_Adun 1 11903
Protoss_Corsair 1 11952
11952
