Protoss_Forge 1 4447
Protoss_Photon_Cannon 1 5735
Protoss_Nexus 1 8402
Protoss_Gateway 1 7400
Protoss_Assimilator 1 7714
Protoss_Zealot 2 9702
Protoss_Cybernetics_Core 1 11604
11604
