Protoss_Forge 1 4679
Protoss_Photon_Cannon 2 6057
Protoss_Nexus 1 8750
Protoss_Gateway 2 12708
Protoss_Assimilator 2 10030
Protoss_Zealot 3 12131
Protoss_Cybernetics_Core 1 9371
Protoss_Stargate 1 11315
Protoss_Dragoon 1 11193
Protoss_Corsair 1 12310
Protoss_Citadel_of_Adun 1 12817
12817
