Protoss_Forge 1 4252
Protoss_Photon_Cannon 1 5498
Protoss_Nexus 1 8092
Protoss_Gateway 2 12393
Protoss_Assimilator 2 10144
Protoss_Zealot 4 11736
Protoss_Cybernetics_Core 1 9424
Protoss_Citadel_of_Adun 1 11139
12393
