Protoss_Forge 1 4774
Protoss_Nexus 1 7761
Protoss_Photon_Cannon 2 12108
Protoss_Gateway 1 7167
Protoss_Assimilator 2 11314
Protoss_Zealot 3 11982
Protoss_Cybernetics_Core 1 9708
Protoss_Stargate 1 12372
12372
