Protoss_Forge 1 4277
Protoss_Photon_Cannon 2 6200
Protoss_Nexus 1 8838
Protoss_Gateway 1 7779
Protoss_Assimilator 2 10502
Protoss_Cybernetics_Core 1 9274
Protoss_Zealot 3 12239
Protoss_Stargate 1 11315
Protoss_Dragoon 1 11267
Protoss_Citadel_of_Adun 1 12557
Protoss_Corsair 1 12292
12557
