Protoss_Gateway 2 4739
Protoss_Zealot 5 7849
Protoss_Forge 1 8117
Protoss_Nexus 1 10942
Protoss_Assimilator 1 9765
Protoss_Photon_Cannon 2 11122
Protoss_Cybernetics_Core 1 11881
11881
