Protoss_Forge 1 4103
Protoss_Photon_Cannon 2 6230
Protoss_Nexus 1 9562
Protoss_Gateway 1 8677
Protoss_Assimilator 2 11568
Protoss_Cybernetics_Core 1 10458
Protoss_Zealot 2 10884
Protoss_Stargate 1 12196
Protoss_Dragoon 1 12004
12196
