Protoss_Forge 1 4328
Protoss_Photon_Cannon 2 6159
Protoss_Nexus 1 8894
Protoss_Gateway 1 7925
Protoss_Assimilator 2 10659
Protoss_Cybernetics_Core 1 9421
Protoss_Zealot 2 10161
Protoss_Stargate 1 11274
Protoss_Citadel_of_Adun 1 11802
11802
