Protoss_Forge 1 4946
Protoss_Nexus 1 7702
Protoss_Photon_Cannon 2 6950
Protoss_Gateway 1 8733
Protoss_Assimilator 1 9023
Protoss_Cybernetics_Core 1 10287
Protoss_Zealot 2 12251
Protoss_Citadel_of_Adun 1 12326
12326
