Protoss_Forge 1 4752
Protoss_Nexus 1 7574
Protoss_Photon_Cannon 2 6751
Protoss_Gateway 1 7817
Protoss_Assimilator 2 10688
Protoss_Cybernetics_Core 1 9282
Protoss_Zealot 4 12200
Protoss_Stargate 1 11137
Protoss_Corsair 1 12266
12266
