Protoss_Forge 1 3794
Protoss_Photon_Cannon 2 6086
Protoss_Nexus 1 9120
Protoss_Gateway 1 7906
Protoss_Assimilator 1 8377
Protoss_Zealot 2 12154
Protoss_Cybernetics_Core 1 12308
12308
