Protoss_Forge 1 4420
Protoss_Photon_Cannon 2 6172
Protoss_Nexus 1 8964
Protoss_Gateway 1 7975
Protoss_Assimilator 2 10949
Protoss_Cybernetics_Core 1 9447
Protoss_Zealot 4 12257
Protoss_Stargate 1 11201
Protoss_Corsair 1 12166
12257
