Protoss_Forge 1 4237
Protoss_Photon_Cannon 2 6011
Protoss_Nexus 1 8798
Protoss_Gateway 1 7960
Protoss_Assimilator 2 11970
Protoss_Cybernetics_Core 1 9468
Protoss_Zealot 3 11294
Protoss_Stargate 1 11386
Protoss_Citadel_of_Adun 1 12233
Protoss_Dragoon 1 12508
12508
