Protoss_Forge 1 4416
Protoss_Nexus 1 7603
Protoss_Photon_Cannon 2 6789
Protoss_Gateway 1 8000
Protoss_Assimilator 2 10791
Protoss_Cybernetics_Core 1 9877
Protoss_Zealot 1 9693
Protoss_Dragoon 1 11322
Protoss_Stargate 1 11800
Protoss_Citadel_of_Adun 1 12421
12421
