Protoss_Forge 1 4289
Protoss_Photon_Cannon 2 6191
Protoss_Nexus 1 9142
Protoss_Gateway 1 8095
Protoss_Assimilator 2 10267
Protoss_Cybernetics_Core 1 9561
Protoss_Zealot 3 11461
Protoss_Stargate 1 11245
Protoss_Corsair 1 12190
12190
