Protoss_Forge 1 4391
Protoss_Nexus 1 7617
Protoss_Photon_Cannon 1 6370
Protoss_Gateway 4 12555
Protoss_Assimilator 2 9149
Protoss_Cybernetics_Core 1 8709
Protoss_Zealot 2 10322
Protoss_Stargate 1 10611
Protoss_Citadel_of_Adun 1 11186
Protoss_Corsair 1 11587
12555
