Protoss_Forge 1 4267
Protoss_Nexus 1 7565
Protoss_Photon_Cannon 2 10772
Protoss_Gateway 1 7343
Protoss_Assimilator 2 12075
Protoss_Zealot 2 11748
Protoss_Cybernetics_Core 1 9204
Protoss_Dragoon 1 10523
Protoss_Stargate 1 11936
Protoss_Citadel_of_Adun 1 12795
12795
