Protoss_Gateway 2 12049
Protoss_Forge 1 4874
Protoss_Zealot 7 12228
Protoss_Photon_Cannon 1 6271
Protoss_Nexus 1 9457
Protoss_Assimilator 1 8004
Protoss_Cybernetics_Core 1 9721
Protoss_Citadel_of_Adun 1 12558
12558
