Protoss_Forge 1 4066
Protoss_Photon_Cannon 2 5870
Protoss_Nexus 1 8844
Protoss_Gateway 1 7902
Protoss_Assimilator 2 11531
Protoss_Zealot 2 9989
Protoss_Cybernetics_Core 1 9803
Protoss_Stargate 1 11889
Protoss_Dragoon 1 11823
Protoss_Citadel_of_Adun 1 12721
12721
