Protoss_Forge 1 3975
Protoss_Nexus 1 7585
Protoss_Gateway 1 6860
Protoss_Photon_Cannon 3 12335
Protoss_Assimilator 2 11347
Protoss_Zealot 2 9330
Protoss_Cybernetics_Core 1 9049
Protoss_Stargate 1 10910
Protoss_Dragoon 1 11226
12335
