Protoss_Forge 1 4521
Protoss_Nexus 1 8089
Protoss_Photon_Cannon 2 7466
Protoss_Gateway 1 8484
Protoss_Assimilator 2 11802
Protoss_Cybernetics_Core 1 10008
Protoss_Zealot 2 10448
Protoss_Citadel_of_Adun 1 11781
Protoss_Dragoon 1 11685
11802
