Protoss_Forge 1 4179
Protoss_Nexus 1 7944
Protoss_Photon_Cannon 2 7004
Protoss_Gateway 1 7940
Protoss_Assimilator 2 10319
Protoss_Cybernetics_Core 1 9585
Protoss_Zealot 2 12244
Protoss_Stargate 1 11444
Protoss_Dragoon 1 11296
Protoss_Citadel_of_Adun 1 12324
12324
