Protoss_Nexus 1 7042
Protoss_Gateway 1 6580
Protoss_Forge 1 6424
Protoss_Assimilator 2 10376
Protoss_Photon_Cannon 1 7775
Protoss_Cybernetics_Core 1 8654
Protoss_Zealot 2 11382
Protoss_Stargate 1 10686
Protoss_Dragoon 1 10233
Protoss_Citadel_of_Adun 1 11379
Protoss_Corsair 1 11628
11628
