Protoss_Nexus 1 7070
Protoss_Forge 1 5666
Protoss_Gateway 1 6588
Protoss_Photon_Cannon 3 11675
Protoss_Assimilator 1 7496
Protoss_Cybernetics_Core 1 8546
Protoss_Zealot 2 10255
Protoss_Stargate 1 11339
11675
