Protoss_Forge 1 4308
Protoss_Photon_Cannon 2 5673
Protoss_Nexus 1 8693
Protoss_Gateway 1 7662
Protoss_Assimilator 2 11925
Protoss_Cybernetics_Core 1 9201
Protoss_Zealot 3 11821
Protoss_Stargate 1 10993
Protoss_Dragoon 1 10895
Protoss_Citadel_of_Adun 1 11821
Protoss_Corsair 1 12131
12131
