Protoss_Gateway 1 4101
Protoss_Assimilator 1 4128
Protoss_Cybernetics_Core 1 5543
Protoss_Zealot 4 11443
Protoss_Dragoon 2 7921
Protoss_Stargate 1 7505
Protoss_Corsair 3 10605
Protoss_Forge 1 10022
Protoss_Nexus 1 14184
14184
