Protoss_Forge 1 4354
Protoss_Nexus 1 7637
Protoss_Photon_Cannon 2 6806
Protoss_Gateway 1 7618
Protoss_Assimilator 2 10098
Protoss_Cybernetics_Core 1 9339
Protoss_Zealot 3 11948
Protoss_Stargate 1 11087
Protoss_Citadel_of_Adun 1 11461
Protoss_Corsair 1 12040
12040
