Protoss_Forge 1 4376
Protoss_Photon_Cannon 1 5688
Protoss_Nexus 1 8490
Protoss_Gateway 1 7533
Protoss_Assimilator 2 10000
Protoss_Cybernetics_Core 1 9020
Protoss_Zealot 2 11212
Protoss_Stargate 1 11113
Protoss_Citadel_of_Adun 1 11755
Protoss_Corsair 1 12119
12119
