Protoss_Forge 1 4322
Protoss_Nexus 1 7413
Protoss_Gateway 2 12178
Protoss_Photon_Cannon 1 6894
Protoss_Assimilator 2 10229
Protoss_Cybernetics_Core 1 8589
Protoss_Zealot 2 9880
Protoss_Stargate 1 10288
Protoss_Citadel_of_Adun 1 11212
Protoss_Corsair 2 12108
Protoss_Templar_Archives 1 12797
12797
