Protoss_Forge 1 4631
Protoss_Photon_Cannon 2 6000
Protoss_Nexus 1 8422
Protoss_Gateway 1 7632
Protoss_Assimilator 2 12312
Protoss_Cybernetics_Core 1 9489
Protoss_Dragoon 1 10681
Protoss_Stargate 1 11467
Protoss_Citadel_of_Adun 1 11677
Protoss_Zealot 1 11683
12312
