Protoss_Gateway 2 4867
Protoss_Zealot 11 10270
Protoss_Nexus 1 11187
Protoss_Assimilator 1 10665
Protoss_Forge 1 10789
Protoss_Cybernetics_Core 1 12476
Protoss_Photon_Cannon 1 12538
12538
