Protoss_Forge 1 4748
Protoss_Photon_Cannon 3 10036
Protoss_Nexus 1 8469
Protoss_Gateway 1 7198
Protoss_Assimilator 2 10650
Protoss_Zealot 5 11822
Protoss_Cybernetics_Core 1 8800
Protoss_Stargate 1 10651
Protoss_Citadel_of_Adun 1 11768
Protoss_Corsair 1 11894
11894
