Protoss_Forge 1 3831
Protoss_Nexus 1 7389
Protoss_Photon_Cannon 2 6636
Protoss_Gateway 2 12102
Protoss_Assimilator 2 10932
Protoss_Cybernetics_Core 1 9270
Protoss_Zealot 3 12245
Protoss_Stargate 1 11286
Protoss_Citadel_of_Adun 1 12312
Protoss_Corsair 1 12225
12312
