Protoss_Forge 1 3760
Protoss_Nexus 1 7366
Protoss_Photon_Cannon 3 12373
Protoss_Gateway 3 12195
Protoss_Assimilator 2 9427
Protoss_Cybernetics_Core 1 9027
Protoss_Dragoon 1 10418
Protoss_Citadel_of_Adun 1 11404
Protoss_Zealot 2 12160
12373
