Protoss_Forge 1 3798
Protoss_Photon_Cannon 2 11009
Protoss_Nexus 1 8048
Protoss_Gateway 1 7173
Protoss_Assimilator 2 9279
Protoss_Cybernetics_Core 1 8622
Protoss_Stargate 1 10548
Protoss_Zealot 2 12017
Protoss_Citadel_of_Adun 1 11756
Protoss_Corsair 1 11552
12017
