Protoss_Gateway 2 12045
Protoss_Zealot 7 12283
Protoss_Forge 1 5470
Protoss_Nexus 1 9270
Protoss_Photon_Cannon 1 8381
Protoss_Assimilator 2 11092
Protoss_Cybernetics_Core 1 9823
Protoss_Stargate 1 11645
Protoss_Citadel_of_Adun 1 12693
12693
