Protoss_Forge 1 4271
Protoss_Nexus 1 7389
Protoss_Photon_Cannon 2 8631
Protoss_Gateway 2 12721
Protoss_Assimilator 2 10113
Protoss_Cybernetics_Core 1 9917
Protoss_Zealot 2 11847
Protoss_Stargate 1 11664
Protoss_Citadel_of_Adun 1 11832
12721
