Protoss_Gateway 1 4221
Protoss_Assimilator 1 4239
Protoss_Zealot 5 11505
Protoss_Cybernetics_Core 1 7024
Protoss_Dragoon 2 9470
Protoss_Stargate 1 9417
Protoss_Citadel_of_Adun 1 10701
Protoss_Corsair 2 11250
Protoss_Templar_Archives 1 12307
Protoss_Forge 1 12228
12307
