Protoss_Gateway 2 10309
Protoss_Assimilator 1 4660
Protoss_Zealot 8 11885
Protoss_Cybernetics_Core 1 6974
Protoss_Stargate 1 9018
Protoss_Corsair 1 9965
Protoss_Citadel_of_Adun 1 11102
Protoss_Forge 1 12011
12011
