Protoss_Forge 1 4044
Protoss_Photon_Cannon 2 7930
Protoss_Nexus 1 8021
Protoss_Gateway 1 7256
Protoss_Assimilator 2 10894
Protoss_Zealot 3 12105
Protoss_Cybernetics_Core 1 10337
Protoss_Stargate 1 12081
Protoss_Citadel_of_Adun 1 12204
12204
