Protoss_Forge 1 4414
Protoss_Photon_Cannon 1 6010
Protoss_Nexus 1 8591
Protoss_Gateway 2 11411
Protoss_Assimilator 1 7887
Protoss_Cybernetics_Core 1 9078
Protoss_Zealot 4 11470
Protoss_Citadel_of_Adun 1 10934
11470
