Protoss_Nexus 1 7339
Protoss_Forge 1 5853
Protoss_Gateway 1 7120
Protoss_Photon_Cannon 2 9212
Protoss_Assimilator 2 11849
Protoss_Zealot 4 11686
Protoss_Cybernetics_Core 1 10034
Protoss_Citadel_of_Adun 1 11648
Protoss_Stargate 1 12022
12022
