Protoss_Forge 1 4224
Protoss_Nexus 1 7653
Protoss_Photon_Cannon 2 6841
Protoss_Gateway 1 7834
Protoss_Assimilator 2 11124
Protoss_Zealot 4 12304
Protoss_Cybernetics_Core 1 10764
Protoss_Stargate 1 12463
12463
