Protoss_Gateway 2 9539
Protoss_Assimilator 1 4409
Protoss_Zealot 5 12152
Protoss_Cybernetics_Core 1 6724
Protoss_Dragoon 4 11079
Protoss_Robotics_Facility 1 8981
Protoss_Shuttle 1 10375
Protoss_Robotics_Support_Bay 1 10067
Protoss_Reaver 1 12120
12152
