Protoss_Forge 1 4327
Protoss_Nexus 1 7852
Protoss_Photon_Cannon 2 8132
Protoss_Gateway 2 12734
Protoss_Assimilator 2 11866
Protoss_Cybernetics_Core 1 9779
Protoss_Zealot 3 12087
Protoss_Citadel_of_Adun 1 11449
Protoss_Dragoon 1 12358
12734
