Protoss_Forge 1 4287
Protoss_Nexus 1 7597
Protoss_Gateway 2 10512
Protoss_Photon_Cannon 1 7416
Protoss_Assimilator 1 7514
Protoss_Cybernetics_Core 1 8512
Protoss_Zealot 6 12157
Protoss_Citadel_of_Adun 1 11243
12157
