Protoss_Forge 1 4243
Protoss_Photon_Cannon 4 12256
Protoss_Nexus 1 8630
Protoss_Gateway 1 7640
Protoss_Assimilator 2 11252
Protoss_Cybernetics_Core 1 9462
Protoss_Zealot 2 11481
Protoss_Stargate 1 11296
Protoss_Corsair 1 12286
12286
