Protoss_Forge 1 4688
Protoss_Photon_Cannon 4 12502
Protoss_Nexus 1 8917
Protoss_Gateway 1 7691
Protoss_Assimilator 1 7985
Protoss_Zealot 2 11970
Protoss_Cybernetics_Core 1 11622
12502
