Protoss_Forge 1 4378
Protoss_Photon_Cannon 2 6028
Protoss_Nexus 1 8740
Protoss_Gateway 1 7685
Protoss_Assimilator 2 9816
Protoss_Cybernetics_Core 1 9479
Protoss_Zealot 3 11996
Protoss_Stargate 1 11252
Protoss_Citadel_of_Adun 1 12112
Protoss_Corsair 1 12233
12233
