Protoss_Forge 1 4302
Protoss_Photon_Cannon 1 5556
Protoss_Nexus 1 8450
Protoss_Gateway 3 11493
Protoss_Assimilator 2 8541
Protoss_Zealot 2 9994
Protoss_Cybernetics_Core 1 9424
Protoss_Dragoon 2 12434
12434
