Protoss_Forge 1 4723
Protoss_Photon_Cannon 2 6060
Protoss_Nexus 1 8844
Protoss_Gateway 1 8205
Protoss_Assimilator 2 10862
Protoss_Cybernetics_Core 1 9667
Protoss_Zealot 3 11291
Protoss_Stargate 1 11371
11371
