Protoss_Forge 1 4669
Protoss_Nexus 1 7503
Protoss_Photon_Cannon 3 8918
Protoss_Gateway 1 7641
Protoss_Assimilator 2 11430
Protoss_Cybernetics_Core 1 9949
Protoss_Stargate 1 11690
Protoss_Zealot 1 11774
11774
