Protoss_Forge 1 4126
Protoss_Photon_Cannon 1 6010
Protoss_Nexus 1 8548
Protoss_Gateway 2 12643
Protoss_Assimilator 2 10638
Protoss_Zealot 4 11952
Protoss_Cybernetics_Core 1 9304
Protoss_Stargate 1 11107
Protoss_Citadel_of_Adun 1 11461
12643
