Protoss_Forge 1 4927
Protoss_Photon_Cannon 1 6208
Protoss_Nexus 1 8197
Protoss_Assimilator 2 11879
Protoss_Gateway 2 9523
Protoss_Zealot 4 11259
Protoss_Cybernetics_Core 1 9681
Protoss_Stargate 1 11448
Protoss_Citadel_of_Adun 1 12239
12239
