Protoss_Forge 1 4097
Protoss_Photon_Cannon 1 5700
Protoss_Nexus 1 8396
Protoss_Gateway 1 7360
Protoss_Assimilator 2 10021
Protoss_Cybernetics_Core 1 8838
Protoss_Zealot 4 11710
Protoss_Stargate 1 10522
Protoss_Dragoon 1 10476
Protoss_Citadel_of_Adun 1 11769
Protoss_Corsair 1 11569
11769
