Protoss_Forge 1 3672
Protoss_Photon_Cannon 2 7828
Protoss_Nexus 1 9237
Protoss_Gateway 1 8652
Protoss_Assimilator 1 8348
Protoss_Cybernetics_Core 1 10135
Protoss_Zealot 3 11443
Protoss_Stargate 1 11851
Protoss_Citadel_of_Adun 1 11831
11851
