Protoss_Forge 1 4239
Protoss_Photon_Cannon 1 5782
Protoss_Nexus 1 8907
Protoss_Gateway 1 7829
Protoss_Assimilator 2 11309
Protoss_Cybernetics_Core 1 9277
Protoss_Zealot 4 11642
Protoss_Stargate 1 11090
Protoss_Citadel_of_Adun 1 11985
Protoss_Corsair 1 12190
12190
