Protoss_Forge 2 6312
Protoss_Nexus 1 7569
Protoss_Gateway 2 12049
Protoss_Photon_Cannon 2 11700
Protoss_Assimilator 2 10344
Protoss_Zealot 4 11680
Protoss_Cybernetics_Core 1 9686
Protoss_Stargate 1 11418
12049
