Protoss_Forge 1 4375
Protoss_Photon_Cannon 2 6194
Protoss_Nexus 1 9049
Protoss_Gateway 2 9456
Protoss_Assimilator 1 8133
Protoss_Zealot 5 11376
Protoss_Cybernetics_Core 1 11468
11468
