Protoss_Forge 1 4433
Protoss_Photon_Cannon 5 9985
Protoss_Nexus 1 10906
Protoss_Gateway 1 9825
Protoss_Assimilator 1 9992
Protoss_Zealot 2 12078
Protoss_Cybernetics_Core 1 11783
12078
