Protoss_Forge 1 4344
Protoss_Photon_Cannon 1 5852
Protoss_Nexus 1 8466
Protoss_Gateway 1 7628
Protoss_Assimilator 1 7918
Protoss_Cybernetics_Core 1 9280
Protoss_Zealot 1 9132
Protoss_Stargate 1 11121
Protoss_Scout 1 13030
13030
