Protoss_Forge 2 5721
Protoss_Nexus 1 7202
Protoss_Gateway 2 12541
Protoss_Photon_Cannon 1 7283
Protoss_Assimilator 2 10056
Protoss_Cybernetics_Core 1 9421
Protoss_Zealot 2 10954
Protoss_Stargate 1 11406
Protoss_Citadel_of_Adun 1 11695
12541
