Protoss_Forge 1 3794
Protoss_Photon_Cannon 3 6036
Protoss_Nexus 1 9666
Protoss_Gateway 1 10543
Protoss_Assimilator 1 10343
Protoss_Zealot 1 11724
Protoss_Cybernetics_Core 1 12836
12836
