Protoss_Forge 1 4019
Protoss_Photon_Cannon 4 12136
Protoss_Nexus 1 8305
Protoss_Gateway 1 7460
Protoss_Assimilator 1 8429
Protoss_Zealot 3 12020
Protoss_Cybernetics_Core 1 11186
Protoss_Dragoon 1 12382
12382
