Protoss_Gateway 1 4701
Protoss_Nexus 1 7831
Protoss_Zealot 3 11569
Protoss_Assimilator 1 7075
Protoss_Cybernetics_Core 1 8420
Protoss_Forge 1 9507
Protoss_Dragoon 1 10307
Protoss_Stargate 1 11178
Protoss_Photon_Cannon 3 12490
12490
