Protoss_Gateway 1 4098
Protoss_Forge 1 4455
Protoss_Zealot 3 9910
Protoss_Photon_Cannon 3 11142
Protoss_Nexus 1 9385
Protoss_Assimilator 2 11824
Protoss_Cybernetics_Core 1 10021
Protoss_Stargate 1 11849
11849
