Protoss_Gateway 2 12558
Protoss_Forge 1 4454
Protoss_Zealot 2 7946
Protoss_Photon_Cannon 3 11918
Protoss_Nexus 1 9464
Protoss_Assimilator 2 10032
Protoss_Cybernetics_Core 1 10089
Protoss_Citadel_of_Adun 1 11919
12558
