Protoss_Gateway 2 12510
Protoss_Forge 1 4493
Protoss_Zealot 4 12131
Protoss_Photon_Cannon 2 9936
Protoss_Nexus 1 9311
Protoss_Assimilator 2 9964
Protoss_Cybernetics_Core 1 9503
Protoss_Citadel_of_Adun 1 11174
12510
