Protoss_Forge 1 4599
Protoss_Photon_Cannon 1 5858
Protoss_Nexus 1 7822
Protoss_Gateway 1 7000
Protoss_Assimilator 2 11938
Protoss_Zealot 3 10562
Protoss_Cybernetics_Core 1 9623
Protoss_Stargate 1 11631
Protoss_Dragoon 1 11682
Protoss_Citadel_of_Adun 1 12460
12460
