Protoss_Forge 1 5077
Protoss_Nexus 1 7923
Protoss_Photon_Cannon 2 6742
Protoss_Gateway 1 7589
Protoss_Assimilator 2 11098
Protoss_Zealot 4 11619
Protoss_Cybernetics_Core 1 10054
Protoss_Stargate 1 11886
Protoss_Citadel_of_Adun 1 11973
11973
