Protoss_Forge 1 4289
Protoss_Nexus 1 7574
Protoss_Photon_Cannon 2 9585
Protoss_Gateway 1 7179
Protoss_Assimilator 1 7085
Protoss_Zealot 3 12195
Protoss_Cybernetics_Core 1 11651
12195
