Protoss_Gateway 2 11857
Protoss_Forge 1 5016
Protoss_Zealot 5 12336
Protoss_Photon_Cannon 2 10339
Protoss_Nexus 1 11434
Protoss_Assimilator 1 10381
Protoss_Cybernetics_Core 1 12255
12336
