Protoss_Forge 1 3757
Protoss_Photon_Cannon 3 8226
Protoss_Nexus 1 8539
Protoss_Gateway 1 7600
Protoss_Assimilator 2 10289
Protoss_Zealot 2 9898
Protoss_Cybernetics_Core 1 9978
Protoss_Dragoon 1 11211
Protoss_Stargate 1 11857
11857
