Protoss_Gateway 2 10171
Protoss_Assimilator 1 4666
Protoss_Zealot 6 11153
Protoss_Cybernetics_Core 1 7176
Protoss_Dragoon 1 8510
Protoss_Citadel_of_Adun 1 11010
Protoss_Nexus 1 14206
14206
