Protoss_Forge 1 4185
Protoss_Nexus 1 7669
Protoss_Gateway 3 12449
Protoss_Assimilator 1 6776
Protoss_Photon_Cannon 1 7795
Protoss_Zealot 4 11250
Protoss_Cybernetics_Core 1 9052
Protoss_Stargate 1 11229
Protoss_Citadel_of_Adun 1 11629
Protoss_Corsair 1 12195
12449
