Protoss_Forge 1 3910
Protoss_Photon_Cannon 3 11392
Protoss_Nexus 1 8419
Protoss_Gateway 1 7545
Protoss_Assimilator 1 7514
Protoss_Zealot 4 11797
Protoss_Cybernetics_Core 1 9172
Protoss_Stargate 1 11178
Protoss_Corsair 1 12169
12169
