Protoss_Nexus 1 7117
Protoss_Forge 1 5701
Protoss_Photon_Cannon 2 7140
Protoss_Gateway 1 7735
Protoss_Assimilator 2 9763
Protoss_Cybernetics_Core 1 9459
Protoss_Zealot 3 12304
Protoss_Stargate 1 11247
Protoss_Dragoon 1 11161
Protoss_Citadel_of_Adun 1 12078
Protoss_Corsair 1 12207
12304
