Protoss_Gateway 2 11074
Protoss_Assimilator 1 4536
Protoss_Zealot 5 11411
Protoss_Cybernetics_Core 1 6987
Protoss_Dragoon 1 8788
Protoss_Stargate 1 9588
Protoss_Corsair 1 11373
11411
