Protoss_Forge 1 3784
Protoss_Photon_Cannon 2 5834
Protoss_Nexus 1 9334
Protoss_Gateway 1 8355
Protoss_Assimilator 2 10719
Protoss_Zealot 2 10261
Protoss_Cybernetics_Core 1 10063
Protoss_Stargate 1 12460
12460
