Protoss_Forge 1 4176
Protoss_Photon_Cannon 3 8963
Protoss_Nexus 1 9447
Protoss_Gateway 1 8926
Protoss_Assimilator 2 12113
Protoss_Zealot 3 12207
Protoss_Cybernetics_Core 1 10850
Protoss_Citadel_of_Adun 1 12438
12438
