Protoss_Gateway 1 4366
Protoss_Zealot 4 11127
Protoss_Assimilator 1 5733
Protoss_Cybernetics_Core 1 7334
Protoss_Stargate 1 9043
Protoss_Dragoon 1 8811
Protoss_Citadel_of_Adun 1 9760
Protoss_Corsair 1 9994
Protoss_Templar_Archives 1 11860
11860
