Protoss_Forge 1 4084
Protoss_Photon_Cannon 3 11445
Protoss_Gateway 1 6267
Protoss_Nexus 1 9318
Protoss_Assimilator 2 9623
Protoss_Cybernetics_Core 1 9089
Protoss_Stargate 1 11040
Protoss_Corsair 1 12070
12070
