Protoss_Nexus 1 7020
Protoss_Gateway 4 12173
Protoss_Assimilator 1 6099
Protoss_Forge 1 6554
Protoss_Cybernetics_Core 1 7924
Protoss_Photon_Cannon 1 8006
Protoss_Zealot 6 12359
Protoss_Citadel_of_Adun 1 9671
12359
