Protoss_Forge 2 5800
Protoss_Nexus 1 7464
Protoss_Photon_Cannon 3 8915
Protoss_Gateway 1 7799
Protoss_Assimilator 1 10530
Protoss_Zealot 2 12010
Protoss_Cybernetics_Core 1 12185
12185
