Protoss_Forge 1 4780
Protoss_Nexus 1 7635
Protoss_Photon_Cannon 1 6358
Protoss_Gateway 3 12618
Protoss_Assimilator 2 10286
Protoss_Cybernetics_Core 1 8894
Protoss_Zealot 1 8952
Protoss_Citadel_of_Adun 1 10454
Protoss_Dragoon 1 10737
Protoss_Templar_Archives 1 12315
12618
