Protoss_Nexus 1 7020
Protoss_Gateway 3 7106
Protoss_Zealot 8 11950
Protoss_Assimilator 2 11718
Protoss_Forge 1 9598
Protoss_Cybernetics_Core 1 11178
Protoss_Photon_Cannon 1 10942
11950
