Protoss_Forge 1 4141
Protoss_Nexus 1 8010
Protoss_Gateway 1 7327
Protoss_Assimilator 2 10098
Protoss_Photon_Cannon 1 8384
Protoss_Cybernetics_Core 1 9389
Protoss_Zealot 1 9646
Protoss_Stargate 1 11317
Protoss_Robotics_Facility 1 13156
Protoss_Corsair 1 12280
13156
