Protoss_Forge 1 4041
Protoss_Photon_Cannon 1 5290
Protoss_Nexus 1 8305
Protoss_Gateway 1 7609
Protoss_Assimilator 2 9665
Protoss_Cybernetics_Core 1 9075
Protoss_Zealot 4 12134
Protoss_Stargate 1 11050
Protoss_Corsair 1 11996
12134
