Protoss_Forge 1 4884
Protoss_Nexus 1 7705
Protoss_Photon_Cannon 1 6569
Protoss_Gateway 3 12658
Protoss_Assimilator 1 7688
Protoss_Zealot 4 11607
Protoss_Cybernetics_Core 1 9475
Protoss_Citadel_of_Adun 1 11039
12658
