Protoss_Gateway 2 5278
Protoss_Zealot 8 11666
Protoss_Assimilator 1 6005
Protoss_Cybernetics_Core 1 7485
Protoss_Dragoon 1 8780
Protoss_Citadel_of_Adun 1 9225
Protoss_Forge 1 11478
11666
