Protoss_Forge 1 3980
Protoss_Nexus 1 8522
Protoss_Assimilator 2 9127
Protoss_Gateway 1 7913
Protoss_Photon_Cannon 1 7956
Protoss_Zealot 1 9143
Protoss_Cybernetics_Core 1 9813
Protoss_Stargate 1 11789
Protoss_Robotics_Facility 1 12728
12728
