Protoss_Forge 1 4234
Protoss_Nexus 1 7683
Protoss_Photon_Cannon 2 12273
Protoss_Gateway 3 12277
Protoss_Assimilator 2 9214
Protoss_Cybernetics_Core 1 9112
Protoss_Zealot 3 10758
Protoss_Citadel_of_Adun 1 10744
Protoss_Templar_Archives 1 12760
12760
