Protoss_Gateway 1 4221
Protoss_Assimilator 1 4512
Protoss_Zealot 4 10180
Protoss_Cybernetics_Core 1 7646
Protoss_Dragoon 2 12585
Protoss_Stargate 1 9954
Protoss_Citadel_of_Adun 1 10243
Protoss_Corsair 2 12010
Protoss_Templar_Archives 1 12017
Protoss_Forge 1 11764
12585
