Protoss_Forge 1 4192
Protoss_Photon_Cannon 3 6712
Protoss_Nexus 1 9769
Protoss_Gateway 1 9131
Protoss_Assimilator 1 9197
Protoss_Cybernetics_Core 1 10698
Protoss_Zealot 2 11329
Protoss_Stargate 1 12464
Protoss_Citadel_of_Adun 1 12702
12702
