Protoss_Forge 1 4047
Protoss_Photon_Cannon 5 12475
Protoss_Gateway 1 8063
Protoss_Nexus 1 10625
Protoss_Zealot 3 10830
Protoss_Assimilator 1 10343
Protoss_Cybernetics_Core 1 11971
12475
