Protoss_Forge 1 3845
Protoss_Nexus 1 7682
Protoss_Photon_Cannon 2 6830
Protoss_Assimilator 1 8336
Protoss_Gateway 3 12270
Protoss_Cybernetics_Core 1 10294
Protoss_Zealot 3 12083
Protoss_Citadel_of_Adun 1 11873
12270
