Protoss_Gateway 3 11932
Protoss_Zealot 7 11819
Protoss_Nexus 1 10755
Protoss_Forge 1 9409
Protoss_Assimilator 1 9876
Protoss_Photon_Cannon 1 10664
Protoss_Cybernetics_Core 1 11546
11932
