Protoss_Forge 1 4766
Protoss_Photon_Cannon 2 7228
Protoss_Nexus 1 8299
Protoss_Gateway 2 8080
Protoss_Assimilator 2 10672
Protoss_Cybernetics_Core 1 9759
Protoss_Zealot 1 10211
Protoss_Stargate 1 11677
Protoss_Dragoon 1 11606
Protoss_Citadel_of_Adun 1 12811
12811
