Protoss_Forge 1 4305
Protoss_Nexus 1 7961
Protoss_Gateway 3 12687
Protoss_Photon_Cannon 2 11327
Protoss_Assimilator 2 10767
Protoss_Zealot 2 11519
Protoss_Cybernetics_Core 1 10161
Protoss_Citadel_of_Adun 1 11922
12687
