Protoss_Forge 1 4135
Protoss_Photon_Cannon 2 6284
Protoss_Nexus 1 8875
Protoss_Gateway 2 12520
Protoss_Assimilator 1 7969
Protoss_Zealot 4 11882
Protoss_Cybernetics_Core 1 9547
Protoss_Citadel_of_Adun 1 11238
12520
