Protoss_Forge 1 4179
Protoss_Nexus 1 7401
Protoss_Photon_Cannon 2 6730
Protoss_Gateway 2 12314
Protoss_Assimilator 1 7789
Protoss_Cybernetics_Core 1 9248
Protoss_Zealot 2 9965
Protoss_Dragoon 1 11196
12314
