Protoss_Forge 1 4407
Protoss_Nexus 1 7904
Protoss_Photon_Cannon 2 7863
Protoss_Gateway 2 11619
Protoss_Assimilator 2 10747
Protoss_Cybernetics_Core 1 10305
Protoss_Zealot 2 11996
Protoss_Citadel_of_Adun 1 12105
12105
