Protoss_Forge 1 4635
Protoss_Photon_Cannon 2 6391
Protoss_Gateway 1 8471
Protoss_Assimilator 1 9185
Protoss_Zealot 2 10916
Protoss_Cybernetics_Core 1 10469
Protoss_Stargate 1 12341
Protoss_Citadel_of_Adun 1 12829
12829
