Protoss_Nexus 1 7111
Protoss_Forge 1 6061
Protoss_Gateway 2 11958
Protoss_Assimilator 2 9036
Protoss_Photon_Cannon 3 12209
Protoss_Cybernetics_Core 1 9324
Protoss_Zealot 1 10085
Protoss_Stargate 1 11520
Protoss_Citadel_of_Adun 1 11325
Protoss_Dragoon 1 11486
12209
