Protoss_Forge 1 4899
Protoss_Nexus 1 8027
Protoss_Photon_Cannon 2 7178
Protoss_Gateway 1 8168
Protoss_Assimilator 2 12210
Protoss_Zealot 2 11458
Protoss_Cybernetics_Core 1 10638
12210
