Protoss_Forge 1 4311
Protoss_Photon_Cannon 3 12417
Protoss_Nexus 1 8487
Protoss_Gateway 1 7430
Protoss_Assimilator 2 10287
Protoss_Cybernetics_Core 1 8891
Protoss_Zealot 2 11028
Protoss_Stargate 1 10610
Protoss_Corsair 1 11549
Protoss_Citadel_of_Adun 1 12362
12417
