Protoss_Forge 1 4063
Protoss_Nexus 1 7639
Protoss_Photon_Cannon 2 7105
Protoss_Gateway 1 8077
Protoss_Assimilator 2 10334
Protoss_Cybernetics_Core 1 9997
Protoss_Zealot 3 11174
Protoss_Stargate 1 11778
Protoss_Citadel_of_Adun 1 11993
Protoss_Dragoon 1 12294
12294
