Protoss_Forge 1 4611
Protoss_Photon_Cannon 3 7089
Protoss_Nexus 1 9461
Protoss_Gateway 1 8559
Protoss_Assimilator 2 10315
Protoss_Zealot 2 10501
Protoss_Cybernetics_Core 1 10092
Protoss_Stargate 1 11830
Protoss_Citadel_of_Adun 1 12311
Protoss_Dragoon 1 12446
12446
