Protoss_Forge 1 4908
Protoss_Nexus 1 7951
Protoss_Photon_Cannon 2 7031
Protoss_Gateway 2 12803
Protoss_Assimilator 2 10827
Protoss_Cybernetics_Core 1 9579
Protoss_Zealot 3 11895
Protoss_Stargate 1 11545
Protoss_Dragoon 1 11155
12803
