Protoss_Forge 1 4277
Protoss_Nexus 1 7508
Protoss_Photon_Cannon 3 12298
Protoss_Gateway 1 7726
Protoss_Assimilator 2 10189
Protoss_Cybernetics_Core 1 9405
Protoss_Zealot 4 12169
Protoss_Stargate 1 11204
Protoss_Citadel_of_Adun 1 11935
Protoss_Corsair 1 12283
12298
