Protoss_Forge 1 4236
Protoss_Photon_Cannon 1 6328
Protoss_Nexus 1 8387
Protoss_Gateway 1 7539
Protoss_Assimilator 2 10856
Protoss_Cybernetics_Core 1 9043
Protoss_Zealot 2 9687
Protoss_Stargate 1 10964
Protoss_Citadel_of_Adun 1 11772
Protoss_Dragoon 1 12007
Protoss_Corsair 1 11999
12007
