Protoss_Forge 1 4150
Protoss_Photon_Cannon 2 6462
Protoss_Nexus 1 8882
Protoss_Gateway 1 8007
Protoss_Assimilator 1 7764
Protoss_Zealot 3 12245
Protoss_Cybernetics_Core 1 9684
Protoss_Dragoon 1 11161
Protoss_Stargate 1 12044
Protoss_Citadel_of_Adun 1 12639
12639
