Protoss_Nexus 1 7176
Protoss_Forge 1 6435
Protoss_Photon_Cannon 1 7716
Protoss_Gateway 3 12255
Protoss_Assimilator 1 8307
Protoss_Cybernetics_Core 1 9623
Protoss_Zealot 3 11616
Protoss_Citadel_of_Adun 1 11270
12255
