Protoss_Forge 1 3971
Protoss_Photon_Cannon 2 6227
Protoss_Nexus 1 8712
Protoss_Gateway 1 7714
Protoss_Assimilator 2 11692
Protoss_Zealot 3 12137
Protoss_Cybernetics_Core 1 9602
Protoss_Dragoon 1 10930
Protoss_Stargate 1 11983
Protoss_Citadel_of_Adun 1 12412
12412
