Protoss_Forge 1 4015
Protoss_Photon_Cannon 2 6272
Protoss_Nexus 1 8905
Protoss_Gateway 1 7802
Protoss_Assimilator 1 7713
Protoss_Zealot 4 11467
Protoss_Cybernetics_Core 1 9492
Protoss_Stargate 1 11655
Protoss_Citadel_of_Adun 1 12377
12377
