Protoss_Forge 1 5355
Protoss_Photon_Cannon 4 9961
Protoss_Nexus 1 10240
Protoss_Gateway 1 8990
Protoss_Assimilator 1 9195
Protoss_Zealot 2 11753
Protoss_Cybernetics_Core 1 11579
11753
