Protoss_Forge 1 3908
Protoss_Nexus 1 7594
Protoss_Photon_Cannon 1 6964
Protoss_Gateway 1 7726
Protoss_Assimilator 2 10423
Protoss_Zealot 3 11660
Protoss_Cybernetics_Core 1 9650
Protoss_Stargate 1 11968
Protoss_Citadel_of_Adun 1 11888
11968
