Protoss_Nexus 1 6497
Protoss_Forge 1 5069
Protoss_Gateway 1 6211
Protoss_Photon_Cannon 1 6317
Protoss_Assimilator 2 10780
Protoss_Zealot 6 12231
Protoss_Cybernetics_Core 1 8938
Protoss_Stargate 1 10884
Protoss_Corsair 1 11944
Protoss_Citadel_of_Adun 1 12697
12697
