Protoss_Forge 1 4078
Protoss_Photon_Cannon 5 12513
Protoss_Nexus 1 8886
Protoss_Gateway 1 8516
Protoss_Assimilator 1 8863
Protoss_Zealot 3 11528
Protoss_Cybernetics_Core 1 10966
12513
