Protoss_Forge 1 4663
Protoss_Nexus 1 7544
Protoss_Photon_Cannon 1 6243
Protoss_Gateway 1 7290
Protoss_Assimilator 2 9955
Protoss_Cybernetics_Core 1 8800
Protoss_Zealot 2 11393
Protoss_Stargate 1 10497
Protoss_Dragoon 1 10529
Protoss_Citadel_of_Adun 1 11379
Protoss_Corsair 1 11481
11481
