Protoss_Forge 1 4230
Protoss_Photon_Cannon 2 7330
Protoss_Nexus 1 8629
Protoss_Gateway 1 8153
Protoss_Assimilator 2 11096
Protoss_Cybernetics_Core 1 9766
Protoss_Zealot 2 10755
Protoss_Stargate 1 11447
Protoss_Dragoon 1 12060
12060
