Protoss_Forge 1 4357
Protoss_Photon_Cannon 3 12279
Protoss_Nexus 1 8150
Protoss_Gateway 1 7754
Protoss_Assimilator 2 9498
Protoss_Cybernetics_Core 1 9418
Protoss_Zealot 4 12292
Protoss_Stargate 1 11204
Protoss_Corsair 1 12169
12292
