Protoss_Forge 1 4460
Protoss_Photon_Cannon 4 8196
Protoss_Nexus 1 10421
Protoss_Gateway 1 9649
Protoss_Assimilator 1 9623
Protoss_Cybernetics_Core 1 11270
Protoss_Zealot 2 11710
Protoss_Stargate 1 12951
12951
