Protoss_Forge 1 4283
Protoss_Nexus 1 7689
Protoss_Gateway 2 12642
Protoss_Photon_Cannon 2 9475
Protoss_Assimilator 2 11082
Protoss_Zealot 4 11118
Protoss_Cybernetics_Core 1 8929
Protoss_Stargate 1 11368
Protoss_Citadel_of_Adun 1 11821
12642
