Protoss_Forge 1 4466
Protoss_Photon_Cannon 2 7043
Protoss_Nexus 1 8206
Protoss_Gateway 1 7814
Protoss_Assimilator 2 9820
Protoss_Cybernetics_Core 1 9394
Protoss_Zealot 4 12190
Protoss_Stargate 1 11669
Protoss_Citadel_of_Adun 1 12337
12337
