Protoss_Forge 1 4309
Protoss_Nexus 1 7777
Protoss_Photon_Cannon 2 6818
Protoss_Gateway 2 12794
Protoss_Assimilator 2 10234
Protoss_Cybernetics_Core 1 9511
Protoss_Zealot 2 11633
Protoss_Stargate 1 11244
Protoss_Citadel_of_Adun 1 11911
Protoss_Corsair 1 12190
12794
