Protoss_Forge 2 6466
Protoss_Nexus 1 7148
Protoss_Gateway 4 12621
Protoss_Assimilator 1 6833
Protoss_Cybernetics_Core 1 8090
Protoss_Photon_Cannon 1 8076
Protoss_Zealot 4 11490
Protoss_Stargate 1 10177
Protoss_Corsair 1 11197
Protoss_Citadel_of_Adun 1 12080
12621
