Protoss_Nexus 1 7035
Protoss_Gateway 1 6052
Protoss_Assimilator 1 6147
Protoss_Forge 1 6978
Protoss_Zealot 7 12002
Protoss_Photon_Cannon 2 11469
Protoss_Cybernetics_Core 1 8856
Protoss_Stargate 1 10554
Protoss_Corsair 1 11578
Protoss_Citadel_of_Adun 1 12252
12252
