Protoss_Nexus 1 6532
Protoss_Forge 1 5025
Protoss_Photon_Cannon 3 9727
Protoss_Gateway 1 6866
Protoss_Assimilator 2 10106
Protoss_Cybernetics_Core 1 8537
Protoss_Zealot 3 12113
Protoss_Stargate 2 11482
Protoss_Corsair 2 12345
12345
