Protoss_Nexus 1 7073
Protoss_Forge 1 5552
Protoss_Assimilator 1 6367
Protoss_Gateway 4 11376
Protoss_Photon_Cannon 1 7951
Protoss_Cybernetics_Core 1 8587
Protoss_Zealot 7 12301
Protoss_Citadel_of_Adun 1 10391
12301
