Protoss_Forge 1 4341
Protoss_Photon_Cannon 2 6104
Protoss_Nexus 1 8876
Protoss_Gateway 2 11519
Protoss_Assimilator 1 8232
Protoss_Cybernetics_Core 1 9427
Protoss_Zealot 3 11470
Protoss_Citadel_of_Adun 1 10965
11519
