Protoss_Nexus 1 6602
Protoss_Forge 1 5060
Protoss_Photon_Cannon 1 6382
Protoss_Gateway 1 7126
Protoss_Assimilator 2 9277
Protoss_Cybernetics_Core 1 8614
Protoss_Zealot 3 10527
Protoss_Stargate 1 10327
Protoss_Robotics_Facility 1 11960
Protoss_Corsair 2 12315
12315
