Protoss_Nexus 1 6611
Protoss_Forge 1 5177
Protoss_Photon_Cannon 1 6455
Protoss_Gateway 1 6921
Protoss_Assimilator 1 7006
Protoss_Cybernetics_Core 1 8789
Protoss_Zealot 4 11856
Protoss_Stargate 1 11065
Protoss_Corsair 1 12043
12043
