Protoss_Forge 1 4764
Protoss_Nexus 1 7424
Protoss_Photon_Cannon 1 6186
Protoss_Gateway 1 6921
Protoss_Assimilator 2 9349
Protoss_Cybernetics_Core 1 8598
Protoss_Zealot 4 11815
Protoss_Stargate 2 12842
Protoss_Citadel_of_Adun 1 11074
Protoss_Corsair 2 12318
Protoss_Templar_Archives 1 12640
12842
