Protoss_Forge 1 4106
Protoss_Nexus 1 7637
Protoss_Gateway 2 10805
Protoss_Assimilator 1 7038
Protoss_Photon_Cannon 4 12578
Protoss_Cybernetics_Core 1 8764
Protoss_Zealot 5 11996
Protoss_Citadel_of_Adun 1 10248
12578
