Protoss_Forge 1 4032
Protoss_Photon_Cannon 1 6077
Protoss_Nexus 1 7942
Protoss_Gateway 1 6956
Protoss_Assimilator 2 10609
Protoss_Cybernetics_Core 1 8724
Protoss_Zealot 3 12286
Protoss_Stargate 1 10587
Protoss_Citadel_of_Adun 1 11543
Protoss_Corsair 1 11525
12286
