Protoss_Forge 1 4625
Protoss_Photon_Cannon 1 5962
Protoss_Nexus 1 8288
Protoss_Gateway 2 7653
Protoss_Assimilator 1 8309
Protoss_Zealot 8 11721
Protoss_Cybernetics_Core 1 10325
Protoss_Stargate 1 12082
12082
