Protoss_Forge 1 4663
Protoss_Photon_Cannon 2 5995
Protoss_Nexus 1 8876
Protoss_Gateway 1 8227
Protoss_Assimilator 2 10112
Protoss_Zealot 4 12130
Protoss_Cybernetics_Core 1 9684
Protoss_Stargate 2 12783
12783
