Protoss_Forge 1 4312
Protoss_Photon_Cannon 2 6253
Protoss_Nexus 1 8952
Protoss_Gateway 1 7947
Protoss_Assimilator 2 10354
Protoss_Cybernetics_Core 1 9468
Protoss_Zealot 3 12096
Protoss_Stargate 1 11308
Protoss_Dragoon 1 11234
Protoss_Citadel_of_Adun 1 12153
Protoss_Corsair 1 12269
12269
