Protoss_Gateway 2 5227
Protoss_Zealot 10 11414
Protoss_Assimilator 1 7483
Protoss_Cybernetics_Core 1 9468
Protoss_Stargate 1 11172
Protoss_Citadel_of_Adun 1 11235
Protoss_Corsair 1 12113
12113
