Protoss_Forge 1 4504
Protoss_Photon_Cannon 2 6215
Protoss_Nexus 1 8949
Protoss_Gateway 1 8105
Protoss_Assimilator 2 9835
Protoss_Zealot 2 10135
Protoss_Cybernetics_Core 1 9618
Protoss_Stargate 1 11444
Protoss_Dragoon 1 11366
Protoss_Robotics_Facility 1 13207
13207
