Protoss_Forge 1 3852
Protoss_Photon_Cannon 1 5821
Protoss_Nexus 1 7910
Protoss_Gateway 1 7149
Protoss_Assimilator 2 10139
Protoss_Zealot 4 11391
Protoss_Cybernetics_Core 1 9511
Protoss_Stargate 1 11427
Protoss_Citadel_of_Adun 1 11689
11689
