Protoss_Gateway 2 5109
Protoss_Zealot 7 8724
Protoss_Forge 1 7875
Protoss_Nexus 1 11715
Protoss_Photon_Cannon 1 10506
Protoss_Assimilator 2 11516
Protoss_Cybernetics_Core 1 11695
11715
