Protoss_Forge 1 4000
Protoss_Photon_Cannon 3 11647
Protoss_Nexus 1 8498
Protoss_Gateway 3 12334
Protoss_Assimilator 2 12298
Protoss_Zealot 5 11707
Protoss_Cybernetics_Core 1 9348
Protoss_Citadel_of_Adun 1 10981
12334
