Protoss_Forge 1 4793
Protoss_Nexus 1 7653
Protoss_Photon_Cannon 1 6126
Protoss_Gateway 1 7227
Protoss_Assimilator 2 12172
Protoss_Zealot 4 11985
Protoss_Cybernetics_Core 1 9198
Protoss_Stargate 1 11211
Protoss_Citadel_of_Adun 1 12084
Protoss_Corsair 1 12356
12356
