Protoss_Nexus 1 6792
Protoss_Forge 1 5338
Protoss_Photon_Cannon 1 6664
Protoss_Gateway 3 11831
Protoss_Assimilator 2 8944
Protoss_Cybernetics_Core 1 8739
Protoss_Zealot 3 11484
Protoss_Stargate 1 10835
Protoss_Citadel_of_Adun 1 11333
Protoss_Corsair 1 11771
11831
