Protoss_Forge 1 4420
Protoss_Nexus 1 7874
Protoss_Gateway 1 6858
Protoss_Assimilator 2 9394
Protoss_Photon_Cannon 2 11969
Protoss_Cybernetics_Core 1 8601
Protoss_Zealot 3 11891
Protoss_Stargate 1 10440
Protoss_Citadel_of_Adun 1 11131
Protoss_Dragoon 1 10989
Protoss_Corsair 1 11405
Protoss_Templar_Archives 1 12729
12729
