Protoss_Forge 1 4540
Protoss_Photon_Cannon 2 7883
Protoss_Nexus 1 7925
Protoss_Gateway 2 12503
Protoss_Assimilator 2 11727
Protoss_Cybernetics_Core 1 8630
Protoss_Zealot 3 11180
Protoss_Stargate 1 10320
Protoss_Citadel_of_Adun 1 11066
Protoss_Corsair 1 11420
12503
