Protoss_Forge 1 4417
Protoss_Nexus 1 7620
Protoss_Photon_Cannon 2 12332
Protoss_Gateway 1 7363
Protoss_Assimilator 2 10085
Protoss_Cybernetics_Core 1 9554
Protoss_Zealot 2 11868
Protoss_Stargate 1 11236
Protoss_Dragoon 1 10833
Protoss_Citadel_of_Adun 1 11824
Protoss_Corsair 1 12175
12332
