Protoss_Nexus 1 7038
Protoss_Forge 1 5585
Protoss_Photon_Cannon 3 12442
Protoss_Gateway 1 9217
Protoss_Assimilator 2 10883
Protoss_Cybernetics_Core 1 10839
Protoss_Zealot 2 11508
Protoss_Stargate 1 13063
13063
