Protoss_Forge 1 3974
Protoss_Photon_Cannon 3 10411
Protoss_Nexus 1 9429
Protoss_Gateway 1 8860
Protoss_Assimilator 2 11247
Protoss_Cybernetics_Core 1 10536
Protoss_Zealot 2 11063
Protoss_Citadel_of_Adun 1 11990
11990
