Protoss_Forge 1 4275
Protoss_Nexus 1 7705
Protoss_Gateway 4 12302
Protoss_Assimilator 1 7199
Protoss_Photon_Cannon 3 12446
Protoss_Zealot 2 9374
Protoss_Cybernetics_Core 1 9389
Protoss_Dragoon 2 11878
12446
