Protoss_Forge 1 4050
Protoss_Photon_Cannon 5 12058
Protoss_Nexus 1 8459
Protoss_Gateway 1 7811
Protoss_Assimilator 2 10755
Protoss_Cybernetics_Core 1 9307
Protoss_Zealot 3 10849
Protoss_Stargate 1 11227
Protoss_Citadel_of_Adun 1 11809
Protoss_Corsair 1 12254
12254
