Protoss_Forge 1 4750
Protoss_Nexus 1 7635
Protoss_Photon_Cannon 2 6853
Protoss_Gateway 2 11793
Protoss_Assimilator 1 8007
Protoss_Cybernetics_Core 1 10029
Protoss_Zealot 3 11440
Protoss_Stargate 1 11766
Protoss_Citadel_of_Adun 1 12563
12563
