Protoss_Forge 1 4881
Protoss_Photon_Cannon 3 12071
Protoss_Nexus 1 8853
Protoss_Gateway 1 7893
Protoss_Assimilator 2 10894
Protoss_Zealot 2 10161
Protoss_Cybernetics_Core 1 9718
Protoss_Stargate 1 11792
Protoss_Dragoon 1 11632
Protoss_Citadel_of_Adun 1 12710
12710
