Protoss_Gateway 1 4117
Protoss_Zealot 8 11663
Protoss_Nexus 1 9077
Protoss_Forge 1 7795
Protoss_Photon_Cannon 3 12345
Protoss_Assimilator 1 9181
Protoss_Cybernetics_Core 1 11124
12345
