Protoss_Forge 2 6321
Protoss_Nexus 1 7102
Protoss_Gateway 1 6449
Protoss_Assimilator 2 10182
Protoss_Photon_Cannon 2 12331
Protoss_Cybernetics_Core 1 8784
Protoss_Zealot 2 11853
Protoss_Stargate 1 10607
Protoss_Dragoon 1 10655
Protoss_Citadel_of_Adun 1 11979
Protoss_Corsair 1 12228
12331
