Protoss_Forge 1 3828
Protoss_Photon_Cannon 2 6478
Protoss_Nexus 1 9261
Protoss_Gateway 1 8349
Protoss_Assimilator 2 10810
Protoss_Zealot 2 11522
Protoss_Cybernetics_Core 1 10290
Protoss_Stargate 1 12073
12073
