Protoss_Forge 1 4558
Protoss_Photon_Cannon 2 5842
Protoss_Nexus 1 9643
Protoss_Gateway 1 9631
Protoss_Assimilator 2 10872
Protoss_Zealot 1 10594
Protoss_Cybernetics_Core 1 12074
12074
