Protoss_Forge 1 4654
Protoss_Nexus 1 7518
Protoss_Photon_Cannon 3 12347
Protoss_Gateway 1 7673
Protoss_Assimilator 2 11967
Protoss_Cybernetics_Core 1 9271
Protoss_Zealot 2 10466
Protoss_Stargate 1 11318
Protoss_Dragoon 1 11586
Protoss_Citadel_of_Adun 1 12352
12352
