Protoss_Forge 1 4133
Protoss_Nexus 1 7541
Protoss_Photon_Cannon 1 6408
Protoss_Gateway 1 7092
Protoss_Assimilator 2 8313
Protoss_Cybernetics_Core 1 8560
Protoss_Zealot 1 8958
Protoss_Stargate 1 10458
Protoss_Citadel_of_Adun 1 11076
Protoss_Corsair 1 11519
Protoss_Templar_Archives 1 12541
12541
