Protoss_Gateway 1 4193
Protoss_Zealot 6 12146
Protoss_Nexus 1 8493
Protoss_Forge 1 7132
Protoss_Photon_Cannon 2 10649
Protoss_Assimilator 2 11414
Protoss_Cybernetics_Core 1 12615
12615
