Protoss_Forge 1 4344
Protoss_Nexus 1 7596
Protoss_Photon_Cannon 1 6376
Protoss_Gateway 1 7100
Protoss_Assimilator 2 10963
Protoss_Zealot 4 12172
Protoss_Cybernetics_Core 1 9555
Protoss_Stargate 1 11396
Protoss_Citadel_of_Adun 1 12239
12239
