Protoss_Forge 1 4196
Protoss_Nexus 1 7937
Protoss_Gateway 3 11892
Protoss_Assimilator 1 6990
Protoss_Zealot 3 11663
Protoss_Photon_Cannon 1 8428
Protoss_Cybernetics_Core 1 9232
Protoss_Dragoon 1 10602
Protoss_Citadel_of_Adun 1 10992
11892
