Protoss_Forge 1 4278
Protoss_Photon_Cannon 2 6530
Protoss_Nexus 1 8940
Protoss_Gateway 1 7987
Protoss_Assimilator 2 10644
Protoss_Cybernetics_Core 1 9501
Protoss_Zealot 3 11168
Protoss_Stargate 1 11220
Protoss_Citadel_of_Adun 1 11888
Protoss_Dragoon 1 12317
Protoss_Corsair 1 12160
12317
