Protoss_Forge 1 4152
Protoss_Nexus 1 7477
Protoss_Photon_Cannon 2 7762
Protoss_Gateway 1 7452
Protoss_Assimilator 1 8172
Protoss_Zealot 3 11774
Protoss_Cybernetics_Core 1 9684
Protoss_Stargate 1 12245
12245
