Protoss_Forge 1 3822
Protoss_Photon_Cannon 2 5937
Protoss_Nexus 1 9024
Protoss_Gateway 1 8101
Protoss_Assimilator 2 8660
Protoss_Zealot 2 10530
Protoss_Cybernetics_Core 1 9965
Protoss_Stargate 1 12056
Protoss_Dragoon 1 11814
Protoss_Citadel_of_Adun 1 12794
12794
