Protoss_Forge 1 3869
Protoss_Nexus 1 7574
Protoss_Photon_Cannon 2 6832
Protoss_Gateway 1 7867
Protoss_Assimilator 2 10262
Protoss_Zealot 4 12274
Protoss_Cybernetics_Core 1 9750
Protoss_Stargate 1 11659
Protoss_Citadel_of_Adun 1 12687
12687
