Protoss_Forge 1 4982
Protoss_Nexus 1 7679
Protoss_Photon_Cannon 2 6806
Protoss_Gateway 1 7624
Protoss_Assimilator 2 11559
Protoss_Cybernetics_Core 1 9532
Protoss_Zealot 2 11250
Protoss_Stargate 1 11330
Protoss_Corsair 1 12266
12266
