Protoss_Forge 1 4271
Protoss_Nexus 1 7623
Protoss_Photon_Cannon 1 6389
Protoss_Gateway 1 7436
Protoss_Assimilator 2 10957
Protoss_Cybernetics_Core 1 8885
Protoss_Zealot 3 11452
Protoss_Stargate 1 11071
Protoss_Corsair 1 12166
12166
