Protoss_Forge 1 4044
Protoss_Nexus 1 7471
Protoss_Photon_Cannon 2 6805
Protoss_Gateway 1 7782
Protoss_Assimilator 2 10371
Protoss_Cybernetics_Core 1 9248
Protoss_Zealot 3 11818
Protoss_Stargate 1 10958
Protoss_Dragoon 1 10956
Protoss_Corsair 1 11917
11917
