Protoss_Forge 1 4220
Protoss_Photon_Cannon 2 6414
Protoss_Nexus 1 8736
Protoss_Gateway 1 7697
Protoss_Assimilator 2 10966
Protoss_Cybernetics_Core 1 9189
Protoss_Zealot 2 11531
Protoss_Stargate 1 11090
Protoss_Corsair 1 12152
12152
