Protoss_Forge 1 4101
Protoss_Nexus 1 7840
Protoss_Gateway 1 7149
Protoss_Assimilator 2 10249
Protoss_Photon_Cannon 2 9712
Protoss_Cybernetics_Core 1 8736
Protoss_Zealot 3 11221
Protoss_Stargate 1 10648
Protoss_Citadel_of_Adun 1 11573
Protoss_Corsair 1 11657
11657
