Protoss_Forge 1 4966
Protoss_Nexus 1 7638
Protoss_Photon_Cannon 1 6355
Protoss_Gateway 2 11996
Protoss_Assimilator 2 9476
Protoss_Cybernetics_Core 1 8768
Protoss_Zealot 4 12081
Protoss_Stargate 1 10613
Protoss_Citadel_of_Adun 1 11420
Protoss_Corsair 1 11862
12081
