Protoss_Gateway 1 4154
Protoss_Zealot 7 11595
Protoss_Nexus 1 8965
Protoss_Forge 1 7631
Protoss_Photon_Cannon 2 10754
Protoss_Assimilator 2 11386
Protoss_Cybernetics_Core 1 11755
11755
