Protoss_Forge 1 4221
Protoss_Photon_Cannon 2 7197
Protoss_Nexus 1 7992
Protoss_Gateway 1 7741
Protoss_Assimilator 2 11092
Protoss_Zealot 2 11780
Protoss_Cybernetics_Core 1 9315
Protoss_Dragoon 1 10725
Protoss_Stargate 1 11292
Protoss_Corsair 1 12266
12266
