Protoss_Forge 1 4777
Protoss_Photon_Cannon 2 6102
Protoss_Nexus 1 8769
Protoss_Gateway 1 7694
Protoss_Assimilator 2 9466
Protoss_Cybernetics_Core 1 9154
Protoss_Zealot 2 10340
Protoss_Stargate 1 10901
Protoss_Dragoon 1 11460
Protoss_Corsair 1 11835
Protoss_Citadel_of_Adun 1 12368
12368
