Protoss_Forge 1 3708
Protoss_Photon_Cannon 2 5853
Protoss_Nexus 1 8981
Protoss_Gateway 1 7943
Protoss_Assimilator 1 7852
Protoss_Cybernetics_Core 1 9432
Protoss_Zealot 4 12362
Protoss_Stargate 1 11590
Protoss_Citadel_of_Adun 1 11660
12362
