Protoss_Forge 1 3895
Protoss_Photon_Cannon 2 5981
Protoss_Nexus 1 9104
Protoss_Gateway 3 12646
Protoss_Assimilator 2 11830
Protoss_Cybernetics_Core 1 9713
Protoss_Zealot 2 10123
Protoss_Citadel_of_Adun 1 11342
Protoss_Dragoon 1 11384
12646
