Protoss_Forge 1 4808
Protoss_Nexus 1 7657
Protoss_Photon_Cannon 1 6367
Protoss_Gateway 1 7426
Protoss_Assimilator 2 10232
Protoss_Cybernetics_Core 1 8967
Protoss_Zealot 4 11657
Protoss_Stargate 1 10879
Protoss_Citadel_of_Adun 1 11742
Protoss_Corsair 1 11818
11818
