Protoss_Nexus 1 6921
Protoss_Forge 1 5440
Protoss_Gateway 1 7073
Protoss_Photon_Cannon 2 7435
Protoss_Assimilator 2 9972
Protoss_Zealot 4 11824
Protoss_Cybernetics_Core 1 9266
Protoss_Stargate 2 11912
Protoss_Corsair 1 11897
Protoss_Citadel_of_Adun 1 12684
12684
