Protoss_Forge 1 4204
Protoss_Nexus 1 7509
Protoss_Gateway 2 11616
Protoss_Photon_Cannon 1 6663
Protoss_Assimilator 2 10223
Protoss_Cybernetics_Core 1 8212
Protoss_Stargate 1 10060
Protoss_Zealot 3 11449
Protoss_Citadel_of_Adun 2 12046
Protoss_Corsair 1 11025
12046
