Protoss_Forge 1 4305
Protoss_Photon_Cannon 2 6107
Protoss_Nexus 1 9100
Protoss_Gateway 1 8270
Protoss_Assimilator 2 10735
Protoss_Cybernetics_Core 1 9804
Protoss_Zealot 3 11490
Protoss_Stargate 1 11511
11511
