Protoss_Forge 1 4764
Protoss_Nexus 1 7799
Protoss_Photon_Cannon 2 6827
Protoss_Gateway 1 7823
Protoss_Assimilator 2 9762
Protoss_Cybernetics_Core 1 9396
Protoss_Stargate 1 11097
Protoss_Zealot 2 11519
Protoss_Citadel_of_Adun 1 11667
Protoss_Corsair 1 12040
12040
