Protoss_Forge 1 4804
Protoss_Nexus 1 7680
Protoss_Photon_Cannon 2 6824
Protoss_Gateway 1 8221
Protoss_Assimilator 2 10395
Protoss_Cybernetics_Core 1 10065
Protoss_Zealot 2 11203
Protoss_Stargate 1 11754
Protoss_Citadel_of_Adun 1 12166
12166
