Protoss_Forge 1 3965
Protoss_Photon_Cannon 2 8432
Protoss_Nexus 1 12050
Protoss_Gateway 1 11045
Protoss_Assimilator 1 10902
Protoss_Zealot 1 12116
Protoss_Cybernetics_Core 1 12617
12617
