Protoss_Forge 1 4005
Protoss_Nexus 1 7565
Protoss_Photon_Cannon 2 7225
Protoss_Gateway 1 7855
Protoss_Assimilator 2 11718
Protoss_Cybernetics_Core 1 9374
Protoss_Zealot 3 11208
Protoss_Stargate 1 11210
Protoss_Citadel_of_Adun 1 11429
Protoss_Corsair 1 12213
12213
