Protoss_Forge 1 3841
Protoss_Photon_Cannon 2 5308
Protoss_Gateway 2 12626
Protoss_Assimilator 1 7428
Protoss_Cybernetics_Core 1 9207
Protoss_Zealot 1 8882
Protoss_Dragoon 1 10412
Protoss_Stargate 1 11034
Protoss_Citadel_of_Adun 1 11314
Protoss_Corsair 1 11979
12626
