Protoss_Forge 1 4404
Protoss_Nexus 1 7645
Protoss_Gateway 1 6773
Protoss_Assimilator 2 10574
Protoss_Photon_Cannon 1 7453
Protoss_Cybernetics_Core 1 8699
Protoss_Zealot 3 12081
Protoss_Dragoon 1 10070
Protoss_Citadel_of_Adun 1 10445
12081
