Protoss_Forge 1 4755
Protoss_Photon_Cannon 3 10946
Protoss_Nexus 1 8870
Protoss_Gateway 1 7811
Protoss_Assimilator 2 11048
Protoss_Cybernetics_Core 1 9263
Protoss_Zealot 3 12146
Protoss_Stargate 1 11039
Protoss_Citadel_of_Adun 1 11901
Protoss_Corsair 1 11991
12146
