Protoss_Gateway 3 11578
Protoss_Assimilator 1 4271
Protoss_Zealot 6 11654
Protoss_Cybernetics_Core 1 8578
Protoss_Dragoon 1 9780
Protoss_Stargate 1 10405
Protoss_Corsair 1 11771
11771
