Protoss_Forge 1 4659
Protoss_Nexus 1 7626
Protoss_Photon_Cannon 3 10491
Protoss_Gateway 1 7024
Protoss_Assimilator 2 11393
Protoss_Cybernetics_Core 1 9230
Protoss_Zealot 2 11958
Protoss_Stargate 1 11210
Protoss_Dragoon 1 11079
Protoss_Citadel_of_Adun 1 12118
Protoss_Corsair 1 12181
12181
