Protoss_Gateway 2 11566
Protoss_Assimilator 1 4827
Protoss_Zealot 4 8732
Protoss_Cybernetics_Core 1 7218
Protoss_Stargate 1 8956
Protoss_Dragoon 1 9851
Protoss_Corsair 2 11636
Protoss_Citadel_of_Adun 1 11203
11636
