Protoss_Forge 1 4934
Protoss_Photon_Cannon 3 8409
Protoss_Nexus 1 8901
Protoss_Gateway 1 7685
Protoss_Assimilator 2 10182
Protoss_Cybernetics_Core 1 9653
Protoss_Zealot 2 11882
Protoss_Dragoon 1 10860
Protoss_Stargate 1 11832
Protoss_Citadel_of_Adun 1 12280
12280
