Protoss_Forge 1 4068
Protoss_Photon_Cannon 2 6177
Protoss_Nexus 1 8736
Protoss_Gateway 1 7717
Protoss_Assimilator 2 10669
Protoss_Cybernetics_Core 1 9228
Protoss_Zealot 4 11841
Protoss_Stargate 1 10933
Protoss_Corsair 1 11873
Protoss_Citadel_of_Adun 1 12573
12573
