Protoss_Forge 1 5271
Protoss_Nexus 1 7754
Protoss_Photon_Cannon 2 7102
Protoss_Gateway 1 7931
Protoss_Assimilator 2 10227
Protoss_Cybernetics_Core 1 9539
Protoss_Zealot 2 11549
Protoss_Stargate 1 11374
Protoss_Citadel_of_Adun 1 11743
Protoss_Corsair 1 12312
12312
