Protoss_Forge 1 4346
Protoss_Photon_Cannon 2 11204
Protoss_Nexus 1 8493
Protoss_Gateway 1 8183
Protoss_Assimilator 2 10512
Protoss_Cybernetics_Core 1 9681
Protoss_Stargate 1 11412
11412
