Protoss_Forge 1 4214
Protoss_Photon_Cannon 2 6017
Protoss_Nexus 1 8829
Protoss_Gateway 1 7987
Protoss_Assimilator 2 10258
Protoss_Cybernetics_Core 1 9506
Protoss_Zealot 3 11751
Protoss_Dragoon 1 10722
Protoss_Stargate 1 11503
Protoss_Citadel_of_Adun 1 12795
12795
