Protoss_Forge 1 4079
Protoss_Photon_Cannon 2 6010
Protoss_Nexus 1 9254
Protoss_Gateway 3 12734
Protoss_Assimilator 1 8304
Protoss_Zealot 2 10352
Protoss_Cybernetics_Core 1 9953
Protoss_Citadel_of_Adun 1 11417
Protoss_Dragoon 1 11448
12734
