Protoss_Forge 1 4407
Protoss_Nexus 1 8037
Protoss_Gateway 1 7578
Protoss_Photon_Cannon 2 8073
Protoss_Assimilator 2 9863
Protoss_Cybernetics_Core 1 9631
Protoss_Zealot 2 11148
Protoss_Stargate 1 11429
Protoss_Citadel_of_Adun 1 12421
12421
