Protoss_Forge 1 3910
Protoss_Photon_Cannon 1 5637
Protoss_Nexus 1 7944
Protoss_Gateway 1 7041
Protoss_Assimilator 2 10881
Protoss_Cybernetics_Core 1 8563
Protoss_Zealot 2 11358
Protoss_Dragoon 1 10078
Protoss_Stargate 1 11178
Protoss_Corsair 1 12113
12113
