Protoss_Forge 1 4404
Protoss_Nexus 1 7547
Protoss_Photon_Cannon 2 6633
Protoss_Gateway 2 12822
Protoss_Assimilator 2 10133
Protoss_Cybernetics_Core 1 9444
Protoss_Stargate 1 11263
Protoss_Citadel_of_Adun 1 11765
Protoss_Corsair 1 12207
12822
