Protoss_Gateway 1 4114
Protoss_Assimilator 1 4817
Protoss_Zealot 4 9626
Protoss_Cybernetics_Core 1 6457
Protoss_Dragoon 1 7822
Protoss_Robotics_Facility 1 9184
Protoss_Forge 1 9864
Protoss_Shuttle 1 10615
Protoss_Robotics_Support_Bay 1 10781
Protoss_Reaver 1 12536
Protoss_Photon_Cannon 1 12139
12536
