Protoss_Forge 1 4987
Protoss_Nexus 1 7541
Protoss_Photon_Cannon 2 6704
Protoss_Gateway 2 8557
Protoss_Zealot 3 11487
Protoss_Assimilator 2 12024
Protoss_Cybernetics_Core 1 11427
12024
