Protoss_Forge 1 4457
Protoss_Nexus 1 7565
Protoss_Photon_Cannon 4 8237
Protoss_Gateway 1 8746
Protoss_Zealot 2 11259
Protoss_Assimilator 1 10030
Protoss_Cybernetics_Core 1 11876
11876
