Protoss_Forge 1 4915
Protoss_Photon_Cannon 3 8726
Protoss_Nexus 1 8736
Protoss_Gateway 1 7837
Protoss_Assimilator 2 11272
Protoss_Zealot 2 10375
Protoss_Cybernetics_Core 1 10010
Protoss_Stargate 1 11855
Protoss_Dragoon 1 12057
12057
