Protoss_Forge 1 3911
Protoss_Photon_Cannon 1 6000
Protoss_Nexus 1 8291
Protoss_Gateway 1 7501
Protoss_Assimilator 1 7673
Protoss_Zealot 4 11952
Protoss_Cybernetics_Core 1 9528
Protoss_Citadel_of_Adun 1 11876
11952
