Protoss_Forge 1 4082
Protoss_Photon_Cannon 3 11346
Protoss_Nexus 1 8832
Protoss_Gateway 1 7963
Protoss_Assimilator 2 11562
Protoss_Cybernetics_Core 1 9580
Protoss_Zealot 3 12149
Protoss_Stargate 1 11447
Protoss_Robotics_Facility 1 12996
12996
