Protoss_Forge 1 4429
Protoss_Photon_Cannon 3 12218
Protoss_Nexus 1 8832
Protoss_Gateway 1 7855
Protoss_Assimilator 2 11297
Protoss_Zealot 2 10114
Protoss_Cybernetics_Core 1 9519
Protoss_Stargate 1 11345
Protoss_Citadel_of_Adun 1 12078
Protoss_Corsair 1 12283
12283
