Protoss_Nexus 1 6997
Protoss_Forge 1 5945
Protoss_Gateway 1 6784
Protoss_Photon_Cannon 2 9791
Protoss_Assimilator 2 10246
Protoss_Cybernetics_Core 1 9269
Protoss_Stargate 1 11210
Protoss_Robotics_Facility 1 12502
Protoss_Zealot 1 12023
Protoss_Dragoon 1 12326
Protoss_Corsair 1 12163
12502
