Protoss_Forge 1 3892
Protoss_Photon_Cannon 2 5870
Protoss_Nexus 1 8879
Protoss_Gateway 1 7897
Protoss_Assimilator 2 11101
Protoss_Zealot 2 10665
Protoss_Cybernetics_Core 1 10242
Protoss_Stargate 1 11942
11942
