Protoss_Nexus 1 6924
Protoss_Gateway 2 12650
Protoss_Assimilator 2 10824
Protoss_Forge 1 6617
Protoss_Photon_Cannon 2 8082
Protoss_Cybernetics_Core 1 9369
Protoss_Zealot 3 11487
Protoss_Stargate 1 11182
Protoss_Citadel_of_Adun 1 11090
Protoss_Templar_Archives 1 12558
12650
