Protoss_Forge 1 4985
Protoss_Nexus 1 7986
Protoss_Gateway 1 7590
Protoss_Photon_Cannon 2 11770
Protoss_Assimilator 2 9738
Protoss_Cybernetics_Core 1 9371
Protoss_Zealot 2 10782
Protoss_Stargate 1 11213
Protoss_Corsair 1 12292
12292
