Protoss_Forge 1 4000
Protoss_Photon_Cannon 3 9333
Protoss_Nexus 1 8583
Protoss_Assimilator 1 7499
Protoss_Gateway 3 12833
Protoss_Cybernetics_Core 1 9924
Protoss_Zealot 1 10018
Protoss_Dragoon 1 11138
Protoss_Citadel_of_Adun 1 11900
12833
