Protoss_Nexus 1 7069
Protoss_Gateway 2 12201
Protoss_Forge 1 6504
Protoss_Assimilator 2 11203
Protoss_Photon_Cannon 1 7822
Protoss_Zealot 6 12052
Protoss_Cybernetics_Core 1 9074
Protoss_Stargate 1 10906
Protoss_Citadel_of_Adun 1 11148
Protoss_Corsair 1 12239
12239
