Protoss_Gateway 1 3718
Protoss_Zealot 7 11478
Protoss_Forge 1 6279
Protoss_Photon_Cannon 1 8404
Protoss_Nexus 1 11528
Protoss_Assimilator 1 9753
Protoss_Cybernetics_Core 1 11508
11528
