Protoss_Forge 1 4126
Protoss_Photon_Cannon 2 5796
Protoss_Nexus 1 8709
Protoss_Gateway 3 12368
Protoss_Assimilator 1 7973
Protoss_Cybernetics_Core 1 9263
Protoss_Zealot 1 9623
Protoss_Citadel_of_Adun 1 10924
Protoss_Dragoon 1 10971
12368
