Protoss_Gateway 2 8704
Protoss_Forge 1 4300
Protoss_Photon_Cannon 4 7247
Protoss_Nexus 1 9777
Protoss_Assimilator 2 10957
Protoss_Cybernetics_Core 1 10425
Protoss_Zealot 1 11001
Protoss_Stargate 1 12182
Protoss_Citadel_of_Adun 1 12719
12719
