Protoss_Forge 1 4065
Protoss_Photon_Cannon 2 6162
Protoss_Nexus 1 8668
Protoss_Gateway 1 7659
Protoss_Assimilator 1 7754
Protoss_Zealot 3 12084
Protoss_Cybernetics_Core 1 9731
Protoss_Dragoon 1 11223
Protoss_Stargate 1 11830
12084
