Protoss_Nexus 1 7127
Protoss_Forge 1 6115
Protoss_Gateway 1 7035
Protoss_Assimilator 2 9260
Protoss_Photon_Cannon 1 7708
Protoss_Cybernetics_Core 1 8493
Protoss_Zealot 3 11976
Protoss_Stargate 1 10371
Protoss_Dragoon 1 10116
Protoss_Citadel_of_Adun 1 11395
Protoss_Corsair 1 11467
11976
