Protoss_Forge 1 5136
Protoss_Nexus 1 7581
Protoss_Photon_Cannon 4 11632
Protoss_Gateway 1 7887
Protoss_Assimilator 2 10313
Protoss_Cybernetics_Core 1 9506
Protoss_Zealot 2 11727
Protoss_Stargate 1 11236
Protoss_Citadel_of_Adun 1 11651
Protoss_Corsair 1 12225
12225
