Protoss_Nexus 1 6960
Protoss_Gateway 1 6140
Protoss_Forge 1 6207
Protoss_Assimilator 2 10915
Protoss_Photon_Cannon 3 9847
Protoss_Zealot 3 11253
Protoss_Cybernetics_Core 1 8835
Protoss_Stargate 1 10998
Protoss_Corsair 1 11955
11955
