Protoss_Forge 1 4066
Protoss_Photon_Cannon 2 5738
Protoss_Nexus 1 8572
Protoss_Gateway 3 12691
Protoss_Assimilator 2 10565
Protoss_Cybernetics_Core 1 9093
Protoss_Zealot 3 12283
Protoss_Stargate 1 10898
Protoss_Citadel_of_Adun 1 11629
Protoss_Corsair 1 12017
12691
