Protoss_Forge 1 4308
Protoss_Photon_Cannon 3 11164
Protoss_Nexus 1 8074
Protoss_Gateway 1 7717
Protoss_Assimilator 1 7517
Protoss_Cybernetics_Core 1 9154
Protoss_Zealot 2 11145
Protoss_Stargate 1 10976
Protoss_Corsair 1 11970
Protoss_Dragoon 1 12508
12508
