Protoss_Forge 1 4057
Protoss_Nexus 1 8010
Protoss_Gateway 2 12645
Protoss_Photon_Cannon 2 8073
Protoss_Assimilator 1 8691
Protoss_Zealot 5 12351
Protoss_Cybernetics_Core 1 10694
Protoss_Citadel_of_Adun 1 12207
12645
