Protoss_Forge 1 4499
Protoss_Photon_Cannon 2 5856
Protoss_Nexus 1 9034
Protoss_Gateway 3 12355
Protoss_Assimilator 1 8194
Protoss_Zealot 4 12046
Protoss_Cybernetics_Core 1 9905
Protoss_Citadel_of_Adun 1 11411
12355
