Protoss_Forge 1 4012
Protoss_Photon_Cannon 2 8289
Protoss_Nexus 1 8563
Protoss_Gateway 1 7509
Protoss_Assimilator 2 10512
Protoss_Zealot 1 9435
Protoss_Cybernetics_Core 1 11279
Protoss_Stargate 1 12982
Protoss_Robotics_Facility 1 13320
13320
