Protoss_Gateway 1 4149
Protoss_Assimilator 1 4420
Protoss_Zealot 6 11531
Protoss_Cybernetics_Core 1 6541
Protoss_Stargate 1 8222
Protoss_Dragoon 1 7816
Protoss_Citadel_of_Adun 1 8929
Protoss_Corsair 1 9228
Protoss_Templar_Archives 1 10624
Protoss_Forge 1 10911
Protoss_Dark_Templar 1 12183
Protoss_Photon_Cannon 1 12238
12238
