Protoss_Forge 1 4347
Protoss_Photon_Cannon 3 9960
Protoss_Nexus 1 8935
Protoss_Gateway 1 7890
Protoss_Assimilator 1 7867
Protoss_Zealot 2 11396
Protoss_Cybernetics_Core 1 11464
11464
