Protoss_Forge 1 4384
Protoss_Photon_Cannon 3 8729
Protoss_Nexus 1 9106
Protoss_Gateway 1 8148
Protoss_Assimilator 2 11029
Protoss_Zealot 3 12149
Protoss_Cybernetics_Core 1 10464
Protoss_Stargate 1 12607
Protoss_Citadel_of_Adun 1 12765
12765
