Protoss_Forge 1 4331
Protoss_Nexus 1 7550
Protoss_Photon_Cannon 2 8586
Protoss_Gateway 2 12108
Protoss_Assimilator 2 10201
Protoss_Zealot 3 11133
Protoss_Cybernetics_Core 1 9585
Protoss_Stargate 1 11457
Protoss_Citadel_of_Adun 1 12342
12342
