Protoss_Forge 1 4372
Protoss_Photon_Cannon 3 8837
Protoss_Nexus 1 8657
Protoss_Gateway 1 7782
Protoss_Assimilator 2 10151
Protoss_Zealot 1 8847
Protoss_Cybernetics_Core 1 10062
Protoss_Dragoon 2 12513
Protoss_Stargate 1 11911
Protoss_Robotics_Facility 1 13025
13025
