Protoss_Gateway 2 12058
Protoss_Zealot 6 12017
Protoss_Nexus 1 9065
Protoss_Assimilator 1 7870
Protoss_Cybernetics_Core 1 8876
Protoss_Forge 1 9084
Protoss_Photon_Cannon 1 10520
Protoss_Stargate 1 11206
Protoss_Dragoon 1 11155
Protoss_Citadel_of_Adun 1 11868
12058
