Protoss_Forge 1 4104
Protoss_Nexus 1 7615
Protoss_Gateway 3 12402
Protoss_Assimilator 1 6769
Protoss_Photon_Cannon 1 7879
Protoss_Zealot 6 11329
Protoss_Cybernetics_Core 1 11494
12402
