Protoss_Forge 1 4652
Protoss_Nexus 1 7694
Protoss_Photon_Cannon 3 12455
Protoss_Gateway 1 7684
Protoss_Assimilator 2 11628
Protoss_Cybernetics_Core 1 10113
Protoss_Zealot 3 11751
Protoss_Stargate 1 12196
12455
