Protoss_Nexus 1 7050
Protoss_Forge 1 5503
Protoss_Photon_Cannon 2 7257
Protoss_Gateway 3 12137
Protoss_Assimilator 2 10944
Protoss_Cybernetics_Core 1 9494
Protoss_Zealot 3 11590
Protoss_Citadel_of_Adun 1 10940
12137
