Protoss_Nexus 1 6950
Protoss_Gateway 2 12242
Protoss_Forge 1 6523
Protoss_Assimilator 2 10037
Protoss_Photon_Cannon 2 8524
Protoss_Zealot 3 12257
Protoss_Cybernetics_Core 1 9719
Protoss_Dragoon 1 10936
Protoss_Stargate 1 11555
Protoss_Citadel_of_Adun 1 11784
12257
