Protoss_Forge 1 4349
Protoss_Photon_Cannon 3 8498
Protoss_Nexus 1 8592
Protoss_Gateway 1 8326
Protoss_Assimilator 2 11679
Protoss_Zealot 2 10714
Protoss_Cybernetics_Core 1 10346
Protoss_Dragoon 1 11647
Protoss_Citadel_of_Adun 1 12501
12501
