Protoss_Forge 1 4641
Protoss_Photon_Cannon 2 6995
Protoss_Nexus 1 8276
Protoss_Gateway 1 7752
Protoss_Assimilator 3 12010
Protoss_Cybernetics_Core 1 9372
Protoss_Zealot 2 11370
Protoss_Stargate 1 11187
Protoss_Citadel_of_Adun 1 11702
Protoss_Corsair 1 12222
12222
