Protoss_Gateway 2 12520
Protoss_Assimilator 1 4654
Protoss_Zealot 6 11841
Protoss_Cybernetics_Core 1 7144
Protoss_Stargate 1 8854
Protoss_Forge 1 8818
Protoss_Citadel_of_Adun 1 10119
Protoss_Corsair 2 10931
12520
