Protoss_Forge 1 4125
Protoss_Photon_Cannon 3 7605
Protoss_Nexus 1 8935
Protoss_Gateway 2 12766
Protoss_Assimilator 2 10473
Protoss_Cybernetics_Core 1 9718
Protoss_Zealot 1 9394
Protoss_Dragoon 1 10924
Protoss_Stargate 1 12243
Protoss_Citadel_of_Adun 1 12599
12766
