Protoss_Forge 1 4090
Protoss_Photon_Cannon 3 9513
Protoss_Gateway 1 6485
Protoss_Nexus 2 13834
Protoss_Assimilator 1 7442
Protoss_Cybernetics_Core 1 9087
Protoss_Zealot 2 10872
Protoss_Stargate 1 11485
Protoss_Citadel_of_Adun 1 11865
13834
