Protoss_Forge 1 4609
Protoss_Nexus 1 7773
Protoss_Photon_Cannon 1 6557
Protoss_Gateway 1 7422
Protoss_Assimilator 2 9639
Protoss_Cybernetics_Core 1 9409
Protoss_Stargate 1 11137
Protoss_Citadel_of_Adun 1 10984
Protoss_Dragoon 1 11477
Protoss_Corsair 1 12081
12081
