Protoss_Gateway 2 11547
Protoss_Assimilator 1 4366
Protoss_Zealot 3 7021
Protoss_Cybernetics_Core 1 7028
Protoss_Dragoon 3 11586
Protoss_Stargate 1 9347
Protoss_Corsair 2 11818
Protoss_Citadel_of_Adun 1 12449
12449
