Protoss_Gateway 1 4171
Protoss_Zealot 4 9430
Protoss_Nexus 1 8785
Protoss_Assimilator 2 10068
Protoss_Cybernetics_Core 1 8680
Protoss_Stargate 1 10430
Protoss_Citadel_of_Adun 1 10979
Protoss_Corsair 2 12356
Protoss_Forge 1 11715
Protoss_Templar_Archives 1 12697
12697
