Protoss_Forge 1 4858
Protoss_Photon_Cannon 3 10029
Protoss_Nexus 1 9748
Protoss_Gateway 1 8865
Protoss_Assimilator 2 9305
Protoss_Zealot 2 10971
Protoss_Cybernetics_Core 1 10807
Protoss_Stargate 1 12927
Protoss_Citadel_of_Adun 1 12816
12927
