Protoss_Forge 1 3895
Protoss_Photon_Cannon 2 6227
Protoss_Nexus 1 9374
Protoss_Gateway 2 8822
Protoss_Assimilator 2 11832
Protoss_Zealot 6 12137
Protoss_Cybernetics_Core 1 10322
Protoss_Stargate 1 12378
12378
