Protoss_Forge 1 4294
Protoss_Nexus 1 7653
Protoss_Photon_Cannon 3 8028
Protoss_Gateway 1 7717
Protoss_Assimilator 2 11771
Protoss_Cybernetics_Core 1 10224
Protoss_Zealot 1 10647
Protoss_Stargate 1 12126
Protoss_Dragoon 1 11770
12126
