Protoss_Forge 1 4296
Protoss_Photon_Cannon 2 5899
Protoss_Nexus 1 8861
Protoss_Gateway 1 7916
Protoss_Assimilator 2 10267
Protoss_Cybernetics_Core 1 9778
Protoss_Zealot 3 11710
Protoss_Stargate 1 11520
Protoss_Citadel_of_Adun 1 11585
11710
