Protoss_Nexus 1 7127
Protoss_Gateway 1 6577
Protoss_Forge 1 6703
Protoss_Assimilator 2 10060
Protoss_Photon_Cannon 1 7953
Protoss_Cybernetics_Core 1 9293
Protoss_Zealot 1 9444
Protoss_Stargate 1 11046
Protoss_Dragoon 1 10810
Protoss_Citadel_of_Adun 1 11865
Protoss_Corsair 1 12298
12298
