Protoss_Forge 1 4344
Protoss_Photon_Cannon 2 12350
Protoss_Nexus 1 8409
Protoss_Gateway 1 7779
Protoss_Assimilator 2 10378
Protoss_Cybernetics_Core 1 9276
Protoss_Zealot 3 11019
Protoss_Stargate 1 11100
Protoss_Citadel_of_Adun 1 11256
Protoss_Corsair 1 12213
12350
