Protoss_Forge 1 4744
Protoss_Nexus 1 7685
Protoss_Gateway 1 6672
Protoss_Photon_Cannon 1 6841
Protoss_Assimilator 1 7109
Protoss_Zealot 3 12026
Protoss_Cybernetics_Core 1 8677
Protoss_Dragoon 1 10231
Protoss_Stargate 1 11421
12026
