Protoss_Forge 1 3948
Protoss_Nexus 1 7915
Protoss_Gateway 1 7264
Protoss_Assimilator 2 10366
Protoss_Photon_Cannon 1 7523
Protoss_Cybernetics_Core 1 8762
Protoss_Zealot 2 11490
Protoss_Dragoon 1 10254
Protoss_Stargate 1 10762
Protoss_Citadel_of_Adun 1 11524
Protoss_Corsair 1 12023
12023
