Protoss_Forge 1 4388
Protoss_Photon_Cannon 3 11647
Protoss_Nexus 1 8715
Protoss_Gateway 3 12740
Protoss_Assimilator 2 10101
Protoss_Cybernetics_Core 1 8894
Protoss_Zealot 1 8680
Protoss_Stargate 1 10641
Protoss_Citadel_of_Adun 1 11177
Protoss_Corsair 1 11607
12740
