Protoss_Forge 1 4391
Protoss_Photon_Cannon 3 12490
Protoss_Nexus 1 8897
Protoss_Gateway 1 7786
Protoss_Assimilator 1 8360
Protoss_Zealot 3 11780
Protoss_Cybernetics_Core 1 10230
Protoss_Stargate 1 12125
Protoss_Citadel_of_Adun 1 12444
12490
