Protoss_Forge 1 4714
Protoss_Photon_Cannon 2 6272
Protoss_Gateway 1 7217
Protoss_Nexus 1 9584
Protoss_Assimilator 2 11379
Protoss_Zealot 2 10068
Protoss_Cybernetics_Core 1 9918
Protoss_Stargate 1 11719
Protoss_Citadel_of_Adun 1 12529
12529
