Protoss_Gateway 2 9551
Protoss_Assimilator 1 4334
Protoss_Zealot 6 10548
Protoss_Cybernetics_Core 1 7202
Protoss_Citadel_of_Adun 1 8840
Protoss_Dragoon 1 8744
Protoss_Templar_Archives 1 10536
Protoss_High_Templar 2 11987
11987
