Protoss_Forge 1 4707
Protoss_Photon_Cannon 2 6373
Protoss_Nexus 1 9479
Protoss_Gateway 1 9007
Protoss_Assimilator 1 8614
Protoss_Zealot 2 11446
Protoss_Cybernetics_Core 1 10695
Protoss_Stargate 1 12403
Protoss_Citadel_of_Adun 1 12429
12429
