Protoss_Forge 2 5916
Protoss_Nexus 1 7247
Protoss_Gateway 2 12500
Protoss_Photon_Cannon 2 7880
Protoss_Zealot 4 11367
Protoss_Assimilator 2 10195
Protoss_Cybernetics_Core 1 10066
Protoss_Stargate 1 11890
Protoss_Citadel_of_Adun 1 12488
Protoss_Dragoon 1 12487
12500
