Protoss_Forge 1 4281
Protoss_Photon_Cannon 2 7634
Protoss_Nexus 1 8159
Protoss_Gateway 2 12810
Protoss_Assimilator 2 11192
Protoss_Cybernetics_Core 1 9327
Protoss_Zealot 3 11531
Protoss_Stargate 1 11077
Protoss_Citadel_of_Adun 1 11497
Protoss_Corsair 1 12049
12810
