Protoss_Nexus 1 7176
Protoss_Gateway 1 6336
Protoss_Forge 1 6443
Protoss_Assimilator 2 9885
Protoss_Photon_Cannon 1 7734
Protoss_Cybernetics_Core 1 8367
Protoss_Zealot 2 11513
Protoss_Dragoon 1 9674
Protoss_Stargate 1 10235
Protoss_Citadel_of_Adun 1 11549
Protoss_Corsair 2 12190
12190
