Protoss_Gateway 2 5033
Protoss_Zealot 6 9968
Protoss_Nexus 1 9290
Protoss_Assimilator 1 7568
Protoss_Cybernetics_Core 1 9315
Protoss_Stargate 1 11124
Protoss_Dragoon 2 11319
Protoss_Citadel_of_Adun 1 12326
Protoss_Corsair 1 12169
12326
