Protoss_Gateway 2 4700
Protoss_Zealot 7 12362
Protoss_Assimilator 1 6670
Protoss_Cybernetics_Core 1 8215
Protoss_Stargate 1 9944
Protoss_Corsair 2 11821
Protoss_Nexus 1 13212
13212
