Protoss_Forge 1 3876
Protoss_Nexus 1 7459
Protoss_Photon_Cannon 2 8346
Protoss_Gateway 2 12536
Protoss_Assimilator 1 7337
Protoss_Zealot 3 11560
Protoss_Cybernetics_Core 1 10457
Protoss_Stargate 1 12167
12536
