Protoss_Forge 1 4864
Protoss_Photon_Cannon 3 9088
Protoss_Nexus 1 8241
Protoss_Gateway 1 7214
Protoss_Zealot 3 10676
Protoss_Assimilator 2 11562
Protoss_Cybernetics_Core 1 11016
Protoss_Dragoon 1 12250
12250
