Protoss_Forge 1 4821
Protoss_Photon_Cannon 2 6247
Protoss_Nexus 1 8876
Protoss_Gateway 1 7793
Protoss_Assimilator 2 9765
Protoss_Cybernetics_Core 1 9427
Protoss_Zealot 2 11827
Protoss_Stargate 1 11245
Protoss_Citadel_of_Adun 1 11382
Protoss_Corsair 1 12260
12260
