Protoss_Forge 1 4262
Protoss_Nexus 1 7536
Protoss_Photon_Cannon 1 6294
Protoss_Gateway 1 7331
Protoss_Assimilator 2 10311
Protoss_Zealot 4 11906
Protoss_Cybernetics_Core 1 9470
Protoss_Stargate 1 11501
Protoss_Citadel_of_Adun 1 11774
11906
