Protoss_Forge 1 4811
Protoss_Nexus 1 7702
Protoss_Photon_Cannon 2 6873
Protoss_Gateway 1 7855
Protoss_Assimilator 2 11976
Protoss_Zealot 2 11276
Protoss_Cybernetics_Core 1 10082
Protoss_Stargate 1 11939
Protoss_Citadel_of_Adun 1 12119
12119
