Protoss_Gateway 2 4928
Protoss_Zealot 6 11391
Protoss_Nexus 1 9505
Protoss_Assimilator 1 8124
Protoss_Cybernetics_Core 1 9691
Protoss_Stargate 1 11470
Protoss_Dragoon 1 11392
Protoss_Forge 1 11809
11809
