Protoss_Forge 1 3828
Protoss_Nexus 1 7755
Protoss_Gateway 1 6871
Protoss_Assimilator 2 10088
Protoss_Photon_Cannon 1 7591
Protoss_Cybernetics_Core 1 8661
Protoss_Zealot 2 11600
Protoss_Stargate 1 10431
Protoss_Dragoon 1 10634
Protoss_Citadel_of_Adun 1 11028
Protoss_Corsair 1 11756
11756
