Protoss_Forge 2 6498
Protoss_Gateway 2 8509
Protoss_Photon_Cannon 2 7814
Protoss_Nexus 1 9608
Protoss_Assimilator 2 9986
Protoss_Cybernetics_Core 1 10003
Protoss_Zealot 3 11391
Protoss_Stargate 1 11825
Protoss_Dragoon 1 11653
11825
