Protoss_Forge 1 5159
Protoss_Photon_Cannon 2 7274
Protoss_Nexus 1 8510
Protoss_Gateway 1 7943
Protoss_Assimilator 2 11633
Protoss_Cybernetics_Core 1 9525
Protoss_Zealot 3 12222
Protoss_Stargate 1 11374
Protoss_Dragoon 1 11360
Protoss_Citadel_of_Adun 1 11894
12222
