Protoss_Forge 2 10594
Protoss_Photon_Cannon 3 12001
Protoss_Gateway 2 7512
Protoss_Zealot 3 9154
Protoss_Nexus 1 11961
Protoss_Assimilator 1 10271
Protoss_Cybernetics_Core 1 12438
12438
