Protoss_Forge 1 4312
Protoss_Photon_Cannon 4 12553
Protoss_Nexus 1 8839
Protoss_Gateway 1 8136
Protoss_Assimilator 1 8061
Protoss_Zealot 3 11982
Protoss_Cybernetics_Core 1 11373
12553
