Protoss_Forge 1 3765
Protoss_Photon_Cannon 2 6031
Protoss_Nexus 1 8853
Protoss_Gateway 2 12277
Protoss_Assimilator 2 10397
Protoss_Zealot 4 11816
Protoss_Cybernetics_Core 1 9449
Protoss_Citadel_of_Adun 1 10968
Protoss_Templar_Archives 1 12465
12465
