Protoss_Gateway 2 8175
Protoss_Assimilator 1 4400
Protoss_Zealot 11 12231
Protoss_Cybernetics_Core 1 5903
Protoss_Stargate 1 7660
Protoss_Dragoon 1 7471
Protoss_Corsair 1 8771
12231
