Protoss_Forge 1 4172
Protoss_Photon_Cannon 2 5577
Protoss_Nexus 1 8610
Protoss_Gateway 2 12690
Protoss_Assimilator 2 10928
Protoss_Cybernetics_Core 1 9548
Protoss_Zealot 2 11314
Protoss_Citadel_of_Adun 1 11052
12690
