Protoss_Forge 1 4905
Protoss_Nexus 1 7445
Protoss_Photon_Cannon 2 6800
Protoss_Gateway 1 7802
Protoss_Assimilator 2 9718
Protoss_Cybernetics_Core 1 9348
Protoss_Zealot 2 11486
Protoss_Stargate 1 11028
Protoss_Dragoon 1 10585
Protoss_Citadel_of_Adun 1 11584
Protoss_Corsair 1 11979
11979
