Protoss_Forge 1 4542
Protoss_Photon_Cannon 2 6017
Protoss_Nexus 1 8875
Protoss_Gateway 1 7837
Protoss_Assimilator 2 11098
Protoss_Cybernetics_Core 1 9348
Protoss_Zealot 3 11929
Protoss_Stargate 1 11132
Protoss_Dragoon 1 11068
Protoss_Citadel_of_Adun 1 12116
Protoss_Corsair 1 12087
12116
