Protoss_Forge 1 4511
Protoss_Photon_Cannon 2 6022
Protoss_Nexus 1 9139
Protoss_Gateway 1 8464
Protoss_Assimilator 2 11639
Protoss_Zealot 1 10495
Protoss_Cybernetics_Core 1 11336
Protoss_Stargate 1 13042
13042
