Protoss_Forge 1 4170
Protoss_Nexus 1 7418
Protoss_Gateway 1 6713
Protoss_Assimilator 2 9405
Protoss_Photon_Cannon 2 12521
Protoss_Cybernetics_Core 1 8674
Protoss_Zealot 3 11967
Protoss_Stargate 1 10513
Protoss_Citadel_of_Adun 1 11221
Protoss_Corsair 1 11484
12521
