Protoss_Forge 1 4331
Protoss_Nexus 1 7833
Protoss_Photon_Cannon 1 6470
Protoss_Gateway 1 7416
Protoss_Assimilator 1 8117
Protoss_Zealot 4 11712
Protoss_Cybernetics_Core 1 9564
Protoss_Stargate 1 11394
Protoss_Citadel_of_Adun 1 12576
12576
