Protoss_Forge 1 4435
Protoss_Photon_Cannon 2 6209
Protoss_Nexus 1 9426
Protoss_Gateway 2 12489
Protoss_Assimilator 2 10758
Protoss_Cybernetics_Core 1 9608
Protoss_Zealot 3 11072
Protoss_Stargate 1 11378
Protoss_Citadel_of_Adun 1 12031
12489
