Protoss_Forge 1 4812
Protoss_Nexus 1 7666
Protoss_Photon_Cannon 3 11477
Protoss_Gateway 2 12219
Protoss_Assimilator 2 11376
Protoss_Cybernetics_Core 1 9241
Protoss_Zealot 3 12140
Protoss_Stargate 1 10944
Protoss_Citadel_of_Adun 1 11287
Protoss_Corsair 1 11897
12219
