Protoss_Gateway 1 4167
Protoss_Assimilator 1 4391
Protoss_Zealot 5 10691
Protoss_Cybernetics_Core 1 7253
Protoss_Stargate 1 9378
Protoss_Dragoon 1 8905
Protoss_Citadel_of_Adun 1 9504
Protoss_Corsair 2 11200
Protoss_Templar_Archives 1 11527
Protoss_Forge 1 12191
12191
