Protoss_Gateway 1 4196
Protoss_Assimilator 1 4416
Protoss_Zealot 6 10059
Protoss_Cybernetics_Core 1 6741
Protoss_Dragoon 1 7939
Protoss_Stargate 1 8813
Protoss_Citadel_of_Adun 1 9554
Protoss_Corsair 3 11792
Protoss_Templar_Archives 1 11455
11792
