Protoss_Gateway 3 12794
Protoss_Zealot 6 11891
Protoss_Nexus 1 8417
Protoss_Assimilator 2 11260
Protoss_Forge 1 7962
Protoss_Cybernetics_Core 1 9011
Protoss_Photon_Cannon 1 9230
Protoss_Stargate 1 10850
Protoss_Citadel_of_Adun 1 11401
Protoss_Corsair 1 11844
12794
