Protoss_Gateway 2 4773
Protoss_Zealot 7 10782
Protoss_Assimilator 1 5737
Protoss_Cybernetics_Core 1 6880
Protoss_Stargate 1 8737
Protoss_Dragoon 1 8954
Protoss_Corsair 2 11437
11437
