Protoss_Forge 1 3637
Protoss_Photon_Cannon 2 5568
Protoss_Nexus 1 8434
Protoss_Gateway 2 12681
Protoss_Assimilator 2 11016
Protoss_Cybernetics_Core 1 9046
Protoss_Zealot 4 12137
Protoss_Stargate 1 10786
Protoss_Corsair 1 11721
Protoss_Citadel_of_Adun 1 12506
12681
