Protoss_Forge 1 4870
Protoss_Nexus 1 7544
Protoss_Photon_Cannon 3 12464
Protoss_Gateway 1 7711
Protoss_Assimilator 2 10031
Protoss_Zealot 3 10773
Protoss_Cybernetics_Core 1 10395
Protoss_Stargate 1 12204
Protoss_Dragoon 1 11893
12464
