Protoss_Forge 1 4027
Protoss_Nexus 1 7528
Protoss_Gateway 1 6807
Protoss_Photon_Cannon 2 10020
Protoss_Assimilator 2 10553
Protoss_Cybernetics_Core 1 9195
Protoss_Zealot 2 11815
Protoss_Citadel_of_Adun 1 10714
Protoss_Templar_Archives 1 12204
12204
