Protoss_Forge 1 4527
Protoss_Photon_Cannon 2 5823
Protoss_Nexus 1 8838
Protoss_Gateway 1 7697
Protoss_Assimilator 2 10034
Protoss_Cybernetics_Core 1 9160
Protoss_Zealot 2 9752
Protoss_Stargate 1 11192
Protoss_Citadel_of_Adun 1 11515
Protoss_Corsair 1 12222
12222
