Protoss_Forge 1 4662
Protoss_Photon_Cannon 2 6028
Protoss_Nexus 1 9150
Protoss_Gateway 1 8051
Protoss_Assimilator 2 11297
Protoss_Cybernetics_Core 1 9569
Protoss_Zealot 4 11906
Protoss_Stargate 1 11481
Protoss_Citadel_of_Adun 1 12012
12012
