Protoss_Forge 1 4281
Protoss_Nexus 1 7657
Protoss_Photon_Cannon 2 12284
Protoss_Gateway 1 7416
Protoss_Assimilator 2 10170
Protoss_Cybernetics_Core 1 9138
Protoss_Zealot 2 10662
Protoss_Stargate 1 10818
Protoss_Citadel_of_Adun 1 11009
Protoss_Corsair 1 11759
Protoss_Templar_Archives 1 12605
12605
