Protoss_Forge 1 4255
Protoss_Nexus 1 7799
Protoss_Photon_Cannon 2 7026
Protoss_Gateway 1 7837
Protoss_Assimilator 2 11013
Protoss_Cybernetics_Core 1 9659
Protoss_Zealot 3 11218
Protoss_Stargate 1 11400
Protoss_Citadel_of_Adun 1 12181
Protoss_Corsair 1 12351
12351
