Protoss_Forge 1 4218
Protoss_Photon_Cannon 1 5697
Protoss_Nexus 1 8051
Protoss_Gateway 1 7401
Protoss_Assimilator 2 11688
Protoss_Cybernetics_Core 1 9207
Protoss_Zealot 3 11835
Protoss_Stargate 1 11059
Protoss_Citadel_of_Adun 1 12340
Protoss_Corsair 1 12032
12340
