Protoss_Forge 1 4050
Protoss_Photon_Cannon 1 5524
Protoss_Nexus 1 8349
Protoss_Gateway 1 7378
Protoss_Assimilator 2 11762
Protoss_Zealot 2 10114
Protoss_Cybernetics_Core 1 9852
Protoss_Dragoon 1 11268
Protoss_Stargate 1 11892
11892
