Protoss_Forge 1 4788
Protoss_Nexus 1 7597
Protoss_Photon_Cannon 2 7711
Protoss_Gateway 1 7603
Protoss_Assimilator 2 10322
Protoss_Cybernetics_Core 1 9052
Protoss_Zealot 3 11838
Protoss_Stargate 1 10791
Protoss_Citadel_of_Adun 1 12182
Protoss_Corsair 1 11847
12182
