Protoss_Forge 1 4804
Protoss_Nexus 1 7677
Protoss_Photon_Cannon 1 6490
Protoss_Gateway 1 7344
Protoss_Assimilator 2 9648
Protoss_Cybernetics_Core 1 8894
Protoss_Zealot 3 11654
Protoss_Stargate 1 10800
Protoss_Citadel_of_Adun 1 11961
Protoss_Corsair 1 11777
11961
