Protoss_Forge 1 4451
Protoss_Photon_Cannon 2 6505
Protoss_Nexus 1 8677
Protoss_Gateway 1 7679
Protoss_Assimilator 2 9662
Protoss_Cybernetics_Core 1 9675
Protoss_Zealot 2 11159
Protoss_Stargate 1 11514
Protoss_Citadel_of_Adun 1 12260
12260
