Protoss_Forge 1 4489
Protoss_Photon_Cannon 2 5973
Protoss_Nexus 1 8826
Protoss_Gateway 2 12769
Protoss_Assimilator 1 7832
Protoss_Cybernetics_Core 1 9463
Protoss_Zealot 2 11672
Protoss_Dragoon 1 10705
Protoss_Citadel_of_Adun 2 12119
12769
