Protoss_Forge 1 4619
Protoss_Nexus 1 7702
Protoss_Photon_Cannon 2 6885
Protoss_Gateway 1 7875
Protoss_Assimilator 2 10937
Protoss_Cybernetics_Core 1 9409
Protoss_Zealot 2 10694
Protoss_Stargate 1 11245
Protoss_Citadel_of_Adun 1 11938
Protoss_Corsair 1 12184
12184
