Protoss_Nexus 1 7143
Protoss_Gateway 1 6672
Protoss_Forge 1 6552
Protoss_Assimilator 1 7075
Protoss_Photon_Cannon 2 8622
Protoss_Zealot 3 10682
Protoss_Cybernetics_Core 1 10249
Protoss_Citadel_of_Adun 1 12045
Protoss_Dragoon 1 11840
12045
