Protoss_Forge 1 4114
Protoss_Photon_Cannon 2 6102
Protoss_Nexus 1 8752
Protoss_Gateway 2 12238
Protoss_Assimilator 2 10485
Protoss_Cybernetics_Core 1 9239
Protoss_Zealot 3 12274
Protoss_Stargate 1 11023
Protoss_Citadel_of_Adun 1 11772
Protoss_Corsair 1 11976
12274
