Protoss_Gateway 2 9263
Protoss_Assimilator 1 4394
Protoss_Cybernetics_Core 1 5633
Protoss_Zealot 9 11756
Protoss_Stargate 1 7475
Protoss_Dragoon 1 7315
Protoss_Corsair 1 8426
Protoss_Citadel_of_Adun 1 11491
Protoss_Forge 1 12231
12231
