Protoss_Forge 1 3970
Protoss_Nexus 1 7623
Protoss_Gateway 1 6795
Protoss_Assimilator 3 10332
Protoss_Photon_Cannon 1 7672
Protoss_Zealot 4 12216
Protoss_Cybernetics_Core 1 9368
Protoss_Stargate 1 11251
Protoss_Dragoon 1 11132
Protoss_Citadel_of_Adun 1 12437
12437
