Protoss_Gateway 2 4770
Protoss_Zealot 6 7635
Protoss_Nexus 1 11059
Protoss_Assimilator 1 9509
Protoss_Cybernetics_Core 1 10808
Protoss_Forge 1 11007
Protoss_Stargate 1 12812
Protoss_Photon_Cannon 2 12490
12812
