Protoss_Forge 1 4884
Protoss_Nexus 1 7553
Protoss_Photon_Cannon 2 6751
Protoss_Gateway 1 8149
Protoss_Assimilator 2 9693
Protoss_Cybernetics_Core 1 9590
Protoss_Zealot 2 11566
Protoss_Stargate 2 11889
11889
