Protoss_Forge 1 4650
Protoss_Nexus 1 7465
Protoss_Photon_Cannon 2 6620
Protoss_Gateway 1 7501
Protoss_Assimilator 2 9951
Protoss_Zealot 4 11379
Protoss_Cybernetics_Core 1 9263
Protoss_Stargate 1 10982
Protoss_Robotics_Facility 1 12114
Protoss_Corsair 1 11926
12114
