Protoss_Forge 1 4736
Protoss_Nexus 1 7689
Protoss_Photon_Cannon 2 6748
Protoss_Gateway 1 7833
Protoss_Assimilator 2 10047
Protoss_Cybernetics_Core 1 9307
Protoss_Zealot 3 12289
Protoss_Stargate 1 11210
Protoss_Dragoon 1 10991
Protoss_Citadel_of_Adun 1 11941
Protoss_Corsair 1 12198
12289
