Protoss_Forge 1 4283
Protoss_Photon_Cannon 2 7310
Protoss_Nexus 1 8051
Protoss_Gateway 1 7149
Protoss_Assimilator 2 12080
Protoss_Zealot 4 11794
Protoss_Cybernetics_Core 1 10114
Protoss_Stargate 1 12000
Protoss_Dragoon 1 11978
12080
