Protoss_Forge 1 4363
Protoss_Photon_Cannon 2 6208
Protoss_Nexus 1 9122
Protoss_Gateway 1 8007
Protoss_Assimilator 2 9718
Protoss_Cybernetics_Core 1 9566
Protoss_Zealot 1 9157
Protoss_Stargate 1 11369
Protoss_Dragoon 1 11237
Protoss_Robotics_Facility 1 12812
12812
