Protoss_Forge 1 4755
Protoss_Nexus 1 7631
Protoss_Photon_Cannon 1 6311
Protoss_Gateway 1 7460
Protoss_Assimilator 2 9930
Protoss_Zealot 4 12064
Protoss_Cybernetics_Core 1 9520
Protoss_Stargate 1 11271
Protoss_Citadel_of_Adun 1 12162
Protoss_Dragoon 1 12420
Protoss_Corsair 1 12239
12420
