Protoss_Forge 1 4350
Protoss_Nexus 1 7617
Protoss_Photon_Cannon 2 6768
Protoss_Gateway 2 12469
Protoss_Assimilator 2 9236
Protoss_Cybernetics_Core 1 9424
Protoss_Zealot 2 11651
Protoss_Stargate 1 11138
Protoss_Dragoon 1 10790
Protoss_Citadel_of_Adun 1 11717
Protoss_Corsair 1 12154
12469
