Protoss_Forge 1 4575
Protoss_Nexus 1 7612
Protoss_Photon_Cannon 2 6771
Protoss_Gateway 1 7780
Protoss_Assimilator 2 9972
Protoss_Cybernetics_Core 1 9453
Protoss_Zealot 2 12222
Protoss_Stargate 1 11383
Protoss_Dragoon 1 11255
Protoss_Robotics_Facility 1 12535
12535
