Protoss_Forge 1 4313
Protoss_Nexus 1 7896
Protoss_Gateway 1 6974
Protoss_Assimilator 2 10577
Protoss_Photon_Cannon 1 8035
Protoss_Cybernetics_Core 1 8925
Protoss_Zealot 4 12315
Protoss_Stargate 1 10664
Protoss_Citadel_of_Adun 1 11335
Protoss_Corsair 1 11654
12315
