Protoss_Forge 1 4867
Protoss_Nexus 1 7817
Protoss_Photon_Cannon 1 6560
Protoss_Gateway 1 7413
Protoss_Assimilator 2 11651
Protoss_Cybernetics_Core 1 9394
Protoss_Zealot 2 10214
Protoss_Stargate 1 11217
Protoss_Citadel_of_Adun 1 11494
Protoss_Dragoon 1 11586
11651
