Protoss_Forge 1 4191
Protoss_Photon_Cannon 2 6159
Protoss_Nexus 1 8654
Protoss_Gateway 1 7621
Protoss_Assimilator 2 9656
Protoss_Cybernetics_Core 1 9100
Protoss_Zealot 3 10884
Protoss_Stargate 1 10847
Protoss_Citadel_of_Adun 1 12153
Protoss_Corsair 1 11862
12153
