Protoss_Forge 1 4371
Protoss_Nexus 1 7574
Protoss_Photon_Cannon 1 6171
Protoss_Gateway 2 12706
Protoss_Assimilator 2 10255
Protoss_Cybernetics_Core 1 8458
Protoss_Zealot 4 12020
Protoss_Stargate 1 10569
Protoss_Citadel_of_Adun 1 11172
Protoss_Corsair 1 11686
Protoss_Templar_Archives 1 12798
12798
