Protoss_Nexus 1 6600
Protoss_Forge 1 5175
Protoss_Photon_Cannon 1 6423
Protoss_Gateway 2 12669
Protoss_Assimilator 2 9238
Protoss_Cybernetics_Core 1 8594
Protoss_Zealot 4 11604
Protoss_Stargate 1 10387
Protoss_Citadel_of_Adun 1 11528
Protoss_Corsair 1 11361
12669
