Protoss_Forge 1 4242
Protoss_Photon_Cannon 1 5965
Protoss_Nexus 1 8301
Protoss_Gateway 1 7114
Protoss_Assimilator 2 9567
Protoss_Cybernetics_Core 1 8859
Protoss_Zealot 2 10275
Protoss_Stargate 1 10692
Protoss_Citadel_of_Adun 1 12059
Protoss_Corsair 1 11780
12059
