Protoss_Forge 1 4335
Protoss_Photon_Cannon 2 8047
Protoss_Nexus 1 8472
Protoss_Gateway 2 12633
Protoss_Zealot 3 10738
Protoss_Assimilator 2 10587
Protoss_Cybernetics_Core 1 10009
Protoss_Stargate 1 11847
Protoss_Citadel_of_Adun 1 12091
12633
