Protoss_Forge 1 4599
Protoss_Nexus 1 7569
Protoss_Photon_Cannon 2 6651
Protoss_Gateway 1 7540
Protoss_Assimilator 2 11246
Protoss_Cybernetics_Core 1 9011
Protoss_Zealot 3 11683
Protoss_Stargate 1 10955
Protoss_Corsair 1 11914
Protoss_Citadel_of_Adun 1 12535
12535
