Protoss_Forge 1 4110
Protoss_Nexus 1 7691
Protoss_Gateway 2 12756
Protoss_Photon_Cannon 2 11969
Protoss_Assimilator 2 10733
Protoss_Cybernetics_Core 1 8844
Protoss_Zealot 3 11566
Protoss_Stargate 1 11090
Protoss_Citadel_of_Adun 1 11709
Protoss_Corsair 1 12034
12756
