Protoss_Forge 1 4327
Protoss_Photon_Cannon 2 5871
Protoss_Nexus 1 9085
Protoss_Assimilator 2 10205
Protoss_Gateway 1 8439
Protoss_Zealot 3 12005
Protoss_Cybernetics_Core 1 10043
Protoss_Stargate 1 11807
Protoss_Citadel_of_Adun 1 11923
12005
