Protoss_Nexus 1 7176
Protoss_Forge 1 6438
Protoss_Gateway 2 11926
Protoss_Photon_Cannon 1 7989
Protoss_Assimilator 2 9651
Protoss_Cybernetics_Core 1 9334
Protoss_Zealot 3 11537
Protoss_Stargate 1 11150
Protoss_Citadel_of_Adun 1 12024
Protoss_Corsair 1 12084
12084
