Protoss_Forge 1 3873
Protoss_Nexus 1 7629
Protoss_Gateway 4 12062
Protoss_Assimilator 1 6773
Protoss_Photon_Cannon 1 7924
Protoss_Cybernetics_Core 1 8648
Protoss_Zealot 3 10530
Protoss_Stargate 1 10550
Protoss_Corsair 1 11490
12062
