Protoss_Forge 1 4410
Protoss_Photon_Cannon 1 6215
Protoss_Nexus 1 8097
Protoss_Gateway 2 12593
Protoss_Assimilator 2 9497
Protoss_Cybernetics_Core 1 8711
Protoss_Zealot 3 11069
Protoss_Stargate 1 10655
Protoss_Citadel_of_Adun 1 11227
Protoss_Corsair 1 11592
Protoss_Templar_Archives 1 12760
12760
