Protoss_Nexus 1 6862
Protoss_Gateway 1 6075
Protoss_Forge 1 6190
Protoss_Assimilator 2 10316
Protoss_Photon_Cannon 3 12483
Protoss_Cybernetics_Core 1 9020
Protoss_Zealot 2 12093
Protoss_Stargate 1 10718
Protoss_Corsair 1 11651
12483
