Protoss_Forge 1 4349
Protoss_Photon_Cannon 2 5829
Protoss_Nexus 1 8718
Protoss_Gateway 1 7697
Protoss_Assimilator 2 11227
Protoss_Cybernetics_Core 1 9143
Protoss_Zealot 4 11373
Protoss_Stargate 1 10876
Protoss_Corsair 1 11879
Protoss_Citadel_of_Adun 1 12716
12716
