Protoss_Forge 1 4249
Protoss_Nexus 1 7863
Protoss_Gateway 1 7013
Protoss_Assimilator 2 11127
Protoss_Cybernetics_Core 1 8509
Protoss_Photon_Cannon 2 12219
Protoss_Zealot 4 11695
Protoss_Stargate 1 10515
Protoss_Citadel_of_Adun 1 11475
Protoss_Corsair 1 11549
12219
