Protoss_Nexus 1 6933
Protoss_Forge 1 5977
Protoss_Gateway 1 7044
Protoss_Assimilator 2 10442
Protoss_Photon_Cannon 3 12581
Protoss_Cybernetics_Core 1 8581
Protoss_Zealot 4 11958
Protoss_Stargate 1 10279
Protoss_Citadel_of_Adun 1 11187
Protoss_Corsair 1 11320
12581
