Protoss_Forge 1 4862
Protoss_Nexus 1 7713
Protoss_Photon_Cannon 2 6803
Protoss_Gateway 1 7688
Protoss_Assimilator 2 10293
Protoss_Cybernetics_Core 1 9131
Protoss_Zealot 3 11626
Protoss_Stargate 1 10867
Protoss_Corsair 1 11803
11803
