Protoss_Forge 1 4833
Protoss_Nexus 1 7852
Protoss_Photon_Cannon 1 6616
Protoss_Gateway 3 11979
Protoss_Assimilator 1 7454
Protoss_Cybernetics_Core 1 9184
Protoss_Zealot 3 11610
Protoss_Citadel_of_Adun 1 11101
Protoss_Stargate 1 12720
12720
