Protoss_Forge 1 4378
Protoss_Photon_Cannon 1 5692
Protoss_Nexus 1 8299
Protoss_Gateway 1 7366
Protoss_Assimilator 2 11863
Protoss_Zealot 5 12295
Protoss_Cybernetics_Core 1 9419
Protoss_Stargate 1 11214
Protoss_Citadel_of_Adun 1 11944
Protoss_Corsair 1 12152
12295
