Protoss_Forge 1 4371
Protoss_Photon_Cannon 3 5881
Protoss_Nexus 1 8823
Protoss_Gateway 1 7829
Protoss_Assimilator 2 10767
Protoss_Cybernetics_Core 1 9304
Protoss_Zealot 3 10855
Protoss_Stargate 1 10993
Protoss_Citadel_of_Adun 1 11970
Protoss_Corsair 1 12014
Protoss_Dragoon 1 12516
12516
