Protoss_Forge 1 4567
Protoss_Photon_Cannon 2 6294
Protoss_Nexus 1 8942
Protoss_Gateway 1 7875
Protoss_Assimilator 2 10672
Protoss_Zealot 2 11557
Protoss_Cybernetics_Core 1 9418
Protoss_Dragoon 1 10696
Protoss_Stargate 1 11435
Protoss_Citadel_of_Adun 1 12781
12781
