Protoss_Forge 1 4846
Protoss_Photon_Cannon 1 6118
Protoss_Nexus 1 8340
Protoss_Gateway 3 11982
Protoss_Assimilator 2 10062
Protoss_Cybernetics_Core 1 9222
Protoss_Zealot 3 12166
Protoss_Dragoon 1 10424
Protoss_Citadel_of_Adun 1 11219
12166
