Protoss_Nexus 1 7053
Protoss_Forge 1 5752
Protoss_Gateway 1 6984
Protoss_Photon_Cannon 1 7046
Protoss_Assimilator 2 9408
Protoss_Cybernetics_Core 1 8868
Protoss_Zealot 3 11388
Protoss_Stargate 1 10829
Protoss_Citadel_of_Adun 1 11797
Protoss_Corsair 1 11871
11871
