Protoss_Gateway 1 4142
Protoss_Assimilator 1 4306
Protoss_Cybernetics_Core 1 5692
Protoss_Zealot 4 11549
Protoss_Stargate 1 7614
Protoss_Dragoon 1 7631
Protoss_Corsair 1 8607
Protoss_Citadel_of_Adun 1 9753
Protoss_Templar_Archives 1 11970
11970
