Protoss_Forge 1 4278
Protoss_Photon_Cannon 2 5902
Protoss_Nexus 1 8790
Protoss_Gateway 1 7793
Protoss_Assimilator 2 10403
Protoss_Zealot 3 10829
Protoss_Cybernetics_Core 1 9416
Protoss_Stargate 1 11206
Protoss_Citadel_of_Adun 1 11911
Protoss_Corsair 1 12272
12272
