Protoss_Forge 1 4489
Protoss_Photon_Cannon 3 7956
Protoss_Nexus 1 8738
Protoss_Gateway 1 7837
Protoss_Assimilator 2 10600
Protoss_Zealot 3 11528
Protoss_Cybernetics_Core 1 10198
Protoss_Stargate 1 11986
11986
