Protoss_Forge 1 4201
Protoss_Nexus 1 7670
Protoss_Gateway 1 7243
Protoss_Assimilator 2 9225
Protoss_Photon_Cannon 1 7784
Protoss_Zealot 4 11651
Protoss_Cybernetics_Core 1 9090
Protoss_Stargate 1 10824
Protoss_Citadel_of_Adun 1 11554
Protoss_Corsair 1 11774
11774
