Protoss_Gateway 1 4217
Protoss_Zealot 6 10603
Protoss_Nexus 1 9422
Protoss_Assimilator 2 11759
Protoss_Cybernetics_Core 1 10114
Protoss_Forge 1 10287
Protoss_Stargate 1 12334
Protoss_Photon_Cannon 1 11962
Protoss_Dragoon 1 12335
12335
