Protoss_Forge 1 4376
Protoss_Photon_Cannon 2 5653
Protoss_Nexus 1 9006
Protoss_Gateway 2 12804
Protoss_Assimilator 2 9934
Protoss_Cybernetics_Core 1 9187
Protoss_Zealot 4 11868
Protoss_Stargate 1 10961
Protoss_Citadel_of_Adun 1 11759
Protoss_Corsair 1 11914
12804
