Protoss_Forge 1 4851
Protoss_Photon_Cannon 2 6522
Protoss_Nexus 1 9075
Protoss_Gateway 1 7848
Protoss_Assimilator 2 11288
Protoss_Cybernetics_Core 1 9431
Protoss_Zealot 2 11607
Protoss_Dragoon 1 10631
Protoss_Stargate 1 11456
Protoss_Citadel_of_Adun 1 12614
12614
