Protoss_Forge 1 4066
Protoss_Photon_Cannon 2 8249
Protoss_Nexus 1 8106
Protoss_Gateway 1 7375
Protoss_Assimilator 2 11168
Protoss_Zealot 3 11777
Protoss_Cybernetics_Core 1 10447
Protoss_Stargate 1 12155
Protoss_Citadel_of_Adun 1 12768
12768
