Protoss_Forge 1 4657
Protoss_Nexus 1 7694
Protoss_Photon_Cannon 2 7184
Protoss_Gateway 1 7989
Protoss_Assimilator 2 9687
Protoss_Cybernetics_Core 1 9719
Protoss_Zealot 3 11789
Protoss_Stargate 1 11520
Protoss_Robotics_Facility 1 12573
12573
