Protoss_Nexus 1 6884
Protoss_Forge 1 5443
Protoss_Photon_Cannon 2 7002
Protoss_Gateway 1 7893
Protoss_Assimilator 2 9825
Protoss_Cybernetics_Core 1 9349
Protoss_Zealot 3 11402
Protoss_Stargate 1 11090
Protoss_Citadel_of_Adun 1 11450
Protoss_Corsair 1 12078
12078
