Protoss_Forge 1 4316
Protoss_Nexus 1 7855
Protoss_Gateway 1 7249
Protoss_Assimilator 2 9449
Protoss_Photon_Cannon 1 7889
Protoss_Cybernetics_Core 1 8806
Protoss_Zealot 4 12134
Protoss_Stargate 1 10610
Protoss_Citadel_of_Adun 1 11080
Protoss_Corsair 1 11619
12134
