Protoss_Gateway 2 12563
Protoss_Assimilator 1 4467
Protoss_Cybernetics_Core 1 5813
Protoss_Robotics_Facility 1 7988
Protoss_Dragoon 3 11524
Protoss_Zealot 1 8603
Protoss_Shuttle 1 9406
Protoss_Observatory 1 9246
Protoss_Observer 2 11600
Protoss_Stargate 1 11421
12563
