Protoss_Gateway 3 14519
Protoss_Zealot 5 7780
Protoss_Assimilator 1 8136
Protoss_Cybernetics_Core 1 9153
Protoss_Dragoon 6 14905
Protoss_Robotics_Facility 1 12505
Protoss_Observatory 1 13633
Protoss_Observer 1 15134
15134
