Protoss_Gateway 3 13938
Protoss_Assimilator 2 15116
Protoss_Cybernetics_Core 1 6084
Protoss_Dragoon 7 14071
Protoss_Robotics_Facility 1 8701
Protoss_Nexus 1 11978
Protoss_Observatory 1 10124
Protoss_Observer 3 15222
Singularity_Charge 1 13362
Protoss_Citadel_of_Adun 1 15643
15643
