Protoss_Gateway 2 10612
Protoss_Assimilator 1 4630
Protoss_Cybernetics_Core 1 5948
Protoss_Dragoon 10 15774
Protoss_Robotics_Facility 1 8821
Protoss_Observatory 1 9613
Protoss_Observer 2 12822
Protoss_Zealot 1 11007
Singularity_Charge 1 13201
Protoss_Shuttle 1 15099
15774
