Protoss_Assimilator 2 7505
Protoss_Gateway 3 15511
Protoss_Cybernetics_Core 1 6232
Protoss_Robotics_Facility 1 8206
Protoss_Dragoon 9 15124
Protoss_Observatory 1 9129
Protoss_Observer 2 11091
Singularity_Charge 1 11087
Protoss_Shuttle 2 13950
Protoss_Zealot 2 13454
15511
