Protoss_Assimilator 1 3583
Protoss_Gateway 3 13164
Protoss_Cybernetics_Core 1 6334
Protoss_Dragoon 12 15617
Protoss_Robotics_Facility 1 8900
Protoss_Observatory 1 9748
Protoss_Observer 3 14622
Singularity_Charge 1 11372
Protoss_Forge 1 14535
15617
