Protoss_Gateway 2 11433
Protoss_Assimilator 1 4710
Protoss_Cybernetics_Core 1 6099
Protoss_Dragoon 6 14568
Protoss_Robotics_Facility 1 8966
Protoss_Observatory 1 9865
Protoss_Observer 3 14486
Singularity_Charge 1 12053
14568
