Protoss_Gateway 2 11648
Protoss_Assimilator 1 4473
Protoss_Cybernetics_Core 1 5889
Protoss_Dragoon 11 15603
Protoss_Robotics_Facility 1 9256
Protoss_Observatory 1 10027
Protoss_Observer 2 11947
Singularity_Charge 1 12426
15603
