Protoss_Gateway 3 10294
Protoss_Assimilator 1 4630
Protoss_Cybernetics_Core 1 6077
Protoss_Robotics_Facility 1 8272
Protoss_Dragoon 5 12388
Protoss_Observatory 1 9216
Protoss_Observer 2 11907
Singularity_Charge 1 11306
Protoss_Shuttle 1 13265
Protoss_Zealot 3 13261
Protoss_Nexus 2 17337
17337
