Protoss_Assimilator 1 3320
Protoss_Gateway 3 10580
Protoss_Cybernetics_Core 1 6219
Protoss_Robotics_Facility 1 8209
Protoss_Dragoon 4 14605
Protoss_Observatory 1 8944
Protoss_Observer 2 10856
Protoss_Shuttle 2 13534
Protoss_Zealot 6 13202
Protoss_Robotics_Support_Bay 1 13845
Protoss_Reaver 1 15615
Protoss_Citadel_of_Adun 1 15819
15819
