Protoss_Gateway 2 10344
Protoss_Assimilator 1 4578
Protoss_Cybernetics_Core 1 5904
Protoss_Dragoon 8 14173
Singularity_Charge 1 10019
Protoss_Nexus 2 16617
Protoss_Stargate 1 13708
Protoss_Forge 1 13811
Protoss_Photon_Cannon 1 15537
Protoss_Scout 1 16424
16617
