Protoss_Gateway 3 14328
Protoss_Assimilator 1 4419
Protoss_Cybernetics_Core 1 5963
Protoss_Dragoon 9 15549
Protoss_Nexus 1 12492
Singularity_Charge 1 10384
Protoss_Robotics_Facility 1 13112
Protoss_Zealot 2 14732
Protoss_Shuttle 1 14828
Protoss_Observatory 1 15013
Protoss_Citadel_of_Adun 1 16000
16000
