Protoss_Gateway 4 15050
Protoss_Assimilator 1 4681
Protoss_Cybernetics_Core 1 6798
Protoss_Dragoon 10 15490
Protoss_Robotics_Facility 1 10368
Protoss_Observatory 1 11151
Singularity_Charge 1 10472
Protoss_Observer 2 13110
Protoss_Nexus 1 15737
15737
