Protoss_Gateway 2 10827
Protoss_Assimilator 1 4542
Protoss_Cybernetics_Core 1 5977
Protoss_Zealot 1 6383
Protoss_Dragoon 7 13510
Protoss_Robotics_Facility 1 11907
Singularity_Charge 1 10589
Protoss_Forge 1 12538
Protoss_Observatory 1 12762
Protoss_Observer 1 13795
Protoss_Nexus 1 17452
17452
