Protoss_Gateway 2 11123
Protoss_Assimilator 1 4473
Protoss_Cybernetics_Core 1 5990
Protoss_Robotics_Facility 1 8246
Protoss_Dragoon 5 15246
Protoss_Observatory 1 9521
Protoss_Observer 1 10875
Singularity_Charge 1 14292
15246
