Protoss_Gateway 2 16063
Protoss_Assimilator 1 4695
Protoss_Cybernetics_Core 1 6263
Protoss_Robotics_Facility 1 8429
Protoss_Dragoon 4 14965
Protoss_Zealot 3 11644
Protoss_Shuttle 2 15926
Protoss_Robotics_Support_Bay 1 9814
Protoss_Reaver 1 11707
Protoss_Observatory 1 11723
Protoss_Observer 2 13666
16063
