Protoss_Gateway 2 11866
Protoss_Assimilator 1 4360
Protoss_Cybernetics_Core 1 6026
Protoss_Dragoon 4 14766
Protoss_Stargate 1 9007
Protoss_Citadel_of_Adun 1 9971
Protoss_Scout 1 11141
Singularity_Charge 1 10180
Protoss_Templar_Archives 1 12108
Protoss_Dark_Templar 4 14824
14824
