Protoss_Nexus 2 8932
Protoss_Assimilator 2 7644
Protoss_Gateway 3 12721
Protoss_Cybernetics_Core 1 9931
Protoss_Robotics_Facility 2 12900
Protoss_Dragoon 8 14960
Protoss_Shuttle 1 13389
Protoss_Observatory 1 12755
Protoss_Robotics_Support_Bay 1 14033
Singularity_Charge 1 13933
14960
