Protoss_Nexus 1 7240
Protoss_Gateway 3 12435
Protoss_Assimilator 2 12422
Protoss_Cybernetics_Core 1 7788
Protoss_Dragoon 9 15430
Protoss_Robotics_Facility 1 10579
Protoss_Forge 1 11009
Protoss_Observatory 1 11381
Protoss_Photon_Cannon 2 15029
Protoss_Observer 2 13392
Singularity_Charge 1 13904
15430
