Protoss_Gateway 4 15168
Protoss_Assimilator 1 4410
Protoss_Cybernetics_Core 1 6094
Protoss_Zealot 1 6310
Protoss_Dragoon 8 15410
Protoss_Robotics_Facility 1 11217
Singularity_Charge 1 9858
Protoss_Nexus 1 14854
Protoss_Observatory 1 12882
Protoss_Observer 2 14879
15410
