Protoss_Gateway 1 4493
Protoss_Assimilator 1 4660
Protoss_Cybernetics_Core 1 6138
Protoss_Dragoon 6 13390
Protoss_Robotics_Facility 1 8853
Protoss_Nexus 2 17217
Singularity_Charge 1 12097
17217
