Protoss_Assimilator 1 3532
Protoss_Gateway 2 14863
Protoss_Cybernetics_Core 1 6314
Protoss_Zealot 4 9895
Protoss_Robotics_Facility 1 8473
Protoss_Shuttle 1 10094
Protoss_Robotics_Support_Bay 1 10209
Protoss_Reaver 1 12066
Protoss_Observatory 1 11311
Protoss_Dragoon 3 14875
Protoss_Observer 3 14969
14969
