Protoss_Gateway 2 9604
Protoss_Assimilator 1 4527
Protoss_Cybernetics_Core 1 6140
Protoss_Dragoon 8 13778
Protoss_Robotics_Facility 1 9534
Protoss_Observatory 1 10283
Protoss_Observer 3 13457
Singularity_Charge 1 12449
Protoss_Nexus 1 16795
Protoss_Shuttle 1 15468
16795
