Protoss_Gateway 3 13924
Protoss_Assimilator 1 4483
Protoss_Cybernetics_Core 1 6195
Protoss_Dragoon 9 14363
Protoss_Robotics_Facility 1 8956
Protoss_Observatory 1 9759
Protoss_Observer 4 15280
Protoss_Nexus 1 14471
Singularity_Charge 1 11672
Protoss_Citadel_of_Adun 1 15359
15359
