Protoss_Gateway 2 7711
Protoss_Assimilator 2 5209
Protoss_Cybernetics_Core 1 6441
Protoss_Dragoon 13 14973
Singularity_Charge 1 10684
Protoss_Citadel_of_Adun 1 14042
Protoss_Nexus 1 16917
Protoss_Templar_Archives 1 15946
16917
