Protoss_Gateway 1 4425
Protoss_Assimilator 1 4635
Protoss_Cybernetics_Core 1 5980
Protoss_Dragoon 3 14834
Protoss_Robotics_Facility 1 8726
Protoss_Zealot 1 10173
Singularity_Charge 1 11627
14834
