Protoss_Gateway 2 11452
Protoss_Assimilator 1 4660
Protoss_Cybernetics_Core 1 6065
Protoss_Dragoon 10 15483
Protoss_Robotics_Facility 1 10235
Protoss_Observatory 1 11379
Protoss_Observer 2 13593
Singularity_Charge 1 12455
Protoss_Nexus 1 16560
16560
