Protoss_Gateway 3 11999
Protoss_Assimilator 1 4419
Protoss_Cybernetics_Core 1 5961
Protoss_Dragoon 6 13939
Protoss_Robotics_Facility 1 8656
Protoss_Observatory 1 9487
Protoss_Observer 1 10605
Protoss_Zealot 4 12566
Protoss_Shuttle 1 12523
Singularity_Charge 1 13260
Protoss_Nexus 1 17027
17027
