Protoss_Gateway 3 10227
Protoss_Assimilator 1 4337
Protoss_Cybernetics_Core 1 5923
Protoss_Robotics_Facility 1 7918
Protoss_Dragoon 9 14176
Protoss_Observatory 1 8802
Protoss_Observer 3 11730
Singularity_Charge 1 11273
Protoss_Nexus 1 16904
16904
