Protoss_Gateway 3 15823
Protoss_Assimilator 1 4690
Protoss_Cybernetics_Core 1 6080
Protoss_Dragoon 9 15007
Protoss_Robotics_Facility 1 8765
Protoss_Observatory 1 9740
Protoss_Observer 4 14756
Singularity_Charge 1 11804
Protoss_Nexus 2 16603
16603
