Protoss_Gateway 2 13788
Protoss_Assimilator 1 4432
Protoss_Cybernetics_Core 1 6055
Protoss_Dragoon 7 14501
Protoss_Robotics_Facility 1 8780
Protoss_Shuttle 1 10467
Protoss_Observatory 1 10008
Protoss_Robotics_Support_Bay 1 10355
Protoss_Observer 2 15149
Protoss_Reaver 1 13196
Singularity_Charge 1 11570
Protoss_Nexus 1 16607
16607
