Protoss_Gateway 2 10411
Protoss_Assimilator 1 4564
Protoss_Cybernetics_Core 1 5824
Protoss_Dragoon 5 14839
Protoss_Robotics_Facility 1 10042
Singularity_Charge 1 10026
Protoss_Observatory 1 10760
Protoss_Shuttle 1 11799
Protoss_Zealot 2 14636
Protoss_Robotics_Support_Bay 1 11826
Protoss_Observer 1 12642
Protoss_Nexus 1 15161
Protoss_Reaver 1 14400
15161
