Protoss_Gateway 2 9031
Protoss_Assimilator 1 4855
Protoss_Cybernetics_Core 1 6209
Protoss_Dragoon 11 15411
Protoss_Robotics_Facility 1 11022
Singularity_Charge 1 10128
Protoss_Observatory 1 12118
Protoss_Observer 2 14089
Protoss_Nexus 1 17361
17361
