Protoss_Gateway 2 11928
Protoss_Assimilator 1 4403
Protoss_Cybernetics_Core 1 6108
Protoss_Dragoon 7 15366
Protoss_Robotics_Facility 1 10061
Protoss_Observatory 1 10942
Singularity_Charge 1 10970
Protoss_Nexus 1 14583
Protoss_Observer 1 13356
Protoss_Shuttle 1 14714
15366
