Protoss_Gateway 3 15889
Protoss_Assimilator 1 4788
Protoss_Cybernetics_Core 1 6134
Protoss_Dragoon 9 15347
Protoss_Robotics_Facility 1 10554
Singularity_Charge 1 10286
Protoss_Observatory 1 11262
Protoss_Nexus 1 14045
Protoss_Observer 3 15579
Protoss_Forge 1 14342
15889
