Protoss_Gateway 3 14816
Protoss_Zealot 1 5168
Protoss_Assimilator 2 13849
Protoss_Cybernetics_Core 1 8554
Protoss_Nexus 1 11140
Protoss_Citadel_of_Adun 1 10130
Protoss_Templar_Archives 1 11652
Protoss_Dark_Templar 3 15108
15108
