Protoss_Gateway 3 16038
Protoss_Assimilator 1 4779
Protoss_Cybernetics_Core 1 6236
Protoss_Dragoon 10 14188
Protoss_Robotics_Facility 1 11051
Singularity_Charge 1 10120
Protoss_Observatory 1 11985
Protoss_Observer 2 14314
Protoss_Nexus 1 16928
16928
