Protoss_Gateway 2 12968
Protoss_Assimilator 1 4315
Protoss_Cybernetics_Core 1 5831
Protoss_Robotics_Facility 1 7997
Protoss_Dragoon 9 15541
Protoss_Observatory 1 8889
Protoss_Observer 1 10041
Protoss_Nexus 1 13272
Protoss_Shuttle 1 12560
Singularity_Charge 1 12177
Protoss_Robotics_Support_Bay 1 13370
15541
