Protoss_Gateway 2 8336
Protoss_Assimilator 1 4903
Protoss_Cybernetics_Core 1 6980
Protoss_Dragoon 11 15818
Singularity_Charge 1 11204
Protoss_Robotics_Facility 1 13255
Protoss_Nexus 1 16064
Protoss_Observatory 1 14046
16064
