Protoss_Gateway 2 10606
Protoss_Assimilator 1 4618
Protoss_Cybernetics_Core 1 6039
Protoss_Dragoon 7 14502
Protoss_Robotics_Facility 1 8751
Protoss_Observatory 1 9455
Protoss_Observer 3 14051
Singularity_Charge 1 12162
Protoss_Nexus 1 15614
15614
