Protoss_Gateway 3 15560
Protoss_Assimilator 2 5222
Protoss_Zealot 6 9836
Protoss_Cybernetics_Core 1 9684
Protoss_Dragoon 7 15042
Protoss_Robotics_Facility 1 13015
Protoss_Observatory 1 13898
Singularity_Charge 1 13882
Protoss_Observer 1 14922
15560
