Protoss_Gateway 2 9089
Protoss_Assimilator 1 4357
Protoss_Cybernetics_Core 1 5869
Protoss_Robotics_Facility 1 7927
Protoss_Dragoon 9 15790
Protoss_Observatory 1 8789
Protoss_Observer 2 15365
Protoss_Shuttle 1 12175
Singularity_Charge 1 13687
15790
