Protoss_Gateway 2 15548
Protoss_Assimilator 1 4739
Protoss_Cybernetics_Core 1 6390
Protoss_Zealot 1 6310
Protoss_Dragoon 4 12971
Protoss_Nexus 1 15513
Protoss_Citadel_of_Adun 1 15696
15696
