Protoss_Gateway 3 13060
Protoss_Assimilator 1 4412
Protoss_Cybernetics_Core 1 5720
Protoss_Dragoon 9 13580
Protoss_Robotics_Facility 1 10748
Singularity_Charge 1 9887
Protoss_Observatory 1 11559
Protoss_Observer 2 13512
Protoss_Shuttle 1 14870
Protoss_Nexus 1 16793
Protoss_Citadel_of_Adun 1 16056
16793
