Protoss_Gateway 2 15640
Protoss_Assimilator 1 4747
Protoss_Cybernetics_Core 1 6147
Protoss_Dragoon 4 13803
Protoss_Robotics_Facility 1 8722
Protoss_Shuttle 1 10138
Protoss_Robotics_Support_Bay 1 9762
Protoss_Zealot 3 14841
Protoss_Reaver 1 11890
Protoss_Observatory 1 11864
Protoss_Observer 2 15127
15640
