Protoss_Gateway 2 9596
Protoss_Assimilator 1 4671
Protoss_Cybernetics_Core 1 6191
Protoss_Dragoon 11 15751
Protoss_Robotics_Facility 1 11044
Singularity_Charge 1 10374
Protoss_Observatory 1 11754
Protoss_Observer 2 13676
Protoss_Shuttle 1 15034
Protoss_Nexus 1 16960
16960
