Protoss_Gateway 4 15226
Protoss_Assimilator 1 4657
Protoss_Cybernetics_Core 1 6018
Protoss_Dragoon 4 11605
Protoss_Robotics_Facility 1 8688
Protoss_Observatory 1 9506
Protoss_Observer 2 12258
Singularity_Charge 1 11767
Protoss_Nexus 1 14951
Protoss_Citadel_of_Adun 1 13867
Protoss_Shuttle 1 14777
Protoss_Templar_Archives 1 15468
15468
