Protoss_Gateway 3 15949
Protoss_Assimilator 1 4520
Protoss_Cybernetics_Core 1 6080
Protoss_Zealot 1 5980
Protoss_Robotics_Facility 1 8539
Protoss_Dragoon 7 15745
Protoss_Observatory 1 9459
Protoss_Observer 3 13539
Protoss_Nexus 1 14905
Singularity_Charge 1 12770
15949
