Protoss_Gateway 2 12728
Protoss_Assimilator 1 4592
Protoss_Cybernetics_Core 1 6131
Protoss_Dragoon 5 15811
Protoss_Robotics_Facility 1 9042
Protoss_Zealot 2 11497
Protoss_Shuttle 1 10504
Protoss_Robotics_Support_Bay 1 9841
Protoss_Reaver 1 12062
Protoss_Observatory 1 11391
Singularity_Charge 1 11884
Protoss_Observer 2 15247
15811
