Protoss_Gateway 2 9612
Protoss_Assimilator 1 4540
Protoss_Cybernetics_Core 1 5780
Protoss_Dragoon 7 15797
Protoss_Robotics_Facility 1 8597
Protoss_Zealot 3 14914
Protoss_Shuttle 2 12201
Protoss_Observatory 1 10318
Protoss_Robotics_Support_Bay 1 10921
Protoss_Reaver 1 14122
Protoss_Observer 1 15514
15797
