Protoss_Gateway 2 12087
Protoss_Assimilator 1 4452
Protoss_Cybernetics_Core 1 5990
Protoss_Robotics_Facility 1 7975
Protoss_Dragoon 9 15756
Protoss_Shuttle 1 9669
Protoss_Observatory 1 9492
Protoss_Observer 2 12078
Protoss_Nexus 1 15325
Singularity_Charge 1 13977
15756
