Protoss_Gateway 3 11174
Protoss_Assimilator 1 4691
Protoss_Cybernetics_Core 1 6122
Protoss_Dragoon 7 12923
Protoss_Robotics_Facility 1 9194
Protoss_Observatory 1 9914
Protoss_Observer 4 14879
Protoss_Nexus 2 17147
17147
