Protoss_Gateway 1 4454
Protoss_Assimilator 1 4769
Protoss_Cybernetics_Core 1 6096
Protoss_Dragoon 6 15631
Protoss_Robotics_Facility 1 9058
Protoss_Zealot 2 10349
Protoss_Shuttle 1 10518
Protoss_Robotics_Support_Bay 1 10008
Protoss_Reaver 2 14195
Protoss_Observatory 1 14878
Gravitic_Drive 1 14380
15631
