Protoss_Gateway 2 9607
Protoss_Assimilator 1 4710
Protoss_Cybernetics_Core 1 6279
Protoss_Dragoon 8 14297
Protoss_Robotics_Facility 1 11155
Singularity_Charge 1 10487
Protoss_Observatory 1 11935
Protoss_Nexus 1 14791
Protoss_Observer 2 13871
Protoss_Robotics_Support_Bay 1 14409
Protoss_Zealot 2 15500
15500
