Protoss_Gateway 2 10349
Protoss_Assimilator 1 4330
Protoss_Cybernetics_Core 1 5860
Protoss_Robotics_Facility 1 8122
Protoss_Zealot 1 7458
Protoss_Dragoon 5 13854
Singularity_Charge 1 11972
13854
