Protoss_Gateway 4 14696
Protoss_Assimilator 3 5273
Protoss_Cybernetics_Core 1 6295
Protoss_Dragoon 9 15292
Protoss_Nexus 1 12236
Singularity_Charge 1 10311
Protoss_Robotics_Facility 1 12644
Protoss_Observatory 1 13446
Protoss_Observer 2 15349
15349
