Protoss_Gateway 2 10994
Protoss_Assimilator 1 4652
Protoss_Zealot 1 5373
Protoss_Cybernetics_Core 1 6646
Protoss_Dragoon 10 14792
Protoss_Robotics_Facility 1 8825
Protoss_Observatory 1 9601
Protoss_Observer 2 11695
Singularity_Charge 1 11958
Protoss_Citadel_of_Adun 1 14948
Protoss_Nexus 1 16610
16610
