Protoss_Gateway 1 4656
Protoss_Assimilator 1 4637
Protoss_Cybernetics_Core 1 6131
Protoss_Dragoon 5 14685
Protoss_Robotics_Facility 1 10220
Protoss_Shuttle 1 11791
Singularity_Charge 1 10801
Protoss_Robotics_Support_Bay 1 11590
Protoss_Reaver 1 13456
Protoss_Zealot 1 12932
Protoss_Observatory 1 13589
Protoss_Observer 2 15517
15517
