Protoss_Gateway 2 11026
Protoss_Assimilator 1 4578
Protoss_Cybernetics_Core 1 5765
Protoss_Zealot 2 14929
Protoss_Dragoon 8 15058
Protoss_Robotics_Facility 1 10492
Singularity_Charge 1 10326
Protoss_Observatory 1 11379
Protoss_Observer 2 13407
Protoss_Nexus 1 16383
16383
