Protoss_Gateway 2 10807
Protoss_Assimilator 1 4542
Protoss_Cybernetics_Core 1 5977
Protoss_Dragoon 7 15556
Protoss_Robotics_Facility 1 11005
Singularity_Charge 1 10406
Protoss_Observatory 1 11774
Protoss_Shuttle 1 12874
Protoss_Zealot 2 12975
15556
