Protoss_Gateway 3 15274
Protoss_Assimilator 1 4717
Protoss_Cybernetics_Core 1 6030
Protoss_Dragoon 10 15431
Protoss_Robotics_Facility 1 8918
Protoss_Observatory 1 10059
Protoss_Observer 3 13169
Singularity_Charge 1 12360
Protoss_Nexus 1 15476
15476
