Protoss_Gateway 2 9134
Protoss_Assimilator 1 4473
Protoss_Cybernetics_Core 1 6134
Protoss_Dragoon 9 14369
Protoss_Robotics_Facility 1 8941
Protoss_Observatory 1 9645
Protoss_Observer 2 11552
Singularity_Charge 1 11533
Protoss_Shuttle 1 15113
Protoss_Zealot 2 15231
15231
