Protoss_Gateway 2 15964
Protoss_Assimilator 1 4551
Protoss_Zealot 2 6807
Protoss_Cybernetics_Core 1 6870
Protoss_Nexus 1 10961
Protoss_Dragoon 6 15172
Singularity_Charge 1 13962
15964
