Protoss_Gateway 3 11800
Protoss_Assimilator 1 4859
Protoss_Cybernetics_Core 1 6257
Protoss_Dragoon 8 15095
Protoss_Robotics_Facility 1 10454
Singularity_Charge 1 10450
Protoss_Observatory 1 11371
Protoss_Shuttle 1 12333
Protoss_Observer 1 13176
Protoss_Robotics_Support_Bay 1 12989
Protoss_Zealot 1 15301
15301
