Protoss_Gateway 5 15972
Protoss_Assimilator 1 4578
Protoss_Cybernetics_Core 1 5926
Protoss_Dragoon 6 15285
Protoss_Nexus 2 16347
Singularity_Charge 1 10209
Protoss_Robotics_Facility 1 12497
Protoss_Observatory 1 13765
Protoss_Observer 1 14936
16347
