Protoss_Gateway 1 4309
Protoss_Assimilator 1 4546
Protoss_Cybernetics_Core 1 6080
Protoss_Zealot 2 8022
Protoss_Robotics_Facility 1 8733
Protoss_Dragoon 2 10877
Singularity_Charge 1 12082
12082
