Protoss_Gateway 2 9674
Protoss_Assimilator 1 4150
Protoss_Zealot 3 7432
Protoss_Cybernetics_Core 1 6694
Protoss_Robotics_Facility 1 8913
Protoss_Dragoon 3 15571
Protoss_Shuttle 1 11813
Protoss_Robotics_Support_Bay 1 11630
Protoss_Observatory 1 12550
Protoss_Reaver 1 13895
Singularity_Charge 1 12345
Protoss_Nexus 1 16274
Protoss_Observer 1 14720
Protoss_Citadel_of_Adun 1 15650
16274
