Protoss_Gateway 4 16047
Protoss_Assimilator 1 4738
Protoss_Cybernetics_Core 1 6049
Protoss_Robotics_Facility 1 8331
Protoss_Dragoon 6 13211
Protoss_Observatory 1 9069
Protoss_Observer 4 14496
Protoss_Nexus 2 16137
Singularity_Charge 1 13799
16137
