Protoss_Gateway 3 13546
Protoss_Assimilator 1 4747
Protoss_Cybernetics_Core 1 6097
Protoss_Dragoon 9 15271
Protoss_Citadel_of_Adun 1 9605
Protoss_Templar_Archives 1 11156
Singularity_Charge 1 10011
Protoss_Dark_Templar 2 12629
Protoss_Nexus 1 14750
Protoss_Robotics_Facility 1 14992
15271
