Protoss_Gateway 2 8385
Protoss_Assimilator 2 6400
Protoss_Cybernetics_Core 1 5963
Protoss_Dragoon 8 14495
Protoss_Forge 1 8636
Protoss_Robotics_Facility 1 11744
Singularity_Charge 1 10267
Protoss_Photon_Cannon 1 12354
Protoss_Observatory 1 12730
Protoss_Robotics_Support_Bay 1 13384
Protoss_Shuttle 1 15135
15135
