Protoss_Gateway 3 14866
Protoss_Assimilator 1 4555
Protoss_Cybernetics_Core 1 5903
Protoss_Zealot 4 8854
Protoss_Dragoon 7 14510
Protoss_Robotics_Facility 1 12824
Singularity_Charge 1 11848
Protoss_Observatory 1 14441
Protoss_Observer 1 15573
Protoss_Nexus 1 17491
17491
