Protoss_Gateway 2 10331
Protoss_Assimilator 1 4646
Protoss_Cybernetics_Core 1 6102
Protoss_Robotics_Facility 1 8411
Protoss_Dragoon 7 15410
Protoss_Observatory 1 9418
Protoss_Observer 3 15247
Singularity_Charge 1 11840
Protoss_Nexus 2 16165
Protoss_Shuttle 1 14404
Protoss_Citadel_of_Adun 1 15118
16165
