Protoss_Gateway 3 13975
Protoss_Assimilator 1 4385
Protoss_Cybernetics_Core 1 5743
Protoss_Zealot 3 15200
Protoss_Dragoon 6 12966
Singularity_Charge 1 10143
Protoss_Nexus 1 13439
Protoss_Robotics_Facility 1 13085
Protoss_Shuttle 1 14813
Protoss_Observatory 1 14362
Protoss_Robotics_Support_Bay 1 14504
15200
