Protoss_Gateway 3 13420
Protoss_Assimilator 1 4543
Protoss_Cybernetics_Core 1 6014
Protoss_Dragoon 11 15756
Protoss_Nexus 1 12059
Singularity_Charge 1 10143
Protoss_Robotics_Facility 1 12168
Protoss_Observatory 1 13071
Protoss_Observer 2 15064
15756
