Protoss_Gateway 2 15007
Protoss_Assimilator 1 4666
Protoss_Cybernetics_Core 1 5793
Protoss_Zealot 1 5710
Protoss_Dragoon 6 14619
Protoss_Robotics_Facility 1 8744
Protoss_Shuttle 1 10204
Protoss_Robotics_Support_Bay 1 9982
Protoss_Reaver 1 12168
Protoss_Observatory 1 12733
Protoss_Observer 1 14644
15007
