Protoss_Gateway 2 11436
Protoss_Assimilator 1 4586
Protoss_Cybernetics_Core 1 6062
Protoss_Dragoon 9 13874
Protoss_Robotics_Facility 1 9840
Protoss_Observatory 1 10560
Protoss_Observer 2 12561
Singularity_Charge 1 12280
Protoss_Shuttle 1 15055
Protoss_Nexus 1 16939
Protoss_Zealot 2 15507
16939
