Protoss_Gateway 3 14849
Protoss_Assimilator 1 4731
Protoss_Cybernetics_Core 1 6380
Protoss_Robotics_Facility 1 8461
Protoss_Dragoon 6 13690
Protoss_Observatory 1 9320
Protoss_Observer 3 12939
Singularity_Charge 1 11628
Protoss_Nexus 1 15055
Protoss_Citadel_of_Adun 1 14256
15055
