Protoss_Gateway 3 15481
Protoss_Assimilator 1 4498
Protoss_Cybernetics_Core 1 6102
Protoss_Robotics_Facility 1 8144
Protoss_Dragoon 9 14751
Protoss_Observatory 1 8979
Protoss_Observer 3 14127
Protoss_Nexus 1 14586
Singularity_Charge 1 13406
Protoss_Shuttle 1 15933
15933
