Protoss_Gateway 4 15138
Protoss_Assimilator 1 4571
Protoss_Cybernetics_Core 1 5875
Protoss_Robotics_Facility 1 8208
Protoss_Dragoon 6 15783
Protoss_Observatory 1 9257
Protoss_Observer 2 12573
Protoss_Nexus 2 15633
Singularity_Charge 1 11658
15783
