Protoss_Gateway 3 13068
Protoss_Assimilator 1 5077
Protoss_Zealot 4 14132
Protoss_Cybernetics_Core 1 7255
Protoss_Dragoon 7 15746
Protoss_Robotics_Facility 1 10968
Protoss_Observatory 1 11821
Singularity_Charge 1 11416
Protoss_Shuttle 1 12882
15746
