Protoss_Gateway 2 4608
Protoss_Zealot 3 5973
Protoss_Assimilator 1 6895
Protoss_Cybernetics_Core 1 8048
Protoss_Dragoon 8 14810
Protoss_Nexus 1 14958
Singularity_Charge 1 12719
Protoss_Robotics_Facility 1 15014
15014
