Protoss_Gateway 2 10157
Protoss_Assimilator 1 4777
Protoss_Zealot 2 13586
Protoss_Cybernetics_Core 1 6640
Protoss_Dragoon 8 14919
Protoss_Robotics_Facility 1 11751
Singularity_Charge 1 10933
Protoss_Shuttle 1 13372
Protoss_Observatory 1 13244
Protoss_Observer 1 14702
14919
