Protoss_Gateway 2 13382
Protoss_Assimilator 1 4637
Protoss_Cybernetics_Core 1 5992
Protoss_Zealot 2 12573
Protoss_Dragoon 7 15775
Protoss_Robotics_Facility 1 10492
Singularity_Charge 1 10370
Protoss_Shuttle 1 12391
Protoss_Robotics_Support_Bay 1 11918
Protoss_Reaver 1 14042
Protoss_Observatory 1 14261
Protoss_Observer 1 15456
15775
