Protoss_Gateway 2 13594
Protoss_Assimilator 1 4507
Protoss_Cybernetics_Core 1 6153
Protoss_Zealot 1 5944
Protoss_Dragoon 6 15439
Protoss_Robotics_Facility 1 10229
Protoss_Observatory 1 11126
Protoss_Nexus 1 13334
Protoss_Observer 3 14054
Protoss_Shuttle 1 15412
15439
