Protoss_Gateway 2 12533
Protoss_Assimilator 1 4855
Protoss_Cybernetics_Core 1 6191
Protoss_Zealot 1 5995
Protoss_Dragoon 9 15443
Protoss_Robotics_Facility 1 10381
Protoss_Observatory 1 11138
Protoss_Observer 2 13656
Singularity_Charge 1 13150
Protoss_Nexus 1 16274
16274
