Protoss_Gateway 5 13485
Protoss_Assimilator 1 4530
Protoss_Cybernetics_Core 1 5999
Protoss_Dragoon 6 14034
Protoss_Nexus 1 11949
Protoss_Robotics_Facility 1 12153
Singularity_Charge 1 10319
Protoss_Observatory 1 12992
Protoss_Shuttle 1 14009
Protoss_Zealot 6 15127
15127
