Protoss_Gateway 3 15896
Protoss_Assimilator 1 4725
Protoss_Cybernetics_Core 1 6036
Protoss_Dragoon 7 13792
Protoss_Robotics_Facility 1 10356
Singularity_Charge 1 10340
Protoss_Observatory 1 11174
Protoss_Observer 2 13095
Protoss_Nexus 2 17182
17182
