Protoss_Gateway 3 14723
Protoss_Assimilator 1 4400
Protoss_Cybernetics_Core 1 5655
Protoss_Dragoon 12 15371
Protoss_Robotics_Facility 1 8397
Protoss_Observatory 1 9562
Protoss_Observer 5 15200
Protoss_Nexus 1 14144
Singularity_Charge 1 11628
15371
