Protoss_Gateway 2 10927
Protoss_Assimilator 1 4641
Protoss_Cybernetics_Core 1 6087
Protoss_Dragoon 4 14758
Protoss_Robotics_Facility 1 9068
Protoss_Observatory 1 9973
Protoss_Robotics_Support_Bay 1 10781
Protoss_Observer 1 11073
Protoss_Shuttle 1 12450
Protoss_Reaver 1 14008
Protoss_Zealot 2 13312
Singularity_Charge 1 13055
14758
