Protoss_Gateway 2 10831
Protoss_Assimilator 1 4527
Protoss_Cybernetics_Core 1 5944
Protoss_Dragoon 10 14255
Protoss_Robotics_Facility 1 10554
Singularity_Charge 1 10067
Protoss_Observatory 1 11252
Protoss_Observer 2 13147
Protoss_Nexus 1 16587
Protoss_Shuttle 1 15277
Protoss_Zealot 2 15143
Protoss_Robotics_Support_Bay 1 15279
16587
