Protoss_Gateway 2 8623
Protoss_Assimilator 1 4536
Protoss_Cybernetics_Core 1 5853
Protoss_Zealot 1 5710
Protoss_Dragoon 4 15702
Protoss_Citadel_of_Adun 1 9977
Protoss_Robotics_Facility 1 11780
Protoss_Templar_Archives 1 11456
Protoss_Dark_Templar 4 13795
Protoss_Shuttle 1 13189
Protoss_Forge 2 14532
Protoss_Observatory 1 14757
15702
