Protoss_Assimilator 2 14434
Protoss_Gateway 2 8380
Protoss_Cybernetics_Core 1 6295
Protoss_Robotics_Facility 1 8247
Protoss_Shuttle 1 9649
Protoss_Observatory 1 9449
Protoss_Dragoon 8 14196
Protoss_Observer 2 11581
Singularity_Charge 1 11018
Protoss_Nexus 1 15220
Protoss_Citadel_of_Adun 1 15017
Protoss_Zealot 2 15424
15424
