Protoss_Gateway 3 12149
Protoss_Assimilator 1 4436
Protoss_Cybernetics_Core 1 5679
Protoss_Dragoon 9 15215
Protoss_Robotics_Facility 1 11290
Singularity_Charge 1 9760
Protoss_Zealot 4 13486
Protoss_Observatory 1 12199
Protoss_Shuttle 1 13404
Protoss_Observer 1 14247
15215
