Protoss_Nexus 1 6681
Protoss_Gateway 3 12175
Protoss_Assimilator 1 5932
Protoss_Cybernetics_Core 1 7548
Protoss_Zealot 1 7463
Protoss_Dragoon 10 15426
Protoss_Robotics_Facility 1 13371
Singularity_Charge 1 11802
Protoss_Observatory 1 14139
Protoss_Observer 1 15248
15426
