Protoss_Gateway 4 14911
Protoss_Assimilator 1 4758
Protoss_Cybernetics_Core 1 6102
Protoss_Dragoon 10 15298
Protoss_Nexus 1 12795
Singularity_Charge 1 10428
Protoss_Robotics_Facility 1 13106
Protoss_Observatory 1 13892
Protoss_Observer 1 15163
Protoss_Zealot 1 15229
15298
