Protoss_Gateway 3 11203
Protoss_Assimilator 1 4578
Protoss_Cybernetics_Core 1 6115
Protoss_Dragoon 8 15095
Protoss_Citadel_of_Adun 1 9409
Protoss_Templar_Archives 1 10940
Protoss_Dark_Templar 2 14297
Protoss_Robotics_Facility 1 16339
16339
