Protoss_Gateway 1 4430
Protoss_Assimilator 1 4780
Protoss_Cybernetics_Core 1 6289
Protoss_Dragoon 6 15257
Protoss_Citadel_of_Adun 1 8407
Protoss_Nexus 1 12813
Singularity_Charge 1 11709
Protoss_Robotics_Facility 1 15958
15958
