Protoss_Gateway 3 10777
Protoss_Assimilator 1 4575
Protoss_Cybernetics_Core 1 6065
Protoss_Dragoon 10 15292
Protoss_Nexus 1 11589
Protoss_Zealot 1 11241
Singularity_Charge 1 13297
15292
