Protoss_Gateway 2 11800
Protoss_Assimilator 1 4911
Protoss_Cybernetics_Core 1 6292
Protoss_Dragoon 7 13017
Protoss_Robotics_Facility 1 8918
Protoss_Observatory 1 9676
Protoss_Observer 3 12810
Protoss_Nexus 2 16625
Singularity_Charge 1 13209
16625
