Protoss_Gateway 2 6535
Protoss_Assimilator 2 4761
Protoss_Zealot 5 10122
Protoss_Cybernetics_Core 1 9277
Protoss_Robotics_Facility 1 11707
Protoss_Dragoon 5 15775
Protoss_Robotics_Support_Bay 1 13743
Protoss_Citadel_of_Adun 1 14808
15775
