Protoss_Assimilator 1 3377
Protoss_Gateway 2 14052
Protoss_Cybernetics_Core 1 6302
Protoss_Zealot 4 9529
Protoss_Robotics_Facility 1 8277
Protoss_Shuttle 3 15495
Protoss_Robotics_Support_Bay 1 9996
Protoss_Observatory 1 10114
Protoss_Dragoon 5 15519
Protoss_Reaver 1 11993
Protoss_Observer 1 14137
15519
