Protoss_Gateway 2 11363
Protoss_Assimilator 1 4419
Protoss_Cybernetics_Core 1 6058
Protoss_Dragoon 7 14625
Protoss_Robotics_Facility 1 10413
Singularity_Charge 1 10340
Protoss_Shuttle 1 11828
Protoss_Zealot 4 13293
Protoss_Observatory 1 11472
Protoss_Observer 2 14146
Protoss_Robotics_Support_Bay 1 15007
15007
