Protoss_Assimilator 1 3576
Protoss_Gateway 2 10267
Protoss_Cybernetics_Core 1 6277
Protoss_Robotics_Facility 1 8370
Protoss_Dragoon 6 14422
Protoss_Observatory 1 9196
Protoss_Observer 3 13476
Protoss_Shuttle 1 12633
Protoss_Forge 1 12810
Protoss_Robotics_Support_Bay 1 12995
Protoss_Photon_Cannon 1 14259
Protoss_Reaver 1 15072
Singularity_Charge 1 14628
15072
