Protoss_Gateway 3 14348
Protoss_Assimilator 1 4668
Protoss_Cybernetics_Core 1 6094
Protoss_Robotics_Facility 1 8283
Protoss_Dragoon 8 15563
Protoss_Observatory 1 9269
Protoss_Nexus 1 12157
Protoss_Observer 3 12792
Singularity_Charge 1 14445
15563
