Protoss_Gateway 2 9806
Protoss_Assimilator 1 4789
Protoss_Cybernetics_Core 1 6340
Protoss_Dragoon 9 15775
Protoss_Robotics_Facility 1 9608
Protoss_Observatory 1 10740
Protoss_Observer 2 12953
Singularity_Charge 1 12733
Protoss_Shuttle 1 14311
Protoss_Nexus 1 16552
16552
