Protoss_Gateway 2 10000
Protoss_Assimilator 1 5110
Protoss_Cybernetics_Core 1 6194
Protoss_Zealot 1 6200
Protoss_Dragoon 5 12322
Protoss_Citadel_of_Adun 1 10638
Protoss_Templar_Archives 1 12188
Protoss_Nexus 1 15327
Protoss_Dark_Templar 3 15446
Protoss_Robotics_Facility 1 15819
15819
