Protoss_Gateway 2 10490
Protoss_Assimilator 1 4739
Protoss_Cybernetics_Core 1 5928
Protoss_Dragoon 4 14378
Protoss_Citadel_of_Adun 1 8787
Protoss_Templar_Archives 1 10243
Protoss_Robotics_Facility 1 11512
Protoss_Dark_Templar 3 12551
Protoss_Shuttle 1 13057
Protoss_Observatory 1 12974
Protoss_Observer 1 14066
Protoss_Nexus 1 16841
16841
