Protoss_Gateway 4 15225
Protoss_Assimilator 1 4512
Protoss_Cybernetics_Core 1 6150
Protoss_Robotics_Facility 1 8182
Protoss_Observatory 1 8933
Protoss_Dragoon 8 15133
Protoss_Observer 3 13428
Protoss_Shuttle 1 11704
Singularity_Charge 1 11033
Protoss_Nexus 1 14937
15225
