Protoss_Gateway 2 10002
Protoss_Assimilator 1 4687
Protoss_Cybernetics_Core 1 5889
Protoss_Dragoon 6 14897
Protoss_Robotics_Facility 1 9742
Protoss_Shuttle 1 11148
Protoss_Robotics_Support_Bay 1 10661
Protoss_Reaver 1 12827
Protoss_Observatory 1 12768
Protoss_Zealot 1 13210
Protoss_Observer 1 13824
Singularity_Charge 1 13282
Gravitic_Drive 1 14409
14897
