Protoss_Gateway 3 15504
Protoss_Assimilator 2 15541
Protoss_Cybernetics_Core 1 6116
Protoss_Dragoon 5 13419
Protoss_Citadel_of_Adun 1 8189
Protoss_Templar_Archives 1 9741
Protoss_Dark_Templar 4 14839
Protoss_Robotics_Facility 1 12884
Protoss_Nexus 1 16967
16967
