Protoss_Gateway 2 7577
Protoss_Assimilator 1 4442
Protoss_Cybernetics_Core 1 6740
Protoss_Dragoon 6 14711
Protoss_Citadel_of_Adun 1 11159
Protoss_Robotics_Facility 1 12143
Protoss_Observatory 1 12893
Protoss_Zealot 2 13483
Protoss_Observer 2 14862
Protoss_Forge 1 14761
Leg_Enhancements 1 14404
Singularity_Charge 1 14539
14862
