Protoss_Gateway 4 16031
Protoss_Assimilator 1 4912
Protoss_Zealot 1 5461
Protoss_Cybernetics_Core 1 6409
Protoss_Dragoon 7 15373
Protoss_Robotics_Facility 1 10915
Singularity_Charge 1 10531
Protoss_Observatory 1 11672
Protoss_Observer 2 13736
Protoss_Nexus 1 15943
Protoss_Shuttle 1 15238
16031
