Protoss_Gateway 2 10388
Protoss_Assimilator 1 4952
Protoss_Cybernetics_Core 1 6255
Protoss_Dragoon 8 15753
Protoss_Robotics_Facility 1 10331
Protoss_Shuttle 1 11740
Singularity_Charge 1 10326
Protoss_Observatory 1 11142
Protoss_Observer 2 13634
Protoss_Citadel_of_Adun 1 13272
Protoss_Nexus 1 16666
16666
