Protoss_Gateway 3 11133
Protoss_Assimilator 1 4593
Protoss_Cybernetics_Core 1 5989
Protoss_Dragoon 9 15212
Protoss_Robotics_Facility 1 10025
Protoss_Observatory 1 10874
Protoss_Zealot 4 12705
Protoss_Observer 2 14980
Protoss_Shuttle 1 13694
Singularity_Charge 1 12565
15212
