Protoss_Gateway 2 12141
Protoss_Assimilator 1 4564
Protoss_Cybernetics_Core 1 6065
Protoss_Dragoon 7 13427
Protoss_Robotics_Facility 1 8827
Protoss_Observatory 1 9711
Protoss_Observer 3 14197
Singularity_Charge 1 11731
Protoss_Nexus 1 15779
Protoss_Zealot 2 15039
Protoss_Shuttle 1 15999
15999
