Protoss_Gateway 2 10423
Protoss_Assimilator 1 4845
Protoss_Cybernetics_Core 1 5963
Protoss_Dragoon 4 11795
Protoss_Robotics_Facility 1 9995
Protoss_Robotics_Support_Bay 1 10772
Protoss_Shuttle 1 11528
Protoss_Observatory 1 13193
Singularity_Charge 1 14599
14599
