Protoss_Gateway 2 8427
Protoss_Assimilator 1 4366
Protoss_Cybernetics_Core 1 5873
Protoss_Robotics_Facility 1 7803
Protoss_Dragoon 11 14867
Protoss_Observatory 1 8568
Protoss_Observer 3 13925
Protoss_Shuttle 1 11028
Protoss_Nexus 1 15704
Singularity_Charge 1 13535
15704
