Protoss_Gateway 2 14383
Protoss_Assimilator 1 4609
Protoss_Cybernetics_Core 1 5891
Protoss_Dragoon 3 14739
Protoss_Robotics_Facility 1 8707
Protoss_Shuttle 1 10277
Protoss_Robotics_Support_Bay 1 9843
Protoss_Reaver 2 13445
Protoss_Observatory 1 12348
Gravitic_Drive 1 13575
Protoss_Observer 2 15569
15569
