Protoss_Assimilator 1 3752
Protoss_Gateway 3 15614
Protoss_Cybernetics_Core 1 6446
Protoss_Citadel_of_Adun 1 7938
Protoss_Robotics_Facility 1 8751
Protoss_Dragoon 3 14714
Protoss_Templar_Archives 1 9636
Protoss_Shuttle 1 10504
Protoss_Dark_Templar 3 11951
Protoss_Observatory 1 11237
Protoss_Observer 1 12610
Protoss_Nexus 1 15245
15614
