Protoss_Gateway 2 11465
Protoss_Assimilator 1 4653
Protoss_Cybernetics_Core 1 6065
Protoss_Dragoon 6 15200
Protoss_Robotics_Facility 1 8859
Protoss_Observatory 1 9664
Protoss_Observer 3 12836
Singularity_Charge 1 11950
Protoss_Nexus 1 16408
16408
