Protoss_Gateway 3 12803
Protoss_Assimilator 1 4653
Protoss_Cybernetics_Core 1 6384
Protoss_Dragoon 7 14692
Protoss_Citadel_of_Adun 1 8102
Protoss_Robotics_Facility 1 9702
Protoss_Nexus 2 16113
Protoss_Observatory 1 10460
Protoss_Observer 4 14837
Singularity_Charge 1 11643
16113
