Protoss_Gateway 2 10659
Protoss_Assimilator 1 4934
Protoss_Cybernetics_Core 1 6318
Protoss_Dragoon 7 15689
Protoss_Robotics_Facility 1 10225
Protoss_Observatory 1 11372
Singularity_Charge 1 12411
15689
