Protoss_Gateway 1 4567
Protoss_Assimilator 1 4915
Protoss_Cybernetics_Core 1 6497
Protoss_Dragoon 5 14872
Protoss_Nexus 1 13339
Singularity_Charge 1 10567
Protoss_Citadel_of_Adun 1 13818
Protoss_Templar_Archives 1 15545
15545
