Protoss_Assimilator 1 3561
Protoss_Gateway 2 13780
Protoss_Cybernetics_Core 1 6216
Protoss_Robotics_Facility 1 8212
Protoss_Dragoon 8 15351
Protoss_Shuttle 1 9640
Protoss_Observatory 1 9389
Protoss_Observer 2 11364
Protoss_Nexus 1 14819
Protoss_Forge 1 13805
Singularity_Charge 1 13518
15351
