Protoss_Gateway 2 13950
Protoss_Assimilator 2 4799
Protoss_Cybernetics_Core 1 6271
Protoss_Dragoon 6 14843
Protoss_Robotics_Facility 1 9445
Protoss_Robotics_Support_Bay 1 10242
Protoss_Shuttle 1 11083
Protoss_Reaver 1 12811
Protoss_Observatory 1 14382
14843
