Protoss_Gateway 3 13005
Protoss_Assimilator 1 4508
Protoss_Cybernetics_Core 1 5906
Protoss_Dragoon 9 14741
Protoss_Robotics_Facility 1 8615
Protoss_Shuttle 1 10416
Protoss_Observatory 1 9985
Singularity_Charge 1 11756
Protoss_Observer 3 14736
Protoss_Nexus 1 17222
17222
