Protoss_Gateway 3 14822
Protoss_Assimilator 1 4644
Protoss_Cybernetics_Core 1 5853
Protoss_Zealot 2 14105
Protoss_Dragoon 4 12849
Protoss_Citadel_of_Adun 1 10409
Protoss_Robotics_Facility 1 11853
Protoss_Templar_Archives 1 12012
Protoss_Observatory 1 12613
Protoss_Dark_Templar 3 15629
Protoss_Observer 2 14537
Protoss_Nexus 1 16517
Protoss_Shuttle 1 15457
16517
