Protoss_Gateway 2 9102
Protoss_Assimilator 1 4502
Protoss_Cybernetics_Core 1 6270
Protoss_Dragoon 7 15256
Protoss_Robotics_Facility 1 9086
Protoss_Observatory 1 9890
Protoss_Observer 2 11815
Protoss_Zealot 4 13884
Protoss_Shuttle 1 13269
Singularity_Charge 1 12075
Protoss_Nexus 1 16702
16702
