Protoss_Gateway 2 10389
Protoss_Assimilator 1 4785
Protoss_Zealot 3 7268
Protoss_Cybernetics_Core 1 8332
Protoss_Dragoon 8 14567
Singularity_Charge 1 12214
Protoss_Robotics_Facility 1 14527
Protoss_Observatory 1 15252
15252
