Protoss_Gateway 2 10015
Protoss_Assimilator 1 4537
Protoss_Cybernetics_Core 1 6055
Protoss_Dragoon 8 15825
Protoss_Robotics_Facility 1 8934
Protoss_Observatory 1 10097
Protoss_Observer 1 11338
Singularity_Charge 1 12174
Protoss_Nexus 1 17117
17117
