Protoss_Gateway 2 13192
Protoss_Assimilator 2 5096
Protoss_Cybernetics_Core 1 6438
Protoss_Zealot 4 12295
Protoss_Robotics_Facility 1 8890
Protoss_Robotics_Support_Bay 1 9658
Protoss_Shuttle 1 10489
Protoss_Observatory 1 10457
Protoss_Reaver 1 12395
Protoss_Observer 1 13232
Protoss_Dragoon 3 15178
Gravitic_Drive 1 13897
15178
