Protoss_Gateway 3 12511
Protoss_Assimilator 1 4618
Protoss_Cybernetics_Core 1 6043
Protoss_Dragoon 6 14912
Protoss_Robotics_Facility 1 9774
Protoss_Observatory 1 10623
Protoss_Observer 1 12507
Protoss_Zealot 4 15214
Protoss_Shuttle 1 13865
Singularity_Charge 1 13275
15214
