Protoss_Gateway 2 11080
Protoss_Assimilator 1 4592
Protoss_Cybernetics_Core 1 6089
Protoss_Dragoon 9 15263
Protoss_Robotics_Facility 1 9512
Protoss_Observatory 1 10232
Protoss_Observer 5 15141
Singularity_Charge 1 11870
15263
