Protoss_Gateway 2 11328
Protoss_Assimilator 3 6459
Protoss_Zealot 2 6961
Protoss_Cybernetics_Core 1 8677
Protoss_Citadel_of_Adun 1 10192
Protoss_Dragoon 2 15219
Protoss_Templar_Archives 1 12182
Protoss_Dark_Templar 2 13485
Protoss_Nexus 1 16222
Singularity_Charge 1 13999
16222
