Protoss_Gateway 2 8906
Protoss_Assimilator 1 4738
Protoss_Cybernetics_Core 1 6141
Protoss_Robotics_Facility 1 8334
Protoss_Dragoon 11 15292
Protoss_Observatory 1 9235
Protoss_Observer 3 14292
Singularity_Charge 1 11497
Protoss_Nexus 1 15660
15660
