Protoss_Gateway 3 11685
Protoss_Assimilator 1 4570
Protoss_Cybernetics_Core 1 5964
Protoss_Dragoon 5 11720
Protoss_Citadel_of_Adun 1 10305
Singularity_Charge 1 10014
Protoss_Zealot 13 15582
Leg_Enhancements 1 13242
15582
