Protoss_Gateway 2 10698
Protoss_Assimilator 2 5010
Protoss_Cybernetics_Core 1 6263
Protoss_Dragoon 4 13961
Protoss_Citadel_of_Adun 1 8976
Protoss_Templar_Archives 1 10426
Protoss_Dark_Templar 4 15219
Singularity_Charge 1 10743
Protoss_Nexus 1 14576
Protoss_Robotics_Facility 1 14072
15219
