Protoss_Gateway 3 13561
Protoss_Assimilator 1 4379
Protoss_Cybernetics_Core 1 5783
Protoss_Robotics_Facility 1 8079
Protoss_Dragoon 9 15789
Protoss_Shuttle 3 14411
Protoss_Observatory 1 9553
Protoss_Nexus 1 13132
Protoss_Observer 2 15365
Singularity_Charge 1 14583
15789
