Protoss_Gateway 3 13628
Protoss_Assimilator 1 4659
Protoss_Cybernetics_Core 1 5960
Protoss_Zealot 1 6595
Protoss_Dragoon 10 15197
Protoss_Robotics_Facility 1 10353
Singularity_Charge 1 10143
Protoss_Observatory 1 11205
Protoss_Observer 2 13685
Protoss_Shuttle 1 15043
15197
