Protoss_Gateway 1 4236
Protoss_Assimilator 1 4549
Protoss_Cybernetics_Core 1 5970
Protoss_Dragoon 2 10588
Protoss_Robotics_Facility 1 9279
Protoss_Citadel_of_Adun 1 9156
Protoss_Templar_Archives 1 10796
Protoss_Shuttle 1 11360
Protoss_Observatory 1 11685
Protoss_Dark_Templar 2 14919
Protoss_Observer 1 13078
14919
