Protoss_Gateway 2 10398
Protoss_Assimilator 1 4698
Protoss_Cybernetics_Core 1 6109
Protoss_Dragoon 10 15629
Singularity_Charge 1 10092
Protoss_Robotics_Facility 1 12425
Protoss_Observatory 1 13304
Protoss_Nexus 1 15915
Protoss_Observer 1 14344
15915
