Protoss_Gateway 2 11695
Protoss_Assimilator 1 4652
Protoss_Cybernetics_Core 1 6182
Protoss_Dragoon 7 14008
Protoss_Robotics_Facility 1 9219
Protoss_Zealot 1 8944
Protoss_Observatory 1 9998
Protoss_Observer 3 15463
Singularity_Charge 1 11526
Protoss_Shuttle 1 14272
Protoss_Nexus 2 17466
17466
