Protoss_Gateway 3 15716
Protoss_Assimilator 1 4352
Protoss_Cybernetics_Core 1 5824
Protoss_Zealot 2 9178
Protoss_Robotics_Facility 1 7917
Protoss_Dragoon 5 14868
Protoss_Shuttle 1 9355
Protoss_Robotics_Support_Bay 1 10485
Protoss_Reaver 1 12615
Protoss_Observatory 1 13206
Gravitic_Drive 1 14365
Protoss_Observer 1 15383
15716
