Protoss_Gateway 2 14595
Protoss_Assimilator 1 4404
Protoss_Cybernetics_Core 1 6163
Protoss_Robotics_Facility 1 8672
Protoss_Dragoon 5 14710
Protoss_Robotics_Support_Bay 1 9480
Protoss_Reaver 3 16055
Protoss_Shuttle 1 12533
Singularity_Charge 1 13728
16055
