Protoss_Gateway 2 14203
Protoss_Assimilator 1 4533
Protoss_Cybernetics_Core 1 5948
Protoss_Dragoon 6 14296
Protoss_Robotics_Facility 1 9175
Protoss_Shuttle 1 10621
Protoss_Robotics_Support_Bay 1 10055
Protoss_Observatory 1 10165
Protoss_Reaver 1 12179
Protoss_Observer 1 13003
14296
