Protoss_Gateway 2 14121
Protoss_Assimilator 1 4599
Protoss_Zealot 4 8477
Protoss_Cybernetics_Core 1 7809
Protoss_Dragoon 5 14861
Protoss_Robotics_Facility 1 10508
Protoss_Shuttle 2 13767
Protoss_Robotics_Support_Bay 1 11700
Protoss_Reaver 2 15864
Protoss_Shield_Battery 1 13580
Singularity_Charge 1 13955
Protoss_Observatory 1 15265
15864
