Protoss_Gateway 3 12538
Protoss_Assimilator 1 4360
Protoss_Cybernetics_Core 1 5569
Protoss_Dragoon 8 15442
Protoss_Robotics_Facility 1 8312
Protoss_Shuttle 1 9845
Protoss_Observatory 1 9824
Protoss_Observer 2 14768
Protoss_Nexus 1 14986
Singularity_Charge 1 12331
15442
