Protoss_Gateway 1 4126
Protoss_Assimilator 1 4243
Protoss_Cybernetics_Core 1 5802
Protoss_Robotics_Facility 1 7844
Protoss_Dragoon 4 12300
Protoss_Shuttle 1 9355
Protoss_Observatory 1 10823
Protoss_Observer 1 11922
Singularity_Charge 1 13904
13904
