Protoss_Gateway 2 10410
Protoss_Assimilator 1 4713
Protoss_Cybernetics_Core 1 6150
Protoss_Dragoon 6 12727
Protoss_Robotics_Facility 1 9958
Protoss_Observatory 1 10854
Singularity_Charge 1 10377
Protoss_Observer 3 15229
Protoss_Nexus 2 17097
Protoss_Shuttle 1 14153
Protoss_Zealot 2 14080
17097
