Protoss_Gateway 2 15528
Protoss_Assimilator 1 4583
Protoss_Cybernetics_Core 1 5948
Protoss_Zealot 1 5695
Protoss_Dragoon 7 14912
Protoss_Robotics_Facility 1 10470
Singularity_Charge 1 10121
Protoss_Shuttle 1 11887
Protoss_Robotics_Support_Bay 1 11321
Protoss_Reaver 1 13445
Protoss_Observatory 1 13411
Protoss_Observer 2 15510
15528
