Protoss_Gateway 1 4467
Protoss_Assimilator 1 4742
Protoss_Cybernetics_Core 1 6656
Protoss_Dragoon 3 10132
Protoss_Robotics_Facility 1 10176
Protoss_Shuttle 1 11696
Protoss_Robotics_Support_Bay 2 11409
Protoss_Reaver 2 15442
Protoss_Nexus 1 16976
16976
