Protoss_Gateway 2 5860
Protoss_Zealot 4 11234
Protoss_Assimilator 1 6245
Protoss_Cybernetics_Core 1 8584
Protoss_Dragoon 6 14773
Protoss_Robotics_Facility 1 12226
Protoss_Nexus 1 14503
Protoss_Observatory 1 14188
Protoss_Shuttle 1 15143
15143
