Protoss_Gateway 4 15953
Protoss_Assimilator 1 4539
Protoss_Cybernetics_Core 1 5967
Protoss_Dragoon 2 11229
Protoss_Robotics_Facility 1 8998
Protoss_Citadel_of_Adun 1 9778
Protoss_Observatory 1 9734
Protoss_Templar_Archives 1 11227
Protoss_Observer 2 14303
Protoss_Shuttle 1 12143
Protoss_Dark_Templar 4 13898
Protoss_Nexus 1 16117
16117
