Protoss_Gateway 3 13992
Protoss_Assimilator 1 4690
Protoss_Cybernetics_Core 1 6125
Protoss_Dragoon 7 12928
Protoss_Robotics_Facility 1 11268
Singularity_Charge 1 10414
Protoss_Observatory 1 12154
Protoss_Observer 1 13356
Protoss_Zealot 5 15536
Protoss_Shuttle 1 14714
Protoss_Shield_Battery 1 14331
Protoss_Citadel_of_Adun 1 15869
15869
