Protoss_Gateway 2 9882
Protoss_Assimilator 1 4719
Protoss_Cybernetics_Core 1 6112
Protoss_Dragoon 6 15622
Protoss_Citadel_of_Adun 1 8524
Protoss_Templar_Archives 1 10294
Protoss_Dark_Templar 4 12980
Protoss_Robotics_Facility 1 12889
Protoss_Shuttle 1 14491
Protoss_Nexus 1 16471
Protoss_Observatory 1 14851
16471
