Protoss_Gateway 1 4550
Protoss_Assimilator 1 4315
Protoss_Cybernetics_Core 1 6039
Protoss_Dragoon 5 15775
Protoss_Robotics_Facility 1 8411
Protoss_Zealot 2 9222
Protoss_Shuttle 1 9830
Protoss_Robotics_Support_Bay 1 9382
Protoss_Reaver 2 12928
Protoss_Observatory 1 13927
Protoss_Nexus 1 16701
Protoss_Observer 1 15522
16701
