Protoss_Gateway 2 14003
Protoss_Assimilator 1 4469
Protoss_Cybernetics_Core 1 6014
Protoss_Dragoon 6 15314
Protoss_Robotics_Facility 1 9799
Protoss_Observatory 1 10765
Protoss_Shuttle 1 11784
Protoss_Observer 3 14903
Singularity_Charge 1 12082
Protoss_Nexus 1 14990
15314
