Protoss_Gateway 2 12649
Protoss_Assimilator 1 4631
Protoss_Cybernetics_Core 1 5721
Protoss_Robotics_Facility 1 8414
Protoss_Forge 1 7890
Protoss_Dragoon 8 15061
Protoss_Shuttle 2 15128
Protoss_Observatory 1 9275
Protoss_Observer 2 11688
Protoss_Photon_Cannon 5 15698
Singularity_Charge 1 11584
Protoss_Nexus 1 16789
16789
