Protoss_Gateway 2 15255
Protoss_Assimilator 1 4717
Protoss_Cybernetics_Core 1 6194
Protoss_Dragoon 8 15137
Protoss_Robotics_Facility 1 9753
Protoss_Observatory 1 10487
Protoss_Observer 3 15412
Singularity_Charge 1 12748
Protoss_Nexus 1 16039
16039
