Protoss_Gateway 4 12870
Protoss_Assimilator 1 4169
Protoss_Cybernetics_Core 1 5648
Protoss_Robotics_Facility 1 7706
Protoss_Citadel_of_Adun 1 7946
Protoss_Shuttle 1 9121
Protoss_Templar_Archives 1 9482
Protoss_Dark_Templar 4 14312
Protoss_Dragoon 3 13910
Protoss_Observatory 1 14232
Protoss_Nexus 1 16815
16815
