Protoss_Assimilator 1 3547
Protoss_Gateway 3 15203
Protoss_Cybernetics_Core 1 6324
Protoss_Stargate 1 8043
Protoss_Robotics_Facility 1 9417
Protoss_Corsair 3 10890
Protoss_Dragoon 2 11897
Protoss_Shuttle 1 10950
Protoss_Robotics_Support_Bay 1 11094
Protoss_Reaver 2 14374
Protoss_Citadel_of_Adun 1 14494
15203
