Protoss_Gateway 1 4338
Protoss_Assimilator 1 4483
Protoss_Cybernetics_Core 1 5977
Protoss_Zealot 1 5841
Protoss_Dragoon 6 13276
Protoss_Robotics_Facility 1 10353
Singularity_Charge 1 10172
Protoss_Shuttle 1 12135
Protoss_Observatory 1 12013
Protoss_Robotics_Support_Bay 1 12192
Protoss_Reaver 1 14166
14166
