Protoss_Gateway 4 14985
Protoss_Assimilator 1 4441
Protoss_Cybernetics_Core 1 5838
Protoss_Zealot 1 5859
Protoss_Dragoon 6 13585
Protoss_Robotics_Facility 1 9042
Protoss_Observatory 1 9841
Protoss_Observer 3 14856
Protoss_Nexus 1 14258
Singularity_Charge 1 11987
14985
