Protoss_Gateway 3 13425
Protoss_Assimilator 1 4605
Protoss_Cybernetics_Core 1 5882
Protoss_Dragoon 9 15710
Protoss_Citadel_of_Adun 1 10141
Singularity_Charge 1 10084
Protoss_Templar_Archives 1 11911
Protoss_Dark_Templar 2 13200
Protoss_Nexus 1 16743
16743
