Protoss_Gateway 3 15607
Protoss_Assimilator 1 4695
Protoss_Cybernetics_Core 1 6160
Protoss_Dragoon 10 14534
Protoss_Robotics_Facility 1 10763
Protoss_Observatory 1 11556
Singularity_Charge 1 11299
Protoss_Observer 2 13461
Protoss_Nexus 1 16442
16442
