Protoss_Gateway 2 8963
Protoss_Assimilator 1 4652
Protoss_Cybernetics_Core 1 6285
Protoss_Dragoon 8 15449
Protoss_Robotics_Facility 1 8782
Protoss_Observatory 1 9554
Protoss_Observer 3 15217
Singularity_Charge 1 11694
Protoss_Nexus 1 15776
Protoss_Shuttle 1 14374
15776
