Protoss_Gateway 2 10618
Protoss_Assimilator 1 4608
Protoss_Cybernetics_Core 1 5999
Protoss_Dragoon 11 15366
Protoss_Robotics_Facility 1 10113
Protoss_Observatory 1 11075
Singularity_Charge 1 10428
Protoss_Observer 3 14578
Protoss_Nexus 1 16274
16274
