Protoss_Gateway 3 13641
Protoss_Assimilator 1 4261
Protoss_Cybernetics_Core 1 5816
Protoss_Dragoon 10 14489
Protoss_Robotics_Facility 1 10362
Singularity_Charge 1 10062
Protoss_Observatory 1 11151
Protoss_Observer 2 15295
Protoss_Nexus 1 17209
17209
