Protoss_Gateway 4 13220
Protoss_Assimilator 1 4565
Protoss_Cybernetics_Core 1 6039
Protoss_Dragoon 7 13792
Protoss_Robotics_Facility 1 8524
Protoss_Observatory 1 9336
Protoss_Observer 2 15288
Protoss_Citadel_of_Adun 1 12646
Singularity_Charge 1 11782
Protoss_Zealot 2 14219
Protoss_Nexus 1 17005
17005
