Protoss_Gateway 2 13545
Protoss_Assimilator 1 4385
Protoss_Cybernetics_Core 1 5736
Protoss_Dragoon 8 14988
Protoss_Robotics_Facility 1 10500
Singularity_Charge 1 10019
Protoss_Citadel_of_Adun 1 12100
Protoss_Observatory 1 11627
Protoss_Shuttle 1 13021
Protoss_Observer 1 13864
Protoss_Nexus 1 16522
16522
