Protoss_Gateway 2 11175
Protoss_Assimilator 1 4524
Protoss_Cybernetics_Core 1 5970
Protoss_Dragoon 9 14561
Protoss_Robotics_Facility 1 10785
Singularity_Charge 1 10348
Protoss_Observatory 1 12104
Protoss_Nexus 1 15615
Protoss_Observer 1 13780
Protoss_Shuttle 1 15443
Protoss_Zealot 2 15422
15615
