Protoss_Gateway 2 13253
Protoss_Assimilator 1 4549
Protoss_Cybernetics_Core 1 5888
Protoss_Dragoon 7 15614
Protoss_Robotics_Facility 1 9051
Protoss_Shuttle 1 10474
Protoss_Robotics_Support_Bay 1 9863
Protoss_Observatory 1 10254
Protoss_Reaver 1 12032
Protoss_Citadel_of_Adun 1 12806
Protoss_Observer 3 14733
15614
