Protoss_Gateway 3 15497
Protoss_Assimilator 2 6413
Protoss_Zealot 2 7527
Protoss_Cybernetics_Core 1 7713
Protoss_Dragoon 7 14992
Protoss_Robotics_Facility 1 10321
Protoss_Shuttle 1 11882
Protoss_Robotics_Support_Bay 1 11672
Protoss_Reaver 1 13502
Protoss_Observatory 1 14434
15497
