Protoss_Gateway 2 13009
Protoss_Assimilator 1 4442
Protoss_Cybernetics_Core 1 6062
Protoss_Dragoon 7 14597
Protoss_Robotics_Facility 1 8802
Protoss_Shuttle 1 10248
Protoss_Observatory 1 10274
Protoss_Nexus 2 16669
Protoss_Observer 1 12639
16669
