Protoss_Gateway 2 12001
Protoss_Assimilator 1 4482
Protoss_Cybernetics_Core 1 5502
Protoss_Dragoon 6 14524
Protoss_Robotics_Facility 1 10548
Singularity_Charge 1 9733
Protoss_Zealot 6 15386
Protoss_Shuttle 1 12091
Protoss_Robotics_Support_Bay 1 11941
Protoss_Citadel_of_Adun 1 13954
Protoss_Reaver 1 14773
Protoss_Templar_Archives 1 15570
15570
