Protoss_Gateway 3 13608
Protoss_Assimilator 1 4638
Protoss_Cybernetics_Core 1 6080
Protoss_Dragoon 7 15635
Protoss_Robotics_Facility 1 10639
Singularity_Charge 1 10458
Protoss_Shuttle 1 12450
Protoss_Observatory 1 12189
Protoss_Observer 2 14410
Protoss_Zealot 4 14657
15635
