Protoss_Gateway 2 15478
Protoss_Assimilator 4 6310
Protoss_Cybernetics_Core 1 6324
Protoss_Dragoon 4 14951
Protoss_Robotics_Facility 1 10352
Protoss_Shuttle 1 11955
Protoss_Robotics_Support_Bay 1 11799
Singularity_Charge 1 11460
Protoss_Reaver 1 13589
Protoss_Zealot 2 13832
Protoss_Observatory 1 13536
Protoss_Observer 1 15216
15478
