Protoss_Gateway 3 15110
Protoss_Assimilator 1 4300
Protoss_Cybernetics_Core 1 5963
Protoss_Dragoon 4 12636
Protoss_Robotics_Facility 1 8653
Protoss_Observatory 1 9606
Protoss_Citadel_of_Adun 1 10366
Protoss_Observer 2 12141
Protoss_Nexus 1 13664
Protoss_Templar_Archives 1 12350
Protoss_Dark_Templar 3 15241
15241
