Protoss_Gateway 2 12440
Protoss_Assimilator 1 5070
Protoss_Cybernetics_Core 1 6064
Protoss_Zealot 5 14483
Protoss_Dragoon 5 12079
Protoss_Robotics_Facility 1 11479
Singularity_Charge 1 10355
Protoss_Observatory 1 12266
Protoss_Observer 1 13553
Protoss_Nexus 1 15851
Protoss_Shuttle 1 15055
15851
