Protoss_Gateway 2 11748
Protoss_Assimilator 1 4530
Protoss_Cybernetics_Core 1 5856
Protoss_Dragoon 10 15484
Protoss_Robotics_Facility 1 10153
Protoss_Observatory 1 10851
Singularity_Charge 1 10234
Protoss_Observer 3 14677
Protoss_Shuttle 1 13834
Protoss_Robotics_Support_Bay 1 14593
15484
