Protoss_Gateway 4 14030
Protoss_Assimilator 1 4729
Protoss_Cybernetics_Core 1 6292
Protoss_Robotics_Facility 1 8345
Protoss_Dragoon 9 14343
Protoss_Observatory 1 9088
Protoss_Observer 1 10202
Protoss_Shuttle 1 11718
Singularity_Charge 1 12839
14343
