Protoss_Gateway 1 4363
Protoss_Assimilator 1 4603
Protoss_Cybernetics_Core 1 5948
Protoss_Dragoon 8 15639
Protoss_Robotics_Facility 1 11223
Singularity_Charge 1 10143
Protoss_Shuttle 1 12809
Protoss_Robotics_Support_Bay 1 12199
Protoss_Reaver 1 14422
Protoss_Observatory 1 15070
15639
