Protoss_Gateway 2 9507
Protoss_Assimilator 1 4675
Protoss_Cybernetics_Core 1 6058
Protoss_Dragoon 8 12928
Protoss_Robotics_Facility 1 11205
Singularity_Charge 1 9850
Protoss_Observatory 1 13094
Protoss_Nexus 1 16310
Protoss_Zealot 4 15356
Protoss_Observer 1 14512
Protoss_Shuttle 1 15870
16310
