Protoss_Gateway 2 9541
Protoss_Assimilator 1 4673
Protoss_Cybernetics_Core 1 5846
Protoss_Robotics_Facility 1 8274
Protoss_Dragoon 10 15746
Protoss_Observatory 1 9074
Protoss_Shuttle 1 9999
Protoss_Observer 2 11723
15746
