Protoss_Gateway 3 13891
Protoss_Assimilator 1 4416
Protoss_Cybernetics_Core 1 5933
Protoss_Dragoon 9 15131
Protoss_Robotics_Facility 1 10596
Singularity_Charge 1 10384
Protoss_Observatory 1 11368
Protoss_Observer 1 12434
Protoss_Shuttle 1 13921
Protoss_Zealot 2 13875
15131
