Protoss_Gateway 2 6387
Protoss_Assimilator 1 4359
Protoss_Cybernetics_Core 1 5750
Protoss_Dragoon 8 15475
Protoss_Nexus 1 12587
Protoss_Robotics_Facility 1 12183
Protoss_Shuttle 1 14133
Protoss_Observatory 1 14063
Protoss_Observer 1 15097
Singularity_Charge 1 14314
15475
