Protoss_Gateway 3 10729
Protoss_Assimilator 1 4559
Protoss_Cybernetics_Core 1 5941
Protoss_Dragoon 8 15263
Protoss_Robotics_Facility 1 9598
Protoss_Observatory 1 10665
Singularity_Charge 1 10275
Protoss_Observer 2 14724
Protoss_Zealot 4 13714
Protoss_Shuttle 1 13229
15263
