Protoss_Gateway 2 11285
Protoss_Assimilator 1 4659
Protoss_Cybernetics_Core 1 6021
Protoss_Robotics_Facility 1 8283
Protoss_Dragoon 6 15329
Protoss_Observatory 1 9083
Protoss_Observer 2 11607
Protoss_Nexus 1 14462
Protoss_Shuttle 1 13496
Singularity_Charge 1 12492
Protoss_Zealot 1 15558
15558
