Protoss_Gateway 2 9225
Protoss_Assimilator 1 4486
Protoss_Cybernetics_Core 1 5876
Protoss_Dragoon 11 14231
Singularity_Charge 1 9901
Protoss_Robotics_Facility 1 11809
Protoss_Observatory 1 12565
Protoss_Observer 2 14991
Protoss_Nexus 1 16900
16900
