Protoss_Gateway 2 11620
Protoss_Assimilator 1 4859
Protoss_Cybernetics_Core 1 6285
Protoss_Dragoon 6 14283
Protoss_Robotics_Facility 1 11670
Singularity_Charge 1 9997
Protoss_Nexus 2 16449
Protoss_Shuttle 1 13182
Protoss_Observatory 1 12613
Protoss_Observer 1 14695
16449
