Protoss_Gateway 3 11729
Protoss_Assimilator 1 4425
Protoss_Cybernetics_Core 1 6036
Protoss_Dragoon 12 15206
Protoss_Robotics_Facility 1 8214
Protoss_Shuttle 1 9618
Protoss_Observatory 1 9162
Protoss_Observer 3 13341
Singularity_Charge 1 11899
Protoss_Nexus 1 17023
17023
