Protoss_Gateway 3 13016
Protoss_Assimilator 1 4637
Protoss_Cybernetics_Core 1 6402
Protoss_Dragoon 9 15658
Protoss_Robotics_Facility 1 9900
Protoss_Nexus 1 12434
Protoss_Robotics_Support_Bay 1 10686
Protoss_Observatory 1 10955
Protoss_Observer 2 13169
Protoss_Shuttle 1 14527
Singularity_Charge 1 14175
Protoss_Citadel_of_Adun 1 15658
15658
