Protoss_Gateway 5 15980
Protoss_Assimilator 1 4953
Protoss_Cybernetics_Core 1 5985
Protoss_Dragoon 8 15420
Protoss_Citadel_of_Adun 1 10357
Protoss_Nexus 1 12761
Protoss_Robotics_Facility 1 12985
Singularity_Charge 1 11277
Protoss_Observatory 1 13798
Protoss_Observer 1 14841
15980
