Protoss_Gateway 3 14917
Protoss_Assimilator 1 4507
Protoss_Cybernetics_Core 1 6048
Protoss_Dragoon 8 14539
Protoss_Robotics_Facility 1 10650
Protoss_Observatory 1 11628
Protoss_Nexus 1 15410
Singularity_Charge 1 12865
Protoss_Observer 1 15200
Protoss_Citadel_of_Adun 1 15728
15728
