Protoss_Gateway 3 13299
Protoss_Assimilator 1 4498
Protoss_Cybernetics_Core 1 6024
Protoss_Dragoon 11 15278
Protoss_Nexus 1 12830
Singularity_Charge 1 10040
Protoss_Robotics_Facility 1 13126
Protoss_Observatory 1 14394
Protoss_Forge 1 15509
15509
