Protoss_Gateway 3 12768
Protoss_Assimilator 1 4483
Protoss_Cybernetics_Core 1 6080
Protoss_Dragoon 6 15285
Protoss_Robotics_Facility 1 9614
Protoss_Nexus 2 15644
Protoss_Observatory 1 11215
Protoss_Observer 4 15304
Singularity_Charge 1 11906
15644
