Protoss_Gateway 3 14844
Protoss_Assimilator 1 4587
Protoss_Cybernetics_Core 1 6062
Protoss_Dragoon 6 12658
Protoss_Robotics_Facility 1 9352
Protoss_Observatory 1 10874
Protoss_Observer 3 13981
Protoss_Nexus 1 15205
Singularity_Charge 1 12411
Protoss_Zealot 2 14651
15205
