Protoss_Forge 2 14715
Protoss_Nexus 1 8560
Protoss_Photon_Cannon 4 12607
Protoss_Gateway 3 13763
Protoss_Zealot 7 15412
Protoss_Assimilator 1 12169
Protoss_Cybernetics_Core 1 14421
Protoss_Citadel_of_Adun 1 15991
15991
