Protoss_Gateway 3 13691
Protoss_Assimilator 1 4438
Protoss_Cybernetics_Core 1 6077
Protoss_Dragoon 8 15314
Singularity_Charge 1 9953
Protoss_Robotics_Facility 1 12057
Protoss_Observatory 1 12789
Protoss_Zealot 4 14519
Protoss_Shuttle 1 14755
Protoss_Observer 1 14344
15314
