Protoss_Gateway 2 13365
Protoss_Assimilator 1 4271
Protoss_Cybernetics_Core 1 6113
Protoss_Dragoon 6 14978
Protoss_Stargate 1 9880
Protoss_Fleet_Beacon 1 11408
Singularity_Charge 1 10150
Protoss_Carrier 1 14756
Protoss_Robotics_Facility 1 14444
Protoss_Forge 1 15206
Protoss_Observatory 1 15193
15206
