Protoss_Gateway 1 4319
Protoss_Assimilator 1 4586
Protoss_Cybernetics_Core 1 6077
Protoss_Dragoon 5 15717
Protoss_Stargate 1 10250
Singularity_Charge 1 9748
Protoss_Fleet_Beacon 1 11707
Protoss_Shield_Battery 1 11589
Protoss_Zealot 1 14000
15717
