Protoss_Gateway 2 10594
Protoss_Assimilator 1 4578
Protoss_Cybernetics_Core 1 5947
Protoss_Dragoon 3 14853
Protoss_Robotics_Facility 1 8654
Protoss_Citadel_of_Adun 1 9201
Protoss_Templar_Archives 1 10676
Protoss_Observatory 1 10427
Protoss_Observer 1 11578
Protoss_Dark_Templar 4 13719
Protoss_Shuttle 1 12936
14853
