Protoss_Gateway 3 15261
Protoss_Assimilator 1 4384
Protoss_Cybernetics_Core 1 5680
Protoss_Dragoon 7 14414
Singularity_Charge 1 9975
Protoss_Robotics_Facility 1 11967
Protoss_Zealot 2 15276
15276
