Protoss_Gateway 4 13517
Protoss_Assimilator 1 4571
Protoss_Cybernetics_Core 1 6189
Protoss_Dragoon 13 15688
Protoss_Nexus 1 11305
Protoss_Robotics_Facility 1 10955
Protoss_Observatory 1 11894
Protoss_Observer 2 15551
Singularity_Charge 1 13267
15688
