Protoss_Gateway 2 11876
Protoss_Assimilator 1 4637
Protoss_Cybernetics_Core 1 6024
Protoss_Dragoon 10 15503
Protoss_Robotics_Facility 1 9131
Protoss_Observatory 1 9979
Protoss_Observer 3 14161
Singularity_Charge 1 12243
Protoss_Shuttle 1 14821
15503
