Protoss_Gateway 3 14822
Protoss_Assimilator 1 4556
Protoss_Cybernetics_Core 1 5868
Protoss_Dragoon 6 15600
Protoss_Stargate 1 10273
Protoss_Fleet_Beacon 1 11887
Singularity_Charge 1 10458
Protoss_Carrier 1 15239
Protoss_Robotics_Facility 1 14773
15600
