Protoss_Gateway 1 4353
Protoss_Assimilator 1 4701
Protoss_Cybernetics_Core 1 6109
Protoss_Robotics_Facility 1 8569
Protoss_Dragoon 7 15631
Protoss_Shuttle 2 15252
Protoss_Robotics_Support_Bay 1 9616
Protoss_Reaver 1 12132
Protoss_Observatory 1 13190
Protoss_Nexus 1 16677
16677
