Protoss_Gateway 2 9987
Protoss_Assimilator 1 4477
Protoss_Cybernetics_Core 1 5748
Protoss_Dragoon 6 12303
Protoss_Robotics_Facility 1 8738
Protoss_Observatory 1 9603
Protoss_Observer 2 14149
Singularity_Charge 1 11138
Protoss_Shuttle 1 13306
Protoss_Zealot 4 14607
14607
