Protoss_Gateway 2 12749
Protoss_Assimilator 1 4454
Protoss_Cybernetics_Core 1 5816
Protoss_Dragoon 10 15644
Protoss_Robotics_Facility 1 9685
Protoss_Shuttle 1 11126
Singularity_Charge 1 9975
Protoss_Robotics_Support_Bay 1 10939
Protoss_Reaver 1 12688
Protoss_Observatory 1 12334
Protoss_Observer 1 13512
15644
