Protoss_Gateway 3 12588
Protoss_Assimilator 1 4512
Protoss_Cybernetics_Core 1 5875
Protoss_Dragoon 6 14722
Protoss_Robotics_Facility 1 10661
Singularity_Charge 1 10143
Protoss_Nexus 1 15425
15425
