Protoss_Gateway 4 15699
Protoss_Assimilator 1 4479
Protoss_Cybernetics_Core 1 5774
Protoss_Dragoon 9 13207
Singularity_Charge 1 9953
Protoss_Robotics_Facility 1 13983
Protoss_Nexus 1 15308
Protoss_Citadel_of_Adun 1 14487
Protoss_Zealot 2 14980
Protoss_Observatory 1 14755
15699
