Protoss_Gateway 3 14377
Protoss_Assimilator 1 4300
Protoss_Cybernetics_Core 1 5783
Protoss_Dragoon 6 14770
Protoss_Robotics_Facility 1 10192
Protoss_Observatory 1 11033
Singularity_Charge 1 10326
Protoss_Nexus 1 13698
Protoss_Observer 1 12083
14770
