Protoss_Gateway 1 4419
Protoss_Assimilator 1 4644
Protoss_Cybernetics_Core 1 5906
Protoss_Dragoon 4 11444
Protoss_Robotics_Facility 1 8647
Protoss_Observatory 1 9407
Protoss_Observer 2 11819
Protoss_Robotics_Support_Bay 1 11988
Protoss_Shuttle 1 13177
Singularity_Charge 1 11775
Protoss_Reaver 1 14735
Protoss_Zealot 1 14263
Protoss_Nexus 1 16190
16190
