Protoss_Gateway 3 12362
Protoss_Assimilator 1 4354
Protoss_Cybernetics_Core 1 5862
Protoss_Dragoon 12 15073
Protoss_Robotics_Facility 1 10394
Protoss_Observatory 1 11198
Singularity_Charge 1 10619
Protoss_Observer 2 13110
15073
