Protoss_Gateway 3 12770
Protoss_Assimilator 1 4546
Protoss_Cybernetics_Core 1 5914
Protoss_Dragoon 7 13873
Protoss_Robotics_Facility 1 8606
Protoss_Shuttle 1 10013
Protoss_Observatory 1 9617
Protoss_Observer 5 14929
Singularity_Charge 1 11182
Protoss_Nexus 2 16380
16380
