Protoss_Gateway 4 13833
Protoss_Assimilator 1 4856
Protoss_Cybernetics_Core 1 6491
Protoss_Dragoon 5 15193
Protoss_Robotics_Facility 1 9172
Protoss_Observatory 1 10059
Protoss_Observer 2 12105
Singularity_Charge 1 11870
15193
