Protoss_Gateway 2 6636
Protoss_Assimilator 1 4422
Protoss_Cybernetics_Core 1 6204
Protoss_Dragoon 7 11395
Protoss_Citadel_of_Adun 1 10499
Singularity_Charge 1 10216
Protoss_Templar_Archives 1 12424
Protoss_Nexus 1 14869
Protoss_Dark_Templar 3 15673
Protoss_Robotics_Facility 1 15607
15673
