Protoss_Gateway 3 13574
Protoss_Assimilator 1 4527
Protoss_Cybernetics_Core 1 5829
Protoss_Dragoon 7 13602
Protoss_Robotics_Facility 1 8495
Protoss_Observatory 1 9276
Protoss_Nexus 1 12052
Protoss_Observer 3 13583
Protoss_Zealot 3 14702
Protoss_Shuttle 1 14941
Singularity_Charge 1 14292
14941
