Protoss_Gateway 3 12075
Protoss_Assimilator 1 4575
Protoss_Cybernetics_Core 1 6067
Protoss_Dragoon 12 15636
Protoss_Robotics_Facility 1 11000
Singularity_Charge 1 10150
Protoss_Observatory 1 11934
Protoss_Observer 2 14597
Protoss_Citadel_of_Adun 1 15140
15636
