Protoss_Nexus 1 7044
Protoss_Gateway 3 9475
Protoss_Assimilator 2 12337
Protoss_Cybernetics_Core 1 7959
Protoss_Zealot 1 8285
Protoss_Dragoon 11 15746
Protoss_Robotics_Facility 1 12496
Singularity_Charge 1 12309
Protoss_Shuttle 1 14243
15746
