Protoss_Assimilator 1 3497
Protoss_Gateway 3 13711
Protoss_Cybernetics_Core 1 6153
Protoss_Robotics_Facility 1 8136
Protoss_Dragoon 6 14245
Protoss_Shuttle 1 9545
Protoss_Observatory 1 10984
Protoss_Observer 3 13925
Protoss_Citadel_of_Adun 1 13079
Singularity_Charge 1 12784
Protoss_Templar_Archives 1 14889
Protoss_Zealot 1 14534
14889
