Protoss_Gateway 2 12945
Protoss_Assimilator 1 4474
Protoss_Cybernetics_Core 1 6058
Protoss_Dragoon 7 15009
Protoss_Robotics_Facility 1 8754
Protoss_Shuttle 1 10167
Protoss_Observatory 1 10260
Protoss_Observer 2 15405
Protoss_Nexus 1 13937
Singularity_Charge 1 11965
Protoss_Robotics_Support_Bay 1 14578
Protoss_Zealot 1 15210
15405
