Protoss_Assimilator 1 3926
Protoss_Gateway 3 14099
Protoss_Cybernetics_Core 1 6021
Protoss_Robotics_Facility 1 7953
Protoss_Shuttle 1 9369
Protoss_Robotics_Support_Bay 1 8717
Protoss_Reaver 2 12467
Protoss_Forge 1 10710
Protoss_Shield_Battery 1 11884
Protoss_Dragoon 6 15740
Gravitic_Drive 1 13721
Protoss_Observatory 1 14666
15740
