Protoss_Gateway 2 7534
Protoss_Assimilator 1 4271
Protoss_Cybernetics_Core 1 5685
Protoss_Dragoon 12 15000
Singularity_Charge 1 10114
Protoss_Robotics_Facility 1 12475
Protoss_Observatory 1 13393
Protoss_Nexus 1 16376
Protoss_Observer 1 14534
16376
