Protoss_Gateway 2 7858
Protoss_Assimilator 1 4425
Protoss_Cybernetics_Core 1 5904
Protoss_Dragoon 11 15417
Singularity_Charge 1 10333
Protoss_Nexus 1 13661
Protoss_Robotics_Facility 1 14195
Protoss_Citadel_of_Adun 1 14859
Protoss_Observatory 1 15064
15417
