Protoss_Gateway 3 13577
Protoss_Assimilator 1 4286
Protoss_Cybernetics_Core 1 5619
Protoss_Dragoon 5 14568
Protoss_Citadel_of_Adun 1 8003
Protoss_Templar_Archives 1 9576
Protoss_Dark_Templar 4 11900
Protoss_Robotics_Facility 1 13697
Protoss_Zealot 3 15573
Protoss_Shuttle 1 15311
Protoss_Observatory 1 14820
15573
