Protoss_Gateway 2 7829
Protoss_Assimilator 2 5000
Protoss_Cybernetics_Core 1 6637
Protoss_Dragoon 7 14188
Protoss_Citadel_of_Adun 1 10149
Protoss_Templar_Archives 1 11671
Protoss_Dark_Templar 4 15578
15578
