Protoss_Gateway 2 10774
Protoss_Assimilator 1 4553
Protoss_Zealot 1 5511
Protoss_Cybernetics_Core 1 7447
Protoss_Dragoon 7 14123
Protoss_Robotics_Facility 1 12247
Singularity_Charge 1 11185
Protoss_Observatory 1 13163
Protoss_Shuttle 1 14604
Protoss_Observer 1 15447
15447
