Protoss_Gateway 2 6759
Protoss_Assimilator 1 4625
Protoss_Cybernetics_Core 1 5900
Protoss_Dragoon 10 15307
Protoss_Zealot 2 10322
Protoss_Robotics_Facility 1 12219
Singularity_Charge 1 10750
Protoss_Observatory 1 12996
Protoss_Observer 1 14571
Protoss_Nexus 1 16923
16923
