Protoss_Gateway 1 4556
Protoss_Assimilator 1 4909
Protoss_Cybernetics_Core 1 6260
Protoss_Dragoon 6 14454
Protoss_Robotics_Facility 1 10387
Protoss_Shuttle 1 12055
Protoss_Zealot 2 15315
Protoss_Robotics_Support_Bay 1 11754
Singularity_Charge 1 11262
Protoss_Reaver 2 15973
15973
