Protoss_Gateway 2 10046
Protoss_Assimilator 1 4687
Protoss_Cybernetics_Core 1 6192
Protoss_Dragoon 7 13051
Protoss_Robotics_Facility 1 8984
Protoss_Observatory 1 9958
Protoss_Observer 2 14432
Singularity_Charge 1 11972
Protoss_Nexus 2 16805
16805
