Protoss_Gateway 2 14250
Protoss_Assimilator 2 4924
Protoss_Zealot 2 6975
Protoss_Cybernetics_Core 1 7293
Protoss_Dragoon 5 13671
Protoss_Robotics_Facility 1 9449
Protoss_Shuttle 1 10862
Protoss_Robotics_Support_Bay 1 10779
Protoss_Reaver 2 14513
Singularity_Charge 1 14043
Protoss_Nexus 1 17239
17239
