Protoss_Gateway 3 11562
Protoss_Assimilator 1 4700
Protoss_Cybernetics_Core 1 6072
Protoss_Dragoon 9 13771
Protoss_Robotics_Facility 1 9436
Protoss_Observatory 1 10425
Protoss_Observer 2 13583
Protoss_Nexus 1 16142
Singularity_Charge 1 13406
16142
