Protoss_Gateway 1 4217
Protoss_Assimilator 1 4193
Protoss_Cybernetics_Core 1 5685
Protoss_Dragoon 6 12920
Protoss_Robotics_Facility 1 8303
Protoss_Observatory 1 9177
Singularity_Charge 1 12777
12920
