Protoss_Gateway 2 9898
Protoss_Assimilator 1 4578
Protoss_Cybernetics_Core 1 5963
Protoss_Dragoon 10 15461
Protoss_Robotics_Facility 1 8612
Protoss_Observatory 1 9704
Protoss_Observer 2 13407
Protoss_Shuttle 1 12948
Singularity_Charge 1 11987
Protoss_Nexus 1 15381
15461
