Protoss_Gateway 2 5626
Protoss_Zealot 3 11263
Protoss_Assimilator 1 5673
Protoss_Cybernetics_Core 1 6994
Protoss_Dragoon 4 13171
Protoss_Robotics_Facility 1 10510
Protoss_Citadel_of_Adun 1 11557
Protoss_Shuttle 1 12011
Protoss_Templar_Archives 1 13079
Protoss_Dark_Templar 4 15434
15434
