Protoss_Gateway 4 13654
Protoss_Assimilator 1 4338
Protoss_Cybernetics_Core 1 5780
Protoss_Robotics_Facility 1 7968
Protoss_Dragoon 9 15285
Protoss_Shuttle 1 9391
Protoss_Observatory 1 8848
Protoss_Observer 2 11300
Singularity_Charge 1 10948
Protoss_Nexus 1 15672
15672
