Protoss_Gateway 3 13255
Protoss_Assimilator 1 4457
Protoss_Cybernetics_Core 1 6127
Protoss_Dragoon 12 14704
Protoss_Robotics_Facility 1 9651
Protoss_Observatory 1 10460
Protoss_Observer 2 12634
Singularity_Charge 1 12155
Protoss_Nexus 1 17137
17137
