Protoss_Gateway 2 9566
Protoss_Assimilator 1 4612
Protoss_Cybernetics_Core 1 5993
Protoss_Dragoon 10 15153
Protoss_Citadel_of_Adun 1 8392
Protoss_Nexus 1 13397
Protoss_Robotics_Facility 1 13075
Singularity_Charge 1 11453
Protoss_Observatory 1 14101
Protoss_Observer 1 15127
15153
