Protoss_Gateway 2 10458
Protoss_Assimilator 1 4769
Protoss_Cybernetics_Core 1 6108
Protoss_Dragoon 9 14717
Protoss_Robotics_Facility 1 9044
Protoss_Observatory 1 9897
Protoss_Observer 3 14666
Singularity_Charge 1 12104
Protoss_Nexus 1 17270
17270
