Protoss_Gateway 4 15153
Protoss_Assimilator 1 4641
Protoss_Cybernetics_Core 1 5999
Protoss_Dragoon 9 14615
Protoss_Robotics_Facility 1 8783
Protoss_Observatory 1 9604
Protoss_Observer 4 15364
Singularity_Charge 1 11987
Protoss_Nexus 1 15564
15564
