Protoss_Gateway 2 13302
Protoss_Assimilator 1 4710
Protoss_Cybernetics_Core 1 6087
Protoss_Dragoon 8 15793
Protoss_Robotics_Facility 1 8814
Protoss_Shuttle 1 10343
Protoss_Robotics_Support_Bay 1 10330
Protoss_Reaver 2 13676
Protoss_Observatory 1 12276
Singularity_Charge 1 12009
Protoss_Observer 1 14500
15793
