Protoss_Gateway 2 9930
Protoss_Assimilator 1 4469
Protoss_Cybernetics_Core 1 6091
Protoss_Dragoon 8 15051
Protoss_Robotics_Facility 1 9850
Protoss_Observatory 1 10686
Protoss_Observer 4 15332
Protoss_Nexus 2 15971
Singularity_Charge 1 12280
15971
