Protoss_Gateway 3 11628
Protoss_Assimilator 1 4477
Protoss_Cybernetics_Core 1 5887
Protoss_Dragoon 9 13491
Protoss_Robotics_Facility 1 10342
Singularity_Charge 1 9932
Protoss_Observatory 1 11101
Protoss_Observer 3 14513
Protoss_Nexus 1 16287
Protoss_Citadel_of_Adun 1 15725
Protoss_Shuttle 1 15871
16287
