Protoss_Gateway 1 4287
Protoss_Assimilator 1 4392
Protoss_Cybernetics_Core 1 5979
Protoss_Dragoon 8 15129
Protoss_Robotics_Facility 1 9990
Protoss_Nexus 1 12141
Protoss_Observatory 1 10822
Protoss_Observer 3 14680
Singularity_Charge 1 13845
15129
