Protoss_Gateway 2 12312
Protoss_Assimilator 1 4558
Protoss_Cybernetics_Core 1 6001
Protoss_Zealot 1 5717
Protoss_Dragoon 9 15241
Singularity_Charge 1 9997
Protoss_Robotics_Facility 1 11978
Protoss_Shuttle 1 13430
Protoss_Observatory 1 12982
Protoss_Observer 2 15412
Protoss_Robotics_Support_Bay 1 14160
15412
