Protoss_Gateway 2 11417
Protoss_Assimilator 1 4600
Protoss_Cybernetics_Core 1 6039
Protoss_Robotics_Facility 1 8246
Protoss_Dragoon 5 12636
Protoss_Observatory 1 9304
Protoss_Observer 1 10356
Protoss_Shuttle 1 11714
Protoss_Nexus 1 15245
Protoss_Zealot 2 13729
Singularity_Charge 1 13706
15245
