Protoss_Gateway 2 10689
Protoss_Assimilator 1 4205
Protoss_Cybernetics_Core 1 5647
Protoss_Robotics_Facility 1 7719
Protoss_Zealot 5 15310
Protoss_Dragoon 7 13295
Protoss_Observatory 1 8435
Protoss_Observer 3 13905
Protoss_Shuttle 1 11964
Singularity_Charge 1 11855
Protoss_Nexus 1 16615
Protoss_Citadel_of_Adun 1 15965
16615
