Protoss_Gateway 3 11557
Protoss_Assimilator 1 4556
Protoss_Cybernetics_Core 1 5977
Protoss_Dragoon 11 15783
Protoss_Robotics_Facility 1 11436
Singularity_Charge 1 9975
Protoss_Observatory 1 12313
Protoss_Observer 2 14326
Protoss_Nexus 1 16386
16386
