Protoss_Gateway 3 10574
Protoss_Assimilator 1 4635
Protoss_Zealot 6 15122
Protoss_Cybernetics_Core 1 6907
Protoss_Dragoon 6 12917
Protoss_Robotics_Facility 1 9281
Protoss_Observatory 1 10007
Protoss_Shuttle 1 11177
Singularity_Charge 1 11497
Protoss_Observer 2 13571
Protoss_Nexus 1 15930
15930
