Protoss_Gateway 3 11351
Protoss_Assimilator 1 4338
Protoss_Zealot 1 5278
Protoss_Cybernetics_Core 1 6427
Protoss_Robotics_Facility 1 8678
Protoss_Dragoon 8 14736
Protoss_Observatory 1 9563
Protoss_Observer 4 14530
Protoss_Nexus 1 14005
Singularity_Charge 1 11877
Protoss_Shuttle 1 15888
15888
