Protoss_Gateway 3 10596
Protoss_Assimilator 1 4517
Protoss_Cybernetics_Core 1 5802
Protoss_Dragoon 6 14520
Protoss_Citadel_of_Adun 1 8502
Protoss_Templar_Archives 1 10113
Protoss_Dark_Templar 3 11810
Protoss_Robotics_Facility 1 15300
Protoss_Zealot 2 15002
Singularity_Charge 1 14328
15300
