Protoss_Gateway 2 12629
Protoss_Assimilator 1 4344
Protoss_Cybernetics_Core 1 6084
Protoss_Dragoon 9 15360
Protoss_Robotics_Facility 1 8905
Protoss_Observatory 1 9609
Protoss_Observer 4 14805
Protoss_Nexus 1 13410
Singularity_Charge 1 12023
15360
