Protoss_Gateway 2 6538
Protoss_Assimilator 1 4294
Protoss_Cybernetics_Core 1 5712
Protoss_Dragoon 11 15341
Singularity_Charge 1 9929
Protoss_Nexus 1 12868
Protoss_Robotics_Facility 1 13511
15341
