Protoss_Gateway 2 11393
Protoss_Assimilator 4 6212
Protoss_Cybernetics_Core 1 6475
Protoss_Dragoon 5 15212
Protoss_Citadel_of_Adun 1 9779
Protoss_Robotics_Facility 1 11490
Protoss_Zealot 1 11212
Singularity_Charge 1 10509
Protoss_Templar_Archives 1 12416
Protoss_Shuttle 1 13445
Protoss_Dark_Templar 2 13631
Protoss_Observatory 1 14054
Protoss_Nexus 1 16522
16522
