Protoss_Gateway 2 10128
Protoss_Assimilator 1 4808
Protoss_Cybernetics_Core 1 6026
Protoss_Dragoon 4 13119
Protoss_Robotics_Facility 1 9065
Protoss_Observatory 1 9903
Protoss_Observer 1 10934
Singularity_Charge 1 11526
13119
