Protoss_Gateway 3 14063
Protoss_Assimilator 1 4637
Protoss_Cybernetics_Core 1 6058
Protoss_Robotics_Facility 1 8246
Protoss_Shuttle 1 9655
Protoss_Observatory 1 8979
Protoss_Dragoon 8 15395
Protoss_Observer 4 14581
Protoss_Nexus 2 17400
Singularity_Charge 1 12287
17400
