Protoss_Gateway 1 4350
Protoss_Assimilator 1 4915
Protoss_Zealot 7 13556
Protoss_Cybernetics_Core 1 7413
Protoss_Dragoon 3 15022
Protoss_Robotics_Facility 1 9791
Protoss_Shuttle 1 11206
Protoss_Robotics_Support_Bay 1 11022
Protoss_Reaver 2 14447
Protoss_Observatory 1 13828
Protoss_Citadel_of_Adun 1 14846
Protoss_Observer 1 15272
15272
