Protoss_Gateway 2 12721
Protoss_Assimilator 1 4783
Protoss_Cybernetics_Core 1 6131
Protoss_Dragoon 9 15797
Protoss_Robotics_Facility 1 9169
Protoss_Observatory 1 10078
Protoss_Observer 2 12012
Singularity_Charge 1 12228
Protoss_Shuttle 1 13701
Protoss_Nexus 1 16906
16906
