Protoss_Gateway 2 16016
Protoss_Assimilator 1 4600
Protoss_Zealot 4 13312
Protoss_Cybernetics_Core 1 7010
Protoss_Dragoon 5 15563
Protoss_Robotics_Facility 1 9870
Protoss_Shuttle 2 15230
Protoss_Robotics_Support_Bay 1 11147
Protoss_Reaver 1 13159
16016
