Protoss_Gateway 3 13375
Protoss_Assimilator 1 4793
Protoss_Cybernetics_Core 1 6321
Protoss_Dragoon 8 14802
Protoss_Nexus 1 12688
Singularity_Charge 1 10040
Protoss_Robotics_Facility 1 12929
Protoss_Observatory 1 13642
Protoss_Observer 1 14783
14802
