Protoss_Gateway 3 10382
Protoss_Assimilator 1 4193
Protoss_Cybernetics_Core 1 5595
Protoss_Dragoon 7 12110
Protoss_Nexus 1 11033
Singularity_Charge 1 9455
Protoss_Robotics_Facility 1 11858
Protoss_Zealot 1 12283
12283
