Protoss_Gateway 2 10060
Protoss_Assimilator 1 4363
Protoss_Cybernetics_Core 1 5884
Protoss_Dragoon 3 10141
Protoss_Citadel_of_Adun 1 8787
Protoss_Templar_Archives 1 10243
Singularity_Charge 1 9843
Protoss_Dark_Templar 2 11577
Protoss_Nexus 1 13904
13904
