Protoss_Gateway 2 10420
Protoss_Assimilator 1 4293
Protoss_Cybernetics_Core 1 5686
Protoss_Dragoon 5 11649
Protoss_Robotics_Facility 1 9636
Singularity_Charge 1 9704
Protoss_Observatory 1 10454
Protoss_Observer 1 11622
Protoss_Nexus 1 14122
14122
