Protoss_Gateway 2 9921
Protoss_Assimilator 1 4204
Protoss_Cybernetics_Core 1 5592
Protoss_Dragoon 8 12551
Protoss_Robotics_Facility 1 9702
Singularity_Charge 1 9645
Protoss_Observatory 1 10422
Protoss_Observer 1 11453
12551
