Protoss_Nexus 1 6717
Protoss_Gateway 2 9160
Protoss_Assimilator 2 10646
Protoss_Cybernetics_Core 1 7619
Protoss_Zealot 2 8527
Protoss_Dragoon 7 12584
Protoss_Robotics_Facility 1 11451
Protoss_Shield_Battery 1 11006
12584
