Protoss_Gateway 2 8914
Protoss_Assimilator 1 4261
Protoss_Zealot 1 5190
Protoss_Cybernetics_Core 1 6888
Protoss_Dragoon 7 12446
Protoss_Nexus 1 12792
Singularity_Charge 1 10984
12792
