Protoss_Gateway 2 11111
Protoss_Assimilator 1 4464
Protoss_Cybernetics_Core 1 5780
Protoss_Dragoon 5 11505
Protoss_Citadel_of_Adun 1 9807
Protoss_Templar_Archives 1 11275
Singularity_Charge 1 9894
Protoss_Dark_Templar 2 12606
12606
