Protoss_Gateway 3 12149
Protoss_Assimilator 1 4272
Protoss_Cybernetics_Core 1 5796
Protoss_Dragoon 6 10652
Singularity_Charge 1 9710
Protoss_Citadel_of_Adun 1 11320
Protoss_Zealot 2 11783
12149
