Protoss_Gateway 2 10409
Protoss_Assimilator 1 4659
Protoss_Cybernetics_Core 1 6020
Protoss_Dragoon 5 11663
Protoss_Robotics_Facility 1 8862
Protoss_Observatory 1 10517
Protoss_Observer 1 12163
12163
