Protoss_Gateway 2 7223
Protoss_Assimilator 1 4995
Protoss_Zealot 2 7188
Protoss_Cybernetics_Core 1 6582
Protoss_Dragoon 8 12411
Singularity_Charge 1 10371
Protoss_Robotics_Facility 1 12402
12411
