Protoss_Gateway 2 10281
Protoss_Assimilator 1 4356
Protoss_Cybernetics_Core 1 5784
Protoss_Dragoon 4 10652
Protoss_Robotics_Facility 1 10225
Singularity_Charge 1 10000
Protoss_Observatory 1 10942
Protoss_Nexus 1 13781
Protoss_Shuttle 1 12629
13781
