Protoss_Gateway 2 8349
Protoss_Assimilator 1 4499
Protoss_Cybernetics_Core 1 5750
Protoss_Dragoon 6 12563
Singularity_Charge 1 9587
Protoss_Robotics_Facility 1 11862
Protoss_Nexus 1 13967
13967
