Protoss_Gateway 2 11819
Protoss_Assimilator 1 4644
Protoss_Cybernetics_Core 1 5914
Protoss_Robotics_Facility 1 8209
Protoss_Dragoon 5 12499
Protoss_Observatory 1 9069
Protoss_Observer 2 11882
12499
