Protoss_Gateway 2 8076
Protoss_Assimilator 1 4403
Protoss_Cybernetics_Core 1 5919
Protoss_Dragoon 4 12102
Protoss_Zealot 3 9295
Protoss_Citadel_of_Adun 1 10798
Protoss_Templar_Archives 1 12513
12513
