Protoss_Gateway 1 4389
Protoss_Assimilator 1 4624
Protoss_Cybernetics_Core 1 6116
Protoss_Dragoon 5 11916
Protoss_Robotics_Facility 1 10055
Protoss_Shuttle 1 11452
Singularity_Charge 1 10128
Protoss_Robotics_Support_Bay 1 11328
Protoss_Reaver 1 13063
13063
