Protoss_Gateway 2 6460
Protoss_Assimilator 1 4331
Protoss_Cybernetics_Core 1 5860
Protoss_Dragoon 7 12058
Protoss_Nexus 1 12595
Singularity_Charge 1 9799
Protoss_Robotics_Facility 1 12892
12892
