Protoss_Gateway 1 4214
Protoss_Assimilator 1 4240
Protoss_Cybernetics_Core 1 5819
Protoss_Robotics_Facility 1 8155
Protoss_Dragoon 2 12369
Protoss_Shuttle 1 9567
Protoss_Robotics_Support_Bay 1 9265
Protoss_Observatory 1 9894
Protoss_Zealot 2 11249
Protoss_Reaver 1 11810
12369
