Protoss_Gateway 2 10692
Protoss_Assimilator 1 4141
Protoss_Cybernetics_Core 1 5569
Protoss_Dragoon 3 9016
Protoss_Citadel_of_Adun 1 9405
Protoss_Robotics_Facility 1 10696
Singularity_Charge 1 9546
Protoss_Templar_Archives 1 11352
Protoss_Shuttle 1 12151
Protoss_Dark_Templar 2 12554
12554
