Protoss_Gateway 2 8112
Protoss_Assimilator 1 4265
Protoss_Cybernetics_Core 1 5772
Protoss_Dragoon 6 11802
Protoss_Robotics_Facility 1 10827
Protoss_Zealot 2 10480
Singularity_Charge 1 9872
Protoss_Shuttle 1 12589
12589
