Protoss_Gateway 1 4322
Protoss_Assimilator 1 4553
Protoss_Cybernetics_Core 1 6239
Protoss_Dragoon 3 11252
Protoss_Robotics_Facility 1 10124
Protoss_Nexus 1 12627
Singularity_Charge 1 10266
Protoss_Citadel_of_Adun 1 11897
Protoss_Shuttle 1 12626
12627
