Protoss_Gateway 2 9744
Protoss_Assimilator 1 4602
Protoss_Cybernetics_Core 1 6004
Protoss_Dragoon 7 12364
Protoss_Robotics_Facility 1 9930
Protoss_Observatory 1 10640
Singularity_Charge 1 9929
Protoss_Observer 1 11654
12364
