Protoss_Gateway 2 6905
Protoss_Assimilator 1 4239
Protoss_Cybernetics_Core 1 5695
Protoss_Dragoon 3 8536
Protoss_Citadel_of_Adun 1 9882
Protoss_Robotics_Facility 1 10879
Singularity_Charge 1 9508
Protoss_Zealot 2 10843
Protoss_Templar_Archives 1 11421
Protoss_Shuttle 1 12336
12336
