Protoss_Gateway 2 9425
Protoss_Assimilator 1 4499
Protoss_Zealot 2 6632
Protoss_Cybernetics_Core 1 6782
Protoss_Citadel_of_Adun 1 8297
Protoss_Dragoon 1 8694
Protoss_Templar_Archives 1 10375
Protoss_Nexus 1 12849
Protoss_Dark_Templar 2 11632
12849
