Protoss_Gateway 2 10975
Protoss_Assimilator 1 4296
Protoss_Zealot 1 5110
Protoss_Cybernetics_Core 1 6020
Protoss_Dragoon 6 12326
Protoss_Robotics_Facility 1 10143
Protoss_Observatory 1 10930
Singularity_Charge 1 10266
Protoss_Observer 1 12263
12326
