Protoss_Nexus 1 6902
Protoss_Gateway 2 7031
Protoss_Assimilator 1 5933
Protoss_Cybernetics_Core 1 7441
Protoss_Zealot 1 7180
Protoss_Dragoon 4 10785
Protoss_Robotics_Facility 1 10825
Protoss_Shuttle 1 12304
Protoss_Robotics_Support_Bay 1 11908
Protoss_Observatory 1 12045
12304
