Protoss_Gateway 2 10293
Protoss_Assimilator 1 4652
Protoss_Cybernetics_Core 1 6168
Protoss_Dragoon 6 11861
Protoss_Robotics_Facility 1 10390
Singularity_Charge 1 10062
Protoss_Observatory 1 11157
Protoss_Observer 1 12251
12251
