Protoss_Gateway 2 8469
Protoss_Assimilator 1 4713
Protoss_Cybernetics_Core 1 6229
Protoss_Dragoon 6 11510
Protoss_Citadel_of_Adun 1 10728
Singularity_Charge 1 10275
Protoss_Templar_Archives 1 12182
12182
