Protoss_Gateway 2 11369
Protoss_Assimilator 1 4474
Protoss_Cybernetics_Core 1 5730
Protoss_Dragoon 5 11729
Protoss_Nexus 1 11673
Singularity_Charge 1 9689
Protoss_Robotics_Facility 1 12256
12256
