Protoss_Gateway 2 10543
Protoss_Assimilator 1 4467
Protoss_Cybernetics_Core 1 5849
Protoss_Dragoon 6 12025
Protoss_Robotics_Facility 1 9812
Singularity_Charge 1 9525
Protoss_Observatory 1 10924
Protoss_Observer 1 12102
12102
