Protoss_Gateway 2 11977
Protoss_Assimilator 1 5408
Protoss_Zealot 2 7214
Protoss_Cybernetics_Core 1 7167
Protoss_Dragoon 4 12458
Protoss_Nexus 1 12619
Protoss_Robotics_Facility 1 12951
12951
