Protoss_Gateway 2 9939
Protoss_Assimilator 1 4400
Protoss_Cybernetics_Core 1 5854
Protoss_Dragoon 7 12414
Protoss_Robotics_Facility 1 10267
Singularity_Charge 1 9739
Protoss_Observatory 1 11053
Protoss_Observer 1 12134
12414
