Protoss_Assimilator 1 3320
Protoss_Gateway 2 8452
Protoss_Cybernetics_Core 1 6109
Protoss_Zealot 6 10378
Protoss_Citadel_of_Adun 1 9267
Protoss_Templar_Archives 1 10744
Protoss_Dark_Templar 2 12073
12073
