Protoss_Gateway 1 4085
Protoss_Assimilator 1 4297
Protoss_Cybernetics_Core 1 5727
Protoss_Dragoon 4 12285
Protoss_Robotics_Facility 1 8310
Protoss_Shuttle 1 9926
Protoss_Zealot 2 11013
Protoss_Observatory 1 10045
Protoss_Robotics_Support_Bay 1 10646
Protoss_Reaver 1 12395
12395
