Protoss_Gateway 2 12146
Protoss_Assimilator 1 4267
Protoss_Cybernetics_Core 1 5853
Protoss_Zealot 1 6544
Protoss_Dragoon 4 11665
Protoss_Nexus 1 11897
Singularity_Charge 1 9566
Protoss_Robotics_Facility 1 11553
12146
