Protoss_Gateway 2 8114
Protoss_Assimilator 1 4265
Protoss_Cybernetics_Core 1 5658
Protoss_Dragoon 8 12437
Protoss_Zealot 1 10185
Singularity_Charge 1 9713
Protoss_Robotics_Facility 1 12385
12437
