Protoss_Nexus 1 6946
Protoss_Gateway 2 10729
Protoss_Assimilator 2 10698
Protoss_Cybernetics_Core 1 7744
Protoss_Forge 1 7720
Protoss_Photon_Cannon 2 12161
Protoss_Dragoon 2 10125
Protoss_Citadel_of_Adun 1 9517
Protoss_Templar_Archives 1 11020
Protoss_Zealot 1 10987
Protoss_Dark_Templar 1 12215
Protoss_Robotics_Facility 1 13223
13223
