Protoss_Gateway 1 4193
Protoss_Assimilator 1 4656
Protoss_Cybernetics_Core 1 5671
Protoss_Dragoon 5 11489
Protoss_Robotics_Facility 1 10160
Singularity_Charge 1 9880
Protoss_Shuttle 1 11619
Protoss_Robotics_Support_Bay 1 11123
11619
