Protoss_Gateway 2 6741
Protoss_Assimilator 2 12353
Protoss_Cybernetics_Core 1 5800
Protoss_Dragoon 5 11471
Protoss_Nexus 1 12075
Singularity_Charge 1 9663
Protoss_Citadel_of_Adun 1 11723
Protoss_Robotics_Facility 1 12885
12885
