Protoss_Gateway 1 4322
Protoss_Assimilator 1 4315
Protoss_Cybernetics_Core 1 5961
Protoss_Zealot 4 9100
Protoss_Robotics_Facility 1 8057
Protoss_Shuttle 1 9465
Protoss_Robotics_Support_Bay 1 9492
Protoss_Reaver 1 11268
Protoss_Dragoon 1 11136
Protoss_Observatory 1 11375
11375
