Protoss_Assimilator 1 3573
Protoss_Gateway 2 11003
Protoss_Cybernetics_Core 1 6425
Protoss_Zealot 1 6127
Protoss_Robotics_Facility 1 8524
Protoss_Dragoon 5 12431
Protoss_Observatory 1 9433
Protoss_Observer 2 11636
Singularity_Charge 1 11160
12431
