Protoss_Gateway 2 10144
Protoss_Assimilator 1 4390
Protoss_Cybernetics_Core 1 5740
Protoss_Dragoon 7 12537
Protoss_Robotics_Facility 1 9882
Protoss_Observatory 1 10725
Singularity_Charge 1 10017
Protoss_Nexus 1 13615
Protoss_Observer 1 11809
13615
