Protoss_Gateway 1 4287
Protoss_Assimilator 1 4608
Protoss_Cybernetics_Core 1 5868
Protoss_Dragoon 5 12137
Protoss_Robotics_Facility 1 10489
Singularity_Charge 1 10253
Protoss_Shuttle 1 11894
Protoss_Robotics_Support_Bay 1 11369
12137
