Protoss_Gateway 2 9497
Protoss_Zealot 3 6872
Protoss_Assimilator 1 5467
Protoss_Cybernetics_Core 1 7063
Protoss_Dragoon 4 10880
Protoss_Robotics_Facility 1 10980
Protoss_Nexus 1 13793
Singularity_Charge 1 11021
Protoss_Observatory 1 11846
13793
