Protoss_Gateway 1 4395
Protoss_Assimilator 2 4792
Protoss_Cybernetics_Core 1 6630
Protoss_Forge 1 7630
Protoss_Robotics_Facility 1 9690
Protoss_Photon_Cannon 2 10305
Protoss_Robotics_Support_Bay 1 10510
Protoss_Shuttle 1 11916
11916
