Protoss_Gateway 2 8047
Protoss_Assimilator 1 4154
Protoss_Cybernetics_Core 1 5573
Protoss_Dragoon 6 10593
Singularity_Charge 1 9675
Protoss_Nexus 1 13255
Protoss_Robotics_Facility 1 12800
13255
