Protoss_Nexus 1 7069
Protoss_Gateway 2 8860
Protoss_Assimilator 1 6173
Protoss_Cybernetics_Core 1 7777
Protoss_Zealot 1 7678
Protoss_Dragoon 6 12518
Protoss_Forge 1 11449
12518
