Protoss_Gateway 2 6454
Protoss_Assimilator 1 4196
Protoss_Cybernetics_Core 1 5598
Protoss_Dragoon 7 12107
Protoss_Citadel_of_Adun 1 10109
Protoss_Zealot 2 10521
Singularity_Charge 1 9593
Protoss_Templar_Archives 1 12093
12107
