Protoss_Gateway 2 12569
Protoss_Assimilator 1 4265
Protoss_Cybernetics_Core 1 5635
Protoss_Dragoon 6 12344
Protoss_Nexus 1 12467
Singularity_Charge 1 9719
Protoss_Robotics_Facility 1 12449
12569
