Protoss_Gateway 2 8412
Protoss_Assimilator 1 4561
Protoss_Cybernetics_Core 1 5941
Protoss_Dragoon 4 10108
Protoss_Citadel_of_Adun 1 9324
Protoss_Templar_Archives 1 10785
Singularity_Charge 1 10017
Protoss_Nexus 1 13827
13827
