Protoss_Gateway 2 10577
Protoss_Assimilator 1 4226
Protoss_Zealot 3 7378
Protoss_Cybernetics_Core 1 6959
Protoss_Dragoon 4 12069
Protoss_Robotics_Facility 1 10261
Protoss_Observatory 1 10962
Protoss_Shuttle 1 11914
Protoss_Robotics_Support_Bay 1 11991
12069
