Protoss_Gateway 2 9770
Protoss_Assimilator 1 4334
Protoss_Cybernetics_Core 1 5709
Protoss_Dragoon 6 12183
Protoss_Robotics_Facility 1 9822
Singularity_Charge 1 9742
Protoss_Observatory 1 10531
Protoss_Observer 1 11645
12183
