Protoss_Gateway 3 12482
Protoss_Assimilator 1 4245
Protoss_Cybernetics_Core 1 5928
Protoss_Dragoon 5 11671
Protoss_Nexus 1 11577
Singularity_Charge 1 9850
Protoss_Robotics_Facility 1 11997
12482
