Protoss_Gateway 2 12129
Protoss_Assimilator 1 4659
Protoss_Cybernetics_Core 1 5948
Protoss_Dragoon 5 12439
Protoss_Citadel_of_Adun 1 8996
Protoss_Zealot 1 9118
Protoss_Templar_Archives 1 11268
Singularity_Charge 1 10289
12439
