Protoss_Gateway 2 10104
Protoss_Assimilator 1 4407
Protoss_Cybernetics_Core 1 5812
Protoss_Dragoon 5 12235
Protoss_Robotics_Facility 1 9695
Protoss_Observatory 1 10447
Singularity_Charge 1 9789
Protoss_Nexus 1 13375
Protoss_Observer 1 11534
13375
