Protoss_Gateway 2 10057
Protoss_Assimilator 1 4403
Protoss_Cybernetics_Core 1 5746
Protoss_Dragoon 8 12453
Protoss_Robotics_Facility 1 10337
Singularity_Charge 1 9755
Protoss_Observatory 1 11103
Protoss_Observer 1 12127
12453
