Protoss_Gateway 1 4280
Protoss_Assimilator 1 4536
Protoss_Cybernetics_Core 1 6045
Protoss_Robotics_Facility 1 8315
Protoss_Dragoon 3 12317
Protoss_Zealot 2 9839
Protoss_Shuttle 1 9721
Protoss_Robotics_Support_Bay 1 9382
Protoss_Reaver 1 11576
Protoss_Observatory 1 12108
12317
