Protoss_Gateway 2 12623
Protoss_Assimilator 1 4229
Protoss_Cybernetics_Core 1 5796
Protoss_Dragoon 5 12484
Protoss_Robotics_Facility 1 9806
Singularity_Charge 1 9760
Protoss_Observatory 1 10670
Protoss_Nexus 1 12981
Protoss_Observer 1 12119
12981
