Protoss_Gateway 2 9263
Protoss_Assimilator 1 4390
Protoss_Cybernetics_Core 1 5651
Protoss_Dragoon 6 12174
Protoss_Nexus 1 12543
Singularity_Charge 1 9730
Protoss_Robotics_Facility 1 12601
12601
