Protoss_Gateway 3 11071
Protoss_Assimilator 1 4303
Protoss_Zealot 2 6058
Protoss_Cybernetics_Core 1 6110
Protoss_Dragoon 3 9616
Protoss_Citadel_of_Adun 1 8789
Protoss_Templar_Archives 1 10498
Protoss_Dark_Templar 3 12391
12391
