Protoss_Gateway 2 11762
Protoss_Assimilator 1 4217
Protoss_Cybernetics_Core 1 5669
Protoss_Dragoon 4 10482
Protoss_Nexus 1 11753
Protoss_Robotics_Facility 1 11768
Singularity_Charge 1 9868
11768
