Protoss_Gateway 3 12662
Protoss_Assimilator 1 4251
Protoss_Cybernetics_Core 1 5686
Protoss_Dragoon 5 12036
Protoss_Nexus 1 11598
Singularity_Charge 1 9616
Protoss_Robotics_Facility 1 11599
12662
