Protoss_Gateway 2 9116
Protoss_Assimilator 1 4505
Protoss_Cybernetics_Core 1 5933
Protoss_Dragoon 6 11593
Protoss_Robotics_Facility 1 10726
Singularity_Charge 1 9843
Protoss_Shuttle 1 12157
Protoss_Observatory 1 11734
Protoss_Zealot 1 12332
12332
