Protoss_Gateway 2 10687
Protoss_Assimilator 1 4615
Protoss_Cybernetics_Core 1 6195
Protoss_Dragoon 5 11912
Protoss_Robotics_Facility 1 8744
Protoss_Observatory 1 9606
Protoss_Observer 1 10678
Protoss_Shuttle 1 12465
12465
