Protoss_Gateway 3 10709
Protoss_Assimilator 1 4119
Protoss_Cybernetics_Core 1 5578
Protoss_Dragoon 6 11925
Protoss_Nexus 1 11036
Singularity_Charge 1 9376
Protoss_Robotics_Facility 1 11959
Protoss_Zealot 1 11189
11959
