Protoss_Gateway 2 10590
Protoss_Assimilator 2 5200
Protoss_Cybernetics_Core 1 6589
Protoss_Dragoon 1 7822
Protoss_Citadel_of_Adun 1 8392
Protoss_Templar_Archives 1 10035
Protoss_Dark_Templar 3 12391
Protoss_Forge 1 11966
12391
