Protoss_Nexus 1 7288
Protoss_Gateway 2 9580
Protoss_Assimilator 1 6861
Protoss_Cybernetics_Core 1 8509
Protoss_Dragoon 3 10939
Protoss_Robotics_Facility 1 12483
Protoss_Zealot 2 11932
12483
