Protoss_Gateway 2 7960
Protoss_Assimilator 1 4313
Protoss_Cybernetics_Core 1 5698
Protoss_Dragoon 8 12453
Protoss_Citadel_of_Adun 1 9993
Singularity_Charge 1 9638
Protoss_Templar_Archives 1 11589
12453
