Protoss_Gateway 1 4722
Protoss_Assimilator 1 4637
Protoss_Cybernetics_Core 1 6511
Protoss_Robotics_Facility 1 8798
Protoss_Dragoon 1 8166
Protoss_Robotics_Support_Bay 1 9521
Protoss_Shuttle 1 10269
Protoss_Zealot 3 11549
Protoss_Reaver 1 12051
12051
