Protoss_Gateway 1 4275
Protoss_Assimilator 1 4496
Protoss_Cybernetics_Core 1 5889
Protoss_Dragoon 4 10734
Protoss_Robotics_Facility 1 8590
Protoss_Shuttle 1 10372
Protoss_Observatory 1 10643
Protoss_Zealot 1 11595
Protoss_Observer 1 11739
Protoss_Robotics_Support_Bay 1 11820
11820
