Protoss_Nexus 1 6985
Protoss_Gateway 2 8057
Protoss_Assimilator 2 9152
Protoss_Cybernetics_Core 1 7488
Protoss_Zealot 1 7963
Protoss_Dragoon 7 12598
Protoss_Robotics_Facility 1 11799
12598
