Protoss_Assimilator 2 8868
Protoss_Gateway 1 4886
Protoss_Zealot 7 11710
Protoss_Nexus 1 9848
Protoss_Cybernetics_Core 1 9997
Protoss_Forge 1 10188
Protoss_Photon_Cannon 2 12559
12559
