Protoss_Gateway 1 4085
Protoss_Assimilator 1 4167
Protoss_Cybernetics_Core 1 5532
Protoss_Dragoon 5 11182
Protoss_Robotics_Facility 1 10230
Singularity_Charge 1 9555
Protoss_Shuttle 1 11628
Protoss_Zealot 2 12272
Protoss_Robotics_Support_Bay 1 11331
12272
