Protoss_Gateway 1 4328
Protoss_Assimilator 1 4347
Protoss_Cybernetics_Core 1 5809
Protoss_Robotics_Facility 1 8005
Protoss_Dragoon 4 11527
Protoss_Observatory 1 8804
Protoss_Observer 2 11944
Protoss_Nexus 1 13691
13691
