Protoss_Nexus 1 7193
Protoss_Gateway 2 9618
Protoss_Assimilator 2 12348
Protoss_Cybernetics_Core 1 7733
Protoss_Zealot 1 7795
Protoss_Dragoon 3 10822
Protoss_Citadel_of_Adun 1 11341
Protoss_Robotics_Facility 1 12610
12610
