Protoss_Gateway 2 6229
Protoss_Assimilator 1 4173
Protoss_Cybernetics_Core 1 5636
Protoss_Dragoon 7 12543
Protoss_Zealot 1 9124
Singularity_Charge 1 9300
Protoss_Nexus 1 13260
13260
