Protoss_Gateway 2 8641
Protoss_Zealot 1 5718
Protoss_Nexus 1 8301
Protoss_Assimilator 2 9918
Protoss_Cybernetics_Core 1 8367
Protoss_Dragoon 4 11425
Protoss_Citadel_of_Adun 1 11149
Protoss_Forge 1 11584
Protoss_Templar_Archives 1 12662
12662
