Protoss_Gateway 1 4331
Protoss_Assimilator 1 4597
Protoss_Cybernetics_Core 1 5963
Protoss_Dragoon 5 12534
Protoss_Nexus 1 12227
Singularity_Charge 1 10008
Protoss_Robotics_Facility 1 12212
12534
