Protoss_Gateway 1 4221
Protoss_Assimilator 1 4337
Protoss_Cybernetics_Core 1 5755
Protoss_Zealot 1 5592
Protoss_Dragoon 5 11927
Singularity_Charge 1 9726
Protoss_Nexus 1 12878
12878
