Protoss_Gateway 2 9854
Protoss_Assimilator 1 4234
Protoss_Cybernetics_Core 1 5630
Protoss_Dragoon 6 11375
Protoss_Robotics_Facility 1 9592
Protoss_Observatory 1 10354
Singularity_Charge 1 9654
Protoss_Observer 1 11783
Protoss_Nexus 1 14147
14147
