Protoss_Gateway 1 4242
Protoss_Assimilator 1 4283
Protoss_Cybernetics_Core 1 6144
Protoss_Dragoon 4 12156
Protoss_Robotics_Facility 1 9174
Protoss_Nexus 1 11643
Protoss_Observatory 1 9934
Protoss_Observer 2 12195
12195
