Protoss_Gateway 1 4293
Protoss_Assimilator 1 4631
Protoss_Cybernetics_Core 1 6178
Protoss_Dragoon 4 10869
Protoss_Robotics_Facility 1 10148
Protoss_Shuttle 1 11557
Singularity_Charge 1 10201
Protoss_Robotics_Support_Bay 1 10937
11557
