Protoss_Gateway 1 4217
Protoss_Assimilator 1 4426
Protoss_Cybernetics_Core 1 5829
Protoss_Dragoon 5 11823
Protoss_Nexus 1 11111
Protoss_Robotics_Facility 1 10883
Singularity_Charge 1 9938
11823
