Protoss_Gateway 2 12710
Protoss_Assimilator 1 4330
Protoss_Cybernetics_Core 1 5786
Protoss_Dragoon 5 12534
Protoss_Nexus 1 11408
Protoss_Robotics_Facility 1 11504
Singularity_Charge 1 9900
12710
