Protoss_Nexus 1 7158
Protoss_Forge 1 5698
Protoss_Gateway 3 12763
Protoss_Photon_Cannon 1 7312
Protoss_Assimilator 2 10212
Protoss_Zealot 2 9462
Protoss_Cybernetics_Core 1 9526
Protoss_Dragoon 2 11978
Protoss_Robotics_Facility 1 12567
12763
