Protoss_Gateway 2 7709
Protoss_Assimilator 1 4549
Protoss_Zealot 1 5336
Protoss_Cybernetics_Core 1 6497
Protoss_Dragoon 5 11012
Protoss_Citadel_of_Adun 1 10527
Singularity_Charge 1 10180
Protoss_Templar_Archives 1 12178
12178
