Protoss_Gateway 2 9643
Protoss_Assimilator 1 4524
Protoss_Cybernetics_Core 1 5831
Protoss_Dragoon 2 8166
Protoss_Citadel_of_Adun 1 8611
Protoss_Robotics_Facility 1 9592
Protoss_Zealot 1 9500
Protoss_Templar_Archives 1 10448
Protoss_Shuttle 1 11309
Protoss_Dark_Templar 2 11685
11685
