Protoss_Gateway 2 6738
Protoss_Assimilator 1 4464
Protoss_Cybernetics_Core 1 5756
Protoss_Dragoon 7 11736
Protoss_Robotics_Facility 1 11231
Singularity_Charge 1 9989
Protoss_Observatory 1 12079
12079
