Protoss_Gateway 2 10044
Protoss_Assimilator 1 4155
Protoss_Cybernetics_Core 1 5745
Protoss_Dragoon 6 11498
Protoss_Robotics_Facility 1 9636
Singularity_Charge 1 9663
Protoss_Observatory 1 10452
Protoss_Observer 1 11493
Protoss_Nexus 1 14133
14133
