Protoss_Gateway 2 12684
Protoss_Assimilator 1 4230
Protoss_Cybernetics_Core 1 5730
Protoss_Dragoon 5 12203
Protoss_Nexus 1 11731
Singularity_Charge 1 9830
Protoss_Robotics_Facility 1 12033
12684
