Protoss_Gateway 1 4248
Protoss_Assimilator 1 4192
Protoss_Cybernetics_Core 1 5805
Protoss_Dragoon 5 11823
Protoss_Robotics_Facility 1 9459
Protoss_Shuttle 1 10852
Singularity_Charge 1 9467
Protoss_Robotics_Support_Bay 1 10958
Protoss_Zealot 1 11680
Protoss_Reaver 1 12688
12688
