Protoss_Gateway 2 9384
Protoss_Assimilator 1 4256
Protoss_Cybernetics_Core 1 5929
Protoss_Dragoon 5 11208
Protoss_Robotics_Facility 1 11258
Singularity_Charge 1 9865
Protoss_Observatory 1 11982
Protoss_Nexus 1 14256
14256
