Protoss_Gateway 2 7527
Protoss_Assimilator 1 4340
Protoss_Zealot 2 6719
Protoss_Cybernetics_Core 1 6893
Protoss_Dragoon 6 10933
Singularity_Charge 1 10781
Protoss_Nexus 1 13841
13841
