Protoss_Gateway 2 6523
Protoss_Assimilator 1 4183
Protoss_Cybernetics_Core 1 5677
Protoss_Dragoon 6 12159
Protoss_Nexus 1 12779
Protoss_Robotics_Facility 1 12284
Singularity_Charge 1 10544
12779
