Protoss_Gateway 2 9953
Protoss_Assimilator 1 5123
Protoss_Zealot 3 7027
Protoss_Cybernetics_Core 1 7299
Protoss_Dragoon 3 11414
Protoss_Nexus 1 12693
Singularity_Charge 1 11043
Protoss_Robotics_Facility 1 13137
13137
