Protoss_Assimilator 1 4640
Protoss_Gateway 2 11996
Protoss_Cybernetics_Core 1 6838
Protoss_Robotics_Facility 1 8947
Protoss_Dragoon 1 9098
Protoss_Robotics_Support_Bay 1 9670
Protoss_Shuttle 1 10852
Protoss_Citadel_of_Adun 1 11582
Protoss_Reaver 1 12586
12586
