Protoss_Gateway 2 8134
Protoss_Assimilator 1 4344
Protoss_Cybernetics_Core 1 5729
Protoss_Dragoon 6 12285
Singularity_Charge 1 9800
Protoss_Nexus 1 12775
Protoss_Robotics_Facility 1 12346
12775
