Protoss_Gateway 2 8673
Protoss_Assimilator 1 4491
Protoss_Cybernetics_Core 1 5911
Protoss_Zealot 1 6277
Protoss_Dragoon 6 12475
Singularity_Charge 1 9642
Protoss_Nexus 1 12611
Protoss_Robotics_Facility 1 12281
12611
