Protoss_Gateway 2 9333
Protoss_Assimilator 1 4504
Protoss_Cybernetics_Core 1 5727
Protoss_Citadel_of_Adun 1 7239
Protoss_Dragoon 6 12297
Protoss_Nexus 1 12317
Protoss_Zealot 1 10709
Singularity_Charge 1 10000
Protoss_Robotics_Facility 1 12496
12496
