Protoss_Gateway 2 8127
Protoss_Assimilator 1 4166
Protoss_Cybernetics_Core 1 5595
Protoss_Zealot 1 5511
Protoss_Dragoon 6 12376
Singularity_Charge 1 9754
Protoss_Nexus 1 12640
Protoss_Robotics_Facility 1 12869
12869
