Protoss_Gateway 2 6482
Protoss_Assimilator 1 4144
Protoss_Cybernetics_Core 1 5642
Protoss_Dragoon 7 12230
Protoss_Nexus 1 11618
Singularity_Charge 1 9587
Protoss_Citadel_of_Adun 1 11529
Protoss_Robotics_Facility 1 12452
12452
