Protoss_Gateway 2 6353
Protoss_Assimilator 1 4248
Protoss_Cybernetics_Core 1 5803
Protoss_Dragoon 7 11940
Singularity_Charge 1 9601
Protoss_Nexus 1 12801
Protoss_Robotics_Facility 1 12990
12990
