Protoss_Gateway 1 4167
Protoss_Assimilator 1 4199
Protoss_Cybernetics_Core 1 5669
Protoss_Dragoon 4 10529
Protoss_Citadel_of_Adun 1 8969
Protoss_Templar_Archives 1 10504
Singularity_Charge 1 9710
Protoss_Nexus 1 13266
Protoss_Dark_Templar 1 11773
13266
