Protoss_Gateway 3 12072
Protoss_Assimilator 1 4360
Protoss_Cybernetics_Core 1 5910
Protoss_Dragoon 4 10734
Protoss_Nexus 1 12006
Singularity_Charge 1 9915
Protoss_Zealot 1 11677
12072
