Protoss_Gateway 1 4303
Protoss_Assimilator 1 4261
Protoss_Cybernetics_Core 1 5853
Protoss_Dragoon 6 12551
Protoss_Nexus 1 11736
Singularity_Charge 1 9713
Protoss_Citadel_of_Adun 1 11373
Protoss_Robotics_Facility 1 12642
12642
