Protoss_Gateway 1 4128
Protoss_Assimilator 1 4368
Protoss_Cybernetics_Core 1 5813
Protoss_Dragoon 5 11668
Protoss_Nexus 1 11683
Singularity_Charge 1 9850
Protoss_Robotics_Facility 2 12920
12920
