Protoss_Gateway 2 11101
Protoss_Assimilator 1 4359
Protoss_Cybernetics_Core 1 5658
Protoss_Zealot 1 5680
Protoss_Dragoon 6 12351
Protoss_Robotics_Facility 1 10639
Singularity_Charge 1 9858
Protoss_Shuttle 1 12062
Protoss_Robotics_Support_Bay 1 11691
12351
