Protoss_Gateway 2 10082
Protoss_Assimilator 1 4192
Protoss_Cybernetics_Core 1 5619
Protoss_Dragoon 3 9209
Protoss_Citadel_of_Adun 1 8450
Protoss_Templar_Archives 1 9898
Protoss_Robotics_Facility 1 11463
Protoss_Dark_Templar 3 12262
12262
