Protoss_Gateway 2 10236
Protoss_Assimilator 1 4246
Protoss_Cybernetics_Core 1 5832
Protoss_Dragoon 6 11632
Protoss_Robotics_Facility 1 9936
Singularity_Charge 1 9960
Protoss_Observatory 1 10757
Protoss_Observer 1 11995
11995
