Protoss_Gateway 2 10106
Protoss_Assimilator 1 4472
Protoss_Cybernetics_Core 1 5844
Protoss_Dragoon 5 11337
Protoss_Robotics_Facility 1 9787
Singularity_Charge 1 9862
Protoss_Observatory 1 10634
Protoss_Shuttle 1 11862
Protoss_Robotics_Support_Bay 1 12053
12053
