Protoss_Gateway 2 11424
Protoss_Assimilator 1 4198
Protoss_Cybernetics_Core 1 5660
Protoss_Dragoon 6 12499
Protoss_Nexus 1 10553
Protoss_Robotics_Facility 1 10690
Singularity_Charge 1 9882
12499
