Protoss_Gateway 2 11057
Protoss_Assimilator 1 4512
Protoss_Cybernetics_Core 1 5955
Protoss_Dragoon 6 12347
Protoss_Nexus 1 11870
Singularity_Charge 1 9997
Protoss_Robotics_Facility 1 12690
12690
