Protoss_Gateway 2 8186
Protoss_Assimilator 1 4553
Protoss_Cybernetics_Core 1 5841
Protoss_Dragoon 6 12598
Protoss_Nexus 1 12385
Singularity_Charge 1 9540
Protoss_Robotics_Facility 1 12834
12834
