Protoss_Gateway 3 12561
Protoss_Assimilator 2 5935
Protoss_Zealot 3 7413
Protoss_Cybernetics_Core 1 7577
Protoss_Dragoon 3 11173
Protoss_Citadel_of_Adun 1 10107
Protoss_Forge 1 11224
Protoss_Templar_Archives 1 11739
12561
