Protoss_Nexus 1 6748
Protoss_Gateway 3 11544
Protoss_Assimilator 1 6109
Protoss_Cybernetics_Core 1 7842
Protoss_Zealot 1 7720
Protoss_Dragoon 5 11679
Protoss_Robotics_Facility 1 11744
11744
