Protoss_Gateway 2 10310
Protoss_Assimilator 1 4352
Protoss_Cybernetics_Core 1 6030
Protoss_Dragoon 6 12124
Protoss_Robotics_Facility 1 10384
Singularity_Charge 1 9740
Protoss_Shuttle 1 12245
Protoss_Observatory 1 11707
12245
