Protoss_Gateway 1 4283
Protoss_Assimilator 1 4701
Protoss_Cybernetics_Core 1 5827
Protoss_Dragoon 3 9241
Protoss_Robotics_Facility 1 10285
Singularity_Charge 1 9900
Protoss_Shuttle 1 11709
Protoss_Robotics_Support_Bay 1 11060
Protoss_Zealot 1 11718
11718
