Protoss_Gateway 1 4126
Protoss_Assimilator 1 4160
Protoss_Cybernetics_Core 1 5606
Protoss_Dragoon 5 11750
Protoss_Robotics_Facility 1 9625
Singularity_Charge 1 9531
Protoss_Shuttle 1 11016
Protoss_Robotics_Support_Bay 1 10548
Protoss_Reaver 1 12688
Protoss_Zealot 1 12023
12688
