Protoss_Gateway 2 10313
Protoss_Assimilator 1 4126
Protoss_Cybernetics_Core 1 5712
Protoss_Zealot 1 5592
Protoss_Dragoon 6 11823
Protoss_Robotics_Facility 1 10169
Singularity_Charge 1 9666
Protoss_Observatory 1 10880
Protoss_Observer 1 11996
11996
