Protoss_Gateway 3 11474
Protoss_Assimilator 1 4521
Protoss_Cybernetics_Core 1 5961
Protoss_Dragoon 3 10342
Protoss_Citadel_of_Adun 1 10471
Singularity_Charge 1 10228
Protoss_Templar_Archives 1 11920
11920
