Protoss_Gateway 1 4114
Protoss_Assimilator 1 4395
Protoss_Cybernetics_Core 1 5664
Protoss_Dragoon 3 9402
Protoss_Robotics_Facility 1 8319
Protoss_Shuttle 1 9728
Protoss_Robotics_Support_Bay 1 9998
Protoss_Nexus 1 13099
Protoss_Zealot 1 11540
Protoss_Reaver 1 12580
13099
