Protoss_Gateway 1 4130
Protoss_Assimilator 1 4246
Protoss_Cybernetics_Core 1 5651
Protoss_Dragoon 5 12540
Protoss_Robotics_Facility 1 9717
Singularity_Charge 1 9640
Protoss_Observatory 1 10437
Protoss_Nexus 1 13421
Protoss_Observer 1 11616
13421
