Protoss_Gateway 1 4195
Protoss_Assimilator 2 4736
Protoss_Cybernetics_Core 1 5813
Protoss_Dragoon 5 10702
Protoss_Robotics_Facility 1 10175
Singularity_Charge 1 9935
Protoss_Observatory 1 11186
Protoss_Nexus 1 13331
Protoss_Observer 1 12307
Protoss_Shuttle 1 12816
13331
