Protoss_Gateway 2 10422
Protoss_Assimilator 2 8212
Protoss_Zealot 3 9222
Protoss_Nexus 1 9720
Protoss_Cybernetics_Core 1 9309
Protoss_Dragoon 1 10623
Protoss_Robotics_Facility 1 12083
12083
