Protoss_Gateway 2 12506
Protoss_Assimilator 1 4491
Protoss_Cybernetics_Core 1 5907
Protoss_Dragoon 5 11644
Protoss_Nexus 1 11861
Singularity_Charge 1 9839
Protoss_Robotics_Facility 1 12566
12566
