Protoss_Gateway 2 12716
Protoss_Assimilator 1 5014
Protoss_Zealot 2 6157
Protoss_Cybernetics_Core 1 6419
Protoss_Dragoon 5 12153
Protoss_Nexus 1 12060
Protoss_Robotics_Facility 1 11400
Singularity_Charge 1 10632
Protoss_Shuttle 1 12795
12795
