Protoss_Gateway 2 8632
Protoss_Assimilator 1 4147
Protoss_Cybernetics_Core 1 5639
Protoss_Dragoon 5 12262
Protoss_Nexus 1 11302
Protoss_Robotics_Facility 1 10999
Singularity_Charge 1 9900
Protoss_Observatory 1 11944
Protoss_Stargate 1 13049
13049
