Protoss_Gateway 2 12226
Protoss_Assimilator 1 4491
Protoss_Cybernetics_Core 1 5882
Protoss_Dragoon 5 11741
Protoss_Nexus 1 11779
Protoss_Robotics_Facility 1 12130
Singularity_Charge 1 10248
12226
