Protoss_Gateway 3 12592
Protoss_Assimilator 1 4343
Protoss_Cybernetics_Core 1 6065
Protoss_Dragoon 5 11826
Protoss_Nexus 1 12063
Protoss_Robotics_Facility 1 11992
Singularity_Charge 1 10143
12592
