Protoss_Gateway 2 12020
Protoss_Assimilator 1 4189
Protoss_Cybernetics_Core 1 5729
Protoss_Dragoon 5 12016
Protoss_Nexus 1 11156
Singularity_Charge 1 9803
Protoss_Robotics_Facility 1 12213
12213
