Protoss_Gateway 2 10217
Protoss_Assimilator 1 4498
Protoss_Cybernetics_Core 1 5780
Protoss_Dragoon 4 10781
Protoss_Citadel_of_Adun 1 9715
Protoss_Templar_Archives 1 11159
Singularity_Charge 1 9856
Protoss_Zealot 1 11194
Protoss_Dark_Templar 2 12393
12393
