Protoss_Assimilator 1 3715
Protoss_Gateway 1 4924
Protoss_Cybernetics_Core 1 6380
Protoss_Dragoon 4 11671
Protoss_Robotics_Facility 1 8700
Protoss_Shuttle 1 10394
Protoss_Observatory 1 11109
Singularity_Charge 1 11358
11671
