Protoss_Gateway 3 10540
Protoss_Assimilator 1 4403
Protoss_Cybernetics_Core 1 5841
Protoss_Dragoon 5 11755
Protoss_Zealot 2 11077
Singularity_Charge 1 9719
Protoss_Nexus 1 14124
14124
