Protoss_Gateway 2 10182
Protoss_Assimilator 1 4268
Protoss_Cybernetics_Core 1 5663
Protoss_Dragoon 6 12396
Protoss_Robotics_Facility 2 10172
Singularity_Charge 1 9736
Protoss_Observatory 1 10920
Protoss_Nexus 1 13418
Protoss_Observer 1 11938
13418
