Protoss_Gateway 2 10670
Protoss_Assimilator 1 4609
Protoss_Cybernetics_Core 1 6122
Protoss_Dragoon 5 12370
Protoss_Nexus 1 10199
Protoss_Zealot 1 11086
Protoss_Robotics_Facility 1 12649
12649
