Protoss_Gateway 2 5380
Protoss_Zealot 6 9912
Protoss_Assimilator 1 6541
Protoss_Cybernetics_Core 1 7650
Protoss_Dragoon 6 12268
Protoss_Forge 1 9273
Protoss_Shield_Battery 1 11393
12268
