Protoss_Gateway 1 4291
Protoss_Assimilator 1 4425
Protoss_Cybernetics_Core 1 5769
Protoss_Dragoon 5 12496
Protoss_Robotics_Facility 1 9824
Protoss_Shuttle 1 11379
Singularity_Charge 1 10014
Protoss_Robotics_Support_Bay 1 10787
Protoss_Reaver 1 12937
12937
