Protoss_Gateway 1 4315
Protoss_Assimilator 2 5821
Protoss_Zealot 3 7518
Protoss_Cybernetics_Core 1 7605
Protoss_Citadel_of_Adun 1 9282
Protoss_Dragoon 3 11281
Protoss_Templar_Archives 1 10780
Protoss_Nexus 1 13307
Protoss_Dark_Templar 1 11987
Protoss_Forge 1 12302
13307
