Protoss_Gateway 1 4284
Protoss_Assimilator 1 4826
Protoss_Cybernetics_Core 1 5952
Protoss_Dragoon 5 11591
Protoss_Nexus 1 12027
Singularity_Charge 1 10096
Protoss_Robotics_Facility 1 13102
13102
