Protoss_Gateway 2 8038
Protoss_Assimilator 1 4232
Protoss_Cybernetics_Core 1 5674
Protoss_Dragoon 6 11094
Singularity_Charge 1 9476
Protoss_Nexus 1 12365
Protoss_Robotics_Facility 1 13156
13156
