Protoss_Gateway 2 8317
Protoss_Assimilator 1 4249
Protoss_Cybernetics_Core 1 5831
Protoss_Dragoon 5 11199
Protoss_Citadel_of_Adun 1 9883
Protoss_Templar_Archives 1 11345
Singularity_Charge 1 9959
Protoss_Zealot 1 11209
11345
