Protoss_Gateway 2 11251
Protoss_Assimilator 1 4580
Protoss_Cybernetics_Core 1 6334
Protoss_Dragoon 5 12461
Protoss_Nexus 1 11897
Singularity_Charge 1 10254
Protoss_Robotics_Facility 1 12538
12538
