Protoss_Gateway 2 10689
Protoss_Assimilator 1 4186
Protoss_Cybernetics_Core 1 5759
Protoss_Dragoon 5 11744
Protoss_Robotics_Facility 1 9886
Singularity_Charge 1 9877
Protoss_Observatory 1 10670
11744
