Protoss_Gateway 2 10564
Protoss_Assimilator 1 4315
Protoss_Cybernetics_Core 1 5731
Protoss_Dragoon 5 12351
Protoss_Nexus 1 11620
Protoss_Robotics_Facility 1 11957
Singularity_Charge 1 10062
12351
