Protoss_Gateway 2 9854
Protoss_Zealot 1 5227
Protoss_Assimilator 1 5873
Protoss_Cybernetics_Core 1 6864
Protoss_Nexus 1 10218
Protoss_Dragoon 4 12121
Protoss_Robotics_Facility 1 11101
Protoss_Observatory 1 11997
12121
