Protoss_Gateway 1 4312
Protoss_Assimilator 1 4423
Protoss_Cybernetics_Core 1 6017
Protoss_Dragoon 5 12004
Protoss_Robotics_Facility 1 9949
Protoss_Observatory 1 10643
Singularity_Charge 1 10207
Protoss_Nexus 1 13222
Protoss_Observer 1 11721
13222
