Protoss_Gateway 1 4291
Protoss_Zealot 5 9383
Protoss_Forge 1 5730
Protoss_Photon_Cannon 2 8015
Protoss_Assimilator 1 8565
Protoss_Cybernetics_Core 1 9668
Protoss_Nexus 1 12387
Protoss_Robotics_Facility 1 12178
Protoss_Dragoon 1 11714
12387
