Protoss_Gateway 2 10073
Protoss_Zealot 2 6052
Protoss_Assimilator 1 5569
Protoss_Cybernetics_Core 1 7189
Protoss_Dragoon 5 11861
Protoss_Robotics_Facility 1 10857
Protoss_Shuttle 1 12251
Singularity_Charge 1 10980
12251
