Protoss_Nexus 1 7199
Protoss_Gateway 2 8127
Protoss_Assimilator 2 11794
Protoss_Cybernetics_Core 1 7638
Protoss_Zealot 1 7413
Protoss_Dragoon 5 11750
Protoss_Robotics_Facility 1 12603
12603
