Protoss_Gateway 2 10521
Protoss_Assimilator 1 4564
Protoss_Cybernetics_Core 1 5910
Protoss_Dragoon 6 12071
Protoss_Robotics_Facility 1 10097
Singularity_Charge 1 10136
Protoss_Observatory 1 10861
Protoss_Observer 1 11892
12071
