Protoss_Nexus 1 6820
Protoss_Gateway 2 7834
Protoss_Assimilator 1 5952
Protoss_Cybernetics_Core 1 7442
Protoss_Zealot 1 7671
Protoss_Dragoon 8 12572
Protoss_Robotics_Facility 1 12812
12812
