Protoss_Gateway 1 4106
Protoss_Assimilator 1 4293
Protoss_Cybernetics_Core 1 5630
Protoss_Dragoon 5 12191
Protoss_Robotics_Facility 1 9812
Singularity_Charge 1 9692
Protoss_Observatory 1 10573
Protoss_Nexus 1 13025
Protoss_Shuttle 1 11964
13025
