Protoss_Gateway 2 6456
Protoss_Assimilator 1 4398
Protoss_Cybernetics_Core 1 5657
Protoss_Dragoon 6 10500
Protoss_Citadel_of_Adun 1 10234
Singularity_Charge 1 9751
Protoss_Templar_Archives 1 11928
11928
