Protoss_Gateway 2 10148
Protoss_Assimilator 1 4270
Protoss_Cybernetics_Core 1 5730
Protoss_Dragoon 6 11732
Protoss_Robotics_Facility 1 9809
Singularity_Charge 1 9784
Protoss_Observatory 1 10866
Protoss_Observer 1 11914
11914
