Protoss_Gateway 2 9416
Protoss_Assimilator 1 4501
Protoss_Cybernetics_Core 1 5906
Protoss_Dragoon 7 11861
Protoss_Robotics_Facility 1 10807
Singularity_Charge 1 9975
Protoss_Observatory 1 11678
11861
