Protoss_Gateway 1 4265
Protoss_Assimilator 1 4549
Protoss_Cybernetics_Core 1 5977
Protoss_Dragoon 5 12600
Protoss_Nexus 1 11649
Singularity_Charge 1 10055
Protoss_Robotics_Facility 1 12651
12651
