Protoss_Nexus 2 13214
Protoss_Gateway 1 5873
Protoss_Assimilator 1 6311
Protoss_Zealot 1 6886
Protoss_Cybernetics_Core 1 7777
Protoss_Citadel_of_Adun 1 9279
Protoss_Dragoon 1 9153
Protoss_Forge 1 9812
Protoss_Templar_Archives 1 10846
Protoss_Photon_Cannon 1 11902
Protoss_Dark_Templar 1 12101
13214
