Protoss_Gateway 1 4065
Protoss_Assimilator 1 4363
Protoss_Cybernetics_Core 1 6036
Protoss_Dragoon 5 11826
Protoss_Robotics_Facility 1 9774
Singularity_Charge 1 9809
Protoss_Shuttle 1 11268
Protoss_Robotics_Support_Bay 1 10752
Protoss_Reaver 1 12826
12826
