Protoss_Assimilator 1 3450
Protoss_Gateway 2 11169
Protoss_Cybernetics_Core 1 6084
Protoss_Dragoon 3 9671
Protoss_Citadel_of_Adun 1 9506
Protoss_Robotics_Facility 1 11003
Protoss_Templar_Archives 1 10949
Singularity_Charge 1 9751
Protoss_Dark_Templar 2 12414
Protoss_Shuttle 1 12497
Protoss_Observatory 1 12069
12497
