Protoss_Gateway 2 9424
Protoss_Assimilator 1 4179
Protoss_Cybernetics_Core 1 5909
Protoss_Dragoon 1 7105
Protoss_Citadel_of_Adun 1 7568
Protoss_Robotics_Facility 1 9102
Protoss_Templar_Archives 1 9952
Protoss_Shuttle 1 10504
Protoss_Dark_Templar 2 11173
Protoss_Nexus 1 14146
14146
