Protoss_Gateway 2 10389
Protoss_Assimilator 1 4346
Protoss_Cybernetics_Core 1 5651
Protoss_Zealot 1 5654
Protoss_Dragoon 5 11615
Protoss_Robotics_Facility 1 10125
Singularity_Charge 1 10087
Protoss_Observatory 1 10819
Protoss_Observer 1 11856
Protoss_Nexus 1 14121
14121
