Protoss_Gateway 2 8210
Protoss_Assimilator 1 4388
Protoss_Cybernetics_Core 1 5865
Protoss_Nexus 1 8961
Protoss_Dragoon 6 11662
Protoss_Zealot 1 8604
Protoss_Citadel_of_Adun 1 12236
12236
