Protoss_Gateway 2 11020
Protoss_Assimilator 1 4252
Protoss_Cybernetics_Core 1 5746
Protoss_Dragoon 5 12364
Protoss_Nexus 1 10869
Protoss_Robotics_Facility 1 10705
Singularity_Charge 1 10040
Protoss_Observatory 1 11485
12364
