Protoss_Gateway 2 8348
Protoss_Assimilator 1 4255
Protoss_Cybernetics_Core 1 5727
Protoss_Dragoon 5 11477
Protoss_Robotics_Facility 1 10115
Singularity_Charge 1 9967
Protoss_Observatory 1 10968
Protoss_Nexus 1 13948
Protoss_Observer 1 12149
13948
