Protoss_Gateway 2 12015
Protoss_Assimilator 1 4237
Protoss_Cybernetics_Core 1 5654
Protoss_Dragoon 5 11568
Protoss_Nexus 1 11974
Protoss_Robotics_Facility 1 11705
Singularity_Charge 1 9818
12015
