Protoss_Gateway 2 10391
Protoss_Zealot 4 8326
Protoss_Forge 1 5809
Protoss_Photon_Cannon 3 10683
Protoss_Assimilator 1 8610
Protoss_Cybernetics_Core 1 9871
Protoss_Dragoon 3 12590
12590
