Protoss_Gateway 1 4252
Protoss_Assimilator 2 4949
Protoss_Zealot 2 5958
Protoss_Cybernetics_Core 1 5944
Protoss_Dragoon 4 11697
Protoss_Robotics_Facility 1 8887
Protoss_Shuttle 1 10346
Protoss_Robotics_Support_Bay 1 10449
Protoss_Reaver 1 12211
Protoss_Observatory 1 11978
12211
