Protoss_Gateway 1 4170
Protoss_Assimilator 1 4461
Protoss_Cybernetics_Core 1 5777
Protoss_Dragoon 5 12136
Protoss_Robotics_Facility 1 9816
Singularity_Charge 1 9777
Protoss_Observatory 1 10662
Protoss_Nexus 1 12918
Protoss_Observer 1 11701
12918
