Protoss_Gateway 1 4110
Protoss_Assimilator 1 4347
Protoss_Cybernetics_Core 1 5727
Protoss_Dragoon 5 11548
Protoss_Nexus 1 11589
Singularity_Charge 1 9660
Protoss_Robotics_Facility 1 12175
12175
