Protoss_Gateway 2 10258
Protoss_Assimilator 1 4429
Protoss_Cybernetics_Core 1 5846
Protoss_Dragoon 7 12560
Protoss_Robotics_Facility 1 10216
Singularity_Charge 1 10093
Protoss_Shuttle 1 11701
Protoss_Observatory 1 11436
12560
