Protoss_Gateway 1 4201
Protoss_Assimilator 1 4466
Protoss_Cybernetics_Core 1 5756
Protoss_Dragoon 5 11890
Protoss_Nexus 1 11539
Singularity_Charge 1 9812
Protoss_Robotics_Facility 1 12042
12042
