Protoss_Gateway 2 10957
Protoss_Assimilator 1 4372
Protoss_Cybernetics_Core 1 5846
Protoss_Dragoon 5 12151
Protoss_Nexus 1 11460
Singularity_Charge 1 9771
Protoss_Robotics_Facility 1 11978
12151
