Protoss_Gateway 2 4752
Protoss_Zealot 6 7735
Protoss_Forge 1 7395
Protoss_Photon_Cannon 3 11840
Protoss_Assimilator 1 8976
Protoss_Cybernetics_Core 1 10370
Protoss_Citadel_of_Adun 1 12409
12409
