Protoss_Gateway 2 9975
Protoss_Assimilator 1 4368
Protoss_Cybernetics_Core 1 5828
Protoss_Dragoon 6 12022
Protoss_Robotics_Facility 1 9636
Singularity_Charge 1 9730
Protoss_Observatory 1 10449
Protoss_Nexus 1 13007
Protoss_Observer 1 11912
13007
