Protoss_Gateway 2 6570
Protoss_Assimilator 1 4653
Protoss_Cybernetics_Core 1 5881
Protoss_Dragoon 6 10980
Protoss_Citadel_of_Adun 1 10164
Singularity_Charge 1 9970
Protoss_Templar_Archives 1 11607
Protoss_Zealot 2 11841
11841
