Protoss_Gateway 2 4726
Protoss_Forge 1 5587
Protoss_Zealot 2 6465
Protoss_Photon_Cannon 2 8510
Protoss_Assimilator 1 8085
Protoss_Cybernetics_Core 1 9168
Protoss_Dragoon 5 12177
12177
