Protoss_Gateway 1 4217
Protoss_Zealot 3 6951
Protoss_Assimilator 1 5486
Protoss_Cybernetics_Core 1 7262
Protoss_Robotics_Facility 1 9266
Protoss_Dragoon 3 11106
Protoss_Shuttle 1 10714
Protoss_Robotics_Support_Bay 1 10333
Protoss_Reaver 1 12272
Protoss_Observatory 1 12092
12272
