Protoss_Gateway 1 4214
Protoss_Assimilator 1 4205
Protoss_Cybernetics_Core 1 5739
Protoss_Zealot 2 11689
Protoss_Dragoon 4 10711
Protoss_Robotics_Facility 1 9895
Singularity_Charge 1 9408
Protoss_Shuttle 1 11361
Protoss_Robotics_Support_Bay 1 10794
Protoss_Reaver 1 13025
13025
