Protoss_Gateway 2 6244
Protoss_Assimilator 1 4502
Protoss_Cybernetics_Core 1 5623
Protoss_Dragoon 3 8117
Protoss_Citadel_of_Adun 1 9134
Protoss_Templar_Archives 1 10581
Singularity_Charge 1 9765
Protoss_Nexus 1 13373
Protoss_Dark_Templar 1 11791
Protoss_Stargate 1 12681
13373
