Protoss_Gateway 1 4179
Protoss_Assimilator 1 4413
Protoss_Zealot 8 11835
Protoss_Forge 1 6833
Protoss_Photon_Cannon 2 8720
Protoss_Cybernetics_Core 1 11189
Protoss_Nexus 1 13388
13388
