Protoss_Gateway 2 8765
Protoss_Zealot 2 6075
Protoss_Nexus 1 8986
Protoss_Assimilator 2 12301
Protoss_Cybernetics_Core 1 8297
Protoss_Dragoon 4 11123
Protoss_Robotics_Facility 1 12595
12595
