Protoss_Assimilator 1 3343
Protoss_Gateway 2 9882
Protoss_Cybernetics_Core 1 6105
Protoss_Dragoon 2 8872
Protoss_Citadel_of_Adun 1 8677
Protoss_Robotics_Facility 1 9298
Protoss_Templar_Archives 1 10237
Protoss_Shuttle 1 10954
Protoss_Dark_Templar 2 11466
11466
