Protoss_Gateway 1 4183
Protoss_Zealot 2 6787
Protoss_Assimilator 1 5755
Protoss_Cybernetics_Core 1 6908
Protoss_Dragoon 4 11553
Protoss_Nexus 1 12811
Singularity_Charge 1 11387
12811
