Protoss_Gateway 2 10447
Protoss_Assimilator 1 4420
Protoss_Cybernetics_Core 1 5800
Protoss_Dragoon 2 8893
Protoss_Citadel_of_Adun 1 9238
Protoss_Robotics_Facility 1 10788
Protoss_Templar_Archives 1 10868
Protoss_Shuttle 1 12192
Protoss_Dark_Templar 2 12077
12192
