Protoss_Gateway 2 8364
Protoss_Assimilator 1 4491
Protoss_Cybernetics_Core 1 5870
Protoss_Dragoon 4 9753
Singularity_Charge 1 9906
Protoss_Nexus 1 13234
Protoss_Citadel_of_Adun 1 12110
13234
