Protoss_Gateway 2 12103
Protoss_Assimilator 1 4158
Protoss_Cybernetics_Core 1 5588
Protoss_Dragoon 5 12189
Protoss_Nexus 1 11217
Singularity_Charge 1 9496
Protoss_Robotics_Facility 1 11452
12189
