Protoss_Gateway 1 4164
Protoss_Assimilator 1 4363
Protoss_Cybernetics_Core 1 5790
Protoss_Robotics_Facility 1 8067
Protoss_Dragoon 2 8732
Protoss_Shuttle 1 9465
Protoss_Robotics_Support_Bay 1 9113
Protoss_Zealot 2 10703
Protoss_Reaver 1 11131
Protoss_Nexus 1 13726
Protoss_Observatory 1 12127
13726
