Protoss_Gateway 1 4217
Protoss_Assimilator 1 4441
Protoss_Cybernetics_Core 1 5794
Protoss_Robotics_Facility 1 8035
Protoss_Dragoon 4 12066
Protoss_Shuttle 1 9429
Protoss_Robotics_Support_Bay 1 9809
Protoss_Zealot 1 10755
Protoss_Reaver 1 11567
Protoss_Observatory 1 11884
12066
