Protoss_Gateway 1 4147
Protoss_Assimilator 1 4243
Protoss_Cybernetics_Core 1 5636
Protoss_Dragoon 5 11826
Protoss_Nexus 1 11076
Protoss_Robotics_Facility 1 10991
Singularity_Charge 1 9294
Protoss_Shuttle 1 12394
Protoss_Robotics_Support_Bay 1 11755
12394
