Protoss_Gateway 2 7411
Protoss_Zealot 1 5074
Protoss_Assimilator 1 5146
Protoss_Cybernetics_Core 1 6500
Protoss_Dragoon 7 12393
Protoss_Nexus 1 11817
Singularity_Charge 1 10433
Protoss_Robotics_Facility 1 12591
12591
