Protoss_Gateway 2 12683
Protoss_Assimilator 1 4368
Protoss_Cybernetics_Core 1 5666
Protoss_Dragoon 5 11594
Protoss_Robotics_Facility 1 9733
Singularity_Charge 1 9698
Protoss_Nexus 1 12950
Protoss_Observatory 1 11391
12950
