Protoss_Gateway 2 7474
Protoss_Assimilator 1 4460
Protoss_Cybernetics_Core 1 5827
Protoss_Zealot 1 5806
Protoss_Dragoon 3 8793
Protoss_Stargate 2 11489
Protoss_Fleet_Beacon 1 10631
Protoss_Carrier 1 14392
14392
