Protoss_Gateway 1 4208
Protoss_Assimilator 1 4499
Protoss_Cybernetics_Core 1 5920
Protoss_Zealot 1 5721
Protoss_Dragoon 4 11676
Protoss_Nexus 1 12040
Singularity_Charge 1 9970
Protoss_Robotics_Facility 1 12185
12185
