Protoss_Gateway 2 12734
Protoss_Assimilator 1 4431
Protoss_Zealot 2 6181
Protoss_Cybernetics_Core 1 7439
Protoss_Dragoon 4 12139
Protoss_Nexus 1 12268
Protoss_Robotics_Facility 1 12311
12734
