Protoss_Gateway 2 8401
Protoss_Assimilator 1 4543
Protoss_Cybernetics_Core 1 6014
Protoss_Dragoon 6 10848
Singularity_Charge 1 9792
Protoss_Nexus 1 13597
Protoss_Citadel_of_Adun 1 12595
13597
