Protoss_Gateway 1 4286
Protoss_Assimilator 1 4517
Protoss_Cybernetics_Core 1 5942
Protoss_Zealot 1 5733
Protoss_Dragoon 5 12203
Protoss_Robotics_Facility 1 10040
Protoss_Observatory 1 10733
Singularity_Charge 1 10190
Protoss_Nexus 1 13489
Protoss_Observer 1 11783
13489
