Protoss_Gateway 2 10057
Protoss_Assimilator 2 5165
Protoss_Cybernetics_Core 1 6501
Protoss_Dragoon 2 9417
Protoss_Citadel_of_Adun 1 9106
Protoss_Templar_Archives 1 10884
Protoss_Zealot 1 10422
Singularity_Charge 1 10544
Protoss_Dark_Templar 2 12297
12297
