Protoss_Gateway 1 4062
Protoss_Assimilator 1 4177
Protoss_Cybernetics_Core 1 5796
Protoss_Dragoon 4 10842
Protoss_Robotics_Facility 1 8348
Protoss_Observatory 1 9074
Protoss_Observer 2 10992
Protoss_Nexus 1 13781
13781
