Protoss_Gateway 2 10237
Protoss_Assimilator 1 4400
Protoss_Cybernetics_Core 1 5783
Protoss_Dragoon 6 11673
Protoss_Robotics_Facility 1 9783
Singularity_Charge 1 9783
Protoss_Observatory 1 10516
Protoss_Observer 1 11552
11673
