Protoss_Gateway 2 9348
Protoss_Assimilator 1 4395
Protoss_Cybernetics_Core 1 5748
Protoss_Dragoon 7 11855
Protoss_Robotics_Facility 1 10448
Singularity_Charge 1 9839
Protoss_Shuttle 1 12131
Protoss_Robotics_Support_Bay 1 11501
12131
