Protoss_Gateway 2 5647
Protoss_Assimilator 3 11581
Protoss_Zealot 7 12263
Protoss_Nexus 1 10677
Protoss_Cybernetics_Core 1 9961
Protoss_Citadel_of_Adun 1 12189
Protoss_Dragoon 2 12587
12587
