Protoss_Gateway 2 12188
Protoss_Assimilator 1 4373
Protoss_Cybernetics_Core 1 5812
Protoss_Dragoon 5 11556
Protoss_Nexus 1 11618
Protoss_Robotics_Facility 1 11506
Singularity_Charge 1 9897
12188
