Protoss_Assimilator 3 12274
Protoss_Gateway 2 11309
Protoss_Zealot 3 7726
Protoss_Nexus 1 9276
Protoss_Forge 1 8423
Protoss_Photon_Cannon 1 9671
Protoss_Cybernetics_Core 1 10373
Protoss_Dragoon 1 11571
Protoss_Robotics_Facility 1 12862
12862
