Protoss_Gateway 1 4141
Protoss_Assimilator 1 4180
Protoss_Cybernetics_Core 1 5589
Protoss_Zealot 1 5590
Protoss_Dragoon 5 11559
Protoss_Robotics_Facility 1 9818
Singularity_Charge 1 9818
Protoss_Shuttle 1 11265
Protoss_Robotics_Support_Bay 1 10983
Protoss_Reaver 1 12823
12823
