Protoss_Gateway 1 4126
Protoss_Assimilator 1 4243
Protoss_Cybernetics_Core 1 5803
Protoss_Dragoon 5 11530
Protoss_Nexus 1 11875
Singularity_Charge 1 9877
Protoss_Robotics_Facility 1 12136
12136
