Protoss_Gateway 1 4182
Protoss_Assimilator 1 4524
Protoss_Cybernetics_Core 1 5949
Protoss_Zealot 1 5873
Protoss_Dragoon 4 11925
Protoss_Robotics_Facility 1 10009
Protoss_Nexus 1 12513
Singularity_Charge 1 9748
Protoss_Shuttle 1 11549
Protoss_Observatory 1 11054
12513
