Protoss_Gateway 2 12105
Protoss_Assimilator 1 4589
Protoss_Zealot 2 6646
Protoss_Cybernetics_Core 1 6889
Protoss_Dragoon 3 10751
Protoss_Nexus 1 11519
Protoss_Citadel_of_Adun 1 10833
Protoss_Robotics_Facility 1 11976
Protoss_Templar_Archives 1 12421
12421
