Protoss_Gateway 2 11458
Protoss_Assimilator 1 4542
Protoss_Cybernetics_Core 1 5875
Protoss_Dragoon 5 12232
Protoss_Robotics_Facility 1 10381
Singularity_Charge 1 10509
Protoss_Observatory 1 11256
12232
