Protoss_Nexus 1 6726
Protoss_Gateway 2 7735
Protoss_Assimilator 1 5733
Protoss_Cybernetics_Core 1 7236
Protoss_Zealot 1 7934
Protoss_Dragoon 6 12382
Protoss_Robotics_Facility 1 11725
12382
