Protoss_Gateway 1 4363
Protoss_Assimilator 1 4836
Protoss_Cybernetics_Core 1 6004
Protoss_Dragoon 4 10921
Protoss_Robotics_Facility 1 10178
Protoss_Shuttle 1 11642
Protoss_Observatory 1 10997
Singularity_Charge 1 10459
Protoss_Robotics_Support_Bay 1 11289
Protoss_Zealot 1 12017
12017
