Protoss_Gateway 1 4182
Protoss_Assimilator 1 4193
Protoss_Cybernetics_Core 1 5708
Protoss_Zealot 1 5841
Protoss_Dragoon 5 12306
Protoss_Nexus 1 11237
Singularity_Charge 1 9780
Protoss_Robotics_Facility 1 11770
12306
