Protoss_Gateway 2 8029
Protoss_Assimilator 1 4271
Protoss_Cybernetics_Core 1 5988
Protoss_Dragoon 6 12115
Protoss_Nexus 1 11238
Singularity_Charge 1 9701
Protoss_Zealot 2 10995
12115
