Protoss_Gateway 2 12077
Protoss_Zealot 2 6962
Protoss_Assimilator 1 5575
Protoss_Cybernetics_Core 1 6778
Protoss_Dragoon 4 11457
Protoss_Robotics_Facility 1 11385
Singularity_Charge 1 11112
12077
