Protoss_Gateway 2 10059
Protoss_Zealot 2 8537
Protoss_Nexus 1 8817
Protoss_Assimilator 2 11347
Protoss_Cybernetics_Core 1 8497
Protoss_Dragoon 2 10889
Protoss_Robotics_Facility 1 11416
Protoss_Shuttle 1 12833
12833
