Protoss_Gateway 2 10944
Protoss_Assimilator 1 4179
Protoss_Cybernetics_Core 1 5626
Protoss_Zealot 1 5610
Protoss_Dragoon 6 12405
Protoss_Robotics_Facility 1 9677
Protoss_Shuttle 1 11282
Singularity_Charge 1 9918
Protoss_Robotics_Support_Bay 1 10740
12405
