Protoss_Gateway 2 10091
Protoss_Assimilator 1 4372
Protoss_Cybernetics_Core 1 5777
Protoss_Dragoon 6 11820
Protoss_Robotics_Facility 1 9841
Singularity_Charge 1 9783
Protoss_Observatory 1 10946
Protoss_Observer 1 11961
11961
