Protoss_Gateway 1 4135
Protoss_Assimilator 1 4242
Protoss_Cybernetics_Core 1 5645
Protoss_Robotics_Facility 1 7767
Protoss_Dragoon 5 11963
Protoss_Observatory 1 8690
Protoss_Observer 1 10056
Protoss_Nexus 1 13363
13363
