Protoss_Gateway 2 11695
Protoss_Assimilator 1 4400
Protoss_Cybernetics_Core 1 5714
Protoss_Dragoon 5 11624
Protoss_Nexus 1 11777
Singularity_Charge 1 9967
Protoss_Robotics_Facility 1 11998
11998
