Protoss_Gateway 2 8107
Protoss_Assimilator 1 4306
Protoss_Cybernetics_Core 1 5657
Protoss_Dragoon 6 11720
Singularity_Charge 1 9809
Protoss_Nexus 1 12816
Protoss_Robotics_Facility 1 13001
13001
