Protoss_Gateway 2 10010
Protoss_Assimilator 2 4949
Protoss_Cybernetics_Core 1 6405
Protoss_Zealot 1 6763
Protoss_Dragoon 3 10269
Protoss_Shield_Battery 1 9205
Protoss_Citadel_of_Adun 1 11088
Singularity_Charge 1 10117
Protoss_Nexus 1 13638
Protoss_Templar_Archives 1 12737
13638
