Protoss_Gateway 1 4142
Protoss_Assimilator 1 5268
Protoss_Cybernetics_Core 1 5837
Protoss_Dragoon 4 10680
Protoss_Nexus 1 9586
Protoss_Robotics_Facility 1 10661
Protoss_Shuttle 1 12064
Protoss_Robotics_Support_Bay 1 11717
Protoss_Zealot 1 12172
12172
