Protoss_Gateway 1 4196
Protoss_Assimilator 1 4385
Protoss_Cybernetics_Core 1 5688
Protoss_Zealot 1 5666
Protoss_Dragoon 4 10705
Protoss_Nexus 2 13890
Singularity_Charge 1 9944
Protoss_Citadel_of_Adun 1 11528
13890
