Protoss_Gateway 2 9424
Protoss_Assimilator 1 4350
Protoss_Zealot 2 6775
Protoss_Cybernetics_Core 1 6795
Protoss_Dragoon 4 10813
Protoss_Nexus 1 13638
Singularity_Charge 1 11056
13638
