Protoss_Gateway 1 4152
Protoss_Assimilator 1 4458
Protoss_Cybernetics_Core 1 5623
Protoss_Dragoon 5 11546
Protoss_Robotics_Facility 1 9781
Singularity_Charge 1 9702
Protoss_Observatory 1 10516
Protoss_Nexus 1 13012
Protoss_Observer 1 11530
13012
