Protoss_Gateway 2 12326
Protoss_Assimilator 1 4135
Protoss_Cybernetics_Core 1 5609
Protoss_Zealot 1 5437
Protoss_Dragoon 5 12449
Protoss_Robotics_Facility 1 9614
Protoss_Nexus 1 12447
Singularity_Charge 1 9754
Protoss_Observatory 1 10494
Protoss_Observer 1 11563
12449
