Protoss_Nexus 1 6817
Protoss_Gateway 3 12067
Protoss_Assimilator 1 5922
Protoss_Cybernetics_Core 1 7678
Protoss_Zealot 1 7899
Protoss_Dragoon 6 12472
Protoss_Robotics_Facility 1 11556
12472
