Protoss_Nexus 1 6631
Protoss_Gateway 2 7749
Protoss_Assimilator 1 5679
Protoss_Cybernetics_Core 1 7155
Protoss_Zealot 1 7662
Protoss_Dragoon 6 11744
Protoss_Robotics_Facility 1 11856
Singularity_Charge 1 11024
11856
