Protoss_Gateway 2 6942
Protoss_Assimilator 1 4644
Protoss_Cybernetics_Core 1 6374
Protoss_Dragoon 4 10154
Protoss_Robotics_Facility 1 10514
Singularity_Charge 1 10146
Protoss_Observatory 1 11330
Protoss_Nexus 1 13664
13664
