Protoss_Gateway 2 5575
Protoss_Assimilator 2 10733
Protoss_Zealot 8 12222
Protoss_Nexus 1 10692
Protoss_Forge 1 9187
Protoss_Photon_Cannon 2 10675
Protoss_Cybernetics_Core 1 12298
12298
