Protoss_Gateway 1 4171
Protoss_Assimilator 1 4647
Protoss_Cybernetics_Core 1 5622
Protoss_Dragoon 3 9215
Protoss_Citadel_of_Adun 1 8794
Protoss_Templar_Archives 1 10394
Protoss_Nexus 1 12649
Singularity_Charge 1 9953
Protoss_Dark_Templar 1 11673
Protoss_Robotics_Facility 1 13064
13064
