Protoss_Gateway 1 4190
Protoss_Assimilator 1 4172
Protoss_Cybernetics_Core 1 5749
Protoss_Zealot 2 10155
Protoss_Robotics_Facility 1 7744
Protoss_Dragoon 5 12434
Protoss_Shuttle 1 9154
Protoss_Robotics_Support_Bay 1 9045
Protoss_Reaver 1 10783
Protoss_Observatory 1 10454
Protoss_Observer 1 11607
12434
