Protoss_Gateway 2 9226
Protoss_Assimilator 1 4293
Protoss_Cybernetics_Core 1 5729
Protoss_Dragoon 6 12415
Protoss_Robotics_Facility 1 10786
Singularity_Charge 1 10033
Protoss_Zealot 2 11295
12415
