Protoss_Gateway 2 11958
Protoss_Assimilator 1 4741
Protoss_Cybernetics_Core 1 6162
Protoss_Dragoon 5 12159
Protoss_Nexus 1 11493
Protoss_Citadel_of_Adun 1 10865
Singularity_Charge 1 10076
Protoss_Templar_Archives 1 12482
12482
