Protoss_Gateway 2 10464
Protoss_Assimilator 1 4647
Protoss_Cybernetics_Core 1 5933
Protoss_Dragoon 5 11985
Protoss_Robotics_Facility 1 8802
Protoss_Observatory 1 10127
Protoss_Observer 2 12251
12251
