Protoss_Gateway 2 6403
Protoss_Assimilator 1 4135
Protoss_Cybernetics_Core 1 5649
Protoss_Dragoon 5 9443
Singularity_Charge 1 9417
Protoss_Nexus 1 12693
Protoss_Robotics_Facility 1 12671
12693
