Protoss_Nexus 1 6807
Protoss_Gateway 2 7919
Protoss_Assimilator 2 11680
Protoss_Cybernetics_Core 1 7444
Protoss_Zealot 1 7949
Protoss_Dragoon 6 11632
Protoss_Robotics_Facility 1 12976
12976
