Protoss_Gateway 1 4337
Protoss_Assimilator 1 4337
Protoss_Cybernetics_Core 1 5786
Protoss_Dragoon 6 12531
Protoss_Nexus 1 12581
Singularity_Charge 1 9961
Protoss_Stargate 1 11727
12581
