Protoss_Gateway 1 4220
Protoss_Assimilator 1 4420
Protoss_Cybernetics_Core 1 5840
Protoss_Dragoon 5 12183
Protoss_Robotics_Facility 1 8436
Protoss_Shuttle 1 9896
Protoss_Robotics_Support_Bay 1 9396
Protoss_Reaver 1 11744
12183
