Protoss_Gateway 1 4199
Protoss_Assimilator 1 4192
Protoss_Cybernetics_Core 1 5670
Protoss_Zealot 1 5563
Protoss_Robotics_Facility 1 7889
Protoss_Dragoon 3 11823
Protoss_Shuttle 1 9286
Protoss_Robotics_Support_Bay 1 8897
Protoss_Reaver 1 10844
Protoss_Observatory 1 10514
11823
