Protoss_Nexus 1 6726
Protoss_Gateway 3 12049
Protoss_Assimilator 1 5771
Protoss_Cybernetics_Core 1 7372
Protoss_Zealot 2 11118
Protoss_Dragoon 6 12291
Protoss_Robotics_Facility 1 11398
12291
