Protoss_Assimilator 2 4940
Protoss_Gateway 1 4937
Protoss_Cybernetics_Core 1 6391
Protoss_Zealot 1 6462
Protoss_Dragoon 4 11551
Protoss_Nexus 2 14171
Singularity_Charge 1 10254
14171
