Protoss_Gateway 2 10202
Protoss_Zealot 3 7372
Protoss_Assimilator 1 5619
Protoss_Cybernetics_Core 1 6801
Protoss_Dragoon 3 11278
Protoss_Nexus 1 13489
Singularity_Charge 1 11159
Protoss_Robotics_Facility 1 13115
13489
