Protoss_Gateway 2 9283
Protoss_Assimilator 1 4444
Protoss_Cybernetics_Core 1 5669
Protoss_Dragoon 7 12525
Protoss_Nexus 1 11787
Singularity_Charge 1 9713
Protoss_Robotics_Facility 1 12319
12525
