Protoss_Gateway 2 11051
Protoss_Assimilator 1 5477
Protoss_Cybernetics_Core 1 6851
Protoss_Dragoon 3 11068
Protoss_Citadel_of_Adun 1 9456
Protoss_Templar_Archives 1 10905
Protoss_Dark_Templar 2 12499
12499
