Protoss_Gateway 1 4079
Protoss_Assimilator 1 4147
Protoss_Cybernetics_Core 1 5537
Protoss_Zealot 1 5458
Protoss_Dragoon 4 11278
Protoss_Forge 1 7703
Protoss_Photon_Cannon 2 9393
Protoss_Stargate 2 11980
Singularity_Charge 1 9833
Protoss_Scout 1 13292
13292
