Protoss_Gateway 2 8070
Protoss_Assimilator 1 4552
Protoss_Zealot 2 6084
Protoss_Cybernetics_Core 1 6192
Protoss_Dragoon 4 12262
Protoss_Nexus 1 12742
Singularity_Charge 1 11094
12742
