Protoss_Gateway 1 4294
Protoss_Assimilator 1 4496
Protoss_Cybernetics_Core 1 5985
Protoss_Zealot 1 5809
Protoss_Dragoon 5 11805
Protoss_Robotics_Facility 1 11040
Singularity_Charge 1 10117
Protoss_Observatory 1 12118
12118
