Protoss_Gateway 1 4291
Protoss_Assimilator 1 4417
Protoss_Zealot 1 5294
Protoss_Cybernetics_Core 1 6775
Protoss_Dragoon 5 12566
Protoss_Robotics_Facility 1 10618
Protoss_Nexus 1 12883
Singularity_Charge 1 10807
12883
