Protoss_Gateway 2 9261
Protoss_Assimilator 1 4306
Protoss_Cybernetics_Core 1 5960
Protoss_Dragoon 6 12108
Protoss_Robotics_Facility 1 9338
Protoss_Observatory 1 10269
Singularity_Charge 1 10048
Protoss_Observer 1 11592
12108
