Protoss_Gateway 2 10128
Protoss_Assimilator 1 4414
Protoss_Cybernetics_Core 1 5810
Protoss_Dragoon 6 11963
Protoss_Robotics_Facility 1 10181
Singularity_Charge 1 9841
Protoss_Observatory 1 10939
Protoss_Observer 1 12090
12090
