Protoss_Gateway 1 4507
Protoss_Zealot 3 7240
Protoss_Assimilator 1 6084
Protoss_Cybernetics_Core 1 7543
Protoss_Dragoon 3 11700
Protoss_Nexus 1 12031
Protoss_Robotics_Facility 1 12019
12031
