Protoss_Gateway 2 10185
Protoss_Assimilator 1 4431
Protoss_Cybernetics_Core 1 5844
Protoss_Dragoon 7 12525
Protoss_Robotics_Facility 1 9756
Singularity_Charge 1 9979
Protoss_Observatory 1 10819
Protoss_Observer 1 12111
12525
