Protoss_Gateway 1 4242
Protoss_Assimilator 2 4902
Protoss_Cybernetics_Core 1 6213
Protoss_Dragoon 4 10740
Protoss_Robotics_Facility 1 9848
Protoss_Shuttle 1 11341
Protoss_Robotics_Support_Bay 1 11052
Protoss_Reaver 1 12899
12899
