Protoss_Gateway 2 10874
Protoss_Assimilator 1 4368
Protoss_Cybernetics_Core 1 5844
Protoss_Dragoon 4 11056
Protoss_Robotics_Facility 1 11025
Singularity_Charge 1 9587
Protoss_Nexus 1 13967
Protoss_Observatory 1 12099
13967
