Protoss_Gateway 1 4366
Protoss_Assimilator 1 4483
Protoss_Cybernetics_Core 1 5944
Protoss_Dragoon 2 8577
Protoss_Robotics_Facility 1 8808
Protoss_Shuttle 1 10202
Protoss_Robotics_Support_Bay 1 9598
Protoss_Zealot 2 11224
Protoss_Reaver 1 11760
Protoss_Observatory 1 11318
11760
