Protoss_Gateway 2 9989
Protoss_Assimilator 1 4381
Protoss_Cybernetics_Core 1 5753
Protoss_Dragoon 6 11451
Protoss_Robotics_Facility 1 9646
Protoss_Observatory 1 10446
Singularity_Charge 1 9771
Protoss_Observer 1 11458
Protoss_Nexus 1 14253
14253
