Protoss_Gateway 2 11067
Protoss_Assimilator 1 4417
Protoss_Zealot 2 10969
Protoss_Cybernetics_Core 1 6075
Protoss_Citadel_of_Adun 2 9317
Protoss_Dragoon 2 9174
Protoss_Robotics_Facility 1 9032
Protoss_Templar_Archives 1 10779
Protoss_Nexus 1 13503
Protoss_Shuttle 1 12482
13503
