Protoss_Gateway 2 9690
Protoss_Assimilator 1 4414
Protoss_Cybernetics_Core 1 5888
Protoss_Dragoon 5 11995
Protoss_Nexus 1 10531
Protoss_Robotics_Facility 1 11688
Singularity_Charge 1 9918
11995
