Protoss_Gateway 2 7277
Protoss_Forge 1 4709
Protoss_Assimilator 1 4975
Protoss_Cybernetics_Core 1 6050
Protoss_Dragoon 7 11951
Protoss_Zealot 1 8410
Singularity_Charge 1 10019
Protoss_Robotics_Facility 1 12300
12300
