Protoss_Gateway 2 7018
Protoss_Assimilator 1 4340
Protoss_Cybernetics_Core 1 5669
Protoss_Dragoon 7 12335
Protoss_Nexus 1 12659
Singularity_Charge 1 10172
Protoss_Robotics_Facility 1 12652
12659
