Protoss_Gateway 2 9289
Protoss_Assimilator 1 4451
Protoss_Cybernetics_Core 1 5835
Protoss_Zealot 1 5859
Protoss_Dragoon 7 12045
Protoss_Robotics_Facility 1 11925
Singularity_Charge 1 10058
12045
