Protoss_Gateway 2 12069
Protoss_Assimilator 1 4663
Protoss_Cybernetics_Core 1 5938
Protoss_Dragoon 5 12092
Protoss_Nexus 1 11343
Protoss_Robotics_Facility 1 11331
Singularity_Charge 1 9765
12092
