Protoss_Gateway 3 12424
Protoss_Assimilator 1 4460
Protoss_Cybernetics_Core 1 5753
Protoss_Dragoon 5 12481
Protoss_Robotics_Facility 1 8365
Protoss_Observatory 3 10152
Protoss_Nexus 1 12694
Protoss_Observer 2 12333
12694
