Protoss_Gateway 2 12416
Protoss_Assimilator 1 4618
Protoss_Cybernetics_Core 1 5774
Protoss_Dragoon 4 10763
Protoss_Citadel_of_Adun 1 9017
Protoss_Templar_Archives 1 10509
Singularity_Charge 1 9856
Protoss_Nexus 1 12953
Protoss_Dark_Templar 1 11767
12953
