Protoss_Gateway 2 10152
Protoss_Assimilator 1 4432
Protoss_Cybernetics_Core 1 6072
Protoss_Dragoon 5 12010
Protoss_Robotics_Facility 1 9663
Protoss_Nexus 1 12476
Protoss_Observatory 1 10482
Singularity_Charge 1 9836
Protoss_Observer 1 11493
12476
