Protoss_Gateway 1 4188
Protoss_Assimilator 1 4233
Protoss_Cybernetics_Core 1 5680
Protoss_Dragoon 4 11082
Protoss_Nexus 2 13824
Protoss_Robotics_Facility 1 11348
Singularity_Charge 1 9777
13824
