Protoss_Gateway 1 4107
Protoss_Assimilator 1 4337
Protoss_Cybernetics_Core 1 5569
Protoss_Dragoon 3 9268
Protoss_Robotics_Facility 2 13069
Protoss_Shuttle 1 9579
Protoss_Robotics_Support_Bay 1 9789
Protoss_Zealot 2 12160
Protoss_Reaver 1 11772
13069
