Protoss_Gateway 1 4182
Protoss_Assimilator 1 4299
Protoss_Cybernetics_Core 1 5840
Protoss_Dragoon 4 10687
Protoss_Robotics_Facility 1 9847
Protoss_Nexus 1 12009
Protoss_Observatory 1 10655
Singularity_Charge 1 9961
Protoss_Observer 1 11692
12009
