Protoss_Gateway 2 11591
Protoss_Assimilator 3 11262
Protoss_Zealot 4 9418
Protoss_Nexus 1 9628
Protoss_Forge 1 8105
Protoss_Photon_Cannon 1 9496
Protoss_Cybernetics_Core 1 10913
Protoss_Dragoon 1 12165
12165
