Protoss_Gateway 1 4038
Protoss_Assimilator 1 4097
Protoss_Cybernetics_Core 1 5528
Protoss_Zealot 1 5499
Protoss_Dragoon 5 11644
Singularity_Charge 1 9669
Protoss_Nexus 1 12628
Protoss_Robotics_Facility 1 12054
12628
