Protoss_Gateway 2 12724
Protoss_Assimilator 1 4549
Protoss_Cybernetics_Core 1 6017
Protoss_Zealot 1 5923
Protoss_Robotics_Facility 1 8366
Protoss_Dragoon 4 12001
Protoss_Nexus 1 12758
Protoss_Observatory 1 10924
Protoss_Observer 1 11935
12758
