Protoss_Gateway 3 12599
Protoss_Assimilator 1 4543
Protoss_Cybernetics_Core 1 5979
Protoss_Dragoon 4 12139
Protoss_Nexus 1 11302
Protoss_Robotics_Facility 1 11662
Singularity_Charge 1 10032
12599
