Protoss_Gateway 3 12842
Protoss_Assimilator 1 4232
Protoss_Cybernetics_Core 1 5750
Protoss_Dragoon 5 11691
Protoss_Nexus 1 11746
Singularity_Charge 1 9909
Protoss_Robotics_Facility 1 11902
12842
