Protoss_Gateway 2 11947
Protoss_Assimilator 1 4334
Protoss_Cybernetics_Core 1 5802
Protoss_Dragoon 5 12066
Protoss_Nexus 1 11854
Singularity_Charge 1 10043
Protoss_Robotics_Facility 1 12001
12066
