Protoss_Gateway 2 9213
Protoss_Assimilator 1 4593
Protoss_Cybernetics_Core 1 5721
Protoss_Dragoon 5 12000
Protoss_Zealot 2 10180
Singularity_Charge 1 9923
Protoss_Nexus 1 12900
Protoss_Robotics_Facility 1 13053
13053
