Protoss_Gateway 2 6833
Protoss_Assimilator 1 4436
Protoss_Cybernetics_Core 1 5711
Protoss_Dragoon 5 9651
Singularity_Charge 1 9920
Protoss_Nexus 1 12795
Protoss_Robotics_Facility 1 12690
12795
