Protoss_Assimilator 2 5086
Protoss_Gateway 1 4906
Protoss_Cybernetics_Core 1 6437
Protoss_Dragoon 5 12590
Protoss_Nexus 1 11968
Protoss_Robotics_Facility 1 11858
Singularity_Charge 1 10386
12590
