Protoss_Gateway 1 4151
Protoss_Assimilator 1 4632
Protoss_Zealot 3 7237
Protoss_Cybernetics_Core 1 7003
Protoss_Dragoon 4 12424
Protoss_Robotics_Facility 1 9821
Protoss_Shuttle 1 11695
Protoss_Observatory 1 11783
12424
