Protoss_Gateway 2 11844
Protoss_Assimilator 1 4392
Protoss_Cybernetics_Core 1 5636
Protoss_Dragoon 6 12361
Protoss_Nexus 1 11485
Singularity_Charge 1 9610
Protoss_Robotics_Facility 1 11565
12361
