Protoss_Nexus 1 6804
Protoss_Gateway 3 12687
Protoss_Assimilator 1 5821
Protoss_Cybernetics_Core 1 7574
Protoss_Zealot 1 7527
Protoss_Dragoon 6 12350
Protoss_Robotics_Facility 1 11375
12687
