Protoss_Gateway 1 4135
Protoss_Assimilator 1 4230
Protoss_Cybernetics_Core 1 5601
Protoss_Dragoon 4 10453
Protoss_Robotics_Facility 1 9665
Singularity_Charge 1 9666
Protoss_Shuttle 1 11107
Protoss_Nexus 1 13110
Protoss_Robotics_Support_Bay 1 11357
13110
