Protoss_Gateway 3 11035
Protoss_Assimilator 1 4444
Protoss_Cybernetics_Core 1 5726
Protoss_Dragoon 5 12585
Protoss_Robotics_Facility 1 10025
Singularity_Charge 1 9762
Protoss_Observatory 1 10932
Protoss_Zealot 2 11958
Protoss_Observer 1 11980
12585
