Protoss_Gateway 2 9547
Protoss_Assimilator 1 3997
Protoss_Cybernetics_Core 1 5847
Protoss_Dragoon 7 11995
Protoss_Robotics_Facility 1 8321
Protoss_Observatory 1 9036
Protoss_Observer 2 11235
Singularity_Charge 1 10594
11995
