Protoss_Gateway 2 10350
Protoss_Assimilator 1 4501
Protoss_Cybernetics_Core 1 5898
Protoss_Dragoon 6 12516
Protoss_Robotics_Facility 1 10024
Singularity_Charge 1 9894
Protoss_Observatory 1 10822
Protoss_Observer 1 11891
12516
