Protoss_Gateway 1 4035
Protoss_Assimilator 1 4297
Protoss_Cybernetics_Core 2 5667
Protoss_Dragoon 5 11319
Protoss_Robotics_Facility 1 10078
Singularity_Charge 1 9704
Protoss_Shuttle 1 11484
Protoss_Robotics_Support_Bay 1 11518
Protoss_Zealot 1 12181
12181
