Protoss_Gateway 2 10313
Protoss_Assimilator 1 4707
Protoss_Cybernetics_Core 1 5982
Protoss_Dragoon 4 10636
Protoss_Robotics_Facility 1 10323
Singularity_Charge 1 10163
Protoss_Observatory 1 11097
Protoss_Nexus 1 13989
Protoss_Observer 1 12236
13989
