Protoss_Gateway 2 12169
Protoss_Assimilator 1 4290
Protoss_Cybernetics_Core 1 5919
Protoss_Dragoon 4 11249
Protoss_Citadel_of_Adun 1 9238
Protoss_Nexus 1 12151
Protoss_Templar_Archives 1 11036
Singularity_Charge 1 9821
Protoss_Dark_Templar 1 12355
12355
