Protoss_Gateway 2 8909
Protoss_Assimilator 1 4419
Protoss_Cybernetics_Core 1 5835
Protoss_Dragoon 9 12534
Protoss_Robotics_Facility 1 11065
Singularity_Charge 1 9818
Protoss_Observatory 1 11788
12534
