Protoss_Gateway 2 8887
Protoss_Assimilator 1 4382
Protoss_Cybernetics_Core 1 5711
Protoss_Dragoon 5 10924
Singularity_Charge 1 9786
Protoss_Nexus 1 12859
Protoss_Zealot 1 11265
12859
