Protoss_Assimilator 1 3924
Protoss_Gateway 1 4989
Protoss_Cybernetics_Core 1 6530
Protoss_Robotics_Facility 1 8593
Protoss_Dragoon 4 12262
Protoss_Shuttle 1 10013
Protoss_Observatory 1 10185
Protoss_Observer 2 12244
Singularity_Charge 1 10758
Protoss_Robotics_Support_Bay 1 11659
12262
