Protoss_Gateway 2 11715
Protoss_Assimilator 2 6716
Protoss_Zealot 1 5455
Protoss_Cybernetics_Core 1 6249
Protoss_Dragoon 5 12180
Protoss_Nexus 1 12327
Singularity_Charge 1 10465
12327
