Protoss_Gateway 2 11838
Protoss_Assimilator 1 4590
Protoss_Cybernetics_Core 1 5800
Protoss_Dragoon 4 10983
Protoss_Nexus 1 11157
Protoss_Robotics_Facility 1 11073
Singularity_Charge 1 10117
Protoss_Shuttle 1 12532
12532
