Protoss_Gateway 1 4094
Protoss_Assimilator 1 4337
Protoss_Cybernetics_Core 1 5771
Protoss_Dragoon 3 9225
Protoss_Robotics_Facility 1 9427
Protoss_Nexus 1 11706
Protoss_Shuttle 1 10908
Protoss_Robotics_Support_Bay 1 10749
Protoss_Zealot 2 12067
Protoss_Reaver 1 12474
12474
