Protoss_Gateway 2 12263
Protoss_Assimilator 1 4592
Protoss_Cybernetics_Core 1 5947
Protoss_Dragoon 5 12405
Protoss_Nexus 1 11153
Protoss_Robotics_Facility 1 11208
Singularity_Charge 1 9920
12405
