Protoss_Gateway 1 4455
Protoss_Assimilator 1 4644
Protoss_Cybernetics_Core 1 6023
Protoss_Dragoon 4 11634
Protoss_Robotics_Facility 1 8698
Protoss_Shuttle 1 10226
Protoss_Observatory 1 10299
Protoss_Robotics_Support_Bay 1 10677
Protoss_Observer 1 11336
Protoss_Reaver 1 12995
12995
