Protoss_Gateway 2 9475
Protoss_Assimilator 1 4644
Protoss_Cybernetics_Core 1 5923
Protoss_Dragoon 4 10851
Protoss_Robotics_Facility 1 11230
Singularity_Charge 1 10134
Protoss_Zealot 2 11891
Protoss_Observatory 1 12016
12016
