Protoss_Gateway 3 12232
Protoss_Assimilator 1 4112
Protoss_Cybernetics_Core 1 5535
Protoss_Dragoon 5 11325
Protoss_Nexus 1 11071
Singularity_Charge 1 9443
Protoss_Robotics_Facility 1 11439
12232
