Protoss_Gateway 2 9517
Protoss_Assimilator 1 4188
Protoss_Zealot 1 5194
Protoss_Cybernetics_Core 1 6189
Protoss_Dragoon 7 12560
Singularity_Charge 1 10368
Protoss_Robotics_Facility 1 12418
12560
