Protoss_Gateway 2 11736
Protoss_Assimilator 1 4985
Protoss_Cybernetics_Core 1 6383
Protoss_Dragoon 5 12004
Protoss_Robotics_Facility 1 10023
Protoss_Observatory 1 10860
Protoss_Observer 1 11995
12004
