Protoss_Gateway 2 6324
Protoss_Assimilator 1 4281
Protoss_Cybernetics_Core 1 5569
Protoss_Dragoon 5 11928
Protoss_Nexus 1 11721
Singularity_Charge 1 9657
Protoss_Robotics_Facility 1 12124
12124
