Protoss_Gateway 2 11051
Protoss_Assimilator 1 4356
Protoss_Zealot 1 5063
Protoss_Cybernetics_Core 1 6787
Protoss_Dragoon 5 12291
Protoss_Nexus 1 11548
Protoss_Citadel_of_Adun 1 11493
Singularity_Charge 1 10456
12291
