Protoss_Gateway 2 12292
Protoss_Assimilator 1 4212
Protoss_Cybernetics_Core 1 5717
Protoss_Dragoon 5 11922
Protoss_Nexus 1 11961
Singularity_Charge 1 9736
Protoss_Robotics_Facility 1 12016
12292
