Protoss_Gateway 1 4158
Protoss_Assimilator 1 4521
Protoss_Cybernetics_Core 1 5891
Protoss_Dragoon 5 11987
Protoss_Robotics_Facility 1 10045
Protoss_Shuttle 1 11449
Singularity_Charge 1 10155
Protoss_Robotics_Support_Bay 1 11494
11987
