Protoss_Gateway 1 4114
Protoss_Assimilator 1 4428
Protoss_Cybernetics_Core 1 5759
Protoss_Dragoon 2 8085
Protoss_Citadel_of_Adun 1 7580
Protoss_Templar_Archives 1 9175
Protoss_Nexus 2 14037
Protoss_Dark_Templar 2 11498
14037
