Protoss_Gateway 1 4136
Protoss_Assimilator 1 4368
Protoss_Cybernetics_Core 1 5774
Protoss_Dragoon 4 10485
Protoss_Citadel_of_Adun 1 9049
Protoss_Templar_Archives 1 10520
Singularity_Charge 1 9882
Protoss_Dark_Templar 1 11717
Protoss_Nexus 1 13714
13714
