Protoss_Gateway 1 4347
Protoss_Assimilator 1 4572
Protoss_Cybernetics_Core 1 6216
Protoss_Zealot 1 5783
Protoss_Dragoon 4 10936
Protoss_Robotics_Facility 1 10532
Singularity_Charge 1 10160
Protoss_Shuttle 1 12315
Protoss_Robotics_Support_Bay 1 11646
12315
