Protoss_Nexus 1 6777
Protoss_Gateway 2 10267
Protoss_Assimilator 1 5718
Protoss_Cybernetics_Core 1 7463
Protoss_Zealot 1 7469
Protoss_Dragoon 5 11984
Protoss_Forge 1 11121
Singularity_Charge 1 11334
Protoss_Photon_Cannon 1 12571
12571
