Protoss_Gateway 2 11048
Protoss_Assimilator 2 5194
Protoss_Zealot 2 6968
Protoss_Cybernetics_Core 1 7176
Protoss_Dragoon 3 10573
Protoss_Citadel_of_Adun 1 10758
Protoss_Robotics_Facility 1 12177
Protoss_Templar_Archives 1 12312
Singularity_Charge 1 11147
12312
