Protoss_Gateway 2 11108
Protoss_Assimilator 1 4251
Protoss_Cybernetics_Core 1 5765
Protoss_Dragoon 7 12534
Protoss_Robotics_Facility 1 9985
Singularity_Charge 1 9666
Protoss_Observatory 1 10787
12534
