Protoss_Gateway 2 12140
Protoss_Assimilator 1 4913
Protoss_Zealot 1 5613
Protoss_Cybernetics_Core 1 6927
Protoss_Dragoon 4 12499
Protoss_Nexus 1 12521
Singularity_Charge 1 11129
12521
