Protoss_Gateway 1 4220
Protoss_Assimilator 1 4464
Protoss_Cybernetics_Core 1 5949
Protoss_Dragoon 3 9364
Protoss_Robotics_Facility 1 8547
Protoss_Shuttle 1 10053
Protoss_Robotics_Support_Bay 1 9888
Protoss_Zealot 2 11443
Protoss_Reaver 1 11614
Protoss_Observatory 1 11878
11878
