Protoss_Gateway 2 8421
Protoss_Assimilator 2 5110
Protoss_Cybernetics_Core 1 6541
Protoss_Dragoon 7 12572
Protoss_Nexus 1 13158
Singularity_Charge 1 10436
Protoss_Robotics_Facility 1 12841
13158
