Protoss_Gateway 2 10589
Protoss_Assimilator 1 4452
Protoss_Cybernetics_Core 1 5748
Protoss_Zealot 1 5815
Protoss_Dragoon 4 11024
Protoss_Robotics_Facility 1 10119
Singularity_Charge 1 10149
Protoss_Shuttle 1 11622
Protoss_Observatory 1 11485
11622
