Protoss_Gateway 2 9138
Protoss_Assimilator 1 4182
Protoss_Cybernetics_Core 1 5777
Protoss_Dragoon 5 10368
Singularity_Charge 1 9727
Protoss_Nexus 1 12979
Protoss_Robotics_Facility 1 12780
12979
