Protoss_Gateway 1 4120
Protoss_Assimilator 1 4232
Protoss_Cybernetics_Core 1 5745
Protoss_Zealot 1 5540
Protoss_Dragoon 5 12253
Protoss_Robotics_Facility 1 8485
Protoss_Observatory 1 9576
Protoss_Observer 2 11897
Protoss_Nexus 1 13667
13667
