Protoss_Gateway 2 9823
Protoss_Assimilator 1 4416
Protoss_Cybernetics_Core 1 5958
Protoss_Dragoon 2 9790
Protoss_Citadel_of_Adun 1 9381
Protoss_Templar_Archives 1 10902
Protoss_Robotics_Facility 1 12591
Protoss_Dark_Templar 2 12124
12591
