Protoss_Gateway 3 12149
Protoss_Zealot 4 8028
Protoss_Forge 1 5112
Protoss_Assimilator 1 6236
Protoss_Cybernetics_Core 1 7448
Protoss_Dragoon 3 11451
Protoss_Robotics_Facility 1 13072
13072
