Protoss_Gateway 2 12314
Protoss_Assimilator 1 4812
Protoss_Cybernetics_Core 1 6375
Protoss_Dragoon 5 12168
Protoss_Robotics_Facility 1 8660
Protoss_Observatory 1 9432
Protoss_Observer 2 11347
12314
