Protoss_Gateway 2 9498
Protoss_Assimilator 1 4366
Protoss_Cybernetics_Core 1 5636
Protoss_Dragoon 2 8311
Protoss_Citadel_of_Adun 1 7884
Protoss_Templar_Archives 1 9327
Protoss_Dark_Templar 3 12028
Protoss_Nexus 1 14238
14238
