Protoss_Gateway 2 11954
Protoss_Assimilator 1 4205
Protoss_Cybernetics_Core 1 5819
Protoss_Zealot 1 5727
Protoss_Dragoon 5 12033
Protoss_Nexus 1 12539
Singularity_Charge 1 9918
Protoss_Robotics_Facility 1 12029
12539
