Protoss_Assimilator 3 5985
Protoss_Gateway 1 4875
Protoss_Zealot 2 7085
Protoss_Cybernetics_Core 1 8158
Protoss_Dragoon 3 11714
Protoss_Robotics_Facility 1 10658
Protoss_Shuttle 1 12069
Protoss_Robotics_Support_Bay 1 11813
12069
