Protoss_Gateway 2 10840
Protoss_Assimilator 1 4630
Protoss_Cybernetics_Core 1 6214
Protoss_Dragoon 6 12156
Protoss_Robotics_Facility 1 10122
Singularity_Charge 1 10108
Protoss_Observatory 1 10842
Protoss_Observer 1 11862
12156
