Protoss_Gateway 2 12384
Protoss_Assimilator 1 4656
Protoss_Cybernetics_Core 1 5895
Protoss_Zealot 1 5868
Protoss_Dragoon 4 11755
Protoss_Robotics_Facility 1 10163
Protoss_Nexus 1 13069
Singularity_Charge 1 10383
Protoss_Observatory 1 11147
Protoss_Observer 1 12272
13069
