Protoss_Gateway 2 10369
Protoss_Assimilator 1 4419
Protoss_Cybernetics_Core 1 5974
Protoss_Dragoon 6 12017
Protoss_Robotics_Facility 1 9867
Singularity_Charge 1 9874
Protoss_Observatory 1 10599
Protoss_Observer 1 11912
12017
