Protoss_Gateway 2 8543
Protoss_Assimilator 1 4612
Protoss_Cybernetics_Core 1 6064
Protoss_Dragoon 7 12449
Protoss_Robotics_Facility 1 10980
Singularity_Charge 1 10269
Protoss_Shuttle 1 12538
12538
