Protoss_Nexus 1 6652
Protoss_Gateway 2 7561
Protoss_Assimilator 2 10695
Protoss_Cybernetics_Core 1 7250
Protoss_Zealot 1 7533
Protoss_Dragoon 6 11205
Protoss_Robotics_Facility 1 12745
12745
