Protoss_Gateway 3 10502
Protoss_Assimilator 1 4395
Protoss_Cybernetics_Core 1 5796
Protoss_Dragoon 4 10612
Protoss_Robotics_Facility 1 9850
Protoss_Citadel_of_Adun 1 10533
Singularity_Charge 1 9858
Protoss_Zealot 3 11746
11746
