Protoss_Gateway 1 4173
Protoss_Assimilator 1 4450
Protoss_Cybernetics_Core 1 5819
Protoss_Zealot 1 5821
Protoss_Dragoon 4 10725
Protoss_Robotics_Facility 1 10751
Singularity_Charge 1 10199
Protoss_Shuttle 1 12154
Protoss_Robotics_Support_Bay 1 11640
12154
