Protoss_Gateway 1 4167
Protoss_Assimilator 1 4425
Protoss_Zealot 1 5151
Protoss_Cybernetics_Core 1 6766
Protoss_Dragoon 5 12598
Protoss_Robotics_Facility 2 10865
Protoss_Robotics_Support_Bay 1 10390
Protoss_Shuttle 1 11622
12598
