Protoss_Gateway 1 4185
Protoss_Assimilator 1 4395
Protoss_Cybernetics_Core 1 5796
Protoss_Dragoon 3 10342
Protoss_Robotics_Facility 1 9826
Protoss_Zealot 2 12061
Singularity_Charge 1 9989
Protoss_Robotics_Support_Bay 1 11128
Protoss_Shuttle 1 11901
Protoss_Observatory 1 11419
12061
