Protoss_Gateway 2 10629
Protoss_Assimilator 1 4423
Protoss_Cybernetics_Core 1 5645
Protoss_Dragoon 6 12074
Protoss_Nexus 1 11757
Singularity_Charge 1 9704
Protoss_Robotics_Facility 1 12320
12320
