Protoss_Gateway 2 12817
Protoss_Assimilator 1 4356
Protoss_Cybernetics_Core 1 5635
Protoss_Dragoon 5 11814
Protoss_Robotics_Facility 1 8325
Protoss_Shuttle 1 9731
Protoss_Robotics_Support_Bay 1 9660
Protoss_Reaver 1 11672
12817
