Protoss_Gateway 2 8074
Protoss_Assimilator 1 4450
Protoss_Cybernetics_Core 1 5752
Protoss_Dragoon 4 9677
Singularity_Charge 1 9663
Protoss_Nexus 1 12679
Protoss_Citadel_of_Adun 1 12137
12679
