Protoss_Gateway 2 7094
Protoss_Assimilator 1 4463
Protoss_Cybernetics_Core 1 5734
Protoss_Dragoon 6 12563
Protoss_Zealot 1 10615
Singularity_Charge 1 10099
Protoss_Nexus 1 13838
Protoss_Robotics_Facility 1 13036
13838
