Protoss_Gateway 1 4111
Protoss_Assimilator 1 4150
Protoss_Cybernetics_Core 1 5572
Protoss_Robotics_Facility 1 7625
Protoss_Dragoon 1 7389
Protoss_Shuttle 1 9020
Protoss_Robotics_Support_Bay 1 8634
Protoss_Reaver 2 12117
12117
