Protoss_Assimilator 1 3956
Protoss_Gateway 2 10460
Protoss_Cybernetics_Core 1 6475
Protoss_Dragoon 5 11679
Protoss_Robotics_Facility 1 11171
Singularity_Charge 1 10149
Protoss_Nexus 1 13417
13417
