Protoss_Gateway 2 10878
Protoss_Assimilator 1 4229
Protoss_Cybernetics_Core 1 5660
Protoss_Dragoon 7 12408
Protoss_Robotics_Facility 1 9557
Protoss_Observatory 1 10298
Singularity_Charge 1 9757
Protoss_Observer 1 11581
12408
