Protoss_Assimilator 2 4968
Protoss_Gateway 2 9895
Protoss_Cybernetics_Core 1 6367
Protoss_Dragoon 2 9083
Protoss_Robotics_Facility 1 9273
Protoss_Zealot 2 10972
Protoss_Shuttle 1 10703
Protoss_Robotics_Support_Bay 1 10125
Protoss_Reaver 1 12261
12261
