Protoss_Gateway 2 10003
Protoss_Assimilator 1 4379
Protoss_Cybernetics_Core 1 5701
Protoss_Dragoon 6 11887
Protoss_Robotics_Facility 1 9727
Singularity_Charge 1 9511
Protoss_Observatory 1 10441
Protoss_Observer 1 11455
Protoss_Nexus 1 14147
14147
