Protoss_Gateway 2 7050
Protoss_Assimilator 1 4608
Protoss_Cybernetics_Core 1 6034
Protoss_Dragoon 5 9879
Singularity_Charge 1 10026
Protoss_Nexus 1 13337
Protoss_Robotics_Facility 1 13207
13337
