Protoss_Gateway 2 6418
Protoss_Assimilator 1 4155
Protoss_Cybernetics_Core 1 5575
Protoss_Dragoon 4 9189
Protoss_Citadel_of_Adun 1 9162
Protoss_Zealot 1 10076
Singularity_Charge 1 9236
Protoss_Templar_Archives 1 10729
Protoss_Dark_Templar 2 11992
11992
