Protoss_Gateway 2 12470
Protoss_Assimilator 1 4515
Protoss_Cybernetics_Core 1 5762
Protoss_Dragoon 5 11805
Protoss_Robotics_Facility 1 10169
Singularity_Charge 1 9771
Protoss_Nexus 1 13020
Protoss_Observatory 1 11114
13020
