Protoss_Gateway 1 4062
Protoss_Assimilator 1 4217
Protoss_Cybernetics_Core 1 5762
Protoss_Dragoon 5 11908
Protoss_Nexus 1 11668
Singularity_Charge 1 9786
Protoss_Robotics_Facility 2 12437
12437
