Protoss_Gateway 2 9623
Protoss_Assimilator 1 4457
Protoss_Cybernetics_Core 1 5925
Protoss_Dragoon 2 8229
Protoss_Citadel_of_Adun 1 7839
Protoss_Templar_Archives 1 9457
Protoss_Dark_Templar 3 12522
Protoss_Nexus 1 13811
13811
