Protoss_Gateway 2 8812
Protoss_Zealot 1 5107
Protoss_Nexus 1 8504
Protoss_Assimilator 2 10924
Protoss_Cybernetics_Core 1 8164
Protoss_Dragoon 5 11913
Protoss_Robotics_Facility 1 13172
13172
