Protoss_Gateway 2 9462
Protoss_Assimilator 1 4498
Protoss_Cybernetics_Core 1 6040
Protoss_Dragoon 5 11191
Protoss_Citadel_of_Adun 1 10293
Protoss_Forge 1 10322
Singularity_Charge 1 10180
Protoss_Templar_Archives 1 11882
11882
