Protoss_Gateway 1 4188
Protoss_Assimilator 1 4354
Protoss_Cybernetics_Core 1 5633
Protoss_Zealot 2 8660
Protoss_Dragoon 3 11574
Protoss_Robotics_Facility 1 8269
Protoss_Shuttle 1 9678
Protoss_Robotics_Support_Bay 1 9701
Protoss_Reaver 2 13048
13048
