Protoss_Gateway 2 12086
Protoss_Assimilator 1 4555
Protoss_Cybernetics_Core 1 6099
Protoss_Dragoon 5 12493
Protoss_Robotics_Facility 1 10018
Singularity_Charge 1 9941
Protoss_Nexus 1 12962
Protoss_Observatory 1 10959
Protoss_Observer 1 11991
12962
