Protoss_Gateway 2 11825
Protoss_Assimilator 1 4217
Protoss_Cybernetics_Core 1 5695
Protoss_Zealot 1 5575
Protoss_Dragoon 1 6985
Protoss_Citadel_of_Adun 1 7660
Protoss_Templar_Archives 1 9220
Protoss_Dark_Templar 2 11635
Protoss_Nexus 1 12609
Protoss_Stargate 1 11710
12609
