Protoss_Gateway 1 4106
Protoss_Assimilator 1 4193
Protoss_Cybernetics_Core 1 5658
Protoss_Dragoon 5 11919
Protoss_Robotics_Facility 1 10416
Singularity_Charge 1 9941
Protoss_Nexus 1 13117
Protoss_Observatory 1 11205
Protoss_Observer 1 12213
13117
