Protoss_Gateway 1 4144
Protoss_Assimilator 1 4208
Protoss_Cybernetics_Core 1 5865
Protoss_Zealot 2 11847
Protoss_Robotics_Facility 1 8070
Protoss_Dragoon 2 10986
Protoss_Shuttle 1 9655
Protoss_Robotics_Support_Bay 1 9000
Protoss_Reaver 1 11283
Protoss_Observatory 1 11243
11847
