Protoss_Gateway 1 4107
Protoss_Assimilator 1 4158
Protoss_Cybernetics_Core 1 5551
Protoss_Robotics_Facility 1 7868
Protoss_Dragoon 5 12508
Protoss_Shuttle 1 9271
Protoss_Robotics_Support_Bay 1 9114
Protoss_Reaver 1 11166
12508
