Protoss_Gateway 2 8933
Protoss_Assimilator 1 4391
Protoss_Cybernetics_Core 1 5654
Protoss_Dragoon 6 11574
Singularity_Charge 1 9815
Protoss_Nexus 1 13619
Protoss_Robotics_Facility 1 12903
13619
