Protoss_Gateway 2 10337
Protoss_Assimilator 1 4270
Protoss_Cybernetics_Core 1 5761
Protoss_Dragoon 4 10683
Protoss_Robotics_Facility 1 10438
Singularity_Charge 1 9856
Protoss_Observatory 1 11194
Protoss_Nexus 1 13541
13541
