Protoss_Gateway 2 7855
Protoss_Assimilator 1 4356
Protoss_Cybernetics_Core 1 5601
Protoss_Dragoon 6 11621
Singularity_Charge 1 9642
Protoss_Nexus 1 12698
Protoss_Robotics_Facility 1 12986
12986
