Protoss_Gateway 2 7668
Protoss_Zealot 2 5882
Protoss_Assimilator 1 5319
Protoss_Cybernetics_Core 1 7035
Protoss_Dragoon 5 10813
Protoss_Nexus 1 13550
Protoss_Citadel_of_Adun 1 12585
Singularity_Charge 1 11217
13550
