Protoss_Gateway 3 12403
Protoss_Assimilator 1 4318
Protoss_Cybernetics_Core 1 5680
Protoss_Dragoon 5 11322
Protoss_Nexus 1 12217
Singularity_Charge 1 9584
Protoss_Robotics_Facility 1 11726
Protoss_Citadel_of_Adun 1 12817
12817
