Protoss_Gateway 2 10340
Protoss_Assimilator 1 4532
Protoss_Zealot 1 5219
Protoss_Cybernetics_Core 1 5875
Protoss_Dragoon 6 11659
Protoss_Robotics_Facility 1 10179
Singularity_Charge 1 9836
Protoss_Observatory 1 10889
Protoss_Observer 1 11914
11914
