Protoss_Gateway 2 9549
Protoss_Assimilator 1 4164
Protoss_Cybernetics_Core 1 5768
Protoss_Dragoon 6 11665
Protoss_Robotics_Facility 1 11575
Singularity_Charge 1 9768
Protoss_Nexus 1 13743
13743
