Protoss_Gateway 2 9813
Protoss_Assimilator 1 4359
Protoss_Cybernetics_Core 1 5714
Protoss_Dragoon 6 12271
Protoss_Robotics_Facility 1 9935
Singularity_Charge 1 9578
Protoss_Observatory 1 10901
Protoss_Nexus 1 13202
Protoss_Observer 1 11947
13202
