Protoss_Gateway 2 10129
Protoss_Assimilator 1 4212
Protoss_Cybernetics_Core 1 5677
Protoss_Dragoon 6 11390
Protoss_Robotics_Facility 1 9825
Singularity_Charge 1 9833
Protoss_Observatory 1 10611
Protoss_Observer 1 11689
Protoss_Nexus 1 14103
14103
