Protoss_Nexus 1 6612
Protoss_Gateway 2 7647
Protoss_Assimilator 1 5727
Protoss_Cybernetics_Core 1 7296
Protoss_Zealot 1 7463
Protoss_Dragoon 6 12165
Protoss_Robotics_Facility 1 11695
12165
