Protoss_Gateway 1 4174
Protoss_Assimilator 1 4217
Protoss_Cybernetics_Core 1 5639
Protoss_Zealot 2 11991
Protoss_Dragoon 2 7948
Protoss_Robotics_Facility 1 9712
Protoss_Nexus 1 12265
Singularity_Charge 1 9648
Protoss_Shuttle 1 11320
Protoss_Robotics_Support_Bay 1 11290
Protoss_Reaver 1 13063
13063
