Protoss_Gateway 2 11481
Protoss_Assimilator 2 4913
Protoss_Cybernetics_Core 1 6454
Protoss_Dragoon 5 12598
Protoss_Nexus 1 12204
Protoss_Robotics_Facility 1 11568
Singularity_Charge 1 10245
12598
