Protoss_Gateway 1 4277
Protoss_Assimilator 2 4843
Protoss_Zealot 2 12321
Protoss_Cybernetics_Core 1 6662
Protoss_Dragoon 4 11278
Protoss_Robotics_Facility 1 10811
Singularity_Charge 1 10430
Protoss_Shuttle 1 12254
Protoss_Robotics_Support_Bay 1 12007
12321
