Protoss_Gateway 1 4025
Protoss_Assimilator 1 4337
Protoss_Zealot 2 11224
Protoss_Cybernetics_Core 1 6680
Protoss_Dragoon 4 11354
Protoss_Robotics_Facility 1 10185
Protoss_Shuttle 1 11607
Protoss_Robotics_Support_Bay 1 11120
Singularity_Charge 1 10995
11607
