Protoss_Gateway 2 9617
Protoss_Assimilator 1 4532
Protoss_Cybernetics_Core 1 5952
Protoss_Dragoon 3 9701
Protoss_Citadel_of_Adun 1 9331
Protoss_Templar_Archives 1 10770
Protoss_Zealot 2 10673
Singularity_Charge 1 9956
Protoss_Dark_Templar 2 12071
12071
