Protoss_Gateway 1 4322
Protoss_Assimilator 1 4590
Protoss_Cybernetics_Core 1 6099
Protoss_Dragoon 5 12344
Protoss_Robotics_Facility 1 10191
Protoss_Shuttle 1 11813
Protoss_Robotics_Support_Bay 1 11198
12344
