Protoss_Gateway 2 12681
Protoss_Assimilator 1 4982
Protoss_Cybernetics_Core 1 6768
Protoss_Zealot 1 6658
Protoss_Dragoon 4 12159
Protoss_Nexus 1 12144
Protoss_Robotics_Facility 1 12449
Singularity_Charge 1 10840
12681
