Protoss_Gateway 2 9965
Protoss_Assimilator 1 4387
Protoss_Cybernetics_Core 1 5592
Protoss_Dragoon 6 12352
Protoss_Robotics_Facility 1 9551
Protoss_Observatory 1 10310
Singularity_Charge 1 9604
Protoss_Observer 2 12263
Protoss_Nexus 1 13369
13369
