Protoss_Gateway 2 12225
Protoss_Assimilator 1 4660
Protoss_Cybernetics_Core 1 6023
Protoss_Zealot 1 5838
Protoss_Dragoon 4 12393
Protoss_Nexus 1 12106
Protoss_Robotics_Facility 1 11877
Singularity_Charge 1 10207
12393
