Protoss_Gateway 1 4179
Protoss_Assimilator 1 4372
Protoss_Cybernetics_Core 1 5761
Protoss_Dragoon 4 11205
Protoss_Robotics_Facility 1 8237
Protoss_Shuttle 1 10027
Protoss_Zealot 2 12067
Protoss_Observatory 1 10474
Protoss_Observer 1 11513
Protoss_Robotics_Support_Bay 1 11429
12067
