Protoss_Gateway 1 4104
Protoss_Assimilator 1 4406
Protoss_Cybernetics_Core 1 5806
Protoss_Dragoon 5 11536
Protoss_Nexus 1 11537
Singularity_Charge 1 9707
Protoss_Robotics_Facility 1 11746
11746
