Protoss_Gateway 1 4097
Protoss_Assimilator 1 4403
Protoss_Cybernetics_Core 1 5635
Protoss_Dragoon 5 11568
Singularity_Charge 1 9663
Protoss_Nexus 1 12802
Protoss_Robotics_Facility 1 12604
12802
