Protoss_Gateway 2 9990
Protoss_Assimilator 1 4397
Protoss_Cybernetics_Core 1 5794
Protoss_Dragoon 5 12001
Protoss_Robotics_Facility 1 8245
Protoss_Observatory 1 9077
Protoss_Observer 3 12269
Protoss_Nexus 1 13015
Singularity_Charge 1 11041
13015
