Protoss_Gateway 1 4229
Protoss_Assimilator 1 4568
Protoss_Cybernetics_Core 1 5781
Protoss_Dragoon 5 12516
Protoss_Robotics_Facility 1 8552
Protoss_Zealot 1 9116
Protoss_Shuttle 1 10035
Protoss_Observatory 1 10681
Protoss_Robotics_Support_Bay 1 11302
Protoss_Observer 1 11938
12516
