Protoss_Gateway 1 4189
Protoss_Assimilator 1 4376
Protoss_Cybernetics_Core 1 5787
Protoss_Robotics_Facility 1 7921
Protoss_Dragoon 2 8694
Protoss_Shuttle 1 9456
Protoss_Robotics_Support_Bay 1 9420
Protoss_Zealot 2 10937
Protoss_Reaver 1 11178
11178
