Protoss_Gateway 2 8885
Protoss_Assimilator 2 8672
Protoss_Zealot 4 9860
Protoss_Nexus 1 9082
Protoss_Cybernetics_Core 1 9958
Protoss_Shield_Battery 1 10706
Protoss_Dragoon 1 11231
11231
