Protoss_Nexus 1 6842
Protoss_Gateway 2 8543
Protoss_Assimilator 1 5926
Protoss_Cybernetics_Core 1 7404
Protoss_Zealot 1 7823
Protoss_Dragoon 6 12197
Protoss_Robotics_Facility 1 12560
12560
