Protoss_Gateway 1 4281
Protoss_Assimilator 2 5910
Protoss_Zealot 1 5288
Protoss_Cybernetics_Core 1 7435
Protoss_Dragoon 4 11990
Protoss_Robotics_Facility 1 11565
Singularity_Charge 1 11249
11990
