Protoss_Gateway 2 8351
Protoss_Zealot 1 5110
Protoss_Nexus 1 7634
Protoss_Assimilator 2 9181
Protoss_Cybernetics_Core 1 7738
Protoss_Dragoon 5 11729
Protoss_Robotics_Facility 1 11752
11752
