Protoss_Gateway 1 4152
Protoss_Assimilator 1 4369
Protoss_Cybernetics_Core 1 5636
Protoss_Zealot 1 5642
Protoss_Dragoon 4 10331
Protoss_Robotics_Facility 1 10280
Singularity_Charge 1 9786
Protoss_Shuttle 1 11689
Protoss_Nexus 1 13661
Protoss_Robotics_Support_Bay 1 11906
13661
