Protoss_Nexus 1 6909
Protoss_Gateway 2 7905
Protoss_Assimilator 2 9700
Protoss_Cybernetics_Core 1 7577
Protoss_Zealot 1 7744
Protoss_Dragoon 6 12101
Protoss_Robotics_Facility 1 12567
12567
