Protoss_Gateway 2 9387
Protoss_Assimilator 1 4242
Protoss_Cybernetics_Core 1 5850
Protoss_Dragoon 5 10991
Protoss_Robotics_Facility 1 10994
Singularity_Charge 1 9906
Protoss_Shuttle 1 12485
12485
