Protoss_Nexus 1 7012
Protoss_Gateway 2 7998
Protoss_Assimilator 1 6370
Protoss_Cybernetics_Core 1 7884
Protoss_Zealot 1 8104
Protoss_Dragoon 6 12543
Protoss_Robotics_Facility 1 12665
12665
