Protoss_Gateway 2 11911
Protoss_Assimilator 1 4248
Protoss_Cybernetics_Core 1 5818
Protoss_Dragoon 5 11618
Protoss_Nexus 1 11929
Singularity_Charge 1 9540
Protoss_Robotics_Facility 1 12758
12758
