Protoss_Gateway 2 10953
Protoss_Assimilator 1 4397
Protoss_Cybernetics_Core 1 5973
Protoss_Dragoon 6 12159
Protoss_Nexus 1 11200
Protoss_Robotics_Facility 1 11100
Singularity_Charge 1 9827
Protoss_Observatory 1 12124
12159
