Protoss_Gateway 2 9909
Protoss_Assimilator 1 4207
Protoss_Cybernetics_Core 1 5582
Protoss_Dragoon 6 11975
Protoss_Robotics_Facility 1 10141
Singularity_Charge 1 9458
Protoss_Observatory 1 11088
Protoss_Nexus 1 13260
Protoss_Observer 1 12116
13260
