Protoss_Gateway 2 9721
Protoss_Assimilator 1 4630
Protoss_Cybernetics_Core 1 6002
Protoss_Dragoon 3 9999
Protoss_Citadel_of_Adun 1 8995
Protoss_Templar_Archives 1 10442
Protoss_Zealot 2 10861
Singularity_Charge 1 9976
Protoss_Dark_Templar 2 11981
11981
