Protoss_Gateway 2 9950
Protoss_Assimilator 1 4416
Protoss_Cybernetics_Core 1 5828
Protoss_Dragoon 6 11559
Protoss_Robotics_Facility 1 9674
Singularity_Charge 1 9736
Protoss_Observatory 1 10752
Protoss_Observer 1 11821
Protoss_Zealot 1 12064
12064
