Protoss_Gateway 2 9029
Protoss_Zealot 1 5098
Protoss_Nexus 1 8465
Protoss_Assimilator 2 9670
Protoss_Cybernetics_Core 1 8674
Protoss_Dragoon 4 11621
Protoss_Citadel_of_Adun 1 11262
Protoss_Robotics_Facility 1 13166
Protoss_Templar_Archives 1 12839
13166
