Protoss_Gateway 2 10027
Protoss_Assimilator 1 4391
Protoss_Cybernetics_Core 1 5689
Protoss_Dragoon 6 12136
Protoss_Robotics_Facility 1 9639
Singularity_Charge 1 9575
Protoss_Shuttle 1 11066
Protoss_Robotics_Support_Bay 1 10775
Protoss_Reaver 1 12758
12758
