Protoss_Gateway 1 4226
Protoss_Assimilator 1 4422
Protoss_Cybernetics_Core 1 5721
Protoss_Zealot 3 10676
Protoss_Robotics_Facility 1 7945
Protoss_Dragoon 2 11199
Protoss_Shuttle 1 9339
Protoss_Robotics_Support_Bay 1 8877
Protoss_Reaver 1 11216
Protoss_Observatory 1 11237
Protoss_Nexus 1 14007
14007
