Protoss_Gateway 2 10185
Protoss_Assimilator 1 4452
Protoss_Cybernetics_Core 1 5786
Protoss_Dragoon 6 11867
Protoss_Robotics_Facility 1 9791
Singularity_Charge 1 9768
Protoss_Observatory 1 10902
Protoss_Observer 1 12105
12105
