Protoss_Gateway 1 4132
Protoss_Assimilator 1 4135
Protoss_Zealot 1 5101
Protoss_Cybernetics_Core 1 5990
Protoss_Dragoon 5 11632
Protoss_Nexus 1 11579
Singularity_Charge 1 9666
11632
