Protoss_Nexus 1 6893
Protoss_Gateway 2 8803
Protoss_Assimilator 1 5996
Protoss_Cybernetics_Core 1 7641
Protoss_Zealot 1 7311
Protoss_Dragoon 5 12136
Protoss_Robotics_Facility 1 12288
12288
