Protoss_Gateway 1 4097
Protoss_Assimilator 2 12209
Protoss_Cybernetics_Core 1 5774
Protoss_Dragoon 5 11577
Protoss_Robotics_Facility 1 10336
Singularity_Charge 1 9719
Protoss_Nexus 1 12862
Protoss_Observatory 1 11210
12862
