Protoss_Gateway 2 10937
Protoss_Assimilator 1 4167
Protoss_Cybernetics_Core 1 5610
Protoss_Dragoon 4 10529
Protoss_Citadel_of_Adun 1 9383
Protoss_Templar_Archives 1 10852
Singularity_Charge 1 9821
Protoss_Dark_Templar 2 12148
Protoss_Nexus 1 14141
14141
