Protoss_Gateway 2 9832
Protoss_Assimilator 1 4248
Protoss_Cybernetics_Core 1 5806
Protoss_Dragoon 6 11641
Protoss_Robotics_Facility 1 9929
Singularity_Charge 1 9707
Protoss_Observatory 1 10851
Protoss_Observer 1 11950
Protoss_Nexus 1 14131
14131
