Protoss_Gateway 1 4196
Protoss_Assimilator 1 4289
Protoss_Cybernetics_Core 1 5690
Protoss_Dragoon 5 11758
Protoss_Robotics_Facility 1 9630
Singularity_Charge 1 9528
Protoss_Observatory 1 10380
Protoss_Nexus 1 13099
Protoss_Observer 2 12286
13099
