Protoss_Nexus 2 11528
Protoss_Gateway 3 12375
Protoss_Assimilator 2 10950
Protoss_Cybernetics_Core 1 7628
Protoss_Dragoon 3 11714
Protoss_Citadel_of_Adun 1 11177
Protoss_Templar_Archives 1 12629
12629
