Protoss_Nexus 1 7015
Protoss_Gateway 3 10786
Protoss_Assimilator 1 5939
Protoss_Cybernetics_Core 1 7381
Protoss_Zealot 1 7975
Protoss_Dragoon 6 11767
Singularity_Charge 1 11384
11767
