Protoss_Gateway 1 4182
Protoss_Assimilator 1 4322
Protoss_Cybernetics_Core 1 5759
Protoss_Dragoon 6 12584
Protoss_Robotics_Facility 1 10731
Singularity_Charge 1 9970
Protoss_Shuttle 1 12230
Protoss_Robotics_Support_Bay 1 11536
12584
