Protoss_Gateway 2 12386
Protoss_Assimilator 1 4472
Protoss_Cybernetics_Core 1 5692
Protoss_Dragoon 6 12522
Protoss_Nexus 1 11749
Singularity_Charge 1 9757
Protoss_Robotics_Facility 1 12352
12522
