Protoss_Gateway 2 12626
Protoss_Assimilator 1 4376
Protoss_Cybernetics_Core 1 5695
Protoss_Zealot 1 5663
Protoss_Dragoon 5 11463
Protoss_Nexus 1 12432
Singularity_Charge 1 9941
Protoss_Citadel_of_Adun 1 12005
12626
