Protoss_Assimilator 2 5036
Protoss_Gateway 2 8894
Protoss_Cybernetics_Core 1 6276
Protoss_Zealot 1 6269
Protoss_Dragoon 6 12584
Protoss_Nexus 1 13129
Singularity_Charge 1 10684
13129
