Protoss_Gateway 2 10455
Protoss_Assimilator 1 4615
Protoss_Cybernetics_Core 1 5961
Protoss_Dragoon 6 12234
Protoss_Robotics_Facility 1 10090
Protoss_Observatory 1 10847
Singularity_Charge 1 10187
Protoss_Observer 1 11900
12234
