Protoss_Gateway 2 9267
Protoss_Assimilator 1 4253
Protoss_Cybernetics_Core 1 5709
Protoss_Dragoon 8 12470
Protoss_Robotics_Facility 1 11094
Singularity_Charge 1 9762
Protoss_Observatory 1 11852
12470
