Protoss_Gateway 3 11688
Protoss_Zealot 1 5112
Protoss_Nexus 1 8364
Protoss_Assimilator 2 9539
Protoss_Cybernetics_Core 1 8042
Protoss_Dragoon 3 11852
Protoss_Robotics_Facility 1 12398
12398
