Protoss_Assimilator 2 5042
Protoss_Gateway 3 10799
Protoss_Zealot 1 5797
Protoss_Cybernetics_Core 1 7388
Protoss_Dragoon 4 12546
Protoss_Robotics_Facility 1 10286
Protoss_Shuttle 1 11683
Protoss_Robotics_Support_Bay 1 11717
Singularity_Charge 1 11240
12546
