Protoss_Gateway 1 4242
Protoss_Assimilator 1 4445
Protoss_Cybernetics_Core 1 5806
Protoss_Dragoon 5 12025
Protoss_Robotics_Facility 1 9892
Singularity_Charge 1 9900
Protoss_Observatory 1 10658
Protoss_Nexus 1 13448
Protoss_Observer 1 11677
13448
