Protoss_Gateway 2 11020
Protoss_Assimilator 1 4196
Protoss_Cybernetics_Core 1 5649
Protoss_Dragoon 6 12341
Protoss_Nexus 1 11807
Singularity_Charge 1 9572
Protoss_Robotics_Facility 1 11943
12341
