Protoss_Gateway 2 9983
Protoss_Assimilator 1 4290
Protoss_Cybernetics_Core 1 5671
Protoss_Zealot 1 5718
Protoss_Dragoon 3 10111
Protoss_Citadel_of_Adun 1 8484
Protoss_Templar_Archives 1 9959
Singularity_Charge 1 10005
Protoss_Dark_Templar 2 11469
11469
