Protoss_Gateway 2 10454
Protoss_Assimilator 1 4199
Protoss_Cybernetics_Core 1 5949
Protoss_Dragoon 3 9347
Protoss_Robotics_Facility 1 10002
Protoss_Zealot 5 12146
Singularity_Charge 1 9918
Protoss_Shuttle 1 11411
Protoss_Observatory 1 10892
Protoss_Observer 1 12342
12342
