Protoss_Gateway 1 4103
Protoss_Assimilator 1 4205
Protoss_Cybernetics_Core 1 5569
Protoss_Dragoon 5 11600
Protoss_Robotics_Facility 1 9604
Singularity_Charge 1 9239
Protoss_Shuttle 1 11016
Protoss_Robotics_Support_Bay 1 11034
11600
