Protoss_Gateway 2 10910
Protoss_Assimilator 1 4580
Protoss_Cybernetics_Core 1 5993
Protoss_Dragoon 5 12203
Protoss_Nexus 1 11582
Singularity_Charge 1 10002
Protoss_Robotics_Facility 1 11934
12203
