Protoss_Gateway 1 4142
Protoss_Assimilator 1 4158
Protoss_Cybernetics_Core 1 5585
Protoss_Dragoon 6 12584
Protoss_Robotics_Facility 1 10109
Singularity_Charge 1 9590
Protoss_Observatory 1 10810
Protoss_Nexus 1 13603
Protoss_Observer 1 11821
13603
