Protoss_Gateway 2 12149
Protoss_Assimilator 1 4720
Protoss_Cybernetics_Core 1 6149
Protoss_Zealot 1 6336
Protoss_Dragoon 4 10798
Protoss_Nexus 1 12280
Protoss_Robotics_Facility 1 11906
Protoss_Citadel_of_Adun 1 11695
Singularity_Charge 1 10494
12280
