Protoss_Nexus 1 6839
Protoss_Gateway 2 7723
Protoss_Assimilator 2 10037
Protoss_Cybernetics_Core 1 7463
Protoss_Zealot 1 7706
Protoss_Dragoon 6 11694
Protoss_Robotics_Facility 1 12771
12771
