Protoss_Nexus 1 6959
Protoss_Gateway 2 8812
Protoss_Assimilator 2 9443
Protoss_Zealot 1 7384
Protoss_Cybernetics_Core 1 7951
Protoss_Dragoon 7 12449
Protoss_Robotics_Facility 1 12389
12449
