Protoss_Gateway 2 10401
Protoss_Assimilator 1 4504
Protoss_Cybernetics_Core 1 5676
Protoss_Dragoon 6 11641
Protoss_Robotics_Facility 1 10198
Singularity_Charge 1 9880
Protoss_Observatory 1 10901
Protoss_Observer 1 12102
Protoss_Nexus 1 14118
14118
