Protoss_Gateway 1 4069
Protoss_Assimilator 1 4290
Protoss_Cybernetics_Core 1 5718
Protoss_Dragoon 4 11548
Protoss_Robotics_Facility 1 8392
Protoss_Shuttle 1 10275
Protoss_Zealot 1 10413
Protoss_Observatory 1 10210
Protoss_Observer 1 11250
Protoss_Robotics_Support_Bay 1 11218
Protoss_Reaver 1 13033
13033
