Protoss_Nexus 1 6868
Protoss_Gateway 2 11227
Protoss_Assimilator 2 11462
Protoss_Cybernetics_Core 1 7603
Protoss_Zealot 1 7489
Protoss_Dragoon 4 12598
Protoss_Citadel_of_Adun 1 11370
Protoss_Templar_Archives 1 12816
12816
