Protoss_Gateway 2 9631
Protoss_Assimilator 1 4155
Protoss_Cybernetics_Core 1 5777
Protoss_Robotics_Facility 1 7726
Protoss_Dragoon 7 12452
Protoss_Observatory 1 8682
Protoss_Observer 2 10586
Protoss_Nexus 1 13290
13290
