Protoss_Nexus 1 6846
Protoss_Gateway 2 7941
Protoss_Assimilator 1 6005
Protoss_Zealot 2 7846
Protoss_Cybernetics_Core 1 7466
Protoss_Dragoon 6 12098
Protoss_Citadel_of_Adun 1 11168
12098
