Protoss_Gateway 1 4325
Protoss_Assimilator 1 4236
Protoss_Cybernetics_Core 1 5860
Protoss_Zealot 1 5628
Protoss_Dragoon 5 11565
Protoss_Robotics_Facility 1 9818
Protoss_Shuttle 1 11227
Singularity_Charge 1 9853
Protoss_Robotics_Support_Bay 1 11441
11565
