Protoss_Gateway 2 9391
Protoss_Zealot 2 6102
Protoss_Nexus 1 8987
Protoss_Assimilator 2 9418
Protoss_Cybernetics_Core 1 8572
Protoss_Dragoon 3 11311
Protoss_Robotics_Facility 1 11509
11509
