Protoss_Gateway 2 11954
Protoss_Assimilator 1 4622
Protoss_Cybernetics_Core 1 5941
Protoss_Dragoon 5 12490
Protoss_Robotics_Facility 1 8720
Protoss_Observatory 1 9486
Protoss_Observer 2 11483
12490
