Protoss_Gateway 2 11493
Protoss_Assimilator 1 4496
Protoss_Cybernetics_Core 1 5865
Protoss_Zealot 1 5739
Protoss_Dragoon 5 12071
Protoss_Nexus 1 12119
Singularity_Charge 1 10029
Protoss_Robotics_Facility 1 12385
12385
