Protoss_Gateway 2 10073
Protoss_Nexus 1 7983
Protoss_Zealot 2 7723
Protoss_Assimilator 2 10774
Protoss_Cybernetics_Core 1 7833
Protoss_Dragoon 4 11545
Protoss_Stargate 1 12416
12416
