Protoss_Gateway 1 4171
Protoss_Assimilator 2 4786
Protoss_Cybernetics_Core 1 5911
Protoss_Zealot 2 6713
Protoss_Dragoon 5 11896
Protoss_Robotics_Facility 1 10766
Singularity_Charge 1 10163
Protoss_Shuttle 1 12623
Protoss_Robotics_Support_Bay 1 11971
12623
