Protoss_Gateway 2 9555
Protoss_Assimilator 1 4589
Protoss_Cybernetics_Core 1 6026
Protoss_Dragoon 5 12549
Protoss_Robotics_Facility 1 8648
Protoss_Observatory 1 9516
Protoss_Observer 1 10575
Protoss_Nexus 1 13819
13819
