Protoss_Gateway 2 10198
Protoss_Assimilator 1 4537
Protoss_Cybernetics_Core 1 6012
Protoss_Dragoon 6 11837
Protoss_Robotics_Facility 1 9935
Singularity_Charge 1 9944
Protoss_Observatory 1 10678
Protoss_Observer 1 11812
11837
