Protoss_Gateway 2 10065
Protoss_Assimilator 1 4467
Protoss_Cybernetics_Core 1 5805
Protoss_Dragoon 6 12385
Protoss_Robotics_Facility 1 9142
Protoss_Robotics_Support_Bay 1 9976
Protoss_Shuttle 1 11033
Protoss_Observatory 1 11174
Protoss_Reaver 1 12591
12591
