Protoss_Gateway 2 9154
Protoss_Assimilator 1 4510
Protoss_Cybernetics_Core 1 5809
Protoss_Nexus 1 8940
Protoss_Dragoon 6 11553
Singularity_Charge 1 10600
Protoss_Robotics_Facility 1 12545
12545
