Protoss_Gateway 2 12213
Protoss_Assimilator 1 4586
Protoss_Cybernetics_Core 1 5882
Protoss_Dragoon 5 12232
Protoss_Robotics_Facility 1 9970
Singularity_Charge 1 9707
Protoss_Nexus 1 12947
Protoss_Observatory 1 11192
Protoss_Observer 1 12204
12947
