Protoss_Gateway 1 4174
Protoss_Assimilator 1 4412
Protoss_Cybernetics_Core 1 5654
Protoss_Dragoon 6 12452
Protoss_Robotics_Facility 1 10213
Singularity_Charge 1 9657
Protoss_Nexus 1 12965
Protoss_Observatory 1 11053
Protoss_Observer 1 12353
12965
