Protoss_Gateway 2 9866
Protoss_Assimilator 1 4578
Protoss_Cybernetics_Core 1 6058
Protoss_Dragoon 6 12241
Protoss_Robotics_Facility 1 8613
Protoss_Observatory 1 9557
Protoss_Observer 2 11518
12241
