Protoss_Gateway 2 8156
Protoss_Assimilator 1 4476
Protoss_Cybernetics_Core 1 5769
Protoss_Dragoon 6 11398
Protoss_Robotics_Facility 1 11100
Singularity_Charge 1 9713
Protoss_Nexus 1 13822
Protoss_Observatory 1 11836
13822
