Protoss_Nexus 1 6704
Protoss_Gateway 4 11388
Protoss_Assimilator 2 11474
Protoss_Cybernetics_Core 1 7209
Protoss_Zealot 1 7568
Protoss_Dragoon 6 11931
Singularity_Charge 1 11039
Protoss_Robotics_Facility 1 13282
13282
