Protoss_Gateway 2 5341
Protoss_Zealot 9 11307
Protoss_Assimilator 1 6779
Protoss_Forge 1 7496
Protoss_Photon_Cannon 2 9006
Protoss_Cybernetics_Core 1 10697
Protoss_Citadel_of_Adun 1 12525
12525
