Protoss_Nexus 1 6886
Protoss_Gateway 2 7896
Protoss_Assimilator 2 10283
Protoss_Cybernetics_Core 1 7533
Protoss_Dragoon 4 11208
Protoss_Citadel_of_Adun 1 11184
Protoss_Robotics_Facility 1 12589
12589
