Protoss_Gateway 2 12732
Protoss_Assimilator 1 4669
Protoss_Cybernetics_Core 1 6517
Protoss_Dragoon 5 12121
Protoss_Robotics_Facility 1 10308
Singularity_Charge 1 10275
Protoss_Observatory 1 11006
Protoss_Nexus 1 13326
Protoss_Observer 1 12119
13326
