Protoss_Gateway 2 11868
Protoss_Zealot 2 8051
Protoss_Nexus 1 8308
Protoss_Assimilator 2 8873
Protoss_Cybernetics_Core 1 8209
Protoss_Dragoon 3 11861
Protoss_Robotics_Facility 1 10895
Protoss_Shuttle 1 12301
12301
