Protoss_Gateway 1 4176
Protoss_Assimilator 1 4400
Protoss_Cybernetics_Core 1 5698
Protoss_Dragoon 4 10634
Protoss_Robotics_Facility 1 9774
Singularity_Charge 1 9739
Protoss_Shuttle 1 11229
Protoss_Nexus 1 13418
Protoss_Robotics_Support_Bay 1 11587
13418
