Protoss_Gateway 2 10590
Protoss_Assimilator 2 4930
Protoss_Cybernetics_Core 1 6125
Protoss_Zealot 1 6312
Protoss_Dragoon 4 11676
Protoss_Robotics_Facility 1 10378
Singularity_Charge 1 9847
Protoss_Observatory 1 11240
Protoss_Nexus 1 14048
14048
