Protoss_Gateway 2 10978
Protoss_Assimilator 1 4182
Protoss_Cybernetics_Core 1 5670
Protoss_Dragoon 6 12282
Protoss_Robotics_Facility 1 9828
Protoss_Nexus 1 11921
Singularity_Charge 1 9335
Protoss_Observatory 1 10529
Protoss_Robotics_Support_Bay 1 11524
12282
