Protoss_Gateway 2 9920
Protoss_Assimilator 1 4432
Protoss_Cybernetics_Core 1 6396
Protoss_Dragoon 3 10608
Protoss_Citadel_of_Adun 1 8478
Protoss_Templar_Archives 1 10234
Singularity_Charge 1 10292
Protoss_Dark_Templar 2 12391
Protoss_Nexus 1 13634
13634
