Protoss_Gateway 2 9548
Protoss_Assimilator 1 4785
Protoss_Cybernetics_Core 1 6233
Protoss_Dragoon 5 12534
Protoss_Citadel_of_Adun 1 8606
Protoss_Templar_Archives 1 10147
Singularity_Charge 1 10055
Protoss_Dark_Templar 2 11422
12534
