Protoss_Gateway 2 11914
Protoss_Assimilator 1 4394
Protoss_Cybernetics_Core 1 5695
Protoss_Zealot 1 5440
Protoss_Dragoon 5 12151
Protoss_Robotics_Facility 1 9704
Protoss_Observatory 1 10394
Protoss_Nexus 1 12545
Singularity_Charge 1 9701
Protoss_Observer 1 11642
12545
