Protoss_Gateway 2 11121
Protoss_Assimilator 1 4542
Protoss_Zealot 4 12333
Protoss_Cybernetics_Core 1 6907
Protoss_Dragoon 4 11471
Protoss_Robotics_Facility 1 10842
Protoss_Observatory 1 11565
Protoss_Shuttle 1 12339
Singularity_Charge 1 11223
12339
