Protoss_Gateway 1 4334
Protoss_Assimilator 1 4571
Protoss_Cybernetics_Core 1 5979
Protoss_Dragoon 5 11659
Protoss_Nexus 1 11728
Singularity_Charge 1 10096
Protoss_Robotics_Facility 1 12048
12048
