Protoss_Nexus 1 6842
Protoss_Gateway 2 7524
Protoss_Assimilator 2 10447
Protoss_Cybernetics_Core 1 7799
Protoss_Zealot 1 7937
Protoss_Dragoon 6 12546
Protoss_Robotics_Facility 1 12131
12546
