Protoss_Gateway 2 9150
Protoss_Assimilator 1 4496
Protoss_Cybernetics_Core 1 5964
Protoss_Dragoon 5 10763
Protoss_Robotics_Facility 1 10481
Singularity_Charge 1 9856
Protoss_Shuttle 1 12026
Protoss_Zealot 2 11841
Protoss_Observatory 1 11946
12026
