Protoss_Gateway 1 4158
Protoss_Assimilator 1 4464
Protoss_Cybernetics_Core 1 5626
Protoss_Zealot 1 5636
Protoss_Dragoon 4 11905
Protoss_Nexus 1 10932
Protoss_Robotics_Facility 1 10491
Protoss_Shuttle 1 11967
Protoss_Robotics_Support_Bay 1 11914
11967
