Protoss_Gateway 2 10013
Protoss_Assimilator 1 4615
Protoss_Cybernetics_Core 1 6043
Protoss_Dragoon 7 12354
Protoss_Robotics_Facility 1 10725
Singularity_Charge 1 10092
Protoss_Observatory 1 11423
12354
