Protoss_Gateway 1 4075
Protoss_Assimilator 1 4119
Protoss_Cybernetics_Core 1 5563
Protoss_Zealot 1 5487
Protoss_Dragoon 3 10871
Protoss_Robotics_Facility 1 8196
Protoss_Shuttle 1 9590
Protoss_Robotics_Support_Bay 1 9151
Protoss_Reaver 1 11148
Protoss_Nexus 1 13667
Protoss_Observatory 1 12007
13667
