Protoss_Gateway 2 10733
Protoss_Assimilator 1 4382
Protoss_Cybernetics_Core 1 5800
Protoss_Dragoon 5 11738
Protoss_Robotics_Facility 1 9914
Singularity_Charge 1 9745
Protoss_Observatory 1 10784
Protoss_Observer 1 11847
Protoss_Nexus 1 14232
14232
