Protoss_Nexus 1 6921
Protoss_Gateway 2 7777
Protoss_Assimilator 2 10464
Protoss_Cybernetics_Core 1 7419
Protoss_Zealot 1 7767
Protoss_Dragoon 6 12057
Protoss_Robotics_Facility 1 11989
12057
