Protoss_Gateway 2 10229
Protoss_Assimilator 1 4218
Protoss_Cybernetics_Core 1 5655
Protoss_Dragoon 3 9148
Protoss_Citadel_of_Adun 1 8846
Protoss_Robotics_Facility 1 10203
Protoss_Templar_Archives 1 10381
Protoss_Zealot 1 10094
Protoss_Shuttle 1 11651
Protoss_Dark_Templar 2 11861
Protoss_Observatory 1 11792
11861
