Protoss_Gateway 2 12323
Protoss_Assimilator 1 4150
Protoss_Cybernetics_Core 1 5712
Protoss_Zealot 1 5552
Protoss_Dragoon 4 11501
Protoss_Nexus 1 11071
Protoss_Robotics_Facility 1 11283
Singularity_Charge 1 9721
Protoss_Shuttle 1 12746
12746
