Protoss_Gateway 2 6564
Protoss_Assimilator 1 4527
Protoss_Cybernetics_Core 1 5745
Protoss_Dragoon 3 8141
Protoss_Citadel_of_Adun 1 9309
Protoss_Robotics_Facility 1 10371
Protoss_Templar_Archives 1 10755
Protoss_Shuttle 1 11777
Protoss_Dark_Templar 2 11969
11969
