Protoss_Gateway 1 4185
Protoss_Assimilator 1 4436
Protoss_Cybernetics_Core 1 5660
Protoss_Dragoon 4 10447
Protoss_Robotics_Facility 1 9660
Singularity_Charge 1 9716
Protoss_Shuttle 1 11347
Protoss_Robotics_Support_Bay 1 10817
Protoss_Zealot 2 12190
Protoss_Reaver 1 13014
13014
