Protoss_Gateway 2 10461
Protoss_Assimilator 1 4249
Protoss_Cybernetics_Core 1 5764
Protoss_Dragoon 6 11875
Protoss_Robotics_Facility 1 10107
Singularity_Charge 1 9429
Protoss_Observatory 1 11056
Protoss_Observer 1 12242
12242
