Protoss_Gateway 1 4309
Protoss_Assimilator 1 4556
Protoss_Cybernetics_Core 1 5851
Protoss_Stargate 1 7562
Protoss_Dragoon 3 11868
Protoss_Scout 1 9611
Protoss_Robotics_Facility 1 12285
12285
