Protoss_Gateway 1 4205
Protoss_Assimilator 1 4473
Protoss_Cybernetics_Core 1 5755
Protoss_Zealot 1 5850
Protoss_Dragoon 4 10359
Protoss_Robotics_Facility 1 10172
Singularity_Charge 1 10061
Protoss_Shuttle 1 11578
Protoss_Nexus 1 13641
Protoss_Robotics_Support_Bay 1 11773
13641
