Protoss_Gateway 1 4041
Protoss_Assimilator 1 4352
Protoss_Cybernetics_Core 1 5720
Protoss_Dragoon 5 12151
Protoss_Robotics_Facility 1 8913
Protoss_Observatory 1 9617
Protoss_Observer 2 11619
Protoss_Nexus 1 13448
13448
