Protoss_Gateway 3 12296
Protoss_Assimilator 1 4676
Protoss_Cybernetics_Core 1 6532
Protoss_Zealot 1 6547
Protoss_Dragoon 5 12376
Protoss_Robotics_Facility 1 10526
Protoss_Nexus 1 13339
Protoss_Observatory 1 11391
Singularity_Charge 1 10740
13339
