Protoss_Gateway 2 8553
Protoss_Assimilator 1 4747
Protoss_Cybernetics_Core 1 6036
Protoss_Dragoon 6 12230
Protoss_Zealot 1 9602
Protoss_Robotics_Facility 1 11078
Singularity_Charge 1 10172
Protoss_Observatory 1 11862
12230
