Protoss_Gateway 2 8145
Protoss_Assimilator 1 4343
Protoss_Cybernetics_Core 1 5592
Protoss_Zealot 1 5619
Protoss_Dragoon 6 10746
Singularity_Charge 1 9742
Protoss_Nexus 1 13527
13527
