Protoss_Gateway 1 4110
Protoss_Assimilator 1 4331
Protoss_Cybernetics_Core 1 5769
Protoss_Dragoon 4 11088
Protoss_Robotics_Facility 1 8294
Protoss_Shuttle 1 10135
Protoss_Observatory 1 9926
Protoss_Observer 1 10978
Protoss_Robotics_Support_Bay 1 11145
Protoss_Zealot 1 11950
Protoss_Reaver 1 12969
12969
