Protoss_Gateway 2 10331
Protoss_Assimilator 1 4592
Protoss_Cybernetics_Core 1 5917
Protoss_Dragoon 6 11831
Protoss_Robotics_Facility 1 9949
Protoss_Observatory 1 10692
Singularity_Charge 1 10092
Protoss_Observer 1 11717
11831
