Protoss_Gateway 2 12239
Protoss_Assimilator 1 4615
Protoss_Cybernetics_Core 1 6230
Protoss_Zealot 1 6078
Protoss_Dragoon 5 12350
Protoss_Nexus 1 12303
Protoss_Robotics_Facility 1 12177
Singularity_Charge 1 10319
12350
