Protoss_Nexus 2 14210
Protoss_Gateway 2 7747
Protoss_Assimilator 1 6023
Protoss_Cybernetics_Core 1 7524
Protoss_Zealot 1 7559
Protoss_Dragoon 4 10930
Protoss_Robotics_Facility 1 11120
Protoss_Robotics_Support_Bay 1 11854
14210
