Protoss_Gateway 2 6491
Protoss_Assimilator 1 4360
Protoss_Cybernetics_Core 1 5679
Protoss_Dragoon 5 12528
Protoss_Nexus 1 11987
Singularity_Charge 1 9809
Protoss_Robotics_Facility 1 11928
12528
