Protoss_Gateway 2 6602
Protoss_Assimilator 1 4313
Protoss_Cybernetics_Core 1 5666
Protoss_Dragoon 6 12519
Singularity_Charge 1 9335
Protoss_Nexus 1 13067
Protoss_Robotics_Facility 1 12955
13067
