Protoss_Nexus 1 6975
Protoss_Gateway 2 8052
Protoss_Assimilator 1 6020
Protoss_Cybernetics_Core 1 7937
Protoss_Zealot 1 8022
Protoss_Dragoon 6 12156
Protoss_Robotics_Facility 1 12405
12405
