Protoss_Gateway 1 4205
Protoss_Assimilator 1 4552
Protoss_Cybernetics_Core 1 5701
Protoss_Dragoon 5 11691
Protoss_Nexus 1 12137
Singularity_Charge 1 9929
Protoss_Robotics_Facility 1 13179
13179
