Protoss_Gateway 2 7878
Protoss_Assimilator 1 4242
Protoss_Cybernetics_Core 1 5730
Protoss_Dragoon 7 11946
Protoss_Citadel_of_Adun 1 9861
Singularity_Charge 1 9426
Protoss_Nexus 1 13792
Protoss_Templar_Archives 1 12510
13792
