Protoss_Gateway 2 9826
Protoss_Assimilator 1 4116
Protoss_Cybernetics_Core 1 5543
Protoss_Dragoon 3 9060
Protoss_Citadel_of_Adun 1 8724
Protoss_Robotics_Facility 1 9573
Protoss_Templar_Archives 1 10267
Protoss_Shuttle 1 11124
Protoss_Dark_Templar 3 12566
12566
