Protoss_Gateway 1 4363
Protoss_Assimilator 1 4622
Protoss_Cybernetics_Core 1 6065
Protoss_Dragoon 4 11758
Protoss_Robotics_Facility 1 10039
Protoss_Shuttle 1 11623
Singularity_Charge 1 10289
Protoss_Robotics_Support_Bay 1 11035
11758
