Protoss_Gateway 2 9249
Protoss_Assimilator 1 4791
Protoss_Cybernetics_Core 1 5919
Protoss_Dragoon 3 9827
Protoss_Citadel_of_Adun 2 9563
Protoss_Templar_Archives 1 11126
Singularity_Charge 1 10150
Protoss_Dark_Templar 2 12358
12358
