Protoss_Gateway 2 10858
Protoss_Assimilator 1 4195
Protoss_Cybernetics_Core 1 5610
Protoss_Dragoon 5 11651
Protoss_Nexus 1 11746
Singularity_Charge 1 9865
Protoss_Robotics_Facility 1 12755
12755
