Protoss_Gateway 1 4138
Protoss_Assimilator 1 4226
Protoss_Cybernetics_Core 1 5733
Protoss_Dragoon 5 11685
Protoss_Robotics_Facility 1 9709
Protoss_Shuttle 1 11150
Singularity_Charge 1 9897
Protoss_Robotics_Support_Bay 1 10623
Protoss_Observatory 1 10910
Protoss_Reaver 1 12723
12723
