Protoss_Assimilator 2 4764
Protoss_Gateway 1 4668
Protoss_Cybernetics_Core 1 6232
Protoss_Zealot 1 6383
Protoss_Dragoon 4 11167
Protoss_Robotics_Facility 1 10265
Protoss_Observatory 1 10956
Protoss_Observer 1 12002
Protoss_Nexus 1 14136
14136
