Protoss_Gateway 2 7040
Protoss_Assimilator 1 4539
Protoss_Cybernetics_Core 1 5920
Protoss_Dragoon 6 11990
Protoss_Citadel_of_Adun 1 9699
Singularity_Charge 1 9610
Protoss_Templar_Archives 1 11446
Protoss_Zealot 1 11733
11990
