Protoss_Gateway 2 12529
Protoss_Assimilator 1 4716
Protoss_Cybernetics_Core 1 6261
Protoss_Robotics_Facility 1 8258
Protoss_Dragoon 4 12461
Protoss_Shuttle 2 11332
Protoss_Nexus 1 13559
13559
