Protoss_Gateway 2 10887
Protoss_Assimilator 1 4435
Protoss_Cybernetics_Core 1 5676
Protoss_Dragoon 5 11574
Protoss_Robotics_Facility 1 9689
Singularity_Charge 1 9672
Protoss_Observatory 1 10405
Protoss_Observer 1 11481
Protoss_Nexus 1 14175
14175
