Protoss_Gateway 1 4075
Protoss_Assimilator 1 4413
Protoss_Cybernetics_Core 1 5717
Protoss_Dragoon 5 12291
Protoss_Nexus 1 11557
Singularity_Charge 1 9771
Protoss_Robotics_Facility 1 11943
12291
