Protoss_Gateway 2 12727
Protoss_Assimilator 1 4270
Protoss_Cybernetics_Core 1 5692
Protoss_Zealot 1 5712
Protoss_Dragoon 5 11703
Protoss_Nexus 1 12024
Singularity_Charge 1 9885
Protoss_Robotics_Facility 1 12800
12800
