Protoss_Gateway 2 6283
Protoss_Assimilator 1 4144
Protoss_Cybernetics_Core 1 5587
Protoss_Dragoon 4 8908
Singularity_Charge 1 9250
Protoss_Nexus 1 12625
Protoss_Citadel_of_Adun 1 11361
Protoss_Robotics_Facility 1 12780
Protoss_Templar_Archives 1 12836
12836
