Protoss_Gateway 1 4111
Protoss_Assimilator 1 4400
Protoss_Zealot 2 6131
Protoss_Cybernetics_Core 1 6983
Protoss_Dragoon 4 12080
Protoss_Robotics_Facility 1 9244
Protoss_Observatory 1 9960
Protoss_Observer 2 11856
Protoss_Nexus 1 13383
13383
