Protoss_Gateway 2 12334
Protoss_Assimilator 1 4417
Protoss_Cybernetics_Core 1 5769
Protoss_Zealot 1 5531
Protoss_Dragoon 5 11597
Protoss_Nexus 1 11595
Singularity_Charge 1 9926
Protoss_Citadel_of_Adun 1 12198
12334
