Protoss_Gateway 2 12046
Protoss_Assimilator 1 4179
Protoss_Cybernetics_Core 1 5516
Protoss_Dragoon 5 11780
Protoss_Nexus 1 11197
Protoss_Robotics_Facility 1 10748
Singularity_Charge 1 9520
Protoss_Observatory 1 11482
12046
