Protoss_Gateway 1 4161
Protoss_Assimilator 1 4180
Protoss_Cybernetics_Core 1 5616
Protoss_Dragoon 6 12490
Protoss_Robotics_Facility 1 9933
Singularity_Charge 1 9736
Protoss_Observatory 1 10683
Protoss_Nexus 1 13685
Protoss_Observer 1 12216
13685
