Protoss_Gateway 3 12377
Protoss_Assimilator 1 4452
Protoss_Cybernetics_Core 1 5832
Protoss_Dragoon 5 11703
Protoss_Nexus 1 11730
Singularity_Charge 1 9847
Protoss_Robotics_Facility 1 11992
12377
