Protoss_Gateway 2 11957
Protoss_Assimilator 1 4401
Protoss_Cybernetics_Core 1 5775
Protoss_Dragoon 5 11545
Protoss_Robotics_Facility 1 10640
Singularity_Charge 1 9877
Protoss_Nexus 1 13939
13939
