Protoss_Nexus 1 6938
Protoss_Gateway 2 7823
Protoss_Assimilator 2 9632
Protoss_Cybernetics_Core 1 7461
Protoss_Zealot 1 7799
Protoss_Dragoon 4 12496
Protoss_Citadel_of_Adun 1 10799
Protoss_Robotics_Facility 1 12521
Protoss_Templar_Archives 1 12346
12521
