Protoss_Gateway 1 4119
Protoss_Assimilator 1 4476
Protoss_Cybernetics_Core 1 5736
Protoss_Dragoon 5 11834
Protoss_Robotics_Facility 1 10598
Singularity_Charge 1 10165
Protoss_Observatory 1 11520
11834
