Protoss_Nexus 1 6735
Protoss_Gateway 2 7653
Protoss_Assimilator 1 5873
Protoss_Cybernetics_Core 1 7583
Protoss_Zealot 1 7773
Protoss_Dragoon 4 10500
Protoss_Robotics_Facility 1 12721
12721
