Protoss_Gateway 2 12204
Protoss_Assimilator 1 4425
Protoss_Cybernetics_Core 1 5977
Protoss_Dragoon 4 11685
Protoss_Robotics_Facility 1 8900
Protoss_Zealot 1 9817
Protoss_Shuttle 1 10313
Protoss_Robotics_Support_Bay 1 9894
Protoss_Reaver 1 11871
12204
