Protoss_Gateway 3 12380
Protoss_Assimilator 1 4366
Protoss_Cybernetics_Core 1 5604
Protoss_Zealot 1 5478
Protoss_Dragoon 5 11624
Protoss_Nexus 1 11867
Singularity_Charge 1 9619
Protoss_Robotics_Facility 1 11856
12380
