Protoss_Nexus 2 13424
Protoss_Gateway 2 7889
Protoss_Assimilator 1 5945
Protoss_Cybernetics_Core 1 7502
Protoss_Zealot 1 7741
Protoss_Dragoon 5 11062
Protoss_Robotics_Facility 1 12932
13424
