Protoss_Nexus 1 6681
Protoss_Gateway 2 7668
Protoss_Assimilator 2 11151
Protoss_Cybernetics_Core 1 7381
Protoss_Zealot 1 7521
Protoss_Dragoon 6 11817
Protoss_Stargate 1 11590
11817
