Protoss_Gateway 2 9893
Protoss_Assimilator 1 4416
Protoss_Cybernetics_Core 1 5753
Protoss_Dragoon 7 12437
Singularity_Charge 1 9634
Protoss_Nexus 1 12602
Protoss_Robotics_Facility 1 12974
12974
