Protoss_Gateway 1 4240
Protoss_Assimilator 1 4438
Protoss_Cybernetics_Core 1 5809
Protoss_Dragoon 3 9832
Protoss_Robotics_Facility 1 10153
Protoss_Zealot 2 11800
Singularity_Charge 1 10058
Protoss_Shuttle 1 11607
Protoss_Robotics_Support_Bay 1 11470
11800
