Protoss_Nexus 2 13556
Protoss_Gateway 2 7736
Protoss_Assimilator 1 5727
Protoss_Cybernetics_Core 1 7389
Protoss_Zealot 1 7515
Protoss_Dragoon 4 10251
Protoss_Robotics_Facility 1 13257
Singularity_Charge 1 11375
13556
