Protoss_Gateway 2 6425
Protoss_Assimilator 1 4420
Protoss_Cybernetics_Core 1 5806
Protoss_Dragoon 6 12253
Protoss_Nexus 1 11616
Singularity_Charge 1 9467
Protoss_Robotics_Facility 1 11404
Protoss_Shuttle 1 12810
12810
