Protoss_Nexus 1 6956
Protoss_Gateway 2 7830
Protoss_Assimilator 1 6127
Protoss_Cybernetics_Core 1 7659
Protoss_Zealot 1 7870
Protoss_Dragoon 4 11922
Protoss_Robotics_Facility 1 11545
11922
