Protoss_Gateway 2 8960
Protoss_Assimilator 1 4350
Protoss_Cybernetics_Core 1 5920
Protoss_Dragoon 6 11515
Protoss_Nexus 1 11532
Singularity_Charge 1 9581
Protoss_Robotics_Facility 1 11830
11830
