Protoss_Gateway 1 4578
Protoss_Zealot 6 10493
Protoss_Nexus 1 10067
Protoss_Assimilator 1 8663
Protoss_Cybernetics_Core 1 10012
Protoss_Forge 1 10479
Protoss_Citadel_of_Adun 1 11667
Protoss_Dragoon 1 11659
11667
