Protoss_Nexus 1 6830
Protoss_Gateway 2 7597
Protoss_Assimilator 1 5749
Protoss_Cybernetics_Core 1 7269
Protoss_Zealot 1 7732
Protoss_Dragoon 8 12288
Protoss_Robotics_Facility 1 12557
Singularity_Charge 1 10933
12557
