Protoss_Gateway 2 12298
Protoss_Assimilator 1 5414
Protoss_Cybernetics_Core 1 6617
Protoss_Zealot 1 6283
Protoss_Dragoon 4 11546
Protoss_Nexus 1 11829
Protoss_Robotics_Facility 1 12443
Singularity_Charge 1 10714
12443
