Protoss_Gateway 2 7615
Protoss_Assimilator 1 4126
Protoss_Cybernetics_Core 1 5546
Protoss_Zealot 1 5288
Protoss_Dragoon 5 12581
Protoss_Nexus 2 14198
Singularity_Charge 1 11281
14198
