Protoss_Gateway 1 4120
Protoss_Assimilator 1 4201
Protoss_Cybernetics_Core 1 5582
Protoss_Dragoon 4 10242
Protoss_Robotics_Facility 1 9623
Singularity_Charge 1 9584
Protoss_Shuttle 1 11028
Protoss_Observatory 1 10418
Protoss_Nexus 1 13360
Protoss_Robotics_Support_Bay 1 11551
Protoss_Observer 1 11873
13360
