Protoss_Gateway 2 12602
Protoss_Assimilator 1 4319
Protoss_Cybernetics_Core 1 5712
Protoss_Zealot 1 5493
Protoss_Dragoon 5 11805
Protoss_Robotics_Facility 1 9895
Singularity_Charge 1 9786
Protoss_Observatory 1 10719
Protoss_Nexus 1 13170
Protoss_Observer 1 11730
13170
