Protoss_Gateway 1 4229
Protoss_Assimilator 1 4466
Protoss_Zealot 3 7104
Protoss_Cybernetics_Core 1 7068
Protoss_Dragoon 4 12007
Protoss_Nexus 1 12678
Protoss_Robotics_Facility 1 12461
Singularity_Charge 1 10962
12678
