Protoss_Gateway 1 4357
Protoss_Assimilator 1 4652
Protoss_Zealot 2 6248
Protoss_Cybernetics_Core 1 7319
Protoss_Dragoon 3 11442
Protoss_Robotics_Facility 1 10716
Protoss_Nexus 1 12400
Protoss_Shuttle 1 12122
Protoss_Robotics_Support_Bay 1 11592
12400
