Protoss_Gateway 1 4572
Protoss_Assimilator 1 4805
Protoss_Cybernetics_Core 1 6405
Protoss_Dragoon 4 10918
Protoss_Robotics_Facility 1 10726
Singularity_Charge 1 10414
Protoss_Shuttle 1 12143
Protoss_Robotics_Support_Bay 1 11467
Protoss_Zealot 1 12346
12346
