Protoss_Gateway 3 12596
Protoss_Assimilator 1 4381
Protoss_Cybernetics_Core 1 5740
Protoss_Zealot 1 5560
Protoss_Dragoon 5 11556
Protoss_Nexus 1 11550
Singularity_Charge 1 9686
Protoss_Robotics_Facility 1 11825
12596
