Protoss_Nexus 1 6717
Protoss_Gateway 2 7785
Protoss_Assimilator 1 5844
Protoss_Cybernetics_Core 1 7363
Protoss_Zealot 1 7574
Protoss_Dragoon 6 11820
Protoss_Robotics_Facility 1 11881
11881
