Protoss_Gateway 3 11980
Protoss_Assimilator 1 4710
Protoss_Cybernetics_Core 1 6102
Protoss_Dragoon 3 10097
Protoss_Robotics_Facility 1 10315
Protoss_Nexus 1 12592
Singularity_Charge 1 10619
Protoss_Observatory 1 11633
Protoss_Citadel_of_Adun 1 12826
12826
