Protoss_Gateway 3 12708
Protoss_Assimilator 1 4221
Protoss_Cybernetics_Core 1 5816
Protoss_Dragoon 4 12499
Protoss_Robotics_Facility 1 9625
Protoss_Nexus 1 12249
Protoss_Observatory 1 10313
Singularity_Charge 1 10017
Protoss_Observer 2 12213
12708
