Protoss_Nexus 1 6836
Protoss_Gateway 2 7776
Protoss_Assimilator 2 10090
Protoss_Cybernetics_Core 1 7550
Protoss_Dragoon 2 8992
Protoss_Citadel_of_Adun 1 10700
Protoss_Forge 1 10997
Protoss_Templar_Archives 1 12264
Protoss_Robotics_Facility 1 12891
Protoss_Photon_Cannon 1 12534
12891
