Protoss_Assimilator 1 3424
Protoss_Gateway 2 9869
Protoss_Cybernetics_Core 1 5999
Protoss_Dragoon 2 8492
Protoss_Citadel_of_Adun 1 8625
Protoss_Robotics_Facility 1 10105
Protoss_Templar_Archives 1 10612
Singularity_Charge 1 9692
Protoss_Shuttle 1 11759
Protoss_Dark_Templar 2 11817
11817
