Protoss_Gateway 1 4173
Protoss_Assimilator 1 4384
Protoss_Cybernetics_Core 1 5753
Protoss_Dragoon 4 12235
Protoss_Robotics_Facility 1 8280
Protoss_Shuttle 1 10056
Protoss_Zealot 2 11115
Protoss_Observatory 1 10032
Protoss_Robotics_Support_Bay 1 10702
Protoss_Observer 1 11127
Singularity_Charge 1 11399
12235
