Protoss_Assimilator 2 4872
Protoss_Gateway 1 4796
Protoss_Cybernetics_Core 1 6664
Protoss_Zealot 1 6658
Protoss_Dragoon 3 11615
Protoss_Robotics_Facility 1 9358
Protoss_Shuttle 1 10779
Protoss_Robotics_Support_Bay 1 10965
Protoss_Reaver 1 12697
12697
