Protoss_Gateway 1 4335
Protoss_Assimilator 1 4826
Protoss_Cybernetics_Core 1 5786
Protoss_Dragoon 3 10953
Protoss_Nexus 2 12312
Singularity_Charge 1 10155
Protoss_Robotics_Facility 1 12882
12882
