Protoss_Gateway 2 10826
Protoss_Assimilator 1 4290
Protoss_Cybernetics_Core 1 5607
Protoss_Dragoon 7 12481
Protoss_Nexus 2 11589
Singularity_Charge 1 9479
Protoss_Robotics_Facility 1 12086
12481
