Protoss_Gateway 2 10829
Protoss_Assimilator 1 4499
Protoss_Cybernetics_Core 1 5897
Protoss_Dragoon 6 12537
Protoss_Nexus 1 11548
Singularity_Charge 1 9841
Protoss_Robotics_Facility 1 12510
12537
