Protoss_Gateway 1 4226
Protoss_Assimilator 1 4278
Protoss_Cybernetics_Core 1 5775
Protoss_Zealot 1 5686
Protoss_Dragoon 5 11735
Protoss_Robotics_Facility 1 9285
Protoss_Robotics_Support_Bay 1 10005
Protoss_Shuttle 1 11215
Protoss_Reaver 1 12856
12856
