Protoss_Gateway 1 4274
Protoss_Assimilator 1 4564
Protoss_Cybernetics_Core 1 6254
Protoss_Dragoon 3 9712
Protoss_Robotics_Facility 1 9487
Protoss_Robotics_Support_Bay 1 10210
Protoss_Shuttle 1 10935
Protoss_Zealot 2 11537
Protoss_Reaver 1 12493
Protoss_Observatory 1 11925
12493
