Protoss_Gateway 2 10110
Protoss_Assimilator 1 4211
Protoss_Cybernetics_Core 1 5813
Protoss_Dragoon 7 12440
Protoss_Robotics_Facility 1 10191
Singularity_Charge 1 9868
Protoss_Observatory 1 11400
12440
