Protoss_Gateway 2 6431
Protoss_Assimilator 1 4142
Protoss_Cybernetics_Core 1 5595
Protoss_Dragoon 7 10810
Protoss_Robotics_Facility 1 10125
Singularity_Charge 1 9262
Protoss_Shuttle 1 11543
Protoss_Robotics_Support_Bay 1 11384
Protoss_Zealot 2 12005
12005
