Protoss_Gateway 2 10189
Protoss_Assimilator 1 4148
Protoss_Cybernetics_Core 1 5562
Protoss_Zealot 1 5598
Protoss_Dragoon 6 11559
Protoss_Robotics_Facility 1 9711
Protoss_Observatory 1 10400
Singularity_Charge 1 9789
Protoss_Observer 2 12351
Protoss_Nexus 1 13702
13702
