Protoss_Gateway 1 4208
Protoss_Assimilator 1 4447
Protoss_Cybernetics_Core 1 5780
Protoss_Dragoon 5 11846
Protoss_Robotics_Facility 1 9727
Singularity_Charge 1 9642
Protoss_Nexus 1 12570
Protoss_Shuttle 1 11935
Protoss_Robotics_Support_Bay 1 11916
12570
