Protoss_Gateway 1 4249
Protoss_Assimilator 1 4346
Protoss_Cybernetics_Core 1 5786
Protoss_Dragoon 5 12458
Protoss_Robotics_Facility 1 9838
Singularity_Charge 1 9926
Protoss_Observatory 1 10819
Protoss_Nexus 2 13538
Protoss_Observer 1 11894
13538
