Protoss_Gateway 1 4147
Protoss_Assimilator 1 4226
Protoss_Cybernetics_Core 1 5625
Protoss_Zealot 1 5569
Protoss_Dragoon 4 11009
Protoss_Citadel_of_Adun 1 9252
Protoss_Templar_Archives 1 10840
Singularity_Charge 1 10005
Protoss_Nexus 1 13735
Protoss_Dark_Templar 1 12110
13735
