Protoss_Gateway 2 10591
Protoss_Assimilator 1 4502
Protoss_Cybernetics_Core 1 6005
Protoss_Dragoon 5 12039
Protoss_Nexus 1 11215
Protoss_Robotics_Facility 1 11638
Singularity_Charge 1 9885
12039
