Protoss_Gateway 2 10529
Protoss_Assimilator 1 4542
Protoss_Cybernetics_Core 1 6176
Protoss_Dragoon 6 12249
Protoss_Robotics_Facility 1 9964
Singularity_Charge 1 10128
Protoss_Observatory 1 10855
Protoss_Robotics_Support_Bay 1 11101
Protoss_Reaver 1 13010
13010
