Protoss_Gateway 1 4190
Protoss_Assimilator 1 4251
Protoss_Cybernetics_Core 1 5648
Protoss_Zealot 1 5648
Protoss_Dragoon 5 12273
Protoss_Robotics_Facility 1 9308
Protoss_Robotics_Support_Bay 1 10140
Protoss_Shuttle 1 11159
12273
