Protoss_Gateway 1 4111
Protoss_Assimilator 1 4403
Protoss_Cybernetics_Core 1 5794
Protoss_Zealot 1 5631
Protoss_Dragoon 5 12083
Protoss_Robotics_Facility 1 10045
Protoss_Shuttle 1 11469
Singularity_Charge 1 10064
Protoss_Robotics_Support_Bay 1 11044
Protoss_Reaver 1 13027
13027
