Protoss_Nexus 1 6511
Protoss_Gateway 2 6798
Protoss_Assimilator 2 11502
Protoss_Zealot 3 7975
Protoss_Cybernetics_Core 1 7597
Protoss_Dragoon 4 10427
Protoss_Citadel_of_Adun 1 12001
12001
