Protoss_Gateway 2 9598
Protoss_Assimilator 1 4587
Protoss_Cybernetics_Core 1 5870
Protoss_Dragoon 5 11837
Protoss_Robotics_Facility 1 9922
Protoss_Nexus 1 12590
Singularity_Charge 1 9792
Protoss_Observatory 1 10983
Protoss_Observer 1 11999
12590
