Protoss_Gateway 2 10929
Protoss_Assimilator 1 4460
Protoss_Cybernetics_Core 1 5929
Protoss_Dragoon 6 12437
Protoss_Nexus 1 11747
Singularity_Charge 1 9733
Protoss_Robotics_Facility 1 12477
12477
