Protoss_Assimilator 3 11780
Protoss_Gateway 2 10413
Protoss_Nexus 1 8463
Protoss_Zealot 5 11610
Protoss_Cybernetics_Core 1 8878
Protoss_Dragoon 1 10699
Protoss_Robotics_Facility 1 12838
12838
