Protoss_Gateway 2 11982
Protoss_Assimilator 1 4395
Protoss_Cybernetics_Core 1 5702
Protoss_Dragoon 5 12174
Protoss_Nexus 1 12334
Singularity_Charge 1 9912
Protoss_Robotics_Facility 1 12058
12334
