Protoss_Gateway 1 4155
Protoss_Assimilator 1 4510
Protoss_Cybernetics_Core 1 5724
Protoss_Zealot 2 10952
Protoss_Dragoon 3 9774
Protoss_Robotics_Facility 1 8357
Protoss_Shuttle 1 9772
Protoss_Robotics_Support_Bay 1 9616
Protoss_Reaver 1 11605
Protoss_Observatory 1 11448
11605
