Protoss_Gateway 2 11928
Protoss_Assimilator 1 4284
Protoss_Cybernetics_Core 1 5742
Protoss_Zealot 1 6269
Protoss_Nexus 1 9788
Protoss_Dragoon 4 12076
Protoss_Citadel_of_Adun 1 11601
12076
