Protoss_Gateway 2 10629
Protoss_Assimilator 1 4758
Protoss_Cybernetics_Core 1 6236
Protoss_Dragoon 4 10828
Protoss_Robotics_Facility 1 10122
Singularity_Charge 1 10061
Protoss_Shuttle 1 11636
Protoss_Observatory 1 11129
Protoss_Robotics_Support_Bay 1 12023
12023
