Protoss_Gateway 2 9778
Protoss_Assimilator 1 4088
Protoss_Cybernetics_Core 1 5543
Protoss_Dragoon 6 12194
Protoss_Robotics_Facility 1 9317
Protoss_Observatory 1 10043
Singularity_Charge 1 9461
Protoss_Nexus 1 13256
Protoss_Observer 1 11352
13256
