Protoss_Gateway 1 4101
Protoss_Assimilator 1 4322
Protoss_Cybernetics_Core 1 5639
Protoss_Zealot 1 5487
Protoss_Dragoon 4 10271
Protoss_Citadel_of_Adun 1 8824
Protoss_Templar_Archives 1 10419
Singularity_Charge 1 9584
Protoss_Nexus 1 13382
Protoss_Dark_Templar 1 11744
13382
