Protoss_Gateway 1 4130
Protoss_Assimilator 1 4429
Protoss_Cybernetics_Core 1 5670
Protoss_Zealot 1 5502
Protoss_Dragoon 5 11305
Protoss_Nexus 1 12576
Singularity_Charge 1 9836
Protoss_Robotics_Facility 1 12244
12576
