Protoss_Gateway 1 4084
Protoss_Assimilator 1 4180
Protoss_Cybernetics_Core 1 5677
Protoss_Dragoon 5 11694
Protoss_Robotics_Facility 1 9787
Singularity_Charge 1 9806
Protoss_Shuttle 1 11721
Protoss_Observatory 1 11489
Protoss_Robotics_Support_Bay 1 11704
11721
