Protoss_Nexus 2 14007
Protoss_Gateway 2 7782
Protoss_Assimilator 1 5856
Protoss_Cybernetics_Core 1 7665
Protoss_Dragoon 4 10602
Protoss_Citadel_of_Adun 1 10027
Protoss_Templar_Archives 1 12056
Singularity_Charge 1 11337
14007
