Protoss_Nexus 1 6763
Protoss_Gateway 3 11418
Protoss_Assimilator 1 5859
Protoss_Cybernetics_Core 1 7360
Protoss_Zealot 1 7732
Protoss_Dragoon 6 11776
Protoss_Robotics_Facility 1 11790
11790
