Protoss_Nexus 1 6870
Protoss_Gateway 2 8221
Protoss_Assimilator 2 10407
Protoss_Cybernetics_Core 1 7515
Protoss_Dragoon 3 10289
Protoss_Robotics_Facility 1 10377
Protoss_Zealot 2 11429
Protoss_Observatory 1 11289
11429
