Protoss_Gateway 2 8297
Protoss_Assimilator 1 4385
Protoss_Cybernetics_Core 1 5578
Protoss_Zealot 1 5440
Protoss_Citadel_of_Adun 1 7208
Protoss_Dragoon 5 12399
Protoss_Templar_Archives 1 8775
Protoss_Dark_Templar 2 9979
12399
