Protoss_Gateway 2 12724
Protoss_Assimilator 1 4318
Protoss_Cybernetics_Core 1 5692
Protoss_Zealot 1 5871
Protoss_Dragoon 5 12382
Protoss_Nexus 1 11674
Singularity_Charge 1 9888
Protoss_Robotics_Facility 1 11994
12724
