Protoss_Gateway 2 10283
Protoss_Assimilator 1 4343
Protoss_Cybernetics_Core 1 5556
Protoss_Dragoon 3 9063
Protoss_Citadel_of_Adun 1 8641
Protoss_Templar_Archives 1 10149
Protoss_Zealot 1 10296
Singularity_Charge 1 9560
Protoss_Dark_Templar 2 11504
Protoss_Nexus 1 14103
14103
