Protoss_Gateway 2 8209
Protoss_Assimilator 1 4352
Protoss_Cybernetics_Core 1 5860
Protoss_Dragoon 7 11606
Singularity_Charge 1 9724
Protoss_Robotics_Facility 1 11638
Protoss_Zealot 1 12263
12263
