Protoss_Gateway 2 10524
Protoss_Assimilator 1 4398
Protoss_Cybernetics_Core 1 5901
Protoss_Dragoon 3 9786
Protoss_Robotics_Facility 1 9572
Protoss_Citadel_of_Adun 1 9312
Protoss_Templar_Archives 1 10859
Protoss_Shuttle 1 11057
Protoss_Dark_Templar 2 12074
12074
