Protoss_Gateway 2 10514
Protoss_Assimilator 1 4738
Protoss_Cybernetics_Core 1 5947
Protoss_Dragoon 5 11971
Protoss_Robotics_Facility 1 8679
Protoss_Observatory 1 9470
Protoss_Observer 2 11427
11971
