Protoss_Gateway 2 12039
Protoss_Assimilator 1 4346
Protoss_Cybernetics_Core 1 6043
Protoss_Dragoon 4 11390
Protoss_Nexus 1 11229
Protoss_Citadel_of_Adun 1 10865
Singularity_Charge 1 9915
Protoss_Robotics_Facility 1 11910
Protoss_Templar_Archives 1 12374
12374
