Protoss_Assimilator 1 3629
Protoss_Gateway 2 8947
Protoss_Cybernetics_Core 1 6210
Protoss_Dragoon 5 12042
Protoss_Robotics_Facility 1 10551
Protoss_Zealot 1 9936
Singularity_Charge 1 9953
Protoss_Nexus 1 13120
Protoss_Observatory 1 11750
13120
