Protoss_Gateway 1 4158
Protoss_Assimilator 1 4239
Protoss_Cybernetics_Core 1 5783
Protoss_Dragoon 5 11823
Protoss_Robotics_Facility 1 9747
Singularity_Charge 1 9856
Protoss_Observatory 1 10576
Protoss_Nexus 1 13152
Protoss_Observer 1 12157
13152
