Protoss_Gateway 2 11970
Protoss_Assimilator 1 4395
Protoss_Cybernetics_Core 1 6100
Protoss_Dragoon 3 11180
Protoss_Robotics_Facility 1 10220
Protoss_Robotics_Support_Bay 1 10964
Singularity_Charge 1 10823
Protoss_Shuttle 1 12348
12348
