Protoss_Gateway 1 4138
Protoss_Assimilator 1 4378
Protoss_Cybernetics_Core 1 5777
Protoss_Dragoon 3 10509
Protoss_Robotics_Facility 1 8272
Protoss_Zealot 2 11405
Protoss_Shuttle 1 9669
Protoss_Robotics_Support_Bay 1 9353
Protoss_Reaver 1 11789
11789
