Protoss_Gateway 1 4243
Protoss_Assimilator 1 4293
Protoss_Cybernetics_Core 1 5809
Protoss_Dragoon 6 12581
Protoss_Robotics_Facility 1 10106
Singularity_Charge 1 9695
Protoss_Observatory 1 10823
Protoss_Observer 1 11964
Protoss_Nexus 1 14269
14269
