Protoss_Gateway 2 12375
Protoss_Assimilator 1 4211
Protoss_Cybernetics_Core 1 5613
Protoss_Dragoon 5 11387
Protoss_Robotics_Facility 1 10096
Singularity_Charge 1 9792
Protoss_Nexus 1 12921
Protoss_Observatory 1 11069
12921
