Protoss_Gateway 1 4375
Protoss_Assimilator 1 4461
Protoss_Cybernetics_Core 1 6020
Protoss_Zealot 1 5797
Protoss_Dragoon 5 11782
Singularity_Charge 1 10414
Protoss_Nexus 1 13531
Protoss_Robotics_Facility 1 12892
13531
