Protoss_Gateway 1 4559
Protoss_Assimilator 1 5089
Protoss_Zealot 1 5519
Protoss_Cybernetics_Core 1 7003
Protoss_Dragoon 4 12472
Protoss_Robotics_Facility 1 10403
Protoss_Nexus 1 12732
Singularity_Charge 1 10699
Protoss_Observatory 1 11520
12732
