Protoss_Gateway 2 12146
Protoss_Assimilator 1 4248
Protoss_Cybernetics_Core 1 5696
Protoss_Zealot 1 5753
Protoss_Dragoon 4 10500
Protoss_Nexus 1 11886
Singularity_Charge 1 9938
Protoss_Robotics_Facility 1 12158
12158
