Protoss_Gateway 2 11774
Protoss_Zealot 2 6111
Protoss_Assimilator 1 5581
Protoss_Cybernetics_Core 1 7287
Protoss_Dragoon 4 12206
Protoss_Nexus 1 12321
Protoss_Robotics_Facility 1 12371
Singularity_Charge 1 11311
12371
