Protoss_Nexus 1 6883
Protoss_Gateway 2 7773
Protoss_Assimilator 2 12043
Protoss_Cybernetics_Core 1 7504
Protoss_Zealot 1 7741
Protoss_Dragoon 6 12077
Protoss_Robotics_Facility 1 12567
12567
