Protoss_Gateway 2 10189
Protoss_Assimilator 1 4217
Protoss_Cybernetics_Core 1 5837
Protoss_Dragoon 6 12209
Protoss_Robotics_Facility 1 9604
Singularity_Charge 1 9581
Protoss_Observatory 1 10513
Protoss_Nexus 1 13420
Protoss_Observer 1 11645
13420
