Protoss_Gateway 2 11805
Protoss_Assimilator 1 4372
Protoss_Cybernetics_Core 1 5592
Protoss_Dragoon 5 12344
Protoss_Nexus 1 11747
Protoss_Robotics_Facility 1 11474
Singularity_Charge 1 9771
12344
