Protoss_Gateway 2 8431
Protoss_Assimilator 1 4925
Protoss_Cybernetics_Core 1 6178
Protoss_Nexus 1 8952
Protoss_Dragoon 7 12335
Protoss_Robotics_Facility 1 12717
Singularity_Charge 1 11065
12717
