Protoss_Gateway 2 10805
Protoss_Assimilator 1 4416
Protoss_Cybernetics_Core 1 5847
Protoss_Dragoon 6 12320
Protoss_Robotics_Facility 1 10072
Singularity_Charge 1 9754
Protoss_Observatory 1 10812
Protoss_Nexus 1 13549
13549
