Protoss_Gateway 3 8982
Protoss_Zealot 2 9169
Protoss_Nexus 1 8779
Protoss_Assimilator 2 11230
Protoss_Cybernetics_Core 1 8455
Protoss_Dragoon 3 11234
Protoss_Robotics_Facility 1 12992
12992
