Protoss_Gateway 2 10580
Protoss_Assimilator 1 4564
Protoss_Cybernetics_Core 1 5879
Protoss_Dragoon 6 11922
Protoss_Robotics_Facility 1 10402
Singularity_Charge 1 9985
Protoss_Observatory 1 11410
11922
