Protoss_Gateway 2 8581
Protoss_Assimilator 2 11992
Protoss_Nexus 1 8364
Protoss_Cybernetics_Core 1 7565
Protoss_Zealot 1 7512
Protoss_Dragoon 5 11583
Protoss_Robotics_Facility 1 11676
11992
