Protoss_Gateway 3 12402
Protoss_Assimilator 1 4397
Protoss_Cybernetics_Core 1 5783
Protoss_Dragoon 5 12004
Protoss_Nexus 1 11095
Protoss_Robotics_Facility 1 11527
Singularity_Charge 1 9903
12402
