Protoss_Gateway 2 6361
Protoss_Assimilator 1 4170
Protoss_Cybernetics_Core 1 5622
Protoss_Dragoon 5 9519
Singularity_Charge 1 9458
Protoss_Nexus 1 13063
Protoss_Robotics_Facility 1 12826
13063
