Protoss_Gateway 1 4117
Protoss_Assimilator 1 4337
Protoss_Cybernetics_Core 1 5658
Protoss_Dragoon 6 12513
Protoss_Robotics_Facility 1 10691
Singularity_Charge 1 9619
Protoss_Nexus 1 13309
Protoss_Observatory 1 11627
13309
