Protoss_Gateway 1 4154
Protoss_Assimilator 1 4327
Protoss_Cybernetics_Core 1 5742
Protoss_Dragoon 4 11995
Protoss_Robotics_Facility 1 8262
Protoss_Zealot 2 11792
Protoss_Shuttle 1 9678
Protoss_Robotics_Support_Bay 1 9537
Protoss_Reaver 1 11526
Singularity_Charge 1 11343
11995
