Protoss_Gateway 1 4218
Protoss_Assimilator 1 4508
Protoss_Cybernetics_Core 1 5891
Protoss_Zealot 1 5607
Protoss_Dragoon 5 11796
Protoss_Robotics_Facility 1 9929
Protoss_Shuttle 1 11364
Singularity_Charge 1 10035
Protoss_Robotics_Support_Bay 1 10763
Protoss_Reaver 1 12922
12922
