Protoss_Gateway 3 11609
Protoss_Zealot 1 5285
Protoss_Nexus 2 9379
Protoss_Assimilator 1 7738
Protoss_Cybernetics_Core 1 8846
Protoss_Dragoon 2 11594
Protoss_Robotics_Facility 1 13109
13109
