Protoss_Gateway 2 9974
Protoss_Assimilator 1 4363
Protoss_Cybernetics_Core 1 5730
Protoss_Dragoon 6 12455
Protoss_Robotics_Facility 1 9702
Singularity_Charge 1 9613
Protoss_Observatory 1 10415
Protoss_Observer 1 11432
Protoss_Nexus 1 13852
13852
