Protoss_Gateway 2 8107
Protoss_Assimilator 1 4360
Protoss_Cybernetics_Core 1 5800
Protoss_Dragoon 6 11937
Protoss_Nexus 1 12236
Singularity_Charge 1 9742
Protoss_Robotics_Facility 1 11950
12236
