Protoss_Nexus 1 6725
Protoss_Gateway 2 6905
Protoss_Assimilator 1 5751
Protoss_Cybernetics_Core 1 7357
Protoss_Zealot 1 7155
Protoss_Dragoon 7 12402
Protoss_Robotics_Facility 1 12985
12985
