Protoss_Nexus 1 6678
Protoss_Gateway 2 7650
Protoss_Assimilator 1 5822
Protoss_Cybernetics_Core 1 7379
Protoss_Zealot 1 7875
Protoss_Dragoon 6 11937
Protoss_Robotics_Facility 1 11840
Singularity_Charge 1 11279
11937
