Protoss_Gateway 2 12058
Protoss_Assimilator 1 4296
Protoss_Cybernetics_Core 1 5715
Protoss_Dragoon 5 12215
Protoss_Robotics_Facility 1 8164
Protoss_Zealot 1 8891
Protoss_Observatory 1 9048
Protoss_Observer 2 11221
Protoss_Nexus 1 12969
Singularity_Charge 1 11255
12969
