Protoss_Gateway 2 7429
Protoss_Assimilator 1 4387
Protoss_Zealot 1 5066
Protoss_Cybernetics_Core 1 6722
Protoss_Dragoon 6 11943
Protoss_Nexus 1 11848
Protoss_Robotics_Facility 1 12025
Singularity_Charge 1 10500
12025
