Protoss_Gateway 2 9996
Protoss_Assimilator 1 4409
Protoss_Cybernetics_Core 1 5739
Protoss_Dragoon 5 11887
Protoss_Robotics_Facility 1 8363
Protoss_Zealot 1 8926
Protoss_Observatory 1 9092
Protoss_Observer 2 11294
Protoss_Nexus 1 12830
Singularity_Charge 1 11340
12830
