Protoss_Gateway 1 4281
Protoss_Assimilator 1 4403
Protoss_Cybernetics_Core 1 5750
Protoss_Dragoon 6 12464
Protoss_Robotics_Facility 1 8615
Protoss_Observatory 1 9530
Protoss_Observer 1 11039
Protoss_Nexus 1 13335
13335
