Protoss_Gateway 2 12361
Protoss_Assimilator 1 4191
Protoss_Cybernetics_Core 1 5683
Protoss_Zealot 1 5587
Protoss_Dragoon 5 11732
Protoss_Nexus 1 11580
Singularity_Charge 1 9727
Protoss_Robotics_Facility 1 12177
12361
