Protoss_Gateway 2 8009
Protoss_Assimilator 1 4057
Protoss_Cybernetics_Core 1 5636
Protoss_Zealot 1 5434
Protoss_Citadel_of_Adun 1 7132
Protoss_Dragoon 3 11214
Protoss_Templar_Archives 1 8572
Protoss_Dark_Templar 6 12511
Protoss_Nexus 1 11813
12511
