Protoss_Gateway 1 4395
Protoss_Assimilator 1 4343
Protoss_Cybernetics_Core 1 5847
Protoss_Dragoon 4 12183
Protoss_Robotics_Facility 1 8489
Protoss_Zealot 2 9962
Protoss_Shuttle 1 9945
Protoss_Observatory 1 9872
Protoss_Observer 1 10890
Protoss_Robotics_Support_Bay 1 11144
Protoss_Reaver 1 12905
12905
