Protoss_Gateway 1 4144
Protoss_Assimilator 1 4398
Protoss_Cybernetics_Core 1 5780
Protoss_Dragoon 4 11287
Protoss_Robotics_Facility 1 8533
Protoss_Shuttle 1 9927
Protoss_Zealot 1 10117
Protoss_Robotics_Support_Bay 1 10051
Protoss_Reaver 1 11795
Protoss_Observatory 1 11461
11795
