Protoss_Nexus 1 6704
Protoss_Gateway 2 9102
Protoss_Assimilator 1 6231
Protoss_Zealot 2 7954
Protoss_Cybernetics_Core 1 7935
Protoss_Dragoon 5 11709
Protoss_Robotics_Facility 1 13265
13265
