Protoss_Gateway 2 10483
Protoss_Assimilator 1 4275
Protoss_Cybernetics_Core 1 5939
Protoss_Dragoon 4 10888
Protoss_Citadel_of_Adun 1 8837
Protoss_Templar_Archives 1 10296
Singularity_Charge 1 9640
Protoss_Zealot 1 10682
Protoss_Dark_Templar 2 12089
12089
