Protoss_Gateway 2 11752
Protoss_Assimilator 1 4255
Protoss_Cybernetics_Core 1 5594
Protoss_Dragoon 5 12077
Protoss_Nexus 1 11071
Protoss_Robotics_Facility 1 11107
Singularity_Charge 1 9540
Protoss_Observatory 1 11905
12077
