Protoss_Gateway 2 12334
Protoss_Assimilator 1 4261
Protoss_Cybernetics_Core 1 5614
Protoss_Zealot 1 5639
Protoss_Dragoon 5 12130
Protoss_Nexus 1 11784
Singularity_Charge 1 9941
Protoss_Robotics_Facility 1 12089
12334
