Protoss_Gateway 3 12509
Protoss_Assimilator 1 4169
Protoss_Cybernetics_Core 1 5660
Protoss_Zealot 1 5575
Protoss_Dragoon 4 11337
Protoss_Robotics_Facility 1 10204
Singularity_Charge 1 9947
Protoss_Nexus 1 12931
Protoss_Observatory 1 10956
Protoss_Observer 1 12131
12931
