Protoss_Gateway 2 12358
Protoss_Assimilator 1 4388
Protoss_Cybernetics_Core 1 5601
Protoss_Dragoon 4 11829
Protoss_Robotics_Facility 1 8223
Protoss_Zealot 1 8805
Protoss_Nexus 1 11872
Protoss_Observatory 1 10514
Protoss_Observer 1 11537
Singularity_Charge 1 11331
12358
