Protoss_Gateway 1 4152
Protoss_Assimilator 2 11999
Protoss_Cybernetics_Core 1 5742
Protoss_Zealot 1 5721
Protoss_Dragoon 2 8214
Protoss_Citadel_of_Adun 1 7618
Protoss_Templar_Archives 1 9067
Protoss_Dark_Templar 2 11521
Protoss_Nexus 1 12615
Protoss_Stargate 1 12477
12615
