Protoss_Gateway 1 4239
Protoss_Assimilator 1 4211
Protoss_Cybernetics_Core 1 5717
Protoss_Dragoon 5 12385
Protoss_Robotics_Facility 1 8287
Protoss_Shuttle 1 9684
Protoss_Robotics_Support_Bay 1 9895
Protoss_Reaver 1 11713
12385
