Protoss_Gateway 1 4182
Protoss_Assimilator 1 4417
Protoss_Cybernetics_Core 1 5745
Protoss_Dragoon 4 11556
Protoss_Robotics_Facility 1 8271
Protoss_Zealot 1 8964
Protoss_Shuttle 1 9810
Protoss_Robotics_Support_Bay 1 9672
Protoss_Reaver 1 11400
Protoss_Observatory 1 11707
Singularity_Charge 1 11375
11707
