Protoss_Gateway 4 12033
Protoss_Assimilator 1 4378
Protoss_Cybernetics_Core 1 5707
Protoss_Dragoon 5 11653
Protoss_Nexus 1 11065
Protoss_Robotics_Facility 1 10835
Singularity_Charge 1 9601
Protoss_Shuttle 1 12456
12456
