Protoss_Gateway 2 12191
Protoss_Assimilator 1 4283
Protoss_Cybernetics_Core 1 5827
Protoss_Zealot 1 6049
Protoss_Dragoon 5 12112
Protoss_Nexus 1 11943
Singularity_Charge 1 9897
Protoss_Robotics_Facility 1 12036
12191
