Protoss_Gateway 1 4130
Protoss_Assimilator 1 4239
Protoss_Cybernetics_Core 1 5689
Protoss_Zealot 1 5631
Protoss_Dragoon 5 11764
Protoss_Robotics_Facility 1 10276
Singularity_Charge 1 9400
Protoss_Shuttle 1 12110
12110
