Protoss_Gateway 2 4951
Protoss_Zealot 1 5063
Protoss_Assimilator 1 5537
Protoss_Cybernetics_Core 1 7269
Protoss_Dragoon 5 12363
Protoss_Nexus 1 12523
Singularity_Charge 1 10977
12523
