Protoss_Gateway 2 10062
Protoss_Assimilator 1 4362
Protoss_Cybernetics_Core 1 5655
Protoss_Dragoon 7 12429
Protoss_Robotics_Facility 1 10011
Singularity_Charge 1 9522
Protoss_Observatory 1 10804
Protoss_Observer 1 12201
12429
