Protoss_Gateway 2 6841
Protoss_Assimilator 1 4606
Protoss_Cybernetics_Core 1 6067
Protoss_Dragoon 5 10453
Singularity_Charge 1 9730
Protoss_Nexus 1 13588
Protoss_Robotics_Facility 1 13306
13588
