Protoss_Gateway 2 10338
Protoss_Assimilator 1 4448
Protoss_Cybernetics_Core 1 5873
Protoss_Dragoon 5 11729
Protoss_Robotics_Facility 1 8482
Protoss_Zealot 1 9245
Protoss_Observatory 1 9282
Protoss_Observer 2 11177
11729
