Protoss_Gateway 2 10486
Protoss_Assimilator 1 4065
Protoss_Zealot 2 6582
Protoss_Cybernetics_Core 1 6751
Protoss_Dragoon 5 12578
Protoss_Nexus 1 11100
Protoss_Robotics_Facility 1 11185
Singularity_Charge 1 10626
12578
