Protoss_Gateway 1 4113
Protoss_Assimilator 1 4391
Protoss_Cybernetics_Core 1 5563
Protoss_Zealot 1 5481
Protoss_Dragoon 4 10579
Protoss_Citadel_of_Adun 1 9116
Protoss_Templar_Archives 1 10605
Singularity_Charge 1 9827
Protoss_Dark_Templar 1 11864
11864
