Protoss_Assimilator 3 5901
Protoss_Gateway 2 7823
Protoss_Zealot 2 7600
Protoss_Cybernetics_Core 1 7193
Protoss_Dragoon 3 10175
Protoss_Nexus 1 13102
Singularity_Charge 1 11088
13102
