Protoss_Gateway 2 10293
Protoss_Assimilator 1 4346
Protoss_Cybernetics_Core 1 5661
Protoss_Dragoon 3 9537
Protoss_Nexus 2 13266
Singularity_Charge 1 9543
Protoss_Robotics_Facility 1 12745
13266
