Protoss_Gateway 2 10188
Protoss_Assimilator 1 4280
Protoss_Zealot 3 7006
Protoss_Cybernetics_Core 1 6974
Protoss_Dragoon 6 12487
Protoss_Robotics_Facility 1 10473
Protoss_Observatory 1 11400
Singularity_Charge 1 10919
12487
