Protoss_Gateway 2 10597
Protoss_Assimilator 1 4297
Protoss_Cybernetics_Core 1 5750
Protoss_Dragoon 4 11161
Protoss_Robotics_Facility 1 8223
Protoss_Zealot 1 8906
Protoss_Observatory 1 9086
Protoss_Observer 2 11072
Protoss_Nexus 1 13833
Singularity_Charge 1 11320
13833
