Protoss_Gateway 1 4220
Protoss_Assimilator 1 4412
Protoss_Cybernetics_Core 1 5797
Protoss_Dragoon 4 12104
Protoss_Robotics_Facility 1 8237
Protoss_Shuttle 1 9886
Protoss_Zealot 2 10981
Protoss_Robotics_Support_Bay 1 10195
Protoss_Reaver 1 12041
Singularity_Charge 1 11340
12104
