Protoss_Gateway 2 9697
Protoss_Assimilator 1 4638
Protoss_Cybernetics_Core 1 6187
Protoss_Zealot 1 5929
Protoss_Dragoon 6 12148
Protoss_Robotics_Facility 1 11991
Singularity_Charge 1 10137
12148
