Protoss_Gateway 2 10100
Protoss_Assimilator 1 4308
Protoss_Cybernetics_Core 1 5769
Protoss_Dragoon 5 12071
Protoss_Robotics_Facility 1 8359
Protoss_Zealot 1 8932
Protoss_Observatory 1 9237
Protoss_Observer 2 11153
Protoss_Nexus 1 13217
Singularity_Charge 1 11308
13217
