Protoss_Gateway 3 10192
Protoss_Assimilator 1 4404
Protoss_Cybernetics_Core 1 5644
Protoss_Dragoon 7 12566
Protoss_Zealot 2 11446
Protoss_Robotics_Facility 1 8894
Protoss_Observatory 1 9780
Protoss_Observer 1 11271
12566
