Protoss_Gateway 2 12789
Protoss_Assimilator 1 4451
Protoss_Cybernetics_Core 1 5753
Protoss_Dragoon 5 12279
Protoss_Robotics_Facility 1 8367
Protoss_Zealot 1 8958
Protoss_Observatory 1 9291
Protoss_Observer 2 11528
Protoss_Nexus 1 13263
13263
