Protoss_Gateway 2 12020
Protoss_Assimilator 1 4264
Protoss_Cybernetics_Core 1 5682
Protoss_Dragoon 5 12470
Protoss_Robotics_Facility 1 8176
Protoss_Zealot 1 8841
Protoss_Observatory 1 9026
Protoss_Observer 2 11174
Protoss_Nexus 1 12662
Singularity_Charge 1 11276
Protoss_Citadel_of_Adun 1 12728
12728
