Protoss_Nexus 1 6868
Protoss_Gateway 2 7694
Protoss_Assimilator 1 6160
Protoss_Cybernetics_Core 1 7565
Protoss_Zealot 1 7387
Protoss_Dragoon 4 10936
Protoss_Robotics_Facility 1 12910
12910
