Protoss_Gateway 1 4208
Protoss_Assimilator 1 4552
Protoss_Cybernetics_Core 1 5727
Protoss_Zealot 1 5914
Protoss_Dragoon 5 11978
Protoss_Robotics_Facility 1 8765
Protoss_Observatory 1 9780
Protoss_Observer 1 10899
Protoss_Nexus 1 13372
13372
