Protoss_Gateway 2 10811
Protoss_Assimilator 1 4455
Protoss_Cybernetics_Core 1 5690
Protoss_Dragoon 6 12153
Protoss_Nexus 1 11343
Singularity_Charge 1 9698
Protoss_Robotics_Facility 1 12327
12327
