Protoss_Gateway 2 12811
Protoss_Assimilator 1 4489
Protoss_Cybernetics_Core 1 6213
Protoss_Zealot 1 6251
Protoss_Dragoon 3 9941
Protoss_Citadel_of_Adun 1 8841
Protoss_Templar_Archives 1 10322
Protoss_Nexus 2 12892
Singularity_Charge 1 9970
Protoss_Dark_Templar 1 11530
12892
