Protoss_Gateway 3 11158
Protoss_Assimilator 1 4144
Protoss_Cybernetics_Core 1 5592
Protoss_Dragoon 7 12534
Protoss_Robotics_Facility 1 10268
Singularity_Charge 1 9610
Protoss_Zealot 1 11039
Protoss_Observatory 1 11094
Protoss_Shuttle 1 12441
12534
