Protoss_Gateway 3 12814
Protoss_Assimilator 1 4463
Protoss_Cybernetics_Core 1 5847
Protoss_Dragoon 6 12118
Protoss_Nexus 1 11510
Singularity_Charge 1 9683
Protoss_Robotics_Facility 1 12434
12814
