Protoss_Nexus 1 6638
Protoss_Gateway 2 7490
Protoss_Assimilator 1 5652
Protoss_Cybernetics_Core 1 7117
Protoss_Zealot 1 7492
Protoss_Dragoon 6 11726
Protoss_Robotics_Facility 1 12038
12038
