Protoss_Gateway 1 4117
Protoss_Assimilator 1 4217
Protoss_Cybernetics_Core 1 5676
Protoss_Zealot 1 5432
Protoss_Dragoon 6 12467
Protoss_Robotics_Facility 1 10558
Singularity_Charge 1 9994
Protoss_Shuttle 1 12122
Protoss_Robotics_Support_Bay 1 11488
12467
