Protoss_Gateway 2 10789
Protoss_Assimilator 1 4340
Protoss_Cybernetics_Core 1 5837
Protoss_Dragoon 5 12490
Protoss_Robotics_Facility 1 8452
Protoss_Zealot 1 9181
Protoss_Observatory 1 9326
Protoss_Observer 2 11241
Protoss_Nexus 1 13639
13639
