Protoss_Gateway 2 11070
Protoss_Assimilator 1 4419
Protoss_Cybernetics_Core 1 5786
Protoss_Dragoon 5 12429
Protoss_Robotics_Facility 1 8369
Protoss_Observatory 1 9449
Protoss_Zealot 1 10161
Protoss_Observer 2 11347
Protoss_Nexus 1 13560
Singularity_Charge 1 11369
13560
