Protoss_Gateway 2 9510
Protoss_Assimilator 1 4444
Protoss_Cybernetics_Core 1 5818
Protoss_Zealot 1 5944
Protoss_Dragoon 4 11928
Protoss_Shield_Battery 1 8637
Singularity_Charge 1 11339
11928
