Protoss_Assimilator 1 3421
Protoss_Gateway 2 11616
Protoss_Cybernetics_Core 1 6219
Protoss_Zealot 1 6163
Protoss_Dragoon 4 11129
Protoss_Nexus 1 11690
Protoss_Citadel_of_Adun 1 10890
Singularity_Charge 1 10360
Protoss_Robotics_Facility 1 12704
Protoss_Templar_Archives 1 12532
12704
