Protoss_Gateway 1 4073
Protoss_Assimilator 1 4448
Protoss_Cybernetics_Core 1 5663
Protoss_Zealot 1 5467
Protoss_Dragoon 5 11586
Protoss_Nexus 1 11714
Singularity_Charge 1 9903
Protoss_Robotics_Facility 1 12080
12080
