Protoss_Gateway 2 7448
Protoss_Assimilator 1 4207
Protoss_Zealot 1 5139
Protoss_Cybernetics_Core 1 6769
Protoss_Dragoon 4 10702
Protoss_Nexus 2 13855
Singularity_Charge 1 11030
13855
