Protoss_Assimilator 1 3645
Protoss_Gateway 2 9576
Protoss_Cybernetics_Core 1 6204
Protoss_Zealot 1 6152
Protoss_Dragoon 2 8501
Protoss_Citadel_of_Adun 1 8683
Protoss_Robotics_Facility 1 9898
Protoss_Templar_Archives 1 10135
Protoss_Shuttle 1 11306
Protoss_Dark_Templar 4 12484
12484
