Protoss_Gateway 1 4000
Protoss_Assimilator 1 4217
Protoss_Cybernetics_Core 1 5613
Protoss_Zealot 1 5408
Protoss_Dragoon 5 11501
Protoss_Nexus 1 11594
Singularity_Charge 1 9815
Protoss_Robotics_Facility 1 11945
11945
