Protoss_Nexus 1 6622
Protoss_Gateway 2 6978
Protoss_Assimilator 2 10239
Protoss_Cybernetics_Core 1 7496
Protoss_Zealot 1 7553
Protoss_Dragoon 3 9961
Protoss_Citadel_of_Adun 1 11404
Protoss_Robotics_Facility 1 12462
12462
