Protoss_Gateway 3 12555
Protoss_Assimilator 1 4160
Protoss_Cybernetics_Core 1 5724
Protoss_Dragoon 5 11875
Protoss_Nexus 1 11383
Singularity_Charge 1 9525
Protoss_Robotics_Facility 1 12286
12555
