Protoss_Gateway 2 12765
Protoss_Assimilator 1 4148
Protoss_Cybernetics_Core 1 5589
Protoss_Dragoon 4 11615
Protoss_Zealot 1 7884
Protoss_Robotics_Facility 1 9033
Protoss_Observatory 1 9806
Singularity_Charge 1 9274
Protoss_Observer 2 11753
Protoss_Nexus 1 13009
13009
