Protoss_Gateway 2 10088
Protoss_Assimilator 1 4469
Protoss_Cybernetics_Core 1 6077
Protoss_Robotics_Facility 1 8100
Protoss_Dragoon 3 10427
Protoss_Observatory 1 8914
Protoss_Observer 2 10834
Protoss_Zealot 2 11288
Protoss_Shuttle 1 12567
12567
