Protoss_Gateway 2 11815
Protoss_Assimilator 1 4376
Protoss_Cybernetics_Core 1 5745
Protoss_Dragoon 5 11972
Protoss_Nexus 1 11775
Protoss_Robotics_Facility 1 11098
Singularity_Charge 1 9584
Protoss_Observatory 1 11796
11972
