Protoss_Gateway 1 4082
Protoss_Assimilator 1 4205
Protoss_Cybernetics_Core 1 5588
Protoss_Robotics_Facility 1 7785
Protoss_Dragoon 3 10438
Protoss_Observatory 1 8599
Protoss_Observer 1 10109
Protoss_Nexus 1 13187
13187
