Protoss_Gateway 2 10125
Protoss_Assimilator 1 4191
Protoss_Zealot 1 5294
Protoss_Cybernetics_Core 1 6669
Protoss_Dragoon 7 12458
Protoss_Robotics_Facility 1 10189
Protoss_Observatory 1 11015
Singularity_Charge 1 10708
12458
