Protoss_Gateway 2 7449
Protoss_Assimilator 1 4426
Protoss_Zealot 2 7349
Protoss_Cybernetics_Core 1 6800
Protoss_Dragoon 5 10561
Protoss_Nexus 1 13041
Singularity_Charge 1 10497
Protoss_Robotics_Facility 1 12791
13041
