Protoss_Gateway 1 4346
Protoss_Assimilator 1 4495
Protoss_Cybernetics_Core 1 5789
Protoss_Zealot 1 5674
Protoss_Dragoon 4 12086
Protoss_Nexus 1 10834
Protoss_Robotics_Facility 1 10507
Protoss_Shuttle 1 12151
Protoss_Robotics_Support_Bay 1 12098
12151
