Protoss_Gateway 2 8429
Protoss_Assimilator 1 4691
Protoss_Cybernetics_Core 1 6078
Protoss_Nexus 1 8873
Protoss_Dragoon 7 11849
Singularity_Charge 1 10845
Protoss_Robotics_Facility 1 12987
12987
