Protoss_Gateway 3 12353
Protoss_Assimilator 1 4106
Protoss_Cybernetics_Core 1 5592
Protoss_Dragoon 6 12569
Protoss_Nexus 1 11434
Singularity_Charge 1 9695
Protoss_Robotics_Facility 1 12004
12569
