Protoss_Gateway 1 4530
Protoss_Assimilator 1 4845
Protoss_Zealot 2 7978
Protoss_Cybernetics_Core 1 7574
Protoss_Robotics_Facility 1 9892
Protoss_Dragoon 2 11583
Protoss_Observatory 1 10604
Protoss_Shuttle 1 11338
Protoss_Forge 1 11038
Protoss_Observer 1 12181
Protoss_Robotics_Support_Bay 1 12016
12181
