Protoss_Gateway 2 11701
Protoss_Assimilator 1 4135
Protoss_Cybernetics_Core 1 5566
Protoss_Zealot 1 5458
Protoss_Citadel_of_Adun 1 7029
Protoss_Dragoon 3 11764
Protoss_Templar_Archives 1 8518
Protoss_Dark_Templar 1 9718
Protoss_Nexus 1 11841
Protoss_Robotics_Facility 1 11738
11841
