Protoss_Gateway 3 11872
Protoss_Assimilator 1 4191
Protoss_Cybernetics_Core 1 5727
Protoss_Dragoon 4 11313
Protoss_Nexus 1 11273
Protoss_Robotics_Facility 1 10757
Singularity_Charge 1 9622
Protoss_Observatory 1 11665
11872
