Protoss_Gateway 1 4287
Protoss_Assimilator 1 4590
Protoss_Cybernetics_Core 1 5844
Protoss_Zealot 1 5780
Protoss_Robotics_Facility 1 8309
Protoss_Dragoon 3 11808
Protoss_Shuttle 1 9722
Protoss_Robotics_Support_Bay 1 9527
Protoss_Reaver 1 11722
Protoss_Observatory 1 11798
11808
