Protoss_Gateway 2 8250
Protoss_Assimilator 1 4379
Protoss_Cybernetics_Core 1 5658
Protoss_Zealot 1 5625
Protoss_Citadel_of_Adun 1 7223
Protoss_Dragoon 3 12350
Protoss_Templar_Archives 1 8753
Protoss_Dark_Templar 2 9967
Protoss_Nexus 1 12663
12663
