Protoss_Gateway 2 9446
Protoss_Assimilator 1 4406
Protoss_Zealot 2 6749
Protoss_Cybernetics_Core 1 6710
Protoss_Dragoon 6 12244
Protoss_Nexus 1 13227
Singularity_Charge 1 10998
13227
