Protoss_Gateway 2 8475
Protoss_Nexus 2 13584
Protoss_Zealot 1 5528
Protoss_Assimilator 2 11269
Protoss_Cybernetics_Core 1 7485
Protoss_Dragoon 5 12598
Protoss_Robotics_Facility 1 11893
13584
