Protoss_Nexus 1 6690
Protoss_Gateway 2 7673
Protoss_Assimilator 2 11964
Protoss_Cybernetics_Core 1 7419
Protoss_Zealot 1 7571
Protoss_Dragoon 6 11758
Protoss_Robotics_Facility 1 12226
12226
