Protoss_Nexus 1 6827
Protoss_Gateway 2 7830
Protoss_Assimilator 2 10829
Protoss_Cybernetics_Core 1 7387
Protoss_Zealot 1 7916
Protoss_Dragoon 6 12010
Protoss_Robotics_Facility 1 12914
12914
