Protoss_Gateway 2 12314
Protoss_Assimilator 1 4512
Protoss_Cybernetics_Core 1 5671
Protoss_Zealot 1 5508
Protoss_Dragoon 6 12534
Protoss_Nexus 1 11999
Singularity_Charge 1 9812
Protoss_Robotics_Facility 1 12294
12534
