Protoss_Gateway 2 11388
Protoss_Assimilator 1 4409
Protoss_Cybernetics_Core 1 5942
Protoss_Dragoon 5 12336
Protoss_Robotics_Facility 1 9658
Protoss_Observatory 1 10403
Protoss_Observer 1 11753
12336
