Protoss_Gateway 1 4417
Protoss_Assimilator 1 4391
Protoss_Cybernetics_Core 1 6195
Protoss_Zealot 2 12090
Protoss_Dragoon 4 10295
Protoss_Robotics_Facility 1 10200
Protoss_Shuttle 1 11645
Protoss_Robotics_Support_Bay 1 11518
12090
