Protoss_Gateway 1 4473
Protoss_Assimilator 1 4635
Protoss_Cybernetics_Core 1 6159
Protoss_Dragoon 4 11868
Protoss_Robotics_Facility 1 9017
Protoss_Shuttle 1 10430
Protoss_Robotics_Support_Bay 1 10055
Protoss_Reaver 1 11988
Protoss_Observatory 1 11215
11988
