Protoss_Gateway 1 4331
Protoss_Assimilator 1 4603
Protoss_Cybernetics_Core 1 5952
Protoss_Dragoon 4 12329
Protoss_Nexus 1 11617
Protoss_Citadel_of_Adun 1 10482
Singularity_Charge 1 9909
Protoss_Templar_Archives 1 12027
Protoss_Stargate 1 12648
12648
