Protoss_Gateway 1 4287
Protoss_Assimilator 1 4654
Protoss_Cybernetics_Core 1 5951
Protoss_Robotics_Facility 1 8122
Protoss_Dragoon 2 9351
Protoss_Shuttle 1 9640
Protoss_Robotics_Support_Bay 1 9828
Protoss_Reaver 1 11568
Protoss_Zealot 2 12072
12072
