Protoss_Gateway 3 11090
Protoss_Assimilator 1 4575
Protoss_Cybernetics_Core 1 5932
Protoss_Nexus 1 9536
Protoss_Dragoon 5 12604
Protoss_Zealot 2 11303
Singularity_Charge 1 10960
12604
