Protoss_Nexus 1 6599
Protoss_Gateway 2 12008
Protoss_Assimilator 2 9156
Protoss_Cybernetics_Core 1 7264
Protoss_Zealot 2 8420
Protoss_Dragoon 4 12039
Protoss_Citadel_of_Adun 1 11565
Singularity_Charge 1 11191
Protoss_Robotics_Facility 1 13137
13137
