Protoss_Nexus 1 6731
Protoss_Gateway 3 11960
Protoss_Assimilator 2 7884
Protoss_Cybernetics_Core 1 7591
Protoss_Dragoon 4 12291
Protoss_Robotics_Facility 1 11009
Protoss_Citadel_of_Adun 1 11423
Protoss_Observatory 1 11755
12291
