Protoss_Gateway 2 11294
Protoss_Assimilator 1 4571
Protoss_Cybernetics_Core 1 5853
Protoss_Dragoon 6 12496
Protoss_Nexus 1 11828
Protoss_Robotics_Facility 1 11536
Singularity_Charge 1 9985
12496
