Protoss_Gateway 2 9378
Protoss_Assimilator 1 4992
Protoss_Zealot 3 7340
Protoss_Cybernetics_Core 1 6822
Protoss_Dragoon 4 10678
Protoss_Robotics_Facility 2 12952
Protoss_Nexus 1 13395
13395
