Protoss_Gateway 2 6791
Protoss_Assimilator 1 4142
Protoss_Cybernetics_Core 1 5576
Protoss_Dragoon 5 9194
Singularity_Charge 1 9382
Protoss_Nexus 1 12707
Protoss_Robotics_Facility 1 12601
12707
