Protoss_Gateway 2 8748
Protoss_Assimilator 1 4594
Protoss_Cybernetics_Core 1 5789
Protoss_Dragoon 5 12265
Protoss_Nexus 1 12103
Protoss_Zealot 2 10621
Singularity_Charge 1 9859
Protoss_Robotics_Facility 1 12267
12267
