Protoss_Gateway 2 9058
Protoss_Assimilator 2 11966
Protoss_Cybernetics_Core 1 5829
Protoss_Dragoon 6 12420
Protoss_Nexus 1 12306
Singularity_Charge 1 9888
Protoss_Citadel_of_Adun 1 12560
12560
