Protoss_Gateway 2 9421
Protoss_Assimilator 2 4772
Protoss_Cybernetics_Core 1 6239
Protoss_Dragoon 5 12604
Protoss_Nexus 1 12631
Singularity_Charge 1 10286
Protoss_Robotics_Facility 1 13071
13071
