Protoss_Gateway 1 4518
Protoss_Assimilator 1 4403
Protoss_Cybernetics_Core 1 6007
Protoss_Dragoon 4 12509
Protoss_Robotics_Facility 1 9771
Protoss_Zealot 2 11326
Protoss_Shuttle 1 11168
Protoss_Observatory 1 10579
Singularity_Charge 1 9938
Protoss_Robotics_Support_Bay 1 11587
Protoss_Observer 1 12144
12509
