Protoss_Gateway 2 11749
Protoss_Assimilator 1 4681
Protoss_Zealot 1 5417
Protoss_Cybernetics_Core 1 6235
Protoss_Dragoon 3 10405
Protoss_Robotics_Facility 1 8839
Protoss_Shuttle 1 10284
Protoss_Robotics_Support_Bay 1 9660
Protoss_Reaver 1 12468
Protoss_Observatory 1 11738
12468
