Protoss_Gateway 2 9251
Protoss_Assimilator 1 4594
Protoss_Zealot 1 5240
Protoss_Cybernetics_Core 1 7016
Protoss_Dragoon 5 12579
Protoss_Nexus 1 13550
Singularity_Charge 1 10788
Protoss_Robotics_Facility 1 12818
13550
