Protoss_Gateway 1 4079
Protoss_Assimilator 1 4318
Protoss_Cybernetics_Core 1 5604
Protoss_Dragoon 5 12332
Protoss_Robotics_Facility 1 9033
Protoss_Shuttle 1 10474
Protoss_Robotics_Support_Bay 1 9919
Protoss_Reaver 1 12032
Singularity_Charge 1 11302
12332
