Protoss_Gateway 2 9994
Protoss_Assimilator 1 4366
Protoss_Cybernetics_Core 1 5794
Protoss_Dragoon 4 11846
Protoss_Robotics_Facility 1 8821
Protoss_Zealot 1 9602
Protoss_Shuttle 1 10504
Protoss_Observatory 1 10168
Protoss_Robotics_Support_Bay 1 10795
Protoss_Reaver 1 12644
12644
