Protoss_Gateway 1 4267
Protoss_Assimilator 1 4249
Protoss_Cybernetics_Core 1 5870
Protoss_Dragoon 4 12344
Protoss_Nexus 2 12532
Singularity_Charge 1 9751
Protoss_Robotics_Facility 1 12670
12670
