Protoss_Gateway 2 8910
Protoss_Assimilator 1 4280
Protoss_Zealot 2 6052
Protoss_Cybernetics_Core 1 6782
Protoss_Dragoon 4 11618
Protoss_Nexus 1 11976
Protoss_Robotics_Facility 1 11556
Singularity_Charge 1 10638
Protoss_Citadel_of_Adun 1 12271
12271
