Protoss_Gateway 2 7359
Protoss_Assimilator 1 4281
Protoss_Cybernetics_Core 1 5544
Protoss_Nexus 1 10105
Protoss_Dragoon 6 11624
Singularity_Charge 1 9206
Protoss_Robotics_Facility 1 11809
11809
