Protoss_Nexus 1 6666
Protoss_Gateway 2 9725
Protoss_Assimilator 1 5777
Protoss_Cybernetics_Core 1 7359
Protoss_Zealot 1 7308
Protoss_Dragoon 6 12587
Protoss_Robotics_Facility 1 11274
Singularity_Charge 1 11264
Protoss_Observatory 1 12092
12587
