Protoss_Gateway 1 4515
Protoss_Assimilator 1 4572
Protoss_Cybernetics_Core 1 6009
Protoss_Dragoon 1 7317
Protoss_Robotics_Facility 1 8539
Protoss_Shuttle 1 10335
Protoss_Robotics_Support_Bay 1 9727
Protoss_Zealot 2 11834
Protoss_Reaver 1 11943
Protoss_Observatory 1 11894
11943
