Protoss_Gateway 2 9782
Protoss_Assimilator 1 4508
Protoss_Cybernetics_Core 1 5813
Protoss_Dragoon 6 11783
Protoss_Robotics_Facility 1 11107
Protoss_Zealot 1 12152
Protoss_Shuttle 1 12648
Singularity_Charge 1 11240
12648
