Protoss_Gateway 2 7685
Protoss_Assimilator 1 4117
Protoss_Zealot 2 6484
Protoss_Cybernetics_Core 1 6994
Protoss_Dragoon 5 11363
Protoss_Robotics_Facility 1 11662
Singularity_Charge 1 10866
11662
