Protoss_Gateway 1 4338
Protoss_Assimilator 1 4363
Protoss_Cybernetics_Core 1 5840
Protoss_Dragoon 5 11949
Protoss_Robotics_Facility 2 10533
Singularity_Charge 1 9499
Protoss_Shuttle 1 12201
Protoss_Robotics_Support_Bay 1 11750
12201
