Protoss_Gateway 2 8936
Protoss_Assimilator 1 4236
Protoss_Cybernetics_Core 1 5636
Protoss_Dragoon 8 11536
Singularity_Charge 1 9768
Protoss_Nexus 1 13808
Protoss_Robotics_Facility 1 13145
13808
