Protoss_Gateway 3 11004
Protoss_Assimilator 1 4264
Protoss_Cybernetics_Core 1 5765
Protoss_Dragoon 6 12396
Protoss_Nexus 1 11190
Protoss_Robotics_Facility 1 10672
Singularity_Charge 1 9692
Protoss_Observatory 1 11722
12396
