Protoss_Gateway 2 6277
Protoss_Assimilator 1 4309
Protoss_Cybernetics_Core 1 5689
Protoss_Dragoon 7 12197
Protoss_Nexus 1 11897
Singularity_Charge 1 9653
Protoss_Robotics_Facility 1 12368
12368
