Protoss_Gateway 3 10287
Protoss_Assimilator 1 4611
Protoss_Cybernetics_Core 1 5947
Protoss_Dragoon 4 10781
Protoss_Citadel_of_Adun 1 9189
Protoss_Templar_Archives 1 10632
Singularity_Charge 1 9607
Protoss_Dark_Templar 3 12115
12115
