Protoss_Gateway 2 12585
Protoss_Assimilator 1 4286
Protoss_Cybernetics_Core 1 6042
Protoss_Robotics_Facility 1 7975
Protoss_Dragoon 4 12051
Protoss_Shuttle 1 9413
Protoss_Observatory 1 9181
Protoss_Observer 3 12223
Singularity_Charge 1 10816
12585
