Protoss_Gateway 2 12454
Protoss_Assimilator 1 4332
Protoss_Cybernetics_Core 1 5780
Protoss_Dragoon 3 12497
Protoss_Robotics_Facility 1 8568
Protoss_Shuttle 1 9977
Protoss_Observatory 1 9415
Protoss_Robotics_Support_Bay 1 9773
Protoss_Observer 1 10820
Protoss_Reaver 1 12615
12615
