Protoss_Assimilator 1 3343
Protoss_Gateway 2 9615
Protoss_Cybernetics_Core 1 6195
Protoss_Citadel_of_Adun 1 7697
Protoss_Robotics_Facility 1 8805
Protoss_Templar_Archives 1 9170
Protoss_Dragoon 1 9674
Protoss_Shuttle 1 10624
Protoss_Dark_Templar 2 11038
Protoss_Observatory 1 10907
Protoss_Observer 1 12102
12102
