Protoss_Gateway 2 9993
Protoss_Assimilator 1 4467
Protoss_Cybernetics_Core 1 6058
Protoss_Robotics_Facility 1 8053
Protoss_Zealot 1 7290
Protoss_Observatory 1 8760
Protoss_Dragoon 4 11552
Protoss_Observer 3 11790
Singularity_Charge 1 11226
11790
