Protoss_Gateway 2 9702
Protoss_Assimilator 1 4334
Protoss_Cybernetics_Core 1 5868
Protoss_Dragoon 7 12203
Protoss_Nexus 1 12502
Singularity_Charge 1 9856
Protoss_Robotics_Facility 1 13134
13134
