Protoss_Gateway 1 4117
Protoss_Assimilator 1 4504
Protoss_Zealot 1 5117
Protoss_Cybernetics_Core 1 7583
Protoss_Dragoon 4 12104
Protoss_Stargate 1 10521
Protoss_Citadel_of_Adun 1 11314
Protoss_Scout 1 12436
12436
