Protoss_Gateway 3 11961
Protoss_Assimilator 1 4710
Protoss_Cybernetics_Core 1 6023
Protoss_Dragoon 6 12244
Protoss_Robotics_Facility 1 10245
Singularity_Charge 1 10465
Protoss_Observatory 1 11719
12244
