Protoss_Gateway 2 11704
Protoss_Assimilator 1 4193
Protoss_Cybernetics_Core 1 5743
Protoss_Dragoon 1 6958
Protoss_Robotics_Facility 1 8467
Protoss_Zealot 2 9924
Protoss_Shuttle 1 9874
Protoss_Robotics_Support_Bay 1 9382
Protoss_Reaver 1 11481
Protoss_Observatory 1 11561
11704
