Protoss_Gateway 2 11619
Protoss_Assimilator 2 4791
Protoss_Cybernetics_Core 1 6318
Protoss_Dragoon 5 11978
Protoss_Robotics_Facility 1 10858
Singularity_Charge 1 10370
Protoss_Observatory 1 11990
11990
