Protoss_Gateway 1 4733
Protoss_Assimilator 1 4662
Protoss_Cybernetics_Core 1 6324
Protoss_Dragoon 4 10912
Protoss_Robotics_Facility 1 10456
Singularity_Charge 1 10128
Protoss_Shuttle 1 11967
Protoss_Zealot 1 11774
Protoss_Robotics_Support_Bay 1 11555
11967
