Protoss_Gateway 2 9290
Protoss_Assimilator 1 4429
Protoss_Cybernetics_Core 1 5815
Protoss_Dragoon 6 12110
Protoss_Nexus 1 10334
Singularity_Charge 1 9806
Protoss_Robotics_Facility 1 11814
12110
