Protoss_Gateway 2 8901
Protoss_Assimilator 1 4226
Protoss_Cybernetics_Core 1 5941
Protoss_Dragoon 6 12300
Protoss_Robotics_Facility 1 11395
Singularity_Charge 1 10099
Protoss_Nexus 1 13623
Protoss_Observatory 1 12102
13623
