Protoss_Gateway 2 10373
Protoss_Assimilator 1 4382
Protoss_Cybernetics_Core 1 5825
Protoss_Dragoon 6 11956
Protoss_Robotics_Facility 1 9900
Singularity_Charge 1 10048
Protoss_Observatory 1 10847
11956
