Protoss_Gateway 2 10237
Protoss_Assimilator 1 4404
Protoss_Cybernetics_Core 1 5663
Protoss_Dragoon 6 11539
Protoss_Robotics_Facility 1 10287
Singularity_Charge 1 9865
Protoss_Observatory 1 11068
Protoss_Observer 1 12214
12214
