Protoss_Gateway 2 10477
Protoss_Assimilator 1 4665
Protoss_Cybernetics_Core 1 5958
Protoss_Dragoon 4 10917
Protoss_Robotics_Facility 1 10040
Protoss_Shuttle 1 11455
Singularity_Charge 1 10275
Protoss_Robotics_Support_Bay 1 11679
11679
