Protoss_Gateway 2 9267
Protoss_Assimilator 1 4845
Protoss_Cybernetics_Core 1 6375
Protoss_Dragoon 4 10492
Protoss_Citadel_of_Adun 1 10580
Singularity_Charge 1 10245
Protoss_Templar_Archives 1 12036
Protoss_Nexus 1 14005
14005
