Protoss_Gateway 2 9612
Protoss_Assimilator 1 4520
Protoss_Cybernetics_Core 1 6050
Protoss_Dragoon 6 11915
Protoss_Robotics_Facility 1 8613
Protoss_Observatory 1 9470
Protoss_Observer 1 10956
Singularity_Charge 1 11365
11915
