Protoss_Gateway 2 10141
Protoss_Assimilator 1 4344
Protoss_Cybernetics_Core 1 6065
Protoss_Dragoon 5 11992
Protoss_Robotics_Facility 1 8861
Protoss_Observatory 1 10099
Protoss_Observer 1 11307
11992
