Protoss_Gateway 1 4113
Protoss_Assimilator 1 4169
Protoss_Cybernetics_Core 1 5568
Protoss_Dragoon 5 11419
Protoss_Nexus 1 11899
Singularity_Charge 1 9236
Protoss_Stargate 1 12726
12726
