Protoss_Gateway 2 9845
Protoss_Assimilator 1 4747
Protoss_Cybernetics_Core 1 5787
Protoss_Dragoon 3 9834
Protoss_Robotics_Facility 1 8912
Protoss_Shuttle 1 10643
Protoss_Robotics_Support_Bay 1 10655
Protoss_Zealot 2 11439
Protoss_Reaver 1 12498
12498
