Protoss_Gateway 2 10060
Protoss_Assimilator 1 4325
Protoss_Cybernetics_Core 1 5951
Protoss_Dragoon 6 12475
Protoss_Robotics_Facility 1 8501
Protoss_Observatory 1 9890
Protoss_Observer 1 10919
12475
