Protoss_Gateway 2 10028
Protoss_Assimilator 1 4278
Protoss_Cybernetics_Core 1 5786
Protoss_Dragoon 5 11810
Protoss_Robotics_Facility 1 9339
Protoss_Observatory 1 10045
Singularity_Charge 1 9997
Protoss_Observer 1 11132
Protoss_Nexus 1 14253
14253
