Protoss_Gateway 2 8971
Protoss_Assimilator 1 4330
Protoss_Cybernetics_Core 1 5742
Protoss_Dragoon 6 12047
Protoss_Nexus 1 11943
Singularity_Charge 1 9792
Protoss_Zealot 1 11563
12047
