Protoss_Gateway 2 10264
Protoss_Assimilator 1 4829
Protoss_Cybernetics_Core 1 6192
Protoss_Robotics_Facility 1 8277
Protoss_Dragoon 4 11905
Protoss_Observatory 1 8975
Protoss_Observer 1 10205
Protoss_Shuttle 1 11870
11905
