Protoss_Gateway 2 9141
Protoss_Assimilator 1 4548
Protoss_Cybernetics_Core 1 5699
Protoss_Dragoon 5 11751
Protoss_Nexus 1 11937
Protoss_Zealot 2 11819
Singularity_Charge 1 9894
Protoss_Robotics_Facility 1 12212
12212
