Protoss_Gateway 2 8107
Protoss_Assimilator 1 4305
Protoss_Cybernetics_Core 1 5794
Protoss_Dragoon 3 9461
Protoss_Zealot 1 7856
Protoss_Citadel_of_Adun 1 8622
Protoss_Templar_Archives 1 10455
Protoss_Dark_Templar 2 11678
Protoss_Nexus 1 13720
13720
