Protoss_Gateway 1 4299
Protoss_Assimilator 1 4653
Protoss_Cybernetics_Core 1 6160
Protoss_Dragoon 4 11508
Protoss_Robotics_Facility 1 8890
Protoss_Observatory 1 9677
Protoss_Observer 2 11692
11692
