Protoss_Gateway 2 10587
Protoss_Assimilator 1 4363
Protoss_Cybernetics_Core 1 6039
Protoss_Robotics_Facility 1 8062
Protoss_Dragoon 4 11410
Protoss_Observatory 1 8782
Protoss_Observer 2 12075
Protoss_Shuttle 1 11232
Singularity_Charge 1 11039
12075
