Protoss_Gateway 2 11531
Protoss_Assimilator 1 4710
Protoss_Cybernetics_Core 1 6081
Protoss_Zealot 1 6068
Protoss_Dragoon 5 11956
Protoss_Robotics_Facility 1 11136
Singularity_Charge 1 10494
Protoss_Observatory 1 11848
11956
