Protoss_Gateway 2 12201
Protoss_Assimilator 1 4218
Protoss_Cybernetics_Core 1 5655
Protoss_Dragoon 2 8071
Protoss_Robotics_Facility 1 8606
Protoss_Zealot 2 10283
Protoss_Shuttle 1 10189
Protoss_Robotics_Support_Bay 1 9655
Protoss_Reaver 1 11747
12201
