Protoss_Gateway 2 6650
Protoss_Assimilator 1 4447
Protoss_Cybernetics_Core 1 5891
Protoss_Dragoon 3 8466
Protoss_Citadel_of_Adun 1 9532
Protoss_Robotics_Facility 1 11012
Protoss_Templar_Archives 1 11041
Protoss_Shuttle 1 12465
Protoss_Dark_Templar 2 12534
12534
