Protoss_Gateway 1 4368
Protoss_Assimilator 1 4688
Protoss_Cybernetics_Core 1 5970
Protoss_Dragoon 5 11960
Protoss_Nexus 1 12505
Singularity_Charge 1 10253
Protoss_Shield_Battery 1 11625
12505
