Protoss_Gateway 2 11578
Protoss_Assimilator 1 4666
Protoss_Zealot 1 5878
Protoss_Cybernetics_Core 1 6475
Protoss_Dragoon 4 11198
Protoss_Robotics_Facility 1 10568
Singularity_Charge 1 10458
Protoss_Shuttle 1 12143
12143
