Protoss_Gateway 2 9936
Protoss_Assimilator 1 4660
Protoss_Cybernetics_Core 1 6052
Protoss_Dragoon 4 11275
Protoss_Citadel_of_Adun 1 9558
Protoss_Templar_Archives 1 11099
Singularity_Charge 1 10187
Protoss_Zealot 1 11263
Protoss_Dark_Templar 2 12549
12549
