Protoss_Gateway 2 11695
Protoss_Assimilator 1 4638
Protoss_Cybernetics_Core 1 5913
Protoss_Dragoon 4 11824
Protoss_Nexus 1 12158
Protoss_Zealot 1 10378
Protoss_Robotics_Facility 1 12900
Singularity_Charge 1 11094
12900
