Protoss_Gateway 2 10382
Protoss_Assimilator 1 4352
Protoss_Cybernetics_Core 1 5809
Protoss_Dragoon 3 9541
Protoss_Citadel_of_Adun 1 9409
Protoss_Templar_Archives 1 10969
Protoss_Zealot 1 10773
Singularity_Charge 1 10172
Protoss_Dark_Templar 2 12271
12271
