Protoss_Gateway 2 12489
Protoss_Assimilator 1 4807
Protoss_Cybernetics_Core 1 6488
Protoss_Dragoon 5 12251
Protoss_Nexus 1 11917
Protoss_Robotics_Facility 1 11575
Singularity_Charge 1 10187
12489
