Protoss_Gateway 2 10499
Protoss_Assimilator 1 4447
Protoss_Zealot 2 6064
Protoss_Cybernetics_Core 1 6004
Protoss_Dragoon 7 12351
Protoss_Citadel_of_Adun 2 10915
Singularity_Charge 1 10143
Protoss_Templar_Archives 1 12424
12424
