Protoss_Gateway 2 10467
Protoss_Assimilator 1 4537
Protoss_Cybernetics_Core 1 6258
Protoss_Dragoon 6 12205
Protoss_Robotics_Facility 1 9153
Protoss_Observatory 1 9887
Protoss_Observer 2 11822
Singularity_Charge 1 11299
12205
