Protoss_Gateway 2 10163
Protoss_Assimilator 1 4728
Protoss_Cybernetics_Core 1 6230
Protoss_Dragoon 5 12131
Protoss_Robotics_Facility 1 9052
Protoss_Observatory 1 10150
Protoss_Observer 1 11271
12131
