Protoss_Gateway 2 10176
Protoss_Assimilator 1 4186
Protoss_Shield_Battery 1 4992
Protoss_Cybernetics_Core 1 5831
Protoss_Dragoon 6 11575
Protoss_Robotics_Facility 1 9652
Singularity_Charge 1 9616
Protoss_Observatory 1 10514
Protoss_Observer 1 11622
11622
