Protoss_Gateway 2 12732
Protoss_Assimilator 2 4868
Protoss_Cybernetics_Core 1 6241
Protoss_Dragoon 3 12139
Protoss_Robotics_Facility 1 8861
Protoss_Shuttle 1 10350
Protoss_Robotics_Support_Bay 1 9972
Protoss_Reaver 1 11908
Protoss_Observatory 1 11940
12732
