Protoss_Gateway 2 9810
Protoss_Assimilator 1 4344
Protoss_Cybernetics_Core 1 5787
Protoss_Dragoon 4 10975
Protoss_Citadel_of_Adun 1 9506
Protoss_Templar_Archives 1 11180
Singularity_Charge 1 9814
Protoss_Zealot 1 10919
Protoss_Dark_Templar 2 12534
12534
