Protoss_Assimilator 1 2988
Protoss_Gateway 2 10670
Protoss_Cybernetics_Core 1 6457
Protoss_Dragoon 4 11897
Protoss_Citadel_of_Adun 1 10040
Protoss_Templar_Archives 1 11538
Singularity_Charge 1 10853
11897
