Protoss_Assimilator 1 3977
Protoss_Gateway 2 10278
Protoss_Cybernetics_Core 1 6762
Protoss_Dragoon 4 11354
Protoss_Robotics_Facility 1 9496
Protoss_Observatory 1 10394
Protoss_Zealot 1 11455
Protoss_Observer 1 11592
Protoss_Citadel_of_Adun 1 12093
12093
