Protoss_Gateway 2 6409
Protoss_Assimilator 1 4412
Protoss_Cybernetics_Core 1 5707
Protoss_Dragoon 6 11092
Protoss_Zealot 1 9601
Protoss_Robotics_Facility 1 11048
Singularity_Charge 1 9587
Protoss_Shuttle 1 12472
12472
