Protoss_Gateway 1 4290
Protoss_Assimilator 1 4542
Protoss_Cybernetics_Core 1 6034
Protoss_Zealot 2 10744
Protoss_Dragoon 4 12358
Protoss_Robotics_Facility 1 8723
Protoss_Shuttle 1 10321
Protoss_Robotics_Support_Bay 1 9901
Protoss_Reaver 1 11879
Protoss_Observatory 1 11564
12358
