Protoss_Nexus 1 6845
Protoss_Gateway 3 10331
Protoss_Assimilator 1 5912
Protoss_Cybernetics_Core 1 7591
Protoss_Zealot 2 11528
Protoss_Dragoon 6 11922
Protoss_Robotics_Facility 1 12158
Singularity_Charge 1 11279
12158
