Protoss_Assimilator 1 3531
Protoss_Gateway 2 8859
Protoss_Cybernetics_Core 1 5923
Protoss_Dragoon 2 12115
Protoss_Citadel_of_Adun 1 7613
Protoss_Robotics_Facility 1 8745
Protoss_Templar_Archives 1 9358
Protoss_Shuttle 1 10293
Protoss_Dark_Templar 3 11752
Protoss_Observatory 1 10876
Protoss_Observer 1 12304
12304
