Protoss_Gateway 2 11093
Protoss_Assimilator 1 4452
Protoss_Cybernetics_Core 1 5604
Protoss_Dragoon 5 11662
Protoss_Robotics_Facility 1 9862
Singularity_Charge 1 9733
Protoss_Shuttle 1 11294
Protoss_Robotics_Support_Bay 1 11233
Protoss_Reaver 1 13010
13010
