Protoss_Gateway 2 9238
Protoss_Assimilator 1 4574
Protoss_Cybernetics_Core 1 6245
Protoss_Dragoon 5 12601
Protoss_Robotics_Facility 1 8665
Protoss_Observatory 1 10248
Protoss_Nexus 1 13373
Protoss_Observer 1 11490
13373
