Protoss_Gateway 2 9677
Protoss_Assimilator 1 4631
Protoss_Cybernetics_Core 1 6151
Protoss_Dragoon 5 12395
Protoss_Robotics_Facility 1 9205
Protoss_Observatory 1 9929
Protoss_Observer 2 11837
12395
