Protoss_Gateway 1 4477
Protoss_Assimilator 1 4783
Protoss_Cybernetics_Core 1 6931
Protoss_Zealot 1 7371
Protoss_Robotics_Facility 1 9224
Protoss_Dragoon 4 11707
Protoss_Shuttle 1 10665
Protoss_Robotics_Support_Bay 1 11087
Protoss_Reaver 1 12944
12944
