Protoss_Gateway 2 9349
Protoss_Assimilator 1 4423
Protoss_Cybernetics_Core 1 5768
Protoss_Dragoon 5 11461
Protoss_Zealot 2 10341
Singularity_Charge 1 9821
Protoss_Nexus 1 14005
14005
