Protoss_Gateway 1 4521
Protoss_Assimilator 1 4703
Protoss_Cybernetics_Core 1 6115
Protoss_Dragoon 4 10735
Protoss_Robotics_Facility 1 10668
Singularity_Charge 1 10326
Protoss_Robotics_Support_Bay 1 11387
Protoss_Shuttle 1 12113
Protoss_Zealot 1 11973
12113
