Protoss_Gateway 1 4536
Protoss_Assimilator 1 4783
Protoss_Cybernetics_Core 1 6056
Protoss_Dragoon 4 11019
Protoss_Citadel_of_Adun 1 9560
Protoss_Templar_Archives 1 11011
Singularity_Charge 1 10289
Protoss_Nexus 1 13742
Protoss_Dark_Templar 1 12307
13742
