Protoss_Gateway 2 10269
Protoss_Assimilator 1 4940
Protoss_Cybernetics_Core 1 6188
Protoss_Dragoon 5 11934
Protoss_Robotics_Facility 1 9161
Protoss_Observatory 1 10453
Protoss_Observer 1 11475
11934
