Protoss_Gateway 2 10265
Protoss_Assimilator 1 4630
Protoss_Cybernetics_Core 1 5983
Protoss_Dragoon 6 12595
Protoss_Robotics_Facility 1 8758
Protoss_Observatory 1 9606
Protoss_Observer 1 10707
Singularity_Charge 1 11336
12595
