Protoss_Gateway 2 8421
Protoss_Assimilator 1 4578
Protoss_Cybernetics_Core 1 5955
Protoss_Dragoon 5 12271
Protoss_Citadel_of_Adun 1 10521
Protoss_Robotics_Facility 1 11670
Singularity_Charge 1 10040
Protoss_Zealot 1 12068
12271
