Protoss_Nexus 1 7016
Protoss_Gateway 2 8481
Protoss_Assimilator 1 6368
Protoss_Cybernetics_Core 1 7916
Protoss_Zealot 2 8559
Protoss_Dragoon 5 12307
Protoss_Forge 1 10432
Protoss_Photon_Cannon 2 11935
12307
