Protoss_Gateway 3 12277
Protoss_Assimilator 1 4545
Protoss_Cybernetics_Core 1 6077
Protoss_Dragoon 7 12475
Protoss_Nexus 1 12125
Singularity_Charge 1 10158
Protoss_Robotics_Facility 1 12297
12475
