Protoss_Gateway 2 10865
Protoss_Assimilator 1 4589
Protoss_Cybernetics_Core 1 5906
Protoss_Dragoon 6 12092
Protoss_Robotics_Facility 1 10198
Singularity_Charge 1 10079
Protoss_Observatory 1 11015
Protoss_Observer 1 12128
12128
