Protoss_Gateway 2 11159
Protoss_Assimilator 1 4722
Protoss_Cybernetics_Core 1 6236
Protoss_Dragoon 4 12168
Protoss_Robotics_Facility 1 10533
Singularity_Charge 1 9967
Protoss_Shuttle 1 11945
Protoss_Robotics_Support_Bay 1 11275
Protoss_Observatory 1 11365
12168
