Protoss_Gateway 3 11194
Protoss_Assimilator 1 4799
Protoss_Cybernetics_Core 1 6528
Protoss_Dragoon 6 12468
Protoss_Robotics_Facility 1 10361
Singularity_Charge 1 10297
Protoss_Observatory 1 11227
Protoss_Observer 1 12288
12468
