Protoss_Gateway 2 10786
Protoss_Assimilator 1 4654
Protoss_Zealot 4 10905
Protoss_Cybernetics_Core 1 7389
Protoss_Dragoon 2 9900
Protoss_Citadel_of_Adun 1 9491
Protoss_Robotics_Facility 1 10805
Protoss_Templar_Archives 1 11118
Protoss_Shuttle 1 12223
Protoss_Dark_Templar 2 12431
12431
