Protoss_Gateway 2 9971
Protoss_Assimilator 1 4593
Protoss_Cybernetics_Core 1 5856
Protoss_Dragoon 5 11180
Singularity_Charge 1 10260
Protoss_Nexus 1 13544
Protoss_Robotics_Facility 1 13018
13544
