Protoss_Nexus 2 14093
Protoss_Gateway 2 7909
Protoss_Assimilator 1 5852
Protoss_Cybernetics_Core 1 7359
Protoss_Zealot 1 7810
Protoss_Dragoon 4 11019
Singularity_Charge 1 11109
14093
