Protoss_Gateway 2 7287
Protoss_Assimilator 1 4776
Protoss_Cybernetics_Core 1 6274
Protoss_Dragoon 5 12519
Protoss_Citadel_of_Adun 1 9492
Protoss_Nexus 1 12403
Protoss_Robotics_Facility 1 11941
12519
