Protoss_Gateway 1 4207
Protoss_Assimilator 1 4504
Protoss_Cybernetics_Core 1 5875
Protoss_Dragoon 5 11251
Protoss_Robotics_Facility 1 8202
Protoss_Shuttle 1 9626
Protoss_Robotics_Support_Bay 1 9282
Protoss_Reaver 1 11729
Protoss_Zealot 1 12112
12112
