Protoss_Gateway 2 9930
Protoss_Assimilator 1 4280
Protoss_Cybernetics_Core 1 5698
Protoss_Dragoon 5 11376
Protoss_Robotics_Facility 1 8451
Protoss_Observatory 1 9385
Protoss_Observer 1 10451
Singularity_Charge 1 10992
Protoss_Shuttle 1 12479
12479
