Protoss_Gateway 2 9746
Protoss_Assimilator 1 4337
Protoss_Cybernetics_Core 1 5803
Protoss_Dragoon 2 9095
Protoss_Citadel_of_Adun 1 8399
Protoss_Templar_Archives 1 10010
Protoss_Dark_Templar 3 12361
Protoss_Nexus 1 13713
Singularity_Charge 1 10860
13713
