Protoss_Gateway 2 9683
Protoss_Assimilator 1 4542
Protoss_Cybernetics_Core 1 5882
Protoss_Dragoon 6 11905
Singularity_Charge 1 9901
Protoss_Nexus 1 13233
Protoss_Robotics_Facility 1 13222
13233
