Protoss_Gateway 2 10120
Protoss_Assimilator 1 4422
Protoss_Cybernetics_Core 1 5777
Protoss_Dragoon 5 12508
Protoss_Robotics_Facility 1 8357
Protoss_Observatory 1 9199
Protoss_Observer 2 11124
Protoss_Nexus 1 12694
12694
