Protoss_Gateway 2 10801
Protoss_Assimilator 1 4517
Protoss_Cybernetics_Core 1 5875
Protoss_Dragoon 7 12284
Protoss_Nexus 1 11386
Singularity_Charge 1 9938
Protoss_Robotics_Facility 1 12260
12284
