Protoss_Gateway 3 12336
Protoss_Assimilator 1 4403
Protoss_Cybernetics_Core 1 5923
Protoss_Zealot 2 11263
Protoss_Dragoon 5 12383
Protoss_Robotics_Facility 1 9395
Protoss_Observatory 1 10149
Protoss_Observer 1 11636
12383
