Protoss_Gateway 2 9930
Protoss_Assimilator 1 4606
Protoss_Cybernetics_Core 1 5838
Protoss_Dragoon 5 12484
Protoss_Nexus 1 12700
Singularity_Charge 1 10067
Protoss_Zealot 1 11326
12700
