Protoss_Gateway 2 9513
Protoss_Assimilator 1 4234
Protoss_Cybernetics_Core 1 5777
Protoss_Dragoon 6 12288
Protoss_Nexus 1 12078
Protoss_Zealot 1 10732
Singularity_Charge 1 9830
Protoss_Robotics_Facility 1 12582
12582
