Protoss_Gateway 2 9583
Protoss_Assimilator 1 4505
Protoss_Cybernetics_Core 1 5739
Protoss_Dragoon 6 12431
Protoss_Nexus 1 12312
Singularity_Charge 1 9847
Protoss_Zealot 1 11288
Protoss_Robotics_Facility 1 12466
12466
