Protoss_Assimilator 1 3326
Protoss_Gateway 3 11421
Protoss_Cybernetics_Core 1 6182
Protoss_Dragoon 3 10231
Protoss_Robotics_Facility 1 8410
Protoss_Observatory 1 9151
Protoss_Citadel_of_Adun 1 9920
Protoss_Observer 1 10340
Protoss_Shuttle 1 11780
Protoss_Zealot 2 12072
Singularity_Charge 1 11082
12072
