Protoss_Gateway 2 11853
Protoss_Assimilator 1 4616
Protoss_Cybernetics_Core 1 5853
Protoss_Dragoon 6 12584
Protoss_Nexus 1 11880
Singularity_Charge 1 9931
Protoss_Robotics_Facility 1 12790
12790
