Protoss_Gateway 2 10338
Protoss_Assimilator 1 4590
Protoss_Cybernetics_Core 1 5967
Protoss_Dragoon 3 9470
Protoss_Citadel_of_Adun 1 9554
Protoss_Robotics_Facility 1 10466
Protoss_Templar_Archives 1 11026
Protoss_Shuttle 1 11862
Protoss_Dark_Templar 2 12241
12241
