Protoss_Assimilator 1 3569
Protoss_Gateway 1 4524
Protoss_Cybernetics_Core 1 5985
Protoss_Dragoon 5 11834
Protoss_Robotics_Facility 1 8624
Protoss_Shuttle 1 10116
Protoss_Robotics_Support_Bay 1 9894
Protoss_Reaver 1 11729
11834
