Protoss_Gateway 3 10258
Protoss_Assimilator 1 4856
Protoss_Zealot 3 11203
Protoss_Cybernetics_Core 1 7280
Protoss_Dragoon 2 10860
Protoss_Citadel_of_Adun 1 9289
Protoss_Templar_Archives 1 11030
Protoss_Dark_Templar 3 12566
12566
