Protoss_Gateway 2 10347
Protoss_Assimilator 1 4375
Protoss_Cybernetics_Core 1 5824
Protoss_Dragoon 6 11662
Protoss_Robotics_Facility 1 9926
Protoss_Observatory 1 10634
Singularity_Charge 1 10128
Protoss_Observer 1 11666
11666
