Protoss_Gateway 2 8041
Protoss_Assimilator 1 4695
Protoss_Cybernetics_Core 1 6036
Protoss_Zealot 1 6551
Protoss_Dragoon 6 11883
Singularity_Charge 1 9740
Protoss_Robotics_Facility 1 11733
11883
