Protoss_Gateway 2 9554
Protoss_Assimilator 1 4572
Protoss_Zealot 1 5256
Protoss_Cybernetics_Core 1 6166
Protoss_Dragoon 7 12271
Singularity_Charge 1 10207
Protoss_Robotics_Facility 1 12389
12389
