Protoss_Gateway 1 4362
Protoss_Assimilator 1 4736
Protoss_Cybernetics_Core 1 6039
Protoss_Dragoon 2 11088
Protoss_Robotics_Facility 1 8988
Protoss_Zealot 2 9608
Protoss_Shuttle 1 10392
Protoss_Robotics_Support_Bay 1 10512
Protoss_Reaver 1 12240
12240
