Protoss_Gateway 2 10081
Protoss_Assimilator 1 4161
Protoss_Cybernetics_Core 1 5655
Protoss_Dragoon 6 11707
Protoss_Robotics_Facility 1 10002
Singularity_Charge 1 9638
Protoss_Observatory 1 10699
Protoss_Observer 1 11980
Protoss_Nexus 1 14026
14026
