Protoss_Gateway 2 9980
Protoss_Assimilator 1 4253
Protoss_Cybernetics_Core 1 5686
Protoss_Dragoon 6 12358
Protoss_Nexus 1 10568
Protoss_Forge 1 9769
Protoss_Photon_Cannon 1 11116
Protoss_Zealot 1 11235
12358
