Protoss_Gateway 2 6476
Protoss_Assimilator 1 4463
Protoss_Cybernetics_Core 1 5730
Protoss_Dragoon 4 10956
Protoss_Citadel_of_Adun 1 9416
Singularity_Charge 1 9391
Protoss_Templar_Archives 1 11023
11023
