Protoss_Gateway 1 4524
Protoss_Assimilator 1 4812
Protoss_Zealot 1 5505
Protoss_Cybernetics_Core 1 6536
Protoss_Dragoon 3 11627
Protoss_Robotics_Facility 1 9614
Protoss_Shuttle 1 11806
Protoss_Robotics_Support_Bay 1 11233
11806
