Protoss_Gateway 2 8142
Protoss_Assimilator 1 4555
Protoss_Zealot 1 5215
Protoss_Cybernetics_Core 1 7079
Protoss_Dragoon 5 11208
Protoss_Nexus 1 13799
Singularity_Charge 1 11153
13799
