Protoss_Gateway 1 4430
Protoss_Assimilator 1 4452
Protoss_Cybernetics_Core 1 5913
Protoss_Dragoon 4 10715
Protoss_Robotics_Facility 1 9783
Protoss_Shuttle 1 11199
Singularity_Charge 1 9777
Protoss_Robotics_Support_Bay 1 10794
Protoss_Zealot 1 11614
Protoss_Reaver 1 12836
12836
