Protoss_Gateway 2 9857
Protoss_Assimilator 1 4549
Protoss_Cybernetics_Core 1 6087
Protoss_Dragoon 2 8641
Protoss_Citadel_of_Adun 1 8007
Protoss_Templar_Archives 1 9547
Protoss_Dark_Templar 4 12164
12164
