Protoss_Gateway 2 6443
Protoss_Assimilator 1 4210
Protoss_Cybernetics_Core 1 5762
Protoss_Dragoon 7 12461
Protoss_Robotics_Facility 1 10819
Singularity_Charge 1 9426
Protoss_Zealot 2 11107
12461
