Protoss_Gateway 2 8256
Protoss_Assimilator 1 4622
Protoss_Cybernetics_Core 1 5954
Protoss_Dragoon 6 11767
Protoss_Citadel_of_Adun 1 10291
Singularity_Charge 1 9976
Protoss_Nexus 1 12991
12991
