Protoss_Gateway 2 9789
Protoss_Assimilator 1 4198
Protoss_Cybernetics_Core 1 5645
Protoss_Dragoon 6 12183
Protoss_Robotics_Facility 1 9139
Protoss_Observatory 1 9947
Singularity_Charge 1 9894
Protoss_Observer 2 12122
12183
