Protoss_Gateway 2 6854
Protoss_Assimilator 1 4150
Protoss_Cybernetics_Core 1 5551
Protoss_Dragoon 8 11199
Singularity_Charge 1 9525
Protoss_Nexus 1 13458
Protoss_Zealot 2 11780
13458
