Protoss_Gateway 2 12168
Protoss_Assimilator 1 4684
Protoss_Cybernetics_Core 1 5941
Protoss_Dragoon 4 12307
Protoss_Robotics_Facility 1 8707
Protoss_Shuttle 1 10116
Protoss_Robotics_Support_Bay 1 9974
Protoss_Reaver 1 11788
12307
