Protoss_Gateway 2 12175
Protoss_Assimilator 1 4515
Protoss_Cybernetics_Core 1 5996
Protoss_Dragoon 5 11641
Protoss_Robotics_Facility 1 10598
Singularity_Charge 1 10158
Protoss_Observatory 1 11363
12175
