Protoss_Gateway 2 10205
Protoss_Assimilator 1 4512
Protoss_Cybernetics_Core 1 5889
Protoss_Dragoon 6 12322
Protoss_Robotics_Facility 1 10273
Singularity_Charge 1 9836
Protoss_Zealot 1 11190
Protoss_Observatory 1 11577
12322
