Protoss_Gateway 2 6912
Protoss_Assimilator 1 4426
Protoss_Cybernetics_Core 1 5935
Protoss_Dragoon 7 12376
Protoss_Robotics_Facility 1 11593
Singularity_Charge 1 10172
Protoss_Nexus 1 13637
13637
