Protoss_Gateway 1 4302
Protoss_Assimilator 1 4556
Protoss_Cybernetics_Core 1 6128
Protoss_Zealot 1 6266
Protoss_Dragoon 4 10851
Protoss_Robotics_Facility 1 11414
Singularity_Charge 1 10545
Protoss_Nexus 1 13793
13793
