Protoss_Gateway 2 11769
Protoss_Assimilator 1 4681
Protoss_Cybernetics_Core 1 5837
Protoss_Dragoon 4 10939
Protoss_Nexus 1 12422
Singularity_Charge 1 9594
Protoss_Robotics_Facility 1 12731
12731
