Protoss_Gateway 2 6781
Protoss_Assimilator 1 4313
Protoss_Cybernetics_Core 1 5870
Protoss_Dragoon 5 10696
Protoss_Citadel_of_Adun 1 10220
Singularity_Charge 1 9967
Protoss_Templar_Archives 1 12110
Protoss_Robotics_Facility 1 12856
12856
