Protoss_Gateway 1 4170
Protoss_Assimilator 1 4243
Protoss_Cybernetics_Core 1 5866
Protoss_Dragoon 3 9587
Protoss_Stargate 1 9065
Protoss_Scout 2 12938
Protoss_Nexus 1 13600
13600
