Protoss_Gateway 2 8418
Protoss_Assimilator 1 4303
Protoss_Cybernetics_Core 1 5929
Protoss_Dragoon 8 12311
Protoss_Robotics_Facility 1 11149
Singularity_Charge 1 10257
Protoss_Observatory 1 11963
12311
