Protoss_Gateway 2 10428
Protoss_Assimilator 1 4495
Protoss_Cybernetics_Core 1 6023
Protoss_Dragoon 6 11995
Protoss_Robotics_Facility 1 10292
Singularity_Charge 1 9704
Protoss_Observatory 1 10989
Protoss_Observer 1 12178
12178
