Protoss_Gateway 2 10215
Protoss_Assimilator 1 4390
Protoss_Cybernetics_Core 1 5702
Protoss_Dragoon 6 11597
Protoss_Robotics_Facility 1 10230
Singularity_Charge 1 9689
Protoss_Observatory 1 11053
Protoss_Observer 1 12198
12198
