Protoss_Assimilator 2 5184
Protoss_Gateway 2 9548
Protoss_Cybernetics_Core 1 6599
Protoss_Dragoon 6 11856
Protoss_Shield_Battery 2 11094
Protoss_Citadel_of_Adun 1 11180
Singularity_Charge 1 10545
Protoss_Templar_Archives 1 12795
12795
