Protoss_Gateway 1 4218
Protoss_Assimilator 1 4937
Protoss_Zealot 2 10632
Protoss_Cybernetics_Core 1 6675
Protoss_Robotics_Facility 1 8606
Protoss_Dragoon 3 12326
Protoss_Shuttle 1 10044
Protoss_Robotics_Support_Bay 1 10146
Protoss_Reaver 1 11907
Protoss_Observatory 1 11499
12326
