Protoss_Gateway 1 4325
Protoss_Assimilator 1 4552
Protoss_Cybernetics_Core 1 5963
Protoss_Dragoon 4 11530
Protoss_Zealot 1 9310
Protoss_Robotics_Facility 1 10485
Singularity_Charge 1 10040
Protoss_Shuttle 1 11923
Protoss_Robotics_Support_Bay 1 11529
11923
