Protoss_Gateway 1 4382
Protoss_Assimilator 1 4507
Protoss_Cybernetics_Core 1 6058
Protoss_Dragoon 3 10342
Protoss_Robotics_Facility 1 10064
Protoss_Forge 1 10126
Protoss_Shuttle 1 11550
Protoss_Photon_Cannon 1 11410
Protoss_Robotics_Support_Bay 1 11316
11550
