Protoss_Gateway 2 8417
Protoss_Assimilator 1 4388
Protoss_Cybernetics_Core 1 5831
Protoss_Dragoon 5 11385
Protoss_Robotics_Facility 1 11543
Protoss_Zealot 2 11066
Singularity_Charge 1 9997
Protoss_Nexus 1 14254
14254
