Protoss_Gateway 2 8253
Protoss_Assimilator 1 4293
Protoss_Cybernetics_Core 1 5815
Protoss_Dragoon 5 11092
Protoss_Citadel_of_Adun 1 10726
Protoss_Zealot 1 10583
Singularity_Charge 1 9865
Protoss_Robotics_Facility 1 12556
Protoss_Templar_Archives 1 12233
12556
