Protoss_Gateway 2 10637
Protoss_Assimilator 1 4600
Protoss_Cybernetics_Core 1 6036
Protoss_Dragoon 5 11897
Protoss_Robotics_Facility 1 8700
Protoss_Observatory 1 9667
Protoss_Observer 2 12112
12112
