Protoss_Gateway 2 8348
Protoss_Assimilator 1 4493
Protoss_Cybernetics_Core 1 5841
Protoss_Dragoon 5 11356
Protoss_Robotics_Facility 1 11457
Protoss_Zealot 3 12217
Singularity_Charge 1 10099
12217
