Protoss_Nexus 1 7508
Protoss_Gateway 3 12446
Protoss_Assimilator 2 12333
Protoss_Zealot 2 8647
Protoss_Cybernetics_Core 1 8436
Protoss_Dragoon 4 12563
Protoss_Citadel_of_Adun 1 11729
12563
