Protoss_Gateway 2 10572
Protoss_Assimilator 1 4690
Protoss_Cybernetics_Core 1 6182
Protoss_Dragoon 6 12303
Protoss_Robotics_Facility 1 10299
Protoss_Observatory 1 11035
Singularity_Charge 1 10326
Protoss_Observer 1 12134
12303
