Protoss_Gateway 1 4209
Protoss_Assimilator 1 4534
Protoss_Cybernetics_Core 1 5875
Protoss_Dragoon 6 12601
Protoss_Robotics_Facility 1 10368
Singularity_Charge 1 9989
Protoss_Observatory 1 11134
Protoss_Nexus 1 13560
13560
