Protoss_Gateway 1 4294
Protoss_Assimilator 1 4583
Protoss_Cybernetics_Core 1 5926
Protoss_Dragoon 2 9014
Protoss_Robotics_Facility 1 8681
Protoss_Shuttle 1 10109
Protoss_Observatory 1 9595
Protoss_Robotics_Support_Bay 1 9696
Protoss_Observer 1 10985
Protoss_Reaver 1 12717
12717
