Protoss_Gateway 1 4395
Protoss_Assimilator 1 4673
Protoss_Cybernetics_Core 1 6160
Protoss_Dragoon 5 12256
Protoss_Robotics_Facility 1 10740
Singularity_Charge 1 10480
Protoss_Observatory 1 11602
12256
