Protoss_Gateway 2 11699
Protoss_Assimilator 1 4798
Protoss_Zealot 2 7290
Protoss_Cybernetics_Core 1 7104
Protoss_Dragoon 4 12095
Protoss_Robotics_Facility 1 10024
Protoss_Observatory 1 10794
Protoss_Observer 1 12061
12095
