Protoss_Gateway 2 10717
Protoss_Assimilator 1 4545
Protoss_Cybernetics_Core 1 6106
Protoss_Dragoon 6 12297
Protoss_Robotics_Facility 1 10410
Singularity_Charge 1 9771
Protoss_Observatory 1 11409
12297
