Protoss_Gateway 2 6795
Protoss_Assimilator 1 4164
Protoss_Cybernetics_Core 1 5575
Protoss_Dragoon 8 12546
Protoss_Nexus 1 12290
Singularity_Charge 1 9452
Protoss_Robotics_Facility 1 12995
12995
