Protoss_Gateway 2 9595
Protoss_Assimilator 1 4473
Protoss_Cybernetics_Core 1 5696
Protoss_Dragoon 6 12209
Protoss_Robotics_Facility 1 8448
Protoss_Observatory 1 9209
Protoss_Observer 1 10533
Protoss_Nexus 1 14241
14241
