Protoss_Gateway 2 9504
Protoss_Assimilator 1 4688
Protoss_Cybernetics_Core 1 6358
Protoss_Dragoon 7 12453
Protoss_Robotics_Facility 1 10797
Singularity_Charge 1 10245
Protoss_Observatory 1 11791
12453
