Protoss_Gateway 2 6447
Protoss_Assimilator 1 4265
Protoss_Cybernetics_Core 1 5607
Protoss_Dragoon 5 10236
Protoss_Citadel_of_Adun 1 9968
Singularity_Charge 1 9780
Protoss_Templar_Archives 1 11475
Protoss_Zealot 2 11607
11607
