Protoss_Gateway 2 12043
Protoss_Assimilator 1 4439
Protoss_Cybernetics_Core 1 6664
Protoss_Zealot 2 9405
Protoss_Robotics_Facility 1 8729
Protoss_Dragoon 3 12478
Protoss_Robotics_Support_Bay 1 9521
Protoss_Shuttle 1 10416
Protoss_Reaver 1 11974
12478
