Protoss_Gateway 3 11395
Protoss_Assimilator 1 4147
Protoss_Cybernetics_Core 1 5832
Protoss_Dragoon 6 12351
Protoss_Nexus 1 11692
Singularity_Charge 1 9872
Protoss_Robotics_Facility 1 12891
12891
