Protoss_Gateway 2 6608
Protoss_Assimilator 1 4529
Protoss_Cybernetics_Core 1 5799
Protoss_Dragoon 7 12439
Protoss_Nexus 1 12221
Singularity_Charge 1 9850
Protoss_Robotics_Facility 1 12480
12480
