Protoss_Nexus 1 6505
Protoss_Gateway 2 11417
Protoss_Assimilator 2 8969
Protoss_Cybernetics_Core 1 7422
Protoss_Zealot 1 7381
Protoss_Citadel_of_Adun 1 8923
Protoss_Dragoon 3 11589
Protoss_Robotics_Facility 1 10276
Protoss_Shuttle 1 11870
Protoss_Robotics_Support_Bay 1 11726
11870
