Protoss_Gateway 2 10518
Protoss_Assimilator 1 4296
Protoss_Cybernetics_Core 1 5729
Protoss_Dragoon 6 11971
Protoss_Robotics_Facility 1 9622
Protoss_Observatory 1 10435
Singularity_Charge 1 9748
Protoss_Observer 1 11512
11971
