Protoss_Gateway 1 4416
Protoss_Assimilator 1 4676
Protoss_Cybernetics_Core 1 6087
Protoss_Dragoon 5 11905
Protoss_Robotics_Facility 1 10533
Protoss_Nexus 1 13666
Singularity_Charge 1 11043
Protoss_Observatory 1 11791
13666
