Protoss_Gateway 3 11707
Protoss_Assimilator 1 4578
Protoss_Zealot 2 6836
Protoss_Cybernetics_Core 1 7173
Protoss_Dragoon 4 11754
Protoss_Nexus 1 11817
Singularity_Charge 1 10919
Protoss_Robotics_Facility 1 13126
13126
