Protoss_Gateway 2 6418
Protoss_Assimilator 1 4289
Protoss_Cybernetics_Core 1 5729
Protoss_Dragoon 6 11034
Protoss_Robotics_Facility 1 10674
Singularity_Charge 1 9762
Protoss_Shuttle 1 12106
Protoss_Robotics_Support_Bay 1 11868
12106
