Protoss_Assimilator 2 10594
Protoss_Gateway 1 4641
Protoss_Zealot 6 11180
Protoss_Nexus 1 11604
Protoss_Forge 1 10488
Protoss_Photon_Cannon 1 11738
Protoss_Cybernetics_Core 1 12497
12497
