Protoss_Gateway 1 4309
Protoss_Assimilator 1 4659
Protoss_Cybernetics_Core 1 6204
Protoss_Robotics_Facility 1 8442
Protoss_Dragoon 1 8122
Protoss_Zealot 2 10041
Protoss_Shuttle 1 10189
Protoss_Robotics_Support_Bay 1 9683
Protoss_Reaver 1 12066
12066
