Protoss_Gateway 2 9125
Protoss_Assimilator 1 4439
Protoss_Cybernetics_Core 1 5794
Protoss_Dragoon 8 12554
Protoss_Robotics_Facility 1 10601
Singularity_Charge 1 9762
Protoss_Observatory 1 11924
12554
