Protoss_Gateway 2 10327
Protoss_Assimilator 1 4461
Protoss_Cybernetics_Core 1 5917
Protoss_Dragoon 6 12162
Protoss_Robotics_Facility 1 9840
Protoss_Observatory 1 10598
Singularity_Charge 1 9956
Protoss_Observer 1 11879
12162
