Protoss_Gateway 2 10469
Protoss_Assimilator 1 4425
Protoss_Cybernetics_Core 1 5853
Protoss_Dragoon 6 11805
Protoss_Robotics_Facility 1 9834
Protoss_Observatory 1 10531
Singularity_Charge 1 9960
Protoss_Observer 1 11556
11805
