Protoss_Gateway 2 9447
Protoss_Assimilator 1 4191
Protoss_Cybernetics_Core 1 5648
Protoss_Dragoon 3 9731
Protoss_Nexus 1 11203
Protoss_Robotics_Facility 1 11277
Singularity_Charge 1 9514
Protoss_Observatory 1 11979
11979
