Protoss_Nexus 1 6868
Protoss_Gateway 2 8881
Protoss_Assimilator 1 5954
Protoss_Cybernetics_Core 1 7618
Protoss_Zealot 1 7954
Protoss_Dragoon 5 11562
Protoss_Robotics_Facility 1 12548
12548
