Protoss_Gateway 2 12482
Protoss_Assimilator 1 4542
Protoss_Cybernetics_Core 1 5730
Protoss_Zealot 1 5516
Protoss_Dragoon 5 11814
Singularity_Charge 1 10128
Protoss_Nexus 1 13366
13366
