Protoss_Gateway 2 7022
Protoss_Assimilator 1 4439
Protoss_Cybernetics_Core 1 5799
Protoss_Dragoon 4 12136
Protoss_Zealot 2 8057
Protoss_Nexus 1 12535
Singularity_Charge 1 10166
12535
