Protoss_Gateway 2 10062
Protoss_Assimilator 1 4227
Protoss_Cybernetics_Core 1 5816
Protoss_Dragoon 6 11615
Protoss_Robotics_Facility 1 9695
Singularity_Charge 1 9828
Protoss_Observatory 1 10586
Protoss_Observer 1 11614
Protoss_Nexus 1 14232
14232
