Protoss_Nexus 1 6857
Protoss_Gateway 4 12460
Protoss_Assimilator 1 5868
Protoss_Cybernetics_Core 1 7638
Protoss_Dragoon 5 12571
Protoss_Zealot 1 9795
Protoss_Robotics_Facility 1 12423
12571
