Protoss_Gateway 2 7032
Protoss_Assimilator 1 4581
Protoss_Cybernetics_Core 1 5837
Protoss_Dragoon 5 10697
Protoss_Zealot 2 9471
Singularity_Charge 1 10092
Protoss_Nexus 1 13723
13723
