Protoss_Gateway 2 8172
Protoss_Assimilator 1 3939
Protoss_Cybernetics_Core 1 5794
Protoss_Dragoon 6 11985
Protoss_Citadel_of_Adun 1 9535
Protoss_Stargate 1 10818
Singularity_Charge 1 9682
Protoss_Templar_Archives 1 11229
Protoss_Nexus 1 13083
13083
