Protoss_Gateway 3 12504
Protoss_Assimilator 1 4564
Protoss_Cybernetics_Core 1 6007
Protoss_Dragoon 5 11729
Protoss_Nexus 1 12077
Protoss_Robotics_Facility 1 11905
Singularity_Charge 1 10004
12504
