Protoss_Gateway 2 6816
Protoss_Assimilator 1 4193
Protoss_Cybernetics_Core 1 5799
Protoss_Dragoon 7 12036
Protoss_Nexus 1 11657
Singularity_Charge 1 10019
Protoss_Robotics_Facility 1 12007
12036
