Protoss_Gateway 2 12374
Protoss_Assimilator 1 4381
Protoss_Cybernetics_Core 1 5755
Protoss_Dragoon 5 11874
Protoss_Robotics_Facility 1 9866
Protoss_Nexus 1 12172
Singularity_Charge 1 9604
Protoss_Observatory 1 10866
Protoss_Observer 1 11932
12374
