Protoss_Gateway 2 8875
Protoss_Assimilator 1 4704
Protoss_Cybernetics_Core 1 5996
Protoss_Zealot 1 5973
Protoss_Dragoon 5 11420
Singularity_Charge 1 10245
Protoss_Nexus 1 13427
13427
