Protoss_Assimilator 1 3620
Protoss_Gateway 1 4770
Protoss_Cybernetics_Core 1 6248
Protoss_Robotics_Facility 1 8180
Protoss_Dragoon 4 11526
Protoss_Shuttle 1 9823
Protoss_Observatory 1 9219
Protoss_Observer 2 11547
11547
