Protoss_Gateway 2 11510
Protoss_Assimilator 1 4594
Protoss_Cybernetics_Core 1 5993
Protoss_Dragoon 4 10769
Protoss_Nexus 1 11715
Singularity_Charge 1 10019
Protoss_Robotics_Facility 1 12581
12581
