Protoss_Gateway 3 11688
Protoss_Assimilator 1 4564
Protoss_Cybernetics_Core 1 5857
Protoss_Dragoon 4 11662
Protoss_Nexus 1 11496
Protoss_Zealot 1 10826
Singularity_Charge 1 9967
11688
