Protoss_Gateway 2 8734
Protoss_Assimilator 1 4373
Protoss_Cybernetics_Core 1 5566
Protoss_Dragoon 6 11337
Protoss_Robotics_Facility 1 8716
Protoss_Observatory 1 9996
Protoss_Observer 1 11265
Singularity_Charge 1 11068
11337
