Protoss_Gateway 2 6962
Protoss_Assimilator 2 11856
Protoss_Cybernetics_Core 1 5644
Protoss_Dragoon 5 10419
Protoss_Nexus 1 11670
Protoss_Robotics_Facility 1 11847
Singularity_Charge 1 10070
Protoss_Citadel_of_Adun 1 11933
11933
