Protoss_Gateway 2 6980
Protoss_Assimilator 1 4444
Protoss_Cybernetics_Core 1 6160
Protoss_Dragoon 5 10020
Singularity_Charge 1 9839
Protoss_Robotics_Facility 1 12109
Protoss_Zealot 2 11505
12109
