Protoss_Gateway 2 6359
Protoss_Assimilator 1 4204
Protoss_Cybernetics_Core 1 5601
Protoss_Dragoon 5 9411
Singularity_Charge 1 9262
Protoss_Nexus 1 13000
Protoss_Citadel_of_Adun 1 12023
13000
