Protoss_Gateway 1 4109
Protoss_Assimilator 1 4401
Protoss_Cybernetics_Core 1 5749
Protoss_Dragoon 3 9944
Protoss_Robotics_Facility 1 10024
Protoss_Zealot 1 10805
Singularity_Charge 1 9932
Protoss_Shuttle 1 11721
Protoss_Robotics_Support_Bay 1 11069
11721
