Protoss_Gateway 3 10675
Protoss_Assimilator 1 4294
Protoss_Cybernetics_Core 1 5635
Protoss_Dragoon 5 11788
Protoss_Nexus 1 11671
Singularity_Charge 1 9375
Protoss_Robotics_Facility 1 13229
13229
