Protoss_Gateway 2 10609
Protoss_Assimilator 1 4463
Protoss_Cybernetics_Core 1 5923
Protoss_Zealot 2 11566
Protoss_Dragoon 4 11767
Protoss_Robotics_Facility 1 10726
Singularity_Charge 1 10169
Protoss_Observatory 1 11474
Protoss_Shuttle 1 12491
12491
