Protoss_Gateway 2 10515
Protoss_Assimilator 1 4369
Protoss_Cybernetics_Core 1 5769
Protoss_Zealot 3 11484
Protoss_Dragoon 3 10269
Protoss_Citadel_of_Adun 2 9810
Protoss_Templar_Archives 1 11306
Singularity_Charge 1 10406
11484
