Protoss_Gateway 2 12751
Protoss_Assimilator 1 4681
Protoss_Cybernetics_Core 1 6336
Protoss_Dragoon 5 12405
Protoss_Robotics_Facility 1 10135
Protoss_Shuttle 1 11623
Protoss_Observatory 1 11072
12751
