Protoss_Gateway 2 6942
Protoss_Assimilator 1 4293
Protoss_Cybernetics_Core 1 5695
Protoss_Dragoon 6 10753
Protoss_Zealot 3 11614
Singularity_Charge 1 9521
Protoss_Nexus 1 12971
12971
