Protoss_Gateway 1 4190
Protoss_Assimilator 1 4526
Protoss_Cybernetics_Core 1 5914
Protoss_Zealot 2 11844
Protoss_Dragoon 3 9748
Protoss_Robotics_Facility 1 8682
Protoss_Observatory 1 9437
Protoss_Shuttle 1 10594
Protoss_Robotics_Support_Bay 1 10740
Protoss_Observer 1 11437
11844
