Protoss_Gateway 2 6569
Protoss_Assimilator 1 4515
Protoss_Cybernetics_Core 1 5765
Protoss_Dragoon 6 10588
Protoss_Robotics_Facility 1 10465
Singularity_Charge 1 9733
Protoss_Zealot 2 11484
Protoss_Shuttle 1 12048
12048
