Protoss_Gateway 2 8123
Protoss_Assimilator 1 4675
Protoss_Zealot 1 5417
Protoss_Cybernetics_Core 1 6892
Protoss_Dragoon 6 12227
Protoss_Nexus 1 13493
Singularity_Charge 1 10816
13493
