Protoss_Nexus 1 6805
Protoss_Gateway 3 10703
Protoss_Assimilator 1 5815
Protoss_Cybernetics_Core 1 7455
Protoss_Dragoon 5 11949
Protoss_Robotics_Facility 1 12046
Protoss_Zealot 2 11439
Singularity_Charge 1 11131
12046
