Protoss_Gateway 2 10315
Protoss_Assimilator 1 4199
Protoss_Cybernetics_Core 1 5633
Protoss_Dragoon 4 10844
Protoss_Citadel_of_Adun 1 9065
Protoss_Templar_Archives 1 10529
Singularity_Charge 1 9821
Protoss_Dark_Templar 2 11944
11944
