Protoss_Assimilator 1 3488
Protoss_Gateway 2 10769
Protoss_Cybernetics_Core 1 5979
Protoss_Dragoon 2 9241
Protoss_Robotics_Facility 1 8839
Protoss_Citadel_of_Adun 1 9007
Protoss_Templar_Archives 1 10700
Protoss_Observatory 1 10456
Protoss_Zealot 1 10736
Protoss_Observer 1 11483
Protoss_Dark_Templar 1 12073
Protoss_Shuttle 1 12841
12841
