Protoss_Gateway 2 11045
Protoss_Assimilator 1 4164
Protoss_Cybernetics_Core 1 5657
Protoss_Dragoon 5 11814
Protoss_Robotics_Facility 1 9955
Singularity_Charge 1 9391
Protoss_Observatory 1 10768
11814
