Protoss_Gateway 2 6358
Protoss_Assimilator 1 4511
Protoss_Cybernetics_Core 1 5729
Protoss_Dragoon 6 9951
Protoss_Nexus 1 12962
Singularity_Charge 1 10480
Protoss_Robotics_Facility 1 12970
12970
