Protoss_Gateway 2 8187
Protoss_Assimilator 1 4211
Protoss_Cybernetics_Core 1 5796
Protoss_Dragoon 6 11106
Protoss_Robotics_Facility 1 10652
Singularity_Charge 1 9481
Protoss_Shuttle 1 12403
Protoss_Robotics_Support_Bay 1 11723
Protoss_Zealot 2 12318
12403
