Protoss_Gateway 2 10272
Protoss_Assimilator 1 4195
Protoss_Cybernetics_Core 1 5750
Protoss_Dragoon 6 11671
Protoss_Robotics_Facility 1 10006
Singularity_Charge 1 9774
Protoss_Observatory 1 10699
Protoss_Observer 1 11724
11724
