Protoss_Gateway 2 7858
Protoss_Assimilator 1 4826
Protoss_Zealot 2 6836
Protoss_Cybernetics_Core 1 6870
Protoss_Dragoon 7 12461
Singularity_Charge 1 10640
Protoss_Nexus 1 13686
13686
