Protoss_Gateway 2 9623
Protoss_Nexus 1 7954
Protoss_Assimilator 1 6260
Protoss_Cybernetics_Core 1 7976
Protoss_Zealot 3 12277
Protoss_Dragoon 5 12320
Protoss_Shield_Battery 1 10011
12320
