Protoss_Gateway 2 10761
Protoss_Assimilator 1 4435
Protoss_Cybernetics_Core 1 6017
Protoss_Dragoon 5 11618
Protoss_Robotics_Facility 1 10324
Singularity_Charge 1 9877
Protoss_Observatory 1 11043
Protoss_Nexus 1 13783
Protoss_Observer 1 12201
13783
