Protoss_Gateway 3 12691
Protoss_Assimilator 1 4428
Protoss_Cybernetics_Core 1 5750
Protoss_Dragoon 7 12516
Protoss_Nexus 1 12221
Singularity_Charge 1 9850
Protoss_Robotics_Facility 1 12371
12691
