Protoss_Gateway 2 10259
Protoss_Assimilator 1 4220
Protoss_Cybernetics_Core 1 5660
Protoss_Dragoon 6 11761
Protoss_Robotics_Facility 1 9739
Protoss_Observatory 1 10471
Singularity_Charge 1 10011
Protoss_Observer 1 11487
11761
