Protoss_Gateway 2 8010
Protoss_Assimilator 1 4212
Protoss_Cybernetics_Core 1 5797
Protoss_Zealot 1 5497
Protoss_Dragoon 6 10968
Protoss_Robotics_Facility 1 10829
Singularity_Charge 1 9572
Protoss_Observatory 1 11562
Protoss_Nexus 1 13837
13837
