Protoss_Nexus 1 6791
Protoss_Gateway 3 10518
Protoss_Assimilator 1 5985
Protoss_Cybernetics_Core 1 7580
Protoss_Zealot 2 11887
Protoss_Dragoon 6 12047
Protoss_Robotics_Facility 1 12393
Singularity_Charge 1 11343
12393
