Protoss_Gateway 2 6273
Protoss_Assimilator 1 4234
Protoss_Cybernetics_Core 1 5628
Protoss_Dragoon 5 9996
Protoss_Citadel_of_Adun 1 9611
Protoss_Zealot 1 9465
Singularity_Charge 1 9370
Protoss_Templar_Archives 1 11093
Protoss_Dark_Templar 2 12511
12511
