Protoss_Gateway 2 8083
Protoss_Assimilator 1 4234
Protoss_Cybernetics_Core 1 5692
Protoss_Zealot 1 5512
Protoss_Dragoon 4 9453
Singularity_Charge 1 9704
Protoss_Nexus 1 12593
Protoss_Robotics_Facility 1 12285
12593
