Protoss_Nexus 1 7083
Protoss_Gateway 3 10946
Protoss_Assimilator 1 6179
Protoss_Cybernetics_Core 1 7843
Protoss_Zealot 3 12235
Protoss_Dragoon 5 12099
Protoss_Robotics_Facility 1 10726
Protoss_Shield_Battery 1 11379
12235
