Protoss_Gateway 2 9312
Protoss_Assimilator 1 4706
Protoss_Cybernetics_Core 1 6179
Protoss_Dragoon 5 12352
Protoss_Robotics_Facility 1 9288
Protoss_Observatory 1 10059
Protoss_Observer 2 12301
12352
