Protoss_Gateway 2 11124
Protoss_Assimilator 1 4454
Protoss_Cybernetics_Core 1 6018
Protoss_Zealot 1 5871
Protoss_Dragoon 5 12500
Protoss_Robotics_Facility 1 10707
Singularity_Charge 1 10538
Protoss_Shield_Battery 1 11592
12500
