Protoss_Gateway 1 4149
Protoss_Assimilator 1 4372
Protoss_Cybernetics_Core 1 5759
Protoss_Zealot 2 6724
Protoss_Dragoon 4 11489
Protoss_Nexus 1 12227
Protoss_Robotics_Facility 1 11785
Singularity_Charge 1 10079
12227
