Protoss_Gateway 3 11374
Protoss_Assimilator 1 4514
Protoss_Cybernetics_Core 1 5926
Protoss_Dragoon 5 11729
Protoss_Nexus 1 11989
Singularity_Charge 1 10033
Protoss_Robotics_Facility 1 12987
12987
