Protoss_Gateway 2 6538
Protoss_Assimilator 1 4242
Protoss_Cybernetics_Core 1 5802
Protoss_Dragoon 6 12249
Protoss_Nexus 1 11971
Singularity_Charge 1 9740
Protoss_Robotics_Facility 1 12241
12249
