Protoss_Gateway 1 4188
Protoss_Assimilator 1 4485
Protoss_Cybernetics_Core 1 5705
Protoss_Dragoon 5 12118
Protoss_Nexus 1 11121
Protoss_Robotics_Facility 1 11202
Singularity_Charge 1 9865
12118
