Protoss_Gateway 2 10814
Protoss_Assimilator 1 4527
Protoss_Cybernetics_Core 1 6009
Protoss_Dragoon 6 12431
Protoss_Nexus 1 11774
Singularity_Charge 1 9814
Protoss_Robotics_Facility 1 12314
12431
