Protoss_Gateway 2 10097
Protoss_Assimilator 1 4461
Protoss_Cybernetics_Core 1 5947
Protoss_Dragoon 4 10776
Protoss_Robotics_Facility 1 11114
Singularity_Charge 1 9967
Protoss_Nexus 2 14223
14223
