Protoss_Gateway 2 6465
Protoss_Assimilator 1 4176
Protoss_Cybernetics_Core 1 5568
Protoss_Dragoon 5 10737
Protoss_Zealot 2 10518
Protoss_Citadel_of_Adun 1 9857
Singularity_Charge 1 9408
Protoss_Templar_Archives 1 11326
11326
