Protoss_Gateway 2 10170
Protoss_Assimilator 1 4375
Protoss_Cybernetics_Core 1 5765
Protoss_Dragoon 6 11744
Protoss_Robotics_Facility 1 10178
Singularity_Charge 1 9770
Protoss_Observatory 1 10984
Protoss_Observer 1 12010
12010
