Protoss_Gateway 2 11443
Protoss_Assimilator 1 4278
Protoss_Cybernetics_Core 1 5996
Protoss_Dragoon 3 9988
Protoss_Robotics_Facility 1 8880
Protoss_Citadel_of_Adun 1 10154
Protoss_Templar_Archives 1 11663
11663
