Protoss_Gateway 3 11964
Protoss_Assimilator 1 4527
Protoss_Zealot 3 12222
Protoss_Cybernetics_Core 1 7250
Protoss_Dragoon 6 12410
Protoss_Robotics_Facility 1 11005
Singularity_Charge 1 10926
Protoss_Observatory 1 11729
12410
