Protoss_Gateway 2 6475
Protoss_Assimilator 1 4337
Protoss_Cybernetics_Core 1 5734
Protoss_Dragoon 8 12600
Singularity_Charge 1 9521
Protoss_Robotics_Facility 1 12516
Protoss_Nexus 1 13888
13888
