Protoss_Gateway 2 8004
Protoss_Assimilator 1 4268
Protoss_Cybernetics_Core 1 5693
Protoss_Dragoon 6 12095
Protoss_Nexus 1 12235
Singularity_Charge 1 9923
Protoss_Robotics_Facility 1 12614
12614
