Protoss_Gateway 1 4327
Protoss_Assimilator 1 4744
Protoss_Cybernetics_Core 1 6247
Protoss_Zealot 1 7091
Protoss_Dragoon 5 12309
Protoss_Robotics_Facility 1 10748
Singularity_Charge 1 10222
Protoss_Nexus 1 13102
Protoss_Observatory 1 11571
13102
