Protoss_Gateway 2 10511
Protoss_Zealot 2 7346
Protoss_Nexus 2 14036
Protoss_Assimilator 1 7586
Protoss_Forge 1 8291
Protoss_Cybernetics_Core 1 9743
Protoss_Photon_Cannon 1 10008
Protoss_Dragoon 2 11714
Protoss_Citadel_of_Adun 1 11502
14036
