Protoss_Assimilator 1 3652
Protoss_Gateway 2 9712
Protoss_Cybernetics_Core 1 6270
Protoss_Dragoon 7 12461
Protoss_Robotics_Facility 1 8489
Protoss_Observatory 1 9664
Protoss_Observer 2 11573
Singularity_Charge 1 10780
12461
