Protoss_Gateway 1 4344
Protoss_Assimilator 1 4337
Protoss_Cybernetics_Core 1 5793
Protoss_Dragoon 3 11922
Protoss_Robotics_Facility 1 8552
Protoss_Zealot 3 10548
Protoss_Shuttle 1 9953
Protoss_Robotics_Support_Bay 1 9568
Protoss_Reaver 1 11587
11922
