Protoss_Gateway 3 12124
Protoss_Assimilator 1 4469
Protoss_Cybernetics_Core 1 6233
Protoss_Dragoon 5 12468
Protoss_Nexus 1 11899
Protoss_Robotics_Facility 1 11287
Singularity_Charge 1 10040
12468
