Protoss_Gateway 2 9892
Protoss_Assimilator 1 4234
Protoss_Cybernetics_Core 1 6080
Protoss_Dragoon 6 11709
Protoss_Robotics_Facility 1 9739
Protoss_Observatory 1 10485
Singularity_Charge 1 9903
Protoss_Observer 1 11531
11709
