Protoss_Gateway 2 9579
Protoss_Assimilator 1 4688
Protoss_Cybernetics_Core 1 5986
Protoss_Dragoon 7 12146
Protoss_Robotics_Facility 1 9000
Protoss_Observatory 1 9704
Protoss_Observer 2 11685
12146
