Protoss_Gateway 3 6570
Protoss_Assimilator 1 4461
Protoss_Cybernetics_Core 1 5802
Protoss_Dragoon 5 11451
Protoss_Nexus 1 11759
Singularity_Charge 1 9477
Protoss_Robotics_Facility 1 12914
Protoss_Zealot 1 12229
12914
