Protoss_Gateway 2 9753
Protoss_Assimilator 1 4615
Protoss_Cybernetics_Core 1 6110
Protoss_Dragoon 2 8586
Protoss_Robotics_Facility 1 9014
Protoss_Observatory 1 9931
Protoss_Observer 2 11925
Protoss_Nexus 1 13303
13303
