Protoss_Gateway 1 3596
Protoss_Zealot 6 9092
Protoss_Assimilator 1 6541
Protoss_Cybernetics_Core 1 8655
Protoss_Citadel_of_Adun 1 10362
Protoss_Dragoon 3 12285
Protoss_Templar_Archives 1 12053
12285
