Protoss_Gateway 2 10580
Protoss_Assimilator 1 4448
Protoss_Cybernetics_Core 1 5853
Protoss_Dragoon 3 9511
Protoss_Robotics_Facility 1 9982
Singularity_Charge 1 9973
Protoss_Nexus 1 12987
Protoss_Observatory 1 10857
Protoss_Shuttle 1 12541
12987
