Protoss_Gateway 2 9819
Protoss_Assimilator 1 4539
Protoss_Cybernetics_Core 1 5825
Protoss_Dragoon 2 8144
Protoss_Citadel_of_Adun 1 7770
Protoss_Templar_Archives 1 9248
Protoss_Dark_Templar 3 12156
Protoss_Zealot 1 11332
12156
