Protoss_Gateway 1 4130
Protoss_Assimilator 1 4352
Protoss_Cybernetics_Core 1 5606
Protoss_Dragoon 4 10427
Protoss_Robotics_Facility 1 9721
Protoss_Shuttle 1 11235
Singularity_Charge 1 9888
Protoss_Robotics_Support_Bay 1 10715
Protoss_Nexus 1 13448
Protoss_Reaver 1 12793
13448
