Protoss_Assimilator 1 3588
Protoss_Gateway 3 11054
Protoss_Cybernetics_Core 1 6090
Protoss_Dragoon 6 12388
Protoss_Robotics_Facility 1 9578
Protoss_Observatory 1 10491
Singularity_Charge 1 9792
Protoss_Observer 1 11654
Protoss_Citadel_of_Adun 1 12222
12388
