Protoss_Gateway 3 10463
Protoss_Assimilator 1 4511
Protoss_Cybernetics_Core 1 5938
Protoss_Dragoon 8 12604
Protoss_Robotics_Facility 1 10011
Singularity_Charge 1 10005
Protoss_Observatory 1 10814
12604
