Protoss_Gateway 2 10483
Protoss_Assimilator 2 12130
Protoss_Cybernetics_Core 1 5628
Protoss_Dragoon 5 12159
Protoss_Nexus 1 11124
Protoss_Robotics_Facility 1 11498
Singularity_Charge 1 9745
12159
