Protoss_Gateway 2 9943
Protoss_Assimilator 1 4452
Protoss_Cybernetics_Core 1 5786
Protoss_Dragoon 7 12251
Protoss_Citadel_of_Adun 1 9182
Protoss_Robotics_Facility 1 10192
Singularity_Charge 1 9821
Protoss_Observatory 1 11419
12251
