Protoss_Gateway 2 8431
Protoss_Nexus 1 7626
Protoss_Assimilator 1 5991
Protoss_Cybernetics_Core 1 7234
Protoss_Zealot 1 7328
Protoss_Dragoon 6 12461
Protoss_Robotics_Facility 1 12565
12565
