Protoss_Gateway 2 6728
Protoss_Assimilator 1 4574
Protoss_Cybernetics_Core 1 5932
Protoss_Dragoon 7 12364
Protoss_Zealot 2 10510
Singularity_Charge 1 10172
Protoss_Robotics_Facility 1 13222
13222
