Protoss_Gateway 2 10714
Protoss_Assimilator 1 4489
Protoss_Cybernetics_Core 1 5824
Protoss_Dragoon 5 11831
Protoss_Robotics_Facility 1 10498
Singularity_Charge 1 9540
Protoss_Observatory 1 11191
Protoss_Nexus 1 14007
Protoss_Observer 1 12289
14007
