Protoss_Gateway 2 10003
Protoss_Assimilator 1 4491
Protoss_Cybernetics_Core 1 6004
Protoss_Dragoon 6 11615
Protoss_Robotics_Facility 1 9755
Protoss_Observatory 1 10494
Singularity_Charge 1 9818
Protoss_Observer 1 11569
Protoss_Nexus 1 14071
14071
