Protoss_Gateway 2 6470
Protoss_Assimilator 1 4245
Protoss_Cybernetics_Core 1 5742
Protoss_Dragoon 6 11231
Singularity_Charge 1 9616
Protoss_Zealot 2 12023
Protoss_Nexus 1 13694
13694
