Protoss_Gateway 2 10277
Protoss_Assimilator 1 4479
Protoss_Cybernetics_Core 1 5882
Protoss_Dragoon 6 11934
Protoss_Robotics_Facility 1 9914
Singularity_Charge 1 9844
Protoss_Observatory 1 10696
Protoss_Observer 1 11850
11934
