Protoss_Gateway 2 6470
Protoss_Assimilator 1 4082
Protoss_Cybernetics_Core 1 5556
Protoss_Dragoon 8 12326
Protoss_Zealot 1 9125
Singularity_Charge 1 9701
Protoss_Nexus 1 13571
13571
