Protoss_Gateway 3 11171
Protoss_Assimilator 1 4511
Protoss_Cybernetics_Core 1 5888
Protoss_Dragoon 5 11908
Protoss_Nexus 1 11791
Singularity_Charge 1 10079
Protoss_Zealot 2 12351
12351
