Protoss_Nexus 1 6737
Protoss_Gateway 3 9763
Protoss_Assimilator 1 5843
Protoss_Cybernetics_Core 1 7430
Protoss_Zealot 2 10846
Protoss_Dragoon 7 12414
Protoss_Robotics_Facility 1 12339
12414
