Protoss_Gateway 2 7770
Protoss_Assimilator 1 4428
Protoss_Cybernetics_Core 1 6125
Protoss_Dragoon 2 9300
Protoss_Citadel_of_Adun 1 9014
Protoss_Robotics_Facility 1 10507
Protoss_Templar_Archives 1 10521
Protoss_Shuttle 1 11916
Protoss_Dark_Templar 2 11751
11916
