Protoss_Gateway 2 6885
Protoss_Assimilator 1 4208
Protoss_Cybernetics_Core 1 5566
Protoss_Dragoon 7 11191
Protoss_Zealot 2 10071
Singularity_Charge 1 9806
Protoss_Robotics_Facility 1 13145
13145
