Protoss_Gateway 2 9860
Protoss_Assimilator 1 4546
Protoss_Cybernetics_Core 1 5862
Protoss_Dragoon 5 11223
Protoss_Robotics_Facility 1 10217
Singularity_Charge 1 10026
Protoss_Observatory 1 10948
Protoss_Observer 1 11996
Protoss_Nexus 1 14049
14049
