Protoss_Gateway 1 4264
Protoss_Assimilator 1 4379
Protoss_Cybernetics_Core 1 6002
Protoss_Dragoon 4 11871
Protoss_Robotics_Facility 1 8730
Protoss_Shuttle 1 10152
Protoss_Observatory 1 10179
Protoss_Robotics_Support_Bay 1 10858
Protoss_Observer 1 11358
Protoss_Reaver 1 12954
12954
