Protoss_Gateway 2 11793
Protoss_Assimilator 1 4220
Protoss_Cybernetics_Core 1 5777
Protoss_Dragoon 4 10667
Protoss_Nexus 1 11823
Protoss_Robotics_Facility 1 11509
Singularity_Charge 1 9874
11823
