Protoss_Gateway 2 10864
Protoss_Assimilator 1 4561
Protoss_Cybernetics_Core 1 5971
Protoss_Dragoon 6 12121
Protoss_Nexus 1 11510
Singularity_Charge 1 9882
Protoss_Robotics_Facility 1 12780
12780
