Protoss_Assimilator 1 3857
Protoss_Gateway 2 10236
Protoss_Cybernetics_Core 1 6289
Protoss_Dragoon 2 8752
Protoss_Robotics_Facility 1 9809
Protoss_Citadel_of_Adun 1 9549
Protoss_Templar_Archives 1 10995
Protoss_Shuttle 1 11490
Protoss_Dark_Templar 2 12221
12221
