Protoss_Gateway 2 6403
Protoss_Assimilator 1 4365
Protoss_Cybernetics_Core 1 5551
Protoss_Dragoon 5 12408
Protoss_Nexus 1 12005
Singularity_Charge 1 9458
Protoss_Robotics_Facility 1 11755
12408
