Protoss_Gateway 2 8758
Protoss_Assimilator 1 4337
Protoss_Cybernetics_Core 1 5919
Protoss_Dragoon 5 11198
Protoss_Zealot 1 10849
Singularity_Charge 1 9916
Protoss_Nexus 1 13603
13603
