Protoss_Gateway 1 4170
Protoss_Assimilator 1 4113
Protoss_Cybernetics_Core 1 5610
Protoss_Dragoon 4 10113
Protoss_Citadel_of_Adun 1 9050
Protoss_Templar_Archives 1 10542
Singularity_Charge 1 9408
Protoss_Nexus 1 12858
Protoss_Dark_Templar 1 11741
Protoss_Robotics_Facility 1 13017
13017
