Protoss_Gateway 2 6789
Protoss_Assimilator 1 4179
Protoss_Cybernetics_Core 1 5898
Protoss_Dragoon 5 9633
Singularity_Charge 1 9601
Protoss_Nexus 1 12592
Protoss_Robotics_Facility 1 12657
Protoss_Citadel_of_Adun 1 12784
12784
