Protoss_Gateway 1 4122
Protoss_Assimilator 1 4182
Protoss_Cybernetics_Core 1 5701
Protoss_Zealot 1 5595
Protoss_Dragoon 6 12554
Protoss_Robotics_Facility 1 10342
Singularity_Charge 1 10087
Protoss_Observatory 1 11110
Protoss_Nexus 1 13735
Protoss_Observer 1 12210
13735
