Protoss_Gateway 2 8443
Protoss_Assimilator 1 4195
Protoss_Cybernetics_Core 1 5705
Protoss_Dragoon 7 12370
Protoss_Robotics_Facility 1 10340
Singularity_Charge 1 9391
Protoss_Shuttle 1 11794
Protoss_Robotics_Support_Bay 1 11153
12370
