Protoss_Gateway 1 4196
Protoss_Assimilator 1 4259
Protoss_Cybernetics_Core 1 5724
Protoss_Dragoon 4 11606
Protoss_Nexus 1 11203
Protoss_Robotics_Facility 1 10857
Singularity_Charge 1 9938
Protoss_Shuttle 1 12541
Protoss_Robotics_Support_Bay 1 11887
12541
