Protoss_Gateway 1 4388
Protoss_Assimilator 1 4463
Protoss_Cybernetics_Core 1 5873
Protoss_Zealot 2 10706
Protoss_Robotics_Facility 1 7984
Protoss_Dragoon 3 11826
Protoss_Shuttle 1 9523
Protoss_Robotics_Support_Bay 1 9072
Protoss_Reaver 1 11081
11826
