Protoss_Assimilator 2 9877
Protoss_Gateway 3 10192
Protoss_Zealot 3 12216
Protoss_Forge 1 6992
Protoss_Photon_Cannon 2 8489
Protoss_Nexus 2 12877
Protoss_Cybernetics_Core 1 12069
12877
