Protoss_Gateway 2 9557
Protoss_Assimilator 1 4422
Protoss_Cybernetics_Core 1 5676
Protoss_Dragoon 3 9815
Protoss_Citadel_of_Adun 1 8724
Protoss_Templar_Archives 1 10201
Singularity_Charge 1 9628
Protoss_Dark_Templar 2 11422
Protoss_Nexus 1 13557
13557
