Protoss_Gateway 2 8408
Protoss_Assimilator 1 4425
Protoss_Cybernetics_Core 1 5682
Protoss_Dragoon 6 11732
Protoss_Nexus 1 11457
Singularity_Charge 1 9347
Protoss_Robotics_Facility 1 11540
11732
