Protoss_Gateway 2 9261
Protoss_Assimilator 1 4173
Protoss_Cybernetics_Core 1 5639
Protoss_Dragoon 5 10637
Singularity_Charge 1 9900
Protoss_Nexus 1 13268
Protoss_Robotics_Facility 1 13018
13268
