Protoss_Gateway 1 4256
Protoss_Assimilator 1 4420
Protoss_Cybernetics_Core 1 5838
Protoss_Dragoon 5 11711
Singularity_Charge 1 9841
Protoss_Nexus 1 12900
Protoss_Robotics_Facility 1 12764
12900
