Protoss_Assimilator 4 7188
Protoss_Gateway 2 12115
Protoss_Cybernetics_Core 1 6596
Protoss_Dragoon 5 12461
Protoss_Nexus 1 12251
Singularity_Charge 1 10720
Protoss_Robotics_Facility 1 13068
13068
