Protoss_Gateway 2 10106
Protoss_Assimilator 1 4246
Protoss_Cybernetics_Core 1 5742
Protoss_Zealot 1 5721
Protoss_Citadel_of_Adun 2 8753
Protoss_Dragoon 2 9115
Protoss_Templar_Archives 1 10379
Singularity_Charge 1 9836
Protoss_Dark_Templar 2 11829
Protoss_Nexus 1 14217
14217
