Protoss_Gateway 2 9882
Protoss_Assimilator 1 4144
Protoss_Cybernetics_Core 1 5557
Protoss_Dragoon 6 12244
Protoss_Robotics_Facility 1 9547
Singularity_Charge 1 9525
Protoss_Observatory 1 10288
Protoss_Nexus 1 13240
Protoss_Observer 1 11502
13240
