Protoss_Nexus 1 6725
Protoss_Gateway 2 7673
Protoss_Assimilator 1 5996
Protoss_Cybernetics_Core 1 7419
Protoss_Dragoon 6 12300
Protoss_Robotics_Facility 1 12338
Protoss_Zealot 1 12187
12338
