Protoss_Gateway 3 12359
Protoss_Assimilator 1 4191
Protoss_Cybernetics_Core 1 5607
Protoss_Dragoon 5 11349
Protoss_Nexus 1 11273
Singularity_Charge 1 9508
Protoss_Robotics_Facility 1 12036
12359
