Protoss_Gateway 2 11901
Protoss_Assimilator 1 4404
Protoss_Zealot 2 6444
Protoss_Cybernetics_Core 1 6661
Protoss_Dragoon 4 12010
Protoss_Nexus 1 12495
Protoss_Robotics_Facility 1 12010
Singularity_Charge 1 10763
12495
