Protoss_Gateway 2 12740
Protoss_Assimilator 1 4173
Protoss_Cybernetics_Core 1 5626
Protoss_Zealot 1 6198
Protoss_Robotics_Facility 1 8146
Protoss_Dragoon 2 11621
Protoss_Shuttle 1 9549
Protoss_Robotics_Support_Bay 1 8912
Protoss_Reaver 1 11254
12740
