Protoss_Gateway 1 4104
Protoss_Assimilator 1 4277
Protoss_Zealot 2 6374
Protoss_Cybernetics_Core 1 6503
Protoss_Dragoon 5 12171
Protoss_Robotics_Facility 1 10946
Singularity_Charge 1 10635
Protoss_Nexus 1 13514
Protoss_Observatory 1 11638
13514
