Protoss_Nexus 1 6775
Protoss_Gateway 3 12835
Protoss_Assimilator 2 10403
Protoss_Cybernetics_Core 1 7476
Protoss_Zealot 1 7732
Protoss_Dragoon 5 12225
Protoss_Robotics_Facility 1 11009
Protoss_Shuttle 1 12672
12835
