Protoss_Gateway 2 8636
Protoss_Assimilator 1 4296
Protoss_Zealot 1 5241
Protoss_Nexus 1 8307
Protoss_Cybernetics_Core 1 7644
Protoss_Dragoon 6 12306
Singularity_Charge 1 11311
12306
