Protoss_Nexus 1 6775
Protoss_Gateway 2 7682
Protoss_Assimilator 2 10293
Protoss_Cybernetics_Core 1 7425
Protoss_Dragoon 6 12273
Protoss_Robotics_Facility 1 12633
Singularity_Charge 1 11363
12633
