Protoss_Gateway 2 10823
Protoss_Assimilator 1 4220
Protoss_Zealot 2 6488
Protoss_Cybernetics_Core 1 6520
Protoss_Dragoon 4 11261
Protoss_Robotics_Facility 1 10260
Protoss_Observatory 1 10997
Singularity_Charge 1 10760
Protoss_Observer 1 12099
Protoss_Nexus 1 14010
14010
