Protoss_Gateway 1 4180
Protoss_Assimilator 1 4395
Protoss_Cybernetics_Core 1 5793
Protoss_Dragoon 5 11398
Protoss_Nexus 2 14190
Singularity_Charge 1 9666
Protoss_Robotics_Facility 1 11855
14190
