Protoss_Gateway 1 3989
Protoss_Zealot 4 11338
Protoss_Assimilator 1 5257
Protoss_Cybernetics_Core 1 6876
Protoss_Dragoon 3 10427
Protoss_Robotics_Facility 1 9723
Protoss_Shuttle 1 11168
Protoss_Robotics_Support_Bay 1 10913
Protoss_Reaver 1 12779
12779
