Protoss_Gateway 2 11420
Protoss_Assimilator 1 4264
Protoss_Cybernetics_Core 1 5613
Protoss_Dragoon 4 11492
Protoss_Robotics_Facility 1 9581
Protoss_Nexus 1 12134
Singularity_Charge 1 9678
Protoss_Observatory 1 10583
Protoss_Observer 1 11610
12134
