Protoss_Gateway 2 10530
Protoss_Assimilator 1 4575
Protoss_Cybernetics_Core 1 5938
Protoss_Zealot 1 5707
Protoss_Dragoon 6 12031
Protoss_Robotics_Facility 1 10804
Singularity_Charge 1 9950
Protoss_Shuttle 1 12339
12339
