Protoss_Gateway 2 11865
Protoss_Assimilator 1 4174
Protoss_Cybernetics_Core 1 5458
Protoss_Dragoon 5 11808
Protoss_Robotics_Facility 1 9484
Protoss_Observatory 1 10310
Singularity_Charge 1 9640
Protoss_Nexus 1 12959
Protoss_Observer 1 11320
12959
