Protoss_Gateway 2 6456
Protoss_Assimilator 1 4413
Protoss_Cybernetics_Core 1 5850
Protoss_Dragoon 5 11805
Protoss_Zealot 2 9658
Protoss_Nexus 1 12570
Singularity_Charge 1 9730
Protoss_Robotics_Facility 1 13151
13151
