Protoss_Gateway 2 11682
Protoss_Assimilator 1 4330
Protoss_Cybernetics_Core 1 5554
Protoss_Zealot 1 5455
Protoss_Dragoon 5 11723
Protoss_Nexus 1 11569
Protoss_Robotics_Facility 1 11612
Singularity_Charge 1 9830
11723
