Protoss_Gateway 2 7755
Protoss_Assimilator 1 4466
Protoss_Cybernetics_Core 1 5688
Protoss_Nexus 1 10265
Protoss_Dragoon 5 12314
Protoss_Robotics_Facility 1 10342
Singularity_Charge 1 9420
Protoss_Observatory 1 11409
12314
