Protoss_Gateway 1 4155
Protoss_Assimilator 1 4340
Protoss_Cybernetics_Core 1 5777
Protoss_Zealot 1 5701
Protoss_Robotics_Facility 1 7972
Protoss_Dragoon 2 11533
Protoss_Robotics_Support_Bay 1 8697
Protoss_Shuttle 1 10062
Protoss_Reaver 1 11620
Protoss_Observatory 1 11960
11960
