Protoss_Gateway 1 4287
Protoss_Assimilator 1 4512
Protoss_Cybernetics_Core 1 5783
Protoss_Dragoon 3 10257
Protoss_Robotics_Facility 1 8422
Protoss_Shuttle 1 9845
Protoss_Robotics_Support_Bay 1 9326
Protoss_Zealot 2 11341
Protoss_Reaver 1 11628
11628
