Protoss_Gateway 3 7799
Protoss_Assimilator 2 6310
Protoss_Zealot 6 10000
Protoss_Cybernetics_Core 1 9697
Protoss_Citadel_of_Adun 1 11200
Protoss_Robotics_Facility 1 11905
Protoss_Dragoon 2 11650
Protoss_Templar_Archives 1 12819
12819
