Protoss_Gateway 2 12728
Protoss_Assimilator 1 4170
Protoss_Cybernetics_Core 1 5606
Protoss_Dragoon 4 12194
Protoss_Nexus 1 10906
Protoss_Robotics_Facility 1 11010
Singularity_Charge 1 9505
Protoss_Citadel_of_Adun 1 11373
Protoss_Observatory 1 11836
12728
