Protoss_Gateway 3 10606
Protoss_Assimilator 1 4204
Protoss_Cybernetics_Core 1 5616
Protoss_Dragoon 6 12071
Protoss_Nexus 1 9434
Singularity_Charge 1 11027
Protoss_Zealot 1 12023
12071
