Protoss_Gateway 2 11153
Protoss_Assimilator 1 4229
Protoss_Cybernetics_Core 1 5585
Protoss_Zealot 1 5522
Protoss_Dragoon 4 12200
Protoss_Nexus 1 10524
Protoss_Robotics_Facility 1 10265
Protoss_Shuttle 1 11841
Protoss_Robotics_Support_Bay 1 11985
12200
