Protoss_Gateway 3 12523
Protoss_Assimilator 1 4182
Protoss_Cybernetics_Core 1 5630
Protoss_Zealot 1 5557
Protoss_Dragoon 5 11870
Protoss_Nexus 1 12300
Singularity_Charge 1 9581
Protoss_Robotics_Facility 1 12152
12523
