Protoss_Nexus 1 6660
Protoss_Gateway 2 8856
Protoss_Assimilator 2 9557
Protoss_Cybernetics_Core 1 7615
Protoss_Zealot 1 7240
Protoss_Dragoon 4 11349
Protoss_Robotics_Facility 1 11685
11685
