Protoss_Gateway 1 4029
Protoss_Assimilator 1 4147
Protoss_Cybernetics_Core 1 5553
Protoss_Zealot 1 5587
Protoss_Dragoon 5 11583
Protoss_Robotics_Facility 1 10659
Singularity_Charge 1 9604
Protoss_Observatory 1 11802
Protoss_Nexus 1 14002
14002
