Protoss_Gateway 1 4062
Protoss_Assimilator 1 4318
Protoss_Cybernetics_Core 1 5584
Protoss_Zealot 1 5537
Protoss_Dragoon 5 11931
Protoss_Robotics_Facility 1 9797
Singularity_Charge 1 9730
Protoss_Observatory 1 10554
Protoss_Nexus 1 13199
Protoss_Observer 1 11581
13199
