Protoss_Gateway 2 12497
Protoss_Assimilator 1 4132
Protoss_Zealot 3 6801
Protoss_Cybernetics_Core 1 7043
Protoss_Dragoon 4 11720
Protoss_Nexus 1 11847
Protoss_Robotics_Facility 1 11948
Singularity_Charge 1 10731
12497
