Protoss_Gateway 2 10779
Protoss_Assimilator 1 4138
Protoss_Cybernetics_Core 1 5575
Protoss_Dragoon 5 11231
Protoss_Nexus 1 11112
Protoss_Robotics_Facility 1 10643
Singularity_Charge 1 9502
Protoss_Shuttle 1 12280
12280
