Protoss_Gateway 1 4444
Protoss_Assimilator 1 4602
Protoss_Cybernetics_Core 1 5966
Protoss_Zealot 2 10161
Protoss_Robotics_Facility 1 8397
Protoss_Dragoon 3 11384
Protoss_Shuttle 1 9962
Protoss_Robotics_Support_Bay 1 9512
Protoss_Reaver 1 11520
11520
