Protoss_Gateway 2 12598
Protoss_Assimilator 2 12252
Protoss_Cybernetics_Core 1 5575
Protoss_Dragoon 3 9666
Protoss_Citadel_of_Adun 1 8809
Protoss_Templar_Archives 1 10327
Protoss_Nexus 1 12467
Protoss_Dark_Templar 1 11527
Protoss_Stargate 1 12171
Singularity_Charge 1 11249
12598
