Protoss_Gateway 2 12318
Protoss_Assimilator 1 4303
Protoss_Cybernetics_Core 1 5709
Protoss_Dragoon 5 12369
Protoss_Robotics_Facility 1 10233
Protoss_Nexus 1 12456
Singularity_Charge 1 9701
Protoss_Observatory 1 11110
Protoss_Observer 1 12154
Protoss_Citadel_of_Adun 1 12814
12814
