Protoss_Gateway 1 4166
Protoss_Assimilator 1 4549
Protoss_Cybernetics_Core 1 5805
Protoss_Dragoon 5 11940
Protoss_Robotics_Facility 1 9873
Singularity_Charge 1 9894
Protoss_Nexus 1 13178
Protoss_Observatory 1 11158
13178
