Protoss_Gateway 2 12716
Protoss_Assimilator 1 4141
Protoss_Cybernetics_Core 1 5683
Protoss_Zealot 1 5464
Protoss_Dragoon 5 11747
Protoss_Robotics_Facility 1 9496
Protoss_Observatory 1 10185
Singularity_Charge 1 9839
Protoss_Nexus 1 13009
Protoss_Observer 2 12166
13009
