Protoss_Gateway 1 4103
Protoss_Assimilator 1 4311
Protoss_Cybernetics_Core 1 5611
Protoss_Zealot 2 11563
Protoss_Dragoon 5 11755
Protoss_Robotics_Facility 1 10037
Singularity_Charge 1 9935
Protoss_Shuttle 1 11443
Protoss_Robotics_Support_Bay 1 10790
Protoss_Reaver 1 13001
13001
