Protoss_Gateway 2 6936
Protoss_Assimilator 1 4199
Protoss_Cybernetics_Core 1 5639
Protoss_Dragoon 7 12443
Protoss_Nexus 1 12897
Singularity_Charge 1 10152
Protoss_Robotics_Facility 1 12967
12967
