Protoss_Gateway 4 12716
Protoss_Assimilator 1 4394
Protoss_Cybernetics_Core 1 5777
Protoss_Dragoon 5 11433
Protoss_Robotics_Facility 1 10239
Singularity_Charge 1 9666
Protoss_Nexus 1 12537
Protoss_Observatory 1 10997
Protoss_Observer 1 12119
12716
