Protoss_Gateway 2 11872
Protoss_Assimilator 1 4234
Protoss_Cybernetics_Core 1 5677
Protoss_Dragoon 5 12297
Protoss_Nexus 1 11648
Singularity_Charge 1 9765
Protoss_Robotics_Facility 1 12071
12297
