Protoss_Gateway 2 10467
Protoss_Assimilator 1 4570
Protoss_Cybernetics_Core 1 6074
Protoss_Dragoon 3 9587
Protoss_Citadel_of_Adun 1 9381
Protoss_Templar_Archives 1 10861
Protoss_Zealot 1 10606
Singularity_Charge 1 10140
Protoss_Dark_Templar 2 12136
12136
