Protoss_Gateway 1 4068
Protoss_Assimilator 1 4325
Protoss_Cybernetics_Core 1 5727
Protoss_Zealot 1 5625
Protoss_Dragoon 5 11934
Protoss_Nexus 1 11785
Singularity_Charge 1 10067
Protoss_Robotics_Facility 1 12235
12235
