Protoss_Gateway 2 11914
Protoss_Assimilator 1 4688
Protoss_Cybernetics_Core 1 6090
Protoss_Dragoon 5 11896
Protoss_Nexus 1 12043
Singularity_Charge 1 10052
Protoss_Robotics_Facility 1 13301
13301
