Protoss_Gateway 1 4343
Protoss_Assimilator 1 4612
Protoss_Cybernetics_Core 1 6058
Protoss_Dragoon 2 8750
Protoss_Robotics_Facility 1 9259
Protoss_Shuttle 1 10758
Protoss_Robotics_Support_Bay 1 10075
Protoss_Reaver 1 12316
Protoss_Zealot 1 11991
12316
