Protoss_Nexus 1 6527
Protoss_Gateway 1 5496
Protoss_Assimilator 1 5657
Protoss_Cybernetics_Core 1 7084
Protoss_Zealot 1 6769
Protoss_Dragoon 4 12525
Singularity_Charge 1 11279
12525
