Protoss_Gateway 2 9923
Protoss_Assimilator 1 4232
Protoss_Cybernetics_Core 1 5607
Protoss_Dragoon 3 9259
Protoss_Citadel_of_Adun 1 8436
Protoss_Robotics_Facility 1 9663
Protoss_Templar_Archives 1 10354
Protoss_Zealot 1 10264
Protoss_Shuttle 1 11212
Protoss_Dark_Templar 2 11668
11668
