Protoss_Nexus 1 6696
Protoss_Gateway 3 12457
Protoss_Assimilator 2 9861
Protoss_Cybernetics_Core 1 7644
Protoss_Zealot 1 7378
Protoss_Dragoon 4 12136
Protoss_Robotics_Facility 1 11951
12457
