Protoss_Assimilator 3 12156
Protoss_Gateway 3 11654
Protoss_Nexus 1 8291
Protoss_Cybernetics_Core 1 8149
Protoss_Zealot 2 11683
Protoss_Dragoon 4 11779
Protoss_Citadel_of_Adun 1 11189
12156
