Protoss_Gateway 2 11584
Protoss_Assimilator 1 4135
Protoss_Cybernetics_Core 1 5557
Protoss_Zealot 1 5522
Protoss_Dragoon 5 11606
Protoss_Nexus 1 11564
Singularity_Charge 1 9678
Protoss_Robotics_Facility 1 11629
11629
