Protoss_Gateway 1 4217
Protoss_Assimilator 1 4441
Protoss_Cybernetics_Core 1 5800
Protoss_Dragoon 4 10889
Protoss_Citadel_of_Adun 1 8928
Protoss_Templar_Archives 1 10559
Protoss_Nexus 1 12336
Singularity_Charge 1 9982
Protoss_Dark_Templar 1 11990
12336
