Protoss_Gateway 2 11475
Protoss_Assimilator 1 4205
Protoss_Cybernetics_Core 1 5648
Protoss_Dragoon 5 11761
Protoss_Robotics_Facility 1 9655
Protoss_Nexus 1 11926
Singularity_Charge 1 9672
Protoss_Observatory 1 10488
Protoss_Observer 1 11578
11926
