Protoss_Gateway 2 8134
Protoss_Assimilator 1 4147
Protoss_Cybernetics_Core 1 5534
Protoss_Zealot 1 5557
Protoss_Dragoon 6 12066
Singularity_Charge 1 9701
Protoss_Nexus 1 13524
13524
