Protoss_Gateway 1 4031
Protoss_Assimilator 1 4120
Protoss_Cybernetics_Core 1 5598
Protoss_Dragoon 6 12573
Protoss_Robotics_Facility 1 9440
Protoss_Observatory 1 10152
Singularity_Charge 1 9464
Protoss_Nexus 1 12701
Protoss_Observer 2 12072
12701
