Protoss_Gateway 1 4059
Protoss_Assimilator 1 4360
Protoss_Cybernetics_Core 1 5636
Protoss_Dragoon 5 11422
Protoss_Robotics_Facility 1 9721
Singularity_Charge 1 9704
Protoss_Nexus 1 12830
Protoss_Shuttle 1 12014
Protoss_Robotics_Support_Bay 1 12014
12830
