Protoss_Gateway 1 4205
Protoss_Assimilator 1 4382
Protoss_Cybernetics_Core 1 5670
Protoss_Zealot 1 5534
Protoss_Dragoon 4 11035
Protoss_Robotics_Facility 1 10160
Protoss_Shuttle 1 11557
Protoss_Robotics_Support_Bay 1 11322
11557
