Protoss_Gateway 1 4315
Protoss_Assimilator 1 4252
Protoss_Cybernetics_Core 1 5756
Protoss_Dragoon 5 12367
Protoss_Nexus 1 10937
Protoss_Robotics_Facility 1 11448
Singularity_Charge 1 9882
12367
