Protoss_Gateway 1 4174
Protoss_Assimilator 1 4537
Protoss_Cybernetics_Core 1 5859
Protoss_Zealot 1 5944
Protoss_Dragoon 4 11360
Protoss_Nexus 1 10677
Protoss_Robotics_Facility 1 11362
Singularity_Charge 1 10040
Protoss_Citadel_of_Adun 1 11954
11954
