Protoss_Nexus 1 6656
Protoss_Gateway 2 7711
Protoss_Assimilator 1 6002
Protoss_Cybernetics_Core 1 7483
Protoss_Zealot 1 7504
Protoss_Dragoon 4 10658
Protoss_Robotics_Facility 1 12257
12257
