Protoss_Gateway 1 4325
Protoss_Assimilator 1 4567
Protoss_Cybernetics_Core 1 6026
Protoss_Dragoon 4 11641
Protoss_Nexus 1 11997
Protoss_Citadel_of_Adun 1 11348
Singularity_Charge 1 10136
Protoss_Robotics_Facility 1 12250
12250
