Protoss_Assimilator 1 3653
Protoss_Gateway 2 11108
Protoss_Cybernetics_Core 1 6304
Protoss_Zealot 1 6280
Protoss_Dragoon 6 12449
Protoss_Nexus 1 11373
Protoss_Robotics_Facility 1 12197
Singularity_Charge 1 10494
12449
