Protoss_Gateway 2 8560
Protoss_Zealot 2 7302
Protoss_Nexus 1 8131
Protoss_Assimilator 2 10660
Protoss_Cybernetics_Core 1 7512
Protoss_Dragoon 5 12083
Protoss_Robotics_Facility 1 12203
12203
