Protoss_Gateway 2 12773
Protoss_Assimilator 1 4245
Protoss_Cybernetics_Core 1 5743
Protoss_Zealot 1 5710
Protoss_Dragoon 5 11741
Protoss_Nexus 1 12052
Protoss_Robotics_Facility 1 11934
Singularity_Charge 1 10131
12773
