Protoss_Gateway 1 4167
Protoss_Assimilator 1 4236
Protoss_Zealot 2 6128
Protoss_Cybernetics_Core 1 6015
Protoss_Dragoon 5 12298
Protoss_Nexus 1 12366
Singularity_Charge 1 9777
12366
