Protoss_Gateway 2 9611
Protoss_Zealot 3 7094
Protoss_Assimilator 1 5288
Protoss_Cybernetics_Core 1 6889
Protoss_Dragoon 5 11984
Singularity_Charge 1 10720
Protoss_Nexus 1 13667
13667
