Protoss_Gateway 2 11064
Protoss_Assimilator 1 4331
Protoss_Cybernetics_Core 1 5909
Protoss_Dragoon 4 11665
Protoss_Nexus 1 11942
Singularity_Charge 1 10049
Protoss_Citadel_of_Adun 1 11793
Protoss_Robotics_Facility 1 13201
13201
