Protoss_Gateway 1 4212
Protoss_Assimilator 1 4679
Protoss_Cybernetics_Core 1 6204
Protoss_Dragoon 5 12174
Protoss_Robotics_Facility 1 10175
Protoss_Nexus 1 12559
Singularity_Charge 1 9891
Protoss_Shuttle 1 11595
Protoss_Robotics_Support_Bay 1 11404
Protoss_Zealot 1 11903
12559
