Protoss_Gateway 1 4176
Protoss_Assimilator 1 4239
Protoss_Cybernetics_Core 1 5660
Protoss_Dragoon 4 10538
Protoss_Robotics_Facility 1 9781
Protoss_Shuttle 1 11183
Singularity_Charge 1 9765
Protoss_Robotics_Support_Bay 1 10781
Protoss_Reaver 1 12741
Protoss_Zealot 1 12254
12741
