Protoss_Gateway 2 11114
Protoss_Assimilator 1 4751
Protoss_Zealot 3 6974
Protoss_Cybernetics_Core 1 7202
Protoss_Dragoon 3 10631
Protoss_Citadel_of_Adun 1 10243
Protoss_Templar_Archives 1 11777
Protoss_Robotics_Facility 1 12325
Singularity_Charge 1 11393
12325
