Protoss_Gateway 1 4092
Protoss_Assimilator 1 4112
Protoss_Cybernetics_Core 1 5534
Protoss_Zealot 1 5508
Protoss_Dragoon 4 10386
Protoss_Robotics_Facility 1 9805
Protoss_Shuttle 1 11200
Singularity_Charge 1 9786
Protoss_Robotics_Support_Bay 1 10984
Protoss_Nexus 1 13676
Protoss_Reaver 1 12893
13676
