Protoss_Gateway 1 4347
Protoss_Assimilator 1 4818
Protoss_Zealot 3 11712
Protoss_Cybernetics_Core 1 6794
Protoss_Dragoon 4 11691
Protoss_Robotics_Facility 1 9925
Protoss_Shuttle 1 11326
Protoss_Robotics_Support_Bay 1 11296
Singularity_Charge 1 10939
Protoss_Reaver 1 13036
13036
