Protoss_Nexus 1 6701
Protoss_Gateway 2 7117
Protoss_Assimilator 1 5812
Protoss_Cybernetics_Core 1 7387
Protoss_Zealot 1 7123
Protoss_Dragoon 6 11665
Protoss_Citadel_of_Adun 1 12444
12444
