Protoss_Gateway 2 9684
Protoss_Assimilator 3 10337
Protoss_Zealot 3 8794
Protoss_Nexus 1 9502
Protoss_Cybernetics_Core 1 8966
Protoss_Dragoon 3 11779
Protoss_Robotics_Facility 1 12098
12098
