Protoss_Gateway 2 12279
Protoss_Assimilator 2 11929
Protoss_Cybernetics_Core 1 5566
Protoss_Zealot 1 5446
Protoss_Dragoon 4 11114
Protoss_Nexus 1 10536
Protoss_Robotics_Facility 1 11436
12279
