Protoss_Gateway 2 9857
Protoss_Assimilator 1 4382
Protoss_Cybernetics_Core 1 5623
Protoss_Robotics_Facility 1 7965
Protoss_Dragoon 4 11079
Protoss_Observatory 1 8878
Protoss_Zealot 1 9588
Protoss_Observer 2 11622
Protoss_Nexus 1 14039
14039
