Protoss_Gateway 2 12667
Protoss_Assimilator 1 4346
Protoss_Cybernetics_Core 1 5765
Protoss_Dragoon 5 11849
Protoss_Robotics_Facility 1 10333
Singularity_Charge 1 9724
Protoss_Nexus 1 13091
Protoss_Observatory 1 11138
Protoss_Observer 1 12201
13091
