Protoss_Gateway 1 4097
Protoss_Assimilator 1 4167
Protoss_Cybernetics_Core 1 5565
Protoss_Dragoon 4 11618
Protoss_Nexus 1 11335
Singularity_Charge 1 9508
Protoss_Robotics_Facility 1 11998
11998
