Protoss_Gateway 1 4207
Protoss_Assimilator 1 4499
Protoss_Cybernetics_Core 1 5816
Protoss_Dragoon 3 11720
Protoss_Robotics_Facility 1 8343
Protoss_Zealot 2 10109
Protoss_Shuttle 1 9746
Protoss_Robotics_Support_Bay 1 9256
Protoss_Reaver 1 11839
11839
