Protoss_Gateway 2 9959
Protoss_Assimilator 1 4173
Protoss_Cybernetics_Core 1 5613
Protoss_Zealot 1 5516
Protoss_Dragoon 3 10450
Protoss_Citadel_of_Adun 1 8769
Protoss_Robotics_Facility 1 10223
Protoss_Templar_Archives 1 10234
Protoss_Shuttle 1 11628
Protoss_Dark_Templar 2 11758
11758
