Protoss_Nexus 1 6780
Protoss_Gateway 2 7586
Protoss_Assimilator 1 5950
Protoss_Cybernetics_Core 1 7479
Protoss_Zealot 1 7398
Protoss_Dragoon 6 12238
Protoss_Robotics_Facility 1 12401
12401
