Protoss_Assimilator 1 3658
Protoss_Gateway 1 4550
Protoss_Cybernetics_Core 1 6036
Protoss_Robotics_Facility 1 8685
Protoss_Dragoon 4 12423
Protoss_Shuttle 1 10438
Singularity_Charge 1 9711
Protoss_Observatory 1 10737
Protoss_Observer 1 11944
Protoss_Robotics_Support_Bay 1 11982
12423
