Protoss_Gateway 2 12665
Protoss_Assimilator 1 4076
Protoss_Cybernetics_Core 1 5550
Protoss_Zealot 2 12257
Protoss_Dragoon 4 10435
Protoss_Robotics_Facility 1 9771
Protoss_Shuttle 1 11171
Singularity_Charge 1 9888
Protoss_Robotics_Support_Bay 1 11772
Protoss_Observatory 1 11848
12665
