Protoss_Nexus 1 6619
Protoss_Gateway 2 7735
Protoss_Assimilator 1 5794
Protoss_Cybernetics_Core 1 7231
Protoss_Zealot 1 7536
Protoss_Dragoon 3 10298
Protoss_Citadel_of_Adun 1 10987
Protoss_Robotics_Facility 1 12904
Protoss_Templar_Archives 1 12451
12904
