Protoss_Nexus 1 6840
Protoss_Gateway 1 6043
Protoss_Assimilator 2 9402
Protoss_Cybernetics_Core 1 7543
Protoss_Stargate 2 9881
Protoss_Forge 1 9870
Protoss_Corsair 4 12119
Protoss_Photon_Cannon 2 12076
12119
