Protoss_Gateway 2 12734
Protoss_Assimilator 1 4243
Protoss_Cybernetics_Core 1 5510
Protoss_Zealot 1 5417
Protoss_Dragoon 5 11829
Protoss_Robotics_Facility 1 9543
Protoss_Observatory 1 10236
Singularity_Charge 1 9748
Protoss_Nexus 1 13120
Protoss_Observer 2 12137
13120
