Protoss_Gateway 2 8859
Protoss_Assimilator 1 4319
Protoss_Cybernetics_Core 1 5783
Protoss_Citadel_of_Adun 1 7378
Protoss_Dragoon 4 11861
Protoss_Templar_Archives 1 9406
Protoss_Dark_Templar 2 10649
11861
