Protoss_Gateway 1 4261
Protoss_Assimilator 1 4568
Protoss_Cybernetics_Core 1 5998
Protoss_Dragoon 4 11533
Protoss_Citadel_of_Adun 1 9569
Protoss_Nexus 1 12558
Singularity_Charge 1 10029
Protoss_Templar_Archives 1 11496
Protoss_Robotics_Facility 1 13229
13229
