Protoss_Gateway 2 10565
Protoss_Assimilator 1 4419
Protoss_Cybernetics_Core 1 5844
Protoss_Dragoon 6 12511
Protoss_Nexus 1 11134
Protoss_Robotics_Facility 1 11518
Singularity_Charge 1 9771
12511
