Protoss_Nexus 1 6775
Protoss_Gateway 4 12558
Protoss_Assimilator 2 11085
Protoss_Cybernetics_Core 1 7398
Protoss_Dragoon 5 11665
Protoss_Robotics_Facility 1 11847
Protoss_Zealot 1 11522
12558
