Protoss_Gateway 1 4135
Protoss_Assimilator 1 4255
Protoss_Cybernetics_Core 1 5674
Protoss_Dragoon 5 12347
Protoss_Robotics_Facility 1 8370
Protoss_Observatory 1 9354
Protoss_Observer 1 10632
Protoss_Nexus 1 13083
Singularity_Charge 1 11270
13083
