Protoss_Gateway 2 10068
Protoss_Assimilator 1 4425
Protoss_Cybernetics_Core 1 5800
Protoss_Dragoon 6 11767
Protoss_Robotics_Facility 1 9946
Singularity_Charge 1 9827
Protoss_Observatory 1 11309
11767
