Protoss_Gateway 3 12639
Protoss_Assimilator 1 4556
Protoss_Cybernetics_Core 1 5920
Protoss_Dragoon 6 12560
Protoss_Nexus 1 11771
Singularity_Charge 1 9953
Protoss_Robotics_Facility 1 12159
12639
