Protoss_Gateway 1 4188
Protoss_Assimilator 1 4416
Protoss_Cybernetics_Core 1 5657
Protoss_Zealot 1 5633
Protoss_Dragoon 4 10405
Protoss_Robotics_Facility 1 10497
Singularity_Charge 1 10084
Protoss_Nexus 1 13208
Protoss_Shuttle 1 12494
Protoss_Robotics_Support_Bay 1 12042
13208
