Protoss_Gateway 2 9746
Protoss_Assimilator 1 4287
Protoss_Cybernetics_Core 1 5837
Protoss_Dragoon 5 11141
Protoss_Robotics_Facility 1 10080
Singularity_Charge 1 9622
Protoss_Observatory 1 10861
Protoss_Observer 1 12093
Protoss_Nexus 1 14086
14086
