Protoss_Gateway 2 6390
Protoss_Assimilator 1 4144
Protoss_Cybernetics_Core 1 5554
Protoss_Dragoon 9 12013
Protoss_Robotics_Facility 1 10195
Singularity_Charge 1 9239
Protoss_Shuttle 1 11592
Protoss_Robotics_Support_Bay 1 11849
12013
