Protoss_Gateway 1 4240
Protoss_Assimilator 1 4559
Protoss_Cybernetics_Core 1 6857
Protoss_Zealot 1 6795
Protoss_Dragoon 3 10898
Protoss_Robotics_Facility 1 10251
Protoss_Shuttle 1 11663
Singularity_Charge 1 10523
Protoss_Robotics_Support_Bay 1 11466
11663
