Protoss_Gateway 2 12248
Protoss_Assimilator 1 4482
Protoss_Cybernetics_Core 1 5742
Protoss_Dragoon 5 11574
Protoss_Nexus 1 11741
Singularity_Charge 1 9982
Protoss_Robotics_Facility 1 11934
12248
