Protoss_Gateway 1 4155
Protoss_Assimilator 1 4328
Protoss_Cybernetics_Core 1 5753
Protoss_Dragoon 4 12300
Protoss_Robotics_Facility 1 8284
Protoss_Shuttle 1 9845
Protoss_Zealot 2 11036
Protoss_Observatory 1 9825
Protoss_Observer 1 10846
Protoss_Robotics_Support_Bay 1 10754
Protoss_Reaver 1 12632
Singularity_Charge 1 11311
12632
