Protoss_Gateway 2 7053
Protoss_Assimilator 2 4932
Protoss_Cybernetics_Core 1 6225
Protoss_Zealot 1 7079
Protoss_Dragoon 5 10771
Singularity_Charge 1 10600
Protoss_Nexus 1 13852
13852
