Protoss_Gateway 2 9050
Protoss_Assimilator 1 4100
Protoss_Cybernetics_Core 1 5496
Protoss_Zealot 1 5446
Protoss_Dragoon 6 11937
Protoss_Nexus 1 11873
Singularity_Charge 1 9165
Protoss_Robotics_Facility 1 12365
12365
