Protoss_Gateway 2 8096
Protoss_Assimilator 1 4246
Protoss_Cybernetics_Core 1 5633
Protoss_Dragoon 6 11158
Protoss_Nexus 1 12271
Singularity_Charge 1 9499
Protoss_Robotics_Facility 1 12870
12870
