Protoss_Gateway 2 12690
Protoss_Assimilator 1 4357
Protoss_Cybernetics_Core 1 5780
Protoss_Dragoon 3 12502
Protoss_Robotics_Facility 1 8331
Protoss_Shuttle 1 9722
Protoss_Robotics_Support_Bay 1 9200
Protoss_Zealot 2 11133
Protoss_Reaver 1 11598
Protoss_Observatory 1 11280
12690
