Protoss_Gateway 2 11925
Protoss_Assimilator 1 4185
Protoss_Cybernetics_Core 1 5689
Protoss_Dragoon 5 11884
Protoss_Nexus 1 11825
Protoss_Robotics_Facility 1 11136
Singularity_Charge 1 9496
Protoss_Robotics_Support_Bay 1 11902
11925
