Protoss_Gateway 2 10556
Protoss_Assimilator 1 4356
Protoss_Cybernetics_Core 1 5762
Protoss_Dragoon 5 12423
Protoss_Robotics_Facility 1 9695
Protoss_Nexus 1 12292
Singularity_Charge 1 9716
Protoss_Shuttle 1 11256
Protoss_Robotics_Support_Bay 1 11903
12423
