Protoss_Gateway 2 8941
Protoss_Assimilator 1 4552
Protoss_Cybernetics_Core 1 5903
Protoss_Dragoon 2 8239
Protoss_Citadel_of_Adun 2 8904
Protoss_Zealot 1 9492
Protoss_Templar_Archives 1 10353
Protoss_Dark_Templar 2 11590
Protoss_Nexus 1 13691
13691
