Protoss_Gateway 2 12835
Protoss_Assimilator 1 4305
Protoss_Cybernetics_Core 1 5762
Protoss_Dragoon 5 11717
Protoss_Robotics_Facility 1 8912
Protoss_Robotics_Support_Bay 1 9521
Protoss_Shuttle 1 10262
Protoss_Reaver 1 11781
12835
