Protoss_Gateway 2 9557
Protoss_Assimilator 1 4442
Protoss_Cybernetics_Core 1 5822
Protoss_Dragoon 2 8330
Protoss_Citadel_of_Adun 1 7689
Protoss_Templar_Archives 1 9189
Protoss_Dark_Templar 4 11871
Protoss_Nexus 1 13957
13957
