Protoss_Gateway 1 4258
Protoss_Zealot 3 7027
Protoss_Assimilator 1 5456
Protoss_Cybernetics_Core 1 6980
Protoss_Dragoon 4 12107
Protoss_Robotics_Facility 1 9446
Protoss_Shuttle 1 10965
Protoss_Robotics_Support_Bay 1 10545
Protoss_Reaver 1 12600
12600
