Protoss_Gateway 3 12178
Protoss_Assimilator 1 4135
Protoss_Cybernetics_Core 1 5622
Protoss_Dragoon 5 12112
Protoss_Nexus 1 11018
Protoss_Robotics_Facility 1 11021
Singularity_Charge 1 9599
Protoss_Observatory 1 12017
12178
