Protoss_Gateway 2 10631
Protoss_Assimilator 1 4649
Protoss_Cybernetics_Core 1 5853
Protoss_Zealot 1 5800
Protoss_Dragoon 5 11940
Protoss_Robotics_Facility 1 10094
Singularity_Charge 1 9991
Protoss_Observatory 1 11237
Protoss_Observer 1 12251
12251
