Protoss_Gateway 3 12353
Protoss_Assimilator 1 4192
Protoss_Cybernetics_Core 1 5929
Protoss_Zealot 1 5771
Protoss_Dragoon 6 11875
Protoss_Robotics_Facility 1 10525
Singularity_Charge 1 9847
Protoss_Observatory 1 11466
12353
