Protoss_Zealot 20 955
Protoss_Gateway 2 12482
Protoss_Assimilator 1 4564
Protoss_Cybernetics_Core 1 5999
Protoss_Dragoon 5 11738
Protoss_Robotics_Facility 1 10690
Singularity_Charge 1 10106
12482
