Protoss_Gateway 2 8033
Protoss_Assimilator 1 4376
Protoss_Cybernetics_Core 1 5900
Protoss_Dragoon 6 10822
Protoss_Citadel_of_Adun 1 10305
Singularity_Charge 1 9682
Protoss_Templar_Archives 1 11809
Protoss_Zealot 2 11944
11944
