Protoss_Gateway 2 10452
Protoss_Assimilator 1 4515
Protoss_Cybernetics_Core 1 5996
Protoss_Dragoon 6 11867
Protoss_Robotics_Facility 1 10009
Singularity_Charge 1 10231
Protoss_Observatory 1 11082
Protoss_Observer 1 12169
12169
