Protoss_Gateway 1 4351
Protoss_Assimilator 1 4337
Protoss_Cybernetics_Core 1 5838
Protoss_Robotics_Facility 1 8029
Protoss_Dragoon 2 12292
Protoss_Shuttle 1 9450
Protoss_Robotics_Support_Bay 1 9079
Protoss_Reaver 2 12547
12547
