Protoss_Gateway 2 10024
Protoss_Assimilator 1 4496
Protoss_Cybernetics_Core 1 6135
Protoss_Dragoon 6 11741
Protoss_Citadel_of_Adun 1 9908
Protoss_Templar_Archives 1 11433
Singularity_Charge 1 10099
11741
