Protoss_Gateway 2 10349
Protoss_Assimilator 1 4337
Protoss_Cybernetics_Core 1 5588
Protoss_Dragoon 6 12019
Protoss_Nexus 1 10922
Singularity_Charge 1 9531
Protoss_Robotics_Facility 1 12005
12019
