Protoss_Gateway 2 11923
Protoss_Assimilator 1 4412
Protoss_Cybernetics_Core 1 5677
Protoss_Dragoon 5 11445
Protoss_Nexus 1 11987
Singularity_Charge 1 9745
Protoss_Robotics_Facility 1 12922
12922
