Protoss_Gateway 2 12784
Protoss_Assimilator 2 4647
Protoss_Cybernetics_Core 1 6116
Protoss_Dragoon 4 11676
Protoss_Nexus 1 13056
Singularity_Charge 1 10544
Protoss_Robotics_Facility 1 12873
13056
