Protoss_Gateway 1 4185
Protoss_Assimilator 1 4416
Protoss_Cybernetics_Core 1 5841
Protoss_Dragoon 3 12069
Protoss_Robotics_Facility 1 8768
Protoss_Shuttle 1 10176
Protoss_Robotics_Support_Bay 1 9660
Protoss_Nexus 1 12859
Protoss_Reaver 1 12021
Protoss_Observatory 1 11458
12859
