Protoss_Gateway 2 8417
Protoss_Assimilator 1 4864
Protoss_Cybernetics_Core 1 6219
Protoss_Dragoon 7 12358
Protoss_Citadel_of_Adun 1 10212
Singularity_Charge 1 10180
Protoss_Templar_Archives 1 11712
12358
