Protoss_Gateway 2 11247
Protoss_Assimilator 1 4556
Protoss_Cybernetics_Core 1 6106
Protoss_Dragoon 5 12512
Protoss_Nexus 1 12281
Singularity_Charge 1 9814
Protoss_Robotics_Facility 1 12630
12630
