Protoss_Gateway 2 12309
Protoss_Assimilator 1 4363
Protoss_Zealot 3 7069
Protoss_Cybernetics_Core 1 8253
Protoss_Dragoon 3 12139
Protoss_Robotics_Facility 1 10725
Protoss_Citadel_of_Adun 1 10689
Protoss_Templar_Archives 1 12168
Protoss_Shuttle 1 12326
12326
