Protoss_Gateway 1 4207
Protoss_Assimilator 1 4445
Protoss_Cybernetics_Core 1 5856
Protoss_Dragoon 4 10754
Protoss_Robotics_Facility 1 10024
Singularity_Charge 1 9979
Protoss_Shuttle 1 11554
Protoss_Robotics_Support_Bay 1 11062
Protoss_Zealot 1 11680
11680
