Protoss_Gateway 2 7157
Protoss_Assimilator 1 4495
Protoss_Cybernetics_Core 1 5736
Protoss_Dragoon 3 9420
Protoss_Zealot 2 9725
Protoss_Citadel_of_Adun 1 9049
Protoss_Templar_Archives 1 10562
Protoss_Dark_Templar 2 11811
Singularity_Charge 1 10652
11811
