Protoss_Nexus 1 6739
Protoss_Gateway 3 12080
Protoss_Assimilator 2 11468
Protoss_Cybernetics_Core 1 7414
Protoss_Zealot 1 7571
Protoss_Dragoon 5 12379
Protoss_Robotics_Facility 1 12014
12379
