Protoss_Nexus 1 7774
Protoss_Assimilator 1 6314
Protoss_Gateway 3 12292
Protoss_Cybernetics_Core 1 8693
Protoss_Zealot 3 11710
Protoss_Dragoon 3 11553
Protoss_Citadel_of_Adun 1 10968
Protoss_Templar_Archives 1 12710
12710
