Protoss_Gateway 2 6302
Protoss_Assimilator 1 4179
Protoss_Cybernetics_Core 1 5575
Protoss_Dragoon 7 12010
Singularity_Charge 1 9619
Protoss_Nexus 1 12608
Protoss_Robotics_Facility 1 12499
12608
