Protoss_Gateway 1 4088
Protoss_Assimilator 1 4196
Protoss_Cybernetics_Core 1 5572
Protoss_Dragoon 5 12051
Protoss_Nexus 1 12567
Singularity_Charge 1 9841
Protoss_Robotics_Facility 1 12165
12567
