Protoss_Gateway 2 10024
Protoss_Assimilator 1 4381
Protoss_Cybernetics_Core 1 5822
Protoss_Dragoon 5 12221
Protoss_Robotics_Facility 1 9923
Singularity_Charge 1 9780
Protoss_Observatory 1 10626
Protoss_Nexus 1 13423
Protoss_Observer 1 11724
13423
