Protoss_Gateway 2 8273
Protoss_Assimilator 1 4488
Protoss_Zealot 3 7138
Protoss_Cybernetics_Core 1 7056
Protoss_Dragoon 3 10280
Protoss_Nexus 2 14074
Singularity_Charge 1 11000
14074
