Protoss_Gateway 1 4180
Protoss_Assimilator 1 4199
Protoss_Cybernetics_Core 1 5721
Protoss_Dragoon 4 10497
Protoss_Robotics_Facility 1 9613
Singularity_Charge 1 9575
Protoss_Shuttle 1 11396
Protoss_Robotics_Support_Bay 1 10797
Protoss_Zealot 2 12239
12239
