Protoss_Gateway 2 10524
Protoss_Assimilator 2 6030
Protoss_Zealot 2 6231
Protoss_Cybernetics_Core 1 7619
Protoss_Dragoon 5 12244
Protoss_Nexus 1 10888
Protoss_Citadel_of_Adun 1 11745
12244
