Protoss_Gateway 2 11521
Protoss_Assimilator 1 4486
Protoss_Cybernetics_Core 1 5999
Protoss_Dragoon 3 10959
Protoss_Nexus 1 11510
Protoss_Robotics_Facility 1 11107
Singularity_Charge 1 9880
Protoss_Observatory 1 11994
11994
