Protoss_Gateway 2 8360
Protoss_Assimilator 1 4548
Protoss_Cybernetics_Core 1 6026
Protoss_Dragoon 3 9689
Protoss_Citadel_of_Adun 1 9336
Protoss_Robotics_Facility 1 10825
Protoss_Templar_Archives 1 10799
Protoss_Nexus 1 13032
Protoss_Dark_Templar 2 12007
Protoss_Shuttle 1 12444
13032
