Protoss_Gateway 2 10381
Protoss_Assimilator 1 4673
Protoss_Zealot 1 5288
Protoss_Cybernetics_Core 1 6866
Protoss_Dragoon 4 12200
Protoss_Nexus 1 11418
Protoss_Robotics_Facility 1 12071
Singularity_Charge 1 11071
12200
