Protoss_Nexus 1 6690
Protoss_Gateway 2 8412
Protoss_Assimilator 2 11522
Protoss_Cybernetics_Core 1 7401
Protoss_Dragoon 3 10400
Protoss_Citadel_of_Adun 2 10136
Protoss_Zealot 2 11262
Protoss_Templar_Archives 1 11838
11838
