Protoss_Gateway 2 10065
Protoss_Assimilator 1 4220
Protoss_Cybernetics_Core 1 5604
Protoss_Dragoon 6 11644
Protoss_Robotics_Facility 1 9749
Singularity_Charge 1 9724
Protoss_Observatory 1 10550
Protoss_Observer 1 11712
11712
