Protoss_Gateway 2 10445
Protoss_Assimilator 1 4154
Protoss_Cybernetics_Core 1 5813
Protoss_Dragoon 5 11937
Protoss_Robotics_Facility 1 9087
Protoss_Shuttle 1 10820
Singularity_Charge 1 9587
Protoss_Observatory 1 10462
Protoss_Robotics_Support_Bay 1 11278
Protoss_Observer 1 11663
11937
