Protoss_Nexus 1 6965
Protoss_Gateway 2 7066
Protoss_Assimilator 1 5923
Protoss_Cybernetics_Core 1 7852
Protoss_Zealot 1 7858
Protoss_Dragoon 6 12314
Protoss_Robotics_Facility 1 12627
12627
