Protoss_Gateway 2 10413
Protoss_Assimilator 1 4413
Protoss_Zealot 2 6077
Protoss_Cybernetics_Core 1 7092
Protoss_Dragoon 4 11659
Protoss_Robotics_Facility 1 9238
Protoss_Observatory 1 10027
Protoss_Observer 2 11920
11920
