Protoss_Gateway 1 4100
Protoss_Assimilator 1 4394
Protoss_Zealot 1 5069
Protoss_Cybernetics_Core 1 6213
Protoss_Dragoon 4 11635
Protoss_Robotics_Facility 1 10052
Singularity_Charge 1 9935
Protoss_Nexus 1 12830
Protoss_Shuttle 1 12213
Protoss_Robotics_Support_Bay 1 11975
12830
