Protoss_Forge 1 4426
Protoss_Photon_Cannon 4 12333
Protoss_Gateway 1 8559
Protoss_Assimilator 1 8432
Protoss_Cybernetics_Core 1 10084
Protoss_Nexus 1 12450
Protoss_Zealot 1 10671
Protoss_Citadel_of_Adun 1 12168
Protoss_Dragoon 1 12007
12450
