Protoss_Assimilator 3 9915
Protoss_Gateway 1 4934
Protoss_Zealot 5 11935
Protoss_Nexus 1 9365
Protoss_Cybernetics_Core 1 9623
Protoss_Dragoon 1 10828
Protoss_Citadel_of_Adun 1 12229
12229
