Protoss_Gateway 1 4812
Protoss_Assimilator 1 4752
Protoss_Cybernetics_Core 1 6263
Protoss_Dragoon 4 11990
Protoss_Nexus 1 11715
Protoss_Citadel_of_Adun 1 10723
Singularity_Charge 1 10269
Protoss_Templar_Archives 1 12242
12242
