Protoss_Assimilator 2 7297
Protoss_Gateway 2 10130
Protoss_Zealot 2 7755
Protoss_Nexus 1 8951
Protoss_Cybernetics_Core 1 8939
Protoss_Dragoon 3 12101
Protoss_Shield_Battery 1 11041
12101
