Protoss_Gateway 2 8420
Protoss_Nexus 1 7853
Protoss_Assimilator 2 10956
Protoss_Cybernetics_Core 1 7632
Protoss_Zealot 1 8367
Protoss_Dragoon 5 12089
Protoss_Robotics_Facility 1 12150
12150
