Protoss_Gateway 1 4152
Protoss_Assimilator 1 4251
Protoss_Cybernetics_Core 1 5808
Protoss_Dragoon 5 12391
Protoss_Robotics_Facility 1 10017
Protoss_Observatory 1 10750
Singularity_Charge 1 10081
Protoss_Nexus 1 13562
Protoss_Observer 1 11797
13562
