Protoss_Gateway 2 10928
Protoss_Assimilator 1 4447
Protoss_Cybernetics_Core 1 5841
Protoss_Dragoon 6 12440
Protoss_Robotics_Facility 1 10314
Singularity_Charge 1 9880
Protoss_Shuttle 1 11809
Protoss_Observatory 1 11621
12440
