Protoss_Gateway 2 12166
Protoss_Assimilator 1 4110
Protoss_Cybernetics_Core 1 5547
Protoss_Dragoon 6 12317
Protoss_Nexus 1 12419
Singularity_Charge 1 9701
Protoss_Robotics_Facility 1 12026
12419
