Protoss_Assimilator 1 3487
Protoss_Gateway 2 12087
Protoss_Cybernetics_Core 1 6245
Protoss_Dragoon 5 12563
Protoss_Nexus 1 11408
Protoss_Citadel_of_Adun 1 10678
Singularity_Charge 1 9944
Protoss_Robotics_Facility 1 12207
Protoss_Templar_Archives 1 12432
12563
