Protoss_Gateway 1 4180
Protoss_Assimilator 1 4217
Protoss_Cybernetics_Core 1 5666
Protoss_Dragoon 4 12221
Protoss_Nexus 2 12472
Singularity_Charge 1 9748
Protoss_Robotics_Facility 1 12042
12472
