Protoss_Gateway 2 12078
Protoss_Assimilator 1 4354
Protoss_Cybernetics_Core 1 5825
Protoss_Zealot 1 5692
Protoss_Citadel_of_Adun 1 7725
Protoss_Dragoon 2 12563
Protoss_Templar_Archives 1 9169
Protoss_Dark_Templar 2 11463
Protoss_Nexus 1 12830
Protoss_Robotics_Facility 1 12939
12939
