Protoss_Gateway 2 6389
Protoss_Assimilator 1 4234
Protoss_Cybernetics_Core 1 5685
Protoss_Dragoon 6 12098
Protoss_Nexus 1 12000
Singularity_Charge 1 9350
Protoss_Citadel_of_Adun 1 10984
Protoss_Robotics_Facility 1 12177
Protoss_Templar_Archives 1 12737
12737
