Protoss_Gateway 2 9298
Protoss_Assimilator 1 4271
Protoss_Cybernetics_Core 1 5717
Protoss_Dragoon 4 10725
Protoss_Robotics_Facility 1 9089
Protoss_Observatory 1 9814
Singularity_Charge 1 9868
Protoss_Observer 2 12122
Protoss_Nexus 1 13720
13720
