Protoss_Gateway 2 9822
Protoss_Assimilator 1 4151
Protoss_Cybernetics_Core 1 5903
Protoss_Dragoon 4 11032
Protoss_Nexus 1 10805
Protoss_Citadel_of_Adun 1 10729
Singularity_Charge 1 10190
Protoss_Zealot 2 11894
Protoss_Templar_Archives 1 12552
12552
