Protoss_Gateway 2 11294
Protoss_Assimilator 1 4347
Protoss_Cybernetics_Core 1 5592
Protoss_Dragoon 5 12019
Protoss_Nexus 1 11007
Singularity_Charge 1 9745
Protoss_Robotics_Facility 1 12368
12368
