Protoss_Gateway 1 4253
Protoss_Assimilator 1 4473
Protoss_Cybernetics_Core 1 5904
Protoss_Dragoon 3 9549
Protoss_Robotics_Facility 1 9783
Protoss_Zealot 2 10916
Protoss_Shuttle 1 11183
Protoss_Robotics_Support_Bay 1 10520
Singularity_Charge 1 9844
Protoss_Reaver 1 12741
12741
