Protoss_Gateway 2 10158
Protoss_Assimilator 1 4515
Protoss_Cybernetics_Core 1 5942
Protoss_Dragoon 6 11875
Protoss_Robotics_Facility 1 9907
Protoss_Shuttle 1 11396
Protoss_Observatory 1 10876
Singularity_Charge 1 10237
11875
