Protoss_Gateway 2 12390
Protoss_Assimilator 1 4469
Protoss_Cybernetics_Core 1 5907
Protoss_Dragoon 5 11609
Protoss_Nexus 1 11657
Singularity_Charge 1 9868
Protoss_Robotics_Facility 1 12089
12390
