Protoss_Gateway 2 8429
Protoss_Assimilator 1 4217
Protoss_Cybernetics_Core 1 5843
Protoss_Citadel_of_Adun 1 7334
Protoss_Dragoon 2 8392
Protoss_Templar_Archives 1 8951
Protoss_Dark_Templar 4 11653
Protoss_Nexus 1 13913
13913
