Protoss_Gateway 1 4316
Protoss_Assimilator 1 4773
Protoss_Zealot 2 11683
Protoss_Cybernetics_Core 1 7319
Protoss_Dragoon 3 10719
Protoss_Robotics_Facility 1 9945
Protoss_Shuttle 1 11388
Protoss_Robotics_Support_Bay 1 10822
Singularity_Charge 1 10992
Protoss_Reaver 1 12946
12946
