Protoss_Gateway 1 4264
Protoss_Assimilator 1 4452
Protoss_Zealot 1 5221
Protoss_Cybernetics_Core 1 6899
Protoss_Dragoon 3 12370
Protoss_Citadel_of_Adun 1 8458
Protoss_Templar_Archives 1 9908
Protoss_Nexus 1 12069
Protoss_Dark_Templar 1 11103
Protoss_Robotics_Facility 1 12699
12699
