Protoss_Gateway 1 4085
Protoss_Assimilator 1 4416
Protoss_Cybernetics_Core 1 5831
Protoss_Dragoon 5 11878
Protoss_Robotics_Facility 1 9813
Protoss_Observatory 1 10526
Singularity_Charge 1 9967
Protoss_Nexus 1 13306
Protoss_Observer 1 11560
Protoss_Robotics_Support_Bay 1 11701
13306
