Protoss_Gateway 2 6465
Protoss_Assimilator 1 4253
Protoss_Cybernetics_Core 1 5654
Protoss_Zealot 1 6251
Protoss_Dragoon 4 8949
Protoss_Nexus 1 12230
Protoss_Robotics_Facility 1 11814
12230
