Protoss_Gateway 1 4169
Protoss_Assimilator 1 4215
Protoss_Cybernetics_Core 1 5786
Protoss_Dragoon 4 10667
Protoss_Robotics_Facility 1 9620
Protoss_Observatory 1 10393
Singularity_Charge 1 9856
Protoss_Nexus 1 14048
Protoss_Observer 1 12187
14048
