Protoss_Gateway 1 4103
Protoss_Assimilator 1 4373
Protoss_Cybernetics_Core 1 5791
Protoss_Dragoon 5 11387
Protoss_Robotics_Facility 1 10024
Singularity_Charge 1 9815
Protoss_Observatory 1 10904
Protoss_Robotics_Support_Bay 1 11068
Protoss_Observer 1 11955
Protoss_Nexus 1 14187
14187
