Protoss_Gateway 2 5227
Protoss_Zealot 5 7246
Protoss_Assimilator 1 6604
Protoss_Cybernetics_Core 1 8241
Protoss_Dragoon 4 10626
Protoss_Robotics_Facility 1 11828
Protoss_Nexus 1 13977
13977
