Protoss_Gateway 1 4103
Protoss_Assimilator 1 4353
Protoss_Cybernetics_Core 1 5714
Protoss_Dragoon 4 10324
Protoss_Robotics_Facility 1 9708
Protoss_Observatory 1 10400
Singularity_Charge 1 9727
Protoss_Nexus 1 13028
Protoss_Observer 1 11417
Protoss_Robotics_Support_Bay 1 11354
Protoss_Shuttle 1 12775
13028
