Protoss_Gateway 2 10416
Protoss_Assimilator 1 4496
Protoss_Cybernetics_Core 1 5829
Protoss_Dragoon 6 12118
Protoss_Robotics_Facility 1 10118
Singularity_Charge 1 10038
Protoss_Observatory 1 10908
Protoss_Nexus 1 13353
Protoss_Observer 1 12058
13353
