Protoss_Nexus 1 6621
Protoss_Gateway 2 8508
Protoss_Assimilator 1 5748
Protoss_Cybernetics_Core 1 7392
Protoss_Zealot 1 7498
Protoss_Dragoon 6 12224
Protoss_Citadel_of_Adun 1 11686
12224
