Protoss_Gateway 2 8554
Protoss_Assimilator 1 4208
Protoss_Cybernetics_Core 1 5688
Protoss_Dragoon 6 11398
Protoss_Robotics_Facility 1 8268
Protoss_Observatory 1 9881
Protoss_Observer 1 10949
Protoss_Shuttle 1 12307
Singularity_Charge 1 11091
12307
