Protoss_Gateway 2 11076
Protoss_Assimilator 1 4403
Protoss_Cybernetics_Core 1 5846
Protoss_Dragoon 6 12285
Protoss_Robotics_Facility 1 10415
Singularity_Charge 1 9900
Protoss_Shuttle 1 11818
Protoss_Observatory 1 11714
12285
