Protoss_Gateway 1 4126
Protoss_Assimilator 1 4409
Protoss_Zealot 3 12119
Protoss_Cybernetics_Core 1 6848
Protoss_Dragoon 3 10368
Protoss_Robotics_Facility 1 9695
Protoss_Shuttle 1 11112
Protoss_Robotics_Support_Bay 1 10664
Singularity_Charge 1 10594
Protoss_Reaver 1 12670
12670
