Protoss_Gateway 2 11527
Protoss_Assimilator 1 4368
Protoss_Zealot 2 6836
Protoss_Cybernetics_Core 1 7068
Protoss_Dragoon 3 10956
Protoss_Nexus 1 11220
Protoss_Citadel_of_Adun 1 10545
Protoss_Robotics_Facility 1 12594
Protoss_Templar_Archives 1 12659
12659
