Protoss_Gateway 2 12228
Protoss_Assimilator 1 4211
Protoss_Cybernetics_Core 1 5907
Protoss_Zealot 1 6172
Protoss_Dragoon 4 11580
Protoss_Citadel_of_Adun 1 9084
Protoss_Nexus 1 11992
Protoss_Robotics_Facility 1 12004
12228
