Protoss_Gateway 2 8472
Protoss_Assimilator 1 4470
Protoss_Cybernetics_Core 1 5892
Protoss_Dragoon 4 11861
Protoss_Citadel_of_Adun 1 7660
Protoss_Templar_Archives 1 9195
Protoss_Dark_Templar 2 10403
11861
