Protoss_Nexus 1 6637
Protoss_Gateway 2 7587
Protoss_Assimilator 2 11698
Protoss_Cybernetics_Core 1 7177
Protoss_Zealot 1 7390
Protoss_Dragoon 6 12212
Protoss_Robotics_Facility 2 12963
12963
