Protoss_Gateway 2 10224
Protoss_Assimilator 1 4559
Protoss_Cybernetics_Core 1 6026
Protoss_Dragoon 6 11773
Protoss_Robotics_Facility 1 10216
Singularity_Charge 1 10000
Protoss_Observatory 1 10973
Protoss_Observer 1 12190
12190
