Protoss_Gateway 1 4192
Protoss_Assimilator 1 4312
Protoss_Cybernetics_Core 1 5868
Protoss_Dragoon 6 12587
Protoss_Nexus 1 12041
Singularity_Charge 1 9742
Protoss_Robotics_Facility 1 12447
12587
