Protoss_Gateway 1 4082
Protoss_Assimilator 1 4433
Protoss_Cybernetics_Core 1 5686
Protoss_Dragoon 5 12183
Protoss_Robotics_Facility 1 9885
Singularity_Charge 1 9862
Protoss_Observatory 1 10614
Protoss_Nexus 1 13541
Protoss_Observer 1 11692
13541
