Protoss_Gateway 2 10313
Protoss_Assimilator 1 4619
Protoss_Cybernetics_Core 1 5976
Protoss_Dragoon 6 11773
Protoss_Robotics_Facility 1 10186
Singularity_Charge 1 9961
Protoss_Observatory 1 11198
Protoss_Observer 1 12280
12280
