Protoss_Gateway 1 4447
Protoss_Assimilator 1 4469
Protoss_Cybernetics_Core 1 6046
Protoss_Dragoon 5 11799
Protoss_Robotics_Facility 1 10039
Singularity_Charge 1 9856
Protoss_Shuttle 1 11452
Protoss_Robotics_Support_Bay 1 11136
Protoss_Zealot 1 11841
11841
