Protoss_Gateway 2 11945
Protoss_Assimilator 1 4311
Protoss_Cybernetics_Core 1 5699
Protoss_Dragoon 5 12136
Protoss_Nexus 1 11591
Protoss_Citadel_of_Adun 1 10275
Singularity_Charge 1 9707
Protoss_Robotics_Facility 1 11934
Protoss_Templar_Archives 1 12039
12136
