Protoss_Gateway 2 10793
Protoss_Assimilator 1 4251
Protoss_Cybernetics_Core 1 5818
Protoss_Dragoon 5 12130
Protoss_Citadel_of_Adun 1 9716
Protoss_Robotics_Facility 1 10797
Singularity_Charge 1 9490
Protoss_Templar_Archives 1 12116
12130
