Protoss_Gateway 1 4252
Protoss_Assimilator 1 4400
Protoss_Cybernetics_Core 1 6033
Protoss_Dragoon 5 12531
Protoss_Robotics_Facility 1 9894
Protoss_Shuttle 1 11376
Singularity_Charge 1 10462
Protoss_Observatory 1 11214
Protoss_Robotics_Support_Bay 1 11714
Protoss_Observer 1 12263
12531
