Protoss_Gateway 2 11167
Protoss_Assimilator 1 4211
Protoss_Zealot 2 6798
Protoss_Cybernetics_Core 1 6819
Protoss_Dragoon 4 11313
Protoss_Robotics_Facility 1 10494
Protoss_Observatory 1 11223
Protoss_Observer 1 12236
Singularity_Charge 1 11396
12236
