Protoss_Gateway 2 10966
Protoss_Assimilator 1 4035
Protoss_Cybernetics_Core 1 5625
Protoss_Dragoon 6 12508
Protoss_Nexus 1 10884
Protoss_Robotics_Facility 1 10745
Singularity_Charge 1 9575
Protoss_Observatory 1 11685
12508
