Protoss_Gateway 2 9836
Protoss_Assimilator 1 4299
Protoss_Cybernetics_Core 1 6011
Protoss_Dragoon 4 11431
Protoss_Citadel_of_Adun 1 9473
Protoss_Templar_Archives 1 10975
Protoss_Zealot 1 10630
Singularity_Charge 1 9912
Protoss_Dark_Templar 2 12531
12531
