Protoss_Gateway 1 4271
Protoss_Assimilator 1 4376
Protoss_Cybernetics_Core 1 5809
Protoss_Dragoon 5 11688
Protoss_Robotics_Facility 1 9949
Singularity_Charge 1 9607
Protoss_Nexus 1 12821
Protoss_Observatory 1 10999
Protoss_Observer 1 12043
12821
