Protoss_Nexus 1 6957
Protoss_Gateway 2 7689
Protoss_Assimilator 1 5824
Protoss_Cybernetics_Core 1 7479
Protoss_Zealot 3 12228
Protoss_Dragoon 5 11653
Protoss_Robotics_Facility 1 11501
12228
