Protoss_Gateway 1 4256
Protoss_Assimilator 1 4397
Protoss_Cybernetics_Core 1 6162
Protoss_Dragoon 5 12262
Protoss_Nexus 1 11182
Protoss_Robotics_Facility 1 11249
Singularity_Charge 1 9850
Protoss_Shuttle 1 12769
12769
