Protoss_Gateway 1 4249
Protoss_Assimilator 2 4728
Protoss_Cybernetics_Core 1 6307
Protoss_Dragoon 5 12086
Protoss_Nexus 1 12093
Singularity_Charge 1 10245
Protoss_Robotics_Facility 1 12430
12430
