Protoss_Gateway 2 12473
Protoss_Assimilator 1 4234
Protoss_Cybernetics_Core 1 5603
Protoss_Dragoon 3 9186
Protoss_Robotics_Facility 1 9513
Protoss_Citadel_of_Adun 1 10504
Protoss_Observatory 1 10277
Singularity_Charge 1 9601
Protoss_Nexus 1 13000
Protoss_Zealot 1 11273
Protoss_Observer 1 11461
Protoss_Templar_Archives 1 12705
13000
