Protoss_Gateway 1 4109
Protoss_Assimilator 1 4246
Protoss_Cybernetics_Core 1 5553
Protoss_Dragoon 5 11492
Protoss_Robotics_Facility 1 9800
Singularity_Charge 1 9490
Protoss_Nexus 1 12716
Protoss_Observatory 1 10645
Protoss_Observer 1 11657
12716
