Protoss_Gateway 2 9981
Protoss_Assimilator 1 4267
Protoss_Cybernetics_Core 1 5749
Protoss_Dragoon 6 12045
Protoss_Robotics_Facility 1 9686
Singularity_Charge 1 9642
Protoss_Observatory 1 10532
Protoss_Nexus 1 13120
Protoss_Observer 1 11873
13120
