Protoss_Gateway 2 8339
Protoss_Nexus 1 7594
Protoss_Assimilator 2 10463
Protoss_Cybernetics_Core 1 7796
Protoss_Zealot 1 8177
Protoss_Dragoon 6 12560
Protoss_Robotics_Facility 1 12730
12730
