Protoss_Assimilator 3 6972
Protoss_Gateway 1 4827
Protoss_Cybernetics_Core 1 6356
Protoss_Dragoon 5 12209
Protoss_Nexus 1 12043
Singularity_Charge 1 10365
Protoss_Robotics_Facility 1 12387
12387
