Protoss_Gateway 1 4082
Protoss_Assimilator 1 4354
Protoss_Cybernetics_Core 1 5683
Protoss_Dragoon 5 12458
Protoss_Robotics_Facility 1 9761
Protoss_Observatory 1 10459
Singularity_Charge 1 9824
Protoss_Observer 1 11595
Protoss_Nexus 1 13732
13732
