Protoss_Gateway 1 4255
Protoss_Assimilator 1 4466
Protoss_Cybernetics_Core 1 5813
Protoss_Dragoon 3 9642
Protoss_Robotics_Facility 1 9843
Singularity_Charge 1 9844
Protoss_Shuttle 1 11455
Protoss_Robotics_Support_Bay 1 10756
Protoss_Zealot 1 11666
Protoss_Reaver 1 13013
13013
