Protoss_Gateway 1 6062
Protoss_Zealot 4 11098
Protoss_Assimilator 1 10193
Protoss_Nexus 1 12709
Protoss_Forge 1 10877
Protoss_Cybernetics_Core 1 12230
Protoss_Photon_Cannon 1 12320
12709
