Protoss_Gateway 2 9810
Protoss_Assimilator 1 4182
Protoss_Cybernetics_Core 1 5734
Protoss_Dragoon 6 12165
Protoss_Robotics_Facility 1 9159
Protoss_Observatory 1 9936
Singularity_Charge 1 9511
Protoss_Observer 2 11832
12165
