Protoss_Gateway 2 8259
Protoss_Assimilator 2 12367
Protoss_Cybernetics_Core 1 6225
Protoss_Dragoon 3 10713
Protoss_Nexus 1 11059
Protoss_Robotics_Facility 1 10858
Singularity_Charge 1 9903
Protoss_Stargate 1 11785
Protoss_Observatory 1 11886
12367
