Protoss_Gateway 1 4217
Protoss_Assimilator 1 4420
Protoss_Cybernetics_Core 1 5831
Protoss_Dragoon 4 11852
Protoss_Robotics_Facility 1 8278
Protoss_Shuttle 1 9781
Protoss_Robotics_Support_Bay 1 9534
Protoss_Zealot 2 10729
Protoss_Reaver 1 11339
Protoss_Observatory 1 11843
11852
