Protoss_Gateway 1 4188
Protoss_Assimilator 1 4454
Protoss_Cybernetics_Core 1 5655
Protoss_Dragoon 5 11524
Protoss_Nexus 1 10490
Protoss_Robotics_Facility 1 10759
Protoss_Observatory 1 11764
11764
