Protoss_Gateway 2 9886
Protoss_Assimilator 1 4292
Protoss_Cybernetics_Core 1 5911
Protoss_Dragoon 6 12452
Protoss_Nexus 1 9779
Protoss_Robotics_Facility 1 11310
Protoss_Observatory 1 12007
Singularity_Charge 1 11322
12452
