Protoss_Gateway 2 8009
Protoss_Assimilator 1 4499
Protoss_Cybernetics_Core 1 5907
Protoss_Dragoon 6 12423
Protoss_Nexus 1 11829
Protoss_Robotics_Facility 1 11397
Singularity_Charge 1 9689
Protoss_Shuttle 1 12813
12813
