Protoss_Nexus 1 6660
Protoss_Gateway 2 7492
Protoss_Assimilator 1 5733
Protoss_Cybernetics_Core 1 7316
Protoss_Zealot 1 7141
Protoss_Dragoon 6 11612
Protoss_Robotics_Facility 1 11635
11635
