Protoss_Gateway 2 12631
Protoss_Assimilator 1 4198
Protoss_Cybernetics_Core 1 5431
Protoss_Dragoon 6 12490
Protoss_Robotics_Facility 1 9799
Singularity_Charge 1 9438
Protoss_Shuttle 1 11197
Protoss_Robotics_Support_Bay 1 10813
Protoss_Observatory 1 11274
Protoss_Reaver 1 12755
12755
