Protoss_Nexus 1 6906
Protoss_Gateway 2 7830
Protoss_Assimilator 2 11967
Protoss_Cybernetics_Core 1 7378
Protoss_Zealot 1 7911
Protoss_Dragoon 6 11741
Protoss_Robotics_Facility 1 11976
Singularity_Charge 1 11167
11976
