Protoss_Gateway 2 10070
Protoss_Assimilator 1 4578
Protoss_Cybernetics_Core 1 6020
Protoss_Dragoon 6 12556
Protoss_Robotics_Facility 1 8700
Protoss_Observatory 1 9509
Protoss_Observer 2 11951
Singularity_Charge 1 11138
12556
