Protoss_Gateway 2 12282
Protoss_Assimilator 1 4255
Protoss_Cybernetics_Core 1 5685
Protoss_Dragoon 5 12083
Protoss_Robotics_Facility 1 8138
Protoss_Observatory 1 9035
Protoss_Nexus 1 11812
Protoss_Observer 3 12023
12282
