Protoss_Gateway 1 4164
Protoss_Assimilator 1 4191
Protoss_Cybernetics_Core 1 5711
Protoss_Dragoon 5 11600
Protoss_Robotics_Facility 1 9942
Singularity_Charge 1 9379
Protoss_Shuttle 1 11522
Protoss_Robotics_Support_Bay 1 10964
Protoss_Nexus 1 13957
13957
