Protoss_Nexus 1 6915
Protoss_Gateway 2 9475
Protoss_Assimilator 2 10622
Protoss_Zealot 2 8420
Protoss_Cybernetics_Core 1 8409
Protoss_Dragoon 3 11065
Protoss_Forge 1 11832
Protoss_Robotics_Facility 1 13137
13137
