Protoss_Gateway 2 8311
Protoss_Assimilator 1 4498
Protoss_Cybernetics_Core 1 5808
Protoss_Dragoon 6 12001
Singularity_Charge 1 9476
Protoss_Nexus 1 12842
Protoss_Robotics_Facility 1 12196
12842
