Protoss_Gateway 1 4111
Protoss_Assimilator 1 4214
Protoss_Cybernetics_Core 1 5680
Protoss_Zealot 1 5575
Protoss_Dragoon 5 11589
Protoss_Robotics_Facility 1 11239
Singularity_Charge 1 9941
Protoss_Shuttle 1 12705
12705
