Protoss_Assimilator 1 3522
Protoss_Gateway 1 4701
Protoss_Cybernetics_Core 1 6207
Protoss_Robotics_Facility 1 8177
Protoss_Dragoon 4 11224
Protoss_Shuttle 1 9582
Protoss_Robotics_Support_Bay 1 10894
Protoss_Forge 1 11279
Protoss_Photon_Cannon 1 12573
12573
