Protoss_Forge 1 4088
Protoss_Photon_Cannon 4 8606
Protoss_Gateway 2 11205
Protoss_Assimilator 1 8252
Protoss_Cybernetics_Core 1 9504
Protoss_Zealot 1 9128
Protoss_Dragoon 2 11808
11808
