Protoss_Gateway 1 4177
Protoss_Assimilator 1 4240
Protoss_Cybernetics_Core 1 6061
Protoss_Dragoon 5 11697
Protoss_Nexus 1 11642
Singularity_Charge 1 9768
Protoss_Robotics_Facility 1 12399
12399
