Protoss_Gateway 1 4264
Protoss_Assimilator 1 4400
Protoss_Cybernetics_Core 1 5784
Protoss_Zealot 2 11631
Protoss_Dragoon 4 10599
Protoss_Robotics_Facility 1 10107
Singularity_Charge 1 9704
Protoss_Shuttle 1 11502
Protoss_Robotics_Support_Bay 1 11183
Protoss_Reaver 1 13060
13060
