Protoss_Gateway 1 4287
Protoss_Assimilator 1 4542
Protoss_Zealot 2 6137
Protoss_Cybernetics_Core 1 6254
Protoss_Dragoon 4 11196
Protoss_Robotics_Facility 1 10333
Singularity_Charge 1 10166
Protoss_Observatory 1 11030
Protoss_Nexus 1 13697
Protoss_Observer 1 12052
13697
