Protoss_Gateway 2 10569
Protoss_Assimilator 1 4395
Protoss_Cybernetics_Core 1 5796
Protoss_Dragoon 3 9224
Protoss_Citadel_of_Adun 1 9245
Protoss_Robotics_Facility 1 9818
Protoss_Templar_Archives 1 10786
Protoss_Shuttle 1 11241
Protoss_Dark_Templar 2 12033
12033
