Protoss_Gateway 1 4171
Protoss_Assimilator 1 4505
Protoss_Cybernetics_Core 1 5894
Protoss_Dragoon 5 12218
Protoss_Robotics_Facility 1 10289
Protoss_Nexus 1 12947
Singularity_Charge 1 10117
Protoss_Shuttle 1 12020
Protoss_Robotics_Support_Bay 1 11994
12947
