Protoss_Gateway 2 11911
Protoss_Assimilator 1 4131
Protoss_Zealot 2 6368
Protoss_Cybernetics_Core 1 6747
Protoss_Dragoon 5 12458
Protoss_Nexus 1 12254
Protoss_Robotics_Facility 1 11837
Singularity_Charge 1 10875
12458
