Protoss_Gateway 2 12787
Protoss_Assimilator 1 4416
Protoss_Cybernetics_Core 1 5832
Protoss_Zealot 1 5897
Protoss_Dragoon 5 12069
Protoss_Robotics_Facility 1 9999
Singularity_Charge 1 9997
Protoss_Nexus 1 13347
Protoss_Observatory 1 11391
13347
