Protoss_Gateway 2 10618
Protoss_Assimilator 1 4104
Protoss_Cybernetics_Core 1 5467
Protoss_Dragoon 4 9964
Protoss_Robotics_Facility 1 9974
Singularity_Charge 1 9695
Protoss_Shuttle 1 11414
Protoss_Nexus 1 13398
Protoss_Robotics_Support_Bay 1 11423
13398
