Protoss_Gateway 2 11645
Protoss_Assimilator 1 4270
Protoss_Cybernetics_Core 1 5838
Protoss_Dragoon 4 11875
Protoss_Robotics_Facility 1 9557
Protoss_Nexus 1 12391
Singularity_Charge 1 9660
Protoss_Observatory 1 10441
Protoss_Observer 1 11651
12391
