Protoss_Nexus 1 6739
Protoss_Gateway 2 8625
Protoss_Assimilator 1 5686
Protoss_Cybernetics_Core 1 7416
Protoss_Zealot 2 10954
Protoss_Dragoon 6 12431
Protoss_Robotics_Facility 1 11384
12431
