Protoss_Gateway 2 10335
Protoss_Assimilator 1 4431
Protoss_Cybernetics_Core 1 5829
Protoss_Zealot 1 5566
Protoss_Dragoon 6 11758
Protoss_Robotics_Facility 1 9844
Protoss_Observatory 1 10608
Singularity_Charge 1 9947
Protoss_Observer 1 11999
11999
