Protoss_Gateway 3 10190
Protoss_Assimilator 1 4360
Protoss_Cybernetics_Core 1 5569
Protoss_Zealot 2 10018
Protoss_Dragoon 3 8934
Protoss_Citadel_of_Adun 1 8269
Protoss_Templar_Archives 1 9719
Protoss_Dark_Templar 5 12399
12399
