Protoss_Nexus 1 7503
Protoss_Gateway 2 8429
Protoss_Assimilator 1 5998
Protoss_Cybernetics_Core 1 7842
Protoss_Zealot 1 7466
Protoss_Dragoon 5 12358
Protoss_Robotics_Facility 1 10690
Protoss_Observatory 1 11514
12358
