Protoss_Gateway 2 9538
Protoss_Assimilator 1 4409
Protoss_Cybernetics_Core 1 5869
Protoss_Dragoon 7 12591
Protoss_Robotics_Facility 1 9862
Singularity_Charge 1 9859
Protoss_Observatory 1 10831
Protoss_Observer 1 11853
12591
