Protoss_Gateway 2 12077
Protoss_Assimilator 1 4331
Protoss_Cybernetics_Core 1 5617
Protoss_Dragoon 4 11349
Protoss_Zealot 1 7676
Protoss_Robotics_Facility 1 9398
Protoss_Observatory 1 10236
Singularity_Charge 1 9584
Protoss_Nexus 1 12835
Protoss_Observer 2 12128
12835
