Protoss_Gateway 1 4065
Protoss_Assimilator 1 4152
Protoss_Cybernetics_Core 1 5607
Protoss_Dragoon 4 10910
Protoss_Robotics_Facility 1 8069
Protoss_Shuttle 1 9497
Protoss_Robotics_Support_Bay 1 9503
Protoss_Reaver 2 12770
12770
