Protoss_Gateway 1 4057
Protoss_Zealot 2 6643
Protoss_Assimilator 1 5521
Protoss_Cybernetics_Core 1 6664
Protoss_Dragoon 4 11823
Protoss_Nexus 1 10872
Protoss_Robotics_Facility 1 10945
Protoss_Shuttle 1 12394
Protoss_Robotics_Support_Bay 1 12092
12394
