Protoss_Gateway 1 4252
Protoss_Assimilator 1 4495
Protoss_Cybernetics_Core 1 5865
Protoss_Zealot 1 5669
Protoss_Dragoon 5 11671
Protoss_Nexus 1 11918
Protoss_Robotics_Facility 1 12152
Singularity_Charge 1 10380
12152
