Protoss_Gateway 2 9506
Protoss_Assimilator 1 5944
Protoss_Forge 1 7201
Protoss_Cybernetics_Core 1 7960
Protoss_Dragoon 3 11214
Protoss_Nexus 1 11700
Protoss_Citadel_of_Adun 1 11955
Protoss_Robotics_Facility 1 13005
13005
