Protoss_Assimilator 2 5190
Protoss_Gateway 2 8920
Protoss_Cybernetics_Core 1 6876
Protoss_Dragoon 4 10310
Protoss_Nexus 1 13031
Singularity_Charge 1 10661
Protoss_Robotics_Facility 1 12979
13031
