Protoss_Gateway 2 9286
Protoss_Assimilator 1 4422
Protoss_Cybernetics_Core 1 5856
Protoss_Zealot 1 5619
Protoss_Dragoon 6 12013
Protoss_Robotics_Facility 1 11015
Singularity_Charge 1 10286
Protoss_Observatory 1 11991
12013
