Protoss_Gateway 2 12535
Protoss_Assimilator 1 4442
Protoss_Cybernetics_Core 1 5870
Protoss_Dragoon 5 12171
Protoss_Robotics_Facility 1 8417
Protoss_Observatory 1 9478
Protoss_Shuttle 1 10632
Protoss_Observer 2 12356
12535
