Protoss_Gateway 1 4065
Protoss_Assimilator 1 4204
Protoss_Cybernetics_Core 1 5616
Protoss_Dragoon 4 10503
Protoss_Robotics_Facility 1 9886
Singularity_Charge 1 9806
Protoss_Shuttle 1 11297
Protoss_Robotics_Support_Bay 1 10943
Protoss_Reaver 1 12855
12855
