Protoss_Gateway 2 10016
Protoss_Assimilator 1 4331
Protoss_Cybernetics_Core 1 5813
Protoss_Dragoon 7 12575
Protoss_Robotics_Facility 1 9680
Singularity_Charge 1 9721
Protoss_Observatory 1 10883
Protoss_Nexus 1 13455
Protoss_Observer 1 12043
13455
