Protoss_Gateway 1 4217
Protoss_Assimilator 1 4245
Protoss_Cybernetics_Core 1 5698
Protoss_Dragoon 5 11747
Protoss_Robotics_Facility 1 10049
Singularity_Charge 1 9932
Protoss_Shuttle 1 11449
Protoss_Robotics_Support_Bay 1 11122
Protoss_Reaver 1 13007
13007
