Protoss_Gateway 2 12058
Protoss_Assimilator 1 4609
Protoss_Cybernetics_Core 1 6192
Protoss_Zealot 1 6163
Protoss_Dragoon 4 12221
Protoss_Nexus 1 11738
Protoss_Robotics_Facility 1 11831
Singularity_Charge 1 10155
12221
