Protoss_Gateway 2 12583
Protoss_Assimilator 1 4300
Protoss_Cybernetics_Core 1 5825
Protoss_Dragoon 5 11562
Protoss_Nexus 1 11607
Singularity_Charge 1 9821
Protoss_Robotics_Facility 1 12093
12583
