Protoss_Gateway 2 11998
Protoss_Assimilator 1 4390
Protoss_Cybernetics_Core 1 5784
Protoss_Dragoon 5 12121
Protoss_Robotics_Facility 1 10047
Singularity_Charge 1 9862
Protoss_Nexus 1 12946
Protoss_Observatory 1 10899
Protoss_Observer 1 11985
12946
