Protoss_Gateway 2 8156
Protoss_Assimilator 1 4357
Protoss_Cybernetics_Core 1 5800
Protoss_Zealot 1 5534
Protoss_Dragoon 4 12069
Protoss_Nexus 1 11981
Protoss_Robotics_Facility 1 11435
Singularity_Charge 1 9730
12069
