Protoss_Gateway 3 12507
Protoss_Assimilator 1 4319
Protoss_Cybernetics_Core 1 5876
Protoss_Dragoon 4 12525
Protoss_Robotics_Facility 1 8363
Protoss_Observatory 1 9146
Protoss_Nexus 1 11560
Protoss_Observer 2 11212
12525
