Protoss_Nexus 1 6874
Protoss_Gateway 2 7659
Protoss_Assimilator 1 5840
Protoss_Cybernetics_Core 1 7539
Protoss_Zealot 1 7744
Protoss_Dragoon 6 12057
Protoss_Robotics_Facility 1 12262
12262
