Protoss_Gateway 1 4188
Protoss_Assimilator 1 4448
Protoss_Cybernetics_Core 1 5859
Protoss_Dragoon 3 10743
Protoss_Robotics_Facility 1 9496
Protoss_Shuttle 1 11229
Protoss_Robotics_Support_Bay 1 10724
Singularity_Charge 1 10711
Protoss_Reaver 1 12787
12787
