Protoss_Gateway 1 4171
Protoss_Assimilator 1 4202
Protoss_Cybernetics_Core 1 5661
Protoss_Dragoon 4 10365
Protoss_Nexus 1 11513
Singularity_Charge 1 9689
Protoss_Robotics_Facility 1 11900
11900
