Protoss_Gateway 2 7653
Protoss_Nexus 1 7833
Protoss_Assimilator 1 6119
Protoss_Cybernetics_Core 1 7177
Protoss_Zealot 1 7458
Protoss_Dragoon 6 12468
Protoss_Robotics_Facility 1 12683
12683
