Protoss_Gateway 2 12131
Protoss_Assimilator 1 4311
Protoss_Cybernetics_Core 1 5669
Protoss_Zealot 1 5543
Protoss_Dragoon 5 11466
Protoss_Nexus 1 11894
Singularity_Charge 1 9724
Protoss_Robotics_Facility 1 11910
12131
