Protoss_Gateway 2 10916
Protoss_Assimilator 1 4180
Protoss_Cybernetics_Core 1 5578
Protoss_Dragoon 4 11796
Protoss_Nexus 1 11138
Protoss_Robotics_Facility 1 10816
Singularity_Charge 1 9736
Protoss_Shuttle 1 12473
12473
