Protoss_Gateway 2 9153
Protoss_Assimilator 1 4597
Protoss_Cybernetics_Core 1 6007
Protoss_Dragoon 5 11123
Protoss_Robotics_Facility 1 10630
Singularity_Charge 1 9935
Protoss_Zealot 2 11985
Protoss_Shuttle 1 12228
Protoss_Observatory 1 11987
12228
