Protoss_Gateway 2 4293
Protoss_Assimilator 1 4302
Protoss_Cybernetics_Core 1 5999
Protoss_Dragoon 5 12074
Protoss_Robotics_Facility 1 10097
Singularity_Charge 1 9944
Protoss_Observatory 1 10860
Protoss_Nexus 1 13348
Protoss_Observer 1 11964
13348
