Protoss_Gateway 2 9050
Protoss_Assimilator 1 4534
Protoss_Cybernetics_Core 1 5853
Protoss_Dragoon 6 12351
Protoss_Citadel_of_Adun 1 10433
Singularity_Charge 1 10070
Protoss_Templar_Archives 1 12094
12351
