Protoss_Gateway 1 4183
Protoss_Assimilator 1 4154
Protoss_Cybernetics_Core 1 5630
Protoss_Zealot 2 11639
Protoss_Dragoon 4 10482
Protoss_Robotics_Facility 1 9610
Protoss_Shuttle 1 11036
Singularity_Charge 1 9669
Protoss_Robotics_Support_Bay 1 10784
Protoss_Reaver 1 12823
12823
