Protoss_Nexus 1 7243
Protoss_Gateway 2 8168
Protoss_Assimilator 1 6555
Protoss_Cybernetics_Core 1 7807
Protoss_Zealot 1 7764
Protoss_Dragoon 6 12496
Protoss_Robotics_Facility 1 12639
12639
