Protoss_Gateway 2 8996
Protoss_Assimilator 1 4697
Protoss_Cybernetics_Core 1 6210
Protoss_Zealot 1 6040
Protoss_Dragoon 5 11211
Protoss_Nexus 1 12245
Singularity_Charge 1 10456
Protoss_Robotics_Facility 1 13119
13119
