Protoss_Gateway 1 4387
Protoss_Assimilator 1 4517
Protoss_Cybernetics_Core 1 6314
Protoss_Dragoon 4 11919
Protoss_Robotics_Facility 1 8392
Protoss_Shuttle 1 9984
Protoss_Observatory 1 9451
Protoss_Observer 2 12056
12056
