Protoss_Gateway 1 4305
Protoss_Assimilator 1 4659
Protoss_Cybernetics_Core 1 6012
Protoss_Zealot 1 5783
Protoss_Dragoon 4 11237
Protoss_Robotics_Facility 1 10286
Singularity_Charge 1 10257
Protoss_Observatory 1 11125
Protoss_Nexus 1 13694
Protoss_Observer 1 12157
13694
