Protoss_Gateway 2 10867
Protoss_Assimilator 1 4272
Protoss_Cybernetics_Core 1 5543
Protoss_Dragoon 4 10049
Protoss_Robotics_Facility 1 10049
Singularity_Charge 1 9666
Protoss_Zealot 3 12105
Protoss_Shuttle 1 11516
Protoss_Observatory 1 11419
12105
