Protoss_Gateway 1 4385
Protoss_Assimilator 1 4577
Protoss_Cybernetics_Core 1 6015
Protoss_Dragoon 4 10775
Protoss_Stargate 1 9714
Protoss_Fleet_Beacon 1 11373
Singularity_Charge 1 10067
11373
