Protoss_Gateway 2 6981
Protoss_Assimilator 1 4404
Protoss_Cybernetics_Core 1 5686
Protoss_Dragoon 2 8454
Protoss_Citadel_of_Adun 1 8497
Protoss_Zealot 1 8367
Protoss_Robotics_Facility 1 10422
Protoss_Templar_Archives 1 10193
Protoss_Dark_Templar 2 11448
Protoss_Shuttle 1 11838
Protoss_Nexus 1 13708
13708
