Protoss_Nexus 1 6701
Protoss_Gateway 2 11167
Protoss_Assimilator 2 12015
Protoss_Zealot 2 8259
Protoss_Cybernetics_Core 1 7732
Protoss_Dragoon 5 12361
Protoss_Robotics_Facility 1 11651
12361
