Protoss_Nexus 1 7377
Protoss_Forge 1 5976
Protoss_Photon_Cannon 3 9537
Protoss_Gateway 1 8469
Protoss_Assimilator 2 11227
Protoss_Cybernetics_Core 1 10492
Protoss_Citadel_of_Adun 1 12267
12267
