Protoss_Gateway 2 9645
Protoss_Assimilator 1 4400
Protoss_Zealot 3 6992
Protoss_Cybernetics_Core 1 6841
Protoss_Citadel_of_Adun 1 8616
Protoss_Dragoon 5 12071
Protoss_Nexus 1 13486
Singularity_Charge 1 11033
13486
