Protoss_Nexus 1 6565
Protoss_Gateway 2 7587
Protoss_Assimilator 2 10501
Protoss_Cybernetics_Core 1 7220
Protoss_Zealot 1 7410
Protoss_Dragoon 6 12080
Protoss_Robotics_Facility 1 12424
12424
