Protoss_Gateway 2 9203
Protoss_Nexus 1 7484
Protoss_Zealot 2 7311
Protoss_Assimilator 1 6128
Protoss_Cybernetics_Core 1 7717
Protoss_Dragoon 5 11896
Protoss_Robotics_Facility 1 12155
12155
