Protoss_Gateway 2 9921
Protoss_Assimilator 1 4354
Protoss_Cybernetics_Core 1 5630
Protoss_Dragoon 3 9490
Protoss_Citadel_of_Adun 1 8625
Protoss_Templar_Archives 1 10126
Singularity_Charge 1 9830
Protoss_Dark_Templar 3 12519
Protoss_Nexus 1 13855
13855
