Protoss_Nexus 1 6824
Protoss_Gateway 2 6595
Protoss_Assimilator 2 10278
Protoss_Cybernetics_Core 1 7521
Protoss_Zealot 2 7676
Protoss_Dragoon 6 12335
Protoss_Robotics_Facility 1 12544
12544
