Protoss_Gateway 2 10988
Protoss_Assimilator 1 4258
Protoss_Zealot 2 6251
Protoss_Cybernetics_Core 1 6350
Protoss_Dragoon 6 12540
Protoss_Robotics_Facility 1 10178
Protoss_Nexus 1 13301
Protoss_Observatory 1 11709
Singularity_Charge 1 11220
13301
