Protoss_Gateway 2 10773
Protoss_Assimilator 1 4398
Protoss_Cybernetics_Core 1 5765
Protoss_Dragoon 6 11972
Protoss_Robotics_Facility 1 9728
Protoss_Observatory 1 10418
Singularity_Charge 1 9865
Protoss_Observer 2 12315
12315
