Protoss_Gateway 1 4234
Protoss_Assimilator 1 4264
Protoss_Cybernetics_Core 1 5791
Protoss_Zealot 1 5777
Protoss_Dragoon 5 12016
Protoss_Robotics_Facility 1 9829
Singularity_Charge 1 10011
Protoss_Observatory 1 10733
Protoss_Nexus 1 13298
Protoss_Observer 1 11914
13298
