Protoss_Gateway 2 7302
Protoss_Assimilator 1 4100
Protoss_Zealot 1 5092
Protoss_Cybernetics_Core 1 6770
Protoss_Dragoon 8 12493
Singularity_Charge 1 10570
Protoss_Nexus 1 13612
13612
