Protoss_Gateway 2 11970
Protoss_Assimilator 1 4556
Protoss_Cybernetics_Core 1 5907
Protoss_Zealot 1 5692
Protoss_Dragoon 4 11158
Protoss_Nexus 1 11446
Singularity_Charge 1 10032
Protoss_Citadel_of_Adun 1 11472
Protoss_Robotics_Facility 1 13125
13125
