Protoss_Gateway 2 8061
Protoss_Assimilator 1 4126
Protoss_Cybernetics_Core 1 5758
Protoss_Zealot 1 5528
Protoss_Dragoon 7 12546
Singularity_Charge 1 9449
Protoss_Nexus 1 12975
Protoss_Robotics_Facility 1 12884
12975
