Protoss_Gateway 2 10309
Protoss_Assimilator 1 4523
Protoss_Cybernetics_Core 1 6096
Protoss_Dragoon 6 12398
Protoss_Robotics_Facility 1 9955
Protoss_Observatory 1 10692
Singularity_Charge 1 10033
Protoss_Observer 1 11746
12398
