Protoss_Nexus 1 6546
Protoss_Gateway 2 7512
Protoss_Assimilator 2 10520
Protoss_Cybernetics_Core 1 7347
Protoss_Zealot 1 7387
Protoss_Dragoon 6 11937
Protoss_Robotics_Facility 1 11761
Singularity_Charge 1 11363
11937
