Protoss_Gateway 3 11677
Protoss_Assimilator 1 4220
Protoss_Cybernetics_Core 1 5619
Protoss_Dragoon 5 11902
Protoss_Nexus 1 11654
Singularity_Charge 1 9578
Protoss_Zealot 1 11543
11902
