Protoss_Gateway 1 4129
Protoss_Assimilator 1 4385
Protoss_Cybernetics_Core 1 5623
Protoss_Dragoon 5 12187
Protoss_Nexus 1 11115
Protoss_Robotics_Facility 1 11067
Singularity_Charge 1 9762
12187
