Protoss_Gateway 1 4132
Protoss_Assimilator 1 4296
Protoss_Cybernetics_Core 1 5610
Protoss_Dragoon 4 10359
Protoss_Robotics_Facility 1 9540
Protoss_Observatory 1 10234
Singularity_Charge 1 9745
Protoss_Nexus 1 12930
Protoss_Observer 1 11250
Protoss_Zealot 1 11379
Protoss_Shuttle 1 12646
12930
