Protoss_Gateway 2 8733
Protoss_Assimilator 1 4281
Protoss_Zealot 2 6646
Protoss_Cybernetics_Core 1 6397
Protoss_Dragoon 7 12592
Protoss_Robotics_Facility 1 10144
Protoss_Observatory 1 10831
Singularity_Charge 1 10125
Protoss_Observer 1 11876
12592
