Protoss_Gateway 3 8500
Protoss_Assimilator 2 6329
Protoss_Zealot 2 8118
Protoss_Cybernetics_Core 1 8235
Protoss_Dragoon 5 12566
Protoss_Nexus 1 12619
Protoss_Robotics_Facility 1 12964
12964
