Protoss_Gateway 2 11257
Protoss_Assimilator 1 4128
Protoss_Cybernetics_Core 1 5682
Protoss_Dragoon 4 11442
Protoss_Nexus 1 11100
Protoss_Robotics_Facility 1 10839
Singularity_Charge 1 9768
Protoss_Shuttle 1 12462
12462
