Protoss_Gateway 2 9804
Protoss_Assimilator 1 4164
Protoss_Cybernetics_Core 1 5481
Protoss_Dragoon 6 11302
Protoss_Robotics_Facility 1 9376
Singularity_Charge 1 9414
Protoss_Observatory 1 10238
Protoss_Observer 1 11347
Protoss_Nexus 1 14105
14105
