Protoss_Nexus 1 6617
Protoss_Gateway 2 7644
Protoss_Assimilator 2 11314
Protoss_Cybernetics_Core 1 7409
Protoss_Zealot 1 7524
Protoss_Dragoon 6 11867
Protoss_Robotics_Facility 1 11703
Singularity_Charge 1 11320
11867
