Protoss_Gateway 2 8609
Protoss_Assimilator 1 4615
Protoss_Cybernetics_Core 1 6002
Protoss_Zealot 1 5985
Protoss_Dragoon 6 12490
Singularity_Charge 1 9695
Protoss_Nexus 1 13537
13537
