Protoss_Gateway 1 4147
Protoss_Assimilator 1 4429
Protoss_Zealot 3 7214
Protoss_Cybernetics_Core 1 7009
Protoss_Dragoon 4 11911
Protoss_Robotics_Facility 1 11774
Protoss_Nexus 1 13737
Singularity_Charge 1 10901
13737
