Protoss_Gateway 1 4388
Protoss_Assimilator 1 4673
Protoss_Cybernetics_Core 1 6050
Protoss_Dragoon 4 11597
Protoss_Stargate 1 10544
Protoss_Scout 1 12458
Singularity_Charge 1 10816
Protoss_Fleet_Beacon 1 12760
12760
