Protoss_Gateway 3 11982
Protoss_Assimilator 1 4196
Protoss_Zealot 1 5136
Protoss_Cybernetics_Core 1 6438
Protoss_Dragoon 4 12203
Protoss_Robotics_Facility 1 9361
Protoss_Nexus 1 12227
Protoss_Observatory 1 10661
Singularity_Charge 1 10248
Protoss_Observer 1 11680
12227
