Protoss_Gateway 3 12696
Protoss_Assimilator 1 4106
Protoss_Cybernetics_Core 1 5661
Protoss_Dragoon 5 11682
Protoss_Robotics_Facility 1 10094
Singularity_Charge 1 9710
Protoss_Nexus 1 12827
Protoss_Observatory 1 10885
Protoss_Observer 1 11894
12827
