Protoss_Gateway 2 12509
Protoss_Assimilator 1 4191
Protoss_Cybernetics_Core 1 5663
Protoss_Zealot 1 5666
Protoss_Dragoon 5 11864
Protoss_Nexus 1 11913
Singularity_Charge 1 9733
Protoss_Robotics_Facility 1 12118
12509
