Protoss_Gateway 2 8104
Protoss_Assimilator 1 4359
Protoss_Cybernetics_Core 1 5644
Protoss_Zealot 1 5592
Protoss_Dragoon 4 11454
Protoss_Nexus 1 11681
Protoss_Robotics_Facility 1 11354
Singularity_Charge 1 9736
11681
