Protoss_Gateway 1 4126
Protoss_Assimilator 1 4287
Protoss_Cybernetics_Core 1 5575
Protoss_Zealot 1 5440
Protoss_Dragoon 5 12344
Protoss_Robotics_Facility 1 9914
Singularity_Charge 1 9645
Protoss_Shuttle 1 11314
Protoss_Robotics_Support_Bay 1 10674
Protoss_Reaver 1 12872
12872
