Protoss_Gateway 1 4161
Protoss_Assimilator 1 4433
Protoss_Cybernetics_Core 1 5724
Protoss_Dragoon 5 11799
Protoss_Robotics_Facility 1 9802
Singularity_Charge 1 9780
Protoss_Observatory 1 10534
Protoss_Nexus 1 13224
Protoss_Observer 1 11581
13224
