Protoss_Nexus 1 6475
Protoss_Gateway 2 9551
Protoss_Assimilator 2 10334
Protoss_Cybernetics_Core 1 6931
Protoss_Zealot 1 6617
Protoss_Dragoon 6 12241
Protoss_Robotics_Facility 1 12060
Singularity_Charge 1 11179
12241
