Protoss_Gateway 2 12431
Protoss_Assimilator 1 4527
Protoss_Cybernetics_Core 1 6002
Protoss_Zealot 2 10779
Protoss_Robotics_Facility 1 8246
Protoss_Dragoon 2 9595
Protoss_Shuttle 1 9649
Protoss_Robotics_Support_Bay 1 9452
Protoss_Reaver 1 11222
12431
