Protoss_Nexus 1 6587
Protoss_Gateway 2 7605
Protoss_Assimilator 2 11323
Protoss_Cybernetics_Core 1 7308
Protoss_Zealot 1 7428
Protoss_Dragoon 6 11583
Protoss_Citadel_of_Adun 1 11071
Singularity_Charge 1 10980
Protoss_Robotics_Facility 1 13204
13204
