Protoss_Gateway 2 8988
Protoss_Assimilator 1 4114
Protoss_Cybernetics_Core 1 5493
Protoss_Dragoon 7 12598
Protoss_Nexus 1 9944
Singularity_Charge 1 9379
Protoss_Robotics_Facility 1 11814
12598
