Protoss_Gateway 2 11361
Protoss_Assimilator 1 4510
Protoss_Cybernetics_Core 1 5851
Protoss_Dragoon 5 11536
Protoss_Robotics_Facility 1 10829
Singularity_Charge 1 10062
Protoss_Observatory 1 11548
11548
