Protoss_Gateway 2 8510
Protoss_Zealot 2 7281
Protoss_Nexus 1 8124
Protoss_Assimilator 2 11253
Protoss_Cybernetics_Core 1 7474
Protoss_Dragoon 5 12475
Protoss_Robotics_Facility 1 11468
12475
