Protoss_Gateway 2 11645
Protoss_Assimilator 1 4594
Protoss_Cybernetics_Core 1 6124
Protoss_Dragoon 5 11829
Protoss_Robotics_Facility 1 10696
Singularity_Charge 1 10340
Protoss_Observatory 1 11432
11829
