Protoss_Gateway 3 11209
Protoss_Assimilator 1 4169
Protoss_Cybernetics_Core 1 5613
Protoss_Robotics_Facility 1 7748
Protoss_Dragoon 6 12585
Protoss_Shuttle 1 9230
Protoss_Observatory 1 8990
Protoss_Observer 2 11139
Singularity_Charge 1 10589
12585
