Protoss_Gateway 1 4246
Protoss_Assimilator 1 4511
Protoss_Cybernetics_Core 1 5699
Protoss_Zealot 1 5739
Protoss_Dragoon 5 11729
Protoss_Robotics_Facility 1 11565
Singularity_Charge 1 10106
11729
