Protoss_Gateway 1 4701
Protoss_Assimilator 1 4602
Protoss_Cybernetics_Core 1 6187
Protoss_Robotics_Facility 1 8496
Protoss_Zealot 2 8571
Protoss_Dragoon 2 10829
Protoss_Shuttle 1 9911
Protoss_Observatory 1 9424
Protoss_Robotics_Support_Bay 1 10052
Protoss_Observer 1 10754
Protoss_Reaver 1 12350
12350
