Protoss_Gateway 2 10234
Protoss_Assimilator 1 4578
Protoss_Cybernetics_Core 1 6124
Protoss_Robotics_Facility 1 8395
Protoss_Dragoon 4 11883
Protoss_Observatory 1 9216
Protoss_Observer 3 12195
12195
