Protoss_Gateway 1 4338
Protoss_Assimilator 1 4578
Protoss_Cybernetics_Core 1 5860
Protoss_Dragoon 4 10655
Protoss_Robotics_Facility 1 10762
Singularity_Charge 1 10282
Protoss_Shuttle 1 12626
12626
