Protoss_Gateway 2 11392
Protoss_Assimilator 1 4564
Protoss_Cybernetics_Core 1 5911
Protoss_Dragoon 5 12042
Protoss_Robotics_Facility 1 10031
Singularity_Charge 1 10209
Protoss_Observatory 1 10983
Protoss_Observer 1 12032
12042
