Protoss_Gateway 1 4207
Protoss_Assimilator 1 4469
Protoss_Cybernetics_Core 1 5758
Protoss_Dragoon 2 8839
Protoss_Robotics_Facility 1 8552
Protoss_Shuttle 1 9962
Protoss_Robotics_Support_Bay 1 9581
Protoss_Zealot 2 11190
Protoss_Reaver 1 11558
Protoss_Observatory 1 11144
11558
