Protoss_Gateway 3 11904
Protoss_Assimilator 1 4330
Protoss_Cybernetics_Core 1 5789
Protoss_Robotics_Facility 1 7895
Protoss_Dragoon 3 11897
Protoss_Shuttle 1 9304
Protoss_Observatory 1 9079
Protoss_Observer 1 10195
11904
