Protoss_Gateway 2 10561
Protoss_Assimilator 1 4653
Protoss_Cybernetics_Core 1 5992
Protoss_Dragoon 5 12512
Protoss_Robotics_Facility 1 8809
Protoss_Observatory 1 9514
Protoss_Observer 1 10590
Protoss_Shuttle 1 12706
12706
