Protoss_Gateway 1 4716
Protoss_Assimilator 2 5307
Protoss_Cybernetics_Core 1 6555
Protoss_Dragoon 2 8878
Protoss_Robotics_Facility 1 10309
Protoss_Forge 1 9817
Protoss_Photon_Cannon 1 11245
Protoss_Shuttle 1 11726
Protoss_Zealot 1 11622
Protoss_Robotics_Support_Bay 1 11668
11726
