Protoss_Gateway 3 12734
Protoss_Assimilator 1 4286
Protoss_Cybernetics_Core 1 5988
Protoss_Dragoon 5 12149
Protoss_Robotics_Facility 1 9117
Protoss_Shuttle 1 10526
Protoss_Observatory 1 9894
Protoss_Observer 1 11369
12734
