Protoss_Gateway 1 4145
Protoss_Assimilator 1 4192
Protoss_Cybernetics_Core 1 5604
Protoss_Dragoon 5 11360
Protoss_Robotics_Facility 1 10390
Singularity_Charge 1 9609
Protoss_Observatory 1 11479
Protoss_Nexus 1 13711
Protoss_Citadel_of_Adun 1 12782
13711
