Protoss_Gateway 2 11682
Protoss_Assimilator 1 4344
Protoss_Cybernetics_Core 1 5928
Protoss_Dragoon 5 11728
Protoss_Robotics_Facility 1 9614
Protoss_Shuttle 1 11023
Protoss_Observatory 1 10409
11728
