Protoss_Gateway 1 4419
Protoss_Assimilator 1 4811
Protoss_Cybernetics_Core 1 6314
Protoss_Dragoon 3 10061
Protoss_Robotics_Facility 1 9044
Protoss_Shuttle 1 11023
Protoss_Robotics_Support_Bay 1 10579
Protoss_Zealot 1 11724
Protoss_Reaver 1 12581
12581
