Protoss_Gateway 1 4221
Protoss_Assimilator 1 4299
Protoss_Cybernetics_Core 1 5729
Protoss_Robotics_Facility 1 7909
Protoss_Dragoon 5 12344
Protoss_Observatory 1 8635
Protoss_Shuttle 1 9596
Protoss_Observer 2 12061
12344
