Protoss_Gateway 2 9691
Protoss_Assimilator 1 4532
Protoss_Cybernetics_Core 1 6116
Protoss_Zealot 1 5929
Protoss_Dragoon 3 9936
Protoss_Robotics_Facility 1 8575
Protoss_Robotics_Support_Bay 1 10099
Protoss_Reaver 1 11956
Protoss_Nexus 1 14196
14196
