Protoss_Gateway 2 10207
Protoss_Assimilator 1 4384
Protoss_Cybernetics_Core 1 5831
Protoss_Dragoon 6 12522
Protoss_Robotics_Facility 1 8899
Protoss_Observatory 1 9613
Protoss_Observer 2 11549
12522
