Protoss_Gateway 1 4289
Protoss_Assimilator 1 4643
Protoss_Cybernetics_Core 1 5897
Protoss_Dragoon 4 11966
Protoss_Robotics_Facility 1 8158
Protoss_Zealot 2 9667
Protoss_Shuttle 1 9655
Protoss_Nexus 1 14103
Protoss_Observatory 1 12079
14103
