Protoss_Gateway 2 12232
Protoss_Assimilator 1 4717
Protoss_Cybernetics_Core 1 6260
Protoss_Dragoon 5 11916
Protoss_Robotics_Facility 1 9797
Protoss_Observatory 1 10516
Protoss_Observer 1 11600
12232
