Protoss_Gateway 3 10572
Protoss_Assimilator 1 4635
Protoss_Cybernetics_Core 1 5980
Protoss_Dragoon 5 11805
Protoss_Robotics_Facility 1 8703
Protoss_Observatory 1 9616
Protoss_Observer 1 10641
11805
