Protoss_Gateway 2 10872
Protoss_Assimilator 1 4720
Protoss_Cybernetics_Core 1 6270
Protoss_Dragoon 5 12571
Protoss_Robotics_Facility 1 9987
Protoss_Observatory 1 10765
Protoss_Observer 1 11878
12571
