Protoss_Gateway 2 11265
Protoss_Assimilator 1 4578
Protoss_Cybernetics_Core 1 5889
Protoss_Dragoon 4 11132
Protoss_Stargate 1 10383
Singularity_Charge 1 10450
Protoss_Fleet_Beacon 1 12007
12007
