Protoss_Gateway 2 10748
Protoss_Assimilator 1 4300
Protoss_Cybernetics_Core 1 5869
Protoss_Dragoon 5 11963
Protoss_Robotics_Facility 1 9974
Protoss_Observatory 1 10807
Protoss_Observer 1 11841
11963
