Protoss_Gateway 2 10050
Protoss_Assimilator 1 4687
Protoss_Cybernetics_Core 1 6214
Protoss_Dragoon 7 12576
Protoss_Robotics_Facility 1 10017
Protoss_Observatory 1 10892
Singularity_Charge 1 10209
Protoss_Observer 1 11914
12576
