Protoss_Gateway 2 10928
Protoss_Assimilator 1 4578
Protoss_Cybernetics_Core 1 5876
Protoss_Zealot 1 5958
Protoss_Dragoon 6 12292
Protoss_Robotics_Facility 1 10355
Singularity_Charge 1 10194
Protoss_Observatory 1 11167
Protoss_Observer 1 12207
12292
