Protoss_Gateway 1 4346
Protoss_Assimilator 1 4757
Protoss_Cybernetics_Core 1 6124
Protoss_Dragoon 3 10983
Protoss_Robotics_Facility 1 8845
Protoss_Shuttle 1 10262
Protoss_Robotics_Support_Bay 1 9872
Protoss_Reaver 1 11820
11820
