Protoss_Gateway 1 4359
Protoss_Assimilator 1 4567
Protoss_Cybernetics_Core 1 6021
Protoss_Dragoon 4 11049
Protoss_Robotics_Facility 1 8714
Protoss_Zealot 1 8307
Protoss_Observatory 1 9455
Protoss_Observer 1 10480
11049
