Protoss_Gateway 2 12683
Protoss_Assimilator 1 4928
Protoss_Zealot 3 11307
Protoss_Cybernetics_Core 1 7207
Protoss_Dragoon 2 9551
Protoss_Robotics_Facility 1 9761
Protoss_Shuttle 1 11191
Protoss_Robotics_Support_Bay 1 10829
Protoss_Reaver 1 12749
12749
