Protoss_Gateway 2 10668
Protoss_Assimilator 1 4508
Protoss_Cybernetics_Core 1 5976
Protoss_Dragoon 5 11912
Protoss_Robotics_Facility 1 8490
Protoss_Observatory 1 9326
Protoss_Observer 2 11607
11912
