Protoss_Gateway 2 10072
Protoss_Assimilator 1 4514
Protoss_Cybernetics_Core 1 5772
Protoss_Robotics_Facility 1 8078
Protoss_Dragoon 6 12434
Protoss_Observatory 1 9060
Protoss_Observer 2 11439
12434
