Protoss_Gateway 2 9961
Protoss_Assimilator 1 4480
Protoss_Cybernetics_Core 1 5771
Protoss_Robotics_Facility 1 7931
Protoss_Dragoon 6 12317
Protoss_Observatory 1 8709
Protoss_Observer 2 11622
12317
