Protoss_Gateway 1 4236
Protoss_Assimilator 1 4330
Protoss_Cybernetics_Core 1 5720
Protoss_Zealot 1 6112
Protoss_Dragoon 5 11836
Singularity_Charge 1 9514
Protoss_Robotics_Facility 1 11553
Protoss_Citadel_of_Adun 1 11806
11836
