Protoss_Gateway 1 4287
Protoss_Assimilator 1 4556
Protoss_Cybernetics_Core 1 5932
Protoss_Robotics_Facility 1 8151
Protoss_Dragoon 3 12186
Protoss_Shuttle 1 9567
Protoss_Robotics_Support_Bay 1 9279
Protoss_Reaver 1 11151
Protoss_Zealot 1 10780
Protoss_Observatory 1 12038
12186
