Protoss_Gateway 2 8392
Protoss_Assimilator 1 4924
Protoss_Cybernetics_Core 1 6197
Protoss_Zealot 1 5973
Protoss_Dragoon 3 9705
Protoss_Citadel_of_Adun 1 8007
Protoss_Templar_Archives 1 9746
Protoss_Dark_Templar 3 12083
12083
