Protoss_Gateway 3 12276
Protoss_Assimilator 1 4504
Protoss_Cybernetics_Core 1 5750
Protoss_Robotics_Facility 1 8013
Protoss_Dragoon 4 12212
Protoss_Shuttle 1 9421
Protoss_Observatory 1 8892
Protoss_Observer 2 11219
Singularity_Charge 1 11072
12276
