Protoss_Gateway 2 12443
Protoss_Assimilator 1 4363
Protoss_Cybernetics_Core 1 5767
Protoss_Dragoon 5 11783
Protoss_Robotics_Facility 1 9348
Protoss_Observatory 1 10055
Protoss_Observer 1 11285
12443
