Protoss_Gateway 3 10521
Protoss_Assimilator 1 4474
Protoss_Cybernetics_Core 1 6029
Protoss_Robotics_Facility 1 8085
Protoss_Dragoon 5 12446
Protoss_Observatory 1 8877
Protoss_Observer 2 10849
Singularity_Charge 1 11321
12446
