Protoss_Gateway 1 4331
Protoss_Assimilator 1 4710
Protoss_Cybernetics_Core 1 6087
Protoss_Dragoon 5 12600
Protoss_Robotics_Facility 1 10456
Singularity_Charge 1 10209
Protoss_Citadel_of_Adun 1 12002
Protoss_Observatory 1 11321
12600
