Protoss_Gateway 1 4243
Protoss_Assimilator 1 4532
Protoss_Cybernetics_Core 1 5923
Protoss_Dragoon 3 12600
Protoss_Stargate 2 9558
Protoss_Scout 2 11667
Protoss_Zealot 1 11410
12600
