Protoss_Gateway 2 9892
Protoss_Assimilator 1 4286
Protoss_Cybernetics_Core 1 5916
Protoss_Dragoon 6 12278
Protoss_Robotics_Facility 1 8883
Protoss_Observatory 1 9972
Protoss_Observer 2 11881
12278
