Protoss_Gateway 1 4192
Protoss_Assimilator 1 4429
Protoss_Cybernetics_Core 1 6021
Protoss_Zealot 1 6171
Protoss_Dragoon 5 12117
Protoss_Robotics_Facility 1 10675
Singularity_Charge 1 10480
Protoss_Shuttle 1 12640
Protoss_Robotics_Support_Bay 1 11990
12640
