Protoss_Gateway 2 9929
Protoss_Assimilator 1 4223
Protoss_Cybernetics_Core 1 5824
Protoss_Dragoon 4 11905
Protoss_Robotics_Facility 1 8672
Protoss_Observatory 1 9382
Protoss_Observer 1 10707
11905
