Protoss_Gateway 2 12576
Protoss_Assimilator 1 4381
Protoss_Cybernetics_Core 1 5891
Protoss_Robotics_Facility 1 8079
Protoss_Dragoon 3 10646
Protoss_Observatory 1 8925
Protoss_Shuttle 1 9955
Protoss_Observer 2 11679
Protoss_Zealot 1 11508
12576
