Protoss_Gateway 3 12823
Protoss_Assimilator 1 4632
Protoss_Cybernetics_Core 1 6223
Protoss_Zealot 1 6002
Protoss_Dragoon 5 12124
Protoss_Nexus 1 12659
Singularity_Charge 1 10838
12823
