Protoss_Gateway 2 11225
Protoss_Nexus 1 8073
Protoss_Zealot 2 7788
Protoss_Assimilator 1 7212
Protoss_Cybernetics_Core 1 9046
Protoss_Dragoon 3 12439
Protoss_Shield_Battery 1 11117
12439
