Protoss_Gateway 2 9282
Protoss_Assimilator 1 4791
Protoss_Cybernetics_Core 1 5955
Protoss_Dragoon 5 11027
Protoss_Robotics_Facility 1 10800
Singularity_Charge 1 10219
Protoss_Zealot 2 12125
Protoss_Shuttle 1 12652
Protoss_Observatory 1 12016
12652
