Protoss_Gateway 2 10660
Protoss_Assimilator 1 4512
Protoss_Cybernetics_Core 1 5895
Protoss_Dragoon 6 11992
Protoss_Robotics_Facility 1 9973
Protoss_Observatory 1 10744
Singularity_Charge 1 10911
Protoss_Observer 1 12017
12017
