Protoss_Gateway 2 10068
Protoss_Assimilator 1 4594
Protoss_Cybernetics_Core 1 5882
Protoss_Dragoon 3 9486
Protoss_Citadel_of_Adun 1 9121
Protoss_Templar_Archives 1 10649
Protoss_Zealot 1 10347
Singularity_Charge 1 9909
Protoss_Dark_Templar 2 11890
11890
