Protoss_Gateway 2 8017
Protoss_Assimilator 1 4286
Protoss_Cybernetics_Core 1 5787
Protoss_Dragoon 6 11875
Protoss_Robotics_Facility 1 9534
Protoss_Observatory 1 10340
Protoss_Citadel_of_Adun 1 11453
Singularity_Charge 1 10809
Protoss_Observer 1 11951
11951
