Protoss_Gateway 2 10122
Protoss_Assimilator 1 4590
Protoss_Cybernetics_Core 1 6296
Protoss_Dragoon 5 12039
Protoss_Robotics_Facility 1 8912
Protoss_Observatory 1 10109
Protoss_Observer 1 11278
Protoss_Zealot 1 11380
Protoss_Shuttle 1 12636
12636
