Protoss_Gateway 2 7865
Protoss_Assimilator 1 4586
Protoss_Cybernetics_Core 1 6014
Protoss_Dragoon 6 11663
Protoss_Nexus 1 12322
Protoss_Robotics_Facility 1 11833
Singularity_Charge 1 11116
12322
