Protoss_Gateway 1 4368
Protoss_Assimilator 1 4615
Protoss_Cybernetics_Core 1 6043
Protoss_Dragoon 3 9478
Protoss_Robotics_Facility 1 8678
Protoss_Shuttle 1 10087
Protoss_Robotics_Support_Bay 1 9799
Protoss_Reaver 1 11661
Protoss_Zealot 1 11197
Protoss_Observatory 1 11196
11661
