Protoss_Nexus 1 7056
Protoss_Gateway 3 12127
Protoss_Assimilator 1 6708
Protoss_Zealot 4 10414
Protoss_Cybernetics_Core 1 9468
Protoss_Dragoon 1 10895
Protoss_Citadel_of_Adun 1 12220
Protoss_Forge 2 12075
12220
