Protoss_Gateway 1 4309
Protoss_Assimilator 1 4624
Protoss_Cybernetics_Core 1 6094
Protoss_Dragoon 1 7310
Protoss_Robotics_Facility 1 8722
Protoss_Zealot 2 9832
Protoss_Shuttle 1 10130
Protoss_Robotics_Support_Bay 1 10070
Protoss_Reaver 1 12256
12256
