Protoss_Gateway 2 10111
Protoss_Assimilator 1 4652
Protoss_Cybernetics_Core 1 6119
Protoss_Dragoon 5 11729
Protoss_Robotics_Facility 1 8877
Protoss_Observatory 1 9755
Protoss_Observer 2 11824
11824
