Protoss_Gateway 2 9602
Protoss_Assimilator 1 4412
Protoss_Zealot 1 5393
Protoss_Cybernetics_Core 1 6383
Protoss_Dragoon 6 12247
Protoss_Robotics_Facility 1 11943
Singularity_Charge 1 10327
12247
