Protoss_Gateway 2 11061
Protoss_Assimilator 1 4833
Protoss_Zealot 2 6927
Protoss_Cybernetics_Core 1 7008
Protoss_Dragoon 5 12355
Protoss_Robotics_Facility 1 10801
Protoss_Observatory 1 11521
Singularity_Charge 1 11358
12355
