Protoss_Gateway 2 9119
Protoss_Assimilator 1 4523
Protoss_Cybernetics_Core 1 5831
Protoss_Dragoon 7 12395
Protoss_Robotics_Facility 1 10759
Singularity_Charge 1 9960
Protoss_Observatory 1 11548
12395
