Protoss_Assimilator 1 3566
Protoss_Gateway 1 4572
Protoss_Cybernetics_Core 1 6146
Protoss_Dragoon 3 11502
Protoss_Robotics_Facility 1 8479
Protoss_Shuttle 1 9918
Protoss_Robotics_Support_Bay 1 9492
Protoss_Reaver 2 13076
Protoss_Observatory 1 10832
13076
