Protoss_Gateway 2 10704
Protoss_Assimilator 1 4467
Protoss_Cybernetics_Core 1 5875
Protoss_Dragoon 6 12091
Protoss_Citadel_of_Adun 1 8070
Protoss_Robotics_Facility 1 9455
Protoss_Observatory 1 10165
Protoss_Observer 1 11790
12091
