Protoss_Gateway 2 8982
Protoss_Assimilator 1 4507
Protoss_Cybernetics_Core 1 6132
Protoss_Dragoon 4 10250
Protoss_Citadel_of_Adun 1 11042
Singularity_Charge 1 9872
Protoss_Zealot 2 11212
Protoss_Robotics_Facility 1 12548
Protoss_Templar_Archives 1 12583
12583
