Protoss_Gateway 1 4517
Protoss_Assimilator 1 4694
Protoss_Cybernetics_Core 1 6277
Protoss_Dragoon 4 10851
Protoss_Robotics_Facility 1 10738
Singularity_Charge 1 10655
Protoss_Shuttle 1 12209
Protoss_Zealot 1 12032
12209
