Protoss_Gateway 2 9109
Protoss_Assimilator 1 4520
Protoss_Cybernetics_Core 1 5810
Protoss_Dragoon 1 7207
Protoss_Citadel_of_Adun 1 7697
Protoss_Templar_Archives 1 9304
Protoss_Dark_Templar 4 11622
11622
