Protoss_Gateway 2 6785
Protoss_Assimilator 1 4444
Protoss_Cybernetics_Core 1 5928
Protoss_Dragoon 4 9534
Protoss_Zealot 2 9975
Singularity_Charge 1 9923
Protoss_Nexus 1 13054
Protoss_Robotics_Facility 1 12989
13054
