Protoss_Gateway 1 4237
Protoss_Assimilator 1 4527
Protoss_Zealot 1 5446
Protoss_Cybernetics_Core 1 6863
Protoss_Dragoon 4 11941
Protoss_Robotics_Facility 1 9165
Protoss_Shuttle 1 10577
Protoss_Robotics_Support_Bay 1 10443
Protoss_Reaver 1 12183
12183
