Protoss_Gateway 2 8291
Protoss_Assimilator 1 4366
Protoss_Cybernetics_Core 1 5784
Protoss_Dragoon 7 12461
Protoss_Robotics_Facility 1 11470
Protoss_Zealot 1 10934
Singularity_Charge 1 9989
12461
