Protoss_Gateway 2 9503
Protoss_Assimilator 1 4293
Protoss_Cybernetics_Core 1 6127
Protoss_Dragoon 5 12512
Protoss_Robotics_Facility 1 8523
Protoss_Observatory 1 9493
Protoss_Observer 1 10568
Protoss_Nexus 1 13571
13571
