Protoss_Gateway 2 6514
Protoss_Assimilator 1 4404
Protoss_Cybernetics_Core 1 5796
Protoss_Dragoon 8 12537
Protoss_Nexus 1 12246
Singularity_Charge 1 9841
Protoss_Robotics_Facility 1 12469
12537
