Protoss_Gateway 2 8686
Protoss_Assimilator 1 4622
Protoss_Zealot 1 5505
Protoss_Cybernetics_Core 1 7215
Protoss_Dragoon 5 11992
Protoss_Robotics_Facility 1 10662
Protoss_Observatory 1 11372
Singularity_Charge 1 11292
11992
