Protoss_Gateway 1 4594
Protoss_Assimilator 1 4520
Protoss_Cybernetics_Core 1 6255
Protoss_Robotics_Facility 1 8297
Protoss_Dragoon 4 12328
Protoss_Observatory 1 9013
Protoss_Observer 2 12242
Protoss_Shuttle 1 11399
12328
