Protoss_Gateway 2 9569
Protoss_Assimilator 1 4390
Protoss_Cybernetics_Core 1 5670
Protoss_Dragoon 7 12257
Protoss_Robotics_Facility 1 9863
Protoss_Observatory 1 10567
Singularity_Charge 1 9872
Protoss_Observer 1 11710
12257
