Protoss_Gateway 3 10861
Protoss_Assimilator 1 4249
Protoss_Cybernetics_Core 1 5622
Protoss_Dragoon 5 11407
Protoss_Robotics_Facility 1 9979
Protoss_Observatory 1 10895
Singularity_Charge 1 10706
Protoss_Observer 1 11929
Protoss_Nexus 1 13866
13866
