Protoss_Gateway 2 8560
Protoss_Assimilator 1 4640
Protoss_Cybernetics_Core 1 6223
Protoss_Dragoon 7 12259
Protoss_Robotics_Facility 1 10424
Singularity_Charge 1 10377
Protoss_Observatory 1 11384
12259
