Protoss_Gateway 2 12681
Protoss_Assimilator 1 4681
Protoss_Cybernetics_Core 1 6207
Protoss_Dragoon 5 12459
Protoss_Robotics_Facility 1 10747
Singularity_Charge 1 10897
Protoss_Observatory 1 11714
Protoss_Citadel_of_Adun 1 12470
12681
