Protoss_Gateway 2 7887
Protoss_Assimilator 1 4161
Protoss_Cybernetics_Core 1 5759
Protoss_Dragoon 7 12279
Singularity_Charge 1 9689
Protoss_Zealot 1 11496
Protoss_Nexus 1 14002
14002
