Protoss_Gateway 2 6901
Protoss_Assimilator 1 4444
Protoss_Cybernetics_Core 1 6020
Protoss_Dragoon 5 11398
Protoss_Nexus 1 11861
Singularity_Charge 1 10163
Protoss_Robotics_Facility 1 12809
12809
