Protoss_Gateway 2 10044
Protoss_Assimilator 1 4501
Protoss_Cybernetics_Core 1 5888
Protoss_Dragoon 5 11334
Protoss_Robotics_Facility 1 8498
Protoss_Observatory 1 9339
Protoss_Observer 2 11546
11546
