Protoss_Gateway 2 9002
Protoss_Assimilator 1 4654
Protoss_Cybernetics_Core 1 6002
Protoss_Dragoon 7 12209
Protoss_Nexus 1 12194
Protoss_Robotics_Facility 1 12330
Singularity_Charge 1 10468
12330
