Protoss_Gateway 2 8752
Protoss_Assimilator 1 4578
Protoss_Cybernetics_Core 1 5988
Protoss_Dragoon 3 9900
Protoss_Citadel_of_Adun 1 9687
Protoss_Zealot 3 10761
Protoss_Templar_Archives 1 11306
Singularity_Charge 1 9982
Protoss_Nexus 1 13853
Protoss_Dark_Templar 1 12578
13853
