Protoss_Gateway 2 8231
Protoss_Assimilator 1 4463
Protoss_Cybernetics_Core 1 5903
Protoss_Dragoon 4 9844
Protoss_Citadel_of_Adun 1 10627
Protoss_Zealot 2 10706
Singularity_Charge 1 9850
Protoss_Templar_Archives 1 12141
Protoss_Robotics_Facility 1 12916
12916
