Protoss_Gateway 2 9623
Protoss_Zealot 3 10649
Protoss_Assimilator 1 5617
Protoss_Cybernetics_Core 1 7375
Protoss_Dragoon 3 10822
Protoss_Citadel_of_Adun 1 9080
Protoss_Templar_Archives 1 10536
Protoss_Dark_Templar 2 11795
11795
