Protoss_Gateway 3 12213
Protoss_Assimilator 1 4278
Protoss_Cybernetics_Core 1 5717
Protoss_Dragoon 8 12549
Protoss_Robotics_Facility 1 11732
Singularity_Charge 1 9935
Protoss_Zealot 1 10960
12549
