Protoss_Gateway 2 8069
Protoss_Assimilator 1 4498
Protoss_Cybernetics_Core 1 5727
Protoss_Dragoon 6 12297
Singularity_Charge 1 9680
Protoss_Nexus 1 12871
Protoss_Robotics_Facility 1 12370
12871
