Protoss_Gateway 2 9929
Protoss_Assimilator 1 4581
Protoss_Cybernetics_Core 1 5948
Protoss_Dragoon 4 11147
Protoss_Robotics_Facility 1 9892
Protoss_Observatory 1 10598
Singularity_Charge 1 10070
Protoss_Observer 1 11673
Protoss_Nexus 1 13903
13903
