Protoss_Gateway 2 10382
Protoss_Assimilator 1 4652
Protoss_Cybernetics_Core 1 6204
Protoss_Dragoon 6 12300
Protoss_Robotics_Facility 1 10128
Singularity_Charge 1 9880
Protoss_Observatory 1 11245
Protoss_Observer 1 12280
12300
