Protoss_Nexus 1 6878
Protoss_Gateway 3 11600
Protoss_Assimilator 1 5715
Protoss_Cybernetics_Core 1 7442
Protoss_Zealot 1 8132
Protoss_Dragoon 5 11725
Protoss_Robotics_Facility 1 12578
12578
