Protoss_Gateway 1 4208
Protoss_Assimilator 1 4334
Protoss_Cybernetics_Core 1 6121
Protoss_Dragoon 2 10529
Protoss_Robotics_Facility 1 8773
Protoss_Shuttle 1 10176
Protoss_Robotics_Support_Bay 1 9557
Protoss_Zealot 2 11367
Protoss_Reaver 1 11918
11918
