Protoss_Nexus 1 6739
Protoss_Gateway 2 9045
Protoss_Assimilator 1 5635
Protoss_Cybernetics_Core 1 7208
Protoss_Zealot 1 7308
Protoss_Dragoon 6 12265
Protoss_Robotics_Facility 1 12399
12399
