Protoss_Gateway 2 10681
Protoss_Assimilator 1 4401
Protoss_Cybernetics_Core 1 5663
Protoss_Dragoon 6 12534
Protoss_Robotics_Facility 1 9671
Singularity_Charge 1 9666
Protoss_Observatory 1 10437
Protoss_Observer 1 11449
Protoss_Nexus 1 13465
13465
