Protoss_Gateway 2 9468
Protoss_Assimilator 1 4132
Protoss_Cybernetics_Core 1 5677
Protoss_Dragoon 4 10397
Protoss_Citadel_of_Adun 1 8818
Protoss_Robotics_Facility 1 9630
Protoss_Templar_Archives 1 10324
Protoss_Zealot 1 10436
Protoss_Shuttle 1 11221
Protoss_Dark_Templar 2 11744
11744
