Protoss_Gateway 2 8133
Protoss_Assimilator 1 4360
Protoss_Cybernetics_Core 1 5707
Protoss_Dragoon 6 10564
Singularity_Charge 1 9719
Protoss_Robotics_Facility 1 11714
Protoss_Zealot 2 11628
11714
