Protoss_Gateway 1 4177
Protoss_Assimilator 1 4574
Protoss_Zealot 2 6649
Protoss_Cybernetics_Core 1 6789
Protoss_Dragoon 5 12554
Protoss_Robotics_Facility 1 10151
Protoss_Observatory 1 10880
Protoss_Nexus 1 13530
Protoss_Observer 1 11909
Singularity_Charge 1 11281
13530
