Protoss_Gateway 2 9021
Protoss_Assimilator 1 4372
Protoss_Cybernetics_Core 1 5933
Protoss_Zealot 1 6807
Protoss_Citadel_of_Adun 1 7951
Protoss_Robotics_Facility 1 9172
Protoss_Templar_Archives 1 9672
Protoss_Shuttle 1 10606
Protoss_Dark_Templar 2 10946
Protoss_Forge 1 11108
Protoss_Photon_Cannon 1 12402
12402
