Protoss_Gateway 2 11465
Protoss_Assimilator 1 4761
Protoss_Cybernetics_Core 1 6219
Protoss_Dragoon 5 12089
Protoss_Robotics_Facility 1 10924
Singularity_Charge 1 10311
Protoss_Shuttle 1 12435
Protoss_Zealot 1 11966
12435
