Protoss_Nexus 1 6817
Protoss_Gateway 3 12836
Protoss_Assimilator 1 5950
Protoss_Cybernetics_Core 1 7624
Protoss_Zealot 1 7363
Protoss_Dragoon 6 12292
Protoss_Robotics_Facility 1 12234
12836
