Protoss_Gateway 2 9640
Protoss_Assimilator 1 4432
Protoss_Cybernetics_Core 1 5850
Protoss_Dragoon 7 12241
Protoss_Robotics_Facility 1 9926
Singularity_Charge 1 9843
Protoss_Observatory 1 10648
Protoss_Observer 1 11724
12241
