Protoss_Gateway 2 10220
Protoss_Assimilator 1 4466
Protoss_Cybernetics_Core 1 5736
Protoss_Dragoon 5 11413
Protoss_Robotics_Facility 1 9926
Singularity_Charge 1 9698
Protoss_Observatory 1 10651
Protoss_Observer 1 11669
Protoss_Nexus 1 14062
14062
