Protoss_Gateway 2 10142
Protoss_Assimilator 1 4188
Protoss_Cybernetics_Core 1 5626
Protoss_Dragoon 6 12519
Protoss_Robotics_Facility 1 9307
Protoss_Shuttle 1 11806
Protoss_Robotics_Support_Bay 1 11132
12519
