Protoss_Gateway 2 5196
Protoss_Zealot 10 11314
Protoss_Nexus 1 9877
Protoss_Assimilator 1 8708
Protoss_Forge 1 9863
Protoss_Cybernetics_Core 1 11401
Protoss_Photon_Cannon 2 12588
12588
