Protoss_Gateway 2 12314
Protoss_Assimilator 1 4293
Protoss_Cybernetics_Core 1 5729
Protoss_Dragoon 3 10141
Protoss_Citadel_of_Adun 1 8797
Protoss_Templar_Archives 1 10395
Protoss_Nexus 1 12494
Singularity_Charge 1 9947
Protoss_Dark_Templar 1 11621
12494
