Protoss_Gateway 2 12276
Protoss_Zealot 2 6263
Protoss_Assimilator 1 5472
Protoss_Cybernetics_Core 1 7202
Protoss_Dragoon 4 11744
Protoss_Nexus 1 11250
Protoss_Robotics_Facility 1 11708
12276
