Protoss_Gateway 1 4212
Protoss_Zealot 3 7709
Protoss_Assimilator 1 5553
Protoss_Cybernetics_Core 1 7387
Protoss_Dragoon 3 12010
Protoss_Nexus 1 13000
Protoss_Robotics_Facility 1 12395
13000
