Protoss_Gateway 2 12590
Protoss_Zealot 3 6997
Protoss_Assimilator 1 5436
Protoss_Cybernetics_Core 1 7018
Protoss_Dragoon 4 12101
Protoss_Nexus 1 12090
Protoss_Robotics_Facility 1 12259
Singularity_Charge 1 11097
12590
