Protoss_Gateway 2 12321
Protoss_Assimilator 1 4271
Protoss_Cybernetics_Core 1 5614
Protoss_Zealot 4 9134
Protoss_Robotics_Facility 1 7902
Protoss_Shuttle 1 9311
Protoss_Observatory 1 9691
Protoss_Dragoon 2 11717
Protoss_Observer 1 11936
12321
