Protoss_Gateway 1 4185
Protoss_Assimilator 1 4223
Protoss_Cybernetics_Core 1 5648
Protoss_Robotics_Facility 1 7918
Protoss_Dragoon 2 10324
Protoss_Shuttle 1 9355
Protoss_Zealot 3 11186
Protoss_Robotics_Support_Bay 1 9492
Protoss_Reaver 1 11247
11247
