Protoss_Gateway 2 11158
Protoss_Assimilator 1 4593
Protoss_Zealot 3 8314
Protoss_Cybernetics_Core 1 7771
Protoss_Dragoon 2 10149
Protoss_Citadel_of_Adun 1 10151
Protoss_Robotics_Facility 1 11275
Protoss_Templar_Archives 1 11743
11743
