Protoss_Gateway 2 11787
Protoss_Assimilator 1 4331
Protoss_Cybernetics_Core 1 6001
Protoss_Robotics_Facility 1 8035
Protoss_Dragoon 4 11883
Protoss_Observatory 1 8930
Protoss_Observer 1 9961
Protoss_Nexus 1 12476
12476
