Protoss_Gateway 2 8907
Protoss_Assimilator 1 4578
Protoss_Zealot 1 5271
Protoss_Cybernetics_Core 1 7060
Protoss_Dragoon 6 11871
Singularity_Charge 1 11080
Protoss_Robotics_Facility 1 13141
13141
