Protoss_Gateway 2 12372
Protoss_Assimilator 1 4763
Protoss_Zealot 2 6759
Protoss_Cybernetics_Core 1 8029
Protoss_Dragoon 3 11559
Protoss_Robotics_Facility 1 10426
Protoss_Observatory 1 11248
Protoss_Observer 1 12288
12372
