Protoss_Gateway 1 4185
Protoss_Assimilator 1 4616
Protoss_Cybernetics_Core 1 6021
Protoss_Dragoon 5 12017
Protoss_Robotics_Facility 1 9971
Protoss_Observatory 1 10910
Protoss_Observer 1 12200
12200
