Protoss_Gateway 2 10211
Protoss_Assimilator 1 4763
Protoss_Zealot 1 5622
Protoss_Cybernetics_Core 1 7003
Protoss_Dragoon 3 11392
Protoss_Robotics_Facility 1 9000
Protoss_Shuttle 1 10452
Protoss_Observatory 1 9872
Protoss_Observer 1 11295
Protoss_Robotics_Support_Bay 1 11870
11870
