Protoss_Gateway 1 4349
Protoss_Assimilator 1 4732
Protoss_Cybernetics_Core 1 6911
Protoss_Zealot 1 6858
Protoss_Dragoon 2 9244
Protoss_Robotics_Facility 1 9556
Protoss_Shuttle 1 11067
Protoss_Observatory 1 10589
Protoss_Robotics_Support_Bay 1 11123
Protoss_Observer 1 11910
11910
