Protoss_Gateway 2 9201
Protoss_Assimilator 1 4191
Protoss_Cybernetics_Core 1 5663
Protoss_Dragoon 8 12594
Protoss_Robotics_Facility 1 10817
Singularity_Charge 1 9590
Protoss_Observatory 1 11513
12594
