Protoss_Gateway 1 4211
Protoss_Assimilator 1 4474
Protoss_Cybernetics_Core 1 5733
Protoss_Robotics_Facility 1 7988
Protoss_Zealot 2 9014
Protoss_Shuttle 1 9391
Protoss_Observatory 1 8933
Protoss_Observer 2 11115
Protoss_Dragoon 2 12080
Protoss_Nexus 1 13849
13849
