Protoss_Gateway 3 12803
Protoss_Assimilator 1 4284
Protoss_Cybernetics_Core 1 5701
Protoss_Robotics_Facility 1 7845
Protoss_Dragoon 4 11960
Protoss_Shuttle 1 9245
Protoss_Observatory 1 9007
Protoss_Observer 3 11967
12803
