Protoss_Gateway 2 8658
Protoss_Zealot 4 7782
Protoss_Assimilator 1 5200
Protoss_Cybernetics_Core 1 6977
Protoss_Dragoon 1 8902
Protoss_Citadel_of_Adun 1 11371
Protoss_Templar_Archives 1 12833
12833
