Protoss_Gateway 3 12781
Protoss_Zealot 3 6968
Protoss_Assimilator 1 5386
Protoss_Cybernetics_Core 1 7160
Protoss_Dragoon 3 10731
Protoss_Nexus 1 11839
Protoss_Robotics_Facility 1 12117
12781
