Protoss_Gateway 2 10915
Protoss_Assimilator 1 4410
Protoss_Cybernetics_Core 1 5829
Protoss_Zealot 1 5824
Protoss_Dragoon 2 9663
Protoss_Citadel_of_Adun 1 9356
Protoss_Templar_Archives 1 11010
Protoss_Forge 2 11382
Protoss_Dark_Templar 2 12347
12347
