Protoss_Gateway 3 12394
Protoss_Assimilator 1 4665
Protoss_Zealot 2 6866
Protoss_Cybernetics_Core 1 6936
Protoss_Citadel_of_Adun 1 8392
Protoss_Dragoon 1 9556
Protoss_Templar_Archives 1 9848
Protoss_Nexus 1 12630
Protoss_Dark_Templar 2 12461
12630
