Protoss_Gateway 1 4280
Protoss_Assimilator 1 4586
Protoss_Zealot 2 6778
Protoss_Cybernetics_Core 1 7868
Protoss_Robotics_Facility 1 9867
Protoss_Dragoon 2 12022
Protoss_Shuttle 1 11528
Protoss_Robotics_Support_Bay 1 10898
Protoss_Citadel_of_Adun 1 12746
12746
