Protoss_Gateway 1 4643
Protoss_Assimilator 1 4644
Protoss_Zealot 1 6090
Protoss_Cybernetics_Core 1 7229
Protoss_Robotics_Facility 1 9275
Protoss_Dragoon 3 11369
Protoss_Shuttle 1 11330
Protoss_Robotics_Support_Bay 1 10822
Protoss_Reaver 1 12888
12888
