Protoss_Gateway 3 11838
Protoss_Assimilator 1 4373
Protoss_Cybernetics_Core 1 5611
Protoss_Robotics_Facility 1 7822
Protoss_Dragoon 5 12505
Protoss_Shuttle 1 9260
Protoss_Observatory 1 8952
Protoss_Observer 1 10103
Protoss_Shield_Battery 1 11644
12505
