Protoss_Gateway 1 4110
Protoss_Assimilator 1 4176
Protoss_Cybernetics_Core 1 5709
Protoss_Zealot 4 9154
Protoss_Robotics_Facility 1 7883
Protoss_Shuttle 1 9296
Protoss_Robotics_Support_Bay 1 9389
Protoss_Reaver 1 11356
Protoss_Dragoon 2 12256
12256
