Protoss_Assimilator 1 3895
Protoss_Gateway 1 5082
Protoss_Cybernetics_Core 1 6557
Protoss_Robotics_Facility 1 8528
Protoss_Dragoon 2 9031
Protoss_Observatory 1 9269
Protoss_Robotics_Support_Bay 1 9376
Protoss_Observer 1 10287
Protoss_Shuttle 1 11645
11645
