Protoss_Assimilator 1 4631
Protoss_Gateway 1 5203
Protoss_Cybernetics_Core 1 6646
Protoss_Robotics_Facility 1 8577
Protoss_Dragoon 3 10190
Protoss_Shuttle 1 9977
Protoss_Observatory 1 9294
Protoss_Robotics_Support_Bay 1 10399
Protoss_Observer 1 10820
Protoss_Reaver 1 12416
12416
