Protoss_Assimilator 1 3665
Protoss_Gateway 2 9409
Protoss_Cybernetics_Core 1 6361
Protoss_Citadel_of_Adun 1 7843
Protoss_Forge 1 8707
Protoss_Templar_Archives 1 9624
Protoss_Photon_Cannon 2 11713
Protoss_Dark_Templar 4 11981
Protoss_Dark_Archon 1 11392
11981
