Protoss_Assimilator 1 3632
Protoss_Gateway 1 4921
Protoss_Cybernetics_Core 1 6488
Protoss_Dragoon 2 10953
Protoss_Robotics_Facility 1 8792
Protoss_Shuttle 1 10350
Protoss_Robotics_Support_Bay 1 9721
Protoss_Observatory 1 9831
Protoss_Observer 2 12214
Singularity_Charge 1 11277
12214
