Protoss_Gateway 2 5092
Protoss_Zealot 13 11688
Protoss_Assimilator 1 7791
Protoss_Forge 1 9842
Protoss_Cybernetics_Core 1 10919
Protoss_Photon_Cannon 1 11365
Protoss_Citadel_of_Adun 1 12806
12806
