Protoss_Gateway 2 6410
Protoss_Assimilator 1 4551
Protoss_Cybernetics_Core 1 5872
Protoss_Dragoon 6 12336
Protoss_Robotics_Facility 1 10222
Protoss_Observatory 1 10951
Protoss_Observer 1 12273
12336
