Protoss_Assimilator 1 3620
Protoss_Gateway 2 10902
Protoss_Cybernetics_Core 1 6226
Protoss_Zealot 4 10992
Protoss_Dragoon 1 7727
Protoss_Citadel_of_Adun 1 8282
Protoss_Templar_Archives 1 10183
Protoss_Dark_Templar 1 11392
Protoss_High_Templar 2 12493
12493
