Protoss_Gateway 2 9757
Protoss_Assimilator 1 4362
Protoss_Zealot 4 12131
Protoss_Cybernetics_Core 1 6787
Protoss_Citadel_of_Adun 1 8268
Protoss_Robotics_Facility 1 9256
Protoss_Templar_Archives 1 9860
Protoss_Shuttle 1 10826
Protoss_Dark_Templar 2 11182
Protoss_Forge 1 11294
12131
