Protoss_Gateway 1 4169
Protoss_Assimilator 1 4387
Protoss_Cybernetics_Core 1 5818
Protoss_Zealot 1 6157
Protoss_Dragoon 5 12490
Protoss_Robotics_Facility 1 8410
Protoss_Shuttle 1 9895
Protoss_Observatory 1 9382
Protoss_Observer 2 11619
12490
