Protoss_Gateway 2 9849
Protoss_Assimilator 1 4479
Protoss_Zealot 2 6465
Protoss_Cybernetics_Core 1 6573
Protoss_Robotics_Facility 1 8653
Protoss_Dragoon 4 11111
Protoss_Observatory 1 9483
Protoss_Observer 2 11850
Protoss_Nexus 1 14150
14150
