Protoss_Gateway 1 4164
Protoss_Assimilator 2 11415
Protoss_Zealot 3 12137
Protoss_Cybernetics_Core 1 6517
Protoss_Robotics_Facility 1 8556
Protoss_Dragoon 2 12107
Protoss_Observatory 1 9377
Protoss_Shuttle 1 10269
Protoss_Observer 2 11271
Protoss_Stargate 1 11489
Protoss_Nexus 1 12726
Protoss_Robotics_Support_Bay 1 11354
12726
